Workbook

Sheet 词盘
A1: 流量 | B1: 大词 | C1: 中尾词 | D1: 长尾词 | H1: GPT关键词分析 | I1: https://chatgpt.com/g/g-RZEovC1BF-vikiguan-jian-ci-fen-xi-zhuan-jia/c/67362093-f224-8010-952b-e4f602764b30
A2: ABA不大于 | B2: 20000 | C2: 100000
A4: 流量大小 | B4: 关键词 | C4: 流量占比 | D4: 转化率 | E4: 竞价 | F4: 转化成本
A5: 大词 | B5: 311 | C5: 0.639 | D5: 0.046350677 | E5: 0.69737999 | F5: 15.045735
A6: 中尾词 | B6: 5 | C6: 0.3374 | D6: 0.062012674 | E6: 0.93455247 | F6: 15.070346
A7: 总计 | B7: 316 | C7: 0.9764 | D7: 0.050736673 | E7: 0.76379793 | F7: 15.054159
A11: 相关性 | B11: 关键词 | C11: 流量占比 | D11: 转化率 | E11: 竞价 | F11: 转化成本
A12: 1 | B12: 60 | C12: 0.3484 | D12: 0.072490363 | E12: 1.0328616 | F12: 14.248261
A13: (空白) | B13: 172 | C13: 0.1487 | D13: 0.040244514 | E13: 0.7659401 | F13: 19.032162
A14: 3 | B14: 43 | C14: 0.1151 | D14: 0.028883909 | E14: 0.52804333 | F14: 18.281575
A15: 2 | B15: 38 | C15: 0.3462 | D15: 0.07555346 | E15: 0.68069731 | F15: 9.009479
A16: 0 | B16: 3 | C16: 0.018 | D16: 0.012878634 | E16: 0.5221281 | F16: 40.542195
A17: 总计 | B17: 316 | C17: 0.9764 | D17: 0.050736673 | E17: 0.76379793 | F17: 15.054159
A19: 有序性 | B19: 关键词 | C19: 流量占比 | D19: 转化率 | E19: 竞价 | F19: 转化成本
A20: 无序 | B20: 262 | C20: 0.6366 | D20: 0.042857494 | E20: 0.69869536 | F20: 16.302758
A21: 有序 | B21: 54 | C21: 0.3398 | D21: 0.11517711 | E21: 1.296244 | F21: 11.254354
A22: 总计 | B22: 316 | C22: 0.9764 | D22: 0.050736673 | E22: 0.76379793 | F22: 15.054159
M24: 流量分配
A25: 词组 | B25: 关键词 | C25: 流量占比 | D25: 转化率 | E25: 竞价 | F25: 转化成本
A26: (空白) | B26: 262 | C26: 0.6366 | D26: 0.042857494 | E26: 0.69869536 | F26: 16.302758 | M26: 新品期
A27: meat thermometer | B27: 48 | C27: 0.2833 | D27: 0.11403542 | E27: 1.3681681 | F27: 11.997747
A28: food thermometer | B28: 6 | C28: 0.0565 | D28: 0.12243178 | E28: 0.83921548 | F28: 6.854556
A29: 总计 | B29: 316 | C29: 0.9764 | D29: 0.050736673 | E29: 0.76379793 | F29: 15.054159
A53: 一级分类 | B53: 关键词 | C53: 流量占比 | D53: 转化率 | E53: 竞价 | F53: 转化成本 | H53: 用户搜索意图标签 | I53: 关键词 | J53: 流量占比 | K53: 转化率 | L53: 竞价 | M53: 转化成本 | Q53: 词根一级分类 | R53: 词根 | S53: 流量占比 | T53: 转化率 | U53: 竞价 | V53: 转化成本 | X53: 词根用户搜索意图标签 | Y53: 词根 | Z53: 流量占比 | AA53: 转化率 | AB53: 竞价 | AC53: 转化成本
A54: 品名词 | B54: 11 | C54: 0.3688 | D54: 0.062431932 | E54: 0.74015247 | F54: 11.855351 | H54: 寻找电源站类型或购买电源站 | I54: 1 | J54: 0.14 | K54: 0.11399792 | L54: 1.786502 | M54: 15.671356 | Q54: (空白) | R54: 704 | S54: 0.47028185 | T54: 0.020350668 | U54: 0.87460421 | V54: 42.976683 | X54: (空白) | Y54: 758 | Z54: 0.60220026 | AA54: 0.023201846 | AB54: 0.86263472 | AC54: 37.179573
A55: 场景词 | B55: 15 | C55: 0.0983 | D55: 0.038522339 | E55: 1.0444286 | F55: 27.112283 | H55: (空白) | I55: 228 | J55: 0.1387 | K55: 0.044655472 | L55: 0.66777448 | M55: 14.953923 | Q55: 功能词 | R55: 21 | S55: 0.17246751 | T55: 0.018603339 | U55: 1.211879 | V55: 65.143092 | X55: 电力驱动 | Y55: 6 | Z55: 0.076449399 | AA55: 0.015468385 | AB55: 1.2780045 | AC55: 82.620422
A56: 功能词 | B56: 28 | C56: 0.1307 | D56: 0.037575658 | E56: 0.83257753 | F56: 22.157364 | H56: 寻找便携式电源站 | I56: 1 | J56: 0.1141 | K56: 0.087299475 | L56: 0.23378488 | M56: 2.6779643 | Q56: 品名词 | R56: 27 | S56: 0.16572555 | T56: 0.016024258 | U56: 1.0859367 | V56: 67.7683 | X56: 发电机 | Y56: 3 | Z56: 0.073066251 | AA56: 0.011070736 | AB56: 1.0251733 | AC56: 92.602085
A57: (空白) | B57: 228 | C57: 0.1387 | D57: 0.044655472 | E57: 0.66777448 | F57: 14.953923 | H57: 寻找太阳能发电机 | I57: 7 | J57: 0.1002 | K57: 0.020121169 | L57: 0.81372003 | M57: 40.440992 | Q57: 品牌词 | R57: 15 | S57: 0.094679453 | T57: 0.027735358 | U57: 1.5254579 | V57: 55.000475 | X57: 电源站 | Y57: 2 | Z57: 0.054982232 | AA57: 0.011324633 | AB57: 2.2192905 | AC57: 195.97018
A58: 品牌词 | B58: 30 | C58: 0.2237 | D58: 0.071724092 | E58: 0.70373669 | F58: 9.8117198 | H58: 了解或购买Jackery品牌的电源产品 | I58: 4 | J58: 0.0767 | K58: 0.12023776 | L58: 1.2959752 | M58: 10.778438 | Q58: 场景词 | R58: 17 | S58: 0.051501728 | T58: 0.034442636 | U58: 0.40707995 | V58: 11.819071 | X58: 太阳能 | Y58: 1 | Z58: 0.045684661 | AA58: 0.012658003 | AB58: 1.0585624 | AC58: 83.627913
A59: 属性词 | B59: 4 | C59: 0.0162 | D59: 0.1815744 | E59: 0.75248255 | F59: 4.1442106 | H59: 了解或购买Anker品牌的电源产品 | I59: 7 | J59: 0.051 | K59: 0.050838059 | L59: 0.50739338 | M59: 9.9805813 | Q59: 属性词 | R59: 22 | S59: 0.045343913 | T59: 0.022113661 | U59: 1.316347 | V59: 59.526418 | X59: 便携 | Y59: 3 | Z59: 0.03882101 | AA59: 0.019876563 | AB59: 1.3960977 | AC59: 70.238385
A60: 总计 | B60: 316 | C60: 0.9764 | D60: 0.050736673 | E60: 0.76379793 | F60: 15.054159 | H60: 寻找便携式发电机 | I60: 3 | J60: 0.0493 | K60: 0.097325285 | L60: 0.91161276 | M60: 9.3666591 | Q60: 总计 | R60: 806 | S60: 1 | T60: 0.022638783 | U60: 0.90751773 | V60: 40.08686 | X60: 交流电 | Y60: 2 | Z60: 0.026748771 | AA60: 0.022858441 | AB60: 1.1928742 | AC60: 52.185282
H61: 了解或购买EcoFlow品牌电源产品 | I61: 6 | J61: 0.047 | K61: 0.14234224 | L61: 0.92465961 | M61: 6.496031 | X61: 太阳能面板 | Y61: 2 | Z61: 0.022319038 | AA61: 0.0096331566 | AB61: 1.1794705 | AC61: 122.43863
H62: 寻找适合户外活动的电源或设备 | I62: 2 | J62: 0.0284 | K62: 0.071819523 | L62: 1.0841268 | M62: 15.095155 | X62: 户外 | Y62: 2 | Z62: 0.018595142 | AA62: 0.0067511937 | AB62: 0.77695581 | AC62: 115.08421
A63: 二级分类 | B63: 关键词 | C63: 流量占比 | D63: 转化率 | E63: 竞价 | F63: 转化成本 | H63: 了解或购买Bluetti品牌的电源产品 | I63: 3 | J63: 0.0266 | K63: 0.025044203 | L63: 0.32855262 | M63: 13.118909 | Q63: 词根二级分类 | R63: 词根 | S63: 流量占比 | T63: 转化率 | U63: 竞价 | V63: 转化成本 | X63: 电池 | Y63: 4 | Z63: 0.013045806 | AA63: 0.025408934 | AB63: 0.7948801 | AC63: 31.283488
A64: (空白) | B64: 269 | C64: 0.7312 | D64: 0.056357327 | E64: 0.69778096 | F64: 12.381371 | H64: 了解户外活动必备电源设备或其他装备 | I64: 3 | J64: 0.0262 | K64: 0.043483967 | L64: 1.371553 | M64: 31.541579 | Q64: (空白) | R64: 720 | S64: 0.57601129 | T64: 0.020782048 | U64: 0.93095755 | V64: 44.796238 | X64: 家庭 | Y64: 3 | Z64: 0.011926204 | AA64: 0.042939623 | AB64: 0.2691463 | AC64: 6.2680174
A65: 太阳能 | B65: 1 | C65: 0.0018 | D65: 0.030196022 | E65: 0.089322571 | F65: 2.9580907 | H65: 寻找带太阳能面板的太阳能发电机 | I65: 1 | J65: 0.022 | K65: 0.15359624 | L65: 0.83151202 | M65: 5.4136221 | Q65: 发电机 | R65: 3 | S65: 0.073066251 | T65: 0.011070736 | U65: 1.0251733 | V65: 92.602085 | X65: 备份 | Y65: 2 | Z65: 0.005476318 | AA65: 0.015755492 | AB65: 1.0311328 | AC65: 65.445926
A66: 包括太阳能面板 | B66: 1 | C66: 0.022 | D66: 0.15359624 | E66: 0.83151202 | F66: 5.4136221 | H66: 寻找家庭用发电机 | I66: 1 | J66: 0.0168 | K66: 0.11588691 | L66: 0.90997948 | M66: 7.8523059 | Q66: 电力 | R66: 1 | S66: 0.067200506 | T66: 0.015333407 | U66: 1.4012018 | V66: 91.382288 | X66: 专业版 | Y66: 1 | Z66: 0.0030180597 | AA66: 0.019525014 | AB66: 1.0702974 | AC66: 54.816727
A67: 户外活动场景 | B67: 1 | C67: 0.0206 | D67: 0.062696883 | E67: 1.1745185 | F67: 18.733285 | H67: 了解或购买便携式房屋及电源产品 | I67: 3 | J67: 0.0122 | K67: 0.0048734688 | L67: 0.45390327 | M67: 93.137616 | Q67: 电源站 | R67: 2 | S67: 0.054982232 | T67: 0.011324633 | U67: 2.2192905 | V67: 195.97018 | X67: 小型设备 | Y67: 2 | Z67: 0.0019714745 | AA67: 0.012385492 | AB67: 0.91032208 | AC67: 73.499067
A68: 户外活动必备品 | B68: 1 | C68: 0.017 | D68: 0.15359286 | E68: 0.86933277 | F68: 5.6599816 | H68: 寻找太阳能面板 | I68: 1 | J68: 0.0086 | K68: 0.13918898 | L68: 0.94905242 | M68: 6.8184449 | Q68: 太阳能 | R68: 1 | S68: 0.045684661 | T68: 0.012658003 | U68: 1.0585624 | V68: 83.627913 | X68: 充电 | Y68: 2 | Z68: 0.0017280826 | AA68: 0.025645074 | AB68: 1.3279707 | AC68: 51.782682
A69: 家庭使用场景 | B69: 1 | C69: 0.0168 | D69: 0.11588691 | E69: 0.90997948 | F69: 7.8523059 | H69: 寻找电动发电机 | I69: 1 | J69: 0.0065 | K69: 0.045595172 | L69: 0.96803926 | M69: 21.231179 | Q69: 便携性 | R69: 1 | S69: 0.03792046 | T69: 0.020357841 | U69: 1.4568378 | V69: 71.561507 | X69: 应急电源 | Y69: 3 | Z69: 0.0015820474 | AA69: 0.014394311 | AB69: 0.52974346 | AC69: 36.80228
A70: 太阳能发电 | B70: 2 | C70: 0.0186 | D70: 0.07337005 | E70: 0.64461797 | F70: 8.7858461 | H70: 寻找电池发电机 | I70: 1 | J70: 0.0065 | K70: 0.029178251 | L70: 4.5957178 | M70: 157.50491 | Q70: 交流电 | R70: 1 | S70: 0.026724432 | T70: 0.023011918 | U70: 1.2109059 | V70: 52.620814 | X70: 电源插座 | Y70: 2 | Z70: 0.0014360123 | AA70: 0.019008256 | AB70: 0.77052084 | AC70: 40.536114
A71: 便携式发电机 | B71: 1 | C71: 0.0161 | D71: 0.088597943 | E71: 0.95051754 | F71: 10.728438 | H71: 寻找电池包或购买电池包 | I71: 1 | J71: 0.0055 | K71: 0.017498642 | L71: 0.50571626 | M71: 28.900314 | Q71: 面板 | R71: 2 | S71: 0.022319038 | T71: 0.0096331566 | U71: 1.1794705 | V71: 122.43863 | X71: 充电器 | Y71: 3 | Z71: 0.00087621087 | AA71: 0.026053195 | AB71: 1.3576644 | AC71: 52.111242
A72: 太阳能面板 | B72: 1 | C72: 0.0086 | D72: 0.13918898 | E72: 0.94905242 | F72: 6.8184449 | H72: 寻找小型发电机 | I72: 2 | J72: 0.0052 | K72: 0.014550098 | L72: 1.268399 | M72: 87.174607 | Q72: 露营 | R72: 1 | S72: 0.016501971 | T72: 0.006469251 | U72: 0.79292794 | V72: 122.56874 | X72: 可充电 | Y72: 1 | Z72: 7.3017573e-05 | AA72: 0.018464063 | AB72: 0.020655523 | AC72: 1.1186878
A73: 户外发电机场景 | B73: 1 | C73: 0.0078 | D73: 0.10007281 | E73: 0.8041791 | F73: 8.0359403 | H73: 寻找带太阳能面板的便携电源站 | I73: 1 | J73: 0.004 | K73: 0.054160126 | L73: 0.99727891 | M73: 18.413527 | Q73: 电池 | R73: 2 | S73: 0.012729397 | T73: 0.026354907 | U73: 0.82190735 | V73: 31.186122 | X73: 无线 | Y73: 1 | Z73: 0 | AA73: 0.032466211 | AB73: 0 | AC73: 0
A74: 太阳能电站 | B74: 1 | C74: 0.0078 | D74: 0.024898884 | E74: 0.19485715 | F74: 7.8259389 | H74: 寻找电力发电机 | I74: 1 | J74: 0.0037 | K74: 0.18666667 | L74: 0.85807192 | M74: 4.5968139 | Q74: 家庭 | R74: 2 | S74: 0.011828847 | T74: 0.043309144 | U74: 0.27022873 | V74: 6.2395307 | X74: 电池包 | Y74: 3 | Z74: 0 | AA74: #DIV/0! | AB74: #DIV/0! | AC74: #DIV/0!
A75: 便携式房屋场景 | B75: 2 | C75: 0.0088 | D75: 0.0074385511 | E75: 0.19722487 | F75: 26.513883 | H75: 寻找电池备份产品 | I75: 1 | J75: 0.0034 | K75: 0.033046978 | L75: 0.84532157 | M75: 25.579391 | Q75: 用途 | R75: 2 | S75: 0.0086160736 | T75: 0.046862306 | U75: 0.27565108 | V75: 5.8821494 | X75: 总计 | Y75: 806 | Z75: 1 | AA75: 0.022638783 | AB75: 0.90751773 | AC75: 40.08686
A76: 电池发电机 | B76: 1 | C76: 0.0065 | D76: 0.029178251 | E76: 4.5957178 | F76: 157.50491 | H76: 了解或购买Anker品牌的电池产品 | I76: 1 | J76: 0.0033 | K76: 0.2274944 | L76: 0 | M76: 0 | Q76: 电力驱动 | R76: 1 | S76: 0.0050625517 | T76: 0.018030684 | U76: 0.98663319 | V76: 54.719675
A77: 电动发电机 | B77: 1 | C77: 0.0065 | D77: 0.045595172 | E77: 0.96803926 | F77: 21.231179 | H77: 了解或购买Jackery品牌的太阳能发电机 | I77: 1 | J77: 0.0032 | K77: 0.092903367 | L77: 0.71891083 | M77: 7.7382645 | Q77: 升级 | R77: 1 | S77: 0.0049165166 | T77: 0.014084213 | U77: 0.55177746 | V77: 39.177017
A78: 户外装备场景 | B78: 1 | C78: 0.0049 | D78: 0.02908596 | E78: 3.2441105 | F78: 111.53527 | H78: 寻找太阳能电池 | I78: 1 | J78: 0.0031 | K78: 0.15359762 | L78: 0.85195948 | M78: 5.546697 | Q78: 背部 | R78: 1 | S78: 0.003699557 | T78: 0.019961376 | U78: 1.3590862 | V78: 68.085796
A79: 户外配件场景 | B79: 1 | C79: 0.0043 | D79: 0.0053943546 | E79: 0.72622646 | F79: 134.62713 | H79: 寻找适合露营使用的发电机 | I79: 1 | J79: 0.0031 | K79: 0.0042988949 | L79: 0.56957112 | M79: 132.49245 | Q79: 备份 | R79: 1 | S79: 0.0035048435 | T79: 0.019997557 | U79: 1.3398652 | V79: 67.001447
A80: 配备太阳能面板的便携电站 | B80: 1 | C80: 0.004 | D80: 0.054160126 | E80: 0.99727891 | F80: 18.413527 | H80: 寻找家庭用太阳能发电机 | I80: 1 | J80: 0.0029 | K80: 0.01019793 | L80: 4.837235 | M80: 474.33498 | Q80: 专业版 | R80: 1 | S80: 0.0030180597 | T80: 0.019525014 | U80: 1.0702974 | V80: 54.816727
A81: 电力发电机 | B81: 1 | C81: 0.0037 | D81: 0.18666667 | E81: 0.85807192 | F81: 4.5968139 | H81: 寻找电池备份电源供应 | I81: 1 | J81: 0.0029 | K81: 0.16239316 | L81: 0.75284715 | M81: 4.6359535 | Q81: 包装 | R81: 1 | S81: 0.0022392056 | T81: 0.041534848 | U81: 1.2170945 | V81: 29.302972
A82: 配有太阳能面板的电站 | B82: 1 | C82: 0.0036 | D82: 0.097874888 | E82: 0.84458845 | F82: 8.6292661 | H82: 寻找便携太阳能发电机 | I82: 1 | J82: 0.0029 | K82: 0.23069719 | L82: 0.88483559 | M82: 3.8354849 | Q82: 电动 | R82: 1 | S82: 0.0020931704 | T82: 0.018966737 | U82: 1.0553414 | V82: 55.641693
A83: 太阳能发电机 | B83: 3 | C83: 0.0069 | D83: 0.020295338 | E83: 0.990528 | F83: 48.805692 | H83: 寻找家庭用便携发电机 | I83: 1 | J83: 0.0028 | K83: 0.040287023 | L83: 0.96294631 | M83: 23.902146 | Q83: 户外 | R83: 1 | S83: 0.0020931704 | T83: 0.012540205 | U83: 0.44900674 | V83: 35.805374
A84: 电池备份 | B84: 1 | C84: 0.0034 | D84: 0.033046978 | E84: 0.84532157 | F84: 25.579391 | H84: 寻找便携式太阳能面板 | I84: 1 | J84: 0.0028 | K84: 0.20629638 | L84: 0.59736834 | M84: 2.8956802 | Q84: 供电 | R84: 1 | S84: 0.0019714745 | T84: 0.011569574 | U84: 0.72648653 | V84: 62.792853
A85: 便携房屋场景 | B85: 1 | C85: 0.0034 | D85: 0.0019931591 | E85: 0.74212533 | F85: 372.33623 | H85: 寻找便携电力产品 | I85: 1 | J85: 0.0028 | K85: 0.22369358 | L85: 0 | M85: 0 | Q85: 小型 | R85: 2 | S85: 0.0019714745 | T85: 0.012385492 | U85: 0.91032208 | V85: 73.499067
A86: 太阳能电池 | B86: 1 | C86: 0.0031 | D86: 0.15359762 | E86: 0.85195948 | F86: 5.546697 | H86: 了解或购买EcoFlow太阳能面板 | I86: 1 | J86: 0.0028 | K86: 0.020695861 | L86: 4.9707558 | M86: 240.18116 | Q86: 呼吸机 | R86: 1 | S86: 0.0018254393 | T86: 0.0067641122 | U86: 1.126291 | V86: 166.5098
A87: 户外露营发电机 | B87: 1 | C87: 0.0031 | D87: 0.0042988949 | E87: 0.56957112 | F87: 132.49245 | H87: 了解或购买Anker太阳能面板 | I87: 1 | J87: 0.0028 | K87: 0.0016961473 | L87: 0.6530396 | M87: 385.01349 | Q87: 充电 | R87: 2 | S87: 0.0017280826 | T87: 0.025645074 | U87: 1.3279707 | V87: 51.782682
... A108: 总计 | B108: 316 | C108: 0.9764 | D108: 0.050736673 | E108: 0.76379793 | F108: 15.054159 | H108: 了解或购买Anker太阳能发电机 | I108: 1 | J108: 0.0017 | K108: 0.037866383 | L108: 1.3833171 | M108: 36.531535 | Q108: 插头 | R108: 1 | S108: 0.00012169595 | T108: 0.023225984 | U108: 0.46749966 | V108: 20.128304
H109: 了解或购买Anker电池包 | I109: 1 | J109: 0.0017 | K109: 0.083575955 | L109: 1.4077291 | M109: 16.843709 | Q109: 附加 | R109: 1 | S109: 9.7356764e-05 | T109: 0.02425107 | U109: 0.72259629 | V109: 29.796471
H110: 寻找电源站 | I110: 1 | J110: 0.0016 | K110: 0.055063187 | L110: 0.42666831 | M110: 7.7487034 | Q110: 房屋 | R110: 1 | S110: 9.7356764e-05 | T110: 0.0041901459 | U110: 0.15563827 | V110: 37.143879
H111: 了解或购买EcoFlow Delta Pro Ultra产品 | I111: 1 | J111: 0.0016 | K111: 0.02616967 | L111: 2.5929465 | M111: 99.082122 | Q111: 可充电 | R111: 1 | S111: 7.3017573e-05 | T111: 0.018464063 | U111: 0.020655523 | V111: 1.1186878
H112: 了解或购买Bluetti AC180电源产品 | I112: 1 | J112: 0.0016 | K112: 0.081168332 | L112: 0.60896849 | M112: 7.5025379 | Q112: 工厂 | R112: 1 | S112: 4.8678382e-05 | T112: 0.015444451 | U112: 0.19196212 | V112: 12.429197
H113: 总计 | I113: 316 | J113: 0.9764 | K113: 0.050736673 | L113: 0.76379793 | M113: 15.054159 | Q113: 旅行 | R113: 1 | S113: 4.8678382e-05 | T113: 0.016549105 | U113: 0.078166034 | V113: 4.7232787
Q114: 冰箱 | R114: 1 | S114: 2.4339191e-05 | T114: 0.014963487 | U114: 0.29784732 | V114: 19.90494
Q115: 110伏特 | R115: 1 | S115: 2.4339191e-05 | T115: 0.019141429 | U115: 0.75616948 | V115: 39.504337
Q116: 零 | R116: 1 | S116: 2.4339191e-05 | T116: 0.012389 | U116: 1.4719421 | V116: 118.8104
Q117: 20伏特 | R117: 1 | S117: 2.4339191e-05 | T117: 0.0017221584 | U117: 2.16 | V117: 1254.24
Q118: 笔记本电脑 | R118: 1 | S118: 2.4339191e-05 | T118: 0.021030494 | U118: 1.4073607 | V118: 66.92
Q119: USB接口 | R119: 1 | S119: 2.4339191e-05 | T119: 0.055152959 | U119: 0.065477117 | V119: 1.1871914
Q120: 200瓦 | R120: 1 | S120: 0 | T120: 0.0065708188 | U120: 0 | V120: 0
Q121: 10000毫安时 | R121: 1 | S121: 0 | T121: #DIV/0! | U121: #DIV/0! | V121: #DIV/0!
Q122: 适配器 | R122: 1 | S122: 0 | T122: #DIV/0! | U122: #DIV/0! | V122: #DIV/0!
Q123: 类型 | R123: 1 | S123: 0 | T123: #DIV/0! | U123: #DIV/0! | V123: #DIV/0!
Q124: 毫安时 | R124: 1 | S124: 0 | T124: 0.035121328 | U124: 0 | V124: 0
Q125: 大型 | R125: 1 | S125: 0 | T125: 0.071404849 | U125: 0 | V125: 0
Q126: 平板电脑 | R126: 1 | S126: 0 | T126: #DIV/0! | U126: #DIV/0! | V126: #DIV/0!
Q127: 移动 | R127: 1 | S127: 0 | T127: 0.0091072271 | U127: 0 | V127: 0
Q128: 移动电源 | R128: 1 | S128: 0 | T128: #DIV/0! | U128: #DIV/0! | V128: #DIV/0!
Q129: 无线 | R129: 1 | S129: 0 | T129: 0.032466211 | U129: 0 | V129: 0
Q130: 外部 | R130: 1 | S130: 0 | T130: #DIV/0! | U130: #DIV/0! | V130: #DIV/0!
Q131: 最佳 | R131: 1 | S131: 0 | T131: #DIV/0! | U131: #DIV/0! | V131: #DIV/0!
Q132: 安卓设备 | R132: 1 | S132: 0 | T132: 0.096586783 | U132: 0 | V132: 0
Q133: 快速 | R133: 1 | S133: 0 | T133: #DIV/0! | U133: #DIV/0! | V133: #DIV/0!
Q134: 手机 | R134: 3 | S134: 0 | T134: 0.055768996 | U134: 0 | V134: 0
Q135: 电池包 | R135: 2 | S135: 0 | T135: #DIV/0! | U135: #DIV/0! | V135: #DIV/0!
Q136: 总计 | R136: 806 | S136: 1 | T136: 0.022638783 | U136: 0.90751773 | V136: 40.08686

Sheet 词根
A1: 词根 | B1: 词频 | C1: 一级分类 | D1: 二级分类 | E1: 用户搜索意图标签 | F1: 否定
A2: thermometer | B2: 1523 | C2: 功能词 | D2: 电力 | E2: 电力驱动
A3: meat | B3: 640 | C3: 属性词 | D3: 便携性 | E3: 便携
A4: probe | B4: 502 | C4: 品名词 | D4: 电池包 | E4: 电池包
A5: gifts | B5: 451 | C5: 功能词 | D5: 充电器 | E5: 充电器
A6: men | B6: 316 | C6: 品名词 | D6: 电池 | E6: 电池
A7: kitchen | B7: 309 | C7: 功能词 | D7: 太阳能 | E7: 太阳能
A8: temperature | B8: 308 | C8: 品名词 | D8: 电源站 | E8: 电源站 | F8: X
A9: wireless | B9: 306 | C9: 品名词 | D9: 发电机 | E9: 发电机 | F9: X
A10: digital | B10: 297 | C10: 品名词 | D10: 手机
A11: grill | B11: 263 | C11: 品名词 | D11: 手机
A12: accessories | B12: 211 | C12: 场景词 | D12: 露营 | E12: 户外
A13: cooking | B13: 210 | C13: 属性词 | D13: 包装
A14: day | B14: 185 | C14: 品牌词
A15: gadgets | B15: 172 | C15: 场景词 | D15: 家庭 | E15: 家庭
A16: oven | B16: 151 | C16: 品牌词
A17: gift | B17: 134 | C17: 功能词 | D17: 充电 | E17: 充电 | F17: X
A18: smoker | B18: 133 | C18: 品名词 | D18: 发电机 | E18: 发电机
A19: valentines | B19: 127 | C19: 品牌词
A20: bbq | B20: 122 | C20: 功能词 | D20: 面板 | E20: 太阳能面板
A21: food | B21: 118 | C21: 功能词 | D21: 备份 | E21: 备份
A22: thermopro | B22: 116 | C22: 功能词 | D22: USB接口 | F22: X
A23: thermometers | B23: 107 | C23: 功能词 | D23: 电源插座 | E23: 电源插座 | F23: X
A24: chef | B24: 104 | C24: 功能词 | D24: 电力驱动 | E24: 电力驱动
A25: smart | B25: 102 | C25: 属性词 | D25: 快速
A26: best | B26: 101 | C26: 品名词 | D26: 专业版 | E26: 专业版
A27: bluetooth | B27: 94 | C27: 功能词 | D27: 供电 | E27: 备份 | F27: X
A28: probes | B28: 85 | C28: 品牌词
A29: temp | B29: 84 | C29: 场景词 | D29: 用途
A30: fryer | B30: 80 | C30: 品牌词
A31: air | B31: 74 | C31: 品名词 | D31: 电池单元
A32: mens | B32: 71 | C32: 功能词 | D32: 交流电 | E32: 交流电
A33: him | B33: 69 | C33: 品牌词
A34: instant | B34: 68 | C34: 场景词 | D34: 呼吸机
A35: deals | B35: 67 | C35: 功能词 | D35: 逆变器 | E35: 电力驱动
A36: grilling | B36: 67 | C36: 品名词 | D36: 充电器 | E36: 充电器 | F36: X
A37: read | B37: 65 | C37: 功能词 | D37: 功率单位
A38: outdoor | B38: 63 | C38: 品名词 | D38: 安卓设备 | F38: X
A39: wifi | B39: 58 | C39: 属性词 | D39: 最大
A40: items | B40: 49 | C40: 品名词 | D40: 便携式设备 | E40: 便携
A41: man | B41: 48 | C41: 品名词 | D41: 面板 | E41: 太阳能面板
A42: remote | B42: 48 | C42: 场景词 | D42: 用途
A43: valentine | B43: 47 | C43: 功能词 | D43: 插头 | E43: 电源插座
A44: home | B44: 46 | C44: 属性词 | D44: 最佳
A45: birthday | B45: 45 | C45: 属性词 | D45: 外部
A46: camp | B46: 45 | C46: 品名词 | D46: 探险者（品牌）
A47: prime | B47: 45 | C47: 品牌词
A48: baking | B48: 44 | C48: 场景词 | D48: 户外 | E48: 户外
A49: cool | B49: 43 | C49: 场景词 | D49: 紧急情况 | E49: 应急电源
A50: tools | B50: 43 | C50: 属性词 | D50: 无线 | E50: 无线
A51: amazon | B51: 42 | C51: 属性词 | D51: 小型 | E51: 小型设备
A52: pro | B52: 42 | C52: 功能词 | D52: 电动 | E52: 电力驱动
A53: essentials | B53: 40 | C53: 品牌词
A54: barbecue | B54: 39 | C54: 品名词 | D54: 便携设备 | E54: 便携
A55: electric | B55: 39 | C55: 功能词 | D55: 充电器 | E55: 充电器
A56: ninja | B56: 38 | C56: 品牌词
A57: replacement | B57: 38 | C57: 品名词
A58: the | B58: 38 | C58: 品名词 | D58: 移动电源 | E58: 电池包
A59: stocking | B59: 37 | C59: 属性词 | D59: 小型 | E59: 小型设备 | F59: X
A60: today | B60: 37 | C60: 场景词 | D60: 背部
A61: dad | B61: 36 | C61: 场景词 | D61: 旅行
A62: sensor | B62: 35 | C62: 场景词 | D62: 移动
A63: stuffers | B63: 34 | C63: 场景词 | D63: 升级
A64: timer | B64: 34 | C64: 品名词 | D64: 电池 | E64: 电池
A65: clearance | B65: 33 | C65: 品名词 | D65: 发电机 | E65: 发电机
A66: thermo | B66: 33 | C66: 功能词 | D66: 可充电 | E66: 可充电 | F66: X
A67: valentine's | B67: 33 | C67: 功能词 | D67: 充电 | E67: 充电
A68: must | B68: 32 | C68: 场景词 | D68: 室内
A69: weber | B69: 32 | C69: 品名词 | D69: 平板电脑
A70: pellet | B70: 31 | C70: 属性词 | D70: 大型
A71: products | B71: 31 | C71: 品牌词
A72: steak | B72: 31 | C72: 场景词 | D72: 停电 | E72: 应急电源
A73: boss | B73: 29 | C73: 属性词 | D73: 锂铁磷电池 | E73: 电池
A74: small | B74: 29 | C74: 场景词 | D74: 房屋 | E74: 家庭
A75: under | B75: 29 | C75: 品名词 | D75: 笔记本电脑
A76: water | B76: 29 | C76: 属性词 | D76: 毫安时
A77: who | B77: 29 | C77: 属性词 | D77: 类型
A78: indoor | B78: 26 | C78: 品牌词
A79: supplies | B79: 26 | C79: 品牌词
A80: thermoworks | B80: 26 | C80: 属性词 | D80: 1000瓦
A81: waterproof | B81: 26 | C81: 属性词 | D81: 加强版
A82: men's | B82: 25 | C82: 属性词 | D82: 300瓦
A83: oil | B83: 25 | C83: 功能词 | D83: 能量 | E83: 电力驱动
A84: candy | B84: 24 | C84: 功能词 | D84: 适配器
A85: para | B85: 24 | C85: 品名词 | D85: 电池包 | E85: 电池包
A86: fathers | B86: 23 | C86: 品名词 | D86: 手机
A87: frying | B87: 23 | C87: 品牌词
A88: haves | B88: 23 | C88: 品名词 | D88: 电源箱
A89: masterbuilt | B89: 23 | C89: 场景词 | D89: 家庭 | E89: 家庭
A90: gauge | B90: 22 | C90: 属性词 | D90: 附加
A91: griddle | B91: 22 | C91: 场景词 | D91: 工厂
A92: gun | B92: 22 | C92: 属性词 | D92: 20伏特
A93: iq | B93: 21 | C93: 属性词 | D93: 零
A94: accessory | B94: 20 | C94: 场景词 | D94: 用品 | E94: 应急电源
A95: everything | B95: 20 | C95: 品名词 | D95: 电源站 | E95: 电源站
A96: gadget | B96: 20 | C96: 品名词 | D96: 机器
A97: lightning | B97: 20 | C97: 属性词 | D97: 110伏特 | E97: 交流电
A98: pit | B98: 20 | C98: 品名词 | D98: 冰箱
A99: taylor | B99: 20 | C99: 属性词 | D99: 10000毫安时 | E99: 电池
A100: bread | B100: 19 | C100: 品牌词
...

Sheet 词库
A1: ABA | B1: 流量大小 | C1: 相关性 | D1: 有序性 | E1: 词组 | F1: 一级分类 | G1: 二级分类 | H1: 用户搜索意图标签 | I1: 流量% | J1: SPR | K1: 辅助列 | L1: 追踪 | M1: 关键词 | N1: 关键词翻译 | O1: AC推荐词 | P1: 流量占比 | Q1: 流量词类型 | R1: 预估周曝光量 | S1: 相关产品 | T1: 相关ASIN | U1: ABA周排名 | V1: 月搜索量 | W1: 月购买量 | X1: 购买率 | Y1: 展示量 | Z1: 点击量 | AA1: SPR | AB1: 标题密度 | AC1: 商品数 | AD1: 需供比 | AE1: 广告竞品数 | AF1: 点击集中度 | AG1: 前三ASIN转化总占比 | AH1: PPC竞价 | AI1: 建议竞价范围 | AJ1: #1 前三ASIN | AK1: #1 点击共享 | AL1: #1 转化共享 | AM1: #2 前三ASIN | AN1: #2 点击共享 | AO1: #2 转化共享 | AP1: #3 前三ASIN | AQ1: #3 点击共享 | AR1: #3 转化共享 | AS1: 前十ASIN | AT1: #3 转化共享 | AU1: 前十ASIN
A2: =W2 -> 53815 | B2: =IF(A2="","",IF(A2<词盘!$B$2,"大词",IF(A2<词盘!$C$2,"中尾词","长尾词"))) -> 中尾词 | C2: =IF(S2/20>70%,1,IF(S2/20>40%,2,IF(S2/20>10%,3,0))) -> 1 | D2: =IF(M2="","",IF(OR(E2="/",E2=""),"无序",IF(COUNTIFS(E:E,E2)<4,"无序","有序"))) -> 有序 | E2: meat thermometer | F2: 品名词 | H2: 寻找电源站类型或购买电源站 | I2: =P2/SUM(P:P) -> 0.14007004 | J2: =AC2 -> 4481 | K2: =IFERROR(Z2*AH2,"") -> 843354 | L2: V | M2: meat thermometer | N2: 肉类温度计 | O2: Y | P2: 0.14 | Q2: 自然搜索词/AC推荐词/SP广告词 | R2: 890313 | S2: 16 | T2: B0DDXWY41V/B005KCG6CE/B096K2L985/B0CRY9V6LL/B01F59K0KA/B0BBR2RL6X/B0C7D27GV8/B017613C3C/B0BQ782XNW/B01IHHLB3W/B0BJK5W11R/B00GRFHXVQ/B07XXSYLL8/B09LSGPHT3/B00S93EQUK/B0C37ZWPZR | U2: 1066 | V2: 472070 | W2: 53815 | X2: 0.114 | Y2: 12434912 | Z2: 187412 | AA2: 1220 | AB2: 64 | AC2: 4481 | AD2: 105.35 | AE2: 252 | AF2: 0.4101 | AG2: 0.4083 | AH2: 4.5 | AI2: $3.38 - $5.53 | AJ2: B00S93EQUK | AK2: 0.219 | AL2: 0.2336 | AM2: B09C32DYV1 | AN2: 0.1088 | AO2: 0.0974 | AP2: B09LSGPHT3 | AQ2: 0.0823 | AR2: 0.0773 | AS2: B00S93EQUK,B0DHZTCNR5,B07XXSYLL8,B0DC87RW4R,B0D9QW8L6H,B0DFH64CCP,B0DHVGDCK2,B0DJY2PWTY,B07Y51PCW7,B09LSGPHT3 | AT2: 0.0128 | AU2: B0BPNMT5DM,B07HY3S811,B0CL9SXSBD,B0B8V6Y2X8,B0BC6G9Q35,B0982TPZTW,B07W76MV4Y,B082K8ZNQ1,B07J63KGNN,B07CMJ5186
A3: =W3 -> 64612 | B3: =IF(A3="","",IF(A3<词盘!$B$2,"大词",IF(A3<词盘!$C$2,"中尾词","长尾词"))) -> 中尾词 | C3: =IF(S3/20>70%,1,IF(S3/20>40%,2,IF(S3/20>10%,3,0))) -> 2 | D3: =IF(M3="","",IF(OR(E3="/",E3=""),"无序",IF(COUNTIFS(E:E,E3)<4,"无序","有序"))) -> 无序 | F3: 品名词 | H3: 寻找便携式电源站 | I3: =P3/SUM(P:P) -> 0.11415708 | J3: =AC3 -> 25416 | K3: =IFERROR(Z3*AH3,"") -> 173028.63 | L3: V | M3: thermometer | N3: 温度计 | P3: 0.1141 | Q3: 自然搜索词/SP广告词 | R3: 725764 | S3: 13 | T3: B00GRFHXVQ/B0BQ782XNW/B07XXSYLL8/B09LSGPHT3/B01F59K0KA/B0BBR2RL6X/B00S93EQUK/B01IHHLB3W/B096K2L985/B0BJK5W11R/B0CRY9V6LL/B017613C3C/B0C7D27GV8 | U3: 478 | V3: 740119 | W3: 64612 | X3: 0.0873 | Y3: 20919624 | Z3: 303559 | AA3: 1465 | AB3: 77 | AC3: 25416 | AD3: 29.12 | AE3: 234 | AF3: 0.4903 | AG3: 0.4279 | AH3: 0.57 | AI3: $0.43 - $0.73 | AJ3: B0824XNJSW | AK3: 0.2672 | AL3: 0.2436 | AM3: B08B8BDG42 | AN3: 0.1346 | AO3: 0.1261 | AP3: B0CGRB23YM | AQ3: 0.0885 | AR3: 0.0582 | AS3: B0CRYX9PMK,B0D8J22Q45,B08B8BDG42,B0DC8MWQ8K,B0824XNJSW,B0D8TMK95V,B0DC8776HK,B08B7V2RG3,B0D9VZ1MWH,B0DD7KZD1G | AT3: 0.0327 | AU3: B0B8V6Y2X8,B07SRRQS5B,B0CXHY4R34,B0C1GQ54QD,B0CFF2JG1N,B0982TPZTW,B07HY3S811,B0CSN2CZQR,B0BVR8F5W3,B07XGMMXY2
A4: =W4 -> 2595 | B4: =IF(A4="","",IF(A4<词盘!$B$2,"大词",IF(A4<词盘!$C$2,"中尾词","长尾词"))) -> 大词 | C4: =IF(S4/20>70%,1,IF(S4/20>40%,2,IF(S4/20>10%,3,0))) -> 3 | D4: =IF(M4="","",IF(OR(E4="/",E4=""),"无序",IF(COUNTIFS(E:E,E4)<4,"无序","有序"))) -> 无序 | F4: 品名词 | H4: 寻找太阳能发电机 | I4: =P4/SUM(P:P) -> 0.065132566 | J4: =AC4 -> 163176 | K4: =IFERROR(Z4*AH4,"") -> 240882.52 | M4: kitchen | N4: 厨房 | P4: 0.0651 | Q4: 自然搜索词/HR推荐词/SP广告词 | R4: 414330 | S4: 7 | T4: B07XXSYLL8/B09LSGPHT3/B00S93EQUK/B01IHHLB3W/B0BJK5W11R/B096K2L985/B0CRY9V6LL | U4: 385 | V4: 540748 | W4: 2595 | X4: 0.0048 | Y4: 13489824 | Z4: 256258 | AA4: 59 | AB4: 59 | AC4: 163176 | AD4: 3.31 | AE4: 1419 | AF4: 0.0815 | AG4: 0.0464 | AH4: 0.94 | AI4: $0.74 - $1.15 | AJ4: B0C3QZ7SNF | AK4: 0.0296 | AL4: 0.0305 | AM4: B0DLGBRSFM | AN4: 0.0289 | AO4: 0 | AP4: B0BKRVT66L | AQ4: 0.023 | AR4: 0.0159 | AS4: B0C7CV5CQR,B0CQJWVP8B,B08573DQ39,B0CR1RHMJY,B0CTKTPKV8,B09N4ZKCH6,B0C7CXGBLZ,B0D2P1HSCV,B0D5L9BHX6,B01ACUA8HC | AT4: 0.0284 | AU4: B08YZ633BY,B0C6X2VP9R,B00I5H5Z1O,B0CC3SQL47,B0BGWZN7MV,B0BZWM3JG4,B07GKVBQDG,B0B7BFMHNF,B07L87GPPT,B0BQDHTCCR
A5: =W5 -> 34912 | B5: =IF(A5="","",IF(A5<词盘!$B$2,"大词",IF(A5<词盘!$C$2,"中尾词","长尾词"))) -> 中尾词 | C5: =IF(S5/20>70%,1,IF(S5/20>40%,2,IF(S5/20>10%,3,0))) -> 1 | D5: =IF(M5="","",IF(OR(E5="/",E5=""),"无序",IF(COUNTIFS(E:E,E5)<4,"无序","有序"))) -> 有序 | E5: meat thermometer | F5: 品牌词 | H5: 了解或购买Jackery品牌的电源产品 | I5: =P5/SUM(P:P) -> 0.059729865 | J5: =AC5 -> 2478 | K5: =IFERROR(Z5*AH5,"") -> 189768.96 | L5: V | M5: meat thermometer digital | N5: 数字式肉类温度计 | P5: 0.0597 | Q5: 自然搜索词 | R5: 379969 | S5: 15 | T5: B01F59K0KA/B0BBR2RL6X/B017613C3C/B0BJK5W11R/B01IHHLB3W/B0BQ782XNW/B00GRFHXVQ/B096K2L985/B07XXSYLL8/B09LSGPHT3/B0CRY9V6LL/B00S93EQUK/B005KCG6CE/B0C7D27GV8/B0DDXWY41V | U5: 2849 | V5: 227297 | W5: 34912 | X5: 0.1536 | Y5: 6331995 | Z5: 87856 | AA5: 792 | AB5: 27 | AC5: 2478 | AD5: 91.73 | AE5: 183 | AF5: 0.4501 | AG5: 0.4422 | AH5: 2.16 | AI5: $1.82 - $2.51 | AJ5: B00S93EQUK | AK5: 0.2546 | AL5: 0.2662 | AM5: B09C32DYV1 | AN5: 0.1141 | AO5: 0.1022 | AP5: B09LSGPHT3 | AQ5: 0.0814 | AR5: 0.0738 | AS5: B00S93EQUK,B07XXSYLL8,B07Y51PCW7,B017613C3C,B01IHHLB3W,B09LSGPHT3,B0BQ782XNW,B0C37DLHWW,B0DHZTCNR5,B0DFW43B44 | AT5: 0.0431 | AU5: B07SRRQS5B,B07HY3S811,B0B8V6Y2X8,B0982TPZTW,B0CFF2JG1N,B01DODMU9I,B0B75JF6CM,B09N71WGLF,B0C6X3VPLC,B0BXCKKNN8
A6: =W6 -> 10419 | B6: =IF(A6="","",IF(A6<词盘!$B$2,"大词",IF(A6<词盘!$C$2,"中尾词","长尾词"))) -> 大词 | C6: =IF(S6/20>70%,1,IF(S6/20>40%,2,IF(S6/20>10%,3,0))) -> 2 | D6: =IF(M6="","",IF(OR(E6="/",E6=""),"无序",IF(COUNTIFS(E:E,E6)<4,"无序","有序"))) -> 有序 | E6: food thermometer | F6: 品名词 | H6: 寻找便携式发电机 | I6: =P6/SUM(P:P) -> 0.031615808 | J6: =AC6 -> 6721 | K6: =IFERROR(Z6*AH6,"") -> 85210 | L6: V | M6: food thermometer | N6: 食品温度计 | P6: 0.0316 | Q6: 自然搜索词/SP广告词 | R6: 200766 | S6: 14 | T6: B005KCG6CE/B096K2L985/B01F59K0KA/B0BBR2RL6X/B017613C3C/B0BQ782XNW/B0BJK5W11R/B01IHHLB3W/B00GRFHXVQ/B07XXSYLL8/B09LSGPHT3/B0CRY9V6LL/B00S93EQUK/B0C7D27GV8 | U6: 10192 | V6: 98116 | W6: 10419 | X6: 0.1062 | Y6: 2737596 | Z6: 42605 | AA6: 237 | AB6: 38 | AC6: 6721 | AD6: 14.6 | AE6: 202 | AF6: 0.3447 | AG6: 0.3347 | AH6: 2 | AI6: $1.39 - $2.22 | AJ6: B00S93EQUK | AK6: 0.1834 | AL6: 0.1894 | AM6: B0BQ782XNW | AN6: 0.0858 | AO6: 0.0718 | AP6: B09LSGPHT3 | AQ6: 0.0755 | AR6: 0.0735 | AS6: B00S93EQUK,B01IHHLB3W,B07Y51PCW7,B09LSGPHT3,B07XXSYLL8,B0D9QW8L6H,B0C37DLHWW,B017613C3C,B0DHKM51RK,B08RWPPD8J | AT6: 0.0431 | AU6: B07SRRQS5B,B0B8V6Y2X8,B0CL9SXSBD,B01DODMU9I,B07HY3S811,B082K8ZNQ1,B07W76MV4Y,B00LB7REMS,B0CFF2JG1N,B07S59BW5F
A7: =W7 -> 9829 | B7: =IF(A7="","",IF(A7<词盘!$B$2,"大词",IF(A7<词盘!$C$2,"中尾词","长尾词"))) -> 大词 | C7: =IF(S7/20>70%,1,IF(S7/20>40%,2,IF(S7/20>10%,3,0))) -> 2 | D7: =IF(M7="","",IF(OR(E7="/",E7=""),"无序",IF(COUNTIFS(E:E,E7)<4,"无序","有序"))) -> 无序 | F7: 品牌词 | H7: 了解或购买Anker品牌的电源产品 | I7: =P7/SUM(P:P) -> 0.026013007 | J7: =AC7 -> 6961 | K7: =IFERROR(Z7*AH7,"") -> 57224.7 | L7: V | M7: cooking thermometer | N7: 烹饪温度计 | P7: 0.026 | Q7: 自然搜索词 | R7: 165473 | S7: 14 | T7: B0C7D27GV8/B005KCG6CE/B00GRFHXVQ/B096K2L985/B0CRY9V6LL/B01F59K0KA/B0BBR2RL6X/B0BJK5W11R/B017613C3C/B0BQ782XNW/B01IHHLB3W/B07XXSYLL8/B09LSGPHT3/B00S93EQUK | U7: 19194 | V7: 72759 | W7: 9829 | X7: 0.1351 | Y7: 1708167 | Z7: 28470 | AA7: 224 | AB7: 12 | AC7: 6961 | AD7: 10.45 | AE7: 179 | AF7: 0.3317 | AG7: 0.3229 | AH7: 2.01 | AI7: $1.59 - $2.25 | AJ7: B00S93EQUK | AK7: 0.1733 | AL7: 0.1951 | AM7: B09C32DYV1 | AN7: 0.0849 | AO7: 0.0712 | AP7: B0BQ782XNW | AQ7: 0.0735 | AR7: 0.0566 | AS7: B00S93EQUK,B07XXSYLL8,B07Y51PCW7,B0DFH64CCP,B01IHHLB3W,B017613C3C,B09LSGPHT3,B0B71HFH9K,B0D6YQ8LV2,B0DC8776HK | AT7: 0.0252 | AU7: B08YZ633BY,B0CL9YMRD5,B07MYW7C3Z,B07Z13H4TP,B09MQWWP87,B07SRRQS5B,B07CZDXDG8,B00I5H5Z1O,B0BN9DD956,B0B7BFMHNF
A8: =W8 -> 9881 | B8: =IF(A8="","",IF(A8<词盘!$B$2,"大词",IF(A8<词盘!$C$2,"中尾词","长尾词"))) -> 大词 | C8: =IF(S8/20>70%,1,IF(S8/20>40%,2,IF(S8/20>10%,3,0))) -> 1 | D8: =IF(M8="","",IF(OR(E8="/",E8=""),"无序",IF(COUNTIFS(E:E,E8)<4,"无序","有序"))) -> 无序 | F8: 功能词 | G8: 包括太阳能面板 | H8: 寻找带太阳能面板的太阳能发电机 | I8: =P8/SUM(P:P) -> 0.022011006 | J8: =AC8 -> 2188 | K8: =IFERROR(Z8*AH8,"") -> 53492 | M8: instant read thermometer | N8: 速读温度计 | P8: 0.022 | Q8: 自然搜索词 | R8: 139639 | S8: 15 | T8: B0DDXWY41V/B0BJK5W11R/B005KCG6CE/B096K2L985/B00GRFHXVQ/B01F59K0KA/B0CRY9V6LL/B0BBR2RL6X/B0BQ782XNW/B017613C3C/B01IHHLB3W/B07XXSYLL8/B09LSGPHT3/B00S93EQUK/B0C7D27GV8 | U8: 23593 | V8: 64331 | W8: 9881 | X8: 0.1536 | Y8: 1633185 | Z8: 31100 | AA8: 225 | AB8: 12 | AC8: 2188 | AD8: 29.4 | AE8: 158 | AF8: 0.4861 | AG8: 0.457 | AH8: 1.72 | AI8: $1.28 - $2.15 | AJ8: B00S93EQUK | AK8: 0.2701 | AL8: 0.2681 | AM8: B07XXSYLL8 | AN8: 0.1379 | AO8: 0.1157 | AP8: B09LSGPHT3 | AQ8: 0.0781 | AR8: 0.0732 | AS8: B0DG2YC3BW,B00S93EQUK,B07XXSYLL8,B0DG6FVVFN,B01IHHLB3W,B07Y51PCW7,B0DJY2PWTY,B08X6KHFMX,B09LSGPHT3,B0BBR2RL6X | AT8: 0.066 | AU8: B00LB7REFK,B01MXSZOKS,B0CFV5LZ3R,B07QHDRCZ3,B09YJ34W96,B079X5FTZR,B0C7F7LS8Z,B09BF7N5MT,B0BC6G9Q35,B0CX53FBSR
A9: =W9 -> 27793 | B9: =IF(A9="","",IF(A9<词盘!$B$2,"大词",IF(A9<词盘!$C$2,"中尾词","长尾词"))) -> 中尾词 | C9: =IF(S9/20>70%,1,IF(S9/20>40%,2,IF(S9/20>10%,3,0))) -> 2 | D9: =IF(M9="","",IF(OR(E9="/",E9=""),"无序",IF(COUNTIFS(E:E,E9)<4,"无序","有序"))) -> 无序 | F9: 品牌词 | H9: 了解或购买EcoFlow品牌电源产品 | I9: =P9/SUM(P:P) -> 0.021710855 | J9: =AC9 -> 3307 | K9: =IFERROR(Z9*AH9,"") -> 114072.96 | M9: oven thermometer | N9: 烤箱温度计 | P9: 0.0217 | Q9: 自然搜索词 | R9: 137749 | S9: 14 | T9: B0BBR2RL6X/B0BJK5W11R/B017613C3C/B005KCG6CE/B00GRFHXVQ/B0CRY9V6LL/B00S93EQUK/B01IHHLB3W/B07XXSYLL8/B09LSGPHT3/B096K2L985/B01F59K0KA/B0BQ782XNW/B0C7D27GV8 | U9: 6999 | V9: 155443 | W9: 27793 | X9: 0.1788 | Y9: 4046535 | Z9: 64448 | AA9: 630 | AB9: 36 | AC9: 3307 | AD9: 47 | AE9: 200 | AF9: 0.6982 | AG9: 0.6352 | AH9: 1.77 | AI9: $1.34 - $2.23 | AJ9: B083BMMQV9 | AK9: 0.4441 | AL9: 0.4444 | AM9: B005KDEIZ0 | AN9: 0.1404 | AO9: 0.0954 | AP9: B0000DJUYR | AQ9: 0.1137 | AR9: 0.0954 | AS9: B083BMMQV9,B0000DJUYR,B07YP9G4Z7,B0D6YQ8LV2,B017613C3C,B0CX19TQH1,B000BQWMTK,B09JSBXJDV,B08GY3K7KD,B0D3XLVZCP | AT9: 0.0164 | AU9: B07SRRQS5B,B07HY3S811,B0982TPZTW,B01DODMU9I,B09NFRC4LM,B0B75JF6CM,B0CFF2JG1N,B0C42FRFHG,B0B8V6Y2X8,B0BN9DD956
A10: =W10 -> 5334 | B10: =IF(A10="","",IF(A10<词盘!$B$2,"大词",IF(A10<词盘!$C$2,"中尾词","长尾词"))) -> 大词 | C10: =IF(S10/20>70%,1,IF(S10/20>40%,2,IF(S10/20>10%,3,0))) -> 2 | D10: =IF(M10="","",IF(OR(E10="/",E10=""),"无序",IF(COUNTIFS(E:E,E10)<4,"无序","有序"))) -> 无序 | F10: 场景词 | G10: 户外活动场景 | H10: 寻找适合户外活动的电源或设备 | I10: =P10/SUM(P:P) -> 0.020610305 | J10: =AC10 -> 10631 | K10: =IFERROR(Z10*AH10,"") -> 99923.34 | L10: V | M10: digital thermometer | N10: 数字温度计 | P10: 0.0206 | Q10: 自然搜索词 | R10: 130893 | S10: 13 | T10: B0CRY9V6LL/B017613C3C/B0BQ782XNW/B01IHHLB3W/B07XXSYLL8/B09LSGPHT3/B01F59K0KA/B00S93EQUK/B0BBR2RL6X/B00GRFHXVQ/B096K2L985/B0BJK5W11R/B0C7D27GV8 | U10: 10392 | V10: 85076 | W10: 5334 | X10: 0.0627 | Y10: 1921067 | Z10: 32978 | AA10: 121 | AB10: 17 | AC10: 10631 | AD10: 8 | AE10: 172 | AF10: 0.3826 | AG10: 0.3653 | AH10: 3.03 | AI10: $2.27 - $3.79 | AJ10: B0824XNJSW | AK10: 0.2111 | AL10: 0.2012 | AM10: B08B8BDG42 | AN10: 0.0944 | AO10: 0.0979 | AP10: B08B7V2RG3 | AQ10: 0.0771 | AR10: 0.0662 | AS10: B0D6RHCSCJ,B0824XNJSW,B08B8BDG42,B00S93EQUK,B0D8HY1YQM,B0CGRB23YM,B0DFLQQ2K7,B08B7V2RG3,B0DFM3S7VR,B07XXSYLL8 | AT10: 0.0354 | AU10: B07SRRQS5B,B0B8V6Y2X8,B0CL9SXSBD,B0995B8K8V,B0982TPZTW,B0B75JF6CM,B01MQQTB51,B0BXCKKNN8,B0BC6G9Q35,B07MXJ93K8
A11: =W11 -> 8676 | B11: =IF(A11="","",IF(A11<词盘!$B$2,"大词",IF(A11<词盘!$C$2,"中尾词","长尾词"))) -> 大词 | C11: =IF(S11/20>70%,1,IF(S11/20>40%,2,IF(S11/20>10%,3,0))) -> 2 | D11: =IF(M11="","",IF(OR(E11="/",E11=""),"无序",IF(COUNTIFS(E:E,E11)<4,"无序","有序"))) -> 有序 | E11: food thermometer | F11: 场景词 | G11: 户外活动必备品 | H11: 了解户外活动必备电源设备或其他装备 | I11: =P11/SUM(P:P) -> 0.017008504 | J11: =AC11 -> 4847 | K11: =IFERROR(Z11*AH11,"") -> 49106 | L11: V | M11: food thermometer for cooking | N11: 烹饪用食物温度计 | P11: 0.017 | Q11: 自然搜索词 | R11: 108140 | S11: 14 | T11: B0C7D27GV8/B005KCG6CE/B096K2L985/B00GRFHXVQ/B0BBR2RL6X/B017613C3C/B0BQ782XNW/B01IHHLB3W/B0BJK5W11R/B07XXSYLL8/B09LSGPHT3/B01F59K0KA/B0CRY9V6LL/B00S93EQUK | U11: 29589 | V11: 56487 | W11: 8676 | X11: 0.1536 | Y11: 1521326 | Z11: 24553 | AA11: 197 | AB11: 5 | AC11: 4847 | AD11: 11.65 | AE11: 124 | AF11: 0.4575 | AG11: 0.4119 | AH11: 2 | AI11: $1.40 - $2.32 | AJ11: B00S93EQUK | AK11: 0.2009 | AL11: 0.1901 | AM11: B09LSGPHT3 | AN11: 0.1636 | AO11: 0.1331 | AP11: B0DQDB5DRR | AQ11: 0.093 | AR11: 0.0887 | AS11: B00S93EQUK,B01IHHLB3W,B09LSGPHT3,B07XXSYLL8,B07Y51PCW7,B0C37DLHWW,B017613C3C,B09MTX71VX,B0B71HFH9K,B0BQ782XNW | AT11: 0.0203 | AU11: B079X5FTZR,B0BY3RK5CC,B07G5KHQGH,B079JYP5DP,B084YPVTXB,B0C5N9YYTY,B079X5XWXP,B07SRRQS5B,B0BWNXJ9QR,B082K8ZNQ1
A12: =W12 -> 8075 | B12: =IF(A12="","",IF(A12<词盘!$B$2,"大词",IF(A12<词盘!$C$2,"中尾词","长尾词"))) -> 大词 | C12: =IF(S12/20>70%,1,IF(S12/20>40%,2,IF(S12/20>10%,3,0))) -> 1 | D12: =IF(M12="","",IF(OR(E12="/",E12=""),"无序",IF(COUNTIFS(E:E,E12)<4,"无序","有序"))) -> 有序 | E12: meat thermometer | F12: 场景词 | G12: 家庭使用场景 | H12: 寻找家庭用发电机 | I12: =P12/SUM(P:P) -> 0.016808404 | J12: =AC12 -> 2490 | K12: =IFERROR(Z12*AH12,"") -> 63407.37 | M12: digital meat thermometer | N12: 数字式肉类温度计 | P12: 0.0168 | Q12: 自然搜索词 | R12: 107187 | S12: 15 | T12: B096K2L985/B0C7D27GV8/B0CRY9V6LL/B0BBR2RL6X/B017613C3C/B0BJK5W11R/B0BQ782XNW/B01IHHLB3W/B07XXSYLL8/B09LSGPHT3/B01F59K0KA/B00S93EQUK/B005KCG6CE/B00GRFHXVQ/B0DDXWY41V | U12: 23252 | V12: 69680 | W12: 8075 | X12: 0.1159 | Y12: 1787141 | Z12: 31863 | AA12: 184 | AB12: 18 | AC12: 2490 | AD12: 27.98 | AE12: 175 | AF12: 0.4705 | AG12: 0.4274 | AH12: 1.99 | AI12: $1.59 - $2.64 | AJ12: B00S93EQUK | AK12: 0.2455 | AL12: 0.2327 | AM12: B09C32DYV1 | AN12: 0.1197 | AO12: 0.0944 | AP12: B09LSGPHT3 | AQ12: 0.1053 | AR12: 0.1003 | AS12: B00S93EQUK,B07XXSYLL8,B07Y51PCW7,B09LSGPHT3,B017613C3C,B01IHHLB3W,B0BQ782XNW,B0DJY2PWTY,B0C37DLHWW,B0DG5LP1VK | AT12: 0.0036 | AU12: B08YZ633BY,B0CJB2KBJX,B01LXFSJY7,B0CGX538DK,B08S8RZ32R,B0CPDYVKPX,B0B7S213SX,B09DYN6SYR,B007BF7BUY,B00I5H5Z1O
A13: =W13 -> 8556 | B13: =IF(A13="","",IF(A13<词盘!$B$2,"大词",IF(A13<词盘!$C$2,"中尾词","长尾词"))) -> 大词 | C13: =IF(S13/20>70%,1,IF(S13/20>40%,2,IF(S13/20>10%,3,0))) -> 1 | D13: =IF(M13="","",IF(OR(E13="/",E13=""),"无序",IF(COUNTIFS(E:E,E13)<4,"无序","有序"))) -> 无序 | F13: 功能词 | G13: 太阳能发电 | H13: 寻找太阳能发电机 | I13: =P13/SUM(P:P) -> 0.016808404 | J13: =AC13 -> 1312 | K13: =IFERROR(Z13*AH13,"") -> 71401.9 | M13: candy thermometer | N13: 糖果温度计 | P13: 0.0168 | Q13: 自然搜索词 | R13: 107080 | S13: 16 | T13: B0DDXWY41V/B017613C3C/B01IHHLB3W/B07XXSYLL8/B09LSGPHT3/B0BBR2RL6X/B00S93EQUK/B0BQ782XNW/B0BJK5W11R/B005KCG6CE/B00GRFHXVQ/B01F59K0KA/B0CRY9V6LL/B096K2L985/B0C7D27GV8/B0DGXKNV6Y | U13: 10343 | V13: 121371 | W13: 8556 | X13: 0.0705 | Y13: 3178848 | Z13: 53285 | AA13: 194 | AB13: 39 | AC13: 1312 | AD13: 92.51 | AE13: 225 | AF13: 0.4028 | AG13: 0.3438 | AH13: 1.34 | AI13: $1.00 - $1.67 | AJ13: B094NBSRT4 | AK13: 0.1496 | AL13: 0.1331 | AM13: B098DSQHY9 | AN13: 0.139 | AO13: 0.1267 | AP13: B0DMNQZTR3 | AQ13: 0.1142 | AR13: 0.084 | AS13: B0DC8MWQ8K,B00004XSC9,B01CI50FJU,B0D89YR1W2,B0BGX4RG9B,B001FB6IFY,B0DC8776HK,B07YP9GT1N,B09QJJSZM5,B01BICCN6M | AT13: 0.0267 | AU13: B0C1GQ54QD,B0CSN2CZQR,B09964WTF5,B0CM6L37XR,B0CT5GCT24,B0CXHY4R34,B08CXGDZXD,B0C6G43SGX,B0BVR8F5W3,B0CP27G91Z
A14: =W14 -> 5461 | B14: =IF(A14="","",IF(A14<词盘!$B$2,"大词",IF(A14<词盘!$C$2,"中尾词","长尾词"))) -> 大词 | C14: =IF(S14/20>70%,1,IF(S14/20>40%,2,IF(S14/20>10%,3,0))) -> 2 | D14: =IF(M14="","",IF(OR(E14="/",E14=""),"无序",IF(COUNTIFS(E:E,E14)<4,"无序","有序"))) -> 无序 | F14: 功能词 | G14: 便携式发电机 | H14: 寻找便携式发电机 | I14: =P14/SUM(P:P) -> 0.016108054 | J14: =AC14 -> 7012 | K14: =IFERROR(Z14*AH14,"") -> 58588 | L14: V | M14: thermometer for cooking | N14: 烹饪温度计 | P14: 0.0161 | Q14: 自然搜索词 | R14: 102107 | S14: 14 | T14: B005KCG6CE/B096K2L985/B01F59K0KA/B017613C3C/B0BQ782XNW/B01IHHLB3W/B0BJK5W11R/B00GRFHXVQ/B07XXSYLL8/B09LSGPHT3/B0CRY9V6LL/B0BBR2RL6X/B00S93EQUK/B0C7D27GV8 | U14: 26839 | V14: 61638 | W14: 5461 | X14: 0.0886 | Y14: 1707180 | Z14: 29294 | AA14: 125 | AB14: 16 | AC14: 7012 | AD14: 8.79 | AE14: 177 | AF14: 0.2989 | AG14: 0.3046 | AH14: 2 | AI14: $1.58 - $2.27 | AJ14: B00S93EQUK | AK14: 0.1447 | AL14: 0.1692 | AM14: B09C32DYV1 | AN14: 0.0779 | AO14: 0.0631 | AP14: B0DQDB5DRR | AQ14: 0.0763 | AR14: 0.0723 | AS14: B00S93EQUK,B07XXSYLL8,B07Y51PCW7,B01IHHLB3W,B017613C3C,B0B71HFH9K,B09LSGPHT3,B09MTX71VX,B0C37DLHWW,B0BQ782XNW | AT14: 0.012 | AU14: B07SRRQS5B,B07VHPFK5B,B0B8V6Y2X8,B0CFV5LZ3R,B07HY3S811,B0982TPZTW,B0C6X25XQ3,B01IEJHJWK,B0BC6G9Q35,B0CFF2JG1N
A15: =W15 -> 5951 | B15: =IF(A15="","",IF(A15<词盘!$B$2,"大词",IF(A15<词盘!$C$2,"中尾词","长尾词"))) -> 大词 | C15: =IF(S15/20>70%,1,IF(S15/20>40%,2,IF(S15/20>10%,3,0))) -> 1 | D15: =IF(M15="","",IF(OR(E15="/",E15=""),"无序",IF(COUNTIFS(E:E,E15)<4,"无序","有序"))) -> 无序 | F15: 品牌词 | H15: 了解或购买Bluetti品牌的电源产品 | I15: =P15/SUM(P:P) -> 0.012606303 | J15: =AC15 -> 2804 | K15: =IFERROR(Z15*AH15,"") -> 26836.59 | M15: digital thermometer for cooking | N15: 烹饪用数字温度计 | P15: 0.0126 | Q15: 自然搜索词 | R15: 80468 | S15: 15 | T15: B096K2L985/B0CRY9V6LL/B0BBR2RL6X/B017613C3C/B0BJK5W11R/B0BQ782XNW/B01IHHLB3W/B0C7D27GV8/B00GRFHXVQ/B07XXSYLL8/B09LSGPHT3/B005KCG6CE/B01F59K0KA/B00S93EQUK/B0DDXWY41V | U15: 36126 | V15: 46866 | W15: 5951 | X15: 0.127 | Y15: 1063853 | Z15: 22179 | AA15: 135 | AB15: 0 | AC15: 2804 | AD15: 16.71 | AE15: 180 | AF15: 0.3822 | AG15: 0.3798 | AH15: 1.21 | AI15: $0.67 - $2.43 | AJ15: B00S93EQUK | AK15: 0.2041 | AL15: 0.2433 | AM15: B09C32DYV1 | AN15: 0.1034 | AO15: 0.0816 | AP15: B0DQDB5DRR | AQ15: 0.0747 | AR15: 0.0549 | AS15: B00S93EQUK,B07XXSYLL8,B07Y51PCW7,B017613C3C,B01IHHLB3W,B09LSGPHT3,B0B71HFH9K,B0C37DLHWW,B09MTX71VX,B09988SD2B | AT15: 0.0514 | AU15: B0CZDB93YR,B0CYBVYNRL,B0CYBV9Q6M,B01DODMU9I,B07WLPBPKM,B01MQQTB51,B0CRQJ23DH,B09PGQD7LS,B0D17C4VNX,B082K8ZNQ1
A16: =W16 -> 3688 | B16: =IF(A16="","",IF(A16<词盘!$B$2,"大词",IF(A16<词盘!$C$2,"中尾词","长尾词"))) -> 大词 | C16: =IF(S16/20>70%,1,IF(S16/20>40%,2,IF(S16/20>10%,3,0))) -> 2 | D16: =IF(M16="","",IF(OR(E16="/",E16=""),"无序",IF(COUNTIFS(E:E,E16)<4,"无序","有序"))) -> 无序 | F16: 品牌词 | H16: 了解或购买Bluetti品牌的电源产品 | I16: =P16/SUM(P:P) -> 0.012006003 | J16: =AC16 -> 58126 | K16: =IFERROR(Z16*AH16,"") -> 116108.69 | L16: V | M16: kitchen gadgets | N16: 厨房小工具 | P16: 0.012 | Q16: 自然搜索词/SP广告词 | R16: 76468 | S16: 10 | T16: B09LSGPHT3/B00S93EQUK/B07XXSYLL8/B0C7D27GV8/B017613C3C/B01F59K0KA/B01IHHLB3W/B096K2L985/B0BBR2RL6X/B0CRY9V6LL | U16: 3814 | V16: 400944 | W16: 3688 | X16: 0.0092 | Y16: 9701425 | Z16: 159053 | AA16: 84 | AB16: 27 | AC16: 58126 | AD16: 6.9 | AE16: 481 | AF16: 0.1517 | AG16: 0.0624 | AH16: 0.73 | AI16: $0.55 - $0.91 | AJ16: B0CJF94M8J | AK16: 0.0687 | AL16: 0.0518 | AM16: B0764HS4SL | AN16: 0.0493 | AO16: 0.0106 | AP16: B0D7CZ9Y7D | AQ16: 0.0337 | AR16: 0 | AS16: B08N9Q24M9,B0764HS4SL,B0C9ZQ434J,B08573DQ39,B07D15V7T3,B0C3H9MJQV,B0CLS1D1SY,B0DCGG1FDT,B0CJ4WZXQF,B07GTC4NCV | AT16: 0.0763 | AU16: B0CXTBZR2H,B0D1KDXFZJ,B0D17DB7SX,B07WLPBPKM,B0CZRC9F86,B01MQQTB51,B0D17C4VNX,B0CZDB93YR,B0D1XL2B6P,B0CYBRQ7FC
A17: =W17 -> 3659 | B17: =IF(A17="","",IF(A17<词盘!$B$2,"大词",IF(A17<词盘!$C$2,"中尾词","长尾词"))) -> 大词 | C17: =IF(S17/20>70%,1,IF(S17/20>40%,2,IF(S17/20>10%,3,0))) -> 1 | D17: =IF(M17="","",IF(OR(E17="/",E17=""),"无序",IF(COUNTIFS(E:E,E17)<4,"无序","有序"))) -> 有序 | E17: meat thermometer | F17: 属性词 | G17: 太阳能面板 | H17: 寻找太阳能面板 | I17: =P17/SUM(P:P) -> 0.0086043022 | J17: =AC17 -> 1378 | K17: =IFERROR(Z17*AH17,"") -> 24948.69 | L17: V | M17: instant read meat thermometer | N17: 速读肉温计 | P17: 0.0086 | Q17: 自然搜索词/SP广告词 | R17: 54748 | S17: 15 | T17: B0BJK5W11R/B005KCG6CE/B096K2L985/B01F59K0KA/B0CRY9V6LL/B0BBR2RL6X/B017613C3C/B0BQ782XNW/B01IHHLB3W/B00GRFHXVQ/B07XXSYLL8/B09LSGPHT3/B00S93EQUK/B0C7D27GV8/B0DDXWY41V | U17: 71611 | V17: 26288 | W17: 3659 | X17: 0.1392 | Y17: 708335 | Z17: 11289 | AA17: 83 | AB17: 32 | AC17: 1378 | AD17: 19.08 | AE17: 137 | AF17: 0.5153 | AG17: 0.5177 | AH17: 2.21 | AI17: $1.61 - $2.76 | AJ17: B00S93EQUK | AK17: 0.2634 | AL17: 0.2752 | AM17: B09LSGPHT3 | AN17: 0.1355 | AO17: 0.1172 | AP17: B0DHZTCNR5 | AQ17: 0.1164 | AR17: 0.1253 | AS17: B00S93EQUK,B07XXSYLL8,B0DJY2PWTY,B07Y51PCW7,B01IHHLB3W,B0DG5LP1VK,B09LSGPHT3,B0DHZTCNR5,B0BBR2RL6X,B0DKHVXLHW | AT17: 0.012 | AU17: B07SRRQS5B,B0CL9SXSBD,B0B8V6Y2X8,B07HY3S811,B0982TPZTW,B082K8ZNQ1,B01DODMU9I,B0CFF2JG1N,B0C9N2GH43,B00DZKQLZ0
A18: =W18 -> 3964 | B18: =IF(A18="","",IF(A18<词盘!$B$2,"大词",IF(A18<词盘!$C$2,"中尾词","长尾词"))) -> 大词 | C18: =IF(S18/20>70%,1,IF(S18/20>40%,2,IF(S18/20>10%,3,0))) -> 0 | D18: =IF(M18="","",IF(OR(E18="/",E18=""),"无序",IF(COUNTIFS(E:E,E18)<4,"无序","有序"))) -> 无序 | F18: 品牌词 | H18: 了解或购买Anker品牌的电源产品 | I18: =P18/SUM(P:P) -> 0.0082041021 | J18: =AC18 -> 197742 | K18: =IFERROR(Z18*AH18,"") -> 150343.83 | L18: V | M18: gifts for men | N18: 男士礼物 | O18: Y | P18: 0.0082 | Q18: 自然搜索词/AC推荐词/SP广告词 | R18: 51984 | S18: 2 | T18: B00S93EQUK/B01F59K0KA | U18: 2044 | V18: 333120 | W18: 3964 | X18: 0.0119 | Y18: 7022443 | Z18: 128499 | AA18: 90 | AB18: 18 | AC18: 197742 | AD18: 1.68 | AE18: 630 | AF18: 0.1052 | AG18: 0.0707 | AH18: 1.17 | AI18: $0.88 - $1.48 | AJ18: 1450845800 | AK18: 0.0431 | AL18: 0.0402 | AM18: B0D4215HCX | AN18: 0.0334 | AO18: 0.0181 | AP18: B0CRR1XXC4 | AQ18: 0.0287 | AR18: 0.0124 | AS18: B0B4X5SLKC,B0BKYR53JB,B0CZ7RQRQD,B0CZ7S666D,B0D84GSMR5,B0D94SF2P6,B0DBH99KYR,B07G142F9Z,B07S1BNNYD,B0CP9YF9W7 | AT18: 0.0113 | AU18: B07SRRQS5B,B0BPNMT5DM,B07HY3S811,B07P8NXQF4,B0BXN2WJ3D,B0982TPZTW,B0B8V6Y2X8,B0BC6G9Q35,B01DODMU9I,B01IEJHJWK
A19: =W19 -> 2749 | B19: =IF(A19="","",IF(A19<词盘!$B$2,"大词",IF(A19<词盘!$C$2,"中尾词","长尾词"))) -> 大词 | C19: =IF(S19/20>70%,1,IF(S19/20>40%,2,IF(S19/20>10%,3,0))) -> 1 | D19: =IF(M19="","",IF(OR(E19="/",E19=""),"无序",IF(COUNTIFS(E:E,E19)<4,"无序","有序"))) -> 无序 | F19: 场景词 | G19: 户外发电机场景 | H19: 寻找适合户外活动的电源或设备 | I19: =P19/SUM(P:P) -> 0.007803902 | J19: =AC19 -> 7489 | K19: =IFERROR(Z19*AH19,"") -> 22090.8 | M19: kitchen thermometer | N19: 厨房温度计 | P19: 0.0078 | Q19: 自然搜索词/SP广告词 | R19: 49804 | S19: 15 | T19: B0BJK5W11R/B005KCG6CE/B096K2L985/B0C7D27GV8/B01F59K0KA/B0CRY9V6LL/B017613C3C/B0BQ782XNW/B01IHHLB3W/B07XXSYLL8/B00GRFHXVQ/B09LSGPHT3/B0BBR2RL6X/B00S93EQUK/B0DDXWY41V | U19: 73086 | V19: 27470 | W19: 2749 | X19: 0.1001 | Y19: 817943 | Z19: 10776 | AA19: 63 | AB19: 3 | AC19: 7489 | AD19: 3.67 | AE19: 202 | AF19: 0.3377 | AG19: 0.2983 | AH19: 2.05 | AI19: $1.54 - $2.57 | AJ19: B00S93EQUK | AK19: 0.1421 | AL19: 0.1559 | AM19: B0C37DLHWW | AN19: 0.1004 | AO19: 0.061 | AP19: B09C32DYV1 | AQ19: 0.0952 | AR19: 0.0814 | AS19: B0D9VYW2Q9,B0D9VZ1MWH,B0DG2YC3BW,B00S93EQUK,B07XXSYLL8,B0C37DLHWW,B09LSGPHT3,B0D174XGXH,B07Y51PCW7,B017613C3C | AT19: 0.0068 | AU19: B0BQZBMXD4,B08YZ633BY,B00I5H5Z1O,B0B7BFMHNF,B07QK9C9KT,B095C7H62X,B007BF7BUY,B0BN9DD956,B0C5R981CT,B07MYW7C3Z
A20: =W20 -> 5405 | B20: =IF(A20="","",IF(A20<词盘!$B$2,"大词",IF(A20<词盘!$C$2,"中尾词","长尾词"))) -> 大词 | C20: =IF(S20/20>70%,1,IF(S20/20>40%,2,IF(S20/20>10%,3,0))) -> 3 | D20: =IF(M20="","",IF(OR(E20="/",E20=""),"无序",IF(COUNTIFS(E:E,E20)<4,"无序","有序"))) -> 无序 | F20: 功能词 | G20: 太阳能电站 | H20: 寻找太阳能发电机 | I20: =P20/SUM(P:P) -> 0.007803902 | J20: =AC20 -> 18127 | K20: =IFERROR(Z20*AH20,"") -> 42299.2 | M20: lightning deals of today prime | N20: 今日黄金闪电交易 | P20: 0.0078 | Q20: SP广告词 | R20: 49386 | S20: 7 | T20: B09LSGPHT3/B0C7D27GV8/B0BBR2RL6X/B01IHHLB3W/B0BQ782XNW/B00S93EQUK/B07XXSYLL8 | U20: 2246 | V20: 217078 | W20: 5405 | X20: 0.0249 | Y20: 4953036 | Z20: 105748 | AA20: 123 | AB20: 1 | AC20: 18127 | AD20: 11.98 | AE20: 1029 | AF20: 0.1149 | AG20: 0.0796 | AH20: 0.4 | AI20: $0.31 - $0.49 | AJ20: B0CFGYFCYL | AK20: 0.06 | AL20: 0.0259 | AM20: B0C7CQFZYM | AN20: 0.0314 | AO20: 0.0134 | AP20: B0BZ7S8QJW | AQ20: 0.0235 | AR20: 0.0403 | AS20: B01D944MIO,B00W5D1MDE,B09QKBBNCX,B0CFGYFCYL,B0DPFXHXSC,B081T7N948,B0DS5BRTT7,B0DSVLD1MF,B08PNYPL28,B0DRVRZF4V | AT20: 0.008 | AU20: B0B8V6Y2X8,B07SRRQS5B,B0BZCMDZNS,B07HXWPBRT,B08CXGDZXD,B0B776Y6JQ,B0C1GQ54QD,B0982TPZTW,B00B2LBNKM,B0CFF2JG1N
A21: =W21 -> 3306 | B21: =IF(A21="","",IF(A21<词盘!$B$2,"大词",IF(A21<词盘!$C$2,"中尾词","长尾词"))) -> 大词 | C21: =IF(S21/20>70%,1,IF(S21/20>40%,2,IF(S21/20>10%,3,0))) -> 2 | D21: =IF(M21="","",IF(OR(E21="/",E21=""),"无序",IF(COUNTIFS(E:E,E21)<4,"无序","有序"))) -> 无序 | F21: 品牌词 | H21: 了解或购买Jackery品牌的电源产品 | I21: =P21/SUM(P:P) -> 0.0069034517 | J21: =AC21 -> 351 | K21: =IFERROR(Z21*AH21,"") -> 219517.48 | M21: meater thermometer wireless | N21: 肉食温度计无线 | P21: 0.0069 | Q21: HR推荐词 | R21: 43648 | S21: 14 | T21: B0C37ZWPZR/B0C7D27GV8/B0CRY9V6LL/B017613C3C/B0BBR2RL6X/B01IHHLB3W/B07XXSYLL8/B09LSGPHT3/B01F59K0KA/B00S93EQUK/B00GRFHXVQ/B096K2L985/B0BJK5W11R/B0BQ782XNW | U21: 29631 | V21: 68884 | W21: 3306 | X21: 0.048 | Y21: 1525007 | Z21: 32473 | AA21: 75 | AB21: 0 | AC21: 351 | AD21: 196.25 | AE21: 128 | AF21: 0.6851 | AG21: 0.5993 | AH21: 6.76 | AI21: $5.05 - $7.75 | AJ21: B07H8WTFHW | AK21: 0.4397 | AL21: 0.3502 | AM21: B0D2LQGJ2V | AN21: 0.127 | AO21: 0.1582 | AP21: B07TJ95CBM | AQ21: 0.1184 | AR21: 0.0909 | AS21: B07H8WTFHW,B0CP8BPXKR,B07TJ95CBM,B07DZB6XZ6,B0BMLDL5GM,B0D5ZRJM51,B0D1TMFTPN,B0CRY9V6LL,B0D5M9RW7C,B08K2G5Y78 | AT21: 0 | AU21: B00L4Z0T2Y,B08FCSLZBY,B08FCSNXQ6,B01IEJHJWK,B0C4G2BPJ2,B0BC6G9Q35,B08FCSZ14H,B01MQQTB51,B07HXWPBRT,B07SRRQS5B
A22: =W22 -> 783 | B22: =IF(A22="","",IF(A22<词盘!$B$2,"大词",IF(A22<词盘!$C$2,"中尾词","长尾词"))) -> 大词 | C22: =IF(S22/20>70%,1,IF(S22/20>40%,2,IF(S22/20>10%,3,0))) -> 3 | D22: =IF(M22="","",IF(OR(E22="/",E22=""),"无序",IF(COUNTIFS(E:E,E22)<4,"无序","有序"))) -> 无序 | F22: 场景词 | G22: 便携式房屋场景 | H22: 了解或购买便携式房屋及电源产品 | I22: =P22/SUM(P:P) -> 0.0068034017 | J22: =AC22 -> 139900 | K22: =IFERROR(Z22*AH22,"") -> 20864.8 | L22: V | M22: kitchen accessories | N22: 厨房配件 | P22: 0.0068 | Q22: 自然搜索词/HR推荐词/SP广告词 | R22: 43553 | S22: 7 | T22: B07XXSYLL8/B00S93EQUK/B01F59K0KA/B0CRY9V6LL/B01IHHLB3W/B096K2L985/B0BBR2RL6X | U22: 8978 | V22: 126356 | W22: 783 | X22: 0.0062 | Y22: 3559977 | Z22: 52162 | AA22: 18 | AB22: 1 | AC22: 139900 | AD22: 0.9 | AE22: 666 | AF22: 0.1456 | AG22: 0.0689 | AH22: 0.4 | AI22: $0.37 - $0.50 | AJ22: B0C3QZ7SNF | AK22: 0.0591 | AL22: 0.0345 | AM22: B0C2Y3T5LN | AN22: 0.0444 | AO22: 0.0172 | AP22: B0BKRVT66L | AQ22: 0.0421 | AR22: 0.0172 | AS22: B0BLSM37FJ,B0C3QZ7SNF,B0D93Y27ZR,B0D9H27SPR,B0C3H9MJQV,B0D6V87HQR,B0D95TCPLP,B09Z65MVY5,B0D832C56W,B0D83SZT1W | AT22: 0.0108 | AU22: B07PJG4FBM,B0B9VGMLZR,B082WJMM5H,B0C33V7QSW,B0C3D6D5VC,B07TRMF56R,B09H2CLPHT,B01DOE0DO6,B0CLRZ7L29,B0CJF9LBQL
A23: =W23 -> 1946 | B23: =IF(A23="","",IF(A23<词盘!$B$2,"大词",IF(A23<词盘!$C$2,"中尾词","长尾词"))) -> 大词 | C23: =IF(S23/20>70%,1,IF(S23/20>40%,2,IF(S23/20>10%,3,0))) -> 2 | D23: =IF(M23="","",IF(OR(E23="/",E23=""),"无序",IF(COUNTIFS(E:E,E23)<4,"无序","有序"))) -> 有序 | E23: meat thermometer | F23: 品牌词 | H23: 了解或购买EcoFlow品牌电源产品 | I23: =P23/SUM(P:P) -> 0.0066033017 | J23: =AC23 -> 915 | K23: =IFERROR(Z23*AH23,"") | M23: meat thermometer digital wireless | N23: 肉类温度计数字无线 | P23: 0.0066 | Q23: 自然搜索词 | R23: 41814 | S23: 14 | T23: B0CRY9V6LL/B017613C3C/B0BJK5W11R/B01IHHLB3W/B00GRFHXVQ/B07XXSYLL8/B09LSGPHT3/B01F59K0KA/B0BBR2RL6X/B00S93EQUK/B0C7D27GV8/B0BQ782XNW/B005KCG6CE/B096K2L985 | U23: 56667 | V23: 36929 | W23: 1946 | X23: 0.0527 | Y23: 800632 | Z23: 16577 | AA23: 45 | AB23: 5 | AC23: 915 | AD23: 40.36 | AE23: 150 | AF23: 0.3045 | AG23: 0.3179 | AI23: - | AJ23: B00S93EQUK | AK23: 0.1533 | AL23: 0.2393 | AM23: B0D5M9RW7C | AN23: 0.0854 | AO23: 0.0536 | AP23: B07H8WTFHW | AQ23: 0.0658 | AR23: 0.025 | AS23: B07H8WTFHW,B0DG5LP1VK,B0D5M9RW7C,B08K2G5Y78,B0B48NL6L8,B0BMLDL5GM,B0D2LQGJ2V,B0CRY9V6LL,B0DPCHVMNP,B0D9JBL8NG | AT23: 0.0079 | AU23: B07SRRQS5B,B07HY3S811,B0982TPZTW,B0B8V6Y2X8,B0BZCMDZNS,B0CFF2JG1N,B082K8ZNQ1,B0BXCKKNN8,B00DZKQLZ0,B0C6YGZ4B6
A24: =W24 -> 1018 | B24: =IF(A24="","",IF(A24<词盘!$B$2,"大词",IF(A24<词盘!$C$2,"中尾词","长尾词"))) -> 大词 | C24: =IF(S24/20>70%,1,IF(S24/20>40%,2,IF(S24/20>10%,3,0))) -> 2 | D24: =IF(M24="","",IF(OR(E24="/",E24=""),"无序",IF(COUNTIFS(E:E,E24)<4,"无序","有序"))) -> 无序 | F24: 功能词 | G24: 电池发电机 | H24: 寻找电池发电机 | I24: =P24/SUM(P:P) -> 0.0065032516 | J24: =AC24 -> 225 | K24: =IFERROR(Z24*AH24,"") -> 160340 | M24: thermapen | N24: 热敏笔 | P24: 0.0065 | Q24: 自然搜索词 | R24: 41511 | S24: 13 | T24: B0BJK5W11R/B00GRFHXVQ/B01F59K0KA/B0CRY9V6LL/B0BBR2RL6X/B01IHHLB3W/B0BQ782XNW/B07XXSYLL8/B00S93EQUK/B017613C3C/B096K2L985/B09LSGPHT3/B0DDXWY41V | U24: 70119 | V24: 34889 | W24: 1018 | X24: 0.0292 | Y24: 889363 | Z24: 16034 | AA24: 24 | AB24: 7 | AC24: 225 | AD24: 155.06 | AE24: 30 | AF24: 0.6541 | AG24: 0.3978 | AH24: 10 | AI24: $9.00 - $11.00 | AJ24: B0DC8MWQ8K | AK24: 0.4674 | AL24: 0.2513 | AM24: B0DC8776HK | AN24: 0.099 | AO24: 0.0366 | AP24: B07XXSYLL8 | AQ24: 0.0877 | AR24: 0.1099 | AS24: B0DC8FWCDT,B0DC8MWQ8K,B07XXSYLL8,B0BBR2RL6X,B0DC82YRDW,B00S93EQUK,B0DC8FD41B,B07R18W3W1,B0DJY2PWTY,B07Y51PCW7 | AT24: 0.0068 | AU24: B0B9V8KN72,B07PJG4FBM,B082WJMM5H,B0C33TRJ48,B01DOE0DO6,B09RWN11T5,B0928K23P6,B07TRMF56R,B0CWLV8TMK,B0BYV8MFNN
A25: =W25 -> 1798 | B25: =IF(A25="","",IF(A25<词盘!$B$2,"大词",IF(A25<词盘!$C$2,"中尾词","长尾词"))) -> 大词 | C25: =IF(S25/20>70%,1,IF(S25/20>40%,2,IF(S25/20>10%,3,0))) -> 2 | D25: =IF(M25="","",IF(OR(E25="/",E25=""),"无序",IF(COUNTIFS(E:E,E25)<4,"无序","有序"))) -> 无序 | F25: 功能词 | G25: 电动发电机 | H25: 寻找电动发电机 | I25: =P25/SUM(P:P) -> 0.0065032516 | J25: =AC25 -> 6743 | K25: =IFERROR(Z25*AH25,"") -> 38173.66 | L25: V | M25: termometro digital | N25: 数字温度计 | P25: 0.0065 | Q25: 自然搜索词 | R25: 41166 | S25: 12 | T25: B096K2L985/B017613C3C/B0BQ782XNW/B07XXSYLL8/B00S93EQUK/B01IHHLB3W/B09LSGPHT3/B01F59K0KA/B0BBR2RL6X/B0C7D27GV8/B00GRFHXVQ/B0CRY9V6LL | U25: 39573 | V25: 39434 | W25: 1798 | X25: 0.0456 | Y25: 895114 | Z25: 15029 | AA25: 41 | AB25: 0 | AC25: 6743 | AD25: 5.85 | AE25: 108 | AF25: 0.4124 | AG25: 0.3497 | AH25: 2.54 | AI25: $1.90 - $3.19 | AJ25: B0824XNJSW | AK25: 0.2125 | AL25: 0.2023 | AM25: B0CGRB23YM | AN25: 0.1174 | AO25: 0.0838 | AP25: B08B8BDG42 | AQ25: 0.0825 | AR25: 0.0636 | AS25: B0824XNJSW,B0CGRB23YM,B0CTCPQ6N9,B08B8BDG42,B087FR1272,B08B7V2RG3,B0C3B2VZLJ,B0DM5SKGL2,B08MT3D361,B00MUK6M82 | AT25: 0.0686 | AU25: B07SRRQS5B,B0B7Z2MRWY,B07VHPFK5B,B01DODMU9I,B0CGD6Q656,B082K8ZNQ1,B0CL6CXMGZ,B07MXJ93K8,B01IEJHJWK,B00LB7REFK
A26: =W26 -> 5187 | B26: =IF(A26="","",IF(A26<词盘!$B$2,"大词",IF(A26<词盘!$C$2,"中尾词","长尾词"))) -> 大词 | C26: =IF(S26/20>70%,1,IF(S26/20>40%,2,IF(S26/20>10%,3,0))) -> 0 | D26: =IF(M26="","",IF(OR(E26="/",E26=""),"无序",IF(COUNTIFS(E:E,E26)<4,"无序","有序"))) -> 无序 | F26: 品名词 | H26: 寻找电池包或购买电池包 | I26: =P26/SUM(P:P) -> 0.0055027514 | J26: =AC26 -> 154561 | K26: =IFERROR(Z26*AH26,"") -> 149905.93 | M26: birthday gifts for men | N26: 男士生日礼物 | P26: 0.0055 | Q26: 自然搜索词/SP广告词 | R26: 34807 | S26: 1 | T26: B00S93EQUK | U26: 3291 | V26: 296423 | W26: 5187 | X26: 0.0175 | Y26: 8476656 | Z26: 140099 | AA26: 120 | AB26: 13 | AC26: 154561 | AD26: 1.92 | AE26: 438 | AF26: 0.1479 | AG26: 0.1091 | AH26: 1.07 | AI26: $0.80 - $1.34 | AJ26: B0CPPSGC6H | AK26: 0.071 | AL26: 0.0499 | AM26: 1450845800 | AN26: 0.0436 | AO26: 0.035 | AP26: B0C1ZXGQRH | AQ26: 0.0333 | AR26: 0.0242 | AS26: B0BJXRWWHX,B06XZTZ7GB,B01HRCU3SW,1957590424,1648451217,B0CPPSGC6H,B06XFY5NZW,B0CLGHVWVQ,B07NPGMDW8,B0B1VM1C6L | AT26: 0.017 | AU26: B07SRRQS5B,B07VHPFK5B,B082K8ZNQ1,B01DODMU9I,B0CRQJ23DH,B09B4Y89F8,B00LB7REBE,B0B7Z2MRWY,B0CFF2JG1N,B0BC6JDHVR
A27: =W27 -> 2274 | B27: =IF(A27="","",IF(A27<词盘!$B$2,"大词",IF(A27<词盘!$C$2,"中尾词","长尾词"))) -> 大词 | C27: =IF(S27/20>70%,1,IF(S27/20>40%,2,IF(S27/20>10%,3,0))) -> 2 | D27: =IF(M27="","",IF(OR(E27="/",E27=""),"无序",IF(COUNTIFS(E:E,E27)<4,"无序","有序"))) -> 有序 | E27: food thermometer | F27: 品牌词 | H27: 了解或购买Jackery品牌的电源产品 | I27: =P27/SUM(P:P) -> 0.0055027514 | J27: =AC27 -> 2902 | K27: =IFERROR(Z27*AH27,"") -> 18550.62 | M27: digital food thermometer | N27: 数字式食品温度计 | P27: 0.0055 | Q27: 自然搜索词 | R27: 34697 | S27: 14 | T27: B005KCG6CE/B096K2L985/B01F59K0KA/B0C7D27GV8/B0BBR2RL6X/B017613C3C/B0BJK5W11R/B0BQ782XNW/B01IHHLB3W/B07XXSYLL8/B09LSGPHT3/B0CRY9V6LL/B00S93EQUK/B0DDXWY41V | U27: 99295 | V27: 18781 | W27: 2274 | X27: 0.1211 | Y27: 473846 | Z27: 9369 | AA27: 52 | AB27: 8 | AC27: 2902 | AD27: 6.47 | AE27: 54 | AF27: 0.349 | AG27: 0.3103 | AH27: 1.98 | AI27: $1.45 - $2.27 | AJ27: B00S93EQUK | AK27: 0.1806 | AL27: 0.1609 | AM27: B09C32DYV1 | AN27: 0.0885 | AO27: 0.0843 | AP27: B09LSGPHT3 | AQ27: 0.0799 | AR27: 0.0651 | AS27: B00S93EQUK,B07XXSYLL8,B09LSGPHT3,B01IHHLB3W,B07Y51PCW7,B0BQ782XNW,B0C37DLHWW,B017613C3C,B09MTX71VX,B0B71HFH9K | AT27: 0.0403 | AU27: B0BVR8F5W3,B0D2W5JK16,B09964WTF5,B0CSN2CZQR,B08CXGDZXD,B0C7QRSLD9,B0D25ZZ8DL,B09S5TZH5N,B0CHPB2719,B0C8587TZP
A28: =W28 -> 4327 | B28: =IF(A28="","",IF(A28<词盘!$B$2,"大词",IF(A28<词盘!$C$2,"中尾词","长尾词"))) -> 大词 | C28: =IF(S28/20>70%,1,IF(S28/20>40%,2,IF(S28/20>10%,3,0))) -> 2 | D28: =IF(M28="","",IF(OR(E28="/",E28=""),"无序",IF(COUNTIFS(E:E,E28)<4,"无序","有序"))) -> 无序 | F28: 品牌词 | H28: 了解或购买EcoFlow品牌电源产品 | I28: =P28/SUM(P:P) -> 0.0053026513 | J28: =AC28 -> 4005 | K28: =IFERROR(Z28*AH28,"") -> 14775 | L28: V | M28: cooking thermometer for meat | N28: 肉类烹饪温度计 | P28: 0.0053 | Q28: 自然搜索词 | R28: 33467 | S28: 14 | T28: B0C7D27GV8/B005KCG6CE/B00GRFHXVQ/B01F59K0KA/B0CRY9V6LL/B0BBR2RL6X/B017613C3C/B0BQ782XNW/B0BJK5W11R/B01IHHLB3W/B096K2L985/B07XXSYLL8/B09LSGPHT3/B00S93EQUK | U28: 121810 | V28: 16343 | W28: 4327 | X28: 0.2648 | Y28: 399317 | Z28: 7500 | AA28: 99 | AB28: 0 | AC28: 4005 | AD28: 4.08 | AE28: 60 | AF28: 0.4336 | AG28: 0.4554 | AH28: 1.97 | AI28: $1.35 - $2.36 | AJ28: B00S93EQUK | AK28: 0.2463 | AL28: 0.2681 | AM28: B09LSGPHT3 | AN28: 0.1326 | AO28: 0.1277 | AP28: B09C32DYV1 | AQ28: 0.0547 | AR28: 0.0596 | AS28: B00S93EQUK,B017613C3C,B07XXSYLL8,B07Y51PCW7,B09LSGPHT3,B0BQ782XNW,B0C37DLHWW,B01IHHLB3W,B01CI4ZYMO,B07477NMF4 | AT28: 0.1074 | AU28: B07CMFWXS6,B09KLVZ88T,B00NM9HO3W,B07VHPFK5B,B092DGF3FK,B088DQDFL1,B00B4S6SLW,B0BM9H6H62,B08N6Z4B75,B01DODMU9I
A29: =W29 -> 1838 | B29: =IF(A29="","",IF(A29<词盘!$B$2,"大词",IF(A29<词盘!$C$2,"中尾词","长尾词"))) -> 大词 | C29: =IF(S29/20>70%,1,IF(S29/20>40%,2,IF(S29/20>10%,3,0))) -> 1 | D29: =IF(M29="","",IF(OR(E29="/",E29=""),"无序",IF(COUNTIFS(E:E,E29)<4,"无序","有序"))) -> 有序 | E29: meat thermometer | F29: 场景词 | G29: 户外装备场景 | H29: 了解户外活动必备电源设备或其他装备 | I29: =P29/SUM(P:P) -> 0.0049024512 | J29: =AC29 -> 1041 | K29: =IFERROR(Z29*AH29,"") -> 205001.83 | L29: V | M29: wireless meat thermometer | N29: 无线肉类温度计 | P29: 0.0049 | Q29: 自然搜索词 | R29: 31290 | S29: 15 | T29: B0C37ZWPZR/B0CRY9V6LL/B0C7D27GV8/B017613C3C/B07XXSYLL8/B09LSGPHT3/B096K2L985/B005KCG6CE/B0BBR2RL6X/B0BJK5W11R/B00S93EQUK/B01F59K0KA/B01IHHLB3W/B0BQ782XNW/B00GRFHXVQ | U29: 27653 | V29: 63192 | W29: 1838 | X29: 0.0291 | Y29: 1743232 | Z29: 29161 | AA29: 42 | AB29: 56 | AC29: 1041 | AD29: 60.7 | AE29: 153 | AF29: 0.2635 | AG29: 0.2211 | AH29: 7.03 | AI29: $4.48 - $7.80 | AJ29: B0DWK2RMWY | AK29: 0.0909 | AL29: 0.103 | AM29: B0D5M9RW7C | AN29: 0.0882 | AO29: 0.0578 | AP29: B0DFNR55LB | AQ29: 0.0844 | AR29: 0.0603 | AS29: B07H8WTFHW,B0D5M9RW7C,B0BMLDL5GM,B0D2LQGJ2V,B0CRY9V6LL,B0B48NL6L8,B0D9QW8L6H,B08K2G5Y78,B0DCG67Z7Q,B0DK9BMDB1 | AT29: 0.0157 | AU29: B08YZ2K3PV,B0B7BP6CJN,B0CJB2KBJX,B0BN4Z47CK,B01LXFSJY7,B0BQ7PD5YW,B00I5H5Z1O,B07MVKJLHV,B0BX8NQBJS,B0B7X8CWZM
A30: =W30 -> 2018 | B30: =IF(A30="","",IF(A30<词盘!$B$2,"大词",IF(A30<词盘!$C$2,"中尾词","长尾词"))) -> 大词 | C30: =IF(S30/20>70%,1,IF(S30/20>40%,2,IF(S30/20>10%,3,0))) -> 2 | D30: =IF(M30="","",IF(OR(E30="/",E30=""),"无序",IF(COUNTIFS(E:E,E30)<4,"无序","有序"))) -> 有序 | E30: meat thermometer | F30: 品牌词 | H30: 了解或购买Anker品牌的电源产品 | I30: =P30/SUM(P:P) -> 0.0049024512 | J30: =AC30 -> 773 | K30: =IFERROR(Z30*AH30,"") -> 13530.88 | M30: thermopro digital meat thermometer | N30: Thermopro 数字肉类温度计 | P30: 0.0049 | Q30: 自然搜索词 | R30: 31188 | S30: 14 | T30: B0BJK5W11R/B096K2L985/B0CRY9V6LL/B0C7D27GV8/B0BBR2RL6X/B017613C3C/B01IHHLB3W/B07XXSYLL8/B09LSGPHT3/B01F59K0KA/B00S93EQUK/B0BQ782XNW/B005KCG6CE/B00GRFHXVQ | U30: 107677 | V30: 25166 | W30: 2018 | X30: 0.0802 | Y30: 553203 | Z30: 10912 | AA30: 46 | AB30: 0 | AC30: 773 | AD30: 32.56 | AE30: 106 | AF30: 0.4038 | AG30: 0.4061 | AH30: 1.24 | AI30: $0.79 - $2.49 | AJ30: B07XXSYLL8 | AK30: 0.2542 | AL30: 0.3152 | AM30: B0CJLNCYG6 | AN30: 0.0879 | AO30: 0.0364 | AP30: B01IHHLB3W | AQ30: 0.0617 | AR30: 0.0545 | AS30: B07XXSYLL8,B017613C3C,B0B48NL6L8,B0BMLDL5GM,B08K2G5Y78,B0CRY9V6LL,B08KZR4F23,B07Y51PCW7,B01IHHLB3W,B0BBR2RL6X | AT30: 0.027 | AU30: B0BPNMT5DM,B07P8NXQF4,B0BSTWKSDX,B0CC54BQVY,B09NV5M55S,B0B8V6Y2X8,B07C85S2PV,B0CHVWVK3C,B0BV6ZR4GL,B0BXN2WJ3D
A31: =W31 -> 2667 | B31: =IF(A31="","",IF(A31<词盘!$B$2,"大词",IF(A31<词盘!$C$2,"中尾词","长尾词"))) -> 大词 | C31: =IF(S31/20>70%,1,IF(S31/20>40%,2,IF(S31/20>10%,3,0))) -> 2 | D31: =IF(M31="","",IF(OR(E31="/",E31=""),"无序",IF(COUNTIFS(E:E,E31)<4,"无序","有序"))) -> 无序 | F31: 品牌词 | H31: 了解或购买EcoFlow品牌电源产品 | I31: =P31/SUM(P:P) -> 0.0048024012 | J31: =AC31 -> 503 | K31: =IFERROR(Z31*AH31,"") -> 16025.31 | L31: V | M31: oil thermometer for frying | N31: 油炸用油温计 | P31: 0.0048 | Q31: 自然搜索词 | R31: 30677 | S31: 14 | T31: B0BQ782XNW/B01IHHLB3W/B0BJK5W11R/B005KCG6CE/B07XXSYLL8/B09LSGPHT3/B0C7D27GV8/B01F59K0KA/B0CRY9V6LL/B0BBR2RL6X/B00S93EQUK/B017613C3C/B00GRFHXVQ/B096K2L985 | U31: 74249 | V31: 22764 | W31: 2667 | X31: 0.1172 | Y31: 591870 | Z31: 8757 | AA31: 61 | AB31: 3 | AC31: 503 | AD31: 45.26 | AE31: 129 | AF31: 0.5133 | AG31: 0.4285 | AH31: 1.83 | AI31: $1.37 - $2.28 | AJ31: B01N7KIDW0 | AK31: 0.2249 | AL31: 0.2381 | AM31: B0BGX4RG9B | AN31: 0.1508 | AO31: 0.1245 | AP31: B098DSQHY9 | AQ31: 0.1376 | AR31: 0.0659 | AS31: B01N7KIDW0,B0BGX4RG9B,B00004XSC9,B0B71HFH9K,B07H9RFNVC,B0C8254GJM,B094V3R7H8,B07YP9GT1N,B088DTK1QZ,B01CI50FJU | AT31: 0.0184 | AU31: B07SRRQS5B,B0B8V6Y2X8,B0982TPZTW,B0CFF2JG1N,B0B7Z2MRWY,B00DZKQLZ0,B0BC6G9Q35,B07MNW4VMY,B00B2KV5D8,B0995B8K8V
A32: =W32 -> 3788 | B32: =IF(A32="","",IF(A32<词盘!$B$2,"大词",IF(A32<词盘!$C$2,"中尾词","长尾词"))) -> 大词 | C32: =IF(S32/20>70%,1,IF(S32/20>40%,2,IF(S32/20>10%,3,0))) -> 2 | D32: =IF(M32="","",IF(OR(E32="/",E32=""),"无序",IF(COUNTIFS(E:E,E32)<4,"无序","有序"))) -> 无序 | F32: 品牌词 | H32: 了解或购买Anker品牌的电源产品 | I32: =P32/SUM(P:P) -> 0.0048024012 | J32: =AC32 -> 1328 | K32: =IFERROR(Z32*AH32,"") | M32: instant read thermometer for cooking | N32: 即时读取烹饪温度计 | P32: 0.0048 | Q32: 自然搜索词 | R32: 30229 | S32: 14 | T32: B005KCG6CE/B00GRFHXVQ/B096K2L985/B01F59K0KA/B0BBR2RL6X/B0BJK5W11R/B017613C3C/B0BQ782XNW/B01IHHLB3W/B09LSGPHT3/B07XXSYLL8/B0CRY9V6LL/B00S93EQUK/B0C7D27GV8 | U32: 121604 | V32: 18065 | W32: 3788 | X32: 0.2097 | Y32: 476243 | Z32: 7861 | AA32: 86 | AB32: 1 | AC32: 1328 | AD32: 13.6 | AE32: 20 | AF32: 0.4853 | AG32: 0.4545 | AI32: - | AJ32: B00S93EQUK | AK32: 0.2647 | AL32: 0.2314 | AM32: B09LSGPHT3 | AN32: 0.1408 | AO32: 0.157 | AP32: B07XXSYLL8 | AQ32: 0.0798 | AR32: 0.0661 | AS32: B00S93EQUK,B07XXSYLL8,B07Y51PCW7,B01IHHLB3W,B0DJY2PWTY,B09LSGPHT3,B0C37DLHWW,B0DG5LP1VK,B0DG5KDHS8,B0BQ782XNW | AT32: 0.082 | AU32: B07SRRQS5B,B082K8ZNQ1,B01DODMU9I,B0BC6G9Q35,B0C6YGZ4B6,B00LB7REFK,B0B7Z2MRWY,B0CXT9W574,B07W76MV4Y,B00L4Z0T2Y
A33: =W33 -> 814 | B33: =IF(A33="","",IF(A33<词盘!$B$2,"大词",IF(A33<词盘!$C$2,"中尾词","长尾词"))) -> 大词 | C33: =IF(S33/20>70%,1,IF(S33/20>40%,2,IF(S33/20>10%,3,0))) -> 2 | D33: =IF(M33="","",IF(OR(E33="/",E33=""),"无序",IF(COUNTIFS(E:E,E33)<4,"无序","有序"))) -> 无序 | F33: 品牌词 | H33: 了解或购买Jackery品牌的电源产品 | I33: =P33/SUM(P:P) -> 0.0046023012 | J33: =AC33 -> 532 | K33: =IFERROR(Z33*AH33,"") -> 17377.08 | L33: V | M33: thermopro | N33: 暖气片 | P33: 0.0046 | Q33: 自然搜索词/SP广告词 | R33: 29327 | S33: 10 | T33: B0BJK5W11R/B096K2L985/B0CRY9V6LL/B0BBR2RL6X/B017613C3C/B01IHHLB3W/B07XXSYLL8/B09LSGPHT3/B00S93EQUK/B01F59K0KA | U33: 80317 | V33: 28574 | W33: 814 | X33: 0.0285 | Y33: 712999 | Z33: 11508 | AA33: 19 | AB33: 72 | AC33: 532 | AD33: 53.71 | AE33: 51 | AF33: 0.3429 | AG33: 0.2917 | AH33: 1.51 | AI33: $1.13 - $1.89 | AJ33: B07XXSYLL8 | AK33: 0.1394 | AL33: 0.1875 | AM33: B0CJLNCYG6 | AN33: 0.111 | AO33: 0.0417 | AP33: B01H1R0K68 | AQ33: 0.0925 | AR33: 0.0625 | AS33: B07XXSYLL8,B08DKKZY19,B0BMLDL5GM,B0B48NL6L8,B0DHFN5HK8,B0CRY9V6LL,B0CJLNCYG6,B08K2G5Y78,B017613C3C,B01H1R0K68 | AT33: 0.066 | AU33: B0D17C4VNX,B0D1KDXFZJ,B0CXTBZR2H,B0D1XL2B6P,B0CZNXB4KN,B0CZRC9F86,B0CZDB93YR,B0CYBRQ7FC,B0CXXTZ45P,B0D17DB7SX
A34: =W34 -> 2202 | B34: =IF(A34="","",IF(A34<词盘!$B$2,"大词",IF(A34<词盘!$C$2,"中尾词","长尾词"))) -> 大词 | C34: =IF(S34/20>70%,1,IF(S34/20>40%,2,IF(S34/20>10%,3,0))) -> 2 | D34: =IF(M34="","",IF(OR(E34="/",E34=""),"无序",IF(COUNTIFS(E:E,E34)<4,"无序","有序"))) -> 无序 | F34: 品牌词 | H34: 了解或购买EcoFlow品牌电源产品 | I34: =P34/SUM(P:P) -> 0.0045022511 | J34: =AC34 -> 261 | K34: =IFERROR(Z34*AH34,"") -> 116030.25 | M34: meater | N34: 肉食者 | P34: 0.0045 | Q34: 品牌广告词 | R34: 28882 | S34: 12 | T34: B0CRY9V6LL/B0BBR2RL6X/B09LSGPHT3/B01F59K0KA/B00S93EQUK/B017613C3C/B096K2L985/B01IHHLB3W/B0BQ782XNW/B00GRFHXVQ/B0BJK5W11R/B0C7D27GV8 | U34: 48197 | V34: 44397 | W34: 2202 | X34: 0.0496 | Y34: 1161936 | Z34: 22101 | AA34: 50 | AB34: 21 | AC34: 261 | AD34: 170.1 | AE34: 72 | AF34: 0.6871 | AG34: 0.6705 | AH34: 5.25 | AI34: $3.94 - $6.55 | AJ34: B07H8WTFHW | AK34: 0.3564 | AL34: 0.2832 | AM34: B0D2LQGJ2V | AN34: 0.1711 | AO34: 0.1792 | AP34: B0CP8BPXKR | AQ34: 0.1596 | AR34: 0.2081 | AS34: B07H8WTFHW,B0CP8BPXKR,B0D2LQGJ2V,B07TJ95CBM,B0D5ZRJM51,B07DZB6XZ6,B0DG5GKJKB,B0BMLDL5GM,B08WWGRGVY,B0DGGMTYXV | AT34: 0.0147 | AU34: B07SRRQS5B,B07HY3S811,B0B75JF6CM,B09N71WGLF,B0982TPZTW,B082K8ZNQ1,B07VHPFK5B,B0BC6G9Q35,B07J63KGNN,B0CWP3757G
A35: =W35 -> 752 | B35: =IF(A35="","",IF(A35<词盘!$B$2,"大词",IF(A35<词盘!$C$2,"中尾词","长尾词"))) -> 大词 | C35: =IF(S35/20>70%,1,IF(S35/20>40%,2,IF(S35/20>10%,3,0))) -> 0 | D35: =IF(M35="","",IF(OR(E35="/",E35=""),"无序",IF(COUNTIFS(E:E,E35)<4,"无序","有序"))) -> 无序 | F35: 场景词 | G35: 户外配件场景 | H35: 了解户外活动必备电源设备或其他装备 | I35: =P35/SUM(P:P) -> 0.0043021511 | J35: =AC35 -> 112243 | K35: =IFERROR(Z35*AH35,"") -> 101239.6 | L35: V | M35: kitchen essentials | N35: 厨房必备品 | P35: 0.0043 | Q35: 自然搜索词/HR推荐词/SP广告词 | R35: 27149 | S35: 2 | T35: B00S93EQUK/B0BQ782XNW | U35: 4762 | V35: 139405 | W35: 752 | X35: 0.0054 | Y35: 3760756 | Z35: 66605 | AA35: 18 | AB35: 7 | AC35: 112243 | AD35: 1.24 | AE35: 390 | AF35: 0.1489 | AG35: 0.0814 | AH35: 1.52 | AI35: $1.14 - $1.90 | AJ35: B08573DQ39 | AK35: 0.0556 | AL35: 0.0366 | AM35: B0C3QZ7SNF | AN35: 0.0504 | AO35: 0.0285 | AP35: B0764HS4SL | AQ35: 0.0429 | AR35: 0.0163 | AS35: B08573DQ39,B0BKRVT66L,B09VZ11WHK,B0CW3SZCW6,B0CJ1B6D6S,B0CTD5PYS3,B0764HS4SL,B0C3H9MJQV,B08J8GZXKZ,B0BSKQW2T2 | AT35: 0.0142 | AU35: B08YZ633BY,B07CZDXDG8,B07KPYMMG6,B07GKVBQDG,B07MYW7C3Z,B007BF7BUY,B07SRRQS5B,B00I5H5Z1O,B0BFWD2VML,B0B7BFMHNF
A36: =W36 -> 2216 | B36: =IF(A36="","",IF(A36<词盘!$B$2,"大词",IF(A36<词盘!$C$2,"中尾词","长尾词"))) -> 大词 | C36: =IF(S36/20>70%,1,IF(S36/20>40%,2,IF(S36/20>10%,3,0))) -> 1 | D36: =IF(M36="","",IF(OR(E36="/",E36=""),"无序",IF(COUNTIFS(E:E,E36)<4,"无序","有序"))) -> 有序 | E36: meat thermometer | F36: 品牌词 | H36: 了解或购买EcoFlow品牌电源产品 | I36: =P36/SUM(P:P) -> 0.004102051 | J36: =AC36 -> 1279 | K36: =IFERROR(Z36*AH36,"") -> 6414.65 | M36: digital meat thermometer instant read | N36: 数字肉类温度计即时读取 | P36: 0.0041 | Q36: 自然搜索词 | R36: 26394 | S36: 15 | T36: B0BJK5W11R/B096K2L985/B01F59K0KA/B0BBR2RL6X/B017613C3C/B0BQ782XNW/B01IHHLB3W/B005KCG6CE/B00GRFHXVQ/B09LSGPHT3/B07XXSYLL8/B0CRY9V6LL/B00S93EQUK/B0C7D27GV8/B0DDXWY41V | U36: 137356 | V36: 13223 | W36: 2216 | X36: 0.1676 | Y36: 385456 | Z36: 5995 | AA36: 51 | AB36: 0 | AC36: 1279 | AD36: 10.34 | AE36: 38 | AF36: 0.5094 | AG36: 0.48 | AH36: 1.07 | AI36: $0.71 - $2.15 | AJ36: B00S93EQUK | AK36: 0.2594 | AL36: 0.2578 | AM36: B09LSGPHT3 | AN36: 0.1627 | AO36: 0.1422 | AP36: B09C32DYV1 | AQ36: 0.0873 | AR36: 0.08 | AS36: B00S93EQUK,B07XXSYLL8,B0DG5LP1VK,B0DJY2PWTY,B01IHHLB3W,B07Y51PCW7,B09LSGPHT3,B0DHZTCNR5,B0DG5KDHS8,B0BQ782XNW | AT36: 0.0199 | AU36: B0B9VGMLZR,B07FH8BCX5,B09RWN11T5,B09H2CLPHT,B0CQ7CQXTL,B0CJF9LBQL,B0C33V7QSW,B0928K23P6,B082WJMM5H,B0CLRZ7L29
A37: =W37 -> 1242 | B37: =IF(A37="","",IF(A37<词盘!$B$2,"大词",IF(A37<词盘!$C$2,"中尾词","长尾词"))) -> 大词 | C37: =IF(S37/20>70%,1,IF(S37/20>40%,2,IF(S37/20>10%,3,0))) -> 2 | D37: =IF(M37="","",IF(OR(E37="/",E37=""),"无序",IF(COUNTIFS(E:E,E37)<4,"无序","有序"))) -> 无序 | F37: 功能词 | G37: 配备太阳能面板的便携电站 | H37: 寻找带太阳能面板的便携电源站 | I37: =P37/SUM(P:P) -> 0.004002001 | J37: =AC37 -> 19897 | K37: =IFERROR(Z37*AH37,"") -> 22869.6 | M37: temperature thermometer | N37: 温度温度计 | P37: 0.004 | Q37: 自然搜索词 | R37: 25252 | S37: 12 | T37: B0BBR2RL6X/B0BQ782XNW/B01IHHLB3W/B07XXSYLL8/B09LSGPHT3/B00S93EQUK/B017613C3C/B0CRY9V6LL/B005KCG6CE/B00GRFHXVQ/B01F59K0KA/B0C7D27GV8 | U37: 74165 | V37: 22932 | W37: 1242 | X37: 0.0542 | Y37: 627532 | Z37: 9529 | AA37: 29 | AB37: 0 | AC37: 19897 | AD37: 1.15 | AE37: 50 | AF37: 0.4055 | AG37: 0.3874 | AH37: 2.4 | AI37: $1.79 - $3.00 | AJ37: B0824XNJSW | AK37: 0.2483 | AL37: 0.2252 | AM37: B08B8BDG42 | AN37: 0.0832 | AO37: 0.096 | AP37: B0CTCPQ6N9 | AQ37: 0.074 | AR37: 0.0662 | AS37: B0824XNJSW,B0CGRB23YM,B075QQ8VZW,B08B8BDG42,B08MT3D361,B0C3B2VZLJ,B07R3YC1BC,B00MUK6M82,B08B7V2RG3,B07WCR5Y4B | AT37: 0.0581 | AU37: B07NS8BF7X,B0BWHG8PMV,B0BNMVB18C,B0CNRFNRB7,B09YY9DLCF,B003Z22QNY,B0CJB7C4G7,B0BZTS57Y7,B0C5N9YYTY,B078NQLWRM
A38: =W38 -> 2310 | B38: =IF(A38="","",IF(A38<词盘!$B$2,"大词",IF(A38<词盘!$C$2,"中尾词","长尾词"))) -> 大词 | C38: =IF(S38/20>70%,1,IF(S38/20>40%,2,IF(S38/20>10%,3,0))) -> 2 | D38: =IF(M38="","",IF(OR(E38="/",E38=""),"无序",IF(COUNTIFS(E:E,E38)<4,"无序","有序"))) -> 有序 | E38: meat thermometer | F38: 功能词 | G38: 电力发电机 | H38: 寻找电力发电机 | I38: =P38/SUM(P:P) -> 0.0037018509 | J38: =AC38 -> 2415 | K38: =IFERROR(Z38*AH38,"") -> 10618.64 | M38: meat thermometer probe | N38: 肉类温度计探头 | O38: Y | P38: 0.0037 | Q38: 自然搜索词/AC推荐词 | R38: 23381 | S38: 14 | T38: B005KCG6CE/B0CRY9V6LL/B0BBR2RL6X/B017613C3C/B0BQ782XNW/B0BJK5W11R/B01IHHLB3W/B07XXSYLL8/B00GRFHXVQ/B096K2L985/B09LSGPHT3/B01F59K0KA/B00S93EQUK/B0C7D27GV8 | U38: 140541 | V38: 12375 | W38: 2310 | X38: 0.1867 | Y38: 249819 | Z38: 5336 | AA38: 53 | AB38: 1 | AC38: 2415 | AD38: 5.12 | AE38: 114 | AF38: 0.347 | AG38: 0.311 | AH38: 1.99 | AI38: $1.49 - $2.49 | AJ38: B00S93EQUK | AK38: 0.1639 | AL38: 0.2012 | AM38: B005KCG6CE | AN38: 0.1012 | AO38: 0.0732 | AP38: B017613C3C | AQ38: 0.0819 | AR38: 0.0366 | AS38: B017613C3C,B00S93EQUK,B07XXSYLL8,B0D6YQ8LV2,B0DBKYNY98,B01CI4ZYMO,B07477NMF4,B0DG5KDHS8,B07Y51PCW7,B0DDXY3V1V | AT38: 0.0312 | AU38: B07SRRQS5B,B01DODMU9I,B082K8ZNQ1,B0BC6G9Q35,B07VHPFK5B,B0CRQJSL1P,B0CFV5LZ3R,B07PDHHS3Y,B00LB7REFK,B07J63KGNN
A39: =W39 -> 981 | B39: =IF(A39="","",IF(A39<词盘!$B$2,"大词",IF(A39<词盘!$C$2,"中尾词","长尾词"))) -> 大词 | C39: =IF(S39/20>70%,1,IF(S39/20>40%,2,IF(S39/20>10%,3,0))) -> 2 | D39: =IF(M39="","",IF(OR(E39="/",E39=""),"无序",IF(COUNTIFS(E:E,E39)<4,"无序","有序"))) -> 无序 | F39: 功能词 | G39: 配有太阳能面板的电站 | H39: 寻找太阳能发电机 | I39: =P39/SUM(P:P) -> 0.0036018009 | J39: =AC39 -> 5483 | K39: =IFERROR(Z39*AH39,"") -> 8465.31 | M39: food temperature thermometer | N39: 食物温度温度计 | P39: 0.0036 | Q39: 自然搜索词/SP广告词 | R39: 22879 | S39: 13 | T39: B0C7D27GV8/B005KCG6CE/B0CRY9V6LL/B017613C3C/B0BQ782XNW/B01IHHLB3W/B0BJK5W11R/B096K2L985/B07XXSYLL8/B09LSGPHT3/B01F59K0KA/B0BBR2RL6X/B00S93EQUK | U39: 153755 | V39: 10023 | W39: 981 | X39: 0.0979 | Y39: 281812 | Z39: 4479 | AA39: 23 | AB39: 0 | AC39: 5483 | AD39: 1.83 | AE39: 50 | AF39: 0.4305 | AG39: 0.4472 | AH39: 1.89 | AI39: $1.37 - $2.20 | AJ39: B00S93EQUK | AK39: 0.2047 | AL39: 0.2484 | AM39: B09LSGPHT3 | AN39: 0.1549 | AO39: 0.1429 | AP39: B0C37DLHWW | AQ39: 0.0709 | AR39: 0.0559 | AS39: B00S93EQUK,B07XXSYLL8,B01IHHLB3W,B0B71HFH9K,B0BQ782XNW,B08RWPPD8J,B09LSGPHT3,B0C37DLHWW,B09MTX71VX,B017613C3C | AT39: 0.0528 | AU39: B0C1R964XD,B09BDZZQ4Y,B09LLYP2XL,B082M35PH3,B0BX5YKTWQ,B077Q382WD,B01IEJHJWK,B07SRRQS5B,B0BB378VKV,B072K59NYZ
A40: =W40 -> 5843 | B40: =IF(A40="","",IF(A40<词盘!$B$2,"大词",IF(A40<词盘!$C$2,"中尾词","长尾词"))) -> 大词 | C40: =IF(S40/20>70%,1,IF(S40/20>40%,2,IF(S40/20>10%,3,0))) -> 3 | D40: =IF(M40="","",IF(OR(E40="/",E40=""),"无序",IF(COUNTIFS(E:E,E40)<4,"无序","有序"))) -> 无序 | F40: 功能词 | G40: 太阳能发电机 | H40: 寻找太阳能发电机 | I40: =P40/SUM(P:P) -> 0.0034017009 | J40: =AC40 -> 8971 | K40: =IFERROR(Z40*AH40,"") -> 51572.22 | M40: outdoor thermometer | N40: 户外温度计 | P40: 0.0034 | Q40: SP广告词 | R40: 21684 | S40: 8 | T40: B0DGXKNV6Y/B09LSGPHT3/B00S93EQUK/B0BQ782XNW/B01IHHLB3W/B096K2L985/B00GRFHXVQ/B01F59K0KA | U40: 15494 | V40: 123284 | W40: 5843 | X40: 0.0474 | Y40: 2615367 | Z40: 55454 | AA40: 133 | AB40: 47 | AC40: 8971 | AD40: 13.74 | AE40: 174 | AF40: 0.3472 | AG40: 0.2948 | AH40: 0.93 | AI40: $0.80 - $1.12 | AJ40: B00004TBJP | AK40: 0.2008 | AL40: 0.1795 | AM40: B06XKH666P | AN40: 0.112 | AO40: 0.0897 | AP40: B000BZYBYU | AQ40: 0.0344 | AR40: 0.0256 | AS40: B06XKH666P,B00004TBJP,B0BYF6CTRK,B0D1VCSY1N,B0D8HY1YQM,B0D8J22Q45,B001A0K8KQ,B01ALO555E,B0BT9B25LP,B0D9B8DDQ9 | AT40: 0.0072 | AU40: B0B9V8KN72,B0C1RJHQ41,B07P8NXQF4,B09H2CLPHT,B082WJMM5H,B0CQ7CQXTL,B07SRRQS5B,B0C33V7QSW,B07TRMF56R,B07PJG4FBM
A41: =W41 -> 427 | B41: =IF(A41="","",IF(A41<词盘!$B$2,"大词",IF(A41<词盘!$C$2,"中尾词","长尾词"))) -> 大词 | C41: =IF(S41/20>70%,1,IF(S41/20>40%,2,IF(S41/20>10%,3,0))) -> 1 | D41: =IF(M41="","",IF(OR(E41="/",E41=""),"无序",IF(COUNTIFS(E:E,E41)<4,"无序","有序"))) -> 无序 | F41: 功能词 | G41: 电池备份 | H41: 寻找电池备份产品 | I41: =P41/SUM(P:P) -> 0.0034017009 | J41: =AC41 -> 349 | K41: =IFERROR(Z41*AH41,"") -> 10922.4 | M41: bread thermometer sourdough | P41: 0.0034 | Q41: 自然搜索词 | R41: 21479 | S41: 15 | T41: B005KCG6CE/B00GRFHXVQ/B01F59K0KA/B01IHHLB3W/B0BQ782XNW/B0BJK5W11R/B096K2L985/B07XXSYLL8/B09LSGPHT3/B0BBR2RL6X/B00S93EQUK/B017613C3C/B0C7D27GV8/B0CRY9V6LL/B0DDXWY41V | U41: 140382 | V41: 12921 | W41: 427 | X41: 0.0331 | Y41: 327125 | Z41: 6068 | AA41: 10 | AB41: 0 | AC41: 349 | AD41: 37.02 | AE41: 75 | AF41: 0.6747 | AG41: 0.5493 | AH41: 1.8 | AI41: $1.36 - $2.25 | AJ41: B09MTX71VX | AK41: 0.4169 | AL41: 0.3873 | AM41: B08RWPPD8J | AN41: 0.1783 | AO41: 0.0986 | AP41: B00S93EQUK | AQ41: 0.0795 | AR41: 0.0634 | AS41: B09MTX71VX,B01IHHLB3W,B00S93EQUK,B08RWPPD8J,B07XXSYLL8,B0B71HFH9K,B0BW5VGF4M,B0C37DLHWW,B01LET2BFC,B07Y51PCW7 | AT41: 0.0833 | AU41: B00LB7REFK,B07PDHHS3Y,B07VHPFK5B,B07QHDRCZ3,B0CFV5LZ3R,B09NFRC4LM,B0BNMVB18C,B079X4ZR6X,B07SRRQS5B,B07WLPBPKM
A42: =W42 -> 236 | B42: =IF(A42="","",IF(A42<词盘!$B$2,"大词",IF(A42<词盘!$C$2,"中尾词","长尾词"))) -> 大词 | D42: =IF(M42="","",IF(OR(E42="/",E42=""),"无序",IF(COUNTIFS(E:E,E42)<4,"无序","有序"))) -> 无序 | F42: 场景词 | G42: 便携房屋场景 | H42: 了解或购买便携式房屋及电源产品 | I42: =P42/SUM(P:P) -> 0.0034017009 | J42: =AC42 -> 240821 | K42: =IFERROR(Z42*AH42,"") -> 87871.35 | M42: cooking | N42: 烹饪 | P42: 0.0034 | Q42: SP广告词 | R42: 21339 | S42: 6 | T42: B00S93EQUK/B07XXSYLL8/B01F59K0KA/B0CRY9V6LL/B00GRFHXVQ/B01IHHLB3W | U42: 9608 | V42: 118405 | W42: 236 | X42: 0.002 | Y42: 3404755 | Z42: 55265 | AA42: 6 | AB42: 33 | AC42: 240821 | AD42: 0.49 | AE42: 71 | AF42: 0.087 | AG42: 0.1059 | AH42: 1.59 | AI42: $1.19 - $1.99 | AJ42: B07B4ZZX8R | AK42: 0.0393 | AL42: 0 | AM42: B01N0SOZPK | AN42: 0.0244 | AO42: 0.0629 | AP42: B01IQ00B04 | AQ42: 0.0233 | AR42: 0.043 | AS42: B0C8VHBBZK,B0CJF94M8J,1628605715,B0B72DL8KL,B0BZHG5VQL,B0D9JSD7QQ,B0DDT2F47W,B0DFM7X5VS,B08573DQ39,B0D9D7FF8J | AT42: 0.0569 | AU42: B07CMFWXS6,B088DQDFL1,B01DODMU9I,B00NM9HO3W,B07SRRQS5B,B01MQQTB51,B079X4S4DQ,B0BC6G9Q35,B082Q1X6BB,B0CZDB93YR
A43: =W43 -> 8630 | B43: =IF(A43="","",IF(A43<词盘!$B$2,"大词",IF(A43<词盘!$C$2,"中尾词","长尾词"))) -> 大词 | D43: =IF(M43="","",IF(OR(E43="/",E43=""),"无序",IF(COUNTIFS(E:E,E43)<4,"无序","有序"))) -> 无序 | F43: 品牌词 | H43: 了解或购买Anker品牌的电池产品 | I43: =P43/SUM(P:P) -> 0.0033016508 | J43: =AC43 -> 519 | K43: =IFERROR(Z43*AH43,"") | M43: oven thermometer for electric oven temperature | N43: 电烤箱温度的烤箱温度计 | P43: 0.0033 | Q43: 自然搜索词 | R43: 21161 | S43: 14 | T43: B017613C3C/B005KCG6CE/B00S93EQUK/B0BJK5W11R/B0C7D27GV8/B01IHHLB3W/B096K2L985/B07XXSYLL8/B0CRY9V6LL/B01F59K0KA/B0BQ782XNW/B09LSGPHT3/B0BBR2RL6X/B00GRFHXVQ | U43: 51337 | V43: 37935 | W43: 8630 | X43: 0.2275 | Y43: 762621 | Z43: 15786 | AA43: 196 | AB43: 1 | AC43: 519 | AD43: 73.09 | AE43: 185 | AF43: 0.6607 | AG43: 0.627 | AI43: - | AJ43: B083BMMQV9 | AK43: 0.4845 | AL43: 0.4849 | AM43: B0000DJUYR | AN43: 0.1303 | AO43: 0.1066 | AP43: B005KDEIZ0 | AQ43: 0.0459 | AR43: 0.0355 | AS43: B0000DJUYR,B083BMMQV9,B07YP9G4Z7,B0CX19TQH1,B09JSBXJDV,B000BQWMTK,B01CF39C4Y,B017613C3C,B08GY3K7KD,B0D3XLVZCP | AT43: 0.0992 | AU43: B07SRRQS5B,B0CQ79FH3S,B082K8ZNQ1,B0BC6G9Q35,B01DODMU9I,B0CL9SXSBD,B0CRQJSL1P,B0CTHCYZ5L,B079X4S4DQ,B00LB7REFK
A44: =W44 -> 847 | B44: =IF(A44="","",IF(A44<词盘!$B$2,"大词",IF(A44<词盘!$C$2,"中尾词","长尾词"))) -> 大词 | D44: =IF(M44="","",IF(OR(E44="/",E44=""),"无序",IF(COUNTIFS(E:E,E44)<4,"无序","有序"))) -> 无序 | F44: 品牌词 | H44: 了解或购买Jackery品牌的太阳能发电机 | I44: =P44/SUM(P:P) -> 0.0032016008 | J44: =AC44 -> 6850 | K44: =IFERROR(Z44*AH44,"") -> 6554.31 | M44: thermometer food | N44: 温度计食物 | P44: 0.0032 | Q44: 自然搜索词 | R44: 20571 | S44: 14 | T44: B0BJK5W11R/B005KCG6CE/B0BBR2RL6X/B017613C3C/B0BQ782XNW/B01IHHLB3W/B096K2L985/B07XXSYLL8/B09LSGPHT3/B01F59K0KA/B0CRY9V6LL/B00S93EQUK/B00GRFHXVQ/B0C7D27GV8 | U44: 155264 | V44: 9117 | W44: 847 | X44: 0.093 | Y44: 273037 | Z44: 3703 | AA44: 20 | AB44: 2 | AC44: 6850 | AD44: 1.33 | AE44: 60 | AF44: 0.3174 | AG44: 0.2993 | AH44: 1.77 | AI44: $1.39 - $2.20 | AJ44: B00S93EQUK | AK44: 0.1693 | AL44: 0.1565 | AM44: B09C32DYV1 | AN44: 0.0767 | AO44: 0.0884 | AP44: B09LSGPHT3 | AQ44: 0.0714 | AR44: 0.0544 | AS44: B00S93EQUK,B07XXSYLL8,B01IHHLB3W,B09LSGPHT3,B0BQ782XNW,B0C37DLHWW,B017613C3C,B0B71HFH9K,B09988SD2B,B07Y51PCW7 | AT44: 0.0944 | AU44: B00LB7REFK,B0C7YG1P44,B07VHPFK5B,B07QHDRCZ3,B00L4Z0T2Y,B0CFV5LZ3R,B07SRRQS5B,B0CGHZ9221,B0758TY861,B0BY3RK5CC
A45: =W45 -> 1759 | B45: =IF(A45="","",IF(A45<词盘!$B$2,"大词",IF(A45<词盘!$C$2,"中尾词","长尾词"))) -> 大词 | D45: =IF(M45="","",IF(OR(E45="/",E45=""),"无序",IF(COUNTIFS(E:E,E45)<4,"无序","有序"))) -> 无序 | F45: 属性词 | G45: 太阳能电池 | H45: 寻找太阳能电池 | I45: =P45/SUM(P:P) -> 0.0031015508 | J45: =AC45 -> 5861 | K45: =IFERROR(Z45*AH45,"") -> 9756.64 | M45: probe thermometer | N45: 探针温度计 | O45: Y | P45: 0.0031 | Q45: 自然搜索词/AC推荐词 | R45: 19776 | S45: 14 | T45: B005KCG6CE/B00GRFHXVQ/B096K2L985/B01F59K0KA/B0C7D27GV8/B0CRY9V6LL/B017613C3C/B0BJK5W11R/B0BQ782XNW/B01IHHLB3W/B07XXSYLL8/B09LSGPHT3/B0BBR2RL6X/B00S93EQUK | U45: 187939 | V45: 11452 | W45: 1759 | X45: 0.1536 | Y45: 258044 | Z45: 4624 | AA45: 40 | AB45: 1 | AC45: 5861 | AD45: 1.95 | AE45: 146 | AF45: 0.3471 | AG45: 0.2956 | AH45: 2.11 | AI45: $1.59 - $2.65 | AJ45: B00S93EQUK | AK45: 0.1497 | AL45: 0.113 | AM45: B07XXSYLL8 | AN45: 0.1019 | AO45: 0.113 | AP45: B017613C3C | AQ45: 0.0955 | AR45: 0.0696 | AS45: B017613C3C,B07XXSYLL8,B07477NMF4,B00S93EQUK,B08K2G5Y78,B08317TDP1,B07Y51PCW7,B08KZR4F23,B0DKHVXLHW,B08RWPPD8J | AT45: 0.0022 | AU45: B01DODMU9I,B0B5XSFZ5Q,B0BC6G9Q35,B0CNTKWP8D,B01MXSZOKS,B0B5XTLLCT,B0CY2MZS8N,B079X4ZR6X,B09NFRC4LM,B07SRRQS5B
A46: =W46 -> 1106 | B46: =IF(A46="","",IF(A46<词盘!$B$2,"大词",IF(A46<词盘!$C$2,"中尾词","长尾词"))) -> 大词 | C46: 3 | D46: =IF(M46="","",IF(OR(E46="/",E46=""),"无序",IF(COUNTIFS(E:E,E46)<4,"无序","有序"))) -> 无序 | F46: 品名词 | H46: 寻找小型发电机 | I46: =P46/SUM(P:P) -> 0.0031015508 | J46: =AC46 -> 4578 | K46: =IFERROR(Z46*AH46,"") -> 14571.72 | M46: grill thermometer | N46: 烧烤温度计 | O46: Y | P46: 0.0031 | Q46: 自然搜索词/AC推荐词/HR推荐词/SP广告词 | R46: 19688 | S46: 11 | T46: B017613C3C/B0BQ782XNW/B0C7D27GV8/B07XXSYLL8/B09LSGPHT3/B00S93EQUK/B01IHHLB3W/B0CRY9V6LL/B0BBR2RL6X/B0BJK5W11R/B01F59K0KA | U46: 95414 | V46: 14403 | W46: 1106 | X46: 0.0768 | Y46: 327483 | Z46: 7143 | AA46: 26 | AB46: 9 | AC46: 4578 | AD46: 3.15 | AE46: 99 | AF46: 0.3328 | AG46: 0.2564 | AH46: 2.04 | AI46: $1.53 - $2.55 | AJ46: B01LZI4IA3 | AK46: 0.1405 | AL46: 0.0462 | AM46: B00S93EQUK | AN46: 0.1037 | AO46: 0.1487 | AP46: B0BBKSQG9K | AQ46: 0.0886 | AR46: 0.0615 | AS46: B00S93EQUK,B08K2G5Y78,B07XXSYLL8,B08KZR4F23,B01LZI4IA3,B0CD4FZ5MZ,B07477NMF4,B0B71HFH9K,B09LSGPHT3,B07H8WTFHW | AT46: 0.0029 | AU46: B0B9VGMLZR,B09RWN11T5,B0CJF9LBQL,B09H2CLPHT,B0C33V7QSW,B0928K23P6,B0CQ7CQXTL,B0CWLV8TMK,B01DOE0DO6,B082WJMM5H
A47: =W47 -> 424 | B47: =IF(A47="","",IF(A47<词盘!$B$2,"大词",IF(A47<词盘!$C$2,"中尾词","长尾词"))) -> 大词 | C47: 1 | D47: =IF(M47="","",IF(OR(E47="/",E47=""),"无序",IF(COUNTIFS(E:E,E47)<4,"无序","有序"))) -> 无序 | F47: 场景词 | G47: 户外露营发电机 | H47: 寻找适合露营使用的发电机 | I47: =P47/SUM(P:P) -> 0.0031015508 | J47: =AC47 -> 15924 | K47: =IFERROR(Z47*AH47,"") -> 56176.8 | M47: smoker | N47: 吸烟者 | P47: 0.0031 | Q47: 自然搜索词 | R47: 19607 | S47: 3 | T47: B07XXSYLL8/B0C7D27GV8/B0BBR2RL6X | U47: 8970 | V47: 98630 | W47: 424 | X47: 0.0043 | Y47: 2252354 | Z47: 46814 | AA47: 11 | AB47: 38 | AC47: 15924 | AD47: 6.19 | AE47: 112 | AF47: 0.2732 | AG47: 0.2283 | AH47: 1.2 | AI47: $0.89 - $1.50 | AJ47: B08F8L6S2R | AK47: 0.1272 | AL47: 0.0761 | AM47: B07QKH47TM | AN47: 0.0852 | AO47: 0.0761 | AP47: B07FKLK6DG | AQ47: 0.0608 | AR47: 0.0761 | AS47: B0BCFK9R8V,B0DHS5PBRR,B07CN38M23,B0BDDHHK3B,B07NQLF9WD,B0D5CPYZM4,B07FKLK6DG,B0D9TCGQ5F,B07QKH47TM,B07GLK1NC2 | AT47: 0.0258 | AU47: B08YZ633BY,B07MYW7C3Z,B0CL9YMRD5,B0BQZBMXD4,B00XZEKSL4,B07CZDXDG8,B0C3CZVKXT,B0BN9DD956,B09NXVJ25C,B07QK9C9KT
A48: =W48 -> 1478 | B48: =IF(A48="","",IF(A48<词盘!$B$2,"大词",IF(A48<词盘!$C$2,"中尾词","长尾词"))) -> 大词 | D48: =IF(M48="","",IF(OR(E48="/",E48=""),"无序",IF(COUNTIFS(E:E,E48)<4,"无序","有序"))) -> 有序 | E48: meat thermometer | F48: 品牌词 | H48: 了解或购买Anker品牌的电源产品 | I48: =P48/SUM(P:P) -> 0.0031015508 | J48: =AC48 -> 4571 | K48: =IFERROR(Z48*AH48,"") -> 6131.19 | M48: meat thermometers | N48: 肉类温度计 | P48: 0.0031 | Q48: 自然搜索词 | R48: 19509 | S48: 15 | T48: B005KCG6CE/B0CRY9V6LL/B01F59K0KA/B0BBR2RL6X/B017613C3C/B0BJK5W11R/B0BQ782XNW/B01IHHLB3W/B096K2L985/B00GRFHXVQ/B09LSGPHT3/B07XXSYLL8/B00S93EQUK/B0C7D27GV8/B0DDXWY41V | U48: 174233 | V48: 7481 | W48: 1478 | X48: 0.1976 | Y48: 212104 | Z48: 3081 | AA48: 34 | AB48: 0 | AC48: 4571 | AD48: 1.64 | AE48: 47 | AF48: 0.1864 | AG48: 0.2196 | AH48: 1.99 | AI48: $1.62 - $2.42 | AJ48: B0DJY2PWTY | AK48: 0.068 | AL48: 0.0488 | AM48: B00S93EQUK | AN48: 0.0651 | AO48: 0.0854 | AP48: B09C32DYV1 | AQ48: 0.0533 | AR48: 0.0854 | AS48: B00S93EQUK,B07XXSYLL8,B07Y51PCW7,B017613C3C,B01IHHLB3W,B0DHZTCNR5,B01CI4ZYMO,B0C37DLHWW,B0DHVGDCK2,B09LSGPHT3 | AT48: 0.0598 | AU48: B07SRRQS5B,B0982TPZTW,B07HY3S811,B0B8V6Y2X8,B0D1KDXFZJ,B0BZCMDZNS,B00DZKQLZ0,B01MXSZOKS,B0CFF2JG1N,B0CL9SXSBD
A49: =W49 -> 203 | B49: =IF(A49="","",IF(A49<词盘!$B$2,"大词",IF(A49<词盘!$C$2,"中尾词","长尾词"))) -> 大词 | C49: 3 | D49: =IF(M49="","",IF(OR(E49="/",E49=""),"无序",IF(COUNTIFS(E:E,E49)<4,"无序","有序"))) -> 无序 | F49: 场景词 | G49: 家庭使用的太阳能发电机 | H49: 寻找家庭用太阳能发电机 | I49: =P49/SUM(P:P) -> 0.0029014507 | J49: =AC49 -> 146 | K49: =IFERROR(Z49*AH49,"") -> 96290 | M49: thermoworks | N49: 热工 | P49: 0.0029 | Q49: 自然搜索词 | R49: 18731 | S49: 8 | T49: B0CRY9V6LL/B01F59K0KA/B0BBR2RL6X/B017613C3C/B0BJK5W11R/B01IHHLB3W/B07XXSYLL8/B096K2L985 | U49: 111150 | V49: 19906 | W49: 203 | X49: 0.0102 | Y49: 590461 | Z49: 9629 | AA49: 5 | AB49: 2 | AC49: 146 | AD49: 136.34 | AE49: 49 | AF49: 0.6069 | AG49: 0.3437 | AH49: 10 | AI49: $9.00 - $11.00 | AJ49: B0DC8MWQ8K | AK49: 0.3198 | AL49: 0.1406 | AM49: B0DC8FD41B | AN49: 0.21 | AO49: 0.1875 | AP49: B0DRR59GDV | AQ49: 0.0771 | AR49: 0.0156 | AS49: B0DC8FWCDT,B0DC8FD41B,B0DC8MWQ8K,B08KZR4F23,B0DC875HXP,B07XXSYLL8,B0BMLDL5GM,B0BBR2RL6X,B094N6DZLC,B01C8557T8 | AT49: 0.0229 | AU49: B0C1GQ54QD,B0BX8M7FP9,B0BF92PVYX,B0C4F7Q36M,B0CSN2CZQR,B0CP27G91Z,B0CCY6S4K2,B0CK6QRX79,B0B7JF6NKX,B0C6G43SGX
A50: =W50 -> 11951 | B50: =IF(A50="","",IF(A50<词盘!$B$2,"大词",IF(A50<词盘!$C$2,"中尾词","长尾词"))) -> 大词 | D50: =IF(M50="","",IF(OR(E50="/",E50=""),"无序",IF(COUNTIFS(E:E,E50)<4,"无序","有序"))) -> 无序 | F50: 功能词 | G50: 电池备份电源 | H50: 寻找电池备份电源供应 | I50: =P50/SUM(P:P) -> 0.0029014507 | J50: =AC50 -> 3107 | K50: =IFERROR(Z50*AH50,"") -> 55404.28 | M50: refrigerator thermometer | N50: 冰箱温度计 | P50: 0.0029 | Q50: 自然搜索词 | R50: 18580 | S50: 8 | T50: B017613C3C/B01IHHLB3W/B09LSGPHT3/B07XXSYLL8/B005KCG6CE/B00S93EQUK/B01F59K0KA/B0CRY9V6LL | U50: 17953 | V50: 73593 | W50: 11951 | X50: 0.1624 | Y50: 1507857 | Z50: 28124 | AA50: 272 | AB50: 28 | AC50: 3107 | AD50: 23.69 | AE50: 120 | AF50: 0.5444 | AG50: 0.5086 | AH50: 1.97 | AI50: $1.48 - $2.46 | AJ50: B089NLQ7SF | AK50: 0.3302 | AL50: 0.3256 | AM50: B07VVHZLLZ | AN50: 0.1145 | AO50: 0.1189 | AP50: B07RPXTKMK | AQ50: 0.0997 | AR50: 0.0641 | AS50: B089NLQ7SF,B07VVHZLLZ,B005KDEFNK,B08NYMFTZT,B0D83Q3X68,B07RN7Z2RT,B000BPE88E,B07RPXTKMK,B0CRHB8T4F,B004QJVU78 | AT50: 0.0268 | AU50: B0CXTBZR2H,B07W76MV4Y,B0C42FRFHG,B0CZRC9F86,B0CZNXWBR2,B0D1KDXFZJ,B0CYBRQ7FC,B09NFQKBZY,B0BC6G9Q35,B0CW63HL7S
A51: =W51 -> 2217 | B51: =IF(A51="","",IF(A51<词盘!$B$2,"大词",IF(A51<词盘!$C$2,"中尾词","长尾词"))) -> 大词 | D51: =IF(M51="","",IF(OR(E51="/",E51=""),"无序",IF(COUNTIFS(E:E,E51)<4,"无序","有序"))) -> 无序 | F51: 功能词 | G51: 便携太阳能发电机 | H51: 寻找便携太阳能发电机 | I51: =P51/SUM(P:P) -> 0.0029014507 | J51: =AC51 -> 2802 | K51: =IFERROR(Z51*AH51,"") -> 8503.27 | M51: digital cooking thermometer | N51: 数字式烹饪温度计 | P51: 0.0029 | Q51: 自然搜索词 | R51: 18456 | S51: 14 | T51: B0BJK5W11R/B00GRFHXVQ/B096K2L985/B01F59K0KA/B017613C3C/B0BQ782XNW/B01IHHLB3W/B0C7D27GV8/B005KCG6CE/B07XXSYLL8/B09LSGPHT3/B0CRY9V6LL/B0BBR2RL6X/B00S93EQUK | U51: 188312 | V51: 9610 | W51: 2217 | X51: 0.2307 | Y51: 267321 | Z51: 4273 | AA51: 51 | AB51: 3 | AC51: 2802 | AD51: 3.43 | AE51: 44 | AF51: 0.4185 | AG51: 0.3832 | AH51: 1.99 | AI51: $1.65 - $2.27 | AJ51: B00S93EQUK | AK51: 0.2236 | AL51: 0.2468 | AM51: B09C32DYV1 | AN51: 0.131 | AO51: 0.0909 | AP51: B09MTX71VX | AQ51: 0.0639 | AR51: 0.0455 | AS51: B00S93EQUK,B07XXSYLL8,B09LSGPHT3,B017613C3C,B07Y51PCW7,B0C37DLHWW,B0BQ782XNW,B0B71HFH9K,B0D46H7194,B01IHHLB3W | AT51: 0.0062 | AU51: B07SRRQS5B,B07HY3S811,B0B8V6Y2X8,B0982TPZTW,B0CL9SXSBD,B0B7Z2MRWY,B082K8ZNQ1,B01DODMU9I,B0CFF2JG1N,B0CWP3757G
A52: =W52 -> 466 | B52: =IF(A52="","",IF(A52<词盘!$B$2,"大词",IF(A52<词盘!$C$2,"中尾词","长尾词"))) -> 大词 | D52: =IF(M52="","",IF(OR(E52="/",E52=""),"无序",IF(COUNTIFS(E:E,E52)<4,"无序","有序"))) -> 无序 | F52: 场景词 | G52: 家庭使用的便携发电机 | H52: 寻找家庭用便携发电机 | I52: =P52/SUM(P:P) -> 0.0028014007 | J52: =AC52 -> 2701 | K52: =IFERROR(Z52*AH52,"") -> 11138.4 | M52: meat probe | N52: 肉探针 | P52: 0.0028 | Q52: 自然搜索词 | R52: 18023 | S52: 14 | T52: B0CRY9V6LL/B01F59K0KA/B017613C3C/B0BJK5W11R/B01IHHLB3W/B0BQ782XNW/B005KCG6CE/B096K2L985/B07XXSYLL8/B00S93EQUK/B0C7D27GV8/B0BBR2RL6X/B00GRFHXVQ/B09LSGPHT3 | U52: 159110 | V52: 11567 | W52: 466 | X52: 0.0403 | Y52: 263136 | Z52: 5712 | AA52: 11 | AB52: 15 | AC52: 2701 | AD52: 4.28 | AE52: 52 | AF52: 0.3279 | AG52: 0.4141 | AH52: 1.95 | AI52: $1.51 - $2.15 | AJ52: B07XXSYLL8 | AK52: 0.1274 | AL52: 0.1919 | AM52: B00S93EQUK | AN52: 0.1111 | AO52: 0.1515 | AP52: B08K2G5Y78 | AQ52: 0.0894 | AR52: 0.0707 | AS52: B07XXSYLL8,B08317TDP1,B07H8WTFHW,B00S93EQUK,B0BMLDL5GM,B08K2G5Y78,B07477NMF4,B0D5M9RW7C,B017613C3C,B0B48NL6L8 | AT52: 0.0721 | AU52: B0BNMVB18C,B07VHPFK5B,B073FRMG3N,B0CRQJ23DH,B0BWHG8PMV,B001DYDAEK,B09PGQD7LS,B00LB7REMS,B09FP3T2M7,B09YTXP8BS
A53: =W53 -> 276 | B53: =IF(A53="","",IF(A53<词盘!$B$2,"大词",IF(A53<词盘!$C$2,"中尾词","长尾词"))) -> 大词 | D53: =IF(M53="","",IF(OR(E53="/",E53=""),"无序",IF(COUNTIFS(E:E,E53)<4,"无序","有序"))) -> 无序 | F53: 品牌词 | H53: 了解或购买EcoFlow太阳能面板 | I53: =P53/SUM(P:P) -> 0.0028014007 | J53: =AC53 -> 124 | K53: =IFERROR(Z53*AH53,"") -> 66290 | M53: thermapen one | N53: 热敏漆一 | P53: 0.0028 | Q53: 自然搜索词/SP广告词 | R53: 17999 | S53: 11 | T53: B0BJK5W11R/B01F59K0KA/B0CRY9V6LL/B0BBR2RL6X/B01IHHLB3W/B07XXSYLL8/B09LSGPHT3/B00S93EQUK/B017613C3C/B096K2L985/B0BQ782XNW | U53: 149432 | V53: 13336 | W53: 276 | X53: 0.0207 | Y53: 305351 | Z53: 6629 | AA53: 7 | AB53: 1 | AC53: 124 | AD53: 107.55 | AE53: 31 | AF53: 0.75 | AG53: 0.5375 | AH53: 10 | AI53: $9.00 - $11.00 | AJ53: B0DC8MWQ8K | AK53: 0.625 | AL53: 0.4125 | AM53: B07XXSYLL8 | AN53: 0.0663 | AO53: 0.1125 | AP53: B0DC8776HK | AQ53: 0.0587 | AR53: 0.0125 | AS53: B0DC8MWQ8K,B07XXSYLL8,B0BBR2RL6X,B0DC875HXP,B0DC8FD41B,B0DJY2PWTY,B01F59K0KA,B0DHZTCNR5,B00S93EQUK,B0CZCX5WDC | AT53: 0.0322 | AU53: B0BPNMT5DM,B07SRRQS5B,B097QGJC2Q,B0C2P72SCX,B01IEJHJWK,B0B8V6Y2X8,B0CHVWVK3C,B07M7M8X1N,B0CK3TGYZ2,B0BV6YFY8D
A54: =W54 -> 9174 | B54: =IF(A54="","",IF(A54<词盘!$B$2,"大词",IF(A54<词盘!$C$2,"中尾词","长尾词"))) -> 大词 | C54: 3 | D54: =IF(M54="","",IF(OR(E54="/",E54=""),"无序",IF(COUNTIFS(E:E,E54)<4,"无序","有序"))) -> 无序 | F54: 属性词 | G54: 便携式太阳能面板 | H54: 寻找便携式太阳能面板 | I54: =P54/SUM(P:P) -> 0.0028014007 | J54: =AC54 -> 665 | K54: =IFERROR(Z54*AH54,"") -> 26564.97 | M54: oven thermometer for gas oven | N54: 燃气烤箱用烤箱温度计 | P54: 0.0028 | Q54: 自然搜索词 | R54: 17803 | S54: 14 | T54: B005KCG6CE/B017613C3C/B01IHHLB3W/B0CRY9V6LL/B01F59K0KA/B0C7D27GV8/B0BJK5W11R/B096K2L985/B0BBR2RL6X/B00GRFHXVQ/B00S93EQUK/B07XXSYLL8/B09LSGPHT3/B0BQ782XNW | U54: 63008 | V54: 44470 | W54: 9174 | X54: 0.2063 | Y54: 944776 | Z54: 20593 | AA54: 208 | AB54: 1 | AC54: 665 | AD54: 66.87 | AE54: 141 | AF54: 0.7301 | AG54: 0.6645 | AH54: 1.29 | AI54: $0.98 - $1.62 | AJ54: B083BMMQV9 | AK54: 0.4807 | AL54: 0.5152 | AM54: B005KDEIZ0 | AN54: 0.127 | AO54: 0.0606 | AP54: B0000DJUYR | AQ54: 0.1224 | AR54: 0.0887 | AS54: B083BMMQV9,B0000DJUYR,B07YP9G4Z7,B01CF39C4Y,B0CX19TQH1,B000BQWMTK,B0D3XLVZCP,B08GY3K7KD,B09JSBXJDV,B017613C3C | AT54: 0.0083 | AU54: B07SRRQS5B,B0B7Z2MRWY,B082K8ZNQ1,B01DODMU9I,B0CFV5LZ3R,B0CFF2JG1N,B07MXJ93K8,B0BC6G9Q35,B09NFRC4LM,B082Q1X6BB
A55: =W55 -> 3142 | B55: =IF(A55="","",IF(A55<词盘!$B$2,"大词",IF(A55<词盘!$C$2,"中尾词","长尾词"))) -> 大词 | D55: =IF(M55="","",IF(OR(E55="/",E55=""),"无序",IF(COUNTIFS(E:E,E55)<4,"无序","有序"))) -> 无序 | F55: 功能词 | G55: 便携电力 | H55: 寻找便携电力产品 | I55: =P55/SUM(P:P) -> 0.0028014007 | J55: =AC55 -> 4213 | K55: =IFERROR(Z55*AH55,"") | M55: kitchen thermometer for cooking | N55: 厨房烹饪温度计 | P55: 0.0028 | Q55: 自然搜索词 | R55: 17647 | S55: 15 | T55: B005KCG6CE/B0C7D27GV8/B017613C3C/B0BJK5W11R/B0BQ782XNW/B01IHHLB3W/B00GRFHXVQ/B07XXSYLL8/B09LSGPHT3/B096K2L985/B01F59K0KA/B0CRY9V6LL/B0BBR2RL6X/B00S93EQUK/B0DDXWY41V | U55: 165975 | V55: 14046 | W55: 3142 | X55: 0.2237 | Y55: 354058 | Z55: 5654 | AA55: 72 | AB55: 1 | AC55: 4213 | AD55: 3.33 | AE55: 14 | AF55: 0.3842 | AG55: 0.4438 | AI55: - | AJ55: B00S93EQUK | AK55: 0.161 | AL55: 0.2125 | AM55: B09C32DYV1 | AN55: 0.1215 | AO55: 0.1688 | AP55: B09MTX71VX | AQ55: 0.1017 | AR55: 0.0625 | AS55: B00S93EQUK,B0C37DLHWW,B07XXSYLL8,B09LSGPHT3,B07Y51PCW7,B09MTX71VX,B017613C3C,B01IHHLB3W,B0B71HFH9K,B0BQ782XNW
A56: =W56 -> 63 | B56: =IF(A56="","",IF(A56<词盘!$B$2,"大词",IF(A56<词盘!$C$2,"中尾词","长尾词"))) -> 大词 | D56: =IF(M56="","",IF(OR(E56="/",E56=""),"无序",IF(COUNTIFS(E:E,E56)<4,"无序","有序"))) -> 无序 | F56: 品牌词 | H56: 了解或购买Anker太阳能面板 | I56: =P56/SUM(P:P) -> 0.0028014007 | J56: =AC56 -> 98971 | K56: =IFERROR(Z56*AH56,"") -> 24255.85 | M56: bbq | N56: 烧烤 | P56: 0.0028 | Q56: 自然搜索词/SP广告词 | R56: 17500 | S56: 7 | T56: B0BQ782XNW/B00S93EQUK/B0C7D27GV8/B01F59K0KA/B017613C3C/B07XXSYLL8/B09LSGPHT3 | U56: 33397 | V56: 37143 | W56: 63 | X56: 0.0017 | Y56: 755523 | Z56: 17705 | AA56: 2 | AB56: 64 | AC56: 98971 | AD56: 0.38 | AE56: 442 | AF56: 0.1014 | AG56: 0.1532 | AH56: 1.37 | AI56: $1.12 - $1.99 | AJ56: B07FKLK6DG | AK56: 0.0421 | AL56: 0.0096 | AM56: B074J6J9PS | AN56: 0.0338 | AO56: 0.134 | AP56: B0B4PY2MDQ | AQ56: 0.0255 | AR56: 0.0096 | AS56: B07FKLK6DG,B09MT5N7Z2,B0CGX3ZGBK,B0D9WJKXNY,B00BXLUXYS,B07VLW8677,B08KZR4F23,B0CPQXD6JV,B08XTGT9J1,B0CT3C99FD | AT56: 0.1038 | AU56: B00LB7REFK,B0CS9H9FRB,B07SRRQS5B,B07QHDRCZ3,B07VHPFK5B,B07JNQMPQJ,B0BC6G9Q35,B00L4Z0T2Y,B0CFV5LZ3R,B09YJ34W96
A57: =W57 -> 706 | B57: =IF(A57="","",IF(A57<词盘!$B$2,"大词",IF(A57<词盘!$C$2,"中尾词","长尾词"))) -> 大词 | C57: 1 | D57: =IF(M57="","",IF(OR(E57="/",E57=""),"无序",IF(COUNTIFS(E:E,E57)<4,"无序","有序"))) -> 有序 | E57: meat thermometer | F57: 品名词 | H57: 寻找便携电池 | I57: =P57/SUM(P:P) -> 0.0024012006 | J57: =AC57 -> 707 | K57: =IFERROR(Z57*AH57,"") -> 53210 | M57: thermoworks meat thermometer | N57: Thermoworks 肉类温度计 | P57: 0.0024 | Q57: 自然搜索词 | R57: 15554 | S57: 15 | T57: B0C37ZWPZR/B005KCG6CE/B096K2L985/B0CRY9V6LL/B01F59K0KA/B0BBR2RL6X/B017613C3C/B01IHHLB3W/B07XXSYLL8/B09LSGPHT3/B00S93EQUK/B0BJK5W11R/B0BQ782XNW/B00GRFHXVQ/B0C7D27GV8 | U57: 200614 | V57: 10777 | W57: 706 | X57: 0.0656 | Y57: 261445 | Z57: 5321 | AA57: 17 | AB57: 0 | AC57: 707 | AD57: 15.24 | AE57: 18 | AF57: 0.4916 | AG57: 0.5075 | AH57: 10 | AI57: $9.00 - $11.00 | AJ57: B0DC8MWQ8K | AK57: 0.2068 | AL57: 0.1791 | AM57: B0DC8FD41B | AN57: 0.2034 | AO57: 0.2239 | AP57: B07XXSYLL8 | AQ57: 0.0814 | AR57: 0.1045 | AS57: B0DC8FD41B,B0DC8MWQ8K,B07XXSYLL8,B08KZR4F23,B0BMLDL5GM,B08K2G5Y78,B0DRQHM2VL,B017613C3C,B0BBR2RL6X,B01GE77QT0 | AT57: 0.0238 | AU57: B079X4ZR6X,B0BY3RK5CC,B084YPVTXB,B07G5KHQGH,B079JYP5DP,B079X5XWXP,B08511JF83,B0C5N9YYTY,B08CQSM1YQ,B0BWNXJ9QR
A58: =W58 -> 2028 | B58: =IF(A58="","",IF(A58<词盘!$B$2,"大词",IF(A58<词盘!$C$2,"中尾词","长尾词"))) -> 大词 | C58: 1 | D58: =IF(M58="","",IF(OR(E58="/",E58=""),"无序",IF(COUNTIFS(E:E,E58)<4,"无序","有序"))) -> 无序 | F58: 功能词 | G58: 便携电源插座 | H58: 寻找便携式电源插座 | I58: =P58/SUM(P:P) -> 0.0024012006 | J58: =AC58 -> 18778 | K58: =IFERROR(Z58*AH58,"") -> 35838.6 | M58: grilling accessories | N58: 烧烤配件 | O58: Y | P58: 0.0024 | Q58: 自然搜索词/AC推荐词/SP广告词 | R58: 15551 | S58: 6 | T58: B00S93EQUK/B096K2L985/B01F59K0KA/B07XXSYLL8/B0BBR2RL6X/B0C7D27GV8 | U58: 15093 | V58: 56815 | W58: 2028 | X58: 0.0357 | Y58: 1169898 | Z58: 25599 | AA58: 47 | AB58: 7 | AC58: 18778 | AD58: 3.03 | AE58: 194 | AF58: 0.1862 | AG58: 0.1295 | AH58: 1.4 | AI58: $1.05 - $1.75 | AJ58: B0C6X6KX2H | AK58: 0.0852 | AL58: 0.0566 | AM58: B079J4KT8H | AN58: 0.0545 | AO58: 0.0474 | AP58: B08CGYYX54 | AQ58: 0.0465 | AR58: 0.0255 | AS58: B00KA2Y1OY,B0C6X6KX2H,B0BVMGNK5B,B00NE5IF3W,B0CBB23R8B,B081JVXDJJ,B00S93EQUK,B0C748BK8B,B0CFHNNFFF,B0CXFCS2MD | AT58: 0.0456 | AU58: B07ZWHKWH9,B0BFJQZH63,B09KYDWH7G,B0884ZVCG7,B0CPGS3S52,B09X6593C1,B097CKJ79B,B0CKLZC74G,B07TMKXZQT,B0BV9ZJLRS
A59: =W59 -> 2072 | B59: =IF(A59="","",IF(A59<词盘!$B$2,"大词",IF(A59<词盘!$C$2,"中尾词","长尾词"))) -> 大词 | D59: =IF(M59="","",IF(OR(E59="/",E59=""),"无序",IF(COUNTIFS(E:E,E59)<4,"无序","有序"))) -> 无序 | F59: 功能词 | G59: CPAP设备电池备份电源 | H59: 寻找CPAP设备的电池备份电源 | I59: =P59/SUM(P:P) -> 0.0024012006 | J59: =AC59 -> 1131 | K59: =IFERROR(Z59*AH59,"") -> 6633 | M59: steak thermometer | N59: 牛排温度计 | P59: 0.0024 | Q59: 自然搜索词 | R59: 15545 | S59: 15 | T59: B005KCG6CE/B01F59K0KA/B0C7D27GV8/B0CRY9V6LL/B017613C3C/B0BQ782XNW/B01IHHLB3W/B0BJK5W11R/B00GRFHXVQ/B07XXSYLL8/B09LSGPHT3/B096K2L985/B0BBR2RL6X/B00S93EQUK/B0DDXWY41V | U59: 210979 | V59: 8439 | W59: 2072 | X59: 0.2456 | Y59: 252292 | Z59: 3300 | AA59: 47 | AB59: 7 | AC59: 1131 | AD59: 7.46 | AE59: 54 | AF59: 0.427 | AG59: 0.4537 | AH59: 2.01 | AI59: $1.51 - $2.52 | AJ59: B00S93EQUK | AK59: 0.2669 | AL59: 0.3148 | AM59: B0C37DLHWW | AN59: 0.0854 | AO59: 0.0926 | AP59: B09C32DYV1 | AQ59: 0.0747 | AR59: 0.0463 | AS59: B00S93EQUK,B07XXSYLL8,B01IHHLB3W,B0BQ782XNW,B07Y51PCW7,B017613C3C,B0C37DLHWW,B09LSGPHT3,B07H8WTFHW,B01CL9G1FU | AT59: 0.0189 | AU59: B0B8V6Y2X8,B07SRRQS5B,B0982TBY1Y,B07HY3S811,B01DODMU9I,B0BC6G9Q35,B01MQQTB51,B09NFRC4LM,B00DZKQLZ0,B00IPPA73C
A60: =W60 -> 1835 | B60: =IF(A60="","",IF(A60<词盘!$B$2,"大词",IF(A60<词盘!$C$2,"中尾词","长尾词"))) -> 大词 | C60: 1 | D60: =IF(M60="","",IF(OR(E60="/",E60=""),"无序",IF(COUNTIFS(E:E,E60)<4,"无序","有序"))) -> 无序 | F60: 场景词 | G60: 呼吸机场景 | H60: 了解CPAP设备或寻找CPAP相关产品 | I60: =P60/SUM(P:P) -> 0.0023011506 | J60: =AC60 -> 179667 | K60: =IFERROR(Z60*AH60,"") -> 253456.06 | M60: mens gifts | N60: 男式礼物 | O60: Y | P60: 0.0023 | Q60: 自然搜索词/AC推荐词/SP广告词 | R60: 14916 | S60: 1 | T60: B00S93EQUK | U60: 14737 | V60: 152938 | W60: 1835 | X60: 0.012 | Y60: 4514078 | Z60: 63206 | AA60: 42 | AB60: 4 | AC60: 179667 | AD60: 0.85 | AE60: 281 | AF60: 0.1062 | AG60: 0.0767 | AH60: 4.01 | AI60: $3.00 - $5.01 | AJ60: B0D4215HCX | AK60: 0.0418 | AL60: 0.0405 | AM60: 1450845800 | AN60: 0.0374 | AO60: 0.0362 | AP60: B087DNXJ7R | AQ60: 0.027 | AR60: 0 | AS60: B09232JHMY,B08P4HHSZT,B0BG4HY4PX,B0CGX3ZGBK,B0CRR1XXC4,B0CG65PYBV,B0D4215HCX,B081T7N948,B0DN21CM94,B0CQP6SSY1 | AT60: 0.0139 | AU60: B0C8HWW4WC,B0CTFPHSLC,B08P8FKQ6T,B0CKNNT27B,B0CH3F2BLQ,B0C1MWKGP6,B07ZZK6QJV,B0BYHTZQVM,B0CFRD8N31,B0BLHZLHJW
A61: =W61 -> 2679 | B61: =IF(A61="","",IF(A61<词盘!$B$2,"大词",IF(A61<词盘!$C$2,"中尾词","长尾词"))) -> 大词 | D61: =IF(M61="","",IF(OR(E61="/",E61=""),"无序",IF(COUNTIFS(E:E,E61)<4,"无序","有序"))) -> 无序 | F61: 功能词 | G61: 电源逆变器 | H61: 寻找电源逆变器 | I61: =P61/SUM(P:P) -> 0.0023011506 | J61: =AC61 -> 733 | K61: =IFERROR(Z61*AH61,"") | M61: candy thermometer for candy making | N61: 糖果制作用糖果温度计 | P61: 0.0023 | Q61: 自然搜索词 | R61: 14815 | S61: 13 | T61: B0DDXWY41V/B01IHHLB3W/B005KCG6CE/B07XXSYLL8/B01F59K0KA/B00S93EQUK/B00GRFHXVQ/B0CRY9V6LL/B0BBR2RL6X/B017613C3C/B096K2L985/B09LSGPHT3/B0C7D27GV8 | U61: 88935 | V61: 28810 | W61: 2679 | X61: 0.093 | Y61: 724950 | Z61: 13659 | AA61: 61 | AB61: 9 | AC61: 733 | AD61: 39.3 | AE61: 144 | AF61: 0.3928 | AG61: 0.3227 | AI61: - | AJ61: B0DMNQZTR3 | AK61: 0.169 | AL61: 0.1409 | AM61: B094NBSRT4 | AN61: 0.1346 | AO61: 0.1409 | AP61: B00004XSC9 | AQ61: 0.0892 | AR61: 0.0409 | AS61: B0BGX4RG9B,B00004XSC9,B01BICCN6M,B001FB6IFY,B07YP9GT1N,B00279OPDU,B0028LVJEA,B0B71HFH9K,B07KCJBW27,B0CM5XFWMY | AT61: 0.061 | AU61: B00LB7REFK,B07SRRQS5B,B0BC6G9Q35,B07QHDRCZ3,B0CFV5LZ3R,B0C7F7LS8Z,B0BX8GZ9R8,B01MQQTB51,B019CJSDM6,B0BNMVB18C
A62: =W62 -> 9894 | B62: =IF(A62="","",IF(A62<词盘!$B$2,"大词",IF(A62<词盘!$C$2,"中尾词","长尾词"))) -> 大词 | D62: =IF(M62="","",IF(OR(E62="/",E62=""),"无序",IF(COUNTIFS(E:E,E62)<4,"无序","有序"))) -> 无序 | F62: 功能词 | G62: 便携电动发电机 | H62: 寻找便携电动发电机 | I62: =P62/SUM(P:P) -> 0.0023011506 | J62: =AC62 -> 4714 | K62: =IFERROR(Z62*AH62,"") -> 58482 | M62: overnight delivery items | N62: 隔夜交货项目 | P62: 0.0023 | Q62: 自然搜索词/SP广告词 | R62: 14335 | S62: 3 | T62: B00S93EQUK/B01F59K0KA/B07XXSYLL8 | U62: 3074 | V62: 221353 | W62: 9894 | X62: 0.0447 | Y62: 4781407 | Z62: 97470 | AA62: 225 | AB62: 0 | AC62: 4714 | AD62: 46.96 | AE62: 675 | AF62: 0.1024 | AG62: 0.0907 | AH62: 0.6 | AI62: $0.50 - $0.86 | AJ62: B0CQY8WNG7 | AK62: 0.0382 | AL62: 0.031 | AM62: B0C2CY22B8 | AN62: 0.036 | AO62: 0.0293 | AP62: B09541P9WH | AQ62: 0.0282 | AR62: 0.0304 | AS62: B00W5D1MDE,B00HSC9F2C,B09Y5HT6HR,B09RY35M4S,B09541P9WH,B0CFGYFCYL,B01FX5H9P0,B08LGD7WRZ,B09VRJFML3,B00KR7PKTC | AT62: 0.0952 | AU62: B07SRRQS5B,B082K8ZNQ1,B01DODMU9I,B00LB7REFK,B0BC6G9Q35,B0B7Z2MRWY,B079X4ZR6X,B0CXT9W574,B01IEJHJWK,B00L4Z0T42
A63: =W63 -> 1695 | B63: =IF(A63="","",IF(A63<词盘!$B$2,"大词",IF(A63<词盘!$C$2,"中尾词","长尾词"))) -> 大词 | D63: =IF(M63="","",IF(OR(E63="/",E63=""),"无序",IF(COUNTIFS(E:E,E63)<4,"无序","有序"))) -> 无序 | F63: 品牌词 | H63: 了解或购买Anker品牌的电源产品 | I63: =P63/SUM(P:P) -> 0.0022011006 | J63: =AC63 -> 7025 | K63: =IFERROR(Z63*AH63,"") -> 5864 | M63: thermometer cooking | N63: 烹饪温度计 | P63: 0.0022 | Q63: 自然搜索词 | R63: 14302 | S63: 14 | T63: B0C7D27GV8/B005KCG6CE/B00GRFHXVQ/B096K2L985/B0CRY9V6LL/B01F59K0KA/B0BBR2RL6X/B017613C3C/B0BQ782XNW/B01IHHLB3W/B0BJK5W11R/B07XXSYLL8/B09LSGPHT3/B00S93EQUK | U63: 271696 | V63: 7177 | W63: 1695 | X63: 0.2363 | Y63: 193553 | Z63: 2932 | AA63: 39 | AB63: 0 | AC63: 7025 | AD63: 1.02 | AE63: 83 | AF63: 0.3363 | AG63: 0.35 | AH63: 2 | AI63: $1.58 - $2.28 | AJ63: B00S93EQUK | AK63: 0.1909 | AL63: 0.225 | AM63: B09C32DYV1 | AN63: 0.0727 | AO63: 0.0875 | AP63: B07XXSYLL8 | AQ63: 0.0727 | AR63: 0.0375 | AS63: B00S93EQUK,B07XXSYLL8,B01IHHLB3W,B0B71HFH9K,B07Y51PCW7,B09LSGPHT3,B0DCY8CZ7Z,B017613C3C,B0C37DLHWW,B09MTX71VX | AT63: 0.0554 | AU63: B07SRRQS5B,B0B75JF6CM,B0B8V6Y2X8,B0BZCMDZNS,B082K8ZNQ1,B07MXJ93K8,B07M7M8X1N,B0982TPZTW,B01IEJHJWK,B0CFF2JG1N
A64: =W64 -> 1079 | B64: =IF(A64="","",IF(A64<词盘!$B$2,"大词",IF(A64<词盘!$C$2,"中尾词","长尾词"))) -> 大词 | C64: 1 | D64: =IF(M64="","",IF(OR(E64="/",E64=""),"无序",IF(COUNTIFS(E:E,E64)<4,"无序","有序"))) -> 无序 | F64: 功能词 | G64: 逆变器 | H64: 寻找逆变器 | I64: =P64/SUM(P:P) -> 0.0022011006 | J64: =AC64 -> 825 | K64: =IFERROR(Z64*AH64,"") -> 5215.5 | M64: cooking thermometer for liquids | N64: 液体烹饪温度计 | P64: 0.0022 | Q64: 自然搜索词 | R64: 14222 | S64: 15 | T64: B005KCG6CE/B0BBR2RL6X/B017613C3C/B01IHHLB3W/B0BJK5W11R/B0BQ782XNW/B09LSGPHT3/B07XXSYLL8/B01F59K0KA/B0CRY9V6LL/B00S93EQUK/B0C7D27GV8/B00GRFHXVQ/B096K2L985/B0DDXWY41V | U64: 189526 | V64: 10520 | W64: 1079 | X64: 0.1026 | Y64: 230607 | Z64: 4275 | AA64: 25 | AB64: 0 | AC64: 825 | AD64: 12.75 | AE64: 49 | AF64: 0.4566 | AG64: 0.4778 | AH64: 1.22 | AI64: $0.64 - $2.45 | AJ64: B087XBXFM6 | AK64: 0.1897 | AL64: 0.2389 | AM64: B09MTX71VX | AN64: 0.1801 | AO64: 0.1504 | AP64: B07YP9GT1N | AQ64: 0.0868 | AR64: 0.0885 | AS64: B087XBXFM6,B0BGX4RG9B,B01N5HPTCU,B09MTX71VX,B00004XSC9,B09988SD2B,B00S93EQUK,B07Y51PCW7,B09LSGPHT3,B07QBP8Y2Q | AT64: 0.0686 | AU64: B09BDZZQ4Y,B077Q382WD,B07M6M1FKW,B082M35PH3,B07MHJSXJY,B0CD7SY39G,B00DZKQLZ0,B07HXWPBRT,B08FY46R39,B07DXDT69P
A65: =W65 -> 618 | B65: =IF(A65="","",IF(A65<词盘!$B$2,"大词",IF(A65<词盘!$C$2,"中尾词","长尾词"))) -> 大词 | D65: =IF(M65="","",IF(OR(E65="/",E65=""),"无序",IF(COUNTIFS(E:E,E65)<4,"无序","有序"))) -> 无序 | F65: 功能词 | G65: 逆变发电机 | H65: 寻找逆变发电机 | I65: =P65/SUM(P:P) -> 0.0022011006 | J65: =AC65 -> 511 | K65: =IFERROR(Z65*AH65,"") -> 12938.25 | M65: thermapen instant read thermometer | N65: 热敏笔即读温度计 | P65: 0.0022 | Q65: 自然搜索词 | R65: 13741 | S65: 13 | T65: B0BJK5W11R/B096K2L985/B01F59K0KA/B0BBR2RL6X/B0CRY9V6LL/B01IHHLB3W/B0BQ782XNW/B07XXSYLL8/B09LSGPHT3/B00GRFHXVQ/B00S93EQUK/B005KCG6CE/B017613C3C | U65: 224252 | V65: 8455 | W65: 618 | X65: 0.0732 | Y65: 225839 | Z65: 3981 | AA65: 15 | AB65: 0 | AC65: 511 | AD65: 16.55 | AE65: 15 | AF65: 0.6906 | AG65: 0.4778 | AH65: 3.25 | AI65: $1.59 - $5.04 | AJ65: B0DC8MWQ8K | AK65: 0.4453 | AL65: 0.2556 | AM65: B07XXSYLL8 | AN65: 0.1434 | AO65: 0.1778 | AP65: B0DC8776HK | AQ65: 0.1019 | AR65: 0.0444 | AS65: B0DC8MWQ8K,B07XXSYLL8,B0BBR2RL6X,B00S93EQUK,B0DJY2PWTY,B07R18W3W1,B0DC8FD41B,B0CZCX5WDC,B01F59K0KA,B07Y51PCW7 | AT65: 0 | AU65: B0CH3SL3HB,B0BFRHGSZK,B0CQL6D42L,B0CG5WF87G,B0CNPZG45V,B0CWCW49WS,B0CN36LVRS,B0CPTT357W,B0CF86YCGT,B0CJ9YKYGB
A66: =W66 -> 854 | B66: =IF(A66="","",IF(A66<词盘!$B$2,"大词",IF(A66<词盘!$C$2,"中尾词","长尾词"))) -> 大词 | D66: =IF(M66="","",IF(OR(E66="/",E66=""),"无序",IF(COUNTIFS(E:E,E66)<4,"无序","有序"))) -> 无序 | F66: 品名词 | H66: 寻找小型发电机 | I66: =P66/SUM(P:P) -> 0.0021010505 | J66: =AC66 -> 118085 | K66: =IFERROR(Z66*AH66,"") -> 156290.51 | M66: gifts for him | N66: 给他的礼物 | O66: Y | P66: 0.0021 | Q66: 自然搜索词/AC推荐词/SP广告词 | R66: 13123 | S66: 3 | T66: B00S93EQUK/B01F59K0KA/B0BBR2RL6X | U66: 19449 | V66: 120304 | W66: 854 | X66: 0.0071 | Y66: 2638129 | Z66: 49303 | AA66: 20 | AB66: 19 | AC66: 118085 | AD66: 1.02 | AE66: 282 | AF66: 0.0846 | AG66: 0.0685 | AH66: 3.17 | AI66: $2.38 - $3.96 | AJ66: B0D4215HCX | AK66: 0.0294 | AL66: 0.028 | AM66: 1450845800 | AN66: 0.0294 | AO66: 0.0125 | AP66: B0C2BJ26P7 | AQ66: 0.0258 | AR66: 0.028 | AS66: B078N1DBY9,B09P1DV7D8,1943200106,B0DKNXYDGR,B08P4HHSZT,B0DGCZXN2X,B0DL2BZWKD,B0BRNZ6FSW,B07FNGP1SV,B0D9VBWTYQ | AT66: 0.0138 | AU66: B07VHPFK5B,B07SRRQS5B,B0CFV5LZ3R,B0B7Z2MRWY,B082K8ZNQ1,B08R7685RH,B01IEJHJWK,B01DODMU9I,B07J63KGNN,B0BC6G9Q35
A67: =W67 -> 1735 | B67: =IF(A67="","",IF(A67<词盘!$B$2,"大词",IF(A67<词盘!$C$2,"中尾词","长尾词"))) -> 大词 | D67: =IF(M67="","",IF(OR(E67="/",E67=""),"无序",IF(COUNTIFS(E:E,E67)<4,"无序","有序"))) -> 无序 | F67: 品牌词 | H67: 了解或购买Bluetti品牌的电源产品 | I67: =P67/SUM(P:P) -> 0.0020010005 | J67: =AC67 -> 4667 | K67: =IFERROR(Z67*AH67,"") -> 6269.19 | M67: thermometer meat | N67: 温度计肉 | P67: 0.002 | Q67: 自然搜索词 | R67: 12911 | S67: 14 | T67: B005KCG6CE/B01F59K0KA/B0CRY9V6LL/B0BBR2RL6X/B017613C3C/B0BQ782XNW/B01IHHLB3W/B0BJK5W11R/B096K2L985/B07XXSYLL8/B09LSGPHT3/B00S93EQUK/B00GRFHXVQ/B0C7D27GV8 | U67: 249294 | V67: 6347 | W67: 1735 | X67: 0.2734 | Y67: 162836 | Z67: 3119 | AA67: 40 | AB67: 0 | AC67: 4667 | AD67: 1.36 | AE67: 67 | AF67: 0.3431 | AG67: 0.3119 | AH67: 2.01 | AI67: $1.47 - $2.36 | AJ67: B00S93EQUK | AK67: 0.1423 | AL67: 0.1398 | AM67: B07XXSYLL8 | AN67: 0.1046 | AO67: 0.0968 | AP67: B09LSGPHT3 | AQ67: 0.0962 | AR67: 0.0753 | AS67: B00S93EQUK,B07XXSYLL8,B07Y51PCW7,B09LSGPHT3,B017613C3C,B01IHHLB3W,B0C37DLHWW,B0BQ782XNW,B08K2G5Y78,B07H8WTFHW | AT67: 0.0199 | AU67: B074KWP2HJ,B08YZ633BY,B08PPVVK9M,B09TK2NDLV,B007LSKI1U,B07QJX17DY,B00SD9IE9O,B085RBQ24G,B0B3HV1322,B09FDRGP6T
A68: =W68 -> 206 | B68: =IF(A68="","",IF(A68<词盘!$B$2,"大词",IF(A68<词盘!$C$2,"中尾词","长尾词"))) -> 大词 | C68: 1 | D68: =IF(M68="","",IF(OR(E68="/",E68=""),"无序",IF(COUNTIFS(E:E,E68)<4,"无序","有序"))) -> 无序 | F68: 场景词 | G68: 便携式房屋场景 | H68: 了解或购买便携式房屋及电源产品 | I68: =P68/SUM(P:P) -> 0.0020010005 | J68: =AC68 -> 932 | K68: =IFERROR(Z68*AH68,"") -> 5357.43 | M68: meet thermometer for cooking | P68: 0.002 | Q68: 自然搜索词 | R68: 12715 | S68: 12 | T68: B0C7D27GV8/B005KCG6CE/B096K2L985/B01F59K0KA/B0CRY9V6LL/B0BBR2RL6X/B017613C3C/B0BQ782XNW/B01IHHLB3W/B07XXSYLL8/B09LSGPHT3/B00S93EQUK | U68: 275246 | V68: 6600 | W68: 206 | X68: 0.0313 | Y68: 157105 | Z68: 3133 | AA68: 5 | AB68: 0 | AC68: 932 | AD68: 7.08 | AE68: 4 | AF68: 0.3778 | AG68: 0.3979 | AH68: 1.71 | AI68: $1.49 - $2.22 | AJ68: B00S93EQUK | AK68: 0.2166 | AL68: 0.2755 | AM68: B07XXSYLL8 | AN68: 0.0829 | AO68: 0.051 | AP68: B0C37DLHWW | AQ68: 0.0783 | AR68: 0.0714 | AS68: B00S93EQUK,B07XXSYLL8,B07Y51PCW7,B0BQ782XNW,B017613C3C,B0C37DLHWW,B07MF18JHT,B01CI4ZYMO,B01IHHLB3W,B07H8WTFHW | AT68: 0.0257 | AU68: B07SRRQS5B,B0982TPZTW,B00DZKQLZ0,B07MXJ93K8,B0B7Z2MRWY,B0CFF2JG1N,B01DODMU9I,B082K8ZNQ1,B0CL9SXSBD,B07VHPFK5B
A69: =W69 -> 3773 | B69: =IF(A69="","",IF(A69<词盘!$B$2,"大词",IF(A69<词盘!$C$2,"中尾词","长尾词"))) -> 大词 | D69: =IF(M69="","",IF(OR(E69="/",E69=""),"无序",IF(COUNTIFS(E:E,E69)<4,"无序","有序"))) -> 无序 | F69: 品牌词 | H69: 了解或购买EcoFlow品牌的电源站产品 | I69: =P69/SUM(P:P) -> 0.0020010005 | J69: =AC69 -> 173321 | K69: =IFERROR(Z69*AH69,"") -> 20274 | M69: deals of the day clearance | N69: 当日清仓交易 | P69: 0.002 | Q69: SP广告词 | R69: 12582 | S69: 2 | T69: B09LSGPHT3/B00S93EQUK | U69: 3419 | V69: 164047 | W69: 3773 | X69: 0.023 | Y69: 3489226 | Z69: 65400 | AA69: 86 | AB69: 1 | AC69: 173321 | AD69: 0.95 | AE69: 862 | AF69: 0.1499 | AG69: 0.1011 | AH69: 0.31 | AI69: $0.23 - $0.38 | AJ69: B0BZ3YVPL8 | AK69: 0.0529 | AL69: 0.0305 | AM69: B0CFGYFCYL | AN69: 0.0515 | AO69: 0.0149 | AP69: B07BGLT25K | AQ69: 0.0455 | AR69: 0.0557 | AS69: B08PNYPL28,B09QKBBNCX,B0DQBTFT8T,B0DS5M3PNJ,B0B1DKN9HG,B0DR7WB5R2,B0DRGVPYMD,B0DSFRQY8W,B0DR45LZST,B0DQ9863N9 | AT69: 0.0571 | AU69: B00LB7REFK,B09YJ34W96,B07SRRQS5B,B07QHDRCZ3,B0CFV5LZ3R,B01IEJHJWK,B0BC6G9Q35,B07VHPFK5B,B01DODMU9I,B00GNTN1NK
A70: =W70 -> 2318 | B70: =IF(A70="","",IF(A70<词盘!$B$2,"大词",IF(A70<词盘!$C$2,"中尾词","长尾词"))) -> 大词 | C70: 3 | D70: =IF(M70="","",IF(OR(E70="/",E70=""),"无序",IF(COUNTIFS(E:E,E70)<4,"无序","有序"))) -> 无序 | F70: 功能词 | G70: 电池供电的电源插座 | H70: 寻找电池供电的电源插座 | I70: =P70/SUM(P:P) -> 0.0019009505 | J70: =AC70 -> 21665 | K70: =IFERROR(Z70*AH70,"") -> 13960.8 | M70: gadgets for men | N70: 男人的小玩意 | P70: 0.0019 | Q70: 自然搜索词 | R70: 12106 | S70: 4 | T70: B00S93EQUK/B01F59K0KA/B07XXSYLL8/B0C7D27GV8 | U70: 21476 | V70: 57102 | W70: 2318 | X70: 0.0406 | Y70: 1446755 | Z70: 23268 | AA70: 53 | AB70: 5 | AC70: 21665 | AD70: 2.64 | AE70: 334 | AF70: 0.1699 | AG70: 0.0706 | AH70: 0.6 | AI70: $0.44 - $0.75 | AJ70: B0BKZW27FY | AK70: 0.0845 | AL70: 0.0294 | AM70: B0D4215HCX | AN70: 0.0429 | AO70: 0.0412 | AP70: B0B7R76M8P | AQ70: 0.0425 | AR70: 0 | AS70: B0DHVG1VK7,B087G6TGJL,B0BKZW27FY,B07S1BNNYD,B0D9X2TH8Y,B0DFLZKMTG,B081T7N948,B0CFQYP7GX,B08GC1G4Y9,B0B7R76M8P
A71: =W71 -> 5578 | B71: =IF(A71="","",IF(A71<词盘!$B$2,"大词",IF(A71<词盘!$C$2,"中尾词","长尾词"))) -> 大词 | D71: =IF(M71="","",IF(OR(E71="/",E71=""),"无序",IF(COUNTIFS(E:E,E71)<4,"无序","有序"))) -> 无序 | F71: 场景词 | G71: 露营使用的便携发电机 | H71: 寻找露营用便携发电机 | I71: =P71/SUM(P:P) -> 0.0019009505 | J71: =AC71 -> 1974 | K71: =IFERROR(Z71*AH71,"") -> 29455.46 | M71: freezer thermometer | N71: 冰箱温度计 | P71: 0.0019 | Q71: 自然搜索词 | R71: 12081 | S71: 8 | T71: B017613C3C/B07XXSYLL8/B09LSGPHT3/B005KCG6CE/B00S93EQUK/B01IHHLB3W/B0BQ782XNW/B01F59K0KA | U71: 36222 | V71: 44170 | W71: 5578 | X71: 0.1263 | Y71: 986528 | Z71: 17638 | AA71: 127 | AB71: 38 | AC71: 1974 | AD71: 22.38 | AE71: 68 | AF71: 0.5326 | AG71: 0.5614 | AH71: 1.67 | AI71: $1.25 - $1.98 | AJ71: B089NLQ7SF | AK71: 0.3336 | AL71: 0.3663 | AM71: B07VVHZLLZ | AN71: 0.1201 | AO71: 0.1229 | AP71: B000BPE88E | AQ71: 0.0789 | AR71: 0.0722 | AS71: B089NLQ7SF,B07VVHZLLZ,B000BPE88E,B0D9Y94J61,B005KDEFNK,B07RN7Z2RT,B07XD68GX6,B0DBVF1XP9,B089YCPWBN,B0D9QCTNFY | AT71: 0.0229 | AU71: B0BV6ZR4GL,B0BPNMT5DM,B07C85S2PV,B07P8NXQF4,B09Y8L1716,B0895KJLRN,B0844HGHWR,B01AMO4R34,B0CN913Z4R,B0BXN2WJ3D
A72: =W72 -> 197 | B72: =IF(A72="","",IF(A72<词盘!$B$2,"大词",IF(A72<词盘!$C$2,"中尾词","长尾词"))) -> 大词 | D72: =IF(M72="","",IF(OR(E72="/",E72=""),"无序",IF(COUNTIFS(E:E,E72)<4,"无序","有序"))) -> 无序 | F72: 功能词 | G72: 太阳能面板发电机 | H72: 寻找太阳能面板发电机 | I72: =P72/SUM(P:P) -> 0.0019009505 | J72: =AC72 -> 133631 | K72: =IFERROR(Z72*AH72,"") -> 10779.56 | M72: kitchen tools | N72: 厨房工具 | P72: 0.0019 | Q72: SP广告词 | R72: 11924 | S72: 8 | T72: B00S93EQUK/B0BJK5W11R/B00GRFHXVQ/B0BBR2RL6X/B01F59K0KA/B01IHHLB3W/B07XXSYLL8/B0CRY9V6LL | U72: 20647 | V72: 63617 | W72: 197 | X72: 0.0031 | Y72: 1491943 | Z72: 24499 | AA72: 5 | AB72: 7 | AC72: 133631 | AD72: 0.48 | AE72: 496 | AF72: 0.114 | AG72: 0.0273 | AH72: 0.44 | AI72: $0.34 - $0.50 | AJ72: B08573DQ39 | AK72: 0.0465 | AL72: 0.0273 | AM72: B0DK8B7KHS | AN72: 0.0432 | AO72: 0 | AP72: B0DPCSTCLL | AQ72: 0.0243 | AR72: 0 | AS72: B0043P0IAK,B08CZDYNF7,B0D7ZVP7F8,B08573DQ39,B08N9Q24M9,B0D7ZTH1VP,B002CQTXBC,B07D15V7T3,B0D1XNX12M,B09Z65MVY5 | AT72: 0.0118 | AU72: B0B7BFMHNF,B08YZ633BY,B00I5H5Z1O,B007BF7BUY,B07QK9C9KT,B07CZDXDG8,B07GKVBQDG,B0BZ418TWS,B07SL2X217,B09XQQP3XD
A73: =W73 -> 34423 | B73: =IF(A73="","",IF(A73<词盘!$B$2,"大词",IF(A73<词盘!$C$2,"中尾词","长尾词"))) -> 中尾词 | D73: =IF(M73="","",IF(OR(E73="/",E73=""),"无序",IF(COUNTIFS(E:E,E73)<4,"无序","有序"))) -> 无序 | F73: 功能词 | G73: 太阳能发电机 | H73: 寻找太阳能发电机 | I73: =P73/SUM(P:P) -> 0.0019009505 | J73: =AC73 -> 12788 | K73: =IFERROR(Z73*AH73,"") -> 1928263.9 | M73: air fryer | N73: 空气炸锅 | P73: 0.0019 | Q73: SP广告词 | R73: 11872 | S73: 2 | T73: B0C7D27GV8/B00S93EQUK | U73: 45 | V73: 1881054 | W73: 34423 | X73: 0.0183 | Y73: 52446365 | Z73: 806805 | AA73: 781 | AB73: 75 | AC73: 12788 | AD73: 147.1 | AE73: 240 | AF73: 0.2101 | AG73: 0.1851 | AH73: 2.39 | AI73: $1.53 - $2.66 | AJ73: B0C33CHG99 | AK73: 0.1016 | AL73: 0.1076 | AM73: B0CNY1F31S | AN73: 0.0606 | AO73: 0.0572 | AP73: B08DL8WH9V | AQ73: 0.0479 | AR73: 0.0203 | AS73: B0CSZ7WBYW,B0DFBTC54P,B07FDJMC9Q,B0CS3V8M9H,B0B7C327LK,B0BYF8PT3L,B0C33CHG99,B0DFZR9BS5,B08DL8WH9V,B0CZDJXDXG | AT73: 0.0341 | AU73: B01N9LH5ZC,B0BQZBMXD4,B07SK6ZFLM,B07D3M5TTZ,B07CB5MSL4,B0924H4XB9,B07MYW7C3Z,B07CN6ZDVY,B07QK9C9KT,B00I5H5Z1O
A74: =W74 -> 1288 | B74: =IF(A74="","",IF(A74<词盘!$B$2,"大词",IF(A74<词盘!$C$2,"中尾词","长尾词"))) -> 大词 | C74: 2 | D74: =IF(M74="","",IF(OR(E74="/",E74=""),"无序",IF(COUNTIFS(E:E,E74)<4,"无序","有序"))) -> 有序 | E74: meat thermometer | F74: 功能词 | G74: 家庭电池备份 | H74: 寻找家庭电池备份产品 | I74: =P74/SUM(P:P) -> 0.0018009005 | J74: =AC74 -> 3290 | K74: =IFERROR(Z74*AH74,"") -> 4608.84 | M74: meat thermometer for grill | N74: 烤肉温度计 | P74: 0.0018 | Q74: 自然搜索词 | R74: 11733 | S74: 15 | T74: B005KCG6CE/B0C7D27GV8/B0CRY9V6LL/B01F59K0KA/B0BBR2RL6X/B0DDXWY41V/B017613C3C/B0BQ782XNW/B0BJK5W11R/B01IHHLB3W/B07XXSYLL8/B00GRFHXVQ/B09LSGPHT3/B096K2L985/B00S93EQUK | U74: 286364 | V74: 5166 | W74: 1288 | X74: 0.2495 | Y74: 129387 | Z74: 2316 | AA74: 30 | AB74: 13 | AC74: 3290 | AD74: 1.57 | AE74: 98 | AF74: 0.4163 | AG74: 0.4147 | AH74: 1.99 | AI74: $1.53 - $2.50 | AJ74: B00S93EQUK | AK74: 0.201 | AL74: 0.2439 | AM74: B09LSGPHT3 | AN74: 0.1244 | AO74: 0.122 | AP74: B017613C3C | AQ74: 0.0909 | AR74: 0.0488 | AS74: B00S93EQUK,B07XXSYLL8,B017613C3C,B08K2G5Y78,B09LSGPHT3,B07Y51PCW7,B0BQ782XNW,B0DG5KDHS8,B07H8WTFHW,B08KZR4F23 | AT74: 0.0033 | AU74: B0CL9YMRD5,B07Z13H4TP,B08YZ633BY,B007BF7BUY,B07QK9C9KT,B07MYW7C3Z,B07CZDXDG8,B07CN6ZDVY,B0BN9DD956,B07KPYMMG6
A75: =W75 -> 2128 | B75: =IF(A75="","",IF(A75<词盘!$B$2,"大词",IF(A75<词盘!$C$2,"中尾词","长尾词"))) -> 大词 | D75: =IF(M75="","",IF(OR(E75="/",E75=""),"无序",IF(COUNTIFS(E:E,E75)<4,"无序","有序"))) -> 无序 | F75: 功能词 | G75: 太阳能发电 | H75: 寻找太阳能电力相关产品 | I75: =P75/SUM(P:P) -> 0.0018009005 | J75: =AC75 -> 7708 | K75: =IFERROR(Z75*AH75,"") -> 22466.08 | M75: water thermometer | N75: 水温计 | P75: 0.0018 | Q75: 自然搜索词 | R75: 11596 | S75: 12 | T75: B07XXSYLL8/B01F59K0KA/B0BQ782XNW/B00GRFHXVQ/B09LSGPHT3/B00S93EQUK/B01IHHLB3W/B0CRY9V6LL/B0BBR2RL6X/B017613C3C/B096K2L985/B005KCG6CE | U75: 71554 | V75: 24247 | W75: 2128 | X75: 0.0878 | Y75: 513139 | Z75: 10801 | AA75: 49 | AB75: 26 | AC75: 7708 | AD75: 3.15 | AE75: 196 | AF75: 0.4342 | AG75: 0.4334 | AH75: 2.08 | AI75: $1.32 - $2.33 | AJ75: B087XBXFM6 | AK75: 0.2937 | AL75: 0.3004 | AM75: B0C59MQ1K3 | AN75: 0.0741 | AO75: 0.076 | AP75: B0B1TXXX47 | AQ75: 0.0664 | AR75: 0.057 | AS75: B0C59MQ1K3,B087XBXFM6,B073GGVN3Q,B0B1TXXX47,B09MTX71VX,B0D9Y89Z36,B0DBZ98LLJ,B01N1QQ4EH,B0CQY4ZTHD,B0DNJCQPHB | AT75: 0.0493 | AU75: B0C1GQ54QD,B0BVR8F5W3,B0CZ6FKCJ8,B0BXP9NT3S,B0C3YLYXYJ,B0C4GRKZ1M,B09964WTF5,B0CPTWVDW1,B0CK6QRX79,B0BWTJVT52
A76: =W76 -> 1156 | B76: =IF(A76="","",IF(A76<词盘!$B$2,"大词",IF(A76<词盘!$C$2,"中尾词","长尾词"))) -> 大词 | C76: 1 | D76: =IF(M76="","",IF(OR(E76="/",E76=""),"无序",IF(COUNTIFS(E:E,E76)<4,"无序","有序"))) -> 有序 | E76: meat thermometer | F76: 品牌词 | H76: 了解或购买Anker品牌的电源产品 | I76: =P76/SUM(P:P) -> 0.0018009005 | J76: =AC76 -> 817 | K76: =IFERROR(Z76*AH76,"") -> 5720.75 | M76: thermopro meat thermometer | N76: Thermopro 肉类温度计 | P76: 0.0018 | Q76: 自然搜索词 | R76: 11595 | S76: 14 | T76: B0BJK5W11R/B096K2L985/B0CRY9V6LL/B0BBR2RL6X/B0C7D27GV8/B017613C3C/B01IHHLB3W/B07XXSYLL8/B09LSGPHT3/B01F59K0KA/B00S93EQUK/B0BQ782XNW/B005KCG6CE/B00GRFHXVQ | U76: 253711 | V76: 6903 | W76: 1156 | X76: 0.1676 | Y76: 145746 | Z76: 3269 | AA76: 27 | AB76: 1 | AC76: 817 | AD76: 8.45 | AE76: 39 | AF76: 0.4213 | AG76: 0.481 | AH76: 1.75 | AI76: $1.32 - $2.20 | AJ76: B07XXSYLL8 | AK76: 0.2894 | AL76: 0.3924 | AM76: B08KZR4F23 | AN76: 0.0681 | AO76: 0.0253 | AP76: B017613C3C | AQ76: 0.0638 | AR76: 0.0633 | AS76: B07XXSYLL8,B017613C3C,B08K2G5Y78,B07Y51PCW7,B0BMLDL5GM,B01IHHLB3W,B0B48NL6L8,B0BBR2RL6X,B01GE77QT0,B07477NMF4 | AT76: 0.0257 | AU76: B0BV6ZR4GL,B07P8NXQF4,B0BPNMT5DM,B0CN913Z4R,B0844HGHWR,B07C85S2PV,B09Y8L1716,B0CC54BQVY,B09PDHVJT9,B0BXN2WJ3D
A77: =W77 -> 2095 | B77: =IF(A77="","",IF(A77<词盘!$B$2,"大词",IF(A77<词盘!$C$2,"中尾词","长尾词"))) -> 大词 | D77: =IF(M77="","",IF(OR(E77="/",E77=""),"无序",IF(COUNTIFS(E:E,E77)<4,"无序","有序"))) -> 无序 | F77: 功能词 | G77: 太阳能 | H77: 寻找太阳能相关产品 | I77: =P77/SUM(P:P) -> 0.0018009005 | J77: =AC77 -> 6271 | K77: =IFERROR(Z77*AH77,"") -> 6197.2 | M77: air fryer accessories | N77: 空气炸锅配件 | P77: 0.0018 | Q77: 自然搜索词/HR推荐词/SP广告词 | R77: 11461 | S77: 3 | T77: B00S93EQUK/B0C7D27GV8/B01F59K0KA | U77: 22368 | V77: 69380 | W77: 2095 | X77: 0.0302 | Y77: 1752690 | Z77: 30986 | AA77: 48 | AB77: 30 | AC77: 6271 | AD77: 11.06 | AE77: 289 | AF77: 0.2017 | AG77: 0.1117 | AH77: 0.2 | AI77: $0.18 - $0.23 | AJ77: B0BKFRZB31 | AK77: 0.0849 | AL77: 0.0508 | AM77: B08H7RL4GN | AN77: 0.0597 | AO77: 0.0533 | AP77: B07QHSZGXC | AQ77: 0.0571 | AR77: 0.0076 | AS77: B09D2QQZKG,B0C6Y8NYK1,B07QHSZGXC,B0BKFRZB31,B0B6PLG6G2,B0BKR66QGC,B08H7RL4GN,B09NKRWXPC,B0DB8JNQ99,B07YVMXFV9 | AT77: 0.0264 | AU77: B000GCS004,B08YZ633BY,B07QK9C9KT,B00I5H5Z1O,B07CZDXDG8,B09NXVJ25C,B08QJ53Y5G,B07SL2X217,B0B7BFMHNF,B09WDQ3G2W
A78: =W78 -> 1590 | B78: =IF(A78="","",IF(A78<词盘!$B$2,"大词",IF(A78<词盘!$C$2,"中尾词","长尾词"))) -> 大词 | C78: 1 | D78: =IF(M78="","",IF(OR(E78="/",E78=""),"无序",IF(COUNTIFS(E:E,E78)<4,"无序","有序"))) -> 有序 | E78: meat thermometer | F78: 功能词 | G78: 便携电池发电机 | H78: 寻找便携电池发电机 | I78: =P78/SUM(P:P) -> 0.0018009005 | J78: =AC78 -> 1448 | K78: =IFERROR(Z78*AH78,"") -> 4200.36 | M78: instant meat thermometer digital | N78: 即时肉类温度计数字 | P78: 0.0018 | Q78: 自然搜索词/SP广告词 | R78: 11288 | S78: 12 | T78: B0BJK5W11R/B00GRFHXVQ/B096K2L985/B01F59K0KA/B0BBR2RL6X/B017613C3C/B0BQ782XNW/B01IHHLB3W/B07XXSYLL8/B09LSGPHT3/B0CRY9V6LL/B00S93EQUK | U78: 289061 | V78: 6361 | W78: 1590 | X78: 0.25 | Y78: 164022 | Z78: 2958 | AA78: 37 | AB78: 0 | AC78: 1448 | AD78: 4.39 | AE78: 17 | AF78: 0.5121 | AG78: 0.5455 | AH78: 1.42 | AI78: $0.69 - $2.05 | AJ78: B00S93EQUK | AK78: 0.285 | AL78: 0.3364 | AM78: B09C32DYV1 | AN78: 0.1208 | AO78: 0.0818 | AP78: B09LSGPHT3 | AQ78: 0.1063 | AR78: 0.1273 | AS78: B07XXSYLL8,B00S93EQUK,B07Y51PCW7,B0DJY2PWTY,B09LSGPHT3,B0DHZTCNR5,B0DG5LP1VK,B01IHHLB3W,B0BQ782XNW,B0C37DLHWW | AT78: 0.0273 | AU78: B07NS8BF7X,B0CNRFNRB7,B0BWHG8PMV,B004MKMHXC,B0BNMVB18C,B0CRQJSL1P,B0BZTS57Y7,B09YY9DLCF,B0CJB7C4G7,B08XXYNRJ1
A79: =W79 -> 925 | B79: =IF(A79="","",IF(A79<词盘!$B$2,"大词",IF(A79<词盘!$C$2,"中尾词","长尾词"))) -> 大词 | D79: =IF(M79="","",IF(OR(E79="/",E79=""),"无序",IF(COUNTIFS(E:E,E79)<4,"无序","有序"))) -> 有序 | E79: meat thermometer | F79: 品牌词 | H79: 了解或购买Anker太阳能发电机 | I79: =P79/SUM(P:P) -> 0.0017008504 | J79: =AC79 -> 725 | K79: =IFERROR(Z79*AH79,"") -> 33791.67 | M79: bluetooth meat thermometer | N79: 蓝牙肉类温度计 | P79: 0.0017 | Q79: 自然搜索词 | R79: 11057 | S79: 13 | T79: B0C7D27GV8/B0CRY9V6LL/B017613C3C/B07XXSYLL8/B096K2L985/B0BBR2RL6X/B01IHHLB3W/B09LSGPHT3/B01F59K0KA/B0BJK5W11R/B00S93EQUK/B005KCG6CE/B0BQ782XNW | U79: 85753 | V79: 24428 | W79: 925 | X79: 0.0379 | Y79: 651883 | Z79: 10527 | AA79: 22 | AB79: 29 | AC79: 725 | AD79: 33.69 | AE79: 141 | AF79: 0.3238 | AG79: 0.2867 | AH79: 3.21 | AI79: $2.29 - $4.46 | AJ79: B0D5M9RW7C | AK79: 0.1301 | AL79: 0.1397 | AM79: B08K2G5Y78 | AN79: 0.1014 | AO79: 0.0735 | AP79: B0DFNR55LB | AQ79: 0.0923 | AR79: 0.0735 | AS79: B08K2G5Y78,B0D2LQGJ2V,B0DPCHVMNP,B0B48NL6L8,B08317TDP1,B0DP4N83B8,B0BMLDL5GM,B07H8WTFHW,B0D5M9RW7C,B076B36HF9 | AT79: 0.0299 | AU79: B07SRRQS5B,B0B8V6Y2X8,B07HY3S811,B0982TPZTW,B0CL9SXSBD,B01DODMU9I,B00DZKQLZ0,B0B7Z2MRWY,B00LB7REFK,B0BZCMDZNS
A80: =W80 -> 1591 | B80: =IF(A80="","",IF(A80<词盘!$B$2,"大词",IF(A80<词盘!$C$2,"中尾词","长尾词"))) -> 大词 | C80: 1 | D80: =IF(M80="","",IF(OR(E80="/",E80=""),"无序",IF(COUNTIFS(E:E,E80)<4,"无序","有序"))) -> 无序 | F80: 属性词 | G80: CPAP电池 | H80: 寻找CPAP电池 | I80: =P80/SUM(P:P) -> 0.0017008504 | J80: =AC80 -> 1656 | K80: =IFERROR(Z80*AH80,"") -> 5795.46 | M80: baking thermometer | N80: 烘烤温度计 | P80: 0.0017 | Q80: 自然搜索词 | R80: 10932 | S80: 15 | T80: B0BJK5W11R/B005KCG6CE/B0DDXWY41V/B01F59K0KA/B017613C3C/B01IHHLB3W/B0BQ782XNW/B07XXSYLL8/B096K2L985/B09LSGPHT3/B0CRY9V6LL/B0BBR2RL6X/B00S93EQUK/B0C7D27GV8/B00GRFHXVQ | U80: 270692 | V80: 6916 | W80: 1591 | X80: 0.2301 | Y80: 139424 | Z80: 2927 | AA80: 37 | AB80: 0 | AC80: 1656 | AD80: 4.18 | AE80: 31 | AF80: 0.4318 | AG80: 0.3593 | AH80: 1.98 | AI80: $1.65 - $2.45 | AJ80: B09MTX71VX | AK80: 0.2455 | AL80: 0.2656 | AM80: B00S93EQUK | AN80: 0.1045 | AO80: 0.0781 | AP80: B0B71HFH9K | AQ80: 0.0818 | AR80: 0.0156 | AS80: B09MTX71VX,B08RWPPD8J,B01IHHLB3W,B0B71HFH9K,B07XXSYLL8,B00S93EQUK,B017613C3C,B01LET2BFC,B07Y51PCW7,B00004XSC9 | AT80: 0.0625 | AU80: B0CPTVJS6R,B0CS2XG7FQ,B0D1KVWCNX,B0CSYRWXCF,B0CG5WF87G,B0CTPXW3YR,B0CNSSFB26,B0CH3SL3HB,B0CN36LVRS,B075B48B3B
A81: =W81 -> 4028 | B81: =IF(A81="","",IF(A81<词盘!$B$2,"大词",IF(A81<词盘!$C$2,"中尾词","长尾词"))) -> 大词 | D81: =IF(M81="","",IF(OR(E81="/",E81=""),"无序",IF(COUNTIFS(E:E,E81)<4,"无序","有序"))) -> 无序 | F81: 场景词 | G81: 停电应急用品 | H81: 寻找停电应急电源用品 | I81: =P81/SUM(P:P) -> 0.0017008504 | J81: =AC81 -> 20334 | K81: =IFERROR(Z81*AH81,"") -> 15185.92 | M81: deals of the day lightning deals | N81: 当天的交易闪电交易 | P81: 0.0017 | Q81: SP广告词 | R81: 10929 | S81: 5 | T81: B09LSGPHT3/B00S93EQUK/B017613C3C/B01IHHLB3W/B07XXSYLL8 | U81: 22695 | V81: 49186 | W81: 4028 | X81: 0.0819 | Y81: 1331296 | Z81: 23728 | AA81: 92 | AB81: 0 | AC81: 20334 | AD81: 2.42 | AE81: 558 | AF81: 0.0745 | AG81: 0.074 | AH81: 0.64 | AI81: $0.49 - $0.89 | AJ81: B0BZ7S8QJW | AK81: 0.0282 | AL81: 0.045 | AM81: B09H799G1B | AN81: 0.0268 | AO81: 0.0129 | AP81: B07T9C5CQR | AQ81: 0.0195 | AR81: 0.0161 | AS81: B09QKBBNCX,B09H799G1B,B08PNYPL28,B0CN6GHGD6,B09KT1N3R4,B09LSGPHT3,B0169P8TGG,B079VM4558,B00551OPJG,B0CBLNBS35 | AT81: 0.0117 | AU81: B07SRRQS5B,B0CQ79FH3S,B00DZKQLZ0,B00LB7REFK,B01DODMU9I,B07HY3S811,B01IEJHJWK,B0BC6G9Q35,B082K8ZNQ1,B0B8V6Y2X8
A82: =W82 -> 1245 | B82: =IF(A82="","",IF(A82<词盘!$B$2,"大词",IF(A82<词盘!$C$2,"中尾词","长尾词"))) -> 大词 | D82: =IF(M82="","",IF(OR(E82="/",E82=""),"无序",IF(COUNTIFS(E:E,E82)<4,"无序","有序"))) -> 无序 | F82: 品牌词 | H82: 了解或购买EcoFlow Wave 2产品 | I82: =P82/SUM(P:P) -> 0.0017008504 | J82: =AC82 -> 2428 | K82: =IFERROR(Z82*AH82,"") -> 5989.65 | M82: meat probe thermometer | N82: 肉探针温度计 | P82: 0.0017 | Q82: 自然搜索词 | R82: 10681 | S82: 14 | T82: B005KCG6CE/B0CRY9V6LL/B017613C3C/B0BJK5W11R/B01IHHLB3W/B0BQ782XNW/B07XXSYLL8/B00GRFHXVQ/B09LSGPHT3/B01F59K0KA/B0BBR2RL6X/B00S93EQUK/B096K2L985/B0C7D27GV8 | U82: 266295 | V82: 6804 | W82: 1245 | X82: 0.1831 | Y82: 177072 | Z82: 2735 | AA82: 29 | AB82: 0 | AC82: 2428 | AD82: 2.8 | AE82: 103 | AF82: 0.2858 | AG82: 0.3583 | AH82: 2.19 | AI82: $1.63 - $2.74 | AJ82: B00S93EQUK | AK82: 0.1563 | AL82: 0.2687 | AM82: B017613C3C | AN82: 0.0759 | AO82: 0.0448 | AP82: B07XXSYLL8 | AQ82: 0.0536 | AR82: 0.0448 | AS82: B017613C3C,B07XXSYLL8,B00S93EQUK,B07477NMF4,B08K2G5Y78,B07Y51PCW7,B08KZR4F23,B0D5M9RW7C,B07H8WTFHW,B0B48NL6L8 | AT82: 0.036 | AU82: B09PGQD7LS,B07DMSLS9B,B08JCYB8CL,B00DHINB8K,B09LLYP2XL,B0BXLC3K69,B0BV6ZR4GL,B0BSTWKSDX,B0CKQ8TZW9,B0BZLV1913
A83: =W83 -> 6982 | B83: =IF(A83="","",IF(A83<词盘!$B$2,"大词",IF(A83<词盘!$C$2,"中尾词","长尾词"))) -> 大词 | D83: =IF(M83="","",IF(OR(E83="/",E83=""),"无序",IF(COUNTIFS(E:E,E83)<4,"无序","有序"))) -> 无序 | F83: 品名词 | H83: 寻找1000w电源站 | I83: =P83/SUM(P:P) -> 0.0017008504 | J83: =AC83 -> 206746 | K83: =IFERROR(Z83*AH83,"") -> 16596.09 | M83: men's accessories | N83: 男装配件 | P83: 0.0017 | Q83: 自然搜索词 | R83: 10557 | S83: 1 | T83: B00S93EQUK | U83: 23652 | V83: 47663 | W83: 6982 | X83: 0.1465 | Y83: 982225 | Z83: 20489 | AA83: 159 | AB83: 0 | AC83: 206746 | AD83: 0.23 | AE83: 150 | AF83: 0.1792 | AG83: 0 | AH83: 0.81 | AI83: $0.62 - $1.32 | AJ83: B0DKBSGPZT | AK83: 0.0646 | AL83: 0 | AM83: B0DTGP83BY | AN83: 0.0575 | AO83: 0 | AP83: B0DJ6LJ8Y5 | AQ83: 0.0571 | AR83: 0 | AS83: B0D4215HCX,B002G9UDYG,B07GGR1N4Y,B09M3Z63QP,B07QNS3HZJ,B0BNX13NX4,B07B2T345D,B07S1BNNYD,B0BNWZRL4K,B09N1B6LL3 | AT83: 0.022 | AU83: B0CFV5LZ3R,B07VHPFK5B,B0758TY861,B08R7685RH,B0CHFD3KM7,B07SRRQS5B,B0CL6CXMGZ,B0CNKL4ZT1,B0BC6G9Q35,B01IEJHJWK
A84: =W84 -> 488 | B84: =IF(A84="","",IF(A84<词盘!$B$2,"大词",IF(A84<词盘!$C$2,"中尾词","长尾词"))) -> 大词 | C84: 2 | D84: =IF(M84="","",IF(OR(E84="/",E84=""),"无序",IF(COUNTIFS(E:E,E84)<4,"无序","有序"))) -> 无序 | F84: 品牌词 | H84: 了解或购买Anker电池包 | I84: =P84/SUM(P:P) -> 0.0017008504 | J84: =AC84 -> 3115 | K84: =IFERROR(Z84*AH84,"") -> 8219.73 | M84: bbq thermometer for grill | N84: 烤架烧烤温度计 | O84: Y | P84: 0.0017 | Q84: 自然搜索词/AC推荐词/SP广告词 | R84: 10497 | S84: 10 | T84: B0C7D27GV8/B0CRY9V6LL/B017613C3C/B0BQ782XNW/B01IHHLB3W/B07XXSYLL8/B09LSGPHT3/B00S93EQUK/B096K2L985/B0BBR2RL6X | U84: 220122 | V84: 5839 | W84: 488 | X84: 0.0837 | Y84: 162312 | Z84: 2643 | AA84: 12 | AB84: 1 | AC84: 3115 | AD84: 1.87 | AE84: 36 | AF84: 0.2676 | AG84: 0.2391 | AH84: 3.11 | AI84: $2.66 - $3.52 | AJ84: B00S93EQUK | AK84: 0.1152 | AL84: 0.1522 | AM84: B01LZI4IA3 | AN84: 0.0855 | AO84: 0.0217 | AP84: B08K2G5Y78 | AQ84: 0.0669 | AR84: 0.0652 | AS84: B00S93EQUK,B08KZR4F23,B08K2G5Y78,B07XXSYLL8,B08317TDP1,B017613C3C,B09LSGPHT3,B0BQ782XNW,B08BXCGD76,B07H8WTFHW | AT84: 0.0273 | AU84: B09J4BZTML,B07QSFJ8S2,B0CM336GBC,B0C141Q82D,B0C6SWK5YJ,B076H8GBBK,B07XGMMXY2,B0B776Y6JQ,B0C7G6RB8T,B072Q9QG68
A85: =W85 -> 671 | B85: =IF(A85="","",IF(A85<词盘!$B$2,"大词",IF(A85<词盘!$C$2,"中尾词","长尾词"))) -> 大词 | C85: 3 | D85: =IF(M85="","",IF(OR(E85="/",E85=""),"无序",IF(COUNTIFS(E:E,E85)<4,"无序","有序"))) -> 无序 | F85: 品名词 | H85: 寻找电源站 | I85: =P85/SUM(P:P) -> 0.0016008004 | J85: =AC85 -> 25743 | K85: =IFERROR(Z85*AH85,"") -> 5199.38 | M85: thermometers | N85: 温度计 | P85: 0.0016 | Q85: 自然搜索词 | R85: 10429 | S85: 10 | T85: B0BQ782XNW/B01IHHLB3W/B005KCG6CE/B07XXSYLL8/B09LSGPHT3/B0BBR2RL6X/B017613C3C/B00S93EQUK/B01F59K0KA/B0CRY9V6LL | U85: 169238 | V85: 12186 | W85: 671 | X85: 0.0551 | Y85: 282588 | Z85: 5842 | AA85: 16 | AB85: 2 | AC85: 25743 | AD85: 0.47 | AE85: 66 | AF85: 0.408 | AG85: 0.437 | AH85: 0.89 | AI85: $0.52 - $1.12 | AJ85: B0824XNJSW | AK85: 0.2385 | AL85: 0.2185 | AM85: B08B8BDG42 | AN85: 0.1178 | AO85: 0.1765 | AP85: B0CTCPQ6N9 | AQ85: 0.0517 | AR85: 0.042 | AS85: B0824XNJSW,B08B8BDG42,B0CGRB23YM,B08B7V2RG3,B0BQ782XNW,B0C82Z3479,B075QQ8VZW,B08MT3D361,B07F4JJH1Z,B00MUK6M82 | AT85: 0.0288 | AU85: B074KWP2HJ,B0B41MYSGP,B07HCNM7KQ,B007TIVLQ8,B07LCH3XN7,B00TF7ZZM2,B0C4KMYQXD,B09FDRGP6T,B08PPVVK9M,B08YZ633BY
A86: =W86 -> 575 | B86: =IF(A86="","",IF(A86<词盘!$B$2,"大词",IF(A86<词盘!$C$2,"中尾词","长尾词"))) -> 大词 | D86: =IF(M86="","",IF(OR(E86="/",E86=""),"无序",IF(COUNTIFS(E:E,E86)<4,"无序","有序"))) -> 无序 | F86: 品牌词 | H86: 了解或购买EcoFlow Delta Pro Ultra产品 | I86: =P86/SUM(P:P) -> 0.0016008004 | J86: =AC86 -> 126 | K86: =IFERROR(Z86*AH86,"") -> 56972.22 | M86: chef iq | N86: 厨师智商 | P86: 0.0016 | Q86: SP广告词 | R86: 10017 | S86: 9 | T86: B0DGXKNV6Y/B0C7D27GV8/B0CRY9V6LL/B0BQ782XNW/B01F59K0KA/B017613C3C/B0BBR2RL6X/B00S93EQUK/B01IHHLB3W | U86: 96600 | V86: 21972 | W86: 575 | X86: 0.0262 | Y86: 628747 | Z86: 9294 | AA86: 14 | AB86: 13 | AC86: 126 | AD86: 174.38 | AE86: 29 | AF86: 0.8071 | AG86: 0.7586 | AH86: 6.13 | AI86: $3.77 - $7.75 | AJ86: B0C7JNJW2N | AK86: 0.4179 | AL86: 0.4368 | AM86: B0C7D27GV8 | AN86: 0.2115 | AO86: 0.2069 | AP86: B0863JB424 | AQ86: 0.1777 | AR86: 0.1149 | AS86: B0C7D27GV8,B0C7JNJW2N,B0B52JJWXJ,B0CWMM82RR,B0863JB424,B0D2LQGJ2V,B0C7JM4Y9G,B0D1TMFTPN,B0BMLDL5GM,B0D1GGM2HZ | AT86: 0.0404 | AU86: B07GMJB5ZZ,B079X4S4DQ,B088DQDFL1,B01DODMU9I,B07SRRQS5B,B09NFRC4LM,B0BWP19CC9,B079K52326,B0CXTBZR2H,B0BC6G9Q35
A87: =W87 -> 436 | B87: =IF(A87="","",IF(A87<词盘!$B$2,"大词",IF(A87<词盘!$C$2,"中尾词","长尾词"))) -> 大词 | C87: 1 | D87: =IF(M87="","",IF(OR(E87="/",E87=""),"无序",IF(COUNTIFS(E:E,E87)<4,"无序","有序"))) -> 无序 | F87: 品名词 | H87: 寻找便携式发电机 | I87: =P87/SUM(P:P) -> 0.0016008004 | J87: =AC87 -> 2377 | K87: =IFERROR(Z87*AH87,"") -> 9028.41 | M87: smoker thermometer | N87: 烟熏炉温度计 | P87: 0.0016 | Q87: 自然搜索词 | R87: 9990 | S87: 14 | T87: B0C7D27GV8/B0CRY9V6LL/B017613C3C/B0BJK5W11R/B01IHHLB3W/B00S93EQUK/B0BQ782XNW/B09LSGPHT3/B096K2L985/B00GRFHXVQ/B0BBR2RL6X/B07XXSYLL8/B01F59K0KA/B0DDXWY41V | U87: 190549 | V87: 7890 | W87: 436 | X87: 0.0553 | Y87: 173448 | Z87: 3513 | AA87: 10 | AB87: 9 | AC87: 2377 | AD87: 3.32 | AE87: 132 | AF87: 0.2839 | AG87: 0.2529 | AH87: 2.57 | AI87: $2.29 - $2.96 | AJ87: B07CWN9QDB | AK87: 0.1194 | AL87: 0.0805 | AM87: B08317TDP1 | AN87: 0.0903 | AO87: 0.1149 | AP87: B08BXCGD76 | AQ87: 0.0742 | AR87: 0.0575 | AS87: B08317TDP1,B08KZR4F23,B08K2G5Y78,B08BXCGD76,B07CWN9QDB,B07477NMF4,B07Z7HDNC4,B081DL5PG1,B0CRY9V6LL,B01GE77QT0 | AT87: 0.0884 | AU87: B0D1KDXFZJ,B0CXTBZR2H,B09NFQKBZY,B0CQ79FH3S,B0D1XL2B6P,B07WLPBPKM,B0CZRC9F86,B0CZNXB4KN,B0CWH7VRZV,B01DODMU9I
A88: =W88 -> 1056 | B88: =IF(A88="","",IF(A88<词盘!$B$2,"大词",IF(A88<词盘!$C$2,"中尾词","长尾词"))) -> 大词 | D88: =IF(M88="","",IF(OR(E88="/",E88=""),"无序",IF(COUNTIFS(E:E,E88)<4,"无序","有序"))) -> 无序 | F88: 品牌词 | H88: 了解或购买Bluetti AC180电源产品 | I88: =P88/SUM(P:P) -> 0.0016008004 | J88: =AC88 -> 918 | K88: =IFERROR(Z88*AH88,"") -> 7922.68 | M88: thermopro thermometer | N88: 温度计 | P88: 0.0016 | Q88: 自然搜索词 | R88: 9878 | S88: 11 | T88: B0BJK5W11R/B096K2L985/B0CRY9V6LL/B0BBR2RL6X/B017613C3C/B01IHHLB3W/B07XXSYLL8/B01F59K0KA/B09LSGPHT3/B00S93EQUK/B0BQ782XNW | U88: 221669 | V88: 13010 | W88: 1056 | X88: 0.0812 | Y88: 307184 | Z88: 6494 | AA88: 24 | AB88: 0 | AC88: 918 | AD88: 14.17 | AE88: 3 | AF88: 0.4142 | AG88: 0.3809 | AH88: 1.22 | AI88: $0.92 - $1.52 | AJ88: B01H1R0K68 | AK88: 0.1679 | AL88: 0.119 | AM88: B07XXSYLL8 | AN88: 0.1642 | AO88: 0.2143 | AP88: B07WCR5Y4B | AQ88: 0.0821 | AR88: 0.0476 | AS88: B07R3YC1BC,B07XXSYLL8,B01H1R0K68,B086PC5962,B09NL17MBR,B07WCR5Y4B,B06XKH666P,B07Y51PCW7,B08K2G5Y78,B0B48NL6L8 | AT88: 0.0584 | AU88: B00LB7REFK,B07SRRQS5B,B00L4Z0T2Y,B07QHDRCZ3,B0BC6G9Q35,B09YJ34W96,B082K8ZNQ1,B0CFV5LZ3R,B07VHPFK5B,B0BNMVB18C
A89: =W89 -> 1118 | B89: =IF(A89="","",IF(A89<词盘!$B$2,"大词",IF(A89<词盘!$C$2,"中尾词","长尾词"))) -> 大词 | C89: 1 | D89: =IF(M89="","",IF(OR(E89="/",E89=""),"无序",IF(COUNTIFS(E:E,E89)<4,"无序","有序"))) -> 无序 | F89: 功能词 | G89: 太阳能发电机 | H89: 寻找太阳能发电机 | I89: =P89/SUM(P:P) -> 0.0016008004 | J89: =AC89 -> 38613 | K89: =IFERROR(Z89*AH89,"") -> 39938.58 | M89: bbq accessories | N89: 烧烤配件 | O89: Y | P89: 0.0016 | Q89: 自然搜索词/AC推荐词 | R89: 9865 | S89: 7 | T89: B00S93EQUK/B07XXSYLL8/B01F59K0KA/B01IHHLB3W/B0BBR2RL6X/B0BQ782XNW/B0C7D27GV8 | U89: 29150 | V89: 34751 | W89: 1118 | X89: 0.0322 | Y89: 960895 | Z89: 15786 | AA89: 26 | AB89: 9 | AC89: 38613 | AD89: 0.9 | AE89: 196 | AF89: 0.1719 | AG89: 0.0929 | AH89: 2.53 | AI89: $1.36 - $3.02 | AJ89: B079J4KT8H | AK89: 0.0652 | AL89: 0.0464 | AM89: B0C6X6KX2H | AN89: 0.063 | AO89: 0.0186 | AP89: B0CGX3ZGBK | AQ89: 0.0437 | AR89: 0.0279 | AS89: B0D8SQDXWQ,B00S93EQUK,B0C6X6KX2H,B00KA2Y1OY,B0DB8V26PB,B0DBHW74LN,B0DCFRFQQP,B0CCTSYJBF,B00NE5IF3W,B0D8KSDBY5 | AT89: 0.1 | AU89: B07SRRQS5B,B082K8ZNQ1,B01DODMU9I,B0BPNMT5DM,B0BC6G9Q35,B0CZDB93YR,B01IEJHJWK,B00L4Z0T2Y,B07VHPFK5B,B00LB7REFK
A90: =W90 -> 770 | B90: =IF(A90="","",IF(A90<词盘!$B$2,"大词",IF(A90<词盘!$C$2,"中尾词","长尾词"))) -> 大词 | C90: 1 | D90: =IF(M90="","",IF(OR(E90="/",E90=""),"无序",IF(COUNTIFS(E:E,E90)<4,"无序","有序"))) -> 无序 | I90: =P90/SUM(P:P) -> 0.0015007504 | J90: =AC90 -> 201 | K90: =IFERROR(Z90*AH90,"") -> 5415.93 | M90: therm pro | N90: 热专业 | P90: 0.0015 | Q90: 自然搜索词 | R90: 9805 | S90: 9 | T90: B0BJK5W11R/B096K2L985/B0CRY9V6LL/B0BBR2RL6X/B017613C3C/B01IHHLB3W/B07XXSYLL8/B01F59K0KA/B0C7D27GV8 | U90: 216645 | V90: 9757 | W90: 770 | X90: 0.079 | Y90: 282776 | Z90: 4629 | AA90: 18 | AB90: 0 | AC90: 201 | AD90: 48.54 | AE90: 15 | AF90: 0.4051 | AG90: 0.3781 | AH90: 1.17 | AI90: $0.88 - $1.48 | AJ90: B07R3YC1BC | AK90: 0.1679 | AL90: 0.0854 | AM90: B07XXSYLL8 | AN90: 0.1533 | AO90: 0.1951 | AP90: B06XKH666P | AQ90: 0.0839 | AR90: 0.0976 | AS90: B01H1R0K68,B07XXSYLL8,B07R3YC1BC,B017613C3C,B06XKH666P,B07WCR5Y4B,B01IHHLB3W,B08KZR4F23,B09NL17MBR,B08K2G5Y78 | AT90: 0.0219 | AU90: B07SRRQS5B,B0B8V6Y2X8,B0C1GQ54QD,B0BWNZD22H,B09Y14R6JT,B09964WTF5,B082K8ZNQ1,B0BVR8F5W3,B0CFF2JG1N,B0CXHY4R34
A91: =W91 -> 511 | B91: =IF(A91="","",IF(A91<词盘!$B$2,"大词",IF(A91<词盘!$C$2,"中尾词","长尾词"))) -> 大词 | D91: =IF(M91="","",IF(OR(E91="/",E91=""),"无序",IF(COUNTIFS(E:E,E91)<4,"无序","有序"))) -> 无序 | I91: =P91/SUM(P:P) -> 0.0015007504 | J91: =AC91 -> 18173 | K91: =IFERROR(Z91*AH91,"") -> 7397.24 | M91: temperature probe | N91: 温度探头 | P91: 0.0015 | Q91: 自然搜索词 | R91: 9582 | S91: 14 | T91: B0BJK5W11R/B005KCG6CE/B0CRY9V6LL/B017613C3C/B0BQ782XNW/B01IHHLB3W/B0C7D27GV8/B07XXSYLL8/B09LSGPHT3/B00S93EQUK/B0BBR2RL6X/B01F59K0KA/B00GRFHXVQ/B096K2L985 | U91: 279797 | V91: 9137 | W91: 511 | X91: 0.056 | Y91: 265684 | Z91: 3662 | AA91: 12 | AB91: 5 | AC91: 18173 | AD91: 0.5 | AE91: 41 | AF91: 0.3178 | AG91: 0.288 | AH91: 2.02 | AI91: $1.51 - $2.53 | AJ91: B07XXSYLL8 | AK91: 0.1168 | AL91: 0.1061 | AM91: B00S93EQUK | AN91: 0.1075 | AO91: 0.1364 | AP91: B017613C3C | AQ91: 0.0935 | AR91: 0.0455 | AS91: B00S93EQUK,B07XXSYLL8,B017613C3C,B07477NMF4,B0BQ782XNW,B08KZR4F23,B07Y51PCW7,B0B71HFH9K,B08K2G5Y78,B08RWPPD8J | AT91: 0 | AU91: B00LB7REFK,B07VHPFK5B,B00L4Z0T2Y,B07QHDRCZ3,B079X5FTZR,B07SRRQS5B,B01IEJHJWK,B0CBD8YWZY,B01DODMU9I,B0C4G2BPJ2
A92: =W92 -> 392 | B92: =IF(A92="","",IF(A92<词盘!$B$2,"大词",IF(A92<词盘!$C$2,"中尾词","长尾词"))) -> 大词 | C92: 2 | D92: =IF(M92="","",IF(OR(E92="/",E92=""),"无序",IF(COUNTIFS(E:E,E92)<4,"无序","有序"))) -> 无序 | I92: =P92/SUM(P:P) -> 0.0015007504 | J92: =AC92 -> 225 | K92: =IFERROR(Z92*AH92,"") -> 26510 | M92: thermopen | N92: 热开 | P92: 0.0015 | Q92: 自然搜索词 | R92: 9473 | S92: 11 | T92: B0BJK5W11R/B00GRFHXVQ/B0CRY9V6LL/B0BBR2RL6X/B01IHHLB3W/B0BQ782XNW/B07XXSYLL8/B00S93EQUK/B017613C3C/B01F59K0KA/B09LSGPHT3 | U92: 250345 | V92: 6528 | W92: 392 | X92: 0.0601 | Y92: 150995 | Z92: 2651 | AA92: 9 | AB92: 0 | AC92: 225 | AD92: 29.01 | AE92: 23 | AF92: 0.6681 | AG92: 0.4058 | AH92: 10 | AI92: $9.00 - $11.00 | AJ92: B0DC8MWQ8K | AK92: 0.395 | AL92: 0.2174 | AM92: B07XXSYLL8 | AN92: 0.1807 | AO92: 0.1594 | AP92: B0DC8776HK | AQ92: 0.0924 | AR92: 0.029 | AS92: B0DC8MWQ8K,B07XXSYLL8,B0BBR2RL6X,B0DC82YRDW,B0DC875HXP,B00S93EQUK,B0DC8FWCDT,B0DC8FD41B,B07R18W3W1,B0DJY2PWTY | AT92: 0 | AU92: B0CP2STMXZ,B0799BJMPJ,B0CNPQ9CJ8,B0C4JKHV4N,B08V729B6V,B000I9U972,B07SRRQS5B,B08V7SN17G,B0C9544ZMG,B07XLH4GJ8
A93: =W93 -> 49 | B93: =IF(A93="","",IF(A93<词盘!$B$2,"大词",IF(A93<词盘!$C$2,"中尾词","长尾词"))) -> 大词 | C93: 3 | D93: =IF(M93="","",IF(OR(E93="/",E93=""),"无序",IF(COUNTIFS(E:E,E93)<4,"无序","有序"))) -> 无序 | I93: =P93/SUM(P:P) -> 0.0015007504 | J93: =AC93 -> 66150 | K93: =IFERROR(Z93*AH93,"") -> 51708.69 | M93: amazon prime | N93: 亚马逊Prime | P93: 0.0015 | Q93: 自然搜索词 | R93: 9310 | S93: 1 | T93: B09LSGPHT3 | U93: 27690 | V93: 49818 | W93: 49 | X93: 0.001 | Y93: 1116635 | Z93: 24741 | AA93: 2 | AB93: 1 | AC93: 66150 | AD93: 0.75 | AE93: 78 | AF93: 0.3364 | AG93: 0.3182 | AH93: 2.09 | AI93: $1.62 - $2.67 | AJ93: B07BGLT25K | AK93: 0.221 | AL93: 0.2576 | AM93: B0CJM1GNFQ | AN93: 0.0677 | AO93: 0.0303 | AP93: B07PCMWTSG | AQ93: 0.0477 | AR93: 0.0303 | AS93: B0721TSVKT,B07PCMWTSG,B0CJM1GNFQ,B07BGLT25K,B07VCB6CRK,B0B6BDTSLW,B08L78KPWJ,B07757W7GN,B07BQXJ123,B0DK7ZNB6Z | AT93: 0.1061 | AU93: B0CFV5LZ3R,B0758TY861,B0CNKKLPM3,B0CL6CXMGZ,B0BZH88ZRF,B016U6WVTA,B0CNGYQQP8,B00VZ94K2Y,B079X4S4DQ,B001DYDAEK
A94: =W94 -> 650 | B94: =IF(A94="","",IF(A94<词盘!$B$2,"大词",IF(A94<词盘!$C$2,"中尾词","长尾词"))) -> 大词 | C94: 1 | D94: =IF(M94="","",IF(OR(E94="/",E94=""),"无序",IF(COUNTIFS(E:E,E94)<4,"无序","有序"))) -> 无序 | I94: =P94/SUM(P:P) -> 0.0015007504 | J94: =AC94 -> 38129 | K94: =IFERROR(Z94*AH94,"") -> 7786.5 | M94: temperature gauge | N94: 温度表 | P94: 0.0015 | Q94: 自然搜索词 | R94: 9254 | S94: 8 | T94: B0BQ782XNW/B01IHHLB3W/B07XXSYLL8/B00S93EQUK/B017613C3C/B01F59K0KA/B09LSGPHT3/B0C7D27GV8 | U94: 152276 | V94: 21253 | W94: 650 | X94: 0.0306 | Y94: 614298 | Z94: 10382 | AA94: 15 | AB94: 13 | AC94: 38129 | AD94: 0.56 | AE94: 69 | AF94: 0.2233 | AG94: 0.2328 | AH94: 0.75 | AI94: $0.56 - $0.93 | AJ94: B01H1R0K68 | AK94: 0.0935 | AL94: 0.1121 | AM94: B00004TBJP | AN94: 0.0753 | AO94: 0.0431 | AP94: B07WCR5Y4B | AQ94: 0.0545 | AR94: 0.0776 | AS94: B07WCR5Y4B,B01H1R0K68,B07R3YC1BC,B09NL17MBR,B09N92NRYN,B00004TBJP,B07XXSYLL8,B07ZSF5RC5,B0C6135GWX,B07Y36FWTT | AT94: 0 | AU94: B07SRRQS5B,B0CFF2JG1N,B0BZCMDZNS,B0CL9SXSBD,B0B7Z2MRWY,B0BN9DD956,B0982TPZTW,B0CGD6Q656,B0CN36LVRS,B0BXCKKNN8
A95: =W95 -> 1876 | B95: =IF(A95="","",IF(A95<词盘!$B$2,"大词",IF(A95<词盘!$C$2,"中尾词","长尾词"))) -> 大词 | C95: 2 | D95: =IF(M95="","",IF(OR(E95="/",E95=""),"无序",IF(COUNTIFS(E:E,E95)<4,"无序","有序"))) -> 无序 | I95: =P95/SUM(P:P) -> 0.0014007004 | J95: =AC95 -> 741 | K95: =IFERROR(Z95*AH95,"") -> 5875.2 | M95: bread thermometer | N95: 面包温度计 | P95: 0.0014 | Q95: 自然搜索词 | R95: 9194 | S95: 15 | T95: B005KCG6CE/B096K2L985/B01F59K0KA/B017613C3C/B01IHHLB3W/B0BQ782XNW/B07XXSYLL8/B09LSGPHT3/B0BBR2RL6X/B00S93EQUK/B0BJK5W11R/B0CRY9V6LL/B00GRFHXVQ/B0C7D27GV8/B0DDXWY41V | U95: 300505 | V95: 6761 | W95: 1876 | X95: 0.2775 | Y95: 169603 | Z95: 3264 | AA95: 43 | AB95: 0 | AC95: 741 | AD95: 9.12 | AE95: 58 | AF95: 0.5729 | AG95: 0.4722 | AH95: 1.8 | AI95: $1.36 - $2.25 | AJ95: B09MTX71VX | AK95: 0.392 | AL95: 0.3333 | AM95: B08RWPPD8J | AN95: 0.1156 | AO95: 0.1111 | AP95: B00S93EQUK | AQ95: 0.0653 | AR95: 0.0278 | AS95: B09MTX71VX,B07XXSYLL8,B08RWPPD8J,B01IHHLB3W,B00S93EQUK,B01LET2BFC,B0BW5VGF4M,B07Y51PCW7,B0B71HFH9K,B0C37DLHWW | AT95: 0.0403 | AU95: B0C6SWK5YJ,B09J4BZTML,B0C7G6RB8T,B0CY245PZZ,B0CM336GBC,B072Q9QG68,B0CR2XTZGY,B0B776Y6JQ,B076H8GBBK,B00E0MGSX2
A96: =W96 -> 0 | B96: =IF(A96="","",IF(A96<词盘!$B$2,"大词",IF(A96<词盘!$C$2,"中尾词","长尾词"))) -> 大词 | D96: =IF(M96="","",IF(OR(E96="/",E96=""),"无序",IF(COUNTIFS(E:E,E96)<4,"无序","有序"))) -> 无序 | I96: =P96/SUM(P:P) -> 0.0014007004 | J96: =AC96 -> 98 | K96: =IFERROR(Z96*AH96,"") | M96: ninja flex flame grill | P96: 0.0014 | Q96: 自然搜索词 | R96: 9190 | S96: 1 | T96: B00S93EQUK | U96: 26905 | AC96: 98 | AE96: 28 | AI96: - | AJ96: B0DSY91FF8 | AK96: 0.8882 | AL96: 0.6 | AM96: B0CB1QX1Q2 | AN96: 0.0243 | AO96: 0 | AP96: B0DX5PQPKD | AQ96: 0.0158 | AR96: 0 | AT96: 0.0123 | AU96: B07PJG4FBM,B0B9V2LZFT,B0928K23P6,B07TRMF56R,B07CSMJGF6,B07GBWDQQQ,B0CW2ZFZV5,B0859RNBYS,B01IVPZUJQ,B082WJMM5H
A97: =W97 -> 504 | B97: =IF(A97="","",IF(A97<词盘!$B$2,"大词",IF(A97<词盘!$C$2,"中尾词","长尾词"))) -> 大词 | D97: =IF(M97="","",IF(OR(E97="/",E97=""),"无序",IF(COUNTIFS(E:E,E97)<4,"无序","有序"))) -> 无序 | I97: =P97/SUM(P:P) -> 0.0014007004 | J97: =AC97 -> 135800 | K97: =IFERROR(Z97*AH97,"") -> 21733.46 | M97: gift for men | N97: 男士礼物 | O97: Y | P97: 0.0014 | Q97: 自然搜索词/AC推荐词/SP广告词 | R97: 8781 | S97: 2 | T97: B00S93EQUK/B096K2L985 | U97: 32492 | V97: 46299 | W97: 504 | X97: 0.0109 | Y97: 1329142 | Z97: 22177 | AA97: 12 | AB97: 4 | AC97: 135800 | AD97: 0.34 | AE97: 355 | AF97: 0.1053 | AG97: 0.0585 | AH97: 0.98 | AI97: $0.79 - $1.25 | AJ97: B0CRR1XXC4 | AK97: 0.038 | AL97: 0.0117 | AM97: 1450845800 | AN97: 0.0349 | AO97: 0.0273 | AP97: B0D4215HCX | AQ97: 0.0324 | AR97: 0.0195 | AS97: B0D4215HCX,B0DL2BZWKD,B012BA0VSM,B0CP9YF9W7,B078N1DBY9,B09BDG5RP3,B0D9ND5QXH,B07G142F9Z,B0BG4HY4PX,B0DB1L7DQ1 | AT97: 0.0793 | AU97: B08YZ633BY,B0CJB2KBJX,B0B7BP6CJN,B09NXVJ25C,B07QK9C9KT,B07CN6ZDVY,B0B41MYSGP,B0131KA7G2,B07GKVBQDG,B0BLZM9NCF
A98: =W98 -> 324 | B98: =IF(A98="","",IF(A98<词盘!$B$2,"大词",IF(A98<词盘!$C$2,"中尾词","长尾词"))) -> 大词 | D98: =IF(M98="","",IF(OR(E98="/",E98=""),"无序",IF(COUNTIFS(E:E,E98)<4,"无序","有序"))) -> 无序 | I98: =P98/SUM(P:P) -> 0.0014007004 | J98: =AC98 -> 618 | K98: =IFERROR(Z98*AH98,"") | M98: termometro digital para alimentos | N98: 数字食品温度计 | P98: 0.0014 | Q98: 自然搜索词 | R98: 8764 | S98: 12 | T98: B00GRFHXVQ/B017613C3C/B0BQ782XNW/B01IHHLB3W/B09LSGPHT3/B07XXSYLL8/B00S93EQUK/B01F59K0KA/B005KCG6CE/B0BBR2RL6X/B0C7D27GV8/B0CRY9V6LL | U98: 248206 | V98: 9736 | W98: 324 | X98: 0.0333 | Y98: 212948 | Z98: 4497 | AA98: 8 | AB98: 0 | AC98: 618 | AD98: 15.75 | AE98: 10 | AF98: 0.2333 | AG98: 0.1346 | AI98: - | AJ98: B0B71HFH9K | AK98: 0.0833 | AL98: 0 | AM98: B09MTX71VX | AN98: 0.075 | AO98: 0.0769 | AP98: B09C32DYV1 | AQ98: 0.075 | AR98: 0.0577 | AS98: B0BQ782XNW,B00S93EQUK,B0B71HFH9K,B07XXSYLL8,B09MTX71VX,B017613C3C,B0C37DLHWW,B01LET2BFC,B09LSGPHT3,B07QBP8Y2Q | AT98: 0.0364 | AU98: B0BPNMT5DM,B07SRRQS5B,B0CJ4PDQRF,B093XVDNNB,B07P8NXQF4,B07HXWPBRT,B0BLS7V2YG,B0BV6ZR4GL,B01IEJHJWK,B09LLYP2XL
A99: =W99 -> 154 | B99: =IF(A99="","",IF(A99<词盘!$B$2,"大词",IF(A99<词盘!$C$2,"中尾词","长尾词"))) -> 大词 | C99: 1 | D99: =IF(M99="","",IF(OR(E99="/",E99=""),"无序",IF(COUNTIFS(E:E,E99)<4,"无序","有序"))) -> 有序 | E99: meat thermometer | I99: =P99/SUM(P:P) -> 0.0014007004 | J99: =AC99 -> 545 | K99: =IFERROR(Z99*AH99,"") | M99: thermpro digital instant read meat thermometer kitchen cooking | N99: thermpro 数字即时读取肉类温度计厨房烹饪 | P99: 0.0014 | Q99: 自然搜索词 | R99: 8683 | S99: 11 | T99: B0BJK5W11R/B096K2L985/B0CRY9V6LL/B0BBR2RL6X/B01F59K0KA/B017613C3C/B01IHHLB3W/B0BQ782XNW/B07XXSYLL8/B09LSGPHT3/B00S93EQUK | U99: 359107 | V99: 5877 | W99: 154 | X99: 0.0264 | Y99: 156113 | Z99: 2621 | AA99: 4 | AB99: 0 | AC99: 545 | AD99: 10.78 | AE99: 21 | AF99: 0.5953 | AG99: 0.6987 | AI99: - | AJ99: B07XXSYLL8 | AK99: 0.375 | AL99: 0.3973 | AM99: B01IHHLB3W | AN99: 0.1429 | AO99: 0.2055 | AP99: B07R18W3W1 | AQ99: 0.0774 | AR99: 0.0959 | AS99: B07XXSYLL8,B01IHHLB3W,B017613C3C,B07Y51PCW7,B07R18W3W1,B0CRY9V6LL,B0BBR2RL6X,B0793MSG7S,B07477NMF4,B08K2G5Y78 | AT99: 0.0291 | AU99: B07SRRQS5B,B07MXJ93K8,B0995B8K8V,B0982TPZTW,B0B8V6Y2X8,B0CL9SXSBD,B082K8ZNQ1,B0BC6G9Q35,B0B75JF6CM,B0B7Z2MRWY
A100: =W100 -> 817 | B100: =IF(A100="","",IF(A100<词盘!$B$2,"大词",IF(A100<词盘!$C$2,"中尾词","长尾词"))) -> 大词 | C100: 1 | D100: =IF(M100="","",IF(OR(E100="/",E100=""),"无序",IF(COUNTIFS(E:E,E100)<4,"无序","有序"))) -> 无序 | I100: =P100/SUM(P:P) -> 0.0014007004 | J100: =AC100 -> 536 | K100: =IFERROR(Z100*AH100,"") -> 6667.65 | M100: thermpro | N100: 热敏电阻 | P100: 0.0014 | Q100: 自然搜索词 | R100: 8676 | S100: 8 | T100: B0BJK5W11R/B096K2L985/B0CRY9V6LL/B0BBR2RL6X/B017613C3C/B01IHHLB3W/B07XXSYLL8/B01F59K0KA | U100: 243988 | V100: 8555 | W100: 817 | X100: 0.0956 | Y100: 215375 | Z100: 4041 | AA100: 19 | AB100: 1 | AC100: 536 | AD100: 15.96 | AE100: 14 | AF100: 0.4262 | AG100: 0.3333 | AH100: 1.65 | AI100: $1.24 - $2.06 | AJ100: B01H1R0K68 | AK100: 0.2254 | AL100: 0.141 | AM100: B07XXSYLL8 | AN100: 0.1475 | AO100: 0.141 | AP100: B07WCR5Y4B | AQ100: 0.0533 | AR100: 0.0513 | AS100: B07XXSYLL8,B0BMLDL5GM,B0B48NL6L8,B0DHFN5HK8,B08KZR4F23,B0CRY9V6LL,B08K2G5Y78,B0CJLNCYG6,B017613C3C,B0CQLD3TXR | AT100: 0.0468 | AU100: B0B7BFMHNF,B08YZ633BY,B07SRRQS5B,B0B4D8S5XL,B0932QJ2JZ,B0BYRHDPK9,B0BZWMJM2F,B08MF4G5NP,B07CNCMT65,B07CZDXDG8
...

Sheet SOP
A1: 序号 | B1: 必做 | C1: 内容 | D1: 操作 | E1: 备注 | F1: 注意
A2: #1 | B2: v | C2: 【词库】对关键词打标按照流量大小、相关性、有无序性、词组、一级分类、二级分类、用户搜索意图，对重点追踪词进行打标“V” | D2: 1、将20个TOP相似的ASIN输入卖家精灵进行关键词“拓展流量词”，按照格式粘贴到【词库】 https://www.sellersprite.com/v3/traffic/extend 2、对加粗字段进行打标，其它都是公式。在这之前建议先做【词根】先把不相关词根找不出否定 https://chatgpt.com/g/g-RZEovC1BF-vikiguan-jian-ci-fen-xi-zhuan-jia/c/67362093-f224-8010-952b-e4f602764b30 | E2: =_xlfn.DISPIMG("ID_0AE6D8C63B884F3E9824A5EE3BDEBE06",1) -> =DISPIMG("ID_0AE6D8C63B884F3E9824A5EE3BDEBE06",1)
A3: #2 | B3: v | C3: 【词根】量化词根数据，对词根进行打标按照一级、二级、用户意图，将不相关词根找出来并标记“X” | D3: 1、将词库中的关键词做词频统计 2、对词根进行打标，其它都是公式 https://chatgpt.com/g/g-RZEovC1BF-vikiguan-jian-ci-fen-xi-zhuan-jia/c/67362093-f224-8010-952b-e4f602764b30 | E3: =_xlfn.DISPIMG("ID_564DC2EA9AEF4D649826B83151F6EAF3",1) -> =DISPIMG("ID_564DC2EA9AEF4D649826B83151F6EAF3",1)
A4: #3 | B4: v | C4: 【词盘】将关键词和词根按照各个维度进行量化，分析类目流量构成与竞争情况，是文案与广告结构预算分配依据 | D4: 1、按照ABA排名，自定义关键词大小，初始2w以内为大词，2-10w为中尾词，10w+为长尾词，划分大词建议在20个左右 2、刷新透视表（透视表如果报错，可能是刷新的数据被后边已有数据遮挡，可以将后边数据剪切到靠后行） | F4: 1、此表可以从多个维度看类目成熟期的流量结构，但不一定适合自己当前阶段。自己的流量结构一个是参考类目结构，另外一个是考虑自己所处阶段的投入产出如何利益最大化； 2、有序更适合做精准与词组，无序更适合做广泛与自动；强相关更适合做精准高竞价，较为相关与弱相关更适合做非精准低竞价； 3、关注用户意图
A11: 显示作者信息 | B11: =IF(A11="隐藏作者信息","",B42) -> 卖家精灵 | C11: =IF(A11="隐藏作者信息","",C42) -> Shulex | D11: =IF(A11="隐藏作者信息","",D42) -> 领星 | E11: =IF(A11="隐藏作者信息","",E42) -> SIF | F11: =IF(A11="隐藏作者信息","",F42) -> H10
A12: =A43 -> =DISPIMG("ID_9D8123A1BC1A4D74A72F65A0A70FB706",1) | B12: =IF(A11="隐藏作者信息","",B43) -> 卖家精灵折扣码： 1、包月套餐9折优惠：FL90，332/月 2、单人包年套餐7.2折优惠：FL72，1928/年 3、含子账号标准包年套餐7.8折优惠：FL78，3445/年（3个子账号）、6534/年（6个子账号）、9342/年（10个子账号） | C12: =IF(A11="隐藏作者信息","",C43) -> 渠道码：FL6688 Shulex购买赠送一个月 | D12: =IF(A11="隐藏作者信息","",D43) -> 领星注册赠送10%单量 | E12: =IF(A11="隐藏作者信息","",E43) -> #Sif坑位监控助力会员日 精准监控每一个关键词排名，一目了然自然和SP广告排名变化！更支持小时级抓取排名。发现波动，立即调整！购买时输入折扣码【FALAO】，享88折 | F12: =IF(A11="隐藏作者信息","",F43) -> H10大促优惠： 🔸创业版（性价比高 单人优选）大促优惠价：$399/年，折扣码：ENT1YKJFL 🔸专业版（功能强大 专业之选）大促优惠价：$999/年，折扣码：PRO1YKJFL 优惠码使用方法和注意事项： 1. 打开无痕窗口，直达H10官网购买链接： https://crushtrk.com/?a=15428&c=528&p=r&s4=KJFLH10&s5=PURL-040511 2. 在方框里输入折扣码，点击右侧提交按钮应用折扣码 3. 价格减扣后，在相应的版本下点击立即购买，跳转到支付页面进行账户注册和购买（支持支付宝支付，且不会自动续费） 4. 此优惠仅限新用户，必须要全新账号（**注册购买同时进行，请不要先注册后购买，邮箱一旦注册不再是新用户**）
A13: =IF(A11="隐藏作者信息","",A44) -> Pharaoh(VX:A9falao) | B13: =IF(A11="隐藏作者信息","",B44) -> https://www.sellersprite.com/cn/price | C13: =IF(A11="隐藏作者信息","",C44) -> https://apps.voc.ai/account?/#/cnRegisterOfficial?lang=cn&coupon_code=fl6688 | D13: =IF(A11="隐藏作者信息","",D44) -> https://erp.lingxing.com/register?invite=qdpharaoh | E13: =IF(A11="隐藏作者信息","",E44) -> https://www.sif.com/ | F13: =IF(A11="隐藏作者信息","",F44) -> https://crushtrk.com/?a=15428&c=528&p=r&s4=KJFLH10&s5=PURL-040511
B42: 卖家精灵 | C42: Shulex | D42: 领星 | E42: SIF | F42: H10
A43: =_xlfn.DISPIMG("ID_9D8123A1BC1A4D74A72F65A0A70FB706",1) -> =DISPIMG("ID_9D8123A1BC1A4D74A72F65A0A70FB706",1) | B43: 卖家精灵折扣码： 1、包月套餐9折优惠：FL90，332/月 2、单人包年套餐7.2折优惠：FL72，1928/年 3、含子账号标准包年套餐7.8折优惠：FL78，3445/年（3个子账号）、6534/年（6个子账号）、9342/年（10个子账号） | C43: 渠道码：FL6688 Shulex购买赠送一个月 | D43: 领星注册赠送10%单量 | E43: #Sif坑位监控助力会员日 精准监控每一个关键词排名，一目了然自然和SP广告排名变化！更支持小时级抓取排名。发现波动，立即调整！购买时输入折扣码【FALAO】，享88折 | F43: H10大促优惠： 🔸创业版（性价比高 单人优选）大促优惠价：$399/年，折扣码：ENT1YKJFL 🔸专业版（功能强大 专业之选）大促优惠价：$999/年，折扣码：PRO1YKJFL 优惠码使用方法和注意事项： 1. 打开无痕窗口，直达H10官网购买链接： https://crushtrk.com/?a=15428&c=528&p=r&s4=KJFLH10&s5=PURL-040511 2. 在方框里输入折扣码，点击右侧提交按钮应用折扣码 3. 价格减扣后，在相应的版本下点击立即购买，跳转到支付页面进行账户注册和购买（支持支付宝支付，且不会自动续费） 4. 此优惠仅限新用户，必须要全新账号（**注册购买同时进行，请不要先注册后购买，邮箱一旦注册不再是新用户**）
A44: Pharaoh(VX:A9falao) | B44: https://www.sellersprite.com/cn/price | C44: https://apps.voc.ai/account?/#/cnRegisterOfficial?lang=cn&coupon_code=fl6688 | D44: https://erp.lingxing.com/register?invite=qdpharaoh | E44: https://www.sif.com/ | F44: https://crushtrk.com/?a=15428&c=528&p=r&s4=KJFLH10&s5=PURL-040511
