Workbook

Sheet 阶段实际盈亏
A1: 时间 | B1: 实际 | C1: 价格 | D1: 站内 coupon | E1: 站内 code | F1: 站外 折扣 | G1: 站外 订单 | H1: 站内 自然单 | I1: 站内 广告单 | J1: 阶段 销售 订单 | K1: 时间 /天 | L1: 阶段广告费 （出1单广告单预估） | M1: 阶段站外费用 （5美金/单） | N1: 阶段订单 盈亏 | O1: 阶段亏损 /美金 | P1: 六阶段 总亏损 | R1: 阶段日均 订单 | S1: 阶段日均 广告订单 | T1: 阶段日均 自然订单 | U1: 新品 排行榜 | V1: 小类目 排名
A2: 9月7-9月12 | B2: 第一阶段 | C2: 99.99 | D2: 0.05 | E2: 0.5 | F2: 0.68 | G2: =SUM(#REF!) -> #REF! | H2: 0 | I2: 0 | J2: =SUM(G2:I2) -> #REF! | K2: 6 | L2: 0 | M2: =SUM(#REF!) -> #REF! | N2: =SUM(#REF!) -> #REF! | O2: =SUM(L2:N2) -> #REF!
A3: 9月13-9月21 | B3: 第二阶段 | C3: 79.99 | D3: 0.3 | E3: 0.2 | F3: 0.3 | G3: 81 | H3: 14 | I3: 0 | J3: =SUM(G3:I3) -> 95 | K3: 9 | L3: =SUM(#REF!) -> #REF! | M3: =SUM(#REF!) -> #REF! | N3: =SUM(#REF!) -> #REF! | O3: =SUM(L3:N3) -> #REF!
A4: 9月22-10月1 | B4: 第三阶段 | C4: 69.99 | D4: 0.3 | E4: 0.2 | F4: 0.25 | G4: 45 | H4: 60 | I4: 3 | J4: =SUM(G4:I4) -> 108 | K4: 10 | L4: =SUM(#REF!) -> #REF! | M4: =SUM(#REF!) -> #REF! | N4: =SUM(#REF!) -> #REF! | O4: =SUM(L4:N4) -> #REF!
A5: 10月2-10月11 | B5: 第四阶段 | C5: 69.99 | D5: 0.3 | E5: 0 | F5: 0.25
A6: 10月12-10月21 | B6: 第五阶段 | C6: 69.99 | D6: 0.3 | E6: 0 | F6: 0.25
A7: 10月22-10月31 | B7: 第六阶段 | C7: 69.99 | D7: 0.3 | E7: 0 | F7: 0
A9: 11月1-11月30 | B9: 十一月份 | C9: 69.99 | D9: 0.2 | E9: 0 | F9: 0
A10: 12月1-12月31 | B10: 十二月份 | C10: 69.99 | D10: 0.2 | E10: 0 | F10: 0
A11: 1月1-1月31 | B11: 一月份 | C11: 69.99 | D11: 0.2 | E11: 0 | F11: 0

Sheet 价格策略模拟
B1: 价格策略模拟
A2: 阶段 | B2: 定价 | C2: coupon/ 秒杀 | D2: code | E2: 折后价 | F2: FBA 配送费 | G2: 亚马逊 佣金 | H2: 账号 回款 | I2: 仓储费+入库配置费 | J2: coupon 费用 | K2: 产品 成本 | L2: 物流费 | M2: 退货成本(公式后面加的是单套产品的移除费） | N2: 退货率 | O2: 每单平摊 退货成本 | P2: 每单 毛利 | Q2: 毛利率 | R2: 订单 数量 | S2: 阶段 订单 亏损 | T2: 阶段 订单 总盈亏
A3: 备注 | B3: 选择性调整 | C3: 选择性调整 | D3: / | E3: 公式 | F3: 3.参考机构或者在亚马逊后台查询 | G3: 公式 | H3: 公式 | I3: 公式 | J3: 未计算 | K3: 1.先填写采购价 | L3: 2.根据材积重推算头程运费 | M3: 4.[ 退货损失成本 = {(产品采购价 + 头程运费)}/{汇率} + 亚马逊配送费 + 佣金的20% + 移除/弃置费用 ] | N3: 5.亚马逊后台- 商机探测器 按关键词或 ASIN 搜索看细分类退货率 | O3: 6.按退货率计算退货成本，然后平摊到没有退货的95%产品里 | P3: 公式 | Q3: 公式 | S3: 公式 | T3: 公式 | U3: 备注：广告费用未计算
A4: 第一阶段 | B4: 17.99 | C4: 0.2 | D4: 0 | E4: =SUM(B4*(1-C4-D4)) -> 14.392 | F4: 6 | G4: =SUM(E4*15%) -> 2.1588 | H4: =SUM(E4-F4-G4) -> 6.2332 | I4: 0.22 | J4: 0.6 | K4: 3.7 | L4: 1.4 | M4: =SUM(20%*15%*E4+F4+I4+K4+L4+0.65) -> 12.40176 | N4: 0.02 | O4: =SUM(M4*N4/(1-N4)) -> 0.25309714 | P4: =SUM(H4-I4-J4-K4-L4-O4) -> 0.060102857 | Q4: =SUM(P4/B4) -> 0.0033409037 | R4: 1 | S4: =SUM(P4*R4) -> 0.060102857 | T4: =SUM(S4:S4) -> 0.060102857
A5: 第二阶段 | B5: 17.99 | C5: 0.15 | D5: 0 | E5: =SUM(B5*(1-C5-D5)) -> 15.2915 | F5: 6 | G5: =SUM(E5*15%) -> 2.293725 | H5: =SUM(E5-F5-G5) -> 6.997775 | I5: 0.22 | J5: 0.6 | K5: 3.7 | L5: 1.4 | M5: =SUM(20%*15%*E5+F5+I5+K5+L5+0.65) -> 12.428745 | N5: 0.02 | O5: =SUM(M5*N5/(1-N5)) -> 0.25364786 | P5: =SUM(H5-I5-J5-K5-L5-O5) -> 0.82412714 | Q5: =SUM(P5/B5) -> 0.045810291 | R5: 1 | S5: =SUM(P5*R5) -> 0.82412714 | T5: =SUM(S5:S5) -> 0.82412714
A6: 第三阶段 | B6: 17.99 | C6: 0.1 | D6: 0 | E6: =SUM(B6*(1-C6-D6)) -> 16.191 | F6: 6 | G6: =SUM(E6*15%) -> 2.42865 | H6: =SUM(E6-F6-G6) -> 7.76235 | I6: 0.22 | J6: 0.6 | K6: 3.7 | L6: 1.4 | M6: =SUM(20%*15%*E6+F6+I6+K6+L6+0.65) -> 12.45573 | N6: 0.02 | O6: =SUM(M6*N6/(1-N6)) -> 0.25419857 | P6: =SUM(H6-I6-J6-K6-L6-O6) -> 1.5881514 | Q6: =SUM(P6/B6) -> 0.088279679 | R6: 1 | S6: =SUM(P6*R6) -> 1.5881514 | T6: =SUM(S6:S6) -> 1.5881514
A7: 第四阶段 | B7: 17.99 | C7: 0.05 | D7: 0 | E7: =SUM(B7*(1-C7-D7)) -> 17.0905 | F7: 6 | G7: =SUM(E7*15%) -> 2.563575 | H7: =SUM(E7-F7-G7) -> 8.526925 | I7: 0.22 | J7: 0.6 | K7: 3.7 | L7: 1.4 | M7: =SUM(20%*15%*E7+F7+I7+K7+L7+0.65) -> 12.482715 | N7: 0.02 | O7: =SUM(M7*N7/(1-N7)) -> 0.25474929 | P7: =SUM(H7-I7-J7-K7-L7-O7) -> 2.3521757 | Q7: =SUM(P7/B7) -> 0.13074907 | R7: 1 | S7: =SUM(P7*R7) -> 2.3521757 | T7: =SUM(S7:S7) -> 2.3521757
A8: 第五阶段 | B8: 17.99 | C8: 0.05 | D8: 0 | E8: =SUM(B8*(1-C8-D8)) -> 17.0905 | F8: 6 | G8: =SUM(E8*15%) -> 2.563575 | H8: =SUM(E8-F8-G8) -> 8.526925 | I8: 0.22 | J8: 0.6 | K8: 3.7 | L8: 1.4 | M8: =SUM(20%*15%*E8+F8+I8+K8+L8+0.65) -> 12.482715 | N8: 0.02 | O8: =SUM(M8*N8/(1-N8)) -> 0.25474929 | P8: =SUM(H8-I8-J8-K8-L8-O8) -> 2.3521757 | Q8: =SUM(P8/B8) -> 0.13074907 | R8: 1 | S8: =SUM(P8*R8) -> 2.3521757 | T8: =SUM(S8:S8) -> 2.3521757
A9: 第六阶段 | B9: 17.99 | C9: 0 | D9: 0 | E9: =SUM(B9*(1-C9-D9)) -> 17.99 | F9: 6 | G9: =SUM(E9*15%) -> 2.6985 | H9: =SUM(E9-F9-G9) -> 9.2915 | I9: 0.22 | J9: 0 | K9: 3.7 | L9: 1.4 | M9: =SUM(20%*15%*E9+F9+I9+K9+L9+0.65) -> 12.5097 | N9: 0.02 | O9: =SUM(M9*N9/(1-N9)) -> 0.2553 | P9: =SUM(H9-I9-J9-K9-L9-O9) -> 3.7162 | Q9: =SUM(P9/B9) -> 0.20657032 | R9: 1 | S9: =SUM(P9*R9) -> 3.7162 | T9: =SUM(S9:S9) -> 3.7162
A11: 竞品日常价格 | B11: 34.99 | C11: 0.1 | D11: 0 | E11: =SUM(B11*(1-C11-D11)) -> 31.491 | F11: 6 | G11: =SUM(E11*15%) -> 4.72365 | H11: =SUM(E11-F11-G11) -> 20.76735 | I11: 0.22 | J11: 0 | K11: 8.5 | L11: 1.3 | M11: =SUM(20%*15%*E11+F11+I11+K11+L11+0.65) -> 17.61473 | N11: 0.05 | O11: =SUM(M11*N11/(1-N11)) -> 0.92709105 | P11: =SUM(H11-I11-J11-K11-L11-O11) -> 9.8202589 | Q11: =SUM(P11/B11) -> 0.28065902 | R11: 1 | S11: =SUM(P11*R11) -> 9.8202589 | T11: =SUM(S11:S11) -> 9.8202589
A12: 竞品日常价格 | B12: 32.99 | C12: 0 | D12: 0 | E12: =SUM(B12*(1-C12-D12)) -> 32.99 | F12: 6 | G12: =SUM(E12*15%) -> 4.9485 | H12: =SUM(E12-F12-G12) -> 22.0415 | I12: 0.22 | J12: 0 | K12: 8.5 | L12: 1.3 | M12: =SUM(20%*15%*E12+F12+I12+K12+L12+0.65) -> 17.6597 | N12: 0.05 | O12: =SUM(M12*N12/(1-N12)) -> 0.92945789 | P12: =SUM(H12-I12-J12-K12-L12-O12) -> 11.092042 | Q12: =SUM(P12/B12) -> 0.33622437 | R12: 1 | S12: =SUM(P12*R12) -> 11.092042 | T12: =SUM(S12:S12) -> 11.092042
A13: 竞品小类目 | B13: https://www.amazon.com/Best-Sellers-Beauty-Personal-Care-Personal-Makeup-Mirrors/zgbs/beauty/3785121/ref=zg_bs_nav_beauty_3_17738944011
A14: 前100名找竞品 | B14: https://www.amazon.com/20X-Magnifying-Adjustable-Brightness-Detachable/dp/B0CT37456F/ref=zg_bs_g_3785121_d_sccl_20/137-8764674-4814218?psc=1
A15: 前100名找竞品 | B15: https://www.amazon.com/20x-Magnifying-Rechargeable-Adjustable-Brightness/dp/B0D3HNWKWF/ref=zg_bs_g_3785121_d_sccl_39/137-8764674-4814218?psc=1
B16: 找到自己对标的竞品，为 新品做准备
K17: 820g
A18: 产品成本：1688询价60左右
A19: 物流费用：以海运为主，因此1.37美金运费足够
A21: 仓储费+配置费的路径 | C21: 后台目录-数据报告-库存与销售报告-月度仓储费 和 后台-帮助—查询-2024 年亚马逊物流入库配置服务费
A22: 产品移除费的路径 | C22: 后台目录-数据报告-库存与销售报告-移除订单详情
A23: 退货率的路径 | C23: 后台-商机探测器-查询框输入"makeup mirror with lights"
A24: 亚马逊退货成本主要包括以下几个方面： 1.亚马逊配送费：当产品被退回时，亚马逊会收取一次性的配送费用。 2.退款管理费：亚马逊在处理退货订单时，会扣除20%的佣金。无论买家是部分退款还是全部退款，这20%的佣金都称为退款管理费。 3.退货服务费：如果产品不可再售，需要支付额外的移除或弃置订单费用。 4.产品成本和头程运费：如果产品不可再售，除了上述费用外，还需要考虑产品的采购成本和头程运费。 具体计算方式如下： 1.可再次销售的情况：[ 退货损失成本 = 亚马逊配送费 + 佣金的20% ] 2.不可再次销售的情况：[ 退货损失成本 = {(产品采购价 + 头程运费)}/{汇率} + 亚马逊配送费 + 佣金的20% + 移除/弃置费用 ] | C24: [ 退货损失成本 = {(产品采购价 + 头程运费)}/{汇率} + 亚马逊配送费 + 佣金的20% + 移除/弃置费用 ]
A26: 美妆镜类目推广方法：
A27: 第一种：新品上架直接广告拉满
A28: 第二种：新品前期配合测款，提升自然排名，再开广告 | F28: 免评单为主，按照测评节奏递增
A29: 第三种：新品前期配合站外，提升自然排名，再开广告 | F29: 站外需要大折扣：50%code+（20%-30%coupon）
A30: 第四种：测评+广告+大coupon | F30: 10个左右高质量买家账户测评评论+100个以上的VINE
A31: 第五种：站外+广告
A32: 第六种：测评+站外+广告

Sheet 阶段总盈亏
A1: 阶段盈亏模拟数据
A2: 阶段 | B2: 周期 | C2: 定价 | D2: cou pon | E2: code | F2: 折后价 | G2: 站内 自然单 | H2: 站内 广告单 | I2: 阶段 销售 订单 | J2: 时间 /天 | K2: CPA | L2: 阶段 广告费 | M2: 毛利 盈亏 | N2: 阶段盈亏 /美金 | O2: 评论 数量 | P2: 阶段 日均 订单 | Q2: 阶段 日均 广告单 | R2: 自然单占比 | S2: 阶段 日均 自然单 | T2: 日均 广告费 | U2: 每周 销售额 | V2: Tacos | W2: 小类目 排名 | X2: 大类目 排名 | Y2: 备注 | Z2: 评论费/（开5个站点VINE，预计来100条评论）,视觉化费用 | AA2: 前期亏损/美金 | AB2: 总亏损（人民币） | AC2: 小类目 排名 | AD2: 对应 月销量 | AE2: 对应 日销量
C3: 与价格模拟表一样 | D3: 与价格模拟表一样 | E3: 与价格模拟表一样 | G3: 第6步 公式算出自然周出单 | H3: 第5步 公式算出广告周出单 | I3: 第4步，周销量等推测日销*7天，毛利模拟表缺的S3一栏就补齐了 | K3: 第8步 需先做CPC模拟表 | L3: 第9步 公式得出 | M3: 第7步 公式 数据来源于《毛利模拟盈亏》S3 | N3: 第10步，计算当周盈亏 | Q3: 第2步，根据订单占比推算广告订单；参考广告为主的竞品广告占比参考 | S3: 第3步，日销订单扣减广告单算出自然单 | AA3: 前期亏损+VINE | AC3: 第1步，根据目标销量倒推排名 | AD3: 根据推排名节奏推销量 | AE3: 分解到日销量
A4: 第一阶段 | B4: 第1周 | C4: =价格策略模拟!B4 -> 17.99 | D4: =价格策略模拟!C4 -> 0.2 | E4: =价格策略模拟!D4 -> 0 | F4: =SUM(C4*(1-D4-E4)) -> 14.392 | G4: =S4*J4 -> 1.4 | H4: =J4*Q4 -> 12.6 | I4: =SUM(G4:H4) -> 14 | J4: 7 | K4: =CPC模拟表格!V4 -> 15.789474 | L4: =SUM(H4*-K4) -> -198.94737 | M4: =毛利模拟盈亏!T4 -> 9.24144 | N4: =SUM(L4:M4) -> -189.70593 | O4: 10 | P4: =AE4 -> 2 | Q4: =P4*0.9 -> 1.8 | R4: =1-Q4/P4 -> 0.1 | S4: =SUM(P4-Q4) -> 0.2 | T4: =SUM(L4/J4) -> -28.421053 | U4: =毛利模拟盈亏!V4 -> 251.86 | V4: =-L4/U4 -> 0.78991252 | W4: =AC4 -> 0 | AA4: =SUM(N4:N22)+Z4 -> -10597.946 | AB4: =AA4*7 -> -74185.62 | AD4: 60 | AE4: =AD4/30 -> 2
B5: 第2周 | C5: =价格策略模拟!B4 -> 17.99 | D5: =价格策略模拟!C4 -> 0.2 | E5: =价格策略模拟!D4 -> 0 | F5: =SUM(C5*(1-D5-E5)) -> 14.392 | G5: =J5*S5 -> 2.1 | H5: =J5*Q5 -> 18.9 | I5: =SUM(G5:H5) -> 21 | J5: 7 | K5: =CPC模拟表格!V5 -> 15.263158 | L5: =SUM(H5*-K5) -> -288.47368 | M5: =毛利模拟盈亏!T5 -> 13.86216 | N5: =SUM(L5:M5) -> -274.61152 | P5: =AE5 -> 3 | Q5: =P5*0.9 -> 2.7 | R5: =1-Q5/P5 -> 0.1 | S5: =SUM(P5-Q5) -> 0.3 | T5: =SUM(L5/J5) -> -41.210526 | U5: =毛利模拟盈亏!V5 -> 377.79 | V5: =-L5/U5 -> 0.76358211 | W5: =AC5 -> 0 | Z5: 到货开售，开始销售时间填写到货时间 | AD5: 90 | AE5: =AD5/30 -> 3
B6: 第3周 | C6: =价格策略模拟!B4 -> 17.99 | D6: =价格策略模拟!C4 -> 0.2 | E6: =价格策略模拟!D4 -> 0 | F6: =SUM(C6*(1-D6-E6)) -> 14.392 | G6: =J6*S6 -> 7 | H6: =J6*Q6 -> 28 | I6: =SUM(G6:H6) -> 35 | J6: 7 | K6: =CPC模拟表格!V6 -> 14.736842 | L6: =SUM(H6*-K6) -> -412.63158 | M6: =毛利模拟盈亏!T6 -> 23.1036 | N6: =SUM(L6:M6) -> -389.52798 | P6: =AE6 -> 5 | Q6: =P6*0.8 -> 4 | R6: =1-Q6/P6 -> 0.2 | S6: =SUM(P6-Q6) -> 1 | T6: =SUM(L6/J6) -> -58.947368 | U6: =毛利模拟盈亏!V6 -> 629.65 | V6: =-L6/U6 -> 0.65533484 | W6: =AC6 -> 0 | Z6: 5个站点vine 送150个，成本$9+物流费$1.37+配送费$6美金一个 | AD6: 150 | AE6: =AD6/30 -> 5
B7: 第4周 | C7: =价格策略模拟!B4 -> 17.99 | D7: =价格策略模拟!C4 -> 0.2 | E7: =价格策略模拟!D4 -> 0 | F7: =SUM(C7*(1-D7-E7)) -> 14.392 | G7: =J7*S7 -> 9.8 | H7: =J7*Q7 -> 39.2 | I7: =SUM(G7:H7) -> 49 | J7: 7 | K7: =CPC模拟表格!V7 -> 14.210526 | L7: =SUM(H7*-K7) -> -557.05263 | M7: =毛利模拟盈亏!T7 -> 32.34504 | N7: =SUM(L7:M7) -> -524.70759 | P7: =AE7 -> 7 | Q7: =P7*0.8 -> 5.6 | R7: =1-Q7/P7 -> 0.2 | S7: =SUM(P7-Q7) -> 1.4 | T7: =SUM(L7/J7) -> -79.578947 | U7: =毛利模拟盈亏!V7 -> 881.51 | V7: =-L7/U7 -> 0.63193002 | W7: =AC7 -> 0 | Z7: vine成本200美金30个，5条vine就是1000美金 | AD7: 210 | AE7: =AD7/30 -> 7
A8: 第二阶段 | B8: 第5周 | C8: =价格策略模拟!B5 -> 17.99 | D8: =价格策略模拟!C5 -> 0.15 | E8: =价格策略模拟!D5 -> 0 | F8: =SUM(C8*(1-D8-E8)) -> 15.2915 | G8: =J8*S8 -> 12.6 | H8: =J8*Q8 -> 50.4 | I8: =SUM(G8:H8) -> 63 | J8: 7 | K8: =CPC模拟表格!V8 -> 13.5 | L8: =SUM(H8*-K8) -> -680.4 | M8: =毛利模拟盈亏!T8 -> 89.72001 | N8: =SUM(L8:M8) -> -590.67999 | O8: 100 | P8: =AE8 -> 9 | Q8: =P8*0.8 -> 7.2 | R8: =1-Q8/P8 -> 0.2 | S8: =SUM(P8-Q8) -> 1.8 | T8: =SUM(L8/J8) -> -97.2 | U8: =毛利模拟盈亏!V8 -> 1133.37 | V8: =-L8/U8 -> 0.60033352 | W8: =AC8 -> 0 | Z8: 图片和视频拍摄费用预估5000美金以内 | AD8: 270 | AE8: =AD8/30 -> 9
B9: 第6周 | C9: =价格策略模拟!B5 -> 17.99 | D9: =价格策略模拟!C5 -> 0.15 | E9: =价格策略模拟!D5 -> 0 | F9: =SUM(C9*(1-D9-E9)) -> 15.2915 | G9: =J9*S9 -> 16.333333 | H9: =J9*Q9 -> 65.333333 | I9: =SUM(G9:H9) -> 81.666667 | J9: 7 | K9: =CPC模拟表格!V9 -> 13.5 | L9: =SUM(H9*-K9) -> -882 | M9: =毛利模拟盈亏!T9 -> 116.30372 | N9: =SUM(L9:M9) -> -765.69628 | P9: =AE9 -> 11.666667 | Q9: =P9*0.8 -> 9.3333333 | R9: =1-Q9/P9 -> 0.2 | S9: =SUM(P9-Q9) -> 2.3333333 | T9: =SUM(L9/J9) -> -126 | U9: =毛利模拟盈亏!V9 -> 1469.1833 | V9: =-L9/U9 -> 0.60033352 | W9: =AC9 -> 0 | Z9: 评论测评费用+买家秀视频1000美金以内 | AD9: 350 | AE9: =AD9/30 -> 11.666667
B10: 第7周 | C10: =价格策略模拟!B5 -> 17.99 | D10: =价格策略模拟!C5 -> 0.15 | E10: =价格策略模拟!D5 -> 0 | F10: =SUM(C10*(1-D10-E10)) -> 15.2915 | G10: =J10*S10 -> 26.25 | H10: =J10*Q10 -> 78.75 | I10: =SUM(G10:H10) -> 105 | J10: 7 | K10: =CPC模拟表格!V10 -> 13.5 | L10: =SUM(H10*-K10) -> -1063.125 | M10: =毛利模拟盈亏!T10 -> 149.53335 | N10: =SUM(L10:M10) -> -913.59165 | P10: =AE10 -> 15 | Q10: =P10*0.75 -> 11.25 | R10: =1-Q10/P10 -> 0.25 | S10: =SUM(P10-Q10) -> 3.75 | T10: =SUM(L10/J10) -> -151.875 | U10: =毛利模拟盈亏!V10 -> 1888.95 | V10: =-L10/U10 -> 0.56281267 | W10: =AC10 -> 0 | Z10: 备注：可以新建子体测评做评论，再合并（测评10个） | AD10: 450 | AE10: =AD10/30 -> 15
B11: 第8周 | C11: =价格策略模拟!B5 -> 17.99 | D11: =价格策略模拟!C5 -> 0.15 | E11: =价格策略模拟!D5 -> 0 | F11: =SUM(C11*(1-D11-E11)) -> 15.2915 | G11: =J11*S11 -> 32.666667 | H11: =J11*Q11 -> 98 | I11: =SUM(G11:H11) -> 130.66667 | J11: 7 | K11: =CPC模拟表格!V11 -> 13.5 | L11: =SUM(H11*-K11) -> -1323 | M11: =毛利模拟盈亏!T11 -> 186.08595 | N11: =SUM(L11:M11) -> -1136.9141 | P11: =AE11 -> 18.666667 | Q11: =P11*0.75 -> 14 | R11: =1-Q11/P11 -> 0.25 | S11: =SUM(P11-Q11) -> 4.6666667 | T11: =SUM(L11/J11) -> -189 | U11: =毛利模拟盈亏!V11 -> 2350.6933 | V11: =-L11/U11 -> 0.56281267 | W11: =AC11 -> 0 | AD11: 560 | AE11: =AD11/30 -> 18.666667
A12: 第三阶段 | B12: 第9周 | C12: =价格策略模拟!B6 -> 17.99 | D12: =价格策略模拟!C6 -> 0.1 | E12: =价格策略模拟!D6 -> 0 | F12: =SUM(C12*(1-D12-E12)) -> 16.191 | G12: =J12*S12 -> 40.25 | H12: =J12*Q12 -> 120.75 | I12: =SUM(G12:H12) -> 161 | J12: 7 | K12: =CPC模拟表格!V12 -> 12.727273 | L12: =SUM(H12*-K12) -> -1536.8182 | M12: =毛利模拟盈亏!T12 -> 352.29238 | N12: =SUM(L12:M12) -> -1184.5258 | O12: 200 | P12: =AE12 -> 23 | Q12: =P12*0.75 -> 17.25 | R12: =1-Q12/P12 -> 0.25 | S12: =SUM(P12-Q12) -> 5.75 | T12: =SUM(L12/J12) -> -219.54545 | U12: =毛利模拟盈亏!V12 -> 2896.39 | V12: =-L12/U12 -> 0.53059781 | W12: =AC12 -> 0 | AD12: 690 | AE12: =AD12/30 -> 23
B13: 第10周 | C13: =价格策略模拟!B6 -> 17.99 | D13: =价格策略模拟!C6 -> 0.1 | E13: =价格策略模拟!D6 -> 0 | F13: =SUM(C13*(1-D13-E13)) -> 16.191 | G13: =J13*S13 -> 72.8 | H13: =J13*Q13 -> 109.2 | I13: =SUM(G13:H13) -> 182 | J13: 7 | K13: =CPC模拟表格!V13 -> 12.727273 | L13: =SUM(H13*-K13) -> -1389.8182 | M13: =毛利模拟盈亏!T13 -> 398.24356 | N13: =SUM(L13:M13) -> -991.57462 | P13: =AE13 -> 26 | Q13: =P13*0.6 -> 15.6 | R13: =1-Q13/P13 -> 0.4 | S13: =SUM(P13-Q13) -> 10.4 | T13: =SUM(L13/J13) -> -198.54545 | U13: =毛利模拟盈亏!V13 -> 3274.18 | V13: =-L13/U13 -> 0.42447825 | W13: =AC13 -> 0 | Z13: 1.链接细节 | AD13: 780 | AE13: =AD13/30 -> 26
B14: 第11周 | C14: =价格策略模拟!B6 -> 17.99 | D14: =价格策略模拟!C6 -> 0.1 | E14: =价格策略模拟!D6 -> 0 | F14: =SUM(C14*(1-D14-E14)) -> 16.191 | G14: =J14*S14 -> 99.166667 | H14: =J14*Q14 -> 99.166667 | I14: =SUM(G14:H14) -> 198.33333 | J14: 7 | K14: =CPC模拟表格!V14 -> 12.727273 | L14: =SUM(H14*-K14) -> -1262.1212 | M14: =毛利模拟盈亏!T14 -> 433.98337 | N14: =SUM(L14:M14) -> -828.13785 | P14: =AE14 -> 28.333333 | Q14: =P14*0.5 -> 14.166667 | R14: =1-Q14/P14 -> 0.5 | S14: =SUM(P14-Q14) -> 14.166667 | T14: =SUM(L14/J14) -> -180.30303 | U14: =毛利模拟盈亏!V14 -> 3568.0167 | V14: =-L14/U14 -> 0.35373187 | W14: =AC14 -> 0 | Z14: 2.产品开售，做关联视频，买家秀视频，最少做10个以上 | AD14: 850 | AE14: =AD14/30 -> 28.333333
B15: 第12周 | C15: =价格策略模拟!B6 -> 17.99 | D15: =价格策略模拟!C6 -> 0.1 | E15: =价格策略模拟!D6 -> 0 | F15: =SUM(C15*(1-D15-E15)) -> 16.191 | G15: =J15*S15 -> 105 | H15: =J15*Q15 -> 105 | I15: =SUM(G15:H15) -> 210 | J15: 7 | K15: =CPC模拟表格!V15 -> 12.272727 | L15: =SUM(H15*-K15) -> -1288.6364 | M15: =毛利模拟盈亏!T15 -> 459.5118 | N15: =SUM(L15:M15) -> -829.12456 | P15: =AE15 -> 30 | Q15: =P15*0.5 -> 15 | R15: =1-Q15/P15 -> 0.5 | S15: =SUM(P15-Q15) -> 15 | T15: =SUM(L15/J15) -> -184.09091 | U15: =毛利模拟盈亏!V15 -> 3777.9 | V15: =-L15/U15 -> 0.34109859 | W15: =AC15 -> 20 | Z15: 3.单独开售做vine，6个站点做VINE评价 | AC15: 20 | AD15: 900 | AE15: =AD15/30 -> 30
A16: 第四阶段 | B16: 第13周 | C16: =价格策略模拟!B7 -> 17.99 | D16: =价格策略模拟!C7 -> 0.05 | E16: =价格策略模拟!D7 -> 0 | F16: =SUM(C16*(1-D16-E16)) -> 17.0905 | G16: =J16*S16 -> 105 | H16: =J16*Q16 -> 105 | I16: =SUM(G16:H16) -> 210 | J16: 7 | K16: =CPC模拟表格!V16 -> 10.833333 | L16: =SUM(H16*-K16) -> -1137.5 | M16: =毛利模拟盈亏!T16 -> 619.9569 | N16: =SUM(L16:M16) -> -517.5431 | O16: 300 | P16: =AE16 -> 30 | Q16: =P16*0.5 -> 15 | R16: =1-Q16/P16 -> 0.5 | S16: =SUM(P16-Q16) -> 15 | T16: =SUM(L16/J16) -> -162.5 | U16: =毛利模拟盈亏!V16 -> 3777.9 | V16: =-L16/U16 -> 0.3010932 | W16: =AC16 -> 0 | Z16: 4.有评论再启动广告，10条优质图片视频评论 | AD16: 900 | AE16: =AD16/30 -> 30
B17: 第14周 | C17: =价格策略模拟!B7 -> 17.99 | D17: =价格策略模拟!C7 -> 0.05 | E17: =价格策略模拟!D7 -> 0 | F17: =SUM(C17*(1-D17-E17)) -> 17.0905 | G17: =J17*S17 -> 105 | H17: =J17*Q17 -> 105 | I17: =SUM(G17:H17) -> 210 | J17: 7 | K17: =CPC模拟表格!V17 -> 10.833333 | L17: =SUM(H17*-K17) -> -1137.5 | M17: =毛利模拟盈亏!T17 -> 619.9569 | N17: =SUM(L17:M17) -> -517.5431 | P17: =AE17 -> 30 | Q17: =P17*0.5 -> 15 | R17: =1-Q17/P17 -> 0.5 | S17: =SUM(P17-Q17) -> 15 | T17: =SUM(L17/J17) -> -162.5 | U17: =毛利模拟盈亏!V17 -> 3777.9 | V17: =-L17/U17 -> 0.3010932 | W17: =AC17 -> 0 | AD17: 900 | AE17: =AD17/30 -> 30
B18: 第15周 | C18: =价格策略模拟!B7 -> 17.99 | D18: =价格策略模拟!C7 -> 0.05 | E18: =价格策略模拟!D7 -> 0 | F18: =SUM(C18*(1-D18-E18)) -> 17.0905 | G18: =J18*S18 -> 126 | H18: =J18*Q18 -> 84 | I18: =SUM(G18:H18) -> 210 | J18: 7 | K18: =CPC模拟表格!V18 -> 10.416667 | L18: =SUM(H18*-K18) -> -875 | M18: =毛利模拟盈亏!T18 -> 619.9569 | N18: =SUM(L18:M18) -> -255.0431 | P18: =AE18 -> 30 | Q18: =P18*0.4 -> 12 | R18: =1-Q18/P18 -> 0.6 | S18: =SUM(P18-Q18) -> 18 | T18: =SUM(L18/J18) -> -125 | U18: =毛利模拟盈亏!V18 -> 3777.9 | V18: =-L18/U18 -> 0.23161015 | W18: =AC18 -> 0 | AD18: 900 | AE18: =AD18/30 -> 30
B19: 第16周 | C19: =价格策略模拟!B7 -> 17.99 | D19: =价格策略模拟!C7 -> 0.05 | E19: =价格策略模拟!D7 -> 0 | F19: =SUM(C19*(1-D19-E19)) -> 17.0905 | G19: =J19*S19 -> 126 | H19: =J19*Q19 -> 84 | I19: =SUM(G19:H19) -> 210 | J19: 7 | K19: =CPC模拟表格!V19 -> 10.416667 | L19: =SUM(H19*-K19) -> -875 | M19: =毛利模拟盈亏!T19 -> 619.9569 | N19: =SUM(L19:M19) -> -255.0431 | P19: =AE19 -> 30 | Q19: =P19*0.4 -> 12 | R19: =1-Q19/P19 -> 0.6 | S19: =SUM(P19-Q19) -> 18 | T19: =SUM(L19/J19) -> -125 | U19: =毛利模拟盈亏!V19 -> 3777.9 | V19: =-L19/U19 -> 0.23161015 | W19: =AC19 -> 0 | AD19: 900 | AE19: =AD19/30 -> 30
A20: 第五阶段 | B20: 第17周 | C20: =价格策略模拟!B8 -> 17.99 | D20: =价格策略模拟!C8 -> 0.05 | E20: =价格策略模拟!D8 -> 0 | F20: =SUM(C20*(1-D20-E20)) -> 17.0905 | G20: =J20*S20 -> 126 | H20: =J20*Q20 -> 84 | I20: =SUM(G20:H20) -> 210 | J20: 7 | K20: =CPC模拟表格!V20 -> 9.2307692 | L20: =SUM(H20*-K20) -> -775.38462 | M20: =毛利模拟盈亏!T20 -> 619.9569 | N20: =SUM(L20:M20) -> -155.42772 | O20: 400 | P20: =AE20 -> 30 | Q20: =P20*0.4 -> 12 | R20: =1-Q20/P20 -> 0.6 | S20: =SUM(P20-Q20) -> 18 | T20: =SUM(L20/J20) -> -110.76923 | U20: =毛利模拟盈亏!V20 -> 3777.9 | V20: =-L20/U20 -> 0.20524223 | W20: =AC20 -> 0 | AD20: 900 | AE20: =AD20/30 -> 30
B21: 第18周 | C21: =价格策略模拟!B8 -> 17.99 | D21: =价格策略模拟!C8 -> 0.05 | E21: =价格策略模拟!D8 -> 0 | F21: =SUM(C21*(1-D21-E21)) -> 17.0905 | G21: =J21*S21 -> 126 | H21: =J21*Q21 -> 84 | I21: =SUM(G21:H21) -> 210 | J21: 7 | K21: =CPC模拟表格!V21 -> 9.2307692 | L21: =SUM(H21*-K21) -> -775.38462 | M21: =毛利模拟盈亏!T21 -> 619.9569 | N21: =SUM(L21:M21) -> -155.42772 | P21: =AE21 -> 30 | Q21: =P21*0.4 -> 12 | R21: =1-Q21/P21 -> 0.6 | S21: =SUM(P21-Q21) -> 18 | T21: =SUM(L21/J21) -> -110.76923 | U21: =毛利模拟盈亏!V21 -> 3777.9 | V21: =-L21/U21 -> 0.20524223 | W21: =AC21 -> 0 | AD21: 900 | AE21: =AD21/30 -> 30
B22: 第19周 | C22: =价格策略模拟!B8 -> 17.99 | D22: =价格策略模拟!C8 -> 0.05 | E22: =价格策略模拟!D8 -> 0 | F22: =SUM(C22*(1-D22-E22)) -> 17.0905 | G22: =J22*S22 -> 126 | H22: =J22*Q22 -> 84 | I22: =SUM(G22:H22) -> 210 | J22: 7 | K22: =CPC模拟表格!V22 -> 8.8461538 | L22: =SUM(H22*-K22) -> -743.07692 | M22: =毛利模拟盈亏!T22 -> 619.9569 | N22: =SUM(L22:M22) -> -123.12002 | P22: =AE22 -> 30 | Q22: =P22*0.4 -> 12 | R22: =1-Q22/P22 -> 0.6 | S22: =SUM(P22-Q22) -> 18 | T22: =SUM(L22/J22) -> -106.15385 | U22: =毛利模拟盈亏!V22 -> 3777.9 | V22: =-L22/U22 -> 0.19669047 | W22: =AC22 -> 0 | AD22: 900 | AE22: =AD22/30 -> 30
B23: 第20周 | C23: =价格策略模拟!B8 -> 17.99 | D23: =价格策略模拟!C8 -> 0.05 | E23: =价格策略模拟!D8 -> 0 | F23: =SUM(C23*(1-D23-E23)) -> 17.0905 | G23: =J23*S23 -> 147 | H23: =J23*Q23 -> 63 | I23: =SUM(G23:H23) -> 210 | J23: 7 | K23: =CPC模拟表格!V23 -> 8.8461538 | L23: =SUM(H23*-K23) -> -557.30769 | M23: =毛利模拟盈亏!T23 -> 619.9569 | N23: =SUM(L23:M23) -> 62.649208 | P23: =AE23 -> 30 | Q23: =P23*0.3 -> 9 | R23: =1-Q23/P23 -> 0.7 | S23: =SUM(P23-Q23) -> 21 | T23: =SUM(L23/J23) -> -79.615385 | U23: =毛利模拟盈亏!V23 -> 3777.9 | V23: =-L23/U23 -> 0.14751785 | W23: =AC23 -> 0 | AD23: 900 | AE23: =AD23/30 -> 30
A24: 第六阶段 | B24: 第21周 | C24: =价格策略模拟!B9 -> 17.99 | D24: =价格策略模拟!C9 -> 0 | E24: =价格策略模拟!D9 -> 0 | F24: =SUM(C24*(1-D24-E24)) -> 17.99 | G24: =J24*S24 -> 147 | H24: =J24*Q24 -> 63 | I24: =SUM(G24:H24) -> 210 | J24: 7 | K24: =CPC模拟表格!V24 -> 7.8571429 | L24: =SUM(H24*-K24) -> -495 | M24: =毛利模拟盈亏!T24 -> 780.402 | N24: =SUM(L24:M24) -> 285.402 | O24: 500 | P24: =AE24 -> 30 | Q24: =P24*0.3 -> 9 | R24: =1-Q24/P24 -> 0.7 | S24: =SUM(P24-Q24) -> 21 | T24: =SUM(L24/J24) -> -70.714286 | U24: =毛利模拟盈亏!V24 -> 3777.9 | V24: =-L24/U24 -> 0.13102517 | W24: =AC24 -> 0 | AD24: 900 | AE24: =AD24/30 -> 30
B25: 第22周 | C25: =价格策略模拟!B9 -> 17.99 | D25: =价格策略模拟!C9 -> 0 | E25: =价格策略模拟!D9 -> 0 | F25: =SUM(C25*(1-D25-E25)) -> 17.99 | G25: =J25*S25 -> 147 | H25: =J25*Q25 -> 63 | I25: =SUM(G25:H25) -> 210 | J25: 7 | K25: =CPC模拟表格!V25 -> 7.8571429 | L25: =SUM(H25*-K25) -> -495 | M25: =毛利模拟盈亏!T25 -> 780.402 | N25: =SUM(L25:M25) -> 285.402 | P25: =AE25 -> 30 | Q25: =P25*0.3 -> 9 | R25: =1-Q25/P25 -> 0.7 | S25: =SUM(P25-Q25) -> 21 | T25: =SUM(L25/J25) -> -70.714286 | U25: =毛利模拟盈亏!V25 -> 3777.9 | V25: =-L25/U25 -> 0.13102517 | W25: =AC25 -> 0 | AD25: 900 | AE25: =AD25/30 -> 30
B26: 第23周 | C26: =价格策略模拟!B9 -> 17.99 | D26: =价格策略模拟!C9 -> 0 | E26: =价格策略模拟!D9 -> 0 | F26: =SUM(C26*(1-D26-E26)) -> 17.99 | G26: =J26*S26 -> 157.5 | H26: =J26*Q26 -> 52.5 | I26: =SUM(G26:H26) -> 210 | J26: 7 | K26: =CPC模拟表格!V26 -> 7.3333333 | L26: =SUM(H26*-K26) -> -385 | M26: =毛利模拟盈亏!T26 -> 780.402 | N26: =SUM(L26:M26) -> 395.402 | P26: =AE26 -> 30 | Q26: =P26*0.25 -> 7.5 | R26: =1-Q26/P26 -> 0.75 | S26: =SUM(P26-Q26) -> 22.5 | T26: =SUM(L26/J26) -> -55 | U26: =毛利模拟盈亏!V26 -> 3777.9 | V26: =-L26/U26 -> 0.10190847 | W26: =AC26 -> 0 | AD26: 900 | AE26: =AD26/30 -> 30
B27: 第24周 | C27: =价格策略模拟!B9 -> 17.99 | D27: =价格策略模拟!C9 -> 0 | E27: =价格策略模拟!D9 -> 0 | F27: =SUM(C27*(1-D27-E27)) -> 17.99 | G27: =J27*S27 -> 157.5 | H27: =J27*Q27 -> 52.5 | I27: =SUM(G27:H27) -> 210 | J27: 7 | K27: =CPC模拟表格!V27 -> 7.3333333 | L27: =SUM(H27*-K27) -> -385 | M27: =毛利模拟盈亏!T27 -> 780.402 | N27: =SUM(L27:M27) -> 395.402 | P27: =AE27 -> 30 | Q27: =P27*0.25 -> 7.5 | R27: =1-Q27/P27 -> 0.75 | S27: =SUM(P27-Q27) -> 22.5 | T27: =SUM(L27/J27) -> -55 | U27: =毛利模拟盈亏!V27 -> 3777.9 | V27: =-L27/U27 -> 0.10190847 | W27: =AC27 -> 0 | AD27: 900 | AE27: =AD27/30 -> 30
R28: =1-Q28/P28 -> #DIV/0! | W28: =AC28 -> 卖家精灵的【销量预测】查月销量 | AC28: 卖家精灵的【销量预测】查月销量
A29: 阶段盈亏真实数据 | R29: =1-Q29/P29 -> #DIV/0!
A30: 第一阶段 | B30: 第1周 | R30: =1-Q30/P30 -> #DIV/0! | W30: =AC30 -> 0
B31: 第2周 | R31: =1-Q31/P31 -> #DIV/0! | W31: =AC31 -> 0
B32: 第3周 | R32: =1-Q32/P32 -> #DIV/0! | W32: =AC32 -> 0
B33: 第4周 | R33: =1-Q33/P33 -> #DIV/0! | W33: =AC33 -> 0
A34: 第二阶段 | B34: 第5周 | R34: =1-Q34/P34 -> #DIV/0! | W34: =AC34 -> 0
B35: 第6周 | R35: =1-Q35/P35 -> #DIV/0! | W35: =AC35 -> 0
B36: 第7周 | R36: =1-Q36/P36 -> #DIV/0! | W36: =AC36 -> 0
B37: 第8周 | R37: =1-Q37/P37 -> #DIV/0! | W37: =AC37 -> 0
A38: 第三阶段 | B38: 第9周 | R38: =1-Q38/P38 -> #DIV/0! | W38: =AC38 -> 0
B39: 第10周 | R39: =1-Q39/P39 -> #DIV/0! | W39: =AC39 -> 0
B40: 第11周 | R40: =1-Q40/P40 -> #DIV/0! | W40: =AC40 -> 0
B41: 第12周 | R41: =1-Q41/P41 -> #DIV/0! | W41: =AC41 -> 0
A42: 第四阶段 | B42: 第13周 | R42: =1-Q42/P42 -> #DIV/0! | W42: =AC42 -> 0
B43: 第14周 | R43: =1-Q43/P43 -> #DIV/0! | W43: =AC43 -> 0
B44: 第15周 | R44: =1-Q44/P44 -> #DIV/0! | W44: =AC44 -> 0
B45: 第16周 | R45: =1-Q45/P45 -> #DIV/0! | W45: =AC45 -> 0
A46: 第五阶段 | B46: 第17周 | R46: =1-Q46/P46 -> #DIV/0! | W46: =AC46 -> 0
B47: 第18周 | R47: =1-Q47/P47 -> #DIV/0! | W47: =AC47 -> 0
B48: 第19周 | R48: =1-Q48/P48 -> #DIV/0! | W48: =AC48 -> 0
B49: 第20周 | R49: =1-Q49/P49 -> #DIV/0! | W49: =AC49 -> 0
A50: 第六阶段 | B50: 第21周 | R50: =1-Q50/P50 -> #DIV/0! | W50: =AC50 -> 0
B51: 第22周 | R51: =1-Q51/P51 -> #DIV/0! | W51: =AC51 -> 0
B52: 第23周 | R52: =1-Q52/P52 -> #DIV/0! | W52: =AC52 -> 0
B53: 第24周 | R53: =1-Q53/P53 -> #DIV/0! | W53: =AC53 -> 0

Sheet CPC模拟表格
A1: 常规数据 | N1: 广告数据 | AB1: 实时更新 | AC1: 操作备注
A2: 阶段 | B2: 周期 | C2: 价格 | D2: 站内 coupon | E2: 站内 code | F2: 折后价 | G2: 新品 榜单 | H2: 小类目 排名 | I2: 总 销量 | J2: 总访 问量 | K2: CVR | L2: 评论 数量 | M2: 评分 | N2: 曝光量 | O2: 广告 点击 | P2: CTR | Q2: 广告单 | R2: CVR | S2: 平均 CPC | T2: 花费 | U2: ACOS | V2: CPA | W2: 日均 广告费 | X2: 自然 访问 | Y2: 自然 订单 | Z2: 自然 单占比 | AA2: 最终 盈亏 | AB2: 质量分 | AC2: 运营调整 | AD2: 广告操作
C3: 与价格模拟表一样 | D3: 与价格模拟表一样 | E3: 与价格模拟表一样 | H3: 数据来源阶段总盈亏 | O3: 公式 | Q3: 数据来源阶段总盈亏 | R3: 转化率参考竞品 用极目可查 | S3: 极目/SIF/卖家精灵都可以 | T3: 1.花费=广告点击*cpc | U3: 2.acos=cpc/转化率/客单价 | V3: 如何得出CPA？ | W3: 公式
A4: 第一阶段 | B4: 第1周 | C4: =价格策略模拟!B4 -> 17.99 | D4: 0.3 | E4: =价格策略模拟!D4 -> 0 | F4: =SUM(C4*(1-D4-E4)) -> 12.593 | H4: =阶段总盈亏!AC4 -> 0 | O4: =SUM(Q4/R4) -> 132.63158 | Q4: =阶段总盈亏!H4 -> 12.6 | R4: 0.095 | S4: 1.5 | T4: =SUM(O4*S4) -> 198.94737 | U4: =SUM(S4/R4/C4) -> 0.87768058 | V4: =SUM(T4/Q4) -> 15.789474 | W4: =T4/7 -> 28.421053
B5: 第2周 | C5: =价格策略模拟!B4 -> 17.99 | D5: =价格策略模拟!C4 -> 0.2 | E5: =价格策略模拟!D4 -> 0 | F5: =SUM(C5*(1-D5-E5)) -> 14.392 | H5: =阶段总盈亏!AC5 -> 0 | O5: =SUM(Q5/R5) -> 198.94737 | Q5: =阶段总盈亏!H5 -> 18.9 | R5: 0.095 | S5: 1.45 | T5: =SUM(O5*S5) -> 288.47368 | U5: =SUM(S5/R5/C5) -> 0.84842456 | V5: =SUM(T5/Q5) -> 15.263158 | W5: =T5/7 -> 41.210526
B6: 第3周 | C6: =价格策略模拟!B4 -> 17.99 | D6: =价格策略模拟!C4 -> 0.2 | E6: =价格策略模拟!D4 -> 0 | F6: =SUM(C6*(1-D6-E6)) -> 14.392 | H6: =阶段总盈亏!AC6 -> 0 | O6: =SUM(Q6/R6) -> 294.73684 | Q6: =阶段总盈亏!H6 -> 28 | R6: 0.095 | S6: 1.4 | T6: =SUM(O6*S6) -> 412.63158 | U6: =SUM(S6/R6/C6) -> 0.81916854 | V6: =SUM(T6/Q6) -> 14.736842 | W6: =T6/7 -> 58.947368
B7: 第4周 | C7: =价格策略模拟!B4 -> 17.99 | D7: =价格策略模拟!C4 -> 0.2 | E7: =价格策略模拟!D4 -> 0 | F7: =SUM(C7*(1-D7-E7)) -> 14.392 | H7: =阶段总盈亏!AC7 -> 0 | O7: =SUM(Q7/R7) -> 412.63158 | Q7: =阶段总盈亏!H7 -> 39.2 | R7: 0.095 | S7: 1.35 | T7: =SUM(O7*S7) -> 557.05263 | U7: =SUM(S7/R7/C7) -> 0.78991252 | V7: =SUM(T7/Q7) -> 14.210526 | W7: =T7/7 -> 79.578947
A8: 第二阶段 | B8: 第5周 | C8: =价格策略模拟!B5 -> 17.99 | D8: =价格策略模拟!C5 -> 0.15 | E8: =价格策略模拟!D5 -> 0 | F8: =SUM(C8*(1-D8-E8)) -> 15.2915 | H8: =阶段总盈亏!AC8 -> 0 | O8: =SUM(Q8/R8) -> 504 | Q8: =阶段总盈亏!H8 -> 50.4 | R8: 0.1 | S8: 1.35 | T8: =SUM(O8*S8) -> 680.4 | U8: =SUM(S8/R8/C8) -> 0.7504169 | V8: =SUM(T8/Q8) -> 13.5 | W8: =T8/7 -> 97.2
B9: 第6周 | C9: =价格策略模拟!B5 -> 17.99 | D9: =价格策略模拟!C5 -> 0.15 | E9: =价格策略模拟!D5 -> 0 | F9: =SUM(C9*(1-D9-E9)) -> 15.2915 | H9: =阶段总盈亏!AC9 -> 0 | O9: =SUM(Q9/R9) -> 653.33333 | Q9: =阶段总盈亏!H9 -> 65.333333 | R9: 0.1 | S9: 1.35 | T9: =SUM(O9*S9) -> 882 | U9: =SUM(S9/R9/C9) -> 0.7504169 | V9: =SUM(T9/Q9) -> 13.5 | W9: =T9/7 -> 126
B10: 第7周 | C10: =价格策略模拟!B5 -> 17.99 | D10: =价格策略模拟!C5 -> 0.15 | E10: =价格策略模拟!D5 -> 0 | F10: =SUM(C10*(1-D10-E10)) -> 15.2915 | H10: =阶段总盈亏!AC10 -> 0 | O10: =SUM(Q10/R10) -> 787.5 | Q10: =阶段总盈亏!H10 -> 78.75 | R10: 0.1 | S10: 1.35 | T10: =SUM(O10*S10) -> 1063.125 | U10: =SUM(S10/R10/C10) -> 0.7504169 | V10: =SUM(T10/Q10) -> 13.5 | W10: =T10/7 -> 151.875
B11: 第8周 | C11: =价格策略模拟!B5 -> 17.99 | D11: =价格策略模拟!C5 -> 0.15 | E11: =价格策略模拟!D5 -> 0 | F11: =SUM(C11*(1-D11-E11)) -> 15.2915 | H11: =阶段总盈亏!AC11 -> 0 | O11: =SUM(Q11/R11) -> 980 | Q11: =阶段总盈亏!H11 -> 98 | R11: 0.1 | S11: 1.35 | T11: =SUM(O11*S11) -> 1323 | U11: =SUM(S11/R11/C11) -> 0.7504169 | V11: =SUM(T11/Q11) -> 13.5 | W11: =T11/7 -> 189
A12: 第三阶段 | B12: 第9周 | C12: =价格策略模拟!B6 -> 17.99 | D12: =价格策略模拟!C6 -> 0.1 | E12: =价格策略模拟!D6 -> 0 | F12: =SUM(C12*(1-D12-E12)) -> 16.191 | H12: =阶段总盈亏!AC12 -> 0 | O12: =SUM(Q12/R12) -> 1097.7273 | Q12: =阶段总盈亏!H12 -> 120.75 | R12: 0.11 | S12: 1.4 | T12: =SUM(O12*S12) -> 1536.8182 | U12: =SUM(S12/R12/C12) -> 0.70746374 | V12: =SUM(T12/Q12) -> 12.727273 | W12: =T12/7 -> 219.54545
B13: 第10周 | C13: =价格策略模拟!B6 -> 17.99 | D13: =价格策略模拟!C6 -> 0.1 | E13: =价格策略模拟!D6 -> 0 | F13: =SUM(C13*(1-D13-E13)) -> 16.191 | H13: =阶段总盈亏!AC13 -> 0 | O13: =SUM(Q13/R13) -> 992.72727 | Q13: =阶段总盈亏!H13 -> 109.2 | R13: 0.11 | S13: 1.4 | T13: =SUM(O13*S13) -> 1389.8182 | U13: =SUM(S13/R13/C13) -> 0.70746374 | V13: =SUM(T13/Q13) -> 12.727273 | W13: =T13/7 -> 198.54545
B14: 第11周 | C14: =价格策略模拟!B6 -> 17.99 | D14: =价格策略模拟!C6 -> 0.1 | E14: =价格策略模拟!D6 -> 0 | F14: =SUM(C14*(1-D14-E14)) -> 16.191 | H14: =阶段总盈亏!AC14 -> 0 | O14: =SUM(Q14/R14) -> 901.51515 | Q14: =阶段总盈亏!H14 -> 99.166667 | R14: 0.11 | S14: 1.4 | T14: =SUM(O14*S14) -> 1262.1212 | U14: =SUM(S14/R14/C14) -> 0.70746374 | V14: =SUM(T14/Q14) -> 12.727273 | W14: =T14/7 -> 180.30303
B15: 第12周 | C15: =价格策略模拟!B6 -> 17.99 | D15: =价格策略模拟!C6 -> 0.1 | E15: =价格策略模拟!D6 -> 0 | F15: =SUM(C15*(1-D15-E15)) -> 16.191 | H15: =阶段总盈亏!AC15 -> 20 | O15: =SUM(Q15/R15) -> 954.54545 | Q15: =阶段总盈亏!H15 -> 105 | R15: 0.11 | S15: 1.35 | T15: =SUM(O15*S15) -> 1288.6364 | U15: =SUM(S15/R15/C15) -> 0.68219718 | V15: =SUM(T15/Q15) -> 12.272727 | W15: =T15/7 -> 184.09091
A16: 第四阶段 | B16: 第13周 | C16: =价格策略模拟!B7 -> 17.99 | D16: =价格策略模拟!C7 -> 0.05 | E16: =价格策略模拟!D7 -> 0 | F16: =SUM(C16*(1-D16-E16)) -> 17.0905 | H16: =阶段总盈亏!AC16 -> 0 | O16: =SUM(Q16/R16) -> 875 | Q16: =阶段总盈亏!H16 -> 105 | R16: 0.12 | S16: 1.3 | T16: =SUM(O16*S16) -> 1137.5 | U16: =SUM(S16/R16/C16) -> 0.6021864 | V16: =SUM(T16/Q16) -> 10.833333 | W16: =T16/7 -> 162.5
B17: 第14周 | C17: =价格策略模拟!B7 -> 17.99 | D17: =价格策略模拟!C7 -> 0.05 | E17: =价格策略模拟!D7 -> 0 | F17: =SUM(C17*(1-D17-E17)) -> 17.0905 | H17: =阶段总盈亏!AC17 -> 0 | O17: =SUM(Q17/R17) -> 875 | Q17: =阶段总盈亏!H17 -> 105 | R17: 0.12 | S17: 1.3 | T17: =SUM(O17*S17) -> 1137.5 | U17: =SUM(S17/R17/C17) -> 0.6021864 | V17: =SUM(T17/Q17) -> 10.833333 | W17: =T17/7 -> 162.5
B18: 第15周 | C18: =价格策略模拟!B7 -> 17.99 | D18: =价格策略模拟!C7 -> 0.05 | E18: =价格策略模拟!D7 -> 0 | F18: =SUM(C18*(1-D18-E18)) -> 17.0905 | H18: =阶段总盈亏!AC18 -> 0 | O18: =SUM(Q18/R18) -> 700 | Q18: =阶段总盈亏!H18 -> 84 | R18: 0.12 | S18: 1.25 | T18: =SUM(O18*S18) -> 875 | U18: =SUM(S18/R18/C18) -> 0.57902538 | V18: =SUM(T18/Q18) -> 10.416667 | W18: =T18/7 -> 125
B19: 第16周 | C19: =价格策略模拟!B7 -> 17.99 | D19: =价格策略模拟!C7 -> 0.05 | E19: =价格策略模拟!D7 -> 0 | F19: =SUM(C19*(1-D19-E19)) -> 17.0905 | H19: =阶段总盈亏!AC19 -> 0 | O19: =SUM(Q19/R19) -> 700 | Q19: =阶段总盈亏!H19 -> 84 | R19: 0.12 | S19: 1.25 | T19: =SUM(O19*S19) -> 875 | U19: =SUM(S19/R19/C19) -> 0.57902538 | V19: =SUM(T19/Q19) -> 10.416667 | W19: =T19/7 -> 125
A20: 第五阶段 | B20: 第17周 | C20: =价格策略模拟!B8 -> 17.99 | D20: =价格策略模拟!C8 -> 0.05 | E20: =价格策略模拟!D8 -> 0 | F20: =SUM(C20*(1-D20-E20)) -> 17.0905 | H20: =阶段总盈亏!AC20 -> 0 | O20: =SUM(Q20/R20) -> 646.15385 | Q20: =阶段总盈亏!H20 -> 84 | R20: 0.13 | S20: 1.2 | T20: =SUM(O20*S20) -> 775.38462 | U20: =SUM(S20/R20/C20) -> 0.51310557 | V20: =SUM(T20/Q20) -> 9.2307692 | W20: =T20/7 -> 110.76923
B21: 第18周 | C21: =价格策略模拟!B8 -> 17.99 | D21: =价格策略模拟!C8 -> 0.05 | E21: =价格策略模拟!D8 -> 0 | F21: =SUM(C21*(1-D21-E21)) -> 17.0905 | H21: =阶段总盈亏!AC21 -> 0 | O21: =SUM(Q21/R21) -> 646.15385 | Q21: =阶段总盈亏!H21 -> 84 | R21: 0.13 | S21: 1.2 | T21: =SUM(O21*S21) -> 775.38462 | U21: =SUM(S21/R21/C21) -> 0.51310557 | V21: =SUM(T21/Q21) -> 9.2307692 | W21: =T21/7 -> 110.76923
B22: 第19周 | C22: =价格策略模拟!B8 -> 17.99 | D22: =价格策略模拟!C8 -> 0.05 | E22: =价格策略模拟!D8 -> 0 | F22: =SUM(C22*(1-D22-E22)) -> 17.0905 | H22: =阶段总盈亏!AC22 -> 0 | O22: =SUM(Q22/R22) -> 646.15385 | Q22: =阶段总盈亏!H22 -> 84 | R22: 0.13 | S22: 1.15 | T22: =SUM(O22*S22) -> 743.07692 | U22: =SUM(S22/R22/C22) -> 0.49172617 | V22: =SUM(T22/Q22) -> 8.8461538 | W22: =T22/7 -> 106.15385
B23: 第20周 | C23: =价格策略模拟!B8 -> 17.99 | D23: =价格策略模拟!C8 -> 0.05 | E23: =价格策略模拟!D8 -> 0 | F23: =SUM(C23*(1-D23-E23)) -> 17.0905 | H23: =阶段总盈亏!AC23 -> 0 | O23: =SUM(Q23/R23) -> 484.61538 | Q23: =阶段总盈亏!H23 -> 63 | R23: 0.13 | S23: 1.15 | T23: =SUM(O23*S23) -> 557.30769 | U23: =SUM(S23/R23/C23) -> 0.49172617 | V23: =SUM(T23/Q23) -> 8.8461538 | W23: =T23/7 -> 79.615385
A24: 第六阶段 | B24: 第21周 | C24: =价格策略模拟!B9 -> 17.99 | D24: =价格策略模拟!C9 -> 0 | E24: =价格策略模拟!D9 -> 0 | F24: =SUM(C24*(1-D24-E24)) -> 17.99 | H24: =阶段总盈亏!AC24 -> 0 | O24: =SUM(Q24/R24) -> 450 | Q24: =阶段总盈亏!H24 -> 63 | R24: 0.14 | S24: 1.1 | T24: =SUM(O24*S24) -> 495 | U24: =SUM(S24/R24/C24) -> 0.43675058 | V24: =SUM(T24/Q24) -> 7.8571429 | W24: =T24/7 -> 70.714286
B25: 第22周 | C25: =价格策略模拟!B9 -> 17.99 | D25: =价格策略模拟!C9 -> 0 | E25: =价格策略模拟!D9 -> 0 | F25: =SUM(C25*(1-D25-E25)) -> 17.99 | H25: =阶段总盈亏!AC25 -> 0 | O25: =SUM(Q25/R25) -> 450 | Q25: =阶段总盈亏!H25 -> 63 | R25: 0.14 | S25: 1.1 | T25: =SUM(O25*S25) -> 495 | U25: =SUM(S25/R25/C25) -> 0.43675058 | V25: =SUM(T25/Q25) -> 7.8571429 | W25: =T25/7 -> 70.714286
B26: 第23周 | C26: =价格策略模拟!B9 -> 17.99 | D26: =价格策略模拟!C9 -> 0 | E26: =价格策略模拟!D9 -> 0 | F26: =SUM(C26*(1-D26-E26)) -> 17.99 | H26: =阶段总盈亏!AC26 -> 0 | O26: =SUM(Q26/R26) -> 350 | Q26: =阶段总盈亏!H26 -> 52.5 | R26: 0.15 | S26: 1.1 | T26: =SUM(O26*S26) -> 385 | U26: =SUM(S26/R26/C26) -> 0.40763387 | V26: =SUM(T26/Q26) -> 7.3333333 | W26: =T26/7 -> 55
B27: 第24周 | C27: =价格策略模拟!B9 -> 17.99 | D27: =价格策略模拟!C9 -> 0 | E27: =价格策略模拟!D9 -> 0 | F27: =SUM(C27*(1-D27-E27)) -> 17.99 | H27: =阶段总盈亏!AC27 -> 0 | O27: =SUM(Q27/R27) -> 350 | Q27: =阶段总盈亏!H27 -> 52.5 | R27: 0.15 | S27: 1.1 | T27: =SUM(O27*S27) -> 385 | U27: =SUM(S27/R27/C27) -> 0.40763387 | V27: =SUM(T27/Q27) -> 7.3333333 | W27: =T27/7 -> 55
R28: 搜索词点击转化率 ABA数据里，ASIN视图里 需要数据加工
R29: 竞品的转化率，极目软件可查
R30: 类目平均转化率在增长建议里面-选品指南针-类目分析-输入关键词找品类-有转化率，有退货率
A31: 广告真实数据
A32: 常规数据 | N32: 广告数据 | AB32: 实时更新 | AC32: 操作备注
A33: 阶段 | B33: 周 | C33: 价格 | D33: 站内 coupon | E33: 站内 code | F33: 折后价 | G33: 新品 榜单 | H33: 小类目 排名 | I33: 总 销量 | J33: 总访 问量 | K33: CVR | L33: 评论 数量 | M33: 评分 | N33: 曝光量 | O33: 点击量 | P33: CTR | Q33: 广告单 | R33: CVR | S33: 平均 CPC | T33: 花费 | U33: ACOS | V33: CPA | W33: 日均 广告费 | X33: 自然 访问 | Y33: 自然 订单 | Z33: 自然 单占比 | AA33: 最终 盈亏 | AB33: 质量分 | AC33: 运营调整 | AD33: 广告操作
A34: 第一阶段 | B34: 第1周
B35: 第2周
B36: 第3周
B37: 第4周
A38: 第二阶段 | B38: 第5周
B39: 第6周
B40: 第7周
B41: 第8周
A42: 第三阶段 | B42: 第9周
B43: 第10周
B44: 第11周
B45: 第12周
A46: 第四阶段 | B46: 第13周
B47: 第14周
B48: 第15周
B49: 第16周
A50: 第五阶段 | B50: 第17周
B51: 第18周
B52: 第19周
B53: 第20周
A54: 第六阶段 | B54: 第21周
B55: 第22周
B56: 第23周
B57: 第24周

Sheet 毛利模拟盈亏
A1: 每日盈亏数据预估
A2: 阶段 | B2: 周期 | C2: 定价 | D2: coupon | E2: code | F2: 折后价 | G2: FBA 配送费 | H2: 亚马逊 佣金 | I2: 账号 回款 | J2: 仓储费+入库配置费 | K2: coupon 费用 | L2: 产品 成本 | M2: 物流费 | N2: 退货成本(公式后面加的是单套产品的移除费） | O2: 退货率 | P2: 每单平摊 退货成本 | Q2: 每单 毛利 | R2: 毛利率 | S2: 订单 数量 | T2: 阶段 订单 亏损 | U2: 阶段 订单 总盈亏 | V2: 每周 销售额 | W2: 实际回款
G3: 公式 来源《价格模拟表》 | L3: 公式 来源《价格模拟表》 | M3: 公式 来源《价格模拟表》 | N3: 公式 来源《价格模拟表》 | O3: 公式 来源《价格模拟表》 | S3: *来源 阶段总盈亏，需要拆解日销量*7天 | T3: 公式 | U3: 公式 | W3: 产品成本+头程运+毛利润）*订单量-广告费
A4: 第一阶段 | B4: 第1周 | C4: =价格策略模拟!B4 -> 17.99 | D4: =价格策略模拟!C4 -> 0.2 | E4: =价格策略模拟!D4 -> 0 | F4: =SUM(C4*(1-D4-E4)) -> 14.392 | G4: =价格策略模拟!F4 -> 6 | H4: =SUM(F4*15%) -> 2.1588 | I4: =SUM(F4-G4-H4) -> 6.2332 | J4: 0.22 | K4: 0 | L4: =价格策略模拟!K4 -> 3.7 | M4: =价格策略模拟!L4 -> 1.4 | N4: =SUM(20%*15%*F4+G4+J4+L4+M4+0.65) -> 12.40176 | O4: =价格策略模拟!N4 -> 0.02 | P4: =SUM(N4*O4/(1-O4)) -> 0.25309714 | Q4: =SUM(I4-J4-K4-L4-M4-P4) -> 0.66010286 | R4: =SUM(Q4/C4) -> 0.036692766 | S4: =阶段总盈亏!I4 -> 14 | T4: =SUM(Q4*S4) -> 9.24144 | U4: =SUM(T4:T4) -> 9.24144 | V4: =S4*C4 -> 251.86 | W4: =(L4+M4+Q4)*S4 -> 80.64144
B5: 第2周 | C5: =价格策略模拟!B4 -> 17.99 | D5: =价格策略模拟!C4 -> 0.2 | E5: =价格策略模拟!D4 -> 0 | F5: =SUM(C5*(1-D5-E5)) -> 14.392 | G5: =G4 -> 6 | H5: =SUM(F5*15%) -> 2.1588 | I5: =SUM(F5-G5-H5) -> 6.2332 | J5: 0.22 | K5: 0 | L5: =L4 -> 3.7 | M5: =M4 -> 1.4 | N5: =SUM(20%*15%*F5+G5+J5+L5+M5+0.65) -> 12.40176 | O5: =O4 -> 0.02 | P5: =SUM(N5*O5/(1-O5)) -> 0.25309714 | Q5: =SUM(I5-J5-K5-L5-M5-P5) -> 0.66010286 | R5: =SUM(Q5/C5) -> 0.036692766 | S5: =阶段总盈亏!I5 -> 21 | T5: =SUM(Q5*S5) -> 13.86216 | U5: =SUM(T5:T5) -> 13.86216 | V5: =S5*C5 -> 377.79 | W5: =(L5+M5+Q5)*S5 -> 120.96216
B6: 第3周 | C6: =价格策略模拟!B4 -> 17.99 | D6: =价格策略模拟!C4 -> 0.2 | E6: =价格策略模拟!D4 -> 0 | F6: =SUM(C6*(1-D6-E6)) -> 14.392 | G6: =G5 -> 6 | H6: =SUM(F6*15%) -> 2.1588 | I6: =SUM(F6-G6-H6) -> 6.2332 | J6: 0.22 | K6: 0 | L6: =L5 -> 3.7 | M6: =M5 -> 1.4 | N6: =SUM(20%*15%*F6+G6+J6+L6+M6+0.65) -> 12.40176 | O6: =O5 -> 0.02 | P6: =SUM(N6*O6/(1-O6)) -> 0.25309714 | Q6: =SUM(I6-J6-K6-L6-M6-P6) -> 0.66010286 | R6: =SUM(Q6/C6) -> 0.036692766 | S6: =阶段总盈亏!I6 -> 35 | T6: =SUM(Q6*S6) -> 23.1036 | U6: =SUM(T6:T6) -> 23.1036 | V6: =S6*C6 -> 629.65 | W6: =(L6+M6+Q6)*S6 -> 201.6036
B7: 第4周 | C7: =价格策略模拟!B4 -> 17.99 | D7: =价格策略模拟!C4 -> 0.2 | E7: =价格策略模拟!D4 -> 0 | F7: =SUM(C7*(1-D7-E7)) -> 14.392 | G7: =G6 -> 6 | H7: =SUM(F7*15%) -> 2.1588 | I7: =SUM(F7-G7-H7) -> 6.2332 | J7: 0.22 | K7: 0 | L7: =L6 -> 3.7 | M7: =M6 -> 1.4 | N7: =SUM(20%*15%*F7+G7+J7+L7+M7+0.65) -> 12.40176 | O7: =O6 -> 0.02 | P7: =SUM(N7*O7/(1-O7)) -> 0.25309714 | Q7: =SUM(I7-J7-K7-L7-M7-P7) -> 0.66010286 | R7: =SUM(Q7/C7) -> 0.036692766 | S7: =阶段总盈亏!I7 -> 49 | T7: =SUM(Q7*S7) -> 32.34504 | U7: =SUM(T7:T7) -> 32.34504 | V7: =S7*C7 -> 881.51 | W7: =(L7+M7+Q7)*S7 -> 282.24504
A8: 第二阶段 | B8: 第5周 | C8: =价格策略模拟!B5 -> 17.99 | D8: =价格策略模拟!C5 -> 0.15 | E8: =价格策略模拟!D5 -> 0 | F8: =SUM(C8*(1-D8-E8)) -> 15.2915 | G8: =G7 -> 6 | H8: =SUM(F8*15%) -> 2.293725 | I8: =SUM(F8-G8-H8) -> 6.997775 | J8: 0.22 | K8: 0 | L8: =L7 -> 3.7 | M8: =M7 -> 1.4 | N8: =SUM(20%*15%*F8+G8+J8+L8+M8+0.65) -> 12.428745 | O8: =O7 -> 0.02 | P8: =SUM(N8*O8/(1-O8)) -> 0.25364786 | Q8: =SUM(I8-J8-K8-L8-M8-P8) -> 1.4241271 | R8: =SUM(Q8/C8) -> 0.079162154 | S8: =阶段总盈亏!I8 -> 63 | T8: =SUM(Q8*S8) -> 89.72001 | U8: =SUM(T8:T8) -> 89.72001 | V8: =S8*C8 -> 1133.37 | W8: =(L8+M8+Q8)*S8 -> 411.02001
B9: 第6周 | C9: =价格策略模拟!B5 -> 17.99 | D9: =价格策略模拟!C5 -> 0.15 | E9: =价格策略模拟!D5 -> 0 | F9: =SUM(C9*(1-D9-E9)) -> 15.2915 | G9: =G8 -> 6 | H9: =SUM(F9*15%) -> 2.293725 | I9: =SUM(F9-G9-H9) -> 6.997775 | J9: 0.22 | K9: 0 | L9: =L8 -> 3.7 | M9: =M8 -> 1.4 | N9: =SUM(20%*15%*F9+G9+J9+L9+M9+0.65) -> 12.428745 | O9: =O8 -> 0.02 | P9: =SUM(N9*O9/(1-O9)) -> 0.25364786 | Q9: =SUM(I9-J9-K9-L9-M9-P9) -> 1.4241271 | R9: =SUM(Q9/C9) -> 0.079162154 | S9: =阶段总盈亏!I9 -> 81.666667 | T9: =SUM(Q9*S9) -> 116.30372 | U9: =SUM(T9:T9) -> 116.30372 | V9: =S9*C9 -> 1469.1833 | W9: =(L9+M9+Q9)*S9 -> 532.80372
B10: 第7周 | C10: =价格策略模拟!B5 -> 17.99 | D10: =价格策略模拟!C5 -> 0.15 | E10: =价格策略模拟!D5 -> 0 | F10: =SUM(C10*(1-D10-E10)) -> 15.2915 | G10: =G9 -> 6 | H10: =SUM(F10*15%) -> 2.293725 | I10: =SUM(F10-G10-H10) -> 6.997775 | J10: 0.22 | K10: 0 | L10: =L9 -> 3.7 | M10: =M9 -> 1.4 | N10: =SUM(20%*15%*F10+G10+J10+L10+M10+0.65) -> 12.428745 | O10: =O9 -> 0.02 | P10: =SUM(N10*O10/(1-O10)) -> 0.25364786 | Q10: =SUM(I10-J10-K10-L10-M10-P10) -> 1.4241271 | R10: =SUM(Q10/C10) -> 0.079162154 | S10: =阶段总盈亏!I10 -> 105 | T10: =SUM(Q10*S10) -> 149.53335 | U10: =SUM(T10:T10) -> 149.53335 | V10: =S10*C10 -> 1888.95 | W10: =(L10+M10+Q10)*S10 -> 685.03335
B11: 第8周 | C11: =价格策略模拟!B5 -> 17.99 | D11: =价格策略模拟!C5 -> 0.15 | E11: =价格策略模拟!D5 -> 0 | F11: =SUM(C11*(1-D11-E11)) -> 15.2915 | G11: =G10 -> 6 | H11: =SUM(F11*15%) -> 2.293725 | I11: =SUM(F11-G11-H11) -> 6.997775 | J11: 0.22 | K11: 0 | L11: =L10 -> 3.7 | M11: =M10 -> 1.4 | N11: =SUM(20%*15%*F11+G11+J11+L11+M11+0.65) -> 12.428745 | O11: =O10 -> 0.02 | P11: =SUM(N11*O11/(1-O11)) -> 0.25364786 | Q11: =SUM(I11-J11-K11-L11-M11-P11) -> 1.4241271 | R11: =SUM(Q11/C11) -> 0.079162154 | S11: =阶段总盈亏!I11 -> 130.66667 | T11: =SUM(Q11*S11) -> 186.08595 | U11: =SUM(T11:T11) -> 186.08595 | V11: =S11*C11 -> 2350.6933 | W11: =(L11+M11+Q11)*S11 -> 852.48595
A12: 第三阶段 | B12: 第9周 | C12: =价格策略模拟!B6 -> 17.99 | D12: =价格策略模拟!C6 -> 0.1 | E12: =价格策略模拟!D6 -> 0 | F12: =SUM(C12*(1-D12-E12)) -> 16.191 | G12: =G11 -> 6 | H12: =SUM(F12*15%) -> 2.42865 | I12: =SUM(F12-G12-H12) -> 7.76235 | J12: 0.22 | K12: 0 | L12: =L11 -> 3.7 | M12: =M11 -> 1.4 | N12: =SUM(20%*15%*F12+G12+J12+L12+M12+0.65) -> 12.45573 | O12: =O11 -> 0.02 | P12: =SUM(N12*O12/(1-O12)) -> 0.25419857 | Q12: =SUM(I12-J12-K12-L12-M12-P12) -> 2.1881514 | R12: =SUM(Q12/C12) -> 0.12163154 | S12: =阶段总盈亏!I12 -> 161 | T12: =SUM(Q12*S12) -> 352.29238 | U12: =SUM(T12:T12) -> 352.29238 | V12: =S12*C12 -> 2896.39 | W12: =(L12+M12+Q12)*S12 -> 1173.3924
B13: 第10周 | C13: =价格策略模拟!B6 -> 17.99 | D13: =价格策略模拟!C6 -> 0.1 | E13: =价格策略模拟!D6 -> 0 | F13: =SUM(C13*(1-D13-E13)) -> 16.191 | G13: =G12 -> 6 | H13: =SUM(F13*15%) -> 2.42865 | I13: =SUM(F13-G13-H13) -> 7.76235 | J13: 0.22 | K13: 0 | L13: =L12 -> 3.7 | M13: =M12 -> 1.4 | N13: =SUM(20%*15%*F13+G13+J13+L13+M13+0.65) -> 12.45573 | O13: =O12 -> 0.02 | P13: =SUM(N13*O13/(1-O13)) -> 0.25419857 | Q13: =SUM(I13-J13-K13-L13-M13-P13) -> 2.1881514 | R13: =SUM(Q13/C13) -> 0.12163154 | S13: =阶段总盈亏!I13 -> 182 | T13: =SUM(Q13*S13) -> 398.24356 | U13: =SUM(T13:T13) -> 398.24356 | V13: =S13*C13 -> 3274.18 | W13: =(L13+M13+Q13)*S13 -> 1326.4436
B14: 第11周 | C14: =价格策略模拟!B6 -> 17.99 | D14: =价格策略模拟!C6 -> 0.1 | E14: =价格策略模拟!D6 -> 0 | F14: =SUM(C14*(1-D14-E14)) -> 16.191 | G14: =G13 -> 6 | H14: =SUM(F14*15%) -> 2.42865 | I14: =SUM(F14-G14-H14) -> 7.76235 | J14: 0.22 | K14: 0 | L14: =L13 -> 3.7 | M14: =M13 -> 1.4 | N14: =SUM(20%*15%*F14+G14+J14+L14+M14+0.65) -> 12.45573 | O14: =O13 -> 0.02 | P14: =SUM(N14*O14/(1-O14)) -> 0.25419857 | Q14: =SUM(I14-J14-K14-L14-M14-P14) -> 2.1881514 | R14: =SUM(Q14/C14) -> 0.12163154 | S14: =阶段总盈亏!I14 -> 198.33333 | T14: =SUM(Q14*S14) -> 433.98337 | U14: =SUM(T14:T14) -> 433.98337 | V14: =S14*C14 -> 3568.0167 | W14: =(L14+M14+Q14)*S14 -> 1445.4834
B15: 第12周 | C15: =价格策略模拟!B6 -> 17.99 | D15: =价格策略模拟!C6 -> 0.1 | E15: =价格策略模拟!D6 -> 0 | F15: =SUM(C15*(1-D15-E15)) -> 16.191 | G15: =G14 -> 6 | H15: =SUM(F15*15%) -> 2.42865 | I15: =SUM(F15-G15-H15) -> 7.76235 | J15: 0.22 | K15: 0 | L15: =L14 -> 3.7 | M15: =M14 -> 1.4 | N15: =SUM(20%*15%*F15+G15+J15+L15+M15+0.65) -> 12.45573 | O15: =O14 -> 0.02 | P15: =SUM(N15*O15/(1-O15)) -> 0.25419857 | Q15: =SUM(I15-J15-K15-L15-M15-P15) -> 2.1881514 | R15: =SUM(Q15/C15) -> 0.12163154 | S15: =阶段总盈亏!I15 -> 210 | T15: =SUM(Q15*S15) -> 459.5118 | U15: =SUM(T15:T15) -> 459.5118 | V15: =S15*C15 -> 3777.9 | W15: =(L15+M15+Q15)*S15 -> 1530.5118
A16: 第四阶段 | B16: 第13周 | C16: =价格策略模拟!B7 -> 17.99 | D16: =价格策略模拟!C7 -> 0.05 | E16: =价格策略模拟!D7 -> 0 | F16: =SUM(C16*(1-D16-E16)) -> 17.0905 | G16: =G15 -> 6 | H16: =SUM(F16*15%) -> 2.563575 | I16: =SUM(F16-G16-H16) -> 8.526925 | J16: 0.22 | K16: 0 | L16: =L15 -> 3.7 | M16: =M15 -> 1.4 | N16: =SUM(20%*15%*F16+G16+J16+L16+M16+0.65) -> 12.482715 | O16: =O15 -> 0.02 | P16: =SUM(N16*O16/(1-O16)) -> 0.25474929 | Q16: =SUM(I16-J16-K16-L16-M16-P16) -> 2.9521757 | R16: =SUM(Q16/C16) -> 0.16410093 | S16: =阶段总盈亏!I16 -> 210 | T16: =SUM(Q16*S16) -> 619.9569 | U16: =SUM(T16:T16) -> 619.9569 | V16: =S16*C16 -> 3777.9 | W16: =(L16+M16+Q16)*S16 -> 1690.9569
B17: 第14周 | C17: =价格策略模拟!B7 -> 17.99 | D17: =价格策略模拟!C7 -> 0.05 | E17: =价格策略模拟!D7 -> 0 | F17: =SUM(C17*(1-D17-E17)) -> 17.0905 | G17: =G16 -> 6 | H17: =SUM(F17*15%) -> 2.563575 | I17: =SUM(F17-G17-H17) -> 8.526925 | J17: 0.22 | K17: 0 | L17: =L16 -> 3.7 | M17: =M16 -> 1.4 | N17: =SUM(20%*15%*F17+G17+J17+L17+M17+0.65) -> 12.482715 | O17: =O16 -> 0.02 | P17: =SUM(N17*O17/(1-O17)) -> 0.25474929 | Q17: =SUM(I17-J17-K17-L17-M17-P17) -> 2.9521757 | R17: =SUM(Q17/C17) -> 0.16410093 | S17: =阶段总盈亏!I17 -> 210 | T17: =SUM(Q17*S17) -> 619.9569 | U17: =SUM(T17:T17) -> 619.9569 | V17: =S17*C17 -> 3777.9 | W17: =(L17+M17+Q17)*S17 -> 1690.9569
B18: 第15周 | C18: =价格策略模拟!B7 -> 17.99 | D18: =价格策略模拟!C7 -> 0.05 | E18: =价格策略模拟!D7 -> 0 | F18: =SUM(C18*(1-D18-E18)) -> 17.0905 | G18: =G17 -> 6 | H18: =SUM(F18*15%) -> 2.563575 | I18: =SUM(F18-G18-H18) -> 8.526925 | J18: 0.22 | K18: 0 | L18: =L17 -> 3.7 | M18: =M17 -> 1.4 | N18: =SUM(20%*15%*F18+G18+J18+L18+M18+0.65) -> 12.482715 | O18: =O17 -> 0.02 | P18: =SUM(N18*O18/(1-O18)) -> 0.25474929 | Q18: =SUM(I18-J18-K18-L18-M18-P18) -> 2.9521757 | R18: =SUM(Q18/C18) -> 0.16410093 | S18: =阶段总盈亏!I18 -> 210 | T18: =SUM(Q18*S18) -> 619.9569 | U18: =SUM(T18:T18) -> 619.9569 | V18: =S18*C18 -> 3777.9 | W18: =(L18+M18+Q18)*S18 -> 1690.9569
B19: 第16周 | C19: =价格策略模拟!B7 -> 17.99 | D19: =价格策略模拟!C7 -> 0.05 | E19: =价格策略模拟!D7 -> 0 | F19: =SUM(C19*(1-D19-E19)) -> 17.0905 | G19: =G18 -> 6 | H19: =SUM(F19*15%) -> 2.563575 | I19: =SUM(F19-G19-H19) -> 8.526925 | J19: 0.22 | K19: 0 | L19: =L18 -> 3.7 | M19: =M18 -> 1.4 | N19: =SUM(20%*15%*F19+G19+J19+L19+M19+0.65) -> 12.482715 | O19: =O18 -> 0.02 | P19: =SUM(N19*O19/(1-O19)) -> 0.25474929 | Q19: =SUM(I19-J19-K19-L19-M19-P19) -> 2.9521757 | R19: =SUM(Q19/C19) -> 0.16410093 | S19: =阶段总盈亏!I19 -> 210 | T19: =SUM(Q19*S19) -> 619.9569 | U19: =SUM(T19:T19) -> 619.9569 | V19: =S19*C19 -> 3777.9 | W19: =(L19+M19+Q19)*S19 -> 1690.9569
A20: 第五阶段 | B20: 第17周 | C20: =价格策略模拟!B8 -> 17.99 | D20: =价格策略模拟!C8 -> 0.05 | E20: =价格策略模拟!D8 -> 0 | F20: =SUM(C20*(1-D20-E20)) -> 17.0905 | G20: =G19 -> 6 | H20: =SUM(F20*15%) -> 2.563575 | I20: =SUM(F20-G20-H20) -> 8.526925 | J20: 0.22 | K20: 0 | L20: =L19 -> 3.7 | M20: =M19 -> 1.4 | N20: =SUM(20%*15%*F20+G20+J20+L20+M20+0.65) -> 12.482715 | O20: =O19 -> 0.02 | P20: =SUM(N20*O20/(1-O20)) -> 0.25474929 | Q20: =SUM(I20-J20-K20-L20-M20-P20) -> 2.9521757 | R20: =SUM(Q20/C20) -> 0.16410093 | S20: =阶段总盈亏!I20 -> 210 | T20: =SUM(Q20*S20) -> 619.9569 | U20: =SUM(T20:T20) -> 619.9569 | V20: =S20*C20 -> 3777.9 | W20: =(L20+M20+Q20)*S20 -> 1690.9569
B21: 第18周 | C21: =价格策略模拟!B8 -> 17.99 | D21: =价格策略模拟!C8 -> 0.05 | E21: =价格策略模拟!D8 -> 0 | F21: =SUM(C21*(1-D21-E21)) -> 17.0905 | G21: =G20 -> 6 | H21: =SUM(F21*15%) -> 2.563575 | I21: =SUM(F21-G21-H21) -> 8.526925 | J21: 0.22 | K21: 0 | L21: =L20 -> 3.7 | M21: =M20 -> 1.4 | N21: =SUM(20%*15%*F21+G21+J21+L21+M21+0.65) -> 12.482715 | O21: =O20 -> 0.02 | P21: =SUM(N21*O21/(1-O21)) -> 0.25474929 | Q21: =SUM(I21-J21-K21-L21-M21-P21) -> 2.9521757 | R21: =SUM(Q21/C21) -> 0.16410093 | S21: =阶段总盈亏!I21 -> 210 | T21: =SUM(Q21*S21) -> 619.9569 | U21: =SUM(T21:T21) -> 619.9569 | V21: =S21*C21 -> 3777.9 | W21: =(L21+M21+Q21)*S21 -> 1690.9569
B22: 第19周 | C22: =价格策略模拟!B8 -> 17.99 | D22: =价格策略模拟!C8 -> 0.05 | E22: =价格策略模拟!D8 -> 0 | F22: =SUM(C22*(1-D22-E22)) -> 17.0905 | G22: =G21 -> 6 | H22: =SUM(F22*15%) -> 2.563575 | I22: =SUM(F22-G22-H22) -> 8.526925 | J22: 0.22 | K22: 0 | L22: =L21 -> 3.7 | M22: =M21 -> 1.4 | N22: =SUM(20%*15%*F22+G22+J22+L22+M22+0.65) -> 12.482715 | O22: =O21 -> 0.02 | P22: =SUM(N22*O22/(1-O22)) -> 0.25474929 | Q22: =SUM(I22-J22-K22-L22-M22-P22) -> 2.9521757 | R22: =SUM(Q22/C22) -> 0.16410093 | S22: =阶段总盈亏!I22 -> 210 | T22: =SUM(Q22*S22) -> 619.9569 | U22: =SUM(T22:T22) -> 619.9569 | V22: =S22*C22 -> 3777.9 | W22: =(L22+M22+Q22)*S22 -> 1690.9569
B23: 第20周 | C23: =价格策略模拟!B8 -> 17.99 | D23: =价格策略模拟!C8 -> 0.05 | E23: =价格策略模拟!D8 -> 0 | F23: =SUM(C23*(1-D23-E23)) -> 17.0905 | G23: =G22 -> 6 | H23: =SUM(F23*15%) -> 2.563575 | I23: =SUM(F23-G23-H23) -> 8.526925 | J23: 0.22 | K23: 0 | L23: =L22 -> 3.7 | M23: =M22 -> 1.4 | N23: =SUM(20%*15%*F23+G23+J23+L23+M23+0.65) -> 12.482715 | O23: =O22 -> 0.02 | P23: =SUM(N23*O23/(1-O23)) -> 0.25474929 | Q23: =SUM(I23-J23-K23-L23-M23-P23) -> 2.9521757 | R23: =SUM(Q23/C23) -> 0.16410093 | S23: =阶段总盈亏!I23 -> 210 | T23: =SUM(Q23*S23) -> 619.9569 | U23: =SUM(T23:T23) -> 619.9569 | V23: =S23*C23 -> 3777.9 | W23: =(L23+M23+Q23)*S23 -> 1690.9569
A24: 第六阶段 | B24: 第21周 | C24: =价格策略模拟!B9 -> 17.99 | D24: =价格策略模拟!C9 -> 0 | E24: =价格策略模拟!D9 -> 0 | F24: =SUM(C24*(1-D24-E24)) -> 17.99 | G24: =G23 -> 6 | H24: =SUM(F24*15%) -> 2.6985 | I24: =SUM(F24-G24-H24) -> 9.2915 | J24: 0.22 | K24: 0 | L24: =L23 -> 3.7 | M24: =M23 -> 1.4 | N24: =SUM(20%*15%*F24+G24+J24+L24+M24+0.65) -> 12.5097 | O24: =O23 -> 0.02 | P24: =SUM(N24*O24/(1-O24)) -> 0.2553 | Q24: =SUM(I24-J24-K24-L24-M24-P24) -> 3.7162 | R24: =SUM(Q24/C24) -> 0.20657032 | S24: =阶段总盈亏!I24 -> 210 | T24: =SUM(Q24*S24) -> 780.402 | U24: =SUM(T24:T24) -> 780.402 | V24: =S24*C24 -> 3777.9 | W24: =(L24+M24+Q24)*S24 -> 1851.402
B25: 第22周 | C25: =价格策略模拟!B9 -> 17.99 | D25: =价格策略模拟!C9 -> 0 | E25: =价格策略模拟!D9 -> 0 | F25: =SUM(C25*(1-D25-E25)) -> 17.99 | G25: =G24 -> 6 | H25: =SUM(F25*15%) -> 2.6985 | I25: =SUM(F25-G25-H25) -> 9.2915 | J25: 0.22 | K25: 0 | L25: =L24 -> 3.7 | M25: =M24 -> 1.4 | N25: =SUM(20%*15%*F25+G25+J25+L25+M25+0.65) -> 12.5097 | O25: =O24 -> 0.02 | P25: =SUM(N25*O25/(1-O25)) -> 0.2553 | Q25: =SUM(I25-J25-K25-L25-M25-P25) -> 3.7162 | R25: =SUM(Q25/C25) -> 0.20657032 | S25: =阶段总盈亏!I25 -> 210 | T25: =SUM(Q25*S25) -> 780.402 | U25: =SUM(T25:T25) -> 780.402 | V25: =S25*C25 -> 3777.9 | W25: =(L25+M25+Q25)*S25 -> 1851.402
B26: 第23周 | C26: =价格策略模拟!B9 -> 17.99 | D26: =价格策略模拟!C9 -> 0 | E26: =价格策略模拟!D9 -> 0 | F26: =SUM(C26*(1-D26-E26)) -> 17.99 | G26: =G25 -> 6 | H26: =SUM(F26*15%) -> 2.6985 | I26: =SUM(F26-G26-H26) -> 9.2915 | J26: 0.22 | K26: 0 | L26: =L25 -> 3.7 | M26: =M25 -> 1.4 | N26: =SUM(20%*15%*F26+G26+J26+L26+M26+0.65) -> 12.5097 | O26: =O25 -> 0.02 | P26: =SUM(N26*O26/(1-O26)) -> 0.2553 | Q26: =SUM(I26-J26-K26-L26-M26-P26) -> 3.7162 | R26: =SUM(Q26/C26) -> 0.20657032 | S26: =阶段总盈亏!I26 -> 210 | T26: =SUM(Q26*S26) -> 780.402 | U26: =SUM(T26:T26) -> 780.402 | V26: =S26*C26 -> 3777.9 | W26: =(L26+M26+Q26)*S26 -> 1851.402
B27: 第24周 | C27: =价格策略模拟!B9 -> 17.99 | D27: =价格策略模拟!C9 -> 0 | E27: =价格策略模拟!D9 -> 0 | F27: =SUM(C27*(1-D27-E27)) -> 17.99 | G27: =G26 -> 6 | H27: =SUM(F27*15%) -> 2.6985 | I27: =SUM(F27-G27-H27) -> 9.2915 | J27: 0.22 | K27: 0 | L27: =L26 -> 3.7 | M27: =M26 -> 1.4 | N27: =SUM(20%*15%*F27+G27+J27+L27+M27+0.65) -> 12.5097 | O27: =O26 -> 0.02 | P27: =SUM(N27*O27/(1-O27)) -> 0.2553 | Q27: =SUM(I27-J27-K27-L27-M27-P27) -> 3.7162 | R27: =SUM(Q27/C27) -> 0.20657032 | S27: =阶段总盈亏!I27 -> 210 | T27: =SUM(Q27*S27) -> 780.402 | U27: =SUM(T27:T27) -> 780.402 | V27: =S27*C27 -> 3777.9 | W27: =(L27+M27+Q27)*S27 -> 1851.402
A29: 每日盈亏真实数据
A30: 第一阶段 | B30: 第1周
B31: 第2周
B32: 第3周
B33: 第4周
A34: 第二阶段 | B34: 第5周
B35: 第6周
B36: 第7周
B37: 第8周
A38: 第三阶段 | B38: 第9周
B39: 第10周
B40: 第11周
B41: 第12周
A42: 第四阶段 | B42: 第13周
B43: 第14周
B44: 第15周
B45: 第16周
A46: 第五阶段 | B46: 第17周
B47: 第18周
B48: 第19周
B49: 第20周
A50: 第六阶段 | B50: 第21周
B51: 第22周
B52: 第23周
B53: 第24周

Sheet 2
A1: amazon-order-id | B1: merchant-order-id | C1: purchase-date | D1: last-updated-date | E1: order-status | F1: fulfillment-channel | G1: sales-channel | H1: order-channel | I1: url | J1: ship-service-level | K1: product-name | L1: sku | M1: asin | N1: item-status | O1: quantity | P1: currency | Q1: item-price | R1: item-tax | S1: shipping-price | T1: shipping-tax | U1: gift-wrap-price | V1: gift-wrap-tax | W1: item-promotion-discount | X1: ship-promotion-discount | Y1: ship-city | Z1: ship-state | AA1: ship-postal-code | AB1: ship-country | AC1: promotion-ids | AD1: is-business-order | AE1: purchase-order-number | AF1: price-designation | AG1: default-ship-from-address-name | AH1: default-ship-from-address-field-1 | AI1: default-ship-from-address-field-2 | AJ1: default-ship-from-address-field-3 | AK1: default-ship-from-city | AL1: default-ship-from-state | AM1: default-ship-from-country | AN1: default-ship-from-postal-code | AO1: actual-ship-from-address-name | AP1: actual-ship-from-address-field-1 | AQ1: actual-ship-from-address-field-2 | AR1: actual-ship-from-address-field-3 | AS1: actual-ship-from-city | AT1: actual-ship-from-state | AU1: actual-ship-from-country | AV1: actual-ship-from-postal-code | AW1: is-buyer-requested-cancellation | AX1: buyer-requested-cancel-reason | AY1: serial-numbers | AZ1: signature-confirmation-recommended
A2: 111-9858618-2103444 | B2: 111-9858618-2103444 | C2: 2023-09-12T05:37:43+00:00 | D2: 2023-09-12T05:37:48+00:00 | E2: Pending | F2: Amazon | G2: Amazon.com | J2: Expedited | K2: Dash Cam Front with FHD 1080p, Wanlipo 2 Inch LCD Dashcam, Dashboard Camera for Cars with 24h Parking Monitor, G-Sensor, Loop Recording, Free 32GB SD | L2: J09-C1 | M2: B0BG6WPM3W | N2: Unshipped | O2: 1 | P2: USD | Q2: 79.99 | Y2: BELLMAWR | Z2: NJ | AA2: 08031-2115 | AB2: US | AC2: MPC-S Percentage Off 2023/09/10 11-52-12-900 | AD2: FALSE | AW2: FALSE | AZ2: FALSE
A3: 114-5667916-6324215 | B3: 114-5667916-6324215 | C3: 2023-09-12T03:37:05+00:00 | D3: 2023-09-12T09:02:46+00:00 | E3: Shipped | F3: Amazon | G3: Amazon.com | J3: Expedited | K3: 4K Dash Cam Front Built-in WiFi, WANLIPO Dash Camera for Cars with 64GB SD Card, Car Camera with 3" IPS Screen, 2160P Dashcam for Cars with App Contro | L3: Wanlipo M03-3 | M3: B0CC8CHTTJ | N3: Shipped | O3: 1 | P3: USD | Q3: 99.99 | R3: 1.89 | W3: 72.99 | Y3: MONROE | Z3: GA | AA3: 30656-4723 | AB3: US | AC3: MPC-S Percentage Off 2023/09/11 9-53-46-600 | AD3: FALSE | AW3: FALSE | AZ3: FALSE
A4: 111-1595396-9168227 | B4: 111-1595396-9168227 | C4: 2023-09-11T23:55:05+00:00 | D4: 2023-09-11T23:55:11+00:00 | E4: Pending | F4: Amazon | G4: Amazon.com | J4: Expedited | K4: Dash Cam Front with FHD 1080p, Wanlipo 2 Inch LCD Dashcam, Dashboard Camera for Cars with 24h Parking Monitor, G-Sensor, Loop Recording, Free 32GB SD | L4: J09-C1 | M4: B0BG6WPM3W | N4: Unshipped | O4: 1 | P4: USD | Q4: 79.99 | Y4: SILVER SPRING | Z4: MD | AA4: 20906-4527 | AB4: US | AC4: MPC-S Percentage Off 2023/09/10 11-52-3-698 | AD4: FALSE | AW4: FALSE | AZ4: FALSE
A5: 112-7810040-2837843 | B5: 112-7810040-2837843 | C5: 2023-09-11T19:41:13+00:00 | D5: 2023-09-12T01:35:23+00:00 | E5: Shipped | F5: Amazon | G5: Amazon.com | J5: Expedited | K5: Dash Cam Front with FHD 1080p, Wanlipo 2 Inch LCD Dashcam, Dashboard Camera for Cars with 24h Parking Monitor, G-Sensor, Loop Recording, Free 32GB SD | L5: J09-C1 | M5: B0BG6WPM3W | N5: Shipped | O5: 1 | P5: USD | Q5: 79.99 | R5: 1.85 | W5: 59.99 | Y5: Nashville | Z5: TN | AA5: 37208-1058 | AB5: US | AC5: MPC-S Percentage Off 2023/09/10 11-52-13-889 | AD5: FALSE | AW5: FALSE | AZ5: FALSE
A6: 111-4369826-2407442 | B6: 111-4369826-2407442 | C6: 2023-09-11T18:52:15+00:00 | D6: 2023-09-11T18:52:21+00:00 | E6: Pending | F6: Amazon | G6: Amazon.com | J6: Standard | K6: 4K Dash Cam Front with WiFi 2160P, VOFRTY Dash Camera for Cars with 3" IPS, Car Camera with App Control, Dashcam with G-Sensor, Loop Recording, 64GB S | L6: M03-3 | M6: B0C1C9T9KP | N6: Unshipped | O6: 1 | P6: USD | Q6: 79.99 | Y6: HUNTINGTON | Z6: WV | AA6: 25704-1119 | AB6: US | AC6: US Core Free Shipping Promotion A3JU1FCINF5SD0,Percentage Off 2023/08/28 6-17-47-400 | AD6: FALSE | AW6: FALSE | AZ6: FALSE
A7: 114-0862837-0430606 | B7: 114-0862837-0430606 | C7: 2023-09-11T17:17:31+00:00 | D7: 2023-09-11T17:17:37+00:00 | E7: Pending | F7: Amazon | G7: Amazon.com | J7: Expedited | K7: Dash Cam Front with FHD 1080p, Wanlipo 2 Inch LCD Dashcam, Dashboard Camera for Cars with 24h Parking Monitor, G-Sensor, Loop Recording, Free 32GB SD | L7: J09-C1 | M7: B0BG6WPM3W | N7: Unshipped | O7: 1 | P7: USD | Q7: 79.99 | Y7: LOS ANGELES | Z7: CA | AA7: 90016-2009 | AB7: US | AC7: MPC-S Percentage Off 2023/09/10 11-52-3-698 | AD7: FALSE | AW7: FALSE | AZ7: FALSE
A8: 114-2447819-7327466 | B8: 114-2447819-7327466 | C8: 2023-09-11T15:45:23+00:00 | D8: 2023-09-11T15:45:29+00:00 | E8: Pending | F8: Amazon | G8: Amazon.com | J8: Expedited | K8: 4K Dash Cam Front with WiFi 2160P, VOFRTY Dash Camera for Cars with 3" IPS, Car Camera with App Control, Dashcam with G-Sensor, Loop Recording, 64GB S | L8: M03-3 | M8: B0C1C9T9KP | N8: Unshipped | O8: 1 | P8: USD | Q8: 79.99 | Y8: DES MOINES | Z8: IA | AA8: 50317-6307 | AB8: US | AC8: MPC-S Percentage Off 2023/09/11 9-54-8-40 | AD8: FALSE | AW8: FALSE | AZ8: FALSE
A9: 114-3078544-2276207 | B9: 114-3078544-2276207 | C9: 2023-09-11T15:21:19+00:00 | D9: 2023-09-12T04:25:37+00:00 | E9: Shipped | F9: Amazon | G9: Amazon.com | J9: Expedited | K9: 4K Dash Cam Front with WiFi 2160P, VOFRTY Dash Camera for Cars with 3" IPS, Car Camera with App Control, Dashcam with G-Sensor, Loop Recording, 64GB S | L9: M03-3 | M9: B0C1C9T9KP | N9: Shipped | O9: 1 | P9: USD | Q9: 79.99 | R9: 3.12 | W9: 47.99 | Y9: LA VERGNE | Z9: TN | AA9: 37086-1439 | AB9: US | AC9: MPC-S Percentage Off 2023/09/11 9-54-8-40 | AD9: FALSE | AW9: FALSE | AZ9: FALSE
A10: 114-1356066-5534643 | B10: 114-1356066-5534643 | C10: 2023-09-11T13:58:53+00:00 | D10: 2023-09-12T07:08:25+00:00 | E10: Shipped | F10: Amazon | G10: Amazon.com | J10: Expedited | K10: Dash Cam Front with FHD 1080p, Wanlipo 2 Inch LCD Dashcam, Dashboard Camera for Cars with 24h Parking Monitor, G-Sensor, Loop Recording, Free 32GB SD | L10: J09-C1 | M10: B0BG6WPM3W | N10: Shipped | O10: 1 | P10: USD | Q10: 79.99 | R10: 1.25 | S10: 2.99 | W10: 59.99 | X10: 2.99 | Y10: BLACKSTONE | Z10: MA | AA10: 01504-1408 | AB10: US | AC10: MPC-S Percentage Off 2023/09/10 5-41-22-292 | AD10: FALSE | AW10: FALSE | AZ10: FALSE
A11: 112-9726611-4879461 | B11: 112-9726611-4879461 | C11: 2023-09-11T12:39:23+00:00 | D11: 2023-09-12T09:25:25+00:00 | E11: Shipped | F11: Amazon | G11: Amazon.com | J11: Standard | K11: 4K Dash Cam Front Built-in WiFi, WANLIPO Dash Camera for Cars with 64GB SD Card, Car Camera with 3" IPS Screen, 2160P Dashcam for Cars with App Contro | L11: Wanlipo M03-3 | M11: B0CC8CHTTJ | N11: Shipped | O11: 1 | P11: USD | Q11: 99.99 | R11: 2.84 | W11: 67.99 | Y11: Brooklyn | Z11: NY | AA11: 11235 | AB11: US | AC11: MPC-S Percentage Off 2023/09/07 1-34-35-547 | AD11: FALSE | AW11: FALSE | AZ11: FALSE
A12: 113-6400382-4997016 | B12: 113-6400382-4997016 | C12: 2023-09-11T11:06:47+00:00 | D12: 2023-09-11T11:06:52+00:00 | E12: Pending | F12: Amazon | G12: Amazon.com | J12: Expedited | K12: Dash Cam Front with FHD 1080p, Wanlipo 2 Inch LCD Dashcam, Dashboard Camera for Cars with 24h Parking Monitor, G-Sensor, Loop Recording, Free 32GB SD | L12: J09-C1 | M12: B0BG6WPM3W | N12: Unshipped | O12: 1 | P12: USD | Q12: 79.99 | Y12: BRONX | Z12: NY | AA12: 10461 | AB12: US | AC12: MPC-S Percentage Off 2023/09/10 11-52-12-900 | AD12: FALSE | AW12: FALSE | AZ12: FALSE
A13: 112-9947498-4884232 | B13: 112-9947498-4884232 | C13: 2023-09-11T07:15:23+00:00 | D13: 2023-09-11T18:12:08+00:00 | E13: Shipped | F13: Amazon | G13: Amazon.com | J13: Expedited | K13: 4K Dash Cam Front with WiFi 2160P, VOFRTY Dash Camera for Cars with 3" IPS, Car Camera with App Control, Dashcam with G-Sensor, Loop Recording, 64GB S | L13: M03-3 | M13: B0C1C9T9KP | N13: Shipped | O13: 1 | P13: USD | Q13: 79.99 | R13: 3.8 | W13: 40 | Y13: WEST COVINA | Z13: CA | AA13: 91792-1494 | AB13: US | AC13: Percentage Off 2023/08/28 6-17-47-400 | AD13: FALSE | AW13: FALSE | AZ13: FALSE

Sheet 逮虾户上贴费用详情
A1: 标题 | B1: 产品链接 | C1: ASIN | D1: 原价 | E1: 折后价 | F1: 折扣码 | G1: 折扣力度 | H1: 其他叠加优惠 | I1: 资源名称 | J1: 资源链接 | K1: 费用 | L1: 状态 | M1: 帖子链接 | N1: 上帖图片 | O1: 失败原因 | P1: 下单时间 | Q1: 接单时间 | R1: 上帖时间 | S1: 退款时间
A2: 4K Dash Cam Front Built-in WiFi, WANLIPO Dash Camera for Cars with 64GB SD Card App Control | B2: https://www.amazon.com/promocode/A1DX8GZASC5MLT | C2: B0CC8CHTTJ | D2: $99.99 | E2: $31.99 | F2: 68WHPID3 | G2: 68 | I2: INSANE CHRISTMAS DEALS, Forking Good Deals | J2: 查看链接 | K2: 37 | L2: 已完成 | M2: 查看帖子 | P2: 2023-09-07 15:24:49 | Q2: 2023-09-07 18:22:38 | R2: 2023-09-08 11:44:55
A3: 4K Dash Cam Front Built-in WiFi, WANLIPO Dash Camera for Cars with 64GB SD Card App Control | B3: https://www.amazon.com/promocode/A1DX8GZASC5MLT | C3: B0CC8CHTTJ | D3: $99.99 | E3: $31.99 | F3: 68WHPID3 | G3: 68 | I3: Saving With Joy- Online Deals and Giveaways | J3: 查看链接 | K3: 14 | L3: 已完成 | M3: 查看帖子 | P3: 2023-09-07 15:24:49 | Q3: 2023-09-07 16:49:59 | R3: 2023-09-08 13:42:22
A4: 4K Dash Cam Front Built-in WiFi, WANLIPO Dash Camera for Cars with 64GB SD Card App Control | B4: https://www.amazon.com/promocode/A1DX8GZASC5MLT | C4: B0CC8CHTTJ | D4: $99.99 | E4: $31.99 | F4: 68WHPID3 | G4: 68 | I4: The Frugal SAHM | Deals & Discounts for Moms + Babies | J4: 查看链接 | K4: 30 | L4: 已完成 | M4: 查看帖子 | P4: 2023-09-07 15:24:49 | Q4: 2023-09-07 18:10:10 | R4: 2023-09-09 03:49:38
A5: 4K Dash Cam Front Built-in WiFi, WANLIPO Dash Camera for Cars with 64GB SD Card App Control | B5: https://www.amazon.com/promocode/A1DX8GZASC5MLT | C5: B0CC8CHTTJ | D5: $99.99 | E5: $31.99 | F5: 68WHPID3 | G5: 68 | I5: Leave it on the Porch | J5: 查看链接 | K5: 63 | L5: 已完成 | M5: 查看帖子 | P5: 2023-09-07 15:24:49 | Q5: 2023-09-07 15:34:15 | R5: 2023-09-08 09:11:21
A6: 4K Dash Cam Front Built-in WiFi, WANLIPO Dash Camera for Cars with 64GB SD Card App Control | B6: https://www.amazon.com/promocode/A1DX8GZASC5MLT | C6: B0CC8CHTTJ | D6: $99.99 | E6: $31.99 | F6: 68WHPID3 | G6: 68 | I6: Nats daily deals and codes | J6: 查看链接 | K6: 32 | L6: 已取消/退款 | O6: 未入选 | P6: 2023-09-07 15:24:49 | Q6: 2023-09-07 18:13:47 | S6: 2023-09-13 15:39:13
A7: 4K Dash Cam Front Built-in WiFi, WANLIPO Dash Camera for Cars with 64GB SD Card App Control | B7: https://www.amazon.com/promocode/A1DX8GZASC5MLT | C7: B0CC8CHTTJ | D7: $99.99 | E7: $31.99 | F7: 68WHPID3 | G7: 68 | I7: Bomb Deals - Promo Codes - Coupons | J7: 查看链接 | K7: 32 | L7: 已完成 | M7: 查看帖子 | P7: 2023-09-07 15:24:49 | Q7: 2023-09-07 22:32:59 | R7: 2023-09-08 10:43:22
A8: 4K Dash Cam Front Built-in WiFi, WANLIPO Dash Camera for Cars with 64GB SD Card App Control | B8: https://www.amazon.com/promocode/A1DX8GZASC5MLT | C8: B0CC8CHTTJ | D8: $99.99 | E8: $31.99 | F8: 68WHPID3 | G8: 68 | I8: Oopsie Deals | J8: 查看链接 | K8: 49 | L8: 已完成 | N8: 查看图片 | P8: 2023-09-07 15:24:49 | Q8: 2023-09-07 15:27:44 | R8: 2023-09-08 09:53:51
A9: 4K Dash Cam Front Built-in WiFi, WANLIPO Dash Camera for Cars with 64GB SD Card App Control | B9: https://www.amazon.com/promocode/A1DX8GZASC5MLT | C9: B0CC8CHTTJ | D9: $99.99 | E9: $31.99 | F9: 68WHPID3 | G9: 68 | I9: Dysautomama Deals | J9: 查看链接 | K9: 24 | L9: 已完成 | M9: 查看帖子 | P9: 2023-09-07 15:24:49 | Q9: 2023-09-07 16:25:17 | R9: 2023-09-08 15:28:24
A10: 4K Dash Cam Front Built-in WiFi, WANLIPO Dash Camera for Cars with 64GB SD Card App Control | B10: https://www.amazon.com/promocode/A1DX8GZASC5MLT | C10: B0CC8CHTTJ | D10: $99.99 | E10: $31.99 | F10: 68WHPID3 | G10: 68 | I10: Gretchen's Adventures Deals | J10: 查看链接 | K10: 14 | L10: 已取消/退款 | O10: 未入选 | P10: 2023-09-07 15:24:49 | Q10: 2023-09-07 18:16:12 | S10: 2023-09-08 18:19:33
A11: 4K Dash Cam Front Built-in WiFi, WANLIPO Dash Camera for Cars with 64GB SD Card App Control | B11: https://www.amazon.com/promocode/A1DX8GZASC5MLT | C11: B0CC8CHTTJ | D11: $99.99 | E11: $31.99 | F11: 68WHPID3 | G11: 68 | I11: Ohana Farmhouse 🌺 Daily Deals & Steals | J11: 查看链接 | K11: 28 | L11: 已完成 | M11: 查看帖子 | P11: 2023-09-07 15:24:49 | Q11: 2023-09-07 16:18:35 | R11: 2023-09-08 23:27:38
A12: 4K Dash Cam Front Built-in WiFi, WANLIPO Dash Camera for Cars with 64GB SD Card App Control | B12: https://www.amazon.com/promocode/A6V41M33IJCOY | C12: - | D12: $99.99 | E12: $31.99 | F12: 685AXW4O | G12: 68 | I12: HarcarSisters - (Deals & Steals) | J12: 查看链接 | K12: 22 | L12: 已取消/退款 | O12: 管理员超时不回复 | P12: 2023-09-08 12:05:34 | S12: 2023-09-10 18:13:38
A13: 4K Dash Cam Front Built-in WiFi, WANLIPO Dash Camera for Cars with 64GB SD Card App Control | B13: https://www.amazon.com/promocode/A6V41M33IJCOY | C13: - | D13: $99.99 | E13: $31.99 | F13: 685AXW4O | G13: 68 | I13: Compras toxicas con la patrona | J13: 查看链接 | K13: 25 | L13: 已完成 | N13: 查看图片 | P13: 2023-09-08 12:05:34 | Q13: 2023-09-08 23:37:45 | R13: 2023-09-09 10:11:14
A14: 4K Dash Cam Front Built-in WiFi, WANLIPO Dash Camera for Cars with 64GB SD Card App Control | B14: https://www.amazon.com/promocode/A6V41M33IJCOY | C14: - | D14: $99.99 | E14: $31.99 | F14: 685AXW4O | G14: 68 | I14: Kristen's Deals and Discounts | J14: 查看链接 | K14: 17 | L14: 已取消/退款 | O14: 未入选 | P14: 2023-09-08 12:05:34 | Q14: 2023-09-08 18:20:51 | S14: 2023-09-09 12:12:40
A15: 4K Dash Cam Front Built-in WiFi, WANLIPO Dash Camera for Cars with 64GB SD Card App Control | B15: https://www.amazon.com/promocode/A6V41M33IJCOY | C15: - | D15: $99.99 | E15: $31.99 | F15: 685AXW4O | G15: 68 | I15: Sales-aholic.com Deals, Glitches, & Free Things | J15: 查看链接 | K15: 80 | L15: 已完成 | M15: 查看帖子 | P15: 2023-09-08 12:05:34 | Q15: 2023-09-08 14:15:56 | R15: 2023-09-09 07:14:41
A16: 4K Dash Cam Front Built-in WiFi, WANLIPO Dash Camera for Cars with 64GB SD Card App Control | B16: https://www.amazon.com/promocode/A6V41M33IJCOY | C16: - | D16: $99.99 | E16: $31.99 | F16: 685AXW4O | G16: 68 | I16: Jackie's Fun Finds | J16: 查看链接 | K16: 51 | L16: 已取消/退款 | O16: 未入选 | P16: 2023-09-08 12:05:34 | Q16: 2023-09-08 18:18:53 | S16: 2023-09-09 14:09:58
A17: 4K Dash Cam Front Built-in WiFi, WANLIPO Dash Camera for Cars with 64GB SD Card App Control | B17: https://www.amazon.com/promocode/A6V41M33IJCOY | C17: - | D17: $99.99 | E17: $31.99 | F17: 685AXW4O | G17: 68 | I17: Coupon with Nada | J17: 查看链接 | K17: 13 | L17: 已完成 | M17: 查看帖子 | P17: 2023-09-08 12:05:34 | Q17: 2023-09-08 19:25:02 | R17: 2023-09-11 09:06:26
A18: 4K Dash Cam Front Built-in WiFi, WANLIPO Dash Camera for Cars with 64GB SD Card App Control | B18: https://www.amazon.com/promocode/A6V41M33IJCOY | C18: - | D18: $99.99 | E18: $31.99 | F18: 685AXW4O | G18: 68 | I18: Thrifty Babes®: The Shop Society | J18: 查看链接 | K18: 30 | L18: 已取消/退款 | O18: 未入选 | P18: 2023-09-08 12:05:34 | Q18: 2023-09-08 12:49:48 | S18: 2023-09-12 22:29:32
A19: 4K Dash Cam Front Built-in WiFi, WANLIPO Dash Camera for Cars with 64GB SD Card App Control | B19: https://www.amazon.com/promocode/A6V41M33IJCOY | C19: - | D19: $99.99 | E19: $31.99 | F19: 685AXW4O | G19: 68 | I19: LaurenLovesDeals & more! | J19: 查看链接 | K19: 47 | L19: 已取消/退款 | O19: Reviews数量不足 | P19: 2023-09-08 12:05:34 | S19: 2023-09-08 13:09:33
A20: 4K Dash Cam Front Built-in WiFi, WANLIPO Dash Camera for Cars with 64GB SD Card App Control | B20: https://www.amazon.com/promocode/A6V41M33IJCOY | C20: - | D20: $99.99 | E20: $31.99 | F20: 685AXW4O | G20: 68 | I20: Amazing - Deals & Codes | J20: 查看链接 | K20: 15 | L20: 已取消/退款 | O20: 拼帖人要求退款 | P20: 2023-09-08 12:05:34 | Q20: 2023-09-08 19:24:03 | S20: 2023-09-13 20:13:33
A21: 4K Dash Cam Front Built-in WiFi, WANLIPO Dash Camera for Cars with 64GB SD Card App Control | B21: https://www.amazon.com/promocode/A6V41M33IJCOY | C21: - | D21: $99.99 | E21: $31.99 | F21: 685AXW4O | G21: 68 | I21: Bullseye🎯on the Bargain | J21: 查看链接 | K21: 47 | L21: 已完成 | M21: 查看帖子 | P21: 2023-09-08 12:05:34 | Q21: 2023-09-08 18:10:20 | R21: 2023-09-11 14:06:40
A22: 4K Dash Cam Front Built-in WiFi, WANLIPO Dash Camera for Cars with 64GB SD Card App Control | B22: https://www.amazon.com/promocode/A6V41M33IJCOY | C22: - | D22: $99.99 | E22: $31.99 | F22: 685AXW4O | G22: 68 | I22: KB's Deals™ | J22: 查看链接 | K22: 28 | L22: 已取消/退款 | O22: 未入选 | P22: 2023-09-08 12:05:34 | Q22: 2023-09-08 12:42:32 | S22: 2023-09-12 20:36:32
A23: 4K Dash Cam Front Built-in WiFi, WANLIPO Dash Camera for Cars with 64GB SD Card App Control | B23: https://www.amazon.com/promocode/A6V41M33IJCOY | C23: - | D23: $99.99 | E23: $31.99 | F23: 685AXW4O | G23: 68 | I23: 🌷simply sales with Alyssa & Sarah | J23: 查看链接 | K23: 39 | L23: 已完成 | M23: 查看帖子 | P23: 2023-09-08 12:05:34 | Q23: 2023-09-08 14:57:17 | R23: 2023-09-09 18:48:42
A24: 4K Dash Cam Front Built-in WiFi, WANLIPO Dash Camera for Cars with 64GB SD Card App Control | B24: https://www.amazon.com/promocode/A3KI4FHP7QJ2RZ | C24: B0CC8CHTTJ | D24: $99.99 | E24: $31.99 | F24: 68Z5D8VU | G24: 68 | I24: LaurenLovesDeals & more! | J24: 查看链接 | K24: 37 | L24: 已取消/退款 | O24: 未入选 | P24: 2023-09-09 11:16:31 | Q24: 2023-09-09 17:18:41 | S24: 2023-09-10 22:43:33
A25: 4K Dash Cam Front Built-in WiFi, WANLIPO Dash Camera for Cars with 64GB SD Card App Control | B25: https://www.amazon.com/promocode/A3KI4FHP7QJ2RZ | C25: B0CC8CHTTJ | D25: $99.99 | E25: $31.99 | F25: 68Z5D8VU | G25: 68 | I25: The Glitch Witch - A Snarky Deals Group | J25: 查看链接 | K25: 36 | L25: 已完成 | M25: 查看帖子 | P25: 2023-09-09 11:16:31 | Q25: 2023-09-09 18:11:16 | R25: 2023-09-09 23:58:34
A26: 4K Dash Cam Front Built-in WiFi, WANLIPO Dash Camera for Cars with 64GB SD Card App Control | B26: https://www.amazon.com/promocode/A3KI4FHP7QJ2RZ | C26: B0CC8CHTTJ | D26: $99.99 | E26: $31.99 | F26: 68Z5D8VU | G26: 68 | I26: Kristen's Deals and Discounts | J26: 查看链接 | K26: 17 | L26: 已取消/退款 | O26: 未入选 | P26: 2023-09-09 11:16:31 | Q26: 2023-09-09 18:10:39 | S26: 2023-09-12 12:32:38
A27: 4K Dash Cam Front Built-in WiFi, WANLIPO Dash Camera for Cars with 64GB SD Card App Control | B27: https://www.amazon.com/promocode/A3KI4FHP7QJ2RZ | C27: B0CC8CHTTJ | D27: $99.99 | E27: $31.99 | F27: 68Z5D8VU | G27: 68 | I27: HarcarSisters - (Deals & Steals) | J27: 查看链接 | K27: 28 | L27: 已取消/退款 | O27: 未入选 | P27: 2023-09-09 11:16:31 | Q27: 2023-09-09 14:42:00 | S27: 2023-09-13 20:05:36
A28: 4K Dash Cam Front Built-in WiFi, WANLIPO Dash Camera for Cars with 64GB SD Card App Control | B28: https://www.amazon.com/promocode/A3KI4FHP7QJ2RZ | C28: B0CC8CHTTJ | D28: $99.99 | E28: $31.99 | F28: 68Z5D8VU | G28: 68 | I28: Thrifty Babes®: The Shop Society | J28: 查看链接 | K28: 30 | L28: 已取消/退款 | O28: 未入选 | P28: 2023-09-09 11:16:31 | Q28: 2023-09-09 14:41:20 | S28: 2023-09-12 22:29:33
A29: 4K Dash Cam Front Built-in WiFi, WANLIPO Dash Camera for Cars with 64GB SD Card App Control | B29: https://www.amazon.com/promocode/A3KI4FHP7QJ2RZ | C29: B0CC8CHTTJ | D29: $99.99 | E29: $31.99 | F29: 68Z5D8VU | G29: 68 | I29: BUT It Was On Sale..💥💥 | J29: 查看链接 | K29: 77 | L29: 已取消/退款 | O29: 未入选 | P29: 2023-09-09 11:16:31 | Q29: 2023-09-09 18:06:35 | S29: 2023-09-10 20:05:36
A30: 4K Dash Cam Front Built-in WiFi, WANLIPO Dash Camera for Cars with 64GB SD Card App Control | B30: https://www.amazon.com/promocode/A3KI4FHP7QJ2RZ | C30: B0CC8CHTTJ | D30: $99.99 | E30: $31.99 | F30: 68Z5D8VU | G30: 68 | I30: Mommy & Me Deals | J30: 查看链接 | K30: 48 | L30: 已完成 | M30: 查看帖子 | P30: 2023-09-09 11:16:31 | Q30: 2023-09-09 17:19:45 | R30: 2023-09-11 22:55:21
A31: 4K Dash Cam Front Built-in WiFi, WANLIPO Dash Camera for Cars with 64GB SD Card App Control | B31: https://www.amazon.com/promocode/A3KI4FHP7QJ2RZ | C31: B0CC8CHTTJ | D31: $99.99 | E31: $31.99 | F31: 68Z5D8VU | G31: 68 | I31: Kouponing With Katie | J31: 查看链接 | K31: 28 | L31: 已完成 | M31: 查看帖子 | P31: 2023-09-09 11:16:31 | Q31: 2023-09-09 18:12:13 | R31: 2023-09-10 09:36:07
A32: 4K Dash Cam Front Built-in WiFi, WANLIPO Dash Camera for Cars with 64GB SD Card App Control | B32: https://www.amazon.com/promocode/A3KI4FHP7QJ2RZ | C32: B0CC8CHTTJ | D32: $99.99 | E32: $31.99 | F32: 68Z5D8VU | G32: 68 | I32: 🍑 Peachy Keen Deals and Steals | J32: 查看链接 | K32: 30 | L32: 已取消/退款 | O32: 未入选 | P32: 2023-09-09 11:16:31 | Q32: 2023-09-09 14:43:07 | S32: 2023-09-11 19:40:40
A33: 4K Dash Cam Front Built-in WiFi, WANLIPO Dash Camera for Cars with 64GB SD Card App Control | B33: https://www.amazon.com/promocode/A3KI4FHP7QJ2RZ | C33: B0CC8CHTTJ | D33: $99.99 | E33: $31.99 | F33: 68Z5D8VU | G33: 68 | I33: Savvy Money Saving Shopaholics Group | J33: 查看链接 | K33: 48 | L33: 进行中 | P33: 2023-09-09 11:16:31 | Q33: 2023-09-11 18:20:47
A34: 4K Dash Cam Front Built-in WiFi, WANLIPO Dash Camera for Cars with 64GB SD Card App Control | B34: https://www.amazon.com/promocode/A3KI4FHP7QJ2RZ | C34: B0CC8CHTTJ | D34: $99.99 | E34: $31.99 | F34: 68Z5D8VU | G34: 68 | I34: Crazy Discount Codes | J34: 查看链接 | K34: 26 | L34: 已完成 | M34: 查看帖子 | P34: 2023-09-09 11:16:31 | Q34: 2023-09-11 10:40:36 | R34: 2023-09-11 11:59:28

Sheet 西柚找词垃圾词
A1: 否定精准 | B1: 否定词组 | C1: 品牌词
A2: car screen | B2: monitor | C2: ring
A3: 4k monitor | B3: digital | C3: VIOFO
A4: digital dash | B4: real | C4: VANTRUE
A5: car wifi | B5: blackvue | C5: Thinkware
A6: screen for car | B6: laser | C6: Blackvue
A7: wifi for car | B7: jammer | C7: Garmin
A8: parking sensor | B8: echo | C8: 70mai
A9: real car | B9: auto | C9: NEXT BASE
A10: digital dashboard | B10: small | C10: REXING
A11: 4k monitors | B11: battery | C11: Blueskysea
A12: car monitor | B12: filler | C12: IIWEY
... A31: camera monitor | B31: front and inside | C31: Zhrmghg
A32: small dash cam | B32: front and back | C32: 360
A33: vehicle | B33: front and backup | C33: ABASK
A34: blue car | B34: pruveeo | C34: Amazon Renewed
A35: dash cam battery pack | B35: 3 channel | C35: AXIL
A36: sticky dash fix | B36: wifi for car | C36: Dongar Technologies
A37: memory saver for car battery | B37: luxi | C37: dosili
A38: wifi battery monitor | B38: ring | C38: FocuWay
A39: wifi password | B39: nexar | C39: Heaboli
A40: amazon auto | B40: link | C40: LAMTTO
A41: battery filler | B41: rove | C41: OBEST
A42: camas | B42: r2 4k | C42: QSAEHLS
A43: dash | B43: pruveeo | C43: QveeQ
A44: pruveeo 3 channel dash cam | B44: car front camera | C44: ROVE
... A72: front camera for car | B72: screen for car | C72: WonVon
A73: dash cam with 1080p dual cameras, fhd dvr 3.0 ips screen 170° wide angle g-sensor parking monitor lo | B73: wolfbox | C73: 360
A74: digital dash | B74: ddpai | C74: Abodost
A75: toguard dash cam | B75: front and back | C75: AIPLUGER
A76: dash cam no wires | B76: apexview | C76: AKKAHH
A77: 70mai | B77: solar | C77: AMORTEK
A78: dashcam front and rear camera wireless | B78: 3 channel | C78: Anumit
A79: desk for car | B79: red tiger | C79: Apexcam
A80: dash cam front and rear 4k | B80: car needs | C80: ARECORD
A81: minolta dash cam | B81: monitor | C81: ASTSH
A82: seicane 10.26 carplay dash camera | B82: car monitor | C82: ATOTO
A83: nexar dash cam front and rear | B83: battery powered | C83: Avaett
A84: dashcams for cars front and rear | B84: stuff for car | C84: AVISIGHT
A85: cooau dash cam | B85: thinkware | C85: BlackboxMyCar
... A91: apexview dash cam | B91: gopro | C91: Car and Driver
A92: 4k | B92: 360 | C92: Carpuride
A93: aukey dash cam | B93: roav | C93: ChargerCity
A94: solar dash cam | B94: car screen | C94: D.DA.D
A95: 3 channel dash cam | B95: bluetooth screen | C95: Digital Village
A96: red tiger dash cam | B96: cloud | C96: Dorman
A97: car needs | B97: screen | C97: Escort
A98: dashcam front and rear camera | B98: fitcamx | C98: E-SHOW TREE
A99: ring dash camera for cars | B99: speed | C99: EYETOO
A100: car monitor | B100: viofo | C100: Frvesroe
A101: stuff for car | B101: garmin | C101: Gebildet
A102: thinkware f70 | B102: car step | C102: Generic
A103: drive cam luxidrive | B103: mini 2 | C103: GILAYGROW
A104: viofo a229 pro | B104: apex view | C104: HUBANFLY
... A112: fitcamx | B112: parking | C112: MEKNIC
A113: dash cam with speed recording | B113: 57 | C113: Minolta
A114: viofo dash cam | B114: car gadgets | C114: Miofive
A115: garmin dashcam mini 2 | B115: car living | C115: Moplasz
A116: car step | B116: cobra sc 201 | C116: MSAFF
A117: apex view dash cam | B117: car stuff | C117: N\C
A118: dash cam with gps | B118: car emergency | C118: nezini
A119: dash cam viofo | B119: star | C119: NUNET
A120: ofertas | B120: truck | C120: OldShark
A121: rove r2 4k | B121: link | C121: Orgtoy
A122: apeman dash cam | B122: trucks | C122: PlayBetter
A123: parking sensors for cars | B123: car driving | C123: PORMIDO
A124: 360 degree dash cam | B124: car engine | C124: Street Guardian
A125: garmin dash cam 57 | B125: real cars | C125: SYLVANIA
... A141: auto camera dash cam front and rear | B141: car camera dash cam front | C141: ZWHT
A142: rove | B142: dash am
A143: dash cam gps | B143: sticky dash fix
A144: dash cam with gps and speed | B144: cars accessories
A145: dash cam battery pack | B145: monitor
A146: battery dash cam | B146: viofo a139 pro
A147: car auto accessories | B147: red tiger
A148: gps car | B148: front and rear 4k
A149: dadh cam | B149: 3 channel
A150: wifi card | B150: amazon renewed store
A151: car camera baby | B151: sd cars
A152: camaras para carros | B152: bodycam c
A153: garmin dash cam 47 | B153: prime deals
... A228: prime deals of the day clearance | B228: izeeker
A229: azdome m550
A230: car alarm
A231: warehouse sale clearance
A232: blue car
A233: car accessories men
A234: link click
A235: cami
A236: warehouse amazon warehouse deals
A237: dash cam ring
A238: wifi dash cam front and rear
A239: car screen
A240: dashcam front and rear

Sheet 产品关键词
A1: 序号 | B1: 关键词 | C1: 翻译 | D1: 相关性 | E1: 关键词归类 | F1: 关键词细分归类 | G1: 周搜索量排名 | H1: 周搜索量 | I1: 关键词搜索趋势 | J1: 关键词大小 | K1: 前三点击占比 | L1: 前三转化占比 | M1: CPR | N1: CPA | O1: CPC | P1: 点击转化率 | Q1: 客单价 | R1: ACOS | S1: 周销售量 | T1: 天销量 | U1: 关键词产品数
A2: 1 | B2: vanity mirror with lights | C2: 带灯的梳妆镜 | D2: 高相关 | E2: 属性关键词 | F2: 功能特性:lights | 品类名称:mirror | 使用场景:vanity | G2: 356 | H2: 181151 | I2: =VLOOKUP(B2,[1]极目数据!A:D,4,0) -> 0.004492 | J2: =_xlfn.IFS(G2<=50000,"大词",AND(G2>50000,G2<=200000),"中词",G2>200000,"长尾词") -> 大词 | K2: =VLOOKUP(B2,[1]极目数据!A:S,19,0) -> 0.1598 | L2: =VLOOKUP(B2,[1]极目数据!A:T,20,0) -> 0.1239 | M2: =VLOOKUP(B2,[1]极目数据!A:P,16,0) -> 273 | N2: =VLOOKUP(B2,[1]极目数据!A:V,22,0) -> 78.775732 | O2: =VLOOKUP(B2,[1]极目数据!A:L,11,0) -> 1.1 | P2: =VLOOKUP(B2,[1]极目数据!A:J,10,0) -> 0.019549 | Q2: 39.99 | R2: =O2/(P2*Q2) -> 1.4070733 | S2: =VLOOKUP(B:B,[1]极目数据!A:H,8,FALSE) -> 1133 | U2: =VLOOKUP(B:B,[1]极目数据!A:U,21,FALSE) -> 98702
A3: 2 | B3: vanity mirror | C3: 梳妆镜 | D3: 高相关 | E3: 共性关键词 | F3: 品类名称:mirror | 使用场景:vanity | G3: 1447 | H3: 84854 | I3: =VLOOKUP(B3,[1]极目数据!A:D,4,0) -> 0.057858 | J3: =_xlfn.IFS(G3<=50000,"大词",AND(G3>50000,G3<=200000),"中词",G3>200000,"长尾词") -> 大词 | K3: =VLOOKUP(B3,[1]极目数据!A:S,19,0) -> 0.1571 | L3: =VLOOKUP(B3,[1]极目数据!A:T,20,0) -> 0.1042 | M3: =VLOOKUP(B3,[1]极目数据!A:P,16,0) -> 143 | N3: =VLOOKUP(B3,[1]极目数据!A:V,22,0) -> 36.714509 | O3: =VLOOKUP(B3,[1]极目数据!A:L,11,0) -> 0.9 | P3: =VLOOKUP(B3,[1]极目数据!A:J,10,0) -> 0.030778 | Q3: 39.99 | R3: =O3/(P3*Q3) -> 0.73122446 | S3: =VLOOKUP(B:B,[1]极目数据!A:H,8,FALSE) -> 666 | U3: =VLOOKUP(B:B,[1]极目数据!A:U,21,FALSE) -> 140805
A4: 3 | B4: makeup mirror | C4: 化妆镜 | D4: 高相关 | E4: 共性关键词 | F4: 品类名称:makeup,mirror | G4: 1683 | H4: 77854 | I4: =VLOOKUP(B4,[1]极目数据!A:D,4,0) -> 0.04868 | J4: =_xlfn.IFS(G4<=50000,"大词",AND(G4>50000,G4<=200000),"中词",G4>200000,"长尾词") -> 大词 | K4: =VLOOKUP(B4,[1]极目数据!A:S,19,0) -> 0.2503 | L4: =VLOOKUP(B4,[1]极目数据!A:T,20,0) -> 0.1454 | M4: =VLOOKUP(B4,[1]极目数据!A:P,16,0) -> 125 | N4: =VLOOKUP(B4,[1]极目数据!A:V,22,0) -> 15.650891 | O4: =VLOOKUP(B4,[1]极目数据!A:L,11,0) -> 1.07 | P4: =VLOOKUP(B4,[1]极目数据!A:J,10,0) -> 0.086896 | Q4: 39.99 | R4: =O4/(P4*Q4) -> 0.30791624 | S4: =VLOOKUP(B:B,[1]极目数据!A:H,8,FALSE) -> 2241 | T4: =S4/7 -> 320.14286 | U4: =VLOOKUP(B:B,[1]极目数据!A:U,21,FALSE) -> 133397
A5: 4 | B5: mirror with lights | C5: 带灯光的镜子 | D5: 高相关 | E5: 属性关键词 | F5: 功能特性:lights | 品类名称:mirror | G5: 4935 | H5: 43272 | I5: =VLOOKUP(B5,[1]极目数据!A:D,4,0) -> 0.038447 | J5: =_xlfn.IFS(G5<=50000,"大词",AND(G5>50000,G5<=200000),"中词",G5>200000,"长尾词") -> 大词 | K5: =VLOOKUP(B5,[1]极目数据!A:S,19,0) -> 0.2227 | L5: =VLOOKUP(B5,[1]极目数据!A:T,20,0) -> 0.2135 | M5: =VLOOKUP(B5,[1]极目数据!A:P,16,0) -> 75 | N5: =VLOOKUP(B5,[1]极目数据!A:V,22,0) -> 10.385622 | O5: =VLOOKUP(B5,[1]极目数据!A:L,11,0) -> 0.35 | P5: =VLOOKUP(B5,[1]极目数据!A:J,10,0) -> 0.045255 | Q5: 39.99 | R5: =O5/(P5*Q5) -> 0.19339715 | S5: =VLOOKUP(B:B,[1]极目数据!A:H,8,FALSE) -> 463 | U5: =VLOOKUP(B:B,[1]极目数据!A:U,21,FALSE) -> 138176
A6: 5 | B6: makeup mirror with lights | C6: 带灯化妆镜 | D6: 高相关 | E6: 属性关键词 | F6: 功能特性:lights | 品类名称:makeup,mirror | G6: 6009 | H6: 31757 | I6: =VLOOKUP(B6,[1]极目数据!A:D,4,0) -> 0.04765 | J6: =_xlfn.IFS(G6<=50000,"大词",AND(G6>50000,G6<=200000),"中词",G6>200000,"长尾词") -> 大词 | K6: =VLOOKUP(B6,[1]极目数据!A:S,19,0) -> 0.2537 | L6: =VLOOKUP(B6,[1]极目数据!A:T,20,0) -> 0.1626 | M6: =VLOOKUP(B6,[1]极目数据!A:P,16,0) -> 62 | N6: =VLOOKUP(B6,[1]极目数据!A:V,22,0) -> 17.620836 | O6: =VLOOKUP(B6,[1]极目数据!A:L,11,0) -> 1 | P6: =VLOOKUP(B6,[1]极目数据!A:J,10,0) -> 0.078316 | Q6: 39.99 | R6: =O6/(P6*Q6) -> 0.3192994 | S6: =VLOOKUP(B:B,[1]极目数据!A:H,8,FALSE) -> 819 | U6: =VLOOKUP(B:B,[1]极目数据!A:U,21,FALSE) -> 69482
A7: 6 | B7: desk mirror | C7: 桌面镜 | D7: 高相关 | E7: 属性关键词 | F7: 品类名称:mirror | 使用场景:desk | G7: 6654 | H7: 29954 | I7: =VLOOKUP(B7,[1]极目数据!A:D,4,0) -> 0.109824 | J7: =_xlfn.IFS(G7<=50000,"大词",AND(G7>50000,G7<=200000),"中词",G7>200000,"长尾词") -> 大词 | K7: =VLOOKUP(B7,[1]极目数据!A:S,19,0) -> 0.1995 | L7: =VLOOKUP(B7,[1]极目数据!A:T,20,0) -> 0.1452 | M7: =VLOOKUP(B7,[1]极目数据!A:P,16,0) -> 55 | N7: =VLOOKUP(B7,[1]极目数据!A:V,22,0) -> 11.033158 | O7: =VLOOKUP(B7,[1]极目数据!A:L,11,0) -> 0.49 | P7: =VLOOKUP(B7,[1]极目数据!A:J,10,0) -> 0.058913 | Q7: 39.99 | R7: =O7/(P7*Q7) -> 0.20798573 | S7: =VLOOKUP(B:B,[1]极目数据!A:H,8,FALSE) -> 292 | U7: =VLOOKUP(B:B,[1]极目数据!A:U,21,FALSE) -> 141011
A8: 7 | B8: mirror for desk | C8: 桌子用镜子 | D8: 高相关 | E8: 属性关键词 | F8: 品类名称:mirror | 使用场景:desk | G8: 10442 | H8: 21904 | I8: =VLOOKUP(B8,[1]极目数据!A:D,4,0) -> 0.073439 | J8: =_xlfn.IFS(G8<=50000,"大词",AND(G8>50000,G8<=200000),"中词",G8>200000,"长尾词") -> 大词 | K8: =VLOOKUP(B8,[1]极目数据!A:S,19,0) -> 0.1965 | L8: =VLOOKUP(B8,[1]极目数据!A:T,20,0) -> 0.0865 | M8: =VLOOKUP(B8,[1]极目数据!A:P,16,0) -> 48 | N8: =VLOOKUP(B8,[1]极目数据!A:V,22,0) -> 14.186264 | O8: =VLOOKUP(B8,[1]极目数据!A:L,11,0) -> 0.81 | P8: =VLOOKUP(B8,[1]极目数据!A:J,10,0) -> 0.071196 | Q8: 39.99 | R8: =O8/(P8*Q8) -> 0.28449722 | S8: =VLOOKUP(B:B,[1]极目数据!A:H,8,FALSE) -> 304 | U8: =VLOOKUP(B:B,[1]极目数据!A:U,21,FALSE) -> 53571
A9: 8 | B9: light up mirror | C9: 发光镜子 | D9: 高相关 | E9: 属性关键词 | F9: 功能特性:light | 品类名称:mirror | G9: 13744 | H9: 17696 | I9: =VLOOKUP(B9,[1]极目数据!A:D,4,0) -> 0.06473 | J9: =_xlfn.IFS(G9<=50000,"大词",AND(G9>50000,G9<=200000),"中词",G9>200000,"长尾词") -> 大词 | K9: =VLOOKUP(B9,[1]极目数据!A:S,19,0) -> 0.2407 | L9: =VLOOKUP(B9,[1]极目数据!A:T,20,0) -> 0.1857 | M9: =VLOOKUP(B9,[1]极目数据!A:P,16,0) -> 44 | N9: =VLOOKUP(B9,[1]极目数据!A:V,22,0) -> 15.087375 | O9: =VLOOKUP(B9,[1]极目数据!A:L,11,0) -> 0.61 | P9: =VLOOKUP(B9,[1]极目数据!A:J,10,0) -> 0.053687 | Q9: 39.99 | R9: =O9/(P9*Q9) -> 0.2841249 | S9: =VLOOKUP(B:B,[1]极目数据!A:H,8,FALSE) -> 252 | U9: =VLOOKUP(B:B,[1]极目数据!A:U,21,FALSE) -> 8900
A10: 9 | B10: led mirror | C10: led镜子 | D10: 中相关 | E10: 属性关键词 | F10: 功能特性:led | 品类名称:mirror | G10: 14248 | H10: 17191 | I10: =VLOOKUP(B10,[1]极目数据!A:D,4,0) -> 0.032673 | J10: =_xlfn.IFS(G10<=50000,"大词",AND(G10>50000,G10<=200000),"中词",G10>200000,"长尾词") -> 大词 | K10: =VLOOKUP(B10,[1]极目数据!A:S,19,0) -> 0.2416 | L10: =VLOOKUP(B10,[1]极目数据!A:T,20,0) -> 0.1231 | M10: =VLOOKUP(B10,[1]极目数据!A:P,16,0) -> 49 | N10: =VLOOKUP(B10,[1]极目数据!A:V,22,0) -> 59.859211 | O10: =VLOOKUP(B10,[1]极目数据!A:L,11,0) -> 1.31 | P10: =VLOOKUP(B10,[1]极目数据!A:J,10,0) -> 0.029235 | Q10: 39.99 | R10: =O10/(P10*Q10) -> 1.1205127 | S10: =VLOOKUP(B:B,[1]极目数据!A:H,8,FALSE) -> 83 | U10: =VLOOKUP(B:B,[1]极目数据!A:U,21,FALSE) -> 105967
A11: 10 | B11: lighted makeup mirror | C11: 化妆镜 | D11: 高相关 | E11: 属性关键词 | F11: 功能特性:lighted | 品类名称:makeup,mirror | G11: 14264 | H11: 17176 | I11: =VLOOKUP(B11,[1]极目数据!A:D,4,0) -> 0.058612 | J11: =_xlfn.IFS(G11<=50000,"大词",AND(G11>50000,G11<=200000),"中词",G11>200000,"长尾词") -> 大词 | K11: =VLOOKUP(B11,[1]极目数据!A:S,19,0) -> 0.2688 | L11: =VLOOKUP(B11,[1]极目数据!A:T,20,0) -> 0.1726 | M11: =VLOOKUP(B11,[1]极目数据!A:P,16,0) -> 45 | N11: =VLOOKUP(B11,[1]极目数据!A:V,22,0) -> 15.290298 | O11: =VLOOKUP(B11,[1]极目数据!A:L,11,0) -> 1.16 | P11: =VLOOKUP(B11,[1]极目数据!A:J,10,0) -> 0.087637 | Q11: 39.99 | R11: =O11/(P11*Q11) -> 0.33099321 | S11: =VLOOKUP(B:B,[1]极目数据!A:H,8,FALSE) -> 400 | T11: =S11/7 -> 57.142857 | U11: =VLOOKUP(B:B,[1]极目数据!A:U,21,FALSE) -> 41994
A12: 11 | B12: magnifying mirror with light | C12: 带灯放大镜 | D12: 高相关 | E12: 属性关键词 | F12: 功能特性:light | 品类名称:mirror | G12: 14386 | H12: 17055 | I12: =VLOOKUP(B12,[1]极目数据!A:D,4,0) -> 0.030365 | J12: =_xlfn.IFS(G12<=50000,"大词",AND(G12>50000,G12<=200000),"中词",G12>200000,"长尾词") -> 大词 | K12: =VLOOKUP(B12,[1]极目数据!A:S,19,0) -> 0.2757 | L12: =VLOOKUP(B12,[1]极目数据!A:T,20,0) -> 0.2365 | M12: =VLOOKUP(B12,[1]极目数据!A:P,16,0) -> 44 | N12: =VLOOKUP(B12,[1]极目数据!A:V,22,0) -> 10.124183 | O12: =VLOOKUP(B12,[1]极目数据!A:L,11,0) -> 1.02 | P12: =VLOOKUP(B12,[1]极目数据!A:J,10,0) -> 0.134332 | Q12: 39.99 | R12: =O12/(P12*Q12) -> 0.18987566 | S12: =VLOOKUP(B:B,[1]极目数据!A:H,8,FALSE) -> 801 | T12: =S12/7 -> 114.42857 | U12: =VLOOKUP(B:B,[1]极目数据!A:U,21,FALSE) -> 39687
A13: 12 | B13: 3 way mirror | C13: 3面镜 | D13: 中相关 | E13: 属性关键词 | F13: 品类名称:mirror | G13: 18311 | H13: 13989 | I13: =VLOOKUP(B13,[1]极目数据!A:D,4,0) -> -0.007161 | J13: =_xlfn.IFS(G13<=50000,"大词",AND(G13>50000,G13<=200000),"中词",G13>200000,"长尾词") -> 大词 | K13: =VLOOKUP(B13,[1]极目数据!A:S,19,0) -> 0.5176 | L13: =VLOOKUP(B13,[1]极目数据!A:T,20,0) -> 0.3333 | M13: =VLOOKUP(B13,[1]极目数据!A:P,16,0) -> 35 | N13: =VLOOKUP(B13,[1]极目数据!A:V,22,0) -> 9.764723 | O13: =VLOOKUP(B13,[1]极目数据!A:L,11,0) -> 0.85 | P13: =VLOOKUP(B13,[1]极目数据!A:J,10,0) -> 0.115723 | Q13: 39.99 | R13: =O13/(P13*Q13) -> 0.18367407 | S13: =VLOOKUP(B:B,[1]极目数据!A:H,8,FALSE) -> 427 | U13: =VLOOKUP(B:B,[1]极目数据!A:U,21,FALSE) -> 1268
A14: 13 | B14: desk mirror with light | C14: 带灯桌面镜子 | D14: 高相关 | E14: 属性关键词 | F14: 功能特性:light | 品类名称:mirror | 使用场景:desk | G14: 21951 | H14: 12045 | I14: =VLOOKUP(B14,[1]极目数据!A:D,4,0) -> 0.117307 | J14: =_xlfn.IFS(G14<=50000,"大词",AND(G14>50000,G14<=200000),"中词",G14>200000,"长尾词") -> 大词 | K14: =VLOOKUP(B14,[1]极目数据!A:S,19,0) -> 0.2209 | L14: =VLOOKUP(B14,[1]极目数据!A:T,20,0) -> 0.1643 | M14: =VLOOKUP(B14,[1]极目数据!A:P,16,0) -> 34 | N14: =VLOOKUP(B14,[1]极目数据!A:V,22,0) -> 31.027491 | O14: =VLOOKUP(B14,[1]极目数据!A:L,11,0) -> 0.89 | P14: =VLOOKUP(B14,[1]极目数据!A:J,10,0) -> 0.040931 | Q14: 39.99 | R14: =O14/(P14*Q14) -> 0.5437337 | S14: =VLOOKUP(B:B,[1]极目数据!A:H,8,FALSE) -> 123 | U14: =VLOOKUP(B:B,[1]极目数据!A:U,21,FALSE) -> 34064
A15: 14 | B15: lighted makeup mirror with magnification | C15: 带放大的化妆镜 | D15: 高相关 | E15: 属性关键词 | F15: 功能特性:lighted,magnification | 品类名称:makeup,mirror | G15: 24352 | H15: 10979 | I15: =VLOOKUP(B15,[1]极目数据!A:D,4,0) -> 0.005352 | J15: =_xlfn.IFS(G15<=50000,"大词",AND(G15>50000,G15<=200000),"中词",G15>200000,"长尾词") -> 大词 | K15: =VLOOKUP(B15,[1]极目数据!A:S,19,0) -> 0.2663 | L15: =VLOOKUP(B15,[1]极目数据!A:T,20,0) -> 0.2101 | M15: =VLOOKUP(B15,[1]极目数据!A:P,16,0) -> 39 | N15: =VLOOKUP(B15,[1]极目数据!A:V,22,0) -> 20.303012 | O15: =VLOOKUP(B15,[1]极目数据!A:L,11,0) -> 1.94 | P15: =VLOOKUP(B15,[1]极目数据!A:J,10,0) -> 0.113776 | Q15: 39.99 | R15: =O15/(P15*Q15) -> 0.42638279 | S15: =VLOOKUP(B:B,[1]极目数据!A:H,8,FALSE) -> 531 | T15: =S15/7 -> 75.857143 | U15: =VLOOKUP(B:B,[1]极目数据!A:U,21,FALSE) -> 23451
A16: 15 | B16: make up mirror | C16: 化妆镜 | D16: 高相关 | E16: 共性关键词 | F16: 品类名称:mirror,make | G16: 24663 | H16: 10868 | I16: =VLOOKUP(B16,[1]极目数据!A:D,4,0) -> 0.050407 | J16: =_xlfn.IFS(G16<=50000,"大词",AND(G16>50000,G16<=200000),"中词",G16>200000,"长尾词") -> 大词 | K16: =VLOOKUP(B16,[1]极目数据!A:S,19,0) -> 0.2644 | L16: =VLOOKUP(B16,[1]极目数据!A:T,20,0) -> 0.1142 | M16: =VLOOKUP(B16,[1]极目数据!A:P,16,0) -> 38 | N16: =VLOOKUP(B16,[1]极目数据!A:V,22,0) -> 15.801713 | O16: =VLOOKUP(B16,[1]极目数据!A:L,11,0) -> 0.98 | P16: =VLOOKUP(B16,[1]极目数据!A:J,10,0) -> 0.103786 | Q16: 39.99 | R16: =O16/(P16*Q16) -> 0.2361217 | S16: =VLOOKUP(B:B,[1]极目数据!A:H,8,FALSE) -> 332 | T16: =S16/7 -> 47.428571 | U16: =VLOOKUP(B:B,[1]极目数据!A:U,21,FALSE) -> 137106
A17: 16 | B17: make up mirror with lighting | C17: 带照明的化妆镜 | D17: 高相关 | E17: 属性关键词 | F17: 功能特性:lighting | 品类名称:mirror,make | G17: 28422 | H17: 9616 | I17: =VLOOKUP(B17,[1]极目数据!A:D,4,0) -> 0.030326 | J17: =_xlfn.IFS(G17<=50000,"大词",AND(G17>50000,G17<=200000),"中词",G17>200000,"长尾词") -> 大词 | K17: =VLOOKUP(B17,[1]极目数据!A:S,19,0) -> 0.3156 | L17: =VLOOKUP(B17,[1]极目数据!A:T,20,0) -> 0.1358 | M17: =VLOOKUP(B17,[1]极目数据!A:P,16,0) -> 36 | N17: =VLOOKUP(B17,[1]极目数据!A:V,22,0) -> 11.263919 | O17: =VLOOKUP(B17,[1]极目数据!A:L,11,0) -> 0.8 | P17: =VLOOKUP(B17,[1]极目数据!A:J,10,0) -> 0.094106 | Q17: 39.99 | R17: =O17/(P17*Q17) -> 0.21257944 | S17: =VLOOKUP(B:B,[1]极目数据!A:H,8,FALSE) -> 262 | T17: =S17/7 -> 37.428571 | U17: =VLOOKUP(B:B,[1]极目数据!A:U,21,FALSE) -> 17162
A18: 17 | B18: makeup mirror with lights and magnification | C18: 带灯放大化妆镜 | D18: 高相关 | E18: 属性关键词 | F18: 功能特性:magnification,lights | 品类名称:makeup,mirror | G18: 47636 | H18: 6070 | I18: =VLOOKUP(B18,[1]极目数据!A:D,4,0) -> 0.009527 | J18: =_xlfn.IFS(G18<=50000,"大词",AND(G18>50000,G18<=200000),"中词",G18>200000,"长尾词") -> 大词 | K18: =VLOOKUP(B18,[1]极目数据!A:S,19,0) -> 0.272 | L18: =VLOOKUP(B18,[1]极目数据!A:T,20,0) -> 0.175 | M18: =VLOOKUP(B18,[1]极目数据!A:P,16,0) -> 35 | N18: =VLOOKUP(B18,[1]极目数据!A:V,22,0) -> 23.721565 | O18: =VLOOKUP(B18,[1]极目数据!A:L,11,0) -> 2.17 | P18: =VLOOKUP(B18,[1]极目数据!A:J,10,0) -> 0.10834 | Q18: 39.99 | R18: =O18/(P18*Q18) -> 0.50086363 | S18: =VLOOKUP(B:B,[1]极目数据!A:H,8,FALSE) -> 318 | T18: =S18/7 -> 45.428571 | U18: =VLOOKUP(B:B,[1]极目数据!A:U,21,FALSE) -> 35432
A19: 18 | B19: mirror with lights for makeup desk | C19: 化妆台用带灯光的镜子 | D19: 高相关 | E19: 属性关键词 | F19: 功能特性:lights | 品类名称:makeup,mirror | 使用场景:desk | G19: 49481 | H19: 5868 | I19: =VLOOKUP(B19,[1]极目数据!A:D,4,0) -> 0.181058 | J19: =_xlfn.IFS(G19<=50000,"大词",AND(G19>50000,G19<=200000),"中词",G19>200000,"长尾词") -> 大词 | K19: =VLOOKUP(B19,[1]极目数据!A:S,19,0) -> 0.1876 | L19: =VLOOKUP(B19,[1]极目数据!A:T,20,0) -> 0.0872 | M19: =VLOOKUP(B19,[1]极目数据!A:P,16,0) -> 32 | N19: =VLOOKUP(B19,[1]极目数据!A:V,22,0) -> 31.250076 | O19: =VLOOKUP(B19,[1]极目数据!A:L,11,0) -> 1.05 | P19: =VLOOKUP(B19,[1]极目数据!A:J,10,0) -> 0.05632 | Q19: 39.99 | R19: =O19/(P19*Q19) -> 0.4662032 | S19: =VLOOKUP(B:B,[1]极目数据!A:H,8,FALSE) -> 125 | U19: =VLOOKUP(B:B,[1]极目数据!A:U,21,FALSE) -> 33996
A20: 19 | B20: led mirror makeup | C20: led化妆镜 | D20: 高相关 | E20: 属性关键词 | F20: 功能特性:led | 品类名称:makeup,mirror | G20: 50501 | H20: 5767 | I20: =VLOOKUP(B20,[1]极目数据!A:D,4,0) -> 0.035917 | J20: =_xlfn.IFS(G20<=50000,"大词",AND(G20>50000,G20<=200000),"中词",G20>200000,"长尾词") -> 中词 | K20: =VLOOKUP(B20,[1]极目数据!A:S,19,0) -> 0.2592 | L20: =VLOOKUP(B20,[1]极目数据!A:T,20,0) -> 0.1564 | M20: =VLOOKUP(B20,[1]极目数据!A:P,16,0) -> 31 | N20: =VLOOKUP(B20,[1]极目数据!A:V,22,0) -> 16.199875 | O20: =VLOOKUP(B20,[1]极目数据!A:L,11,0) -> 0.74 | P20: =VLOOKUP(B20,[1]极目数据!A:J,10,0) -> 0.051235 | Q20: 39.99 | R20: =O20/(P20*Q20) -> 0.36117158 | S20: =VLOOKUP(B:B,[1]极目数据!A:H,8,FALSE) -> 84 | U20: =VLOOKUP(B:B,[1]极目数据!A:U,21,FALSE) -> 57082
A21: 20 | B21: makeup vanity mirror with lights | C21: 带灯的化妆梳妆台镜子 | D21: 高相关 | E21: 属性关键词 | F21: 功能特性:lights | 品类名称:makeup,mirror | 使用场景:vanity | G21: 51757 | H21: 5641 | I21: =VLOOKUP(B21,[1]极目数据!A:D,4,0) -> 0.003609 | J21: =_xlfn.IFS(G21<=50000,"大词",AND(G21>50000,G21<=200000),"中词",G21>200000,"长尾词") -> 中词 | K21: =VLOOKUP(B21,[1]极目数据!A:S,19,0) -> 0.171 | L21: =VLOOKUP(B21,[1]极目数据!A:T,20,0) -> 0.125 | M21: =VLOOKUP(B21,[1]极目数据!A:P,16,0) -> 32 | N21: =VLOOKUP(B21,[1]极目数据!A:V,22,0) -> 22.522843 | O21: =VLOOKUP(B21,[1]极目数据!A:L,11,0) -> 0.78 | P21: =VLOOKUP(B21,[1]极目数据!A:J,10,0) -> 0.038627 | Q21: 39.99 | R21: =O21/(P21*Q21) -> 0.50495447 | S21: =VLOOKUP(B:B,[1]极目数据!A:H,8,FALSE) -> 44 | U21: =VLOOKUP(B:B,[1]极目数据!A:U,21,FALSE) -> 117945
A22: 21 | B22: lighted mirror | C22: 点亮的镜子 | D22: 高相关 | E22: 属性关键词 | F22: 功能特性:lighted | 品类名称:mirror | G22: 52882 | H22: 5530 | I22: =VLOOKUP(B22,[1]极目数据!A:D,4,0) -> 0.028322 | J22: =_xlfn.IFS(G22<=50000,"大词",AND(G22>50000,G22<=200000),"中词",G22>200000,"长尾词") -> 中词 | K22: =VLOOKUP(B22,[1]极目数据!A:S,19,0) -> 0.1936 | L22: =VLOOKUP(B22,[1]极目数据!A:T,20,0) -> 0.2029 | M22: =VLOOKUP(B22,[1]极目数据!A:P,16,0) -> 33 | N22: =VLOOKUP(B22,[1]极目数据!A:V,22,0) -> 18.825425 | O22: =VLOOKUP(B22,[1]极目数据!A:L,11,0) -> 1.01 | P22: =VLOOKUP(B22,[1]极目数据!A:J,10,0) -> 0.071712 | Q22: 39.99 | R22: =O22/(P22*Q22) -> 0.3521909 | S22: =VLOOKUP(B:B,[1]极目数据!A:H,8,FALSE) -> 98 | U22: =VLOOKUP(B:B,[1]极目数据!A:U,21,FALSE) -> 59841
A23: 22 | B23: light up mirror for makeup | C23: 化妆用发光镜子 | D23: 高相关 | E23: 属性关键词 | F23: 功能特性:light | 品类名称:makeup,mirror | G23: 53467 | H23: 5469 | I23: =VLOOKUP(B23,[1]极目数据!A:D,4,0) -> 0.057193 | J23: =_xlfn.IFS(G23<=50000,"大词",AND(G23>50000,G23<=200000),"中词",G23>200000,"长尾词") -> 中词 | K23: =VLOOKUP(B23,[1]极目数据!A:S,19,0) -> 0.2686 | L23: =VLOOKUP(B23,[1]极目数据!A:T,20,0) -> 0.2049 | M23: =VLOOKUP(B23,[1]极目数据!A:P,16,0) -> 30 | N23: =VLOOKUP(B23,[1]极目数据!A:V,22,0) -> 18.685903 | O23: =VLOOKUP(B23,[1]极目数据!A:L,11,0) -> 1.04 | P23: =VLOOKUP(B23,[1]极目数据!A:J,10,0) -> 0.074388 | Q23: 39.99 | R23: =O23/(P23*Q23) -> 0.34960614 | S23: =VLOOKUP(B:B,[1]极目数据!A:H,8,FALSE) -> 106 | U23: =VLOOKUP(B:B,[1]极目数据!A:U,21,FALSE) -> 2727
A24: 23 | B24: mirror for dorm | C24: 宿舍用镜子 | D24: 中相关 | E24: 属性关键词 | F24: 品类名称:mirror | 使用场景:dorm | G24: 54623 | H24: 5363 | I24: =VLOOKUP(B24,[1]极目数据!A:D,4,0) -> 0.238956 | J24: =_xlfn.IFS(G24<=50000,"大词",AND(G24>50000,G24<=200000),"中词",G24>200000,"长尾词") -> 中词 | K24: =VLOOKUP(B24,[1]极目数据!A:S,19,0) -> 0.2138 | L24: =VLOOKUP(B24,[1]极目数据!A:T,20,0) -> 0.1923 | M24: =VLOOKUP(B24,[1]极目数据!A:P,16,0) -> 32 | N24: =VLOOKUP(B24,[1]极目数据!A:V,22,0) -> 10.493488 | O24: =VLOOKUP(B24,[1]极目数据!A:L,11,0) -> 0.65 | P24: =VLOOKUP(B24,[1]极目数据!A:J,10,0) -> 0.073379 | Q24: 39.99 | R24: =O24/(P24*Q24) -> 0.22150838 | S24: =VLOOKUP(B:B,[1]极目数据!A:H,8,FALSE) -> 60 | U24: =VLOOKUP(B:B,[1]极目数据!A:U,21,FALSE) -> 4625
A25: 24 | B25: smart mirror | C25: 智能镜子 | D25: 中相关 | E25: 属性关键词 | F25: 功能特性:smart | 品类名称:mirror | G25: 56701 | H25: 5186 | I25: =VLOOKUP(B25,[1]极目数据!A:D,4,0) -> 0.089673 | J25: =_xlfn.IFS(G25<=50000,"大词",AND(G25>50000,G25<=200000),"中词",G25>200000,"长尾词") -> 中词 | K25: =VLOOKUP(B25,[1]极目数据!A:S,19,0) -> 0.3048 | L25: =VLOOKUP(B25,[1]极目数据!A:T,20,0) -> 0.1667 | M25: =VLOOKUP(B25,[1]极目数据!A:P,16,0) -> 31 | N25: =VLOOKUP(B25,[1]极目数据!A:V,22,0) -> 1132.337 | O25: =VLOOKUP(B25,[1]极目数据!A:L,11,0) -> 0.97 | P25: =VLOOKUP(B25,[1]极目数据!A:J,10,0) -> 0.001298 | Q25: 39.99 | R25: =O25/(P25*Q25) -> 18.68726 | S25: =VLOOKUP(B:B,[1]极目数据!A:H,8,FALSE) -> 2 | U25: =VLOOKUP(B:B,[1]极目数据!A:U,21,FALSE) -> 62658
A26: 25 | B26: lighted vanity mirror | C26: 点亮的梳妆镜 | D26: 高相关 | E26: 属性关键词 | F26: 功能特性:lighted | 品类名称:mirror | 使用场景:vanity | G26: 57814 | H26: 5095 | I26: =VLOOKUP(B26,[1]极目数据!A:D,4,0) -> 0.047147 | J26: =_xlfn.IFS(G26<=50000,"大词",AND(G26>50000,G26<=200000),"中词",G26>200000,"长尾词") -> 中词 | K26: =VLOOKUP(B26,[1]极目数据!A:S,19,0) -> 0.2051 | L26: =VLOOKUP(B26,[1]极目数据!A:T,20,0) -> 0.1009 | M26: =VLOOKUP(B26,[1]极目数据!A:P,16,0) -> 31 | N26: =VLOOKUP(B26,[1]极目数据!A:V,22,0) -> 24.498407 | O26: =VLOOKUP(B26,[1]极目数据!A:L,11,0) -> 0.85 | P26: =VLOOKUP(B26,[1]极目数据!A:J,10,0) -> 0.050207 | Q26: 39.99 | R26: =O26/(P26*Q26) -> 0.42335359 | S26: =VLOOKUP(B:B,[1]极目数据!A:H,8,FALSE) -> 51 | U26: =VLOOKUP(B:B,[1]极目数据!A:U,21,FALSE) -> 47472
A27: 26 | B27: espejo con luz para maquillaje | C27: 带灯的化妆镜 | D27: 高相关 | E27: 属性关键词 | F27: 品类名称:espejo,para | 使用场景:maquillaje | G27: 61029 | H27: 4848 | I27: =VLOOKUP(B27,[1]极目数据!A:D,4,0) -> -0.011456 | J27: =_xlfn.IFS(G27<=50000,"大词",AND(G27>50000,G27<=200000),"中词",G27>200000,"长尾词") -> 中词 | K27: =VLOOKUP(B27,[1]极目数据!A:S,19,0) -> 0.1969 | L27: =VLOOKUP(B27,[1]极目数据!A:T,20,0) -> 0.0922 | M27: =VLOOKUP(B27,[1]极目数据!A:P,16,0) -> 33 | N27: =VLOOKUP(B27,[1]极目数据!A:V,22,0) -> 60.950144 | O27: =VLOOKUP(B27,[1]极目数据!A:L,11,0) -> 1.12 | P27: =VLOOKUP(B27,[1]极目数据!A:J,10,0) -> 0.024446 | Q27: 39.99 | R27: =O27/(P27*Q27) -> 1.1456681 | S27: =VLOOKUP(B:B,[1]极目数据!A:H,8,FALSE) -> 32 | U27: =VLOOKUP(B:B,[1]极目数据!A:U,21,FALSE) -> 682
A28: 27 | B28: hollywood mirror | C28: 好莱坞镜子 | D28: 中相关 | E28: 属性关键词 | F28: 品类名称:mirror | 风格/款式:hollywood | G28: 61179 | H28: 4838 | I28: =VLOOKUP(B28,[1]极目数据!A:D,4,0) -> 0.063983 | J28: =_xlfn.IFS(G28<=50000,"大词",AND(G28>50000,G28<=200000),"中词",G28>200000,"长尾词") -> 中词 | K28: =VLOOKUP(B28,[1]极目数据!A:S,19,0) -> 0.213 | L28: =VLOOKUP(B28,[1]极目数据!A:T,20,0) -> 0.0968 | M28: =VLOOKUP(B28,[1]极目数据!A:P,16,0) -> 30 | N28: =VLOOKUP(B28,[1]极目数据!A:V,22,0) -> 31.928684 | O28: =VLOOKUP(B28,[1]极目数据!A:L,11,0) -> 0.59 | P28: =VLOOKUP(B28,[1]极目数据!A:J,10,0) -> 0.024429 | Q28: 39.99 | R28: =O28/(P28*Q28) -> 0.60394156 | S28: =VLOOKUP(B:B,[1]极目数据!A:H,8,FALSE) -> 34 | U28: =VLOOKUP(B:B,[1]极目数据!A:U,21,FALSE) -> 778
A29: 28 | B29: led vanity mirror | C29: LED梳妆镜 | D29: 高相关 | E29: 属性关键词 | F29: 功能特性:led | 品类名称:mirror | 使用场景:vanity | G29: 63884 | H29: 4651 | I29: =VLOOKUP(B29,[1]极目数据!A:D,4,0) -> 0.037263 | J29: =_xlfn.IFS(G29<=50000,"大词",AND(G29>50000,G29<=200000),"中词",G29>200000,"长尾词") -> 中词 | K29: =VLOOKUP(B29,[1]极目数据!A:S,19,0) -> 0.1651 | L29: =VLOOKUP(B29,[1]极目数据!A:T,20,0) -> 0.0782 | M29: =VLOOKUP(B29,[1]极目数据!A:P,16,0) -> 31 | N29: =VLOOKUP(B29,[1]极目数据!A:V,22,0) -> 56.510765 | O29: =VLOOKUP(B29,[1]极目数据!A:L,11,0) -> 1.03 | P29: =VLOOKUP(B29,[1]极目数据!A:J,10,0) -> 0.027782 | Q29: 39.99 | R29: =O29/(P29*Q29) -> 0.92709089 | S29: =VLOOKUP(B:B,[1]极目数据!A:H,8,FALSE) -> 25 | U29: =VLOOKUP(B:B,[1]极目数据!A:U,21,FALSE) -> 75718
A30: 29 | B30: table mirror | C30: 桌面镜子 | D30: 中相关 | E30: 属性关键词 | F30: 品类名称:mirror | 使用场景:table | G30: 64537 | H30: 4611 | I30: =VLOOKUP(B30,[1]极目数据!A:D,4,0) -> 0.066748 | J30: =_xlfn.IFS(G30<=50000,"大词",AND(G30>50000,G30<=200000),"中词",G30>200000,"长尾词") -> 中词 | K30: =VLOOKUP(B30,[1]极目数据!A:S,19,0) -> 0.2102 | L30: =VLOOKUP(B30,[1]极目数据!A:T,20,0) -> 0.1734 | M30: =VLOOKUP(B30,[1]极目数据!A:P,16,0) -> 29 | N30: =VLOOKUP(B30,[1]极目数据!A:V,22,0) -> 9.822733 | O30: =VLOOKUP(B30,[1]极目数据!A:L,11,0) -> 0.77 | P30: =VLOOKUP(B30,[1]极目数据!A:J,10,0) -> 0.104859 | Q30: 39.99 | R30: =O30/(P30*Q30) -> 0.18362576 | S30: =VLOOKUP(B:B,[1]极目数据!A:H,8,FALSE) -> 65 | U30: =VLOOKUP(B:B,[1]极目数据!A:U,21,FALSE) -> 92398
... A38: 37 | B38: self cut mirror | C38: 自我剪发镜子 | D38: 中相关 | E38: 属性关键词 | F38: 品类名称:mirror | G38: 89170 | H38: 3439 | I38: =VLOOKUP(B38,[1]极目数据!A:D,4,0) -> -0.004592 | J38: =_xlfn.IFS(G38<=50000,"大词",AND(G38>50000,G38<=200000),"中词",G38>200000,"长尾词") -> 中词 | K38: =VLOOKUP(B38,[1]极目数据!A:S,19,0) -> 0.7724 | L38: =VLOOKUP(B38,[1]极目数据!A:T,20,0) -> 0.4083 | M38: =VLOOKUP(B38,[1]极目数据!A:P,16,0) -> 27 | N38: =VLOOKUP(B38,[1]极目数据!A:V,22,0) -> 9.722274 | O38: =VLOOKUP(B38,[1]极目数据!A:L,11,0) -> 0.71 | P38: =VLOOKUP(B38,[1]极目数据!A:J,10,0) -> 0.082285 | Q38: 39.99 | R38: =O38/(P38*Q38) -> 0.21576762 | S38: =VLOOKUP(B:B,[1]极目数据!A:H,8,FALSE) -> 87 | U38: =VLOOKUP(B:B,[1]极目数据!A:U,21,FALSE) -> 559
A39: 38 | B39: light up makeup mirror | C39: 带灯化妆镜 | D39: 高相关 | E39: 属性关键词 | F39: 功能特性:light | 品类名称:makeup,mirror | G39: 90821 | H39: 3383 | I39: =VLOOKUP(B39,[1]极目数据!A:D,4,0) -> 0.007452 | J39: =_xlfn.IFS(G39<=50000,"大词",AND(G39>50000,G39<=200000),"中词",G39>200000,"长尾词") -> 中词 | K39: =VLOOKUP(B39,[1]极目数据!A:S,19,0) -> 0.2761 | L39: =VLOOKUP(B39,[1]极目数据!A:T,20,0) -> 0.1832 | M39: =VLOOKUP(B39,[1]极目数据!A:P,16,0) -> 29 | N39: =VLOOKUP(B39,[1]极目数据!A:V,22,0) -> 18.908162 | O39: =VLOOKUP(B39,[1]极目数据!A:L,11,0) -> 1.06 | P39: =VLOOKUP(B39,[1]极目数据!A:J,10,0) -> 0.081446 | Q39: 39.99 | R39: =O39/(P39*Q39) -> 0.32545032 | S39: =VLOOKUP(B:B,[1]极目数据!A:H,8,FALSE) -> 89 | T39: =S39/7 -> 12.714286 | U39: =VLOOKUP(B:B,[1]极目数据!A:U,21,FALSE) -> 2722
A40: 39 | B40: light mirror | C40: 光镜 | D40: 高相关 | E40: 属性关键词 | F40: 功能特性:light | 品类名称:mirror | G40: 94523 | H40: 3257 | I40: =VLOOKUP(B40,[1]极目数据!A:D,4,0) -> 0.07256 | J40: =_xlfn.IFS(G40<=50000,"大词",AND(G40>50000,G40<=200000),"中词",G40>200000,"长尾词") -> 中词 | K40: =VLOOKUP(B40,[1]极目数据!A:S,19,0) -> 0.2511 | L40: =VLOOKUP(B40,[1]极目数据!A:T,20,0) -> 0.2436 | M40: =VLOOKUP(B40,[1]极目数据!A:P,16,0) -> 29 | N40: =VLOOKUP(B40,[1]极目数据!A:V,22,0) -> 8.791929 | O40: =VLOOKUP(B40,[1]极目数据!A:L,11,0) -> 0.41 | P40: =VLOOKUP(B40,[1]极目数据!A:J,10,0) -> 0.06142 | Q40: 39.99 | R40: =O40/(P40*Q40) -> 0.16692548 | S40: =VLOOKUP(B:B,[1]极目数据!A:H,8,FALSE) -> 64 | U40: =VLOOKUP(B:B,[1]极目数据!A:U,21,FALSE) -> 137316
A41: 40 | B41: makeup mirror for desk | C41: 桌面化妆镜 | D41: 高相关 | E41: 属性关键词 | F41: 品类名称:makeup,mirror | 使用场景:desk | G41: 96575 | H41: 3196 | I41: =VLOOKUP(B41,[1]极目数据!A:D,4,0) -> 0.006057 | J41: =_xlfn.IFS(G41<=50000,"大词",AND(G41>50000,G41<=200000),"中词",G41>200000,"长尾词") -> 中词 | K41: =VLOOKUP(B41,[1]极目数据!A:S,19,0) -> 0.1896 | L41: =VLOOKUP(B41,[1]极目数据!A:T,20,0) -> 0.1083 | M41: =VLOOKUP(B41,[1]极目数据!A:P,16,0) -> 29 | N41: =VLOOKUP(B41,[1]极目数据!A:V,22,0) -> 25.487508 | O41: =VLOOKUP(B41,[1]极目数据!A:L,11,0) -> 1.52 | P41: =VLOOKUP(B41,[1]极目数据!A:J,10,0) -> 0.069838 | Q41: 39.99 | R41: =O41/(P41*Q41) -> 0.54425245 | S41: =VLOOKUP(B:B,[1]极目数据!A:H,8,FALSE) -> 85 | U41: =VLOOKUP(B:B,[1]极目数据!A:U,21,FALSE) -> 48647
A42: 41 | B42: small vanity mirror with lights | C42: 带灯的小梳妆镜 | D42: 中相关 | E42: 属性关键词 | F42: 功能特性:lights | 品类名称:mirror | 尺寸/大小:small | 使用场景:vanity | G42: 101306 | H42: 3055 | I42: =VLOOKUP(B42,[1]极目数据!A:D,4,0) -> 0.003023 | J42: =_xlfn.IFS(G42<=50000,"大词",AND(G42>50000,G42<=200000),"中词",G42>200000,"长尾词") -> 中词 | K42: =VLOOKUP(B42,[1]极目数据!A:S,19,0) -> 0.2214 | L42: =VLOOKUP(B42,[1]极目数据!A:T,20,0) -> 0.0308 | M42: =VLOOKUP(B42,[1]极目数据!A:P,16,0) -> 30 | N42: =VLOOKUP(B42,[1]极目数据!A:V,22,0) -> 17.879888 | O42: =VLOOKUP(B42,[1]极目数据!A:L,11,0) -> 0.55 | P42: =VLOOKUP(B42,[1]极目数据!A:J,10,0) -> 0.041387 | Q42: 39.99 | R42: =O42/(P42*Q42) -> 0.33231301 | S42: =VLOOKUP(B:B,[1]极目数据!A:H,8,FALSE) -> 23 | U42: =VLOOKUP(B:B,[1]极目数据!A:U,21,FALSE) -> 132695
A43: 42 | B43: mirror vanity | C43: 镜面梳妆台 | D43: 高相关 | E43: 共性关键词 | F43: 品类名称:mirror | 使用场景:vanity | G43: 108206 | H43: 2873 | I43: =VLOOKUP(B43,[1]极目数据!A:D,4,0) -> 0.049491 | J43: =_xlfn.IFS(G43<=50000,"大词",AND(G43>50000,G43<=200000),"中词",G43>200000,"长尾词") -> 中词 | K43: =VLOOKUP(B43,[1]极目数据!A:S,19,0) -> 0.1671 | L43: =VLOOKUP(B43,[1]极目数据!A:T,20,0) -> 0.0784 | M43: =VLOOKUP(B43,[1]极目数据!A:P,16,0) -> 28 | N43: =VLOOKUP(B43,[1]极目数据!A:V,22,0) -> 28.152614 | O43: =VLOOKUP(B43,[1]极目数据!A:L,11,0) -> 0.89 | P43: =VLOOKUP(B43,[1]极目数据!A:J,10,0) -> 0.044756 | Q43: 39.99 | R43: =O43/(P43*Q43) -> 0.49726436 | S43: =VLOOKUP(B:B,[1]极目数据!A:H,8,FALSE) -> 38 | U43: =VLOOKUP(B:B,[1]极目数据!A:U,21,FALSE) -> 137728
A44: 43 | B44: lighted magnifying mirror | C44: 点亮的放大镜 | D44: 高相关 | E44: 属性关键词 | F44: 功能特性:lighted | 品类名称:mirror | G44: 110200 | H44: 2823 | I44: =VLOOKUP(B44,[1]极目数据!A:D,4,0) -> 0.026288 | J44: =_xlfn.IFS(G44<=50000,"大词",AND(G44>50000,G44<=200000),"中词",G44>200000,"长尾词") -> 中词 | K44: =VLOOKUP(B44,[1]极目数据!A:S,19,0) -> 0.2629 | L44: =VLOOKUP(B44,[1]极目数据!A:T,20,0) -> 0.162 | M44: =VLOOKUP(B44,[1]极目数据!A:P,16,0) -> 28 | N44: =VLOOKUP(B44,[1]极目数据!A:V,22,0) -> 11.069974 | O44: =VLOOKUP(B44,[1]极目数据!A:L,11,0) -> 0.96 | P44: =VLOOKUP(B44,[1]极目数据!A:J,10,0) -> 0.115628 | Q44: 39.99 | R44: =O44/(P44*Q44) -> 0.20761409 | S44: =VLOOKUP(B:B,[1]极目数据!A:H,8,FALSE) -> 137 | T44: =S44/7 -> 19.571429 | U44: =VLOOKUP(B:B,[1]极目数据!A:U,21,FALSE) -> 28123
A45: 44 | B45: vanity mirror for dorm | C45: 宿舍用梳妆镜 | D45: 高相关 | E45: 属性关键词 | F45: 品类名称:mirror | 使用场景:dorm,vanity | G45: 121301 | H45: 2575 | I45: =VLOOKUP(B45,[1]极目数据!A:D,4,0) -> 0.211287 | J45: =_xlfn.IFS(G45<=50000,"大词",AND(G45>50000,G45<=200000),"中词",G45>200000,"长尾词") -> 中词 | K45: =VLOOKUP(B45,[1]极目数据!A:S,19,0) -> 0.1961 | L45: =VLOOKUP(B45,[1]极目数据!A:T,20,0) -> 0.125 | M45: =VLOOKUP(B45,[1]极目数据!A:P,16,0) -> 28 | N45: =VLOOKUP(B45,[1]极目数据!A:V,22,0) -> 10.423112 | O45: =VLOOKUP(B45,[1]极目数据!A:L,11,0) -> 0.69 | P45: =VLOOKUP(B45,[1]极目数据!A:J,10,0) -> 0.078671 | Q45: 39.99 | R45: =O45/(P45*Q45) -> 0.21932241 | S45: =VLOOKUP(B:B,[1]极目数据!A:H,8,FALSE) -> 65 | U45: =VLOOKUP(B:B,[1]极目数据!A:U,21,FALSE) -> 2543
A46: 45 | B46: trifold mirror | C46: 三折镜子 | D46: 中相关 | E46: 属性关键词 | F46: 品类名称:mirror | G46: 122606 | H46: 2550 | I46: =VLOOKUP(B46,[1]极目数据!A:D,4,0) -> 0.007058 | J46: =_xlfn.IFS(G46<=50000,"大词",AND(G46>50000,G46<=200000),"中词",G46>200000,"长尾词") -> 中词 | K46: =VLOOKUP(B46,[1]极目数据!A:S,19,0) -> 0.3782 | L46: =VLOOKUP(B46,[1]极目数据!A:T,20,0) -> 0.383 | M46: =VLOOKUP(B46,[1]极目数据!A:P,16,0) -> 27 | N46: =VLOOKUP(B46,[1]极目数据!A:V,22,0) -> 7.689297 | O46: =VLOOKUP(B46,[1]极目数据!A:L,11,0) -> 0.67 | P46: =VLOOKUP(B46,[1]极目数据!A:J,10,0) -> 0.126149 | Q46: 39.99 | R46: =O46/(P46*Q46) -> 0.13281269 | S46: =VLOOKUP(B:B,[1]极目数据!A:H,8,FALSE) -> 69 | U46: =VLOOKUP(B:B,[1]极目数据!A:U,21,FALSE) -> 3284
A47: 46 | B47: gold vanity mirror | C47: 金色梳妆镜 | D47: 高相关 | E47: 属性关键词 | F47: 功能特性:gold | 品类名称:mirror | 使用场景:vanity | G47: 124997 | H47: 2505 | I47: =VLOOKUP(B47,[1]极目数据!A:D,4,0) -> 0.176205 | J47: =_xlfn.IFS(G47<=50000,"大词",AND(G47>50000,G47<=200000),"中词",G47>200000,"长尾词") -> 中词 | K47: =VLOOKUP(B47,[1]极目数据!A:S,19,0) -> 0.2138 | L47: =VLOOKUP(B47,[1]极目数据!A:T,20,0) -> 0.0652 | M47: =VLOOKUP(B47,[1]极目数据!A:P,16,0) -> 28 | N47: =VLOOKUP(B47,[1]极目数据!A:V,22,0) -> 30.058947 | O47: =VLOOKUP(B47,[1]极目数据!A:L,11,0) -> 0.68 | P47: =VLOOKUP(B47,[1]极目数据!A:J,10,0) -> 0.029276 | Q47: 39.99 | R47: =O47/(P47*Q47) -> 0.58082563 | S47: =VLOOKUP(B:B,[1]极目数据!A:H,8,FALSE) -> 19 | U47: =VLOOKUP(B:B,[1]极目数据!A:U,21,FALSE) -> 35945
A48: 47 | B48: desk mirror with lights | C48: 带灯的桌面镜 | D48: 高相关 | E48: 属性关键词 | F48: 功能特性:lights | 品类名称:mirror | 使用场景:desk | G48: 127206 | H48: 2464 | I48: =VLOOKUP(B48,[1]极目数据!A:D,4,0) -> 0.228708 | J48: =_xlfn.IFS(G48<=50000,"大词",AND(G48>50000,G48<=200000),"中词",G48>200000,"长尾词") -> 中词 | K48: =VLOOKUP(B48,[1]极目数据!A:S,19,0) -> 0.2234 | L48: =VLOOKUP(B48,[1]极目数据!A:T,20,0) -> 0.1445 | M48: =VLOOKUP(B48,[1]极目数据!A:P,16,0) -> 28 | N48: =VLOOKUP(B48,[1]极目数据!A:V,22,0) -> 25.876929 | O48: =VLOOKUP(B48,[1]极目数据!A:L,11,0) -> 0.81 | P48: =VLOOKUP(B48,[1]极目数据!A:J,10,0) -> 0.051784 | Q48: 39.99 | R48: =O48/(P48*Q48) -> 0.39114521 | S48: =VLOOKUP(B:B,[1]极目数据!A:H,8,FALSE) -> 40 | U48: =VLOOKUP(B:B,[1]极目数据!A:U,21,FALSE) -> 34065
A49: 48 | B49: vanity mirror with lights small | C49: 小型带灯梳妆镜 | D49: 高相关 | E49: 属性关键词 | F49: 功能特性:lights | 品类名称:mirror | 尺寸/大小:small | 使用场景:vanity | G49: 128290 | H49: 2444 | I49: =VLOOKUP(B49,[1]极目数据!A:D,4,0) -> 0.081953 | J49: =_xlfn.IFS(G49<=50000,"大词",AND(G49>50000,G49<=200000),"中词",G49>200000,"长尾词") -> 中词 | K49: =VLOOKUP(B49,[1]极目数据!A:S,19,0) -> 0.283 | L49: =VLOOKUP(B49,[1]极目数据!A:T,20,0) -> 0.297 | M49: =VLOOKUP(B49,[1]极目数据!A:P,16,0) -> 28 | N49: =VLOOKUP(B49,[1]极目数据!A:V,22,0) -> 16.270223 | O49: =VLOOKUP(B49,[1]极目数据!A:L,11,0) -> 0.97 | P49: =VLOOKUP(B49,[1]极目数据!A:J,10,0) -> 0.078671 | Q49: 39.99 | R49: =O49/(P49*Q49) -> 0.30832281 | S49: =VLOOKUP(B:B,[1]极目数据!A:H,8,FALSE) -> 61 | U49: =VLOOKUP(B:B,[1]极目数据!A:U,21,FALSE) -> 54631
A50: 49 | B50: mirror with light | C50: 带灯光的镜子 | D50: 高相关 | E50: 属性关键词 | F50: 功能特性:light | 品类名称:mirror | G50: 129516 | H50: 2424 | I50: =VLOOKUP(B50,[1]极目数据!A:D,4,0) -> 0.077612 | J50: =_xlfn.IFS(G50<=50000,"大词",AND(G50>50000,G50<=200000),"中词",G50>200000,"长尾词") -> 中词 | K50: =VLOOKUP(B50,[1]极目数据!A:S,19,0) -> 0.2854 | L50: =VLOOKUP(B50,[1]极目数据!A:T,20,0) -> 0.1834 | M50: =VLOOKUP(B50,[1]极目数据!A:P,16,0) -> 28 | N50: =VLOOKUP(B50,[1]极目数据!A:V,22,0) -> 11.732956 | O50: =VLOOKUP(B50,[1]极目数据!A:L,11,0) -> 0.83 | P50: =VLOOKUP(B50,[1]极目数据!A:J,10,0) -> 0.082673 | Q50: 39.99 | R50: =O50/(P50*Q50) -> 0.2510516 | S50: =VLOOKUP(B:B,[1]极目数据!A:H,8,FALSE) -> 65 | T50: =S50/7 -> 9.2857143 | U50: =VLOOKUP(B:B,[1]极目数据!A:U,21,FALSE) -> 129719
A51: 50 | B51: vanity mirrors | C51: 梳妆镜 | D51: 高相关 | E51: 共性关键词 | F51: 品类名称:mirrors | 使用场景:vanity | G51: 134746 | H51: 2333 | I51: =VLOOKUP(B51,[1]极目数据!A:D,4,0) -> -0.040993 | J51: =_xlfn.IFS(G51<=50000,"大词",AND(G51>50000,G51<=200000),"中词",G51>200000,"长尾词") -> 中词 | K51: =VLOOKUP(B51,[1]极目数据!A:S,19,0) -> 0.1493 | L51: =VLOOKUP(B51,[1]极目数据!A:T,20,0) -> 0.0682 | M51: =VLOOKUP(B51,[1]极目数据!A:P,16,0) -> 28 | N51: =VLOOKUP(B51,[1]极目数据!A:V,22,0) -> 42.323944 | O51: =VLOOKUP(B51,[1]极目数据!A:L,11,0) -> 0.75 | P51: =VLOOKUP(B51,[1]极目数据!A:J,10,0) -> 0.023627 | Q51: 39.99 | R51: =O51/(P51*Q51) -> 0.79378206 | S51: =VLOOKUP(B:B,[1]极目数据!A:H,8,FALSE) -> 7 | U51: =VLOOKUP(B:B,[1]极目数据!A:U,21,FALSE) -> 129091
A52: 51 | B52: led mirror for desk | C52: led桌面镜 | D52: 高相关 | E52: 属性关键词 | F52: 功能特性:led | 品类名称:mirror | 使用场景:desk | G52: 134746 | H52: 2333 | I52: =VLOOKUP(B52,[1]极目数据!A:D,4,0) -> 0.209245 | J52: =_xlfn.IFS(G52<=50000,"大词",AND(G52>50000,G52<=200000),"中词",G52>200000,"长尾词") -> 中词 | K52: =VLOOKUP(B52,[1]极目数据!A:S,19,0) -> 0.2576 | L52: =VLOOKUP(B52,[1]极目数据!A:T,20,0) -> 0.2745 | M52: =VLOOKUP(B52,[1]极目数据!A:P,16,0) -> 28 | N52: =VLOOKUP(B52,[1]极目数据!A:V,22,0) -> 23.261334 | O52: =VLOOKUP(B52,[1]极目数据!A:L,11,0) -> 1.28 | P52: =VLOOKUP(B52,[1]极目数据!A:J,10,0) -> 0.078671 | Q52: 39.99 | R52: =O52/(P52*Q52) -> 0.40685897 | S52: =VLOOKUP(B:B,[1]极目数据!A:H,8,FALSE) -> 59 | U52: =VLOOKUP(B:B,[1]极目数据!A:U,21,FALSE) -> 29586
A53: 52 | B53: light up mirror for desk | C53: 桌面用发光镜子 | D53: 高相关 | E53: 属性关键词 | F53: 功能特性:light | 品类名称:mirror | 使用场景:desk | G53: 140371 | H53: 2247 | I53: =VLOOKUP(B53,[1]极目数据!A:D,4,0) -> -0.03019 | J53: =_xlfn.IFS(G53<=50000,"大词",AND(G53>50000,G53<=200000),"中词",G53>200000,"长尾词") -> 中词 | K53: =VLOOKUP(B53,[1]极目数据!A:S,19,0) -> 0.2269 | L53: =VLOOKUP(B53,[1]极目数据!A:T,20,0) -> 0.1972 | M53: =VLOOKUP(B53,[1]极目数据!A:P,16,0) -> 28 | N53: =VLOOKUP(B53,[1]极目数据!A:V,22,0) -> 14.741284 | O53: =VLOOKUP(B53,[1]极目数据!A:L,11,0) -> 0.66 | P53: =VLOOKUP(B53,[1]极目数据!A:J,10,0) -> 0.059696 | Q53: 39.99 | R53: =O53/(P53*Q53) -> 0.27646955 | S53: =VLOOKUP(B:B,[1]极目数据!A:H,8,FALSE) -> 42 | U53: =VLOOKUP(B:B,[1]极目数据!A:U,21,FALSE) -> 1614
A54: 53 | B54: large vanity mirror with lights | C54: 带灯的大号梳妆镜 | D54: 中相关 | E54: 属性关键词 | F54: 功能特性:lights | 品类名称:mirror | 尺寸/大小:large | 使用场景:vanity | G54: 142459 | H54: 2217 | I54: =VLOOKUP(B54,[1]极目数据!A:D,4,0) -> -0.008569 | J54: =_xlfn.IFS(G54<=50000,"大词",AND(G54>50000,G54<=200000),"中词",G54>200000,"长尾词") -> 中词 | K54: =VLOOKUP(B54,[1]极目数据!A:S,19,0) -> 0.2893 | L54: =VLOOKUP(B54,[1]极目数据!A:T,20,0) -> 0.1841 | M54: =VLOOKUP(B54,[1]极目数据!A:P,16,0) -> 28 | N54: =VLOOKUP(B54,[1]极目数据!A:V,22,0) -> 21.271258 | O54: =VLOOKUP(B54,[1]极目数据!A:L,11,0) -> 1.01 | P54: =VLOOKUP(B54,[1]极目数据!A:J,10,0) -> 0.059705 | Q54: 39.99 | R54: =O54/(P54*Q54) -> 0.42301841 | S54: =VLOOKUP(B:B,[1]极目数据!A:H,8,FALSE) -> 42 | U54: =VLOOKUP(B:B,[1]极目数据!A:U,21,FALSE) -> 72187
A55: 54 | B55: mirror light | C55: 镜子灯 | D55: 中相关 | E55: 属性关键词 | F55: 功能特性:light | 品类名称:mirror | G55: 149373 | H55: 2121 | I55: =VLOOKUP(B55,[1]极目数据!A:D,4,0) -> 0.055911 | J55: =_xlfn.IFS(G55<=50000,"大词",AND(G55>50000,G55<=200000),"中词",G55>200000,"长尾词") -> 中词 | K55: =VLOOKUP(B55,[1]极目数据!A:S,19,0) -> 0.2548 | L55: =VLOOKUP(B55,[1]极目数据!A:T,20,0) -> 0.1282 | M55: =VLOOKUP(B55,[1]极目数据!A:P,16,0) -> 27 | N55: =VLOOKUP(B55,[1]极目数据!A:V,22,0) -> 11.117647 | O55: =VLOOKUP(B55,[1]极目数据!A:L,11,0) -> 0.42 | P55: =VLOOKUP(B55,[1]极目数据!A:J,10,0) -> 0.05037 | Q55: 39.99 | R55: =O55/(P55*Q55) -> 0.20850954 | S55: =VLOOKUP(B:B,[1]极目数据!A:H,8,FALSE) -> 14 | U55: =VLOOKUP(B:B,[1]极目数据!A:U,21,FALSE) -> 145846
A56: 55 | B56: makeup vanity mirror | C56: 化妆梳妆台镜子 | D56: 高相关 | E56: 属性关键词 | F56: 品类名称:makeup,mirror | 使用场景:vanity | G56: 153118 | H56: 2070 | I56: =VLOOKUP(B56,[1]极目数据!A:D,4,0) -> 0.077728 | J56: =_xlfn.IFS(G56<=50000,"大词",AND(G56>50000,G56<=200000),"中词",G56>200000,"长尾词") -> 中词 | K56: =VLOOKUP(B56,[1]极目数据!A:S,19,0) -> 0.2 | L56: =VLOOKUP(B56,[1]极目数据!A:T,20,0) -> 0.2094 | M56: =VLOOKUP(B56,[1]极目数据!A:P,16,0) -> 27 | N56: =VLOOKUP(B56,[1]极目数据!A:V,22,0) -> 20.68606 | O56: =VLOOKUP(B56,[1]极目数据!A:L,11,0) -> 0.83 | P56: =VLOOKUP(B56,[1]极目数据!A:J,10,0) -> 0.05656 | Q56: 39.99 | R56: =O56/(P56*Q56) -> 0.36695878 | S56: =VLOOKUP(B:B,[1]极目数据!A:H,8,FALSE) -> 37 | U56: =VLOOKUP(B:B,[1]极目数据!A:U,21,FALSE) -> 114246
A57: 56 | B57: small mirror for desk | C57: 桌面用小镜子 | D57: 中相关 | E57: 属性关键词 | F57: 品类名称:mirror | 尺寸/大小:small | 使用场景:desk | G57: 156291 | H57: 2030 | I57: =VLOOKUP(B57,[1]极目数据!A:D,4,0) -> 0.087638 | J57: =_xlfn.IFS(G57<=50000,"大词",AND(G57>50000,G57<=200000),"中词",G57>200000,"长尾词") -> 中词 | K57: =VLOOKUP(B57,[1]极目数据!A:S,19,0) -> 0.2338 | L57: =VLOOKUP(B57,[1]极目数据!A:T,20,0) -> 0.1875 | M57: =VLOOKUP(B57,[1]极目数据!A:P,16,0) -> 27 | N57: =VLOOKUP(B57,[1]极目数据!A:V,22,0) -> 6.901912 | O57: =VLOOKUP(B57,[1]极目数据!A:L,11,0) -> 0.62 | P57: =VLOOKUP(B57,[1]极目数据!A:J,10,0) -> 0.113012 | Q57: 39.99 | R57: =O57/(P57*Q57) -> 0.13718787 | S57: =VLOOKUP(B:B,[1]极目数据!A:H,8,FALSE) -> 63 | U57: =VLOOKUP(B:B,[1]极目数据!A:U,21,FALSE) -> 121831
A58: 57 | B58: 360 mirror for haircuts for men | C58: 360男士理发镜 | D58: 中相关 | E58: 属性关键词 | F58: 功能特性:360 | 品类名称:mirror | G58: 157117 | H58: 2020 | I58: =VLOOKUP(B58,[1]极目数据!A:D,4,0) -> 0.012673 | J58: =_xlfn.IFS(G58<=50000,"大词",AND(G58>50000,G58<=200000),"中词",G58>200000,"长尾词") -> 中词 | K58: =VLOOKUP(B58,[1]极目数据!A:S,19,0) -> 0.725 | L58: =VLOOKUP(B58,[1]极目数据!A:T,20,0) -> 0.4486 | M58: =VLOOKUP(B58,[1]极目数据!A:P,16,0) -> 12 | N58: =VLOOKUP(B58,[1]极目数据!A:V,22,0) -> 13.970451 | O58: =VLOOKUP(B58,[1]极目数据!A:L,11,0) -> 1.16 | P58: =VLOOKUP(B58,[1]极目数据!A:J,10,0) -> 0.110233 | Q58: 39.99 | R58: =O58/(P58*Q58) -> 0.2631449 | S58: =VLOOKUP(B:B,[1]极目数据!A:H,8,FALSE) -> 42 | U58: =VLOOKUP(B:B,[1]极目数据!A:U,21,FALSE) -> 109
A59: 58 | B59: light mirror makeup | C59: 化妆光镜 | D59: 高相关 | E59: 属性关键词 | F59: 功能特性:light | 品类名称:makeup,mirror | G59: 158328 | H59: 2005 | I59: =VLOOKUP(B59,[1]极目数据!A:D,4,0) -> 0.138587 | J59: =_xlfn.IFS(G59<=50000,"大词",AND(G59>50000,G59<=200000),"中词",G59>200000,"长尾词") -> 中词 | K59: =VLOOKUP(B59,[1]极目数据!A:S,19,0) -> 0.2293 | L59: =VLOOKUP(B59,[1]极目数据!A:T,20,0) -> 0.2058 | M59: =VLOOKUP(B59,[1]极目数据!A:P,16,0) -> 27 | N59: =VLOOKUP(B59,[1]极目数据!A:V,22,0) -> 16.443226 | O59: =VLOOKUP(B59,[1]极目数据!A:L,11,0) -> 1 | P59: =VLOOKUP(B59,[1]极目数据!A:J,10,0) -> 0.080884 | Q59: 39.99 | R59: =O59/(P59*Q59) -> 0.30916191 | S59: =VLOOKUP(B:B,[1]极目数据!A:H,8,FALSE) -> 52 | T59: =S59/7 -> 7.4285714 | U59: =VLOOKUP(B:B,[1]极目数据!A:U,21,FALSE) -> 69581
A60: 59 | B60: best rated lighted makeup mirror | C60: 最佳评价的带灯化妆镜 | D60: 高相关 | E60: 属性关键词 | F60: 功能特性:lighted | 品类名称:makeup,mirror | G60: 163509 | H60: 1944 | I60: =VLOOKUP(B60,[1]极目数据!A:D,4,0) -> 0.416725 | J60: =_xlfn.IFS(G60<=50000,"大词",AND(G60>50000,G60<=200000),"中词",G60>200000,"长尾词") -> 中词 | K60: =VLOOKUP(B60,[1]极目数据!A:S,19,0) -> 0.1974 | L60: =VLOOKUP(B60,[1]极目数据!A:T,20,0) -> 0.3208 | M60: =VLOOKUP(B60,[1]极目数据!A:P,16,0) -> 27 | N60: =VLOOKUP(B60,[1]极目数据!A:V,22,0) -> 37.750263 | O60: =VLOOKUP(B60,[1]极目数据!A:L,11,0) -> 1.49 | P60: =VLOOKUP(B60,[1]极目数据!A:J,10,0) -> 0.05245 | Q60: 39.99 | R60: =O60/(P60*Q60) -> 0.71037779 | S60: =VLOOKUP(B:B,[1]极目数据!A:H,8,FALSE) -> 30 | U60: =VLOOKUP(B:B,[1]极目数据!A:U,21,FALSE) -> 673
A61: 60 | B61: mirror for vanity | C61: 梳妆台用的镜子 | D61: 高相关 | E61: 属性关键词 | F61: 品类名称:mirror | 使用场景:vanity | G61: 163509 | H61: 1944 | I61: =VLOOKUP(B61,[1]极目数据!A:D,4,0) -> -0.101238 | J61: =_xlfn.IFS(G61<=50000,"大词",AND(G61>50000,G61<=200000),"中词",G61>200000,"长尾词") -> 中词 | K61: =VLOOKUP(B61,[1]极目数据!A:S,19,0) -> 0.1532 | L61: =VLOOKUP(B61,[1]极目数据!A:T,20,0) -> 0.16 | M61: =VLOOKUP(B61,[1]极目数据!A:P,16,0) -> 27 | N61: =VLOOKUP(B61,[1]极目数据!A:V,22,0) -> 11.205623 | O61: =VLOOKUP(B61,[1]极目数据!A:L,11,0) -> 0.5 | P61: =VLOOKUP(B61,[1]极目数据!A:J,10,0) -> 0.058899 | Q61: 39.99 | R61: =O61/(P61*Q61) -> 0.21228078 | S61: =VLOOKUP(B:B,[1]极目数据!A:H,8,FALSE) -> 34 | U61: =VLOOKUP(B:B,[1]极目数据!A:U,21,FALSE) -> 128255
A62: 61 | B62: vanity mirror for desk | C62: 桌用梳妆镜 | D62: 高相关 | E62: 属性关键词 | F62: 品类名称:mirror | 使用场景:desk,vanity | G62: 165737 | H62: 1919 | I62: =VLOOKUP(B62,[1]极目数据!A:D,4,0) -> -0.035096 | J62: =_xlfn.IFS(G62<=50000,"大词",AND(G62>50000,G62<=200000),"中词",G62>200000,"长尾词") -> 中词 | K62: =VLOOKUP(B62,[1]极目数据!A:S,19,0) -> 0.1999 | L62: =VLOOKUP(B62,[1]极目数据!A:T,20,0) -> 0.1025 | M62: =VLOOKUP(B62,[1]极目数据!A:P,16,0) -> 27 | N62: =VLOOKUP(B62,[1]极目数据!A:V,22,0) -> 32.389614 | O62: =VLOOKUP(B62,[1]极目数据!A:L,11,0) -> 0.91 | P62: =VLOOKUP(B62,[1]极目数据!A:J,10,0) -> 0.036123 | Q62: 39.99 | R62: =O62/(P62*Q62) -> 0.62995014 | S62: =VLOOKUP(B:B,[1]极目数据!A:H,8,FALSE) -> 20 | U62: =VLOOKUP(B:B,[1]极目数据!A:U,21,FALSE) -> 35290
A63: 62 | B63: mirror makeup | C63: 化妆镜 | D63: 高相关 | E63: 共性关键词 | F63: 品类名称:makeup,mirror | G63: 168450 | H63: 1888 | I63: =VLOOKUP(B63,[1]极目数据!A:D,4,0) -> 0.047165 | J63: =_xlfn.IFS(G63<=50000,"大词",AND(G63>50000,G63<=200000),"中词",G63>200000,"长尾词") -> 中词 | K63: =VLOOKUP(B63,[1]极目数据!A:S,19,0) -> 0.2513 | L63: =VLOOKUP(B63,[1]极目数据!A:T,20,0) -> 0.1857 | M63: =VLOOKUP(B63,[1]极目数据!A:P,16,0) -> 27 | N63: =VLOOKUP(B63,[1]极目数据!A:V,22,0) -> 20.251325 | O63: =VLOOKUP(B63,[1]极目数据!A:L,11,0) -> 1.24 | P63: =VLOOKUP(B63,[1]极目数据!A:J,10,0) -> 0.08197 | Q63: 39.99 | R63: =O63/(P63*Q63) -> 0.37828171 | S63: =VLOOKUP(B:B,[1]极目数据!A:H,8,FALSE) -> 50 | T63: =S63/7 -> 7.1428571 | U63: =VLOOKUP(B:B,[1]极目数据!A:U,21,FALSE) -> 139115
A64: 63 | B64: self cut system | C64: 自剪系统 | D64: 中相关 | E64: 属性关键词 | G64: 172871 | H64: 1843 | I64: =VLOOKUP(B64,[1]极目数据!A:D,4,0) -> -0.008655 | J64: =_xlfn.IFS(G64<=50000,"大词",AND(G64>50000,G64<=200000),"中词",G64>200000,"长尾词") -> 中词 | K64: =VLOOKUP(B64,[1]极目数据!A:S,19,0) -> 0.7233 | L64: =VLOOKUP(B64,[1]极目数据!A:T,20,0) -> 0.4688 | M64: =VLOOKUP(B64,[1]极目数据!A:P,16,0) -> 26 | N64: =VLOOKUP(B64,[1]极目数据!A:V,22,0) -> 12.262602 | O64: =VLOOKUP(B64,[1]极目数据!A:L,11,0) -> 0.55 | P64: =VLOOKUP(B64,[1]极目数据!A:J,10,0) -> 0.060346 | Q64: 39.99 | R64: =O64/(P64*Q64) -> 0.22790969 | S64: =VLOOKUP(B:B,[1]极目数据!A:H,8,FALSE) -> 36 | U64: =VLOOKUP(B:B,[1]极目数据!A:U,21,FALSE) -> 158
A65: 64 | B65: espejos para maquillaje | C65: 化妆镜 | D65: 高相关 | E65: 属性关键词 | F65: 品类名称:espejos,para | 使用场景:maquillaje | G65: 172871 | H65: 1843 | I65: =VLOOKUP(B65,[1]极目数据!A:D,4,0) -> -0.045994 | J65: =_xlfn.IFS(G65<=50000,"大词",AND(G65>50000,G65<=200000),"中词",G65>200000,"长尾词") -> 中词 | K65: =VLOOKUP(B65,[1]极目数据!A:S,19,0) -> 0.1836 | L65: =VLOOKUP(B65,[1]极目数据!A:T,20,0) -> 0.0435 | M65: =VLOOKUP(B65,[1]极目数据!A:P,16,0) -> 27 | N65: =VLOOKUP(B65,[1]极目数据!A:V,22,0) -> 47.745316 | O65: =VLOOKUP(B65,[1]极目数据!A:L,11,0) -> 1.14 | P65: =VLOOKUP(B65,[1]极目数据!A:J,10,0) -> 0.031836 | Q65: 39.99 | R65: =O65/(P65*Q65) -> 0.89543683 | S65: =VLOOKUP(B:B,[1]极目数据!A:H,8,FALSE) -> 15 | U65: =VLOOKUP(B:B,[1]极目数据!A:U,21,FALSE) -> 1244
A66: 65 | B66: magnified mirror with lights | C66: 带灯放大镜 | D66: 高相关 | E66: 属性关键词 | F66: 功能特性:lights | 品类名称:mirror | G66: 175884 | H66: 1813 | I66: =VLOOKUP(B66,[1]极目数据!A:D,4,0) -> 0.069182 | J66: =_xlfn.IFS(G66<=50000,"大词",AND(G66>50000,G66<=200000),"中词",G66>200000,"长尾词") -> 中词 | K66: =VLOOKUP(B66,[1]极目数据!A:S,19,0) -> 0.2759 | L66: =VLOOKUP(B66,[1]极目数据!A:T,20,0) -> 0.2079 | M66: =VLOOKUP(B66,[1]极目数据!A:P,16,0) -> 27 | N66: =VLOOKUP(B66,[1]极目数据!A:V,22,0) -> 11.648351 | O66: =VLOOKUP(B66,[1]极目数据!A:L,11,0) -> 1.06 | P66: =VLOOKUP(B66,[1]极目数据!A:J,10,0) -> 0.121047 | Q66: 39.99 | R66: =O66/(P66*Q66) -> 0.21897797 | S66: =VLOOKUP(B:B,[1]极目数据!A:H,8,FALSE) -> 69 | T66: =S66/7 -> 9.8571429 | U66: =VLOOKUP(B:B,[1]极目数据!A:U,21,FALSE) -> 11186
A67: 66 | B67: haircut mirror | C67: 理发镜 | D67: 中相关 | E67: 属性关键词 | F67: 品类名称:mirror | G67: 179609 | H67: 1777 | I67: =VLOOKUP(B67,[1]极目数据!A:D,4,0) -> -0.012104 | J67: =_xlfn.IFS(G67<=50000,"大词",AND(G67>50000,G67<=200000),"中词",G67>200000,"长尾词") -> 中词 | K67: =VLOOKUP(B67,[1]极目数据!A:S,19,0) -> 0.6988 | L67: =VLOOKUP(B67,[1]极目数据!A:T,20,0) -> 0.4435 | M67: =VLOOKUP(B67,[1]极目数据!A:P,16,0) -> 26 | N67: =VLOOKUP(B67,[1]极目数据!A:V,22,0) -> 15.32958 | O67: =VLOOKUP(B67,[1]极目数据!A:L,11,0) -> 1.48 | P67: =VLOOKUP(B67,[1]极目数据!A:J,10,0) -> 0.12851 | Q67: 39.99 | R67: =O67/(P67*Q67) -> 0.28798733 | S67: =VLOOKUP(B:B,[1]极目数据!A:H,8,FALSE) -> 61 | U67: =VLOOKUP(B:B,[1]极目数据!A:U,21,FALSE) -> 941
A68: 67 | B68: small desk mirror | C68: 小桌子镜子 | D68: 中相关 | E68: 属性关键词 | F68: 品类名称:mirror | 尺寸/大小:small | 使用场景:desk | G68: 181206 | H68: 1762 | I68: =VLOOKUP(B68,[1]极目数据!A:D,4,0) -> 0.119416 | J68: =_xlfn.IFS(G68<=50000,"大词",AND(G68>50000,G68<=200000),"中词",G68>200000,"长尾词") -> 中词 | K68: =VLOOKUP(B68,[1]极目数据!A:S,19,0) -> 0.2149 | L68: =VLOOKUP(B68,[1]极目数据!A:T,20,0) -> 0.1344 | M68: =VLOOKUP(B68,[1]极目数据!A:P,16,0) -> 26 | N68: =VLOOKUP(B68,[1]极目数据!A:V,22,0) -> 7.250505 | O68: =VLOOKUP(B68,[1]极目数据!A:L,11,0) -> 0.44 | P68: =VLOOKUP(B68,[1]极目数据!A:J,10,0) -> 0.081374 | Q68: 39.99 | R68: =O68/(P68*Q68) -> 0.13521212 | S68: =VLOOKUP(B:B,[1]极目数据!A:H,8,FALSE) -> 32 | U68: =VLOOKUP(B:B,[1]极目数据!A:U,21,FALSE) -> 124929
A69: 68 | B69: small mirror with lights | C69: 带灯的小镜子 | D69: 高相关 | E69: 属性关键词 | F69: 功能特性:lights | 品类名称:mirror | 尺寸/大小:small | G69: 181739 | H69: 1757 | I69: =VLOOKUP(B69,[1]极目数据!A:D,4,0) -> 0.072442 | J69: =_xlfn.IFS(G69<=50000,"大词",AND(G69>50000,G69<=200000),"中词",G69>200000,"长尾词") -> 中词 | K69: =VLOOKUP(B69,[1]极目数据!A:S,19,0) -> 0.3276 | L69: =VLOOKUP(B69,[1]极目数据!A:T,20,0) -> 0.193 | M69: =VLOOKUP(B69,[1]极目数据!A:P,16,0) -> 27 | N69: =VLOOKUP(B69,[1]极目数据!A:V,22,0) -> 9.656224 | O69: =VLOOKUP(B69,[1]极目数据!A:L,11,0) -> 0.57 | P69: =VLOOKUP(B69,[1]极目数据!A:J,10,0) -> 0.076635 | Q69: 39.99 | R69: =O69/(P69*Q69) -> 0.18599287 | S69: =VLOOKUP(B:B,[1]极目数据!A:H,8,FALSE) -> 25 | U69: =VLOOKUP(B:B,[1]极目数据!A:U,21,FALSE) -> 71453
A70: 69 | B70: self haircut mirror | C70: 自用理发镜 | D70: 中相关 | E70: 属性关键词 | F70: 品类名称:mirror | G70: 182291 | H70: 1752 | I70: =VLOOKUP(B70,[1]极目数据!A:D,4,0) -> -0.014523 | J70: =_xlfn.IFS(G70<=50000,"大词",AND(G70>50000,G70<=200000),"中词",G70>200000,"长尾词") -> 中词 | K70: =VLOOKUP(B70,[1]极目数据!A:S,19,0) -> 0.6657 | L70: =VLOOKUP(B70,[1]极目数据!A:T,20,0) -> 0.45 | M70: =VLOOKUP(B70,[1]极目数据!A:P,16,0) -> 12 | N70: =VLOOKUP(B70,[1]极目数据!A:V,22,0) -> 20.406854 | O70: =VLOOKUP(B70,[1]极目数据!A:L,11,0) -> 1.77 | P70: =VLOOKUP(B70,[1]极目数据!A:J,10,0) -> 0.115647 | Q70: 39.99 | R70: =O70/(P70*Q70) -> 0.38272558 | S70: =VLOOKUP(B:B,[1]极目数据!A:H,8,FALSE) -> 54 | U70: =VLOOKUP(B:B,[1]极目数据!A:U,21,FALSE) -> 348
A71: 70 | B71: 3 way mirror for self hair cutting | C71: 自剪头发用三面镜 | D71: 中相关 | E71: 属性关键词 | F71: 品类名称:mirror | 使用场景:hair | G71: 183368 | H71: 1742 | I71: =VLOOKUP(B71,[1]极目数据!A:D,4,0) -> -0.002904 | J71: =_xlfn.IFS(G71<=50000,"大词",AND(G71>50000,G71<=200000),"中词",G71>200000,"长尾词") -> 中词 | K71: =VLOOKUP(B71,[1]极目数据!A:S,19,0) -> 0.6579 | L71: =VLOOKUP(B71,[1]极目数据!A:T,20,0) -> 0.4666 | M71: =VLOOKUP(B71,[1]极目数据!A:P,16,0) -> 26 | N71: =VLOOKUP(B71,[1]极目数据!A:V,22,0) -> 10.236522 | O71: =VLOOKUP(B71,[1]极目数据!A:L,11,0) -> 0.93 | P71: =VLOOKUP(B71,[1]极目数据!A:J,10,0) -> 0.121135 | Q71: 39.99 | R71: =O71/(P71*Q71) -> 0.19198261 | S71: =VLOOKUP(B:B,[1]极目数据!A:H,8,FALSE) -> 57 | U71: =VLOOKUP(B:B,[1]极目数据!A:U,21,FALSE) -> 115
A72: 71 | B72: makeup light mirror | C72: 化妆镜 | D72: 高相关 | E72: 属性关键词 | F72: 功能特性:light | 品类名称:makeup,mirror | G72: 185065 | H72: 1727 | I72: =VLOOKUP(B72,[1]极目数据!A:D,4,0) -> -0.043869 | J72: =_xlfn.IFS(G72<=50000,"大词",AND(G72>50000,G72<=200000),"中词",G72>200000,"长尾词") -> 中词 | K72: =VLOOKUP(B72,[1]极目数据!A:S,19,0) -> 0.3596 | L72: =VLOOKUP(B72,[1]极目数据!A:T,20,0) -> 0.2413 | M72: =VLOOKUP(B72,[1]极目数据!A:P,16,0) -> 27 | N72: =VLOOKUP(B72,[1]极目数据!A:V,22,0) -> 18.812133 | O72: =VLOOKUP(B72,[1]极目数据!A:L,11,0) -> 1.14 | P72: =VLOOKUP(B72,[1]极目数据!A:J,10,0) -> 0.080799 | Q72: 39.99 | R72: =O72/(P72*Q72) -> 0.35281534 | S72: =VLOOKUP(B:B,[1]极目数据!A:H,8,FALSE) -> 45 | T72: =S72/7 -> 6.4285714 | U72: =VLOOKUP(B:B,[1]极目数据!A:U,21,FALSE) -> 69602
A73: 72 | B73: mirror desk | C73: 镜面书桌 | D73: 高相关 | E73: 属性关键词 | F73: 品类名称:mirror | 使用场景:desk | G73: 186181 | H73: 1717 | I73: =VLOOKUP(B73,[1]极目数据!A:D,4,0) -> 0.120174 | J73: =_xlfn.IFS(G73<=50000,"大词",AND(G73>50000,G73<=200000),"中词",G73>200000,"长尾词") -> 中词 | K73: =VLOOKUP(B73,[1]极目数据!A:S,19,0) -> 0.1912 | L73: =VLOOKUP(B73,[1]极目数据!A:T,20,0) -> 0.1555 | M73: =VLOOKUP(B73,[1]极目数据!A:P,16,0) -> 27 | N73: =VLOOKUP(B73,[1]极目数据!A:V,22,0) -> 13.239189 | O73: =VLOOKUP(B73,[1]极目数据!A:L,11,0) -> 0.81 | P73: =VLOOKUP(B73,[1]极目数据!A:J,10,0) -> 0.076289 | Q73: 39.99 | R73: =O73/(P73*Q73) -> 0.26550438 | S73: =VLOOKUP(B:B,[1]极目数据!A:H,8,FALSE) -> 36 | U73: =VLOOKUP(B:B,[1]极目数据!A:U,21,FALSE) -> 132022
A74: 73 | B74: vanity makeup mirror | C74: 化妆镜 | D74: 高相关 | E74: 共性关键词 | F74: 品类名称:makeup,mirror | 使用场景:vanity | G74: 190299 | H74: 1681 | I74: =VLOOKUP(B74,[1]极目数据!A:D,4,0) -> 0.069175 | J74: =_xlfn.IFS(G74<=50000,"大词",AND(G74>50000,G74<=200000),"中词",G74>200000,"长尾词") -> 中词 | K74: =VLOOKUP(B74,[1]极目数据!A:S,19,0) -> 0.1711 | L74: =VLOOKUP(B74,[1]极目数据!A:T,20,0) -> 0.0926 | M74: =VLOOKUP(B74,[1]极目数据!A:P,16,0) -> 27 | N74: =VLOOKUP(B74,[1]极目数据!A:V,22,0) -> 42.436667 | O74: =VLOOKUP(B74,[1]极目数据!A:L,11,0) -> 1.25 | P74: =VLOOKUP(B74,[1]极目数据!A:J,10,0) -> 0.039353 | Q74: 39.99 | R74: =O74/(P74*Q74) -> 0.79429305 | S74: =VLOOKUP(B:B,[1]极目数据!A:H,8,FALSE) -> 21 | U74: =VLOOKUP(B:B,[1]极目数据!A:U,21,FALSE) -> 112069
A75: 74 | B75: portable mirror with lights | C75: 带灯便携式镜子 | D75: 中相关 | E75: 属性关键词 | F75: 功能特性:portable,lights | 品类名称:mirror | G75: 193330 | H75: 1656 | I75: =VLOOKUP(B75,[1]极目数据!A:D,4,0) -> 0.004521 | J75: =_xlfn.IFS(G75<=50000,"大词",AND(G75>50000,G75<=200000),"中词",G75>200000,"长尾词") -> 中词 | K75: =VLOOKUP(B75,[1]极目数据!A:S,19,0) -> 0.5549 | L75: =VLOOKUP(B75,[1]极目数据!A:T,20,0) -> 0.3522 | M75: =VLOOKUP(B75,[1]极目数据!A:P,16,0) -> 26 | N75: =VLOOKUP(B75,[1]极目数据!A:V,22,0) -> 7.872254 | O75: =VLOOKUP(B75,[1]极目数据!A:L,11,0) -> 0.7 | P75: =VLOOKUP(B75,[1]极目数据!A:J,10,0) -> 0.118136 | Q75: 39.99 | R75: =O75/(P75*Q75) -> 0.1481714 | S75: =VLOOKUP(B:B,[1]极目数据!A:H,8,FALSE) -> 62 | U75: =VLOOKUP(B:B,[1]极目数据!A:U,21,FALSE) -> 36054
A76: 75 | B76: wall mounted makeup mirror | C76: 壁挂式化妆镜 | D76: 中相关 | E76: 属性关键词 | F76: 功能特性:mounted | 品类名称:makeup,mirror | 使用场景:wall | G76: 194556 | H76: 1646 | I76: =VLOOKUP(B76,[1]极目数据!A:D,4,0) -> 0.041013 | J76: =_xlfn.IFS(G76<=50000,"大词",AND(G76>50000,G76<=200000),"中词",G76>200000,"长尾词") -> 中词 | K76: =VLOOKUP(B76,[1]极目数据!A:S,19,0) -> 0.3313 | L76: =VLOOKUP(B76,[1]极目数据!A:T,20,0) -> 0.2425 | M76: =VLOOKUP(B76,[1]极目数据!A:P,16,0) -> 27 | N76: =VLOOKUP(B76,[1]极目数据!A:V,22,0) -> 9.062919 | O76: =VLOOKUP(B76,[1]极目数据!A:L,11,0) -> 0.63 | P76: =VLOOKUP(B76,[1]极目数据!A:J,10,0) -> 0.092685 | Q76: 39.99 | R76: =O76/(P76*Q76) -> 0.1699729 | S76: =VLOOKUP(B:B,[1]极目数据!A:H,8,FALSE) -> 54 | U76: =VLOOKUP(B:B,[1]极目数据!A:U,21,FALSE) -> 67844
A77: 76 | B77: desk mirror for dorm | C77: 宿舍用桌面镜子 | D77: 高相关 | E77: 属性关键词 | F77: 品类名称:mirror | 使用场景:dorm,desk | G77: 201629 | H77: 1590 | I77: =VLOOKUP(B77,[1]极目数据!A:D,4,0) -> 0.130759 | J77: =_xlfn.IFS(G77<=50000,"大词",AND(G77>50000,G77<=200000),"中词",G77>200000,"长尾词") -> 长尾词 | K77: =VLOOKUP(B77,[1]极目数据!A:S,19,0) -> 0.2603 | L77: =VLOOKUP(B77,[1]极目数据!A:T,20,0) -> 0.1568 | M77: =VLOOKUP(B77,[1]极目数据!A:P,16,0) -> 27 | N77: =VLOOKUP(B77,[1]极目数据!A:V,22,0) -> 12.27989 | O77: =VLOOKUP(B77,[1]极目数据!A:L,11,0) -> 0.61 | P77: =VLOOKUP(B77,[1]极目数据!A:J,10,0) -> 0.062704 | Q77: 39.99 | R77: =O77/(P77*Q77) -> 0.24326699 | S77: =VLOOKUP(B:B,[1]极目数据!A:H,8,FALSE) -> 31 | U77: =VLOOKUP(B:B,[1]极目数据!A:U,21,FALSE) -> 5999
A78: 77 | B78: makeup mirrors | C78: 化妆镜 | D78: 高相关 | E78: 共性关键词 | F78: 品类名称:makeup,mirrors | G78: 201629 | H78: 1590 | I78: =VLOOKUP(B78,[1]极目数据!A:D,4,0) -> 0.106764 | J78: =_xlfn.IFS(G78<=50000,"大词",AND(G78>50000,G78<=200000),"中词",G78>200000,"长尾词") -> 长尾词 | K78: =VLOOKUP(B78,[1]极目数据!A:S,19,0) -> 0.2159 | L78: =VLOOKUP(B78,[1]极目数据!A:T,20,0) -> 0.08 | M78: =VLOOKUP(B78,[1]极目数据!A:P,16,0) -> 27 | N78: =VLOOKUP(B78,[1]极目数据!A:V,22,0) -> 23.007112 | O78: =VLOOKUP(B78,[1]极目数据!A:L,11,0) -> 1.46 | P78: =VLOOKUP(B78,[1]极目数据!A:J,10,0) -> 0.078671 | Q78: 39.99 | R78: =O78/(P78*Q78) -> 0.46407351 | S78: =VLOOKUP(B:B,[1]极目数据!A:H,8,FALSE) -> 40 | U78: =VLOOKUP(B:B,[1]极目数据!A:U,21,FALSE) -> 119787
A79: 78 | B79: led light mirror | C79: LED灯镜 | D79: 中相关 | E79: 属性关键词 | F79: 功能特性:led,light | 品类名称:mirror | G79: 202277 | H79: 1585 | I79: =VLOOKUP(B79,[1]极目数据!A:D,4,0) -> -0.024047 | J79: =_xlfn.IFS(G79<=50000,"大词",AND(G79>50000,G79<=200000),"中词",G79>200000,"长尾词") -> 长尾词 | K79: =VLOOKUP(B79,[1]极目数据!A:S,19,0) -> 0.2676 | L79: =VLOOKUP(B79,[1]极目数据!A:T,20,0) -> 0.2 | M79: =VLOOKUP(B79,[1]极目数据!A:P,16,0) -> 27 | N79: =VLOOKUP(B79,[1]极目数据!A:V,22,0) -> 15.436975 | O79: =VLOOKUP(B79,[1]极目数据!A:L,11,0) -> 0.59 | P79: =VLOOKUP(B79,[1]极目数据!A:J,10,0) -> 0.051176 | Q79: 39.99 | R79: =O79/(P79*Q79) -> 0.28829311 | S79: =VLOOKUP(B:B,[1]极目数据!A:H,8,FALSE) -> 23 | U79: =VLOOKUP(B:B,[1]极目数据!A:U,21,FALSE) -> 80853
A80: 79 | B80: make up mirrors lighted magnifying stand up | C80: 立式带灯放大化妆镜 | D80: 高相关 | E80: 属性关键词 | F80: 功能特性:lighted,stand | 品类名称:mirrors,make | G80: 202277 | H80: 1585 | I80: =VLOOKUP(B80,[1]极目数据!A:D,4,0) -> 0.039913 | J80: =_xlfn.IFS(G80<=50000,"大词",AND(G80>50000,G80<=200000),"中词",G80>200000,"长尾词") -> 长尾词 | K80: =VLOOKUP(B80,[1]极目数据!A:S,19,0) -> 0.3121 | L80: =VLOOKUP(B80,[1]极目数据!A:T,20,0) -> 0.2329 | M80: =VLOOKUP(B80,[1]极目数据!A:P,16,0) -> 27 | N80: =VLOOKUP(B80,[1]极目数据!A:V,22,0) -> 17.846338 | O80: =VLOOKUP(B80,[1]极目数据!A:L,11,0) -> 1.64 | P80: =VLOOKUP(B80,[1]极目数据!A:J,10,0) -> 0.122714 | Q80: 39.99 | R80: =O80/(P80*Q80) -> 0.33419376 | S80: =VLOOKUP(B:B,[1]极目数据!A:H,8,FALSE) -> 65 | T80: =S80/7 -> 9.2857143 | U80: =VLOOKUP(B:B,[1]极目数据!A:U,21,FALSE) -> 752
A81: 80 | B81: led mirror vanity | C81: led梳妆镜 | D81: 高相关 | E81: 属性关键词 | F81: 功能特性:led | 品类名称:mirror | 使用场景:vanity | G81: 213583 | H81: 1505 | I81: =VLOOKUP(B81,[1]极目数据!A:D,4,0) -> -0.240385 | J81: =_xlfn.IFS(G81<=50000,"大词",AND(G81>50000,G81<=200000),"中词",G81>200000,"长尾词") -> 长尾词 | K81: =VLOOKUP(B81,[1]极目数据!A:S,19,0) -> 0.208 | L81: =VLOOKUP(B81,[1]极目数据!A:T,20,0) -> 0.0834 | M81: =VLOOKUP(B81,[1]极目数据!A:P,16,0) -> 27 | N81: =VLOOKUP(B81,[1]极目数据!A:V,22,0) -> 14.886857 | O81: =VLOOKUP(B81,[1]极目数据!A:L,11,0) -> 0.74 | P81: =VLOOKUP(B81,[1]极目数据!A:J,10,0) -> 0.061128 | Q81: 39.99 | R81: =O81/(P81*Q81) -> 0.30271931 | S81: =VLOOKUP(B:B,[1]极目数据!A:H,8,FALSE) -> 29 | U81: =VLOOKUP(B:B,[1]极目数据!A:U,21,FALSE) -> 75835
A82: 81 | B82: desktop mirror | C82: 桌面镜 | D82: 中相关 | E82: 属性关键词 | F82: 品类名称:mirror | G82: 215093 | H82: 1494 | I82: =VLOOKUP(B82,[1]极目数据!A:D,4,0) -> 0.067586 | J82: =_xlfn.IFS(G82<=50000,"大词",AND(G82>50000,G82<=200000),"中词",G82>200000,"长尾词") -> 长尾词 | K82: =VLOOKUP(B82,[1]极目数据!A:S,19,0) -> 0.2128 | L82: =VLOOKUP(B82,[1]极目数据!A:T,20,0) -> 0.1 | M82: =VLOOKUP(B82,[1]极目数据!A:P,16,0) -> 27 | N82: =VLOOKUP(B82,[1]极目数据!A:V,22,0) -> 13.302381 | O82: =VLOOKUP(B82,[1]极目数据!A:L,11,0) -> 0.55 | P82: =VLOOKUP(B82,[1]极目数据!A:J,10,0) -> 0.055629 | Q82: 39.99 | R82: =O82/(P82*Q82) -> 0.24723505 | S82: =VLOOKUP(B:B,[1]极目数据!A:H,8,FALSE) -> 7 | U82: =VLOOKUP(B:B,[1]极目数据!A:U,21,FALSE) -> 19553
A83: 82 | B83: tabletop mirror | C83: 桌面镜子 | D83: 中相关 | E83: 属性关键词 | F83: 品类名称:mirror | G83: 218903 | H83: 1469 | I83: =VLOOKUP(B83,[1]极目数据!A:D,4,0) -> 0.044572 | J83: =_xlfn.IFS(G83<=50000,"大词",AND(G83>50000,G83<=200000),"中词",G83>200000,"长尾词") -> 长尾词 | K83: =VLOOKUP(B83,[1]极目数据!A:S,19,0) -> 0.268 | L83: =VLOOKUP(B83,[1]极目数据!A:T,20,0) -> 0.1052 | M83: =VLOOKUP(B83,[1]极目数据!A:P,16,0) -> 27 | N83: =VLOOKUP(B83,[1]极目数据!A:V,22,0) -> 9.568882 | O83: =VLOOKUP(B83,[1]极目数据!A:L,11,0) -> 0.79 | P83: =VLOOKUP(B83,[1]极目数据!A:J,10,0) -> 0.09301 | Q83: 39.99 | R83: =O83/(P83*Q83) -> 0.21239586 | S83: =VLOOKUP(B:B,[1]极目数据!A:H,8,FALSE) -> 20 | U83: =VLOOKUP(B:B,[1]极目数据!A:U,21,FALSE) -> 63058
A84: 83 | B84: magnified mirror | C84: 放大镜 | D84: 中相关 | E84: 属性关键词 | F84: 品类名称:mirror | G84: 220495 | H84: 1459 | I84: =VLOOKUP(B84,[1]极目数据!A:D,4,0) -> 0.021097 | J84: =_xlfn.IFS(G84<=50000,"大词",AND(G84>50000,G84<=200000),"中词",G84>200000,"长尾词") -> 长尾词 | K84: =VLOOKUP(B84,[1]极目数据!A:S,19,0) -> 0.2907 | L84: =VLOOKUP(B84,[1]极目数据!A:T,20,0) -> 0.217 | M84: =VLOOKUP(B84,[1]极目数据!A:P,16,0) -> 26 | N84: =VLOOKUP(B84,[1]极目数据!A:V,22,0) -> 4.779045 | O84: =VLOOKUP(B84,[1]极目数据!A:L,11,0) -> 0.72 | P84: =VLOOKUP(B84,[1]极目数据!A:J,10,0) -> 0.200877 | Q84: 39.99 | R84: =O84/(P84*Q84) -> 0.08962948 | S84: =VLOOKUP(B:B,[1]极目数据!A:H,8,FALSE) -> 93 | U84: =VLOOKUP(B:B,[1]极目数据!A:U,21,FALSE) -> 15217
A85: 84 | B85: wall mirror with lights | C85: 带灯的墙面镜子 | D85: 中相关 | E85: 属性关键词 | F85: 功能特性:lights | 品类名称:mirror | 使用场景:wall | G85: 222104 | H85: 1449 | I85: =VLOOKUP(B85,[1]极目数据!A:D,4,0) -> 0.03535 | J85: =_xlfn.IFS(G85<=50000,"大词",AND(G85>50000,G85<=200000),"中词",G85>200000,"长尾词") -> 长尾词 | K85: =VLOOKUP(B85,[1]极目数据!A:S,19,0) -> 0.2891 | L85: =VLOOKUP(B85,[1]极目数据!A:T,20,0) -> 0.1111 | M85: =VLOOKUP(B85,[1]极目数据!A:P,16,0) -> 27 | N85: =VLOOKUP(B85,[1]极目数据!A:V,22,0) -> 38.916923 | O85: =VLOOKUP(B85,[1]极目数据!A:L,11,0) -> 0.51 | P85: =VLOOKUP(B85,[1]极目数据!A:J,10,0) -> 0.017473 | Q85: 39.99 | R85: =O85/(P85*Q85) -> 0.72987972 | S85: =VLOOKUP(B:B,[1]极目数据!A:H,8,FALSE) -> 8 | U85: =VLOOKUP(B:B,[1]极目数据!A:U,21,FALSE) -> 132121
A86: 85 | B86: mirror to see back of head | C86: 看后脑勺的镜子 | D86: 中相关 | E86: 属性关键词 | F86: 品类名称:mirror | G86: 222104 | H86: 1449 | I86: =VLOOKUP(B86,[1]极目数据!A:D,4,0) -> -0.010288 | J86: =_xlfn.IFS(G86<=50000,"大词",AND(G86>50000,G86<=200000),"中词",G86>200000,"长尾词") -> 长尾词 | K86: =VLOOKUP(B86,[1]极目数据!A:S,19,0) -> 0.4983 | L86: =VLOOKUP(B86,[1]极目数据!A:T,20,0) -> 0.3966 | M86: =VLOOKUP(B86,[1]极目数据!A:P,16,0) -> 12 | N86: =VLOOKUP(B86,[1]极目数据!A:V,22,0) -> 6.507387 | O86: =VLOOKUP(B86,[1]极目数据!A:L,11,0) -> 0.51 | P86: =VLOOKUP(B86,[1]极目数据!A:J,10,0) -> 0.109107 | Q86: 39.99 | R86: =O86/(P86*Q86) -> 0.11688699 | S86: =VLOOKUP(B:B,[1]极目数据!A:H,8,FALSE) -> 32 | U86: =VLOOKUP(B:B,[1]极目数据!A:U,21,FALSE) -> 214
A87: 86 | B87: light up desk mirror | C87: 发光桌镜 | D87: 高相关 | E87: 属性关键词 | F87: 功能特性:light | 品类名称:mirror | 使用场景:desk | G87: 227029 | H87: 1419 | I87: =VLOOKUP(B87,[1]极目数据!A:D,4,0) -> 0.201288 | J87: =_xlfn.IFS(G87<=50000,"大词",AND(G87>50000,G87<=200000),"中词",G87>200000,"长尾词") -> 长尾词 | K87: =VLOOKUP(B87,[1]极目数据!A:S,19,0) -> 0.2775 | L87: =VLOOKUP(B87,[1]极目数据!A:T,20,0) -> 0.1522 | M87: =VLOOKUP(B87,[1]极目数据!A:P,16,0) -> 27 | N87: =VLOOKUP(B87,[1]极目数据!A:V,22,0) -> 14.170906 | O87: =VLOOKUP(B87,[1]极目数据!A:L,11,0) -> 0.58 | P87: =VLOOKUP(B87,[1]极目数据!A:J,10,0) -> 0.061393 | Q87: 39.99 | R87: =O87/(P87*Q87) -> 0.23624234 | S87: =VLOOKUP(B:B,[1]极目数据!A:H,8,FALSE) -> 27 | U87: =VLOOKUP(B:B,[1]极目数据!A:U,21,FALSE) -> 1619
A88: 87 | B88: mirror for desk with lights | C88: 带灯的桌子用镜子 | D88: 高相关 | E88: 属性关键词 | F88: 功能特性:lights | 品类名称:mirror | 使用场景:desk | G88: 227912 | H88: 1414 | I88: =VLOOKUP(B88,[1]极目数据!A:D,4,0) -> -0.026832 | J88: =_xlfn.IFS(G88<=50000,"大词",AND(G88>50000,G88<=200000),"中词",G88>200000,"长尾词") -> 长尾词 | K88: =VLOOKUP(B88,[1]极目数据!A:S,19,0) -> 0.1822 | L88: =VLOOKUP(B88,[1]极目数据!A:T,20,0) -> 0.1666 | M88: =VLOOKUP(B88,[1]极目数据!A:P,16,0) -> 27 | N88: =VLOOKUP(B88,[1]极目数据!A:V,22,0) -> 36.665387 | O88: =VLOOKUP(B88,[1]极目数据!A:L,11,0) -> 1.37 | P88: =VLOOKUP(B88,[1]极目数据!A:J,10,0) -> 0.049638 | Q88: 39.99 | R88: =O88/(P88*Q88) -> 0.69016811 | S88: =VLOOKUP(B:B,[1]极目数据!A:H,8,FALSE) -> 22 | U88: =VLOOKUP(B:B,[1]极目数据!A:U,21,FALSE) -> 34133
A89: 88 | B89: barber mirror self cut | C89: 理发师自剪镜 | D89: 中相关 | E89: 属性关键词 | F89: 目标受众:barber | 品类名称:mirror | G89: 228739 | H89: 1409 | I89: =VLOOKUP(B89,[1]极目数据!A:D,4,0) -> -0.009873 | J89: =_xlfn.IFS(G89<=50000,"大词",AND(G89>50000,G89<=200000),"中词",G89>200000,"长尾词") -> 长尾词 | K89: =VLOOKUP(B89,[1]极目数据!A:S,19,0) -> 0.7455 | L89: =VLOOKUP(B89,[1]极目数据!A:T,20,0) -> 0.4039 | M89: =VLOOKUP(B89,[1]极目数据!A:P,16,0) -> 11 | N89: =VLOOKUP(B89,[1]极目数据!A:V,22,0) -> 16.011306 | O89: =VLOOKUP(B89,[1]极目数据!A:L,11,0) -> 1.31 | P89: =VLOOKUP(B89,[1]极目数据!A:J,10,0) -> 0.108673 | Q89: 39.99 | R89: =O89/(P89*Q89) -> 0.30143816 | S89: =VLOOKUP(B:B,[1]极目数据!A:H,8,FALSE) -> 35 | U89: =VLOOKUP(B:B,[1]极目数据!A:U,21,FALSE) -> 199
A90: 89 | B90: personal makeup mirrors | C90: 个人化妆镜 | D90: 高相关 | E90: 属性关键词 | F90: 品类名称:makeup,mirrors | G90: 229565 | H90: 1404 | I90: =VLOOKUP(B90,[1]极目数据!A:D,4,0) -> 0.091716 | J90: =_xlfn.IFS(G90<=50000,"大词",AND(G90>50000,G90<=200000),"中词",G90>200000,"长尾词") -> 长尾词 | K90: =VLOOKUP(B90,[1]极目数据!A:S,19,0) -> 0.2267 | L90: =VLOOKUP(B90,[1]极目数据!A:T,20,0) -> 0.0999 | M90: =VLOOKUP(B90,[1]极目数据!A:P,16,0) -> 27 | N90: =VLOOKUP(B90,[1]极目数据!A:V,22,0) -> 21.736001 | O90: =VLOOKUP(B90,[1]极目数据!A:L,11,0) -> 1.28 | P90: =VLOOKUP(B90,[1]极目数据!A:J,10,0) -> 0.078671 | Q90: 39.99 | R90: =O90/(P90*Q90) -> 0.40685897 | S90: =VLOOKUP(B:B,[1]极目数据!A:H,8,FALSE) -> 35 | U90: =VLOOKUP(B:B,[1]极目数据!A:U,21,FALSE) -> 108277
A91: 90 | B91: impressions vanity mirror | C91: 印象梳妆镜 | D91: 中相关 | E91: 属性关键词 | F91: 品类名称:mirror | 使用场景:vanity | G91: 229565 | H91: 1404 | I91: =VLOOKUP(B91,[1]极目数据!A:D,4,0) -> -0.059873 | J91: =_xlfn.IFS(G91<=50000,"大词",AND(G91>50000,G91<=200000),"中词",G91>200000,"长尾词") -> 长尾词 | K91: =VLOOKUP(B91,[1]极目数据!A:S,19,0) -> 0.2447 | L91: =VLOOKUP(B91,[1]极目数据!A:T,20,0) -> 0.1333 | M91: =VLOOKUP(B91,[1]极目数据!A:P,16,0) -> 27 | N91: =VLOOKUP(B91,[1]极目数据!A:V,22,0) -> 48.286588 | O91: =VLOOKUP(B91,[1]极目数据!A:L,11,0) -> 0.84 | P91: =VLOOKUP(B91,[1]极目数据!A:J,10,0) -> 0.02423 | Q91: 39.99 | R91: =O91/(P91*Q91) -> 0.86691091 | S91: =VLOOKUP(B:B,[1]极目数据!A:H,8,FALSE) -> 6 | U91: =VLOOKUP(B:B,[1]极目数据!A:U,21,FALSE) -> 812
A92: 91 | B92: face mirror | C92: 面部镜子 | D92: 高相关 | E92: 属性关键词 | F92: 品类名称:mirror | G92: 231290 | H92: 1393 | I92: =VLOOKUP(B92,[1]极目数据!A:D,4,0) -> -0.056628 | J92: =_xlfn.IFS(G92<=50000,"大词",AND(G92>50000,G92<=200000),"中词",G92>200000,"长尾词") -> 长尾词 | K92: =VLOOKUP(B92,[1]极目数据!A:S,19,0) -> 0.2354 | L92: =VLOOKUP(B92,[1]极目数据!A:T,20,0) -> 0.1947 | M92: =VLOOKUP(B92,[1]极目数据!A:P,16,0) -> 27 | N92: =VLOOKUP(B92,[1]极目数据!A:V,22,0) -> 5.50655 | O92: =VLOOKUP(B92,[1]极目数据!A:L,11,0) -> 0.49 | P92: =VLOOKUP(B92,[1]极目数据!A:J,10,0) -> 0.118041 | Q92: 39.99 | R92: =O92/(P92*Q92) -> 0.10380345 | S92: =VLOOKUP(B:B,[1]极目数据!A:H,8,FALSE) -> 41 | T92: =S92/7 -> 5.8571429 | U92: =VLOOKUP(B:B,[1]极目数据!A:U,21,FALSE) -> 13755
A93: 92 | B93: lighted vanity mirror tabletop | C93: 桌面用点亮的梳妆镜 | D93: 高相关 | E93: 属性关键词 | F93: 功能特性:lighted | 品类名称:mirror | 使用场景:vanity | G93: 234768 | H93: 1373 | I93: =VLOOKUP(B93,[1]极目数据!A:D,4,0) -> 0.168149 | J93: =_xlfn.IFS(G93<=50000,"大词",AND(G93>50000,G93<=200000),"中词",G93>200000,"长尾词") -> 长尾词 | K93: =VLOOKUP(B93,[1]极目数据!A:S,19,0) -> 0.2573 | L93: =VLOOKUP(B93,[1]极目数据!A:T,20,0) -> 0.0681 | M93: =VLOOKUP(B93,[1]极目数据!A:P,16,0) -> 27 | N93: =VLOOKUP(B93,[1]极目数据!A:V,22,0) -> 21.990223 | O93: =VLOOKUP(B93,[1]极目数据!A:L,11,0) -> 1.23 | P93: =VLOOKUP(B93,[1]极目数据!A:J,10,0) -> 0.078671 | Q93: 39.99 | R93: =O93/(P93*Q93) -> 0.39096604 | S93: =VLOOKUP(B:B,[1]极目数据!A:H,8,FALSE) -> 35 | U93: =VLOOKUP(B:B,[1]极目数据!A:U,21,FALSE) -> 7410
A94: 93 | B94: small makeup mirror | C94: 小化妆镜 | D94: 中相关 | E94: 属性关键词 | F94: 品类名称:makeup,mirror | 尺寸/大小:small | G94: 239267 | H94: 1348 | I94: =VLOOKUP(B94,[1]极目数据!A:D,4,0) -> 0.050314 | J94: =_xlfn.IFS(G94<=50000,"大词",AND(G94>50000,G94<=200000),"中词",G94>200000,"长尾词") -> 长尾词 | K94: =VLOOKUP(B94,[1]极目数据!A:S,19,0) -> 0.2884 | L94: =VLOOKUP(B94,[1]极目数据!A:T,20,0) -> 0.0728 | M94: =VLOOKUP(B94,[1]极目数据!A:P,16,0) -> 26 | N94: =VLOOKUP(B94,[1]极目数据!A:V,22,0) -> 3.264925 | O94: =VLOOKUP(B94,[1]极目数据!A:L,11,0) -> 0.32 | P94: =VLOOKUP(B94,[1]极目数据!A:J,10,0) -> 0.1072 | Q94: 39.99 | R94: =O94/(P94*Q94) -> 0.074645527 | S94: =VLOOKUP(B:B,[1]极目数据!A:H,8,FALSE) -> 16 | U94: =VLOOKUP(B:B,[1]极目数据!A:U,21,FALSE) -> 131485
A95: 94 | B95: 10x magnifying mirror with light | C95: 带灯的10倍放大镜 | D95: 高相关 | E95: 属性关键词 | F95: 功能特性:light,10x | 品类名称:mirror | G95: 244849 | H95: 1318 | I95: =VLOOKUP(B95,[1]极目数据!A:D,4,0) -> 0.01936 | J95: =_xlfn.IFS(G95<=50000,"大词",AND(G95>50000,G95<=200000),"中词",G95>200000,"长尾词") -> 长尾词 | K95: =VLOOKUP(B95,[1]极目数据!A:S,19,0) -> 0.3295 | L95: =VLOOKUP(B95,[1]极目数据!A:T,20,0) -> 0.3044 | M95: =VLOOKUP(B95,[1]极目数据!A:P,16,0) -> 26 | N95: =VLOOKUP(B95,[1]极目数据!A:V,22,0) -> 17.539838 | O95: =VLOOKUP(B95,[1]极目数据!A:L,11,0) -> 1.33 | P95: =VLOOKUP(B95,[1]极目数据!A:J,10,0) -> 0.100913 | Q95: 39.99 | R95: =O95/(P95*Q95) -> 0.32957413 | S95: =VLOOKUP(B:B,[1]极目数据!A:H,8,FALSE) -> 45 | T95: =S95/7 -> 6.4285714 | U95: =VLOOKUP(B:B,[1]极目数据!A:U,21,FALSE) -> 9665
A96: 95 | B96: espejo para cortar pelo uno mismo | C96: 自用理发镜 | D96: 中相关 | E96: 属性关键词 | F96: 品类名称:espejo,para | G96: 245832 | H96: 1313 | I96: =VLOOKUP(B96,[1]极目数据!A:D,4,0) -> 0.002288 | J96: =_xlfn.IFS(G96<=50000,"大词",AND(G96>50000,G96<=200000),"中词",G96>200000,"长尾词") -> 长尾词 | K96: =VLOOKUP(B96,[1]极目数据!A:S,19,0) -> 0.6884 | L96: =VLOOKUP(B96,[1]极目数据!A:T,20,0) -> 0.2791 | M96: =VLOOKUP(B96,[1]极目数据!A:P,16,0) -> 12 | N96: =VLOOKUP(B96,[1]极目数据!A:V,22,0) -> 14.325224 | O96: =VLOOKUP(B96,[1]极目数据!A:L,11,0) -> 0.69 | P96: =VLOOKUP(B96,[1]极目数据!A:J,10,0) -> 0.064222 | Q96: 39.99 | R96: =O96/(P96*Q96) -> 0.26866671 | S96: =VLOOKUP(B:B,[1]极目数据!A:H,8,FALSE) -> 25 | U96: =VLOOKUP(B:B,[1]极目数据!A:U,21,FALSE) -> 115
A97: 96 | B97: espejo con luz | C97: 带灯的镜子 | D97: 中相关 | E97: 属性关键词 | F97: 品类名称:espejo | G97: 248846 | H97: 1297 | I97: =VLOOKUP(B97,[1]极目数据!A:D,4,0) -> -0.114637 | J97: =_xlfn.IFS(G97<=50000,"大词",AND(G97>50000,G97<=200000),"中词",G97>200000,"长尾词") -> 长尾词 | K97: =VLOOKUP(B97,[1]极目数据!A:S,19,0) -> 0.2179 | L97: =VLOOKUP(B97,[1]极目数据!A:T,20,0) -> 0.1111 | M97: =VLOOKUP(B97,[1]极目数据!A:P,16,0) -> 26 | N97: =VLOOKUP(B97,[1]极目数据!A:V,22,0) -> 22.516314 | O97: =VLOOKUP(B97,[1]极目数据!A:L,11,0) -> 0.48 | P97: =VLOOKUP(B97,[1]极目数据!A:J,10,0) -> 0.028424 | Q97: 39.99 | R97: =O97/(P97*Q97) -> 0.42228401 | S97: =VLOOKUP(B:B,[1]极目数据!A:H,8,FALSE) -> 9 | U97: =VLOOKUP(B:B,[1]极目数据!A:U,21,FALSE) -> 5850
A98: 97 | B98: desk makeup mirror | C98: 桌面化妆镜 | D98: 高相关 | E98: 属性关键词 | F98: 品类名称:makeup,mirror | 使用场景:desk | G98: 248846 | H98: 1297 | I98: =VLOOKUP(B98,[1]极目数据!A:D,4,0) -> -0.114637 | J98: =_xlfn.IFS(G98<=50000,"大词",AND(G98>50000,G98<=200000),"中词",G98>200000,"长尾词") -> 长尾词 | K98: =VLOOKUP(B98,[1]极目数据!A:S,19,0) -> 0.2684 | L98: =VLOOKUP(B98,[1]极目数据!A:T,20,0) -> 0.2889 | M98: =VLOOKUP(B98,[1]极目数据!A:P,16,0) -> 26 | N98: =VLOOKUP(B98,[1]极目数据!A:V,22,0) -> 16.778667 | O98: =VLOOKUP(B98,[1]极目数据!A:L,11,0) -> 0.96 | P98: =VLOOKUP(B98,[1]极目数据!A:J,10,0) -> 0.078671 | Q98: 39.99 | R98: =O98/(P98*Q98) -> 0.30514423 | S98: =VLOOKUP(B:B,[1]极目数据!A:H,8,FALSE) -> 33 | U98: =VLOOKUP(B:B,[1]极目数据!A:U,21,FALSE) -> 48784
A99: 98 | B99: magnifying makeup mirror | C99: 化妆放大镜 | D99: 高相关 | E99: 属性关键词 | F99: 品类名称:makeup,mirror | G99: 250844 | H99: 1287 | I99: =VLOOKUP(B99,[1]极目数据!A:D,4,0) -> -0.026474 | J99: =_xlfn.IFS(G99<=50000,"大词",AND(G99>50000,G99<=200000),"中词",G99>200000,"长尾词") -> 长尾词 | K99: =VLOOKUP(B99,[1]极目数据!A:S,19,0) -> 0.2039 | L99: =VLOOKUP(B99,[1]极目数据!A:T,20,0) -> 0.1947 | M99: =VLOOKUP(B99,[1]极目数据!A:P,16,0) -> 27 | N99: =VLOOKUP(B99,[1]极目数据!A:V,22,0) -> 7.184905 | O99: =VLOOKUP(B99,[1]极目数据!A:L,11,0) -> 0.83 | P99: =VLOOKUP(B99,[1]极目数据!A:J,10,0) -> 0.154491 | Q99: 39.99 | R99: =O99/(P99*Q99) -> 0.13434562 | S99: =VLOOKUP(B:B,[1]极目数据!A:H,8,FALSE) -> 80 | T99: =S99/7 -> 11.428571 | U99: =VLOOKUP(B:B,[1]极目数据!A:U,21,FALSE) -> 81593
A100: 99 | B100: large vanity mirror | C100: 大号梳妆镜 | D100: 中相关 | E100: 属性关键词 | F100: 品类名称:mirror | 尺寸/大小:large | 使用场景:vanity | G100: 251809 | H100: 1282 | I100: =VLOOKUP(B100,[1]极目数据!A:D,4,0) -> 0.066246 | J100: =_xlfn.IFS(G100<=50000,"大词",AND(G100>50000,G100<=200000),"中词",G100>200000,"长尾词") -> 长尾词 | K100: =VLOOKUP(B100,[1]极目数据!A:S,19,0) -> 0.2087 | L100: =VLOOKUP(B100,[1]极目数据!A:T,20,0) -> 0.05 | M100: =VLOOKUP(B100,[1]极目数据!A:P,16,0) -> 26 | N100: =VLOOKUP(B100,[1]极目数据!A:V,22,0) -> 28.623933 | O100: =VLOOKUP(B100,[1]极目数据!A:L,11,0) -> 1.31 | P100: =VLOOKUP(B100,[1]极目数据!A:J,10,0) -> 0.061138 | Q100: 39.99 | R100: =O100/(P100*Q100) -> 0.53580735 | S100: =VLOOKUP(B:B,[1]极目数据!A:H,8,FALSE) -> 24 | U100: =VLOOKUP(B:B,[1]极目数据!A:U,21,FALSE) -> 126109
A101: 100 | B101: lighted mirror makeup vanity | C101: 化妆梳妆台用点亮的镜子 | D101: 高相关 | E101: 属性关键词 | F101: 功能特性:lighted | 品类名称:makeup,mirror | 使用场景:vanity | G101: 251809 | H101: 1282 | I101: =VLOOKUP(B101,[1]极目数据!A:D,4,0) -> 0.221319 | J101: =_xlfn.IFS(G101<=50000,"大词",AND(G101>50000,G101<=200000),"中词",G101>200000,"长尾词") -> 长尾词 | K101: =VLOOKUP(B101,[1]极目数据!A:S,19,0) -> 0.2835 | L101: =VLOOKUP(B101,[1]极目数据!A:T,20,0) -> 0.1628 | M101: =VLOOKUP(B101,[1]极目数据!A:P,16,0) -> 26 | N101: =VLOOKUP(B101,[1]极目数据!A:V,22,0) -> 19.829334 | O101: =VLOOKUP(B101,[1]极目数据!A:L,11,0) -> 1 | P101: =VLOOKUP(B101,[1]极目数据!A:J,10,0) -> 0.078671 | Q101: 39.99 | R101: =O101/(P101*Q101) -> 0.31785857 | S101: =VLOOKUP(B:B,[1]极目数据!A:H,8,FALSE) -> 32 | U101: =VLOOKUP(B:B,[1]极目数据!A:U,21,FALSE) -> 35719
A102: 101 | B102: 10x mirror | C102: 10倍镜 | D102: 中相关 | E102: 属性关键词 | F102: 功能特性:10x | 品类名称:mirror | G102: 251809 | H102: 1282 | I102: =VLOOKUP(B102,[1]极目数据!A:D,4,0) -> -0.022071 | J102: =_xlfn.IFS(G102<=50000,"大词",AND(G102>50000,G102<=200000),"中词",G102>200000,"长尾词") -> 长尾词 | K102: =VLOOKUP(B102,[1]极目数据!A:S,19,0) -> 0.315 | L102: =VLOOKUP(B102,[1]极目数据!A:T,20,0) -> 0.2192 | M102: =VLOOKUP(B102,[1]极目数据!A:P,16,0) -> 26 | N102: =VLOOKUP(B102,[1]极目数据!A:V,22,0) -> 4.57649 | O102: =VLOOKUP(B102,[1]极目数据!A:L,11,0) -> 0.6 | P102: =VLOOKUP(B102,[1]极目数据!A:J,10,0) -> 0.185732 | Q102: 39.99 | R102: =O102/(P102*Q102) -> 0.080781723 | S102: =VLOOKUP(B:B,[1]极目数据!A:H,8,FALSE) -> 67 | U102: =VLOOKUP(B:B,[1]极目数据!A:U,21,FALSE) -> 31223
A103: 102 | B103: tabletop vanity mirror with lights | C103: 带灯桌面梳妆镜 | D103: 高相关 | E103: 属性关键词 | F103: 功能特性:lights | 品类名称:mirror | 使用场景:vanity | G103: 252856 | H103: 1277 | I103: =VLOOKUP(B103,[1]极目数据!A:D,4,0) -> -0.065278 | J103: =_xlfn.IFS(G103<=50000,"大词",AND(G103>50000,G103<=200000),"中词",G103>200000,"长尾词") -> 长尾词 | K103: =VLOOKUP(B103,[1]极目数据!A:S,19,0) -> 0.257 | L103: =VLOOKUP(B103,[1]极目数据!A:T,20,0) -> 0.2142 | M103: =VLOOKUP(B103,[1]极目数据!A:P,16,0) -> 26 | N103: =VLOOKUP(B103,[1]极目数据!A:V,22,0) -> 16.143112 | O103: =VLOOKUP(B103,[1]极目数据!A:L,11,0) -> 1.06 | P103: =VLOOKUP(B103,[1]极目数据!A:J,10,0) -> 0.078671 | Q103: 39.99 | R103: =O103/(P103*Q103) -> 0.33693008 | S103: =VLOOKUP(B:B,[1]极目数据!A:H,8,FALSE) -> 32 | U103: =VLOOKUP(B:B,[1]极目数据!A:U,21,FALSE) -> 12562
A104: 103 | B104: mini vanity mirror | C104: 迷你梳妆镜 | D104: 高相关 | E104: 属性关键词 | F104: 品类名称:mirror | 尺寸/大小:mini | 使用场景:vanity | G104: 258119 | H104: 1252 | I104: =VLOOKUP(B104,[1]极目数据!A:D,4,0) -> -0.115282 | J104: =_xlfn.IFS(G104<=50000,"大词",AND(G104>50000,G104<=200000),"中词",G104>200000,"长尾词") -> 长尾词 | K104: =VLOOKUP(B104,[1]极目数据!A:S,19,0) -> 0.2943 | L104: =VLOOKUP(B104,[1]极目数据!A:T,20,0) -> 0.15 | M104: =VLOOKUP(B104,[1]极目数据!A:P,16,0) -> 26 | N104: =VLOOKUP(B104,[1]极目数据!A:V,22,0) -> 10.423112 | O104: =VLOOKUP(B104,[1]极目数据!A:L,11,0) -> 0.47 | P104: =VLOOKUP(B104,[1]极目数据!A:J,10,0) -> 0.078671 | Q104: 39.99 | R104: =O104/(P104*Q104) -> 0.14939353 | S104: =VLOOKUP(B:B,[1]极目数据!A:H,8,FALSE) -> 32 | U104: =VLOOKUP(B:B,[1]极目数据!A:U,21,FALSE) -> 9871
A105: 104 | B105: mirror with lights for desk | C105: 桌面用带灯光的镜子 | D105: 高相关 | E105: 属性关键词 | F105: 功能特性:lights | 品类名称:mirror | 使用场景:desk | G105: 258119 | H105: 1252 | I105: =VLOOKUP(B105,[1]极目数据!A:D,4,0) -> 0.226766 | J105: =_xlfn.IFS(G105<=50000,"大词",AND(G105>50000,G105<=200000),"中词",G105>200000,"长尾词") -> 长尾词 | K105: =VLOOKUP(B105,[1]极目数据!A:S,19,0) -> 0.242 | L105: =VLOOKUP(B105,[1]极目数据!A:T,20,0) -> 0.1333 | M105: =VLOOKUP(B105,[1]极目数据!A:P,16,0) -> 26 | N105: =VLOOKUP(B105,[1]极目数据!A:V,22,0) -> 13.707431 | O105: =VLOOKUP(B105,[1]极目数据!A:L,11,0) -> 0.64 | P105: =VLOOKUP(B105,[1]极目数据!A:J,10,0) -> 0.057633 | Q105: 39.99 | R105: =O105/(P105*Q105) -> 0.27768815 | S105: =VLOOKUP(B:B,[1]极目数据!A:H,8,FALSE) -> 23 | U105: =VLOOKUP(B:B,[1]极目数据!A:U,21,FALSE) -> 34043
A106: 105 | B106: makeup mirror wall mount | C106: 壁挂化妆镜 | D106: 中相关 | E106: 属性关键词 | F106: 品类名称:makeup,mirror | 使用场景:wall | G106: 271832 | H106: 1191 | I106: =VLOOKUP(B106,[1]极目数据!A:D,4,0) -> -0.054846 | J106: =_xlfn.IFS(G106<=50000,"大词",AND(G106>50000,G106<=200000),"中词",G106>200000,"长尾词") -> 长尾词 | K106: =VLOOKUP(B106,[1]极目数据!A:S,19,0) -> 0.3983 | L106: =VLOOKUP(B106,[1]极目数据!A:T,20,0) -> 0.2758 | M106: =VLOOKUP(B106,[1]极目数据!A:P,16,0) -> 26 | N106: =VLOOKUP(B106,[1]极目数据!A:V,22,0) -> 14.505664 | O106: =VLOOKUP(B106,[1]极目数据!A:L,11,0) -> 0.77 | P106: =VLOOKUP(B106,[1]极目数据!A:J,10,0) -> 0.094446 | Q106: 39.99 | R106: =O106/(P106*Q106) -> 0.20387114 | S106: =VLOOKUP(B:B,[1]极目数据!A:H,8,FALSE) -> 38 | U106: =VLOOKUP(B:B,[1]极目数据!A:U,21,FALSE) -> 11663
A107: 106 | B107: vanity mirror with led lights | C107: 带LED灯的梳妆镜 | D107: 高相关 | E107: 属性关键词 | F107: 功能特性:led,lights | 品类名称:mirror | 使用场景:vanity | G107: 271832 | H107: 1191 | I107: =VLOOKUP(B107,[1]极目数据!A:D,4,0) -> 0.120214 | J107: =_xlfn.IFS(G107<=50000,"大词",AND(G107>50000,G107<=200000),"中词",G107>200000,"长尾词") -> 长尾词 | K107: =VLOOKUP(B107,[1]极目数据!A:S,19,0) -> 0.2161 | L107: =VLOOKUP(B107,[1]极目数据!A:T,20,0) -> 0.125 | M107: =VLOOKUP(B107,[1]极目数据!A:P,16,0) -> 26 | N107: =VLOOKUP(B107,[1]极目数据!A:V,22,0) -> 38.743333 | O107: =VLOOKUP(B107,[1]极目数据!A:L,11,0) -> 0.88 | P107: =VLOOKUP(B107,[1]极目数据!A:J,10,0) -> 0.030457 | Q107: 39.99 | R107: =O107/(P107*Q107) -> 0.72251047 | S107: =VLOOKUP(B:B,[1]极目数据!A:H,8,FALSE) -> 11 | U107: =VLOOKUP(B:B,[1]极目数据!A:U,21,FALSE) -> 56782
...

Sheet 广告架构
A1: 阶段 | C1: 广告目的 | D1: 广告出单目标（/天） | E1: 广告活动 | F1: 广告预算 | G1: 广告类型 | H1: 投放方式 | I1: 关键词类型 | J1: 关键词 | K1: 匹配方式 | L1: 竞价策略 | M1: cpc | N1: 位置加价 | O1: 精准否定 | P1: 词组否定 | Q1: 备注 | R1: 曝光量 | S1: 搜索结果首页首位展示量份额 (IS) | T1: 点击次数 | U1: 点击率 | V1: 花费 | W1: 单次点击 | X1: 订单 | Y1: 转化率 | Z1: acos | AA1: 搜索词
A2: 第一阶段 打标签 | B2: 第1周 | C2: 测试链接 | D2: 1 | E2: 2024-AT自动 | F2: 10 | G2: SP自动 （紧密） | H2: 自动 | I2: / | K2: 紧密匹配 | L2: 固定 | M2: 建议竞价70% | N2: 无
C3: 打关键词收录 | D3: 1 | E3: 2024-JZ01中级词 | F3: 20 | G3: SP手动 （中级词） | H3: 手动 | I3: 中级词3个(高相关高转化低竞争) | J3: magnified mirror with lights lighted magnifying mirror magnifying makeup mirror | K3: 精准 | L3: 固定 | M3: 建议竞价80% | N3: 搜索结果的其余位置BID+30%-50% | Q3: 需要测试cpc和bid加价多少更多流量在其余位置，20%以下在商品页面
C4: 打关键词收录 | D4: 1 | E4: 2024-JZ02中级词 | F4: 20 | H4: 手动 | I4: 中级词3个(高相关高转化低竞争) | J4: light up makeup mirror light mirror makeup makeup light mirror | K4: 精准 | L4: 固定 | M4: 建议竞价80% | N4: 搜索结果的其余位置BID+30%-50%
C5: 高转化打关键词排名 | D5: 1 | E5: 2024-JZ03长尾 | F5: 10 | G5: SP手动 （长尾词） | H5: 手动 | I5: 长尾词5-6个(高相关高转化) | J5: 10x magnifying mirror with light magnifying makeup mirror makeup mirror with magnification make up mirrors lighted magnifying make up mirror with lights and magnification | K5: 精准 | L5: 固定 | M5: 建议竞价70% | N5: 搜索结果的其余位置BID+30%
C6: 高转化打关键词排名 | D6: 1 | E6: 2024-JZ04长尾 | F6: 10 | H6: 手动 | I6: 长尾词5-6个(高相关高转化) | J6: lighted mirror with magnification lighted magnifying makeup mirror magnifying makeup mirror with lights mirror for makeup with lights light up magnifying mirror lighted mirror makeup | K6: 精准 | L6: 固定 | M6: 建议竞价70% | N6: 首页加价30%
C7: 高转化打关键词排名 | D7: 1 | E7: 2024-JZ05长尾 | F7: 10 | H7: 手动 | I7: 长尾词5-6个(高相关高转化) | J7: make up light mirror makeup mirror lights make up mirror with stand standing makeup mirror make up mirrors lighted magnifying stand up | K7: 精准 | L7: 固定 | M7: 建议竞价70% | N7: 首页加价30%
C8: 高转化打关键词排名 | D8: 1 | E8: 2024-JZ06长尾 | F8: 10 | H8: 手动 | I8: 长尾词5-6个(高相关高转化) | J8: makeup mirror with light led makeup mirror with lights rechargeable makeup mirror with lights magnified makeup mirror with lights cosmetic mirror with light and magnification double sided mirror with magnification | K8: 精准 | L8: 固定 | M8: 建议竞价70% | N8: 首页加价30%
B9: 第2周 | C9: 拓词 | D9: 2 | E9: 2024-词组01（中级词） | F9: 20 | G9: SP手动 （中级词） | H9: 手动 | I9: 中级词3-5个(高相关高转化低竞争) | J9: magnified mirror with lights lighted magnifying mirror magnifying makeup mirror | K9: 词组 | L9: 固定 | M9: 建议竞价70% | N9: 搜索结果的其余位置BID+30% | O9: 如果投放词转化不行占预算40%以上就精准否定投放词 | P9: 不相关特征
C10: 拓词 | D10: 2 | E10: 2024-词组02（中级词） | F10: 20 | H10: 手动 | I10: 中级词3-5个(高相关高转化低竞争) | J10: light up makeup mirror light mirror makeup makeup light mirror | K10: 词组 | L10: 固定 | M10: 建议竞价70% | N10: 搜索结果的其余位置BID+30% | O10: 如果投放词转化不行占预算40%以上就精准否定投放词 | P10: 不相关特征
C11: 流量闭环 | D11: 0 | E11: 2024-ASIN定投1 | F11: 10 | G11: SP ASIN定投 | H11: 手动 | I11: 定投自己品牌的同类ASIN | K11: 精准 | L11: 固定 | M11: 建议竞价70%
B12: 第3周 | C12: 打标签 | D12: 1 | E12: 2024-ASIN定投2 | F12: 10 | H12: 手动 | I12: 定投链接半年以上TOP50-TOP100的强相关链接 | K12: 精准 | L12: 固定 | M12: 建议竞价70%
C13: 打标签 | D13: 2 | E13: 2024-ASIN定投2 | F13: 20 | H13: 手动 | I13: 定投链接半年以上TOP20-TOP50的强相关链接 | K13: 精准 | L13: 固定 | M13: 建议竞价70%
C14: 打标签 | D14: 1 | E14: 2024-ASIN定投3 | F14: 10 | H14: 手动 | I14: 定投价格/评分比竞品有优势的 | K14: 精准 | L14: 固定 | M14: 建议竞价70%
B15: 第4周 | C15: 打标签 | D15: 1 | E15: 2024-ASIN定投4 | F15: 10 | H15: 手动 | I15: 定投价格/评分比竞品有优势的 | K15: 精准 | L15: 固定 | M15: 建议竞价70%
A16: 14
A17: 第二阶段 抢排位 | B17: 第5周 | C17: 拓流量 | D17: 0 | E17: 2024-词组03（中级词） | F17: 20 | G17: SP手动词组 （中级词） | H17: 手动 | I17: 中级词偏上2-3个（同词根） | J17: mirror with light makeup mirror lights | K17: 词组 | L17: 固定 | M17: 建议竞价80% | N17: 搜索结果的其余位置30%
C18: 拓流量 | D18: 1 | E18: 2024-词组04（大词） | F18: 10 | H18: 手动 | I18: 大词偏下2-3个（同词根） | J18: lighted makeup mirror makeup mirror lighted | K18: 词组 | L18: 固定 | M18: 建议竞价80% | N18: 搜索结果的其余位置30%
B19: 第6周 | C19: 拓流量 | D19: 1 | E19: 2024-词组05（大词） | F19: 10 | H19: 手动 | I19: 大词偏下2-3个（同词根） | J19: make up mirror with lighting make up mirror with lights | K19: 词组 | L19: 固定 | M19: 建议竞价80% | N19: 搜索结果的其余位置30%
C20: 拓流量 | D20: 1 | E20: 2024-词组06（大词） | F20: 10 | H20: 手动 | I20: 大词偏下2-3个（同词根） | J20: magnifying mirror with light magnified mirror with lights | K20: 词组 | L20: 固定 | M20: 建议竞价80% | N20: 搜索结果的其余位置30%
B21: 第7周 | C21: 打关键词收录,排名卡位 | D21: 1 | E21: 2024-JZ07（大词） | F21: 20 | G21: SP手动精准 （大词） | H21: 手动 | I21: SKAG 大词1个 | J21: makeup mirror with lights and magnification | K21: 精准 | L21: 固定 | M21: 建议竞价80% | N21: 搜索结果的其余位置30%-50%
C22: 打关键词收录,排名卡位 | D22: 1 | E22: 2024-JZ08（大词） | F22: 20 | H22: 手动 | I22: SKAG 大词1个 | J22: lighted makeup mirror with magnification | K22: 精准 | L22: 固定 | M22: 建议竞价80% | N22: 搜索结果的其余位置30%-50%
B23: 第8周 | C23: 高转化高点击 | D23: 1 | E23: SBV-精准1（中级词） | F23: 15 | G23: SBV精准 | H23: 手动 | I23: 中级词5-8个（SP表现好的） | J23: magnified mirror with lights lighted magnifying mirror magnifying makeup mirror light up makeup mirror light mirror makeup makeup light mirror | K23: 精准 | M23: 建议竞价60%
C24: 拓流量 | D24: 1 | E24: SBV-精准2（大词） | F24: 20 | H24: 手动 | I24: 大词3-4个 | J24: makeup mirror with lights and magnification lighted makeup mirror with magnification | K24: 精准 | M24: 建议竞价70% | N24: 跑的好加预算
A25: 8
A26: 第三阶段 拓流量 | B26: 第9周 | C26: 拓流量 | D26: 1 | E26: 2024-词组07（大词） | F26: 20 | G26: SP手动词组 （大词） | H26: 手动 | I26: 大词1-2个（中高相关） | J26: makeup mirror make up mirror | K26: 词组 | L26: 固定 | M26: 建议竞价80% | N26: 搜索结果的其余位置30%
C27: 拓流量 | D27: 1 | E27: 2024-词组08（大词） | F27: 20 | H27: 手动 | I27: 大词1-2个（中高相关） | J27: mirror for makeup vanity mirror | K27: 词组 | L27: 固定 | M27: 建议竞价80% | N27: 搜索结果的其余位置30%
B28: 第10周 | C28: 打关键词收录,排名卡位 | D28: 1 | E28: 2024-JZ09（大词） | F28: 20 | G28: SP手动精准 （大词） | H28: 手动 | I28: SKAG 大词1个 | J28: make up mirror with lighting | K28: 精准 | L28: 固定 | M28: 建议竞价80% | N28: 搜索结果的其余位置30%-50%
C29: 打关键词收录,排名卡位 | D29: 1 | E29: 2024-JZ10（大词） | F29: 20 | H29: 手动 | I29: SKAG 大词1个 | J29: makeup mirror with lights | K29: 精准 | L29: 固定 | M29: 建议竞价80% | N29: 搜索结果的其余位置30%-50%
C30: 打关键词收录,排名卡位 | D30: 1 | E30: 2024-JZ11（大词） | F30: 20 | H30: 手动 | I30: SKAG 大词1个 | J30: makeup mirror | K30: 精准 | L30: 固定 | M30: 建议竞价80% | N30: 搜索结果的其余位置30%-50%
B31: 第11周 | C31: 拓流量 | D31: 0 | E31: SBV-词组1 中级词 | F31: 15 | G31: SBV词组 | H31: 手动 | I31: 大词2-3个 | J31: makeup mirror with lights and magnification lighted makeup mirror with magnification | K31: 词组 | M31: 建议竞价50%-60% | N31: 跑的好加预算，控制SBV流量占比不超过50%
C32: 拓流量 | D32: 1 | E32: SBV-词组2 大词 | F32: 15 | H32: 手动 | I32: 大词2-3个 | J32: make up mirror with lighting lighted makeup mirror | K32: 词组 | M32: 建议竞价50%-60% | N32: 跑的好加预算，控制SBV流量占比不超过50%
B33: 第12周 | C33: 高转化高点击 | D33: 1 | E33: SBV-精准3 大词 | F33: 15 | G33: SBV精准 | H33: 手动 | I33: 大词3-4个 | J33: makeup mirror with lights and magnification lighted makeup mirror with magnification lighted makeup mirror | K33: 精准 | M33: 建议竞价50%-60%
C34: 高转化高点击 | D34: 0 | E34: SBV-精准4 中级词/大词 | F34: 15 | H34: 手动 | I34: SP词组里表现好的词5-8个 | K34: 精准 | M34: 建议竞价50%-60%
A35: 9

Sheet 否词
A1: 精准否定 | B1: 词组否定(不相关特征) | C1: 品牌
A2: 3 way mirror | B2: Wall Mounted | C2: conair
A3: three way mirror | B3: wall | C3: nusvan
A4: trifold mirror | B4: with suction cups
A5: 3 way mirror | B5: suction cups
A6: three way mirror | B6: fogless
A7: trifold mirror | B7: 3 way
A8: 3 way mirror for self hair cutting | B8: hair mirror
A9: mirror to see back of head | B9: haircut mirror
A10: 3 way mirror for braiding hair | B10: self cut mirror
A11: tri fold mirror
A12: 3way mirror
A13: hair mirror
A14: 3 sided mirror
A15: 360 mirror for women for braiding
A16: make up light
A17: bathroom magnifying mirror
A18: hair cutting mirror
A19: three way mirror for self hair braiding
A20: mirror for cutting your own hair
A21: 3 mirror for braiding hair
A22: hair mirror back of head
... A36: self cut mirror
