Workbook

Sheet 1.0 竞品拓词法 （至少50个）
A1: 品拓词导出_相似竞品拓词&筛查 | N1: Administrator:B08BLTZQ7R,B0DQT1MKZ3,B0DDPXCK6L,B0CPJ76KXR,B0CKTKBSP8,B0D9BQHSWQ,B0D6YTJD1S,B0DDCVZWCY,B0CJ9FL94H,B0DNYVJ4PL,B0DLTVHN3B,B0CHMPZVZT,B0CJFR8YZ1,B0DLWJD9MV,B0DGJPJJD9,B0DKY6RQRC,B0DDXZNCKL,B0DL5J6MK4,B0DPDK6RLJ,B0D73F6HDZ,B0D3QGFGR8,B0DKPGVGT5,B0DHCXJRS9,B0D7HF8S2W,B0DBLK3543,B0DPDHSHGK,B0DQSF6MDL,B0DCS2M8XZ,B08XQF7NRH,B0DQSLNPSK,B0DPKNMGRZ,B0CTCP2S2W,B0DBLKGKFZ,B0CTCMLZSQ,B0D83SRY9V,B0D7HN9GKW,B0DCG3BSC5,B0DDPHBKLK,B0DFL7333M,B0CRKGHTNR,B0DBLL3P6C,B0DBHBPWXW,B0DJ35DCZD,B0DFL7333M拓词并筛查共44个目标产品(加入拓词竞品库)，按Listing拓展后总共58个变体，合并去重后总共反查出848个关键词848
A2: # | B2: 关键词 | C2: 相关性-自动百分比 | D2: 相关性-自动占比 | E2: 相关性-自动 | F2: 自然位前4占位率 | G2: 自然位前8占位率 | H2: 自然位前16占位率 | I2: 自然位前32占位率 | J2: 自然位前48占位率 | K2: 搜索量 | L2: 排名 | M2: 相关性-手动 | N2: 流量大小 | O2: 相关性 | P2: 修饰词类型 | Q2: 搜索转化率
A3: 1 | B3: hoover milbensauger | C3: hoover除螨吸尘器 | D3: 0.7451 | E3: 高相关 | F3: 0.9063 | G3: 0.6719 | H3: 0.6094 | I3: 0.3555 | J3: 0.2578 | K3: 374 | L3: 149958 | M3: =E3 -> 高相关 | O3: =E3 -> 高相关
A4: 2 | B4: milbenstaubsauger | C4: 除螨吸尘器 | D4: 0.509 | E4: 中相关 | F4: 0.5 | G4: 0.5 | H4: 0.5625 | I4: 0.5234 | J4: 0.4323 | K4: 334 | L4: 169036 | M4: =E4 -> 中相关 | O4: =E4 -> 中相关
A5: 3 | B5: milbensauger für matratzen testsieger | C5: 床垫用除螨吸尘器测试冠军 | D5: 0.4965 | E5: 中相关 | F5: 0.5 | G5: 0.4844 | H5: 0.5156 | I5: 0.4961 | J5: 0.4453 | K5: 389 | L5: 143911 | M5: =E5 -> 中相关 | O5: =E5 -> 中相关
A6: 4 | B6: milbensauger | C6: 除螨吸尘器 | D6: 0.4962 | E6: 中相关 | F6: 0.5 | G6: 0.4844 | H6: 0.5156 | I6: 0.4844 | J6: 0.4609 | K6: 9229 | L6: 3344 | M6: =E6 -> 中相关 | O6: =E6 -> 中相关
A7: 5 | B7: milbensauger mit uv licht | C7: 带紫外线的除螨吸尘器 | D7: 0.4877 | E7: 中相关 | F7: 0.5 | G7: 0.4844 | H7: 0.4453 | I7: 0.5195 | J7: 0.4479 | K7: 879 | L7: 59735 | M7: =E7 -> 中相关 | O7: =E7 -> 中相关
A8: 6 | B8: jimmy jv35 milbensauger | C8: 吉米 JV35 除螨吸尘器 | D8: 0.4669 | E8: 中相关 | F8: 0.5 | G8: 0.5 | H8: 0.4375 | I8: 0.2734 | J8: 0.237 | K8: 774 | L8: 68603 | M8: =E8 -> 中相关 | O8: =E8 -> 中相关
A9: 7 | B9: milbensauger für matratzen | C9: 床垫用除螨吸尘器 | D9: 0.4617 | E9: 中相关 | F9: 0.4375 | G9: 0.4844 | H9: 0.5 | I9: 0.4766 | J9: 0.4505 | K9: 5289 | L9: 7239 | M9: =E9 -> 中相关 | O9: =E9 -> 中相关
A10: 8 | B10: hoover | C10: hoover | D10: 0.337 | E10: 中相关 | F10: 0.5 | G10: 0.25 | H10: 0.125 | I10: 0.0625 | J10: 0.0443 | K10: 594 | L10: 91525 | M10: =E10 -> 中相关 | O10: =E10 -> 中相关
A11: 9 | B11: matratzenreiniger gerät | C11: 床垫清洁设备 | D11: 0.3198 | E11: 中相关 | F11: 0.2813 | G11: 0.3594 | H11: 0.3672 | I11: 0.3477 | J11: 0.3307 | K11: 309 | L11: 183070 | M11: =E11 -> 中相关 | O11: =E11 -> 中相关
A12: 10 | B12: matratzen reiniger | C12: 床垫清洁剂 | D12: 0.1847 | E12: 低相关 | F12: 0.25 | G12: 0.125 | H12: 0.0625 | I12: 0.1953 | J12: 0.1797 | K12: 359 | L12: 156629 | M12: =E12 -> 低相关 | O12: =E12 -> 低相关
A13: 11 | B13: milben | C13: 螨虫 | D13: 0.1843 | E13: 低相关 | F13: 0.25 | G13: 0.125 | H13: 0.1094 | I13: 0.1133 | J13: 0.1224 | K13: 539 | L13: 101622 | M13: =E13 -> 低相关 | O13: =E13 -> 低相关
A14: 12 | B14: hoover staubsauger | C14: hoover吸尘器 | D14: 0.1795 | E14: 低相关 | F14: 0.25 | G14: 0.125 | H14: 0.1172 | I14: 0.0625 | J14: 0.0443 | K14: 334 | L14: 169036 | M14: =E14 -> 低相关 | O14: =E14 -> 低相关
... A90: 88 | B90: uwant b200 | C90: uwant b200 | D90: 0.0022 | E90: 不相关 | F90: 0 | G90: 0 | H90: 0.0078 | I90: 0.0117 | J90: 0.0078 | K90: 234 | L90: 243917 | M90: =E90 -> 不相关 | O90: =E90 -> 不相关
A91: 89 | B91: shark detect clean & empty | D91: 0.0021 | E91: 不相关 | F91: 0 | G91: 0 | H91: 0 | I91: 0.0234 | J91: 0.0156 | K91: 449 | L91: 123476 | M91: =E91 -> 不相关 | O91: =E91 -> 不相关
A92: 90 | B92: sofa cleaner | C92: 沙发清洁剂 | D92: 0.002 | E92: 不相关 | F92: 0 | G92: 0 | H92: 0 | I92: 0.0156 | J92: 0.0313 | K92: 369 | L92: 152138 | M92: =E92 -> 不相关 | O92: =E92 -> 不相关
A93: 91 | B93: sofa | C93: 沙发 | D93: 0.0019 | E93: 不相关 | F93: 0 | G93: 0 | H93: 0 | I93: 0.0195 | J93: 0.0182 | K93: 30522 | L93: 499 | M93: =E93 -> 不相关 | O93: =E93 -> 不相关
A94: 92 | B94: couch reinigen | C94: 清洁沙发 | D94: 0.0019 | E94: 不相关 | F94: 0 | G94: 0 | H94: 0.0078 | I94: 0.0078 | J94: 0.0052 | K94: 0 | L94: 0 | M94: =E94 -> 不相关 | O94: =E94 -> 不相关
A95: 93 | B95: polsterreiniger gerät klein | D95: 0.0018 | E95: 不相关 | F95: 0 | G95: 0 | H95: 0.0078 | I95: 0.0039 | J95: 0.0104 | K95: 0 | L95: 0 | M95: =E95 -> 不相关 | O95: =E95 -> 不相关
A96: 94 | B96: pink vacuum cleaner | C96: 粉色吸尘器 | D96: 0.0018 | E96: 不相关 | F96: 0 | G96: 0 | H96: 0 | I96: 0.0195 | J96: 0.0156 | K96: 139 | L96: 405844 | M96: =E96 -> 不相关 | O96: =E96 -> 不相关
A97: 95 | B97: bissell spotclean c3 | C97: 必胜点状清洁c3 | D97: 0.0018 | E97: 不相关 | F97: 0 | G97: 0 | H97: 0 | I97: 0.0195 | J97: 0.013 | K97: 0 | L97: 0 | M97: =E97 -> 不相关 | O97: =E97 -> 不相关
A98: 96 | B98: haushof waschsauger | C98: Haushof 洗地机 | D98: 0.0017 | E98: 不相关 | F98: 0 | G98: 0 | H98: 0 | I98: 0.0039 | J98: 0.0469 | K98: 1344 | L98: 37411 | M98: =E98 -> 不相关 | O98: =E98 -> 不相关
A99: 97 | B99: staubsauger wasserfilter | C99: 水过滤吸尘器 | D99: 0.0017 | E99: 不相关 | F99: 0 | G99: 0 | H99: 0 | I99: 0.0156 | J99: 0.0208 | K99: 464 | L99: 119207 | M99: =E99 -> 不相关 | O99: =E99 -> 不相关
A100: 98 | B100: matratzen | C100: 床垫 | D100: 0.0017 | E100: 不相关 | F100: 0 | G100: 0 | H100: 0.0078 | I100: 0.0039 | J100: 0.0078 | K100: 3484 | L100: 12253 | M100: =E100 -> 不相关 | O100: =E100 -> 不相关
A101: 99 | B101: bissell fleckenreiniger | C101: bissell 去污剂 | D101: 0.0016 | E101: 不相关 | F101: 0 | G101: 0 | H101: 0 | I101: 0.0156 | J101: 0.0156 | K101: 459 | L101: 120596 | M101: =E101 -> 不相关 | O101: =E101 -> 不相关
A102: 100 | B102: doppelzyklon | C102: doppelzyklon | D102: 0.0015 | E102: 不相关 | F102: 0 | G102: 0 | H102: 0.0078 | I102: 0.0039 | J102: 0.0026 | K102: 124 | L102: 451926 | M102: =E102 -> 不相关 | O102: =E102 -> 不相关
A103: 101 | B103: mini henry hoover | C103: 迷你亨利吸尘器 | D103: 0.0015 | E103: 不相关 | F103: 0 | G103: 0 | H103: 0.0078 | I103: 0.0039 | J103: 0.0026 | K103: 0 | L103: 0 | M103: =E103 -> 不相关 | O103: =E103 -> 不相关
A104: 102 | B104: dampfreiniger couch | C104: 沙发蒸汽清洁器 | D104: 0.0015 | E104: 不相关 | F104: 0 | G104: 0 | H104: 0.0078 | I104: 0.0039 | J104: 0.0026 | K104: 139 | L104: 405844 | M104: =E104 -> 不相关 | O104: =E104 -> 不相关
A105: 103 | B105: allergiker | C105: 过敏者 | D105: 0.0015 | E105: 不相关 | F105: 0 | G105: 0 | H105: 0.0078 | I105: 0.0039 | J105: 0.0026 | K105: 154 | L105: 367674 | M105: =E105 -> 不相关 | O105: =E105 -> 不相关
A106: 104 | B106: powercleany handstaubsauger der stärkste | C106: PowerCleany最强手持吸尘器 | D106: 0.0015 | E106: 不相关 | F106: 0 | G106: 0 | H106: 0 | I106: 0.0117 | J106: 0.0234 | K106: 0 | L106: 0 | M106: =E106 -> 不相关 | O106: =E106 -> 不相关
A107: 105 | B107: kroqo | C107: kroqo | D107: 0.0015 | E107: 不相关 | F107: 0 | G107: 0 | H107: 0.0078 | I107: 0.0039 | J107: 0.0026 | K107: 0 | L107: 0 | M107: =E107 -> 不相关 | O107: =E107 -> 不相关
... A113: 111 | B113: dampfreiniger für polstermöbel | C113: 软垫家具用蒸汽清洁器 | D113: 0.0015 | E113: 不相关 | F113: 0 | G113: 0 | H113: 0.0078 | I113: 0.0039 | J113: 0.0026 | K113: 274 | L113: 207537 | M113: =E113 -> 不相关 | O113: =E113 -> 不相关
A114: 112 | B114: pureprotect mini 900 series | D114: 0.0015 | E114: 不相关 | F114: 0 | G114: 0 | H114: 0.0078 | I114: 0.0039 | J114: 0.0026 | K114: 144 | L114: 392148 | M114: =E114 -> 不相关 | O114: =E114 -> 不相关
A115: 113 | B115: shark wv200eu | C115: 鲨鱼 wv200eu | D115: 0.0015 | E115: 不相关 | F115: 0 | G115: 0 | H115: 0.0078 | I115: 0.0039 | J115: 0.0026 | K115: 159 | L115: 356754 | M115: =E115 -> 不相关 | O115: =E115 -> 不相关
A116: 114 | B116: hover air x1 drohne | C116: hover air x1 无人机 | D116: 0.0014 | E116: 不相关 | F116: 0 | G116: 0 | H116: 0 | I116: 0.0156 | J116: 0.0104 | K116: 334 | L116: 169036 | M116: =E116 -> 不相关 | O116: =E116 -> 不相关
A117: 115 | B117: neakasa magic 1 vacuum steamer | D117: 0.0014 | E117: 不相关 | F117: 0 | G117: 0 | H117: 0 | I117: 0.0156 | J117: 0.0104 | K117: 774 | L117: 68603 | M117: =E117 -> 不相关 | O117: =E117 -> 不相关
A118: 116 | B118: polstersauger nass | C118: 湿式软垫吸尘器 | D118: 0.0014 | E118: 不相关 | F118: 0 | G118: 0 | H118: 0 | I118: 0.0039 | J118: 0.0365 | K118: 394 | L118: 142001 | M118: =E118 -> 不相关 | O118: =E118 -> 不相关
A119: 117 | B119: dupray steam cleaner | C119: dupray 蒸汽清洁器 | D119: 0.0014 | E119: 不相关 | F119: 0 | G119: 0 | H119: 0 | I119: 0.0117 | J119: 0.0208 | K119: 319 | L119: 177104 | M119: =E119 -> 不相关 | O119: =E119 -> 不相关
A120: 118 | B120: ryer nasssauger reinigung teppich und kauqe reinigung | D120: 0.0012 | E120: 不相关 | F120: 0 | G120: 0 | H120: 0 | I120: 0 | J120: 0.0391 | K120: 1179 | L120: 43236 | M120: =E120 -> 不相关 | O120: =E120 -> 不相关
A121: 119 | B121: nassreiniger polstermöbel | C121: 软垫家具湿式清洁器 | D121: 0.0012 | E121: 不相关 | F121: 0 | G121: 0 | H121: 0 | I121: 0.0117 | J121: 0.013 | K121: 364 | L121: 154320 | M121: =E121 -> 不相关 | O121: =E121 -> 不相关
A122: 120 | B122: kärcher fc8 | D122: 0.0011 | E122: 不相关 | F122: 0 | G122: 0 | H122: 0 | I122: 0.0078 | J122: 0.0182 | K122: 424 | L122: 131303 | M122: =E122 -> 不相关 | O122: =E122 -> 不相关
A123: 121 | B123: ambiano polsterreinigungsgerät | D123: 0.0011 | E123: 不相关 | F123: 0 | G123: 0 | H123: 0 | I123: 0.0117 | J123: 0.0078 | K123: 214 | L123: 266736 | M123: =E123 -> 不相关 | O123: =E123 -> 不相关
A124: 122 | B124: eureka j15 pro ultra | C124: 尤里卡j15 pro ultra | D124: 0.0009 | E124: 不相关 | F124: 0 | G124: 0 | H124: 0 | I124: 0.0078 | J124: 0.0104 | K124: 954 | L124: 54599 | M124: =E124 -> 不相关 | O124: =E124 -> 不相关
A125: 123 | B125: hetty staubsauger | C125: hetty 吸尘器 | D125: 0.0009 | E125: 不相关 | F125: 0 | G125: 0 | H125: 0 | I125: 0.0078 | J125: 0.013 | K125: 304 | L125: 186231 | M125: =E125 -> 不相关 | O125: =E125 -> 不相关
A126: 124 | B126: sofareiniger waschsauger | C126: 洗吸一体沙发清洁机 | D126: 0.0009 | E126: 不相关 | F126: 0 | G126: 0 | H126: 0 | I126: 0 | J126: 0.0286 | K126: 239 | L126: 238857 | M126: =E126 -> 不相关 | O126: =E126 -> 不相关
A127: 125 | B127: sauger | C127: 吸尘器 | D127: 0.0008 | E127: 不相关 | F127: 0 | G127: 0 | H127: 0 | I127: 0.0039 | J127: 0.0182 | K127: 774 | L127: 68603 | M127: =E127 -> 不相关 | O127: =E127 -> 不相关
A128: 126 | B128: dampfsauger für alles | C128: 万能蒸汽吸尘器 | D128: 0.0008 | E128: 不相关 | F128: 0 | G128: 0 | H128: 0 | I128: 0.0039 | J128: 0.0182 | K128: 359 | L128: 156629 | M128: =E128 -> 不相关 | O128: =E128 -> 不相关
A129: 127 | B129: tierhaarstaubsauger | C129: 宠物毛发吸尘器 | D129: 0.0008 | E129: 不相关 | F129: 0 | G129: 0 | H129: 0 | I129: 0.0078 | J129: 0.0078 | K129: 0 | L129: 0 | M129: =E129 -> 不相关 | O129: =E129 -> 不相关
A130: 128 | B130: aspirator | C130: 吸尘器 | D130: 0.0007 | E130: 不相关 | F130: 0 | G130: 0 | H130: 0 | I130: 0.0039 | J130: 0.0156 | K130: 389 | L130: 143911 | M130: =E130 -> 不相关 | O130: =E130 -> 不相关
A131: 129 | B131: wasser staubsauger | C131: 水吸尘器 | D131: 0.0007 | E131: 不相关 | F131: 0 | G131: 0 | H131: 0 | I131: 0 | J131: 0.0234 | K131: 459 | L131: 120596 | M131: =E131 -> 不相关 | O131: =E131 -> 不相关
A132: 130 | B132: triflex hx2 carcare | D132: 0.0007 | E132: 不相关 | F132: 0 | G132: 0 | H132: 0 | I132: 0.0078 | J132: 0.0052 | K132: 134 | L132: 420189 | M132: =E132 -> 不相关 | O132: =E132 -> 不相关
A133: 131 | B133: hydrosteam | C133: 水蒸汽 | D133: 0.0007 | E133: 不相关 | F133: 0 | G133: 0 | H133: 0 | I133: 0.0078 | J133: 0.0052 | K133: 199 | L133: 286755 | M133: =E133 -> 不相关 | O133: =E133 -> 不相关
A134: 132 | B134: uvo desinfektionsturm | C134: uvo 消毒塔 | D134: 0.0007 | E134: 不相关 | F134: 0 | G134: 0 | H134: 0 | I134: 0.0078 | J134: 0.0052 | K134: 0 | L134: 0 | M134: =E134 -> 不相关 | O134: =E134 -> 不相关
A135: 133 | B135: numatic | C135: numatic | D135: 0.0007 | E135: 不相关 | F135: 0 | G135: 0 | H135: 0 | I135: 0.0039 | J135: 0.0156 | K135: 159 | L135: 356754 | M135: =E135 -> 不相关 | O135: =E135 -> 不相关
A136: 134 | B136: polsterreiniger gerät bissell | C136: Bissell软垫清洁设备 | D136: 0.0007 | E136: 不相关 | F136: 0 | G136: 0 | H136: 0 | I136: 0 | J136: 0.0234 | K136: 329 | L136: 171657 | M136: =E136 -> 不相关 | O136: =E136 -> 不相关
A137: 135 | B137: dampfsauger | C137: 蒸汽吸尘器 | D137: 0.0007 | E137: 不相关 | F137: 0 | G137: 0 | H137: 0 | I137: 0 | J137: 0.0234 | K137: 2379 | L137: 19471 | M137: =E137 -> 不相关 | O137: =E137 -> 不相关
A138: 136 | B138: dyson ontrac | C138: 戴森ontrac | D138: 0.0007 | E138: 不相关 | F138: 0 | G138: 0 | H138: 0 | I138: 0.0078 | J138: 0.0052 | K138: 289 | L138: 196377 | M138: =E138 -> 不相关 | O138: =E138 -> 不相关
A139: 137 | B139: odkurzacz pioracy | C139: 洗地吸尘器 | D139: 0.0006 | E139: 不相关 | F139: 0 | G139: 0 | H139: 0 | I139: 0 | J139: 0.0208 | K139: 319 | L139: 177104 | M139: =E139 -> 不相关 | O139: =E139 -> 不相关
A140: 138 | B140: bissell hydrosteam | C140: 比塞尔水蒸汽 | D140: 0.0006 | E140: 不相关 | F140: 0 | G140: 0 | H140: 0 | I140: 0.0039 | J140: 0.0104 | K140: 519 | L140: 105721 | M140: =E140 -> 不相关 | O140: =E140 -> 不相关
A141: 139 | B141: staub entferner | C141: staub 清洁剂 | D141: 0.0006 | E141: 不相关 | F141: 0 | G141: 0 | H141: 0 | I141: 0 | J141: 0.0208 | K141: 314 | L141: 180010 | M141: =E141 -> 不相关 | O141: =E141 -> 不相关
A142: 140 | B142: samsung bespoke jet | C142: 三星Bespoke Jet | D142: 0.0005 | E142: 不相关 | F142: 0 | G142: 0 | H142: 0 | I142: 0 | J142: 0.0182 | K142: 939 | L142: 55578 | M142: =E142 -> 不相关 | O142: =E142 -> 不相关
A143: 141 | B143: tepichreinigungsmaschine | C143: 地毯清洁机 | D143: 0.0005 | E143: 不相关 | F143: 0 | G143: 0 | H143: 0 | I143: 0 | J143: 0.0156 | K143: 449 | L143: 123476 | M143: =E143 -> 不相关 | O143: =E143 -> 不相关
A144: 142 | B144: wasserstaubsauger | C144: 水过滤吸尘器 | D144: 0.0005 | E144: 不相关 | F144: 0 | G144: 0 | H144: 0 | I144: 0 | J144: 0.0182 | K144: 1994 | L144: 23942 | M144: =E144 -> 不相关 | O144: =E144 -> 不相关
... A156: 154 | B156: hepa filter handstaubsauger | C156: 手持吸尘器用 HEPA 过滤器 | D156: 0.0004 | E156: 不相关 | F156: 0 | G156: 0 | H156: 0 | I156: 0.0039 | J156: 0.0026 | K156: 0 | L156: 0 | M156: =E156 -> 不相关 | O156: =E156 -> 不相关
A157: 155 | B157: shark nasssauger | D157: 0.0004 | E157: 不相关 | F157: 0 | G157: 0 | H157: 0 | I157: 0 | J157: 0.013 | K157: 369 | L157: 152138 | M157: =E157 -> 不相关 | O157: =E157 -> 不相关
A158: 156 | B158: lautux | C158: 劳图克斯 | D158: 0.0004 | E158: 不相关 | F158: 0 | G158: 0 | H158: 0 | I158: 0.0039 | J158: 0.0026 | K158: 489 | L158: 112725 | M158: =E158 -> 不相关 | O158: =E158 -> 不相关
A159: 157 | B159: sebo staubsauger | C159: SEBO 吸尘器 | D159: 0.0004 | E159: 不相关 | F159: 0 | G159: 0 | H159: 0 | I159: 0 | J159: 0.013 | K159: 569 | L159: 95827 | M159: =E159 -> 不相关 | O159: =E159 -> 不相关
A160: 158 | B160: cleaning tools | C160: 清洁工具 | D160: 0.0004 | E160: 不相关 | F160: 0 | G160: 0 | H160: 0 | I160: 0 | J160: 0.013 | K160: 684 | L160: 78564 | M160: =E160 -> 不相关 | O160: =E160 -> 不相关
A161: 159 | B161: sofa matratze | C161: 沙发床垫 | D161: 0.0004 | E161: 不相关 | F161: 0 | G161: 0 | H161: 0 | I161: 0.0039 | J161: 0.0052 | K161: 124 | L161: 451926 | M161: =E161 -> 不相关 | N161: =E161 -> 不相关
A162: 160 | B162: nasssauger sofa | C162: 沙发湿式吸尘器 | D162: 0.0004 | E162: 不相关 | F162: 0 | G162: 0 | H162: 0 | I162: 0.0039 | J162: 0.0026 | K162: 239 | L162: 238857 | M162: =E162 -> 不相关 | N162: =E162 -> 不相关
A163: 161 | B163: dampfreiniger polster | C163: 蒸汽清洁器 软垫 | D163: 0.0004 | E163: 不相关 | F163: 0 | G163: 0 | H163: 0 | I163: 0.0039 | J163: 0.0026 | K163: 334 | L163: 169036 | M163: =E163 -> 不相关 | N163: =E163 -> 不相关
A164: 162 | B164: metabo asa 30 h pc | D164: 0.0004 | E164: 不相关 | F164: 0 | G164: 0 | H164: 0 | I164: 0.0039 | J164: 0.0026 | K164: 0 | L164: 0 | M164: =E164 -> 不相关 | N164: =E164 -> 不相关
A165: 163 | B165: henry hoover | C165: 亨利·胡佛 | D165: 0.0004 | E165: 不相关 | F165: 0 | G165: 0 | H165: 0 | I165: 0.0039 | J165: 0.0026 | K165: 0 | L165: 0 | M165: =E165 -> 不相关 | N165: =E165 -> 不相关
A166: 164 | B166: مكنسة كهربائية | C166: 吸尘器 | D166: 0.0004 | E166: 不相关 | F166: 0 | G166: 0 | H166: 0 | I166: 0.0039 | J166: 0.0026 | K166: 254 | L166: 224321 | M166: =E166 -> 不相关 | N166: =E166 -> 不相关
A167: 165 | B167: anti staub | C167: 防尘（德语） | D167: 0.0004 | E167: 不相关 | F167: 0 | G167: 0 | H167: 0 | I167: 0.0039 | J167: 0.0026 | K167: 189 | L167: 301719 | M167: =E167 -> 不相关 | N167: =E167 -> 不相关
A168: 166 | B168: dyson v8 advanced | D168: 0.0004 | E168: 不相关 | F168: 0 | G168: 0 | H168: 0 | I168: 0 | J168: 0.013 | K168: 464 | L168: 119207 | M168: =E168 -> 不相关 | N168: =E168 -> 不相关
A169: 167 | B169: waschsauger mit dampffunktion | C169: 具有蒸汽功能的真空吸尘器 | D169: 0.0004 | E169: 不相关 | F169: 0 | G169: 0 | H169: 0 | I169: 0 | J169: 0.013 | K169: 379 | L169: 147888 | M169: =E169 -> 不相关 | N169: =E169 -> 不相关
A170: 168 | B170: roborock flexi pro | C170: 罗博岩 Flexi Pro | D170: 0.0004 | E170: 不相关 | F170: 0 | G170: 0 | H170: 0 | I170: 0 | J170: 0.013 | K170: 684 | L170: 78564 | M170: =E170 -> 不相关 | N170: =E170 -> 不相关
A171: 169 | B171: bissell little green | C171: 比赛尔小绿 | D171: 0.0004 | E171: 不相关 | F171: 0 | G171: 0 | H171: 0 | I171: 0.0039 | J171: 0.0026 | K171: 274 | L171: 207537 | M171: =E171 -> 不相关 | N171: =E171 -> 不相关
A172: 170 | B172: sofa reinigen | C172: 沙发清洁 | D172: 0.0004 | E172: 不相关 | F172: 0 | G172: 0 | H172: 0 | I172: 0.0039 | J172: 0.0026 | K172: 269 | L172: 211450 | M172: =E172 -> 不相关 | N172: =E172 -> 不相关
A173: 171 | B173: hausstaubmilben spray | C173: 防尘螨喷雾 | D173: 0.0004 | E173: 不相关 | F173: 0 | G173: 0 | H173: 0 | I173: 0.0039 | J173: 0.0026 | K173: 179 | L173: 318223 | M173: =E173 -> 不相关 | N173: =E173 -> 不相关
A174: 172 | B174: bissell spotclean pro | C174: bissell专业清洁器 | D174: 0.0004 | E174: 不相关 | F174: 0 | G174: 0 | H174: 0 | I174: 0 | J174: 0.013 | K174: 3829 | L174: 10879 | M174: =E174 -> 不相关 | N174: =E174 -> 不相关
A175: 173 | B175: staubsauger wasser | C175: 水过滤吸尘器 | D175: 0.0004 | E175: 不相关 | F175: 0 | G175: 0 | H175: 0 | I175: 0.0039 | J175: 0.0026 | K175: 199 | L175: 286755 | M175: =E175 -> 不相关 | N175: =E175 -> 不相关
A176: 174 | B176: couchreiniger | C176: 沙发清洁剂 | D176: 0.0004 | E176: 不相关 | F176: 0 | G176: 0 | H176: 0 | I176: 0.0039 | J176: 0.0026 | K176: 294 | L176: 192884 | M176: =E176 -> 不相关 | N176: =E176 -> 不相关
A177: 175 | B177: bissl | C177: 比斯尔 | D177: 0.0004 | E177: 不相关 | F177: 0 | G177: 0 | H177: 0 | I177: 0.0039 | J177: 0.0026 | K177: 0 | L177: 0 | M177: =E177 -> 不相关 | N177: =E177 -> 不相关
A178: 176 | B178: miluna pro | D178: 0.0004 | E178: 不相关 | F178: 0 | G178: 0 | H178: 0 | I178: 0.0039 | J178: 0.0026 | K178: 334 | L178: 169036 | M178: =E178 -> 不相关 | N178: =E178 -> 不相关
A179: 177 | B179: kärcher teppich und polsterreiniger | C179: 凯驰地毯和软垫清洁器 | D179: 0.0003 | E179: 不相关 | F179: 0 | G179: 0 | H179: 0 | I179: 0 | J179: 0.0104 | K179: 334 | L179: 169036 | M179: =E179 -> 不相关 | N179: =E179 -> 不相关
A180: 178 | B180: shark hydrovac | C180: 鲨鱼 hydrovac | D180: 0.0003 | E180: 不相关 | F180: 0 | G180: 0 | H180: 0 | I180: 0 | J180: 0.0104 | K180: 2579 | L180: 17678 | M180: =E180 -> 不相关 | N180: =E180 -> 不相关
A181: 179 | B181: allergiker bettwäsche | C181: 过敏者床上用品 | D181: 0.0003 | E181: 不相关 | F181: 0 | G181: 0 | H181: 0 | I181: 0 | J181: 0.0104 | K181: 1314 | L181: 38350 | M181: =E181 -> 不相关 | N181: =E181 -> 不相关
A182: 180 | B182: luftreiniger dyson | C182: 戴森空气净化器 | D182: 0.0003 | E182: 不相关 | F182: 0 | G182: 0 | H182: 0 | I182: 0 | J182: 0.0104 | K182: 974 | L182: 53337 | M182: =E182 -> 不相关 | N182: =E182 -> 不相关
A183: 181 | B183: mini henry staubsauger | C183: 迷你亨利吸尘器 | D183: 0.0003 | E183: 不相关 | F183: 0 | G183: 0 | H183: 0 | I183: 0 | J183: 0.0104 | K183: 2739 | L183: 16379 | M183: =E183 -> 不相关 | N183: =E183 -> 不相关
A184: 182 | B184: livington pocket vac | D184: 0.0003 | E184: 不相关 | F184: 0 | G184: 0 | H184: 0 | I184: 0 | J184: 0.0104 | K184: 3304 | L184: 13033 | M184: =E184 -> 不相关 | N184: =E184 -> 不相关
A185: 183 | B185: aeg staubsauger akku raumpflege | C185: AEG 吸尘器 电池 清洁 | D185: 0.0003 | E185: 不相关 | F185: 0 | G185: 0 | H185: 0 | I185: 0 | J185: 0.0104 | K185: 339 | L185: 166337 | M185: =E185 -> 不相关 | N185: =E185 -> 不相关
A186: 184 | B186: teppichreiniger schaum | C186: 地毯清洁泡沫 | D186: 0.0003 | E186: 不相关 | F186: 0 | G186: 0 | H186: 0 | I186: 0 | J186: 0.0104 | K186: 469 | L186: 117858 | M186: =E186 -> 不相关 | N186: =E186 -> 不相关
A187: 185 | B187: norsky | C187: 诺斯基 | D187: 0.0003 | E187: 不相关 | F187: 0 | G187: 0 | H187: 0 | I187: 0 | J187: 0.0104 | K187: 0 | L187: 0 | M187: =E187 -> 不相关 | N187: =E187 -> 不相关
A188: 186 | B188: polsterreiniger gerät | C188: 软垫清洁设备 | D188: 0.0003 | E188: 不相关 | F188: 0 | G188: 0 | H188: 0 | I188: 0 | J188: 0.0104 | K188: 22444 | L188: 851 | M188: =E188 -> 不相关 | N188: =E188 -> 不相关
A189: 187 | B189: carpet cleaner machine | C189: 地毯清洁机 | D189: 0.0003 | E189: 不相关 | F189: 0 | G189: 0 | H189: 0 | I189: 0 | J189: 0.0104 | K189: 384 | L189: 145869 | M189: =E189 -> 不相关 | N189: =E189 -> 不相关
A190: 188 | B190: henry mini staubsauger | C190: 亨利 迷你 吸尘器 | D190: 0.0002 | E190: 不相关 | F190: 0 | G190: 0 | H190: 0 | I190: 0 | J190: 0.0078 | K190: 5949 | L190: 6188 | M190: =E190 -> 不相关 | N190: =E190 -> 不相关
A191: 189 | B191: dampfreiniger sauger | C191: 蒸汽吸尘器 | D191: 0.0002 | E191: 不相关 | F191: 0 | G191: 0 | H191: 0 | I191: 0 | J191: 0.0052 | K191: 134 | L191: 420189 | M191: =E191 -> 不相关 | N191: =E191 -> 不相关
...

Sheet 1.1 竞品拓词法 （至少20个）
A1: milbensauger竞品拓词导出_相似竞品拓词&筛查 | N1: B0DQSMD5VW,B0DL5J6MK4,B08BLTZQ7R,B0DKPGVGT5,B0CKTKBSP8,B014SPNQV2,B0CJFR8YZ1,B0CHMPZVZT,B0DDPXCK6L,B0CJ9FL94H
A2: # | B2: 关键词 | C2: 相关性-自动百分比 | D2: 相关性-自动 | E2: 相关性-自动 | F2: 相关性-自动 | G2: 自然位前4占位率 | H2: 自然位前8占位率 | I2: 自然位前16占位率 | J2: 自然位前32占位率 | K2: 自然位前48占位率 | L2: 搜索量 | M2: 排名 | N2: 相关性-手动 | O2: 流量大小 | P2: 相关性 | Q2: 修饰词类型 | R2: 搜索转化率
A3: 1 | B3: hoover milbensauger | C3: 胡佛除螨吸尘器 | D3: 72.81% | E3: 高相关 | F3: 高相关 | G3: 93.75% | H3: 60.94% | I3: 54.69% | J3: 27.73% | K3: 18.49% | L3: 329 | M3: 177403
A4: 2 | B4: milbensauger für matratzen testsieger | C4: 床垫用除螨吸尘器测试冠军 | D4: 42.67% | E4: 中相关 | F4: 中相关 | G4: 46.88% | H4: 43.75% | I4: 36.72% | J4: 30.08% | K4: 22.66% | L4: 444 | M4: 129581
A5: 3 | B5: milbensauger | C5: 除螨吸尘器 | D5: 41.68% | E5: 中相关 | F5: 中相关 | G5: 46.88% | H5: 39.06% | I5: 39.06% | J5: 27.73% | K5: 22.66% | L5: 10049 | M5: 3142
A6: 4 | B6: milbenstaubsauger | C6: 除螨吸尘器 | D6: 40.3% | E6: 中相关 | F6: 中相关 | G6: 46.88% | H6: 37.5% | I6: 31.25% | J6: 30.86% | K6: 21.35% | L6: 434 | M6: 132720
A7: 5 | B7: milbensauger mit uv licht | C7: 带紫外线的除螨吸尘器 | D7: 40.04% | E7: 中相关 | F7: 中相关 | G7: 46.88% | H7: 37.5% | I7: 31.25% | J7: 26.95% | K7: 21.88% | L7: 899 | M7: 60795
A8: 6 | B8: milbensauger für matratzen | C8: 床垫用除螨吸尘器 | D8: 39.39% | E8: 中相关 | F8: 中相关 | G8: 43.75% | H8: 42.19% | I8: 29.69% | J8: 26.17% | K8: 22.66% | L8: 5589 | M8: 7084
A9: 7 | B9: hoover | C9: 胡佛 | D9: 33.69% | E9: 中相关 | F9: 中相关 | G9: 50% | H9: 25% | I9: 12.5% | J9: 6.25% | K9: 4.17% | L9: 549 | M9: 103370
A10: 8 | B10: matratzenreiniger gerät | C10: 床垫清洁设备 | D10: 24.97% | E10: 中相关 | F10: 中相关 | G10: 28.13% | H10: 21.88% | I10: 23.44% | J10: 19.92% | K10: 17.71% | L10: 364 | M10: 159716
A11: 9 | B11: jimmy jv35 milbensauger | C11: 吉米 JV35 除螨吸尘器 | D11: 23.63% | E11: 中相关 | F11: 中相关 | G11: 25% | H11: 25% | I11: 25% | J11: 12.5% | K11: 8.59% | L11: 689 | M11: 81160
A12: 10 | B12: milben | C12: 螨虫 | D12: 18.37% | E12: 低相关 | F12: 低相关 | G12: 25% | H12: 12.5% | I12: 11.72% | J12: 9.77% | K12: 10.16% | L12: 524 | M12: 108734
A13: 11 | B13: hoover staubsauger | C13: 胡佛吸尘器 | D13: 17.84% | E13: 低相关 | F13: 低相关 | G13: 25% | H13: 12.5% | I13: 10.94% | J13: 6.25% | K13: 4.43% | L13: 319 | M13: 183101
A14: 12 | B14: matratzen reiniger | C14: 床垫清洁剂 | D14: 17.81% | E14: 低相关 | F14: 低相关 | G14: 25% | H14: 12.5% | I14: 6.25% | J14: 13.28% | K14: 10.68% | L14: 509 | M14: 112137
A15: 13 | B15: bettwanzen | C15: 臭虫（复数） | D15: 16.84% | F15: 低相关 | G15: 25% | H15: 12.5% | I15: 6.25% | J15: 3.13% | K15: 2.08% | L15: 874 | M15: 62632
A16: 14 | B16: bettwanzen bekämpfung | C16: 臭虫防治 | D16: 16.84% | F16: 低相关 | G16: 25% | H16: 12.5% | I16: 6.25% | J16: 3.13% | K16: 2.08% | L16: 959 | M16: 56582
A17: 15 | B17: jigoo j300 milbensauger | C17: 吉戈J300除螨吸尘器 | D17: 9.42% | F17: 低相关 | G17: 12.5% | H17: 7.81% | I17: 6.25% | J17: 3.13% | K17: 2.08% | L17: 144 | M17: 405696
A18: 16 | B18: jigoo j300 | C18: 吉戈J300 | D18: 9.27% | F18: 低相关 | G18: 12.5% | H18: 7.81% | I18: 5.47% | J18: 2.73% | K18: 1.82% | L18: 144 | M18: 405696
A19: 17 | B19: matratzenreiniger | C19: 床垫清洁剂 | D19: 8.43% | F19: 低相关 | G19: 3.13% | H19: 12.5% | I19: 13.28% | J19: 18.36% | K19: 15.63% | L19: 804 | M19: 68595
A20: 18 | B20: jigoo t600 milbensauger | D20: 7.74% | F20: 低相关 | G20: 9.38% | H20: 7.81% | I20: 5.47% | J20: 3.13% | K20: 2.08% | L20: 294 | M20: 199357
A21: 19 | B21: milbensauger jigoo | D21: 7.71% | F21: 低相关 | G21: 9.38% | H21: 7.81% | I21: 5.47% | J21: 2.73% | K21: 1.82% | L21: 149 | M21: 392766
A22: 20 | B22: jigoo milbensauger | C22: 吉戈除螨吸尘器 | D22: 7.55% | F22: 低相关 | G22: 9.38% | H22: 7.81% | I22: 4.69% | J22: 2.34% | K22: 1.56% | L22: 159 | M22: 368973
A23: 21 | B23: hoover ultra vortex milbensauger | C23: hoover ultra vortex 除螨吸尘器 | D23: 7.32% | F23: 低相关 | G23: 9.38% | H23: 6.25% | I23: 5.47% | J23: 2.73% | K23: 1.82% | L23: 129 | M23: 450049
A24: 22 | B24: hyla staubsauger | C24: hyla 吸尘器 | D24: 6.81% | F24: 低相关 | G24: 3.13% | H24: 10.94% | I24: 10.94% | J24: 8.98% | K24: 8.07% | L24: 674 | M24: 83172
A25: 23 | B25: jimmy milbensauger | C25: 吉米 除螨吸尘器 | D25: 6.5% | F25: 低相关 | G25: 6.25% | H25: 6.25% | I25: 8.59% | J25: 5.86% | K25: 3.91% | L25: 274 | M25: 214312
A26: 24 | B26: polstersauger | C26: 软垫吸尘器 | D26: 6.25% | F26: 低相关 | G26: 3.13% | H26: 12.5% | I26: 6.25% | J26: 5.86% | K26: 7.03% | L26: 684 | M26: 81829
A27: 25 | B27: mattress vacuum cleaner | C27: 床垫吸尘器 | D27: 5.75% | F27: 低相关 | G27: 6.25% | H27: 6.25% | I27: 5.47% | J27: 2.73% | K27: 1.82% | L27: 239 | M27: 246305
A28: 26 | B28: bed vacuum cleaner | C28: 床用吸尘器 | D28: 5.21% | F28: 低相关 | G28: 6.25% | H28: 4.69% | I28: 4.69% | J28: 2.34% | K28: 1.56% | L28: 154 | M28: 380614
A29: 27 | B29: hausstaubmilben sauger | C29: 防尘螨吸尘器 | D29: 5.12% | F29: 低相关 | G29: 6.25% | H29: 4.69% | I29: 3.13% | J29: 3.91% | K29: 2.6% | L29: 149 | M29: 392766
A30: 28 | B30: dampfreiniger matratze | C30: 蒸汽清洁器 床垫 | D30: 5.06% | F30: 低相关 | G30: 6.25% | H30: 4.69% | I30: 3.91% | J30: 1.95% | K30: 1.3% | L30: 209 | M30: 282089
A31: 29 | B31: sofa staubsauger | C31: 沙发吸尘器 | D31: 4.95% | F31: 低相关 | G31: 6.25% | H31: 4.69% | I31: 3.13% | J31: 1.95% | K31: 1.56% | L31: 184 | M31: 320398
A32: 30 | B32: matratzensauger | C32: 床垫吸尘器 | D32: 4.82% | F32: 低相关 | G32: 6.25% | H32: 3.13% | I32: 4.69% | J32: 2.34% | K32: 1.56% | L32: 219 | M32: 269187
A33: 31 | B33: milben sauger | C33: 螨虫吸尘器 | D33: 4.78% | F33: 低相关 | G33: 6.25% | H33: 3.13% | I33: 3.91% | J33: 3.13% | K33: 2.34% | L33: 249 | M33: 236350
... A46: 44 | B46: hausstaubmilben | C46: 尘螨 | D46: 2.76% | F46: 低相关 | G46: 3.13% | H46: 3.13% | I46: 1.56% | J46: 1.56% | K46: 2.34% | L46: 264 | M46: 222710
A47: 45 | B47: jimmy bx8 | D47: 2.65% | F47: 低相关 | G47: 3.13% | H47: 3.13% | I47: 1.56% | J47: 0.78% | K47: 0.52% | L47: 129 | M47: 450049
A48: 46 | B48: hyla wasserstaubsauger | C48: hyla 水吸尘器 | D48: 2.31% | F48: 低相关 | G48: 0% | H48: 0% | I48: 10.16% | J48: 8.59% | K48: 6.25% | L48: 2579 | M48: 18511
A49: 47 | B49: jimmy | C49: 吉米 | D49: 2.29% | F49: 低相关 | G49: 3.13% | H49: 1.56% | I49: 1.56% | J49: 1.17% | K49: 0.78% | L49: 259 | M49: 227059
A50: 48 | B50: matratzen reiniger gerät | C50: 床垫清洁设备 | D50: 2.26% | F50: 低相关 | G50: 3.13% | H50: 1.56% | I50: 1.56% | J50: 0.78% | K50: 0.52% | L50: 209 | M50: 282089
A51: 49 | B51: anti milben | C51: 抗螨虫 | D51: 2.19% | F51: 低相关 | G51: 3.13% | H51: 1.56% | I51: 0.78% | J51: 1.17% | K51: 1.3% | L51: 129 | M51: 450049
A52: 50 | B52: power cleany | C52: 电动清洁 | D52: 1.82% | F52: 不相关 | G52: 0% | H52: 0% | I52: 6.25% | J52: 8.2% | K52: 10.16% | L52: 0 | M52: 0
A53: 51 | B53: jimmy bx7 pro | C53: 吉米bx7 pro | D53: 1.31% | F53: 不相关 | G53: 0% | H53: 3.13% | I53: 2.34% | J53: 1.95% | K53: 1.3% | L53: 214 | M53: 275487
A54: 52 | B54: milben waschmittel | C54: 防螨洗涤剂 | D54: 1.22% | F54: 不相关 | G54: 0% | H54: 0% | I54: 6.25% | J54: 3.13% | K54: 2.08% | L54: 299 | M54: 195944
A55: 53 | B55: sofa cleaner machine | C55: 沙发清洁机 | D55: 1.21% | F55: 不相关 | G55: 0% | H55: 0% | I55: 3.91% | J55: 6.25% | K55: 6.25% | L55: 324 | M55: 180226
A56: 54 | B56: shark polsterreiniger | D56: 1.21% | F56: 不相关 | G56: 0% | H56: 0% | I56: 3.13% | J56: 8.2% | K56: 5.47% | L56: 439 | M56: 131127
A57: 55 | B57: staubsauger allergiker | C57: 过敏患者吸尘器 | D57: 1.01% | F57: 不相关 | G57: 0% | H57: 0% | I57: 4.69% | J57: 3.13% | K57: 2.86% | L57: 319 | M57: 183101
A58: 56 | B58: lifevac | C58: lifevac | D58: 0.75% | F58: 不相关 | G58: 0% | H58: 0% | I58: 3.13% | J58: 3.13% | K58: 2.08% | L58: 1649 | M58: 31105
A59: 57 | B59: dampfreiniger sofa | C59: 蒸汽清洁器 沙发 | D59: 0.7% | F59: 不相关 | G59: 0% | H59: 1.56% | I59: 1.56% | J59: 0.78% | K59: 0.78% | L59: 244 | M59: 241244
A60: 58 | B60: polster dampfreiniger | C60: 软垫蒸汽清洁器 | D60: 0.63% | F60: 不相关 | G60: 0% | H60: 0% | I60: 2.34% | J60: 3.13% | K60: 2.08% | L60: 609 | M60: 92588
A61: 59 | B61: allergiker staubsauger | C61: 过敏者吸尘器 | D61: 0.62% | F61: 不相关 | G61: 0% | H61: 1.56% | I61: 0.78% | J61: 1.17% | K61: 1.04% | L61: 144 | M61: 405696
A62: 60 | B62: wasserstaubsauger hyla alternative | C62: Hyla水过滤吸尘器替代品 | D62: 0.62% | F62: 不相关 | G62: 0% | H62: 1.56% | I62: 0.78% | J62: 1.17% | K62: 1.04% | L62: 239 | M62: 246305
A63: 61 | B63: dampfstaubsauger | C63: 蒸汽吸尘器 | D63: 0.58% | F63: 不相关 | G63: 0% | H63: 1.56% | I63: 0.78% | J63: 0.78% | K63: 0.52% | L63: 169 | M63: 347903
A64: 62 | B64: hausstaubmilben luftreiniger | C64: 防尘螨空气净化器 | D64: 0.58% | F64: 不相关 | G64: 0% | H64: 1.56% | I64: 0.78% | J64: 0.78% | K64: 0.52% | L64: 254 | M64: 231563
A65: 63 | B65: wasserstaubsauger mit luftreiniger | C65: 带空气净化器的水过滤吸尘器 | D65: 0.55% | F65: 不相关 | G65: 0% | H65: 1.56% | I65: 0.78% | J65: 0.39% | K65: 0.52% | L65: 289 | M65: 202909
A66: 64 | B66: litheli | C66: Litheli（品牌名） | D66: 0.54% | F66: 不相关 | G66: 0% | H66: 1.56% | I66: 0.78% | J66: 0.39% | K66: 0.26% | L66: 904 | M66: 60439
A67: 65 | B67: haarsauger | C67: 吸发器 | D67: 0.54% | F67: 不相关 | G67: 0% | H67: 1.56% | I67: 0.78% | J67: 0.39% | K67: 0.26% | L67: 184 | M67: 320398
A68: 66 | B68: nasssauger klein | C68: 小型湿式吸尘器 | D68: 0.54% | F68: 不相关 | G68: 0% | H68: 1.56% | I68: 0.78% | J68: 0.39% | K68: 0.26% | L68: 144 | M68: 405696
... A72: 70 | B72: couch reiniger | C72: 沙发清洁剂 | D72: 0.52% | F72: 不相关 | G72: 0% | H72: 0% | I72: 1.56% | J72: 3.13% | K72: 2.08% | L72: 549 | M72: 103370
A73: 71 | B73: vacmaster sca0801 | D73: 0.48% | F73: 不相关 | G73: 0% | H73: 0% | I73: 0.78% | J73: 3.91% | K73: 2.86% | L73: 329 | M73: 177403
A74: 72 | B74: rowenta x clean 10 | D74: 0.4% | F74: 不相关 | G74: 0% | H74: 0% | I74: 0.78% | J74: 3.13% | K74: 2.08% | L74: 549 | M74: 103370
A75: 73 | B75: spotclean hydrosteam | C75: spotclean hydrosteam | D75: 0.36% | F75: 不相关 | G75: 0% | H75: 0% | I75: 0% | J75: 3.91% | K75: 2.86% | L75: 709 | M75: 78704
A76: 74 | B76: couch reiniger gerät | C76: 沙发清洁设备 | D76: 0.34% | F76: 不相关 | G76: 0% | H76: 0% | I76: 0% | J76: 3.13% | K76: 4.17% | L76: 704 | M76: 79309
A77: 75 | B77: milbenspray für matratzen | C77: 床垫用除螨喷雾 | D77: 0.32% | F77: 不相关 | G77: 0% | H77: 0% | I77: 0% | J77: 3.52% | K77: 2.6% | L77: 1564 | M77: 33041
A78: 76 | B78: sofa reiniger gerät | C78: 沙发清洁设备 | D78: 0.31% | F78: 不相关 | G78: 0% | H78: 0% | I78: 0% | J78: 3.13% | K78: 3.13% | L78: 1314 | M78: 40094
A79: 77 | B79: polster reinigung gerät | C79: 垫子清洁设备 | D79: 0.3% | F79: 不相关 | G79: 0% | H79: 0% | I79: 0% | J79: 3.13% | K79: 2.86% | L79: 304 | M79: 192672
A80: 78 | B80: milbenspray | C80: 除螨喷雾 | D80: 0.29% | F80: 不相关 | G80: 0% | H80: 0% | I80: 0% | J80: 3.13% | K80: 2.34% | L80: 2649 | M80: 17920
A81: 79 | B81: anyson | C81: 任何儿子 | D81: 0.28% | F81: 不相关 | G81: 0% | H81: 0% | I81: 0% | J81: 3.13% | K81: 2.08% | L81: 2349 | M81: 20732
A82: 80 | B82: quilted northern | C82: 北方的棉被 | D82: 0.28% | F82: 不相关 | G82: 0% | H82: 0% | I82: 0% | J82: 3.13% | K82: 2.08% | L82: 344 | M82: 169457
A83: 81 | B83: uvo desinfektionsturm | C83: uvo 消毒塔 | D83: 0.26% | F83: 不相关 | G83: 0% | H83: 0% | I83: 0.78% | J83: 1.56% | K83: 1.04% | L83: 0 | M83: 0
A84: 82 | B84: vacuum steamer | C84: 真空蒸汽机 | D84: 0.25% | F84: 不相关 | G84: 0% | H84: 0% | I84: 0% | J84: 2.73% | K84: 2.08% | L84: 1299 | M84: 40628
A85: 83 | B85: dreame h15 pro | D85: 0.25% | F85: 不相关 | G85: 0% | H85: 0% | I85: 0% | J85: 2.73% | K85: 1.82% | L85: 1514 | M85: 34270
A86: 84 | B86: perobuno | C86: 佩罗布诺 | D86: 0.23% | F86: 不相关 | G86: 0% | H86: 0% | I86: 0% | J86: 2.34% | K86: 2.08% | L86: 0 | M86: 0
A87: 85 | B87: sofa | C87: 沙发 | D87: 0.23% | F87: 不相关 | G87: 0% | H87: 0% | I87: 0% | J87: 2.34% | K87: 2.08% | L87: 32911 | M87: 506
A88: 86 | B88: uwant b200 | C88: uwant b200 | D88: 0.22% | F88: 不相关 | G88: 0% | H88: 0% | I88: 0.78% | J88: 1.17% | K88: 0.78% | L88: 174 | M88: 338257
A89: 87 | B89: dyson milbensauger aufsatz | C89: 戴森除螨吸头 | D89: 0.22% | F89: 不相关 | G89: 0% | H89: 0% | I89: 0.78% | J89: 1.17% | K89: 0.78% | L89: 144 | M89: 405696
A90: 88 | B90: shark detect clean & empty | D90: 0.21% | F90: 不相关 | G90: 0% | H90: 0% | I90: 0% | J90: 2.34% | K90: 1.56% | L90: 304 | M90: 192672
A91: 89 | B91: sofa cleaner | C91: 沙发清洁剂 | D91: 0.2% | F91: 不相关 | G91: 0% | H91: 0% | I91: 0% | J91: 1.56% | K91: 2.86% | L91: 464 | M91: 123738
A92: 90 | B92: pink vacuum cleaner | C92: 粉色吸尘器 | D92: 0.18% | F92: 不相关 | G92: 0% | H92: 0% | I92: 0% | J92: 1.95% | K92: 1.3% | L92: 944 | M92: 57635
A93: 91 | B93: staubsauger wasserfilter | C93: 水过滤吸尘器 | D93: 0.17% | F93: 不相关 | G93: 0% | H93: 0% | I93: 0% | J93: 1.56% | K93: 2.08% | L93: 534 | M93: 106532
A94: 92 | B94: polsterreiniger gerät klein | D94: 0.17% | F94: 不相关 | G94: 0% | H94: 0% | I94: 0.78% | J94: 0.39% | K94: 0.78% | L94: 144 | M94: 405696
A95: 93 | B95: matratzen | C95: 床垫 | D95: 0.16% | F95: 不相关 | G95: 0% | H95: 0% | I95: 0.78% | J95: 0.39% | K95: 0.52% | L95: 3904 | M95: 11162
A96: 94 | B96: bissell fleckenreiniger | C96: bissell 去污剂 | D96: 0.16% | F96: 不相关 | G96: 0% | H96: 0% | I96: 0% | J96: 1.56% | K96: 1.82% | L96: 364 | M96: 159716
A97: 95 | B97: kroqo | D97: 0.15% | F97: 不相关 | G97: 0% | H97: 0% | I97: 0.78% | J97: 0.39% | K97: 0.26% | L97: 154 | M97: 380614
A98: 96 | B98: couch reinigen | C98: 清洁沙发 | D98: 0.15% | F98: 不相关 | G98: 0% | H98: 0% | I98: 0.78% | J98: 0.39% | K98: 0.26% | L98: 154 | M98: 380614
A99: 97 | B99: polster sauger | C99: 吸尘垫子 | D99: 0.15% | F99: 不相关 | G99: 0% | H99: 0% | I99: 0.78% | J99: 0.39% | K99: 0.26% | L99: 134 | M99: 434422
A100: 98 | B100: shark wv200eu | C100: 鲨鱼 wv200eu | D100: 0.15% | F100: 不相关 | G100: 0% | H100: 0% | I100: 0.78% | J100: 0.39% | K100: 0.26% | L100: 139 | M100: 419552
A101: 99 | B101: allergiker | C101: 过敏者 | D101: 0.15% | F101: 不相关 | G101: 0% | H101: 0% | I101: 0.78% | J101: 0.39% | K101: 0.26% | L101: 174 | M101: 338257
A102: 100 | B102: doppelzyklon | D102: 0.15% | F102: 不相关 | G102: 0% | H102: 0% | I102: 0.78% | J102: 0.39% | K102: 0.26% | L102: 144 | M102: 405696
A103: 101 | B103: reinigungsgeräte | C103: 清洁设备 | D103: 0.15% | F103: 不相关 | G103: 0% | H103: 0% | I103: 0.78% | J103: 0.39% | K103: 0.26% | L103: 184 | M103: 320398
A104: 102 | B104: teppich staubsauger | C104: 地毯吸尘器 | D104: 0.15% | F104: 不相关 | G104: 0% | H104: 0% | I104: 0.78% | J104: 0.39% | K104: 0.26% | L104: 254 | M104: 231563
A105: 103 | B105: dampfreiniger couch | C105: 沙发蒸汽清洁器 | D105: 0.15% | F105: 不相关 | G105: 0% | H105: 0% | I105: 0.78% | J105: 0.39% | K105: 0.26% | L105: 239 | M105: 246305
A106: 104 | B106: mini henry hoover | C106: 迷你亨利吸尘器 | D106: 0.15% | F106: 不相关 | G106: 0% | H106: 0% | I106: 0.78% | J106: 0.39% | K106: 0.26% | L106: 219 | M106: 269187
A107: 105 | B107: dampfreiniger für polstermöbel | C107: 软垫家具用蒸汽清洁器 | D107: 0.15% | F107: 不相关 | G107: 0% | H107: 0% | I107: 0.78% | J107: 0.39% | K107: 0.26% | L107: 179 | M107: 329044
A108: 106 | B108: flöhe im bett bekämpfen | C108: 消灭床上的跳蚤 | D108: 0.15% | F108: 不相关 | G108: 0% | H108: 0% | I108: 0.78% | J108: 0.39% | K108: 0.26% | L108: 299 | M108: 195944
A109: 107 | B109: pureprotect mini 900 series | D109: 0.15% | F109: 不相关 | G109: 0% | H109: 0% | I109: 0.78% | J109: 0.39% | K109: 0.26% | L109: 254 | M109: 231563
A110: 108 | B110: dupray steam cleaner | C110: dupray 蒸汽清洁器 | D110: 0.14% | F110: 不相关 | G110: 0% | H110: 0% | I110: 0% | J110: 1.17% | K110: 2.08% | L110: 504 | M110: 113311
A111: 109 | B111: haushof waschsauger | C111: Haushof 洗地机 | D111: 0.12% | F111: 不相关 | G111: 0% | H111: 0% | I111: 0% | J111: 0% | K111: 4.17% | L111: 2204 | M111: 22302
A112: 110 | B112: hover air x1 drohne | C112: hover air x1 无人机 | D112: 0.11% | F112: 不相关 | G112: 0% | H112: 0% | I112: 0% | J112: 1.17% | K112: 0.78% | L112: 444 | M112: 129581
A113: 111 | B113: shark stain striker | C113: 鲨鱼污渍清洁剂 | D113: 0.11% | F113: 不相关 | G113: 0% | H113: 0% | I113: 0% | J113: 0.78% | K113: 1.82% | L113: 1334 | M113: 39406
A114: 112 | B114: neakasa magic 1 vacuum steamer | D114: 0.11% | F114: 不相关 | G114: 0% | H114: 0% | I114: 0% | J114: 1.17% | K114: 0.78% | L114: 849 | M114: 64701
A115: 113 | B115: staub entferner | C115: staub 清洁剂 | D115: 0.09% | F115: 不相关 | G115: 0% | H115: 0% | I115: 0% | J115: 0.39% | K115: 2.08% | L115: 329 | M115: 177403
...

Sheet 1.2 以词拓词（词根法）
A1: 以词拓词导出_2023-08-25 词根: milbensauger
A2: # | B2: 关键词 | C2: 中文名字 | D2: 匹配模式 | E2: 搜索量 | F2: 排名 | G2: 相关性-手动
A3: 1 | B3: milbensauger | C3: 除螨吸尘器 | D3: 精准匹配 | E3: 49183 | F3: 2230 | G3: 高相干性
A4: 2 | B4: milbensauger für matratzen | C4: 床垫用除螨吸尘器 | D4: 词组匹配,下拉框匹配 | E4: 24649 | F4: 6107 | G4: 高相干性
A5: 3 | B5: milbensauger mit uv licht | C5: 带紫外线的除螨吸尘器 | D5: 词组匹配,下拉框匹配 | E5: 4514 | F5: 48570 | G5: 高相干性
A6: 4 | B6: jimmy jv35 milbensauger | C6: 吉米 JV35 除螨吸尘器 | D6: 词组匹配 | E6: 2814 | F6: 81546 | G6: 高相干性
A7: 5 | B7: hoover milbensauger | C7: 胡佛除螨吸尘器 | D7: 词组匹配 | E7: 2664 | F7: 86495 | G7: 高相干性
A8: 6 | B8: milbensauger für matratzen testsieger | C8: 床垫用除螨吸尘器测试冠军 | D8: 词组匹配,下拉框匹配 | E8: 2144 | F8: 109170 | G8: 高相干性
A9: 7 | B9: hoover ultra vortex milbensauger | C9: hoover ultra vortex 除螨吸尘器 | D9: 词组匹配 | E9: 1489 | F9: 160697 | G9: 高相干性
A10: 8 | B10: milbensauger | C10: 品类词 除螨仪 | E10: 49183 | F10: 2230 | G10: 高相干性
A11: 9
A12: 10
A13: 11
A14: 12
A15: 13
A16: 14
A17: 15
A18: 16
A19: 17
A20: 18
A21: 19
A22: 20
... A2414: 2412

Sheet 1.3品类拓词法
A1: 品类拓词导出 | N1: milbensauger
A2: # | B2: 关键词 | C2: 搜索量 | D2: 排名 | E2: 相关性-手动 | L2: 排名 | M2: 相关性-手动
A3: 1 | B3: sofareiniger waschsauger | C3: 洗吸一体沙发清洁机 | D3: 1249 | E3: 192640
A4: 2 | B4: dampfreiniger sofa | C4: 蒸汽清洁器 沙发 | D4: 1249 | E4: 192640
A5: 3 | B5: textilreiniger sofa | C5: 沙发纺织清洁剂 | D5: 1249 | E5: 192640
A6: 4 | B6: wasserstaubsauger hyla alternative | C6: Hyla水过滤吸尘器替代品 | D6: 1264 | E6: 190291
A7: 5 | B7: matratzenreiniger gerät | C7: 床垫清洁设备 | D7: 1284 | E7: 187252 | M7: 弱相关
A8: 6 | B8: couchreiniger | C8: 沙发清洁剂 | D8: 1289 | E8: 186501
A9: 7 | B9: avuso luminex | C9: avuso luminex | D9: 1459 | E9: 164157 | M9: 弱相关
A10: 8 | B10: hoover ultra vortex milbensauger | C10: hoover ultra vortex 除螨吸尘器 | D10: 1489 | E10: 160697 | M10: 强
A11: 9 | B11: polster reinigung gerät | C11: 垫子清洁设备 | D11: 1639 | E11: 145285
A12: 10 | B12: matratzen reiniger | C12: 床垫清洁剂 | D12: 1664 | E12: 142994 | M12: 强
A13: 11 | B13: polstersauger nass | C13: 湿式软垫吸尘器 | D13: 1724 | E13: 137760 | M13: 不相关
A14: 12 | B14: tepichreinigungsmaschine | C14: 地毯清洁机 | D14: 1779 | E14: 133271
A15: 13 | B15: nassreiniger polstermöbel | C15: 软垫家具湿式清洁器 | D15: 1844 | E15: 128289 | M15: 不相关，品牌词
A16: 14 | B16: sofareiniger | C16: 沙发清洁剂 | D16: 1854 | E16: 127540 | M16: 不相关，品牌词
A17: 15 | B17: jimmy | C17: 吉米 | D17: 1874 | E17: 126067
A18: 16 | B18: waschsauger polster | C18: 软垫洗涤吸尘器 | D18: 2009 | E18: 116986
A19: 17 | B19: milben | C19: 螨虫 | D19: 2124 | E19: 110246
A20: 18 | B20: milbensauger für matratzen testsieger | C20: 床垫用除螨吸尘器测试冠军 | D20: 2144 | E20: 109170
A21: 19 | B21: polster dampfreiniger | C21: 软垫蒸汽清洁器 | D21: 2154 | E21: 108626 | M21: 不相关
A22: 20 | B22: akku polsterreiniger | C22: 电池软垫清洁机 | D22: 2229 | E22: 104666
A23: 21 | B23: ambiano polsterreinigungsgerät | C23: 0 | D23: 2534 | E23: 91179
A24: 22 | B24: vivenso wasserstaubsauger - luftreiniger | C24: vivenso 水吸尘器 - 空气净化器 | D24: 2569 | E24: 89844 | M24: 不相关
A25: 23 | B25: milbenstaubsauger | C25: 除螨吸尘器 | D25: 2604 | E25: 88569 | M25: 不相关
A26: 24 | B26: couch reiniger | C26: 沙发清洁剂 | D26: 2609 | E26: 88374
A27: 25 | B27: couch reiniger gerät | C27: 沙发清洁设备 | D27: 2649 | E27: 86985
A28: 26 | B28: hoover milbensauger | C28: 胡佛除螨吸尘器 | D28: 2664 | E28: 86495
A29: 27 | B29: jimmy jv35 milbensauger | C29: 吉米 JV35 除螨吸尘器 | D29: 2814 | E29: 81546
A30: 28 | B30: polster und teppichreiniger gerät | C30: 垫子和地毯清洁设备 | D30: 2829 | E30: 81073 | M30: 强
A31: 29 | B31: vivenso | C31: 维文索 | D31: 2924 | E31: 78204
A32: 30 | B32: polstersauger | C32: 软垫吸尘器 | D32: 3069 | E32: 74278
A33: 31 | B33: hoover | C33: 胡佛 | D33: 3159 | E33: 72025
A34: 32 | B34: ryer nasssauger reinigung teppich und kauqe reinigung | C34: 0 | D34: 3184 | E34: 71407 | M34: 强
A35: 33 | B35: hyla staubsauger | C35: hyla 吸尘器 | D35: 3819 | E35: 58420
A36: 34 | B36: matratzenreiniger | C36: 床垫清洁剂 | D36: 3889 | E36: 57237 | M36: 强
A37: 35 | B37: sofa reiniger | C37: 沙发清洁剂 | D37: 4234 | E37: 52119
A38: 36 | B38: milbensauger mit uv licht | C38: 带紫外线的除螨吸尘器 | D38: 4514 | E38: 48570
A39: 37 | B39: nass trockensauger polsterreiniger | C39: 软垫清洁湿干两用吸尘器 | D39: 4759 | E39: 45832
A40: 38 | B40: milbenspray für matratzen | C40: 床垫用除螨喷雾 | D40: 4884 | E40: 44574
A41: 39 | B41: sofa reiniger gerät | C41: 沙发清洁设备 | D41: 5439 | E41: 39525
A42: 40 | B42: polsterreiniger sofa | C42: 沙发软垫清洁剂 | D42: 5629 | E42: 38054
A43: 41 | B43: polsterreinigungsgerät | C43: 软垫清洁设备 | D43: 6639 | E43: 31506
A44: 42 | B44: dampfreiniger polstermöbel | C44: 蒸汽清洁器 软垫家具 | D44: 7279 | E44: 28320
A45: 43 | B45: wasserstaubsauger | C45: 水过滤吸尘器 | D45: 8439 | E45: 23877
A46: 44 | B46: hyla | C46: 海拉 | D46: 8849 | E46: 22655
A47: 45 | B47: hyla wasserstaubsauger | C47: hyla 水吸尘器 | D47: 13504 | E47: 13619
A48: 46 | B48: milbensauger für matratzen | C48: 床垫用除螨吸尘器 | D48: 24649 | E48: 6107
... A54: 52 | B54: jigoo milbensauger | C54: 吉戈除螨吸尘器 | D54: 0 | E54: 0
A55: 53 | B55: jigoo t600 milbensauger | C55: 0 | D55: 0 | E55: 0
A56: 54 | B56: mattress cleaner | C56: 床垫清洁剂 | D56: 0 | E56: 0
A57: 55 | B57: milbenreiniger für matratzen | C57: 床垫用除螨清洁剂 | D57: 0 | E57: 0
A58: 56 | B58: milbensauger jigoo | C58: 0 | D58: 0 | E58: 0
A59: 57 | B59: polsterreiniger gerät klein | C59: 0 | D59: 0 | E59: 0
A60: 58 | B60: sofa staubsauger | C60: 沙发吸尘器 | D60: 0 | E60: 0
A61: 59 | B61: avuso detect milbensauger | C61: 0 | D61: 0 | E61: 0
A62: 60 | B62: bed vacuum cleaner | C62: 床用吸尘器 | D62: 0 | E62: 0
A63: 61 | B63: bett staubsauger | C63: 床吸尘器 | D63: 0 | E63: 0
A64: 62 | B64: bettsauger milben | C64: 床螨吸尘器 | D64: 0 | E64: 0
A65: 63 | B65: clean air pro milbensauger | C65: 0 | D65: 0 | E65: 0
A66: 64 | B66: cleanmaxx milbensauger | C66: cleanmaxx 螨虫吸尘器 | D66: 0 | E66: 0
A67: 65 | B67: dust mite vacuum cleaner | C67: 除螨吸尘器 | D67: 0 | E67: 0
A68: 66 | B68: hausstaubmilbe bekämpfen | C68: 对抗尘螨 | D68: 0 | E68: 0
A69: 67 | B69: hausstaubmilben bekämpfen | C69: 对抗尘螨 | D69: 0 | E69: 0
A70: 68 | B70: hausstaubmilben sauger | C70: 防尘螨吸尘器 | D70: 0 | E70: 0
A71: 69 | B71: hochfrequenz milbenreiniger | C71: 高频螨虫清洁器 | D71: 0 | E71: 0
A72: 70 | B72: hoover ultra vortex | C72: 胡佛超旋风 | D72: 0 | E72: 0
A73: 71 | B73: hoover ultra vortex milbensauger mit uv-licht | C73: hoover ultra vortex 带紫外线的除螨吸尘器 | D73: 0 | E73: 0
A74: 72 | B74: jimmy bx7 pro | C74: 吉米bx7 pro | D74: 0 | E74: 0
A75: 73 | B75: jimmy jv35 | C75: 吉米 JV35 | D75: 0 | E75: 0
A76: 74 | B76: jimmy milbensauger | C76: 吉米 除螨吸尘器 | D76: 0 | E76: 0
A77: 75 | B77: matratzen reiniger gerät | C77: 床垫清洁设备 | D77: 0 | E77: 0
... A90: 88 | B90: milbensauger akku | C90: 电池供电除螨吸尘器 | D90: 0 | E90: 0
A91: 89 | B91: milbensauger für matratzen mit akku | C91: 0 | D91: 0 | E91: 0
A92: 90 | B92: milbensauger hoover | C92: Hoover除螨吸尘器 | D92: 0 | E92: 0
A93: 91 | B93: milbensauger jimmy | C93: Jimmy除螨吸尘器 | D93: 0 | E93: 0
A94: 92 | B94: milbensauger jimmy jv35 | C94: Jimmy JV35除螨吸尘器 | D94: 0 | E94: 0
A95: 93 | B95: milbensauger kabellos | C95: 无线除螨吸尘器 | D95: 0 | E95: 0
A96: 94 | B96: milbensauger mit wasser | C96: 水过滤除螨吸尘器 | D96: 0 | E96: 0
A97: 95 | B97: milbensauger nasssauger | C97: 湿式除螨吸尘器 | D97: 0 | E97: 0
A98: 96 | B98: milbensauger silvercrest | C98: Silvercrest除螨吸尘器 | D98: 0 | E98: 0
A99: 97 | B99: milbensauger testsieger | C99: 除螨吸尘器测试冠军 | D99: 0 | E99: 0
A100: 98 | B100: milbenstaubsauger für matratzen | C100: 床垫用除螨吸尘器 | D100: 0 | E100: 0
A101: 99 | B101: milbenstaubsauger testsieger | C101: 除螨吸尘器测试冠军 | D101: 0 | E101: 0
A102: 100 | B102: mini staubsauger bett | C102: 0 | D102: 0 | E102: 0
A103: 101 | B103: mite vacuum cleaner | C103: 除螨吸尘器 | D103: 0 | E103: 0
A104: 102 | B104: nooro milbensauger | C104: 0 | D104: 0 | E104: 0
A105: 103 | B105: nooroa deep vac | C105: nooroa deep vac | D105: 0 | E105: 0
A106: 104 | B106: polsterreiniger auto gerät | C106: 汽车软垫清洁设备 | D106: 0 | E106: 0
A107: 105 | B107: polsterreiniger sofa gerät | C107: 沙发软垫清洁设备 | D107: 0 | E107: 0
A108: 106 | B108: powercleany handstaubsauger der stärkste | C108: PowerCleany最强手持吸尘器 | D108: 0 | E108: 0
A109: 107 | B109: powercleany ultraviolett staubsauger | C109: 0 | D109: 0 | E109: 0
A110: 108 | B110: quilted northern handstaubsauger | C110: 绗缝北方手持吸尘器 | D110: 0 | E110: 0
A111: 109 | B111: silvercrest milbensauger | C111: 银尔克螨虫吸尘器 | D111: 0 | E111: 0
A112: 110 | B112: sofa sauger | C112: 沙发吸尘器 | D112: 0 | E112: 0
A113: 111 | B113: staubsauger milben | C113: 螨虫吸尘器 | D113: 0 | E113: 0
A114: 112 | B114: bissell little green multi-purpose portable carpet and upholstery cleaner, 1400b | C114: bissell小绿多功能便携式地毯和家具清洁器，1400b | D114: 0 | E114: 0
A115: 113 | B115: bissell polsterreinigungsgerät | C115: 必胜软垫清洁设备 | D115: 0 | E115: 0
A116: 114 | B116: dampfreiniger couch | C116: 沙发蒸汽清洁器 | D116: 0 | E116: 0
A117: 115 | B117: dampfreiniger matratze | C117: 蒸汽清洁器 床垫 | D117: 0 | E117: 0
...

Sheet 2. 竞品拓词结果表
A1: milbensauger 关键词库 | Q1: 竞品拓词导出_2025-08-07 ASIN:B0DXKCZD5Z,B0DXQ34XZN,B0FHPRKP7F,B0F8VQ2Q6H,B0DJ9CSK63,B0F3JGRDBP,B0F32MV4J3,B0DJFMT6LS,B0CXCQR22Z,B0FCM61WRD,B0C1C73WS9,B0F187FF99,B0CDP5V9W8,B0DJ2YVV6F,B0DXPSYS1N,B0F2H6YTVS,B0F9W71RQQ,B0F7RDTSDF,B0F1YKY242,B0DCTPQLK2,B0F917NVW9,B0F9XTZDGW,B0CKVFMYH4,B0FFSTYXML,B0FH1K5PGW,B0D9NGRD9M,B0D45V1YXT,B0F484XM47
A2: # | B2: 关键词 | C2: 中文品名 | D2: 相关性-自动百分比 | E2: 相关性-自动 | F2: 自然位前4占位率 | G2: 自然位前8占位率 | H2: 自然位前16占位率 | I2: 自然位前32占位率 | J2: 自然位前48占位率 | K2: 搜索量 | L2: 排名 | M2: 流量大小 | N2: 相关性手动 | O2: 修饰词类型 | P2: 搜索转化率 | Q2: 搜索转化率 | R2: 360商品搜索量大小
A3: 1 | B3: jml go vac | C3: JML Go Vac吸尘器 | D3: 0.6173 | E3: 高相关 | F3: 0.7188 | G3: 0.5938 | H3: 0.4766 | I3: 0.4102 | J3: 0.3099 | K3: 1025 | L3: 43518 | M3: =K3 -> 1025 | N3: =E3 -> 高相关 | O3: 场景词 | P3: =VLOOKUP(B3,'附表-搜索转化率'!A:F,6,FALSE) -> #N/A | Q3: =IFERROR(P3,"-") -> - | R3: =IFERROR(VLOOKUP(B3,'附表-搜索转化率'!A:B,2,FALSE),"-") -> -
A4: 2 | B4: mini car hoover | C4: 迷你车吸尘器 | D4: 0.6092 | E4: 高相关 | F4: 0.75 | G4: 0.6094 | H4: 0.3438 | I4: 0.3047 | J4: 0.2995 | K4: 380 | L4: 125464 | M4: =K4 -> 380 | N4: =E4 -> 高相关 | O4: 产品词 | P4: =VLOOKUP(B4,'附表-搜索转化率'!A:F,6,FALSE) -> #N/A | Q4: =IFERROR(P4,"-") -> - | R4: =IFERROR(VLOOKUP(B4,'附表-搜索转化率'!A:B,2,FALSE),"-") -> -
A5: 3 | B5: mini vacuum cleaner cordless | C5: 迷你无绳吸尘器 | D5: 0.5826 | E5: 高相关 | F5: 0.7188 | G5: 0.4688 | H5: 0.4844 | I5: 0.3477 | J5: 0.3021 | K5: 1225 | L5: 36062 | M5: =K5 -> 1225 | N5: =E5 -> 高相关 | O5: 受众词 | P5: =VLOOKUP(B5,'附表-搜索转化率'!A:F,6,FALSE) -> 0.0196 | Q5: =IFERROR(P5,"-") -> 0.0196 | R5: =IFERROR(VLOOKUP(B5,'附表-搜索转化率'!A:B,2,FALSE),"-") -> 35791
A6: 4 | B6: car hoover cordless | C6: 无线汽车吸尘器 | D6: 0.5416 | E6: 高相关 | F6: 0.625 | G6: 0.5 | H6: 0.4453 | I6: 0.375 | J6: 0.3698 | K6: 503 | L6: 93422 | M6: =K6 -> 503 | N6: =E6 -> 高相关 | O6: 配件词 | P6: =VLOOKUP(B6,'附表-搜索转化率'!A:F,6,FALSE) -> #N/A | Q6: =IFERROR(P6,"-") -> - | R6: =IFERROR(VLOOKUP(B6,'附表-搜索转化率'!A:B,2,FALSE),"-") -> -
A7: 5 | B7: car vacuum | C7: 汽车吸尘器 | D7: 0.5381 | E7: 高相关 | F7: 0.5938 | G7: 0.5469 | H7: 0.4844 | I7: 0.332 | J7: 0.2865 | K7: 1825 | L7: 23157 | M7: =K7 -> 1825 | N7: =E7 -> 高相关 | O7: 尺寸词 | P7: =VLOOKUP(B7,'附表-搜索转化率'!A:F,6,FALSE) -> 0.0148 | Q7: =IFERROR(P7,"-") -> 0.0148 | R7: =IFERROR(VLOOKUP(B7,'附表-搜索转化率'!A:B,2,FALSE),"-") -> 109696
A8: 6 | B8: mini vacuum | C8: 迷你吸尘器 | D8: 0.5219 | E8: 高相关 | F8: 0.5625 | G8: 0.5625 | H8: 0.4922 | I8: 0.2734 | J8: 0.2344 | K8: 903 | L8: 49946 | M8: =K8 -> 903 | N8: =E8 -> 高相关 | O8: 尺寸词 | P8: =VLOOKUP(B8,'附表-搜索转化率'!A:F,6,FALSE) -> #N/A | Q8: =IFERROR(P8,"-") -> - | R8: =IFERROR(VLOOKUP(B8,'附表-搜索转化率'!A:B,2,FALSE),"-") -> -
A9: 7 | B9: cordless car vacuum cleaner | C9: 无线汽车吸尘器 | D9: 0.5205 | E9: 高相关 | F9: 0.5 | G9: 0.6094 | H9: 0.5547 | I9: 0.3594 | J9: 0.3281 | K9: 890 | L9: 50748 | M9: =K9 -> 890 | N9: =E9 -> 高相关 | O9: 无关词 | P9: =VLOOKUP(B9,'附表-搜索转化率'!A:F,6,FALSE) -> #N/A | Q9: =IFERROR(P9,"-") -> - | R9: =IFERROR(VLOOKUP(B9,'附表-搜索转化率'!A:B,2,FALSE),"-") -> -
A10: 8 | B10: car hoover powerful | C10: 强力汽车吸尘器 | D10: 0.5184 | E10: 高相关 | F10: 0.5 | G10: 0.5313 | H10: 0.6172 | I10: 0.457 | J10: 0.3672 | K10: 354 | L10: 134806 | M10: =K10 -> 354 | N10: =E10 -> 高相关 | O10: 不相关词 | P10: =VLOOKUP(B10,'附表-搜索转化率'!A:F,6,FALSE) -> #N/A | Q10: =IFERROR(P10,"-") -> - | R10: =IFERROR(VLOOKUP(B10,'附表-搜索转化率'!A:B,2,FALSE),"-") -> -
A11: 9 | B11: car vacuum cleaner cordless powerful | C11: 无线强力汽车吸尘器 | D11: 0.5161 | E11: 高相关 | F11: 0.5313 | G11: 0.5313 | H11: 0.5234 | I11: 0.4102 | J11: 0.3464 | K11: 1935 | L11: 21618 | M11: =K11 -> 1935 | N11: =E11 -> 高相关 | O11: NA | P11: =VLOOKUP(B11,'附表-搜索转化率'!A:F,6,FALSE) -> 0.0162 | Q11: =IFERROR(P11,"-") -> 0.0162 | R11: =IFERROR(VLOOKUP(B11,'附表-搜索转化率'!A:B,2,FALSE),"-") -> 68512
A12: 10 | B12: car hoovers cordless powerful | C12: 无线强力汽车吸尘器 | D12: 0.5154 | E12: 高相关 | F12: 0.5313 | G12: 0.4844 | H12: 0.5703 | I12: 0.4609 | J12: 0.362 | K12: 3161 | L12: 12203 | M12: =K12 -> 3161 | N12: =E12 -> 高相关 | O12: 功能词 | P12: =VLOOKUP(B12,'附表-搜索转化率'!A:F,6,FALSE) -> 0.0275 | Q12: =IFERROR(P12,"-") -> 0.0275 | R12: =IFERROR(VLOOKUP(B12,'附表-搜索转化率'!A:B,2,FALSE),"-") -> 133015
A13: 11 | B13: mini vacuum cleaner | C13: 迷你吸尘器 | D13: 0.4978 | E13: 中相关 | F13: 0.5 | G13: 0.5469 | H13: 0.4922 | I13: 0.3828 | J13: 0.349 | K13: 683 | L13: 67422 | M13: =K13 -> 683 | N13: =E13 -> 中相关 | O13: 尺寸词 | P13: =VLOOKUP(B13,'附表-搜索转化率'!A:F,6,FALSE) -> #N/A | Q13: =IFERROR(P13,"-") -> - | R13: =IFERROR(VLOOKUP(B13,'附表-搜索转化率'!A:B,2,FALSE),"-") -> -
A14: 12 | B14: car vacuum cleaner | C14: 车用吸尘器 | D14: 0.4955 | E14: 中相关 | F14: 0.5313 | G14: 0.5 | H14: 0.4531 | I14: 0.3906 | J14: 0.3177 | K14: 9851 | L14: 2688 | M14: =K14 -> 9851 | N14: =E14 -> 中相关 | O14: 不相关词 | P14: =VLOOKUP(B14,'附表-搜索转化率'!A:F,6,FALSE) -> 0.0146 | Q14: =IFERROR(P14,"-") -> 0.0146 | R14: =IFERROR(VLOOKUP(B14,'附表-搜索转化率'!A:B,2,FALSE),"-") -> 455206
... A29: 27 | B29: small vacuum | C29: 小型吸尘器 | D29: 0.3012 | E29: 中相关 | F29: 0.3125 | G29: 0.3438 | H29: 0.2266 | I29: 0.2539 | J29: 0.2422 | K29: 393 | L29: 121159 | M29: =K29 -> 393 | N29: =E29 -> 中相关 | O29: 尺寸词 | P29: =VLOOKUP(B29,'附表-搜索转化率'!A:F,6,FALSE) -> #N/A | Q29: =IFERROR(P29,"-") -> - | R29: =IFERROR(VLOOKUP(B29,'附表-搜索转化率'!A:B,2,FALSE),"-") -> -
A30: 28 | B30: portable hoover | C30: 便携式吸尘器 | D30: 0.2994 | E30: 中相关 | F30: 0.25 | G30: 0.3438 | H30: 0.3828 | I30: 0.3242 | J30: 0.2786 | K30: 845 | L30: 53677 | M30: =K30 -> 845 | N30: =E30 -> 中相关 | P30: =VLOOKUP(B30,'附表-搜索转化率'!A:F,6,FALSE) -> #N/A | Q30: =IFERROR(P30,"-") -> - | R30: =IFERROR(VLOOKUP(B30,'附表-搜索转化率'!A:B,2,FALSE),"-") -> -
A31: 29 | B31: hand held hoovers cordless | C31: 无线手持吸尘器 | D31: 0.2888 | E31: 中相关 | F31: 0.25 | G31: 0.3594 | H31: 0.3203 | I31: 0.2656 | J31: 0.2448 | K31: 1045 | L31: 42673 | M31: =K31 -> 1045 | N31: =E31 -> 中相关 | P31: =VLOOKUP(B31,'附表-搜索转化率'!A:F,6,FALSE) -> #N/A | Q31: =IFERROR(P31,"-") -> - | R31: =IFERROR(VLOOKUP(B31,'附表-搜索转化率'!A:B,2,FALSE),"-") -> -
A32: 30 | B32: handheld hoover cordless | C32: 无线手持式吸尘器 | D32: 0.2573 | E32: 中相关 | F32: 0.2188 | G32: 0.3125 | H32: 0.3125 | I32: 0.2344 | J32: 0.2161 | K32: 683 | L32: 67422 | M32: =K32 -> 683 | N32: =E32 -> 中相关 | P32: =VLOOKUP(B32,'附表-搜索转化率'!A:F,6,FALSE) -> #N/A | Q32: =IFERROR(P32,"-") -> - | R32: =IFERROR(VLOOKUP(B32,'附表-搜索转化率'!A:B,2,FALSE),"-") -> -
A33: 31 | B33: hand held hoover | C33: 手持吸尘器 | D33: 0.2468 | E33: 中相关 | F33: 0.2188 | G33: 0.2813 | H33: 0.2891 | I33: 0.2461 | J33: 0.2187 | K33: 1922 | L33: 21781 | M33: =K33 -> 1922 | N33: =E33 -> 中相关 | O33: 尺寸词 | P33: =VLOOKUP(B33,'附表-搜索转化率'!A:F,6,FALSE) -> 0.0248 | Q33: =IFERROR(P33,"-") -> 0.0248 | R33: =IFERROR(VLOOKUP(B33,'附表-搜索转化率'!A:B,2,FALSE),"-") -> 75659
A34: 32 | B34: portable vacuum cleaner | C34: 便携式吸尘器 | D34: 0.2318 | E34: 中相关 | F34: 0.0938 | G34: 0.3438 | H34: 0.4219 | I34: 0.3594 | J34: 0.3516 | K34: 432 | L34: 109761 | M34: =K34 -> 432 | N34: =E34 -> 中相关 | P34: =VLOOKUP(B34,'附表-搜索转化率'!A:F,6,FALSE) -> #N/A | Q34: =IFERROR(P34,"-") -> - | R34: =IFERROR(VLOOKUP(B34,'附表-搜索转化率'!A:B,2,FALSE),"-") -> -
A35: 33 | B35: handheld hoover | C35: 手持式吸尘器 | D35: 0.2195 | E35: 中相关 | F35: 0.125 | G35: 0.3438 | H35: 0.2969 | I35: 0.2656 | J35: 0.263 | K35: 3148 | L35: 12264 | M35: =K35 -> 3148 | N35: =E35 -> 中相关 | O35: 尺寸词 | P35: =VLOOKUP(B35,'附表-搜索转化率'!A:F,6,FALSE) -> 0.0243 | Q35: =IFERROR(P35,"-") -> 0.0243 | R35: =IFERROR(VLOOKUP(B35,'附表-搜索转化率'!A:B,2,FALSE),"-") -> 109751
A36: 34 | B36: handheld vacuum | C36: 手持吸尘器 | D36: 0.217 | E36: 中相关 | F36: 0.2188 | G36: 0.25 | H36: 0.1797 | I36: 0.1797 | J36: 0.1875 | K36: 1561 | L36: 27634 | M36: =K36 -> 1561 | N36: =E36 -> 中相关 | P36: =VLOOKUP(B36,'附表-搜索转化率'!A:F,6,FALSE) -> 0.0143 | Q36: =IFERROR(P36,"-") -> 0.0143 | R36: =IFERROR(VLOOKUP(B36,'附表-搜索转化率'!A:B,2,FALSE),"-") -> 83977
A37: 35 | B37: handheld vacuums | C37: 手持吸尘器 | D37: 0.2126 | E37: 中相关 | F37: 0.1875 | G37: 0.2344 | H37: 0.2656 | I37: 0.1992 | J37: 0.2161 | K37: 1787 | L37: 23757 | M37: =K37 -> 1787 | N37: =E37 -> 中相关 | P37: =VLOOKUP(B37,'附表-搜索转化率'!A:F,6,FALSE) -> 0.0082 | Q37: =IFERROR(P37,"-") -> 0.0082 | R37: =IFERROR(VLOOKUP(B37,'附表-搜索转化率'!A:B,2,FALSE),"-") -> 100456
A38: 36 | B38: handheld vacuum cleaner cordless | C38: 手持吸尘器无线 | D38: 0.201 | E38: 中相关 | F38: 0.125 | G38: 0.25 | H38: 0.2969 | I38: 0.3164 | J38: 0.3099 | K38: 1277 | L38: 34452 | M38: =K38 -> 1277 | N38: =E38 -> 中相关 | P38: =VLOOKUP(B38,'附表-搜索转化率'!A:F,6,FALSE) -> 0.0172 | Q38: =IFERROR(P38,"-") -> 0.0172 | R38: =IFERROR(VLOOKUP(B38,'附表-搜索转化率'!A:B,2,FALSE),"-") -> 38290
A39: 37 | B39: handheld vacuum cleaner | C39: 手持吸尘器 | D39: 0.191 | E39: 低相关 | F39: 0.125 | G39: 0.2344 | H39: 0.2969 | I39: 0.2617 | J39: 0.2344 | K39: 9677 | L39: 2772 | M39: =K39 -> 9677 | N39: =E39 -> 低相关 | P39: =VLOOKUP(B39,'附表-搜索转化率'!A:F,6,FALSE) -> 0.0197 | Q39: =IFERROR(P39,"-") -> 0.0197 | R39: =IFERROR(VLOOKUP(B39,'附表-搜索转化率'!A:B,2,FALSE),"-") -> 717259
A40: 38 | B40: hand vacuum cleaner cordless | C40: 无线手持吸尘器 | D40: 0.1846 | E40: 低相关 | F40: 0.125 | G40: 0.2656 | H40: 0.2188 | I40: 0.2461 | J40: 0.1901 | K40: 1187 | L40: 37323 | M40: =K40 -> 1187 | N40: =E40 -> 低相关 | P40: =VLOOKUP(B40,'附表-搜索转化率'!A:F,6,FALSE) -> 0.0245 | Q40: =IFERROR(P40,"-") -> 0.0245 | R40: =IFERROR(VLOOKUP(B40,'附表-搜索转化率'!A:B,2,FALSE),"-") -> 53076
A41: 39 | B41: hand held vacuum cordless | C41: 无线手持吸尘器 | D41: 0.1748 | E41: 低相关 | F41: 0.1563 | G41: 0.1719 | H41: 0.2031 | I41: 0.2188 | J41: 0.2656 | K41: 6670 | L41: 4697 | M41: =K41 -> 6670 | N41: =E41 -> 低相关 | P41: =VLOOKUP(B41,'附表-搜索转化率'!A:F,6,FALSE) -> 0.022 | Q41: =IFERROR(P41,"-") -> 0.022 | R41: =IFERROR(VLOOKUP(B41,'附表-搜索转化率'!A:B,2,FALSE),"-") -> 410982
A42: 40 | B42: cordless handheld vacuum cleaner | C42: 无线手持吸尘器 | D42: 0.1744 | E42: 低相关 | F42: 0.0938 | G42: 0.2188 | H42: 0.2969 | I42: 0.293 | J42: 0.2604 | K42: 819 | L42: 55576 | M42: =K42 -> 819 | N42: =E42 -> 低相关 | P42: =VLOOKUP(B42,'附表-搜索转化率'!A:F,6,FALSE) -> #N/A | Q42: =IFERROR(P42,"-") -> - | R42: =IFERROR(VLOOKUP(B42,'附表-搜索转化率'!A:B,2,FALSE),"-") -> -
A43: 41 | B43: car gadget | C43: 汽车小工具 | D43: 0.1684 | E43: 低相关 | F43: 0.25 | G43: 0.125 | H43: 0.0625 | I43: 0.0313 | J43: 0.0208 | K43: 0 | L43: 0 | M43: =K43 -> 0 | N43: =E43 -> 低相关 | P43: =VLOOKUP(B43,'附表-搜索转化率'!A:F,6,FALSE) -> #N/A | Q43: =IFERROR(P43,"-") -> - | R43: =IFERROR(VLOOKUP(B43,'附表-搜索转化率'!A:B,2,FALSE),"-") -> -
A44: 42 | B44: cordless vacuum cleaner handheld | C44: 无线手持吸尘器 | D44: 0.163 | E44: 低相关 | F44: 0.0313 | G44: 0.2344 | H44: 0.4063 | I44: 0.2813 | J44: 0.2734 | K44: 458 | L44: 103225 | M44: =K44 -> 458 | N44: =E44 -> 低相关 | P44: =VLOOKUP(B44,'附表-搜索转化率'!A:F,6,FALSE) -> #N/A | Q44: =IFERROR(P44,"-") -> - | R44: =IFERROR(VLOOKUP(B44,'附表-搜索转化率'!A:B,2,FALSE),"-") -> -
A45: 43 | B45: handheld cordless vacuum cleaner | C45: 手持无线吸尘器 | D45: 0.1589 | E45: 低相关 | F45: 0.0938 | G45: 0.1875 | H45: 0.2813 | I45: 0.2383 | J45: 0.2083 | K45: 380 | L45: 125464 | M45: =K45 -> 380 | N45: =E45 -> 低相关 | P45: =VLOOKUP(B45,'附表-搜索转化率'!A:F,6,FALSE) -> #N/A | Q45: =IFERROR(P45,"-") -> - | R45: =IFERROR(VLOOKUP(B45,'附表-搜索转化率'!A:B,2,FALSE),"-") -> -
A46: 44 | B46: hand held vacuum | C46: 手持吸尘器 | D46: 0.1528 | E46: 低相关 | F46: 0.0625 | G46: 0.2656 | H46: 0.1875 | I46: 0.2813 | J46: 0.2448 | K46: 825 | L46: 55108 | M46: =K46 -> 825 | N46: =E46 -> 低相关 | P46: =VLOOKUP(B46,'附表-搜索转化率'!A:F,6,FALSE) -> 0.0172 | Q46: =IFERROR(P46,"-") -> 0.0172 | R46: =IFERROR(VLOOKUP(B46,'附表-搜索转化率'!A:B,2,FALSE),"-") -> 52249
A47: 45 | B47: cordless car vacuum cleaners | C47: 无线汽车吸尘器 | D47: 0.1366 | E47: 低相关 | F47: 0.1563 | G47: 0.125 | H47: 0.1172 | I47: 0.1016 | J47: 0.0833 | K47: 387 | L47: 123268 | M47: =K47 -> 387 | N47: =E47 -> 低相关 | P47: =VLOOKUP(B47,'附表-搜索转化率'!A:F,6,FALSE) -> #N/A | Q47: =IFERROR(P47,"-") -> - | R47: =IFERROR(VLOOKUP(B47,'附表-搜索转化率'!A:B,2,FALSE),"-") -> -
... A64: 62 | B64: powerful car vacuum cleaner | C64: 强大的车载吸尘器 | D64: 0.0684 | E64: 低相关 | F64: 0.0625 | G64: 0.0781 | H64: 0.0781 | I64: 0.0625 | J64: 0.0495 | K64: 212 | L64: 225855 | M64: =K64 -> 212 | N64: =E64 -> 低相关 | P64: =VLOOKUP(B64,'附表-搜索转化率'!A:F,6,FALSE) -> #N/A | Q64: =IFERROR(P64,"-") -> - | R64: =IFERROR(VLOOKUP(B64,'附表-搜索转化率'!A:B,2,FALSE),"-") -> -
A65: 63 | B65: d80 pro car vacuum cleaner | D65: 0.0666 | E65: 低相关 | F65: 0.0625 | G65: 0.0781 | H65: 0.0703 | I65: 0.0547 | J65: 0.0469 | K65: 335 | L65: 142827 | M65: =K65 -> 335 | N65: =E65 -> 低相关 | P65: =VLOOKUP(B65,'附表-搜索转化率'!A:F,6,FALSE) -> #N/A | Q65: =IFERROR(P65,"-") -> - | R65: =IFERROR(VLOOKUP(B65,'附表-搜索转化率'!A:B,2,FALSE),"-") -> -
A66: 64 | B66: cordless car hoover | C66: 无线汽车吸尘器 | D66: 0.0627 | E66: 低相关 | F66: 0.0625 | G66: 0.0625 | H66: 0.0703 | I66: 0.0547 | J66: 0.0495 | K66: 187 | L66: 255329 | M66: =K66 -> 187 | N66: =E66 -> 低相关 | P66: =VLOOKUP(B66,'附表-搜索转化率'!A:F,6,FALSE) -> #N/A | Q66: =IFERROR(P66,"-") -> - | R66: =IFERROR(VLOOKUP(B66,'附表-搜索转化率'!A:B,2,FALSE),"-") -> -
A67: 65 | B67: handheld hoover for car | C67: 车用手持式吸尘器 | D67: 0.0618 | E67: 低相关 | F67: 0.0625 | G67: 0.0625 | H67: 0.0625 | I67: 0.0547 | J67: 0.0573 | K67: 193 | L67: 247222 | M67: =K67 -> 193 | N67: =E67 -> 低相关 | P67: =VLOOKUP(B67,'附表-搜索转化率'!A:F,6,FALSE) -> #N/A | Q67: =IFERROR(P67,"-") -> - | R67: =IFERROR(VLOOKUP(B67,'附表-搜索转化率'!A:B,2,FALSE),"-") -> -
A68: 66 | B68: portable car hoover | C68: 便携式车用吸尘器 | D68: 0.0616 | E68: 低相关 | F68: 0.0625 | G68: 0.0625 | H68: 0.0625 | I68: 0.0547 | J68: 0.0495 | K68: 187 | L68: 255329 | M68: =K68 -> 187 | N68: =E68 -> 低相关 | P68: =VLOOKUP(B68,'附表-搜索转化率'!A:F,6,FALSE) -> #N/A | Q68: =IFERROR(P68,"-") -> - | R68: =IFERROR(VLOOKUP(B68,'附表-搜索转化率'!A:B,2,FALSE),"-") -> -
A69: 67 | B69: car hoovers | C69: 汽车吸尘器 | D69: 0.0613 | E69: 低相关 | F69: 0.0625 | G69: 0.0625 | H69: 0.0625 | I69: 0.0508 | J69: 0.0495 | K69: 212 | L69: 225855 | M69: =K69 -> 212 | N69: =E69 -> 低相关 | P69: =VLOOKUP(B69,'附表-搜索转化率'!A:F,6,FALSE) -> #N/A | Q69: =IFERROR(P69,"-") -> - | R69: =IFERROR(VLOOKUP(B69,'附表-搜索转化率'!A:B,2,FALSE),"-") -> -
A70: 68 | B70: car vacuum cleaner high power | C70: 高功率汽车吸尘器 | D70: 0.0604 | E70: 低相关 | F70: 0.0625 | G70: 0.0625 | H70: 0.0547 | I70: 0.0547 | J70: 0.0495 | K70: 180 | L70: 263780 | M70: =K70 -> 180 | N70: =E70 -> 低相关 | P70: =VLOOKUP(B70,'附表-搜索转化率'!A:F,6,FALSE) -> #N/A | Q70: =IFERROR(P70,"-") -> - | R70: =IFERROR(VLOOKUP(B70,'附表-搜索转化率'!A:B,2,FALSE),"-") -> -
A71: 69 | B71: car cleaner | C71: 汽车清洁剂 | D71: 0.0595 | E71: 低相关 | F71: 0.0313 | G71: 0.1094 | H71: 0.0625 | I71: 0.0742 | J71: 0.0651 | K71: 793 | L71: 57444 | M71: =K71 -> 793 | N71: =E71 -> 低相关 | P71: =VLOOKUP(B71,'附表-搜索转化率'!A:F,6,FALSE) -> #N/A | Q71: =IFERROR(P71,"-") -> - | R71: =IFERROR(VLOOKUP(B71,'附表-搜索转化率'!A:B,2,FALSE),"-") -> -
A72: 70 | B72: flexup car vacuum and blower | C72: flexup汽车吸尘器和鼓风机 | D72: 0.0575 | E72: 低相关 | F72: 0.0625 | G72: 0.0469 | H72: 0.0625 | I72: 0.0547 | J72: 0.0443 | K72: 232 | L72: 207517 | M72: =K72 -> 232 | N72: =E72 -> 低相关 | P72: =VLOOKUP(B72,'附表-搜索转化率'!A:F,6,FALSE) -> #N/A | Q72: =IFERROR(P72,"-") -> - | R72: =IFERROR(VLOOKUP(B72,'附表-搜索转化率'!A:B,2,FALSE),"-") -> -
A73: 71 | B73: mini hoover for bedroom | C73: 卧室用迷你吸尘器 | D73: 0.0561 | E73: 低相关 | F73: 0.0625 | G73: 0.0469 | H73: 0.0547 | I73: 0.0508 | J73: 0.0469 | K73: 245 | L73: 196627 | M73: =K73 -> 245 | N73: =E73 -> 低相关 | P73: =VLOOKUP(B73,'附表-搜索转化率'!A:F,6,FALSE) -> #N/A | Q73: =IFERROR(P73,"-") -> - | R73: =IFERROR(VLOOKUP(B73,'附表-搜索转化率'!A:B,2,FALSE),"-") -> -
A74: 72 | B74: hand vacuum for car | C74: 车用手持吸尘器 | D74: 0.0541 | E74: 低相关 | F74: 0.0625 | G74: 0.0469 | H74: 0.0391 | I74: 0.0547 | J74: 0.0495 | K74: 167 | L74: 282442 | M74: =K74 -> 167 | N74: =E74 -> 低相关 | P74: =VLOOKUP(B74,'附表-搜索转化率'!A:F,6,FALSE) -> #N/A | Q74: =IFERROR(P74,"-") -> - | R74: =IFERROR(VLOOKUP(B74,'附表-搜索转化率'!A:B,2,FALSE),"-") -> -
A75: 73 | B75: portable hoover for car | C75: 车用便携式吸尘器 | D75: 0.0514 | E75: 低相关 | F75: 0.0625 | G75: 0.0313 | H75: 0.0469 | I75: 0.0547 | J75: 0.0495 | K75: 258 | L75: 186831 | M75: =K75 -> 258 | N75: =E75 -> 低相关 | P75: =VLOOKUP(B75,'附表-搜索转化率'!A:F,6,FALSE) -> #N/A | Q75: =IFERROR(P75,"-") -> - | R75: =IFERROR(VLOOKUP(B75,'附表-搜索转化率'!A:B,2,FALSE),"-") -> -
A76: 74 | B76: handheld car vacuum cleaner | C76: 手持车用吸尘器 | D76: 0.0509 | E76: 低相关 | F76: 0.0625 | G76: 0.0313 | H76: 0.0469 | I76: 0.0469 | J76: 0.0521 | K76: 206 | L76: 232592 | M76: =K76 -> 206 | N76: =E76 -> 低相关 | P76: =VLOOKUP(B76,'附表-搜索转化率'!A:F,6,FALSE) -> #N/A | Q76: =IFERROR(P76,"-") -> - | R76: =IFERROR(VLOOKUP(B76,'附表-搜索转化率'!A:B,2,FALSE),"-") -> -
A77: 75 | B77: car vacuum cleaner powerful | C77: 强力汽车吸尘器 | D77: 0.0498 | E77: 低相关 | F77: 0.0313 | G77: 0.0781 | H77: 0.0625 | I77: 0.0547 | J77: 0.0495 | K77: 296 | L77: 162149 | M77: =K77 -> 296 | N77: =E77 -> 低相关 | P77: =VLOOKUP(B77,'附表-搜索转化率'!A:F,6,FALSE) -> #N/A | Q77: =IFERROR(P77,"-") -> - | R77: =IFERROR(VLOOKUP(B77,'附表-搜索转化率'!A:B,2,FALSE),"-") -> -
... A82: 80 | B82: best handheld vacuum cleaner | C82: 最佳手持式吸尘器 | D82: 0.0348 | E82: 低相关 | F82: 0.0313 | G82: 0.0313 | H82: 0.0469 | I82: 0.043 | J82: 0.0443 | K82: 167 | L82: 282442 | M82: =K82 -> 167 | N82: =E82 -> 低相关 | P82: =VLOOKUP(B82,'附表-搜索转化率'!A:F,6,FALSE) -> #N/A | Q82: =IFERROR(P82,"-") -> - | R82: =IFERROR(VLOOKUP(B82,'附表-搜索转化率'!A:B,2,FALSE),"-") -> -
A83: 81 | B83: best handheld vacuum amazon | D83: 0.0331 | E83: 低相关 | F83: 0.0313 | G83: 0.0313 | H83: 0.0391 | I83: 0.0391 | J83: 0.0365 | K83: 374 | L83: 127631 | M83: =K83 -> 374 | N83: =E83 -> 低相关 | P83: =VLOOKUP(B83,'附表-搜索转化率'!A:F,6,FALSE) -> #N/A | Q83: =IFERROR(P83,"-") -> - | R83: =IFERROR(VLOOKUP(B83,'附表-搜索转化率'!A:B,2,FALSE),"-") -> -
A84: 82 | B84: motorhome gadgets | C84: 房车小工具 | D84: 0.0326 | E84: 低相关 | F84: 0 | G84: 0.0938 | H84: 0.0469 | I84: 0.0234 | J84: 0.0156 | K84: 309 | L84: 155265 | M84: =K84 -> 309 | N84: =E84 -> 低相关 | P84: =VLOOKUP(B84,'附表-搜索转化率'!A:F,6,FALSE) -> #N/A | Q84: =IFERROR(P84,"-") -> - | R84: =IFERROR(VLOOKUP(B84,'附表-搜索转化率'!A:B,2,FALSE),"-") -> -
A85: 83 | B85: shark hand held vacuum cordless | C85: 鲨鱼手持无绳吸尘器 | D85: 0.0314 | E85: 低相关 | F85: 0 | G85: 0 | H85: 0.125 | I85: 0.1406 | J85: 0.0938 | K85: 367 | L85: 129938 | M85: =K85 -> 367 | N85: =E85 -> 低相关 | P85: =VLOOKUP(B85,'附表-搜索转化率'!A:F,6,FALSE) -> #N/A | Q85: =IFERROR(P85,"-") -> - | R85: =IFERROR(VLOOKUP(B85,'附表-搜索转化率'!A:B,2,FALSE),"-") -> -
A86: 84 | B86: hand held vacuum cleaners rechargeable cordless | C86: 手持式吸尘器可充电无绳 | D86: 0.0309 | E86: 低相关 | F86: 0.0313 | G86: 0.0313 | H86: 0.0313 | I86: 0.0273 | J86: 0.0286 | K86: 212 | L86: 225855 | M86: =K86 -> 212 | N86: =E86 -> 低相关 | P86: =VLOOKUP(B86,'附表-搜索转化率'!A:F,6,FALSE) -> #N/A | Q86: =IFERROR(P86,"-") -> - | R86: =IFERROR(VLOOKUP(B86,'附表-搜索转化率'!A:B,2,FALSE),"-") -> -
A87: 85 | B87: hand held hoovers | C87: 手持吸尘器 | D87: 0.0307 | E87: 低相关 | F87: 0.0313 | G87: 0.0156 | H87: 0.0469 | I87: 0.043 | J87: 0.0365 | K87: 167 | L87: 282442 | M87: =K87 -> 167 | N87: =E87 -> 低相关 | P87: =VLOOKUP(B87,'附表-搜索转化率'!A:F,6,FALSE) -> #N/A | Q87: =IFERROR(P87,"-") -> - | R87: =IFERROR(VLOOKUP(B87,'附表-搜索转化率'!A:B,2,FALSE),"-") -> -
A88: 86 | B88: portable vacuum | C88: 便携式吸尘器 | D88: 0.0302 | E88: 低相关 | F88: 0.0313 | G88: 0.0156 | H88: 0.0469 | I88: 0.0391 | J88: 0.0313 | K88: 270 | L88: 177971 | M88: =K88 -> 270 | N88: =E88 -> 低相关 | P88: =VLOOKUP(B88,'附表-搜索转化率'!A:F,6,FALSE) -> #N/A | Q88: =IFERROR(P88,"-") -> - | R88: =IFERROR(VLOOKUP(B88,'附表-搜索转化率'!A:B,2,FALSE),"-") -> -
A89: 87 | B89: handheld vaccum | C89: 手持式吸尘器 | D89: 0.0293 | E89: 低相关 | F89: 0.0313 | G89: 0.0313 | H89: 0.0234 | I89: 0.0234 | J89: 0.0234 | K89: 174 | L89: 273000 | M89: =K89 -> 174 | N89: =E89 -> 低相关 | P89: =VLOOKUP(B89,'附表-搜索转化率'!A:F,6,FALSE) -> #N/A | Q89: =IFERROR(P89,"-") -> - | R89: =IFERROR(VLOOKUP(B89,'附表-搜索转化率'!A:B,2,FALSE),"-") -> -
A90: 88 | B90: life vac | C90: 生活吸尘器 | D90: 0.0278 | E90: 低相关 | F90: 0 | G90: 0.0625 | H90: 0.0625 | I90: 0.0313 | J90: 0.0208 | K90: 1058 | L90: 42145 | M90: =K90 -> 1058 | N90: =E90 -> 低相关 | P90: =VLOOKUP(B90,'附表-搜索转化率'!A:F,6,FALSE) -> #N/A | Q90: =IFERROR(P90,"-") -> - | R90: =IFERROR(VLOOKUP(B90,'附表-搜索转化率'!A:B,2,FALSE),"-") -> -
A91: 89 | B91: hand-held vacuum | C91: 手持吸尘器 | D91: 0.0269 | E91: 低相关 | F91: 0.0313 | G91: 0.0156 | H91: 0.0313 | I91: 0.0273 | J91: 0.026 | K91: 174 | L91: 273000 | M91: =K91 -> 174 | N91: =E91 -> 低相关 | P91: =VLOOKUP(B91,'附表-搜索转化率'!A:F,6,FALSE) -> #N/A | Q91: =IFERROR(P91,"-") -> - | R91: =IFERROR(VLOOKUP(B91,'附表-搜索转化率'!A:B,2,FALSE),"-") -> -
A92: 90 | B92: stair vacuum cleaner | C92: 楼梯吸尘器 | D92: 0.0263 | E92: 低相关 | F92: 0.0313 | G92: 0.0156 | H92: 0.0313 | I92: 0.0234 | J92: 0.0156 | K92: 206 | L92: 232592 | M92: =K92 -> 206 | N92: =E92 -> 低相关 | P92: =VLOOKUP(B92,'附表-搜索转化率'!A:F,6,FALSE) -> #N/A | Q92: =IFERROR(P92,"-") -> - | R92: =IFERROR(VLOOKUP(B92,'附表-搜索转化率'!A:B,2,FALSE),"-") -> -
A93: 91 | B93: hand held vacuum cleaner | C93: 手持吸尘器清洁器 | D93: 0.0261 | E93: 低相关 | F93: 0.0313 | G93: 0.0156 | H93: 0.0234 | I93: 0.0313 | J93: 0.0286 | K93: 329 | L93: 145729 | M93: =K93 -> 329 | N93: =E93 -> 低相关 | P93: =VLOOKUP(B93,'附表-搜索转化率'!A:F,6,FALSE) -> #N/A | Q93: =IFERROR(P93,"-") -> - | R93: =IFERROR(VLOOKUP(B93,'附表-搜索转化率'!A:B,2,FALSE),"-") -> -
A94: 92 | B94: caravan hoover | C94: 房车吸尘器 | D94: 0.0226 | E94: 低相关 | F94: 0.0313 | G94: 0.0156 | H94: 0.0078 | I94: 0.0195 | J94: 0.0182 | K94: 219 | L94: 219531 | M94: =K94 -> 219 | N94: =E94 -> 低相关 | P94: =VLOOKUP(B94,'附表-搜索转化率'!A:F,6,FALSE) -> #N/A | Q94: =IFERROR(P94,"-") -> - | R94: =IFERROR(VLOOKUP(B94,'附表-搜索转化率'!A:B,2,FALSE),"-") -> -
A95: 93 | B95: car accesories | C95: 汽车配件 | D95: 0.0214 | E95: 低相关 | F95: 0.0313 | G95: 0.0156 | H95: 0.0078 | I95: 0.0078 | J95: 0.0052 | K95: 348 | L95: 137386 | M95: =K95 -> 348 | N95: =E95 -> 低相关 | P95: =VLOOKUP(B95,'附表-搜索转化率'!A:F,6,FALSE) -> #N/A | Q95: =IFERROR(P95,"-") -> - | R95: =IFERROR(VLOOKUP(B95,'附表-搜索转化率'!A:B,2,FALSE),"-") -> -
... A154: 152 | B154: bush vacuum | C154: bush吸尘器 | D154: 0.0004 | E154: 不相关 | F154: 0 | G154: 0 | H154: 0 | I154: 0.0039 | J154: 0.0026 | K154: 167 | L154: 282442 | M154: =K154 -> 167 | N154: =E154 -> 不相关 | P154: =VLOOKUP(B154,'附表-搜索转化率'!A:F,6,FALSE) -> #N/A | Q154: =IFERROR(P154,"-") -> - | R154: =IFERROR(VLOOKUP(B154,'附表-搜索转化率'!A:B,2,FALSE),"-") -> -
A155: 153 | B155: pet hair vacuum cleaner powerful | D155: 0.0004 | E155: 不相关 | F155: 0 | G155: 0 | H155: 0 | I155: 0.0039 | J155: 0.0026 | K155: 212 | L155: 225855 | M155: =K155 -> 212 | N155: =E155 -> 不相关 | P155: =VLOOKUP(B155,'附表-搜索转化率'!A:F,6,FALSE) -> #N/A | Q155: =IFERROR(P155,"-") -> - | R155: =IFERROR(VLOOKUP(B155,'附表-搜索转化率'!A:B,2,FALSE),"-") -> -
A156: 154 | B156: car stuff for men | C156: 男士汽车用品 | D156: 0.0004 | E156: 不相关 | F156: 0 | G156: 0 | H156: 0 | I156: 0 | J156: 0.013 | K156: 0 | L156: 0 | M156: =K156 -> 0 | N156: =E156 -> 不相关 | P156: =VLOOKUP(B156,'附表-搜索转化率'!A:F,6,FALSE) -> #N/A | Q156: =IFERROR(P156,"-") -> - | R156: =IFERROR(VLOOKUP(B156,'附表-搜索转化率'!A:B,2,FALSE),"-") -> -
A157: 155 | B157: powerful vacuum cleaner | C157: 强力吸尘器 | D157: 0.0004 | E157: 不相关 | F157: 0 | G157: 0 | H157: 0 | I157: 0.0039 | J157: 0.0026 | K157: 167 | L157: 282442 | M157: =K157 -> 167 | N157: =E157 -> 不相关 | P157: =VLOOKUP(B157,'附表-搜索转化率'!A:F,6,FALSE) -> #N/A | Q157: =IFERROR(P157,"-") -> - | R157: =IFERROR(VLOOKUP(B157,'附表-搜索转化率'!A:B,2,FALSE),"-") -> -
A158: 156 | B158: black and decker handheld vacuum cleaner | C158: 黑德克手持式吸尘器 | D158: 0.0004 | E158: 不相关 | F158: 0 | G158: 0 | H158: 0 | I158: 0.0039 | J158: 0.0026 | K158: 206 | L158: 232592 | M158: =K158 -> 206 | N158: =E158 -> 不相关 | P158: =VLOOKUP(B158,'附表-搜索转化率'!A:F,6,FALSE) -> #N/A | Q158: =IFERROR(P158,"-") -> - | R158: =IFERROR(VLOOKUP(B158,'附表-搜索转化率'!A:B,2,FALSE),"-") -> -
A159: 157 | B159: kitchen plinth vacuum | C159: 厨房底座吸尘器 | D159: 0.0004 | E159: 不相关 | F159: 0 | G159: 0 | H159: 0 | I159: 0.0039 | J159: 0.0026 | K159: 264 | L159: 182282 | M159: =K159 -> 264 | N159: =E159 -> 不相关 | P159: =VLOOKUP(B159,'附表-搜索转化率'!A:F,6,FALSE) -> #N/A | Q159: =IFERROR(P159,"-") -> - | R159: =IFERROR(VLOOKUP(B159,'附表-搜索转化率'!A:B,2,FALSE),"-") -> -
A160: 158 | B160: car essentials for women | C160: 女性汽车必需品 | D160: 0.0003 | E160: 不相关 | F160: 0 | G160: 0 | H160: 0 | I160: 0 | J160: 0.0104 | K160: 529 | L160: 88684 | M160: =K160 -> 529 | N160: =E160 -> 不相关 | P160: =VLOOKUP(B160,'附表-搜索转化率'!A:F,6,FALSE) -> #N/A | Q160: =IFERROR(P160,"-") -> - | R160: =IFERROR(VLOOKUP(B160,'附表-搜索转化率'!A:B,2,FALSE),"-") -> -
A161: 159 | B161: vacuum cleaner cordless powerful | C161: 真空吸尘器 无绳 强力 | D161: 0.0003 | E161: 不相关 | F161: 0 | G161: 0 | H161: 0 | I161: 0 | J161: 0.0104 | K161: 929 | L161: 48422 | M161: =K161 -> 929 | N161: =E161 -> 不相关 | P161: =VLOOKUP(B161,'附表-搜索转化率'!A:F,6,FALSE) -> #N/A | Q161: =IFERROR(P161,"-") -> - | R161: =IFERROR(VLOOKUP(B161,'附表-搜索转化率'!A:B,2,FALSE),"-") -> -
A162: 160 | B162: handheld upholstery cleaner | C162: 手持式家具清洁器 | D162: 0.0002 | E162: 不相关 | F162: 0 | G162: 0 | H162: 0 | I162: 0 | J162: 0.0052 | K162: 322 | L162: 148766 | M162: =K162 -> 322 | N162: =E162 -> 不相关 | P162: =VLOOKUP(B162,'附表-搜索转化率'!A:F,6,FALSE) -> #N/A | Q162: =IFERROR(P162,"-") -> - | R162: =IFERROR(VLOOKUP(B162,'附表-搜索转化率'!A:B,2,FALSE),"-") -> -
A163: 161 | B163: vytronix | C163: 维特罗尼克斯 | D163: 0.0002 | E163: 不相关 | F163: 0 | G163: 0 | H163: 0 | I163: 0 | J163: 0.0052 | K163: 425 | L163: 111495 | M163: =K163 -> 425 | N163: =E163 -> 不相关 | P163: =VLOOKUP(B163,'附表-搜索转化率'!A:F,6,FALSE) -> #N/A | Q163: =IFERROR(P163,"-") -> - | R163: =IFERROR(VLOOKUP(B163,'附表-搜索转化率'!A:B,2,FALSE),"-") -> -
A164: 162 | B164: shop vac | C164: 吸尘器 | D164: 0.0002 | E164: 不相关 | F164: 0 | G164: 0 | H164: 0 | I164: 0 | J164: 0.0078 | K164: 554 | L164: 84413 | M164: =K164 -> 554 | N164: =E164 -> 不相关 | P164: =VLOOKUP(B164,'附表-搜索转化率'!A:F,6,FALSE) -> #N/A | Q164: =IFERROR(P164,"-") -> - | R164: =IFERROR(VLOOKUP(B164,'附表-搜索转化率'!A:B,2,FALSE),"-") -> -
A165: 163 | B165: lightweight cordless vacuum cleaner | C165: 轻便无绳吸尘器 | D165: 0.0002 | E165: 不相关 | F165: 0 | G165: 0 | H165: 0 | I165: 0 | J165: 0.0052 | K165: 277 | L165: 173778 | M165: =K165 -> 277 | N165: =E165 -> 不相关 | P165: =VLOOKUP(B165,'附表-搜索转化率'!A:F,6,FALSE) -> #N/A | Q165: =IFERROR(P165,"-") -> - | R165: =IFERROR(VLOOKUP(B165,'附表-搜索转化率'!A:B,2,FALSE),"-") -> -
A166: 164 | B166: battery vacuum cleaner cordless | C166: 电池无线吸尘器 | D166: 0.0002 | E166: 不相关 | F166: 0 | G166: 0 | H166: 0 | I166: 0 | J166: 0.0052 | K166: 303 | L166: 158607 | M166: =K166 -> 303 | N166: =E166 -> 不相关 | P166: =VLOOKUP(B166,'附表-搜索转化率'!A:F,6,FALSE) -> #N/A | Q166: =IFERROR(P166,"-") -> - | R166: =IFERROR(VLOOKUP(B166,'附表-搜索转化率'!A:B,2,FALSE),"-") -> -
A167: 165 | B167: rechargeable hoover cordless | C167: 无线充电吸尘器 | D167: 0.0002 | E167: 不相关 | F167: 0 | G167: 0 | H167: 0 | I167: 0 | J167: 0.0052 | K167: 245 | L167: 196627 | M167: =K167 -> 245 | N167: =E167 -> 不相关 | P167: =VLOOKUP(B167,'附表-搜索转化率'!A:F,6,FALSE) -> #N/A | Q167: =IFERROR(P167,"-") -> - | R167: =IFERROR(VLOOKUP(B167,'附表-搜索转化率'!A:B,2,FALSE),"-") -> -
... A275: 273 | B275: car dash cleaner | C275: 汽车仪表板清洁剂 | D275: 0 | E275: 不相关 | F275: 0 | G275: 0 | H275: 0 | I275: 0 | J275: 0 | K275: 167 | L275: 282442 | M275: =K275 -> 167 | N275: =E275 -> 不相关 | P275: =VLOOKUP(B275,'附表-搜索转化率'!A:F,6,FALSE) -> #N/A | Q275: =IFERROR(P275,"-") -> - | R275: =IFERROR(VLOOKUP(B275,'附表-搜索转化率'!A:B,2,FALSE),"-") -> -
A276: 274 | B276: bed hoover uv light dust mites cordless | D276: 0 | E276: 不相关 | F276: 0 | G276: 0 | H276: 0 | I276: 0 | J276: 0 | K276: 180 | L276: 263780 | M276: =K276 -> 180 | N276: =E276 -> 不相关 | P276: =VLOOKUP(B276,'附表-搜索转化率'!A:F,6,FALSE) -> #N/A | Q276: =IFERROR(P276,"-") -> - | R276: =IFERROR(VLOOKUP(B276,'附表-搜索转化率'!A:B,2,FALSE),"-") -> -
A277: 275 | B277: kids car accessories | C277: 儿童汽车配件 | D277: 0 | E277: 不相关 | F277: 0 | G277: 0 | H277: 0 | I277: 0 | J277: 0 | K277: 445 | L277: 106379 | M277: =K277 -> 445 | N277: =E277 -> 不相关 | P277: =VLOOKUP(B277,'附表-搜索转化率'!A:F,6,FALSE) -> #N/A | Q277: =IFERROR(P277,"-") -> - | R277: =IFERROR(VLOOKUP(B277,'附表-搜索转化率'!A:B,2,FALSE),"-") -> -
A278: 276 | B278: karcher vacuum cleaner | C278: 凯驰吸尘器 | D278: 0 | E278: 不相关 | F278: 0 | G278: 0 | H278: 0 | I278: 0 | J278: 0 | K278: 903 | L278: 49946 | M278: =K278 -> 903 | N278: =E278 -> 不相关 | P278: =VLOOKUP(B278,'附表-搜索转化率'!A:F,6,FALSE) -> #N/A | Q278: =IFERROR(P278,"-") -> - | R278: =IFERROR(VLOOKUP(B278,'附表-搜索转化率'!A:B,2,FALSE),"-") -> -
A279: 277 | B279: ford focus accessories | C279: 福特福克斯配件 | D279: 0 | E279: 不相关 | F279: 0 | G279: 0 | H279: 0 | I279: 0 | J279: 0 | K279: 916 | L279: 49167 | M279: =K279 -> 916 | N279: =E279 -> 不相关 | P279: =VLOOKUP(B279,'附表-搜索转化率'!A:F,6,FALSE) -> #N/A | Q279: =IFERROR(P279,"-") -> - | R279: =IFERROR(VLOOKUP(B279,'附表-搜索转化率'!A:B,2,FALSE),"-") -> -
A280: 278 | B280: car brush | C280: 汽车刷 | D280: 0 | E280: 不相关 | F280: 0 | G280: 0 | H280: 0 | I280: 0 | J280: 0 | K280: 451 | L280: 104804 | M280: =K280 -> 451 | N280: =E280 -> 不相关 | P280: =VLOOKUP(B280,'附表-搜索转化率'!A:F,6,FALSE) -> #N/A | Q280: =IFERROR(P280,"-") -> - | R280: =IFERROR(VLOOKUP(B280,'附表-搜索转化率'!A:B,2,FALSE),"-") -> -
A281: 279 | B281: hand cleaner | C281: 手部清洁剂 | D281: 0 | E281: 不相关 | F281: 0 | G281: 0 | H281: 0 | I281: 0 | J281: 0 | K281: 335 | L281: 142827 | M281: =K281 -> 335 | N281: =E281 -> 不相关 | P281: =VLOOKUP(B281,'附表-搜索转化率'!A:F,6,FALSE) -> #N/A | Q281: =IFERROR(P281,"-") -> - | R281: =IFERROR(VLOOKUP(B281,'附表-搜索转化率'!A:B,2,FALSE),"-") -> -
A282: 280 | B282: mini accessories car | C282: 车用 mini 配件 | D282: 0 | E282: 不相关 | F282: 0 | G282: 0 | H282: 0 | I282: 0 | J282: 0 | K282: 380 | L282: 125464 | M282: =K282 -> 380 | N282: =E282 -> 不相关 | P282: =VLOOKUP(B282,'附表-搜索转化率'!A:F,6,FALSE) -> #N/A | Q282: =IFERROR(P282,"-") -> - | R282: =IFERROR(VLOOKUP(B282,'附表-搜索转化率'!A:B,2,FALSE),"-") -> -
A283: 281 | B283: pool hoover vacuum | C283: 泳池吸尘器 | D283: 0 | E283: 不相关 | F283: 0 | G283: 0 | H283: 0 | I283: 0 | J283: 0 | K283: 1270 | L283: 34630 | M283: =K283 -> 1270 | N283: =E283 -> 不相关 | P283: =VLOOKUP(B283,'附表-搜索转化率'!A:F,6,FALSE) -> #N/A | Q283: =IFERROR(P283,"-") -> - | R283: =IFERROR(VLOOKUP(B283,'附表-搜索转化率'!A:B,2,FALSE),"-") -> -
A284: 282 | B284: vax vacuum | C284: vax 真空 | D284: 0 | E284: 不相关 | F284: 0 | G284: 0 | H284: 0 | I284: 0 | J284: 0 | K284: 0 | L284: 0 | M284: =K284 -> 0 | N284: =E284 -> 不相关 | P284: =VLOOKUP(B284,'附表-搜索转化率'!A:F,6,FALSE) -> #N/A | Q284: =IFERROR(P284,"-") -> - | R284: =IFERROR(VLOOKUP(B284,'附表-搜索转化率'!A:B,2,FALSE),"-") -> -
A285: 283 | B285: cordless steamer | C285: 无线蒸汽机 | D285: 0 | E285: 不相关 | F285: 0 | G285: 0 | H285: 0 | I285: 0 | J285: 0 | K285: 445 | L285: 106379 | M285: =K285 -> 445 | N285: =E285 -> 不相关 | P285: =VLOOKUP(B285,'附表-搜索转化率'!A:F,6,FALSE) -> #N/A | Q285: =IFERROR(P285,"-") -> - | R285: =IFERROR(VLOOKUP(B285,'附表-搜索转化率'!A:B,2,FALSE),"-") -> -
A286: 284 | B286: mini leaf blower | C286: 迷你吹叶机 | D286: 0 | E286: 不相关 | F286: 0 | G286: 0 | H286: 0 | I286: 0 | J286: 0 | K286: 238 | L286: 201946 | M286: =K286 -> 238 | N286: =E286 -> 不相关 | P286: =VLOOKUP(B286,'附表-搜索转化率'!A:F,6,FALSE) -> #N/A | Q286: =IFERROR(P286,"-") -> - | R286: =IFERROR(VLOOKUP(B286,'附表-搜索转化率'!A:B,2,FALSE),"-") -> -
A287: 285 | B287: sixpad s80 cordless vacuum cleaner | C287: sixpad s80无绳吸尘器 | D287: 0 | E287: 不相关 | F287: 0 | G287: 0 | H287: 0 | I287: 0 | J287: 0 | K287: 283 | L287: 169703 | M287: =K287 -> 283 | N287: =E287 -> 不相关 | P287: =VLOOKUP(B287,'附表-搜索转化率'!A:F,6,FALSE) -> #N/A | Q287: =IFERROR(P287,"-") -> - | R287: =IFERROR(VLOOKUP(B287,'附表-搜索转化率'!A:B,2,FALSE),"-") -> -
A288: 286 | B288: beldray cordless vacuum cleaner | C288: 贝尔德雷无线吸尘器 | D288: 0 | E288: 不相关 | F288: 0 | G288: 0 | H288: 0 | I288: 0 | J288: 0 | K288: 483 | L288: 97399 | M288: =K288 -> 483 | N288: =E288 -> 不相关 | P288: =VLOOKUP(B288,'附表-搜索转化率'!A:F,6,FALSE) -> #N/A | Q288: =IFERROR(P288,"-") -> - | R288: =IFERROR(VLOOKUP(B288,'附表-搜索转化率'!A:B,2,FALSE),"-") -> -
... A300: 298 | B300: car air con cleaner antibacterial | C300: 汽车空调清洁剂抗菌 | D300: 0 | E300: 不相关 | F300: 0 | G300: 0 | H300: 0 | I300: 0 | J300: 0 | K300: 303 | L300: 158607 | M300: =K300 -> 303 | N300: =E300 -> 不相关 | P300: =VLOOKUP(B300,'附表-搜索转化率'!A:F,6,FALSE) -> #N/A | Q300: =IFERROR(P300,"-") -> - | R300: =IFERROR(VLOOKUP(B300,'附表-搜索转化率'!A:B,2,FALSE),"-") -> -
A301: 299 | B301: g tech air ram cordless vacuum cleaner | D301: 0 | E301: 不相关 | F301: 0 | G301: 0 | H301: 0 | I301: 0 | J301: 0 | K301: 438 | L301: 108044 | M301: =K301 -> 438 | N301: =E301 -> 不相关 | P301: =VLOOKUP(B301,'附表-搜索转化率'!A:F,6,FALSE) -> #N/A | Q301: =IFERROR(P301,"-") -> - | R301: =IFERROR(VLOOKUP(B301,'附表-搜索转化率'!A:B,2,FALSE),"-") -> -
A302: 300 | B302: gtech hoover | C302: gtech 吸尘器 | D302: 0 | E302: 不相关 | F302: 0 | G302: 0 | H302: 0 | I302: 0 | J302: 0 | K302: 380 | L302: 125464 | M302: =K302 -> 380 | N302: =E302 -> 不相关 | P302: =VLOOKUP(B302,'附表-搜索转化率'!A:F,6,FALSE) -> #N/A | Q302: =IFERROR(P302,"-") -> - | R302: =IFERROR(VLOOKUP(B302,'附表-搜索转化率'!A:B,2,FALSE),"-") -> -
A303: 301 | B303: car cleaning putty | C303: 汽车清洁膏 | D303: 0 | E303: 不相关 | F303: 0 | G303: 0 | H303: 0 | I303: 0 | J303: 0 | K303: 264 | L303: 182282 | M303: =K303 -> 264 | N303: =E303 -> 不相关 | P303: =VLOOKUP(B303,'附表-搜索转化率'!A:F,6,FALSE) -> #N/A | Q303: =IFERROR(P303,"-") -> - | R303: =IFERROR(VLOOKUP(B303,'附表-搜索转化率'!A:B,2,FALSE),"-") -> -
A304: 302 | B304: passenger princess car accessories | C304: 乘客公主汽车配件 | D304: 0 | E304: 不相关 | F304: 0 | G304: 0 | H304: 0 | I304: 0 | J304: 0 | K304: 522 | L304: 89825 | M304: =K304 -> 522 | N304: =E304 -> 不相关 | P304: =VLOOKUP(B304,'附表-搜索转化率'!A:F,6,FALSE) -> #N/A | Q304: =IFERROR(P304,"-") -> - | R304: =IFERROR(VLOOKUP(B304,'附表-搜索转化率'!A:B,2,FALSE),"-") -> -
A305: 303 | B305: pc duster | C305: 电脑除尘器 | D305: 0 | E305: 不相关 | F305: 0 | G305: 0 | H305: 0 | I305: 0 | J305: 0 | K305: 277 | L305: 173778 | M305: =K305 -> 277 | N305: =E305 -> 不相关 | P305: =VLOOKUP(B305,'附表-搜索转化率'!A:F,6,FALSE) -> #N/A | Q305: =IFERROR(P305,"-") -> - | R305: =IFERROR(VLOOKUP(B305,'附表-搜索转化率'!A:B,2,FALSE),"-") -> -
A306: 304 | B306: henry hoover accessories | C306: 亨利胡佛配件 | D306: 0 | E306: 不相关 | F306: 0 | G306: 0 | H306: 0 | I306: 0 | J306: 0 | K306: 625 | L306: 74084 | M306: =K306 -> 625 | N306: =E306 -> 不相关 | P306: =VLOOKUP(B306,'附表-搜索转化率'!A:F,6,FALSE) -> #N/A | Q306: =IFERROR(P306,"-") -> - | R306: =IFERROR(VLOOKUP(B306,'附表-搜索转化率'!A:B,2,FALSE),"-") -> -
A307: 305 | B307: laresar robot vacuum | C307: laresar 机器人吸尘器 | D307: 0 | E307: 不相关 | F307: 0 | G307: 0 | H307: 0 | I307: 0 | J307: 0 | K307: 483 | L307: 97399 | M307: =K307 -> 483 | N307: =E307 -> 不相关 | P307: =VLOOKUP(B307,'附表-搜索转化率'!A:F,6,FALSE) -> #N/A | Q307: =IFERROR(P307,"-") -> - | R307: =IFERROR(VLOOKUP(B307,'附表-搜索转化率'!A:B,2,FALSE),"-") -> -
A308: 306 | B308: handheld steamer for clothes | C308: 手持蒸汽熨斗用于衣物 | D308: 0 | E308: 不相关 | F308: 0 | G308: 0 | H308: 0 | I308: 0 | J308: 0 | K308: 3825 | L308: 9606 | M308: =K308 -> 3825 | N308: =E308 -> 不相关 | P308: =VLOOKUP(B308,'附表-搜索转化率'!A:F,6,FALSE) -> #N/A | Q308: =IFERROR(P308,"-") -> - | R308: =IFERROR(VLOOKUP(B308,'附表-搜索转化率'!A:B,2,FALSE),"-") -> -
A309: 307 | B309: washing machine hair catcher | C309: 洗衣机毛发捕捉器 | D309: 0 | E309: 不相关 | F309: 0 | G309: 0 | H309: 0 | I309: 0 | J309: 0 | K309: 587 | L309: 79307 | M309: =K309 -> 587 | N309: =E309 -> 不相关 | P309: =VLOOKUP(B309,'附表-搜索转化率'!A:F,6,FALSE) -> #N/A | Q309: =IFERROR(P309,"-") -> - | R309: =IFERROR(VLOOKUP(B309,'附表-搜索转化率'!A:B,2,FALSE),"-") -> -
A310: 308 | B310: pet hair hoovers vacuum cleaners | C310: 宠物毛发吸尘器 | D310: 0 | E310: 不相关 | F310: 0 | G310: 0 | H310: 0 | I310: 0 | J310: 0 | K310: 161 | L310: 292717 | M310: =K310 -> 161 | N310: =E310 -> 不相关 | P310: =VLOOKUP(B310,'附表-搜索转化率'!A:F,6,FALSE) -> #N/A | Q310: =IFERROR(P310,"-") -> - | R310: =IFERROR(VLOOKUP(B310,'附表-搜索转化率'!A:B,2,FALSE),"-") -> -
...

Sheet 3.词频统计完成
B1: 3.词根统计表
A2: 1个单词词根 | G2: 2个单词词根 | M2: 3个单词词根
A3: # | B3: 单词 | C3: 单词翻译 | D3: 出现次数词频 | E3: 搜索量加权词频 (亚马逊官方方法) | G3: # | H3: 单词 | I3: 单词翻译 | J3: 出现次数词频 | K3: 搜索量加权词频(亚马逊官方方法) | M3: # | N3: 单词 | O3: 单词翻译 | P3: 出现次数词频 | Q3: 搜索量加权词频(亚马逊官方方法)
A4: 词语 | B4: 词频 | C4: 一级分类 | D4: 二级分类 | E4: 用户搜索意图标签 | F4: 否定
A5: vacuum | B5: 597 | C5: 功能词 | D5: 电力 | E5: 电力驱动
A6: cleaner | B6: 392 | C6: 属性词 | D6: 便携性 | E6: 便携
A7: car | B7: 255 | C7: 品名词 | D7: 电池包 | E7: 电池包
A8: handheld | B8: 186 | C8: 功能词 | D8: 充电器 | E8: 充电器
A9: cordless | B9: 183 | C9: 品名词 | D9: 电池 | E9: 电池
A10: hoover | B10: 123 | C10: 功能词 | D10: 太阳能 | E10: 太阳能
A11: blower | B11: 87 | C11: 品名词 | D11: 电源站 | E11: 电源站 | F11: X
A12: shark | B12: 71 | C12: 品名词 | D12: 发电机 | E12: 发电机 | F12: X
A13: hand | B13: 70 | C13: 品名词 | D13: 手机
A14: air | B14: 64 | C14: 品名词 | D14: 手机
A15: mini | B15: 60 | C15: 场景词 | D15: 露营 | E15: 户外
A16: held | B16: 53 | C16: 属性词 | D16: 包装
A17: dust | B17: 46 | C17: 品牌词
A18: portable | B18: 45 | C18: 场景词 | D18: 家庭 | E18: 家庭
A19: duster | B19: 39 | C19: 品牌词
A20: cleaners | B20: 31 | C20: 功能词 | D20: 充电 | E20: 充电 | F20: X
A21: powerful | B21: 29 | C21: 品名词 | D21: 发电机 | E21: 发电机
A22: accessories | B22: 27 | C22: 品牌词
A23: small | B23: 25 | C23: 功能词 | D23: 面板 | E23: 太阳能面板
A24: cleaning | B24: 24 | C24: 功能词 | D24: 备份 | E24: 备份
A25: pet | B25: 23 | C25: 功能词 | D25: USB接口 | F25: X
A26: vac | B26: 23 | C26: 功能词 | D26: 电源插座 | E26: 电源插座 | F26: X
A27: kit | B27: 21 | C27: 功能词 | D27: 电力驱动 | E27: 电力驱动
A28: power | B28: 19 | C28: 属性词 | D28: 快速
A29: vacuums | B29: 18 | C29: 品名词 | D29: 专业版 | E29: 专业版
A30: dyson | B30: 17 | C30: 功能词 | D30: 供电 | E30: 备份 | F30: X
A31: pro | B31: 17 | C31: 品牌词
A32: suction | B32: 16 | C32: 场景词 | D32: 用途
A33: high | B33: 15 | C33: 品牌词
A34: rechargeable | B34: 15 | C34: 品名词 | D34: 电池单元
A35: desk | B35: 14 | C35: 功能词 | D35: 交流电 | E35: 交流电
A36: home | B36: 14 | C36: 品牌词
A37: dryer | B37: 13 | C37: 场景词 | D37: 呼吸机
A38: wireless | B38: 13 | C38: 功能词 | D38: 逆变器 | E38: 电力驱动
A39: brush | B39: 12 | C39: 品名词 | D39: 充电器 | E39: 充电器 | F39: X
A40: compressed | B40: 12 | C40: 功能词 | D40: 功率单位
A41: hair | B41: 12 | C41: 品名词 | D41: 安卓设备 | F41: X
A42: pump | B42: 12 | C42: 属性词 | D42: 最大
A43: hoovers | B43: 11 | C43: 品名词 | D43: 便携式设备 | E43: 便携
A44: interior | B44: 11 | C44: 品名词 | D44: 面板 | E44: 太阳能面板
A45: machine | B45: 11 | C45: 场景词 | D45: 用途
A46: window | B46: 11 | C46: 功能词 | D46: 插头 | E46: 电源插座
A47: carpet | B47: 10 | C47: 属性词 | D47: 最佳
A48: filter | B48: 10 | C48: 属性词 | D48: 外部
A49: gtech | B49: 10 | C49: 品名词 | D49: 探险者（品牌）
A50: pc | B50: 10 | C50: 品牌词
A51: wet | B51: 10 | C51: 场景词 | D51: 户外 | E51: 户外
A52: amazon | B52: 9 | C52: 场景词 | D52: 紧急情况 | E52: 应急电源
A53: battery | B53: 9 | C53: 属性词 | D53: 无线 | E53: 无线
A54: detailing | B54: 9 | C54: 属性词 | D54: 小型 | E54: 小型设备
A55: electric | B55: 9 | C55: 功能词 | D55: 电动 | E55: 电力驱动
A56: henry | B56: 9 | C56: 品牌词
A57: karcher | B57: 9 | C57: 品名词 | D57: 便携设备 | E57: 便携
A58: pool | B58: 9 | C58: 功能词 | D58: 充电器 | E58: 充电器
A59: strong | B59: 9 | C59: 品牌词
A60: steam | B60: 8 | C60: 品名词
A61: vax | B61: 8 | C61: 品名词 | D61: 移动电源 | E61: 电池包
A62: best | B62: 7 | C62: 属性词 | D62: 小型 | E62: 小型设备 | F62: X
A63: computer | B63: 7 | C63: 场景词 | D63: 背部
A64: flexup | B64: 7 | C64: 场景词 | D64: 旅行
A65: gadgets | B65: 7 | C65: 场景词 | D65: 移动
A66: mate | B66: 7 | C66: 场景词 | D66: 升级
A67: replacement | B67: 7 | C67: 品名词 | D67: 电池 | E67: 电池
A68: set | B68: 7 | C68: 品名词 | D68: 发电机 | E68: 发电机
A69: black | B69: 6 | C69: 功能词 | D69: 可充电 | E69: 可充电 | F69: X
A70: compact | B70: 6 | C70: 功能词 | D70: 充电 | E70: 充电
A71: container | B71: 6 | C71: 场景词 | D71: 室内
A72: go | B72: 6 | C72: 品名词 | D72: 平板电脑
A73: jml | B73: 6 | C73: 属性词 | D73: 大型
A74: keyboard | B74: 6 | C74: 品牌词
A75: makita | B75: 6 | C75: 场景词 | D75: 停电 | E75: 应急电源
A76: slim | B76: 6 | C76: 属性词 | D76: 锂铁磷电池 | E76: 电池
A77: stairs | B77: 6 | C77: 场景词 | D77: 房屋 | E77: 家庭
A78: upright | B78: 6 | C78: 品名词 | D78: 笔记本电脑
A79: v8 | B79: 6 | C79: 属性词 | D79: 毫安时
A80: water | B80: 6 | C80: 属性词 | D80: 类型
A81: 12v | B81: 5 | C81: 品牌词
A82: bags | B82: 5 | C82: 品牌词
A83: bin | B83: 5 | C83: 属性词 | D83: 1000瓦
A84: decker | B84: 5 | C84: 属性词 | D84: 加强版
A85: dry | B85: 5 | C85: 属性词 | D85: 300瓦
A86: dustbuster | B86: 5 | C86: 功能词 | D86: 能量 | E86: 电力驱动
A87: fan | B87: 5 | C87: 功能词 | D87: 适配器
A88: flex | B88: 5 | C88: 品名词 | D88: 电池包 | E88: 电池包
A89: garden | B89: 5 | C89: 品名词 | D89: 手机
A90: products | B90: 5 | C90: 品牌词
A91: storage | B91: 5 | C91: 品名词 | D91: 电源箱
A92: tank | B92: 5 | C92: 场景词 | D92: 家庭 | E92: 家庭
A93: up | B93: 5 | C93: 属性词 | D93: 附加
A94: vaccum | B94: 5 | C94: 场景词 | D94: 工厂
A95: blowers | B95: 4 | C95: 属性词 | D95: 20伏特
A96: buster | B96: 4 | C96: 属性词 | D96: 零
A97: charger | B97: 4 | C97: 场景词 | D97: 用品 | E97: 应急电源
A98: cover | B98: 4 | C98: 品名词 | D98: 电源站 | E98: 电源站
A99: desktop | B99: 4 | C99: 品名词 | D99: 机器
A100: drying | B100: 4 | C100: 属性词 | D100: 110伏特 | E100: 交流电
...

Sheet 4.标题怎么写
A1: 标题 | B1: asin | C1: 内容
A2: 标题1 | D2: 选出优秀竞品10个标题结合词频统计
A3: 标题2
A4: 标题3
A5: 标题4
A6: 标题5
A7: 标题6
A8: 标题7
A9: 标题8
A10: 标题9
A11: 标题10
A13: 标题OK | B13: 标题
AG16: 德语 | AL16: 中文 | AP16: 英语
AL17: 直译 | AP17: 直译
A18: 卖点1 | P18: Robust Suction: This mattress vacuum boasts a powerful 15Kpa suction capability, capable of reaching deep into the mattress to eliminate even the tiniest dust particles and mites. | AG18: Schauen wir uns einmal die Geräte speks an: | AL18: 让我们来看一下这些设备的规格： | AP18: Let's take a look at the device specifications:
A19: 卖点2 | P19: UV Disinfection: Fitted with 273nm UV light, it effectively eradicates bacteria and viruses that have seeped into your mattress, ensuring meticulous hygiene and a refreshing sleep environment. | AG19: 👍 15 Kpa starke Saugleistung für eine gründliche Tiegenreinigung | AL19: 👍 15 Kpa 强大的吸力，用于彻底的深度清洁 | AP19: 👍 15 Kpa strong suction for thorough deep cleaning
A20: 卖点3 | P20: Ultrasonic Cleaning: Utilizing a 55KHz frequency, the ultrasonic feature aids in destroying minuscule mites and grime, resulting in a comprehensive mattress cleaning. | AG20: 👍 400 Watt Leistungsaufnahme | AL20: 👍 400 瓦的功率消耗 | AP20: 👍 400 Watt power consumption
A21: 卖点4 | P21: HEPA Filtration for Optimal Air Quality: The built-in HEPA filter traps up to 99.92% of airborne particles, preventing harmful allergens from re-entering your space. | AG21: 👍 Motordrehzal von 3000 U/min | AL21: 👍 电动机转速为3000转/分钟 | AP21: 👍 Motor speed of 3000 U/min
A22: 卖点5 | P22: Wide Cleaning Reach: Equipped with a 214mm wide suction head, it allows for quick and efficient cleaning of extensive mattress areas, cutting down on cleaning time. | AG22: 👍 UV-C Licht (273,7 nm) für eine gründliche Desinfektion gegen Bakterien und Viren. | AL22: 👍 UV-C 光（273.7 nm），用于对细菌和病毒进行彻底消毒。 | AP22: 👍 UV-C light (273.7 nm) for thorough disinfection against bacteria and viruses.
A23: 卖点6 | P23: User-Friendly and Adaptable: The vacuum's 4m cord and mere 2.3 kg weight ensure easy maneuverability, making it suitable for cleaning various surfaces including mattresses, pillows, and upholstery. | AG23: 👍 Ultraschalltechnologie: Mit einer Frequenz von 50KHz. Zerstört Mikroskopisch kleine Milben und Schmutzpartikel für eine gute Tiefenreinigung. | AL23: 👍 超声波技术：频率为50KHz。破坏显微镜下可见的微小螨虫和污垢颗粒，实现良好的深度清洁。 | AP23: 👍 Ultrasound technology: With a frequency of 50KHz. Destroys microscopic small mites and dirt particles for good deep cleaning.
AG24: 👍 60° Heißlufttechnik entfernt Feuchtigkeit | AL24: 👍 60° 热空气技术去除湿度 | AP24: 👍 60° hot air technology removes moisture
A25: 标题 | AG25: 👍 HEPA Filter filtert 99.92 % der Staubpartikel aus der Luft | AL25: 👍 HEPA 过滤器过滤掉空气中99.92%的尘埃颗粒 | AP25: 👍 HEPA filter filters 99.92% of dust particles from the air
A26: 卖点1 | AG26: 👍 214 mm großer Saugkopf für eine schnelle Reinigung | AL26: 👍 214毫米宽的吸头，用于快速清洁 | AP26: 👍 214 mm large suction head for quick cleaning
A27: 卖点2 | AG27: 👍 4 Meter langes Kabel für eine flexible Reinigung | AL27: 👍 4米长的电缆，用于灵活的清洁 | AP27: 👍 4 meters long cable for flexible cleaning
A28: 卖点3 | AG28: 👍 Gewicht 2.3 Kg | AL28: 👍 重量为2.3公斤 | AP28: 👍 Weight 2.3 Kg
A29: 卖点4
A30: 卖点5
A31: 卖点6
A33: 评论内容：
A34: 评论1
A35: 评论1
A36: 评论1
A37: 评论1
A38: 评论1
A39: 评论1
A40: 评论1
A41: 评论1
... A67: 买家图

Sheet 5.ASIN表
CP1: 搜索词 | CQ1: 搜索量（过去 360 天） | CR1: 搜索量增长（过去 90 天） | CS1: 搜索量增长（过去 180 天） | CT1: 点击份额（过去 360 天） | CU1: 搜索转化率（过去 360 天） | CV1: 点击率最高的商品1（标题） | CW1: 点击率最高的商品1 (ASIN) | CX1: 点击率最高的商品2（标题） | CY1: 点击率最高的商品2 (ASIN) | CZ1: 点击率最高的商品3（标题） | DA1: 点击率最高的商品3 (ASIN) | DB1: ASIN | DC1: 前台售价 | DD1: 日销量 | DE1: BSR | DF1: 近30天销量（子体） | DG1: 近30天销量（父体） | DH1: 优惠券 | DI1: 备注 | DJ1: 大类BSR | DK1: 小类BSR | DL1: 月销量 | DM1: 子体销量 | DN1: 子体销售额(£) | DO1: 价格(£) | DP1: 商品标题
A2: 图片 | B2: 是否同类 | C2: ASIN | D2: 品牌 | E2: 类目路径 | F2: 大类目 | G2: 大类BSR | H2: 小类目 | I2: 小类BSR | J2: 近30天销量 | K2: 价格($) | L2: Prime价格($) | M2: FBA($) | N2: 评分 | O2: 评分数 | P2: 留评率 | Q2: 变体数 | R2: 图片 | S2: ASIN | T2: SKU | U2: 详细参数 | V2: 品牌 | W2: 品牌链接 | X2: 商品标题 | Y2: 标题(翻译) | Z2: 产品卖点 | AA2: 产品卖点(翻译) | AB2: 商品详情页链接 | AC2: 商品主图 | AD2: 父ASIN | AE2: 类目路径 | AF2: 大类目 | AG2: 大类BSR | AH2: 大类BSR增长数 | AI2: 大类BSR增长率 | AJ2: 小类目 | AK2: 小类BSR | AL2: 月销量 | AM2: 月销量增长率 | AN2: 月销售额(€) | AO2: 子体销量 | AP2: 子体销售额(€) | AQ2: 变体数 | AR2: 价格(€) | AS2: Prime价格(€) | AT2: Coupon | AU2: Q&A数 | AV2: 评分数 | AW2: 月新增 评分数 | AX2: 评分 | AY2: 留评率 | AZ2: FBA(€) | BA2: 毛利率 | BB2: 评级 | BC2: 上架时间 | BD2: 上架天数 | BE2: 配送方式 | BF2: LQS | BG2: 卖家数 | BH2: Buybox卖家 | BI2: BuyBox类型 | BJ2: 卖家所属地 | BK2: 卖家信息 | BL2: 卖家首页 | BM2: Best Seller标识 | BN2: Amazon's Choice | BO2: New Release标识 | BP2: A+页面 | BQ2: 视频介绍 | BR2: SP广告 | BS2: 品牌故事 | BT2: 品牌广告 | BU2: 7天促销 | BV2: AC关键词 | BW2: 重量 | BX2: 重量 | BY2: 体积 | BZ2: 体积 | CA2: 包装重量 | CB2: 包装体积 | CP2: handheld vacuum cleaner | CQ2: 717259 | CR2: -0.0715 | CS2: -0.1965 | CT2: 0.2138 | CU2: 0.0197 | CV2: Shark Handheld Cordless Vacuum Cleaner with Pet Tool Crevice Tool & Dusting Brush 80 W 0.45 liters 10 Minute Run-Time Washable Filter Black & Yellow CH950UKT | CW2: B08M9JQ1J1 | CX2: Handheld Vacuum Cleaner Powerful Suction Portable Lightweight Hand Held Vacuum Cordless with 25-30Mins Long Runtime Rechargeable Battery Quick Charge for Home Car Carpet Stairs Pet Hair Cleaning | CY2: B09VKPHJVF | CZ2: Higoom 4 in 1 Cordless Handheld Vacuum Cleaner Car Vacuum Cleaner 22000PA Strong Suction Mini Vacuum Dust Blower Can be Used for Home Car | DA2: B0DJFMT6LS | DB2: B0F3JGRDBP | DC2: 25.49 | DD2: 83.7 | DE2: 2 | DF2: 2000 | DG2: 2511 | DJ2: 523 | DK2: 2 | DL2: 2511 | DM2: 2000 | DN2: 50980 | DO2: 25.49 | DP2: Handheld Vacuum Cleaner, 22000Pa Cordless Car Vacuum Cleaner, 3 Speed Brushless Motor Mini Hoover with Multiple Brush HeadsHigh Power Hand Held Vacuum Cordless, for Office, Home Kitchen, Car,Pet Hair
B3: 否 | C3: B003TFE7ZM | D3: Flexzilla | E3: Patio, Lawn & Garden:Gardening & Lawn Care:Watering Equipment:Garden Hoses | F3: Patio, Lawn & Garden | G3: 10 | H3: Garden Hoses | I3: 1 | J3: 37379 | K3: 39.97 | M3: 8.77 | N3: 4.5 | O3: 75158 | P3: 0.0361 | Q3: 15 | CP3: car vacuum cleaner | CQ3: 455206 | CR3: 0.0195 | CS3: -0.1366 | CT3: 0.148 | CU3: 0.0146 | CV3: Ginarelo Handheld Cordless Car Vacuum Cleaner - 4000Pa Small Hand Held Vacuums Cleaners Strong Suction Powerful Portable Wireless Lightweight Mini Long Runtime Hand-held Vaccum USB Vacum Blower | CW3: B0DB5VMBTC | CX3: Higoom 4 in 1 Cordless Handheld Vacuum Cleaner Car Vacuum Cleaner 22000PA Strong Suction Mini Vacuum Dust Blower Can be Used for Home Car | CY3: B0DJFMT6LS | CZ3: Wirelume Handheld Car Vacuum Cleaner Cordless Powerful 22000Pa Strong Cyclonic Suction Blowing Brushless Motor Mini Hand Held Portable Rechargeable Lightweight for Pet Hair Vehicle Home Office Purple | DA3: B0D45V1YXT | DB3: B0DJ2YVV6F | DC3: 21.24 | DD3: 64.166667 | DE3: 12 | DF3: 1000 | DG3: 1925 | DJ3: 2315 | DK3: 12 | DL3: 1925 | DM3: 1000 | DN3: 25990 | DO3: 21.24 | DP3: Nctoberows Handheld Vacuum Cleaner Cordless, 22000Pa Powerful Car Mini Vacuum Cleaner, Rechargeable Portable Lightweight dust catcher for Home Car Carpet Stairs Pet Hair Deep Cleaning
CP4: hand held vacuum cordless | CQ4: 410982 | CR4: -0.1937 | CS4: -0.1952 | CT4: 0.1142 | CU4: 0.022 | CV4: Shark Handheld Cordless Vacuum Cleaner with Pet Tool Crevice Tool & Dusting Brush 80 W 0.45 liters 10 Minute Run-Time Washable Filter Black & Yellow CH950UKT | CW4: B08M9JQ1J1 | CX4: Vax Gator Cordless Handheld Vacuum Cleaner | Lightweight Quick Cleaning | Built-in Crevice Tool - H85-GA-B10 0.3 Litre White and Orange | CY4: B015QZH2EU | CZ4: Handheld Vacuum Cleaner Powerful Suction Portable Lightweight Hand Held Vacuum Cordless with 25-30Mins Long Runtime Rechargeable Battery Quick Charge for Home Car Carpet Stairs Pet Hair Cleaning | DA4: B09VKPHJVF | DB4: B0D45V1YXT | DC4: 25.49 | DD4: 42.233333 | DE4: 13 | DF4: 600 | DG4: 1267 | DJ4: 3218 | DK4: 13 | DL4: 1267 | DM4: 600 | DN4: 15294 | DO4: 25.49 | DP4: Wirelume Handheld Car Vacuum Cleaner Cordless Powerful 22000Pa Strong Cyclonic Suction Blowing Brushless Motor Mini Hand Held Portable Rechargeable Lightweight for Pet Hair Vehicle Home Office Purple
CP5: car hoover | CQ5: 320576 | CR5: -0.0656 | CS5: -0.1624 | CT5: 0.107 | CU5: 0.0233 | CV5: Handheld Vacuum Cleaner Powerful Suction Portable Lightweight Hand Held Vacuum Cordless with 25-30Mins Long Runtime Rechargeable Battery Quick Charge for Home Car Carpet Stairs Pet Hair Cleaning | CW5: B09VKPHJVF | CX5: Handheld Vacuum Cordless 9000Pa Powerful Car Vacuum Cleaner Rechargeable Portable Lightweight Mini Vacuum Cleaner USB Car Vacuum Cleaner Car Cleaner for Pet Hair Car Home Office Kitchen | CY5: B0CKVFMYH4 | CZ5: Nctoberows Handheld Vacuum Cleaner Cordless 22000Pa Powerful Car Mini Vacuum Cleaner Rechargeable Portable Lightweight dust catcher for Home Car Carpet Stairs Pet Hair Deep Cleaning | DA5: B0DJ2YVV6F | DB5: B0CKVFMYH4 | DC5: 22.55 | DD5: 37.066667 | DE5: 14 | DF5: 900 | DG5: 1112 | DJ5: 3508 | DK5: 14 | DL5: 1112 | DM5: 900 | DN5: 20295 | DO5: 22.55 | DP5: Handheld Vacuum Cordless, 9000Pa Powerful Car Vacuum Cleaner, Rechargeable Portable Lightweight Mini Vacuum Cleaner, USB Car Vacuum Cleaner Car Cleaner for Pet Hair, Car, Home, Office, Kitchen
CP6: car vacuum cleaner cordless | CQ6: 190272 | CR6: 0.1062 | CS6: -0.1319 | CT6: 0.0734 | CU6: 0.0194 | CV6: Ginarelo Handheld Cordless Car Vacuum Cleaner - 4000Pa Small Hand Held Vacuums Cleaners Strong Suction Powerful Portable Wireless Lightweight Mini Long Runtime Hand-held Vaccum USB Vacum Blower | CW6: B0DB5VMBTC | CX6: Handheld Vacuum Cleaner Powerful Suction Portable Lightweight Hand Held Vacuum Cordless with 25-30Mins Long Runtime Rechargeable Battery Quick Charge for Home Car Carpet Stairs Pet Hair Cleaning | CY6: B09VKPHJVF | CZ6: Wirelume Handheld Car Vacuum Cleaner Cordless Powerful 22000Pa Strong Cyclonic Suction Blowing Brushless Motor Mini Hand Held Portable Rechargeable Lightweight for Pet Hair Vehicle Home Office Purple | DA6: B0D45V1YXT | DB6: B0D9NGRD9M | DC6: 49.99 | DD6: 42.833333 | DE6: 15 | DF6: 800 | DG6: 1285 | DJ6: 3667 | DK6: 15 | DL6: 1285 | DM6: 800 | DN6: 39992 | DO6: 49.99 | DP6: Lyiazsoy Car Vacuum Cleaner,22000PA High Power Mini Vacuum Cleaner,Rechargeable Handheld Vacuum,Portable Cordless Compressed Air Duster Air Blower for Car Home (Gold black)
CP7: handheld hoover | CQ7: 109751 | CR7: 0.5662 | CS7: -0.1233 | CT7: 0.0473 | CU7: 0.0243 | CV7: Shark Handheld Cordless Vacuum Cleaner with Pet Tool Crevice Tool & Dusting Brush 80 W 0.45 liters 10 Minute Run-Time Washable Filter Black & Yellow CH950UKT | CW7: B08M9JQ1J1 | CX7: Handheld Vacuum Cleaner Powerful Suction Portable Lightweight Hand Held Vacuum Cordless with 25-30Mins Long Runtime Rechargeable Battery Quick Charge for Home Car Carpet Stairs Pet Hair Cleaning | CY7: B09VKPHJVF | CZ7: Powools Handheld Vacuum Cordless with 2 Filters Car Vacuum Cleaner High Power with Fast Cahrge Tech Portable Rechargeable Mini Vacuum with Large-Capacity Battery Orange 14.3X4.6X4.0 | DA7: B0D4M3MSG7 | DB7: B0DJFMT6LS | DC7: 24.99 | DD7: 44.433333 | DE7: 19 | DF7: 1000 | DG7: 1333 | DJ7: 4342 | DK7: 19 | DL7: 1333 | DM7: 1000 | DN7: 24990 | DO7: 24.99 | DP7: Higoom 4 in 1 Cordless Handheld Vacuum Cleaner,Car Vacuum Cleaner,22000PA Strong Suction Mini Vacuum,Dust Blower,Can be Used for Home,Car
CP8: car hoovers cordless powerful | CQ8: 133015 | CR8: -0.001 | CS8: -0.1131 | CT8: 0.0558 | CU8: 0.0275 | CV8: Handheld Vacuum Cleaner Powerful Suction Portable Lightweight Hand Held Vacuum Cordless with 25-30Mins Long Runtime Rechargeable Battery Quick Charge for Home Car Carpet Stairs Pet Hair Cleaning | CW8: B09VKPHJVF | CX8: Nctoberows Handheld Vacuum Cleaner Cordless 22000Pa Powerful Car Mini Vacuum Cleaner Rechargeable Portable Lightweight dust catcher for Home Car Carpet Stairs Pet Hair Deep Cleaning | CY8: B0DJ2YVV6F | CZ8: Semflagree Handheld Mini Vacuum 4 in 1 Cordless 23000PA Powerful Strong Cyclonic Suction USB Rechargeable Portable Car Vacuum Cleaner Car Cleaner for Pet Hair Car Home Office Kitchen | DA8: B0DXKCZD5Z | DB8: B0F7RDTSDF | DC8: 32.99 | DD8: 12.366667 | DE8: 20 | DF8: 300 | DG8: 371 | DJ8: 4356 | DK8: 20 | DL8: 371 | DM8: 300 | DN8: 6000 | DO8: 32.99 | DP8: Handheld Vacuum Cleaner, 22000Pa Brushless Motor Cordless Vacuum Cleaners, 3-Speed Car Vacuum Cleaner with Dual Filters and Multiple Brush Heads for Office, Home, Car, Kitchen and Pet Hair, Dark Grey
CP9: car vacuum | CQ9: 109696 | CR9: 0.0631 | CS9: -0.2452 | CT9: 0.0331 | CU9: 0.0148 | CV9: Wirelume Handheld Car Vacuum Cleaner Cordless Powerful 22000Pa Strong Cyclonic Suction Blowing Brushless Motor Mini Portable Rechargeable Lightweight Blower for Pet Hair Vehicle Home Office Dark Grey | CW9: B0D45VR94F | CX9: Handheld Vacuum Cleaner Powerful Suction Portable Lightweight Hand Held Vacuum Cordless with 25-30Mins Long Runtime Rechargeable Battery Quick Charge for Home Car Carpet Stairs Pet Hair Cleaning | CY9: B09VKPHJVF | CZ9: Higoom 4 in 1 Cordless Handheld Vacuum Cleaner Car Vacuum Cleaner 22000PA Strong Suction Mini Vacuum Dust Blower Can be Used for Home Car | DA9: B0DJFMT6LS | DB9: B0CXCQR22Z | DC9: 23.99 | DD9: 23.4 | DE9: 24 | DF9: 600 | DG9: 702 | DJ9: 5908 | DK9: 24 | DL9: 702 | DM9: 600 | DN9: 14394 | DO9: 23.99 | DP9: Handheld Car Vacuum Cleaner, 15000Pa Powerful Vacuum Cleaner Cordless, 3 in 1 Lightweight Vacuum & Blower Dust Buster, LED Display, USB Rechargeable Mini Cleaner for Car, Home and Pet Hair Cleaning
CP10: mini hoover | CQ10: 96946 | CR10: -0.0553 | CS10: -0.2516 | CT10: 0.0227 | CU10: 0.0199 | CV10: Handheld Vacuum Cleaner Powerful Suction Portable Lightweight Hand Held Vacuum Cordless with 25-30Mins Long Runtime Rechargeable Battery Quick Charge for Home Car Carpet Stairs Pet Hair Cleaning | CW10: B09VKPHJVF | CX10: Handheld Vacuum Cordless 9000Pa Powerful Car Vacuum Cleaner Rechargeable Portable Lightweight Mini Vacuum Cleaner USB Car Vacuum Cleaner Car Cleaner for Pet Hair Car Home Office Kitchen | CY10: B0CKVFMYH4 | CZ10: Nctoberows Handheld Vacuum Cleaner Cordless 22000Pa Powerful Car Mini Vacuum Cleaner Rechargeable Portable Lightweight dust catcher for Home Car Carpet Stairs Pet Hair Deep Cleaning | DA10: B0DJ2YVV6F | DB10: B0FFSTYXML | DC10: 29.99 | DD10: 14.066667 | DE10: 26 | DF10: 400 | DG10: 422 | DJ10: 5985 | DK10: 26 | DL10: 422 | DM10: 400 | DN10: 12000 | DO10: 29.99 | DP10: Grixz Handheld Vacuum Cleaner, 22000Pa Powerful Car Vacuum Cleaner Cordless, Lightweight Mini Vacuum & Air Duster, Rechargeable Portable Vacuum for Car, Home, Office, Kitchen
CP11: handheld vacuum | CQ11: 83977 | CR11: 0.2376 | CS11: -0.2902 | CT11: 0.0226 | CU11: 0.0143 | CV11: Shark Handheld Cordless Vacuum Cleaner with Pet Tool Crevice Tool & Dusting Brush 80 W 0.45 liters 10 Minute Run-Time Washable Filter Black & Yellow CH950UKT | CW11: B08M9JQ1J1 | CX11: Vax Gator Cordless Handheld Vacuum Cleaner | Lightweight Quick Cleaning | Built-in Crevice Tool - H85-GA-B10 0.3 Litre White and Orange | CY11: B015QZH2EU | CZ11: Handheld Vacuum Cleaner Powerful Suction Portable Lightweight Hand Held Vacuum Cordless with 25-30Mins Long Runtime Rechargeable Battery Quick Charge for Home Car Carpet Stairs Pet Hair Cleaning | DA11: B09VKPHJVF | DB11: B0DXKCZD5Z | DC11: 26.99 | DD11: 38.366667 | DE11: 28 | DF11: 600 | DG11: 1151 | DJ11: 6205 | DK11: 28 | DL11: 1151 | DM11: 600 | DN11: 16194 | DO11: 26.99 | DP11: Semflagree Handheld Mini Vacuum 4 in 1 Cordless, 23000PA Powerful Strong Cyclonic Suction USB Rechargeable Portable Car Vacuum Cleaner Car Cleaner for Pet Hair, Car, Home, Office, Kitchen
CP12: hand held hoover | CQ12: 75659 | CR12: 0.2587 | CS12: -0.167 | CT12: 0.0253 | CU12: 0.0248 | CV12: Shark Handheld Cordless Vacuum Cleaner with Pet Tool Crevice Tool & Dusting Brush 80 W 0.45 liters 10 Minute Run-Time Washable Filter Black & Yellow CH950UKT | CW12: B08M9JQ1J1 | CX12: Handheld Vacuum Cleaner Powerful Suction Portable Lightweight Hand Held Vacuum Cordless with 25-30Mins Long Runtime Rechargeable Battery Quick Charge for Home Car Carpet Stairs Pet Hair Cleaning | CY12: B09VKPHJVF | CZ12: Nctoberows Handheld Vacuum Cleaner Cordless 22000Pa Powerful Car Mini Vacuum Cleaner Rechargeable Portable Lightweight dust catcher for Home Car Carpet Stairs Pet Hair Deep Cleaning | DA12: B0DJ2YVV6F | DB12: B0F1YKY242 | DC12: 25.99 | DD12: 15.666667 | DE12: 30 | DF12: 500 | DG12: 470 | DJ12: 6935 | DK12: 30 | DL12: 470 | DM12: 500 | DN12: 12995 | DO12: 25.99 | DP12: ONEWEST Handheld Vacuum Cleaner,15000pa Car Vacuum Cleaner Cordless Powerful,4 IN 1 USB Rechargeable Portable Mini Vacuum,Lightweight Hand Vacuum for Car,Keyboard,Pet Hair,Home,Office - Black
CP13: car vacuum cleaner cordless powerful | CQ13: 68512 | CR13: 0.0573 | CS13: -0.1873 | CT13: 0.0225 | CU13: 0.0162 | CV13: Handheld Vacuum Cleaner Powerful Suction Portable Lightweight Hand Held Vacuum Cordless with 25-30Mins Long Runtime Rechargeable Battery Quick Charge for Home Car Carpet Stairs Pet Hair Cleaning | CW13: B09VKPHJVF | CX13: Wirelume Handheld Car Vacuum Cleaner Cordless Powerful 22000Pa Strong Cyclonic Suction Blowing Brushless Motor Mini Hand Held Portable Rechargeable Lightweight for Pet Hair Vehicle Home Office Purple | CY13: B0D45V1YXT | CZ13: Semflagree Handheld Mini Vacuum 4 in 1 Cordless 23000PA Powerful Strong Cyclonic Suction USB Rechargeable Portable Car Vacuum Cleaner Car Cleaner for Pet Hair Car Home Office Kitchen | DA13: B0DXKCZD5Z | DB13: B0F187FF99 | DC13: 19.49 | DD13: 14.8 | DE13: 36 | DF13: 400 | DG13: 444 | DJ13: 11184 | DK13: 36 | DL13: 444 | DM13: 400 | DN13: 7796 | DO13: 19.49 | DP13: Handheld Vacuum Cleaner, Small Portable Car Vacuum Cleaner Cordless Powerful 7000Pa, 3 in 1 Car Hoovers Cordless Powerful USB Rechargeable, Air Duster & Blower for Car, Home Office (Black-logo)
CP14: handheld vacuums | CQ14: 100456 | CR14: -0.1738 | CS14: -0.4709 | CT14: 0.0125 | CU14: 0.0082 | CV14: Shark Handheld Cordless Vacuum Cleaner with Pet Tool Crevice Tool & Dusting Brush 80 W 0.45 liters 10 Minute Run-Time Washable Filter Black & Yellow CH950UKT | CW14: B08M9JQ1J1 | CX14: Shark WandVac 1.0 Cordless Handheld Vacuum Cleaner Small & Lightweight Powerful Suction Handheld Vacuum with Duster/Crevice and Multi-Surface Tools Charging Base Grey WV200UK | CY14: B07H5XMVGD | CZ14: Handheld Vacuum Cleaner Powerful Suction Portable Lightweight Hand Held Vacuum Cordless with 25-30Mins Long Runtime Rechargeable Battery Quick Charge for Home Car Carpet Stairs Pet Hair Cleaning | DA14: B09VKPHJVF | DB14: B0DXPSYS1N | DC14: 39.98 | DD14: 8.3666667 | DE14: 40 | DF14: 200 | DG14: 251 | DJ14: 13255 | DK14: 40 | DL14: 251 | DM14: 200 | DN14: 7996 | DO14: 39.98 | DP14: Handheld Vacuum Cleaner, 22000Pa Car Vacuum Cleaner Powerful, with Brushless Motor Rechargeable High Power Handheld Vacuum & Air Duster, Cleaning for Kitchen, Car, Computer desktop, Pet, Home
CP15: small hoover | CQ15: 65578 | CR15: -0.0286 | CS15: -0.1825 | CT15: 0.0079 | CU15: 0.0075 | CV15: Amazon Basics 2-in-1 Corded Upright Vacuum Cleaner ECO Motor HEPA filtration Lightweight Stick Black | CW15: B07SH66PXX | CX15: VYTRONIX HSV3 Upright Vacuum Cleaner | Lightweight 3-in-1 Compact Powerful Multifunction Corded Stick & Handheld Vacuum | 600 Watt 5 Metre Power Cord | 2.5Kg | CY15: B09RMQ1XLL | CZ15: Handheld Vacuum Cleaner Powerful Suction Portable Lightweight Hand Held Vacuum Cordless with 25-30Mins Long Runtime Rechargeable Battery Quick Charge for Home Car Carpet Stairs Pet Hair Cleaning | DA15: B09VKPHJVF | DB15: B0DJ9CSK63 | DC15: 19.94 | DD15: 4.6666667 | DE15: 46 | DF15: 100 | DG15: 140 | DJ15: 18723 | DK15: 46 | DL15: 140 | DM15: 100 | DN15: 1994 | DO15: 19.94 | DP15: VOLTATECH 13000PA Handheld Vacuum Cleaner Cordless - Dual Gear, Powerful, Hand held Vacuum Cordless, car hoover, Mini, Wireless & Portable, Type-C – Black
... CP21: handheld vacuum cleaner cordless | CQ21: 38290 | CR21: 0.683 | CS21: -0.1409 | CT21: 0.0151 | CU21: 0.0172 | CV21: Shark Handheld Cordless Vacuum Cleaner with Pet Tool Crevice Tool & Dusting Brush 80 W 0.45 liters 10 Minute Run-Time Washable Filter Black & Yellow CH950UKT | CW21: B08M9JQ1J1 | CX21: Handheld Vacuum Cleaner Powerful Suction Portable Lightweight Hand Held Vacuum Cordless with 25-30Mins Long Runtime Rechargeable Battery Quick Charge for Home Car Carpet Stairs Pet Hair Cleaning | CY21: B09VKPHJVF | CZ21: Higoom 4 in 1 Cordless Handheld Vacuum Cleaner Car Vacuum Cleaner 22000PA Strong Suction Mini Vacuum Dust Blower Can be Used for Home Car | DA21: B0DJFMT6LS | DB21: B0F32MV4J3 | DC21: 29.99 | DD21: 8.4 | DE21: 60 | DF21: 200 | DG21: 252 | DJ21: 29196 | DK21: 60 | DL21: 252 | DM21: 200 | DN21: 5998 | DO21: 29.99 | DP21: DEUKNICE Handheld Vacuum Cleaner, 22000Pa Powerful Car Vacuum Cleaner Cordless, Portable Rechargeable Air Duster, Mini Lightweight Vacuum for Car, Home
DB22: B0FH1K5PGW | DC22: 27.99 | DD22: 0.36666667 | DE22: 71 | DF22: 50 | DG22: 11 | DJ22: 35465 | DK22: 71 | DL22: 11 | DM22: 50 | DN22: 500 | DO22: 27.99 | DP22: Bemkia Cordless Handheld Vacuum Cleaner, 21000Pa Powerful Suction, 4-in-1 Portable Car Hoovers with Washable HEPA Filter, Ideal for Pet Hair, Home, Office, Vehicle Cleaning (Black)
DB23: B0F9XTZDGW | DC23: 39.99 | DD23: 0.73333333 | DE23: 73 | DF23: 50 | DG23: 22 | DJ23: 36527 | DK23: 73 | DL23: 22 | DM23: 50 | DN23: 1100 | DO23: 39.99 | DP23: Handheld Vacuum Cleaner, 25000Pa/120W Powerful Mini Car Vacuum Cleaner, 9000mAh Rechargeable Battery, Portable Lightweight Car Hoover, Air Duster Air Blower for Car, Office and Home Deep Cleaning
DB24: B0F9W71RQQ | DC24: 55.99 | DD24: 1.0666667 | DE24: 75 | DF24: 50 | DG24: 32 | DJ24: 36837 | DK24: 75 | DL24: 32 | DM24: 50 | DN24: 1500 | DO24: 55.99 | DP24: Lyiazsoy Car Vacuum Cleaner Cordless,22000PA High Power Mini Vacuum Cleaner,Rechargeable Handheld Vacuum Cordless,car hoovers for Pet Hair, Home, Office, Kitchen(Gold Black)
DB25: B0F2H6YTVS | DC25: 22.79 | DD25: 11.266667 | DE25: 76 | DF25: 200 | DG25: 338 | DJ25: 37165 | DK25: 76 | DL25: 338 | DM25: 200 | DN25: 6837 | DO25: 22.79 | DP25: Portable Handheld Car Vacuum Cleaner 9000PA,4 in 1 Air Duster and Vacuum Cleaner with Multi-Nozzles,120W High Power Lightweight Mini Rechargeable Cordless Hoover for Car Home Office, Pet Hair
DB26: B0DXQ34XZN | DC26: 26.98 | DD26: 4.6666667 | DE26: 80 | DF26: 50 | DG26: 140 | DJ26: 38198 | DK26: 80 | DL26: 140 | DM26: 50 | DN26: 1349 | DO26: 26.98 | DP26: LUCUHM Handheld Vacuum Cleaner Cordless - 16000Pa Powerful Dust Buster Handheld Car Vacuum Cleaner - Portable Lightweight USB Rechargeable for Car, Pet Hair, Office, Home, Kitchen (Grey)
DB27: B0F484XM47 | DC27: 19.99 | DD27: 12.466667 | DE27: 82 | DF27: 200 | DG27: 374 | DJ27: 39916 | DK27: 82 | DL27: 374 | DM27: 200 | DN27: 3998 | DO27: 19.99 | DP27: Handheld Vacuum Cleaner Powerful Car Vacuum Cordless Cleaner 4 in 1 Mini Car Vacuum Rechargeable Air Blower Cleaner with Extension Brush and Nozzles for Car,Office,Home with Washable HEPA Filter Grey
DB28: B0C1C73WS9 | DC28: 18.96 | DD28: 4.0333333 | DE28: 92 | DF28: 50 | DG28: 121 | DJ28: 50285 | DK28: 92 | DL28: 121 | DM28: 50 | DN28: 948 | DO28: 18.96 | DP28: YWSS Cordless Mini Handheld Vacuum, Electric Air Duster & Vacuum Cleaner 2 in 1 Rechargeable, Portable for Home, Office and Car
DB29: B0CDP5V9W8 | DC29: 18.98 | DD29: 3.1 | DE29: 93 | DF29: 50 | DG29: 93 | DJ29: 50292 | DK29: 93 | DL29: 93 | DM29: 50 | DN29: 949 | DO29: 18.98 | DP29: Mini Car Vacuum Cleaner,Handheld Vacuum Cordless,2 in 1 Rechargeable Vacuum Cleaner & Blower,Small Wireless Car Vacuum with 6000Pa Suction Power,Dust Buster,Portable Hoover Vacuum for Car Home Office
DB31: 平均售价是 | DC31: 28.49
S53: B0DBLKGKFZ | U53: Marke: Royalswill | Besonderes Merkmal: Kabellos | Filtertyp: HEPA Filter | Enthaltene Komponenten: Flachsaugdüse, Borstenbürstendüse, Kurze Bürstendüse, Milbenentfernungs-Bürstenkopf, Ladegerät, Betriebsanleitung | Kabellos Ja/Nein?: Ja | V53: Royalswill | W53: https://www.amazon.de/Royalswill/b/ref=bl_dp_s_web_64944844031?ie=UTF8&node=64944844031&field-lbr_brands_browse-bin=Royalswill | X53: Milbensauger für matratzen mit UV-Licht, Handstaubsauger, Schmutzbehälter 200 ml, Milbenstaubsauger mit Staubmilben-Sensor, 10kpa Anziehung Milben Staubsauger Antimilben-Staubsauger entfernt 99,9% | Z53: Langlebig und Zuverlässig --- Unser Milbensauger mit uv licht und HEPA filter wurde mit höchster Sorgfalt und Qualitätsstandards entwickelt, um eine effektive Milbenbekämpfung zu gewährleisten. Sollten Sie aus irgendeinem Grund nicht zufrieden sein, kontaktieren Sie uns einfach und wir werden eine Lösung finden. Effiziente Milbenentfernung --- Milbensauger verwendet eine innovative UV-Desinfektionstechnologie, mit der Staub, Milben und Bakterien tief entfernt werden können. Milbensauger für matratzen mit Zyklon-System bietet der Milbenstaubsauger eine effiziente Staubseparation, mit einem UV-C-Licht und einer Ultraschalltechnologie ausgestattet, die 99,9 % der Mikroorganismen wie Bakterien. Milbensauger Kabellos --- Neuester verbesserte kabelloser Milbensauger, den Sie überall hin bewegen können und vollständig von der Kabelbindung befreit sind, um die Milbenentfernung in der ganzen Familie zu realisieren, ohne sich um lockere Stecker, Stolpern über das Kabel, Kabelverwicklungen usw. sorgen zu müssen, um Sicherheitsrisiken zu beseitigen. Besonders breite Saugkraft --- Mit einer Leistung von 10Kpa Vakuum-Saugkraft der Antimilben-Staubsauger bis zu 99,9% der Milben entfernen. Durch die Kombination von UV-Licht und Vibration werden die Milben effektiv abgetötet und können dann mit dem Staubsauger aufgesaugt werden.Lang anhaltende Hemmung der Neubildung von Bakterien und Milben auf der Liegefläche. Leicht zu Reinigen --- Dieser milbensauger kabellos hat 200ML-Kapazitäts-Staubkasten und mit visuellem Staubkasten ist der Reinigungseffekt deutlich sichtbar, der einfach abnehmbar ist und leicht gereinigt werden kann. Sie müssen sich keine Sorgen machen, dass die Saugkraft nach der Reinigung nachlässt oder dass der Staubbehälter verstopft. | AB53: https://www.amazon.de/dp/B0DBLKGKFZ?psc=1 | AC53: https://images-na.ssl-images-amazon.com/images/I/61KKb6XIn2L._AC_US600_.jpg | AD53: B0DBLKGKFZ | AE53: Küche, Haushalt & Wohnen:Haushaltsreiniger & Staubsauger:Staubsauger:Matratzensauger | AF53: Küche, Haushalt & Wohnen | AG53: 1162356 | AH53: 1909301 | AI53: 0.8 | AJ53: Matratzensauger | AK53: 51 | AL53: 1 | AM53: -1 | AN53: 41 | AQ53: 1 | AR53: 40.67 | AY53: 0 | BA53: 0.85 | BC53: 45502 | BD53: 242 | BE53: FBM | BF53: 7 | BG53: 1 | BH53: Royalswill | BI53: FBM | BJ53: CN | BK53: 公司名称：Guangzhoushi Junjia Nengyuan Youxiangongsi 公司类型：Unternehmen in Privatbesitz 电话号码：+86 173 2863 3420 办公地址： Jinzhuxilu 4hao Lichengjie Guangzhoushi Zengchengqu Guangdong 511300 CN | BL53: https://www.amazon.de/gp/help/seller/at-a-glance.html/ref=dp_merchant_link?seller=AO1YDDAXLQTYR | BW53: 1.1 kg | BX53: 1.10 kg
S54: B0DNSG966L | U54: Marke: Kamanan | Formfaktor: Handheld | Farbe: Rosa | Produktabmessungen: 10L x 10B x 10H Millimeter | Hersteller: Kamanan | V54: Kamanan | W54: https://www.amazon.de/Kamanan/b/ref=bl_dp_s_web_64947579031?ie=UTF8&node=64947579031&field-lbr_brands_browse-bin=Kamanan | X54: Kamanan Tragbarer Kabelloser Matratzenstaubsauger,10 KPa Milbensauger Matratzenreiniger Milbensauger für Matratzen,Milbenstaubsauger Bettmatratzen-Staubsauger mit UV-Licht(Rosa) | Z54: 10kPa Starke Absaugung:matratzensauger Pulsierende Pad nimmt schwebenden Modus, vibrierende 8000 Mal pro Minute,Milbensauger kann effektiv lösen den Staub und Schmutz tief in der Matratze,Handstaubsauger für Milben 10kpa starke Saugmodus kann leicht saugen Staub und Schmutz,milbensauger mit akku Heißluftentfeuchtung hält die Matratze trocken zu allen Zeiten und verhindert Milben von Zucht Hocheffizientes Filtersystem:Kabelloser Matratzenstaubsauger Das versiegelte Filtersystem kann effektiv saubere Luft und Staub ohne Leckage trennen.matratzensauger Einfach zu demontieren und zu reinigen.Milbensauger Der Filter ist waschbar und wiederverwendbar. Sie müssen sich keine Sorgen machen, dass die Saugleistung nachlässt oder der Staubsammelbehälter nach der Reinigung verstopft Leicht und Kompakt Milbensauger: Matratzenreiniger Handstaubsauger Mit drei Funktionen von Hochfrequenz-Flattern, starke Absaugung und violettes Licht eindringen,matratzensauger mit doppelschichtigen pulsierenden Pads für eine größere Reinigungsfläche und höhere Reinigungseffizienz.Milbensauger hat 50 ℃ Heißluftentfeuchtung, Milben geeignet für das Überleben der Umgebungstemperatur von etwa 25-32 ℃, 50 ℃ hohe Temperatur kann effektiv töten Milben Bass Lärmreduzierung: Unsere Milbensauger für Matratzen arbeitet leiser, das Geräusch ist etwa 50 Dezibel, so dass Sie ruhig schlafen können, diese kann sanft getan werden, ohne zu stören,milbensauger mit uv licht hat eine Rauschunterdrückungsfunktion, milbensauger für matratzen doppelte hocheffiziente Filtration und Anionen-Luftreinigung, die helfen können, die Gesundheit Ihrer Familie zu schützen Schnurlos und Tragbar: Mit dem neuesten Design von Matratzensauger, müssen Sie sich keine Sorgen über die Länge des Netzkabels während des Gebrauchs machen, matratzensauger ermöglicht es Ihnen, überall ohne externe Stromversorgung zu reinigen,milbenstaubsauger für matratzen breite Saugöffnung mit Anti-Leck-Pads, um zu verhindern, dass Staub aus der Saugöffnung fällt, wenn es aufhört zu arbeiten, kompakt und tragbar, können Sie es jederzeit und überall verwenden | AB54: https://www.amazon.de/dp/B0DNSG966L?psc=1 | AC54: https://m.media-amazon.com/images/I/41QwPW7ZqRL._AC_US600_.jpg | AD54: B0DNSG966L | AE54: Küche, Haushalt & Wohnen:Haushaltsreiniger & Staubsauger:Staubsauger:Matratzensauger | AF54: Küche, Haushalt & Wohnen | AG54: 1213797 | AI54: 0 | AJ54: Matratzensauger | AK54: 52 | AQ54: 1 | AR54: 26.59 | AY54: 0 | BA54: 0 | BC54: 45617 | BD54: 127 | BE54: FBA | BG54: 1 | BH54: radishde | BI54: FBA | BJ54: CN | BK54: 公司名称：WuHanShiJiaLaiBoDianZiShangWuYouXianGongSi 公司类型：Unternehmen in Privatbesitz 电话号码：+86 153 2710 1426 办公地址： 2HaoDi1Dong5Ceng21Shi CaiDianQu DunKouXiaoQu WuHanShi 430100 CN | BL54: https://www.amazon.de/gp/help/seller/at-a-glance.html/ref=dp_merchant_link?seller=A3UMTMFY4BME13 | BQ54: Y | BW54: 910 Gramm | BX54: 910.00 g | BY54: 1 x 1 x 1 cm | BZ54: 1.00 x 1.00 x 1.00 cm
S55: B0CTCMLZSQ | U55: Marke: Kevsuvqin | Besonderes Merkmal: UV-Licht, Hochpräziser Milbensensor, Staub mit einem Klick entleeren, 2-stufige Saugleistung einstellbar, Patentierte Magnetwalzenbürste | Filtertyp: HEPA Filter | Enthaltene Komponenten: HEPA Filter, double dust box | Kabellos Ja/Nein?: Nein | V55: Kevsuvqin | W55: https://www.amazon.de/Kevsuvqin/b/ref=bl_dp_s_web_64958027031?ie=UTF8&node=64958027031&field-lbr_brands_browse-bin=Kevsuvqin | X55: Kevsuvqin Milbensauger für Matratzen mit Staubmilben-Sensor & Intelligente Anzeige, 700W 18KPA Milbenstaubsauger mit 2 Saugstufen, Milbensauger mit UV Licht & Ultraschall, Entfernt 99% Staub,Allergene | Z55: 🏆【Testsieger】: Der milben staubsauger ist mit einem bürstenlosen 700W Motor ausgestattet, der eine starke Saugleistung von bis zu 18Kpa bietet. In Kombination mit dem Hausstaubmilben-Erkennungssystem und dem Smart Display können Sie Milben, Staub und Haare ganz einfach von Matratzen, Decken und Sofas entfernen. Dank innovativer Geräuschreduzierungstechnologie beträgt der Geräuschpegel weniger als 80 Dezibel. Im Vergleich zu ähnlichen Produkten haben Sie ein besseres Benutzererlebnis. ⭐【Effiziente Milbenentfernung】: Die Hochgeschwindigkeits-Metallwalzenbürste hat eine Schlagfrequenz von bis zu 40.000 Mal/Minute, was dreimal so viel ist wie bei herkömmlichen matratzensauger, wodurch ein kraftvolles Schlagen erzielt wird. Hochfrequente Vibrationen können tief im Inneren verborgenen Staub, Milben und Allergene problemlos entfernen. Die Walzenbürste verfügt über ein exklusives patentiertes Design und kann in einer Sekunde ohne Werkzeug zerlegt werden. 🧹【Auf einen Blick klar】: Der milbensauger für matratzen testsieger nutzt den fortschrittlichsten Hausstaubmilbensensor und die intelligente LED-Anzeige, um Milben und Staub in Echtzeit zu überwachen. Wenn mehr Milben und Staub eingeatmet werden, wird das Licht rot und die Saugleistung erhöht sich entsprechend. Wenn das Licht blau wird, ist die Reinigung des Bereichs abgeschlossen. (Drücken Sie lange auf die rote Taste, um die Leistung manuell auf Maximum einzustellen.) ☀️【UV & Ultraschall】: Mithilfe der Dual-Reinigungstechnologie, 40.000 Hz Ultraschall und 253,7 nm U/V-LED-Licht können bis zu 99,99 % der Allergene effektiv entfernt werden. Die Unterseite des Milbensaugers erzeugt eine hohe Temperatur von 65 °C, wodurch die Vermehrung allergischer Milben wirksam verhindert werden kann. (Der Milbensauger erzeugt eine hohe Temperatur zur Desinfektion und ist nicht überhitzt. Bitte seien Sie versichert.) 🥇【Doppelter Staubbecher】: Im Gegensatz zu anderen matratzensauger, die mit einem einzelnen Staubbecher ausgestattet sind, verfügt der doppelte Staubbecher über ein konisches Design und ein 5-lagiges Filtersystem. Dieses Design trennt Allergene, Staub und Haare Schicht für Schicht, sodass der Filter auch bei längerem Gebrauch nicht verstopft und die Saugleistung immer stark bleibt. Ausgestattet mit HEAP-Filterelementen höchster Qualität, die nach der Reinigung wiederverwendet werden können. 💦【Leicht zu reinigen】: Der doppelte Staubbecher und die Walzenbürste können einfach mit einem Klick zerlegt werden, und alle Teile können leicht gereinigt werden, einschließlich des Staubsammelbehälters, der Metallwalzenbürste und des Filterelements. (Hinweis: Alle Teile müssen nach der Reinigung vor dem Gebrauch vollständig trocken sein, da sonst der bürstenlose Motor beschädigt wird.) 🎁【100 % Zufriedenheitsgarantie】: 1 Milben staubsauger, 1 HEAP-Filter (Stufe P10). Wir sind bestrebt, unseren Kunden bessere Produkte und Dienstleistungen zu bieten, und versprechen, dass wir bei Qualitätsproblemen mit dem Produkt eine einjährige Herstellergarantie und einen lebenslangen, freundlichen Kundenservice gewähren, keine Rückgabe, direkter Ersatz. Wenn Sie Fragen zum Produkt haben, kontaktieren Sie uns bitte und wir helfen Ihnen gerne weiter. | AB55: https://www.amazon.de/dp/B0CTCMLZSQ?psc=1 | AC55: https://m.media-amazon.com/images/I/41oR7Ui-LXL._AC_US600_.jpg | AD55: B0CTCMLZSQ | AE55: Küche, Haushalt & Wohnen:Haushaltsreiniger & Staubsauger:Staubsauger:Matratzensauger | AF55: Küche, Haushalt & Wohnen | AG55: 1254414 | AI55: 0 | AJ55: Matratzensauger | AK55: 53 | AM55: -1 | AQ55: 1 | AR55: 89.99 | AV55: 10 | AX55: 4 | AY55: 0 | BA55: 0 | BC55: 45332 | BD55: 412 | BE55: NA | BF55: 7 | BG55: 1 | BH55: Dexcosut | BI55: NA | BJ55: CN | BK55: 公司名称：shenzhenlonggangqubantiandaikesutebaihuodian 公司类型：Unternehmen in Privatbesitz 电话号码：+8613632801133 办公地址： ban tian jie dao di wu yuan she qu wan ke di wu yuan she qu zi yue shan (jiu qi) 1dong 4202 shenzhen longgang guangdong 518100 CN | BL55: https://www.amazon.de/gp/help/seller/at-a-glance.html/ref=dp_merchant_link?seller=A340R00BJZF69A | BW55: 2,2 Kilogramm | BX55: 2.20 kg | BY55: 31 x 27,5 x 22,5 cm | BZ55: 31.00 x 27.50 x 22.50 cm
S56: B0D4YZVBSY | U56: Marke: Probuk | Besonderes Merkmal: Kabellos | Filtertyp: Scheibe | Enthaltene Komponenten: HEPA | Kabellos Ja/Nein?: Ja | V56: Probuk | W56: https://www.amazon.de/s/ref=bl_dp_s_web_0?ie=UTF8&search-type=ss&index=kitchen-de&field-keywords=Probuk | X56: Probuk Milbensauger, Staubsauger für Textilmatratzen mit UV-Licht, waschbarer HEPA-Filter und 200 ml Staubbehälter, sehr geeignet für Allergiker | Z56: MILF REMOVAL PERFORMANCE - Dieser Matratzenreiniger ist mit einem eingebauten 50 W Lithium-Akku ausgestattet, der eine starke Saugleistung von 10 kPa bietet und 8600 Schläge pro Minute verwendet, um Hausstaubmilben schnell tief zu schütteln. Mit seinem violetten Licht von 254,7 nm sorgt er für die vollständige Entfernung von Milben. FÜR ALLE STOFFE IM HAUSE - Der Milbensauger ist ideal zum Saugen und Desinfizieren von Matratzen, Bettdecken, Kissen, Bettwäsche oder jeder anderen Oberfläche. HEPA-Filter - Der waschbare und wiederverwendbare HEPA-Filter bewältigt auch kleine Schwebeteilchen und ist somit ideal für Allergiker. EINFACHE BEDIENUNG - Mit einem Geräuschpegel von nur 40 dB sorgt dieser Bettstaubsauger für einen leisen Betrieb, so dass Sie ihn verwenden können, ohne Ihren Schlaf oder Ihre täglichen Aktivitäten zu stören. Verabschieden Sie sich von lästigen Geräuschen herkömmlicher Staubsauger! KABEL UND EFFIZIENT - Dieser Matratzenstaubsauger ist kabellos, sodass Sie sich ohne Einschränkungen frei bewegen können. Der eingebaute Lithium-Akku sorgt für dauerhafte Leistung, sorgt für eine effiziente Reinigung und eliminiert die Notwendigkeit für Kabel oder Steckdosen. Verabschieden Sie sich von lästigem Kabelsalat! | AB56: https://www.amazon.de/dp/B0D4YZVBSY?psc=1 | AC56: https://m.media-amazon.com/images/I/31p830ONKOL._AC_US600_.jpg | AD56: B0D4YZVBSY | AE56: Küche, Haushalt & Wohnen:Haushaltsreiniger & Staubsauger:Staubsauger:Matratzensauger | AF56: Küche, Haushalt & Wohnen | AG56: 1358229 | AI56: 0 | AJ56: Matratzensauger | AK56: 54 | AQ56: 1 | AR56: 32.59 | AV56: 11 | AX56: 3.4 | AY56: 0 | BA56: 0 | BC56: 45469 | BD56: 275 | BE56: NA | BF56: 8 | BG56: 1 | BH56: CZWTingwei | BI56: NA | BJ56: CN | BK56: 公司名称：Wuhan Zhi Wei Technology Co., Ltd 公司类型：Unternehmen in Privatbesitz 电话号码：+8613260615878 办公地址： 中南路街道武珞路230号 绿洲广场5层B-3号-75 武汉市 武昌区 湖北 430064 CN | BL56: https://www.amazon.de/gp/help/seller/at-a-glance.html/ref=dp_merchant_link?seller=A2TSUDJWZ9XMKN | BW56: 950 Gramm | BX56: 950.00 g | BY56: 30 x 20 x 10 cm | BZ56: 30.00 x 20.00 x 10.00 cm
S57: B0D83SRY9V | U57: Marke: Redcoutt | Besonderes Merkmal: UV-Licht | Filtertyp: HEPA Filter | Enthaltene Komponenten: HEPA-Filter | Kabellos Ja/Nein?: Nein | V57: Redcoutt | W57: https://www.amazon.de/s/ref=bl_dp_s_web_0?ie=UTF8&search-type=ss&index=kitchen-de&field-keywords=Redcoutt | X57: Redcoutt Milbensauger für Matratzen 16KPa Saugkraft und UV-Licht-Technologie für eine effektive Entfernung von 99,9% der Allergene. Ideal für Matratzen, Betten, Sofas und Polstermöbel | Z57: 【Leistungsstarke 16KPa Saugkraft】Unser Milbensauger verfügt über eine beeindruckende Saugkraft von 16KPa, die eine gründliche Reinigung Ihres Bettes gewährleistet und effektiv Staub, Schmutz sowie lästige Tierhaare entfernt. Genießen Sie eine sauberere und gesündere Schlafumgebung! 【UV- & Ultraschall-Technologie】Ausgestattet mit fortschrittlicher UV- und Ultraschall-Technologie geht dieser Handstaubsauger über die oberflächliche Reinigung hinaus. Er dringt tief in Ihre Matratze ein und eliminiert bis zu 99,9 % der Allergene, was zu besserem Schlaf und allgemeinem Wohlbefinden beiträgt. 【Doppelbehälter-Design】Eine Kammer für die Filtration, die andere für die Staubsammlung. Dieses innovative Dual-Cup-Design entfernt effizient Milben und Allergene aus der Luft, gewährleistet eine überlegene Filtration, verhindert Filterverstopfungen und erhält eine starke, langlebige Saugleistung. 【Hohe Heizfunktion】Unser Milbensauger verfügt über eine hohe Heizfunktion, die Temperaturen bis zu 60 °C (140 ℉) erreicht und Allergene in der Matratze effektiv weiter eliminiert. So bieten Sie sich und Ihrer Familie ein hygienisches Schlafumfeld. 【Lange Arbeitsreichweite】Das lange 3 m-Kabel reicht aus, um die gesamte Oberfläche eines Sofas oder einer King-Size-Matratze zu reinigen, ohne ständig die Steckdose wechseln zu müssen. 【Vielseitig & Einfach zu Bedienen】Egal ob Sie Ihre Matratze, Ihr Sofa oder Ihre Polster reinigen möchten, unser Handstaubsauger ist Ihre ideale Lösung. Sein leichtes und ergonomisches Design ermöglicht eine einfache Handhabung, während der abnehmbare Staubbehälter ein müheloses Entleeren garantiert. | AB57: https://www.amazon.de/dp/B0D83SRY9V?psc=1 | AC57: https://m.media-amazon.com/images/I/51LjSaAmb9L._AC_US600_.jpg | AD57: B0D83SRY9V | AE57: Küche, Haushalt & Wohnen:Haushaltsreiniger & Staubsauger:Staubsauger:Matratzensauger | AF57: Küche, Haushalt & Wohnen | AG57: 1441907 | AH57: -162213 | AI57: -0.2 | AJ57: Matratzensauger | AK57: 55 | AM57: -1 | AQ57: 1 | AR57: 69.99 | AV57: 15 | AW57: 2 | AX57: 3.7 | AY57: 0.5 | AZ57: 5.95 | BA57: 0.77 | BC57: 45524 | BD57: 220 | BE57: FBA | BF57: 10 | BG57: 1 | BH57: Wenzhawenda | BI57: FBA | BJ57: CN | BK57: 公司名称：shenzhenshitaiyidianziyouxiangongsi 公司类型：Unternehmen in Privatbesitz 电话号码：+8618476699698 办公地址： 深南中路 统建办公楼2栋6B 深圳市 福田 广东 518000 CN | BL57: https://www.amazon.de/gp/help/seller/at-a-glance.html/ref=dp_merchant_link?seller=A13YVB7LMWVCUM | BP57: Y | BW57: 1,98 Kilogramm | BX57: 1.98 kg | BY57: 35,2 x 28,8 x 22 cm | BZ57: 35.20 x 28.80 x 22.00 cm | CA57: 1.98 kg | CB57: 35.2 x 28.8 x 22 cm
S58: B0DBLLLLKV | U58: Marke: Royalswill | Besonderes Merkmal: Kabellos | Filtertyp: HEPA Filter | Enthaltene Komponenten: Flachsaugdüse, Borstenbürstendüse, Kurze Bürstendüse, Milbenentfernungs-Bürstenkopf, Ladegerät | Kabellos Ja/Nein?: Ja | V58: Royalswill | W58: https://www.amazon.de/Royalswill/b/ref=bl_dp_s_web_64944844031?ie=UTF8&node=64944844031&field-lbr_brands_browse-bin=Royalswill | X58: Milbensauger für matratzen mit UV-Licht & Staubmilben-Sensor, 10kpa Antimilben-Staubsauger entfernt 99,9%, Handstaubsauger für Matratzen, Schmutzbehälter 200ml, Milbenstaubsauger für Betten, Sofas | Z58: Milbensauger Kabellos --- Neuester verbesserte kabelloser Milbensauger, den Sie überall hin bewegen können und vollständig von der Kabelbindung befreit sind, um die Milbenentfernung in der ganzen Familie zu realisieren, ohne sich um lockere Stecker, Stolpern über das Kabel, Kabelverwicklungen usw. sorgen zu müssen, um Sicherheitsrisiken zu beseitigen. Effiziente Milbenentfernung --- Milbensauger verwendet eine innovative UV-Desinfektionstechnologie, mit der Staub, Milben und Bakterien tief entfernt werden können. Milbensauger für matratzen mit Zyklon-System bietet der Milbenstaubsauger eine effiziente Staubseparation, mit einem UV-C-Licht und einer Ultraschalltechnologie ausgestattet, die 99,9 % der Mikroorganismen wie Bakterien. Besonders breite Saugkraft --- Mit einer Leistung von 10Kpa Vakuum-Saugkraft der Antimilben-Staubsauger bis zu 99,9% der Milben entfernen. Durch die Kombination von UV-Licht und Vibration werden die Milben effektiv abgetötet und können dann mit dem Staubsauger aufgesaugt werden.Lang anhaltende Hemmung der Neubildung von Bakterien und Milben auf der Liegefläche. Einfache Bedienung --- Dieser kabellose Milbensauger muss nicht die ganze Zeit gedrückt werden, um den Schalter zu halten, nur eine Taste zum Einschalten und Verwenden, einfach zu bedienen, einfach zu verstauen, wird keine Verwirrung verursachen. Milbenentferner ist mit einem großen 200 ml Staubbehälter ausgestattet, der eine längere Reinigungszeit ermöglicht und weniger häufig geleert werden muss. Langlebig und Zuverlässig --- Unser Milbensauger mit uv licht und HEPA filter wurde mit höchster Sorgfalt und Qualitätsstandards entwickelt, um eine effektive Milbenbekämpfung zu gewährleisten. Sollten Sie aus irgendeinem Grund nicht zufrieden sein, kontaktieren Sie uns einfach und wir werden eine Lösung finden. | AB58: https://www.amazon.de/dp/B0DBLLLLKV?psc=1 | AC58: https://images-na.ssl-images-amazon.com/images/I/61Bj6qwEZML._AC_US600_.jpg | AD58: B0DBLLLLKV | AE58: Küche, Haushalt & Wohnen:Haushaltsreiniger & Staubsauger:Staubsauger:Matratzensauger | AF58: Küche, Haushalt & Wohnen | AG58: 1633316 | AH58: -391105 | AI58: -0.49 | AJ58: Matratzensauger | AK58: 56 | AL58: 1 | AN58: 41 | AQ58: 1 | AR58: 40.67 | AY58: 0 | BA58: 0.85 | BC58: 45502 | BD58: 242 | BE58: FBM | BF58: 7 | BG58: 1 | BH58: Royalswill | BI58: FBM | BJ58: CN | BK58: 公司名称：Guangzhoushi Junjia Nengyuan Youxiangongsi 公司类型：Unternehmen in Privatbesitz 电话号码：+86 173 2863 3420 办公地址： Jinzhuxilu 4hao Lichengjie Guangzhoushi Zengchengqu Guangdong 511300 CN | BL58: https://www.amazon.de/gp/help/seller/at-a-glance.html/ref=dp_merchant_link?seller=AO1YDDAXLQTYR | BW58: 1,1 Kilograms | BX58: 1.10 kg
S59: B0D7HN9GKW | U59: Marke: Homuserr | Besonderes Merkmal: Kabellos | Filtertyp: HEPA Filter | Enthaltene Komponenten: Doppelrollenbürste, Doppeldüsen-Staubsauger mit Ultraschall, UV-Licht | Kabellos Ja/Nein?: Nein | V59: Homuserr | W59: https://www.amazon.de/Homuserr/b/ref=bl_dp_s_web_76232657031?ie=UTF8&node=76232657031&field-lbr_brands_browse-bin=Homuserr | X59: Homuserr Milbensauger für Matratzen, mit UV-Licht 500W, 16kpa Matratzensauger mit LED Anzeige, Doppelrollenbürste/Doppeldüsen-Milbensauger mit Ultraschall für Matratzen, Kissen, Sofas, Teppiche | Z59: Leistungsstarker Matratzenstaubsauger mit 16kPa: Ausgestattet mit einem Motor von bis zu 500W und einer leistungsstarken Saugleistung von 16kPa kann unser Staubsauger zur Milbenentfernung problemlos eingebetteten Staub und Allergene von Betten, Kissen, Matratzen, Sofas und mehr entfernen. Gleichzeitig ermöglichen Ihnen die 2 einstellbaren Modi eine flexible Auswahl entsprechend den tatsächlichen Bedürfnissen, was durchdacht und praktisch ist. Verbesserte Version von Doppelwalzenbürsten und Ultraschall: Der milbensauger für matratzen verfügt über ein Doppelwalzenbürsten- und Doppelsaugdüsendesign. Die Doppelwalzenbürsten sorgen für eine doppelte Schlagfrequenz (3600 x 2 = 7200 U/min). Der Adsorptionsbereich hilft in Kombination mit der 4000-Hz-Ultraschalltechnologie, tiefsitzenden Schmutz zu entfernen und Ihr Bett wie neu aussehen zu lassen. 99,9 % Effektive Milbenentfernung: Der matratzensauger ist mit 254 nm UV-Licht ausgestattet, um verschiedene Allergene und andere unsichtbare Schadstoffe auf der Oberfläche von Matratzen, Kissen und anderen Stoffen zu beseitigen. Lassen Sie und Ihre Familie jede Nacht ruhig schlafen. HINWEIS: Die UV-Funktion funktioniert nur, wenn das Gerät in direktem Kontakt mit der Matratze steht. Durch das Anheben wird die Maschine automatisch abgeschaltet. Smarter Staubsensor: Der milbenstaubsauger für matratzen verfügt über eine intelligente Stauberkennung mit einem Gradientenindikator, der die Allergenanzahl widerspiegelt und in Echtzeit über die Sauberkeit Ihres Bettes informiert. Wenn die Reinigungsstatusleuchte grün leuchtet, ist die Reinigung abgeschlossen. Hocheffizienter Filter und Doppelter Auffangbecher: Der Matratzenstaubsauger verwendet eine 5-lagige Filtertechnologie. Der aktualisierte MIF-Filter ist besser als HEPA und kann 99,99 % der kleinen Partikel mit einer Größe von 0,3 Mikron filtern Entfernen Sie Allergene und Staub. Lässt sich vom Haar lösen und ist weniger anfällig für Verstopfungen und Verhedderungen. | AB59: https://www.amazon.de/dp/B0D7HN9GKW?psc=1 | AC59: https://m.media-amazon.com/images/I/41KMKYrhY6L._AC_US600_.jpg | AD59: B0D7HN9GKW | AE59: Küche, Haushalt & Wohnen:Haushaltsreiniger & Staubsauger:Staubsauger:Matratzensauger | AF59: Küche, Haushalt & Wohnen | AG59: 1729363 | AH59: -232694 | AI59: -0.19 | AJ59: Matratzensauger | AK59: 57 | AM59: -1 | AQ59: 1 | AR59: 99.99 | AT59: €20.00 | AV59: 8 | AW59: 0 | AX59: 4.2 | AY59: 0 | AZ59: 5.74 | BA59: 0.8 | BC59: 45461 | BD59: 283 | BE59: FBA | BF59: 10 | BG59: 1 | BH59: Jixikeji | BI59: FBA | BJ59: CN | BK59: 公司名称：Shenzhen Jixi Trading Co., Ltd. 公司类型：Unternehmen in Privatbesitz 电话号码：+8618823728295 办公地址： pinghujiedaohehuashequhuanandadaoyihaohuananguoji pigepijuyuanfuliaowuliuquerqi4A-045 shenzhenshi longgangqu guangdongsheng 518000 CN | BL59: https://www.amazon.de/gp/help/seller/at-a-glance.html/ref=dp_merchant_link?seller=A21WW8M4UD2HUM | BP59: Y | BW59: 2,89 Kilogramm | BX59: 2.89 kg | BY59: 29 x 24 x 23,5 cm | BZ59: 29.00 x 24.00 x 23.50 cm | CA59: 2.89 kg | CB59: 32.7 x 28.4 x 25.8 cm
S60: B0DCG3BSC5 | U60: Marke: VickyHome | Produktabmessungen: 29L x 21,5B x 17,5H cm | Hersteller: VickyHome | Anzahl der Artikel: 1 | V60: VickyHome | W60: https://www.amazon.de/VickyHome/b/ref=bl_dp_s_web_65753270031?ie=UTF8&node=65753270031&field-lbr_brands_browse-bin=VickyHome | X60: Powerful Milbenstaubsauger 10KPA Milbensauger Für Matratzen Testsieger, 3-Gang Matratzenreiniger Milbensauger Mit UV Licht, Staubmilben-Sensor, Intelligente Led-Anzeige, 100W, 8000 Vibrationen/Min | Z60: Hocheffiziente Filtration: Ausgestattet mit einem HEPA-Filter kann er problemlos mit Feinstaub und Fleckenpartikeln umgehen. Der HEPA-Filter kann zerlegt, gereinigt und wiederverwendet werden, sodass Sie den Filter nicht häufig wechseln müssen! Auffangbecher: 200 ML Staubbecher mit großem Fassungsvermögen, der für größere Müllpartikel verwendet wird, fest in Staub und Schmutz einrastet und nicht abläuft. Der UV-Staubsauger verfügt über eine Absaugung von 10000 Pa, die selbst die am meisten vernachlässigten Oberflächen frontal anpackt. 1500mAh Batteriebetrieben: Kabelloser Hand-Matratzenreiniger, keine externe Stromversorgung erforderlich, bequem zu jeder Zeit und an jedem Ort zu verwenden. Weit verbreitet: VickyHome Bettstaubsauger kann effektiv mehr als 99% der Allergene auf der Oberfläche von Stoffen beseitigen. Geeignet für verschiedene Möbel wie Betten, Sofas, Kissen und Matratzen und bietet eine umfassende Lösung zur Milbenentfernung für Ihr Zuhause. Super Saugleistung: Mit seinem Ultrahochleistungsmotor und seiner starken Saugleistung kann der Matratzenstaubsauger Staub und Partikel mit einer Größe von bis zu 0,3 Mikrometern sowie Staub, Semmelbrösel und Tierhaare problemlos von Teppichen, Küchen, Wohnzimmern und Büros entfernen hervorragende Leistung. | AB60: https://www.amazon.de/dp/B0DCG3BSC5?psc=1 | AC60: https://images-na.ssl-images-amazon.com/images/I/71AAYSPFVLL._AC_US600_.jpg | AD60: B0DCG3BSC5 | AE60: Küche, Haushalt & Wohnen:Haushaltsreiniger & Staubsauger:Staubsauger:Matratzensauger | AF60: Küche, Haushalt & Wohnen | AG60: 2181499 | AH60: -297714 | AI60: -0.27 | AJ60: Matratzensauger | AK60: 58 | AL60: 1 | AN60: 35 | AQ60: 1 | AR60: 34.67 | AY60: 0 | BA60: 0.85 | BC60: 45510 | BD60: 234 | BE60: FBM | BF60: 7 | BG60: 1 | BH60: Lucn | BI60: FBM | BJ60: CN | BK60: 公司名称：Guangzhoushi Lucheng Nengyuan Youxiangongsi 公司类型：Unternehmen in Privatbesitz 电话号码：+86 180 5426 9514 办公地址： Lichengjie Hehuiguangchang Zuanshijie55hao 911fang Guangzhoushi Zengchengqu Guangdongsheng 511300 CN | BL60: https://www.amazon.de/gp/help/seller/at-a-glance.html/ref=dp_merchant_link?seller=AJD9ONY8MI53U | BQ60: Y
S61: B0DDPHBKLK | U61: Marke: JPHYLL | Wattzahl: 500 Watt | Geräuschpegel: 75 dB | Anzahl der Artikel: 4 | V61: JPHYLL | W61: https://www.amazon.de/stores/JPHYLL/page/FDE40311-556C-4DBD-81AF-72728FE969F3?ref_=ast_bln&store_ref=bl_ast_dp_brandLogo_sto | X61: JPHYLL Milbensauger für Matratzen Milbenstaubsauger mit UV-Licht 16Kpa Bürstenrolle Ultraschall HEPA Filter Heißer Wind Funktion Matratzenreiniger Handstaubsauger 500W Kabel | AB61: https://www.amazon.de/dp/B0DDPHBKLK?psc=1 | AC61: https://m.media-amazon.com/images/I/417+5aiF26L._AC_US600_.jpg | AD61: B0DDPHBKLK | AE61: Küche, Haushalt & Wohnen:Haushaltsreiniger & Staubsauger:Staubsauger:Matratzensauger | AF61: Küche, Haushalt & Wohnen | AG61: 2210999 | AI61: 0 | AJ61: Matratzensauger | AK61: 59 | AQ61: 1 | AR61: 119.99 | AV61: 3 | AX61: 1.4 | AY61: 0 | BA61: 0 | BC61: 45523 | BD61: 221 | BE61: NA | BF61: 6 | BG61: 1 | BH61: LUORONGLU | BI61: NA | BJ61: CN | BK61: 公司名称：Quanzhoufengzequfanshengweimaoyiyouxiangongsi 公司类型：Unternehmen in Privatbesitz 电话号码：+8615767402660 办公地址： 丰泽区 50号领海苑3幢902室 泉州市 泉南路 福建 362000 CN | BL61: https://www.amazon.de/gp/help/seller/at-a-glance.html/ref=dp_merchant_link?seller=A33AHHCP4XRCM2 | BP61: Y | BS61: Y | BW61: 1,72 Kilogramm | BX61: 1.72 kg | BY61: 26 x 24 x 14 cm | BZ61: 26.00 x 24.00 x 14.00 cm
S62: B0DFL7333M | U62: Marke: Nastopee | Besonderes Merkmal: UV Light | Filtertyp: HEPA Filter | Enthaltene Komponenten: Filter | Kabellos Ja/Nein?: Nein | V62: Nastopee | W62: https://www.amazon.de/Nastopee/b/ref=bl_dp_s_web_94222892031?ie=UTF8&node=94222892031&field-lbr_brands_browse-bin=Nastopee | X62: Milbensauger für Matratzen, Milben Sauger Milbenstaubsauger Matratzensauger Milben mit UV Licht Absaugung Matratzenreiniger Handstaubsauger für Matratzen Betten Sofas Entfernt 99,9% der Bakterien | Z62: 【Integriertes Doppelbecher-Design】Der milbensauger mit uv licht und bettwanzen sauger verwendet ein integriertes Doppelbecher-System, wobei ein Becher speziell für die Filtration und der andere für die Staubaufbewahrung vorgesehen ist; Der Wirbelwindfilterbecher filtert effektiv Milben aus und gibt saubere Luft frei, um die höchste Filtrationseffizienz zu erreichen; Dieses einzigartige Design minimiert das Risiko einer Filterverstopfung und gewährleistet eine lang anhaltende starke Saugkraft 【Fünffache Technologie】253,7 nm UV-C-Ultraviolettlicht, Ultraschall, motorisierte 65℃ hohe Temperatur, 50.000 U/min Bürstenrotation und 13kpa Saugleistung, der multifunktionale UV-Bettstaubsauger und milbenstaubsauger für matratzen bietet Ihnen eine gesündere Umgebung zu Hause 【Intelligenter Milben-Sensor】Der mattress vacuum cleaner und bed vacuum cleaner ist mit einem intelligenten Sensor ausgestattet, der die Milben in der Umgebung hochpräzise erkennen kann; Hausstaubmilben sauger, ein intelligentes LED-Display zeigt in Echtzeit den Milbenindex und den Reinigungsstatus an, um Ihnen bei der intelligenten Reinigung zu helfen 【Ein Echtes Klopfen der Matratze】Der bett staubsauger und milbenstaubsauger mit uv licht verfügt über ein Vibrationsplatte, das 5000 Male jede Minute auf Bettwäsche schlägt und Milben herausklopft; Im Gegensatz zu den milben staubsauger mit Walze, verwickelt unser Milbenentferner und matratzenreiniger gerät sich nicht in Haaren und verschädet in keinem Fall Ihre Matratze 【99,9 % Effektive Milbenentfernung】Der matratze milbensauger und milbensauger für matratzen mit uv licht ist mit einer 254-Nanometer-UV-Lampe und Ultraschalltechnologie ausgestattet, die Milben und Bakterien effizient tief abtöten kann, mit einer Effektivität von 99,99 %; Die Ultraschalltechnologie verhindert die Vermehrung von Milben und gewährleistet die vollständige Beseitigung von Milben, Staub, Schuppen, Tierhaaren und anderen verborgenen Allergenen tief in der Matratze | AB62: https://www.amazon.de/dp/B0DFL7333M?psc=1 | AC62: https://m.media-amazon.com/images/I/41MeXiSMZHL._AC_US600_.jpg | AD62: B0DFL7333M | AE62: Küche, Haushalt & Wohnen:Haushaltsreiniger & Staubsauger:Staubsauger:Matratzensauger | AF62: Küche, Haushalt & Wohnen | AG62: 2240354 | AI62: 0 | AJ62: Matratzensauger | AK62: 60 | AM62: -1 | AQ62: 1 | AR62: 65.69 | AY62: 0 | BA62: 0 | BC62: 45532 | BD62: 212 | BE62: FBA | BF62: 7 | BG62: 1 | BH62: SILVER LION Limited | BI62: FBA | BJ62: GB | BK62: 公司名称：SILVER LION LIMITED 公司类型：Unternehmen in Privatbesitz 电话号码：+8617026168395 办公地址： 115 HALCOMBE SQUARE, WOODSTOCK ROAD BELFAST NORTHERN IRELAND BT6 8AB GB | BL62: https://www.amazon.de/gp/help/seller/at-a-glance.html/ref=dp_merchant_link?seller=A293PR5KJVMX8F | BW62: 1,38 Kilogramm | BX62: 1.38 kg | BY62: 35 x 28,5 x 22 cm | BZ62: 35.00 x 28.50 x 22.00 cm
S63: B0CRKGHTNR | U63: Marke: Trsaow | Besonderes Merkmal: Waschbarer Filter | Filtertyp: Patrone | Enthaltene Komponenten: Reinigungsbürste, 2 x Baumwollfilter | Kabellos Ja/Nein?: Nein | V63: Trsaow | W63: https://www.amazon.de/Trsaow/b/ref=bl_dp_s_web_94103400031?ie=UTF8&node=94103400031&field-lbr_brands_browse-bin=Trsaow | X63: Trsaow Matratzensauger, leistungsstarker Handstaubsauger Staubsauger mit 500 W, für Staub und Tierhaare, antiallergische Reinigung von Matratzen, Saugleistung 13 Kpa mit 0,6 l Stauraum | Y63: Trsaow 床垫吸尘器，强力手持式吸尘器 500 W 吸尘器，用于灰尘和宠物毛发，床垫抗过敏清洁，吸力 13 Kpa，0.6 升存储空间 | Z63: Effizienter 500 W Bett-Staubsauger, starker Motor, Saugleistung 13 Kpa, LED-Display. Intelligenter Staubsensor: LED-Display zeigt den Reinigungsstatus an. Rot für schmutzig, grün für sauber. 253,7 nm UV-Licht: Entfernt Allergene und schädliche Partikel, schafft eine gemütliche Atmosphäre. Erweiterte Filterung: Edelstahlfilter, entfernt 99,97% der Partikel ab 0,3 Mikrometern. Waschbar und wiederverwendbar, alle 4-6 Monate ersetzen. Einfach zu bedienen: langes Kabel, 0,6 l Behälter, breite Saugdüse. Tragbares Design. | AA63: 高效的 500W 床式吸尘器，强大的电机，吸力 13 Kpa，LED 显示屏，智能灰尘传感器：LED 显示屏显示清洁状态，红色表示脏，绿色表示清洁，253.7nm 紫外线：去除过敏原和有害颗粒，营造舒适的氛围，先进的过滤：不锈钢过滤器，从 0.3 微米中去除 99.97% 的颗粒。可水洗可重复使用，每 4-6 个月更换一次，使用方便：长电缆，0.6L 容器，宽吸嘴。便携式设计。 | AB63: https://www.amazon.de/dp/B0CRKGHTNR?psc=1 | AC63: https://m.media-amazon.com/images/I/41HBKsJwJkL._AC_US200_.jpg | AD63: B0CRKGHTNR | AE63: Küche, Haushalt & Wohnen:Haushaltsreiniger & Staubsauger:Staubsauger:Matratzensauger | AF63: Küche, Haushalt & Wohnen | AG63: 2486442 | AI63: 0 | AJ63: Matratzensauger | AK63: 61 | AQ63: 1 | AV63: 11 | AX63: 4 | AY63: 0 | BA63: 0 | BC63: 45319 | BD63: 425 | BE63: NA | BI63: NA | BP63: Y | BQ63: Y | BS63: Y | BW63: 3 Kilogramm | BX63: 3.00 kg | BY63: 42,5 x 32 x 27 cm | BZ63: 42.50 x 32.00 x 27.00 cm
S64: B0DBLL3P6C | U64: Marke: Royalswill | Besonderes Merkmal: Kabellos | Filtertyp: HEPA Filter | Enthaltene Komponenten: Flachsaugdüse, Borstenbürstendüse, Kurze Bürstendüse, Milbenentfernungs-Bürstenkopf, Ladegerät, Betriebsanleitung | Kabellos Ja/Nein?: Ja | V64: Royalswill | W64: https://www.amazon.de/Royalswill/b/ref=bl_dp_s_web_64944844031?ie=UTF8&node=64944844031&field-lbr_brands_browse-bin=Royalswill | X64: Milbensauger für Matratzen & Polster, 10Kpa Milbensauger, Milbenstaubsauger mit UV-Licht und Staubmilben-Sensor zur Entfernung von Staubmilben, Bakterien, Allergenen, Handstaubsauger für Matratzen | Y64: 床垫和室内装饰用螨类吸尘器，10Kpa螨类吸尘器，带紫外线和尘螨传感器的螨类吸尘器，用于去除灰尘螨类、细菌、过敏原，手持式床垫吸尘器 | Z64: Bettwanzen & Milben Bekämpfen --- Milben sind wirklich eine Katastrophe, wenn Sie allergisch sind. Egal, ob Sie ein Erwachsener, ein Kind oder ein Baby sind, Allergiesymptome wie laufende Nase, Niesen und Husten werden Ihr Leben ernsthaft stören. Das stört Ihre Atmungsaktivität und führt zu Schlafstörungen. Hautausschläge sind auch ein häufiges Symptom. Besonders breite Saugkraft --- Mit einer Leistung von 10Kpa Vakuum-Saugkraft der Antimilben-Staubsauger bis zu 99,9% der Milben entfernen. Durch die Kombination von UV-Licht und Vibration werden die Milben effektiv abgetötet und können dann mit dem Staubsauger aufgesaugt werden.Lang anhaltende Hemmung der Neubildung von Bakterien und Milben auf der Liegefläche. Milbensauger Kabellos --- Neuester verbesserte kabelloser Milbensauger, den Sie überall hin bewegen können und vollständig von der Kabelbindung befreit sind, um die Milbenentfernung in der ganzen Familie zu realisieren, ohne sich um lockere Stecker, Stolpern über das Kabel, Kabelverwicklungen usw. sorgen zu müssen, um Sicherheitsrisiken zu beseitigen. Einfache Bedienung --- Dieser kabellose Milbensauger muss nicht die ganze Zeit gedrückt werden, um den Schalter zu halten, nur eine Taste zum Einschalten und Verwenden, einfach zu bedienen, einfach zu verstauen, wird keine Verwirrung verursachen. Milbenentferner ist mit einem großen 200 ml Staubbehälter ausgestattet, der eine längere Reinigungszeit ermöglicht und weniger häufig geleert werden muss. Langlebig und Zuverlässig --- Unser Milbensauger mit uv licht und HEPA filter wurde mit höchster Sorgfalt und Qualitätsstandards entwickelt, um eine effektive Milbenbekämpfung zu gewährleisten. Sollten Sie aus irgendeinem Grund nicht zufrieden sein, kontaktieren Sie uns einfach und wir werden eine Lösung finden. | AA64: 对抗臭虫和螨虫 ---如果你过敏，那真是一场灾难。无论您是成人、儿童还是婴儿，流鼻涕、打喷嚏和咳嗽等过敏症状都会严重扰乱您的生活。这会破坏您的呼吸能力并导致睡眠障碍。皮疹也是一种常见的症状，超宽的吸力--- 凭借 10Kpa 真空吸力的防螨吸尘器，可去除高达 99.9% 的螨虫紫外线和振动的结合有效地杀死了螨虫，然后可以用真空吸尘器吸尘。长效抑制躺卧表面新细菌和螨虫的形成，螨虫吸尘器 Cordless --- 最新改进的无绳螨虫吸尘器，您可以移动到任何地方，完全摆脱绳索绑带，实现全家除螨，无需担心插头松动、电缆绊倒、电缆缠结等，消除安全隐患。易于使用 --- 这款无绳螨类吸尘器无需一直按住开关，只需一个按钮即可开启使用，易于使用，易于存放，不会造成任何混淆。除螨器配备了一个 200 毫升的大集尘桶，可以延长清洁时间，并且需要较少的清空频率。耐用可靠---我们的紫外线和 HEPA 过滤器的螨虫吸尘器是以最谨慎和质量标准开发的，以确保有效的螨虫控制。如果您因任何原因不满意，只需联系我们，我们将找到解决方案。 | AB64: https://www.amazon.de/dp/B0DBLL3P6C?psc=1 | AC64: https://m.media-amazon.com/images/I/41zVk26YoHL._AC_US600_.jpg | AD64: B0DBLL3P6C | AE64: Küche, Haushalt & Wohnen:Haushaltsreiniger & Staubsauger:Staubsauger:Matratzensauger | AF64: Küche, Haushalt & Wohnen | AG64: 2932532 | AI64: 0 | AJ64: Matratzensauger | AK64: 62 | AQ64: 1 | AR64: 40.67 | AY64: 0 | BA64: 0 | BC64: 45502 | BD64: 242 | BE64: FBM | BF64: 7 | BG64: 1 | BH64: Royalswill | BI64: FBM | BJ64: CN | BK64: 公司名称：Guangzhoushi Junjia Nengyuan Youxiangongsi 公司类型：Unternehmen in Privatbesitz 电话号码：+86 173 2863 3420 办公地址： Jinzhuxilu 4hao Lichengjie Guangzhoushi Zengchengqu Guangdong 511300 CN | BL64: https://www.amazon.de/gp/help/seller/at-a-glance.html/ref=dp_merchant_link?seller=AO1YDDAXLQTYR
S65: B0DD7RHGZR | U65: Marke: Bewinner | Besonderes Merkmal: UV-Licht | Enthaltene Komponenten: Ladekabel | Kabellos Ja/Nein?: Ja | Empfohlene Anwendungen für Produkt: Teppiche, Polstermöbel, Kleinteile | V65: Bewinner | W65: https://www.amazon.de/stores/Bewinner/page/DD0810D3-DA32-4656-992B-4BE49341C963?ref_=ast_bln | X65: Bewinner Matratzen Staubsauger mit UV Beleuchtung, 12 KPa Saugleistung, Tragbarer Bettstaubsauger, Kabelloser Staubmilben Entferner Staubsauger mit Doppelhahn für Bettkissen, Sofa | Y65: Bewinner 床垫吸尘器，带紫外线照明，12 KPa 吸力，便携式床上吸尘器，无绳除尘螨吸尘器，带双水龙头，适用于床枕、沙发 | Z65: HOCHFREQUENZ-DOPPELTIPP: Unser Bettsauger verfügt über einen leistungsstarken Doppelklopfmechanismus, der die doppelte Kraft liefert, um Staub und Schmutz tief in Ihrer Bettwäsche effektiv auszuschütteln. UV-REINIGUNG: Durch den Einsatz leistungsstarker UV-Lichter mit tiefer Eindringtiefe zerstört der Bettstaubsauger effektiv Schadstoffe, sorgt für einen gründlichen Reinigungsprozess Ihrer Bettwäsche und sorgt für eine saubere und gesunde Schlafumgebung. 12000 PA STARKE SAUGUNG: Die robuste Saugkraft des Matratzensaugers dringt tief in die Fasern ein und entfernt effektiv Staub, Hautschuppen und schädliche Substanzen, sodass Ihre Bettwäsche sauber bleibt. PRÄZISE FILTRATION: Unser Staubsauger nutzt ein versiegeltes Filtersystem, um Staubpartikel sicher im Gerät einzufangen und mehrere Schutzschichten gegen juckende Haut bereitzustellen. VIELSEITIGE REINIGUNG: Von Bettwäsche und Polstermöbeln bis hin zu Teppichen und Spielzeug – unser Bettstaubsauger ist so konzipiert, dass er alle Ihre Haushaltsreinigungsbedürfnisse mit einer einfachen One-Touch-Bedienung und einem bequemen Griff erfüllt. | AA65: 高频双尖：我们的床上吸尘器具有强大的双敲机构，可以提供两倍的力量来有效地抖出床上用品深处的灰尘和污垢。紫外线清洁：通过使用深度渗透的强大紫外线灯，床上吸尘器有效地破坏污染物，确保对您的床上用品进行彻底清洁的过程，并确保干净健康的睡眠环境。，12000 PA强吸力： 床垫吸尘器的强大吸力深入纤维中，有效去除灰尘、皮屑和有害物质，保持您的床上用品清洁。，精确过滤：我们的吸尘器使用密封的过滤系统安全地捕获设备内的尘埃颗粒，并提供多层保护防止皮肤瘙痒。多功能清洁：从床上用品和室内装饰到地毯和玩具，我们的床上吸尘器旨在 它通过简单的一键式作和舒适的手柄满足您的所有家庭清洁需求。 | AB65: https://www.amazon.de/dp/B0DD7RHGZR?psc=1 | AC65: https://m.media-amazon.com/images/I/41rKQo9MhrL._AC_US600_.jpg | AD65: B0DD7RHGZR | AE65: Küche, Haushalt & Wohnen:Haushaltsreiniger & Staubsauger:Staubsauger:Matratzensauger | AF65: Küche, Haushalt & Wohnen | AG65: 3363907 | AI65: 0 | AJ65: Matratzensauger | AK65: 63 | AM65: -1 | AQ65: 1 | AR65: 93.33 | AY65: 0 | BA65: 0 | BC65: 45518 | BD65: 226 | BE65: FBA | BF65: 8 | BG65: 2 | BH65: Qinqinzi | BI65: FBA | BJ65: CN | BK65: 公司名称：wu han fei shuai wang luo ke ji you xian gong si 公司类型：Unternehmen in Privatbesitz 电话号码：+86 173 8614 3711 办公地址： ru zhu wu han fan zhou shang wu mi shu fu wu you xian gong si (tuo guan hao :424) wu han shi hu bei sheng 430000 CN | BL65: https://www.amazon.de/gp/help/seller/at-a-glance.html/ref=dp_merchant_link?seller=A1U52J69U5IZF7 | BP65: Y | BW65: 1,19 Kilogramm | BX65: 1.19 kg | BY65: 29 x 29 x 17 cm | BZ65: 29.00 x 29.00 x 17.00 cm
S66: B0DCG1CWVY | U66: Marke: VickyHome | Besonderes Merkmal: Kabellos | Filtertyp: Patrone | Enthaltene Komponenten: Kabelloser Matratzenreiniger, Staubbecher, Flache spitze, Pinsel kopf, Kurzer Bürstenkopf, Milbenentfernungsbürstenkopf, USB-Ladekabel, Netzteil | Kabellos Ja/Nein?: Ja | V66: VickyHome | W66: https://www.amazon.de/VickyHome/b/ref=bl_dp_s_web_65753270031?ie=UTF8&node=65753270031&field-lbr_brands_browse-bin=VickyHome | X66: VickyHome 2 In 1 Handstaubsauger Milbensauger Für Matratzen, 10KPA Chmutzbehälter 200ML Akkustaubsauger Kabelloser Staubsauger, Autostaubsauger Milbensauger Mit UV Licht Für Allergiker | Y66: VickyHome 2 合 1 手持式吸尘器 床垫螨类吸尘器，10KPA Chmutz 容器 200ML 无绳吸尘器，汽车吸尘器 带紫外线灯的螨类吸尘器，适合过敏患者 | Z66: Doppelte Reinigungseffizienz: Diese verbesserte Version des Matratzenstaubsaugers basiert auf einer Saugkraft von 10 kpa und einer Leistung von 100 W mit zwei verschiedenen Düsentypen, wodurch die Reinigungseffizienz verdoppelt wird. Bettstaubsauger entfernt mühelos Staub und Schmutz von Ihrem Bett. Staubsammelbecher: Der kabellose Matratzenreiniger hat ein Staubsammelvolumen von 200 ML, das keine häufige Reinigung erfordert. Verbesserte Reinigungsleistung: Das pulsierende Pad vibriert etwa 8.000 Mal pro Minute und rührt Staub und Schmutz auf der losen Matratze mit hochfrequenten Vibrationen auf. Multifunktionaler UV-Bettstaubsauger für eine gesündere Familie! Starke Penetration: Unser Hausstaubmilbenvernichter verwendet ultraviolettes Licht zum Sterilisieren, und 99,99% der Milben und Bakterien werden eliminiert. Wenn die Rolle der Maschine nach unten gedrückt wird, wird das ultraviolette Licht aktiviert, und wenn es angehoben wird oder sich nicht in einer flachen Position befindet, wird das ultraviolette Licht ausgeschaltet. Schnelles Laden und lange Laufzeit: Der kabellose Handstaubsauger benötigt 2,5 bis 3 Stunden zum Laden und kann bei voller Ladung 0,5 Stunden lang ununterbrochen verwendet werden. Der 1500-mAh-Lithiumakku mit großer Kapazität hilft Ihnen, Ihre Reinigungsarbeiten effizient durchzuführen. | AA66: 双倍清洁效率： 这款升级版床垫吸尘器基于 10kpa 吸力和 100W 功率，配备两种不同类型的喷嘴，清洁效率翻倍。床上吸尘器可以毫不费力地清除床上的灰尘和污垢，集尘杯：无绳床垫吸尘器的集尘量为200ML，不需要频繁清洁，提高清洁性能：脉动垫每分钟振动约8,000次，以高频振动搅动松散床垫上的灰尘和污垢。多功能紫外线床式吸尘器，让家庭更健康！，强渗透力：我们的尘螨杀手使用紫外线杀菌，消除99.99%的螨虫和细菌。当机器的滚筒被按下时，紫外线灯将被激活，当它被抬起或未处于平坦位置时，紫外线灯将被关闭，快速充电和长运行时间：无线手持式吸尘器需要 2.5 到 3 小时充电，充满电后可连续使用 0.5 小时。1500mAh 大容量锂电池可帮助您高效地进行清洁工作。 | AB66: https://www.amazon.de/dp/B0DCG1CWVY?psc=1 | AC66: https://m.media-amazon.com/images/I/417mcvJqnSL._AC_US600_.jpg | AD66: B0DCG1CWVY | AE66: Küche, Haushalt & Wohnen:Haushaltsreiniger & Staubsauger:Staubsauger:Matratzensauger | AF66: Küche, Haushalt & Wohnen | AG66: 3509630 | AI66: 0 | AJ66: Matratzensauger | AK66: 64 | AM66: -1 | AQ66: 1 | AR66: 34.67 | AY66: 0 | BA66: 0 | BC66: 45510 | BD66: 234 | BE66: FBM | BF66: 7 | BG66: 1 | BH66: Lucn | BI66: FBM | BJ66: CN | BK66: 公司名称：Guangzhoushi Lucheng Nengyuan Youxiangongsi 公司类型：Unternehmen in Privatbesitz 电话号码：+86 180 5426 9514 办公地址： Lichengjie Hehuiguangchang Zuanshijie55hao 911fang Guangzhoushi Zengchengqu Guangdongsheng 511300 CN | BL66: https://www.amazon.de/gp/help/seller/at-a-glance.html/ref=dp_merchant_link?seller=AJD9ONY8MI53U | BQ66: Y
S67: B0D1V4SBGD | U67: Marke: VersLife | Material: Hepa | Kompatible Geräte: Handstaubsauger | Produktabmessungen: 40L x 40B x 50H Millimeter | Stückzahl: 3 | V67: VersLife | W67: https://www.amazon.de/s/ref=bl_dp_s_web_0?ie=UTF8&search-type=ss&index=appliances&field-keywords=VersLife | X67: VersLife mattress vacuum M6 HEPA Filter | Y67: VersLife 床垫真空吸尘器 M6 HEPA 过滤器 | Z67: VersLife mattress vacuum M6 HEPA Filter | AA67: VersLife 床垫真空吸尘器 M6 HEPA 过滤器 | AB67: https://www.amazon.de/dp/B0D1V4SBGD?psc=1 | AC67: https://m.media-amazon.com/images/I/416qqdZuJcL._AC_SR200,200_.jpg | AD67: B0D1V4SBGD | AE67: Küche, Haushalt & Wohnen:Haushaltsreiniger & Staubsauger:Staubsauger:Matratzensauger | AF67: Küche, Haushalt & Wohnen | AG67: 4102907 | AI67: 0 | AJ67: Matratzensauger Haushaltsgroßgeräte | AK67: 65 142833 | AQ67: 1 | AV67: 2 | AX67: 3.1 | AY67: 0 | BA67: 0 | BC67: 45447 | BD67: 297 | BE67: NA | BI67: NA | BY67: 5,08 x 7,62 x 5,08 cm | BZ67: 5.08 x 7.62 x 5.08 cm
S68: B0DBLKYD4P | U68: Marke: Royalswill | Besonderes Merkmal: Kabellos | Formfaktor: Handheld | Produktabmessungen: 21,5L x 29B x 17,5H cm | Hersteller: Royalswill | V68: Royalswill | W68: https://www.amazon.de/Royalswill/b/ref=bl_dp_s_web_64944844031?ie=UTF8&node=64944844031&field-lbr_brands_browse-bin=Royalswill | X68: Milbensauger für Matratzen, 10Kpa Matratzenreiniger mit Staubmilben-Sensor und UV-Licht, entfernt 99,9% Allergene von Betten, Sofas, Tierhaare, Handstaubsauger Milbenstaubsauger für Matratzen | Y68: 床垫螨类吸尘器，10Kpa 床垫清洁器，带尘螨传感器和紫外线，去除床、沙发、宠物毛发、背包上 99.9% 的过敏原 | Z68: Milbensauger Kabellos --- Neuester verbesserte kabelloser Milbensauger, den Sie überall hin bewegen können und vollständig von der Kabelbindung befreit sind, um die Milbenentfernung in der ganzen Familie zu realisieren, ohne sich um lockere Stecker, Stolpern über das Kabel, Kabelverwicklungen usw. sorgen zu müssen, um Sicherheitsrisiken zu beseitigen. Bettwanzen & Milben Bekämpfen --- Milben sind wirklich eine Katastrophe, wenn Sie allergisch sind. Egal, ob Sie ein Erwachsener, ein Kind oder ein Baby sind, Allergiesymptome wie laufende Nase, Niesen und Husten werden Ihr Leben ernsthaft stören. Das stört Ihre Atmungsaktivität und führt zu Schlafstörungen. Hautausschläge sind auch ein häufiges Symptom. Besonders breite Saugkraft --- Mit einer Leistung von 10Kpa Vakuum-Saugkraft der Antimilben-Staubsauger bis zu 99,9% der Milben entfernen. Durch die Kombination von UV-Licht und Vibration werden die Milben effektiv abgetötet und können dann mit dem Staubsauger aufgesaugt werden.Lang anhaltende Hemmung der Neubildung von Bakterien und Milben auf der Liegefläche. Einfache Bedienung --- Dieser kabellose Milbensauger muss nicht die ganze Zeit gedrückt werden, um den Schalter zu halten, nur eine Taste zum Einschalten und Verwenden, einfach zu bedienen, einfach zu verstauen, wird keine Verwirrung verursachen. Milbenentferner ist mit einem großen 200 ml Staubbehälter ausgestattet, der eine längere Reinigungszeit ermöglicht und weniger häufig geleert werden muss. Langlebig und Zuverlässig --- Unser Milbensauger mit uv licht und HEPA filter wurde mit höchster Sorgfalt und Qualitätsstandards entwickelt, um eine effektive Milbenbekämpfung zu gewährleisten. Sollten Sie aus irgendeinem Grund nicht zufrieden sein, kontaktieren Sie uns einfach und wir werden eine Lösung finden. | AA68: 螨虫吸尘器 无绳--- 最新升级的无绳螨虫吸尘器，您可以移动到任何地方，完全摆脱绳索束缚，实现全家除螨，无需担心插头松动、电线绊倒、电缆缠结等，消除安全隐患---.无论您是成人、儿童还是婴儿，流鼻涕、打喷嚏和咳嗽等过敏症状都会严重扰乱您的生活。这会破坏您的呼吸能力并导致睡眠障碍。皮疹也是一种常见的症状，超宽的吸力--- 凭借 10Kpa 真空吸力的防螨吸尘器，可去除高达 99.9% 的螨虫紫外线和振动的结合有效地杀死了螨虫，然后可以用真空吸尘器吸尘。长效抑制躺卧表面新细菌和螨虫的形成，使用方便---这款无线螨虫吸尘器无需一直按住开关，只需一个按钮即可开启使用，易于使用，易于存放，不会造成混乱。除螨器配备了一个 200 毫升的大集尘桶，可以延长清洁时间，并且需要较少的清空频率。耐用可靠---我们的紫外线和 HEPA 过滤器的螨虫吸尘器是以最谨慎和质量标准开发的，以确保有效的螨虫控制。如果您因任何原因不满意，只需联系我们，我们将找到解决方案。 | AB68: https://www.amazon.de/dp/B0DBLKYD4P?psc=1 | AC68: https://m.media-amazon.com/images/I/418enrOei-L._AC_US600_.jpg | AD68: B0DBLKYD4P | AE68: Küche, Haushalt & Wohnen:Haushaltsreiniger & Staubsauger:Staubsauger:Matratzensauger | AF68: Küche, Haushalt & Wohnen | AG68: 4760530 | AI68: 0 | AJ68: Matratzensauger | AK68: 66 | AM68: -1 | AQ68: 1 | AR68: 40.67 | AY68: 0 | BA68: 0 | BC68: 45502 | BD68: 242 | BE68: FBM | BF68: 7 | BG68: 1 | BH68: Royalswill | BI68: FBM | BJ68: CN | BK68: 公司名称：Guangzhoushi Junjia Nengyuan Youxiangongsi 公司类型：Unternehmen in Privatbesitz 电话号码：+86 173 2863 3420 办公地址： Jinzhuxilu 4hao Lichengjie Guangzhoushi Zengchengqu Guangdong 511300 CN | BL68: https://www.amazon.de/gp/help/seller/at-a-glance.html/ref=dp_merchant_link?seller=AO1YDDAXLQTYR | BW68: 1,1 Kilograms | BX68: 1.10 kg
S69: B0DBHBPWXW | U69: Marke: UCerdveos | Besonderes Merkmal: UV-Licht | Filtertyp: HEPA Filter | Kabellos Ja/Nein?: Ja | Empfohlene Anwendungen für Produkt: Matratzen, Betten, Sofas, Auto-Interieurs, Polster | V69: UCerdveos | W69: https://www.amazon.de/s/ref=bl_dp_s_web_0?ie=UTF8&search-type=ss&index=kitchen-de&field-keywords=UCerdveos | X69: UCerdveos Kabellos Milbensauger mit Staubmilben-Sensor und Intelligente LED-Anzeige,1000W Milbenstaubsauger mit UV-Licht, Für Allergiker, entfernt 99,9% der Allergene, für Matratzen, Betten, Sofas | Y69: UCerdveos 无绳螨类吸尘器，带尘螨传感器和智能 LED 显示屏，1000W 紫外线螨类吸尘器，适用于过敏患者，去除 99.9% 的过敏原，适用于床垫、床、沙发 | Z69: 【99,9 % Milbenentfernungsrate】: Milbensauger gibt ultraviolette Strahlen mit einer Wellenlänge von 253,7 nm ab und bläst Luft mit 60 °C aus, um 99,9 % der im Matratzeninneren verborgenen Milben und Bakterien zu entfernen. UV-Strahlen können Textilien desinfizieren und die DNA und RNA der Milben stören, während die 60 °C heiße Luft die Aktivität der Milben reduzieren und Ihre Matratze trocken halten kann, um eine hygienische Schlafumgebung zu schaffen. Zur Sicherheit wird die UV-Lampe automatisch ausgeschaltet, wenn das Gerät angehoben wird, um mögliche Schäden für Ihre Augen zu vermeiden. 【Starke Saugleistung】: Der milben staubsauger ist mit einem bürstenlosen 800W Motor ausgestattet, der eine starke Saugleistung von bis zu 18000 PA bieten kann. In Kombination mit dem Hochgeschwindigkeitsstreichen der darunter liegenden Metallwalzenbürste (40.000 Mal/Minute) können Sie Milben, Staub und Haare problemlos von Matratzen, Decken und Sofas entfernen. Sie erhalten stärkere Reinigungsergebnisse als vergleichbare Produkte. 【5-Stufen-Filtersystem】Der HEPA-Filter filtert 99,97% der Partikel, die so klein wie 0,3 Mikrometer sind, verhindert Verstopfungen und sorgt für eine optimale Filterleistung. Ausgestattet mit einem doppelten Zyklon-Filtersystem, trennt dieser Matratzenstaubsauger Haare von Staub für eine saubere Luftausgabe. 【Doppelte Reinigungsleistung】Basierend auf 18Kpa Saugkraft und 800W Leistung, verfügt dieser aktualisierte Matratzenstaubsauger über eine innovative verdickte Doppelwalzenbürste und erweiterte 10-Zoll-Doppelsaugöffnungen, die die Reinigungseffizienz verdoppeln. Es fegt mühelos Staub und Schmutz von Ihrem Bett mit Leichtigkeit we 【Benutzerfreundlich & Langlebig】Mit müheloser Ein-Knopf-Bedienung und einem 16,5ft verlängerten Kabel für eine einfache Reichweite zu Ihrem Bett. Enthält ein Snap-Lock-Design für den Staubbehälter und die Walzenbürste, was eine einfache Demontage, Reinigung und Wiedermontage ermöglicht. Der aus hochwertigen Komponenten gefertigte Matratzenstaubsauger KM-PA1600-SE hat eine Lebensdauer von bis zu 10 Jahren und minimiert die Wartungskosten. | AA69: 【99.9% 除螨率】：螨虫吸尘器发出波长为 253.7nm 的紫外线，并在 60°C 下吹出空气，以去除 99.9% 隐藏在床垫内的螨虫和细菌。紫外线可以对纺织品进行消毒并破坏螨虫的 DNA 和 RNA，而 60°C 的热空气可以减少螨虫的活动并保持床垫干燥，以创造卫生的睡眠环境。为安全起见，当设备被抬起时，紫外线灯会自动关闭，以防止可能对您的眼睛造成伤害。【强力吸力】：螨虫吸尘器配备 800W 无刷电机，可提供高达 18000PA 的强大吸力。结合下面的金属滚刷高速喷涂（40,000 次/分钟），您可以轻松去除床垫、毯子和沙发上的螨虫、灰尘和毛发。您将获得比同类产品更强的清洁效果，【5 级过滤系统】HEPA 过滤器过滤 99.97% 的小至 0.3 微米的颗粒，防止堵塞并确保最佳过滤性能。这款床垫吸尘器配备双旋风过滤系统，可将头发与灰尘分离，提供清洁空气输出。【双重清洁功率】基于 18Kpa 吸力和 800W 功率，这款更新的床垫真空吸尘器采用创新的加厚双滚刷和加长的 10 英寸双吸孔，清洁效率翻倍。它可以轻松地从您的床上扫除灰尘和碎屑，【易于使用且耐用】一键作和一根16.5英尺的延长线，方便您触及您的床。包括用于集尘桶和滚刷的弹簧锁设计，便于拆卸、清洁和重新组装。KM-PA1600-SE 床垫吸尘器由优质组件制成，使用寿命长达 10 年，并将维护成本降至最低。 | AB69: https://www.amazon.de/dp/B0DBHBPWXW?psc=1 | AC69: https://images-na.ssl-images-amazon.com/images/I/41tBdo12ItL._AC_US600_.jpg | AD69: B0DM94D755 | AE69: Küche, Haushalt & Wohnen:Haushaltsreiniger & Staubsauger:Staubsauger:Matratzensauger | AF69: Küche, Haushalt & Wohnen | AG69: 4769559 | AH69: -92075 | AI69: -2.03 | AJ69: Matratzensauger | AK69: 67 | AL69: 122 | AM69: -0.62 | AN69: 7319 | AQ69: 1 | AR69: 59.99 | AV69: 4 | AW69: 0 | AX69: 5 | AY69: 0 | AZ69: 4.29 | BA69: 0.78 | BC69: 45502 | BD69: 242 | BE69: NA | BF69: 10 | BG69: 1 | BH69: Guangzhou Xinsu International Trade Co., Ltd. | BI69: NA | BJ69: CN | BK69: 公司名称：guangzhouxinsuguojimaoyiyouxiangongsi 公司类型：Unternehmen in Privatbesitz 电话号码：+8619125217616 办公地址： he long jie kang zhuang lu1hao 414 fang F114 hao guang zhou shi bai yun qu guang dong sheng 510080 CN | BL69: https://www.amazon.de/gp/help/seller/at-a-glance.html/ref=dp_merchant_link?seller=AFA72BBZGCVA1 | BP69: Y | BW69: 1 Kilogramm | BX69: 1,000.00 g | BY69: 10 x 10 x 10 cm | BZ69: 10.00 x 10.00 x 10.00 cm | CA69: 1 kg | CB69: 10 x 10 x 10 cm

Sheet 附表-搜索转化率
A1: 搜索词 | B1: 搜索量（过去 360 天） | C1: 搜索量增长（过去 90 天） | D1: 搜索量增长（过去 180 天） | E1: 点击份额（过去 360 天） | F1: 搜索转化率（过去 360 天） | G1: 点击率最高的商品1（标题） | H1: 点击率最高的商品1 (ASIN) | I1: 点击率最高的商品2（标题） | J1: 点击率最高的商品2 (ASIN) | K1: 点击率最高的商品3（标题） | L1: 点击率最高的商品3 (ASIN)
A2: handheld vacuum cleaner | B2: 717259 | C2: -0.0715 | D2: -0.1965 | E2: 0.2138 | F2: 0.0197 | G2: Shark Handheld Cordless Vacuum Cleaner with Pet Tool Crevice Tool & Dusting Brush 80 W 0.45 liters 10 Minute Run-Time Washable Filter Black & Yellow CH950UKT | H2: B08M9JQ1J1 | I2: Handheld Vacuum Cleaner Powerful Suction Portable Lightweight Hand Held Vacuum Cordless with 25-30Mins Long Runtime Rechargeable Battery Quick Charge for Home Car Carpet Stairs Pet Hair Cleaning | J2: B09VKPHJVF | K2: Higoom 4 in 1 Cordless Handheld Vacuum Cleaner Car Vacuum Cleaner 22000PA Strong Suction Mini Vacuum Dust Blower Can be Used for Home Car | L2: B0DJFMT6LS
A3: car vacuum cleaner | B3: 455206 | C3: 0.0195 | D3: -0.1366 | E3: 0.148 | F3: 0.0146 | G3: Ginarelo Handheld Cordless Car Vacuum Cleaner - 4000Pa Small Hand Held Vacuums Cleaners Strong Suction Powerful Portable Wireless Lightweight Mini Long Runtime Hand-held Vaccum USB Vacum Blower | H3: B0DB5VMBTC | I3: Higoom 4 in 1 Cordless Handheld Vacuum Cleaner Car Vacuum Cleaner 22000PA Strong Suction Mini Vacuum Dust Blower Can be Used for Home Car | J3: B0DJFMT6LS | K3: Wirelume Handheld Car Vacuum Cleaner Cordless Powerful 22000Pa Strong Cyclonic Suction Blowing Brushless Motor Mini Hand Held Portable Rechargeable Lightweight for Pet Hair Vehicle Home Office Purple | L3: B0D45V1YXT
A4: hand held vacuum cordless | B4: 410982 | C4: -0.1937 | D4: -0.1952 | E4: 0.1142 | F4: 0.022 | G4: Shark Handheld Cordless Vacuum Cleaner with Pet Tool Crevice Tool & Dusting Brush 80 W 0.45 liters 10 Minute Run-Time Washable Filter Black & Yellow CH950UKT | H4: B08M9JQ1J1 | I4: Vax Gator Cordless Handheld Vacuum Cleaner | Lightweight Quick Cleaning | Built-in Crevice Tool - H85-GA-B10 0.3 Litre White and Orange | J4: B015QZH2EU | K4: Handheld Vacuum Cleaner Powerful Suction Portable Lightweight Hand Held Vacuum Cordless with 25-30Mins Long Runtime Rechargeable Battery Quick Charge for Home Car Carpet Stairs Pet Hair Cleaning | L4: B09VKPHJVF
A5: car hoover | B5: 320576 | C5: -0.0656 | D5: -0.1624 | E5: 0.107 | F5: 0.0233 | G5: Handheld Vacuum Cleaner Powerful Suction Portable Lightweight Hand Held Vacuum Cordless with 25-30Mins Long Runtime Rechargeable Battery Quick Charge for Home Car Carpet Stairs Pet Hair Cleaning | H5: B09VKPHJVF | I5: Handheld Vacuum Cordless 9000Pa Powerful Car Vacuum Cleaner Rechargeable Portable Lightweight Mini Vacuum Cleaner USB Car Vacuum Cleaner Car Cleaner for Pet Hair Car Home Office Kitchen | J5: B0CKVFMYH4 | K5: Nctoberows Handheld Vacuum Cleaner Cordless 22000Pa Powerful Car Mini Vacuum Cleaner Rechargeable Portable Lightweight dust catcher for Home Car Carpet Stairs Pet Hair Deep Cleaning | L5: B0DJ2YVV6F
A6: car vacuum cleaner cordless | B6: 190272 | C6: 0.1062 | D6: -0.1319 | E6: 0.0734 | F6: 0.0194 | G6: Ginarelo Handheld Cordless Car Vacuum Cleaner - 4000Pa Small Hand Held Vacuums Cleaners Strong Suction Powerful Portable Wireless Lightweight Mini Long Runtime Hand-held Vaccum USB Vacum Blower | H6: B0DB5VMBTC | I6: Handheld Vacuum Cleaner Powerful Suction Portable Lightweight Hand Held Vacuum Cordless with 25-30Mins Long Runtime Rechargeable Battery Quick Charge for Home Car Carpet Stairs Pet Hair Cleaning | J6: B09VKPHJVF | K6: Wirelume Handheld Car Vacuum Cleaner Cordless Powerful 22000Pa Strong Cyclonic Suction Blowing Brushless Motor Mini Hand Held Portable Rechargeable Lightweight for Pet Hair Vehicle Home Office Purple | L6: B0D45V1YXT
A7: handheld hoover | B7: 109751 | C7: 0.5662 | D7: -0.1233 | E7: 0.0473 | F7: 0.0243 | G7: Shark Handheld Cordless Vacuum Cleaner with Pet Tool Crevice Tool & Dusting Brush 80 W 0.45 liters 10 Minute Run-Time Washable Filter Black & Yellow CH950UKT | H7: B08M9JQ1J1 | I7: Handheld Vacuum Cleaner Powerful Suction Portable Lightweight Hand Held Vacuum Cordless with 25-30Mins Long Runtime Rechargeable Battery Quick Charge for Home Car Carpet Stairs Pet Hair Cleaning | J7: B09VKPHJVF | K7: Powools Handheld Vacuum Cordless with 2 Filters Car Vacuum Cleaner High Power with Fast Cahrge Tech Portable Rechargeable Mini Vacuum with Large-Capacity Battery Orange 14.3X4.6X4.0 | L7: B0D4M3MSG7
A8: car hoovers cordless powerful | B8: 133015 | C8: -0.001 | D8: -0.1131 | E8: 0.0558 | F8: 0.0275 | G8: Handheld Vacuum Cleaner Powerful Suction Portable Lightweight Hand Held Vacuum Cordless with 25-30Mins Long Runtime Rechargeable Battery Quick Charge for Home Car Carpet Stairs Pet Hair Cleaning | H8: B09VKPHJVF | I8: Nctoberows Handheld Vacuum Cleaner Cordless 22000Pa Powerful Car Mini Vacuum Cleaner Rechargeable Portable Lightweight dust catcher for Home Car Carpet Stairs Pet Hair Deep Cleaning | J8: B0DJ2YVV6F | K8: Semflagree Handheld Mini Vacuum 4 in 1 Cordless 23000PA Powerful Strong Cyclonic Suction USB Rechargeable Portable Car Vacuum Cleaner Car Cleaner for Pet Hair Car Home Office Kitchen | L8: B0DXKCZD5Z
A9: car vacuum | B9: 109696 | C9: 0.0631 | D9: -0.2452 | E9: 0.0331 | F9: 0.0148 | G9: Wirelume Handheld Car Vacuum Cleaner Cordless Powerful 22000Pa Strong Cyclonic Suction Blowing Brushless Motor Mini Portable Rechargeable Lightweight Blower for Pet Hair Vehicle Home Office Dark Grey | H9: B0D45VR94F | I9: Handheld Vacuum Cleaner Powerful Suction Portable Lightweight Hand Held Vacuum Cordless with 25-30Mins Long Runtime Rechargeable Battery Quick Charge for Home Car Carpet Stairs Pet Hair Cleaning | J9: B09VKPHJVF | K9: Higoom 4 in 1 Cordless Handheld Vacuum Cleaner Car Vacuum Cleaner 22000PA Strong Suction Mini Vacuum Dust Blower Can be Used for Home Car | L9: B0DJFMT6LS
A10: mini hoover | B10: 96946 | C10: -0.0553 | D10: -0.2516 | E10: 0.0227 | F10: 0.0199 | G10: Handheld Vacuum Cleaner Powerful Suction Portable Lightweight Hand Held Vacuum Cordless with 25-30Mins Long Runtime Rechargeable Battery Quick Charge for Home Car Carpet Stairs Pet Hair Cleaning | H10: B09VKPHJVF | I10: Handheld Vacuum Cordless 9000Pa Powerful Car Vacuum Cleaner Rechargeable Portable Lightweight Mini Vacuum Cleaner USB Car Vacuum Cleaner Car Cleaner for Pet Hair Car Home Office Kitchen | J10: B0CKVFMYH4 | K10: Nctoberows Handheld Vacuum Cleaner Cordless 22000Pa Powerful Car Mini Vacuum Cleaner Rechargeable Portable Lightweight dust catcher for Home Car Carpet Stairs Pet Hair Deep Cleaning | L10: B0DJ2YVV6F
A11: handheld vacuum | B11: 83977 | C11: 0.2376 | D11: -0.2902 | E11: 0.0226 | F11: 0.0143 | G11: Shark Handheld Cordless Vacuum Cleaner with Pet Tool Crevice Tool & Dusting Brush 80 W 0.45 liters 10 Minute Run-Time Washable Filter Black & Yellow CH950UKT | H11: B08M9JQ1J1 | I11: Vax Gator Cordless Handheld Vacuum Cleaner | Lightweight Quick Cleaning | Built-in Crevice Tool - H85-GA-B10 0.3 Litre White and Orange | J11: B015QZH2EU | K11: Handheld Vacuum Cleaner Powerful Suction Portable Lightweight Hand Held Vacuum Cordless with 25-30Mins Long Runtime Rechargeable Battery Quick Charge for Home Car Carpet Stairs Pet Hair Cleaning | L11: B09VKPHJVF
A12: hand held hoover | B12: 75659 | C12: 0.2587 | D12: -0.167 | E12: 0.0253 | F12: 0.0248 | G12: Shark Handheld Cordless Vacuum Cleaner with Pet Tool Crevice Tool & Dusting Brush 80 W 0.45 liters 10 Minute Run-Time Washable Filter Black & Yellow CH950UKT | H12: B08M9JQ1J1 | I12: Handheld Vacuum Cleaner Powerful Suction Portable Lightweight Hand Held Vacuum Cordless with 25-30Mins Long Runtime Rechargeable Battery Quick Charge for Home Car Carpet Stairs Pet Hair Cleaning | J12: B09VKPHJVF | K12: Nctoberows Handheld Vacuum Cleaner Cordless 22000Pa Powerful Car Mini Vacuum Cleaner Rechargeable Portable Lightweight dust catcher for Home Car Carpet Stairs Pet Hair Deep Cleaning | L12: B0DJ2YVV6F
A13: car vacuum cleaner cordless powerful | B13: 68512 | C13: 0.0573 | D13: -0.1873 | E13: 0.0225 | F13: 0.0162 | G13: Handheld Vacuum Cleaner Powerful Suction Portable Lightweight Hand Held Vacuum Cordless with 25-30Mins Long Runtime Rechargeable Battery Quick Charge for Home Car Carpet Stairs Pet Hair Cleaning | H13: B09VKPHJVF | I13: Wirelume Handheld Car Vacuum Cleaner Cordless Powerful 22000Pa Strong Cyclonic Suction Blowing Brushless Motor Mini Hand Held Portable Rechargeable Lightweight for Pet Hair Vehicle Home Office Purple | J13: B0D45V1YXT | K13: Semflagree Handheld Mini Vacuum 4 in 1 Cordless 23000PA Powerful Strong Cyclonic Suction USB Rechargeable Portable Car Vacuum Cleaner Car Cleaner for Pet Hair Car Home Office Kitchen | L13: B0DXKCZD5Z
... A21: handheld vacuum cleaner cordless | B21: 38290 | C21: 0.683 | D21: -0.1409 | E21: 0.0151 | F21: 0.0172 | G21: Shark Handheld Cordless Vacuum Cleaner with Pet Tool Crevice Tool & Dusting Brush 80 W 0.45 liters 10 Minute Run-Time Washable Filter Black & Yellow CH950UKT | H21: B08M9JQ1J1 | I21: Handheld Vacuum Cleaner Powerful Suction Portable Lightweight Hand Held Vacuum Cordless with 25-30Mins Long Runtime Rechargeable Battery Quick Charge for Home Car Carpet Stairs Pet Hair Cleaning | J21: B09VKPHJVF | K21: Higoom 4 in 1 Cordless Handheld Vacuum Cleaner Car Vacuum Cleaner 22000PA Strong Suction Mini Vacuum Dust Blower Can be Used for Home Car | L21: B0DJFMT6LS

Sheet UK竞品分析
A1: # | B1: 图片 | C1: ASIN | D1: SKU | E1: 详细参数 | F1: 品牌 | G1: 品牌链接 | H1: 商品标题 | I1: 标题(翻译) | J1: 产品卖点 | K1: 产品卖点(翻译) | L1: 商品详情页链接 | M1: 商品主图 | N1: 父ASIN | O1: 类目路径 | P1: 大类目 | Q1: 大类BSR | R1: 大类BSR增长数 | S1: 大类BSR增长率 | T1: 小类目 | U1: 小类BSR | V1: 月销量 | W1: 月销量增长率 | X1: 月销售额(£) | Y1: 子体销量 | Z1: 子体销售额(£) | AA1: 变体数 | AB1: 价格(£) | AC1: Prime价格(£) | AD1: Coupon | AE1: Q&A数 | AF1: 评分数 | AG1: 月新增 评分数 | AH1: 评分 | AI1: 留评率 | AJ1: FBA(£) | AK1: 毛利率 | AL1: 评级 | AM1: 上架时间 | AN1: 上架天数 | AO1: 配送方式 | AP1: LQS | AQ1: 卖家数 | AR1: Buybox卖家 | AS1: BuyBox类型 | AT1: 卖家所属地 | AU1: 卖家信息 | AV1: 卖家首页 | AW1: Best Seller标识 | AX1: Amazon's Choice | AY1: CPF绿标 | AZ1: CPF绿标信息 | BA1: New Release标识 | BB1: A+页面 | BC1: 视频介绍 | BD1: SP广告 | BE1: 品牌故事 | BF1: 品牌广告 | BG1: 7天促销 | BH1: AC关键词 | BI1: 重量 | BJ1: 重量 | BK1: 体积 | BL1: 体积 | BM1: 包装重量 | BN1: 包装重量 | BO1: 包装体积 | BP1: 包装体积
A2: 1 | C2: B09VKPHJVF | D2: Colour Name: A-white | E2: Brand: Portutif | Special feature: Cordless, lightweight portable only 1.92 pounds Reusable washable Hepa Filter 8Kpa Strong suction 30 minutes long runtime Equipped with wide selection of tools accessories | Filter type: HEPA Filter | Included components: Wall charger, handheld vacuum cleaner, 1 x washable filter, brush nozzle, crevice nozzle, cleaning brush | Is cordless?: Yes | F2: Portutif | G2: https://www.amazon.co.uk/stores/PortutifHandheldVacuum/page/9187774A-0444-4972-9CD4-5D99E5A7DE79?lp_asin=B09VKPHJVF&ref_=ast_bln | H2: Handheld Vacuum Cleaner, Powerful Suction Portable Lightweight Hand Held Vacuum Cordless with 25-30Mins Long Runtime Rechargeable Battery Quick Charge for Home, Car, Carpet Stairs, Pet Hair Cleaning | I2: 手持真空吸尘器，功能强大的吸力便携式轻巧的手持真空无线无线无绳，长25-30分钟长的可充电电池快速充电，汽车，地毯楼梯，宠物头发清洁 | J2: STRONG SUCTION & QUIET OPERATION: Our upgraded hand-held vacuum features a powerful 70W ultra-high-power motor capable of suctioning up to 8Kpa, easily eliminating even the smallest particles of dust and debris from sofas and mattresses. With noise-reducing technology, the operational noise is below 78dB, making it exemplary for daily cleaning tasks. LONGER USE WITH QUIET CHARGING: Our cord-free handheld vacuum is powered by 2200mah high-capacity Lithium batteries, fully charging in just 3-4 hours for up to 30 minutes of runtime. The 400ml large-capacity dust container ensures uninterrupted deep cleaning of your kitchen, living room, and bedroom. ERGONOMIC DESIGN & PORTABLE: Our hand-held vacuum is lightweight and compact, weighing only 1.92 pounds, making it effortlessly portable and suitable for cleaning every corner of your home, regardless of location. It's an outstanding choice for the elderly, arthritis sufferers, and even children, due to its user-friendly design and painless operation. VERSATILE CLEANING: Our hand-held vacuum is equipped with a wide range of tools and attachments. It is adept at cleaning hard-to-reach spots, like under sofas, car seat gaps, and laptops. The crevice nozzle is suitable for narrow spaces, while the brush nozzle excels at cleaning car air vents and pet hair from carpets. The wide-mouth nozzle can tackle larger particles, such as food crumbs. Additionally, it comes with a storage bag for organizing all your accessories. GREAT PRESENT IDEA: Our hand-held vacuum is a superb present for anyone, regardless of age or gender. It's suitable for birthdays, Christmas, New Year's Day, Thanksgiving Day, Valentine's Day, Father's Day, Mother's Day, and any other special occasion. Our hand-held vacuum cleaner makes cleaning simpler and more efficient. | K2: 强大的吸力和安静的操作：我们升级的手持真空吸尘器具有强大的70W超高功率电动机，能够吸入高达8KPA，即使是从沙发和床垫上消除了最小的灰尘和碎屑颗粒。借助降噪技术，操作噪声低于78dB，这是每日清洁任务的典范。更长的时间与安静充电：我们的无绳索手持式吸尘器由2200mAh高容量的锂电池供电，仅在3-4小时的运行时间内填充3-4小时。 400毫升的大容量灰尘容器可确保您的厨房，客厅和卧室的深层清洁。符合人体工程学设计和便携式：我们的手持真空度轻巧且紧凑，重量仅为1.92磅，使其毫不费力地便携，并且适合清洁房屋的每个角落。由于其用户友好的设计和无痛的操作，这是老年人，关节炎患者甚至儿童的出色选择。多功能清洁：我们的手持真空吸尘器配备了广泛的工具和附件。它擅长清洁难以触及的景点，例如沙发，汽车座椅间隙和笔记本电脑。缝隙喷嘴适用于狭窄的空间，而刷子喷嘴在清洁汽车通风口和地毯上的宠物头发方面表现出色。宽口喷嘴可以应对较大的颗粒，例如食物碎屑。此外，它带有一个用于组织所有配件的存储袋。它适用于生日，圣诞节，元旦，感恩节，情人节，父亲节，母亲节和其他任何特殊场合。我们的手持真空吸尘器可以使清洁更简单，更高效。 | L2: https://www.amazon.co.uk/dp/B09VKPHJVF?psc=1 | M2: https://images-na.ssl-images-amazon.com/images/I/81gvb6bSSSL._AC_US600_.jpg | N2: B0BP6DXRBJ | O2: Home & Kitchen:Kitchen & Home Appliances:Vacuums & Floor Care:Vacuums:Handheld Vacuums | P2: Home & Kitchen | Q2: 272 | R2: 68 | S2: 0.2429 | T2: Handheld Vacuums | U2: 1 | V2: 5494 | W2: 0.1993 | X2: 186741.06 | Y2: 4,000 | Z2: 101970.01 | AA2: 3 | AB2: 33.99 | AC2: 33.99 | AF2: 8101 | AG2: 183 | AH2: 4.3 | AI2: 0.0333 | AJ2: 3.58 | AK2: 0.8947 | AM2: 2022-09-30 | AN2: 1042 | AO2: FBA | AP2: 10 | AQ2: 2 | AR2: Portutif-UK | AS2: FBA | AT2: CN | AU2: 公司名称：dongguanshishanchenkangdianzishangwuyouxiangongsi 公司类型：Privately-owned business 办公地址： 陈村北区五巷3号302房 东莞市 虎门镇 广东省 523900 CN | AV2: https://www.amazon.co.uk/gp/help/seller/at-a-glance.html/ref=dp_merchant_link?seller=AGT5ZPYQI2FPY | AW2: Y | AX2: Y | BB2: Y | BC2: Y | BE2: Y | BH2: powerful handheld vacuum cleaner | BI2: 871 g | BJ2: 871.00 g | BK2: 40.6L x 15.2W x 12.7H centimetres | BM2: 1.5 kg | BN2: 1.50 kg | BO2: 41.1 x 15.4 x 13.8 cm | BP2: 41.10 x 15.40 x 13.80 cm
A3: 2 | C3: B0F3JGRDBP | D3: Colour Name: Silver Gray | E3: Brand: NVKHG | Filter type: HEPA Filter | Included components: Anti-static Bristle Heads, Charging Cable | Is cordless?: Yes | Recommended uses for product: Car | F3: NVKHG | G3: https://www.amazon.co.uk/s/ref=bl_dp_s_web_0?ie=UTF8&search-type=ss&index=kitchen-uk&field-keywords=NVKHG | H3: Handheld Vacuum Cleaner, 22000Pa Cordless Car Vacuum Cleaner, 3 Speed Brushless Motor Mini Hoover with Multiple Brush HeadsHigh Power Hand Held Vacuum Cordless, for Office, Home Kitchen, Car,Pet Hair | I3: 手持真空吸尘器，22000Pa无绳汽车真空吸尘器，3速无刷电动机迷你胡佛与多个刷子式头号电源手持真空无线无线，用于办公室，家用厨房，汽车，宠物头发 | J3: 【Brushless Motor and 22000Pa High Power】The rechargeable handheld vacuum cleaner utilizes state-of-the-art brushless motor technology with a speed of up to 80,000 RPM and suction power of up to 22000PA.The brushless design provides stronger suction power, better performance and longer service life compared to traditional motors. 【4 in 1 Mini Hoover】 Our cordless vacuum cleaner is a multifunctional device with vacuuming, blowing, inflating and suction functions. Use the suction and blow function to remove small debris. Use the inflate function to blow up balloons or camping mattresses, or use the blower to fan the air during outdoor activities. Use the powerful suction function to quickly remove air from your hoeing bag. All of this can be accomplished with the compact unit and its versatile attachments 【Cordless Easy Cleaning】This car vacuum cleaner is designed for your convenience and its lightweight, ultra-compact and rechargeable design makes it easy to carry for storage and use wherever you go. With up to 22000PA of suction power, it quickly removes dust, dirt and debris, leaving your car spotless. Three extra anti-static bristle heads are an effective option for removing pet hair, keeping your car fresh and clean 【Compact and Easy to Carry】This hand held vacuum cordless is compact and easy to carry. All parts are washable except the vacuum cleaner itself. This high-performance car hoover comes with a USB-C charging cable for charging via a car charger, mobile power supply or other USB source, The battery charging status of the car hoover is shown on the display, which is very convenient! Note: The battery needs to be fully charged for the first use. 【Easy Maintenance】The car vacuum cleaner cordless allows you to easily empty and clean your vacuum cleaner. the Hepa filter can be washed and reused, and the Hepa filter can be removed and cleaned when the vacuum cleaner filter is full of dust or the suction power is reduced. Other accessories are removable for cleaning The Hepa filter can be washed and reused to ensure efficient suction while keeping out dust and dirt and preventing clogging | K3: 【无刷电机和22000Pa高功率】可充电的手持真空吸尘器利用最先进的无刷电机技术技术，速度高达80,000 rpm且吸力功率高达22000Pa。无刷设计可提供更强的吸力功能，更强的性能，更具性能和更长的服务寿命。吸尘，吹，充气和吸力功能。使用抽吸和打击功能去除小碎片。使用膨胀功能炸毁气球或露营床垫，或在户外活动中使用鼓风机来扇动空气。使用功能强大的吸力功能快速从头袋中取出空气。所有这些都可以通过紧凑的单元及其多功能附件来完成，【无绳易于清洁】此汽车真空吸尘器的设计是为您的便利而设计的，其轻巧，超紧凑型和可充电的设计使您可以轻松携带存储空间和使用，无论您走到哪里。凭借高达22000 pa的吸力，它迅速消除了灰尘，污垢和碎屑，使您的汽车一尘不染。三个额外的抗静电刷头是去除宠物头发的有效选择，使您的汽车新鲜和清洁，紧凑且易于携带。除了真空吸尘器本身，所有零件均可清洗。这款高性能的汽车胡佛配备了USB-C充电电缆，用于通过汽车充电器，移动电源或其他USB来源充电，显示在显示屏上的电池充电状态，显示在显示屏上，非常方便！注意：首次使用电池需要充满电。可以洗涤并重复使用HEPA过滤器，当真空清洁器滤清器充满灰尘或降低吸力功率时，HEPA过滤器可以去除和清洁。可以清除其他配件以清洗HEPA过滤器，并重新使用以确保有效的吸力，同时防止灰尘和污垢并防止堵塞 | L3: https://www.amazon.co.uk/dp/B0F3JGRDBP?psc=1 | M3: https://images-na.ssl-images-amazon.com/images/I/619a1iIETdL._AC_US600_.jpg | N3: B0FFTN6M97 | O3: Home & Kitchen:Kitchen & Home Appliances:Vacuums & Floor Care:Vacuums:Handheld Vacuums | P3: Home & Kitchen | Q3: 475 | R3: 934 | S3: 0.6629 | T3: Handheld Vacuums | U3: 2 | V3: 2511 | W3: 36.7419 | X3: 64005.39 | Y3: 2,000 | Z3: 50980 | AA3: 1 | AB3: 25.49 | AF3: 909 | AG3: 0 | AH3: 4.6 | AI3: 0 | AJ3: 3.14 | AK3: 0.8768 | AM3: 2025-04-02 | AN3: 127 | AO3: FBA | AP3: 10 | AQ3: 1 | AR3: ROBERT MURRAY UK | AS3: FBA | AT3: GB | AU3: 公司名称：ROBERT MURRAY LIMITED 公司类型：Privately-owned business 办公地址： B5 14 ISAAC CLOSE SALFORD UNITED KINGDOM M5 4GL GB | AV3: https://www.amazon.co.uk/gp/help/seller/at-a-glance.html/ref=dp_merchant_link?seller=AFZJAJ8K6AUJZ | BB3: Y | BE3: Y | BG3: Y | BI3: 690 g | BJ3: 690.00 g | BK3: 7L x 20W x 23H centimetres | BM3: 690 g | BN3: 690.00 g | BO3: 23.5 x 21.6 x 7.4 cm | BP3: 23.50 x 21.60 x 7.40 cm
A4: 3 | C4: B0D4M3MSG7 | D4: Colour Name: Orange | Size Name: 14.3"X4.6"X4.0" | E4: Brand: Powools | Special feature: Portable, Lightweight, Cordless, Washable Filter, HEPA, Headlight, Fast Charging | Filter type: HEPA Filter | Included components: Motor*1; Filter*1; Dust Cup*1 | Is cordless?: Yes | F4: Powools | G4: https://www.amazon.co.uk/Powools/b/ref=bl_dp_s_web_84732259031?ie=UTF8&node=84732259031&field-lbr_brands_browse-bin=Powools | H4: Powools Handheld Vacuum Cordless with 2 Filters, Car Vacuum Cleaner High Power with Fast Cahrge Tech, Portable Rechargeable Mini Vacuum with Large-Capacity Battery, Orange, 14.3"X4.6"X4.0" | I4: Powools手持式真空无线带2个过滤器，带有快速Cahrge Tech的汽车真空吸尘器高功率，便携式可充电迷你真空吸尘器，带有大容量电池，橙色，14.3“ x4.6” x4.0” | J4: Cordless Design: The handheld vacuum cleaner features a lightweight and portable design, enabling you to quickly move it from one room to another. It is easy for people of all ages to operate with no effort. You can easily clean the stairs, kitchen, car, or hard-to-reach corners with this cordless handheld vacuum. All-Around Cleaning: Equipped with a powerful motor, the Powools portable vacuum cleaner provides deep cleaning for both your home and car. Coming with three practical attachments, this vacuum cleaner can help you efficiently clean the dirt, dust, and pet hair from sofas, floors, and other hard-to-reach areas. Large-Capacity Battery: The Powools vacuum cleaner is embedded with a large-capacity battery of 2,000mAh. With fast-charge technology, this product can continuously provide strong suction for about 20 minutes with a full charge of 2.5-3 hours. Additionally, there is an over-charging protection design to ensure your safety of use! Improved HEPA Filter: The Powools pet hair vacuum features an enhanced HEPA filter with a premium filter wrap designed to extend filter lifespan further and avoid clogging while ensuring strong suction. Exquisite workmanship with notable durability provides you with an unparalleled user experience. Bright LED Light: The Powools cordless handheld vacuum cleaner features a bright LED light that makes dust hiding nowhere to be found. No more worries when cleaning in dark environments or at night! The LED light can help you easily locate debris, pet hair, and tiny dust. | K4: 无绳设计：手持真空吸尘器具有轻巧且便携式的设计，使您能够将其从一个房间迅速移动到另一个房间。所有年龄段的人都很容易毫不费力。您可以使用这种无绳手持式真空吸尘器轻松清洁楼梯，厨房，汽车或难以到达的角落。带有三个实用的附件，该真空吸尘器可以帮助您有效地清洁来自沙发，地板和其他难以触及的区域的污垢，灰尘和宠物头发。借助快速充电技术，该产品可以连续提供大约20分钟的强大吸力，而全额充电为2.5-3小时。此外，还有一种过度充电的保护设计，以确保您的使用安全性！改进的HEPA过滤器：Powools宠物毛发真空具有增强的HEPA滤波器，其高级滤清器包装纸旨在进一步延长过滤器寿命，并避免堵塞，同时堵塞，同时确保强大的吸力。精致的工艺具有明显的耐用性，为您提供了无与伦比的用户体验。，明亮的LED灯：无绳手持真空吸尘器具有明亮的LED灯，使灰尘无处可寻。在黑暗环境或晚上清洁时不再担心！ LED灯可以帮助您轻松找到碎屑，宠物头发和微小的灰尘。 | L4: https://www.amazon.co.uk/dp/B0D4M3MSG7?psc=1 | M4: https://images-na.ssl-images-amazon.com/images/I/61Fn2ReuTkL._AC_US600_.jpg | N4: B0DFYDQTT3 | O4: Home & Kitchen:Kitchen & Home Appliances:Vacuums & Floor Care:Vacuums:Handheld Vacuums | P4: Home & Kitchen | Q4: 570 | R4: 7 | S4: 0.0112 | T4: Handheld Vacuums | U4: 3 | V4: 2871 | W4: 1.3353 | X4: 71746.29 | Y4: 2,000 | Z4: 49980 | AA4: 1 | AB4: 19.99 | AF4: 2335 | AG4: 6 | AH4: 4.3 | AI4: 0.0021 | AJ4: 3.36 | AK4: 0.8656 | AM4: 2024-08-29 | AN4: 343 | AO4: FBA | AP4: 10 | AQ4: 1 | AR4: Powools-uk | AS4: FBA | AT4: CN | AU4: 公司名称：fuzhoushiyishenglongdianzishangwuyouxiangongsi 公司类型：Privately-owned business 办公地址： shangjiezhenkejidonglu9hao 1haolou12ceng1203shi fuzhoushi minhouxian fujiansheng 350108 CN | AV4: https://www.amazon.co.uk/gp/help/seller/at-a-glance.html/ref=dp_merchant_link?seller=A19XAXWJJ1M75 | AW4: Y | AX4: Y | BB4: Y | BC4: Y | BG4: Y | BH4: handheld vacuum cleaner | BI4: 0.66 Kilograms | BJ4: 660.00 g | BK4: 36.3L x 10W x 11.7H centimetres | BM4: 980 g | BN4: 980.00 g | BO4: 37.1 x 13.2 x 11.3 cm | BP4: 37.10 x 13.20 x 11.30 cm
A5: 4 | C5: B08M9JQ1J1 | D5: Colour Name: Orange | Size Name: 14.3"X4.6"X4.0" | E5: Brand: Shark | Special feature: Powerful Suction, Portable, Motorised Pet Tool, Dusting Brush & Crevice tool, Washable Filter | Filter type: HEPA Filter | Included components: Dusting Brush | Is cordless?: Yes | F5: Shark | G5: https://www.amazon.co.uk/stores/Shark/page/525766F4-D5DD-4FFC-8A20-92AC184FF87C?is_byline_deeplink=true&deeplink=21BE5559-6199-42D2-8790-41111D79D214&redirect_store_id=525766F4-D5DD-4FFC-8A20-92AC184FF87C&lp_asin=B08M9JQ1J1&ref_=ast_bln&store_ref=bl_ast_dp_brandLogo_sto | H5: Shark Handheld Cordless Vacuum Cleaner with Pet Tool, Crevice Tool & Dusting Brush, 80 W, 0.45 liters, 10 Minute Run-Time, Washable Filter, Black & Yellow, CH950UKT | I5: 鲨鱼手持式无线真空吸尘器，带宠物工具，缝隙工具和粉尘刷，80 W，0.45升，运行10分钟，可洗的滤清器，黑色和黄色，CH950UKT | J5: FAST, EASY CORDLESS CLEANING: Quickly remove dust, debris & pet hair from surfaces & soft furnishings INCLUDES 3 ATTACHMENTS: Motorised Pet Tool, Dusting Brush & Crevice Tool. Perfect for homes with pets UP TO 10 MINUTES RUN-TIME: No-fade Lithium-ion technology ensures lasting power & performance ONE-TOUCH EASY EMPTY: Large capacity dust cup with easy debris disposal. Washable filter INCLUDES: Shark Cordless Handheld Vacuum Cleaner, Charger (UK Plug), Motorised Pet Tool, Dusting Brush, Crevice Tool. In Use Weight: 1.2kg. Colour: Black and Yellow 2-YEAR GUARANTEE: Upon registration with Shark, UK & ROI only | K5: 快速，简单的无绳清洁：从表面和柔软家具中迅速清除灰尘，碎屑和宠物头发，包括3个附件：电动宠物工具，灰尘刷和缝隙工具。非常适合带宠物的房屋，最多10分钟的运行时间：无效的锂离子技术可确保持久的功率和性能，一键式易于空的空空：大容量灰尘杯，带有易于碎屑。可洗的过滤器，包括：鲨鱼无绳手持真空吸尘器，充电器（英国插头），电动宠物工具，灰尘刷，缝隙工具。使用重量：1.2kg。颜色：黑色和黄色，两年保证：仅在英国鲨鱼注册后 | L5: https://www.amazon.co.uk/dp/B08M9JQ1J1?psc=1 | M5: https://images-na.ssl-images-amazon.com/images/I/71y7U3sicPL._AC_US600_.jpg | N5: B08M9JQ1J1 | O5: Home & Kitchen:Kitchen & Home Appliances:Vacuums & Floor Care:Vacuums:Handheld Vacuums | P5: Home & Kitchen | Q5: 833 | R5: -558 | S5: -2.9368 | T5: Handheld Vacuums | U5: 4 | V5: 4345 | W5: 1.795 | X5: 323659.03 | Y5: 4,000 | Z5: 223469.98 | AA5: 1 | AB5: 74.49 | AE5: 31 | AF5: 6189 | AG5: 69 | AH5: 4.5 | AI5: 0.0159 | AJ5: 5.25 | AK5: 0.9295 | AM5: 2020-11-08 | AN5: 1733 | AO5: AMZ | AP5: 10 | AQ5: 9 | AR5: Amazon | AS5: AMZ | AW5: Y | AX5: Y | BB5: Y | BC5: Y | BE5: Y | BH5: handheld vacuums | BI5: 1.2 Kilograms | BJ5: 1.20 kg | BK5: 20.5L x 3.7W x 4.3H centimetres | BM5: 1.91 kg | BN5: 1.91 kg | BO5: 46.8 x 17.1 x 13.9 cm | BP5: 46.80 x 17.10 x 13.90 cm
A6: 5 | C6: B0FB3RQ9D9 | D6: Colour Name: Blue | E6: Brand: Milunho | Special feature: Cordless | Filter type: HEPA Filter | Form factor: Handheld | Colour: Blue | F6: Milunho | G6: https://www.amazon.co.uk/Milunho/b/ref=bl_dp_s_web_64927021031?ie=UTF8&node=64927021031&field-lbr_brands_browse-bin=Milunho | H6: Milunho Handheld Vacuum Cleaner, 9500PA Car Vacuum Cleaner Cordless with Powerful Suction, Lightweight & Portable Car Cleaner for Car/Home/Pet | I6: Milunho手持式吸尘器，9500PA汽车真空吸尘器无线，可强大的吸力，轻巧和便携式汽车清洁器，用于汽车/家用/宠物 | J6: 【NEWLY UPGRADED 9500PA STRONG SUCTION POWER】: The upgraded handheld vacuum cleaner provides up to 9500Pa strong cyclonic suction power, which is twice as strong as the average car vacuum cleaner. Car Vacuum idea for cleaning dust, crumbs and pet hair in cars, sofas, walls, stairs and other hard-to-reach places. 【DEEP CLEANING & NO BLIND CORNERS】: The handheld vacuum cleaner is equipped with 3 multi-function accessories (flathead, extendable, or brush nozzle) to support all-round cleaning. 500ML large-capacity transparent dust bucket, and the "one-button dust removal" design makes emptying easy. HEPA filter can effectively filter dust and fine particles to avoid secondary pollution. Regular cleaning of the washable filter prevents loss of suction and blockage, maintains good suction. 【LIGHTWEIGHT AND CORDLESS】:The hand held vacuum cordless get rid of bulky or tangled cords, making them easy to carry and store. Equipped with extendable accessory to visualize efficient cleaning in the deep without worrying about crevices corners and dark areas, handheld Vacuum for a deeper, more thorough clean however you want and ideal for cleaning inside the home/car. 【SAFE & FAST CHARGING】:The mini vacuum cleaner is equipped with 3* 2000mAh high performance Li-Ion battery for long battery life.15-25 Mins Runtime, and only takes 3-4 hours to charge. Provide temperature/short circuit/overvoltage/overcurrent/overcharge protection to ensure the safety of the device. 【AMAZING GIFT】: This lightweight portable vacuum cleaner must be a thoughtful gift for your family or friends who have pets or cars. If you have any questions, please feel free to contact us for support and assistance! WORRY-FREE CUSTOMER SERVICE | K6: 【新升级的9500Pa强吸力】：升级的手持式真空吸尘器可提供高达9500Pa强的气旋吸力功率，其强度是普通汽车真空吸尘器的两倍。汽车真空的想法，用于清洁汽车，沙发，墙壁，楼梯和其他难以到达的地方的灰尘，碎屑和宠物头发。 500毫升大容量透明的防尘桶和“一次键防尘”设计使排空变得容易。 HEPA过滤器可以有效地过滤灰尘和细颗粒，以避免继发污染。定期清洁可洗的过滤器可防止吸力和阻塞的损失，保持良好的吸力。配备可扩展的附件，可在深处可视化有效的清洁，而不必担心缝隙角和黑暗区域，手持式真空，以进行更深，更彻底的清洁，无论您想要，并且是在家用/汽车内进行清洁的理想选择。提供温度/短路/过电压/过电流/过度充电保护，以确保设备的安全性。如果您有任何疑问，请随时与我们联系以寻求支持和帮助！无忧的客户服务 | L6: https://www.amazon.co.uk/dp/B0FB3RQ9D9?psc=1 | M6: https://images-na.ssl-images-amazon.com/images/I/71sCJ4g1QiL._AC_US600_.jpg | N6: B0F9LBHL28 | O6: Home & Kitchen:Kitchen & Home Appliances:Vacuums & Floor Care:Vacuums:Handheld Vacuums | P6: Home & Kitchen | Q6: 1116 | R6: -344 | S6: -0.6866 | T6: Handheld Vacuums | U6: 5 | V6: 3185 | W6: 22.1719 | X6: 73223.15 | Y6: 3,000 | Z6: 68970 | AA6: 1 | AB6: 22.99 | AF6: 155 | AG6: 107 | AH6: 4.1 | AI6: 0.0336 | AJ6: 3.14 | AK6: 0.8634 | AM6: 2025-05-27 | AN6: 72 | AO6: FBA | AP6: 9.9 | AQ6: 2 | AR6: ONE WONG Limited | AS6: FBA | AT6: GB | AU6: 公司名称：ONE WONG LIMITED 公司类型：Privately-owned business 办公地址： 712 POTTERS COURT, FENTON HALL CLOSE STOKE-ON-TRENT UNITED KINGDOM ST4 4PT GB | AV6: https://www.amazon.co.uk/gp/help/seller/at-a-glance.html/ref=dp_merchant_link?seller=A13S52GK5RIYE5 | BB6: Y | BC6: Y | BI6: 750 g | BJ6: 750.00 g | BK6: 35L x 11.5W x 9.5H centimetres | BM6: 750 g | BN6: 750.00 g | BO6: 35.1 x 11.9 x 9.6 cm | BP6: 35.10 x 11.90 x 9.60 cm
A7: 6 | C7: B0DJ2YVV6F | D7: Colour Name: Black Gold | E7: Brand: Nctoberows | Special feature: Portable, Wireless | Filter type: HEPA Filter | Included components: 6* Blow-Suction Attachments, Crevice Nozzle, Brush Nozzle, Wide-Mouth Nozzle | Is cordless?: Yes | F7: Nctoberows | G7: https://www.amazon.co.uk/s/ref=bl_dp_s_web_0?ie=UTF8&search-type=ss&index=kitchen-uk&field-keywords=Nctoberows | H7: Nctoberows Handheld Vacuum Cleaner Cordless, 22000Pa Powerful Car Mini Vacuum Cleaner, Rechargeable Portable Lightweight dust catcher for Home Car Carpet Stairs Pet Hair Deep Cleaning | I7: nctoberows手持真空吸尘器无绳，22000 pa强大的汽车迷你真空吸尘器，可充电的便携式便携式轻巧的防尘架，用于家庭汽车地毯楼梯宠物头发宠物头发深清洁 | J7: 【4-IN-1 Car Vacuum Cleaner】The mini Handheld Vacuum cleaner used with 6 accessories can be used to get 4 modes of suction, blowing, inflation and vacuum compression to meet your different use scenarios. Not only can be used for daily blowing & vacuuming cleaning,such as dust cleaning on the surface of seat, keyboard and cabinet corner, but also be used as a vacuum pump for or inflate balloons, swim rings and more. 【Powerful Suction】This dust catcher equipped with a powerful motor and with cordless and portable design, it offers three suction levels: high (22000PA), medium (16000PA) and low (9000PA). The adjustable modes make it perfect for cleaning dust and pet hair from your car, sofa and floor with maximum efficiency. 【Type-C Fast Charging & Long Battery Life】The Electric Vacuum Cleaner has a built-in 6000mAh battery with a fast Type-C charging port. It can be easily charged using a car charger, mobile power, laptop, rechargeable battery, and other methods. It takes only 3 hours to charge and high performance mode lasts 12 minutes, medium performance mode lasts 18 minutes, and low performance mode lasts 30 minutes. 【Wide Application】The Cordless Vacuum Cleaner comes with many different detachable brush head nozzle accessories for cleaning various scenes. For example, it can thoroughly clean car interior, dust, crumbs, pet hair from carpets, kitchen, living room and offices with outstanding performance. 【Effortless Maintenance】With just one-click dismantling, you can easily dump garbage and clean the vacuum cleaner. The HEPA filter can be washed and reused, ensuring efficient suction power while keeping dust and dirt outside to prevent blockage. 【What You Get】You will receive 1* Handheld Vacuum Cleaner, 2* Filters, 6* Blow-Suction Attachments, 1* Type-C Charging Cable, 1* User Manual, 1*Packaging Box. If you have any questions, please feel free to contact us, we will reply you within 24 hours. | K7: 【4英寸1辆汽车真空吸尘器】用6个配件使用的迷你手持真空吸尘器可用于获得4种吸力，吹吹，通货膨胀和真空压缩，以满足您的不同使用情况。不仅可以用于日常吹和吸尘清洁，例如在座椅表面，键盘和橱柜角上清洁灰尘，还可以用作吸尘器，用于气球，游泳环，更多。可调节的模式非常适合从汽车，沙发和地板上清洁灰尘和宠物头发，并具有最大的效率。可以使用汽车充电器，移动电源，笔记本电脑，可充电电池和其他方法轻松充电。充电只需要3个小时，高性能模式持续12分钟，中等性能模式持续18分钟，低性能模式持续30分钟。例如，它可以彻底清洁汽车内部，灰尘，碎屑，地毯，厨房，客厅和表现出色的办公室。 HEPA过滤器可以洗涤和重复使用，从而确保有效的吸力，同时将灰尘和灰尘保持在外面以防止阻塞。如果您有任何疑问，请随时与我们联系，我们将在24小时内回复您。 | L7: https://www.amazon.co.uk/dp/B0DJ2YVV6F?psc=1 | M7: https://images-na.ssl-images-amazon.com/images/I/71McuBMh05L._AC_US600_.jpg | N7: B0FDFW9J9Y | O7: Home & Kitchen:Kitchen & Home Appliances:Vacuums & Floor Care:Vacuums:Handheld Vacuums | P7: Home & Kitchen | Q7: 1612 | R7: -1418 | S7: -1.5808 | T7: Handheld Vacuums | U7: 6 | V7: 1924 | W7: 0.0538 | X7: 40865.758 | Y7: 2,000 | Z7: 21240 | AA7: 1 | AB7: 21.24 | AF7: 376 | AG7: 138 | AH7: 4.3 | AI7: 0.0717 | AJ7: 3.14 | AK7: 0.8522 | AM7: 2024-09-26 | AN7: 315 | AO7: FBA | AP7: 10 | AQ7: 1 | AR7: NC-UK | AS7: FBA | AT7: CN | AU7: 公司名称：Yichang Haimu Technology Co., Ltd. 公司类型：Privately-owned business 办公地址： 港城路6号1号楼1楼众创基地1015 宜昌 高新区 湖北 443000 CN | AV7: https://www.amazon.co.uk/gp/help/seller/at-a-glance.html/ref=dp_merchant_link?seller=A2PCFP7KL71SXW | AX7: Y | BB7: Y | BC7: Y | BG7: Y | BH7: car hoover | BI7: 680 g | BJ7: 680.00 g | BK7: 23L x 10W x 9H centimetres | BM7: 680 g | BN7: 680.00 g | BO7: 23.4 x 20.7 x 7.4 cm | BP7: 23.40 x 20.70 x 7.40 cm
A8: 7 | C8: B0CCSDRKLJ | D8: Colour Name: Black Gold | E8: Brand: CubeTECH | Special feature: Bagless, Spotless Cleaning | Filter type: Cloth | Included components: Accessory Kit, Mop, SlimeLine 17cm Nozzle, Standard 28cm Nozzle | Is cordless?: Yes | F8: CubeTECH | G8: https://www.amazon.co.uk/stores/CubeTECH/page/1A978791-E693-4905-BDE2-F87D2A48047B?is_byline_deeplink=true&deeplink=1A978791-E693-4905-BDE2-F87D2A48047B&redirect_store_id=1A978791-E693-4905-BDE2-F87D2A48047B&lp_asin=B0CCSDRKLJ&ref_=ast_bln | H8: CubeTECH CTWV2 Cordless Vacuum Cleaner - Handheld Vacuum Cordless Rechargeable Power Kit (Microfibre Cloth & Window Squeegee Vacuum) Cleaning Condensation Double Glazed Glass Window Cleaning | I8: Cubetech CTWV2无绳真空吸尘器 - 手持真空无线可充电功率套件（微纤维布和窗户挤压真空吸尘器）清洁凝结双玻璃杯玻璃窗户清洁 | J8: Powerful Suction: The CTWV2 features a high-performance motor that generates strong suction, effectively extracting water, dirt, and cleaning solutions from windows, leaving them spotless and dry. Large Capacity and Quick Emptying: The CTWV2 boasts a generous water tank capacity, enabling continuous cleaning without frequent emptying. The tank is easily removed and emptied without mess. Versatile Cleaning Accessories: With a wide 28cm suction nozzle for larger windows and SlimLine 17cm nozzle fro hard to reach places, precision spray bottle with microfiber cloth, you have all the tools you need for exceptional results. Cordless Freedom: No more hassle with cords and outlets. Powered by a high-capacity rechargeable lithium battery, move around freely without restriction. Clean windows indoors or outdoors with ease. Time-Saving and Efficient: Thanks to its efficient cleaning technology, Achieve streak-free windows in a fraction of the time, leaving you with more free time for other activities. | K8: 功能强大的吸力：CTWV2具有高性能的电动机，可产生强大的吸力，有效地从窗户上提取水，污垢和清洁溶液，使它们变得毫无用处和干燥。坦克很容易被拆除和清空，而无需混乱。多功能清洁配件：带有28厘米宽的吸气喷嘴，用于较大的窗户，而Slimline 17厘米的喷嘴很难到达位置，精密喷雾瓶带有微型纤维布，您需要所有需要出色的效果的工具。由高容量可充电锂电池提供动力，无限制地四处移动。在室内或室外清洁窗户，节省时间和高效：由于其有效的清洁技术，在很短的时间内实现无条纹的窗户，使您有更多的空闲时间进行其他活动。 | L8: https://www.amazon.co.uk/dp/B0CCSDRKLJ?psc=1 | M8: https://images-na.ssl-images-amazon.com/images/I/71X2i24T9FL._AC_US600_.jpg | N8: B0CCSDRKLJ | O8: Home & Kitchen:Kitchen & Home Appliances:Vacuums & Floor Care:Vacuums:Handheld Vacuums | P8: Home & Kitchen | Q8: 1714 | R8: -209 | S8: -0.1452 | T8: Handheld Vacuums | U8: 8 | V8: 1842 | W8: 2.0587 | X8: 55167.902 | Y8: 1,000 | Z8: 29950 | AA8: 1 | AB8: 29.95 | AF8: 1063 | AG8: 64 | AH8: 4.3 | AI8: 0.0347 | AJ8: 3.27 | AK8: 0.8908 | AM8: 2023-07-24 | AN8: 745 | AO8: FBA | AP8: 10 | AQ8: 2 | AR8: Remora Prime | AS8: FBA | AT8: GB | AU8: 公司名称：Remora Electrical Ltd 公司类型：Privately-owned business 办公地址： Unit 8A, Shortwood Court Shortwood Business Park, Hoyland BARNSLEY South Yorkshire S74 9LH GB | AV8: https://www.amazon.co.uk/gp/help/seller/at-a-glance.html/ref=dp_merchant_link?seller=A1N6EK8CPAOH2W | AX8: Y | BB8: Y | BC8: Y | BH8: window vacuum cleaner cordless | BI8: 730 Grams | BJ8: 730.00 g | BK8: 28L x 17W x 34H centimetres | BM8: 1.16 kg | BN8: 1.16 kg | BO8: 31.2 x 22.6 x 11.9 cm | BP8: 31.20 x 22.60 x 11.90 cm
