Workbook

Sheet 决策总览
A2: 墨西哥美客多｜壁灯选品决策
A3: 范围：用户上传的TOP400商品链接；近30天销量与销售额为工具估算值。全站结果数3,586来自截图，不作为市场总量分母。
A5: 样本链接 | B5: =COUNTA('400链接明细'!B4:B403) -> 400 | C5: 样本30天销量 | D5: =SUM('400链接明细'!N4:N403) -> 69143 | E5: 样本销售额 MXN | F5: =SUM('400链接明细'!Q4:Q403) -> 15718189 | G5: 核心壁灯链接 | H5: =SUM(B11:B15) -> 319 | J5: 平均销售额MXN | K5: =15718189/69143 -> 227.32871
A6: 核心壁灯销量 | B6: =C16 -> 54348 | C6: 核心壁灯销售额 MXN | D6: =D16 -> 11940507 | E6: 相邻/待复核销量 | F6: =D5-B6 -> 14795 | G6: 原排序TOP30销量 | H6: =SUM('400链接明细'!N4:N33) -> 20551
A8: 细分结构：主用途互斥归类；只用“核心壁灯”五类计算壁灯机会
A10: 细分 | B10: 链接数 | C10: 30天销量 | D10: 30天销售额 MXN | E10: 平均标价 MXN | F10: 占核心销量 | G10: 判断
A11: 有线户外/通用壁灯 | B11: =COUNTIF('400链接明细'!$D$4:$D$403,A11) -> 189 | C11: =SUMIF('400链接明细'!$D$4:$D$403,A11,'400链接明细'!$N$4:$N$403) -> 33039 | D11: =SUMIF('400链接明细'!$D$4:$D$403,A11,'400链接明细'!$Q$4:$Q$403) -> 6436705.6 | E11: =IFERROR(AVERAGEIF('400链接明细'!$D$4:$D$403,A11,'400链接明细'!$J$4:$J$403),0) -> 201.61434 | F11: =IFERROR(C11/$C$16,0) -> 0.60791565 | G11: 高需求，高同质化
A12: 太阳能户外壁灯 | B12: =COUNTIF('400链接明细'!$D$4:$D$403,A12) -> 41 | C12: =SUMIF('400链接明细'!$D$4:$D$403,A12,'400链接明细'!$N$4:$N$403) -> 8111 | D12: =SUMIF('400链接明细'!$D$4:$D$403,A12,'400链接明细'!$Q$4:$Q$403) -> 1940810 | E12: =IFERROR(AVERAGEIF('400链接明细'!$D$4:$D$403,A12,'400链接明细'!$J$4:$J$403),0) -> 240.32585 | F12: =IFERROR(C12/$C$16,0) -> 0.14924192 | G12: 感应/续航可差异化
A13: 充电/感应壁灯 | B13: =COUNTIF('400链接明细'!$D$4:$D$403,A13) -> 39 | C13: =SUMIF('400链接明细'!$D$4:$D$403,A13,'400链接明细'!$N$4:$N$403) -> 5107 | D13: =SUMIF('400链接明细'!$D$4:$D$403,A13,'400链接明细'!$Q$4:$Q$403) -> 1196764.4 | E13: =IFERROR(AVERAGEIF('400链接明细'!$D$4:$D$403,A13,'400链接明细'!$J$4:$J$403),0) -> 265.99949 | F13: =IFERROR(C13/$C$16,0) -> 0.093968499 | G13: 先验证电池与退货
A14: 复古/灯笼壁灯 | B14: =COUNTIF('400链接明细'!$D$4:$D$403,A14) -> 24 | C14: =SUMIF('400链接明细'!$D$4:$D$403,A14,'400链接明细'!$N$4:$N$403) -> 4780 | D14: =SUMIF('400链接明细'!$D$4:$D$403,A14,'400链接明细'!$Q$4:$Q$403) -> 1594593.6 | E14: =IFERROR(AVERAGEIF('400链接明细'!$D$4:$D$403,A14,'400链接明细'!$J$4:$J$403),0) -> 351.52917 | F14: =IFERROR(C14/$C$16,0) -> 0.087951719 | G14: 套装与外观有价差
A15: 室内装饰壁灯 | B15: =COUNTIF('400链接明细'!$D$4:$D$403,A15) -> 26 | C15: =SUMIF('400链接明细'!$D$4:$D$403,A15,'400链接明细'!$N$4:$N$403) -> 3311 | D15: =SUMIF('400链接明细'!$D$4:$D$403,A15,'400链接明细'!$Q$4:$Q$403) -> 771633.19 | E15: =IFERROR(AVERAGEIF('400链接明细'!$D$4:$D$403,A15,'400链接明细'!$J$4:$J$403),0) -> 237.44962 | F15: =IFERROR(C15/$C$16,0) -> 0.060922205 | G15: 低规模，造型定向验证
A16: 核心壁灯合计 | B16: =SUM(B11:B15) -> 319 | C16: =SUM(C11:C15) -> 54348 | D16: =SUM(D11:D15) -> 11940507 | F16: =SUM(F11:F15) -> 1
A17: 邻近：橱柜/衣柜灯 | B17: =COUNTIF('400链接明细'!$D$4:$D$403,A17) -> 47 | C17: =SUMIF('400链接明细'!$D$4:$D$403,A17,'400链接明细'!$N$4:$N$403) -> 9588 | D17: =SUMIF('400链接明细'!$D$4:$D$403,A17,'400链接明细'!$Q$4:$Q$403) -> 1936310 | E17: =IFERROR(AVERAGEIF('400链接明细'!$D$4:$D$403,A17,'400链接明细'!$J$4:$J$403),0) -> 214.50681 | G17: 关键词污染：单独成类
A18: 邻近：路灯/投光灯 | B18: =COUNTIF('400链接明细'!$D$4:$D$403,A18) -> 7 | C18: =SUMIF('400链接明细'!$D$4:$D$403,A18,'400链接明细'!$N$4:$N$403) -> 2031 | D18: =SUMIF('400链接明细'!$D$4:$D$403,A18,'400链接明细'!$Q$4:$Q$403) -> 767323.67 | E18: =IFERROR(AVERAGEIF('400链接明细'!$D$4:$D$403,A18,'400链接明细'!$J$4:$J$403),0) -> 296.59286 | G18: 远离壁灯核心定义
A19: 邻近：镜前灯 | B19: =COUNTIF('400链接明细'!$D$4:$D$403,A19) -> 14 | C19: =SUMIF('400链接明细'!$D$4:$D$403,A19,'400链接明细'!$N$4:$N$403) -> 1365 | D19: =SUMIF('400链接明细'!$D$4:$D$403,A19,'400链接明细'!$Q$4:$Q$403) -> 426682.49 | E19: =IFERROR(AVERAGEIF('400链接明细'!$D$4:$D$403,A19,'400链接明细'!$J$4:$J$403),0) -> 294.565 | G19: 另作镜前灯赛道
A20: 邻近：楼梯/嵌入灯 | B20: =COUNTIF('400链接明细'!$D$4:$D$403,A20) -> 8 | C20: =SUMIF('400链接明细'!$D$4:$D$403,A20,'400链接明细'!$N$4:$N$403) -> 1123 | D20: =SUMIF('400链接明细'!$D$4:$D$403,A20,'400链接明细'!$Q$4:$Q$403) -> 342060.28 | E20: =IFERROR(AVERAGEIF('400链接明细'!$D$4:$D$403,A20,'400链接明细'!$J$4:$J$403),0) -> 307.185 | G20: 独立场景验证
A21: 邻近：顶灯/配件/地灯 | B21: =COUNTIF('400链接明细'!$D$4:$D$403,A21) -> 3 | C21: =SUMIF('400链接明细'!$D$4:$D$403,A21,'400链接明细'!$N$4:$N$403) -> 243 | D21: =SUMIF('400链接明细'!$D$4:$D$403,A21,'400链接明细'!$Q$4:$Q$403) -> 156691.36 | E21: =IFERROR(AVERAGEIF('400链接明细'!$D$4:$D$403,A21,'400链接明细'!$J$4:$J$403),0) -> 721.04 | G21: 非核心
A22: 待人工复核 | B22: =COUNTIF('400链接明细'!$D$4:$D$403,A22) -> 2 | C22: =SUMIF('400链接明细'!$D$4:$D$403,A22,'400链接明细'!$N$4:$N$403) -> 445 | D22: =SUMIF('400链接明细'!$D$4:$D$403,A22,'400链接明细'!$Q$4:$Q$403) -> 148614.74 | E22: =IFERROR(AVERAGEIF('400链接明细'!$D$4:$D$403,A22,'400链接明细'!$J$4:$J$403),0) -> 380.44 | G22: 链接用途需人工复核
A23: 相邻/待复核合计 | B23: =SUM(B17:B22) -> 81 | C23: =SUM(C17:C22) -> 14795 | D23: =SUM(D17:D22) -> 3777682.5
A24: 400链接校核 | B24: =B16+B23 -> 400 | C24: =C16+C23 -> 69143 | D24: =D16+D23 -> 15718189
A27: 核心壁灯价格带（链接标价；套装仍按单链接计销量）
A28: 标价 MXN | B28: 链接数 | C28: 30天销量 | D28: 30天销售额 MXN | E28: 销量占比
A29: <100 | B29: =COUNTIFS('400链接明细'!$J$4:$J$403,"<100",'400链接明细'!$AJ$4:$AJ$403,1) -> 21 | C29: =SUMIFS('400链接明细'!$N$4:$N$403,'400链接明细'!$J$4:$J$403,"<100",'400链接明细'!$AJ$4:$AJ$403,1) -> 3376 | D29: =SUMIFS('400链接明细'!$Q$4:$Q$403,'400链接明细'!$J$4:$J$403,"<100",'400链接明细'!$AJ$4:$AJ$403,1) -> 309852.26 | E29: =IFERROR(C29/$C$16,0) -> 0.062118201 | J29: 试验优先级 | K29: 切入与判断
A30: 100–149 | B30: =COUNTIFS('400链接明细'!$J$4:$J$403,">=100",'400链接明细'!$J$4:$J$403,"<150",'400链接明细'!$AJ$4:$AJ$403,1) -> 64 | C30: =SUMIFS('400链接明细'!$N$4:$N$403,'400链接明细'!$J$4:$J$403,">=100",'400链接明细'!$J$4:$J$403,"<150",'400链接明细'!$AJ$4:$AJ$403,1) -> 11604 | D30: =SUMIFS('400链接明细'!$Q$4:$Q$403,'400链接明细'!$J$4:$J$403,">=100",'400链接明细'!$J$4:$J$403,"<150",'400链接明细'!$AJ$4:$AJ$403,1) -> 1571267.2 | E30: =IFERROR(C30/$C$16,0) -> 0.21351292 | J30: 1 有线户外 | K30: 单支 150–199；双支套装 309–349：检验防水、色温、安装与净利。
A31: 150–199 | B31: =COUNTIFS('400链接明细'!$J$4:$J$403,">=150",'400链接明细'!$J$4:$J$403,"<200",'400链接明细'!$AJ$4:$AJ$403,1) -> 75 | C31: =SUMIFS('400链接明细'!$N$4:$N$403,'400链接明细'!$J$4:$J$403,">=150",'400链接明细'!$J$4:$J$403,"<200",'400链接明细'!$AJ$4:$AJ$403,1) -> 14111 | D31: =SUMIFS('400链接明细'!$Q$4:$Q$403,'400链接明细'!$J$4:$J$403,">=150",'400链接明细'!$J$4:$J$403,"<200",'400链接明细'!$AJ$4:$AJ$403,1) -> 2518535.9 | E31: =IFERROR(C31/$C$16,0) -> 0.25964157 | J31: 2 复古/灯笼 | K31: 单支/双支、黑色/铜色，明确是否含灯泡、底座安装方式。
A32: 200–299 | B32: =COUNTIFS('400链接明细'!$J$4:$J$403,">=200",'400链接明细'!$J$4:$J$403,"<300",'400链接明细'!$AJ$4:$AJ$403,1) -> 122 | C32: =SUMIFS('400链接明细'!$N$4:$N$403,'400链接明细'!$J$4:$J$403,">=200",'400链接明细'!$J$4:$J$403,"<300",'400链接明细'!$AJ$4:$AJ$403,1) -> 20025 | D32: =SUMIFS('400链接明细'!$Q$4:$Q$403,'400链接明细'!$J$4:$J$403,">=200",'400链接明细'!$J$4:$J$403,"<300",'400链接明细'!$AJ$4:$AJ$403,1) -> 5178411.5 | E32: =IFERROR(C32/$C$16,0) -> 0.36845882 | J32: 3 太阳能户外 | K32: 双支 229–299；实测续航、雨淋、感应距离，不夸大流明。
A33: 300–499 | B33: =COUNTIFS('400链接明细'!$J$4:$J$403,">=300",'400链接明细'!$J$4:$J$403,"<500",'400链接明细'!$AJ$4:$AJ$403,1) -> 28 | C33: =SUMIFS('400链接明细'!$N$4:$N$403,'400链接明细'!$J$4:$J$403,">=300",'400链接明细'!$J$4:$J$403,"<500",'400链接明细'!$AJ$4:$AJ$403,1) -> 4413 | D33: =SUMIFS('400链接明细'!$Q$4:$Q$403,'400链接明细'!$J$4:$J$403,">=300",'400链接明细'!$J$4:$J$403,"<500",'400链接明细'!$AJ$4:$AJ$403,1) -> 1618128.9 | E33: =IFERROR(C33/$C$16,0) -> 0.08119894 | J33: 4 充电感应 | K33: 先小样试点；验证电池寿命、磁吸跌落、传感误触与退货。
A34: ≥500 | B34: =COUNTIFS('400链接明细'!$J$4:$J$403,">=500",'400链接明细'!$AJ$4:$AJ$403,1) -> 9 | C34: =SUMIFS('400链接明细'!$N$4:$N$403,'400链接明细'!$J$4:$J$403,">=500",'400链接明细'!$AJ$4:$AJ$403,1) -> 819 | D34: =SUMIFS('400链接明细'!$Q$4:$Q$403,'400链接明细'!$J$4:$J$403,">=500",'400链接明细'!$AJ$4:$AJ$403,1) -> 744310.93 | E34: =IFERROR(C34/$C$16,0) -> 0.015069552 | J34: 决策门槛 | K34: 取得单SKU实际费率/运费/税/广告/退货成本后再计算边际利润。
A36: 店铺结构：核心壁灯样本
A37: 店铺类型 | B37: 链接数 | C37: 30天销量 | D37: 30天销售额 MXN | E37: 每链接30天销量
A38: 本土店 | B38: =COUNTIFS('400链接明细'!$I$4:$I$403,A38,'400链接明细'!$AJ$4:$AJ$403,1) -> 144 | C38: =SUMIFS('400链接明细'!$N$4:$N$403,'400链接明细'!$I$4:$I$403,A38,'400链接明细'!$AJ$4:$AJ$403,1) -> 27708 | D38: =SUMIFS('400链接明细'!$Q$4:$Q$403,'400链接明细'!$I$4:$I$403,A38,'400链接明细'!$AJ$4:$AJ$403,1) -> 5787498.7 | E38: =IFERROR(C38/B38,0) -> 192.41667
A39: 跨境店 | B39: =COUNTIFS('400链接明细'!$I$4:$I$403,A39,'400链接明细'!$AJ$4:$AJ$403,1) -> 175 | C39: =SUMIFS('400链接明细'!$N$4:$N$403,'400链接明细'!$I$4:$I$403,A39,'400链接明细'!$AJ$4:$AJ$403,1) -> 26640 | D39: =SUMIFS('400链接明细'!$Q$4:$Q$403,'400链接明细'!$I$4:$I$403,A39,'400链接明细'!$AJ$4:$AJ$403,1) -> 6153008 | E39: =IFERROR(C39/B39,0) -> 152.22857
A42: 核心壁灯品牌（按归一品牌汇总；“Genérica”是泛称）
A43: 品牌 | B43: 链接数 | C43: 30天销量 | D43: 30天销售额 MXN
A44: dehobo | B44: =COUNTIFS('400链接明细'!$G$4:$G$403,A44,'400链接明细'!$AJ$4:$AJ$403,1) -> 49 | C44: =SUMIFS('400链接明细'!$N$4:$N$403,'400链接明细'!$G$4:$G$403,A44,'400链接明细'!$AJ$4:$AJ$403,1) -> 6000 | D44: =SUMIFS('400链接明细'!$Q$4:$Q$403,'400链接明细'!$G$4:$G$403,A44,'400链接明细'!$AJ$4:$AJ$403,1) -> 912497.61
A45: vanance | B45: =COUNTIFS('400链接明细'!$G$4:$G$403,A45,'400链接明细'!$AJ$4:$AJ$403,1) -> 16 | C45: =SUMIFS('400链接明细'!$N$4:$N$403,'400链接明细'!$G$4:$G$403,A45,'400链接明细'!$AJ$4:$AJ$403,1) -> 4415 | D45: =SUMIFS('400链接明细'!$Q$4:$Q$403,'400链接明细'!$G$4:$G$403,A45,'400链接明细'!$AJ$4:$AJ$403,1) -> 684391.54
A46: judeng | B46: =COUNTIFS('400链接明细'!$G$4:$G$403,A46,'400链接明细'!$AJ$4:$AJ$403,1) -> 22 | C46: =SUMIFS('400链接明细'!$N$4:$N$403,'400链接明细'!$G$4:$G$403,A46,'400链接明细'!$AJ$4:$AJ$403,1) -> 3979 | D46: =SUMIFS('400链接明细'!$Q$4:$Q$403,'400链接明细'!$G$4:$G$403,A46,'400链接明细'!$AJ$4:$AJ$403,1) -> 806046.09
A47: generica | B47: =COUNTIFS('400链接明细'!$G$4:$G$403,A47,'400链接明细'!$AJ$4:$AJ$403,1) -> 21 | C47: =SUMIFS('400链接明细'!$N$4:$N$403,'400链接明细'!$G$4:$G$403,A47,'400链接明细'!$AJ$4:$AJ$403,1) -> 2942 | D47: =SUMIFS('400链接明细'!$Q$4:$Q$403,'400链接明细'!$G$4:$G$403,A47,'400链接明细'!$AJ$4:$AJ$403,1) -> 603740.78
A48: time4buy | B48: =COUNTIFS('400链接明细'!$G$4:$G$403,A48,'400链接明细'!$AJ$4:$AJ$403,1) -> 15 | C48: =SUMIFS('400链接明细'!$N$4:$N$403,'400链接明细'!$G$4:$G$403,A48,'400链接明细'!$AJ$4:$AJ$403,1) -> 2601 | D48: =SUMIFS('400链接明细'!$Q$4:$Q$403,'400链接明细'!$G$4:$G$403,A48,'400链接明细'!$AJ$4:$AJ$403,1) -> 693246.13
A49: hutiirich | B49: =COUNTIFS('400链接明细'!$G$4:$G$403,A49,'400链接明细'!$AJ$4:$AJ$403,1) -> 2 | C49: =SUMIFS('400链接明细'!$N$4:$N$403,'400链接明细'!$G$4:$G$403,A49,'400链接明细'!$AJ$4:$AJ$403,1) -> 2205 | D49: =SUMIFS('400链接明细'!$Q$4:$Q$403,'400链接明细'!$G$4:$G$403,A49,'400链接明细'!$AJ$4:$AJ$403,1) -> 295141.01
A50: geopower | B50: =COUNTIFS('400链接明细'!$G$4:$G$403,A50,'400链接明细'!$AJ$4:$AJ$403,1) -> 4 | C50: =SUMIFS('400链接明细'!$N$4:$N$403,'400链接明细'!$G$4:$G$403,A50,'400链接明细'!$AJ$4:$AJ$403,1) -> 1253 | D50: =SUMIFS('400链接明细'!$Q$4:$Q$403,'400链接明细'!$G$4:$G$403,A50,'400链接明细'!$AJ$4:$AJ$403,1) -> 625767.2
A51: gosun | B51: =COUNTIFS('400链接明细'!$G$4:$G$403,A51,'400链接明细'!$AJ$4:$AJ$403,1) -> 4 | C51: =SUMIFS('400链接明细'!$N$4:$N$403,'400链接明细'!$G$4:$G$403,A51,'400链接明细'!$AJ$4:$AJ$403,1) -> 1244 | D51: =SUMIFS('400链接明细'!$Q$4:$Q$403,'400链接明细'!$G$4:$G$403,A51,'400链接明细'!$AJ$4:$AJ$403,1) -> 322759.61
A52: luminicola | B52: =COUNTIFS('400链接明细'!$G$4:$G$403,A52,'400链接明细'!$AJ$4:$AJ$403,1) -> 7 | C52: =SUMIFS('400链接明细'!$N$4:$N$403,'400链接明细'!$G$4:$G$403,A52,'400链接明细'!$AJ$4:$AJ$403,1) -> 1228 | D52: =SUMIFS('400链接明细'!$Q$4:$Q$403,'400链接明细'!$G$4:$G$403,A52,'400链接明细'!$AJ$4:$AJ$403,1) -> 261141.26
A53: ambueco | B53: =COUNTIFS('400链接明细'!$G$4:$G$403,A53,'400链接明细'!$AJ$4:$AJ$403,1) -> 3 | C53: =SUMIFS('400链接明细'!$N$4:$N$403,'400链接明细'!$G$4:$G$403,A53,'400链接明细'!$AJ$4:$AJ$403,1) -> 1189 | D53: =SUMIFS('400链接明细'!$Q$4:$Q$403,'400链接明细'!$G$4:$G$403,A53,'400链接明细'!$AJ$4:$AJ$403,1) -> 273829.08
A54: emotinia | B54: =COUNTIFS('400链接明细'!$G$4:$G$403,A54,'400链接明细'!$AJ$4:$AJ$403,1) -> 3 | C54: =SUMIFS('400链接明细'!$N$4:$N$403,'400链接明细'!$G$4:$G$403,A54,'400链接明细'!$AJ$4:$AJ$403,1) -> 1107 | D54: =SUMIFS('400链接明细'!$Q$4:$Q$403,'400链接明细'!$G$4:$G$403,A54,'400链接明细'!$AJ$4:$AJ$403,1) -> 213510.17
A55: sonheo | B55: =COUNTIFS('400链接明细'!$G$4:$G$403,A55,'400链接明细'!$AJ$4:$AJ$403,1) -> 3 | C55: =SUMIFS('400链接明细'!$N$4:$N$403,'400链接明细'!$G$4:$G$403,A55,'400链接明细'!$AJ$4:$AJ$403,1) -> 1015 | D55: =SUMIFS('400链接明细'!$Q$4:$Q$403,'400链接明细'!$G$4:$G$403,A55,'400链接明细'!$AJ$4:$AJ$403,1) -> 291153.54
A57: 方法：细分与套装件数仅根据标题判定；销售额沿用原表，不能以当前标价×近30天销量替代；库存覆盖=库存快照÷(近30天销量/30)，只作预警；转化率非广告CVR。
A58: 核对：原排序TOP30=20,551件，TOP10=9,642件，TOP30平均685.03件；截图的9.98%为前30条工具转化率简单均值，定义待平台核实。

Sheet 重点竞品
A1: 重点竞品 | 来源于400条链接
A2: 按场景选择代表款，非全站热销排名。库存覆盖天数按静态库存÷近30天日均销量；标价和评论均为抓取时快照。
A3: 原排序 | B3: 商品ID | C3: 细分 | D3: 标价 MXN | E3: 套装件数* | F3: 估算每件标价 MXN* | G3: 30天销量 | H3: 30天销售额 MXN | I3: 库存覆盖天数* | J3: 品牌 | K3: 店铺类型 | L3: 评论数 | M3: 上架日期 | N3: 要观察什么 | O3: 商品链接
A4: 1 | B4: MLM3854627100 | C4: 有线户外/通用壁灯 | D4: 133.91 | E4: 1 | F4: 133.91 | G4: 1340 | H4: 183590.61 | I4: 7.1 | J4: HUTIIRICH | K4: 本土店 | L4: 931 | M4: 45860 | N4: 低价长销；核实20W实际功率、安装与售后 | O4: https://articulo.mercadolibre.com.mx/MLM-3854627100-hutiirich-lamparas-de-pared-exterior-y-interiores-color-negro-cuadrado-arbotante-20w-modernas-decorativas-3000k-luz-blanco-calido-impermeable-lamparas-para-jardin-sala-bano-rectangulo-negro-_JM
A5: 2 | B5: MLM5194406162 | C5: 有线户外/通用壁灯 | D5: 128.96 | E5: 1 | F5: 128.96 | G5: 1241 | H5: 160039.36 | I5: 26.4 | J5: Vanance | K5: 本土店 | L5: 1411 | M5: 46127 | N5: 低价长销；核实调光功能与实际电压 | O5: https://articulo.mercadolibre.com.mx/MLM-5194406162-vanance-lampara-pared-luces-luz-calida-interiores-exterior-muro-12w-lamparas-modernas-regulador-de-luz-lampara-arbotante-lampara-decorativas-color-negro-_JM
A6: 3 | B6: MLM4124322628 | C6: 复古/灯笼壁灯 | D6: 239 | E6: 2 | F6: 119.5 | G6: 1007 | H6: 240673 | I6: 32.1 | J6: Raganet | K6: 本土店 | L6: 35 | M6: 45924 | N6: 双支复古套装，高销量；查是否含灯泡 | O6: https://articulo.mercadolibre.com.mx/MLM-4124322628-kit-2-lamparas-decorativas-de-pared-intext-vintage-retro-negro-_JM
A7: 4 | B7: MLM5598303430 | C7: 充电/感应壁灯 | D7: 217.9 | E7: 6 | F7: 36.32 | G7: 987 | H7: 215067.3 | I7: 5.6 | J7: AGTCOBT | K7: 跨境店 | L7: 101 | M7: 46202 | N7: 六支充电感应灯；极低单件价与短库存 | O7: https://articulo.mercadolibre.com.mx/MLM-5598303430-6pcs-lampara-pared-recargable-sensor-movimiento-led-luces-_JM
A8: 5 | B8: MLM5542913308 | C8: 有线户外/通用壁灯 | D8: 184.19 | E8: 1 | F8: 184.19 | G8: 902 | H8: 166139.38 | I8: 18.2 | J8: EMOTINIA | K8: 本土店 | L8: 353 | M8: 46194 | N8: 多色温有线款；观察竞品同款分流 | O8: https://articulo.mercadolibre.com.mx/MLM-5542913308-lampara-pared-exterior-impermeable-arbotante-moderna-3-modos-negro-_JM
A9: 6 | B9: MLM3854640070 | C9: 有线户外/通用壁灯 | D9: 128.96 | E9: 1 | F9: 128.96 | G9: 865 | H9: 111550.4 | I9: 8.4 | J9: HUTIIRICH | K9: 本土店 | L9: 931 | M9: 45860 | N9: 同牌圆款；验证造型变体带来的销量 | O9: https://articulo.mercadolibre.com.mx/MLM-3854640070-hutiirich-lamparas-de-pared-exterior-y-interiores-color-negro-redondo-arbotante-20w-modernas-decorativas-3000k-luz-blanco-calido-impermeable-lamparas-para-jardin-sala-bano-redondo-negro-_JM
A10: 9 | B10: MLM2979688231 | C10: 有线户外/通用壁灯 | D10: 269.45 | E10: 1 | F10: 269.45 | G10: 817 | H10: 225529.65 | I10: 15.6 | J10: SONHEO | K10: 本土店 | L10: 617 | M10: 46176 | N10: 双灯头/三色温；留意与同质款的差别 | O10: https://articulo.mercadolibre.com.mx/MLM-2979688231-sonheo-lampara-de-pared-exterior-y-interior-moderna-decorativas-para-jardin-sala-con-2-focos-y-3-modos-de-luz-blancacalidaneutra-negro-_JM
A11: 10 | B11: MLM2326733309 | C11: 复古/灯笼壁灯 | D11: 314.1 | E11: 1 | F11: 314.1 | G11: 782 | H11: 253478.7 | I11: 84.7 | J11: Geopower | K11: 本土店 | L11: 992 | M11: 45806 | N11: 单支复古灯；与双支套装比价格 | O11: https://articulo.mercadolibre.com.mx/MLM-2326733309-lampara-de-pared-exterior-farol-decorativo-negro-espanol-100-w-geopower-_JM
A12: 11 | B12: MLM4243156976 | C12: 太阳能户外壁灯 | D12: 292.57 | E12: 1 | F12: 292.57 | G12: 743 | H12: 217379.51 | I12: 1.7 | J12: Vedd | K12: 跨境店 | L12: 780 | M12: 45951 | N12: 太阳能高客单；库存很薄，核实续航 | O12: https://articulo.mercadolibre.com.mx/MLM-4243156976-vedd-lampara-solar-de-paruz-192-led-estructura-negro-_JM
A13: 12 | B13: MLM2280811385 | C13: 有线户外/通用壁灯 | D13: 154.85 | E13: 1 | F13: 154.85 | G13: 705 | H13: 113505.05 | I13: 2.2 | J13: HSLING | K13: 本土店 | L13: 60 | M13: 45759 | N13: 3000K壁灯；7天速度比30天更快 | O13: https://articulo.mercadolibre.com.mx/MLM-2280811385-aplique-led-de-pared-ip65-negro-3000k-lampara-interior-y-exterior-_JM
A14: 13 | B14: MLM2517942983 | C14: 复古/灯笼壁灯 | D14: 273.47 | E14: 1 | F14: 273.47 | G14: 679 | H14: 185686.13 | I14: 6.5 | J14: Gosun | K14: 跨境店 | L14: 741 | M14: 45951 | N14: 灯笼造型；验证不含灯泡说明 | O14: https://articulo.mercadolibre.com.mx/MLM-2517942983-farol-hexagonal-pared-negro-e27-exterior-impermeable-aluminio-_JM
A15: 16 | B15: MLM4780094146 | C15: 太阳能户外壁灯 | D15: 190 | E15: 1 | F15: 190 | G15: 642 | H15: 127680 | I15: 26.7 | J15: Ambueco | K15: 本土店 | L15: 204 | M15: 46065 | N15: 太阳能三色温；本土供给 | O15: https://articulo.mercadolibre.com.mx/MLM-4780094146-lampara-pared-led-solar-exterior-moderna-impermeable-3-modosluz-blanca-calida-neutralmodernas-decorativa-para-jardin-arbotante-exterior-ambueco-negro-_JM
... A27: 96 | B27: MLM3140818875 | C27: 室内装饰壁灯 | D27: 192.75 | E27: 1 | F27: 192.75 | G27: 192 | H27: 37008 | I27: 10.3 | J27: Pcmos | K27: 跨境店 | L27: 15 | M27: 46219 | N27: 室内装饰；低评论高销量样本 | O27: https://articulo.mercadolibre.com.mx/MLM-3140818875-aplique-de-pared-led-moderno-para-interior-_JM

Sheet 400链接明细
A1: 墨西哥美客多壁灯 | 400条链接逐条明细
A2: 来源：用户上传「400_商品列表 (39).xlsx」；采集时间未写在源表；30天销售额、转化率、库存均为第三方工具口径。细分/套装件数按标题推断，请逐条复核。
A3: 原排序 | B3: 商品ID | C3: 商品名称 | D3: 细分（标题判断） | E3: 标价带 MXN | F3: 品牌（原表） | G3: 品牌（归一） | H3: 卖家 | I3: 店铺类型 | J3: 标价 MXN | K3: 套装件数* | L3: 估算每件标价 MXN* | M3: 7天销量 | N3: 30天销量 | O3: 90天销量 | P3: 累计销量 | Q3: 近30天销售额 MXN* | R3: 7天折算/30天 | S3: 库存数（快照） | T3: 库存覆盖天数* | U3: 库存类型 | V3: 评论数 | W3: 评分 | X3: 转化率* | Y3: 上架日期 | Z3: 上架龄 | AA3: BSR | AB3: 销量环比 | AC3: 长度 | AD3: 宽度 | AE3: 高度 | AF3: 重量 | AG3: 商品状态 | AH3: 商品链接 | AI3: 原类目 | AJ3: 核心壁灯标识
A4: 1 | B4: MLM3854627100 | C4: Hutiirich® Lámparas De Pared Exterior Y Interiores Color Negro Cuadrado Arbotante 20w Modernas Decorativas 3000k Luz Blanco Cálido Impermeable Lámparas Para Jardín Sala Baño Rectángulo Negro | D4: 有线户外/通用壁灯 | E4: 100–149 | F4: HUTIIRICH | G4: hutiirich | H4: GREEN08EVEREVEN | I4: 本土店 | J4: 133.91 | K4: 1 | L4: 133.91 | M4: 393 | N4: 1340 | O4: 3558 | P4: 12756 | Q4: 183590.61 | R4: =IFERROR(M4*30/(N4*7),0) -> 1.2569296 | S4: 316 | T4: =IFERROR(S4*30/N4,0) -> 7.0746269 | U4: FULL | V4: 931 | W4: 4.6 | X4: 0.1177 | Y4: 45860 | Z4: 更早 | AA4: 5 | AB4: 0.16928447 | AC4: 21.6 cm | AD4: 10.8 cm | AE4: 9.4 cm | AF4: 1.26 kg | AG4: 在售 | AH4: https://articulo.mercadolibre.com.mx/MLM-3854627100-hutiirich-lamparas-de-pared-exterior-y-interiores-color-negro-cuadrado-arbotante-20w-modernas-decorativas-3000k-luz-blanco-calido-impermeable-lamparas-para-jardin-sala-bano-rectangulo-negro-_JM | AI4: Hogar, Muebles y Jardín(家居、家具和花园) -> Iluminación para el Hogar(家居照明) -> Lámparas(灯具) -> Lámparas de Pared(壁灯) | AJ4: 1
A5: 2 | B5: MLM5194406162 | C5: Vanance® Lámpara Pared Luces Luz Cálida Interiores Exterior Muro 12w Lamparas Modernas Regulador De Luz Lampara Arbotante Lampara Decorativas Color Negro | D5: 有线户外/通用壁灯 | E5: 100–149 | F5: Vanance | G5: vanance | H5: VANANCE | I5: 本土店 | J5: 128.96 | K5: 1 | L5: 128.96 | M5: 321 | N5: 1241 | O5: 3834 | P5: 6295 | Q5: 160039.36 | R5: =IFERROR(M5*30/(N5*7),0) -> 1.108553 | S5: 1092 | T5: =IFERROR(S5*30/N5,0) -> 26.398066 | U5: FULL | V5: 1411 | W5: 4.5 | X5: 0.1363 | Y5: 46127 | Z5: 91–180天 | AA5: 14 | AB5: 0.053480475 | AC5: 21.4 cm | AD5: 10.8 cm | AE5: 9.4 cm | AF5: 0.3 kg | AG5: 在售 | AH5: https://articulo.mercadolibre.com.mx/MLM-5194406162-vanance-lampara-pared-luces-luz-calida-interiores-exterior-muro-12w-lamparas-modernas-regulador-de-luz-lampara-arbotante-lampara-decorativas-color-negro-_JM | AI5: Hogar, Muebles y Jardín(家居、家具和花园) -> Iluminación para el Hogar(家居照明) -> Lámparas(灯具) -> Lámparas de Pared(壁灯) | AJ5: 1
A6: 3 | B6: MLM4124322628 | C6: Kit 2 Lámparas Decorativas De Pared Int/ext. Vintage Retro Negro | D6: 复古/灯笼壁灯 | E6: 200–299 | F6: Raganet | G6: raganet | H6: JANSEK | I6: 本土店 | J6: 239 | K6: 2 | L6: 119.5 | M6: 244 | N6: 1007 | O6: 2226 | P6: 6970 | Q6: 240673 | R6: =IFERROR(M6*30/(N6*7),0) -> 1.0384452 | S6: 1079 | T6: =IFERROR(S6*30/N6,0) -> 32.144985 | U6: FULL | V6: 35 | W6: 5 | X6: 0.0625 | Y6: 45924 | Z6: 更早 | AB6: 0.077005348 | AC6: 48.8 cm | AD6: 24.8 cm | AE6: 11.6 cm | AF6: 1.18 kg | AG6: 在售 | AH6: https://articulo.mercadolibre.com.mx/MLM-4124322628-kit-2-lamparas-decorativas-de-pared-intext-vintage-retro-negro-_JM | AI6: Hogar, Muebles y Jardín(家居、家具和花园) -> Iluminación para el Hogar(家居照明) -> Lámparas(灯具) -> Lámparas de Pared(壁灯) | AJ6: 1
A7: 4 | B7: MLM5598303430 | C7: 6pcs Lampara Pared Recargable Sensor Movimiento Led Luces | D7: 充电/感应壁灯 | E7: 200–299 | F7: AGTCOBT | G7: agtcobt | H7: NIUDEYIBI | I7: 跨境店 | J7: 217.9 | K7: 6 | L7: 36.32 | M7: 142 | N7: 987 | O7: 1656 | P7: 1656 | Q7: 215067.3 | R7: =IFERROR(M7*30/(N7*7),0) -> 0.61658706 | S7: 184 | T7: =IFERROR(S7*30/N7,0) -> 5.5927052 | U7: FULL | V7: 101 | W7: 4.7 | X7: 0.0769 | Y7: 46202 | Z7: 近90天上架 | AA7: 2 | AB7: 0.41 | AC7: 38.3 cm | AD7: 16.2 cm | AE7: 3.1 cm | AF7: 0.9 kg | AG7: 在售 | AH7: https://articulo.mercadolibre.com.mx/MLM-5598303430-6pcs-lampara-pared-recargable-sensor-movimiento-led-luces-_JM | AI7: Hogar, Muebles y Jardín(家居、家具和花园) -> Iluminación para el Hogar(家居照明) -> Lámparas(灯具) -> Lámparas de Pared(壁灯) | AJ7: 1
A8: 5 | B8: MLM5542913308 | C8: Lámpara Pared Exterior Impermeable Arbotante Moderna 3 Modos Negro | D8: 有线户外/通用壁灯 | E8: 150–199 | F8: EMOTINIA | G8: emotinia | H8: FALOVIGNADOSHOP | I8: 本土店 | J8: 184.19 | K8: 1 | L8: 184.19 | M8: 134 | N8: 902 | O8: 1377 | P8: 1377 | Q8: 166139.38 | R8: =IFERROR(M8*30/(N8*7),0) -> 0.63668039 | S8: 547 | T8: =IFERROR(S8*30/N8,0) -> 18.192905 | U8: FULL | V8: 353 | W8: 4.8 | X8: 0.0959 | Y8: 46194 | Z8: 91–180天 | AA8: 15 | AB8: 1.4444444 | AC8: 36.6 cm | AD8: 21.8 cm | AE8: 9.6 cm | AF8: 0.44 kg | AG8: 在售 | AH8: https://articulo.mercadolibre.com.mx/MLM-5542913308-lampara-pared-exterior-impermeable-arbotante-moderna-3-modos-negro-_JM | AI8: Hogar, Muebles y Jardín(家居、家具和花园) -> Iluminación para el Hogar(家居照明) -> Lámparas(灯具) -> Lámparas de Pared(壁灯) | AJ8: 1
A9: 6 | B9: MLM3854640070 | C9: Hutiirich® Lámparas De Pared Exterior Y Interiores Color Negro Redondo Arbotante 20w Modernas Decorativas 3000k Luz Blanco Cálido Impermeable Lámparas Para Jardín Sala Baño Redondo Negro | D9: 有线户外/通用壁灯 | E9: 100–149 | F9: HUTIIRICH | G9: hutiirich | H9: GREEN08EVEREVEN | I9: 本土店 | J9: 128.96 | K9: 1 | L9: 128.96 | M9: 238 | N9: 865 | O9: 2940 | P9: 9975 | Q9: 111550.4 | R9: =IFERROR(M9*30/(N9*7),0) -> 1.1791908 | S9: 243 | T9: =IFERROR(S9*30/N9,0) -> 8.4277457 | U9: FULL | V9: 931 | W9: 4.6 | X9: 0.1059 | Y9: 45860 | Z9: 更早 | AA9: 4 | AB9: -0.22698838 | AC9: 22 cm | AD9: 11.4 cm | AE9: 9.6 cm | AF9: 0.26 kg | AG9: 在售 | AH9: https://articulo.mercadolibre.com.mx/MLM-3854640070-hutiirich-lamparas-de-pared-exterior-y-interiores-color-negro-redondo-arbotante-20w-modernas-decorativas-3000k-luz-blanco-calido-impermeable-lamparas-para-jardin-sala-bano-redondo-negro-_JM | AI9: Hogar, Muebles y Jardín(家居、家具和花园) -> Iluminación para el Hogar(家居照明) -> Lámparas(灯具) -> Lámparas de Pared(壁灯) | AJ9: 1
A10: 7 | B10: MLM2740945503 | C10: Bakeway Reflector Lámpara Led Solar Exterior Luminaria Suburbanas 2500w Led Solar Light Lámparas De Pared | D10: 邻近：路灯/投光灯 | E10: 200–299 | F10: BAKEWAY | G10: bakeway | H10: O C | I10: 本土店 | J10: 298 | K10: 1 | L10: 298 | M10: 223 | N10: 860 | O10: 1388 | P10: 2665 | Q10: 256280 | R10: =IFERROR(M10*30/(N10*7),0) -> 1.1112957 | S10: 110 | T10: =IFERROR(S10*30/N10,0) -> 3.8372093 | U10: FULL | V10: 340 | W10: 4.7 | X10: 0.0766 | Y10: 46065 | Z10: 更早 | AA10: 6 | AB10: 2.1386861 | AC10: 38.4 cm | AD10: 20.2 cm | AE10: 25.8 cm | AF10: 0.72 kg | AG10: 在售 | AH10: https://articulo.mercadolibre.com.mx/MLM-2740945503-lampara-solar-led-exterior-suburbana-alumbrado-publiclamparas-de-pared-focos-solares-led-exteriore-impermeable-_JM | AI10: Hogar, Muebles y Jardín(家居、家具和花园) -> Iluminación para el Hogar(家居照明) -> Lámparas(灯具) -> Lámparas de Pared(壁灯) | AJ10: 0
A11: 8 | B11: MLM4348721588 | C11: 6pzs Luz De Led Clóset Lámpara Armario Noche Recargable Usb Led Closet Light 6 Packs | D11: 邻近：橱柜/衣柜灯 | E11: 150–199 | F11: Zhimatiandi | G11: zhimatiandi | H11: ZHIMATIANDI | I11: 本土店 | J11: 199.99 | K11: 6 | L11: 33.33 | M11: 73 | N11: 841 | O11: 2653 | P11: 4340 | Q11: 168191.59 | R11: =IFERROR(M11*30/(N11*7),0) -> 0.37200612 | S11: 231 | T11: =IFERROR(S11*30/N11,0) -> 8.2401902 | U11: FULL | V11: 0 | W11: 0 | X11: 0.0599 | Y11: 45970 | Z11: 更早 | AB11: -0.18900675 | AC11: 15.8 cm | AD11: 8.8 cm | AE11: 9 cm | AF11: 0.9 kg | AG11: 在售 | AH11: https://articulo.mercadolibre.com.mx/MLM-4348721588-6pzs-luz-de-led-closet-lampara-armario-noche-recargable-usb-led-closet-light-6-packs-_JM | AI11: Hogar, Muebles y Jardín(家居、家具和花园) -> Iluminación para el Hogar(家居照明) -> Lámparas(灯具) -> Lámparas de Pared(壁灯) | AJ11: 0
A12: 9 | B12: MLM2979688231 | C12: Sonheo® Lampara De Pared Exterior Y Interior Moderna Decorativas Para Jardin Sala Con 2 Focos Y 3 Modos De Luz Blanca,cálida,neutra | D12: 有线户外/通用壁灯 | E12: 200–299 | F12: SONHEO | G12: sonheo | H12: FANOKI | I12: 本土店 | J12: 269.45 | K12: 1 | L12: 269.45 | M12: 244 | N12: 817 | O12: 1542 | P12: 1654 | Q12: 225529.65 | R12: =IFERROR(M12*30/(N12*7),0) -> 1.279944 | S12: 426 | T12: =IFERROR(S12*30/N12,0) -> 15.642595 | U12: FULL | V12: 617 | W12: 4.6 | X12: 0.0858 | Y12: 46176 | Z12: 91–180天 | AA12: 20 | AB12: 0.36166667 | AC12: 30 cm | AD12: 16.2 cm | AE12: 9.6 cm | AF12: 1.08 kg | AG12: 在售 | AH12: https://articulo.mercadolibre.com.mx/MLM-2979688231-sonheo-lampara-de-pared-exterior-y-interior-moderna-decorativas-para-jardin-sala-con-2-focos-y-3-modos-de-luz-blancacalidaneutra-negro-_JM | AI12: Hogar, Muebles y Jardín(家居、家具和花园) -> Iluminación para el Hogar(家居照明) -> Lámparas(灯具) -> Lámparas de Pared(壁灯) | AJ12: 1
A13: 10 | B13: MLM2326733309 | C13: Lámpara De Pared Exterior Farol Decorativo Negro Español 100 W Geopower | D13: 复古/灯笼壁灯 | E13: 300–499 | F13: Geopower | G13: geopower | H13: GEOPOWER | I13: 本土店 | J13: 314.1 | K13: 1 | L13: 314.1 | M13: 136 | N13: 782 | O13: 2089 | P13: 13686 | Q13: 253478.7 | R13: =IFERROR(M13*30/(N13*7),0) -> 0.74534161 | S13: 2208 | T13: =IFERROR(S13*30/N13,0) -> 84.705882 | U13: FULL | V13: 992 | W13: 4.8 | X13: 0.0933 | Y13: 45806 | Z13: 更早 | AA13: 19 | AB13: -0.32118056 | AC13: 20.6 cm | AD13: 16.5 cm | AE13: 14.3 cm | AF13: 1.09 kg | AG13: 在售 | AH13: https://articulo.mercadolibre.com.mx/MLM-2326733309-lampara-de-pared-exterior-farol-decorativo-negro-espanol-100-w-geopower-_JM | AI13: Hogar, Muebles y Jardín(家居、家具和花园) -> Iluminación para el Hogar(家居照明) -> Lámparas(灯具) -> Lámparas de Pared(壁灯) | AJ13: 1
A14: 11 | B14: MLM4243156976 | C14: Vedd® Lámpara Solar De Pared Exteriores Sensor Luz 192 Led Estructura Negro | D14: 太阳能户外壁灯 | E14: 200–299 | F14: Vedd | G14: vedd | H14: VEDD | I14: 跨境店 | J14: 292.57 | K14: 1 | L14: 292.57 | M14: 118 | N14: 743 | O14: 2186 | P14: 12767 | Q14: 217379.51 | R14: =IFERROR(M14*30/(N14*7),0) -> 0.68063834 | S14: 41 | T14: =IFERROR(S14*30/N14,0) -> 1.6554509 | U14: FULL | V14: 780 | W14: 4.6 | X14: 0.108 | Y14: 45951 | Z14: 更早 | AA14: 4 | AB14: -0.022368421 | AC14: 21 cm | AD14: 14 cm | AE14: 14.6 cm | AF14: 0.65 kg | AG14: 在售 | AH14: https://articulo.mercadolibre.com.mx/MLM-4243156976-vedd-lampara-solar-de-paruz-192-led-estructura-negro-_JM | AI14: Hogar, Muebles y Jardín(家居、家具和花园) -> Iluminación para el Hogar(家居照明) -> Lámparas(灯具) -> Lámparas de Pared(壁灯) | AJ14: 1
A15: 12 | B15: MLM2280811385 | C15: Lámpara De Pared Led De Foco Flotante Moderno 3000k Estructura Negro | D15: 有线户外/通用壁灯 | E15: 150–199 | F15: HSLING | G15: hsling | H15: QISHUIQISHUI | I15: 本土店 | J15: 154.85 | K15: 1 | L15: 154.85 | M15: 263 | N15: 705 | O15: 1526 | P15: 2762 | Q15: 113505.05 | R15: =IFERROR(M15*30/(N15*7),0) -> 1.5987842 | S15: 52 | T15: =IFERROR(S15*30/N15,0) -> 2.212766 | U15: FULL | V15: 60 | W15: 4.8 | X15: 0.1185 | Y15: 45759 | Z15: 更早 | AB15: 0.5326087 | AC15: 11 cm | AD15: 11.2 cm | AE15: 11.6 cm | AF15: 0.26 kg | AG15: 在售 | AH15: https://articulo.mercadolibre.com.mx/MLM-2280811385-aplique-led-de-pared-ip65-negro-3000k-lampara-interior-y-exterior-_JM | AI15: Hogar, Muebles y Jardín(家居、家具和花园) -> Iluminación para el Hogar(家居照明) -> Lámparas(灯具) -> Lámparas de Pared(壁灯) | AJ15: 1
A16: 13 | B16: MLM2517942983 | C16: Gosun® Hexágono Faroles Lámparas De Pared Casa Decoración No Focos Wei World Zt-302 Color De Negro | D16: 复古/灯笼壁灯 | E16: 200–299 | F16: Gosun | G16: gosun | H16: CNWEIWORLD-MXF | I16: 跨境店 | J16: 273.47 | K16: 1 | L16: 273.47 | M16: 184 | N16: 679 | O16: 2480 | P16: 18851 | Q16: 185686.13 | R16: =IFERROR(M16*30/(N16*7),0) -> 1.1613718 | S16: 147 | T16: =IFERROR(S16*30/N16,0) -> 6.4948454 | U16: FULL | V16: 741 | W16: 4.8 | X16: 0.3063 | Y16: 45951 | Z16: 更早 | AA16: 10 | AB16: -0.34332689 | AC16: 15.2 cm | AD16: 16.8 cm | AE16: 20.8 cm | AF16: 0.72 kg | AG16: 在售 | AH16: https://articulo.mercadolibre.com.mx/MLM-2517942983-farol-hexagonal-pared-negro-e27-exterior-impermeable-aluminio-_JM | AI16: Hogar, Muebles y Jardín(家居、家具和花园) -> Iluminación para el Hogar(家居照明) -> Lámparas(灯具) -> Lámparas de Pared(壁灯) | AJ16: 1
A17: 14 | B17: MLM3699273080 | C17: Lámpara Pared Exterior Impermeable Arbotante Moderna 3 Modos | D17: 有线户外/通用壁灯 | E17: 150–199 | F17: arbotante exterior,arbotante de pared,lampara arbotante exterior | G17: arbotante exterior,arbotante de pared,lampara arbotante exterior | H17: FALOVIGNADOSHOP | I17: 本土店 | J17: 184.19 | K17: 1 | L17: 184.19 | M17: 266 | N17: 674 | O17: 1661 | P17: 6370 | Q17: 124144.06 | R17: =IFERROR(M17*30/(N17*7),0) -> 1.6913947 | S17: 191 | T17: =IFERROR(S17*30/N17,0) -> 8.5014837 | U17: FULL | V17: 319 | W17: 4.8 | X17: 0.1102 | Y17: 45796 | Z17: 更早 | AB17: 0.085346216 | AC17: 21.4 cm | AD17: 11.2 cm | AE17: 8.6 cm | AF17: 0.26 kg | AG17: 在售 | AH17: https://articulo.mercadolibre.com.mx/MLM-3699273080-lampara-pared-exterior-impermeable-arbotante-moderna-3-modos-negro-_JM | AI17: Hogar, Muebles y Jardín(家居、家具和花园) -> Iluminación para el Hogar(家居照明) -> Lámparas(灯具) -> Lámparas de Pared(壁灯) | AJ17: 1
A18: 15 | B18: MLM3323814200 | C18: Sensor De Movimiento Led Inalámbrico My Bajo Luces Color Silver 40cm | D18: 充电/感应壁灯 | E18: <100 | F18: Genérica | G18: generica | H18: CNTORISE-MXF | I18: 跨境店 | J18: 84.33 | K18: 1 | L18: 84.33 | M18: 174 | N18: 644 | O18: 1703 | P18: 16817 | Q18: 55910.79 | R18: =IFERROR(M18*30/(N18*7),0) -> 1.1579414 | S18: 789 | T18: =IFERROR(S18*30/N18,0) -> 36.754658 | U18: FULL | V18: 1573 | W18: 4.5 | X18: 0.0736 | Y18: 45525 | Z18: 更早 | AA18: 16 | AB18: 0.24084778 | AC18: 41.2 cm | AD18: 4.6 cm | AE18: 2.2 cm | AF18: 0.16 kg | AG18: 在售 | AH18: https://articulo.mercadolibre.com.mx/MLM-3323814200-sensor-de-movimiento-led-inalambrico-my-bajo-luces-color-silver-40cm-_JM | AI18: Hogar, Muebles y Jardín(家居、家具和花园) -> Iluminación para el Hogar(家居照明) -> Lámparas(灯具) -> Lámparas de Pared(壁灯) | AJ18: 1
A19: 16 | B19: MLM4780094146 | C19: Lampara Pared Led Solar Exterior Moderna Impermeable 3 Modos,luz Blanca / Cálida / Neutral,modernas Decorativa Para Jardín Arbotante Exterior Ambueco® Negro | D19: 太阳能户外壁灯 | E19: 150–199 | F19: Ambueco | G19: ambueco | H19: ZENITHIA | I19: 本土店 | J19: 190 | K19: 1 | L19: 190 | M19: 143 | N19: 642 | O19: 2112 | P19: 3955 | Q19: 127680 | R19: =IFERROR(M19*30/(N19*7),0) -> 0.95460614 | S19: 572 | T19: =IFERROR(S19*30/N19,0) -> 26.728972 | U19: FULL | V19: 204 | W19: 4.5 | X19: 0.0522 | Y19: 46065 | Z19: 更早 | AA19: 8 | AB19: -0.064139942 | AC19: 18.8 cm | AD19: 8.4 cm | AE19: 6.6 cm | AF19: 0.35 kg | AG19: 在售 | AH19: https://articulo.mercadolibre.com.mx/MLM-4780094146-lampara-pared-led-solar-exterior-moderna-impermeable-3-modosluz-blanca-calida-neutralmodernas-decorativa-para-jardin-arbotante-exterior-ambueco-negro-_JM | AI19: Hogar, Muebles y Jardín(家居、家具和花园) -> Iluminación para el Hogar(家居照明) -> Lámparas(灯具) -> Lámparas de Pared(壁灯) | AJ19: 1
A20: 17 | B20: MLM2980774929 | C20: Lamparas Solares Exterior Lamparas Solares Lampara Led 2pcs | D20: 太阳能户外壁灯 | E20: 200–299 | F20: YETONE | G20: yetone | H20: CNYUEHT-MXF | I20: 跨境店 | J20: 237.5 | K20: 2 | L20: 118.75 | M20: 114 | N20: 589 | O20: 589 | P20: 589 | Q20: 139887.5 | R20: =IFERROR(M20*30/(N20*7),0) -> 0.82949309 | S20: 125 | T20: =IFERROR(S20*30/N20,0) -> 6.3667233 | U20: FULL | V20: 5 | W20: 4.6 | X20: 0.0549 | Y20: 46177 | Z20: 91–180天 | AB20: 64.444444 | AC20: 14 cm | AD20: 11.8 cm | AE20: 10 cm | AF20: 0.36 kg | AG20: 在售 | AH20: https://articulo.mercadolibre.com.mx/MLM-2980774929-lamparas-solares-exterior-lamparas-solares-lampara-led-2pcs-_JM | AI20: Hogar, Muebles y Jardín(家居、家具和花园) -> Iluminación para el Hogar(家居照明) -> Lámparas(灯具) -> Lámparas de Pared(壁灯) | AJ20: 1
A21: 18 | B21: MLM4478861044 | C21: Lámpara Solar Exterior De Pared De 120 Cob Con Sensor | D21: 太阳能户外壁灯 | E21: 100–149 | F21: Cyotman | G21: cyotman | H21: O C | I21: 本土店 | J21: 115 | K21: 1 | L21: 115 | M21: 264 | N21: 588 | O21: 1495 | P21: 3751 | Q21: 69460 | R21: =IFERROR(M21*30/(N21*7),0) -> 1.9241983 | S21: 238 | T21: =IFERROR(S21*30/N21,0) -> 12.142857 | U21: FULL | V21: 1668 | W21: 4.3 | X21: 0.0656 | Y21: 45998 | Z21: 更早 | AA21: 10 | AB21: 0.32432432 | AC21: 23.1 cm | AD21: 9.2 cm | AE21: 4.4 cm | AF21: 0.21 kg | AG21: 在售 | AH21: https://articulo.mercadolibre.com.mx/MLM-4478861044-lampara-solar-exterior-de-pared-de-120-cob-con-sensor-_JM | AI21: Hogar, Muebles y Jardín(家居、家具和花园) -> Iluminación para el Hogar(家居照明) -> Lámparas(灯具) -> Lámparas de Pared(壁灯) | AJ21: 1
A22: 19 | B22: MLM4289959428 | C22: 6800w Lámpara Led Solar Exterior Suburbana Alumbrado Públic | D22: 邻近：路灯/投光灯 | E22: ≥500 | F22: General | G22: general | H22: OUTLETMEX | I22: 本土店 | J22: 597.13 | K22: 1 | L22: 597.13 | M22: 139 | N22: 586 | O22: 2623 | P22: 6696 | Q22: 356486.61 | R22: =IFERROR(M22*30/(N22*7),0) -> 1.0165773 | S22: 413 | T22: =IFERROR(S22*30/N22,0) -> 21.143345 | U22: FULL | V22: 0 | W22: 0 | X22: 0.0877 | Y22: 45959 | Z22: 更早 | AB22: -0.45690454 | AC22: 46.8 cm | AD22: 27.8 cm | AE22: 5.6 cm | AF22: 1.62 kg | AG22: 在售 | AH22: https://articulo.mercadolibre.com.mx/MLM-4289959428-7800w-lampara-led-solar-exterior-suburbana-alumbrado-public-_JM | AI22: Hogar, Muebles y Jardín(家居、家具和花园) -> Iluminación para el Hogar(家居照明) -> Lámparas(灯具) -> Lámparas de Pared(壁灯) | AJ22: 0
A23: 20 | B23: MLM4121803576 | C23: 6 Pzs Luz Led Clóset Lámpara Armario Noche Recargable Usb | D23: 邻近：橱柜/衣柜灯 | E23: 150–199 | F23: Genérica | G23: generica | H23: RSHX | I23: 本土店 | J23: 177.73 | K23: 6 | L23: 29.62 | M23: 285 | N23: 525 | O23: 2252 | P23: 4841 | Q23: 93308.25 | R23: =IFERROR(M23*30/(N23*7),0) -> 2.3265306 | S23: 325 | T23: =IFERROR(S23*30/N23,0) -> 18.571429 | U23: FULL | V23: 58 | W23: 4.6 | X23: 0.0751 | Y23: 45924 | Z23: 更早 | AA23: 17 | AB23: -0.45932029 | AC23: 16 cm | AD23: 8.8 cm | AE23: 8.6 cm | AF23: 0.27 kg | AG23: 在售 | AH23: https://articulo.mercadolibre.com.mx/MLM-4121803576-6-pzs-luz-led-closet-lampara-armario-noche-recargable-usb-blanco-_JM | AI23: Hogar, Muebles y Jardín(家居、家具和花园) -> Iluminación para el Hogar(家居照明) -> Lámparas(灯具) -> Lámparas de Pared(壁灯) | AJ23: 0
A24: 21 | B24: MLM2551024807 | C24: 2pcs 50cm Luz De Led Clóset Usb Con Sensor Movimiento | D24: 邻近：橱柜/衣柜灯 | E24: 100–149 | F24: Tongze | G24: tongze | H24: TONGZE | I24: 跨境店 | J24: 148.01 | K24: 2 | L24: 74 | M24: 130 | N24: 522 | O24: 1180 | P24: 1948 | Q24: 80073.41 | R24: =IFERROR(M24*30/(N24*7),0) -> 1.0673235 | S24: 77 | T24: =IFERROR(S24*30/N24,0) -> 4.4252874 | U24: FULL | V24: 137 | W24: 4.8 | X24: 0.0915 | Y24: 45969 | Z24: 更早 | AA24: 12 | AB24: 0.37368421 | AC24: 51 cm | AD24: 4.8 cm | AE24: 4.6 cm | AF24: 0.38 kg | AG24: 在售 | AH24: https://articulo.mercadolibre.com.mx/MLM-2551024807-2pcs-50cm-luz-de-led-closet-usb-con-sensor-movimiento-_JM | AI24: Hogar, Muebles y Jardín(家居、家具和花园) -> Iluminación para el Hogar(家居照明) -> Lámparas(灯具) -> Lámparas de Pared(壁灯) | AJ24: 0
A25: 22 | B25: MLM4308432370 | C25: 30cmcon Sensor Movimiento Luz De Led Clóset Usb 5 Piezas | D25: 邻近：橱柜/衣柜灯 | E25: 100–149 | F25: Try Me | G25: try me | H25: OSASKUFHBED | I25: 本土店 | J25: 149 | K25: 5 | L25: 29.8 | M25: 121 | N25: 509 | O25: 851 | P25: 1425 | Q25: 77480 | R25: =IFERROR(M25*30/(N25*7),0) -> 1.0188044 | S25: 171 | T25: =IFERROR(S25*30/N25,0) -> 10.078585 | U25: FULL | V25: 138 | W25: 4.7 | X25: 0.1159 | Y25: 45961 | Z25: 更早 | AB25: 0.76736111 | AC25: 37.8 cm | AD25: 12.6 cm | AE25: 3 cm | AF25: 0.34 kg | AG25: 在售 | AH25: https://articulo.mercadolibre.com.mx/MLM-4308432370-30cmcon-sensor-movimiento-luz-de-led-closet-usb-5-piezas-_JM | AI25: Hogar, Muebles y Jardín(家居、家具和花园) -> Iluminación para el Hogar(家居照明) -> Lámparas(灯具) -> Lámparas de Pared(壁灯) | AJ25: 0
A26: 23 | B26: MLM3632053106 | C26: Gosun® Lámpara De Pared Led 12w Impermeable Foco Flotante Estructura Negro - Blanco Cálido | D26: 有线户外/通用壁灯 | E26: 150–199 | F26: Genérica | G26: generica | H26: CNWEIWORLD-MXF | I26: 跨境店 | J26: 176.23 | K26: 1 | L26: 176.23 | M26: 132 | N26: 484 | O26: 1293 | P26: 6960 | Q26: 88291.23 | R26: =IFERROR(M26*30/(N26*7),0) -> 1.1688312 | S26: 612 | T26: =IFERROR(S26*30/N26,0) -> 37.933884 | U26: FULL | V26: 301 | W26: 4.9 | X26: 0.1695 | Y26: 45757 | Z26: 更早 | AA26: 20 | AB26: 0.10502283 | AC26: 11.4 cm | AD26: 11 cm | AE26: 11.2 cm | AF26: 0.27 kg | AG26: 在售 | AH26: https://articulo.mercadolibre.com.mx/MLM-3632053106-gosun-lampara-de-pared-led-12w-impermeable-foco-flotante-estructura-negro-blanco-calido-_JM | AI26: Hogar, Muebles y Jardín(家居、家具和花园) -> Iluminación para el Hogar(家居照明) -> Lámparas(灯具) -> Lámparas de Pared(壁灯) | AJ26: 1
A27: 24 | B27: MLM2766217743 | C27: 2 Barras Led 50cm Lampara Inteligente Con Sensor Corporal | D27: 邻近：橱柜/衣柜灯 | E27: 150–199 | F27: Rindion | G27: rindion | H27: RINDION | I27: 跨境店 | J27: 158.81 | K27: 2 | L27: 79.41 | M27: 99 | N27: 473 | O27: 477 | P27: 557 | Q27: 75117.13 | R27: =IFERROR(M27*30/(N27*7),0) -> 0.89700997 | S27: 98 | T27: =IFERROR(S27*30/N27,0) -> 6.2156448 | U27: FULL | V27: 22 | W27: 4.9 | X27: 0.0649 | Y27: 46087 | Z27: 更早 | AA27: 12 | AB27: 117.25 | AC27: 52.2 cm | AD27: 5.2 cm | AE27: 5.6 cm | AF27: 0.44 kg | AG27: 在售 | AH27: https://articulo.mercadolibre.com.mx/MLM-2766217743-2-barras-led-50cm-lampara-inteligente-con-sensor-corporal-_JM | AI27: Hogar, Muebles y Jardín(家居、家具和花园) -> Iluminación para el Hogar(家居照明) -> Lámparas(灯具) -> Lámparas de Pared(壁灯) | AJ27: 0
A28: 25 | B28: MLM2910627089 | C28: Time4buy 3pzs Lámpara De Pared Led 12w Exteriores Interior Impermeable Exterior Para Jardín, Patio, Terraza, Inicio (luz Cálida ) | D28: 有线户外/通用壁灯 | E28: 200–299 | F28: Time4buy | G28: time4buy | H28: TIME4BUY | I28: 跨境店 | J28: 296.87 | K28: 3 | L28: 98.96 | M28: 132 | N28: 440 | O28: 1486 | P28: 2172 | Q28: 134185.24 | R28: =IFERROR(M28*30/(N28*7),0) -> 1.2857143 | S28: 214 | T28: =IFERROR(S28*30/N28,0) -> 14.590909 | U28: FULL | V28: 164 | W28: 4.8 | X28: 0.0956 | Y28: 46148 | Z28: 91–180天 | AA28: 16 | AB28: 0.11392405 | AC28: 35 cm | AD28: 11.6 cm | AE28: 11.6 cm | AF28: 0.79 kg | AG28: 在售 | AH28: https://articulo.mercadolibre.com.mx/MLM-2910627089-time4buy-3pzs-lampara-de-pared-led-6w-exteriores-interior-angulo-de-luz-ajustable-10x10x10cm-haz-superior-e-inferior-impermeable-exterior-para-jardin-patio-terraza-inicio-luz-calida--_JM | AI28: Hogar, Muebles y Jardín(家居、家具和花园) -> Iluminación para el Hogar(家居照明) -> Lámparas(灯具) -> Lámparas de Pared(壁灯) | AJ28: 1
A29: 26 | B29: MLM2609956161 | C29: Lámpara Solar Pared Exterior Con Sensor De Movimiento Jardin | D29: 太阳能户外壁灯 | E29: 300–499 | F29: NENSED | G29: nensed | H29: NENSED STORE | I29: 跨境店 | J29: 343.51 | K29: 1 | L29: 343.51 | M29: 97 | N29: 432 | O29: 1495 | P29: 2855 | Q29: 154923.01 | R29: =IFERROR(M29*30/(N29*7),0) -> 0.96230159 | S29: 750 | T29: =IFERROR(S29*30/N29,0) -> 52.083333 | U29: FULL | V29: 157 | W29: 4.8 | X29: 0.0348 | Y29: 45999 | Z29: 更早 | AA29: 16 | AB29: 0.6744186 | AC29: 20.4 cm | AD29: 19 cm | AE29: 13.6 cm | AF29: 0.61 kg | AG29: 在售 | AH29: https://articulo.mercadolibre.com.mx/MLM-2609956161-lampara-solar-pared-exterior-con-sensor-de-movimiento-jardin-_JM | AI29: Hogar, Muebles y Jardín(家居、家具和花园) -> Iluminación para el Hogar(家居照明) -> Lámparas(灯具) -> Lámparas de Pared(壁灯) | AJ29: 1
A30: 27 | B30: MLM2115041365 | C30: 2 Barra De Luz Led Inteligente Con Sensor De Cuerpo Humano | D30: 邻近：橱柜/衣柜灯 | E30: 100–149 | F30: TIANZHI | G30: tianzhi | H30: TIANZHI | I30: 跨境店 | J30: 145.52 | K30: 2 | L30: 72.76 | M30: 52 | N30: 425 | O30: 1298 | P30: 5984 | Q30: 61846 | R30: =IFERROR(M30*30/(N30*7),0) -> 0.52436975 | S30: 145 | T30: =IFERROR(S30*30/N30,0) -> 10.235294 | U30: FULL | V30: 594 | W30: 4.6 | X30: 0.1248 | Y30: 45511 | Z30: 更早 | AA30: 18 | AB30: 0.021634615 | AC30: 40.2 cm | AD30: 4.6 cm | AE30: 4 cm | AF30: 0.25 kg | AG30: 在售 | AH30: https://articulo.mercadolibre.com.mx/MLM-2115041365-2-barra-de-luz-led-inteligente-con-sensor-de-cuerpo-humano-_JM | AI30: Hogar, Muebles y Jardín(家居、家具和花园) -> Iluminación para el Hogar(家居照明) -> Lámparas(灯具) -> Lámparas de Pared(壁灯) | AJ30: 0
A31: 28 | B31: MLM2284562447 | C31: Judeng® Lámpara Led De Pared Impermeable Para Interior Y Exterior Lampara De Pared Exterior Y Interior Moderna Decorativas Para Jardin Sala Con 2 Focos Y 3 Modos De Luz Blanca,cálida,neutra Negro | D31: 有线户外/通用壁灯 | E31: 200–299 | F31: Judeng | G31: judeng | H31: CNJUDENG-MXF | I31: 跨境店 | J31: 259.87 | K31: 1 | L31: 259.87 | M31: 59 | N31: 425 | O31: 941 | P31: 6508 | Q31: 110444.75 | R31: =IFERROR(M31*30/(N31*7),0) -> 0.59495798 | S31: 977 | T31: =IFERROR(S31*30/N31,0) -> 68.964706 | U31: FULL | V31: 305 | W31: 4.7 | X31: 0.0893 | Y31: 45764 | Z31: 更早 | AA31: 20 | AB31: 1.0238095 | AC31: 16.8 cm | AD31: 30 cm | AE31: 9.6 cm | AF31: 0.68 kg | AG31: 在售 | AH31: https://articulo.mercadolibre.com.mx/MLM-2284562447-lampara-de-pared-judeng-led-cuadrada-negra-para-exterior-e-interior-negro-_JM | AI31: Hogar, Muebles y Jardín(家居、家具和花园) -> Iluminación para el Hogar(家居照明) -> Lámparas(灯具) -> Lámparas de Pared(壁灯) | AJ31: 1
A32: 29 | B32: MLM3897340848 | C32: Dehobo Lámparas Pared Exterior Focos Impermeable Ip65 8w, Led Moderna Y Decorativas Arbotante Iluminacion Hogar Lamparas Exteriores,iluminacion Led Pared Uso Exterior/interior Color Negro,luz Cálida | D32: 有线户外/通用壁灯 | E32: 100–149 | F32: DEHOBO | G32: dehobo | H32: CNHAIZHILIMYMXF | I32: 跨境店 | J32: 140.26 | K32: 1 | L32: 140.26 | M32: 45 | N32: 416 | O32: 816 | P32: 2306 | Q32: 60031.28 | R32: =IFERROR(M32*30/(N32*7),0) -> 0.4635989 | S32: 205 | T32: =IFERROR(S32*30/N32,0) -> 14.783654 | U32: FULL | V32: 79 | W32: 4.7 | X32: 0.1551 | Y32: 45875 | Z32: 更早 | AB32: 0.67068273 | AC32: 22.6 cm | AD32: 8.8 cm | AE32: 5.6 cm | AF32: 0.3 kg | AG32: 在售 | AH32: https://articulo.mercadolibre.com.mx/MLM-3897340848-dehobo-lamparas-pared-exterior-focos-impermeable-ip65-8w-led-moderna-y-decorativas-arbotante-iluminacion-hogar-lamparas-exterioresiluminacion-led-pared-uso-exteriorinterior-color-negroluz-calida-_JM | AI32: Hogar, Muebles y Jardín(家居、家具和花园) -> Iluminación para el Hogar(家居照明) -> Lámparas(灯具) -> Lámparas de Pared(壁灯) | AJ32: 1
A33: 30 | B33: MLM2852310939 | C33: Vanance® Lamparas De Pared Led Exterior Interiores Arbotante Decorativa Modernas Impermeable Luz Cálida Lámpara Led Pared De 24w Lámparas Para Jardín Sala Baño Negro | D33: 有线户外/通用壁灯 | E33: 150–199 | F33: Vanance | G33: vanance | H33: VANANCE | I33: 本土店 | J33: 159 | K33: 1 | L33: 159 | M33: 141 | N33: 408 | O33: 1265 | P33: 2056 | Q33: 64872 | R33: =IFERROR(M33*30/(N33*7),0) -> 1.4810924 | S33: 345 | T33: =IFERROR(S33*30/N33,0) -> 25.367647 | U33: FULL | V33: 97 | W33: 4.5 | X33: 0.09 | Y33: 46121 | Z33: 91–180天 | AB33: 0.068062827 | AC33: 25.8 cm | AD33: 12 cm | AE33: 9.4 cm | AF33: 0.37 kg | AG33: 在售 | AH33: https://articulo.mercadolibre.com.mx/MLM-2852310939-vanance-lamparas-de-pared-led-exterior-interiores-arbotante-decorativa-modernas-impermeable-luz-calida-lampara-led-pared-de-24w-lamparas-para-jardin-sala-bano-negro-_JM | AI33: Hogar, Muebles y Jardín(家居、家具和花园) -> Iluminación para el Hogar(家居照明) -> Lámparas(灯具) -> Lámparas de Pared(壁灯) | AJ33: 1
A34: 31 | B34: MLM2863105865 | C34: 6 Piezas Lampara Con Sensor Movimiento Luz De Led Clóset Usb | D34: 邻近：橱柜/衣柜灯 | E34: 150–199 | F34: Genérica | G34: generica | H34: RIFENGSHAN | I34: 本土店 | J34: 190.78 | K34: 6 | L34: 31.8 | M34: 86 | N34: 405 | O34: 877 | P34: 929 | Q34: 77265.9 | R34: =IFERROR(M34*30/(N34*7),0) -> 0.91005291 | S34: 229 | T34: =IFERROR(S34*30/N34,0) -> 16.962963 | U34: FULL | V34: 60 | W34: 4.5 | X34: 0.0769 | Y34: 46126 | Z34: 91–180天 | AB34: 2.4913793 | AC34: 26 cm | AD34: 9.5 cm | AE34: 5.7 cm | AF34: 0.4 kg | AG34: 在售 | AH34: https://articulo.mercadolibre.com.mx/MLM-2863105865-6-piezas-lampara-con-sensor-movimiento-luz-de-led-closet-usb-_JM | AI34: Hogar, Muebles y Jardín(家居、家具和花园) -> Iluminación para el Hogar(家居照明) -> Lámparas(灯具) -> Lámparas de Pared(壁灯) | AJ34: 0
A35: 32 | B35: MLM4308534336 | C35: 50cm Con Sensor Movimiento Luz De Led Clóset Usb 5 Piezas | D35: 邻近：橱柜/衣柜灯 | E35: 150–199 | F35: Try Me | G35: try me | H35: OSASKUFHBED | I35: 本土店 | J35: 169 | K35: 5 | L35: 33.8 | M35: 123 | N35: 401 | O35: 539 | P35: 800 | Q35: 70304 | R35: =IFERROR(M35*30/(N35*7),0) -> 1.3145707 | S35: 395 | T35: =IFERROR(S35*30/N35,0) -> 29.551122 | U35: FULL | V35: 62 | W35: 4.8 | X35: 0.0989 | Y35: 45961 | Z35: 更早 | AA35: 8 | AB35: 99.25 | AC35: 56 cm | AD35: 12.2 cm | AE35: 2.8 cm | AF35: 0.48 kg | AG35: 在售 | AH35: https://articulo.mercadolibre.com.mx/MLM-4308534336-50cm-con-sensor-movimiento-luz-de-led-closet-usb-5-piezas-_JM | AI35: Hogar, Muebles y Jardín(家居、家具和花园) -> Iluminación para el Hogar(家居照明) -> Lámparas(灯具) -> Lámparas de Pared(壁灯) | AJ35: 0
A36: 33 | B36: MLM2630649971 | C36: Judeng® Lámpara De Pared Negra Impermeable Para Lámpara De Pared Led Para Exteriores Lampara De Pared Exterior Y Interior Moderna Decorativas Para Jardin Sala 3 Modos De Luz Blanca,cálida,neutra Negro | D36: 有线户外/通用壁灯 | E36: 200–299 | F36: Judeng | G36: judeng | H36: JUDENG ONLINE | I36: 跨境店 | J36: 254.02 | K36: 1 | L36: 254.02 | M36: 57 | N36: 396 | O36: 1177 | P36: 3089 | Q36: 103386.14 | R36: =IFERROR(M36*30/(N36*7),0) -> 0.61688312 | S36: 1 | T36: =IFERROR(S36*30/N36,0) -> 0.075757576 | U36: FULL | V36: 98 | W36: 4.7 | X36: 0.0906 | Y36: 46009 | Z36: 更早 | AB36: 0.29836066 | AC36: 31.4 cm | AD36: 13.8 cm | AE36: 11.8 cm | AF36: 0.7 kg | AG36: 在售 | AH36: https://articulo.mercadolibre.com.mx/MLM-2630649971-lampara-de-pared-judeng-led-de-2-focos-para-exterior-e-interior-_JM | AI36: Hogar, Muebles y Jardín(家居、家具和花园) -> Iluminación para el Hogar(家居照明) -> Lámparas(灯具) -> Lámparas de Pared(壁灯) | AJ36: 1
A37: 34 | B37: MLM2658745862 | C37: Lámpara Plástica Esférica Tipo Pantalla Decorativa De 15cm De Diámetro Cubre Socket Y Cubre Foco En Techo Y Pared O' Farrill Lucefacil-lf02t Color Blanco Opalino | D37: 有线户外/通用壁灯 | E37: 150–199 | F37: O Farrill Refract | G37: o farrill refract | H37: LOFFA | I37: 本土店 | J37: 179.99 | K37: 1 | L37: 179.99 | M37: 79 | N37: 395 | O37: 1392 | P37: 26980 | Q37: 73075.94 | R37: =IFERROR(M37*30/(N37*7),0) -> 0.85714286 | S37: 1489 | T37: =IFERROR(S37*30/N37,0) -> 113.08861 | U37: FULL | V37: 4591 | W37: 4.5 | X37: 0.0956 | Y37: 45236 | Z37: 更早 | AA37: 1 | AB37: -0.27655678 | AC37: 16.6 cm | AD37: 15.2 cm | AE37: 20.2 cm | AF37: 0.16 kg | AG37: 在售 | AH37: https://articulo.mercadolibre.com.mx/MLM-2658745862-lampara-esferica-blanca-o-farrill-techo-y-pared-para-led-e26e27-interior-exterior-blanco-_JM | AI37: Hogar, Muebles y Jardín(家居、家具和花园) -> Iluminación para el Hogar(家居照明) -> Lámparas(灯具) -> Lámparas de Pared(壁灯) | AJ37: 1
A38: 35 | B38: MLM2231781627 | C38: 3pack 40cm Luz De Led Clóset Usb Con Sensor Movimiento | D38: 邻近：橱柜/衣柜灯 | E38: 150–199 | F38: OCEBEEC | G38: ocebeec | H38: JUOYTGXZ | I38: 本土店 | J38: 173 | K38: 3 | L38: 57.67 | M38: 35 | N38: 385 | O38: 1057 | P38: 3607 | Q38: 68681 | R38: =IFERROR(M38*30/(N38*7),0) -> 0.38961039 | S38: 123 | T38: =IFERROR(S38*30/N38,0) -> 9.5844156 | U38: FULL | V38: 122 | W38: 4.7 | X38: 0.0645 | Y38: 45694 | Z38: 更早 | AB38: 0.27906977 | AC38: 43 cm | AD38: 9.9 cm | AE38: 5.4 cm | AF38: 0.35 kg | AG38: 在售 | AH38: https://articulo.mercadolibre.com.mx/MLM-2231781627-3pack-40cm-luz-de-led-closet-usb-con-sensor-movimiento-blanco-_JM | AI38: Hogar, Muebles y Jardín(家居、家具和花园) -> Iluminación para el Hogar(家居照明) -> Lámparas(灯具) -> Lámparas de Pared(壁灯) | AJ38: 0
A39: 36 | B39: MLM2310510009 | C39: Yuju Lámpara De Pared Led Impermeable Sobreponer Para Exterior Lamparas De Pared Exterior Lampara Arbotante Lampara Arbotante Potencia 60 W Negro | D39: 有线户外/通用壁灯 | E39: 200–299 | F39: Yuju | G39: yuju | H39: YU JU STORE | I39: 跨境店 | J39: 263.31 | K39: 1 | L39: 263.31 | M39: 93 | N39: 383 | O39: 1064 | P39: 4825 | Q39: 105060.69 | R39: =IFERROR(M39*30/(N39*7),0) -> 1.0406565 | S39: 579 | T39: =IFERROR(S39*30/N39,0) -> 45.35248 | U39: FULL | V39: 462 | W39: 4.7 | X39: 0.1074 | Y39: 45791 | Z39: 更早 | AB39: 0.018617021 | AC39: 30.6 cm | AD39: 16.4 cm | AE39: 9.6 cm | AF39: 0.8 kg | AG39: 在售 | AH39: https://articulo.mercadolibre.com.mx/MLM-2310510009-lampara-de-pared-para-exterior-led-ip65-y-con-diseno-de-iluminacion-arriba-y-abajo-e27-negro-_JM | AI39: Hogar, Muebles y Jardín(家居、家具和花园) -> Iluminación para el Hogar(家居照明) -> Lámparas(灯具) -> Lámparas de Pared(壁灯) | AJ39: 1
A40: 37 | B40: MLM2220599481 | C40: 2 Piezas Lámparas De Pared Lampara Solar Jardin Impermeables | D40: 太阳能户外壁灯 | E40: 150–199 | F40: Wasume | G40: wasume | H40: WASUME | I40: 跨境店 | J40: 194.47 | K40: 2 | L40: 97.23 | M40: 61 | N40: 376 | O40: 596 | P40: 1474 | Q40: 73120.72 | R40: =IFERROR(M40*30/(N40*7),0) -> 0.69528875 | S40: 21 | T40: =IFERROR(S40*30/N40,0) -> 1.6755319 | U40: FULL | V40: 149 | W40: 4.5 | X40: 0.0946 | Y40: 45670 | Z40: 更早 | AB40: 0.82524272 | AC40: 25.6 cm | AD40: 17.7 cm | AE40: 6.8 cm | AF40: 0.61 kg | AG40: 在售 | AH40: https://articulo.mercadolibre.com.mx/MLM-2220599481-2-piezas-lamparas-de-pared-lampara-solar-jardin-impermeables-_JM | AI40: Hogar, Muebles y Jardín(家居、家具和花园) -> Iluminación para el Hogar(家居照明) -> Lámparas(灯具) -> Lámparas de Pared(壁灯) | AJ40: 1
A41: 38 | B41: MLM2866035563 | C41: Time4buy® 4pzs Lámpara 2led Pared Luces Iluminacion Exterior Interiore,pared Moderna, Ip65 Impermeable, Para Porche, Escaleras, Pasillo (negro Luz Cálida) | D41: 有线户外/通用壁灯 | E41: 200–299 | F41: Time4buy | G41: time4buy | H41: TIME4BUY | I41: 跨境店 | J41: 254.71 | K41: 4 | L41: 63.68 | M41: 76 | N41: 368 | O41: 1112 | P41: 1571 | Q41: 93733.28 | R41: =IFERROR(M41*30/(N41*7),0) -> 0.88509317 | S41: 352 | T41: =IFERROR(S41*30/N41,0) -> 28.695652 | U41: FULL | V41: 192 | W41: 4.8 | X41: 0.0537 | Y41: 46127 | Z41: 91–180天 | AA41: 20 | AB41: -0.044155844 | AC41: 20 cm | AD41: 13.6 cm | AE41: 9.8 cm | AF41: 0.96 kg | AG41: 在售 | AH41: https://articulo.mercadolibre.com.mx/MLM-2866035563-time4buy-4pcs-lampara-de-4w-led-exterior-22-leds-superior-e-inferior-10x8x4-cm-ip65-impermeable-kit-completo-para-fachadas-jardines-escaleras-pasillos-luz-calida-negro-_JM | AI41: Hogar, Muebles y Jardín(家居、家具和花园) -> Iluminación para el Hogar(家居照明) -> Lámparas(灯具) -> Lámparas de Pared(壁灯) | AJ41: 1
A42: 39 | B42: MLM2187123085 | C42: 4lampara Led Escalera Pared Cortesía Empotrable Foco 3w Ip65 Negro | D42: 邻近：楼梯/嵌入灯 | E42: 200–299 | F42: Utieer | G42: utieer | H42: ILLSORY | I42: 本土店 | J42: 239.27 | K42: 1 | L42: 239.27 | M42: 103 | N42: 351 | O42: 974 | P42: 3277 | Q42: 83983.77 | R42: =IFERROR(M42*30/(N42*7),0) -> 1.2576313 | S42: 653 | T42: =IFERROR(S42*30/N42,0) -> 55.811966 | U42: FULL | V42: 59 | W42: 4.9 | X42: 0.1196 | Y42: 45614 | Z42: 更早 | AB42: 0.044642857 | AC42: 11 cm | AD42: 10.6 cm | AE42: 19.4 cm | AF42: 0.6 kg | AG42: 在售 | AH42: https://articulo.mercadolibre.com.mx/MLM-2187123085-4lampara-led-escalera-pared-cortesia-empotrable-foco-3w-ip65-negro-_JM | AI42: Hogar, Muebles y Jardín(家居、家具和花园) -> Iluminación para el Hogar(家居照明) -> Lámparas(灯具) -> Lámparas de Pared(壁灯) | AJ42: 0
A43: 40 | B43: MLM1498036164 | C43: Lámpara De Pared Led De 12w Foco Flotante Moderno | D43: 有线户外/通用壁灯 | E43: 100–149 | F43: arbotantes de techo,arbotante exterior,arbotante interior,lamparas para jardin,lámparas para exterior modernas,lampara de pared interior,lamparas para jardin de pared | G43: arbotantes de techo,arbotante exterior,arbotante interior,lamparas para jardin,lamparas para exterior modernas,lampara de pared interior,lamparas para jardin de pared | H43: DELAIDATECH | I43: 本土店 | J43: 129 | K43: 1 | L43: 129 | M43: 63 | N43: 347 | O43: 976 | P43: 22795 | Q43: 47343 | R43: =IFERROR(M43*30/(N43*7),0) -> 0.77809798 | S43: 332 | T43: =IFERROR(S43*30/N43,0) -> 28.70317 | U43: FULL | V43: 728 | W43: 4.5 | X43: 0.0951 | Y43: 44812 | Z43: 更早 | AA43: 19 | AB43: 0.035820896 | AC43: 12.4 cm | AD43: 11.8 cm | AE43: 5.4 cm | AF43: 0.2 kg | AG43: 在售 | AH43: https://articulo.mercadolibre.com.mx/MLM-1498036164-lampara-de-pared-led-de-12w-foco-flotante-moderno-_JM | AI43: Hogar, Muebles y Jardín(家居、家具和花园) -> Iluminación para el Hogar(家居照明) -> Lámparas(灯具) -> Lámparas de Pared(壁灯) | AJ43: 1
A44: 41 | B44: MLM5782662244 | C44: Lámparas Solares De Pared Sensor Recargable Exterior Jardin | D44: 太阳能户外壁灯 | E44: 300–499 | F44: CCALMX | G44: ccalmx | H44: CCAL | I44: 本土店 | J44: 340.86 | K44: 1 | L44: 340.86 | M44: 40 | N44: 344 | O44: 370 | P44: 370 | Q44: 117255.84 | R44: =IFERROR(M44*30/(N44*7),0) -> 0.49833887 | S44: 383 | T44: =IFERROR(S44*30/N44,0) -> 33.401163 | U44: FULL | V44: 0 | W44: 0 | X44: 0.0383 | Y44: 46225 | Z44: 近90天上架 | AB44: 7.3902439 | AC44: 20 cm | AD44: 20 cm | AE44: 13.6 cm | AF44: 0.62 kg | AG44: 在售 | AH44: https://articulo.mercadolibre.com.mx/MLM-5782662244-lamparas-solares-de-pared-sensor-recargable-exterior-jardin-negro-_JM | AI44: Hogar, Muebles y Jardín(家居、家具和花园) -> Iluminación para el Hogar(家居照明) -> Lámparas(灯具) -> Lámparas de Pared(壁灯) | AJ44: 1
A45: 42 | B45: MLM2038288378 | C45: Lámpara De Pared Led De 6w Impermeable Foco Flotante | D45: 有线户外/通用壁灯 | E45: 150–199 | F45: Judeng | G45: judeng | H45: CNJUDENG-MXF | I45: 跨境店 | J45: 153.17 | K45: 1 | L45: 153.17 | M45: 77 | N45: 336 | O45: 1056 | P45: 6482 | Q45: 54375.35 | R45: =IFERROR(M45*30/(N45*7),0) -> 0.98214286 | S45: 450 | T45: =IFERROR(S45*30/N45,0) -> 40.178571 | U45: FULL | V45: 195 | W45: 4.7 | X45: 0.1757 | Y45: 45026 | Z45: 更早 | AB45: -0.21678322 | AC45: 11.2 cm | AD45: 11.2 cm | AE45: 11.2 cm | AF45: 0.25 kg | AG45: 在售 | AH45: https://articulo.mercadolibre.com.mx/MLM-2038288378-lampara-de-pared-led-de-6w-impermeable-foco-flotante-_JM | AI45: Hogar, Muebles y Jardín(家居、家具和花园) -> Iluminación para el Hogar(家居照明) -> Lámparas(灯具) -> Lámparas de Pared(壁灯) | AJ45: 1
A46: 43 | B46: MLM5039859338 | C46: Vanance® Lámpara Luz Led Lamparas Arbotante Pared Interiores Exterior Cuadrado Impermeable 6w Lampara Arbotante Lampara Decorativas De Alta Eficiencialuz Ajustable Manualmente Negro | D46: 有线户外/通用壁灯 | E46: 150–199 | F46: Vanance | G46: vanance | H46: VANANCE | I46: 本土店 | J46: 154 | K46: 1 | L46: 154 | M46: 104 | N46: 323 | O46: 749 | P46: 1446 | Q46: 49742 | R46: =IFERROR(M46*30/(N46*7),0) -> 1.3799204 | S46: 229 | T46: =IFERROR(S46*30/N46,0) -> 21.26935 | U46: FULL | V46: 50 | W46: 4.7 | X46: 0.1517 | Y46: 46101 | Z46: 更早 | AB46: 0.7 | AC46: 11.3 cm | AD46: 11.3 cm | AE46: 11.2 cm | AF46: 0.26 kg | AG46: 在售 | AH46: https://articulo.mercadolibre.com.mx/MLM-5039859338-vanance-lampara-luz-led-lamparas-arbotante-pared-interiores-exterior-cuadrado-impermeable-6w-lampara-arbotante-lampara-decorativas-de-alta-eficiencialuz-ajustable-manualmente-negro-_JM | AI46: Hogar, Muebles y Jardín(家居、家具和花园) -> Iluminación para el Hogar(家居照明) -> Lámparas(灯具) -> Lámparas de Pared(壁灯) | AJ46: 1
A47: 44 | B47: MLM3584405842 | C47: Lampara Tecnolite De Exterior Aplicación Suspendido Decorativa 26 W Color Negro Ftl-6003/n | D47: 待人工复核 | E47: 200–299 | F47: Tecnolite | G47: tecnolite | H47: MERCADOLIBRE HOME_MX | I47: 本土店 | J47: 266.18 | K47: 1 | L47: 266.18 | M47: 53 | N47: 313 | O47: 876 | P47: 2929 | Q47: 83314.34 | R47: =IFERROR(M47*30/(N47*7),0) -> 0.72569603 | S47: 181 | T47: =IFERROR(S47*30/N47,0) -> 17.348243 | U47: FULL | V47: 992 | W47: 4.8 | X47: 0.1189 | Y47: 45721 | Z47: 更早 | AA47: 19 | AB47: 0.46261682 | AC47: 18.6 cm | AD47: 18.4 cm | AE47: 24.4 cm | AF47: 0.51 kg | AG47: 在售 | AH47: https://articulo.mercadolibre.com.mx/MLM-3584405842-lampara-tecnolite-de-exterior-aplicacion-suspendido-decorativa-26-w-color-negro-ftl-6003n-_JM | AI47: Hogar, Muebles y Jardín(家居、家具和花园) -> Iluminación para el Hogar(家居照明) -> Lámparas(灯具) -> Lámparas de Pared(壁灯) | AJ47: 0
A48: 45 | B48: MLM4344060268 | C48: Lámpara Pared Solar Exterior Impermeable Moderna Con 3 Modos Estructura Temperatura Tricolor | D48: 太阳能户外壁灯 | E48: 200–299 | F48: Ambueco | G48: ambueco | H48: AMBUECO SHOP | I48: 跨境店 | J48: 253.68 | K48: 1 | L48: 253.68 | M48: 36 | N48: 306 | O48: 1151 | P48: 2403 | Q48: 77626.08 | R48: =IFERROR(M48*30/(N48*7),0) -> 0.50420168 | S48: 551 | T48: =IFERROR(S48*30/N48,0) -> 54.019608 | U48: FULL | V48: 116 | W48: 4.8 | X48: 0.0539 | Y48: 45968 | Z48: 更早 | AA48: 17 | AB48: -0.21134021 | AC48: 33 cm | AD48: 8.6 cm | AE48: 6.4 cm | AF48: 0.55 kg | AG48: 在售 | AH48: https://articulo.mercadolibre.com.mx/MLM-4344060268-lampara-pared-solar-exterior-impermeable-moderna-con-3-modos-estructura-temperatura-tricolor-_JM | AI48: Hogar, Muebles y Jardín(家居、家具和花园) -> Iluminación para el Hogar(家居照明) -> Lámparas(灯具) -> Lámparas de Pared(壁灯) | AJ48: 1
A49: 46 | B49: MLM2809299349 | C49: Vanance® Lámpara Pared Exterior Y Interiores 3000k Luz Cálida Impermeable 24w Modernas Led Lampara Ambiente Decorativas Para Sala Iluminacion Lamparas Para Exteriores 110-265v Color Negro Blanco | D49: 有线户外/通用壁灯 | E49: 150–199 | F49: Vanance | G49: vanance | H49: VANANCE | I49: 本土店 | J49: 159 | K49: 1 | L49: 159 | M49: 49 | N49: 298 | O49: 1073 | P49: 2644 | Q49: 50403 | R49: =IFERROR(M49*30/(N49*7),0) -> 0.70469799 | S49: 363 | T49: =IFERROR(S49*30/N49,0) -> 36.543624 | U49: FULL | V49: 260 | W49: 4.6 | X49: 0.1105 | Y49: 46104 | Z49: 更早 | AB49: -0.255 | AC49: 12 cm | AD49: 9.7 cm | AE49: 25.9 cm | AF49: 0.34 kg | AG49: 在售 | AH49: https://articulo.mercadolibre.com.mx/MLM-2809299349-vanance-lampara-pared-exterior-y-interiores-3000k-luz-calida-impermeable-24w-modernas-led-lampara-ambiente-decorativas-para-sala-iluminacion-lamparas-para-exteriores-110-265v-color-negro-blanco-_JM | AI49: Hogar, Muebles y Jardín(家居、家具和花园) -> Iluminación para el Hogar(家居照明) -> Lámparas(灯具) -> Lámparas de Pared(壁灯) | AJ49: 1
A50: 47 | B50: MLM3094430028 | C50: Gosun® Hexágono Faroles Lámparas De Pared Casa Decoración No Focos Wei World Zt-302 Color Darado Bronce | D50: 复古/灯笼壁灯 | E50: 200–299 | F50: Gosun | G50: gosun | H50: GOSUN | I50: 跨境店 | J50: 275.36 | K50: 1 | L50: 275.36 | M50: 63 | N50: 297 | O50: 769 | P50: 5014 | Q50: 81781.92 | R50: =IFERROR(M50*30/(N50*7),0) -> 0.90909091 | S50: 214 | T50: =IFERROR(S50*30/N50,0) -> 21.616162 | U50: FULL | V50: 739 | W50: 4.8 | X50: 0.0906 | Y50: 45437 | Z50: 更早 | AA50: 11 | AB50: 0.027681661 | AC50: 26.8 cm | AD50: 29.8 cm | AE50: 16.6 cm | AF50: 1.03 kg | AG50: 在售 | AH50: https://articulo.mercadolibre.com.mx/MLM-3094430028-gosun-hexagono-faroles-lamparas-de-pared-casa-decoracion-no-focos-wei-world-zt-302-color-darado-bronce-_JM | AI50: Hogar, Muebles y Jardín(家居、家具和花园) -> Iluminación para el Hogar(家居照明) -> Lámparas(灯具) -> Lámparas de Pared(壁灯) | AJ50: 1
A51: 48 | B51: MLM2809250589 | C51: Lámpara Pared Exterior Y Interiores 24w Vanance® Lámpara Muro Pared Impermeables Luz Cálida 3000k De Modernas Decorativa Pare Jardín Pasillos Escaleras Sala Baño Arbotante Negro | D51: 有线户外/通用壁灯 | E51: 150–199 | F51: Vanance | G51: vanance | H51: VANANCE | I51: 本土店 | J51: 163.66 | K51: 1 | L51: 163.66 | M51: 38 | N51: 291 | O51: 1560 | P51: 2438 | Q51: 47625.06 | R51: =IFERROR(M51*30/(N51*7),0) -> 0.55964654 | S51: 387 | T51: =IFERROR(S51*30/N51,0) -> 39.896907 | U51: FULL | V51: 153 | W51: 4.6 | X51: 0.1028 | Y51: 46104 | Z51: 更早 | AA51: 20 | AB51: -0.5245098 | AC51: 12.6 cm | AD51: 9.6 cm | AE51: 25.6 cm | AF51: 1.19 kg | AG51: 在售 | AH51: https://articulo.mercadolibre.com.mx/MLM-2809250589-lampara-pared-exterior-y-interiores-24w-vanance-lampara-muro-pared-impermeables-luz-calida-3000k-de-modernas-decorativa-pare-jardin-pasillos-escaleras-sala-bano-arbotante-negro-_JM | AI51: Hogar, Muebles y Jardín(家居、家具和花园) -> Iluminación para el Hogar(家居照明) -> Lámparas(灯具) -> Lámparas de Pared(壁灯) | AJ51: 1
A52: 49 | B52: MLM2858051029 | C52: Vanance Lámpara Pared Luces Luz Cálida Interiores Exterior Muro Color Negro 4w Regulador De Luz Luz Arbotante Lamparas Modernas Lampara Decorativas | D52: 有线户外/通用壁灯 | E52: <100 | F52: Vanance | G52: vanance | H52: VANANCE | I52: 本土店 | J52: 88.45 | K52: 1 | L52: 88.45 | M52: 83 | N52: 291 | O52: 970 | P52: 2096 | Q52: 27065.7 | R52: =IFERROR(M52*30/(N52*7),0) -> 1.2223859 | S52: 321 | T52: =IFERROR(S52*30/N52,0) -> 33.092784 | U52: FULL | V52: 441 | W52: 4.5 | X52: 0.0833 | Y52: 46123 | Z52: 91–180天 | AA52: 17 | AB52: -0.042763158 | AC52: 13.2 cm | AD52: 9.6 cm | AE52: 5 cm | AF52: 0.62 kg | AG52: 在售 | AH52: https://articulo.mercadolibre.com.mx/MLM-2858051029-vanance-lampara-pared-luces-luz-calida-interiores-exterior-muro-color-negro-4w-regulador-de-luz-luz-arbotante-lamparas-modernas-lampara-decorativas-_JM | AI52: Hogar, Muebles y Jardín(家居、家具和花园) -> Iluminación para el Hogar(家居照明) -> Lámparas(灯具) -> Lámparas de Pared(壁灯) | AJ52: 1
A53: 50 | B53: MLM4428679062 | C53: Luminicola Aplique De Pared Exterior Negro Led 12w Ip65 Para Jardín Y Patio | D53: 有线户外/通用壁灯 | E53: 150–199 | F53: Luminicola | G53: luminicola | H53: CNLUMINICOLAMXF | I53: 跨境店 | J53: 163.5 | K53: 1 | L53: 163.5 | M53: 20 | N53: 285 | O53: 438 | P53: 1690 | Q53: 46597.5 | R53: =IFERROR(M53*30/(N53*7),0) -> 0.30075188 | S53: 1 | T53: =IFERROR(S53*30/N53,0) -> 0.10526316 | U53: FULL | V53: 51 | W53: 4.8 | X53: 0.1241 | Y53: 45988 | Z53: 更早 | AB53: 0.97916667 | AC53: 11.7 cm | AD53: 12.1 cm | AE53: 13.4 cm | AF53: 0.28 kg | AG53: 在售 | AH53: https://articulo.mercadolibre.com.mx/MLM-4428679062-luminicola-lampara-de-pared-led-exterior-ip65-negra-3000k-luz-calida-para-interior-exterior-impermeable-negro-_JM | AI53: Hogar, Muebles y Jardín(家居、家具和花园) -> Iluminación para el Hogar(家居照明) -> Lámparas(灯具) -> Lámparas de Pared(壁灯) | AJ53: 1
A54: 51 | B54: MLM3011039024 | C54: Lámparas De Pared Decorativa Exteriores Interior Jardin Ip65 | D54: 有线户外/通用壁灯 | E54: 200–299 | F54: Nifuna | G54: nifuna | H54: CNNIFUNA | I54: 跨境店 | J54: 253.16 | K54: 1 | L54: 253.16 | M54: 57 | N54: 285 | O54: 964 | P54: 4774 | Q54: 72150.6 | R54: =IFERROR(M54*30/(N54*7),0) -> 0.85714286 | S54: 404 | T54: =IFERROR(S54*30/N54,0) -> 42.526316 | U54: FULL | V54: 236 | W54: 4.8 | X54: 0.0898 | Y54: 45397 | Z54: 更早 | AB54: -0.23796791 | AC54: 34.8 cm | AD54: 12 cm | AE54: 10.6 cm | AF54: 0.66 kg | AG54: 在售 | AH54: https://articulo.mercadolibre.com.mx/MLM-3011039024-lamparas-de-pared-decorativa-exteriores-interior-jardin-ip65-_JM | AI54: Hogar, Muebles y Jardín(家居、家具和花园) -> Iluminación para el Hogar(家居照明) -> Lámparas(灯具) -> Lámparas de Pared(壁灯) | AJ54: 1
A55: 52 | B55: MLM3479661302 | C55: Lámpara De Pared De Interior Cristal Decorativa Moderna Estructura Cuadrado Dorado | D55: 室内装饰壁灯 | E55: 150–199 | F55: Lumoku | G55: lumoku | H55: TIENDAOFICIAL LUMOKU | I55: 本土店 | J55: 173.44 | K55: 1 | L55: 173.44 | M55: 42 | N55: 279 | O55: 689 | P55: 2506 | Q55: 49256.96 | R55: =IFERROR(M55*30/(N55*7),0) -> 0.64516129 | S55: 96 | T55: =IFERROR(S55*30/N55,0) -> 10.322581 | U55: FULL | V55: 1418 | W55: 4.7 | X55: 0.0565 | Y55: 45623 | Z55: 更早 | AA55: 19 | AB55: 0.077220077 | AC55: 15.5 cm | AD55: 15 cm | AE55: 14.5 cm | AF55: 0.65 kg | AG55: 在售 | AH55: https://articulo.mercadolibre.com.mx/MLM-3479661302-lampara-de-pared-de-interior-cristal-decorativa-moderna-estructura-cuadrado-dorado-_JM | AI55: Hogar, Muebles y Jardín(家居、家具和花园) -> Iluminación para el Hogar(家居照明) -> Lámparas(灯具) -> Lámparas de Pared(壁灯) | AJ55: 1
A56: 53 | B56: MLM4427663676 | C56: Dehobo 2pcs Lampara Exterior Decorativas Pared Led 3000k,luces Exterior Jardin Impermeable,lámparas De Moderna Pared Para Interior Y Exterior Porche, Escaleras, Pasillo,sala. Negro | D56: 有线户外/通用壁灯 | E56: 150–199 | F56: DEHOBO | G56: dehobo | H56: CNMINGHOUMXFMXF | I56: 跨境店 | J56: 154.72 | K56: 2 | L56: 77.36 | M56: 104 | N56: 279 | O56: 1259 | P56: 2222 | Q56: 43166.88 | R56: =IFERROR(M56*30/(N56*7),0) -> 1.5975422 | S56: 263 | T56: =IFERROR(S56*30/N56,0) -> 28.27957 | U56: FULL | V56: 183 | W56: 4.7 | X56: 0.0451 | Y56: 45987 | Z56: 更早 | AA56: 14 | AB56: -0.47654784 | AC56: 17.2 cm | AD56: 9.4 cm | AE56: 5.4 cm | AF56: 0.22 kg | AG56: 在售 | AH56: https://articulo.mercadolibre.com.mx/MLM-4427663676-dehobo-2pcs-lamparas-para-escaleras-exterior-lampara-pared-led-focos-3000kluces-exterior-jardin-impermeablelamparas-para-bano-para-interior-y-exterior-porche-escaleras-pasillosala-negro-_JM | AI56: Hogar, Muebles y Jardín(家居、家具和花园) -> Iluminación para el Hogar(家居照明) -> Lámparas(灯具) -> Lámparas de Pared(壁灯) | AJ56: 1
A57: 54 | B57: MLM1790041085 | C57: Lámpara Luz De Pared Solar Led Pared Exterior Sensor 3 Modos | D57: 太阳能户外壁灯 | E57: 100–149 | F57: BAKEWAY | G57: bakeway | H57: CNDLXZXDL-MXF | I57: 跨境店 | J57: 125.63 | K57: 1 | L57: 125.63 | M57: 36 | N57: 277 | O57: 766 | P57: 6472 | Q57: 35930.18 | R57: =IFERROR(M57*30/(N57*7),0) -> 0.55698814 | S57: 377 | T57: =IFERROR(S57*30/N57,0) -> 40.830325 | U57: FULL | V57: 820 | W57: 4.4 | X57: 0.0708 | Y57: 44957 | Z57: 更早 | AB57: 0.077821012 | AC57: 10.6 cm | AD57: 10.4 cm | AE57: 10.4 cm | AF57: 0.26 kg | AG57: 在售 | AH57: https://articulo.mercadolibre.com.mx/MLM-1790041085-lampara-luz-de-pared-solar-led-pared-exterior-sensor-3-modos-_JM | AI57: Hogar, Muebles y Jardín(家居、家具和花园) -> Iluminación para el Hogar(家居照明) -> Lámparas(灯具) -> Lámparas de Pared(壁灯) | AJ57: 1
A58: 55 | B58: MLM2846207451 | C58: Lámpara Led De Pared Ondulado 60cm 3 Tono Blanco Cálido Nneutro Interior Exterior Dormitor Estructura Negro | D58: 有线户外/通用壁灯 | E58: 200–299 | F58: Yishabeier | G58: yishabeier | H58: HOOMEEMXF | I58: 跨境店 | J58: 285.51 | K58: 1 | L58: 285.51 | M58: 71 | N58: 274 | O58: 531 | P58: 960 | Q58: 78229.74 | R58: =IFERROR(M58*30/(N58*7),0) -> 1.1105318 | S58: 38 | T58: =IFERROR(S58*30/N58,0) -> 4.1605839 | U58: FULL | V58: 53 | W58: 4.7 | X58: 0.0499 | Y58: 46118 | Z58: 91–180天 | AB58: 1.8842105 | AC58: 38.8 cm | AD58: 9.8 cm | AE58: 4.6 cm | AF58: 0.35 kg | AG58: 在售 | AH58: https://articulo.mercadolibre.com.mx/MLM-2846207451-lampara-led-de-pared-ondulado-60cm-3-tono-blanco-calido-nneutro-interior-exterior-dormitor-estructura-negro-_JM | AI58: Hogar, Muebles y Jardín(家居、家具和花园) -> Iluminación para el Hogar(家居照明) -> Lámparas(灯具) -> Lámparas de Pared(壁灯) | AJ58: 1
A59: 56 | B59: MLM5194320708 | C59: 2 Pack 60cm Luz De Led Clóset Usb Con Sensor Movimiento,lampara De Pared De Recargable, Inalámbrica Y 3-color Dimmable,para Dormitorio, Sala De Estar, Pasillo, Cocina, Vitrina, Guardarropa,negro | D59: 邻近：橱柜/衣柜灯 | E59: 200–299 | F59: DGSITC | G59: dgsitc | H59: SLMXSHOP | I59: 本土店 | J59: 219.99 | K59: 2 | L59: 110 | M59: 47 | N59: 267 | O59: 334 | P59: 546 | Q59: 59837.28 | R59: =IFERROR(M59*30/(N59*7),0) -> 0.75441413 | S59: 5 | T59: =IFERROR(S59*30/N59,0) -> 0.56179775 | U59: FULL | V59: 274 | W59: 4.7 | X59: 0.055 | Y59: 46127 | Z59: 91–180天 | AA59: 20 | AB59: 4.0377358 | AC59: 62.2 cm | AD59: 5.4 cm | AE59: 5 cm | AF59: 0.54 kg | AG59: 在售 | AH59: https://articulo.mercadolibre.com.mx/MLM-5194320708-pack-2-lamparas-led-con-sensor-de-movimiento-de-60-cm-recargables-y-3-colores-negro-_JM | AI59: Hogar, Muebles y Jardín(家居、家具和花园) -> Iluminación para el Hogar(家居照明) -> Lámparas(灯具) -> Lámparas de Pared(壁灯) | AJ59: 0
A60: 57 | B60: MLM2237372899 | C60: Farol Decorativo Español Blanco Exterior Luminario Pared 100w Geopower | D60: 复古/灯笼壁灯 | E60: 300–499 | F60: Geopower | G60: geopower | H60: QUALITY_TECH_BRANDS | I60: 本土店 | J60: 323.1 | K60: 1 | L60: 323.1 | M60: 24 | N60: 266 | O60: 974 | P60: 5046 | Q60: 88852.5 | R60: =IFERROR(M60*30/(N60*7),0) -> 0.38668099 | S60: 647 | T60: =IFERROR(S60*30/N60,0) -> 72.969925 | U60: FULL | V60: 440 | W60: 4.8 | X60: 0.0646 | Y60: 45701 | Z60: 更早 | AA60: 14 | AB60: -0.36363636 | AC60: 16.4 cm | AD60: 14.2 cm | AE60: 20 cm | AF60: 0.78 kg | AG60: 在售 | AH60: https://articulo.mercadolibre.com.mx/MLM-2237372899-lampara-de-pared-exterior-farol-decorativo-blanco-espanol-100w-geopower-_JM | AI60: Hogar, Muebles y Jardín(家居、家具和花园) -> Iluminación para el Hogar(家居照明) -> Lámparas(灯具) -> Lámparas de Pared(壁灯) | AJ60: 1
A61: 58 | B61: MLM5123360450 | C61: Vanance® Lámpara De Pared De Exterior Y Interiores Moderna Decorativas Foco Led Luz Estructura Redondo Arbotante 12w Luz Blanco Cálido Impermeable Negro | D61: 有线户外/通用壁灯 | E61: 100–149 | F61: Vanance | G61: vanance | H61: VANANCE | I61: 本土店 | J61: 148.8 | K61: 1 | L61: 148.8 | M61: 47 | N61: 266 | O61: 805 | P61: 1706 | Q61: 40771.2 | R61: =IFERROR(M61*30/(N61*7),0) -> 0.75725027 | S61: 233 | T61: =IFERROR(S61*30/N61,0) -> 26.278195 | U61: FULL | V61: 107 | W61: 4.7 | X61: 0.0725 | Y61: 46115 | Z61: 91–180天 | AB61: 0.1875 | AC61: 12.4 cm | AD61: 11.6 cm | AE61: 14.2 cm | AF61: 0.67 kg | AG61: 在售 | AH61: https://articulo.mercadolibre.com.mx/MLM-5123360450-vanance-lampara-de-pared-de-exterior-y-interiores-moderna-decorativas-foco-led-luz-estructura-redondo-arbotante-12w-luz-blanco-calido-impermeable-negro-_JM | AI61: Hogar, Muebles y Jardín(家居、家具和花园) -> Iluminación para el Hogar(家居照明) -> Lámparas(灯具) -> Lámparas de Pared(壁灯) | AJ61: 1
A62: 59 | B62: MLM5827853256 | C62: Lámparas De Pared Led Para Interior Y Exterior Negra Con Iluminación Bi-direccional, Rectangulares, De Aluminio Y Acrílico, Impermeable Ip67, Moderna Y Decorativa, Fácil De Montar. Gris Oscuro | D62: 有线户外/通用壁灯 | E62: 200–299 | F62: YASIMING | G62: yasiming | H62: AUDIOSIGNALGLOBAL | I62: 跨境店 | J62: 259.84 | K62: 1 | L62: 259.84 | M62: 48 | N62: 266 | O62: 403 | P62: 419 | Q62: 71715.84 | R62: =IFERROR(M62*30/(N62*7),0) -> 0.77336198 | S62: 97 | T62: =IFERROR(S62*30/N62,0) -> 10.93985 | U62: FULL | V62: 11 | W62: 4.5 | X62: 0.1485 | Y62: 46231 | Z62: 近90天上架 | AB62: 0.94160584 | AC62: 30.4 cm | AD62: 12.8 cm | AE62: 10 cm | AF62: 0.67 kg | AG62: 在售 | AH62: https://articulo.mercadolibre.com.mx/MLM-5827853256-lampara-de-pared-yasiming-led-rectangular-para-interior-y-exterior-en-negro-gris-oscuro-_JM | AI62: Hogar, Muebles y Jardín(家居、家具和花园) -> Iluminación para el Hogar(家居照明) -> Lámparas(灯具) -> Lámparas de Pared(壁灯) | AJ62: 1
A63: 60 | B63: MLM2465201109 | C63: Dehobo Lamparas De Pared Arbotantes 3000k, Ángulo De Luz Ajustable Lampara Arbotante Exterior Adecuado Para Instalación En Jardines, Pasillos, Portales Y Otros Ambientes Interiores Y Exteriores Negro | D63: 有线户外/通用壁灯 | E63: 150–199 | F63: DEHOBO | G63: dehobo | H63: DADA | I63: 本土店 | J63: 166.24 | K63: 1 | L63: 166.24 | M63: 68 | N63: 265 | O63: 786 | P63: 1713 | Q63: 44884.8 | R63: =IFERROR(M63*30/(N63*7),0) -> 1.0997305 | S63: 35 | T63: =IFERROR(S63*30/N63,0) -> 3.9622642 | U63: FULL | V63: 47 | W63: 4.7 | X63: 0.1408 | Y63: 45923 | Z63: 更早 | AB63: 0.19369369 | AC63: 11.2 cm | AD63: 11.2 cm | AE63: 11.4 cm | AF63: 0.37 kg | AG63: 在售 | AH63: https://articulo.mercadolibre.com.mx/MLM-2465201109-dehobo-lamparas-de-pared-exterior-arbotantes-3000kangulo-de-luz-ajustable-lampara-arbotante-exterior-adecuado-para-negro-_JM | AI63: Hogar, Muebles y Jardín(家居、家具和花园) -> Iluminación para el Hogar(家居照明) -> Lámparas(灯具) -> Lámparas de Pared(壁灯) | AJ63: 1
A64: 61 | B64: MLM2639303019 | C64: Dehobo Lampara De Pared Exterior 2pcs, 4 Led Focos Impermeable, Fácil De Instalar, Lámpara De Pared Elegante, Con Luces... Negro | D64: 有线户外/通用壁灯 | E64: 150–199 | F64: DEHOBO | G64: dehobo | H64: DADA | I64: 本土店 | J64: 151.42 | K64: 2 | L64: 75.71 | M64: 76 | N64: 265 | O64: 552 | P64: 2072 | Q64: 40126.3 | R64: =IFERROR(M64*30/(N64*7),0) -> 1.2291105 | S64: 96 | T64: =IFERROR(S64*30/N64,0) -> 10.867925 | U64: FULL | V64: 149 | W64: 4.9 | X64: 0.0458 | Y64: 46013 | Z64: 更早 | AA64: 13 | AB64: 0.86619718 | AC64: 16.8 cm | AD64: 9.2 cm | AE64: 5.4 cm | AF64: 0.22 kg | AG64: 在售 | AH64: https://articulo.mercadolibre.com.mx/MLM-2639303019-dehobo-2pcs-lampara-de-pared-led-modernopara-exterior-e-interior-pack-de-2-luces-arriba-y-abajo-luz-calida-3000k-impermeable-ip65para-salasdormitoriosescalerasjardinespatios-y-paredes-negro-_JM | AI64: Hogar, Muebles y Jardín(家居、家具和花园) -> Iluminación para el Hogar(家居照明) -> Lámparas(灯具) -> Lámparas de Pared(壁灯) | AJ64: 1
A65: 62 | B65: MLM6072589752 | C65: Lámpara Solar De Pared Exterior Con Sensor De Movimiento, Luz Led Impermeable Ip65,lámparas De Pared Para Jardín, Patio, Casa Y Acceso Negro | D65: 太阳能户外壁灯 | E65: 150–199 | F65: Qzgyoool | G65: qzgyoool | H65: GWRZJ STORE | I65: 跨境店 | J65: 178.64 | K65: 1 | L65: 178.64 | M65: 88 | N65: 264 | O65: 264 | P65: 264 | Q65: 47160.96 | R65: =IFERROR(M65*30/(N65*7),0) -> 1.4285714 | S65: 177 | T65: =IFERROR(S65*30/N65,0) -> 20.113636 | U65: FULL | V65: 70 | W65: 4.6 | X65: 0.0544 | Y65: 46259 | Z65: 近90天上架 | AB65: 65 | AF65: 0.42 kg | AG65: 在售 | AH65: https://articulo.mercadolibre.com.mx/MLM-6072589752-lampara-solar-de-pared-exterior-con-sensor-de-movimiento-luz-led-impermeable-ip65lamparas-de-pared-para-jardin-patio-casa-y-acceso-negro-_JM | AI65: Hogar, Muebles y Jardín(家居、家具和花园) -> Iluminación para el Hogar(家居照明) -> Lámparas(灯具) -> Lámparas de Pared(壁灯) | AJ65: 1
A66: 63 | B66: MLM5350389264 | C66: Time4buy® 2pzs Lámpara De Pared Led 12w Exteriores Interior Impermeable Iluminación Exterior Para Jardín, Patio, Terraza, Inicio (luz Cálida ) Negro | D66: 有线户外/通用壁灯 | E66: 200–299 | F66: Time4buy | G66: time4buy | H66: TIME4BUY | I66: 跨境店 | J66: 243.67 | K66: 2 | L66: 121.83 | M66: 29 | N66: 261 | O66: 717 | P66: 1030 | Q66: 65790.9 | R66: =IFERROR(M66*30/(N66*7),0) -> 0.47619048 | S66: 130 | T66: =IFERROR(S66*30/N66,0) -> 14.942529 | U66: FULL | V66: 217 | W66: 4.6 | X66: 0.0976 | Y66: 46157 | Z66: 91–180天 | AB66: 0.023529412 | AC66: 22.4 cm | AD66: 11.4 cm | AE66: 7.4 cm | AF66: 0.42 kg | AG66: 在售 | AH66: https://articulo.mercadolibre.com.mx/MLM-5350389264-time4buy-2pzs-lampara-de-pared-led-aluminio-12w-exteriores-interior-carcasa-robusta-y-duradera-ip65-impermeable-para-jardin-patio-terraza-inicio-negro-luz-calida--_JM | AI66: Hogar, Muebles y Jardín(家居、家具和花园) -> Iluminación para el Hogar(家居照明) -> Lámparas(灯具) -> Lámparas de Pared(壁灯) | AJ66: 1
A67: 64 | B67: MLM5477308968 | C67: 12w Luz De Pared Luz Arbotante Led Pared Uso Exterior 3000k Estructura Negro | D67: 有线户外/通用壁灯 | E67: 100–149 | F67: Lámpara Pared Led | G67: lampara pared led | H67: LEIKETECHNOLOGYLEIKETECHNOLO | I67: 本土店 | J67: 144 | K67: 1 | L67: 144 | M67: 103 | N67: 260 | O67: 1205 | P67: 1430 | Q67: 38160 | R67: =IFERROR(M67*30/(N67*7),0) -> 1.6978022 | S67: 476 | T67: =IFERROR(S67*30/N67,0) -> 54.923077 | U67: FULL | V67: 902 | W67: 4.5 | X67: 0.1288 | Y67: 46182 | Z67: 91–180天 | AA67: 20 | AB67: -0.3175853 | AC67: 13.2 cm | AD67: 11.8 cm | AE67: 5.8 cm | AF67: 0.43 kg | AG67: 在售 | AH67: https://articulo.mercadolibre.com.mx/MLM-5477308968-12w-luz-de-pared-luz-arbotante-led-pared-uso-exterior-3000k-estructura-negro-_JM | AI67: Hogar, Muebles y Jardín(家居、家具和花园) -> Iluminación para el Hogar(家居照明) -> Lámparas(灯具) -> Lámparas de Pared(壁灯) | AJ67: 1
A68: 65 | B68: MLM4893841770 | C68: 2pcs Lámparas Led Pared Interior Recargable Con Sensor Movimiento Aplique Inalámbricas Magnética Foco Emergencia Dormitorio Cocina Marrón Con Patrón De Madera Blanco Cálido Neutro Frío Gm Genmigos | D68: 充电/感应壁灯 | E68: 150–199 | F68: GM Genmigos | G68: gm genmigos | H68: BE20250829166666 | I68: 本土店 | J68: 198.99 | K68: 2 | L68: 99.5 | M68: 93 | N68: 260 | O68: 703 | P68: 1157 | Q68: 51737.4 | R68: =IFERROR(M68*30/(N68*7),0) -> 1.532967 | S68: 116 | T68: =IFERROR(S68*30/N68,0) -> 13.384615 | U68: FULL | V68: 121 | W68: 4.4 | X68: 0.0274 | Y68: 46083 | Z68: 更早 | AB68: 0.069958848 | AC68: 28.8 cm | AD68: 8.4 cm | AE68: 4.2 cm | AF68: 0.16 kg | AG68: 在售 | AH68: https://articulo.mercadolibre.com.mx/MLM-4893841770-pack-2-lamparas-led-pared-interior-aplique-recargable-con-sensor-movimiento-inalambricas-magnetica-foco-emergencia-dormitorio-cocina-marron-con-patron-de-madera-blanco-calido-neutro-frio-gm-genmigos-_JM | AI68: Hogar, Muebles y Jardín(家居、家具和花园) -> Iluminación para el Hogar(家居照明) -> Lámparas(灯具) -> Lámparas de Pared(壁灯) | AJ68: 1
A69: 66 | B69: MLM4555681314 | C69: Dehobo Lamparas Led Para Moderna Exteriores 3000k, Lampara Impermeable Ip65 Pared Decorativas Led Luces,lámparas... Negro | D69: 有线户外/通用壁灯 | E69: 150–199 | F69: DEHOBO | G69: dehobo | H69: CNMINGHOUMXFMXF | I69: 跨境店 | J69: 163.67 | K69: 1 | L69: 163.67 | M69: 46 | N69: 258 | O69: 509 | P69: 1073 | Q69: 42226.86 | R69: =IFERROR(M69*30/(N69*7),0) -> 0.7641196 | S69: 14 | T69: =IFERROR(S69*30/N69,0) -> 1.627907 | U69: FULL | V69: 36 | W69: 4.9 | X69: 0.069 | Y69: 46012 | Z69: 更早 | AB69: 0.21126761 | AC69: 19.2 cm | AD69: 9.5 cm | AE69: 8.2 cm | AF69: 0.29 kg | AG69: 在售 | AH69: https://articulo.mercadolibre.com.mx/MLM-4555681314-dehobo-lamparas-led-para-moderna-exteriores-3000k-lampara-impermeable-ip65-pared-decorativas-led-luceslamparas-negro-_JM | AI69: Hogar, Muebles y Jardín(家居、家具和花园) -> Iluminación para el Hogar(家居照明) -> Lámparas(灯具) -> Lámparas de Pared(壁灯) | AJ69: 1
A70: 67 | B70: MLM2281396897 | C70: Judeng Lámpara Led De Pared Impermeable Para Interior/exterior Lamparas De Pared Interior Y Exterior Focos Led Moderna... Negro | D70: 有线户外/通用壁灯 | E70: 200–299 | F70: Judeng | G70: judeng | H70: CNJUDENG-MXF | I70: 跨境店 | J70: 213 | K70: 1 | L70: 213 | M70: 1 | N70: 256 | O70: 1259 | P70: 3634 | Q70: 54528 | R70: =IFERROR(M70*30/(N70*7),0) -> 0.016741071 | S70: 2 | T70: =IFERROR(S70*30/N70,0) -> 0.234375 | U70: FULL | V70: 142 | W70: 4.5 | X70: 0.0949 | Y70: 45760 | Z70: 更早 | AB70: -0.54850088 | AC70: 24.2 cm | AD70: 14.4 cm | AE70: 11.8 cm | AF70: 0.62 kg | AG70: 在售 | AH70: https://articulo.mercadolibre.com.mx/MLM-2281396897-lampara-de-pared-led-para-interior-y-exterior-negra-con-iluminacion-bi-direccional-negro-_JM | AI70: Hogar, Muebles y Jardín(家居、家具和花园) -> Iluminación para el Hogar(家居照明) -> Lámparas(灯具) -> Lámparas de Pared(壁灯) | AJ70: 1
A71: 68 | B71: MLM2641629649 | C71: Dehobo Lampara De Pared Exterior 6w, 3000k Led Lampara Exterior Pared Moderna, Luces Exterior Jardin Impermeable Ip65, Iluminación De Pared Exterior Para Porche, Escaleras, Pasillo, Negro | D71: 有线户外/通用壁灯 | E71: <100 | F71: DEHOBO | G71: dehobo | H71: WEWE20240106010117 | I71: 本土店 | J71: 98.98 | K71: 1 | L71: 98.98 | M71: 130 | N71: 253 | O71: 729 | P71: 2118 | Q71: 25041.94 | R71: =IFERROR(M71*30/(N71*7),0) -> 2.2021457 | S71: 156 | T71: =IFERROR(S71*30/N71,0) -> 18.498024 | U71: FULL | V71: 90 | W71: 4.8 | X71: 0.134 | Y71: 46014 | Z71: 更早 | AB71: 0.78169014 | AC71: 18.4 cm | AD71: 8.8 cm | AE71: 6 cm | AF71: 0.22 kg | AG71: 在售 | AH71: https://articulo.mercadolibre.com.mx/MLM-2641629649-dehobo-lampara-de-pared-led-para-exterior-de-6w-3000k-negro-lampara-exteriores-pared-moderna-luceslamparas-iluminacion-pared-eluz-calida-ip65-para-jardino-en-locales-comerciales-como-restaurantes-_JM | AI71: Hogar, Muebles y Jardín(家居、家具和花园) -> Iluminación para el Hogar(家居照明) -> Lámparas(灯具) -> Lámparas de Pared(壁灯) | AJ71: 1
A72: 69 | B72: MLM2716865735 | C72: Dehobo Lámparas De Pared Para Exterior Interior Y Impermeable 3000k,lampara Arbotante Exterior Resistente Al Agua Y Al Sol, Puede Emitir Luz Tanto Desde Arriba Como Desde Abajo. Negro | D72: 有线户外/通用壁灯 | E72: <100 | F72: DEHOBO | G72: dehobo | H72: DADA | I72: 本土店 | J72: 88.88 | K72: 1 | L72: 88.88 | M72: 80 | N72: 252 | O72: 640 | P72: 1749 | Q72: 22397.76 | R72: =IFERROR(M72*30/(N72*7),0) -> 1.3605442 | S72: 18 | T72: =IFERROR(S72*30/N72,0) -> 2.1428571 | U72: FULL | V72: 70 | W72: 4.8 | X72: 0.1135 | Y72: 46049 | Z72: 更早 | AB72: 0.42372881 | AC72: 13 cm | AD72: 8.8 cm | AE72: 5.8 cm | AF72: 0.15 kg | AG72: 在售 | AH72: https://articulo.mercadolibre.com.mx/MLM-2716865735-lampara-de-pared-dehobo-led-para-exterior-e-interior-luz-calida-3000-k-y-4-w-negro-_JM | AI72: Hogar, Muebles y Jardín(家居、家具和花园) -> Iluminación para el Hogar(家居照明) -> Lámparas(灯具) -> Lámparas de Pared(壁灯) | AJ72: 1
A73: 70 | B73: MLM2194041233 | C73: Lámpara De Pared De Interior Cristal Decorativa Moderna Estructura Ronda Dorada | D73: 室内装饰壁灯 | E73: 150–199 | F73: Lumoku | G73: lumoku | H73: TIENDAOFICIAL LUMOKU | I73: 本土店 | J73: 178.76 | K73: 1 | L73: 178.76 | M73: 55 | N73: 252 | O73: 713 | P73: 2564 | Q73: 46656.36 | R73: =IFERROR(M73*30/(N73*7),0) -> 0.93537415 | S73: 9 | T73: =IFERROR(S73*30/N73,0) -> 1.0714286 | U73: FULL | V73: 1415 | W73: 4.7 | X73: 0.0475 | Y73: 45623 | Z73: 更早 | AA73: 20 | AB73: 0.081545064 | AC73: 14.4 cm | AD73: 13.8 cm | AE73: 16.6 cm | AF73: 0.54 kg | AG73: 在售 | AH73: https://articulo.mercadolibre.com.mx/MLM-2194041233-lampara-de-pared-de-interior-cristal-decorativa-moderna-estructura-ronda-dorada-_JM | AI73: Hogar, Muebles y Jardín(家居、家具和花园) -> Iluminación para el Hogar(家居照明) -> Lámparas(灯具) -> Lámparas de Pared(壁灯) | AJ73: 1
A74: 71 | B74: MLM5971841976 | C74: Lamparas Modernas De Jardin Solar Exterior 3 Modos,con 3 Modos De Luz, 3 Modos De Luz, Luz Blanca / Cálida / Neutral,para Jardines, Patios, Pasillos, Escaleras Ambueco Temperatura Tricolor | D74: 太阳能户外壁灯 | E74: 200–299 | F74: Ambueco | G74: ambueco | H74: AB20260518104845 | I74: 本土店 | J74: 273 | K74: 1 | L74: 273 | M74: 52 | N74: 241 | O74: 304 | P74: 321 | Q74: 68523 | R74: =IFERROR(M74*30/(N74*7),0) -> 0.92471844 | S74: 129 | T74: =IFERROR(S74*30/N74,0) -> 16.058091 | U74: FULL | V74: 207 | W74: 4.4 | X74: 0.0427 | Y74: 46247 | Z74: 近90天上架 | AA74: 3 | AB74: 2.8253968 | AC74: 32.7 cm | AD74: 8.4 cm | AE74: 6.4 cm | AF74: 0.56 kg | AG74: 在售 | AH74: https://articulo.mercadolibre.com.mx/MLM-5971841976-lamparas-modernas-de-jardin-solar-exterior-3-modoscon-3-modos-de-luz-3-modos-de-luz-luz-blanca-calida-neutralpara-jardines-patios-pasillos-escaleras-ambueco-temperatura-tricolor-_JM | AI74: Hogar, Muebles y Jardín(家居、家具和花园) -> Iluminación para el Hogar(家居照明) -> Lámparas(灯具) -> Lámparas de Pared(壁灯) | AJ74: 1
A75: 72 | B75: MLM5828230094 | C75: 2pcs Lámparas De Pared Led Para Interior Y Exterior Negra Con Iluminación Bi-direccional, Rectangulares, De Aluminio Y Acrílico, Impermeable Ip67, Moderna Y Decorativa, Fácil De Montar. Gris Oscuro | D75: 有线户外/通用壁灯 | E75: 200–299 | F75: YASIMING | G75: yasiming | H75: AUDIOSIGNALGLOBAL | I75: 跨境店 | J75: 292.23 | K75: 2 | L75: 146.12 | M75: 29 | N75: 239 | O75: 313 | P75: 326 | Q75: 71888.58 | R75: =IFERROR(M75*30/(N75*7),0) -> 0.52002391 | S75: 269 | T75: =IFERROR(S75*30/N75,0) -> 33.76569 | U75: FULL | V75: 6 | W75: 4.3 | X75: 0.0855 | Y75: 46231 | Z75: 近90天上架 | AB75: 2.2739726 | AC75: 23.9 cm | AD75: 23.6 cm | AE75: 10.6 cm | AF75: 0.77 kg | AG75: 在售 | AH75: https://articulo.mercadolibre.com.mx/MLM-5828230094-lampara-de-pared-yasiming-negra-bi-direccional-para-interior-y-exterior-pack-de-2-gris-oscuro-_JM | AI75: Hogar, Muebles y Jardín(家居、家具和花园) -> Iluminación para el Hogar(家居照明) -> Lámparas(灯具) -> Lámparas de Pared(壁灯) | AJ75: 1
A76: 73 | B76: MLM2255722503 | C76: Lamparas De Pared Inteligentes Interior Con Sensor 33cm 10w | D76: 室内装饰壁灯 | E76: <100 | F76: Treck | G76: treck | H76: TRECKTRECK20230627132042 | I76: 本土店 | J76: 96 | K76: 1 | L76: 96 | M76: 68 | N76: 235 | O76: 683 | P76: 2740 | Q76: 22560 | R76: =IFERROR(M76*30/(N76*7),0) -> 1.2401216 | S76: 10 | T76: =IFERROR(S76*30/N76,0) -> 1.2765957 | U76: FULL | V76: 244 | W76: 4.7 | X76: 0.0736 | Y76: 45727 | Z76: 更早 | AB76: 0.18686869 | AC76: 31 cm | AD76: 5.2 cm | AE76: 4.2 cm | AF76: 0.18 kg | AG76: 在售 | AH76: https://articulo.mercadolibre.com.mx/MLM-2255722503-lamparas-de-pared-inteligentes-interior-con-sensor-33cm-10w-blanco-_JM | AI76: Hogar, Muebles y Jardín(家居、家具和花园) -> Iluminación para el Hogar(家居照明) -> Lámparas(灯具) -> Lámparas de Pared(壁灯) | AJ76: 1
A77: 74 | B77: MLM5248639530 | C77: Vanance Lámparas De Pared Led Interiores Exterior Impermeable Arbotante Moderna Decorativas 3000k Lampara Luz Blanco Cálido Luces Jardin Cristal Hogar Decorativ 12w Color Negro | D77: 有线户外/通用壁灯 | E77: 150–199 | F77: Vanance | G77: vanance | H77: VANANCE | I77: 本土店 | J77: 154.68 | K77: 1 | L77: 154.68 | M77: 68 | N77: 234 | O77: 565 | P77: 843 | Q77: 36195.12 | R77: =IFERROR(M77*30/(N77*7),0) -> 1.2454212 | S77: 110 | T77: =IFERROR(S77*30/N77,0) -> 14.102564 | U77: FULL | V77: 31 | W77: 4.9 | X77: 0.0563 | Y77: 46138 | Z77: 91–180天 | AB77: 0.17 | AC77: 12.4 cm | AD77: 11.5 cm | AE77: 14.3 cm | AF77: 0.3 kg | AG77: 在售 | AH77: https://articulo.mercadolibre.com.mx/MLM-5248639530-vanance-lamparas-de-pared-led-interiores-exterior-impermeable-arbotante-moderna-decorativas-3000k-lampara-luz-blanco-calido-luces-jardin-cristal-hogar-decorativ-12w-color-negro-_JM | AI77: Hogar, Muebles y Jardín(家居、家具和花园) -> Iluminación para el Hogar(家居照明) -> Lámparas(灯具) -> Lámparas de Pared(壁灯) | AJ77: 1
A78: 75 | B78: MLM2208228539 | C78: Lámpara Led Sensor Movimiento Goodea Recargable Usb Para Armario Cocina Plateado | D78: 邻近：橱柜/衣柜灯 | E78: 200–299 | F78: Goode | G78: goode | H78: CNHAPPYFANLE-MXF | I78: 跨境店 | J78: 256.45 | K78: 1 | L78: 256.45 | M78: 44 | N78: 234 | O78: 686 | P78: 3830 | Q78: 60009.3 | R78: =IFERROR(M78*30/(N78*7),0) -> 0.80586081 | S78: 219 | T78: =IFERROR(S78*30/N78,0) -> 28.076923 | U78: FULL | V78: 630 | W78: 4.7 | X78: 0.0462 | Y78: 45645 | Z78: 更早 | AA78: 19 | AB78: -0.078740157 | AC78: 23.8 cm | AD78: 4.6 cm | AE78: 3.8 cm | AF78: 0.26 kg | AG78: 在售 | AH78: https://articulo.mercadolibre.com.mx/MLM-2208228539-lampara-led-sensor-movimiento-goodea-recargable-usb-luces-iluminacion-led-luz-para-interiores-para-armario-cocina-3000k4000k6500k-plateado-_JM | AI78: Hogar, Muebles y Jardín(家居、家具和花园) -> Iluminación para el Hogar(家居照明) -> Lámparas(灯具) -> Lámparas de Pared(壁灯) | AJ78: 0
A79: 76 | B79: MLM2195420501 | C79: Lámpara Led Recargable Con Sensor Movimiento Pack 6 Piezas 30cm, Luce Inalámbrica Recargable Usb Lámpara De Barra Magnética Iluminación Nocturna Para Gabinete Clóset Luz Blanca Para Interiores Blanco | D79: 邻近：橱柜/衣柜灯 | E79: 200–299 | F79: Genérica | G79: generica | H79: CNHAPPYFANLE-MXF | I79: 跨境店 | J79: 280.87 | K79: 6 | L79: 46.81 | M79: 31 | N79: 233 | O79: 826 | P79: 3726 | Q79: 68251.41 | R79: =IFERROR(M79*30/(N79*7),0) -> 0.57020233 | S79: 144 | T79: =IFERROR(S79*30/N79,0) -> 18.540773 | U79: FULL | V79: 530 | W79: 4.5 | X79: 0.0486 | Y79: 45624 | Z79: 更早 | AA79: 18 | AB79: -0.33237822 | AC79: 40.8 cm | AD79: 10.4 cm | AE79: 5.6 cm | AF79: 0.6 kg | AG79: 在售 | AH79: https://articulo.mercadolibre.com.mx/MLM-2195420501-6pzs-lamparas-sensor-movimiento-recargable-usb-luz-led-30cm-3000k-lamparas-de-pared-interior-luces-con-sensor-para-armario-cocina-closet-blanco-_JM | AI79: Hogar, Muebles y Jardín(家居、家具和花园) -> Iluminación para el Hogar(家居照明) -> Lámparas(灯具) -> Lámparas de Pared(壁灯) | AJ79: 0
A80: 77 | B80: MLM3517137784 | C80: Lampara De Pared Led Impermeable Para Exterior Simplicidad | D80: 有线户外/通用壁灯 | E80: 200–299 | F80: Judeng | G80: judeng | H80: CNJUDENG-MXF | I80: 跨境店 | J80: 230.61 | K80: 1 | L80: 230.61 | M80: 49 | N80: 232 | O80: 488 | P80: 1357 | Q80: 53501.52 | R80: =IFERROR(M80*30/(N80*7),0) -> 0.90517241 | S80: 304 | T80: =IFERROR(S80*30/N80,0) -> 39.310345 | U80: FULL | V80: 39 | W80: 4.6 | X80: 0.091 | Y80: 45657 | Z80: 更早 | AB80: 0.73134328 | AC80: 20.8 cm | AD80: 15.2 cm | AE80: 7.2 cm | AF80: 0.45 kg | AG80: 在售 | AH80: https://articulo.mercadolibre.com.mx/MLM-3517137784-lampara-de-pared-led-impermeable-para-exterior-simplicidad-_JM | AI80: Hogar, Muebles y Jardín(家居、家具和花园) -> Iluminación para el Hogar(家居照明) -> Lámparas(灯具) -> Lámparas de Pared(壁灯) | AJ80: 1
A81: 78 | B81: MLM2568962317 | C81: 2pcs Lámpara Solarexterior Pared Sensor 240led 3modos+remoto | D81: 太阳能户外壁灯 | E81: 200–299 | F81: ZYTURIAFLY | G81: zyturiafly | H81: ZYTURIAFLY | I81: 本土店 | J81: 248 | K81: 2 | L81: 124 | M81: 54 | N81: 232 | O81: 1445 | P81: 3654 | Q81: 57536 | R81: =IFERROR(M81*30/(N81*7),0) -> 0.99753695 | S81: 6 | T81: =IFERROR(S81*30/N81,0) -> 0.77586207 | U81: FULL | V81: 0 | W81: 0 | X81: 0.0705 | Y81: 45978 | Z81: 更早 | AB81: -0.36956522 | AC81: 15.7 cm | AD81: 14.3 cm | AE81: 16.3 cm | AF81: 0.46 kg | AG81: 在售 | AH81: https://articulo.mercadolibre.com.mx/MLM-2568962317-2pcs-lampara-solar-de-pared-exteriores-sensor-luz-3-modos-negro-_JM | AI81: Hogar, Muebles y Jardín(家居、家具和花园) -> Iluminación para el Hogar(家居照明) -> Lámparas(灯具) -> Lámparas de Pared(壁灯) | AJ81: 1
A82: 79 | B82: MLM4410821994 | C82: Lámpara Pared Exterior 2 Focos Led Moderna Negra Impermeable Negro | D82: 有线户外/通用壁灯 | E82: 200–299 | F82: Luminicola | G82: luminicola | H82: CNLUMINICOLAMXF | I82: 跨境店 | J82: 219.51 | K82: 1 | L82: 219.51 | M82: 42 | N82: 230 | O82: 631 | P82: 2460 | Q82: 52023.87 | R82: =IFERROR(M82*30/(N82*7),0) -> 0.7826087 | S82: 1 | T82: =IFERROR(S82*30/N82,0) -> 0.13043478 | U82: FULL | V82: 87 | W82: 4.7 | X82: 0.1104 | Y82: 45984 | Z82: 更早 | AB82: 0.15577889 | AC82: 15.6 cm | AD82: 11.2 cm | AE82: 23.8 cm | AF82: 0.58 kg | AG82: 在售 | AH82: https://articulo.mercadolibre.com.mx/MLM-4410821994-aplique-led-de-pared-luminicola-negro-para-exterior-bidireccional-ip65-_JM | AI82: Hogar, Muebles y Jardín(家居、家具和花园) -> Iluminación para el Hogar(家居照明) -> Lámparas(灯具) -> Lámparas de Pared(壁灯) | AJ82: 1
A83: 80 | B83: MLM4724679976 | C83: Pack 4 Lampara Foco Solar Aplique Exterior Impermeable | D83: 太阳能户外壁灯 | E83: 300–499 | F83: KEYIFA | G83: keyifa | H83: MOBKERO | I83: 本土店 | J83: 369.36 | K83: 4 | L83: 92.34 | M83: 131 | N83: 229 | O83: 548 | P83: 733 | Q83: 84583.44 | R83: =IFERROR(M83*30/(N83*7),0) -> 2.4516532 | S83: 72 | T83: =IFERROR(S83*30/N83,0) -> 9.4323144 | U83: FULL | V83: 60 | W83: 4.7 | X83: 0.0548 | Y83: 46051 | Z83: 更早 | AB83: 0.09569378 | AC83: 37.7 cm | AD83: 30.8 cm | AE83: 7.5 cm | AF83: 0.43 kg | AG83: 在售 | AH83: https://articulo.mercadolibre.com.mx/MLM-4724679976-pack-4-luces-solares-para-pared-keyifa-apliques-led-con-sensor-de-movimiento-y-3-modos-impermeables-ip65-para-jardin-y-patio-negro-_JM | AI83: Hogar, Muebles y Jardín(家居、家具和花园) -> Iluminación para el Hogar(家居照明) -> Lámparas(灯具) -> Lámparas de Pared(壁灯) | AJ83: 1
A84: 81 | B84: MLM2802749657 | C84: Lámpara De Pared Led Moderna A Prueba De Agua De 10w Para Exteriores | D84: 有线户外/通用壁灯 | E84: 100–149 | F84: Judeng | G84: judeng | H84: JUDENG ONLINE | I84: 跨境店 | J84: 143.82 | K84: 1 | L84: 143.82 | M84: 53 | N84: 225 | O84: 784 | P84: 1098 | Q84: 32359.5 | R84: =IFERROR(M84*30/(N84*7),0) -> 1.0095238 | S84: 193 | T84: =IFERROR(S84*30/N84,0) -> 25.733333 | U84: FULL | V84: 264 | W84: 4.7 | X84: 0.1282 | Y84: 46101 | Z84: 更早 | AB84: 0.24309392 | AC84: 28.4 cm | AD84: 8.8 cm | AE84: 6.6 cm | AF84: 0.28 kg | AG84: 在售 | AH84: https://articulo.mercadolibre.com.mx/MLM-2802749657-judeng-lampara-de-pared-led-moderna-a-prueba-de-agua-de-10w-para-exteriores-_JM | AI84: Hogar, Muebles y Jardín(家居、家具和花园) -> Iluminación para el Hogar(家居照明) -> Lámparas(灯具) -> Lámparas de Pared(壁灯) | AJ84: 1
A85: 82 | B85: MLM2042026349 | C85: Lámpara De Pared Led Impermeable Sobreponer Para Exterior | D85: 有线户外/通用壁灯 | E85: 200–299 | F85: Loho Tech | G85: loho tech | H85: DELAIDATECH | I85: 本土店 | J85: 261.25 | K85: 1 | L85: 261.25 | M85: 57 | N85: 224 | O85: 224 | P85: 3600 | Q85: 58520 | R85: =IFERROR(M85*30/(N85*7),0) -> 1.0905612 | S85: 216 | T85: =IFERROR(S85*30/N85,0) -> 28.928571 | U85: FULL | V85: 94 | W85: 4.7 | X85: 0.0847 | Y85: 45378 | Z85: 更早 | AB85: 224 | AC85: 31 cm | AD85: 16.2 cm | AE85: 9.6 cm | AF85: 0.82 kg | AG85: 在售 | AH85: https://articulo.mercadolibre.com.mx/MLM-2042026349-lampara-de-pared-led-impermeable-sobreponer-para-exterior-negro-_JM | AI85: Hogar, Muebles y Jardín(家居、家具和花园) -> Iluminación para el Hogar(家居照明) -> Lámparas(灯具) -> Lámparas de Pared(壁灯) | AJ85: 1
A86: 83 | B86: MLM2244626171 | C86: Judeng Lámpara De Pared Led 8w Bidireccional Ip65 Interior Exterior Luz Cálida 3000k Negra Negro | D86: 有线户外/通用壁灯 | E86: 100–149 | F86: Judeng | G86: judeng | H86: CNJUDENG-MXF | I86: 跨境店 | J86: 127.95 | K86: 1 | L86: 127.95 | M86: 34 | N86: 221 | O86: 550 | P86: 4572 | Q86: 28276.95 | R86: =IFERROR(M86*30/(N86*7),0) -> 0.65934066 | S86: 40 | T86: =IFERROR(S86*30/N86,0) -> 5.4298643 | U86: FULL | V86: 196 | W86: 4.8 | X86: 0.1238 | Y86: 45712 | Z86: 更早 | AA86: 14 | AB86: 0.31547619 | AC86: 25.6 cm | AD86: 11.4 cm | AE86: 7.4 cm | AF86: 0.32 kg | AG86: 在售 | AH86: https://articulo.mercadolibre.com.mx/MLM-2244626171-lampara-de-pared-judeng-led-8w-luz-calida-3000k-negra-para-interiores-y-exteriores-negro-_JM | AI86: Hogar, Muebles y Jardín(家居、家具和花园) -> Iluminación para el Hogar(家居照明) -> Lámparas(灯具) -> Lámparas de Pared(壁灯) | AJ86: 1
A87: 84 | B87: MLM5115676566 | C87: Vanance 4 Pcs Lámpara Pared Luces Cálida Interiores Exterior Muro Color Negro 4w Regulador De Luz Luz Arbotante Lamparas Moderna | D87: 有线户外/通用壁灯 | E87: 300–499 | F87: Vanance | G87: vanance | H87: VANANCE | I87: 本土店 | J87: 338.34 | K87: 4 | L87: 84.58 | M87: 51 | N87: 221 | O87: 912 | P87: 1680 | Q87: 74773.14 | R87: =IFERROR(M87*30/(N87*7),0) -> 0.98901099 | S87: 295 | T87: =IFERROR(S87*30/N87,0) -> 40.045249 | U87: FULL | V87: 379 | W87: 4.7 | X87: 0.049 | Y87: 46114 | Z87: 91–180天 | AA87: 11 | AB87: -0.24054983 | AC87: 19.6 cm | AD87: 13.6 cm | AE87: 9.6 cm | AF87: 0.54 kg | AG87: 在售 | AH87: https://articulo.mercadolibre.com.mx/MLM-5115676566-vanance-4-pcs-lampara-2led-pared-luces-calida-interiores-exterior-muro-color-negro-4w-regulador-de-luz-luz-arbotante-lamparas-moderna-ip65-_JM | AI87: Hogar, Muebles y Jardín(家居、家具和花园) -> Iluminación para el Hogar(家居照明) -> Lámparas(灯具) -> Lámparas de Pared(壁灯) | AJ87: 1
A88: 85 | B88: MLM5929008056 | C88: Eobromd 6pcs Luz Led Recargable Sensor De Movimiento Clóset Lámpara Pared Usb 3 Colores,luz Led Para Interiores,ideal... Blanco | D88: 邻近：橱柜/衣柜灯 | E88: 200–299 | F88: EOBROMD | G88: eobromd | H88: BEMANDA | I88: 本土店 | J88: 214.56 | K88: 6 | L88: 35.76 | M88: 44 | N88: 219 | O88: 239 | P88: 239 | Q88: 46988.64 | R88: =IFERROR(M88*30/(N88*7),0) -> 0.86105675 | S88: 76 | T88: =IFERROR(S88*30/N88,0) -> 10.410959 | U88: FULL | V88: 196 | W88: 4.7 | X88: 0.0866 | Y88: 46243 | Z88: 近90天上架 | AB88: 7.4230769 | AC88: 19.6 cm | AD88: 9.2 cm | AE88: 7.6 cm | AF88: 1 kg | AG88: 在售 | AH88: https://articulo.mercadolibre.com.mx/MLM-5929008056-eobromd-6pcs-luz-led-recargable-sensor-de-movimiento-closet-lampara-pared-usb-3-coloresluz-led-para-interioresideal-blanco-_JM | AI88: Hogar, Muebles y Jardín(家居、家具和花园) -> Iluminación para el Hogar(家居照明) -> Lámparas(灯具) -> Lámparas de Pared(壁灯) | AJ88: 0
A89: 86 | B89: MLM6130071982 | C89: Lámparas Solares Glowlin 2 Piezas Para Pared Exterior, Sensor De Movimiento 3 Modos, Luz Led Automática Impermeable Para Jardín, Patio, Garaje, Entrada Y Terraza Blanco Cálido | D89: 太阳能户外壁灯 | E89: 150–199 | F89: Glowlin | G89: glowlin | H89: GLOWLIN TIENDA OFICAL | I89: 本土店 | J89: 187.74 | K89: 2 | L89: 93.87 | M89: 74 | N89: 218 | O89: 218 | P89: 224 | Q89: 42053.76 | R89: =IFERROR(M89*30/(N89*7),0) -> 1.4547837 | S89: 177 | T89: =IFERROR(S89*30/N89,0) -> 24.357798 | U89: FULL | V89: 7 | W89: 4.3 | X89: 0.0538 | Y89: 46264 | Z89: 近90天上架 | AB89: 218 | AF89: 0.71 kg | AG89: 在售 | AH89: https://articulo.mercadolibre.com.mx/MLM-6130071982-lamparas-solares-glowlin-led-para-pared-pack-de-2-con-sensor-de-movimiento-y-3-modos-blanco-calido-_JM | AI89: Hogar, Muebles y Jardín(家居、家具和花园) -> Iluminación para el Hogar(家居照明) -> Lámparas(灯具) -> Lámparas de Pared(壁灯) | AJ89: 1
A90: 87 | B90: MLM2350300939 | C90: Lámpara De Pared Negra Retro Exterior Impermeable Jardín | D90: 复古/灯笼壁灯 | E90: 300–499 | F90: Judeng | G90: judeng | H90: JUDENG ONLINE | I90: 跨境店 | J90: 352.8 | K90: 1 | L90: 352.8 | M90: 37 | N90: 217 | O90: 352 | P90: 569 | Q90: 76557.6 | R90: =IFERROR(M90*30/(N90*7),0) -> 0.73074391 | S90: 270 | T90: =IFERROR(S90*30/N90,0) -> 37.327189 | U90: FULL | V90: 20 | W90: 4.1 | X90: 0.0635 | Y90: 45831 | Z90: 更早 | AB90: 0.72222222 | AC90: 21.6 cm | AD90: 28.2 cm | AE90: 17.6 cm | AF90: 0.42 kg | AG90: 在售 | AH90: https://articulo.mercadolibre.com.mx/MLM-2350300939-lampara-de-pared-negra-retro-exterior-impermeable-jardin-_JM | AI90: Hogar, Muebles y Jardín(家居、家具和花园) -> Iluminación para el Hogar(家居照明) -> Lámparas(灯具) -> Lámparas de Pared(壁灯) | AJ90: 1
A91: 88 | B91: MLM4756124104 | C91: 2 Pack Lámpara De Pared Giratoria Multiforma Magnéticas Luz Blanca / Luz Cálida / Luz Neutra | D91: 充电/感应壁灯 | E91: 100–149 | F91: ASVEL | G91: asvel | H91: DIAZOBERTODIAZOBERTO | I91: 本土店 | J91: 147.63 | K91: 2 | L91: 73.81 | M91: 60 | N91: 217 | O91: 226 | P91: 226 | Q91: 32035.71 | R91: =IFERROR(M91*30/(N91*7),0) -> 1.1849901 | S91: 788 | T91: =IFERROR(S91*30/N91,0) -> 108.94009 | U91: FULL | V91: 0 | W91: 0 | X91: 0.0648 | Y91: 46059 | Z91: 更早 | AB91: 20.7 | AC91: 32.6 cm | AD91: 14.8 cm | AE91: 6 cm | AF91: 0.22 kg | AG91: 在售 | AH91: https://articulo.mercadolibre.com.mx/MLM-4756124104-2-pack-lampara-de-pared-giratoria-multiforma-magneticas-luz-blanca-luz-calida-luz-neutra-_JM | AI91: Hogar, Muebles y Jardín(家居、家具和花园) -> Iluminación para el Hogar(家居照明) -> Lámparas(灯具) -> Lámparas de Pared(壁灯) | AJ91: 1
A92: 89 | B92: MLM5318189194 | C92: Time4buy 2pcs Lámpara 5 Led 12w Pared Para Exterior Jardín Luz,ip65 Impermeable Iluminación De Pared Exterior Para Porche,escaleras,pasillo (negro Luz Amarillo) | D92: 有线户外/通用壁灯 | E92: 200–299 | F92: Time4buy | G92: time4buy | H92: TIME4BUY | I92: 跨境店 | J92: 208.59 | K92: 2 | L92: 104.3 | M92: 46 | N92: 211 | O92: 751 | P92: 887 | Q92: 45472.62 | R92: =IFERROR(M92*30/(N92*7),0) -> 0.93432634 | S92: 377 | T92: =IFERROR(S92*30/N92,0) -> 53.601896 | U92: FULL | V92: 249 | W92: 4.7 | X92: 0.0906 | Y92: 46153 | Z92: 91–180天 | AA92: 17 | AB92: -0.42032967 | AC92: 27.8 cm | AD92: 11.4 cm | AE92: 8.4 cm | AF92: 0.34 kg | AG92: 在售 | AH92: https://articulo.mercadolibre.com.mx/MLM-5318189194-time4buy-2pcs-lampara-55-led-10w-pared-para-exterior-jardin-luzip65-impermeable-27x8x5-cm-iluminacion-de-pared-exterior-para-porcheescaleraspasillo-negro-luz-amarillo-_JM | AI92: Hogar, Muebles y Jardín(家居、家具和花园) -> Iluminación para el Hogar(家居照明) -> Lámparas(灯具) -> Lámparas de Pared(壁灯) | AJ92: 1
A93: 90 | B93: MLM2622843495 | C93: 2pack 60cm Luz De Led Clóset Usb Con Sensor Movimiento Negro Negro | D93: 邻近：橱柜/衣柜灯 | E93: 200–299 | F93: General | G93: general | H93: RR20250A6051166666 | I93: 本土店 | J93: 217.54 | K93: 2 | L93: 108.77 | M93: 24 | N93: 210 | O93: 257 | P93: 517 | Q93: 47206.18 | R93: =IFERROR(M93*30/(N93*7),0) -> 0.48979592 | S93: 37 | T93: =IFERROR(S93*30/N93,0) -> 5.2857143 | U93: FULL | V93: 0 | W93: 0 | X93: 0.0507 | Y93: 46006 | Z93: 更早 | AB93: 210 | AC93: 62 cm | AD93: 6.2 cm | AE93: 5 cm | AF93: 0.4 kg | AG93: 在售 | AH93: https://articulo.mercadolibre.com.mx/MLM-2622843495-2pack-60cm-luz-de-led-closet-usb-con-sensor-movimiento-negro-negro-_JM | AI93: Hogar, Muebles y Jardín(家居、家具和花园) -> Iluminación para el Hogar(家居照明) -> Lámparas(灯具) -> Lámparas de Pared(壁灯) | AJ93: 0
A94: 91 | B94: MLM4683918834 | C94: 2 Pack Modernas Lámpara De Pared Led Recargable,inteligente | D94: 充电/感应壁灯 | E94: 200–299 | F94: BLIMEXOTAGE | G94: blimexotage | H94: BLIMEXOTAGE | I94: 本土店 | J94: 220 | K94: 2 | L94: 110 | M94: 20 | N94: 209 | O94: 441 | P94: 498 | Q94: 47080 | R94: =IFERROR(M94*30/(N94*7),0) -> 0.4101162 | S94: 49 | T94: =IFERROR(S94*30/N94,0) -> 7.0334928 | U94: FULL | V94: 20 | W94: 4.7 | X94: 0.0522 | Y94: 46041 | Z94: 更早 | AB94: 0.64566929 | AC94: 18.6 cm | AD94: 8.8 cm | AE94: 7.4 cm | AF94: 0.24 kg | AG94: 在售 | AH94: https://articulo.mercadolibre.com.mx/MLM-4683918834-2-pack-modernas-lampara-de-pared-led-recargableinteligente-_JM | AI94: Hogar, Muebles y Jardín(家居、家具和花园) -> Iluminación para el Hogar(家居照明) -> Lámparas(灯具) -> Lámparas de Pared(壁灯) | AJ94: 1
A95: 92 | B95: MLM2535655985 | C95: 20cmcon Sensor Movimiento Luz De Led Clóset Usb 5 Piezas | D95: 邻近：橱柜/衣柜灯 | E95: 100–149 | F95: Try Me | G95: try me | H95: OSASKUFHBED | I95: 本土店 | J95: 139 | K95: 5 | L95: 27.8 | M95: 62 | N95: 206 | O95: 386 | P95: 992 | Q95: 28634 | R95: =IFERROR(M95*30/(N95*7),0) -> 1.2898752 | S95: 438 | T95: =IFERROR(S95*30/N95,0) -> 63.786408 | U95: FULL | V95: 114 | W95: 4.6 | X95: 0.0979 | Y95: 45961 | Z95: 更早 | AB95: 0.49275362 | AC95: 27.6 cm | AD95: 12.8 cm | AE95: 2.6 cm | AF95: 0.4 kg | AG95: 在售 | AH95: https://articulo.mercadolibre.com.mx/MLM-2535655985-20cmcon-sensor-movimiento-luz-de-led-closet-usb-5-piezas-_JM | AI95: Hogar, Muebles y Jardín(家居、家具和花园) -> Iluminación para el Hogar(家居照明) -> Lámparas(灯具) -> Lámparas de Pared(壁灯) | AJ95: 0
A96: 93 | B96: MLM2824263577 | C96: Vanance® Lámpara De Pared Giratoria Multiforma Lampara Led Con Reloj Usb Recargable Ajustable Con Táctil Y Remoto 3 Modos Luz Cálida Blanca Neutra Luz De Led Clóset Blanco | D96: 邻近：橱柜/衣柜灯 | E96: 100–149 | F96: Vanance | G96: vanance | H96: VANANCE | I96: 本土店 | J96: 148.5 | K96: 1 | L96: 148.5 | M96: 49 | N96: 205 | O96: 635 | P96: 972 | Q96: 30442.5 | R96: =IFERROR(M96*30/(N96*7),0) -> 1.0243902 | S96: 189 | T96: =IFERROR(S96*30/N96,0) -> 27.658537 | U96: FULL | V96: 177 | W96: 4.7 | X96: 0.0355 | Y96: 46108 | Z96: 91–180天 | AA96: 18 | AB96: -0.11637931 | AC96: 30.6 cm | AD96: 5.6 cm | AE96: 4.8 cm | AF96: 0.2 kg | AG96: 在售 | AH96: https://articulo.mercadolibre.com.mx/MLM-2824263577-vanance-lampara-de-pared-giratoria-multiforma-lampara-led-con-reloj-usb-recargable-ajustable-con-tactil-y-remoto-3-modos-luz-calida-blanca-neutra-luz-de-led-closet-blanco-_JM | AI96: Hogar, Muebles y Jardín(家居、家具和花园) -> Iluminación para el Hogar(家居照明) -> Lámparas(灯具) -> Lámparas de Pared(壁灯) | AJ96: 0
A97: 94 | B97: MLM5461697990 | C97: 12w Luz De Pared Luz Arbotante Led Pared Uso Exterior 3000k Estructura Negro Luz Blanca | D97: 有线户外/通用壁灯 | E97: 100–149 | F97: Lámpara Pared Led | G97: lampara pared led | H97: LEIKETECHNOLOGYLEIKETECHNOLO | I97: 本土店 | J97: 144 | K97: 1 | L97: 144 | M97: 121 | N97: 203 | O97: 655 | P97: 793 | Q97: 29232 | R97: =IFERROR(M97*30/(N97*7),0) -> 2.5545391 | S97: 103 | T97: =IFERROR(S97*30/N97,0) -> 15.221675 | U97: FULL | V97: 866 | W97: 4.5 | X97: 0.1168 | Y97: 46179 | Z97: 91–180天 | AA97: 11 | AB97: 0.63709677 | AC97: 13.2 cm | AD97: 11.6 cm | AE97: 5.6 cm | AF97: 0.36 kg | AG97: 在售 | AH97: https://articulo.mercadolibre.com.mx/MLM-5461697990-12w-luz-de-pared-luz-arbotante-led-pared-uso-exterior-3000k-estructura-negro-luz-blanca-_JM | AI97: Hogar, Muebles y Jardín(家居、家具和花园) -> Iluminación para el Hogar(家居照明) -> Lámparas(灯具) -> Lámparas de Pared(壁灯) | AJ97: 1
A98: 95 | B98: MLM2295917709 | C98: Lámparas De Pared Exterior Lámparas Decorativas Modernas | D98: 有线户外/通用壁灯 | E98: 200–299 | F98: Luminicola | G98: luminicola | H98: CNLUMINICOLAMXF | I98: 跨境店 | J98: 280.52 | K98: 1 | L98: 280.52 | M98: 54 | N98: 199 | O98: 528 | P98: 1536 | Q98: 58067.64 | R98: =IFERROR(M98*30/(N98*7),0) -> 1.1629576 | S98: 4 | T98: =IFERROR(S98*30/N98,0) -> 0.60301508 | U98: FULL | V98: 64 | W98: 4.8 | X98: 0.0599 | Y98: 45776 | Z98: 更早 | AB98: 0.099447514 | AC98: 40.2 cm | AD98: 16.8 cm | AE98: 10.6 cm | AF98: 0.95 kg | AG98: 在售 | AH98: https://articulo.mercadolibre.com.mx/MLM-2295917709-lamparas-de-pared-exterior-lamparas-decorativas-modernas-_JM | AI98: Hogar, Muebles y Jardín(家居、家具和花园) -> Iluminación para el Hogar(家居照明) -> Lámparas(灯具) -> Lámparas de Pared(壁灯) | AJ98: 1
A99: 96 | B99: MLM3140818875 | C99: Aplique De Pared Led Moderno Para Interior | D99: 室内装饰壁灯 | E99: 150–199 | F99: Pcmos | G99: pcmos | H99: PCMOS SHOP | I99: 跨境店 | J99: 192.75 | K99: 1 | L99: 192.75 | M99: 67 | N99: 192 | O99: 494 | P99: 494 | Q99: 37008 | R99: =IFERROR(M99*30/(N99*7),0) -> 1.4955357 | S99: 66 | T99: =IFERROR(S99*30/N99,0) -> 10.3125 | U99: FULL | V99: 15 | W99: 4.7 | X99: 0.0303 | Y99: 46219 | Z99: 近90天上架 | AB99: -0.36842105 | AC99: 42.5 cm | AD99: 12.9 cm | AE99: 8.5 cm | AF99: 0.4 kg | AG99: 在售 | AH99: https://articulo.mercadolibre.com.mx/MLM-3140818875-aplique-de-pared-led-moderno-para-interior-_JM | AI99: Hogar, Muebles y Jardín(家居、家具和花园) -> Iluminación para el Hogar(家居照明) -> Lámparas(灯具) -> Lámparas de Pared(壁灯) | AJ99: 1
A100: 97 | B100: MLM5129764298 | C100: Vanance® Lámpara De Pared Giratoria Multiforma Lampara Led Recargable Ajustable Interior Con Táctil Y Remoto 3 Modos Luz Cálida Blanca Neutra Luz De Led Clóset Usb Blanco | D100: 邻近：橱柜/衣柜灯 | E100: 100–149 | F100: Vanance | G100: vanance | H100: VANANCE | I100: 本土店 | J100: 118.9 | K100: 1 | L100: 118.9 | M100: 38 | N100: 192 | O100: 427 | P100: 555 | Q100: 23542.2 | R100: =IFERROR(M100*30/(N100*7),0) -> 0.84821429 | S100: 164 | T100: =IFERROR(S100*30/N100,0) -> 25.625 | U100: FULL | V100: 127 | W100: 4.7 | X100: 0.0451 | Y100: 46116 | Z100: 91–180天 | AA100: 11 | AB100: 0.5483871 | AC100: 31 cm | AD100: 5.4 cm | AE100: 5.6 cm | AF100: 0.2 kg | AG100: 在售 | AH100: https://articulo.mercadolibre.com.mx/MLM-5129764298-vanance-lampara-de-pared-giratoria-multiforma-lampara-led-recargable-ajustable-interior-con-tactil-y-remoto-3-modos-luz-calida-blanca-neutra-luz-de-led-closet-usb-blanco-_JM | AI100: Hogar, Muebles y Jardín(家居、家具和花园) -> Iluminación para el Hogar(家居照明) -> Lámparas(灯具) -> Lámparas de Pared(壁灯) | AJ100: 0
...
