Workbook

Sheet 项目封面
J1: 德国切菜板实战市场调研
J4: 德文关键词 | L4: schneidebrett / schneidebrett holz | O4: 调研时间 | Q4: 2026-09-10 | T4: 类目编号 | V4: 3177921031
J9: 阅读说明
J12: 本次填入：竞争格局、CPC（每次点击竞价）预估、自然流量，以及砧板榜单100款明细。 类目：Hackbretter（砧板），节点3177921031。切菜板、木制切菜板关键词样本分别展示，不与类目榜单混算。 子体订单量“1,000+”保留原显示；自然流量是关键词样本内份额，不等于自然订单比例。 13张“模拟_”业务表全部保留原输入和公式，各套售价、佣金及推广目标分别保留。推广计划源表已有26处公式错误，尚未修改。 无关案例数据和图片已清除，未开展部分保留空白模板。

Sheet ①市场背景调查
A1: 德国站切菜板 Hackbretter｜市场背景调查
A2: 1.宏观分析 | V2: 【总结】 2026年1—8月销量43.11万件，同比增长35.47%；销售额€898.48万，同比增长40.82%。 2025年第四季度贡献全年32.91%的销量。 2026年8月第三方销量占68.69%，自营28.98%。 【趋势表明】 需求增长、年末放量明显。按日期核验的12款新品月销2,529件，前三款贡献60.02%；有新品成交机会，但集中于少数款。 | AA2: 2026年较2025年｜固定样本销量 | AI2: 2025年较2024年｜固定样本销量
AA4: 月份 | AB4: 2025 已知销量 | AC4: 2026 已知销量 | AD4: 2025 配对销量 | AE4: 2026 配对销量 | AF4: 配对父体数 | AG4: 配对同比 | AI4: 月份 | AJ4: 2024 已知销量 | AK4: 2025 已知销量 | AL4: 2024 配对销量 | AM4: 2025 配对销量 | AN4: 配对父体数 | AO4: 配对同比
AA5: 1 | AB5: =SUM(J772:J871) -> 19056 | AC5: =SUM(V772:V871) -> 44072 | AD5: =SUM(J772,J776,J777,J778,J779,J780,J781,J782,J784,J786,J790,J792,J793,J794,J798,J800,J801,J804,J810,J813,J814,J816,J818,J819,J820,J822,J823,J825,J827,J830,J833,J834,J837,J840,J841,J842,J848,J852,J853,J855,J856,J857,J859,J863,J868,J869,J871) -> 19056 | AE5: =SUM(V772,V776,V777,V778,V779,V780,V781,V782,V784,V786,V790,V792,V793,V794,V798,V800,V801,V804,V810,V813,V814,V816,V818,V819,V820,V822,V823,V825,V827,V830,V833,V834,V837,V840,V841,V842,V848,V852,V853,V855,V856,V857,V859,V863,V868,V869,V871) -> 30709 | AF5: 47 | AG5: =AE5/AD5-1 -> 0.61151343 | AI5: 1 | AJ5: 缺数据 | AK5: =SUM(J772:J871) -> 19056 | AL5: 缺数据 | AM5: 缺数据 | AN5: 缺数据 | AO5: 缺数据
AA6: 2 | AB6: =SUM(K772:K871) -> 18616 | AC6: =SUM(W772:W871) -> 40545 | AD6: =SUM(K772,K776,K777,K778,K779,K780,K781,K782,K784,K785,K786,K790,K792,K793,K794,K798,K800,K801,K807,K809,K810,K813,K814,K816,K817,K818,K819,K820,K822,K823,K824,K825,K827,K830,K833,K834,K837,K840,K841,K842,K848,K849,K852,K853,K855,K856,K857,K859,K862,K863,K866,K868,K869) -> 18616 | AE6: =SUM(W772,W776,W777,W778,W779,W780,W781,W782,W784,W785,W786,W790,W792,W793,W794,W798,W800,W801,W807,W809,W810,W813,W814,W816,W817,W818,W819,W820,W822,W823,W824,W825,W827,W830,W833,W834,W837,W840,W841,W842,W848,W849,W852,W853,W855,W856,W857,W859,W862,W863,W866,W868,W869) -> 31513 | AF6: 53 | AG6: =AE6/AD6-1 -> 0.69279115 | AI6: 2 | AJ6: 缺数据 | AK6: =SUM(K772:K871) -> 18616 | AL6: 缺数据 | AM6: 缺数据 | AN6: 缺数据 | AO6: 缺数据
AA7: 3 | AB7: =SUM(L772:L871) -> 21515 | AC7: =SUM(X772:X871) -> 40468 | AD7: =SUM(L772,L776,L777,L778,L779,L780,L782,L784,L785,L786,L789,L790,L792,L793,L794,L798,L800,L801,L807,L809,L810,L813,L814,L816,L817,L818,L819,L820,L822,L823,L824,L825,L827,L830,L833,L834,L837,L840,L841,L842,L848,L852,L853,L855,L856,L857,L859,L862,L863,L866,L868,L869,L871) -> 21515 | AE7: =SUM(X772,X776,X777,X778,X779,X780,X782,X784,X785,X786,X789,X790,X792,X793,X794,X798,X800,X801,X807,X809,X810,X813,X814,X816,X817,X818,X819,X820,X822,X823,X824,X825,X827,X830,X833,X834,X837,X840,X841,X842,X848,X852,X853,X855,X856,X857,X859,X862,X863,X866,X868,X869,X871) -> 30960 | AF7: 53 | AG7: =AE7/AD7-1 -> 0.43899605 | AI7: 3 | AJ7: 缺数据 | AK7: =SUM(L772:L871) -> 21515 | AL7: 缺数据 | AM7: 缺数据 | AN7: 缺数据 | AO7: 缺数据
AA8: 4 | AB8: =SUM(M772:M871) -> 20379 | AC8: =SUM(Y772:Y871) -> 39223 | AD8: =SUM(M776,M777,M778,M779,M780,M781,M782,M784,M785,M786,M789,M790,M792,M793,M794,M798,M800,M801,M807,M809,M810,M813,M814,M816,M817,M818,M819,M820,M822,M823,M824,M825,M827,M828,M830,M833,M834,M837,M840,M841,M842,M849,M852,M853,M855,M856,M857,M859,M860,M862,M863,M866,M868,M869,M871) -> 20379 | AE8: =SUM(Y776,Y777,Y778,Y779,Y780,Y781,Y782,Y784,Y785,Y786,Y789,Y790,Y792,Y793,Y794,Y798,Y800,Y801,Y807,Y809,Y810,Y813,Y814,Y816,Y817,Y818,Y819,Y820,Y822,Y823,Y824,Y825,Y827,Y828,Y830,Y833,Y834,Y837,Y840,Y841,Y842,Y849,Y852,Y853,Y855,Y856,Y857,Y859,Y860,Y862,Y863,Y866,Y868,Y869,Y871) -> 30493 | AF8: 55 | AG8: =AE8/AD8-1 -> 0.49629521 | AI8: 4 | AJ8: 缺数据 | AK8: =SUM(M772:M871) -> 20379 | AL8: 缺数据 | AM8: 缺数据 | AN8: 缺数据 | AO8: 缺数据
AA9: 5 | AB9: =SUM(N772:N871) -> 26972 | AC9: =SUM(Z772:Z871) -> 45879 | AD9: =SUM(N776,N777,N778,N779,N780,N781,N782,N784,N785,N786,N787,N789,N790,N792,N793,N794,N798,N800,N801,N802,N807,N809,N810,N811,N813,N814,N816,N817,N818,N819,N820,N822,N823,N824,N825,N827,N828,N830,N833,N834,N837,N840,N841,N842,N848,N849,N852,N853,N855,N856,N857,N859,N860,N862,N863,N866,N867,N868,N869,N871) -> 26972 | AE9: =SUM(Z776,Z777,Z778,Z779,Z780,Z781,Z782,Z784,Z785,Z786,Z787,Z789,Z790,Z792,Z793,Z794,Z798,Z800,Z801,Z802,Z807,Z809,Z810,Z811,Z813,Z814,Z816,Z817,Z818,Z819,Z820,Z822,Z823,Z824,Z825,Z827,Z828,Z830,Z833,Z834,Z837,Z840,Z841,Z842,Z848,Z849,Z852,Z853,Z855,Z856,Z857,Z859,Z860,Z862,Z863,Z866,Z867,Z868,Z869,Z871) -> 36503 | AF9: 60 | AG9: =AE9/AD9-1 -> 0.35336645 | AI9: 5 | AJ9: 缺数据 | AK9: =SUM(N772:N871) -> 26972 | AL9: 缺数据 | AM9: 缺数据 | AN9: 缺数据 | AO9: 缺数据
AA10: 6 | AB10: =SUM(O772:O871) -> 20510 | AC10: =SUM(AA772:AA871) -> 45455 | AD10: =SUM(O772,O776,O777,O778,O779,O780,O781,O782,O784,O785,O786,O787,O789,O790,O792,O793,O794,O798,O800,O801,O802,O804,O807,O809,O810,O811,O813,O814,O816,O817,O818,O819,O820,O822,O823,O824,O825,O827,O828,O829,O830,O832,O833,O834,O837,O840,O841,O842,O843,O848,O849,O852,O853,O855,O856,O857,O859,O860,O862,O863,O866,O867,O868,O869,O871) -> 20510 | AE10: =SUM(AA772,AA776,AA777,AA778,AA779,AA780,AA781,AA782,AA784,AA785,AA786,AA787,AA789,AA790,AA792,AA793,AA794,AA798,AA800,AA801,AA802,AA804,AA807,AA809,AA810,AA811,AA813,AA814,AA816,AA817,AA818,AA819,AA820,AA822,AA823,AA824,AA825,AA827,AA828,AA829,AA830,AA832,AA833,AA834,AA837,AA840,AA841,AA842,AA843,AA848,AA849,AA852,AA853,AA855,AA856,AA857,AA859,AA860,AA862,AA863,AA866,AA867,AA868,AA869,AA871) -> 36457 | AF10: 65 | AG10: =AE10/AD10-1 -> 0.77752316 | AI10: 6 | AJ10: =SUM(C772:C871) -> 10880 | AK10: =SUM(O772:O871) -> 20510 | AL10: =SUM(C772,C776,C777,C778,C779,C780,C782,C784,C786,C792,C793,C794,C798,C800,C801,C813,C814,C816,C819,C820,C822,C823,C825,C827,C828,C830,C834,C837,C840,C841,C842,C848,C849,C852,C853,C855,C856,C857,C859) -> 10880 | AM10: =SUM(O772,O776,O777,O778,O779,O780,O782,O784,O786,O792,O793,O794,O798,O800,O801,O813,O814,O816,O819,O820,O822,O823,O825,O827,O828,O830,O834,O837,O840,O841,O842,O848,O849,O852,O853,O855,O856,O857,O859) -> 15247 | AN10: 39 | AO10: =AM10/AL10-1 -> 0.40137868
AA11: 7 | AB11: =SUM(P772:P871) -> 28857 | AC11: =SUM(AB772:AB871) -> 40513 | AD11: =SUM(P772,P776,P777,P778,P779,P780,P781,P782,P784,P785,P786,P787,P789,P790,P792,P793,P794,P798,P800,P801,P802,P804,P807,P809,P810,P811,P813,P814,P816,P817,P818,P819,P820,P822,P823,P824,P825,P827,P828,P829,P830,P832,P833,P834,P837,P838,P840,P841,P842,P843,P848,P849,P852,P853,P855,P856,P857,P859,P860,P862,P863,P866,P867,P868,P869,P871) -> 28857 | AE11: =SUM(AB772,AB776,AB777,AB778,AB779,AB780,AB781,AB782,AB784,AB785,AB786,AB787,AB789,AB790,AB792,AB793,AB794,AB798,AB800,AB801,AB802,AB804,AB807,AB809,AB810,AB811,AB813,AB814,AB816,AB817,AB818,AB819,AB820,AB822,AB823,AB824,AB825,AB827,AB828,AB829,AB830,AB832,AB833,AB834,AB837,AB838,AB840,AB841,AB842,AB843,AB848,AB849,AB852,AB853,AB855,AB856,AB857,AB859,AB860,AB862,AB863,AB866,AB867,AB868,AB869,AB871) -> 33719 | AF11: 66 | AG11: =AE11/AD11-1 -> 0.16848598 | AI11: 7 | AJ11: =SUM(D772:D871) -> 16308 | AK11: =SUM(P772:P871) -> 28857 | AL11: =SUM(D772,D776,D777,D778,D779,D780,D782,D784,D786,D792,D793,D794,D798,D800,D801,D813,D814,D816,D819,D820,D822,D823,D825,D827,D828,D830,D833,D834,D837,D840,D841,D842,D848,D849,D852,D853,D855,D856,D857,D859,D868) -> 16308 | AM11: =SUM(P772,P776,P777,P778,P779,P780,P782,P784,P786,P792,P793,P794,P798,P800,P801,P813,P814,P816,P819,P820,P822,P823,P825,P827,P828,P830,P833,P834,P837,P840,P841,P842,P848,P849,P852,P853,P855,P856,P857,P859,P868) -> 23075 | AN11: 41 | AO11: =AM11/AL11-1 -> 0.41494972
AA12: 8 | AB12: =SUM(Q772:Q871) -> 25245 | AC12: =SUM(AC772:AC871) -> 55240 | AD12: =SUM(Q772,Q774,Q776,Q777,Q778,Q779,Q780,Q781,Q782,Q784,Q785,Q786,Q787,Q789,Q790,Q792,Q793,Q794,Q798,Q800,Q801,Q802,Q804,Q807,Q809,Q810,Q811,Q812,Q813,Q814,Q816,Q817,Q818,Q819,Q820,Q822,Q823,Q824,Q825,Q827,Q828,Q829,Q830,Q832,Q833,Q834,Q837,Q838,Q840,Q841,Q842,Q843,Q848,Q849,Q852,Q853,Q855,Q856,Q857,Q859,Q860,Q862,Q863,Q866,Q867,Q868,Q869,Q871) -> 25245 | AE12: =SUM(AC772,AC774,AC776,AC777,AC778,AC779,AC780,AC781,AC782,AC784,AC785,AC786,AC787,AC789,AC790,AC792,AC793,AC794,AC798,AC800,AC801,AC802,AC804,AC807,AC809,AC810,AC811,AC812,AC813,AC814,AC816,AC817,AC818,AC819,AC820,AC822,AC823,AC824,AC825,AC827,AC828,AC829,AC830,AC832,AC833,AC834,AC837,AC838,AC840,AC841,AC842,AC843,AC848,AC849,AC852,AC853,AC855,AC856,AC857,AC859,AC860,AC862,AC863,AC866,AC867,AC868,AC869,AC871) -> 43783 | AF12: 68 | AG12: =AE12/AD12-1 -> 0.73432363 | AI12: 8 | AJ12: =SUM(E772:E871) -> 16301 | AK12: =SUM(Q772:Q871) -> 25245 | AL12: =SUM(E772,E776,E777,E778,E779,E780,E782,E784,E786,E792,E793,E794,E798,E800,E801,E813,E814,E816,E819,E820,E822,E823,E825,E827,E828,E830,E834,E837,E840,E842,E848,E852,E853,E855,E856,E857,E859,E868) -> 16301 | AM12: =SUM(Q772,Q776,Q777,Q778,Q779,Q780,Q782,Q784,Q786,Q792,Q793,Q794,Q798,Q800,Q801,Q813,Q814,Q816,Q819,Q820,Q822,Q823,Q825,Q827,Q828,Q830,Q834,Q837,Q840,Q842,Q848,Q852,Q853,Q855,Q856,Q857,Q859,Q868) -> 17340 | AN12: 38 | AO12: =AM12/AL12-1 -> 0.063738421
AA13: 9 | AB13: =SUM(R772:R871) -> 24913 | AI13: 9 | AJ13: =SUM(F772:F871) -> 13575 | AK13: =SUM(R772:R871) -> 24913 | AL13: =SUM(F772,F776,F777,F778,F779,F780,F781,F782,F784,F786,F792,F793,F794,F798,F800,F801,F813,F814,F816,F819,F822,F823,F825,F827,F828,F830,F833,F834,F837,F840,F841,F842,F852,F853,F855,F856,F857,F859,F868,F869) -> 13575 | AM13: =SUM(R772,R776,R777,R778,R779,R780,R781,R782,R784,R786,R792,R793,R794,R798,R800,R801,R813,R814,R816,R819,R822,R823,R825,R827,R828,R830,R833,R834,R837,R840,R841,R842,R852,R853,R855,R856,R857,R859,R868,R869) -> 18122 | AN13: 40 | AO13: =AM13/AL13-1 -> 0.33495396
AA14: 10 | AB14: =SUM(S772:S871) -> 30380 | AI14: 10 | AJ14: =SUM(G772:G871) -> 18563 | AK14: =SUM(S772:S871) -> 30380 | AL14: =SUM(G772,G776,G777,G778,G779,G780,G781,G782,G784,G786,G792,G793,G794,G798,G800,G801,G813,G814,G816,G819,G820,G822,G823,G825,G827,G828,G830,G833,G834,G837,G840,G841,G842,G848,G852,G853,G855,G856,G857,G859,G868,G869) -> 18563 | AM14: =SUM(S772,S776,S777,S778,S779,S780,S781,S782,S784,S786,S792,S793,S794,S798,S800,S801,S813,S814,S816,S819,S820,S822,S823,S825,S827,S828,S830,S833,S834,S837,S840,S841,S842,S848,S852,S853,S855,S856,S857,S859,S868,S869) -> 21599 | AN14: 42 | AO14: =AM14/AL14-1 -> 0.16355115
AA15: 11 | AB15: =SUM(T772:T871) -> 44117 | AI15: 11 | AJ15: =SUM(H772:H871) -> 24356 | AK15: =SUM(T772:T871) -> 44117 | AL15: =SUM(H772,H776,H777,H778,H779,H780,H781,H782,H784,H786,H790,H792,H793,H794,H798,H800,H801,H804,H813,H814,H816,H819,H820,H822,H823,H825,H827,H828,H830,H833,H834,H837,H840,H841,H842,H848,H852,H853,H856,H857,H859,H868,H869) -> 24356 | AM15: =SUM(T772,T776,T777,T778,T779,T780,T781,T782,T784,T786,T790,T792,T793,T794,T798,T800,T801,T804,T813,T814,T816,T819,T820,T822,T823,T825,T827,T828,T830,T833,T834,T837,T840,T841,T842,T848,T852,T853,T856,T857,T859,T868,T869) -> 31781 | AN15: 43 | AO15: =AM15/AL15-1 -> 0.30485301
AA16: 12 | AB16: =SUM(U772:U871) -> 59834 | AI16: 12 | AJ16: =SUM(I772:I871) -> 27524 | AK16: =SUM(U772:U871) -> 59834 | AL16: =SUM(I772,I776,I777,I778,I779,I780,I781,I782,I784,I786,I790,I792,I793,I794,I798,I800,I801,I804,I810,I813,I814,I816,I818,I819,I820,I822,I823,I825,I827,I830,I833,I834,I837,I840,I841,I842,I848,I852,I853,I856,I857,I859,I868,I869,I871) -> 27524 | AM16: =SUM(U772,U776,U777,U778,U779,U780,U781,U782,U784,U786,U790,U792,U793,U794,U798,U800,U801,U804,U810,U813,U814,U816,U818,U819,U820,U822,U823,U825,U827,U830,U833,U834,U837,U840,U841,U842,U848,U852,U853,U856,U857,U859,U868,U869,U871) -> 42330 | AN16: 45 | AO16: =AM16/AL16-1 -> 0.53793053
AA18: 已知销量：该月100个固定父体中全部有值记录合计；两表2025同月数值一致。配对销量：仅两年同月都有值的父体，用于同比。2026仅列1—8月完整月。 | AI18: 已知销量：该月100个固定父体中全部有值记录合计；两表2025同月数值一致。配对销量：仅两年同月都有值的父体，用于同比。2024年1—5月缺失，不算全年同比。
A22: 2.行业分析&市场大盘分析 | V22: 【竞争结构】 9月10日已验证图保留：前三品牌销量占30.00%，前三卖家占46.89%，自营销量占34.55%。品牌集中度低于卖家，不能只看品牌分散就判断进入容易。 卖家地区销量份额：德国50.45%、中国30.23%、英国10.78%；这描述供给方，不是买家画像。 9月11日当前100款快照：前20销量占57.13%，尾部80款占42.87%；新品分析卡8款与日期明细12款不一致。按日期核验的12款月销2,529件，前三款贡献60.02%，不能用分析卡概括全部新品。 【历史口径】 卖家/配送与新品销量历史：自然月每天进入Top100的商品汇总，不是某日固定100款；与当前快照不交叉计算。 历史自营占比已确认是商品数量占比。12个月自营及第三方销量份额见A490，年龄销量份额见A512。前20历史系数的销量/金额口径仍待确认。 上架年龄分布为插件原分组；“3个月新品”不自行改称精确90天。 【产业链｜待补】 缺切菜板材料供给、产区及供应商证据。 右侧销售额补表使用9月11日独立100款数据，与左侧9月10日图分日期展示。
AB23: “目前我不会直接判断能做。大盘需求是增长的，今年1—8月销量同比增长35%左右，而且Q4有明显旺季，说明需求端没问题。但我比较关注新品表现，新品占8%，销量只占3%左右，说明增长不一定代表新品容易进入。另外TOP20已经拿走57%的销量，有一定头部效应。所以我下一步会重点看头部产品为什么卖得好、新品为什么占比低，以及我们的SKU在材质、场景、功能和差评痛点上有没有明确差异化。如果能找到可打的产品机会，再判断值得开发。”
A24: Hackbretter｜市场销售额历史 | J24: 第三方／自营销售结构｜销量历史
A38: 来源：9月11日Sorftime网页。2026年9月未结束；首月窗口完整性待确认。 | J38: 纵轴为件数；自然月每日上榜商品汇总。销售额结构仍待补。
A40: 第三方逐月销量趋势（件） | J40: Amazon自营逐月销量趋势（件）
AA51: 9月11日100款快照。预估销售额占比＝该组已知销售额÷样本已知销售额；3款金额缺失。左图为9月10日销量口径。
AA54: 品牌 | AB54: 商品数 | AC54: 月销量 | AD54: 月销售额€ | AE54: 预估销售额占比 | AG54: 卖家 | AH54: 商品数 | AI54: 月销量 | AJ54: 月销售额€ | AK54: 预估销售额占比
A55: 第三方固定样本74个父体。按9月3日卖家类型固定分组；非各月真实卖家身份。缺值不作零，9月未完整不展示。与上方Sorftime商品池不同，不能据此计算销售单价。 | J55: Amazon自营固定样本25个父体。按9月3日卖家类型固定分组；非各月真实卖家身份。缺值不作零，9月未完整不展示。与上方Sorftime商品池不同，不能据此计算销售单价。
A56: =_xlfn.DISPIMG("ID_DDBF4758CE894FF29B68EE54D39B2F47",1) -> =DISPIMG("ID_DDBF4758CE894FF29B68EE54D39B2F47",1) | AA56: Deer & Oak | AB56: =COUNTIF($B$234:$B$333,AA56) -> 3 | AC56: =SUMIF($B$234:$B$333,AA56,$E$234:$E$333) -> 3640 | AD56: =SUMIF($B$234:$B$333,AA56,$F$234:$F$333) -> 69796.08 | AE56: =AD56/$F$334 -> 0.070616096 | AG56: Amazon | AH56: =COUNTIF($C$234:$C$333,AG56) -> 21 | AI56: =SUMIF($C$234:$C$333,AG56,$E$234:$E$333) -> 15471 | AJ56: =SUMIF($C$234:$C$333,AG56,$F$234:$F$333) -> 231956.27 | AK56: =AJ56/$F$334 -> 0.23468146
AA57: WMF | AB57: =COUNTIF($B$234:$B$333,AA57) -> 2 | AC57: =SUMIF($B$234:$B$333,AA57,$E$234:$E$333) -> 2092 | AD57: =SUMIF($B$234:$B$333,AA57,$F$234:$F$333) -> 68158.58 | AE57: =AD57/$F$334 -> 0.068959357 | AG57: Great Ideas | AH57: =COUNTIF($C$234:$C$333,AG57) -> 3 | AI57: =SUMIF($C$234:$C$333,AG57,$E$234:$E$333) -> 3640 | AJ57: =SUMIF($C$234:$C$333,AG57,$F$234:$F$333) -> 69796.08 | AK57: =AJ57/$F$334 -> 0.070616096
AA58: MUVELL | AB58: =COUNTIF($B$234:$B$333,AA58) -> 1 | AC58: =SUMIF($B$234:$B$333,AA58,$E$234:$E$333) -> 1514 | AD58: =SUMIF($B$234:$B$333,AA58,$F$234:$F$333) -> 60484.3 | AE58: =AD58/$F$334 -> 0.061194914 | AG58: Gastro Service Profis | AH58: =COUNTIF($C$234:$C$333,AG58) -> 1 | AI58: =SUMIF($C$234:$C$333,AG58,$E$234:$E$333) -> 1514 | AJ58: =SUMIF($C$234:$C$333,AG58,$F$234:$F$333) -> 60484.3 | AK58: =AJ58/$F$334 -> 0.061194914
AA59: Culiex | AB59: =COUNTIF($B$234:$B$333,AA59) -> 2 | AC59: =SUMIF($B$234:$B$333,AA59,$E$234:$E$333) -> 1680 | AD59: =SUMIF($B$234:$B$333,AA59,$F$234:$F$333) -> 53211.13 | AE59: =AD59/$F$334 -> 0.053836294 | AG59: Culiex Direct | AH59: =COUNTIF($C$234:$C$333,AG59) -> 1 | AI59: =SUMIF($C$234:$C$333,AG59,$E$234:$E$333) -> 887 | AJ59: =SUMIF($C$234:$C$333,AG59,$F$234:$F$333) -> 53211.13 | AK59: =AJ59/$F$334 -> 0.053836294
AA60: Kesper | AB60: =COUNTIF($B$234:$B$333,AA60) -> 6 | AC60: =SUMIF($B$234:$B$333,AA60,$E$234:$E$333) -> 6992 | AD60: =SUMIF($B$234:$B$333,AA60,$F$234:$F$333) -> 47232.95 | AE60: =AD60/$F$334 -> 0.047787878 | AG60: Bestcook DE | AH60: =COUNTIF($C$234:$C$333,AG60) -> 5 | AI60: =SUMIF($C$234:$C$333,AG60,$E$234:$E$333) -> 1193 | AJ60: =SUMIF($C$234:$C$333,AG60,$F$234:$F$333) -> 46680.07 | AK60: =AJ60/$F$334 -> 0.047228502
AA61: BESTCOOK | AB61: =COUNTIF($B$234:$B$333,AA61) -> 5 | AC61: =SUMIF($B$234:$B$333,AA61,$E$234:$E$333) -> 1193 | AD61: =SUMIF($B$234:$B$333,AA61,$F$234:$F$333) -> 46680.07 | AE61: =AD61/$F$334 -> 0.047228502 | AG61: Everbrent | AH61: =COUNTIF($C$234:$C$333,AG61) -> 3 | AI61: =SUMIF($C$234:$C$333,AG61,$E$234:$E$333) -> 2618 | AJ61: =SUMIF($C$234:$C$333,AG61,$F$234:$F$333) -> 43758.82 | AK61: =AJ61/$F$334 -> 0.044272931
AA62: Blumtal | AB62: =COUNTIF($B$234:$B$333,AA62) -> 3 | AC62: =SUMIF($B$234:$B$333,AA62,$E$234:$E$333) -> 2618 | AD62: =SUMIF($B$234:$B$333,AA62,$F$234:$F$333) -> 43758.82 | AE62: =AD62/$F$334 -> 0.044272931 | AG62: ACESELF-EU | AH62: =COUNTIF($C$234:$C$333,AG62) -> 1 | AI62: =SUMIF($C$234:$C$333,AG62,$E$234:$E$333) -> 824 | AJ62: =SUMIF($C$234:$C$333,AG62,$F$234:$F$333) -> 37895.76 | AK62: =AJ62/$F$334 -> 0.038340987
AA63: Aceselfㅤㅤㅤㅤㅤ | AB63: =COUNTIF($B$234:$B$333,AA63) -> 1 | AC63: =SUMIF($B$234:$B$333,AA63,$E$234:$E$333) -> 824 | AD63: =SUMIF($B$234:$B$333,AA63,$F$234:$F$333) -> 37895.76 | AE63: =AD63/$F$334 -> 0.038340987 | AG63: MOQIULI | AH63: =COUNTIF($C$234:$C$333,AG63) -> 4 | AI63: =SUMIF($C$234:$C$333,AG63,$E$234:$E$333) -> 2178 | AJ63: =SUMIF($C$234:$C$333,AG63,$F$234:$F$333) -> 36448.77 | AK63: =AJ63/$F$334 -> 0.036876997
A64: =_xlfn.DISPIMG("ID_C610484858B34BD29F18685F9AF88DA2",1) -> =DISPIMG("ID_C610484858B34BD29F18685F9AF88DA2",1) | AA64: KIKIIKE | AB64: =COUNTIF($B$234:$B$333,AA64) -> 2 | AC64: =SUMIF($B$234:$B$333,AA64,$E$234:$E$333) -> 1054 | AD64: =SUMIF($B$234:$B$333,AA64,$F$234:$F$333) -> 29855.46 | AE64: =AD64/$F$334 -> 0.030206224 | AG64: KIKIIKE-INC | AH64: =COUNTIF($C$234:$C$333,AG64) -> 2 | AI64: =SUMIF($C$234:$C$333,AG64,$E$234:$E$333) -> 1054 | AJ64: =SUMIF($C$234:$C$333,AG64,$F$234:$F$333) -> 29855.46 | AK64: =AJ64/$F$334 -> 0.030206224
AA65: Giftasy | AB65: =COUNTIF($B$234:$B$333,AA65) -> 3 | AC65: =SUMIF($B$234:$B$333,AA65,$E$234:$E$333) -> 1896 | AD65: =SUMIF($B$234:$B$333,AA65,$F$234:$F$333) -> 29683.59 | AE65: =AD65/$F$334 -> 0.030032335 | AG65: Gintan DE | AH65: =COUNTIF($C$234:$C$333,AG65) -> 1 | AI65: =SUMIF($C$234:$C$333,AG65,$E$234:$E$333) -> 1032 | AJ65: =SUMIF($C$234:$C$333,AG65,$F$234:$F$333) -> 23674.08 | AK65: =AJ65/$F$334 -> 0.023952221
AA66: ROTTOGOON | AB66: =COUNTIF($B$234:$B$333,AA66) -> 1 | AC66: =SUMIF($B$234:$B$333,AA66,$E$234:$E$333) -> 1650 | AD66: =SUMIF($B$234:$B$333,AA66,$F$234:$F$333) -> 28033.5 | AE66: =AD66/$F$334 -> 0.028362858 | AG66: Kitchenville Home &amp; Kitchen | AH66: =COUNTIF($C$234:$C$333,AG66) -> 1 | AI66: =SUMIF($C$234:$C$333,AG66,$E$234:$E$333) -> 1211 | AJ66: =SUMIF($C$234:$C$333,AG66,$F$234:$F$333) -> 21785.89 | AK66: =AJ66/$F$334 -> 0.022041847
AA67: Joseph Joseph | AB67: =COUNTIF($B$234:$B$333,AA67) -> 2 | AC67: =SUMIF($B$234:$B$333,AA67,$E$234:$E$333) -> 585 | AD67: =SUMIF($B$234:$B$333,AA67,$F$234:$F$333) -> 24864.54 | AE67: =AD67/$F$334 -> 0.025156667 | AG67: EDELHAUS DE | AH67: =COUNTIF($C$234:$C$333,AG67) -> 2 | AI67: =SUMIF($C$234:$C$333,AG67,$E$234:$E$333) -> 459 | AJ67: =SUMIF($C$234:$C$333,AG67,$F$234:$F$333) -> 21497.05 | AK67: =AJ67/$F$334 -> 0.021749613
AA71: 国家/地区 | AB71: 商品数 | AC71: 月销量 | AD71: 月销售额€ | AE71: 预估销售额占比
A72: =_xlfn.DISPIMG("ID_AD02DE2458004063B2AB959888551888",1) -> =DISPIMG("ID_AD02DE2458004063B2AB959888551888",1)
AA73: 中国 | AB73: =COUNTIF($D$234:$D$333,AA73) -> 47 | AC73: =SUMIF($D$234:$D$333,AA73,$E$234:$E$333) -> 16885 | AD73: =SUMIF($D$234:$D$333,AA73,$F$234:$F$333) -> 408206.37 | AE73: =AD73/$F$334 -> 0.41300228
AA74: 未知 | AB74: =COUNTIF($D$234:$D$333,AA74) -> 27 | AC74: =SUMIF($D$234:$D$333,AA74,$E$234:$E$333) -> 16948 | AD74: =SUMIF($D$234:$D$333,AA74,$F$234:$F$333) -> 245932.13 | AE74: =AD74/$F$334 -> 0.24882152
AA75: 德国 | AB75: =COUNTIF($D$234:$D$333,AA75) -> 13 | AC75: =SUMIF($D$234:$D$333,AA75,$E$234:$E$333) -> 7059 | AD75: =SUMIF($D$234:$D$333,AA75,$F$234:$F$333) -> 185457.84 | AE75: =AD75/$F$334 -> 0.18763674
AA76: 英国 | AB76: =COUNTIF($D$234:$D$333,AA76) -> 6 | AC76: =SUMIF($D$234:$D$333,AA76,$E$234:$E$333) -> 5502 | AD76: =SUMIF($D$234:$D$333,AA76,$F$234:$F$333) -> 99779.62 | AE76: =AD76/$F$334 -> 0.1009519
AA77: 捷克共和国 | AB77: =COUNTIF($D$234:$D$333,AA77) -> 2 | AC77: =SUMIF($D$234:$D$333,AA77,$E$234:$E$333) -> 459 | AD77: =SUMIF($D$234:$D$333,AA77,$F$234:$F$333) -> 21497.05 | AE77: =AD77/$F$334 -> 0.021749613
AA78: 中国香港 | AB78: =COUNTIF($D$234:$D$333,AA78) -> 2 | AC78: =SUMIF($D$234:$D$333,AA78,$E$234:$E$333) -> 450 | AD78: =SUMIF($D$234:$D$333,AA78,$F$234:$F$333) -> 11205.25 | AE78: =AD78/$F$334 -> 0.011336898
AA79: 荷兰 | AB79: =COUNTIF($D$234:$D$333,AA79) -> 1 | AC79: =SUMIF($D$234:$D$333,AA79,$E$234:$E$333) -> 272 | AD79: =SUMIF($D$234:$D$333,AA79,$F$234:$F$333) -> 10333.28 | AE79: =AD79/$F$334 -> 0.010454683
A80: =_xlfn.DISPIMG("ID_F742E69090A54CD2B5D97537C71163A8",1) -> =DISPIMG("ID_F742E69090A54CD2B5D97537C71163A8",1) | AA80: 毛里求斯 | AB80: =COUNTIF($D$234:$D$333,AA80) -> 1 | AC80: =SUMIF($D$234:$D$333,AA80,$E$234:$E$333) -> 94 | AD80: =SUMIF($D$234:$D$333,AA80,$F$234:$F$333) -> 3759.06 | AE80: =AD80/$F$334 -> 0.0038032242
AA81: 波兰 | AB81: =COUNTIF($D$234:$D$333,AA81) -> 1 | AC81: =SUMIF($D$234:$D$333,AA81,$E$234:$E$333) -> 281 | AD81: =SUMIF($D$234:$D$333,AA81,$F$234:$F$333) -> 2217.09 | AE81: =AD81/$F$334 -> 0.002243138
A88: 头部与尾部｜当前销量分布 | J88: 新品表现｜当前销售额与上架年龄
A101: 当前前20销量57.13%。固定样本历史销售额分布补图见A670；两者分开解读。 | J101: 分析卡：3个月新品8款；逐款日期核对为12款。差异待确认，核验明细见A534。
A103: 3.买家画像（人工补充） | V103: 用户购买属性偏好 待补——数据源：卖家精灵
A105: 受众性别分布 待补——数据源：卖家精灵 | J105: 受众年龄分布 待补——数据源：卖家精灵
A123: 访客国家及地区分布 待补——数据源：卖家精灵 | J123: 跨网站浏览重合 待补——数据源：卖家精灵
A138: 交叉浏览历史变化 待补——数据源：卖家精灵 | J138: 受众兴趣分布 待补——数据源：卖家精灵 | V138: 待补——数据源：卖家精灵
A153: 受众常访问网站 待补——数据源：卖家精灵 | J153: 网站流量渠道结构 待补——数据源：卖家精灵
A169: 24个模块：完整8项，部分完成5项，待补11项（含9项人工画像）。第三方、自营趋势按确认改用插件逐月销量原图。
A172: 宏观销量、品牌及卖家趋势 | F172: 完成 | H172: A4 | J172: 2019—2026图保留；精确数据复核2024-09—2026-08。
A173: 2026较2025月度同比 | F173: 完成 | H173: Q4 | J173: 仅比较1—8月；9月未结束。
A174: 2025较2024月度同比 | F174: 部分完成 | H174: AA4 | J174: 固定样本2025较2024已补6—12月配对同比。缺2024年1—5月；不是类目总量同比。
A175: 2024较2023月度同比 | F175: 待补 | H175: AF4 | J175: 原2024较2023表已按用户要求改为2025较2024固定样本同比；2023数据不再作为本表待补项。
A176: 大盘销售额趋势 | F176: 完成 | H176: A24 | J176: 原图A24；首尾月份可能不完整，不与旧快照混算。
A177: 第三方与自营销售结构趋势 | F177: 部分完成 | H177: J24 | J177: 已补12个月自营、第三方、其他销量份额（A490）；逐月销售额结构仍缺。
A178: 第三方逐月销量趋势 | F178: 完成 | H178: A40 | J178: 按用户确认改用销量：插件原图仅显示第三方两种配送方式；2025-09至2026-08。
A179: Amazon自营逐月销量趋势 | F179: 完成 | H179: J40 | J179: 按用户确认改用销量：插件原图仅显示自营；2025-09至2026-08。图中无同比线。
A180: 品牌竞争结构 | F180: 完成 | H180: A56 | J180: 分日期展示；销售额表位于AA54:AE67。
A181: 卖家竞争结构 | F181: 完成 | H181: A64 | J181: 分日期展示；销售额表位于AG54:AK67。
A182: 卖家国家及地区分布 | F182: 完成 | H182: A72 | J182: 未知归属单列，不推定为德国；表在AA71:AE86。
A183: 配送方式历史变化 | F183: 部分完成 | H183: A80 | J183: 历史销量份额已导出（A490）；FBA、FBM、自营和其他单列，未混算销售额。
... A195: 用户购买属性偏好 | F195: 待补（人工） | H195: V103 | J195: 待补——数据源：卖家精灵
A200: 类目历史数据｜Sorftime德国站节点3177921031。月销量与份额来自接口；销售额来自原切菜板同比截图。不同维度未交叉相乘。
A202: 月份 | B202: 月销量（件） | C202: 销售额（欧元） | D202: 自营销售额份额 | E202: 前三商品销售额份额 | F202: 新品销售额份额（定义待确认） | G202: 平均品牌数 | H202: 平均卖家数 | I202: 销量同比 | J202: 销售额同比 | K202: 月份状态
A203: 2024-09 | B203: 32377 | D203: 0.1414 | E203: 0.1558 | F203: 0.1298 | G203: 77 | H203: 73 | K203: 完整月
A204: 2024-10 | B204: 36817 | D204: 0.1953 | E204: 0.1474 | F204: 0.1081 | G204: 75 | H204: 69 | K204: 完整月
A205: 2024-11 | B205: 47499 | D205: 0.2121 | E205: 0.1337 | F205: 0.0707 | G205: 75 | H205: 69 | K205: 完整月
A206: 2024-12 | B206: 57901 | D206: 0.1758 | E206: 0.1671 | F206: 0.0608 | G206: 73 | H206: 69 | K206: 完整月
A207: 2025-01 | B207: 40534 | C207: 900076.31 | D207: 0.1717 | E207: 0.1393 | F207: 0.0868 | G207: 76 | H207: 69 | K207: 完整月
A208: 2025-02 | B208: 36545 | C208: 805844.74 | D208: 0.159 | E208: 0.118 | F208: 0.0982 | G208: 75 | H208: 71 | K208: 完整月
A209: 2025-03 | B209: 39843 | C209: 846326.3 | D209: 0.1828 | E209: 0.1528 | F209: 0.0968 | G209: 77 | H209: 69 | K209: 完整月
A210: 2025-04 | B210: 37378 | C210: 771102.08 | D210: 0.1988 | E210: 0.1544 | F210: 0.0878 | G210: 77 | H210: 70 | K210: 完整月
A211: 2025-05 | B211: 49185 | C211: 906206.37 | D211: 0.1999 | E211: 0.1724 | F211: 0.0597 | G211: 76 | H211: 68 | K211: 完整月
A212: 2025-06 | B212: 34736 | C212: 659987.81 | D212: 0.2167 | E212: 0.1437 | F212: 0.076 | G212: 74 | H212: 64 | K212: 完整月
A213: 2025-07 | B213: 41030 | C213: 764333.12 | D213: 0.2165 | E213: 0.1363 | F213: 0.0826 | G213: 74 | H213: 63 | K213: 完整月
A214: 2025-08 | B214: 38937 | C214: 726359.62 | D214: 0.2164 | E214: 0.1538 | F214: 0.0839 | G214: 72 | H214: 61 | K214: 完整月
A215: 2025-09 | B215: 40875 | C215: 803473.08 | D215: 0.2434 | E215: 0.1414 | F215: 0.074 | G215: 70 | H215: 60 | I215: =B215/B203-1 -> 0.26247027 | K215: 完整月
A216: 2025-10 | B216: 48860 | C216: 943046.98 | D216: 0.279 | E216: 0.1202 | F216: 0.0594 | G216: 71 | H216: 58 | I216: =B216/B204-1 -> 0.32710433 | K216: 完整月
A217: 2025-11 | B217: 54711 | C217: 1047931.2 | D217: 0.2917 | E217: 0.1433 | F217: 0.0644 | G217: 69 | H217: 57 | I217: =B217/B205-1 -> 0.15183478 | K217: 完整月
A218: 2025-12 | B218: 72578 | C218: 1469234.9 | D218: 0.2218 | E218: 0.1813 | F218: 0.0829 | G218: 71 | H218: 61 | I218: =B218/B206-1 -> 0.2534844 | K218: 完整月
A219: 2026-01 | B219: 61381 | C219: 1261888.9 | D219: 0.2208 | E219: 0.1445 | F219: 0.0768 | G219: 76 | H219: 64 | I219: =B219/B207-1 -> 0.51430898 | J219: =C219/C207-1 -> 0.40197993 | K219: 完整月
A220: 2026-02 | B220: 48373 | C220: 998726.87 | D220: 0.1995 | E220: 0.1266 | F220: 0.0689 | G220: 77 | H220: 64 | I220: =B220/B208-1 -> 0.32365577 | J220: =C220/C208-1 -> 0.23935396 | K220: 完整月
A221: 2026-03 | B221: 53855 | C221: 1119003.8 | D221: 0.1829 | E221: 0.1284 | F221: 0.0787 | G221: 79 | H221: 65 | I221: =B221/B209-1 -> 0.35168035 | J221: =C221/C209-1 -> 0.32218959 | K221: 完整月
A222: 2026-04 | B222: 52690 | C222: 1152494.2 | D222: 0.1984 | E222: 0.1149 | F222: 0.0957 | G222: 78 | H222: 66 | I222: =B222/B210-1 -> 0.40965274 | J222: =C222/C210-1 -> 0.49460651 | K222: 完整月
A223: 2026-05 | B223: 62954 | C223: 1295381.7 | D223: 0.181 | E223: 0.1668 | F223: 0.0942 | G223: 77 | H223: 66 | I223: =B223/B211-1 -> 0.27994307 | J223: =C223/C211-1 -> 0.42945548 | K223: 完整月
A224: 2026-06 | B224: 50629 | C224: 1101471.5 | D224: 0.1979 | E224: 0.1519 | F224: 0.0943 | G224: 76 | H224: 64 | I224: =B224/B212-1 -> 0.45753685 | J224: =C224/C212-1 -> 0.66892699 | K224: 完整月
A225: 2026-07 | B225: 49969 | C225: 969966.61 | D225: 0.1872 | E225: 0.1415 | F225: 0.0916 | G225: 76 | H225: 66 | I225: =B225/B213-1 -> 0.21786498 | J225: =C225/C213-1 -> 0.26903648 | K225: 完整月
A226: 2026-08 | B226: 51211 | C226: 1085860.3 | D226: 0.2041 | E226: 0.19 | F226: 0.0914 | G226: 77 | H226: 66 | I226: =B226/B214-1 -> 0.31522716 | J226: =C226/C214-1 -> 0.49493489 | K226: 完整月
A228: 口径核对：2026年8月类目趋势为51,211件；历史区间报告返回190款、61,252件；两者不合并。2026年9月未结束，不参与完整月比较。新品接口未说明90天/其他年龄界限，份额仅按原字段展示。
A232: 9月11日接口独立快照｜100款；合计47,950件、€988,387.69。未与9月10日网页图合并。
A233: 商品编号 | B233: 品牌 | C233: 卖家 | D233: 卖家国家/地区 | E233: 月销量 | F233: 月销售额（欧元） | G233: 上架日期 | H233: 评分数 | I233: 配送原字段 | J233: 商品标题 | K233: 数据来源
A234: B01CR1L1GQ | B234: Kesper | C234: Amazon | D234: 未知 | E234: 5519 | F234: 29305.89 | G234: 2017-01-25 | H234: 2409 | I234: FBA | J234: KESPER | K234: Sorftime 2026-09-11
A235: B092JPBC1H | B235: Deer & Oak | C235: Great Ideas | D235: 英国 | E235: 3075 | F235: 52121.25 | G235: 2021-09-07 | H235: 7851 | I235: FBA | J235: Deer & Oak Schneidebrett Bambus XXL 44x30 x2 cm, vorgeölt | K235: Sorftime 2026-09-11
A236: B07TV8S14K | B236: WMF | C236: Amazon | D236: 未知 | E236: 1775 | F236: 63882.25 | G236: 2019-10-09 | H236: 3858 | I236: AmzFBA | J236: WMF Schneidebrett Holz groß massiv 40 x 32 x 4 cm, Holz, Akazienholz, klingenschonend, große Arbeitsfläche, Küchenbrett, Stirnholzoptik, Gummierte Füße | K236: Sorftime 2026-09-11
...

Sheet ②谷歌趋势
A1: 德国切菜板｜产品生命周期与搜索趋势 | B1: 德国切菜板｜产品生命周期与搜索趋势 | C1: 德国切菜板｜产品生命周期与搜索趋势 | D1: 德国切菜板｜产品生命周期与搜索趋势 | E1: 德国切菜板｜产品生命周期与搜索趋势 | F1: 德国切菜板｜产品生命周期与搜索趋势 | G1: 德国切菜板｜产品生命周期与搜索趋势 | H1: 德国切菜板｜产品生命周期与搜索趋势 | I1: 德国切菜板｜产品生命周期与搜索趋势 | J1: 德国切菜板｜产品生命周期与搜索趋势 | K1: 德国切菜板｜产品生命周期与搜索趋势 | L1: 德国切菜板｜产品生命周期与搜索趋势 | M1: 德国切菜板｜产品生命周期与搜索趋势 | N1: 德国切菜板｜产品生命周期与搜索趋势 | O1: 德国切菜板｜产品生命周期与搜索趋势 | P1: 德国切菜板｜产品生命周期与搜索趋势 | Q1: 德国切菜板｜产品生命周期与搜索趋势 | R1: 德国切菜板｜产品生命周期与搜索趋势 | S1: 德国切菜板｜产品生命周期与搜索趋势 | T1: 德国切菜板｜产品生命周期与搜索趋势 | U1: 德国切菜板｜产品生命周期与搜索趋势 | V1: 德国切菜板｜产品生命周期与搜索趋势 | W1: 德国切菜板｜产品生命周期与搜索趋势 | X1: 德国切菜板｜产品生命周期与搜索趋势
A2: 1. 产品季节性｜德国·过去12个月 | B2: 1. 产品季节性｜德国·过去12个月 | C2: 1. 产品季节性｜德国·过去12个月 | D2: 1. 产品季节性｜德国·过去12个月 | E2: 1. 产品季节性｜德国·过去12个月 | F2: 1. 产品季节性｜德国·过去12个月 | G2: 1. 产品季节性｜德国·过去12个月 | H2: 1. 产品季节性｜德国·过去12个月 | I2: 1. 产品季节性｜德国·过去12个月 | J2: 1. 产品季节性｜德国·过去12个月 | K2: 1. 产品季节性｜德国·过去12个月 | L2: 1. 产品季节性｜德国·过去12个月 | M2: 3. 产品流行区域｜德国·过去12个月 | N2: 3. 产品流行区域｜德国·过去12个月 | O2: 3. 产品流行区域｜德国·过去12个月 | P2: 3. 产品流行区域｜德国·过去12个月 | Q2: 3. 产品流行区域｜德国·过去12个月 | R2: 3. 产品流行区域｜德国·过去12个月 | S2: 3. 产品流行区域｜德国·过去12个月 | T2: 3. 产品流行区域｜德国·过去12个月 | U2: 3. 产品流行区域｜德国·过去12个月 | V2: 3. 产品流行区域｜德国·过去12个月 | W2: 3. 产品流行区域｜德国·过去12个月 | X2: 3. 产品流行区域｜德国·过去12个月 | Y2: 数据源：Google Trends（谷歌趋势）官网 截图日期：2026-09-11 地区：德国；所有类别；网页搜索 关键词： schneidebrett（切菜板） schneidebrett holz（木切菜板） 0—100是相对搜索热度，不是搜索次数或销量。关键词范围不完全等于Amazon切菜板类目。 【地区数据】 卖家精灵接口本次没有返回地区分布。本表的德国地图、州排名来自谷歌官网，不能用接口趋势数据代替。
A3: 1. 产品季节性｜德国·过去12个月 | B3: 1. 产品季节性｜德国·过去12个月 | C3: 1. 产品季节性｜德国·过去12个月 | D3: 1. 产品季节性｜德国·过去12个月 | E3: 1. 产品季节性｜德国·过去12个月 | F3: 1. 产品季节性｜德国·过去12个月 | G3: 1. 产品季节性｜德国·过去12个月 | H3: 1. 产品季节性｜德国·过去12个月 | I3: 1. 产品季节性｜德国·过去12个月 | J3: 1. 产品季节性｜德国·过去12个月 | K3: 1. 产品季节性｜德国·过去12个月 | L3: 1. 产品季节性｜德国·过去12个月 | M3: 3. 产品流行区域｜德国·过去12个月 | N3: 3. 产品流行区域｜德国·过去12个月 | O3: 3. 产品流行区域｜德国·过去12个月 | P3: 3. 产品流行区域｜德国·过去12个月 | Q3: 3. 产品流行区域｜德国·过去12个月 | R3: 3. 产品流行区域｜德国·过去12个月 | S3: 3. 产品流行区域｜德国·过去12个月 | T3: 3. 产品流行区域｜德国·过去12个月 | U3: 3. 产品流行区域｜德国·过去12个月 | V3: 3. 产品流行区域｜德国·过去12个月 | W3: 3. 产品流行区域｜德国·过去12个月 | X3: 3. 产品流行区域｜德国·过去12个月
A16: 近一年两个词均在2025年11月下旬至12月走高。主词12月7日所在周达到100，木切菜板词12月14日所在周达到21（同图统一尺度）。2026年多数非年末周仍有持续搜索，呈全年需求叠加年末旺季。 | B16: 近一年两个词均在2025年11月下旬至12月走高。主词12月7日所在周达到100，木切菜板词12月14日所在周达到21（同图统一尺度）。2026年多数非年末周仍有持续搜索，呈全年需求叠加年末旺季。 | C16: 近一年两个词均在2025年11月下旬至12月走高。主词12月7日所在周达到100，木切菜板词12月14日所在周达到21（同图统一尺度）。2026年多数非年末周仍有持续搜索，呈全年需求叠加年末旺季。 | D16: 近一年两个词均在2025年11月下旬至12月走高。主词12月7日所在周达到100，木切菜板词12月14日所在周达到21（同图统一尺度）。2026年多数非年末周仍有持续搜索，呈全年需求叠加年末旺季。 | E16: 近一年两个词均在2025年11月下旬至12月走高。主词12月7日所在周达到100，木切菜板词12月14日所在周达到21（同图统一尺度）。2026年多数非年末周仍有持续搜索，呈全年需求叠加年末旺季。 | F16: 近一年两个词均在2025年11月下旬至12月走高。主词12月7日所在周达到100，木切菜板词12月14日所在周达到21（同图统一尺度）。2026年多数非年末周仍有持续搜索，呈全年需求叠加年末旺季。 | G16: 近一年两个词均在2025年11月下旬至12月走高。主词12月7日所在周达到100，木切菜板词12月14日所在周达到21（同图统一尺度）。2026年多数非年末周仍有持续搜索，呈全年需求叠加年末旺季。 | H16: 近一年两个词均在2025年11月下旬至12月走高。主词12月7日所在周达到100，木切菜板词12月14日所在周达到21（同图统一尺度）。2026年多数非年末周仍有持续搜索，呈全年需求叠加年末旺季。 | I16: 近一年两个词均在2025年11月下旬至12月走高。主词12月7日所在周达到100，木切菜板词12月14日所在周达到21（同图统一尺度）。2026年多数非年末周仍有持续搜索，呈全年需求叠加年末旺季。 | J16: 近一年两个词均在2025年11月下旬至12月走高。主词12月7日所在周达到100，木切菜板词12月14日所在周达到21（同图统一尺度）。2026年多数非年末周仍有持续搜索，呈全年需求叠加年末旺季。 | K16: 近一年两个词均在2025年11月下旬至12月走高。主词12月7日所在周达到100，木切菜板词12月14日所在周达到21（同图统一尺度）。2026年多数非年末周仍有持续搜索，呈全年需求叠加年末旺季。 | L16: 近一年两个词均在2025年11月下旬至12月走高。主词12月7日所在周达到100，木切菜板词12月14日所在周达到21（同图统一尺度）。2026年多数非年末周仍有持续搜索，呈全年需求叠加年末旺季。
A17: 近一年两个词均在2025年11月下旬至12月走高。主词12月7日所在周达到100，木切菜板词12月14日所在周达到21（同图统一尺度）。2026年多数非年末周仍有持续搜索，呈全年需求叠加年末旺季。 | B17: 近一年两个词均在2025年11月下旬至12月走高。主词12月7日所在周达到100，木切菜板词12月14日所在周达到21（同图统一尺度）。2026年多数非年末周仍有持续搜索，呈全年需求叠加年末旺季。 | C17: 近一年两个词均在2025年11月下旬至12月走高。主词12月7日所在周达到100，木切菜板词12月14日所在周达到21（同图统一尺度）。2026年多数非年末周仍有持续搜索，呈全年需求叠加年末旺季。 | D17: 近一年两个词均在2025年11月下旬至12月走高。主词12月7日所在周达到100，木切菜板词12月14日所在周达到21（同图统一尺度）。2026年多数非年末周仍有持续搜索，呈全年需求叠加年末旺季。 | E17: 近一年两个词均在2025年11月下旬至12月走高。主词12月7日所在周达到100，木切菜板词12月14日所在周达到21（同图统一尺度）。2026年多数非年末周仍有持续搜索，呈全年需求叠加年末旺季。 | F17: 近一年两个词均在2025年11月下旬至12月走高。主词12月7日所在周达到100，木切菜板词12月14日所在周达到21（同图统一尺度）。2026年多数非年末周仍有持续搜索，呈全年需求叠加年末旺季。 | G17: 近一年两个词均在2025年11月下旬至12月走高。主词12月7日所在周达到100，木切菜板词12月14日所在周达到21（同图统一尺度）。2026年多数非年末周仍有持续搜索，呈全年需求叠加年末旺季。 | H17: 近一年两个词均在2025年11月下旬至12月走高。主词12月7日所在周达到100，木切菜板词12月14日所在周达到21（同图统一尺度）。2026年多数非年末周仍有持续搜索，呈全年需求叠加年末旺季。 | I17: 近一年两个词均在2025年11月下旬至12月走高。主词12月7日所在周达到100，木切菜板词12月14日所在周达到21（同图统一尺度）。2026年多数非年末周仍有持续搜索，呈全年需求叠加年末旺季。 | J17: 近一年两个词均在2025年11月下旬至12月走高。主词12月7日所在周达到100，木切菜板词12月14日所在周达到21（同图统一尺度）。2026年多数非年末周仍有持续搜索，呈全年需求叠加年末旺季。 | K17: 近一年两个词均在2025年11月下旬至12月走高。主词12月7日所在周达到100，木切菜板词12月14日所在周达到21（同图统一尺度）。2026年多数非年末周仍有持续搜索，呈全年需求叠加年末旺季。 | L17: 近一年两个词均在2025年11月下旬至12月走高。主词12月7日所在周达到100，木切菜板词12月14日所在周达到21（同图统一尺度）。2026年多数非年末周仍有持续搜索，呈全年需求叠加年末旺季。
A18: 近一年两个词均在2025年11月下旬至12月走高。主词12月7日所在周达到100，木切菜板词12月14日所在周达到21（同图统一尺度）。2026年多数非年末周仍有持续搜索，呈全年需求叠加年末旺季。 | B18: 近一年两个词均在2025年11月下旬至12月走高。主词12月7日所在周达到100，木切菜板词12月14日所在周达到21（同图统一尺度）。2026年多数非年末周仍有持续搜索，呈全年需求叠加年末旺季。 | C18: 近一年两个词均在2025年11月下旬至12月走高。主词12月7日所在周达到100，木切菜板词12月14日所在周达到21（同图统一尺度）。2026年多数非年末周仍有持续搜索，呈全年需求叠加年末旺季。 | D18: 近一年两个词均在2025年11月下旬至12月走高。主词12月7日所在周达到100，木切菜板词12月14日所在周达到21（同图统一尺度）。2026年多数非年末周仍有持续搜索，呈全年需求叠加年末旺季。 | E18: 近一年两个词均在2025年11月下旬至12月走高。主词12月7日所在周达到100，木切菜板词12月14日所在周达到21（同图统一尺度）。2026年多数非年末周仍有持续搜索，呈全年需求叠加年末旺季。 | F18: 近一年两个词均在2025年11月下旬至12月走高。主词12月7日所在周达到100，木切菜板词12月14日所在周达到21（同图统一尺度）。2026年多数非年末周仍有持续搜索，呈全年需求叠加年末旺季。 | G18: 近一年两个词均在2025年11月下旬至12月走高。主词12月7日所在周达到100，木切菜板词12月14日所在周达到21（同图统一尺度）。2026年多数非年末周仍有持续搜索，呈全年需求叠加年末旺季。 | H18: 近一年两个词均在2025年11月下旬至12月走高。主词12月7日所在周达到100，木切菜板词12月14日所在周达到21（同图统一尺度）。2026年多数非年末周仍有持续搜索，呈全年需求叠加年末旺季。 | I18: 近一年两个词均在2025年11月下旬至12月走高。主词12月7日所在周达到100，木切菜板词12月14日所在周达到21（同图统一尺度）。2026年多数非年末周仍有持续搜索，呈全年需求叠加年末旺季。 | J18: 近一年两个词均在2025年11月下旬至12月走高。主词12月7日所在周达到100，木切菜板词12月14日所在周达到21（同图统一尺度）。2026年多数非年末周仍有持续搜索，呈全年需求叠加年末旺季。 | K18: 近一年两个词均在2025年11月下旬至12月走高。主词12月7日所在周达到100，木切菜板词12月14日所在周达到21（同图统一尺度）。2026年多数非年末周仍有持续搜索，呈全年需求叠加年末旺季。 | L18: 近一年两个词均在2025年11月下旬至12月走高。主词12月7日所在周达到100，木切菜板词12月14日所在周达到21（同图统一尺度）。2026年多数非年末周仍有持续搜索，呈全年需求叠加年末旺季。
A19: 近一年两个词均在2025年11月下旬至12月走高。主词12月7日所在周达到100，木切菜板词12月14日所在周达到21（同图统一尺度）。2026年多数非年末周仍有持续搜索，呈全年需求叠加年末旺季。 | B19: 近一年两个词均在2025年11月下旬至12月走高。主词12月7日所在周达到100，木切菜板词12月14日所在周达到21（同图统一尺度）。2026年多数非年末周仍有持续搜索，呈全年需求叠加年末旺季。 | C19: 近一年两个词均在2025年11月下旬至12月走高。主词12月7日所在周达到100，木切菜板词12月14日所在周达到21（同图统一尺度）。2026年多数非年末周仍有持续搜索，呈全年需求叠加年末旺季。 | D19: 近一年两个词均在2025年11月下旬至12月走高。主词12月7日所在周达到100，木切菜板词12月14日所在周达到21（同图统一尺度）。2026年多数非年末周仍有持续搜索，呈全年需求叠加年末旺季。 | E19: 近一年两个词均在2025年11月下旬至12月走高。主词12月7日所在周达到100，木切菜板词12月14日所在周达到21（同图统一尺度）。2026年多数非年末周仍有持续搜索，呈全年需求叠加年末旺季。 | F19: 近一年两个词均在2025年11月下旬至12月走高。主词12月7日所在周达到100，木切菜板词12月14日所在周达到21（同图统一尺度）。2026年多数非年末周仍有持续搜索，呈全年需求叠加年末旺季。 | G19: 近一年两个词均在2025年11月下旬至12月走高。主词12月7日所在周达到100，木切菜板词12月14日所在周达到21（同图统一尺度）。2026年多数非年末周仍有持续搜索，呈全年需求叠加年末旺季。 | H19: 近一年两个词均在2025年11月下旬至12月走高。主词12月7日所在周达到100，木切菜板词12月14日所在周达到21（同图统一尺度）。2026年多数非年末周仍有持续搜索，呈全年需求叠加年末旺季。 | I19: 近一年两个词均在2025年11月下旬至12月走高。主词12月7日所在周达到100，木切菜板词12月14日所在周达到21（同图统一尺度）。2026年多数非年末周仍有持续搜索，呈全年需求叠加年末旺季。 | J19: 近一年两个词均在2025年11月下旬至12月走高。主词12月7日所在周达到100，木切菜板词12月14日所在周达到21（同图统一尺度）。2026年多数非年末周仍有持续搜索，呈全年需求叠加年末旺季。 | K19: 近一年两个词均在2025年11月下旬至12月走高。主词12月7日所在周达到100，木切菜板词12月14日所在周达到21（同图统一尺度）。2026年多数非年末周仍有持续搜索，呈全年需求叠加年末旺季。 | L19: 近一年两个词均在2025年11月下旬至12月走高。主词12月7日所在周达到100，木切菜板词12月14日所在周达到21（同图统一尺度）。2026年多数非年末周仍有持续搜索，呈全年需求叠加年末旺季。
A20: 近一年两个词均在2025年11月下旬至12月走高。主词12月7日所在周达到100，木切菜板词12月14日所在周达到21（同图统一尺度）。2026年多数非年末周仍有持续搜索，呈全年需求叠加年末旺季。 | B20: 近一年两个词均在2025年11月下旬至12月走高。主词12月7日所在周达到100，木切菜板词12月14日所在周达到21（同图统一尺度）。2026年多数非年末周仍有持续搜索，呈全年需求叠加年末旺季。 | C20: 近一年两个词均在2025年11月下旬至12月走高。主词12月7日所在周达到100，木切菜板词12月14日所在周达到21（同图统一尺度）。2026年多数非年末周仍有持续搜索，呈全年需求叠加年末旺季。 | D20: 近一年两个词均在2025年11月下旬至12月走高。主词12月7日所在周达到100，木切菜板词12月14日所在周达到21（同图统一尺度）。2026年多数非年末周仍有持续搜索，呈全年需求叠加年末旺季。 | E20: 近一年两个词均在2025年11月下旬至12月走高。主词12月7日所在周达到100，木切菜板词12月14日所在周达到21（同图统一尺度）。2026年多数非年末周仍有持续搜索，呈全年需求叠加年末旺季。 | F20: 近一年两个词均在2025年11月下旬至12月走高。主词12月7日所在周达到100，木切菜板词12月14日所在周达到21（同图统一尺度）。2026年多数非年末周仍有持续搜索，呈全年需求叠加年末旺季。 | G20: 近一年两个词均在2025年11月下旬至12月走高。主词12月7日所在周达到100，木切菜板词12月14日所在周达到21（同图统一尺度）。2026年多数非年末周仍有持续搜索，呈全年需求叠加年末旺季。 | H20: 近一年两个词均在2025年11月下旬至12月走高。主词12月7日所在周达到100，木切菜板词12月14日所在周达到21（同图统一尺度）。2026年多数非年末周仍有持续搜索，呈全年需求叠加年末旺季。 | I20: 近一年两个词均在2025年11月下旬至12月走高。主词12月7日所在周达到100，木切菜板词12月14日所在周达到21（同图统一尺度）。2026年多数非年末周仍有持续搜索，呈全年需求叠加年末旺季。 | J20: 近一年两个词均在2025年11月下旬至12月走高。主词12月7日所在周达到100，木切菜板词12月14日所在周达到21（同图统一尺度）。2026年多数非年末周仍有持续搜索，呈全年需求叠加年末旺季。 | K20: 近一年两个词均在2025年11月下旬至12月走高。主词12月7日所在周达到100，木切菜板词12月14日所在周达到21（同图统一尺度）。2026年多数非年末周仍有持续搜索，呈全年需求叠加年末旺季。 | L20: 近一年两个词均在2025年11月下旬至12月走高。主词12月7日所在周达到100，木切菜板词12月14日所在周达到21（同图统一尺度）。2026年多数非年末周仍有持续搜索，呈全年需求叠加年末旺季。
A21: 近一年两个词均在2025年11月下旬至12月走高。主词12月7日所在周达到100，木切菜板词12月14日所在周达到21（同图统一尺度）。2026年多数非年末周仍有持续搜索，呈全年需求叠加年末旺季。 | B21: 近一年两个词均在2025年11月下旬至12月走高。主词12月7日所在周达到100，木切菜板词12月14日所在周达到21（同图统一尺度）。2026年多数非年末周仍有持续搜索，呈全年需求叠加年末旺季。 | C21: 近一年两个词均在2025年11月下旬至12月走高。主词12月7日所在周达到100，木切菜板词12月14日所在周达到21（同图统一尺度）。2026年多数非年末周仍有持续搜索，呈全年需求叠加年末旺季。 | D21: 近一年两个词均在2025年11月下旬至12月走高。主词12月7日所在周达到100，木切菜板词12月14日所在周达到21（同图统一尺度）。2026年多数非年末周仍有持续搜索，呈全年需求叠加年末旺季。 | E21: 近一年两个词均在2025年11月下旬至12月走高。主词12月7日所在周达到100，木切菜板词12月14日所在周达到21（同图统一尺度）。2026年多数非年末周仍有持续搜索，呈全年需求叠加年末旺季。 | F21: 近一年两个词均在2025年11月下旬至12月走高。主词12月7日所在周达到100，木切菜板词12月14日所在周达到21（同图统一尺度）。2026年多数非年末周仍有持续搜索，呈全年需求叠加年末旺季。 | G21: 近一年两个词均在2025年11月下旬至12月走高。主词12月7日所在周达到100，木切菜板词12月14日所在周达到21（同图统一尺度）。2026年多数非年末周仍有持续搜索，呈全年需求叠加年末旺季。 | H21: 近一年两个词均在2025年11月下旬至12月走高。主词12月7日所在周达到100，木切菜板词12月14日所在周达到21（同图统一尺度）。2026年多数非年末周仍有持续搜索，呈全年需求叠加年末旺季。 | I21: 近一年两个词均在2025年11月下旬至12月走高。主词12月7日所在周达到100，木切菜板词12月14日所在周达到21（同图统一尺度）。2026年多数非年末周仍有持续搜索，呈全年需求叠加年末旺季。 | J21: 近一年两个词均在2025年11月下旬至12月走高。主词12月7日所在周达到100，木切菜板词12月14日所在周达到21（同图统一尺度）。2026年多数非年末周仍有持续搜索，呈全年需求叠加年末旺季。 | K21: 近一年两个词均在2025年11月下旬至12月走高。主词12月7日所在周达到100，木切菜板词12月14日所在周达到21（同图统一尺度）。2026年多数非年末周仍有持续搜索，呈全年需求叠加年末旺季。 | L21: 近一年两个词均在2025年11月下旬至12月走高。主词12月7日所在周达到100，木切菜板词12月14日所在周达到21（同图统一尺度）。2026年多数非年末周仍有持续搜索，呈全年需求叠加年末旺季。
A22: 2. 产品生命周期｜德国·过去5年 | B22: 2. 产品生命周期｜德国·过去5年 | C22: 2. 产品生命周期｜德国·过去5年 | D22: 2. 产品生命周期｜德国·过去5年 | E22: 2. 产品生命周期｜德国·过去5年 | F22: 2. 产品生命周期｜德国·过去5年 | G22: 2. 产品生命周期｜德国·过去5年 | H22: 2. 产品生命周期｜德国·过去5年 | I22: 2. 产品生命周期｜德国·过去5年 | J22: 2. 产品生命周期｜德国·过去5年 | K22: 2. 产品生命周期｜德国·过去5年 | L22: 2. 产品生命周期｜德国·过去5年 | M22: 4. 总结 | N22: 4. 总结 | O22: 4. 总结 | P22: 4. 总结 | Q22: 4. 总结 | R22: 4. 总结 | S22: 4. 总结 | T22: 4. 总结 | U22: 4. 总结 | V22: 4. 总结 | W22: 4. 总结 | X22: 4. 总结 | Y22: 【接口实测｜2026-09-12】 两个词各返回262条周数据；主词另有61条月数据。 【与官网的区别】 ①本次接口截至8月9日，官网到9月6日，慢4周。 ②走势接近，数值略有差别。主词257个重叠周，平均差0.67点，最大差7点。 ③例：2025年12月7日两边都是100；2026年8月9日接口64、官网57。 ④每个词单独算0—100，不能跨词比较需求大小。 ⑤没有地区分布；月数据的完整性和汇总方式未说明。 【用法】 批量初筛用接口；近期变化、两词对比和地区分布看官网。
A23: 2. 产品生命周期｜德国·过去5年 | B23: 2. 产品生命周期｜德国·过去5年 | C23: 2. 产品生命周期｜德国·过去5年 | D23: 2. 产品生命周期｜德国·过去5年 | E23: 2. 产品生命周期｜德国·过去5年 | F23: 2. 产品生命周期｜德国·过去5年 | G23: 2. 产品生命周期｜德国·过去5年 | H23: 2. 产品生命周期｜德国·过去5年 | I23: 2. 产品生命周期｜德国·过去5年 | J23: 2. 产品生命周期｜德国·过去5年 | K23: 2. 产品生命周期｜德国·过去5年 | L23: 2. 产品生命周期｜德国·过去5年 | M23: 4. 总结 | N23: 4. 总结 | O23: 4. 总结 | P23: 4. 总结 | Q23: 4. 总结 | R23: 4. 总结 | S23: 4. 总结 | T23: 4. 总结 | U23: 4. 总结 | V23: 4. 总结 | W23: 4. 总结 | X23: 4. 总结
M24: 【总结】 1）季节性：两个词的年末高峰同步，备货与推广应提前于11—12月；不能把平时有需求写成“无季节性”。 2）五年走势：主词2021—2025年各年最高周均在12月；对应指数71、68、66、94、100。2024—2025年的峰值高于前三年，但不是五年逐年增长。 3）地区：主词相对热度前三为汉堡100、巴伐利亚（网页译“拜仁”）96、巴登-符腾堡94；木切菜板为汉堡100、巴登-符腾堡91、萨克森91。地区指数不代表订单或购买力。 【趋势表明】 切菜板属于持续有搜索需求、年末旺季明显的成熟需求。近两年主词旺季热度抬升，值得继续研究；是否能带来新品成交，仍应结合第一表的竞争与销量数据。 | N24: 【总结】 1）季节性：两个词的年末高峰同步，备货与推广应提前于11—12月；不能把平时有需求写成“无季节性”。 2）五年走势：主词2021—2025年各年最高周均在12月；对应指数71、68、66、94、100。2024—2025年的峰值高于前三年，但不是五年逐年增长。 3）地区：主词相对热度前三为汉堡100、巴伐利亚（网页译“拜仁”）96、巴登-符腾堡94；木切菜板为汉堡100、巴登-符腾堡91、萨克森91。地区指数不代表订单或购买力。 【趋势表明】 切菜板属于持续有搜索需求、年末旺季明显的成熟需求。近两年主词旺季热度抬升，值得继续研究；是否能带来新品成交，仍应结合第一表的竞争与销量数据。 | O24: 【总结】 1）季节性：两个词的年末高峰同步，备货与推广应提前于11—12月；不能把平时有需求写成“无季节性”。 2）五年走势：主词2021—2025年各年最高周均在12月；对应指数71、68、66、94、100。2024—2025年的峰值高于前三年，但不是五年逐年增长。 3）地区：主词相对热度前三为汉堡100、巴伐利亚（网页译“拜仁”）96、巴登-符腾堡94；木切菜板为汉堡100、巴登-符腾堡91、萨克森91。地区指数不代表订单或购买力。 【趋势表明】 切菜板属于持续有搜索需求、年末旺季明显的成熟需求。近两年主词旺季热度抬升，值得继续研究；是否能带来新品成交，仍应结合第一表的竞争与销量数据。 | P24: 【总结】 1）季节性：两个词的年末高峰同步，备货与推广应提前于11—12月；不能把平时有需求写成“无季节性”。 2）五年走势：主词2021—2025年各年最高周均在12月；对应指数71、68、66、94、100。2024—2025年的峰值高于前三年，但不是五年逐年增长。 3）地区：主词相对热度前三为汉堡100、巴伐利亚（网页译“拜仁”）96、巴登-符腾堡94；木切菜板为汉堡100、巴登-符腾堡91、萨克森91。地区指数不代表订单或购买力。 【趋势表明】 切菜板属于持续有搜索需求、年末旺季明显的成熟需求。近两年主词旺季热度抬升，值得继续研究；是否能带来新品成交，仍应结合第一表的竞争与销量数据。 | Q24: 【总结】 1）季节性：两个词的年末高峰同步，备货与推广应提前于11—12月；不能把平时有需求写成“无季节性”。 2）五年走势：主词2021—2025年各年最高周均在12月；对应指数71、68、66、94、100。2024—2025年的峰值高于前三年，但不是五年逐年增长。 3）地区：主词相对热度前三为汉堡100、巴伐利亚（网页译“拜仁”）96、巴登-符腾堡94；木切菜板为汉堡100、巴登-符腾堡91、萨克森91。地区指数不代表订单或购买力。 【趋势表明】 切菜板属于持续有搜索需求、年末旺季明显的成熟需求。近两年主词旺季热度抬升，值得继续研究；是否能带来新品成交，仍应结合第一表的竞争与销量数据。 | R24: 【总结】 1）季节性：两个词的年末高峰同步，备货与推广应提前于11—12月；不能把平时有需求写成“无季节性”。 2）五年走势：主词2021—2025年各年最高周均在12月；对应指数71、68、66、94、100。2024—2025年的峰值高于前三年，但不是五年逐年增长。 3）地区：主词相对热度前三为汉堡100、巴伐利亚（网页译“拜仁”）96、巴登-符腾堡94；木切菜板为汉堡100、巴登-符腾堡91、萨克森91。地区指数不代表订单或购买力。 【趋势表明】 切菜板属于持续有搜索需求、年末旺季明显的成熟需求。近两年主词旺季热度抬升，值得继续研究；是否能带来新品成交，仍应结合第一表的竞争与销量数据。 | S24: 【总结】 1）季节性：两个词的年末高峰同步，备货与推广应提前于11—12月；不能把平时有需求写成“无季节性”。 2）五年走势：主词2021—2025年各年最高周均在12月；对应指数71、68、66、94、100。2024—2025年的峰值高于前三年，但不是五年逐年增长。 3）地区：主词相对热度前三为汉堡100、巴伐利亚（网页译“拜仁”）96、巴登-符腾堡94；木切菜板为汉堡100、巴登-符腾堡91、萨克森91。地区指数不代表订单或购买力。 【趋势表明】 切菜板属于持续有搜索需求、年末旺季明显的成熟需求。近两年主词旺季热度抬升，值得继续研究；是否能带来新品成交，仍应结合第一表的竞争与销量数据。 | T24: 【总结】 1）季节性：两个词的年末高峰同步，备货与推广应提前于11—12月；不能把平时有需求写成“无季节性”。 2）五年走势：主词2021—2025年各年最高周均在12月；对应指数71、68、66、94、100。2024—2025年的峰值高于前三年，但不是五年逐年增长。 3）地区：主词相对热度前三为汉堡100、巴伐利亚（网页译“拜仁”）96、巴登-符腾堡94；木切菜板为汉堡100、巴登-符腾堡91、萨克森91。地区指数不代表订单或购买力。 【趋势表明】 切菜板属于持续有搜索需求、年末旺季明显的成熟需求。近两年主词旺季热度抬升，值得继续研究；是否能带来新品成交，仍应结合第一表的竞争与销量数据。 | U24: 【总结】 1）季节性：两个词的年末高峰同步，备货与推广应提前于11—12月；不能把平时有需求写成“无季节性”。 2）五年走势：主词2021—2025年各年最高周均在12月；对应指数71、68、66、94、100。2024—2025年的峰值高于前三年，但不是五年逐年增长。 3）地区：主词相对热度前三为汉堡100、巴伐利亚（网页译“拜仁”）96、巴登-符腾堡94；木切菜板为汉堡100、巴登-符腾堡91、萨克森91。地区指数不代表订单或购买力。 【趋势表明】 切菜板属于持续有搜索需求、年末旺季明显的成熟需求。近两年主词旺季热度抬升，值得继续研究；是否能带来新品成交，仍应结合第一表的竞争与销量数据。 | V24: 【总结】 1）季节性：两个词的年末高峰同步，备货与推广应提前于11—12月；不能把平时有需求写成“无季节性”。 2）五年走势：主词2021—2025年各年最高周均在12月；对应指数71、68、66、94、100。2024—2025年的峰值高于前三年，但不是五年逐年增长。 3）地区：主词相对热度前三为汉堡100、巴伐利亚（网页译“拜仁”）96、巴登-符腾堡94；木切菜板为汉堡100、巴登-符腾堡91、萨克森91。地区指数不代表订单或购买力。 【趋势表明】 切菜板属于持续有搜索需求、年末旺季明显的成熟需求。近两年主词旺季热度抬升，值得继续研究；是否能带来新品成交，仍应结合第一表的竞争与销量数据。 | W24: 【总结】 1）季节性：两个词的年末高峰同步，备货与推广应提前于11—12月；不能把平时有需求写成“无季节性”。 2）五年走势：主词2021—2025年各年最高周均在12月；对应指数71、68、66、94、100。2024—2025年的峰值高于前三年，但不是五年逐年增长。 3）地区：主词相对热度前三为汉堡100、巴伐利亚（网页译“拜仁”）96、巴登-符腾堡94；木切菜板为汉堡100、巴登-符腾堡91、萨克森91。地区指数不代表订单或购买力。 【趋势表明】 切菜板属于持续有搜索需求、年末旺季明显的成熟需求。近两年主词旺季热度抬升，值得继续研究；是否能带来新品成交，仍应结合第一表的竞争与销量数据。 | X24: 【总结】 1）季节性：两个词的年末高峰同步，备货与推广应提前于11—12月；不能把平时有需求写成“无季节性”。 2）五年走势：主词2021—2025年各年最高周均在12月；对应指数71、68、66、94、100。2024—2025年的峰值高于前三年，但不是五年逐年增长。 3）地区：主词相对热度前三为汉堡100、巴伐利亚（网页译“拜仁”）96、巴登-符腾堡94；木切菜板为汉堡100、巴登-符腾堡91、萨克森91。地区指数不代表订单或购买力。 【趋势表明】 切菜板属于持续有搜索需求、年末旺季明显的成熟需求。近两年主词旺季热度抬升，值得继续研究；是否能带来新品成交，仍应结合第一表的竞争与销量数据。
M25: 【总结】 1）季节性：两个词的年末高峰同步，备货与推广应提前于11—12月；不能把平时有需求写成“无季节性”。 2）五年走势：主词2021—2025年各年最高周均在12月；对应指数71、68、66、94、100。2024—2025年的峰值高于前三年，但不是五年逐年增长。 3）地区：主词相对热度前三为汉堡100、巴伐利亚（网页译“拜仁”）96、巴登-符腾堡94；木切菜板为汉堡100、巴登-符腾堡91、萨克森91。地区指数不代表订单或购买力。 【趋势表明】 切菜板属于持续有搜索需求、年末旺季明显的成熟需求。近两年主词旺季热度抬升，值得继续研究；是否能带来新品成交，仍应结合第一表的竞争与销量数据。 | N25: 【总结】 1）季节性：两个词的年末高峰同步，备货与推广应提前于11—12月；不能把平时有需求写成“无季节性”。 2）五年走势：主词2021—2025年各年最高周均在12月；对应指数71、68、66、94、100。2024—2025年的峰值高于前三年，但不是五年逐年增长。 3）地区：主词相对热度前三为汉堡100、巴伐利亚（网页译“拜仁”）96、巴登-符腾堡94；木切菜板为汉堡100、巴登-符腾堡91、萨克森91。地区指数不代表订单或购买力。 【趋势表明】 切菜板属于持续有搜索需求、年末旺季明显的成熟需求。近两年主词旺季热度抬升，值得继续研究；是否能带来新品成交，仍应结合第一表的竞争与销量数据。 | O25: 【总结】 1）季节性：两个词的年末高峰同步，备货与推广应提前于11—12月；不能把平时有需求写成“无季节性”。 2）五年走势：主词2021—2025年各年最高周均在12月；对应指数71、68、66、94、100。2024—2025年的峰值高于前三年，但不是五年逐年增长。 3）地区：主词相对热度前三为汉堡100、巴伐利亚（网页译“拜仁”）96、巴登-符腾堡94；木切菜板为汉堡100、巴登-符腾堡91、萨克森91。地区指数不代表订单或购买力。 【趋势表明】 切菜板属于持续有搜索需求、年末旺季明显的成熟需求。近两年主词旺季热度抬升，值得继续研究；是否能带来新品成交，仍应结合第一表的竞争与销量数据。 | P25: 【总结】 1）季节性：两个词的年末高峰同步，备货与推广应提前于11—12月；不能把平时有需求写成“无季节性”。 2）五年走势：主词2021—2025年各年最高周均在12月；对应指数71、68、66、94、100。2024—2025年的峰值高于前三年，但不是五年逐年增长。 3）地区：主词相对热度前三为汉堡100、巴伐利亚（网页译“拜仁”）96、巴登-符腾堡94；木切菜板为汉堡100、巴登-符腾堡91、萨克森91。地区指数不代表订单或购买力。 【趋势表明】 切菜板属于持续有搜索需求、年末旺季明显的成熟需求。近两年主词旺季热度抬升，值得继续研究；是否能带来新品成交，仍应结合第一表的竞争与销量数据。 | Q25: 【总结】 1）季节性：两个词的年末高峰同步，备货与推广应提前于11—12月；不能把平时有需求写成“无季节性”。 2）五年走势：主词2021—2025年各年最高周均在12月；对应指数71、68、66、94、100。2024—2025年的峰值高于前三年，但不是五年逐年增长。 3）地区：主词相对热度前三为汉堡100、巴伐利亚（网页译“拜仁”）96、巴登-符腾堡94；木切菜板为汉堡100、巴登-符腾堡91、萨克森91。地区指数不代表订单或购买力。 【趋势表明】 切菜板属于持续有搜索需求、年末旺季明显的成熟需求。近两年主词旺季热度抬升，值得继续研究；是否能带来新品成交，仍应结合第一表的竞争与销量数据。 | R25: 【总结】 1）季节性：两个词的年末高峰同步，备货与推广应提前于11—12月；不能把平时有需求写成“无季节性”。 2）五年走势：主词2021—2025年各年最高周均在12月；对应指数71、68、66、94、100。2024—2025年的峰值高于前三年，但不是五年逐年增长。 3）地区：主词相对热度前三为汉堡100、巴伐利亚（网页译“拜仁”）96、巴登-符腾堡94；木切菜板为汉堡100、巴登-符腾堡91、萨克森91。地区指数不代表订单或购买力。 【趋势表明】 切菜板属于持续有搜索需求、年末旺季明显的成熟需求。近两年主词旺季热度抬升，值得继续研究；是否能带来新品成交，仍应结合第一表的竞争与销量数据。 | S25: 【总结】 1）季节性：两个词的年末高峰同步，备货与推广应提前于11—12月；不能把平时有需求写成“无季节性”。 2）五年走势：主词2021—2025年各年最高周均在12月；对应指数71、68、66、94、100。2024—2025年的峰值高于前三年，但不是五年逐年增长。 3）地区：主词相对热度前三为汉堡100、巴伐利亚（网页译“拜仁”）96、巴登-符腾堡94；木切菜板为汉堡100、巴登-符腾堡91、萨克森91。地区指数不代表订单或购买力。 【趋势表明】 切菜板属于持续有搜索需求、年末旺季明显的成熟需求。近两年主词旺季热度抬升，值得继续研究；是否能带来新品成交，仍应结合第一表的竞争与销量数据。 | T25: 【总结】 1）季节性：两个词的年末高峰同步，备货与推广应提前于11—12月；不能把平时有需求写成“无季节性”。 2）五年走势：主词2021—2025年各年最高周均在12月；对应指数71、68、66、94、100。2024—2025年的峰值高于前三年，但不是五年逐年增长。 3）地区：主词相对热度前三为汉堡100、巴伐利亚（网页译“拜仁”）96、巴登-符腾堡94；木切菜板为汉堡100、巴登-符腾堡91、萨克森91。地区指数不代表订单或购买力。 【趋势表明】 切菜板属于持续有搜索需求、年末旺季明显的成熟需求。近两年主词旺季热度抬升，值得继续研究；是否能带来新品成交，仍应结合第一表的竞争与销量数据。 | U25: 【总结】 1）季节性：两个词的年末高峰同步，备货与推广应提前于11—12月；不能把平时有需求写成“无季节性”。 2）五年走势：主词2021—2025年各年最高周均在12月；对应指数71、68、66、94、100。2024—2025年的峰值高于前三年，但不是五年逐年增长。 3）地区：主词相对热度前三为汉堡100、巴伐利亚（网页译“拜仁”）96、巴登-符腾堡94；木切菜板为汉堡100、巴登-符腾堡91、萨克森91。地区指数不代表订单或购买力。 【趋势表明】 切菜板属于持续有搜索需求、年末旺季明显的成熟需求。近两年主词旺季热度抬升，值得继续研究；是否能带来新品成交，仍应结合第一表的竞争与销量数据。 | V25: 【总结】 1）季节性：两个词的年末高峰同步，备货与推广应提前于11—12月；不能把平时有需求写成“无季节性”。 2）五年走势：主词2021—2025年各年最高周均在12月；对应指数71、68、66、94、100。2024—2025年的峰值高于前三年，但不是五年逐年增长。 3）地区：主词相对热度前三为汉堡100、巴伐利亚（网页译“拜仁”）96、巴登-符腾堡94；木切菜板为汉堡100、巴登-符腾堡91、萨克森91。地区指数不代表订单或购买力。 【趋势表明】 切菜板属于持续有搜索需求、年末旺季明显的成熟需求。近两年主词旺季热度抬升，值得继续研究；是否能带来新品成交，仍应结合第一表的竞争与销量数据。 | W25: 【总结】 1）季节性：两个词的年末高峰同步，备货与推广应提前于11—12月；不能把平时有需求写成“无季节性”。 2）五年走势：主词2021—2025年各年最高周均在12月；对应指数71、68、66、94、100。2024—2025年的峰值高于前三年，但不是五年逐年增长。 3）地区：主词相对热度前三为汉堡100、巴伐利亚（网页译“拜仁”）96、巴登-符腾堡94；木切菜板为汉堡100、巴登-符腾堡91、萨克森91。地区指数不代表订单或购买力。 【趋势表明】 切菜板属于持续有搜索需求、年末旺季明显的成熟需求。近两年主词旺季热度抬升，值得继续研究；是否能带来新品成交，仍应结合第一表的竞争与销量数据。 | X25: 【总结】 1）季节性：两个词的年末高峰同步，备货与推广应提前于11—12月；不能把平时有需求写成“无季节性”。 2）五年走势：主词2021—2025年各年最高周均在12月；对应指数71、68、66、94、100。2024—2025年的峰值高于前三年，但不是五年逐年增长。 3）地区：主词相对热度前三为汉堡100、巴伐利亚（网页译“拜仁”）96、巴登-符腾堡94；木切菜板为汉堡100、巴登-符腾堡91、萨克森91。地区指数不代表订单或购买力。 【趋势表明】 切菜板属于持续有搜索需求、年末旺季明显的成熟需求。近两年主词旺季热度抬升，值得继续研究；是否能带来新品成交，仍应结合第一表的竞争与销量数据。
M26: 【总结】 1）季节性：两个词的年末高峰同步，备货与推广应提前于11—12月；不能把平时有需求写成“无季节性”。 2）五年走势：主词2021—2025年各年最高周均在12月；对应指数71、68、66、94、100。2024—2025年的峰值高于前三年，但不是五年逐年增长。 3）地区：主词相对热度前三为汉堡100、巴伐利亚（网页译“拜仁”）96、巴登-符腾堡94；木切菜板为汉堡100、巴登-符腾堡91、萨克森91。地区指数不代表订单或购买力。 【趋势表明】 切菜板属于持续有搜索需求、年末旺季明显的成熟需求。近两年主词旺季热度抬升，值得继续研究；是否能带来新品成交，仍应结合第一表的竞争与销量数据。 | N26: 【总结】 1）季节性：两个词的年末高峰同步，备货与推广应提前于11—12月；不能把平时有需求写成“无季节性”。 2）五年走势：主词2021—2025年各年最高周均在12月；对应指数71、68、66、94、100。2024—2025年的峰值高于前三年，但不是五年逐年增长。 3）地区：主词相对热度前三为汉堡100、巴伐利亚（网页译“拜仁”）96、巴登-符腾堡94；木切菜板为汉堡100、巴登-符腾堡91、萨克森91。地区指数不代表订单或购买力。 【趋势表明】 切菜板属于持续有搜索需求、年末旺季明显的成熟需求。近两年主词旺季热度抬升，值得继续研究；是否能带来新品成交，仍应结合第一表的竞争与销量数据。 | O26: 【总结】 1）季节性：两个词的年末高峰同步，备货与推广应提前于11—12月；不能把平时有需求写成“无季节性”。 2）五年走势：主词2021—2025年各年最高周均在12月；对应指数71、68、66、94、100。2024—2025年的峰值高于前三年，但不是五年逐年增长。 3）地区：主词相对热度前三为汉堡100、巴伐利亚（网页译“拜仁”）96、巴登-符腾堡94；木切菜板为汉堡100、巴登-符腾堡91、萨克森91。地区指数不代表订单或购买力。 【趋势表明】 切菜板属于持续有搜索需求、年末旺季明显的成熟需求。近两年主词旺季热度抬升，值得继续研究；是否能带来新品成交，仍应结合第一表的竞争与销量数据。 | P26: 【总结】 1）季节性：两个词的年末高峰同步，备货与推广应提前于11—12月；不能把平时有需求写成“无季节性”。 2）五年走势：主词2021—2025年各年最高周均在12月；对应指数71、68、66、94、100。2024—2025年的峰值高于前三年，但不是五年逐年增长。 3）地区：主词相对热度前三为汉堡100、巴伐利亚（网页译“拜仁”）96、巴登-符腾堡94；木切菜板为汉堡100、巴登-符腾堡91、萨克森91。地区指数不代表订单或购买力。 【趋势表明】 切菜板属于持续有搜索需求、年末旺季明显的成熟需求。近两年主词旺季热度抬升，值得继续研究；是否能带来新品成交，仍应结合第一表的竞争与销量数据。 | Q26: 【总结】 1）季节性：两个词的年末高峰同步，备货与推广应提前于11—12月；不能把平时有需求写成“无季节性”。 2）五年走势：主词2021—2025年各年最高周均在12月；对应指数71、68、66、94、100。2024—2025年的峰值高于前三年，但不是五年逐年增长。 3）地区：主词相对热度前三为汉堡100、巴伐利亚（网页译“拜仁”）96、巴登-符腾堡94；木切菜板为汉堡100、巴登-符腾堡91、萨克森91。地区指数不代表订单或购买力。 【趋势表明】 切菜板属于持续有搜索需求、年末旺季明显的成熟需求。近两年主词旺季热度抬升，值得继续研究；是否能带来新品成交，仍应结合第一表的竞争与销量数据。 | R26: 【总结】 1）季节性：两个词的年末高峰同步，备货与推广应提前于11—12月；不能把平时有需求写成“无季节性”。 2）五年走势：主词2021—2025年各年最高周均在12月；对应指数71、68、66、94、100。2024—2025年的峰值高于前三年，但不是五年逐年增长。 3）地区：主词相对热度前三为汉堡100、巴伐利亚（网页译“拜仁”）96、巴登-符腾堡94；木切菜板为汉堡100、巴登-符腾堡91、萨克森91。地区指数不代表订单或购买力。 【趋势表明】 切菜板属于持续有搜索需求、年末旺季明显的成熟需求。近两年主词旺季热度抬升，值得继续研究；是否能带来新品成交，仍应结合第一表的竞争与销量数据。 | S26: 【总结】 1）季节性：两个词的年末高峰同步，备货与推广应提前于11—12月；不能把平时有需求写成“无季节性”。 2）五年走势：主词2021—2025年各年最高周均在12月；对应指数71、68、66、94、100。2024—2025年的峰值高于前三年，但不是五年逐年增长。 3）地区：主词相对热度前三为汉堡100、巴伐利亚（网页译“拜仁”）96、巴登-符腾堡94；木切菜板为汉堡100、巴登-符腾堡91、萨克森91。地区指数不代表订单或购买力。 【趋势表明】 切菜板属于持续有搜索需求、年末旺季明显的成熟需求。近两年主词旺季热度抬升，值得继续研究；是否能带来新品成交，仍应结合第一表的竞争与销量数据。 | T26: 【总结】 1）季节性：两个词的年末高峰同步，备货与推广应提前于11—12月；不能把平时有需求写成“无季节性”。 2）五年走势：主词2021—2025年各年最高周均在12月；对应指数71、68、66、94、100。2024—2025年的峰值高于前三年，但不是五年逐年增长。 3）地区：主词相对热度前三为汉堡100、巴伐利亚（网页译“拜仁”）96、巴登-符腾堡94；木切菜板为汉堡100、巴登-符腾堡91、萨克森91。地区指数不代表订单或购买力。 【趋势表明】 切菜板属于持续有搜索需求、年末旺季明显的成熟需求。近两年主词旺季热度抬升，值得继续研究；是否能带来新品成交，仍应结合第一表的竞争与销量数据。 | U26: 【总结】 1）季节性：两个词的年末高峰同步，备货与推广应提前于11—12月；不能把平时有需求写成“无季节性”。 2）五年走势：主词2021—2025年各年最高周均在12月；对应指数71、68、66、94、100。2024—2025年的峰值高于前三年，但不是五年逐年增长。 3）地区：主词相对热度前三为汉堡100、巴伐利亚（网页译“拜仁”）96、巴登-符腾堡94；木切菜板为汉堡100、巴登-符腾堡91、萨克森91。地区指数不代表订单或购买力。 【趋势表明】 切菜板属于持续有搜索需求、年末旺季明显的成熟需求。近两年主词旺季热度抬升，值得继续研究；是否能带来新品成交，仍应结合第一表的竞争与销量数据。 | V26: 【总结】 1）季节性：两个词的年末高峰同步，备货与推广应提前于11—12月；不能把平时有需求写成“无季节性”。 2）五年走势：主词2021—2025年各年最高周均在12月；对应指数71、68、66、94、100。2024—2025年的峰值高于前三年，但不是五年逐年增长。 3）地区：主词相对热度前三为汉堡100、巴伐利亚（网页译“拜仁”）96、巴登-符腾堡94；木切菜板为汉堡100、巴登-符腾堡91、萨克森91。地区指数不代表订单或购买力。 【趋势表明】 切菜板属于持续有搜索需求、年末旺季明显的成熟需求。近两年主词旺季热度抬升，值得继续研究；是否能带来新品成交，仍应结合第一表的竞争与销量数据。 | W26: 【总结】 1）季节性：两个词的年末高峰同步，备货与推广应提前于11—12月；不能把平时有需求写成“无季节性”。 2）五年走势：主词2021—2025年各年最高周均在12月；对应指数71、68、66、94、100。2024—2025年的峰值高于前三年，但不是五年逐年增长。 3）地区：主词相对热度前三为汉堡100、巴伐利亚（网页译“拜仁”）96、巴登-符腾堡94；木切菜板为汉堡100、巴登-符腾堡91、萨克森91。地区指数不代表订单或购买力。 【趋势表明】 切菜板属于持续有搜索需求、年末旺季明显的成熟需求。近两年主词旺季热度抬升，值得继续研究；是否能带来新品成交，仍应结合第一表的竞争与销量数据。 | X26: 【总结】 1）季节性：两个词的年末高峰同步，备货与推广应提前于11—12月；不能把平时有需求写成“无季节性”。 2）五年走势：主词2021—2025年各年最高周均在12月；对应指数71、68、66、94、100。2024—2025年的峰值高于前三年，但不是五年逐年增长。 3）地区：主词相对热度前三为汉堡100、巴伐利亚（网页译“拜仁”）96、巴登-符腾堡94；木切菜板为汉堡100、巴登-符腾堡91、萨克森91。地区指数不代表订单或购买力。 【趋势表明】 切菜板属于持续有搜索需求、年末旺季明显的成熟需求。近两年主词旺季热度抬升，值得继续研究；是否能带来新品成交，仍应结合第一表的竞争与销量数据。
M27: 【总结】 1）季节性：两个词的年末高峰同步，备货与推广应提前于11—12月；不能把平时有需求写成“无季节性”。 2）五年走势：主词2021—2025年各年最高周均在12月；对应指数71、68、66、94、100。2024—2025年的峰值高于前三年，但不是五年逐年增长。 3）地区：主词相对热度前三为汉堡100、巴伐利亚（网页译“拜仁”）96、巴登-符腾堡94；木切菜板为汉堡100、巴登-符腾堡91、萨克森91。地区指数不代表订单或购买力。 【趋势表明】 切菜板属于持续有搜索需求、年末旺季明显的成熟需求。近两年主词旺季热度抬升，值得继续研究；是否能带来新品成交，仍应结合第一表的竞争与销量数据。 | N27: 【总结】 1）季节性：两个词的年末高峰同步，备货与推广应提前于11—12月；不能把平时有需求写成“无季节性”。 2）五年走势：主词2021—2025年各年最高周均在12月；对应指数71、68、66、94、100。2024—2025年的峰值高于前三年，但不是五年逐年增长。 3）地区：主词相对热度前三为汉堡100、巴伐利亚（网页译“拜仁”）96、巴登-符腾堡94；木切菜板为汉堡100、巴登-符腾堡91、萨克森91。地区指数不代表订单或购买力。 【趋势表明】 切菜板属于持续有搜索需求、年末旺季明显的成熟需求。近两年主词旺季热度抬升，值得继续研究；是否能带来新品成交，仍应结合第一表的竞争与销量数据。 | O27: 【总结】 1）季节性：两个词的年末高峰同步，备货与推广应提前于11—12月；不能把平时有需求写成“无季节性”。 2）五年走势：主词2021—2025年各年最高周均在12月；对应指数71、68、66、94、100。2024—2025年的峰值高于前三年，但不是五年逐年增长。 3）地区：主词相对热度前三为汉堡100、巴伐利亚（网页译“拜仁”）96、巴登-符腾堡94；木切菜板为汉堡100、巴登-符腾堡91、萨克森91。地区指数不代表订单或购买力。 【趋势表明】 切菜板属于持续有搜索需求、年末旺季明显的成熟需求。近两年主词旺季热度抬升，值得继续研究；是否能带来新品成交，仍应结合第一表的竞争与销量数据。 | P27: 【总结】 1）季节性：两个词的年末高峰同步，备货与推广应提前于11—12月；不能把平时有需求写成“无季节性”。 2）五年走势：主词2021—2025年各年最高周均在12月；对应指数71、68、66、94、100。2024—2025年的峰值高于前三年，但不是五年逐年增长。 3）地区：主词相对热度前三为汉堡100、巴伐利亚（网页译“拜仁”）96、巴登-符腾堡94；木切菜板为汉堡100、巴登-符腾堡91、萨克森91。地区指数不代表订单或购买力。 【趋势表明】 切菜板属于持续有搜索需求、年末旺季明显的成熟需求。近两年主词旺季热度抬升，值得继续研究；是否能带来新品成交，仍应结合第一表的竞争与销量数据。 | Q27: 【总结】 1）季节性：两个词的年末高峰同步，备货与推广应提前于11—12月；不能把平时有需求写成“无季节性”。 2）五年走势：主词2021—2025年各年最高周均在12月；对应指数71、68、66、94、100。2024—2025年的峰值高于前三年，但不是五年逐年增长。 3）地区：主词相对热度前三为汉堡100、巴伐利亚（网页译“拜仁”）96、巴登-符腾堡94；木切菜板为汉堡100、巴登-符腾堡91、萨克森91。地区指数不代表订单或购买力。 【趋势表明】 切菜板属于持续有搜索需求、年末旺季明显的成熟需求。近两年主词旺季热度抬升，值得继续研究；是否能带来新品成交，仍应结合第一表的竞争与销量数据。 | R27: 【总结】 1）季节性：两个词的年末高峰同步，备货与推广应提前于11—12月；不能把平时有需求写成“无季节性”。 2）五年走势：主词2021—2025年各年最高周均在12月；对应指数71、68、66、94、100。2024—2025年的峰值高于前三年，但不是五年逐年增长。 3）地区：主词相对热度前三为汉堡100、巴伐利亚（网页译“拜仁”）96、巴登-符腾堡94；木切菜板为汉堡100、巴登-符腾堡91、萨克森91。地区指数不代表订单或购买力。 【趋势表明】 切菜板属于持续有搜索需求、年末旺季明显的成熟需求。近两年主词旺季热度抬升，值得继续研究；是否能带来新品成交，仍应结合第一表的竞争与销量数据。 | S27: 【总结】 1）季节性：两个词的年末高峰同步，备货与推广应提前于11—12月；不能把平时有需求写成“无季节性”。 2）五年走势：主词2021—2025年各年最高周均在12月；对应指数71、68、66、94、100。2024—2025年的峰值高于前三年，但不是五年逐年增长。 3）地区：主词相对热度前三为汉堡100、巴伐利亚（网页译“拜仁”）96、巴登-符腾堡94；木切菜板为汉堡100、巴登-符腾堡91、萨克森91。地区指数不代表订单或购买力。 【趋势表明】 切菜板属于持续有搜索需求、年末旺季明显的成熟需求。近两年主词旺季热度抬升，值得继续研究；是否能带来新品成交，仍应结合第一表的竞争与销量数据。 | T27: 【总结】 1）季节性：两个词的年末高峰同步，备货与推广应提前于11—12月；不能把平时有需求写成“无季节性”。 2）五年走势：主词2021—2025年各年最高周均在12月；对应指数71、68、66、94、100。2024—2025年的峰值高于前三年，但不是五年逐年增长。 3）地区：主词相对热度前三为汉堡100、巴伐利亚（网页译“拜仁”）96、巴登-符腾堡94；木切菜板为汉堡100、巴登-符腾堡91、萨克森91。地区指数不代表订单或购买力。 【趋势表明】 切菜板属于持续有搜索需求、年末旺季明显的成熟需求。近两年主词旺季热度抬升，值得继续研究；是否能带来新品成交，仍应结合第一表的竞争与销量数据。 | U27: 【总结】 1）季节性：两个词的年末高峰同步，备货与推广应提前于11—12月；不能把平时有需求写成“无季节性”。 2）五年走势：主词2021—2025年各年最高周均在12月；对应指数71、68、66、94、100。2024—2025年的峰值高于前三年，但不是五年逐年增长。 3）地区：主词相对热度前三为汉堡100、巴伐利亚（网页译“拜仁”）96、巴登-符腾堡94；木切菜板为汉堡100、巴登-符腾堡91、萨克森91。地区指数不代表订单或购买力。 【趋势表明】 切菜板属于持续有搜索需求、年末旺季明显的成熟需求。近两年主词旺季热度抬升，值得继续研究；是否能带来新品成交，仍应结合第一表的竞争与销量数据。 | V27: 【总结】 1）季节性：两个词的年末高峰同步，备货与推广应提前于11—12月；不能把平时有需求写成“无季节性”。 2）五年走势：主词2021—2025年各年最高周均在12月；对应指数71、68、66、94、100。2024—2025年的峰值高于前三年，但不是五年逐年增长。 3）地区：主词相对热度前三为汉堡100、巴伐利亚（网页译“拜仁”）96、巴登-符腾堡94；木切菜板为汉堡100、巴登-符腾堡91、萨克森91。地区指数不代表订单或购买力。 【趋势表明】 切菜板属于持续有搜索需求、年末旺季明显的成熟需求。近两年主词旺季热度抬升，值得继续研究；是否能带来新品成交，仍应结合第一表的竞争与销量数据。 | W27: 【总结】 1）季节性：两个词的年末高峰同步，备货与推广应提前于11—12月；不能把平时有需求写成“无季节性”。 2）五年走势：主词2021—2025年各年最高周均在12月；对应指数71、68、66、94、100。2024—2025年的峰值高于前三年，但不是五年逐年增长。 3）地区：主词相对热度前三为汉堡100、巴伐利亚（网页译“拜仁”）96、巴登-符腾堡94；木切菜板为汉堡100、巴登-符腾堡91、萨克森91。地区指数不代表订单或购买力。 【趋势表明】 切菜板属于持续有搜索需求、年末旺季明显的成熟需求。近两年主词旺季热度抬升，值得继续研究；是否能带来新品成交，仍应结合第一表的竞争与销量数据。 | X27: 【总结】 1）季节性：两个词的年末高峰同步，备货与推广应提前于11—12月；不能把平时有需求写成“无季节性”。 2）五年走势：主词2021—2025年各年最高周均在12月；对应指数71、68、66、94、100。2024—2025年的峰值高于前三年，但不是五年逐年增长。 3）地区：主词相对热度前三为汉堡100、巴伐利亚（网页译“拜仁”）96、巴登-符腾堡94；木切菜板为汉堡100、巴登-符腾堡91、萨克森91。地区指数不代表订单或购买力。 【趋势表明】 切菜板属于持续有搜索需求、年末旺季明显的成熟需求。近两年主词旺季热度抬升，值得继续研究；是否能带来新品成交，仍应结合第一表的竞争与销量数据。
M28: 【总结】 1）季节性：两个词的年末高峰同步，备货与推广应提前于11—12月；不能把平时有需求写成“无季节性”。 2）五年走势：主词2021—2025年各年最高周均在12月；对应指数71、68、66、94、100。2024—2025年的峰值高于前三年，但不是五年逐年增长。 3）地区：主词相对热度前三为汉堡100、巴伐利亚（网页译“拜仁”）96、巴登-符腾堡94；木切菜板为汉堡100、巴登-符腾堡91、萨克森91。地区指数不代表订单或购买力。 【趋势表明】 切菜板属于持续有搜索需求、年末旺季明显的成熟需求。近两年主词旺季热度抬升，值得继续研究；是否能带来新品成交，仍应结合第一表的竞争与销量数据。 | N28: 【总结】 1）季节性：两个词的年末高峰同步，备货与推广应提前于11—12月；不能把平时有需求写成“无季节性”。 2）五年走势：主词2021—2025年各年最高周均在12月；对应指数71、68、66、94、100。2024—2025年的峰值高于前三年，但不是五年逐年增长。 3）地区：主词相对热度前三为汉堡100、巴伐利亚（网页译“拜仁”）96、巴登-符腾堡94；木切菜板为汉堡100、巴登-符腾堡91、萨克森91。地区指数不代表订单或购买力。 【趋势表明】 切菜板属于持续有搜索需求、年末旺季明显的成熟需求。近两年主词旺季热度抬升，值得继续研究；是否能带来新品成交，仍应结合第一表的竞争与销量数据。 | O28: 【总结】 1）季节性：两个词的年末高峰同步，备货与推广应提前于11—12月；不能把平时有需求写成“无季节性”。 2）五年走势：主词2021—2025年各年最高周均在12月；对应指数71、68、66、94、100。2024—2025年的峰值高于前三年，但不是五年逐年增长。 3）地区：主词相对热度前三为汉堡100、巴伐利亚（网页译“拜仁”）96、巴登-符腾堡94；木切菜板为汉堡100、巴登-符腾堡91、萨克森91。地区指数不代表订单或购买力。 【趋势表明】 切菜板属于持续有搜索需求、年末旺季明显的成熟需求。近两年主词旺季热度抬升，值得继续研究；是否能带来新品成交，仍应结合第一表的竞争与销量数据。 | P28: 【总结】 1）季节性：两个词的年末高峰同步，备货与推广应提前于11—12月；不能把平时有需求写成“无季节性”。 2）五年走势：主词2021—2025年各年最高周均在12月；对应指数71、68、66、94、100。2024—2025年的峰值高于前三年，但不是五年逐年增长。 3）地区：主词相对热度前三为汉堡100、巴伐利亚（网页译“拜仁”）96、巴登-符腾堡94；木切菜板为汉堡100、巴登-符腾堡91、萨克森91。地区指数不代表订单或购买力。 【趋势表明】 切菜板属于持续有搜索需求、年末旺季明显的成熟需求。近两年主词旺季热度抬升，值得继续研究；是否能带来新品成交，仍应结合第一表的竞争与销量数据。 | Q28: 【总结】 1）季节性：两个词的年末高峰同步，备货与推广应提前于11—12月；不能把平时有需求写成“无季节性”。 2）五年走势：主词2021—2025年各年最高周均在12月；对应指数71、68、66、94、100。2024—2025年的峰值高于前三年，但不是五年逐年增长。 3）地区：主词相对热度前三为汉堡100、巴伐利亚（网页译“拜仁”）96、巴登-符腾堡94；木切菜板为汉堡100、巴登-符腾堡91、萨克森91。地区指数不代表订单或购买力。 【趋势表明】 切菜板属于持续有搜索需求、年末旺季明显的成熟需求。近两年主词旺季热度抬升，值得继续研究；是否能带来新品成交，仍应结合第一表的竞争与销量数据。 | R28: 【总结】 1）季节性：两个词的年末高峰同步，备货与推广应提前于11—12月；不能把平时有需求写成“无季节性”。 2）五年走势：主词2021—2025年各年最高周均在12月；对应指数71、68、66、94、100。2024—2025年的峰值高于前三年，但不是五年逐年增长。 3）地区：主词相对热度前三为汉堡100、巴伐利亚（网页译“拜仁”）96、巴登-符腾堡94；木切菜板为汉堡100、巴登-符腾堡91、萨克森91。地区指数不代表订单或购买力。 【趋势表明】 切菜板属于持续有搜索需求、年末旺季明显的成熟需求。近两年主词旺季热度抬升，值得继续研究；是否能带来新品成交，仍应结合第一表的竞争与销量数据。 | S28: 【总结】 1）季节性：两个词的年末高峰同步，备货与推广应提前于11—12月；不能把平时有需求写成“无季节性”。 2）五年走势：主词2021—2025年各年最高周均在12月；对应指数71、68、66、94、100。2024—2025年的峰值高于前三年，但不是五年逐年增长。 3）地区：主词相对热度前三为汉堡100、巴伐利亚（网页译“拜仁”）96、巴登-符腾堡94；木切菜板为汉堡100、巴登-符腾堡91、萨克森91。地区指数不代表订单或购买力。 【趋势表明】 切菜板属于持续有搜索需求、年末旺季明显的成熟需求。近两年主词旺季热度抬升，值得继续研究；是否能带来新品成交，仍应结合第一表的竞争与销量数据。 | T28: 【总结】 1）季节性：两个词的年末高峰同步，备货与推广应提前于11—12月；不能把平时有需求写成“无季节性”。 2）五年走势：主词2021—2025年各年最高周均在12月；对应指数71、68、66、94、100。2024—2025年的峰值高于前三年，但不是五年逐年增长。 3）地区：主词相对热度前三为汉堡100、巴伐利亚（网页译“拜仁”）96、巴登-符腾堡94；木切菜板为汉堡100、巴登-符腾堡91、萨克森91。地区指数不代表订单或购买力。 【趋势表明】 切菜板属于持续有搜索需求、年末旺季明显的成熟需求。近两年主词旺季热度抬升，值得继续研究；是否能带来新品成交，仍应结合第一表的竞争与销量数据。 | U28: 【总结】 1）季节性：两个词的年末高峰同步，备货与推广应提前于11—12月；不能把平时有需求写成“无季节性”。 2）五年走势：主词2021—2025年各年最高周均在12月；对应指数71、68、66、94、100。2024—2025年的峰值高于前三年，但不是五年逐年增长。 3）地区：主词相对热度前三为汉堡100、巴伐利亚（网页译“拜仁”）96、巴登-符腾堡94；木切菜板为汉堡100、巴登-符腾堡91、萨克森91。地区指数不代表订单或购买力。 【趋势表明】 切菜板属于持续有搜索需求、年末旺季明显的成熟需求。近两年主词旺季热度抬升，值得继续研究；是否能带来新品成交，仍应结合第一表的竞争与销量数据。 | V28: 【总结】 1）季节性：两个词的年末高峰同步，备货与推广应提前于11—12月；不能把平时有需求写成“无季节性”。 2）五年走势：主词2021—2025年各年最高周均在12月；对应指数71、68、66、94、100。2024—2025年的峰值高于前三年，但不是五年逐年增长。 3）地区：主词相对热度前三为汉堡100、巴伐利亚（网页译“拜仁”）96、巴登-符腾堡94；木切菜板为汉堡100、巴登-符腾堡91、萨克森91。地区指数不代表订单或购买力。 【趋势表明】 切菜板属于持续有搜索需求、年末旺季明显的成熟需求。近两年主词旺季热度抬升，值得继续研究；是否能带来新品成交，仍应结合第一表的竞争与销量数据。 | W28: 【总结】 1）季节性：两个词的年末高峰同步，备货与推广应提前于11—12月；不能把平时有需求写成“无季节性”。 2）五年走势：主词2021—2025年各年最高周均在12月；对应指数71、68、66、94、100。2024—2025年的峰值高于前三年，但不是五年逐年增长。 3）地区：主词相对热度前三为汉堡100、巴伐利亚（网页译“拜仁”）96、巴登-符腾堡94；木切菜板为汉堡100、巴登-符腾堡91、萨克森91。地区指数不代表订单或购买力。 【趋势表明】 切菜板属于持续有搜索需求、年末旺季明显的成熟需求。近两年主词旺季热度抬升，值得继续研究；是否能带来新品成交，仍应结合第一表的竞争与销量数据。 | X28: 【总结】 1）季节性：两个词的年末高峰同步，备货与推广应提前于11—12月；不能把平时有需求写成“无季节性”。 2）五年走势：主词2021—2025年各年最高周均在12月；对应指数71、68、66、94、100。2024—2025年的峰值高于前三年，但不是五年逐年增长。 3）地区：主词相对热度前三为汉堡100、巴伐利亚（网页译“拜仁”）96、巴登-符腾堡94；木切菜板为汉堡100、巴登-符腾堡91、萨克森91。地区指数不代表订单或购买力。 【趋势表明】 切菜板属于持续有搜索需求、年末旺季明显的成熟需求。近两年主词旺季热度抬升，值得继续研究；是否能带来新品成交，仍应结合第一表的竞争与销量数据。
M29: 【总结】 1）季节性：两个词的年末高峰同步，备货与推广应提前于11—12月；不能把平时有需求写成“无季节性”。 2）五年走势：主词2021—2025年各年最高周均在12月；对应指数71、68、66、94、100。2024—2025年的峰值高于前三年，但不是五年逐年增长。 3）地区：主词相对热度前三为汉堡100、巴伐利亚（网页译“拜仁”）96、巴登-符腾堡94；木切菜板为汉堡100、巴登-符腾堡91、萨克森91。地区指数不代表订单或购买力。 【趋势表明】 切菜板属于持续有搜索需求、年末旺季明显的成熟需求。近两年主词旺季热度抬升，值得继续研究；是否能带来新品成交，仍应结合第一表的竞争与销量数据。 | N29: 【总结】 1）季节性：两个词的年末高峰同步，备货与推广应提前于11—12月；不能把平时有需求写成“无季节性”。 2）五年走势：主词2021—2025年各年最高周均在12月；对应指数71、68、66、94、100。2024—2025年的峰值高于前三年，但不是五年逐年增长。 3）地区：主词相对热度前三为汉堡100、巴伐利亚（网页译“拜仁”）96、巴登-符腾堡94；木切菜板为汉堡100、巴登-符腾堡91、萨克森91。地区指数不代表订单或购买力。 【趋势表明】 切菜板属于持续有搜索需求、年末旺季明显的成熟需求。近两年主词旺季热度抬升，值得继续研究；是否能带来新品成交，仍应结合第一表的竞争与销量数据。 | O29: 【总结】 1）季节性：两个词的年末高峰同步，备货与推广应提前于11—12月；不能把平时有需求写成“无季节性”。 2）五年走势：主词2021—2025年各年最高周均在12月；对应指数71、68、66、94、100。2024—2025年的峰值高于前三年，但不是五年逐年增长。 3）地区：主词相对热度前三为汉堡100、巴伐利亚（网页译“拜仁”）96、巴登-符腾堡94；木切菜板为汉堡100、巴登-符腾堡91、萨克森91。地区指数不代表订单或购买力。 【趋势表明】 切菜板属于持续有搜索需求、年末旺季明显的成熟需求。近两年主词旺季热度抬升，值得继续研究；是否能带来新品成交，仍应结合第一表的竞争与销量数据。 | P29: 【总结】 1）季节性：两个词的年末高峰同步，备货与推广应提前于11—12月；不能把平时有需求写成“无季节性”。 2）五年走势：主词2021—2025年各年最高周均在12月；对应指数71、68、66、94、100。2024—2025年的峰值高于前三年，但不是五年逐年增长。 3）地区：主词相对热度前三为汉堡100、巴伐利亚（网页译“拜仁”）96、巴登-符腾堡94；木切菜板为汉堡100、巴登-符腾堡91、萨克森91。地区指数不代表订单或购买力。 【趋势表明】 切菜板属于持续有搜索需求、年末旺季明显的成熟需求。近两年主词旺季热度抬升，值得继续研究；是否能带来新品成交，仍应结合第一表的竞争与销量数据。 | Q29: 【总结】 1）季节性：两个词的年末高峰同步，备货与推广应提前于11—12月；不能把平时有需求写成“无季节性”。 2）五年走势：主词2021—2025年各年最高周均在12月；对应指数71、68、66、94、100。2024—2025年的峰值高于前三年，但不是五年逐年增长。 3）地区：主词相对热度前三为汉堡100、巴伐利亚（网页译“拜仁”）96、巴登-符腾堡94；木切菜板为汉堡100、巴登-符腾堡91、萨克森91。地区指数不代表订单或购买力。 【趋势表明】 切菜板属于持续有搜索需求、年末旺季明显的成熟需求。近两年主词旺季热度抬升，值得继续研究；是否能带来新品成交，仍应结合第一表的竞争与销量数据。 | R29: 【总结】 1）季节性：两个词的年末高峰同步，备货与推广应提前于11—12月；不能把平时有需求写成“无季节性”。 2）五年走势：主词2021—2025年各年最高周均在12月；对应指数71、68、66、94、100。2024—2025年的峰值高于前三年，但不是五年逐年增长。 3）地区：主词相对热度前三为汉堡100、巴伐利亚（网页译“拜仁”）96、巴登-符腾堡94；木切菜板为汉堡100、巴登-符腾堡91、萨克森91。地区指数不代表订单或购买力。 【趋势表明】 切菜板属于持续有搜索需求、年末旺季明显的成熟需求。近两年主词旺季热度抬升，值得继续研究；是否能带来新品成交，仍应结合第一表的竞争与销量数据。 | S29: 【总结】 1）季节性：两个词的年末高峰同步，备货与推广应提前于11—12月；不能把平时有需求写成“无季节性”。 2）五年走势：主词2021—2025年各年最高周均在12月；对应指数71、68、66、94、100。2024—2025年的峰值高于前三年，但不是五年逐年增长。 3）地区：主词相对热度前三为汉堡100、巴伐利亚（网页译“拜仁”）96、巴登-符腾堡94；木切菜板为汉堡100、巴登-符腾堡91、萨克森91。地区指数不代表订单或购买力。 【趋势表明】 切菜板属于持续有搜索需求、年末旺季明显的成熟需求。近两年主词旺季热度抬升，值得继续研究；是否能带来新品成交，仍应结合第一表的竞争与销量数据。 | T29: 【总结】 1）季节性：两个词的年末高峰同步，备货与推广应提前于11—12月；不能把平时有需求写成“无季节性”。 2）五年走势：主词2021—2025年各年最高周均在12月；对应指数71、68、66、94、100。2024—2025年的峰值高于前三年，但不是五年逐年增长。 3）地区：主词相对热度前三为汉堡100、巴伐利亚（网页译“拜仁”）96、巴登-符腾堡94；木切菜板为汉堡100、巴登-符腾堡91、萨克森91。地区指数不代表订单或购买力。 【趋势表明】 切菜板属于持续有搜索需求、年末旺季明显的成熟需求。近两年主词旺季热度抬升，值得继续研究；是否能带来新品成交，仍应结合第一表的竞争与销量数据。 | U29: 【总结】 1）季节性：两个词的年末高峰同步，备货与推广应提前于11—12月；不能把平时有需求写成“无季节性”。 2）五年走势：主词2021—2025年各年最高周均在12月；对应指数71、68、66、94、100。2024—2025年的峰值高于前三年，但不是五年逐年增长。 3）地区：主词相对热度前三为汉堡100、巴伐利亚（网页译“拜仁”）96、巴登-符腾堡94；木切菜板为汉堡100、巴登-符腾堡91、萨克森91。地区指数不代表订单或购买力。 【趋势表明】 切菜板属于持续有搜索需求、年末旺季明显的成熟需求。近两年主词旺季热度抬升，值得继续研究；是否能带来新品成交，仍应结合第一表的竞争与销量数据。 | V29: 【总结】 1）季节性：两个词的年末高峰同步，备货与推广应提前于11—12月；不能把平时有需求写成“无季节性”。 2）五年走势：主词2021—2025年各年最高周均在12月；对应指数71、68、66、94、100。2024—2025年的峰值高于前三年，但不是五年逐年增长。 3）地区：主词相对热度前三为汉堡100、巴伐利亚（网页译“拜仁”）96、巴登-符腾堡94；木切菜板为汉堡100、巴登-符腾堡91、萨克森91。地区指数不代表订单或购买力。 【趋势表明】 切菜板属于持续有搜索需求、年末旺季明显的成熟需求。近两年主词旺季热度抬升，值得继续研究；是否能带来新品成交，仍应结合第一表的竞争与销量数据。 | W29: 【总结】 1）季节性：两个词的年末高峰同步，备货与推广应提前于11—12月；不能把平时有需求写成“无季节性”。 2）五年走势：主词2021—2025年各年最高周均在12月；对应指数71、68、66、94、100。2024—2025年的峰值高于前三年，但不是五年逐年增长。 3）地区：主词相对热度前三为汉堡100、巴伐利亚（网页译“拜仁”）96、巴登-符腾堡94；木切菜板为汉堡100、巴登-符腾堡91、萨克森91。地区指数不代表订单或购买力。 【趋势表明】 切菜板属于持续有搜索需求、年末旺季明显的成熟需求。近两年主词旺季热度抬升，值得继续研究；是否能带来新品成交，仍应结合第一表的竞争与销量数据。 | X29: 【总结】 1）季节性：两个词的年末高峰同步，备货与推广应提前于11—12月；不能把平时有需求写成“无季节性”。 2）五年走势：主词2021—2025年各年最高周均在12月；对应指数71、68、66、94、100。2024—2025年的峰值高于前三年，但不是五年逐年增长。 3）地区：主词相对热度前三为汉堡100、巴伐利亚（网页译“拜仁”）96、巴登-符腾堡94；木切菜板为汉堡100、巴登-符腾堡91、萨克森91。地区指数不代表订单或购买力。 【趋势表明】 切菜板属于持续有搜索需求、年末旺季明显的成熟需求。近两年主词旺季热度抬升，值得继续研究；是否能带来新品成交，仍应结合第一表的竞争与销量数据。
M30: 【总结】 1）季节性：两个词的年末高峰同步，备货与推广应提前于11—12月；不能把平时有需求写成“无季节性”。 2）五年走势：主词2021—2025年各年最高周均在12月；对应指数71、68、66、94、100。2024—2025年的峰值高于前三年，但不是五年逐年增长。 3）地区：主词相对热度前三为汉堡100、巴伐利亚（网页译“拜仁”）96、巴登-符腾堡94；木切菜板为汉堡100、巴登-符腾堡91、萨克森91。地区指数不代表订单或购买力。 【趋势表明】 切菜板属于持续有搜索需求、年末旺季明显的成熟需求。近两年主词旺季热度抬升，值得继续研究；是否能带来新品成交，仍应结合第一表的竞争与销量数据。 | N30: 【总结】 1）季节性：两个词的年末高峰同步，备货与推广应提前于11—12月；不能把平时有需求写成“无季节性”。 2）五年走势：主词2021—2025年各年最高周均在12月；对应指数71、68、66、94、100。2024—2025年的峰值高于前三年，但不是五年逐年增长。 3）地区：主词相对热度前三为汉堡100、巴伐利亚（网页译“拜仁”）96、巴登-符腾堡94；木切菜板为汉堡100、巴登-符腾堡91、萨克森91。地区指数不代表订单或购买力。 【趋势表明】 切菜板属于持续有搜索需求、年末旺季明显的成熟需求。近两年主词旺季热度抬升，值得继续研究；是否能带来新品成交，仍应结合第一表的竞争与销量数据。 | O30: 【总结】 1）季节性：两个词的年末高峰同步，备货与推广应提前于11—12月；不能把平时有需求写成“无季节性”。 2）五年走势：主词2021—2025年各年最高周均在12月；对应指数71、68、66、94、100。2024—2025年的峰值高于前三年，但不是五年逐年增长。 3）地区：主词相对热度前三为汉堡100、巴伐利亚（网页译“拜仁”）96、巴登-符腾堡94；木切菜板为汉堡100、巴登-符腾堡91、萨克森91。地区指数不代表订单或购买力。 【趋势表明】 切菜板属于持续有搜索需求、年末旺季明显的成熟需求。近两年主词旺季热度抬升，值得继续研究；是否能带来新品成交，仍应结合第一表的竞争与销量数据。 | P30: 【总结】 1）季节性：两个词的年末高峰同步，备货与推广应提前于11—12月；不能把平时有需求写成“无季节性”。 2）五年走势：主词2021—2025年各年最高周均在12月；对应指数71、68、66、94、100。2024—2025年的峰值高于前三年，但不是五年逐年增长。 3）地区：主词相对热度前三为汉堡100、巴伐利亚（网页译“拜仁”）96、巴登-符腾堡94；木切菜板为汉堡100、巴登-符腾堡91、萨克森91。地区指数不代表订单或购买力。 【趋势表明】 切菜板属于持续有搜索需求、年末旺季明显的成熟需求。近两年主词旺季热度抬升，值得继续研究；是否能带来新品成交，仍应结合第一表的竞争与销量数据。 | Q30: 【总结】 1）季节性：两个词的年末高峰同步，备货与推广应提前于11—12月；不能把平时有需求写成“无季节性”。 2）五年走势：主词2021—2025年各年最高周均在12月；对应指数71、68、66、94、100。2024—2025年的峰值高于前三年，但不是五年逐年增长。 3）地区：主词相对热度前三为汉堡100、巴伐利亚（网页译“拜仁”）96、巴登-符腾堡94；木切菜板为汉堡100、巴登-符腾堡91、萨克森91。地区指数不代表订单或购买力。 【趋势表明】 切菜板属于持续有搜索需求、年末旺季明显的成熟需求。近两年主词旺季热度抬升，值得继续研究；是否能带来新品成交，仍应结合第一表的竞争与销量数据。 | R30: 【总结】 1）季节性：两个词的年末高峰同步，备货与推广应提前于11—12月；不能把平时有需求写成“无季节性”。 2）五年走势：主词2021—2025年各年最高周均在12月；对应指数71、68、66、94、100。2024—2025年的峰值高于前三年，但不是五年逐年增长。 3）地区：主词相对热度前三为汉堡100、巴伐利亚（网页译“拜仁”）96、巴登-符腾堡94；木切菜板为汉堡100、巴登-符腾堡91、萨克森91。地区指数不代表订单或购买力。 【趋势表明】 切菜板属于持续有搜索需求、年末旺季明显的成熟需求。近两年主词旺季热度抬升，值得继续研究；是否能带来新品成交，仍应结合第一表的竞争与销量数据。 | S30: 【总结】 1）季节性：两个词的年末高峰同步，备货与推广应提前于11—12月；不能把平时有需求写成“无季节性”。 2）五年走势：主词2021—2025年各年最高周均在12月；对应指数71、68、66、94、100。2024—2025年的峰值高于前三年，但不是五年逐年增长。 3）地区：主词相对热度前三为汉堡100、巴伐利亚（网页译“拜仁”）96、巴登-符腾堡94；木切菜板为汉堡100、巴登-符腾堡91、萨克森91。地区指数不代表订单或购买力。 【趋势表明】 切菜板属于持续有搜索需求、年末旺季明显的成熟需求。近两年主词旺季热度抬升，值得继续研究；是否能带来新品成交，仍应结合第一表的竞争与销量数据。 | T30: 【总结】 1）季节性：两个词的年末高峰同步，备货与推广应提前于11—12月；不能把平时有需求写成“无季节性”。 2）五年走势：主词2021—2025年各年最高周均在12月；对应指数71、68、66、94、100。2024—2025年的峰值高于前三年，但不是五年逐年增长。 3）地区：主词相对热度前三为汉堡100、巴伐利亚（网页译“拜仁”）96、巴登-符腾堡94；木切菜板为汉堡100、巴登-符腾堡91、萨克森91。地区指数不代表订单或购买力。 【趋势表明】 切菜板属于持续有搜索需求、年末旺季明显的成熟需求。近两年主词旺季热度抬升，值得继续研究；是否能带来新品成交，仍应结合第一表的竞争与销量数据。 | U30: 【总结】 1）季节性：两个词的年末高峰同步，备货与推广应提前于11—12月；不能把平时有需求写成“无季节性”。 2）五年走势：主词2021—2025年各年最高周均在12月；对应指数71、68、66、94、100。2024—2025年的峰值高于前三年，但不是五年逐年增长。 3）地区：主词相对热度前三为汉堡100、巴伐利亚（网页译“拜仁”）96、巴登-符腾堡94；木切菜板为汉堡100、巴登-符腾堡91、萨克森91。地区指数不代表订单或购买力。 【趋势表明】 切菜板属于持续有搜索需求、年末旺季明显的成熟需求。近两年主词旺季热度抬升，值得继续研究；是否能带来新品成交，仍应结合第一表的竞争与销量数据。 | V30: 【总结】 1）季节性：两个词的年末高峰同步，备货与推广应提前于11—12月；不能把平时有需求写成“无季节性”。 2）五年走势：主词2021—2025年各年最高周均在12月；对应指数71、68、66、94、100。2024—2025年的峰值高于前三年，但不是五年逐年增长。 3）地区：主词相对热度前三为汉堡100、巴伐利亚（网页译“拜仁”）96、巴登-符腾堡94；木切菜板为汉堡100、巴登-符腾堡91、萨克森91。地区指数不代表订单或购买力。 【趋势表明】 切菜板属于持续有搜索需求、年末旺季明显的成熟需求。近两年主词旺季热度抬升，值得继续研究；是否能带来新品成交，仍应结合第一表的竞争与销量数据。 | W30: 【总结】 1）季节性：两个词的年末高峰同步，备货与推广应提前于11—12月；不能把平时有需求写成“无季节性”。 2）五年走势：主词2021—2025年各年最高周均在12月；对应指数71、68、66、94、100。2024—2025年的峰值高于前三年，但不是五年逐年增长。 3）地区：主词相对热度前三为汉堡100、巴伐利亚（网页译“拜仁”）96、巴登-符腾堡94；木切菜板为汉堡100、巴登-符腾堡91、萨克森91。地区指数不代表订单或购买力。 【趋势表明】 切菜板属于持续有搜索需求、年末旺季明显的成熟需求。近两年主词旺季热度抬升，值得继续研究；是否能带来新品成交，仍应结合第一表的竞争与销量数据。 | X30: 【总结】 1）季节性：两个词的年末高峰同步，备货与推广应提前于11—12月；不能把平时有需求写成“无季节性”。 2）五年走势：主词2021—2025年各年最高周均在12月；对应指数71、68、66、94、100。2024—2025年的峰值高于前三年，但不是五年逐年增长。 3）地区：主词相对热度前三为汉堡100、巴伐利亚（网页译“拜仁”）96、巴登-符腾堡94；木切菜板为汉堡100、巴登-符腾堡91、萨克森91。地区指数不代表订单或购买力。 【趋势表明】 切菜板属于持续有搜索需求、年末旺季明显的成熟需求。近两年主词旺季热度抬升，值得继续研究；是否能带来新品成交，仍应结合第一表的竞争与销量数据。
M31: 【总结】 1）季节性：两个词的年末高峰同步，备货与推广应提前于11—12月；不能把平时有需求写成“无季节性”。 2）五年走势：主词2021—2025年各年最高周均在12月；对应指数71、68、66、94、100。2024—2025年的峰值高于前三年，但不是五年逐年增长。 3）地区：主词相对热度前三为汉堡100、巴伐利亚（网页译“拜仁”）96、巴登-符腾堡94；木切菜板为汉堡100、巴登-符腾堡91、萨克森91。地区指数不代表订单或购买力。 【趋势表明】 切菜板属于持续有搜索需求、年末旺季明显的成熟需求。近两年主词旺季热度抬升，值得继续研究；是否能带来新品成交，仍应结合第一表的竞争与销量数据。 | N31: 【总结】 1）季节性：两个词的年末高峰同步，备货与推广应提前于11—12月；不能把平时有需求写成“无季节性”。 2）五年走势：主词2021—2025年各年最高周均在12月；对应指数71、68、66、94、100。2024—2025年的峰值高于前三年，但不是五年逐年增长。 3）地区：主词相对热度前三为汉堡100、巴伐利亚（网页译“拜仁”）96、巴登-符腾堡94；木切菜板为汉堡100、巴登-符腾堡91、萨克森91。地区指数不代表订单或购买力。 【趋势表明】 切菜板属于持续有搜索需求、年末旺季明显的成熟需求。近两年主词旺季热度抬升，值得继续研究；是否能带来新品成交，仍应结合第一表的竞争与销量数据。 | O31: 【总结】 1）季节性：两个词的年末高峰同步，备货与推广应提前于11—12月；不能把平时有需求写成“无季节性”。 2）五年走势：主词2021—2025年各年最高周均在12月；对应指数71、68、66、94、100。2024—2025年的峰值高于前三年，但不是五年逐年增长。 3）地区：主词相对热度前三为汉堡100、巴伐利亚（网页译“拜仁”）96、巴登-符腾堡94；木切菜板为汉堡100、巴登-符腾堡91、萨克森91。地区指数不代表订单或购买力。 【趋势表明】 切菜板属于持续有搜索需求、年末旺季明显的成熟需求。近两年主词旺季热度抬升，值得继续研究；是否能带来新品成交，仍应结合第一表的竞争与销量数据。 | P31: 【总结】 1）季节性：两个词的年末高峰同步，备货与推广应提前于11—12月；不能把平时有需求写成“无季节性”。 2）五年走势：主词2021—2025年各年最高周均在12月；对应指数71、68、66、94、100。2024—2025年的峰值高于前三年，但不是五年逐年增长。 3）地区：主词相对热度前三为汉堡100、巴伐利亚（网页译“拜仁”）96、巴登-符腾堡94；木切菜板为汉堡100、巴登-符腾堡91、萨克森91。地区指数不代表订单或购买力。 【趋势表明】 切菜板属于持续有搜索需求、年末旺季明显的成熟需求。近两年主词旺季热度抬升，值得继续研究；是否能带来新品成交，仍应结合第一表的竞争与销量数据。 | Q31: 【总结】 1）季节性：两个词的年末高峰同步，备货与推广应提前于11—12月；不能把平时有需求写成“无季节性”。 2）五年走势：主词2021—2025年各年最高周均在12月；对应指数71、68、66、94、100。2024—2025年的峰值高于前三年，但不是五年逐年增长。 3）地区：主词相对热度前三为汉堡100、巴伐利亚（网页译“拜仁”）96、巴登-符腾堡94；木切菜板为汉堡100、巴登-符腾堡91、萨克森91。地区指数不代表订单或购买力。 【趋势表明】 切菜板属于持续有搜索需求、年末旺季明显的成熟需求。近两年主词旺季热度抬升，值得继续研究；是否能带来新品成交，仍应结合第一表的竞争与销量数据。 | R31: 【总结】 1）季节性：两个词的年末高峰同步，备货与推广应提前于11—12月；不能把平时有需求写成“无季节性”。 2）五年走势：主词2021—2025年各年最高周均在12月；对应指数71、68、66、94、100。2024—2025年的峰值高于前三年，但不是五年逐年增长。 3）地区：主词相对热度前三为汉堡100、巴伐利亚（网页译“拜仁”）96、巴登-符腾堡94；木切菜板为汉堡100、巴登-符腾堡91、萨克森91。地区指数不代表订单或购买力。 【趋势表明】 切菜板属于持续有搜索需求、年末旺季明显的成熟需求。近两年主词旺季热度抬升，值得继续研究；是否能带来新品成交，仍应结合第一表的竞争与销量数据。 | S31: 【总结】 1）季节性：两个词的年末高峰同步，备货与推广应提前于11—12月；不能把平时有需求写成“无季节性”。 2）五年走势：主词2021—2025年各年最高周均在12月；对应指数71、68、66、94、100。2024—2025年的峰值高于前三年，但不是五年逐年增长。 3）地区：主词相对热度前三为汉堡100、巴伐利亚（网页译“拜仁”）96、巴登-符腾堡94；木切菜板为汉堡100、巴登-符腾堡91、萨克森91。地区指数不代表订单或购买力。 【趋势表明】 切菜板属于持续有搜索需求、年末旺季明显的成熟需求。近两年主词旺季热度抬升，值得继续研究；是否能带来新品成交，仍应结合第一表的竞争与销量数据。 | T31: 【总结】 1）季节性：两个词的年末高峰同步，备货与推广应提前于11—12月；不能把平时有需求写成“无季节性”。 2）五年走势：主词2021—2025年各年最高周均在12月；对应指数71、68、66、94、100。2024—2025年的峰值高于前三年，但不是五年逐年增长。 3）地区：主词相对热度前三为汉堡100、巴伐利亚（网页译“拜仁”）96、巴登-符腾堡94；木切菜板为汉堡100、巴登-符腾堡91、萨克森91。地区指数不代表订单或购买力。 【趋势表明】 切菜板属于持续有搜索需求、年末旺季明显的成熟需求。近两年主词旺季热度抬升，值得继续研究；是否能带来新品成交，仍应结合第一表的竞争与销量数据。 | U31: 【总结】 1）季节性：两个词的年末高峰同步，备货与推广应提前于11—12月；不能把平时有需求写成“无季节性”。 2）五年走势：主词2021—2025年各年最高周均在12月；对应指数71、68、66、94、100。2024—2025年的峰值高于前三年，但不是五年逐年增长。 3）地区：主词相对热度前三为汉堡100、巴伐利亚（网页译“拜仁”）96、巴登-符腾堡94；木切菜板为汉堡100、巴登-符腾堡91、萨克森91。地区指数不代表订单或购买力。 【趋势表明】 切菜板属于持续有搜索需求、年末旺季明显的成熟需求。近两年主词旺季热度抬升，值得继续研究；是否能带来新品成交，仍应结合第一表的竞争与销量数据。 | V31: 【总结】 1）季节性：两个词的年末高峰同步，备货与推广应提前于11—12月；不能把平时有需求写成“无季节性”。 2）五年走势：主词2021—2025年各年最高周均在12月；对应指数71、68、66、94、100。2024—2025年的峰值高于前三年，但不是五年逐年增长。 3）地区：主词相对热度前三为汉堡100、巴伐利亚（网页译“拜仁”）96、巴登-符腾堡94；木切菜板为汉堡100、巴登-符腾堡91、萨克森91。地区指数不代表订单或购买力。 【趋势表明】 切菜板属于持续有搜索需求、年末旺季明显的成熟需求。近两年主词旺季热度抬升，值得继续研究；是否能带来新品成交，仍应结合第一表的竞争与销量数据。 | W31: 【总结】 1）季节性：两个词的年末高峰同步，备货与推广应提前于11—12月；不能把平时有需求写成“无季节性”。 2）五年走势：主词2021—2025年各年最高周均在12月；对应指数71、68、66、94、100。2024—2025年的峰值高于前三年，但不是五年逐年增长。 3）地区：主词相对热度前三为汉堡100、巴伐利亚（网页译“拜仁”）96、巴登-符腾堡94；木切菜板为汉堡100、巴登-符腾堡91、萨克森91。地区指数不代表订单或购买力。 【趋势表明】 切菜板属于持续有搜索需求、年末旺季明显的成熟需求。近两年主词旺季热度抬升，值得继续研究；是否能带来新品成交，仍应结合第一表的竞争与销量数据。 | X31: 【总结】 1）季节性：两个词的年末高峰同步，备货与推广应提前于11—12月；不能把平时有需求写成“无季节性”。 2）五年走势：主词2021—2025年各年最高周均在12月；对应指数71、68、66、94、100。2024—2025年的峰值高于前三年，但不是五年逐年增长。 3）地区：主词相对热度前三为汉堡100、巴伐利亚（网页译“拜仁”）96、巴登-符腾堡94；木切菜板为汉堡100、巴登-符腾堡91、萨克森91。地区指数不代表订单或购买力。 【趋势表明】 切菜板属于持续有搜索需求、年末旺季明显的成熟需求。近两年主词旺季热度抬升，值得继续研究；是否能带来新品成交，仍应结合第一表的竞争与销量数据。
M32: 【总结】 1）季节性：两个词的年末高峰同步，备货与推广应提前于11—12月；不能把平时有需求写成“无季节性”。 2）五年走势：主词2021—2025年各年最高周均在12月；对应指数71、68、66、94、100。2024—2025年的峰值高于前三年，但不是五年逐年增长。 3）地区：主词相对热度前三为汉堡100、巴伐利亚（网页译“拜仁”）96、巴登-符腾堡94；木切菜板为汉堡100、巴登-符腾堡91、萨克森91。地区指数不代表订单或购买力。 【趋势表明】 切菜板属于持续有搜索需求、年末旺季明显的成熟需求。近两年主词旺季热度抬升，值得继续研究；是否能带来新品成交，仍应结合第一表的竞争与销量数据。 | N32: 【总结】 1）季节性：两个词的年末高峰同步，备货与推广应提前于11—12月；不能把平时有需求写成“无季节性”。 2）五年走势：主词2021—2025年各年最高周均在12月；对应指数71、68、66、94、100。2024—2025年的峰值高于前三年，但不是五年逐年增长。 3）地区：主词相对热度前三为汉堡100、巴伐利亚（网页译“拜仁”）96、巴登-符腾堡94；木切菜板为汉堡100、巴登-符腾堡91、萨克森91。地区指数不代表订单或购买力。 【趋势表明】 切菜板属于持续有搜索需求、年末旺季明显的成熟需求。近两年主词旺季热度抬升，值得继续研究；是否能带来新品成交，仍应结合第一表的竞争与销量数据。 | O32: 【总结】 1）季节性：两个词的年末高峰同步，备货与推广应提前于11—12月；不能把平时有需求写成“无季节性”。 2）五年走势：主词2021—2025年各年最高周均在12月；对应指数71、68、66、94、100。2024—2025年的峰值高于前三年，但不是五年逐年增长。 3）地区：主词相对热度前三为汉堡100、巴伐利亚（网页译“拜仁”）96、巴登-符腾堡94；木切菜板为汉堡100、巴登-符腾堡91、萨克森91。地区指数不代表订单或购买力。 【趋势表明】 切菜板属于持续有搜索需求、年末旺季明显的成熟需求。近两年主词旺季热度抬升，值得继续研究；是否能带来新品成交，仍应结合第一表的竞争与销量数据。 | P32: 【总结】 1）季节性：两个词的年末高峰同步，备货与推广应提前于11—12月；不能把平时有需求写成“无季节性”。 2）五年走势：主词2021—2025年各年最高周均在12月；对应指数71、68、66、94、100。2024—2025年的峰值高于前三年，但不是五年逐年增长。 3）地区：主词相对热度前三为汉堡100、巴伐利亚（网页译“拜仁”）96、巴登-符腾堡94；木切菜板为汉堡100、巴登-符腾堡91、萨克森91。地区指数不代表订单或购买力。 【趋势表明】 切菜板属于持续有搜索需求、年末旺季明显的成熟需求。近两年主词旺季热度抬升，值得继续研究；是否能带来新品成交，仍应结合第一表的竞争与销量数据。 | Q32: 【总结】 1）季节性：两个词的年末高峰同步，备货与推广应提前于11—12月；不能把平时有需求写成“无季节性”。 2）五年走势：主词2021—2025年各年最高周均在12月；对应指数71、68、66、94、100。2024—2025年的峰值高于前三年，但不是五年逐年增长。 3）地区：主词相对热度前三为汉堡100、巴伐利亚（网页译“拜仁”）96、巴登-符腾堡94；木切菜板为汉堡100、巴登-符腾堡91、萨克森91。地区指数不代表订单或购买力。 【趋势表明】 切菜板属于持续有搜索需求、年末旺季明显的成熟需求。近两年主词旺季热度抬升，值得继续研究；是否能带来新品成交，仍应结合第一表的竞争与销量数据。 | R32: 【总结】 1）季节性：两个词的年末高峰同步，备货与推广应提前于11—12月；不能把平时有需求写成“无季节性”。 2）五年走势：主词2021—2025年各年最高周均在12月；对应指数71、68、66、94、100。2024—2025年的峰值高于前三年，但不是五年逐年增长。 3）地区：主词相对热度前三为汉堡100、巴伐利亚（网页译“拜仁”）96、巴登-符腾堡94；木切菜板为汉堡100、巴登-符腾堡91、萨克森91。地区指数不代表订单或购买力。 【趋势表明】 切菜板属于持续有搜索需求、年末旺季明显的成熟需求。近两年主词旺季热度抬升，值得继续研究；是否能带来新品成交，仍应结合第一表的竞争与销量数据。 | S32: 【总结】 1）季节性：两个词的年末高峰同步，备货与推广应提前于11—12月；不能把平时有需求写成“无季节性”。 2）五年走势：主词2021—2025年各年最高周均在12月；对应指数71、68、66、94、100。2024—2025年的峰值高于前三年，但不是五年逐年增长。 3）地区：主词相对热度前三为汉堡100、巴伐利亚（网页译“拜仁”）96、巴登-符腾堡94；木切菜板为汉堡100、巴登-符腾堡91、萨克森91。地区指数不代表订单或购买力。 【趋势表明】 切菜板属于持续有搜索需求、年末旺季明显的成熟需求。近两年主词旺季热度抬升，值得继续研究；是否能带来新品成交，仍应结合第一表的竞争与销量数据。 | T32: 【总结】 1）季节性：两个词的年末高峰同步，备货与推广应提前于11—12月；不能把平时有需求写成“无季节性”。 2）五年走势：主词2021—2025年各年最高周均在12月；对应指数71、68、66、94、100。2024—2025年的峰值高于前三年，但不是五年逐年增长。 3）地区：主词相对热度前三为汉堡100、巴伐利亚（网页译“拜仁”）96、巴登-符腾堡94；木切菜板为汉堡100、巴登-符腾堡91、萨克森91。地区指数不代表订单或购买力。 【趋势表明】 切菜板属于持续有搜索需求、年末旺季明显的成熟需求。近两年主词旺季热度抬升，值得继续研究；是否能带来新品成交，仍应结合第一表的竞争与销量数据。 | U32: 【总结】 1）季节性：两个词的年末高峰同步，备货与推广应提前于11—12月；不能把平时有需求写成“无季节性”。 2）五年走势：主词2021—2025年各年最高周均在12月；对应指数71、68、66、94、100。2024—2025年的峰值高于前三年，但不是五年逐年增长。 3）地区：主词相对热度前三为汉堡100、巴伐利亚（网页译“拜仁”）96、巴登-符腾堡94；木切菜板为汉堡100、巴登-符腾堡91、萨克森91。地区指数不代表订单或购买力。 【趋势表明】 切菜板属于持续有搜索需求、年末旺季明显的成熟需求。近两年主词旺季热度抬升，值得继续研究；是否能带来新品成交，仍应结合第一表的竞争与销量数据。 | V32: 【总结】 1）季节性：两个词的年末高峰同步，备货与推广应提前于11—12月；不能把平时有需求写成“无季节性”。 2）五年走势：主词2021—2025年各年最高周均在12月；对应指数71、68、66、94、100。2024—2025年的峰值高于前三年，但不是五年逐年增长。 3）地区：主词相对热度前三为汉堡100、巴伐利亚（网页译“拜仁”）96、巴登-符腾堡94；木切菜板为汉堡100、巴登-符腾堡91、萨克森91。地区指数不代表订单或购买力。 【趋势表明】 切菜板属于持续有搜索需求、年末旺季明显的成熟需求。近两年主词旺季热度抬升，值得继续研究；是否能带来新品成交，仍应结合第一表的竞争与销量数据。 | W32: 【总结】 1）季节性：两个词的年末高峰同步，备货与推广应提前于11—12月；不能把平时有需求写成“无季节性”。 2）五年走势：主词2021—2025年各年最高周均在12月；对应指数71、68、66、94、100。2024—2025年的峰值高于前三年，但不是五年逐年增长。 3）地区：主词相对热度前三为汉堡100、巴伐利亚（网页译“拜仁”）96、巴登-符腾堡94；木切菜板为汉堡100、巴登-符腾堡91、萨克森91。地区指数不代表订单或购买力。 【趋势表明】 切菜板属于持续有搜索需求、年末旺季明显的成熟需求。近两年主词旺季热度抬升，值得继续研究；是否能带来新品成交，仍应结合第一表的竞争与销量数据。 | X32: 【总结】 1）季节性：两个词的年末高峰同步，备货与推广应提前于11—12月；不能把平时有需求写成“无季节性”。 2）五年走势：主词2021—2025年各年最高周均在12月；对应指数71、68、66、94、100。2024—2025年的峰值高于前三年，但不是五年逐年增长。 3）地区：主词相对热度前三为汉堡100、巴伐利亚（网页译“拜仁”）96、巴登-符腾堡94；木切菜板为汉堡100、巴登-符腾堡91、萨克森91。地区指数不代表订单或购买力。 【趋势表明】 切菜板属于持续有搜索需求、年末旺季明显的成熟需求。近两年主词旺季热度抬升，值得继续研究；是否能带来新品成交，仍应结合第一表的竞争与销量数据。
M33: 【总结】 1）季节性：两个词的年末高峰同步，备货与推广应提前于11—12月；不能把平时有需求写成“无季节性”。 2）五年走势：主词2021—2025年各年最高周均在12月；对应指数71、68、66、94、100。2024—2025年的峰值高于前三年，但不是五年逐年增长。 3）地区：主词相对热度前三为汉堡100、巴伐利亚（网页译“拜仁”）96、巴登-符腾堡94；木切菜板为汉堡100、巴登-符腾堡91、萨克森91。地区指数不代表订单或购买力。 【趋势表明】 切菜板属于持续有搜索需求、年末旺季明显的成熟需求。近两年主词旺季热度抬升，值得继续研究；是否能带来新品成交，仍应结合第一表的竞争与销量数据。 | N33: 【总结】 1）季节性：两个词的年末高峰同步，备货与推广应提前于11—12月；不能把平时有需求写成“无季节性”。 2）五年走势：主词2021—2025年各年最高周均在12月；对应指数71、68、66、94、100。2024—2025年的峰值高于前三年，但不是五年逐年增长。 3）地区：主词相对热度前三为汉堡100、巴伐利亚（网页译“拜仁”）96、巴登-符腾堡94；木切菜板为汉堡100、巴登-符腾堡91、萨克森91。地区指数不代表订单或购买力。 【趋势表明】 切菜板属于持续有搜索需求、年末旺季明显的成熟需求。近两年主词旺季热度抬升，值得继续研究；是否能带来新品成交，仍应结合第一表的竞争与销量数据。 | O33: 【总结】 1）季节性：两个词的年末高峰同步，备货与推广应提前于11—12月；不能把平时有需求写成“无季节性”。 2）五年走势：主词2021—2025年各年最高周均在12月；对应指数71、68、66、94、100。2024—2025年的峰值高于前三年，但不是五年逐年增长。 3）地区：主词相对热度前三为汉堡100、巴伐利亚（网页译“拜仁”）96、巴登-符腾堡94；木切菜板为汉堡100、巴登-符腾堡91、萨克森91。地区指数不代表订单或购买力。 【趋势表明】 切菜板属于持续有搜索需求、年末旺季明显的成熟需求。近两年主词旺季热度抬升，值得继续研究；是否能带来新品成交，仍应结合第一表的竞争与销量数据。 | P33: 【总结】 1）季节性：两个词的年末高峰同步，备货与推广应提前于11—12月；不能把平时有需求写成“无季节性”。 2）五年走势：主词2021—2025年各年最高周均在12月；对应指数71、68、66、94、100。2024—2025年的峰值高于前三年，但不是五年逐年增长。 3）地区：主词相对热度前三为汉堡100、巴伐利亚（网页译“拜仁”）96、巴登-符腾堡94；木切菜板为汉堡100、巴登-符腾堡91、萨克森91。地区指数不代表订单或购买力。 【趋势表明】 切菜板属于持续有搜索需求、年末旺季明显的成熟需求。近两年主词旺季热度抬升，值得继续研究；是否能带来新品成交，仍应结合第一表的竞争与销量数据。 | Q33: 【总结】 1）季节性：两个词的年末高峰同步，备货与推广应提前于11—12月；不能把平时有需求写成“无季节性”。 2）五年走势：主词2021—2025年各年最高周均在12月；对应指数71、68、66、94、100。2024—2025年的峰值高于前三年，但不是五年逐年增长。 3）地区：主词相对热度前三为汉堡100、巴伐利亚（网页译“拜仁”）96、巴登-符腾堡94；木切菜板为汉堡100、巴登-符腾堡91、萨克森91。地区指数不代表订单或购买力。 【趋势表明】 切菜板属于持续有搜索需求、年末旺季明显的成熟需求。近两年主词旺季热度抬升，值得继续研究；是否能带来新品成交，仍应结合第一表的竞争与销量数据。 | R33: 【总结】 1）季节性：两个词的年末高峰同步，备货与推广应提前于11—12月；不能把平时有需求写成“无季节性”。 2）五年走势：主词2021—2025年各年最高周均在12月；对应指数71、68、66、94、100。2024—2025年的峰值高于前三年，但不是五年逐年增长。 3）地区：主词相对热度前三为汉堡100、巴伐利亚（网页译“拜仁”）96、巴登-符腾堡94；木切菜板为汉堡100、巴登-符腾堡91、萨克森91。地区指数不代表订单或购买力。 【趋势表明】 切菜板属于持续有搜索需求、年末旺季明显的成熟需求。近两年主词旺季热度抬升，值得继续研究；是否能带来新品成交，仍应结合第一表的竞争与销量数据。 | S33: 【总结】 1）季节性：两个词的年末高峰同步，备货与推广应提前于11—12月；不能把平时有需求写成“无季节性”。 2）五年走势：主词2021—2025年各年最高周均在12月；对应指数71、68、66、94、100。2024—2025年的峰值高于前三年，但不是五年逐年增长。 3）地区：主词相对热度前三为汉堡100、巴伐利亚（网页译“拜仁”）96、巴登-符腾堡94；木切菜板为汉堡100、巴登-符腾堡91、萨克森91。地区指数不代表订单或购买力。 【趋势表明】 切菜板属于持续有搜索需求、年末旺季明显的成熟需求。近两年主词旺季热度抬升，值得继续研究；是否能带来新品成交，仍应结合第一表的竞争与销量数据。 | T33: 【总结】 1）季节性：两个词的年末高峰同步，备货与推广应提前于11—12月；不能把平时有需求写成“无季节性”。 2）五年走势：主词2021—2025年各年最高周均在12月；对应指数71、68、66、94、100。2024—2025年的峰值高于前三年，但不是五年逐年增长。 3）地区：主词相对热度前三为汉堡100、巴伐利亚（网页译“拜仁”）96、巴登-符腾堡94；木切菜板为汉堡100、巴登-符腾堡91、萨克森91。地区指数不代表订单或购买力。 【趋势表明】 切菜板属于持续有搜索需求、年末旺季明显的成熟需求。近两年主词旺季热度抬升，值得继续研究；是否能带来新品成交，仍应结合第一表的竞争与销量数据。 | U33: 【总结】 1）季节性：两个词的年末高峰同步，备货与推广应提前于11—12月；不能把平时有需求写成“无季节性”。 2）五年走势：主词2021—2025年各年最高周均在12月；对应指数71、68、66、94、100。2024—2025年的峰值高于前三年，但不是五年逐年增长。 3）地区：主词相对热度前三为汉堡100、巴伐利亚（网页译“拜仁”）96、巴登-符腾堡94；木切菜板为汉堡100、巴登-符腾堡91、萨克森91。地区指数不代表订单或购买力。 【趋势表明】 切菜板属于持续有搜索需求、年末旺季明显的成熟需求。近两年主词旺季热度抬升，值得继续研究；是否能带来新品成交，仍应结合第一表的竞争与销量数据。 | V33: 【总结】 1）季节性：两个词的年末高峰同步，备货与推广应提前于11—12月；不能把平时有需求写成“无季节性”。 2）五年走势：主词2021—2025年各年最高周均在12月；对应指数71、68、66、94、100。2024—2025年的峰值高于前三年，但不是五年逐年增长。 3）地区：主词相对热度前三为汉堡100、巴伐利亚（网页译“拜仁”）96、巴登-符腾堡94；木切菜板为汉堡100、巴登-符腾堡91、萨克森91。地区指数不代表订单或购买力。 【趋势表明】 切菜板属于持续有搜索需求、年末旺季明显的成熟需求。近两年主词旺季热度抬升，值得继续研究；是否能带来新品成交，仍应结合第一表的竞争与销量数据。 | W33: 【总结】 1）季节性：两个词的年末高峰同步，备货与推广应提前于11—12月；不能把平时有需求写成“无季节性”。 2）五年走势：主词2021—2025年各年最高周均在12月；对应指数71、68、66、94、100。2024—2025年的峰值高于前三年，但不是五年逐年增长。 3）地区：主词相对热度前三为汉堡100、巴伐利亚（网页译“拜仁”）96、巴登-符腾堡94；木切菜板为汉堡100、巴登-符腾堡91、萨克森91。地区指数不代表订单或购买力。 【趋势表明】 切菜板属于持续有搜索需求、年末旺季明显的成熟需求。近两年主词旺季热度抬升，值得继续研究；是否能带来新品成交，仍应结合第一表的竞争与销量数据。 | X33: 【总结】 1）季节性：两个词的年末高峰同步，备货与推广应提前于11—12月；不能把平时有需求写成“无季节性”。 2）五年走势：主词2021—2025年各年最高周均在12月；对应指数71、68、66、94、100。2024—2025年的峰值高于前三年，但不是五年逐年增长。 3）地区：主词相对热度前三为汉堡100、巴伐利亚（网页译“拜仁”）96、巴登-符腾堡94；木切菜板为汉堡100、巴登-符腾堡91、萨克森91。地区指数不代表订单或购买力。 【趋势表明】 切菜板属于持续有搜索需求、年末旺季明显的成熟需求。近两年主词旺季热度抬升，值得继续研究；是否能带来新品成交，仍应结合第一表的竞争与销量数据。
M34: 【总结】 1）季节性：两个词的年末高峰同步，备货与推广应提前于11—12月；不能把平时有需求写成“无季节性”。 2）五年走势：主词2021—2025年各年最高周均在12月；对应指数71、68、66、94、100。2024—2025年的峰值高于前三年，但不是五年逐年增长。 3）地区：主词相对热度前三为汉堡100、巴伐利亚（网页译“拜仁”）96、巴登-符腾堡94；木切菜板为汉堡100、巴登-符腾堡91、萨克森91。地区指数不代表订单或购买力。 【趋势表明】 切菜板属于持续有搜索需求、年末旺季明显的成熟需求。近两年主词旺季热度抬升，值得继续研究；是否能带来新品成交，仍应结合第一表的竞争与销量数据。 | N34: 【总结】 1）季节性：两个词的年末高峰同步，备货与推广应提前于11—12月；不能把平时有需求写成“无季节性”。 2）五年走势：主词2021—2025年各年最高周均在12月；对应指数71、68、66、94、100。2024—2025年的峰值高于前三年，但不是五年逐年增长。 3）地区：主词相对热度前三为汉堡100、巴伐利亚（网页译“拜仁”）96、巴登-符腾堡94；木切菜板为汉堡100、巴登-符腾堡91、萨克森91。地区指数不代表订单或购买力。 【趋势表明】 切菜板属于持续有搜索需求、年末旺季明显的成熟需求。近两年主词旺季热度抬升，值得继续研究；是否能带来新品成交，仍应结合第一表的竞争与销量数据。 | O34: 【总结】 1）季节性：两个词的年末高峰同步，备货与推广应提前于11—12月；不能把平时有需求写成“无季节性”。 2）五年走势：主词2021—2025年各年最高周均在12月；对应指数71、68、66、94、100。2024—2025年的峰值高于前三年，但不是五年逐年增长。 3）地区：主词相对热度前三为汉堡100、巴伐利亚（网页译“拜仁”）96、巴登-符腾堡94；木切菜板为汉堡100、巴登-符腾堡91、萨克森91。地区指数不代表订单或购买力。 【趋势表明】 切菜板属于持续有搜索需求、年末旺季明显的成熟需求。近两年主词旺季热度抬升，值得继续研究；是否能带来新品成交，仍应结合第一表的竞争与销量数据。 | P34: 【总结】 1）季节性：两个词的年末高峰同步，备货与推广应提前于11—12月；不能把平时有需求写成“无季节性”。 2）五年走势：主词2021—2025年各年最高周均在12月；对应指数71、68、66、94、100。2024—2025年的峰值高于前三年，但不是五年逐年增长。 3）地区：主词相对热度前三为汉堡100、巴伐利亚（网页译“拜仁”）96、巴登-符腾堡94；木切菜板为汉堡100、巴登-符腾堡91、萨克森91。地区指数不代表订单或购买力。 【趋势表明】 切菜板属于持续有搜索需求、年末旺季明显的成熟需求。近两年主词旺季热度抬升，值得继续研究；是否能带来新品成交，仍应结合第一表的竞争与销量数据。 | Q34: 【总结】 1）季节性：两个词的年末高峰同步，备货与推广应提前于11—12月；不能把平时有需求写成“无季节性”。 2）五年走势：主词2021—2025年各年最高周均在12月；对应指数71、68、66、94、100。2024—2025年的峰值高于前三年，但不是五年逐年增长。 3）地区：主词相对热度前三为汉堡100、巴伐利亚（网页译“拜仁”）96、巴登-符腾堡94；木切菜板为汉堡100、巴登-符腾堡91、萨克森91。地区指数不代表订单或购买力。 【趋势表明】 切菜板属于持续有搜索需求、年末旺季明显的成熟需求。近两年主词旺季热度抬升，值得继续研究；是否能带来新品成交，仍应结合第一表的竞争与销量数据。 | R34: 【总结】 1）季节性：两个词的年末高峰同步，备货与推广应提前于11—12月；不能把平时有需求写成“无季节性”。 2）五年走势：主词2021—2025年各年最高周均在12月；对应指数71、68、66、94、100。2024—2025年的峰值高于前三年，但不是五年逐年增长。 3）地区：主词相对热度前三为汉堡100、巴伐利亚（网页译“拜仁”）96、巴登-符腾堡94；木切菜板为汉堡100、巴登-符腾堡91、萨克森91。地区指数不代表订单或购买力。 【趋势表明】 切菜板属于持续有搜索需求、年末旺季明显的成熟需求。近两年主词旺季热度抬升，值得继续研究；是否能带来新品成交，仍应结合第一表的竞争与销量数据。 | S34: 【总结】 1）季节性：两个词的年末高峰同步，备货与推广应提前于11—12月；不能把平时有需求写成“无季节性”。 2）五年走势：主词2021—2025年各年最高周均在12月；对应指数71、68、66、94、100。2024—2025年的峰值高于前三年，但不是五年逐年增长。 3）地区：主词相对热度前三为汉堡100、巴伐利亚（网页译“拜仁”）96、巴登-符腾堡94；木切菜板为汉堡100、巴登-符腾堡91、萨克森91。地区指数不代表订单或购买力。 【趋势表明】 切菜板属于持续有搜索需求、年末旺季明显的成熟需求。近两年主词旺季热度抬升，值得继续研究；是否能带来新品成交，仍应结合第一表的竞争与销量数据。 | T34: 【总结】 1）季节性：两个词的年末高峰同步，备货与推广应提前于11—12月；不能把平时有需求写成“无季节性”。 2）五年走势：主词2021—2025年各年最高周均在12月；对应指数71、68、66、94、100。2024—2025年的峰值高于前三年，但不是五年逐年增长。 3）地区：主词相对热度前三为汉堡100、巴伐利亚（网页译“拜仁”）96、巴登-符腾堡94；木切菜板为汉堡100、巴登-符腾堡91、萨克森91。地区指数不代表订单或购买力。 【趋势表明】 切菜板属于持续有搜索需求、年末旺季明显的成熟需求。近两年主词旺季热度抬升，值得继续研究；是否能带来新品成交，仍应结合第一表的竞争与销量数据。 | U34: 【总结】 1）季节性：两个词的年末高峰同步，备货与推广应提前于11—12月；不能把平时有需求写成“无季节性”。 2）五年走势：主词2021—2025年各年最高周均在12月；对应指数71、68、66、94、100。2024—2025年的峰值高于前三年，但不是五年逐年增长。 3）地区：主词相对热度前三为汉堡100、巴伐利亚（网页译“拜仁”）96、巴登-符腾堡94；木切菜板为汉堡100、巴登-符腾堡91、萨克森91。地区指数不代表订单或购买力。 【趋势表明】 切菜板属于持续有搜索需求、年末旺季明显的成熟需求。近两年主词旺季热度抬升，值得继续研究；是否能带来新品成交，仍应结合第一表的竞争与销量数据。 | V34: 【总结】 1）季节性：两个词的年末高峰同步，备货与推广应提前于11—12月；不能把平时有需求写成“无季节性”。 2）五年走势：主词2021—2025年各年最高周均在12月；对应指数71、68、66、94、100。2024—2025年的峰值高于前三年，但不是五年逐年增长。 3）地区：主词相对热度前三为汉堡100、巴伐利亚（网页译“拜仁”）96、巴登-符腾堡94；木切菜板为汉堡100、巴登-符腾堡91、萨克森91。地区指数不代表订单或购买力。 【趋势表明】 切菜板属于持续有搜索需求、年末旺季明显的成熟需求。近两年主词旺季热度抬升，值得继续研究；是否能带来新品成交，仍应结合第一表的竞争与销量数据。 | W34: 【总结】 1）季节性：两个词的年末高峰同步，备货与推广应提前于11—12月；不能把平时有需求写成“无季节性”。 2）五年走势：主词2021—2025年各年最高周均在12月；对应指数71、68、66、94、100。2024—2025年的峰值高于前三年，但不是五年逐年增长。 3）地区：主词相对热度前三为汉堡100、巴伐利亚（网页译“拜仁”）96、巴登-符腾堡94；木切菜板为汉堡100、巴登-符腾堡91、萨克森91。地区指数不代表订单或购买力。 【趋势表明】 切菜板属于持续有搜索需求、年末旺季明显的成熟需求。近两年主词旺季热度抬升，值得继续研究；是否能带来新品成交，仍应结合第一表的竞争与销量数据。 | X34: 【总结】 1）季节性：两个词的年末高峰同步，备货与推广应提前于11—12月；不能把平时有需求写成“无季节性”。 2）五年走势：主词2021—2025年各年最高周均在12月；对应指数71、68、66、94、100。2024—2025年的峰值高于前三年，但不是五年逐年增长。 3）地区：主词相对热度前三为汉堡100、巴伐利亚（网页译“拜仁”）96、巴登-符腾堡94；木切菜板为汉堡100、巴登-符腾堡91、萨克森91。地区指数不代表订单或购买力。 【趋势表明】 切菜板属于持续有搜索需求、年末旺季明显的成熟需求。近两年主词旺季热度抬升，值得继续研究；是否能带来新品成交，仍应结合第一表的竞争与销量数据。
M35: 【总结】 1）季节性：两个词的年末高峰同步，备货与推广应提前于11—12月；不能把平时有需求写成“无季节性”。 2）五年走势：主词2021—2025年各年最高周均在12月；对应指数71、68、66、94、100。2024—2025年的峰值高于前三年，但不是五年逐年增长。 3）地区：主词相对热度前三为汉堡100、巴伐利亚（网页译“拜仁”）96、巴登-符腾堡94；木切菜板为汉堡100、巴登-符腾堡91、萨克森91。地区指数不代表订单或购买力。 【趋势表明】 切菜板属于持续有搜索需求、年末旺季明显的成熟需求。近两年主词旺季热度抬升，值得继续研究；是否能带来新品成交，仍应结合第一表的竞争与销量数据。 | N35: 【总结】 1）季节性：两个词的年末高峰同步，备货与推广应提前于11—12月；不能把平时有需求写成“无季节性”。 2）五年走势：主词2021—2025年各年最高周均在12月；对应指数71、68、66、94、100。2024—2025年的峰值高于前三年，但不是五年逐年增长。 3）地区：主词相对热度前三为汉堡100、巴伐利亚（网页译“拜仁”）96、巴登-符腾堡94；木切菜板为汉堡100、巴登-符腾堡91、萨克森91。地区指数不代表订单或购买力。 【趋势表明】 切菜板属于持续有搜索需求、年末旺季明显的成熟需求。近两年主词旺季热度抬升，值得继续研究；是否能带来新品成交，仍应结合第一表的竞争与销量数据。 | O35: 【总结】 1）季节性：两个词的年末高峰同步，备货与推广应提前于11—12月；不能把平时有需求写成“无季节性”。 2）五年走势：主词2021—2025年各年最高周均在12月；对应指数71、68、66、94、100。2024—2025年的峰值高于前三年，但不是五年逐年增长。 3）地区：主词相对热度前三为汉堡100、巴伐利亚（网页译“拜仁”）96、巴登-符腾堡94；木切菜板为汉堡100、巴登-符腾堡91、萨克森91。地区指数不代表订单或购买力。 【趋势表明】 切菜板属于持续有搜索需求、年末旺季明显的成熟需求。近两年主词旺季热度抬升，值得继续研究；是否能带来新品成交，仍应结合第一表的竞争与销量数据。 | P35: 【总结】 1）季节性：两个词的年末高峰同步，备货与推广应提前于11—12月；不能把平时有需求写成“无季节性”。 2）五年走势：主词2021—2025年各年最高周均在12月；对应指数71、68、66、94、100。2024—2025年的峰值高于前三年，但不是五年逐年增长。 3）地区：主词相对热度前三为汉堡100、巴伐利亚（网页译“拜仁”）96、巴登-符腾堡94；木切菜板为汉堡100、巴登-符腾堡91、萨克森91。地区指数不代表订单或购买力。 【趋势表明】 切菜板属于持续有搜索需求、年末旺季明显的成熟需求。近两年主词旺季热度抬升，值得继续研究；是否能带来新品成交，仍应结合第一表的竞争与销量数据。 | Q35: 【总结】 1）季节性：两个词的年末高峰同步，备货与推广应提前于11—12月；不能把平时有需求写成“无季节性”。 2）五年走势：主词2021—2025年各年最高周均在12月；对应指数71、68、66、94、100。2024—2025年的峰值高于前三年，但不是五年逐年增长。 3）地区：主词相对热度前三为汉堡100、巴伐利亚（网页译“拜仁”）96、巴登-符腾堡94；木切菜板为汉堡100、巴登-符腾堡91、萨克森91。地区指数不代表订单或购买力。 【趋势表明】 切菜板属于持续有搜索需求、年末旺季明显的成熟需求。近两年主词旺季热度抬升，值得继续研究；是否能带来新品成交，仍应结合第一表的竞争与销量数据。 | R35: 【总结】 1）季节性：两个词的年末高峰同步，备货与推广应提前于11—12月；不能把平时有需求写成“无季节性”。 2）五年走势：主词2021—2025年各年最高周均在12月；对应指数71、68、66、94、100。2024—2025年的峰值高于前三年，但不是五年逐年增长。 3）地区：主词相对热度前三为汉堡100、巴伐利亚（网页译“拜仁”）96、巴登-符腾堡94；木切菜板为汉堡100、巴登-符腾堡91、萨克森91。地区指数不代表订单或购买力。 【趋势表明】 切菜板属于持续有搜索需求、年末旺季明显的成熟需求。近两年主词旺季热度抬升，值得继续研究；是否能带来新品成交，仍应结合第一表的竞争与销量数据。 | S35: 【总结】 1）季节性：两个词的年末高峰同步，备货与推广应提前于11—12月；不能把平时有需求写成“无季节性”。 2）五年走势：主词2021—2025年各年最高周均在12月；对应指数71、68、66、94、100。2024—2025年的峰值高于前三年，但不是五年逐年增长。 3）地区：主词相对热度前三为汉堡100、巴伐利亚（网页译“拜仁”）96、巴登-符腾堡94；木切菜板为汉堡100、巴登-符腾堡91、萨克森91。地区指数不代表订单或购买力。 【趋势表明】 切菜板属于持续有搜索需求、年末旺季明显的成熟需求。近两年主词旺季热度抬升，值得继续研究；是否能带来新品成交，仍应结合第一表的竞争与销量数据。 | T35: 【总结】 1）季节性：两个词的年末高峰同步，备货与推广应提前于11—12月；不能把平时有需求写成“无季节性”。 2）五年走势：主词2021—2025年各年最高周均在12月；对应指数71、68、66、94、100。2024—2025年的峰值高于前三年，但不是五年逐年增长。 3）地区：主词相对热度前三为汉堡100、巴伐利亚（网页译“拜仁”）96、巴登-符腾堡94；木切菜板为汉堡100、巴登-符腾堡91、萨克森91。地区指数不代表订单或购买力。 【趋势表明】 切菜板属于持续有搜索需求、年末旺季明显的成熟需求。近两年主词旺季热度抬升，值得继续研究；是否能带来新品成交，仍应结合第一表的竞争与销量数据。 | U35: 【总结】 1）季节性：两个词的年末高峰同步，备货与推广应提前于11—12月；不能把平时有需求写成“无季节性”。 2）五年走势：主词2021—2025年各年最高周均在12月；对应指数71、68、66、94、100。2024—2025年的峰值高于前三年，但不是五年逐年增长。 3）地区：主词相对热度前三为汉堡100、巴伐利亚（网页译“拜仁”）96、巴登-符腾堡94；木切菜板为汉堡100、巴登-符腾堡91、萨克森91。地区指数不代表订单或购买力。 【趋势表明】 切菜板属于持续有搜索需求、年末旺季明显的成熟需求。近两年主词旺季热度抬升，值得继续研究；是否能带来新品成交，仍应结合第一表的竞争与销量数据。 | V35: 【总结】 1）季节性：两个词的年末高峰同步，备货与推广应提前于11—12月；不能把平时有需求写成“无季节性”。 2）五年走势：主词2021—2025年各年最高周均在12月；对应指数71、68、66、94、100。2024—2025年的峰值高于前三年，但不是五年逐年增长。 3）地区：主词相对热度前三为汉堡100、巴伐利亚（网页译“拜仁”）96、巴登-符腾堡94；木切菜板为汉堡100、巴登-符腾堡91、萨克森91。地区指数不代表订单或购买力。 【趋势表明】 切菜板属于持续有搜索需求、年末旺季明显的成熟需求。近两年主词旺季热度抬升，值得继续研究；是否能带来新品成交，仍应结合第一表的竞争与销量数据。 | W35: 【总结】 1）季节性：两个词的年末高峰同步，备货与推广应提前于11—12月；不能把平时有需求写成“无季节性”。 2）五年走势：主词2021—2025年各年最高周均在12月；对应指数71、68、66、94、100。2024—2025年的峰值高于前三年，但不是五年逐年增长。 3）地区：主词相对热度前三为汉堡100、巴伐利亚（网页译“拜仁”）96、巴登-符腾堡94；木切菜板为汉堡100、巴登-符腾堡91、萨克森91。地区指数不代表订单或购买力。 【趋势表明】 切菜板属于持续有搜索需求、年末旺季明显的成熟需求。近两年主词旺季热度抬升，值得继续研究；是否能带来新品成交，仍应结合第一表的竞争与销量数据。 | X35: 【总结】 1）季节性：两个词的年末高峰同步，备货与推广应提前于11—12月；不能把平时有需求写成“无季节性”。 2）五年走势：主词2021—2025年各年最高周均在12月；对应指数71、68、66、94、100。2024—2025年的峰值高于前三年，但不是五年逐年增长。 3）地区：主词相对热度前三为汉堡100、巴伐利亚（网页译“拜仁”）96、巴登-符腾堡94；木切菜板为汉堡100、巴登-符腾堡91、萨克森91。地区指数不代表订单或购买力。 【趋势表明】 切菜板属于持续有搜索需求、年末旺季明显的成熟需求。近两年主词旺季热度抬升，值得继续研究；是否能带来新品成交，仍应结合第一表的竞争与销量数据。
... M41: 【总结】 1）季节性：两个词的年末高峰同步，备货与推广应提前于11—12月；不能把平时有需求写成“无季节性”。 2）五年走势：主词2021—2025年各年最高周均在12月；对应指数71、68、66、94、100。2024—2025年的峰值高于前三年，但不是五年逐年增长。 3）地区：主词相对热度前三为汉堡100、巴伐利亚（网页译“拜仁”）96、巴登-符腾堡94；木切菜板为汉堡100、巴登-符腾堡91、萨克森91。地区指数不代表订单或购买力。 【趋势表明】 切菜板属于持续有搜索需求、年末旺季明显的成熟需求。近两年主词旺季热度抬升，值得继续研究；是否能带来新品成交，仍应结合第一表的竞争与销量数据。 | N41: 【总结】 1）季节性：两个词的年末高峰同步，备货与推广应提前于11—12月；不能把平时有需求写成“无季节性”。 2）五年走势：主词2021—2025年各年最高周均在12月；对应指数71、68、66、94、100。2024—2025年的峰值高于前三年，但不是五年逐年增长。 3）地区：主词相对热度前三为汉堡100、巴伐利亚（网页译“拜仁”）96、巴登-符腾堡94；木切菜板为汉堡100、巴登-符腾堡91、萨克森91。地区指数不代表订单或购买力。 【趋势表明】 切菜板属于持续有搜索需求、年末旺季明显的成熟需求。近两年主词旺季热度抬升，值得继续研究；是否能带来新品成交，仍应结合第一表的竞争与销量数据。 | O41: 【总结】 1）季节性：两个词的年末高峰同步，备货与推广应提前于11—12月；不能把平时有需求写成“无季节性”。 2）五年走势：主词2021—2025年各年最高周均在12月；对应指数71、68、66、94、100。2024—2025年的峰值高于前三年，但不是五年逐年增长。 3）地区：主词相对热度前三为汉堡100、巴伐利亚（网页译“拜仁”）96、巴登-符腾堡94；木切菜板为汉堡100、巴登-符腾堡91、萨克森91。地区指数不代表订单或购买力。 【趋势表明】 切菜板属于持续有搜索需求、年末旺季明显的成熟需求。近两年主词旺季热度抬升，值得继续研究；是否能带来新品成交，仍应结合第一表的竞争与销量数据。 | P41: 【总结】 1）季节性：两个词的年末高峰同步，备货与推广应提前于11—12月；不能把平时有需求写成“无季节性”。 2）五年走势：主词2021—2025年各年最高周均在12月；对应指数71、68、66、94、100。2024—2025年的峰值高于前三年，但不是五年逐年增长。 3）地区：主词相对热度前三为汉堡100、巴伐利亚（网页译“拜仁”）96、巴登-符腾堡94；木切菜板为汉堡100、巴登-符腾堡91、萨克森91。地区指数不代表订单或购买力。 【趋势表明】 切菜板属于持续有搜索需求、年末旺季明显的成熟需求。近两年主词旺季热度抬升，值得继续研究；是否能带来新品成交，仍应结合第一表的竞争与销量数据。 | Q41: 【总结】 1）季节性：两个词的年末高峰同步，备货与推广应提前于11—12月；不能把平时有需求写成“无季节性”。 2）五年走势：主词2021—2025年各年最高周均在12月；对应指数71、68、66、94、100。2024—2025年的峰值高于前三年，但不是五年逐年增长。 3）地区：主词相对热度前三为汉堡100、巴伐利亚（网页译“拜仁”）96、巴登-符腾堡94；木切菜板为汉堡100、巴登-符腾堡91、萨克森91。地区指数不代表订单或购买力。 【趋势表明】 切菜板属于持续有搜索需求、年末旺季明显的成熟需求。近两年主词旺季热度抬升，值得继续研究；是否能带来新品成交，仍应结合第一表的竞争与销量数据。 | R41: 【总结】 1）季节性：两个词的年末高峰同步，备货与推广应提前于11—12月；不能把平时有需求写成“无季节性”。 2）五年走势：主词2021—2025年各年最高周均在12月；对应指数71、68、66、94、100。2024—2025年的峰值高于前三年，但不是五年逐年增长。 3）地区：主词相对热度前三为汉堡100、巴伐利亚（网页译“拜仁”）96、巴登-符腾堡94；木切菜板为汉堡100、巴登-符腾堡91、萨克森91。地区指数不代表订单或购买力。 【趋势表明】 切菜板属于持续有搜索需求、年末旺季明显的成熟需求。近两年主词旺季热度抬升，值得继续研究；是否能带来新品成交，仍应结合第一表的竞争与销量数据。 | S41: 【总结】 1）季节性：两个词的年末高峰同步，备货与推广应提前于11—12月；不能把平时有需求写成“无季节性”。 2）五年走势：主词2021—2025年各年最高周均在12月；对应指数71、68、66、94、100。2024—2025年的峰值高于前三年，但不是五年逐年增长。 3）地区：主词相对热度前三为汉堡100、巴伐利亚（网页译“拜仁”）96、巴登-符腾堡94；木切菜板为汉堡100、巴登-符腾堡91、萨克森91。地区指数不代表订单或购买力。 【趋势表明】 切菜板属于持续有搜索需求、年末旺季明显的成熟需求。近两年主词旺季热度抬升，值得继续研究；是否能带来新品成交，仍应结合第一表的竞争与销量数据。 | T41: 【总结】 1）季节性：两个词的年末高峰同步，备货与推广应提前于11—12月；不能把平时有需求写成“无季节性”。 2）五年走势：主词2021—2025年各年最高周均在12月；对应指数71、68、66、94、100。2024—2025年的峰值高于前三年，但不是五年逐年增长。 3）地区：主词相对热度前三为汉堡100、巴伐利亚（网页译“拜仁”）96、巴登-符腾堡94；木切菜板为汉堡100、巴登-符腾堡91、萨克森91。地区指数不代表订单或购买力。 【趋势表明】 切菜板属于持续有搜索需求、年末旺季明显的成熟需求。近两年主词旺季热度抬升，值得继续研究；是否能带来新品成交，仍应结合第一表的竞争与销量数据。 | U41: 【总结】 1）季节性：两个词的年末高峰同步，备货与推广应提前于11—12月；不能把平时有需求写成“无季节性”。 2）五年走势：主词2021—2025年各年最高周均在12月；对应指数71、68、66、94、100。2024—2025年的峰值高于前三年，但不是五年逐年增长。 3）地区：主词相对热度前三为汉堡100、巴伐利亚（网页译“拜仁”）96、巴登-符腾堡94；木切菜板为汉堡100、巴登-符腾堡91、萨克森91。地区指数不代表订单或购买力。 【趋势表明】 切菜板属于持续有搜索需求、年末旺季明显的成熟需求。近两年主词旺季热度抬升，值得继续研究；是否能带来新品成交，仍应结合第一表的竞争与销量数据。 | V41: 【总结】 1）季节性：两个词的年末高峰同步，备货与推广应提前于11—12月；不能把平时有需求写成“无季节性”。 2）五年走势：主词2021—2025年各年最高周均在12月；对应指数71、68、66、94、100。2024—2025年的峰值高于前三年，但不是五年逐年增长。 3）地区：主词相对热度前三为汉堡100、巴伐利亚（网页译“拜仁”）96、巴登-符腾堡94；木切菜板为汉堡100、巴登-符腾堡91、萨克森91。地区指数不代表订单或购买力。 【趋势表明】 切菜板属于持续有搜索需求、年末旺季明显的成熟需求。近两年主词旺季热度抬升，值得继续研究；是否能带来新品成交，仍应结合第一表的竞争与销量数据。 | W41: 【总结】 1）季节性：两个词的年末高峰同步，备货与推广应提前于11—12月；不能把平时有需求写成“无季节性”。 2）五年走势：主词2021—2025年各年最高周均在12月；对应指数71、68、66、94、100。2024—2025年的峰值高于前三年，但不是五年逐年增长。 3）地区：主词相对热度前三为汉堡100、巴伐利亚（网页译“拜仁”）96、巴登-符腾堡94；木切菜板为汉堡100、巴登-符腾堡91、萨克森91。地区指数不代表订单或购买力。 【趋势表明】 切菜板属于持续有搜索需求、年末旺季明显的成熟需求。近两年主词旺季热度抬升，值得继续研究；是否能带来新品成交，仍应结合第一表的竞争与销量数据。 | X41: 【总结】 1）季节性：两个词的年末高峰同步，备货与推广应提前于11—12月；不能把平时有需求写成“无季节性”。 2）五年走势：主词2021—2025年各年最高周均在12月；对应指数71、68、66、94、100。2024—2025年的峰值高于前三年，但不是五年逐年增长。 3）地区：主词相对热度前三为汉堡100、巴伐利亚（网页译“拜仁”）96、巴登-符腾堡94；木切菜板为汉堡100、巴登-符腾堡91、萨克森91。地区指数不代表订单或购买力。 【趋势表明】 切菜板属于持续有搜索需求、年末旺季明显的成熟需求。近两年主词旺季热度抬升，值得继续研究；是否能带来新品成交，仍应结合第一表的竞争与销量数据。

Sheet ③站内竞争情况
A1: # | B1: 关键词 | C1: 中文翻译 | D1: 搜索量 | E1: 点击量 | F1: 购买量 | G1: 搜索转化率 | H1: 点击转化率 | I1: 建议竞价-最低 | J1: 建议竞价-推荐 | K1: 建议竞价-最高 | L1: CPA-最低 | M1: CPA-推荐 | N1: CPA-最高 | O1: ACOS-最低 | P1: ACOS-均价 | Q1: ACOS-最高 | R1: 产品均价-最低 | S1: 产品均价-均价 | T1: 产品均价-最高 | U1: top3产品转化率 | V1: top3产品转化率 | W1: top3产品转化率 | X1: ABATop3集中度-点击 | Y1: ABATop3集中度-转化
A2: 1 | B2: schneidebrett | C2: 切菜板 | D2: 20727 | E2: 6347 | F2: 665 | G2: 0.0321 | H2: 0.1048 | I2: 0.5 | J2: 0.56 | K2: 0.77 | L2: 4.771 | M2: 5.3435 | N2: 7.3473 | O2: 0.7688 | P2: 0.2206 | Q2: 0.054 | R2: 6.95 | S2: 24.22 | T2: 98.89 | U2: B07K1Y86KN:12.35% | V2: B0FCMB514Z:10.34% | W2: B0DZVK3RXR:2.75% | X2: 0.2037 | Y2: 0.1522
A3: 2 | B3: schneidebretter | C3: 切菜板（复数） | D3: 2012 | E3: 756 | F3: 84 | G3: 0.0417 | H3: 0.1111 | I3: 0.5 | J3: 0.56 | K3: 0.77 | L3: 4.5005 | M3: 5.0405 | N3: 6.9307 | O3: 0.7253 | P3: 0.2095 | Q3: 0.051 | R3: 6.95 | S3: 24.06 | T3: 98.89 | U3: B0DS8SJ8SH:18.49% | V3: B0FCMB514Z:10.5% | W3: B0FHQDQSKM:6.69% | X3: 0.2212 | Y3: 0.2333
A4: 3 | B4: schneidebrett holz | C4: 木制切菜板 | D4: 12015 | E4: 4829 | F4: 442 | G4: 0.0368 | H4: 0.0915 | I4: 0.59 | J4: 0.79 | K4: 1.08 | L4: 6.4481 | M4: 8.6339 | N4: 11.8033 | O4: 1.4414 | P4: 0.319 | Q4: 0.1235 | R4: 5.99 | S4: 27.07 | T4: 69.9 | U4: B07K1Y86KN:8.91% | V4: B0FHQDQSKM:8.31% | W4: B07TV8S14K:4.28% | X4: 0.3383 | Y4: 0.229
A5: 4 | B5: schneidebrett kunststoff | C5: 塑料砧板 | D5: 4956 | E5: 2289 | F5: 309 | G5: 0.0623 | H5: 0.135 | R5: 5.55 | S5: 18.28 | T5: 53.53 | U5: B0BRNP6QXB:13.75% | V5: B0C3HP1D7Z:12.8% | W5: B0FCMB514Z:12.21% | X5: 0.2366 | Y5: 0.2228
A6: 5 | B6: schneidebrett edelstahl | C6: 不锈钢切菜板 | D6: 4088 | E6: 2213 | F6: 198 | G6: 0.0484 | H6: 0.0895 | I6: 0.55 | J6: 0.66 | K6: 0.86 | L6: 6.1453 | M6: 7.3743 | N6: 9.6089 | O6: 1.4778 | P6: 0.2938 | Q6: 0.1123 | R6: 4.99 | S6: 25.1 | T6: 65.69 | U6: B0FVYFBN8G:8.44% | V6: B0GKQK28YC:4.98% | W6: B0GK6N6YKB:3.97% | X6: 0.3673 | Y6: 0.2488
A7: 6 | B7: titan schneidebrett | C7: 钛切菜板 | D7: 3711 | E7: 1942 | F7: 135 | G7: 0.0364 | H7: 0.0695 | I7: 0.51 | J7: 0.59 | K7: 0.81 | L7: 7.3381 | M7: 8.4892 | N7: 11.6547 | O7: 1.0625 | P7: 0.2652 | Q7: 0.1062 | R7: 7.99 | S7: 32.01 | T7: 79.9 | U7: B0H7RB9GRJ:6.4% | V7: B0FVYFBN8G:4.22% | W7: B0H8YJD6DL:3.86% | X7: 0.2772 | Y7: 0.1912
A8: 7 | B8: schneidebretter ohne mikroplastik | C8: 无微塑料砧板 | D8: 3653 | E8: 1882 | F8: 94 | G8: 0.0257 | H8: 0.0499 | I8: 0.49 | J8: 0.67 | K8: 0.78 | L8: 9.8196 | M8: 13.4269 | N8: 15.6313 | O8: 2.2416 | P8: 0.5363 | Q8: 0.2356 | R8: 5.99 | S8: 25.04 | T8: 56.99 | U8: B0BRNP6QXB:4.45% | V8: B0FJR2M8F4:2.2% | W8: B0DZVK3RXR:0.94% | X8: 0.3807 | Y8: 0.196
A9: 8 | B9: edelstahl schneidebrett | C9: 不锈钢切菜板 | D9: 2994 | E9: 1885 | F9: 123 | G9: 0.0411 | H9: 0.0653 | I9: 0.51 | J9: 0.58 | K9: 0.76 | L9: 7.8101 | M9: 8.8821 | N9: 11.6386 | O9: 1.4828 | P9: 0.3306 | Q9: 0.1269 | R9: 5.99 | S9: 26.87 | T9: 69.97 | U9: B0FM8B27BF:5.55% | V9: B0FVYFBN8G:4.12% | W9: B0GK6N6YKB:3.14% | X9: 0.3693 | Y9: 0.2154
A10: 9 | B10: everdrop schneidebrett | C10: everdrop切菜板 | D10: 2561 | E10: 1411 | F10: 22 | G10: 0.0086 | H10: 0.0156 | I10: 0.36 | J10: 0.54 | K10: 0.7 | L10: 23.0769 | M10: 34.6154 | N10: 44.8718 | O10: 3.6476 | P10: 0.9724 | Q10: 0.3463 | R10: 9.49 | S10: 35.6 | T10: 99.95 | U10: B0FJR2M8F4:0.77% | V10: B0FJR23VWK:0.77% | X10: 0.5232 | Y10: 0.1785
A11: 10 | B11: schneidebrett holzfaser | C11: 木纤维切菜板 | D11: 1950 | E11: 784 | F11: 21 | G11: 0.0108 | H11: 0.0268 | I11: 0.37 | J11: 0.57 | K11: 0.77 | L11: 13.806 | M11: 21.2687 | N11: 28.7313 | O11: 2.2412 | P11: 0.6744 | Q11: 0.2128 | R11: 9.49 | S11: 31.54 | T11: 99.95 | U11: B0G64SWBWL:1.38% | V11: B0FJR23VWK:1.29% | X11: 0.3573 | Y11: 0.0968
A12: 11 | B12: schneidebrett glas | C12: 玻璃切菜板 | D12: 1650 | E12: 731 | F12: 58 | G12: 0.0352 | H12: 0.0793 | I12: 0.4 | J12: 0.62 | K12: 0.74 | L12: 5.0441 | M12: 7.8184 | N12: 9.3317 | O12: 2.7337 | P12: 0.491 | Q12: 0.2234 | R12: 2.86 | S12: 15.92 | T12: 34.99 | U12: B0DZD9S912:5.15% | V12: B0GN3NB724:4.68% | W12: B0B57MR2JJ:2.41% | X12: 0.4627 | Y12: 0.2273
A13: 12 | B13: holzfaser schneidebrett | C13: 木质纤维砧板 | D13: 1572 | E13: 845 | F13: 24 | G13: 0.0153 | H13: 0.0284 | I13: 0.34 | J13: 0.48 | K13: 0.6 | L13: 11.9718 | M13: 16.9014 | N13: 21.1268 | O13: 1.596 | P13: 0.5291 | Q13: 0.1691 | R13: 10.59 | S13: 31.94 | T13: 99.95 | U13: B0FJR2M8F4:2.35% | V13: B0FJR23VWK:2.12% | W13: B0G64SWBWL:0.86% | X13: 0.3548 | Y13: 0.2156
A14: 13 | B14: schneidebrett titan | C14: 钛切菜板 | D14: 1378 | E14: 736 | F14: 46 | G14: 0.0334 | H14: 0.0625 | I14: 0.57 | J14: 0.67 | K14: 0.87 | L14: 9.12 | M14: 10.72 | N14: 13.92 | O14: 1.7896 | P14: 0.3339 | Q14: 0.1484 | R14: 5.99 | S14: 32.11 | T14: 72.24 | U14: B0H8YJD6DL:3.92% | V14: B0DPDKLHYM:3.85% | W14: B0GKNXSPZF:2.48% | X14: 0.2395 | Y14: 0.1323
A15: 14 | B15: holz schneidebrett | C15: 木制切菜板 | D15: 1311 | E15: 615 | F15: 53 | G15: 0.0404 | H15: 0.0862 | I15: 0.33 | J15: 0.56 | K15: 0.7 | L15: 3.8283 | M15: 6.4965 | N15: 8.1206 | O15: 0.834 | P15: 0.2026 | Q15: 0.0657 | R15: 7.79 | S15: 32.07 | T15: 98.89 | U15: B0FHQDQSKM:9.68% | V15: B07TV8S14K:6.44% | W15: B0FLXV8ZXD:3.53% | X15: 0.3698 | Y15: 0.3051
A16: 15 | B16: schneidebrett mit auffangschale | C16: 带接汁槽的砧板 | D16: 1092 | E16: 555 | F16: 28 | G16: 0.0256 | H16: 0.0505 | I16: 0.41 | J16: 0.46 | K16: 0.55 | L16: 8.1188 | M16: 9.1089 | N16: 10.8911 | O16: 1.3106 | P16: 0.2182 | Q16: 0.0759 | R16: 6.95 | S16: 41.74 | T16: 119.99 | U16: B09NRY8FSC:5.96% | V16: B078KYGCMH:2.21% | W16: B09LHXJ7PB:1.84% | X16: 0.4065 | Y16: 0.2258
A17: 16 | B17: schneidebrett set | C17: 切菜板套装 | D17: 1008 | E17: 336 | F17: 31 | G17: 0.0308 | H17: 0.0923 | I17: 0.41 | J17: 0.46 | K17: 0.55 | L17: 8.1188 | R17: 8.49 | S17: 24.76 | T17: 69.99 | U17: B0FCMB514Z:16.26% | V17: B07YH19K5N:2.04% | X17: 0.2811 | Y17: 0.1429
A18: 17 | B18: schneidebrett spülmaschinenfest | C18: 可放入洗碗机的切菜板 | D18: 933 | E18: 331 | F18: 29 | G18: 0.0311 | H18: 0.0876 | I18: 0.44 | J18: 0.61 | K18: 0.77 | L18: 5.0228 | M18: 6.9635 | N18: 8.79 | O18: 1.2547 | P18: 0.3143 | Q18: 0.1161 | R18: 5.55 | S18: 22.15 | T18: 59.99 | U18: B0DZVK3RXR:3.32% | V18: B0BRNP6QXB:2.85% | W18: B0FCMB514Z:2.85% | X18: 0.2197 | Y18: 0.075
A19: 18 | B19: stirnholz schneidebrett | C19: 端粒木砧板 | D19: 755 | E19: 395 | F19: 13 | G19: 0.0172 | H19: 0.0329 | I19: 0.16 | J19: 0.2 | K19: 0.25 | L19: 4.8632 | M19: 6.079 | N19: 7.5988 | O19: 0.6203 | P19: 0.0954 | Q19: 0.0338 | R19: 9.8 | S19: 63.7 | T19: 179.99 | U19: B0FLXV8ZXD:4.12% | V19: B0DJ7PN7NW:2.75% | W19: B07TV8S14K:2.55% | X19: 0.4331 | Y19: 0.4
A20: 19 | B20: olivenholz schneidebrett | C20: 橄榄木切菜板 | D20: 662 | E20: 385 | F20: 12 | G20: 0.0181 | H20: 0.0312 | R20: 12.5 | S20: 38.92 | T20: 149.9 | X20: 0.3538
A21: 20 | B21: schneidebrett stirnholz | C21: 端木切菜板 | D21: 616 | E21: 209 | F21: 7 | G21: 0.0114 | H21: 0.0335 | I21: 0.17 | J21: 0.23 | K21: 0.29 | L21: 5.0746 | M21: 6.8657 | N21: 8.6567 | O21: 0.7006 | P21: 0.1044 | Q21: 0.0381 | R21: 9.8 | S21: 65.79 | T21: 179.99 | X21: 0.3913
A22: 21 | B22: glas schneidebrett | C22: 玻璃砧板 | D22: 579 | E22: 278 | F22: 18 | G22: 0.0311 | H22: 0.0647 | I22: 0.56 | J22: 0.75 | K22: 0.94 | L22: 8.6553 | M22: 11.592 | N22: 14.5286 | O22: 4.0531 | P22: 0.746 | Q22: 0.3513 | R22: 2.86 | S22: 15.54 | T22: 33 | U22: B004BKYIQC:5.05% | V22: B0DZD9S912:3.42% | W22: B0B57MR2JJ:0.98% | X22: 0.5294 | Y22: 0.2142
A23: 22 | B23: schneidebrett klein | C23: 小砧板 | D23: 468 | E23: 185 | F23: 24 | G23: 0.0513 | H23: 0.1297 | I23: 0.35 | J23: 0.47 | K23: 0.65 | L23: 2.6985 | M23: 3.6237 | N23: 5.0116 | O23: 1.1727 | P23: 0.2947 | Q23: 0.1171 | R23: 3.09 | S23: 12.3 | T23: 30.95 | U23: B0DHY2HQXK:17.72% | V23: B0DP2V8XL2:5.25% | W23: B08YNB45N4:3.94% | X23: 0.2842 | Y23: 0.1785
A24: 23 | B24: schneidebrett akazienholz | C24: 相思木切菜板 | D24: 446 | E24: 136 | F24: 11 | G24: 0.0247 | H24: 0.0809 | I24: 0.28 | J24: 0.37 | K24: 0.46 | L24: 3.4611 | M24: 4.5735 | N24: 5.686 | O24: 0.6581 | P24: 0.1467 | Q24: 0.0538 | R24: 6.95 | S24: 31.18 | T24: 84.99 | U24: B01CR1L2L0:24.26% | X24: 0.28 | Y24: 0.2
A25: 24 | B25: schneidebrett öl | C25: 切菜板油 | D25: 430 | E25: 278 | F25: 53 | G25: 0.1233 | H25: 0.1906 | I25: 0.85 | J25: 1.08 | K25: 1.53 | L25: 4.4596 | M25: 5.6663 | N25: 8.0273 | O25: 0.6674 | P25: 0.3189 | Q25: 0.0887 | R25: 8.49 | S25: 17.77 | T25: 63.9 | U25: B09MS5ZV1Y:13.52% | V25: B0FDGQYL5Z:10.09% | W25: B07CYXK3T3:8.16% | X25: 0.5556 | Y25: 0.3455
A26: 25 | B26: schneidebrett eiche | C26: 橡木切菜板 | D26: 389 | E26: 178 | F26: 5 | G26: 0.0129 | H26: 0.0281 | I26: 0.28 | J26: 0.4 | K26: 0.5 | L26: 9.9644 | M26: 14.2349 | N26: 17.7936 | O26: 0.9996 | P26: 0.2646 | Q26: 0.0791 | R26: 14.24 | S26: 53.81 | T26: 179.99 | U26: B0G64ZM2XF:4.92% | X26: 0.4285 | Y26: 0.1429
A27: 26 | B27: joseph joseph schneidebrett | C27: joseph joseph 砧板 | D27: 383 | E27: 215 | F27: 11 | G27: 0.0287 | H27: 0.0512 | I27: 0.32 | J27: 0.42 | K27: 0.53 | L27: 6.25 | M27: 8.2031 | N27: 10.3516 | O27: 0.9125 | P27: 0.2184 | Q27: 0.0803 | R27: 8.99 | S27: 37.57 | T27: 102.1 | U27: B0B1DXDZK8:4.58% | V27: B0B1DTQH56:4.22% | W27: B07YH19K5N:1.48% | X27: 0.5255 | Y27: 0.2727
A28: 27 | B28: wmf schneidebrett | C28: WMF 切菜板 | D28: 371 | E28: 247 | F28: 35 | G28: 0.0943 | H28: 0.1417 | I28: 0.53 | J28: 0.69 | K28: 0.77 | L28: 3.7403 | M28: 4.8694 | N28: 5.434 | O28: 0.6094 | P28: 0.164 | Q28: 0.0707 | R28: 7.99 | S28: 29.7 | T28: 68.88 | U28: B07TV8S14K:19.27% | V28: B00I3YHJO0:13.77% | W28: B0015ZCSUE:9.17% | X28: 0.6985 | Y28: 0.7857
A29: 28 | B29: schneidebrett holz gross | C29: 大号木制切菜板 | D29: 365 | E29: 173 | F29: 11 | G29: 0.0301 | H29: 0.0636 | I29: 0.33 | J29: 0.44 | K29: 0.58 | L29: 5.1887 | M29: 6.9182 | N29: 9.1195 | O29: 0.6627 | P29: 0.1871 | Q29: 0.07 | R29: 10.44 | S29: 36.98 | T29: 98.89 | U29: B092JPBC1H:5.04% | V29: B079YCKPYW:4.47% | X29: 0.3684 | Y29: 0.2
A30: 29 | B30: silit schneidebrett | C30: silit切菜板 | D30: 348 | E30: 198 | F30: 32 | G30: 0.092 | H30: 0.1616 | I30: 0.37 | J30: 0.58 | K30: 0.82 | L30: 2.2896 | M30: 3.5891 | N30: 5.0743 | O30: 0.413 | P30: 0.1416 | Q30: 0.0561 | R30: 8.69 | S30: 25.34 | T30: 63.95 | U30: B000P5V3OC:22.02% | V30: B0883Q7N4Z:13.91% | W30: B000P0YTXE:13.34% | X30: 0.7248 | Y30: 0.65
A31: 30 | B31: schneidebrett olivenholz | C31: 橄榄木砧板 | D31: 342 | E31: 264 | F31: 8 | G31: 0.0234 | H31: 0.0303 | I31: 0.77 | J31: 1.03 | K31: 1.29 | L31: 25.4125 | M31: 33.9934 | N31: 42.5743 | O31: 2.7195 | P31: 0.8735 | Q31: 0.2268 | R31: 12.5 | S31: 38.92 | T31: 149.9 | U31: B0DP3DDM89:4.88% | X31: 0.338 | Y31: 0.1111
A32: 31 | B32: schneidebrett kunststoff groß | C32: 大型塑料砧板 | D32: 340 | E32: 187 | F32: 14 | G32: 0.0412 | H32: 0.0749 | I32: 0.48 | J32: 0.64 | K32: 0.8 | L32: 6.4085 | M32: 8.5447 | N32: 10.6809 | O32: 1.2224 | P32: 0.4031 | Q32: 0.1257 | R32: 6.99 | S32: 21.2 | T32: 67.96 | U32: B0D7HR3T18:6.42% | V32: B09TW5RTXF:5.51% | W32: B07D9SG91G:2.57% | X32: 0.2719 | Y32: 0.15
A33: 32 | B33: metall schneidebrett | C33: 金属切菜板 | D33: 316 | E33: 175 | F33: 13 | G33: 0.0411 | H33: 0.0743 | I33: 0.44 | J33: 0.76 | K33: 0.86 | L33: 5.9219 | M33: 10.2288 | N33: 11.5747 | O33: 2.0499 | P33: 0.4351 | Q33: 0.1557 | R33: 4.99 | S33: 23.51 | T33: 65.69 | U33: B0FVYFBN8G:11.15% | V33: B0GK6N6YKB:4.69% | X33: 0.4583 | Y33: 0.4375
A34: 33 | B34: ocean wash schneidebrett | C34: 海洋风切菜板 | D34: 309 | E34: 187 | F34: 8 | G34: 0.0259 | H34: 0.0428 | I34: 0.35 | J34: 0.58 | K34: 0.71 | L34: 8.1776 | M34: 13.5514 | N34: 16.5888 | O34: 0.8863 | P34: 0.3848 | Q34: 0.113 | R34: 15.29 | S34: 35.22 | T34: 119.95 | U34: B0H2MJP2XR:1.76% | X34: 0.6311 | Y34: 0.2
A35: 34 | B35: brotkasten mit schneidebrett | C35: 带切菜板的面包箱 | D35: 304 | E35: 122 | F35: 4 | G35: 0.0132 | H35: 0.0328 | I35: 0.31 | J35: 0.41 | K35: 0.55 | L35: 9.4512 | M35: 12.5 | N35: 16.7683 | O35: 0.8741 | P35: 0.3286 | Q35: 0.1564 | R35: 14.3 | S35: 38.04 | T35: 79.94 | U35: B09FF9F2BH:9.15% | X35: 0.3135 | Y35: 0.125
A36: 35 | B36: schneidebrett holz groß | C36: 大号木制切菜板 | D36: 301 | E36: 144 | F36: 9 | G36: 0.0299 | H36: 0.0625 | I36: 0.33 | J36: 0.38 | K36: 0.48 | L36: 5.28 | M36: 6.08 | N36: 7.68 | O36: 0.5088 | P36: 0.1462 | Q36: 0.0507 | R36: 11.95 | S36: 41.59 | T36: 119.92 | U36: B079YCKPYW:16.46% | V36: B092JNZ2Q1:5.49% | X36: 0.3291 | Y36: 0.4
A37: 36 | B37: glas schneidebrett spülmaschinenfest | C37: 玻璃切菜板可用洗碗机清洗 | D37: 300 | E37: 133 | F37: 9 | G37: 0.03 | H37: 0.0677 | I37: 0.37 | J37: 0.53 | K37: 0.74 | L37: 5.4653 | M37: 7.8287 | N37: 10.9306 | O37: 0.9885 | P37: 0.4318 | Q37: 0.1187 | R37: 7.92 | S37: 18.13 | T37: 65.95 | U37: B0FYDD3JGF:10.3% | V37: B0DZD9S912:7.72% | W37: B0B57MR2JJ:4.75% | X37: 0.4247 | Y37: 0.4375
A38: 37 | B38: schneidebrett papier | C38: 纸质切菜板 | D38: 288 | E38: 140 | F38: 19 | G38: 0.066 | H38: 0.1357 | I38: 0.38 | J38: 0.51 | K38: 0.64 | L38: 2.8003 | M38: 3.7583 | N38: 4.7163 | O38: 0.6274 | P38: 0.1444 | Q38: 0.0316 | R38: 5.99 | S38: 26.02 | T38: 119 | U38: B07MP9JQ4W:14.51% | V38: B083FBYHXR:10.88% | W38: B09FDV5SZZ:2.56% | X38: 0.4026 | Y38: 0.2083
A39: 38 | B39: schneidebrett personalisiert | C39: 个性化切菜板 | D39: 280 | E39: 151 | F39: 2 | G39: 0.0071 | H39: 0.0132 | I39: 0.52 | J39: 0.7 | K39: 0.88 | L39: 39.3939 | M39: 53.0303 | N39: 66.6667 | O39: 8.8828 | P39: 1.992 | Q39: 0.8853 | R39: 5.97 | S39: 26.62 | T39: 59.9 | U39: B0863VYYT4:3.13% | X39: 0.265 | Y39: 0.1429
A40: 39 | B40: akazienholz schneidebrett | C40: 金合欢木砧板 | D40: 270 | E40: 124 | F40: 8 | G40: 0.0296 | H40: 0.0645 | I40: 0.28 | J40: 0.37 | K40: 0.46 | L40: 4.3411 | M40: 5.7364 | N40: 7.1318 | O40: 0.8254 | P40: 0.1812 | Q40: 0.0675 | R40: 6.95 | S40: 31.67 | T40: 84.99 | U40: B0DP3DDM89:10.45% | V40: B071NG664G:6.27% | X40: 0.4118 | Y40: 0.2858
A41: 40 | B41: schneidebrett holz klein | C41: 小号木制切菜板 | D41: 257 | E41: 155 | F41: 26 | G41: 0.1012 | H41: 0.1677 | I41: 0.23 | J41: 0.27 | K41: 0.3 | L41: 1.3715 | M41: 1.61 | N41: 1.7889 | O41: 0.309 | P41: 0.1102 | Q41: 0.0403 | R41: 5.21 | S41: 14.62 | T41: 39.99 | U41: B01KO094L6:11.31% | V41: B0B92PB4SY:7.54% | W41: B0B5Y38ZJG:5.65% | X41: 0.3883 | Y41: 0.1904
A42: 41 | B42: schneidebrett set mit ständer | C42: 带支架的切菜板套装 | D42: 243 | E42: 113 | F42: 4 | G42: 0.0165 | H42: 0.0354 | I42: 0.22 | J42: 0.37 | K42: 0.51 | L42: 6.2147 | M42: 10.452 | N42: 14.4068 | O42: 1.3081 | P42: 0.3632 | Q42: 0.1046 | R42: 7.99 | S42: 28.78 | T42: 99.95 | U42: B08PVXG7Z5:3.66% | X42: 0.4193 | Y42: 0.2
A43: 42 | B43: schneidebretter holzfaser | C43: 木质纤维砧板 | D43: 239 | E43: 115 | F43: 3 | G43: 0.0126 | H43: 0.0261 | I43: 0.37 | J43: 0.57 | K43: 0.77 | L43: 14.1762 | M43: 21.8391 | N43: 29.5019 | O43: 2.3013 | P43: 0.6689 | Q43: 0.2185 | R43: 9.49 | S43: 32.65 | T43: 99.95 | X43: 0.4285
A44: 43 | B44: pizza schneidebrett | C44: 披萨切割板 | D44: 226 | E44: 53 | F44: 5 | G44: 0.0221 | H44: 0.0943 | I44: 0.28 | J44: 0.41 | K44: 0.51 | L44: 2.9692 | M44: 4.3478 | N44: 5.4083 | O44: 0.8837 | P44: 0.2019 | Q44: 0.0792 | R44: 4.92 | S44: 21.53 | T44: 54.9 | U44: B00CHJBBAK:34.17% | X44: 0.2759 | Y44: 0.25
A45: 44 | B45: schneidebrett mit ständer | C45: 带支架的砧板 | D45: 219 | E45: 84 | F45: 4 | G45: 0.0183 | H45: 0.0476 | I45: 0.26 | J45: 0.35 | K45: 0.44 | L45: 5.4622 | M45: 7.3529 | N45: 9.2437 | O45: 0.9203 | P45: 0.2964 | Q45: 0.1226 | R45: 7.99 | S45: 24.8 | T45: 59.99 | X45: 0.3479
A46: 45 | B46: schneidebrett holz set | C46: 木质砧板套装 | D46: 218 | E46: 85 | F46: 4 | G46: 0.0183 | H46: 0.0471 | I46: 0.39 | J46: 0.77 | K46: 1.03 | L46: 8.2803 | M46: 16.3482 | N46: 21.8684 | O46: 2.8782 | P46: 0.5265 | Q46: 0.2336 | R46: 5.68 | S46: 31.05 | T46: 69.99 | U46: B0DQLFRSV9:11.07% | X46: 0.2766 | Y46: 0.2
A47: 46 | B47: schneidebrett wmf | C47: WMF品牌切菜板 | D47: 213 | E47: 144 | F47: 14 | G47: 0.0657 | H47: 0.0972 | R47: 7.99 | S47: 28.7 | T47: 67.96 | U47: B0015ZCSUE:13.12% | V47: B07TV8S14K:3.11% | X47: 0.5822 | Y47: 0.2307
A48: 47 | B48: schneidebrett everdrop | C48: everdrop砧板 | D48: 202 | E48: 129 | F48: 2 | G48: 0.0099 | H48: 0.0155 | R48: 8.98 | S48: 33.35 | T48: 99.95 | U48: B0D93F12NV:4.59% | X48: 0.5352 | Y48: 0.25
A49: 48 | B49: schneidebrett holz mit auffangschale | C49: 带接屑盘的木制切菜板 | D49: 199 | E49: 115 | F49: 6 | G49: 0.0302 | H49: 0.0522 | I49: 0.38 | J49: 0.51 | K49: 0.64 | L49: 7.2797 | M49: 9.7701 | N49: 12.2605 | O49: 0.978 | P49: 0.2505 | Q49: 0.0814 | R49: 9.99 | S49: 39 | T49: 119.99 | U49: B09LHXJ7PB:4.57% | X49: 0.4286 | Y49: 0.125
A50: 49 | B50: schneidebrett rund | C50: 圆形切菜板 | D50: 198 | E50: 67 | F50: 3 | G50: 0.0152 | H50: 0.0448 | I50: 0.26 | J50: 0.34 | K50: 0.43 | L50: 5.8036 | M50: 7.5893 | N50: 9.5982 | O50: 1.5425 | P50: 0.4994 | Q50: 0.2056 | R50: 4.92 | S50: 15.2 | T50: 36.92 | U50: B0C46WBJRB:13.81% | V50: B0CJ8GNZ66:4.6% | X50: 0.3784 | Y50: 0.5
A51: 50 | B51: schneidebrett holz massiv | C51: 实心木制切菜板 | D51: 197 | E51: 71 | F51: 5 | G51: 0.0254 | H51: 0.0704 | R51: 14.24 | S51: 43.01 | T51: 98.89 | U51: B07TV8S14K:9.81% | V51: B0FLXV8ZXD:6.86% | X51: 0.3846 | Y51: 0.375
A52: 51 | B52: öl für schneidebrett | C52: 切菜板用油 | D52: 195 | E52: 100 | F52: 20 | G52: 0.1026 | H52: 0.2 | I52: 0.86 | J52: 1.15 | K52: 1.44 | L52: 4.3 | M52: 5.75 | N52: 7.2 | O52: 0.7278 | P52: 0.3106 | Q52: 0.09 | R52: 7.9 | S52: 18.51 | T52: 63.9 | U52: B09MS5ZV1Y:16.08% | V52: B0FDGQYL5Z:12.87% | W52: B07CYXK3T3:7.23% | X52: 0.6364 | Y52: 0.4211
A53: 52 | B53: schneidebretter mit ständer | C53: 带支架的切菜板（复数） | D53: 195 | E53: 104 | F53: 8 | G53: 0.041 | H53: 0.0769 | I53: 0.26 | J53: 0.35 | K53: 0.44 | L53: 3.381 | M53: 4.5514 | N53: 5.7217 | O53: 0.5696 | P53: 0.1483 | Q53: 0.0379 | R53: 7.99 | S53: 30.69 | T53: 119.99 | U53: B00Q6QQUNS:8.77% | V53: B0D315RCN6:8.77% | X53: 0.4035 | Y53: 0.2
A54: 53 | B54: schneidebrett ahorn | C54: 枫木切菜板 | D54: 185 | E54: 85 | F54: 3 | G54: 0.0162 | H54: 0.0353 | I54: 0.54 | J54: 0.82 | K54: 0.98 | L54: 15.2975 | M54: 23.2295 | N54: 27.762 | O54: 1.9358 | P54: 0.4343 | Q54: 0.1258 | R54: 12 | S54: 53.49 | T54: 184.6 | X54: 0.3404
A55: 54 | B55: schneidebrett glas spülmaschinenfest | C55: 可用洗碗机清洗的玻璃切菜板 | D55: 184 | E55: 105 | F55: 8 | G55: 0.0435 | H55: 0.0762 | I55: 0.43 | J55: 0.68 | K55: 0.76 | L55: 5.643 | M55: 8.9239 | N55: 9.9738 | O55: 1.4898 | P55: 0.4254 | Q55: 0.1275 | R55: 5.99 | S55: 20.98 | T55: 69.99 | U55: B0B57MR2JJ:24.56% | V55: B0DZD9S912:12.28% | X55: 0.4137 | Y55: 0.6666
A56: 55 | B56: schneidebrett walnuss | C56: 胡桃木切菜板 | D56: 182 | E56: 87 | F56: 2 | G56: 0.011 | H56: 0.023 | I56: 0.36 | J56: 0.44 | K56: 0.55 | L56: 15.6522 | M56: 19.1304 | N56: 23.913 | O56: 1.5942 | P56: 0.3369 | Q56: 0.0732 | R56: 12 | S56: 56.78 | T56: 261.42 | X56: 0.3542
A57: 56 | B57: öl schneidebrett | C57: 砧板油 | D57: 182 | E57: 96 | F57: 20 | G57: 0.1099 | H57: 0.2083 | I57: 0.32 | J57: 0.42 | K57: 0.53 | L57: 1.5362 | M57: 2.0163 | N57: 2.5444 | O57: 0.2375 | P57: 0.1123 | Q57: 0.0316 | R57: 8.49 | S57: 17.95 | T57: 63.9 | U57: B09MS5ZV1Y:25.76% | V57: B0FDGQYL5Z:18.4% | W57: B0741D4LGG:7.88% | X57: 0.5283 | Y57: 0.5
A58: 57 | B58: katori titan schneidebrett | C58: Katori钛合金砧板 | D58: 174 | E58: 55 | F58: 2 | G58: 0.0115 | H58: 0.0364 | R58: 8.98 | S58: 33.87 | T58: 79.9 | U58: B0H8YJD6DL:5.46% | X58: 0.4333 | Y58: 0.25
A59: 58 | B59: schneidebrett akazie | C59: 相思木切菜板 | D59: 160 | E59: 67 | F59: 6 | G59: 0.0375 | H59: 0.0896 | I59: 0.26 | J59: 0.35 | K59: 0.44 | L59: 2.9018 | M59: 3.9062 | N59: 4.9107 | O59: 0.562 | P59: 0.1316 | Q59: 0.0567 | R59: 6.95 | S59: 29.68 | T59: 68.88 | U59: B01CR1L2L0:24.87% | X59: 0.3783 | Y59: 0.375
A60: 59 | B60: ahorn schneidebrett | C60: 枫木砧板 | D60: 158 | E60: 80 | F60: 3 | G60: 0.019 | H60: 0.0375 | R60: 12.46 | S60: 53.11 | T60: 184.6 | X60: 0.3636
A61: 60 | B61: schneidebrett holzfaser spülmaschinenfest | C61: 木质纤维洗碗机适用砧板 | D61: 155 | E61: 85 | F61: 3 | G61: 0.0194 | H61: 0.0353 | R61: 7.99 | S61: 34.01 | T61: 99.95 | U61: B0FJR23VWK:6.91% | X61: 0.4043 | Y61: 0.1667
A62: 61 | B62: schneidebrett metall | C62: 金属砧板 | D62: 154 | E62: 105 | F62: 8 | G62: 0.0519 | H62: 0.0762 | I62: 0.71 | J62: 0.95 | K62: 1.19 | L62: 9.3176 | M62: 12.4672 | N62: 15.6168 | O62: 2.4984 | P62: 0.5353 | Q62: 0.1898 | R62: 4.99 | S62: 23.29 | T62: 65.69 | U62: B0DSHMJ5LM:7.89% | X62: 0.4656 | Y62: 0.125
A63: 62 | B63: schneidebrett titan spülmaschinenfest | C63: 钛合金洗碗机适用砧板 | D63: 152 | E63: 60 | F63: 5 | G63: 0.0329 | H63: 0.0833 | I63: 0.58 | J63: 0.71 | K63: 0.86 | L63: 6.9628 | M63: 8.5234 | N63: 10.3241 | O63: 0.9922 | P63: 0.284 | Q63: 0.1067 | R63: 8.59 | S63: 30.01 | T63: 79.9 | U63: B0GKNXSPZF:18.33% | V63: B0H8YJD6DL:9.16% | X63: 0.3939 | Y63: 0.4
A64: 63 | B64: großes schneidebrett holz | C64: 大木质切菜板 | D64: 148 | E64: 78 | F64: 6 | G64: 0.0405 | H64: 0.0769 | I64: 0.28 | J64: 0.33 | K64: 0.47 | L64: 3.6411 | M64: 4.2913 | N64: 6.1118 | O64: 0.4095 | P64: 0.1082 | Q64: 0.0358 | R64: 10.48 | S64: 39.66 | T64: 119.92 | X64: 0.3488
A65: 64 | B65: hirnholz schneidebrett | C65: 脑木砧板 | D65: 147 | E65: 60 | F65: 2 | G65: 0.0136 | H65: 0.0333 | I65: 0.68 | J65: 0.84 | K65: 0.99 | L65: 20.4204 | M65: 25.2252 | N65: 29.7297 | O65: 1.9479 | P65: 0.3724 | Q65: 0.1401 | R65: 12.95 | S65: 67.74 | T65: 179.99 | X65: 0.5151
A66: 65 | B66: schneidebrett nussbaum | C66: 胡桃木砧板 | D66: 147 | E66: 98 | F66: 2 | G66: 0.0136 | H66: 0.0204 | R66: 9.49 | S66: 57.87 | T66: 261.42 | X66: 0.3703
A67: 66 | B67: eiche schneidebrett | C67: 橡木切菜板 | D67: 145 | E67: 78 | F67: 2 | G67: 0.0138 | H67: 0.0256 | I67: 0.59 | J67: 0.78 | K67: 0.91 | L67: 23.0469 | M67: 30.4688 | N67: 35.5469 | O67: 2.1397 | P67: 0.6003 | Q67: 0.1693 | R67: 14.24 | S67: 50.75 | T67: 179.99 | X67: 0.3488
A68: 67 | B68: walnuss schneidebrett | C68: 核桃砧板 | D68: 143 | E68: 73 | F68: 1 | G68: 0.007 | H68: 0.0137 | I68: 0.57 | J68: 0.87 | K68: 0.97 | L68: 41.6058 | M68: 63.5036 | N68: 70.8029 | O68: 4.9038 | P68: 0.9868 | Q68: 0.2429 | R68: 12.95 | S68: 64.35 | T68: 261.42 | U68: B0DGTXQ5KM:4.57% | X68: 0.25 | Y68: 0.25
A69: 68 | B69: personalisiertes schneidebrett | C69: 个性化切菜板 | D69: 138 | E69: 73 | F69: 1 | G69: 0.0072 | H69: 0.0137 | I69: 0.52 | J69: 0.69 | K69: 0.86 | L69: 37.9562 | M69: 50.365 | N69: 62.7737 | O69: 8.4363 | P69: 1.9003 | Q69: 0.8396 | R69: 5.97 | S69: 26.5 | T69: 59.99 | U69: B0GPX82G1T:2.74% | X69: 0.25 | Y69: 0.2
A70: 69 | B70: schneidebrett mit gravur | C70: 带雕刻的砧板 | D70: 138 | E70: 45 | F70: 1 | G70: 0.0072 | H70: 0.0222 | I70: 0.68 | J70: 0.77 | K70: 0.91 | L70: 30.6306 | M70: 34.6847 | N70: 40.991 | O70: 5.8098 | P70: 1.3731 | Q70: 0.579 | R70: 5.97 | S70: 25.26 | T70: 59.9 | U70: B0CY4QH41Z:27.75% | X70: 0.32 | Y70: 1
A71: 70 | B71: titan schneidebrett testsieger | C71: 钛砧板测试获胜者 | D71: 133 | E71: 91 | F71: 5 | G71: 0.0376 | H71: 0.0549 | I71: 0.54 | J71: 0.69 | K71: 0.96 | L71: 9.8361 | M71: 12.5683 | N71: 17.4863 | O71: 1.4648 | P71: 0.3582 | Q71: 0.0968 | R71: 8.58 | S71: 35.09 | T71: 129.9 | U71: B0H8YJD6DL:6.86% | V71: B0H7RB9GRJ:5.49% | X71: 0.42 | Y71: 0.4
A72: 71 | B72: holz schneidebrett set | C72: 木制切菜板套装 | D72: 130 | E72: 91 | F72: 9 | G72: 0.0692 | H72: 0.0989 | I72: 0.55 | J72: 0.74 | K72: 0.93 | L72: 5.5612 | M72: 7.4823 | N72: 9.4034 | O72: 0.7019 | P72: 0.2213 | Q72: 0.0624 | R72: 10.66 | S72: 33.81 | T72: 119.99 | U72: B07K1Y86KN:19.02% | V72: B0FNQK1YHK:16.49% | X72: 0.46 | Y72: 0.6667
A73: 72 | B73: brot schneidebrett | C73: 面包切割板 | D73: 127 | E73: 55 | F73: 4 | G73: 0.0315 | H73: 0.0727 | I73: 0.54 | J73: 0.63 | K73: 0.79 | L73: 7.4278 | M73: 8.6657 | N73: 10.8666 | O73: 0.8269 | P73: 0.343 | Q73: 0.1275 | R73: 10.48 | S73: 25.26 | T73: 67.96 | U73: B008L07SGK:18.18% | V73: B0F4RHFS57:7.27% | X73: 0.7 | Y73: 0.75
A74: 73 | B74: stirnholz schneidebrett eiche | C74: 前木切菜板橡木 | D74: 118 | E74: 56 | F74: 2 | G74: 0.0169 | H74: 0.0357 | I74: 0.27 | J74: 0.36 | K74: 0.45 | L74: 7.563 | M74: 10.084 | N74: 12.605 | O74: 0.7787 | P74: 0.1397 | Q74: 0.056 | R74: 12.95 | S74: 72.21 | T74: 179.99 | X74: 0.3871
A75: 74 | B75: schneidebrett öl lebensmittelecht | C75: 食品级切菜板油 | D75: 118 | E75: 82 | F75: 19 | G75: 0.161 | H75: 0.2317 | I75: 0.36 | J75: 0.48 | K75: 0.6 | L75: 1.5537 | M75: 2.0716 | N75: 2.5896 | O75: 0.2622 | P75: 0.1159 | Q75: 0.0324 | R75: 7.9 | S75: 17.87 | T75: 63.9 | U75: B0CBSVFCH8:37.23% | V75: B09MS5ZV1Y:23.0% | W75: B0BNHTWDQJ:16.29% | X75: 0.6223 | Y75: 0.6875
A76: 75 | B76: oceanwash schneidebrett | C76: Oceanwash砧板 | D76: 115 | E76: 84 | F76: 4 | G76: 0.0348 | H76: 0.0476 | I76: 0.38 | J76: 0.47 | K76: 0.69 | L76: 7.9832 | M76: 9.8739 | N76: 14.4958 | O76: 0.7266 | P76: 0.2774 | Q76: 0.0823 | R76: 13.59 | S76: 35.59 | T76: 119.95 | U76: B0H2MJP2XR:3.65% | X76: 0.8262 | Y76: 0.5
A77: 76 | B77: wmf schneidebrett holz | C77: WMF 木制切菜板 | D77: 113 | E77: 64 | F77: 10 | G77: 0.0885 | H77: 0.1562 | R77: 12.74 | S77: 36.32 | T77: 98.89 | U77: B07TV8S14K:22.78% | X77: 0.8857 | Y77: 1
A78: 77 | B78: schneidebrett basteln | C78: 制作切菜板 | D78: 109 | E78: 45 | F78: 4 | G78: 0.0367 | H78: 0.0889 | I78: 0.65 | J78: 0.87 | K78: 1.09 | L78: 7.3116 | M78: 9.7863 | N78: 12.261 | O78: 1.6392 | P78: 0.6264 | Q78: 0.2695 | R78: 5.97 | S78: 15.62 | T78: 36.31 | U78: B07MP9JQ4W:22.23% | V78: B08HSG72ZQ:22.23% | W78: B09FDV5SZZ:6.35% | X78: 0.44 | Y78: 0.6
A79: 78 | B79: schneidebretter glas | C79: 玻璃切菜板（复数） | D79: 109 | E79: 49 | F79: 4 | G79: 0.0367 | H79: 0.0816 | I79: 0.4 | J79: 0.62 | K79: 0.74 | L79: 4.902 | M79: 7.598 | N79: 9.0686 | O79: 2.6566 | P79: 0.4696 | Q79: 0.2235 | R79: 2.86 | S79: 16.18 | T79: 33.99 | U79: B0B57MR2JJ:18.36% | V79: B0GN3NB724:13.77% | X79: 0.4814 | Y79: 0.5
A80: 79 | B80: personalisiertes schneidebrett handgefertigt | C80: 手工个性化切菜板 | D80: 105 | E80: 56 | F80: 1 | G80: 0.0095 | H80: 0.0179 | I80: 0.46 | J80: 0.63 | K80: 0.92 | L80: 25.6983 | M80: 35.1955 | N80: 51.3966 | O80: 2.7178 | P80: 1.0973 | Q80: 0.5871 | R80: 12.95 | S80: 32.07 | T80: 59.95 | U80: B0GPX82G1T:3.7% | X80: 0.3871 | Y80: 0.3333
A81: 80 | B81: stirnholz schneidebrett 60 x 40 | C81: 60x40厘米端面砧板 | D81: 95 | E81: 45 | F81: 2 | G81: 0.0211 | H81: 0.0444 | R81: 11.25 | S81: 87.9 | T81: 259.5 | X81: 0.36
A82: 81 | B82: papier schneidebrett | C82: 切纸板 | D82: 92 | E82: 47 | F82: 6 | G82: 0.0652 | H82: 0.1277 | I82: 0.2 | J82: 0.24 | K82: 0.28 | L82: 1.5662 | M82: 1.8794 | N82: 2.1926 | O82: 0.3774 | P82: 0.0846 | Q82: 0.0207 | R82: 4.98 | S82: 22.21 | T82: 90.63 | U82: B000SO78B2:16.6% | V82: B09FDV5SZZ:13.83% | X82: 0.5769 | Y82: 0.5
A83: 82 | B83: schneidebrett holz personalisiert | C83: 个性化木质砧板 | D83: 87 | E83: 49 | F83: 1 | G83: 0.0115 | H83: 0.0204 | I83: 0.26 | J83: 0.34 | K83: 0.43 | L83: 12.7451 | M83: 16.6667 | N83: 21.0784 | O83: 3.199 | P83: 0.594 | Q83: 0.2384 | R83: 5.21 | S83: 28.06 | T83: 69.9 | X83: 0.3333
A84: 83 | B84: schneidebrett klein holz | C84: 小型木质砧板 | D84: 81 | E84: 60 | F84: 6 | G84: 0.0741 | H84: 0.1 | I84: 0.25 | J84: 0.33 | K84: 0.46 | L84: 2.5 | M84: 3.3 | N84: 4.6 | O84: 0.6334 | P84: 0.2293 | Q84: 0.0825 | R84: 5.21 | S84: 14.39 | T84: 39.99 | U84: B01KO09DLW:18.34% | V84: B01CR1L1GQ:18.33% | X84: 0.3939 | Y84: 0.5
A85: 84 | B85: glas schneidebretter | C85: 玻璃砧板（复数） | D85: 77 | E85: 49 | F85: 4 | G85: 0.0519 | H85: 0.0816 | I85: 0.2 | J85: 0.32 | K85: 0.37 | L85: 2.451 | M85: 3.9216 | N85: 4.5343 | O85: 1.3712 | P85: 0.2489 | Q85: 0.1154 | R85: 2.86 | S85: 15.76 | T85: 33.99 | U85: B004BKYIQC:18.36% | V85: B0DZD9S912:12.24% | X85: 0.4074 | Y85: 0.3334
A86: 85 | B86: stahl schneidebrett | C86: 钢制砧板 | D86: 64 | E86: 49 | F86: 2 | G86: 0.0312 | H86: 0.0408 | I86: 0.49 | J86: 0.62 | K86: 0.85 | L86: 12.0098 | M86: 15.1961 | N86: 20.8333 | O86: 2.5369 | P86: 0.6785 | Q86: 0.3045 | R86: 5.99 | S86: 22.4 | T86: 49.9 | U86: B0DZVK3RXR:18.35% | X86: 0.5926 | Y86: 0.3333
A87: 86 | B87: brotkasten | C87: 面包箱 | D87: 25577 | E87: 7351 | F87: 295 | G87: 0.0115 | H87: 0.0401 | I87: 0.35 | J87: 0.47 | K87: 0.59 | L87: 8.7282 | M87: 11.7207 | N87: 14.7132 | O87: 0.8196 | P87: 0.2882 | Q87: 0.1173 | R87: 14.3 | S87: 40.67 | T87: 99.95 | U87: B0D929JF1C:2.45% | V87: B08DFBTQ62:1.75% | W87: B0F92FQ6VJ:1.48% | X87: 0.1736 | Y87: 0.0816
A88: 87 | B88: papierschneider | C88: 切纸器 | D88: 4833 | E88: 2831 | F88: 379 | G88: 0.0784 | H88: 0.1339 | I88: 0.62 | J88: 0.83 | K88: 1.04 | L88: 4.6303 | M88: 6.1987 | N88: 7.767 | O88: 1.2447 | P88: 0.1677 | Q88: 0.0314 | R88: 4.98 | S88: 36.97 | T88: 197.45 | U88: B07QP5TJ9K:16.69% | V88: B09FDV5SZZ:9.02% | W88: B0CLNVM6ZS:8.87% | X88: 0.3751 | Y88: 0.3032
A89: 88 | B89: frühstücksbrettchen | C89: 早餐板 | D89: 8184 | E89: 2520 | F89: 200 | G89: 0.0244 | H89: 0.0794 | I89: 0.29 | J89: 0.32 | K89: 0.4 | L89: 3.6524 | M89: 4.0302 | N89: 5.0378 | O89: 0.5766 | P89: 0.2215 | Q89: 0.0761 | R89: 6.99 | S89: 18.2 | T89: 52.99 | U89: B0BKKS5T1V:7.32% | V89: B0DJVVH9FL:5.05% | W89: B0996212XY:1.05% | X89: 0.2302 | Y89: 0.1429
A90: 89 | B90: brotbox | C90: 面包盒 | D90: 4643 | E90: 1904 | F90: 108 | G90: 0.0233 | H90: 0.0567 | I90: 0.2 | J90: 0.25 | K90: 0.29 | L90: 3.5273 | M90: 4.4092 | N90: 5.1146 | O90: 0.4926 | P90: 0.1704 | Q90: 0.0441 | R90: 8.95 | S90: 25.88 | T90: 99.95 | U90: B0F92FQ6VJ:4.56% | V90: B0D92258M8:4.46% | W90: B08DFBTQ62:1.25% | X90: 0.1719 | Y90: 0.0977
A91: 90 | B91: holzbrett | C91: 木板 | D91: 5339 | E91: 1818 | F91: 178 | G91: 0.0333 | H91: 0.0979 | I91: 0.36 | J91: 0.42 | K91: 0.55 | L91: 3.6772 | M91: 4.2901 | N91: 5.618 | O91: 0.7186 | P91: 0.1661 | Q91: 0.0617 | R91: 5.97 | S91: 25.82 | T91: 69.56 | U91: B0FHQDQSKM:11.77% | V91: B071KVB5WY:5.2% | W91: B07TV8S14K:2.77% | X91: 0.241 | Y91: 0.164
A92: 91 | B92: holzbrett küche | C92: 厨房木板 | D92: 2706 | E92: 1260 | F92: 138 | G92: 0.051 | H92: 0.1095 | I92: 0.81 | J92: 1.08 | K92: 1.35 | L92: 7.3973 | M92: 9.863 | N92: 12.3288 | O92: 1.6521 | P92: 0.4012 | Q92: 0.1644 | R92: 5.97 | S92: 24.58 | T92: 59.99 | U92: B0FHQDQSKM:12.68% | V92: B071KVB5WY:9.45% | W92: B09TR5S57G:5.81% | X92: 0.2857 | Y92: 0.2662
A93: 92 | B93: pizzabrett | C93: 披萨板 | D93: 2274 | E93: 955 | F93: 88 | G93: 0.0387 | H93: 0.0921 | I93: 0.33 | J93: 0.44 | K93: 0.55 | L93: 3.5831 | M93: 4.7774 | N93: 5.9718 | O93: 0.5979 | P93: 0.2074 | Q93: 0.087 | R93: 7.99 | S93: 23.04 | T93: 54.9 | U93: B01N0UY3QC:9.13% | V93: B096G33XPV:9.03% | W93: B0CXDZ36TV:2.88% | X93: 0.3295 | Y93: 0.2738
A94: 93 | B94: brotkasten holz | C94: 木制面包箱 | D94: 2430 | E94: 904 | F94: 56 | G94: 0.023 | H94: 0.0619 | I94: 0.19 | J94: 0.25 | K94: 0.31 | L94: 3.0695 | M94: 4.0388 | N94: 5.0081 | O94: 0.2694 | P94: 0.1302 | Q94: 0.0577 | R94: 14.99 | S94: 31.01 | T94: 69.95 | U94: B00CS3PNWM:7.37% | V94: B0CJVHKJ1W:2.52% | X94: 0.3058 | Y94: 0.1806
A95: 94 | B95: cutting board | C95: 切菜板 | D95: 1950 | E95: 831 | F95: 68 | G95: 0.0349 | H95: 0.0818 | I95: 0.73 | J95: 0.97 | K95: 1.21 | L95: 8.9242 | M95: 11.8582 | N95: 14.7922 | O95: 2.0877 | P95: 0.5382 | Q95: 0.1977 | R95: 5.68 | S95: 22.04 | T95: 59.99 | U95: B07K1Y86KN:8.81% | V95: B0DZVK3RXR:3.61% | X95: 0.291 | Y95: 0.1642
A96: 95 | B96: papierschneidemaschine | C96: 切纸机 | D96: 1440 | E96: 815 | F96: 108 | G96: 0.075 | H96: 0.1325 | I96: 0.48 | J96: 0.68 | K96: 0.93 | L96: 3.6226 | M96: 5.1321 | N96: 7.0189 | O96: 0.8568 | P96: 0.1225 | Q96: 0.0215 | R96: 5.99 | S96: 41.89 | T96: 239 | U96: B000SO78B2:8.54% | V96: B0CLNVM6ZS:7.01% | W96: B09FDV5SZZ:4.32% | X96: 0.3593 | Y96: 0.1681
A97: 96 | B97: holzschneidebrett | C97: 木制切菜板 | D97: 1596 | E97: 760 | F97: 77 | G97: 0.0482 | H97: 0.1013 | I97: 0.55 | J97: 0.74 | K97: 0.97 | L97: 5.4294 | M97: 7.305 | N97: 9.5755 | O97: 1.0511 | P97: 0.258 | Q97: 0.1218 | R97: 6.95 | S97: 28.32 | T97: 59.99 | U97: B07K1Y86KN:16.13% | V97: B0FHQDQSKM:7.01% | W97: B07TV8S14K:3.13% | X97: 0.3396 | Y97: 0.2555
A98: 97 | B98: schneidemaschine | C98: 切割机 | D98: 1509 | E98: 704 | F98: 86 | G98: 0.057 | H98: 0.1222 | I98: 0.47 | J98: 0.82 | K98: 0.91 | L98: 3.8462 | M98: 6.7103 | N98: 7.4468 | O98: 0.7617 | P98: 0.0835 | Q98: 0.0198 | R98: 8.81 | S98: 80.37 | T98: 339 | U98: B09FDV5SZZ:10.98% | V98: B000SO78B2:5.05% | W98: B0CMQTW6MH:3.56% | X98: 0.3617 | Y98: 0.2237
A99: 98 | B99: schneidemaschine papier | C99: 纸张切割机 | D99: 1172 | E99: 669 | F99: 100 | G99: 0.0853 | H99: 0.1495 | I99: 0.38 | J99: 0.51 | K99: 0.64 | L99: 2.5418 | M99: 3.4114 | N99: 4.2809 | O99: 0.685 | P99: 0.1032 | Q99: 0.0234 | R99: 4.98 | S99: 33.06 | T99: 145.99 | U99: B000SO78B2:15.43% | V99: B09FDV5SZZ:11.78% | W99: B0CLNVM6ZS:10.76% | X99: 0.4837 | Y99: 0.413
A100: 99 | B100: schneidbrett | C100: 切菜板 | D100: 1584 | E100: 636 | F100: 78 | G100: 0.0492 | H100: 0.1226 | R100: 7.95 | S100: 22.35 | T100: 59.99 | U100: B0BRNP6QXB:13.63% | V100: B07TV8S14K:5.72% | W100: B0DZVK3RXR:2.31% | X100: 0.22 | Y100: 0.1167
...

Sheet ④top100打标数据
A1: 图片 | B1: ASIN（商品编号） | C1: PASIN（父体编号） | D1: 规格原文 | E1: 商品链接 | F1: 商品主图链接 | G1: 品牌 | H1: 网页商品标题 | I1: 中文标题（按网页原文翻译） | J1: 商品标签原值 | K1: 月度类目路径 | L1: 大类目 | M1: 8月大类排名 | N1: 小类目 | O1: 网页榜单排名 | P1: 颜色（未打标） | Q1: 材质（未打标） | R1: 商品尺寸原文 | S1: 包装尺寸原文 | T1: 包装重量原文 | U1: 用途（未打标） | V1: 网页榜单排名 | W1: 月度数据月份 | X1: 本榜单同父体商品数 | Y1: 月度数据状态 | Z1: 网页价格€ | AA1: 网页评分数 | AB1: 网页星级 | AC1: 月度数据来源 | AD1: 材料验证（未开展） | AE1: 价格带（未打标） | AF1: 上架日期 | AG1: 评分分组（未打标） | AH1: 评分数分组（未打标） | AI1: 商品计数 | AJ1: 8月父体销量（不可直接合计） | AK1: 8月销售额估算€ | AL1: 8月价格€ | AM1: 平台费用后毛利率 | AN1: FBA配送费€ | AO1: 8月星级 | AP1: 8月评分数 | AQ1: 留评率原值 | AR1: 评分数月增量 | AS1: 问答数（未采） | AT1: 评级（未打标） | AU1: 上架日期 | AV1: 上架天数（未算） | AW1: 变体数 | AX1: 卖家数 | AY1: 卖家名称 | AZ1: 卖家国家 | BA1: 卖家信息（未采） | BB1: 配送方式 | BC1: 重量原文 | BD1: 尺寸原文 | BE1: 9月3日导出匹配方式 | BF1: 导出完整标题 | BG1: 导出详细参数 | BH1: 导出完整卖点 | BI1: 导出子体销量原值（周期待确认） | BJ1: 导出子体销售额原值€（周期待确认） | BK1: 2026-07子体历史销量原值 | BL1: 2026-07子体历史销售额原值€ | BM1: 2026-05父体历史销量 | BN1: 2026-06父体历史销量 | BO1: 2026-07父体历史销量 | BP1: 2026-08父体历史销量 | BQ1: 5—8月父体历史完整月数 | BR1: 5—8月父体最低月销 | BS1: 原表与历史8月销量差值 | BT1: 补充证据说明 | BU1: 原始产品明细行号 | BV1: 父体历史行号
B2: B01CR1L1GQ | C2: B01N30EOLD | D2: Größe: 32L x 21B cm | Material: Akazienholz | E2: https://www.amazon.de/dp/B01CR1L1GQ | F2: https://images-na.ssl-images-amazon.com/images/I/51OBPeTpVjL._AC_US200_.jpg | G2: Kesper | H2: KESPER | Schneidbrett mit Saftrille, Material: Akazienholz, Maße: 32 x 21 x 1,5 cm, Farbe: Braun, Natur | 28180 | I2: KESPER 金合欢木切菜板，32×21×1.5厘米，棕色原木色，带汁槽，型号28180 | J2: {"bestSeller": "Bestseller Nr. 1 in Hackbretter", "amazonChoice": "Amazons Tipp", "newRelease": "N", "ebc": "Y", "video": "Y"} | K2: Küche, Haushalt & Wohnen:Küche, Kochen & Backen:Küchenhelfer & Kochzubehör:Schneidbretter & -matten:Hackbretter | L2: kitchen | M2: 768 | N2: Hackbretter（砧板） | O2: 1 | R2: 32 x 21 x 1.5 cm | S2: 31.9 x 21 x 1.7 cm | T2: 539 g | V2: 1 | W2: 202608 | X2: 1 | Y2: 已匹配202608 | Z2: 4.46 | AA2: 2407 | AB2: 4.4 | AC2: 卖家精灵 | AF2: 2017-01-24 | AI2: 1 | AJ2: 6132 | AK2: 44763.6 | AL2: 8.99 | AM2: 0.5508 | AN2: 2.69 | AO2: 4.4 | AP2: 2382 | AQ2: 0.72 | AR2: 44 | AU2: 2017-01-24 | AW2: 13 | AX2: 7 | AY2: Amazon | AZ2: DE | BB2: AMZ | BC2: 539 g | BD2: 32 x 21 x 1.5 cm | BE2: 仅同父体；属性不借用 | BM2: 2351 | BN2: 2050 | BO2: 4235 | BP2: 5886 | BQ2: 4 | BR2: 2050 | BS2: -246 | BT2: 历史为固定父体样本，不能分配给该规格；子体原值多为50/100等阶梯值，不视为精确订单。未按同父体借用其他变体参数。 | BV2: 52
B3: B0DP38VJGG | C3: B0DP375X1X | D3: Farbe: Grau | Größe: 2er-Set | E3: https://www.amazon.de/dp/B0DP38VJGG | F3: https://images-na.ssl-images-amazon.com/images/I/71LDg+cezeL._AC_US200_.jpg | G3: Blumtal | H3: Blumtal Schneidebrett Kunststoff groß 40x24,5 cm 2er Set - Schneidebretter + Saftrillen & Griff - Cutting Board - Schneidbret | I3: Blumtal 大号塑料切菜板两件套，40×24.5厘米，带汁槽和把手 | J3: {"bestSeller": "N", "amazonChoice": "Amazons Tipp", "newRelease": "N", "ebc": "Y", "video": "N"} | K3: Küche, Haushalt & Wohnen:Küche, Kochen & Backen:Küchenhelfer & Kochzubehör:Schneidbretter & -matten:Hackbretter | L3: kitchen | M3: 1455 | N3: Hackbretter（砧板） | O3: 2 | R3: 40 x 24.5 x 1 cm | S3: 41.1 x 28 x 2.4 cm | T3: 1.23 kg | V3: 2 | W3: 202608 | X3: 1 | Y3: 已匹配202608 | Z3: 14.99 | AA3: 395 | AB3: 4.3 | AC3: 卖家精灵 | AF3: 2025-03-19 | AI3: 1 | AJ3: 1376 | AK3: 18920 | AL3: 12.74 | AM3: 0.5368 | AN3: 3.99 | AO3: 4.3 | AP3: 392 | AQ3: 1.89 | AR3: 26 | AU3: 2025-03-19 | AW3: 9 | AX3: 5 | AY3: Everbrent | AZ3: DE | BB3: FBA | BC3: 600 g | BD3: 40 x 24.5 x 1 cm | BE3: 仅同父体；属性不借用 | BM3: 836 | BN3: 1209 | BO3: 1073 | BP3: 1450 | BQ3: 4 | BR3: 836 | BS3: 74 | BT3: 历史为固定父体样本，不能分配给该规格；子体原值多为50/100等阶梯值，不视为精确订单。未按同父体借用其他变体参数。 | BV3: 54
B4: B0BRNP6QXB | C4: B0BRNP6QXB | D4: NA | E4: https://www.amazon.de/dp/B0BRNP6QXB | F4: https://images-na.ssl-images-amazon.com/images/I/611oQab+T8L._AC_US200_.jpg | G4: Aututer | H4: Aututer Schneidebrett Set 3er Weizenstroh Saftrille spülmaschinenfest | BPA-freie Schneidebretter für Fleisch, Fisch, Obst, G | I4: Aututer 麦秸切菜板三件套，带汁槽，宣称可洗碗机清洗、不含双酚A（BPA），用于肉、鱼和水果等（原文截断） | J4: {"bestSeller": "N", "amazonChoice": "Amazons Tipp", "newRelease": "N", "ebc": "Y", "video": "Y"} | K4: Küche, Haushalt & Wohnen:Küche, Kochen & Backen:Küchenhelfer & Kochzubehör:Schneidbretter & -matten:Hackbretter | L4: kitchen | M4: 2366 | N4: Hackbretter（砧板） | O4: 3 | R4: 35 x 21 x 0.8 cm | S4: 35.8 x 21 x 2.6 cm | T4: 1.31 kg | V4: 3 | W4: 202608 | X4: 1 | Y4: 已匹配202608 | Z4: 16.3 | AA4: 624 | AB4: 4.5 | AC4: 卖家精灵 | AF4: 2023-02-09 | AI4: 1 | AJ4: 1382 | AK4: 24005.34 | AL4: 16.98 | AM4: 0.6281 | AN4: 3.99 | AO4: 4.5 | AP4: 622 | AQ4: 1.52 | AR4: 21 | AU4: 2023-02-09 | AW4: 1 | AX4: 2 | AY4: Aututerm | AZ4: CN | BB4: FBA | BC4: 1.2 kg | BD4: 35 x 21 x 0.8 cm | BE4: 同子体匹配 | BF4: Schneidebrett Set 3er Weizenstroh Saftrille spülmaschinenfest | BG4: Marke: Aututer | Farbe: Beige,grün,pink | Produktabmessungen: 36L x 21B x 0,8D cm | Material: Weizenstroh | Empfohlene Anwendungen für Produkt: Brot, Fisch, Fleisch, Gemüse, Käse, Obst | Form: Rechteckig | Produktpflegeanweisungen: Spülmaschinenfest oder Handwäsche | Besonderes Merkmal: BPA-frei, Eingebaute Saftrille, Leicht zu reinigen, Rutschfest, Spülmaschinengeeignet | Enthaltene Komponenten: Schneidebrett | Artikelgewicht: 1,2 Kilograms | BH4: 【Hochwertige Materialien】Aututer EU-patentiertes Küchenschneidebrett aus lebensmittelechtem Material – BPA-frei, geruchsneutral, robust und pflegeleicht. Für sauberes, komfortables Schneiden entwickelt – leicht zu reinigen und praktisch im Küchenalltag. 【3-teiliges Schneidebrett Set】3 Schneidebretter in verschiedenen Farben für eine getrennte Lebensmittelzubereitung. Geeignet für Fleisch, Gemüse, Obst, Fisch, Käse und Brot – für mehr Ordnung, Hygiene und eine saubere Küchenvorbereitung. 【Praktische Größe】Schneidebrett ca. 35 × 21 × 0,8 cm – geeignet für Fleisch, Gemüse, Obst, Käse und Brot sowie für die tägliche Lebensmittelzubereitung in Küche und Haushalt. 【Rutschhemmende Kanten & Leicht zu Reinigen】Schneidebrett mit rutschhemmenden Kanten für mehr Stabilität beim Schneiden und Zubereiten. Spülmaschinengeeignet, leicht zu reinigen und geeignet für die tägliche Lebensmittelzubereitung ohne störende Geruchs- oder Fleckenrückstände. 【Alltag & Verwendung】Das Aututer Schneidebrett Set für Küche und Haushalt eignet sich für den täglichen Gebrauch sowie für verschiedene Anlässe wie Weihnachten, Erntedankfest, Muttertag, Vatertag, Geburtstage, Jubiläen und Einweihungsfeiern. | BI4: 900 | BJ4: 15759 | BK4: 600 | BL4: 11292 | BM4: 1154 | BN4: 1570 | BO4: 829 | BP4: 1416 | BQ4: 4 | BR4: 829 | BS4: 34 | BT4: 历史为固定父体样本，不能分配给该规格；子体原值多为50/100等阶梯值，不视为精确订单。 | BU4: 57 | BV4: 57
B5: B0D7HSM67V | C5: B0D7MXT9HT | D5: Größe: 60L x 40B cm | Farbe: Schwarz | E5: https://www.amazon.de/dp/B0D7HSM67V | F5: https://images-na.ssl-images-amazon.com/images/I/51woxLm8kVL._AC_US200_.jpg | G5: MUVELL | H5: Muvell stabiles Schneidebrett Kunststoff | Schwarz, 60x40x2 cm | Spülmaschinenfest, EXTRA dick, messerschonend | Farben & Grö | I5: Muvell 黑色加厚塑料切菜板，60×40×2厘米，宣称可洗碗机清洗、保护刀刃（原文截断） | J5: {"bestSeller": "N", "amazonChoice": "N", "newRelease": "N", "ebc": "Y", "video": "N"} | K5: Küche, Haushalt & Wohnen:Küche, Kochen & Backen:Küchenhelfer & Kochzubehör:Schneidbretter & -matten:Hackbretter | L5: kitchen | M5: 2021 | N5: Hackbretter（砧板） | O5: 4 | R5: 60 x 40 x 2 cm | S5: 60 x 40 x 3 cm | T5: 3.98 kg | V5: 4 | W5: 202608 | X5: 1 | Y5: 已匹配202608 | Z5: 39.95 | AA5: 475 | AB5: 4.4 | AC5: 卖家精灵 | AF5: 2024-06-26 | AI5: 1 | AJ5: 1517 | AK5: 60604.15 | AL5: 39.95 | AM5: 0.7151 | AN5: 5.39 | AO5: 4.4 | AP5: 463 | AQ5: 2.7 | AR5: 41 | AU5: 2024-06-26 | AW5: 17 | AX5: 1 | AY5: Gastro Service Profis | AZ5: DE | BB5: FBA | BC5: 3.8 kg | BD5: 60 x 40 x 2 cm | BE5: 同子体匹配 | BF5: stabiles Schneidebrett Kunststoff | Schwarz, 60x40x2 cm | Spülmaschinenfest, EXTRA dick, messerschonend | Farben & Größen auswählbar | BBQ & Bar Küchenbrett | Schneidbrett mit Saftrill | BG5: Marke: MUVELL | Farbe: Schwarz | Produktabmessungen: 60L x 40B x 2D cm | Material: Kunststoff | Empfohlene Anwendungen für Produkt: BBQ | Form: Rechteckig | Produktpflegeanweisungen: Spülmaschinenfest, leicht sauber zu halten. Standardpflege anwenden. | Besonderes Merkmal: 1 Seite mit Saftrille, 2-seitig nutzbar, Stabiles Schneidebrett | Artikelgewicht: 3,8 Kilograms | Muster: Einfarbig | BH5: AUSWAHL: Schneidebrett Kunststoff - Schwarz - 60x40x2 cm - 4,4 Kg. Alle MUVELL Schneidbretter sind sehr stabil & EXTRA dick (2 cm). Das Schneidebrett ist aus dem hochwertigen Kunststoff (HDPE 500) hergestellt. Dieses Kunststoff ist besonders für Lebensmittel geeignet. HDPE 500 ist ein sehr harter Kunststoff und besonders schonend zu Ihren Messern zugleich. EIGENSCHAFT: Unser Schneidebrett aus HDPE-500 ist leicht sauber zu halten (spülmaschinengeeignet) & hat eine lange Lebensdauer. Bakterien und andere Verschmutzungen haften nur schwer an diesem Typ Polyethylen, der auch Hart-Polyethylen (Hart PE) genannt wird. Es ist zu 100 % recycelbar. GOOD TO KNOW: Im Vergleich zu anderen Kunststoff Schneidebrettern aus Standard-PE hat unser MUVELL Schneidbrett eine höhere Molekularmasse. Dadurch ist unser Schneidebrett aus HDPE-500 stabiler und langlebiger als andere herkömmliche Schneidbretter. ANTIRUTSCH STRUKTUR: Unsere Schneidebretter haben auf beiden Seiten eine leichte Oberflächenstruktur. Durch dieser Antirutsch-Eigenschaft, bleibt Ihr Schnittgut auf der Stelle liegen und Sie können sicher und präzise Schneiden. EIN BRETT MIT 2 SEITEN: Eine Seite mit Saftrinne und eine Seite ohne Saftrinne. Somit können Sie individuell selbst bestimmen, welche Nutzungsart Sie verwenden möchten und können von der Verarbeitung von trocknen bis feuchten Lebensmitteln alle Varianten darauf bearbeiten. ABDECKUNG ODER UNTERLAGE: Dieses Brett können Sie auch als Abdeckbrett für Ihr Ceran- / Induktionskochfeld ggfs. verwenden sofern die Maße passen. Auch als Unterlage für die unterschiedlichsten Haus- und Designarbeiten geeignet. Gerne können Sie als Inspiration einen Blick in unsere Bewertungen werfen. | BI5: 100 | BJ5: 3995 | BK5: 50 | BL5: 1998 | BM5: 889 | BN5: 785 | BO5: 1081 | BP5: 1589 | BQ5: 4 | BR5: 785 | BS5: 72 | BT5: 历史为固定父体样本，不能分配给该规格；子体原值多为50/100等阶梯值，不视为精确订单。 | BU5: 58 | BV5: 58
B6: B0FCMB514Z | C6: B0FDWG58L2 | D6: Farbe: Schwarz | E6: https://www.amazon.de/dp/B0FCMB514Z | F6: https://images-na.ssl-images-amazon.com/images/I/81oTzaaWNiL._AC_US200_.jpg | G6: ROTTOGOON | H6: 3er-Set Kunststoff-Schneidebrett, BPA-frei, Schwarz | Rutschfeste Füße, tiefe Safurille, spülmaschinensicher, ergonomischer G | I6: 黑色塑料切菜板三件套，宣称不含双酚A（BPA），带防滑脚、深汁槽，可洗碗机清洗（原文截断） | J6: {"bestSeller": "N", "amazonChoice": "Amazons Tipp", "newRelease": "N", "ebc": "Y", "video": "Y"} | K6: Küche, Haushalt & Wohnen:Küche, Kochen & Backen:Küchenhelfer & Kochzubehör:Schneidbretter & -matten:Hackbretter | L6: kitchen | M6: 2272 | N6: Hackbretter（砧板） | O6: 5 | R6: 40.3 x 2.9 x 24 cm | S6: 40.2 x 25.3 x 2.5 cm | T6: 1.28 kg | V6: 5 | W6: 202608 | X6: 1 | Y6: 已匹配202608 | Z6: 14.28 | AA6: 9194 | AB6: 4.5 | AC6: 卖家精灵 | AF6: 2025-06-11 | AI6: 1 | AJ6: 1796 | AK6: 29202.96 | AL6: 16.99 | AM6: 0.6152 | AN6: 3.99 | AO6: 4.5 | AP6: 9170 | AQ6: 2.9 | AR6: 52 | AU6: 2025-06-11 | AW6: 2 | AX6: 2 | AY6: Amazon | AZ6: DE | BB6: AMZ | BC6: 1.28 kg | BD6: 40.3 x 2.9 x 24 cm | BE6: 同子体匹配 | BF6: ROTTOGOON Schneidebrett Kunststoff Set mit Saftrille für Küche, Schwarz | BG6: Marke: ROTTOGOON | Farbe: Schwarz | Produktabmessungen: 40,3L x 2,9B x 24D cm | Material: Kunststoff | Empfohlene Anwendungen für Produkt: Fleisch, Gemüse, Obst | Form: Quadratisch | Produktpflegeanweisungen: Nur Handwäsche, spülmaschinenfest | Besonderes Merkmal: Rutschfeste Füße | Enthaltene Komponenten: Schneidebrett-Set, Schäler | Artikelgewicht: 1,28 Kilograms | BH6: 【4- IN -1 Schneidebrett-Set – Bonus-Schäler】Dieses 4-teilige Schneidebrett-Set in schwarz, sondern auch einen kostenlosen Gemüseschäler, ermöglicht hygienisches Trennen (Trennkost) von Lebensmitteln, der Ihr bester Küchenhelfer bei täglichen Küchenutensilien sein würde. 【Hochwertiges Material & Einfache Pflege】Hergestellt aus BPA-freiem, lebensmittelechtem Kunststoff. Spülmaschinengeeignet für mühelose Reinigung. Robust, geruchsneutral und resistent gegen Verfärbungen – die sichere Wahl für Familien mit Kindern und gesundheitsbewusste Haushalte. 【Durchdachtes Design gegen Chaos】Jedes Brett verfügt über eine integrierte Saftrille, die Flüssigkeiten sicher auffängt und Ihre Arbeitsfläche sauber hält. Die rutschfeste Kante und das leichte Design garantieren sicheren Halt beim Schneiden – kein Verrutschen und kein Überschwappen mehr. 【Optimale Größen für jeden Zweck】Das Set enthält die gebräuchlichen Formate (40x24 cm & 30x20 cm & 20x15 cm). Ideal für Brot, Gemüse, Obst oder Fleisch. Auch für kleine Küchen oder Wohnungen bestens geeignet, da platzsparend und vielseitig einsetzbar. 【Ihre Zufriedenheit ist unser Antrieb】Wir stehen für geprüfte Qualität und begleiten Sie mit diesem Schneidebrett-Set zu mehr Freude und Gesundheit beim Kochen – Ihr täglicher Küchenhelfer auf den Sie sich verlassen können. | BI6: 1,000 | BJ6: 16190 | BK6: 800 | BL6: 13088 | BM6: 1390 | BN6: 1908 | BO6: 1622 | BP6: 1895 | BQ6: 4 | BR6: 1390 | BS6: 99 | BT6: 历史为固定父体样本，不能分配给该规格；子体原值多为50/100等阶梯值，不视为精确订单。 | BU6: 59 | BV6: 59
B7: B079YCKPYW | C7: B0FX9D519P | D7: Größe: 45L x 30B cm | E7: https://www.amazon.de/dp/B079YCKPYW | F7: https://images-na.ssl-images-amazon.com/images/I/71G2zIUF03L._AC_US200_.jpg | G7: Blumtal | H7: Blumtal Schneidebrett aus 100% Bambus - antiseptisches Holz-Brett mit Saftrille, Holz-Brettchen, 45x30x2cm | I7: Blumtal 100%竹制切菜板，45×30×2厘米，带汁槽，宣称抑菌 | J7: {"bestSeller": "N", "amazonChoice": "N", "newRelease": "N", "ebc": "Y", "video": "Y"} | K7: Küche, Haushalt & Wohnen:Küche, Kochen & Backen:Küchenhelfer & Kochzubehör:Schneidbretter & -matten:Hackbretter | L7: kitchen | M7: 1949 | N7: Hackbretter（砧板） | O7: 6 | R7: 45 x 23 x 2 cm | S7: 44.2 x 31.6 x 2.7 cm | T7: 1.74 kg | V7: 6 | W7: 202608 | X7: 1 | Y7: 已匹配202608 | Z7: 19.99 | AA7: 7055 | AB7: 4.6 | AC7: 卖家精灵 | AF7: 2018-05-07 | AI7: 1 | AJ7: 1789 | AK7: 29536.39 | AL7: 15.29 | AM7: 0.5878 | AN7: 4.01 | AO7: 4.6 | AP7: 7051 | AQ7: 3.91 | AR7: 70 | AU7: 2018-05-07 | AW7: 3 | AX7: 5 | AY7: Everbrent | AZ7: DE | BB7: FBA | BC7: 1.74 kg | BD7: 45 x 23 x 2 cm | BE7: 同子体匹配 | BF7: Blumtal Schneidebrett aus 100% Bambus - antiseptisches Holz-Brett mit Saftrille, Holz-Brettchen, 45x30x2cm | BG7: Marke: Blumtal | Farbe: Holzfarbe | Produktabmessungen: 45L x 30B x 2D cm | Material: Bambus | Empfohlene Anwendungen für Produkt: Brot, Fisch, Fleisch, Gemüse, Käse, Obst | Form: Rechteckig | Produktpflegeanweisungen: Nur Handwäsche | Besonderes Merkmal: Antimikrobiell, Eingebaute Nut, Langanhaltend, Schmutzabweisend | Enthaltene Komponenten: Schale | Artikelgewicht: 1,74 Kilograms | BH7: Hochwertiges Schneidebrett aus 100% Bambus: Bambus hat viele praktische Eigenschaften und großartige Vorteile. Aufgrund seiner dichten Zellstruktur ist Bambus härter als die meisten Holzarten und hat eine überdurchschnittliche Lebensdauer. Die Blumtal Holzschneidbretter sind ideal zum Schneiden von Fleisch und vielem mehr. Multifunktional mit antibakteriellen Eigenschaften: Bambus hat natürliche antiseptische Eigenschaften. Diese großen Bambus-Schneidebretter sind äußerst hygienisch und erzeugen deutlich weniger Bakterien als herkömmliche Schneidebretter. Wenn das Brett nicht zum Schneiden verwendet wird, kann es als Servierbrett für Käse, Sushi, Tomaten und mehr genutzt werden. Klingenschonende Oberfläche: Die Oberfläche des Schneidebretts ist aufgrund des extrem robusten Bambus hart. Dieses Werkzeug bietet nicht nur die ideale Unterlage zum Schneiden, sondern sorgt auch dafür, dass Ihr Küchenmesser scharf bleibt. Praktische Saftrille: Das 45 x 30 x 2 cm große Schneidebrett verfügt über eine praktische Saftrille am Rand des Bretts. Es schützt auch Ihre Küchenarbeitsplatte vor Verfärbungen durch Säfte oder farbige Lebensmittel. Einfache Reinigung – mit Pflegehinweisen: Das Schneidebrett kann einfach von Hand abgespült und getrocknet werden. Alles Weitere zur Pflege finden Sie in der beiliegenden Pflegeanleitung. Seien Sie Ihr eigener Küchenchef. | BI7: 700 | BJ7: 11571 | BK7: 300 | BL7: 5028 | BM7: 1728 | BN7: 1955 | BO7: 1297 | BP7: 1864 | BQ7: 4 | BR7: 1297 | BS7: 75 | BT7: 历史为固定父体样本，不能分配给该规格；子体原值多为50/100等阶梯值，不视为精确订单。 | BU7: 55 | BV7: 55
B8: B07TV8S14K | C8: B0H276RX1T | D8: Größe: 40L x 32B cm | E8: https://www.amazon.de/dp/B07TV8S14K | F8: https://images-na.ssl-images-amazon.com/images/I/71WCfAeuoVL._AC_US200_.jpg | G8: WMF | H8: WMF Schneidebrett Holz groß massiv 40 x 32 x 4 cm, Holz, Akazienholz, klingenschonend, große Arbeitsfläche, Küchenbrett, Stir | I8: WMF 大号实心金合欢木切菜板，40×32×4厘米，宽大操作面，保护刀刃（原文截断） | J8: {"bestSeller": "N", "amazonChoice": "Amazons Tipp", "newRelease": "N", "ebc": "Y", "video": "Y"} | K8: Küche, Haushalt & Wohnen:Küche, Kochen & Backen:Küchenhelfer & Kochzubehör:Schneidbretter & -matten:Hackbretter | L8: kitchen | M8: 1884 | N8: Hackbretter（砧板） | O8: 7 | R8: 40 x 32 x 4 cm | S8: 41.3 x 33.3 x 4.7 cm | T8: 2.87 kg | V8: 7 | W8: 202608 | X8: 1 | Y8: 已匹配202608 | Z8: 30.24 | AA8: 3858 | AB8: 4.6 | AC8: 卖家精灵 | AF8: 2019-10-09 | AI8: 1 | AJ8: 1784 | AK8: 64206.16 | AL8: 35.99 | AM8: 0.7219 | AN8: 4.61 | AO8: 4.6 | AP8: 3850 | AQ8: 0.78 | AR8: 14 | AU8: 2019-10-09 | AW8: 5 | AX8: 21 | AY8: Amazon | AZ8: DE | BB8: AMZ | BC8: 2.37 kg | BD8: 40 x 32 x 4 cm | BE8: 同子体匹配 | BF8: WMF Schneidebrett Holz groß massiv 40 x 32 x 4 cm, Holz, Akazienholz, klingenschonend, große Arbeitsfläche, Küchenbrett, Stirnholzoptik, Gummierte Füße | BG8: Marke: WMF | Farbe: Braun | Produktabmessungen: 40L x 32B x 4D cm | Material: Akazienholz, Klingenschonend: Da Holz weicher ist als der Klingenstahl, bietet dieses Hackbrett eine nachgiebige und somit klingenschonende Unterlage für jegliche Art von Hack- und Schneidearbeiten | Empfohlene Anwendungen für Produkt: Gemüse | Form: Rechteckig | Produktpflegeanweisungen: Nur Handwäsche | Besonderes Merkmal: Flexibel | Enthaltene Komponenten: schneidebrett | Artikelgewicht: 2,37 Kilograms | BH8: Inhalt: 1x Schneidebrett XL (40 x 32 x 4 cm) aus Akazienholz - Artikelnummer: 1879984500 Klingenschonend: Da Holz weicher ist als der Klingenstahl, bietet dieses Hackbrett eine nachgiebige und somit klingenschonende Unterlage für jegliche Art von Hack- und Schneidearbeiten Das Holz-Schneidbrett ist sehr massiv (4 cm Dicke), groß und schwer, sodass es auch für gröbste Arbeiten eine standhafte und sichere Grundlage bietet Dank der großen komfortablen Arbeitsfläche können mehrere Zutaten gleichzeitig vorbereitet werden, ohne dass der Platz auf den Schneidebrett ausgeht Gummierte Füße versprechen einen sicheren Halt beim Schneiden, Hacken oder Filetieren. Durch das stilvolle Design kann das Brett auch zum Servieren am Tisch verwendet werden | BI8: 800 | BJ8: 28792 | BK8: 400 | BL8: 16232 | BM8: 2161 | BN8: 2118 | BO8: 1255 | BP8: 1784 | BQ8: 4 | BR8: 1255 | BS8: 0 | BT8: 历史为固定父体样本，不能分配给该规格；子体原值多为50/100等阶梯值，不视为精确订单。 | BU8: 53 | BV8: 53
B9: B0D93F12NV | C9: B09Z6CXVK1 | D9: Farbe: Grau+grün | E9: https://www.amazon.de/dp/B0D93F12NV | F9: https://images-na.ssl-images-amazon.com/images/I/61F40NvOiBL._AC_US200_.jpg | G9: Gintan | H9: Gintan 2 Pack Flexibles TPU Schneidebrett, BPA-frei, mit Messer- und Saftrille, kratzfeste flexible Schneidebretter für die K | I9: Gintan 柔性TPU切菜板两件套，宣称不含双酚A（BPA），带刀槽和汁槽、耐刮（原文截断） | J9: {"bestSeller": "N", "amazonChoice": "Amazons Tipp", "newRelease": "N", "ebc": "Y", "video": "N"} | K9: Küche, Haushalt & Wohnen:Küche, Kochen & Backen:Küchenhelfer & Kochzubehör:Schneidbretter & -matten:Hackbretter | L9: kitchen | M9: 2058 | N9: Hackbretter（砧板） | O9: 8 | R9: 30 x 20 x 0.4 cm | S9: 35.8 x 25 x 1.6 cm | T9: 560 g | V9: 8 | W9: 202608 | X9: 1 | Y9: 已匹配202608 | Z9: 22.94 | AA9: 4384 | AB9: 4.3 | AC9: 卖家精灵 | AF9: 2024-07-15 | AI9: 1 | AJ9: 1125 | AK9: 28462.5 | AL9: 26.99 | AM9: 0.7207 | AN9: 3.49 | AO9: 4.3 | AP9: 4364 | AQ9: 4.71 | AR9: 53 | AU9: 2024-07-15 | AW9: 6 | AX9: 1 | AY9: Gintan DE | AZ9: CN | BB9: FBA | BC9: 136 g | BD9: 30 x 20 x 0.4 cm | BE9: 同子体匹配 | BF9: Gintan 2 Pack Flexibles TPU Schneidebrett, BPA-frei, mit Messer- und Saftrille, kratzfeste flexible Schneidebretter für die Küche, spülmaschinenfest, griffiger Griff, rutschfest (Grau+Green) | BG9: Marke: Gintan | Farbe: Grau+grün | Produktabmessungen: 30L x 20B x 0,4D cm | Material: TPU (Thermoplastisches Polyurethan) | Empfohlene Anwendungen für Produkt: Fleisch | Form: Quadratisch | Produktpflegeanweisungen: Spülmaschinenfest | Besonderes Merkmal: Flexibel, Saftrille, rutschfest, kratzfest, spülmaschinenfest | Enthaltene Komponenten: Geschirrbehälter, Messer | Artikelgewicht: 136 g | BH9: 【BPA-frei】: TPU ist ein recycelbares, hochbelastbares thermoplastisches Elastomermaterial mit guter Elastizität und Abriebfestigkeit. 【Messerfreundlich】: Das Anti-Messer-Markierungs-Design des hochwertigen flexiblen Schneidebretts ist kratzfest, hinterlässt nicht leicht Messerspuren, kein Spänen, keine Beschädigung der Messer und hat eine Saftrille, um das Verschütten von Flüssigkeiten zu verhindern. 【Leicht zu reinigen】: Gintan-Schneidebretter sind spülmaschinenfest, dünn und biegsam, um Zutaten einfach in Kochutensilien zu gießen. 【Platz sparen】: Küchenschneidebretter sind dünn und langlebig, unsere TPU-Schneidebretter haben ein dünneres Profil als Holz oder Bambus und lassen sich leicht in einer Schublade verstauen oder an einem Haken aufhängen. 【Schneidebrett-Set】: Dieses TPU-Schneidebrett-Set wird mit einem zusätzlichen Messer geliefert, das Ihr bester Helfer in der täglichen Küche sein wird. Wenn Sie Fragen zu Gintan Schneidebrettern haben, zögern Sie nicht, uns zu kontaktieren - Ihre Zufriedenheit ist das Wichtigste! | BI9: 200 | BJ9: 4964 | BK9: 100 | BL9: 2471 | BM9: 800 | BN9: 1280 | BO9: 952 | BP9: 1160 | BQ9: 4 | BR9: 800 | BS9: 35 | BT9: 历史为固定父体样本，不能分配给该规格；子体原值多为50/100等阶梯值，不视为精确订单。 | BU9: 63 | BV9: 63
B10: B000P0YTXE | C10: B0GNSMGFSH | D10: Farbe: Schwarz | Größe: 38 x 25 cm | E10: https://www.amazon.de/dp/B000P0YTXE | F10: https://images-na.ssl-images-amazon.com/images/I/51M+QHr0QbL._AC_US200_.jpg | G10: Silit | H10: Silit Schneidebrett 38 x 25 cm rechteckig, Kunststoff, Tranchierbrett mit Saftrillen, praktischer Griff, spülmaschinengeeigne | I10: Silit 黑色矩形塑料切菜板，38×25厘米，带汁槽和把手，可洗碗机清洗（原文截断） | J10: {"bestSeller": "N", "amazonChoice": "Amazons Tipp", "newRelease": "N", "ebc": "Y", "video": "Y"} | K10: Küche, Haushalt & Wohnen:Küche, Kochen & Backen:Küchenhelfer & Kochzubehör:Schneidbretter & -matten:Hackbretter | L10: kitchen | M10: 3501 | N10: Hackbretter（砧板） | O10: 9 | R10: 39.3 x 25.2 x 1.3 cm | S10: 38.1 x 25.1 x 1.4 cm | T10: 893 g | V10: 9 | W10: 202608 | X10: 1 | Y10: 已匹配202608 | Z10: 13.41 | AA10: 2456 | AB10: 4.5 | AC10: 卖家精灵 | AF10: 2014-05-02 | AI10: 1 | AJ10: 1044 | AK10: 18259.56 | AL10: 15.96 | AM10: 0.6313 | AN10: 3.49 | AO10: 4.5 | AP10: 2452 | AQ10: 1.05 | AR10: 11 | AU10: 2014-05-02 | AW10: 6 | AX10: 12 | AY10: Amazon | AZ10: DE | BB10: AMZ | BC10: 880 g | BD10: 39.3 x 25.2 x 1.3 cm | BE10: 同子体匹配 | BF10: Silit Schneidebrett 38 x 25 cm rechteckig, Kunststoff, Tranchierbrett mit Saftrillen, praktischer Griff, spülmaschinengeeignet, klingenschonend | BG10: Marke: Silit | Farbe: Schwarz | Produktabmessungen: 39,3L x 25,2B x 1,3D cm | Material: Kunststoff | Empfohlene Anwendungen für Produkt: Fleisch, Gemüse, Käse, Obst | Form: Rechteckig | Produktpflegeanweisungen: Handwäsche, spülmaschinenfest | Besonderes Merkmal: Spülmaschinengeeignet | Enthaltene Komponenten: Messer | Artikelgewicht: 880 g | BH10: Inhalt: 1x Schneidebrett mittel (38 x 25 cm) - Artikelnummer: 2142235347 Klingenschonend: Da Kunststoff weicher ist als der Klingenstahl, bietet dieses Schneidbrett eine nachgiebige und somit klingenschonende Unterlage für jegliche Art von Schneidarbeiten Das Kunststoffbrett ist beidseitig nutzbar: eine Seite mit Saftrille (z.B. für Fleisch oder Tomaten) um Flüssigkeiten aufzufangen, die andere Seite ohne Saftrille (z.B. für Zwiebeln) Kunststoff: Klingenschonendes und spülmaschinenfestes Material Rutschfeste Unterlage zum Schneiden, Hacken oder Filetieren | BI10: 200 | BJ10: 3448 | BK10: 100 | BL10: 1693 | BM10: 1471 | BN10: 1136 | BO10: 954 | BP10: 1088 | BQ10: 4 | BR10: 954 | BS10: 44 | BT10: 历史为固定父体样本，不能分配给该规格；子体原值多为50/100等阶梯值，不视为精确订单。 | BU10: 64 | BV10: 64
B11: B0DZVK3RXR | C11: B0F6VHZWR1 | D11: NA | E11: https://www.amazon.de/dp/B0DZVK3RXR | F11: https://images-na.ssl-images-amazon.com/images/I/718Ev85N-FL._AC_US200_.jpg | G11: KIKIIKE | H11: Titan-Schneidebrett, doppelseitig, reines Titan, Schneidebretter für die Küche, lebensmittelecht, Rutschfest, auslaufsicher, | I11: 双面切菜板，宣称纯钛、食品接触适用、防滑防漏（原文截断） | J11: {"bestSeller": "N", "amazonChoice": "Amazons Tipp", "newRelease": "N", "ebc": "Y", "video": "Y"} | K11: Küche, Haushalt & Wohnen:Küche, Kochen & Backen:Küchenhelfer & Kochzubehör:Schneidbretter & -matten:Hackbretter | L11: kitchen | M11: 3058 | N11: Hackbretter（砧板） | O11: 10 | R11: 38.6 x 27.9 x 1.5 cm | S11: 39.9 x 28.2 x 2.7 cm | T11: 1.34 kg | V11: 10 | W11: 202608 | X11: 1 | Y11: 已匹配202608 | Z11: 27.99 | AA11: 1087 | AB11: 4.2 | AC11: 卖家精灵 | AF11: 2025-05-08 | AI11: 1 | AJ11: 972 | AK11: 25991.28 | AL11: 27.99 | AM11: 0.7121 | AN11: 3.86 | AO11: 4.2 | AP11: 1063 | AQ11: 8.74 | AR11: 85 | AU11: 2025-05-08 | AW11: 1 | AX11: 1 | AY11: KIKIIKE-INC | AZ11: CN | BB11: FBA | BC11: 1.09 kg | BD11: 38.6 x 27.9 x 1.5 cm | BE11: 同子体匹配 | BF11: Titan-Schneidebrett, doppelseitig, reines Titan, Schneidebretter für die Küche, lebensmittelecht, Rutschfest, auslaufsicher, langlebig und leicht zu reinigen | BG11: Marke: KIKIIKE | Farbe: 1 | Produktabmessungen: 39L x 28B x 1,5D cm | Material: Titan, Weizenstroh-PP | Empfohlene Anwendungen für Produkt: Fleisch, Gemüse, Obst | Form: Rechteckig | Produktpflegeanweisungen: Spülmaschinenfest | Besonderes Merkmal: Antimikrobiell, Eingebaute Nut, Eingebauter Griff, Umweltfreundlich | Enthaltene Komponenten: 1 | Artikelgewicht: 1,09 Kilograms | BH11: Doppeloberflächen-Innovation: Erleben Sie die Zubereitung von Lebensmitteln in professioneller Qualität mit unserem 2-in-1-Schneidesystem. Die schmutzabweisende Titanoberfläche ermöglicht die sichere Handhabung von Fleisch, während die Seite aus ökologischem Weizenstroh (BPA-frei) die Produkte frisch hält. Erfüllt die strengen Lebensmittelsicherheitsstandards der FDA für die separate Zubereitung von rohen/gekochten Lebensmitteln Revolutionäre kratzfeste Oberfläche: Mit unserer PureShield-Titan-Technologie, die Messerschlitze entfernt, wo sich Flecken verstecken. Im Gegensatz zu Holzbrettern widersteht es Flecken, Gerüchen und Verformungen, zertifiziert 73 % hygienischer als herkömmliche Bretter in Labortests, die strukturierte Mikro-Zerkleinererzone zerkleinert Knoblauch und Ingwer in Sekunden Spalt- und extrem langlebig: Im Gegensatz zu Schneidebrettern aus Holz oder Kunststoff reißen, verformen oder absorbieren diese reinen Titan-Schneidebretter keine Flüssigkeiten. Sie sind für robuste Schneid-, Schneid- und Knetaufgaben gebaut und somit die beste Wahl für Ihre Küche. Der doppelseitige Behälter verhindert Wasseraustritt Mühelose Pflege: Das Titan-Schneidebrett kann leicht in der Spülmaschine gereinigt werden und wird 40% schneller sauber als herkömmliche Bretter. Nicht poröse Materialien weisen Flüssigkeiten und Lebensmittelpartikel ab. Verfügt über Öse zum Aufhängen und rutschfeste Silikonfüße für kompakte Aufbewahrung Vielseitig für jede Küchenaufgabe: KIKIIKE Titan Schneidebrett ideal zum Schneiden, Würfeln, Ausrollen von Teig, Kneten von Brot und sogar zum Zubereiten von Sandwiches. Kann auch als Obstteller verwendet werden und kann in den Kühlschrank und die Spülmaschine gestellt werden | BI11: 700 | BJ11: 18781 | BK11: 100 | BL11: 2657 | BM11: 736 | BN11: 379 | BO11: 377 | BP11: 1025 | BQ11: 4 | BR11: 377 | BS11: 53 | BT11: 历史为固定父体样本，不能分配给该规格；子体原值多为50/100等阶梯值，不视为精确订单。 | BU11: 62 | BV11: 62
B12: B0GZ7GFCHJ | C12: B0H1PC342M | D12: Farbe: Silber 3pcs | E12: https://www.amazon.de/dp/B0GZ7GFCHJ | F12: https://images-na.ssl-images-amazon.com/images/I/71MvR8A91oL._AC_US200_.jpg | G12: Fegat | H12: 3Stück Titan Schneidebrett, Edelstahl Schneidbretter BPA-frei Lebensmittel | Doppelseitig Titanium Cutting Board für Fleisch | I12: 金属切菜板三件套，双面、不含双酚A（BPA）；原文同时称钛与不锈钢，材质待确认（原文截断） | J12: {"bestSeller": "N", "amazonChoice": "N", "newRelease": "N", "ebc": "Y", "video": "Y"} | K12: Küche, Haushalt & Wohnen:Küche, Kochen & Backen:Küchenhelfer & Kochzubehör:Schneidbretter & -matten:Hackbretter | L12: kitchen | M12: 7088 | N12: Hackbretter（砧板） | O12: 11 | R12: 39 x 28 x 2 cm | S12: 40 x 30 x 0.7 cm | T12: 1.59 kg | V12: 11 | W12: 202608 | X12: 1 | Y12: 已匹配202608 | Z12: 19.49 | AA12: 246 | AB12: 3.8 | AC12: 卖家精灵 | AF12: 2026-05-13 | AI12: 1 | AJ12: 566 | AK12: 13255.72 | AL12: 19.49 | AM12: 0.6443 | AN12: 4.01 | AO12: 3.8 | AP12: 241 | AQ12: 4.42 | AR12: 25 | AU12: 2026-05-13 | AW12: 3 | AX12: 1 | AY12: WuLu-UK | AZ12: CN | BB12: FBA | BC12: 800 g | BD12: 39 x 28 x 2 cm | BE12: 同子体匹配 | BF12: 3Stück Titan Schneidebrett, Edelstahl Schneidbretter BPA-frei Lebensmittel | BG12: Marke: Fegat | Farbe: Silber 3pcs | Produktabmessungen: 39L x 28B x 2D cm | Material: 304 Edelstahl-Titan, Titan | Empfohlene Anwendungen für Produkt: Brot, Fisch, Fleisch, Gemüse, Obst | Form: Rechteckig | Produktpflegeanweisungen: Spülmaschinenfest | Besonderes Merkmal: Antimikrobiell, Eingebauter Griff, Hitzebeständig, Kratzfest, Langanhaltend Rostbeständig Schmutzabweisend Wechselseitig | Enthaltene Komponenten: 3 Stück Titanium Cutting Board | Artikelgewicht: 800 g | BH12: 【Premium 3er-Set】Dieses hochwertige Set enthält drei praktische Größen (29x20cm, 34x23cm, 39x28cm) für unterschiedliche Schneideaufgaben. Die Titan-Oberfläche ist extrem widerstandsfähig gegen Messerspuren, antibakteriell und hygienisch - perfekt für den täglichen Gebrauch. Die doppelseitige Nutzung ermöglicht eine hygienische Trennung von Fleisch und Gemüse. Die optimale Gewichtsverteilung sorgt für Stabilität beim Schneiden, während die rutschfeste Unterseite ein Verrutschen verhindert 【100% Sicher & Frei von Schadstoffen】Herzstück dieser Schneidbretter ist das lebensmittelechte Titan-Material, das komplett frei von BPA, Mikroplastik und anderen schädlichen Chemikalien ist. Im Gegensatz zu herkömmlichen Plastikbrettern, bieten diese Bretter eine absolut saubere Schneidfläche. Die antibakteriellen Eigenschaften von Titan reduzieren zudem die Keimbildung - ein entscheidender Vorteil für die Lebensmittelhygiene in Ihrer Küche 【Messerschonend Langlebig】Titan ist dreimal weicher als Stahl und schont daher Ihre Messerklingen optimal. Anders als bei Glas-, Stein- oder Bambusbrettern bleiben Ihre Messer länger scharf. Die speziell behandelte Oberfläche verhindert tiefe Schnittspuren und verlängert so die Lebensdauer Ihrer hochwertigen Küchenmesser. Die robuste Konstruktion hält selbst intensiver Nutzung stand, ohne sich zu verformen oder Risse zu bilden 【Pfeilschnelle Reinigung & Pflegeleicht】Die nicht-poröse Titan-Oberfläche nimmt weder Gerüche noch Verfärbungen an. Einfach unter fließendem Wasser abspülen oder in die Spülmaschine geben - schon ist das Brett wieder einsatzbereit. Kein Einweichen oder aufwändiges Schrubben notwendig. Die glatte Oberfläche verhindert zudem das Festsetzen von Bakterien und sorgt so für optimale Hygiene in Ihrer Küche 【Optimale Stabilität & Sicherheit】Durch das durchdachte Gewicht und die rutschfeste Unterseite bleibt das Brett auch bei feuchten Bedingungen stabil liegen. Die abgerundeten Kanten erhöhen die Sicherheit beim Handling. Egal ob Sie Gemüse schnippeln, Fleisch schneiden oder Brot aufschneiden - Sie haben stets die volle Kontrolle über Ihre Schneidebewegungen. Die drei Größen bieten für jede Küchenarbeit das passende Format. Ideal für Hobbyköche und Profis gleichermaßen | BI12: 300 | BJ12: 6813 | BK12: 100 | BL12: 2458 | BM12: 116 | BN12: 369 | BO12: 171 | BP12: 593 | BQ12: 4 | BR12: 116 | BS12: 27 | BT12: 历史为固定父体样本，不能分配给该规格；子体原值多为50/100等阶梯值，不视为精确订单。 | BU12: 69 | BV12: 69
B13: B0B57MR2JJ | C13: B0BGQQSWPJ | D13: Farbe: Klare | Größe: 40L x 30B cm | E13: https://www.amazon.de/dp/B0B57MR2JJ | F13: https://images-na.ssl-images-amazon.com/images/I/91PSAItxtZL._AC_US200_.jpg | G13: Kitchenville | H13: Kitchenville Glasschneidebrett 40×30 cm – Hygienisches Schneidebrett aus gehärtetem Glas – Hitzebeständig, Kratzfest & Rutsch | I13: Kitchenville 钢化玻璃切菜板，40×30厘米，宣称耐热、耐刮、防滑（原文截断） | J13: {"bestSeller": "N", "amazonChoice": "Amazons Tipp", "newRelease": "N", "ebc": "Y", "video": "Y"} | K13: Küche, Haushalt & Wohnen:Küche, Kochen & Backen:Küchenhelfer & Kochzubehör:Schneidbretter & -matten:Hackbretter | L13: kitchen | M13: 3375 | N13: Hackbretter（砧板） | O13: 12 | R13: 40 x 30 x 1 cm | S13: 41.1 x 30.7 x 1.4 cm | T13: 1.58 kg | V13: 12 | W13: 202608 | X13: 1 | Y13: 已匹配202608 | Z13: 17.09 | AA13: 4884 | AB13: 4.6 | AC13: 卖家精灵 | AF13: 2022-10-27 | AI13: 1 | AJ13: 1215 | AK13: 22987.8 | AL13: 18.95 | AM13: 0.6463 | AN13: 3.86 | AO13: 4.6 | AP13: 4796 | AQ13: 11.28 | AR13: 137 | AU13: 2022-10-27 | AW13: 18 | AX13: 1 | AY13: Kitchenville Home & Kitchen | AZ13: GB | BB13: FBA | BC13: 1.32 kg | BD13: 40 x 30 x 1 cm | BE13: 同子体匹配 | BF13: Glasschneidebrett 40×30 cm – Hygienisches Schneidebrett aus gehärtetem Glas – Hitzebeständig, Kratzfest & Rutschfest – Glasplatte für die Küche – Transparentes Design | BG13: Marke: Kitchenville | Farbe: Klare | Produktabmessungen: 40L x 30B x 1D cm | Material: Hartglas | Empfohlene Anwendungen für Produkt: Brot, Fisch, Fleisch, Gemüse, Käse, Obst | Form: Rechteckig | Produktpflegeanweisungen: Nur Handwäsche | Besonderes Merkmal: Hitzebeständig, Kratzfest, Rutschfeste Füße, Schmutzabweisend, Umweltfreundlich | Enthaltene Komponenten: Benutzerhandbuch, Ersatzfüße aus Silikon | Artikelgewicht: 1,32 Kilograms | BH13: Langlebig & Bruchsicher: Hergestellt aus hochwertigem, gehärtetem Glas, bietet dieses Schneidebrett eine lange Lebensdauer und ist ideal für den täglichen Küchengebrauch. Hitzebeständig & Multifunktional: Schützt Ihre Küchenoberflächen vor Hitze, Feuchtigkeit und Kratzern, und dient zugleich als praktischer Untersetzter. Leicht zu Reinigen & Hygienisch: Seine glatte Oberfläche ist einfach abzuwischen, widerstandsfähig gegen Bakterien und Kratzer, und fördert eine saubere Küchenumgebung. Essenzieller Küchenhelfer: Ein Must-Have für jede Küche, das Design und Funktionalität geschickt kombiniert. Zusätzliche Sicherheit: Inklusive rutschfester Silikonfüße, die Stabilität beim Schneiden gewährleisten. | BI13: 200 | BJ13: 3790 | BK13: 100 | BL13: 1836 | BM13: 971 | BN13: 1014 | BO13: 920 | BP13: 1292 | BQ13: 4 | BR13: 920 | BS13: 77 | BT13: 历史为固定父体样本，不能分配给该规格；子体原值多为50/100等阶梯值，不视为精确订单。 | BU13: 60 | BV13: 60
B14: B0D8FKBN65 | C14: B0DP8BFBS4 | D14: Stil: Ehemann | E14: https://www.amazon.de/dp/B0D8FKBN65 | F14: https://images-na.ssl-images-amazon.com/images/I/71sPxsW0UUL._AC_US200_.jpg | G14: Giftasy | H14: Giftasy Hochzeitstag Geschenke für Männer - Bambus Schneidebrett, Jahrestag Geschenk für ihn, Geschenk Ehemann Geburtstag, Ge | I14: Giftasy 竹切菜板，男士结婚周年及丈夫生日礼物（原文截断） | J14: {"bestSeller": "N", "amazonChoice": "Amazons Tipp", "newRelease": "N", "ebc": "Y", "video": "N"} | K14: Küche, Haushalt & Wohnen:Küche, Kochen & Backen:Küchenhelfer & Kochzubehör:Schneidbretter & -matten:Hackbretter | L14: kitchen | M14: 4514 | N14: Hackbretter（砧板） | O14: 13 | R14: 31.2 x 22 x 1 cm | S14: 30.9 x 21.8 x 0.9 cm | T14: 410 g | V14: 13 | W14: 202608 | X14: 1 | Y14: 已匹配202608 | Z14: 16.99 | AA14: 724 | AB14: 4.6 | AC14: 卖家精灵 | AF14: 2024-07-26 | AI14: 1 | AJ14: 1252 | AK14: 21271.48 | AL14: 16.99 | AM14: 0.6899 | AN14: 2.72 | AO14: 4.6 | AP14: 718 | AQ14: 2 | AR14: 25 | AU14: 2024-07-26 | AW14: 13 | AX14: 1 | AY14: MOQIULI | AZ14: CN | BB14: FBA | BC14: 400 g | BD14: 31.2 x 22 x 1 cm | BE14: 仅同父体；属性不借用 | BM14: 4621 | BN14: 1310 | BO14: 1143 | BP14: 1353 | BQ14: 4 | BR14: 1143 | BS14: 101 | BT14: 历史为固定父体样本，不能分配给该规格；子体原值多为50/100等阶梯值，不视为精确订单。未按同父体借用其他变体参数。 | BV14: 67
B15: B0H8YJD6DL | C15: B0HFWFMBYQ | D15: Größe: 3 Stück | E15: https://www.amazon.de/dp/B0H8YJD6DL | F15: https://images-na.ssl-images-amazon.com/images/I/71kDwRtL4pL._AC_US200_.jpg | G15: Aceselfㅤㅤㅤㅤㅤ | H15: Titan Schneidebrett Set 3 Stück, Spülmaschinenfest, Rutschfest & Langlebig | Robust, Ideal für Küche, Fleisch, Brot und Gemüs | I15: 钛切菜板三件套，宣称可洗碗机清洗、防滑耐用，用于肉、面包和蔬菜（原文截断） | J15: {"bestSeller": "N", "amazonChoice": "Amazons Tipp", "newRelease": "N", "ebc": "Y", "video": "N"} | K15: Küche, Haushalt & Wohnen:Küche, Kochen & Backen:Küchenhelfer & Kochzubehör:Schneidbretter & -matten:Hackbretter | L15: kitchen | M15: 1834 | N15: Hackbretter（砧板） | O15: 14 | R15: 40 x 27 x 0.8 cm | S15: 42.2 x 27.3 x 1 cm | T15: 2.39 kg | V15: 14 | W15: 202608 | X15: 1 | Y15: 已匹配202608 | Z15: 45.99 | AA15: 5 | AB15: 4.1 | AC15: 卖家精灵 | AF15: 2026-08-14 | AI15: 1 | AJ15: 875 | AK15: 36207.5 | AL15: 38.99 | AM15: 0.7318 | AN15: 4.61 | AO15: 4.6 | AP15: 15 | AQ15: 0 | AR15: 0 | AU15: 2026-08-14 | AW15: 3 | AX15: 1 | AY15: ACESELF-EU | AZ15: CN | BB15: FBA | BC15: 1.92 kg | BD15: 40 x 27 x 0.8 cm | BE15: 仅同父体；属性不借用 | BM15: 13 | BN15: 0 | BO15: 202 | BP15: 943 | BQ15: 4 | BR15: 0 | BS15: 68 | BT15: 历史为固定父体样本，不能分配给该规格；子体原值多为50/100等阶梯值，不视为精确订单。未按同父体借用其他变体参数。 | BV15: 56
B16: B0GWRD2C1L | C16: B0GWRD2C1L | D16: NA | E16: https://www.amazon.de/dp/B0GWRD2C1L | F16: https://images-na.ssl-images-amazon.com/images/I/919N7dhDBWL._AC_US200_.jpg | G16: EDELHAUS | H16: EDELHAUS Schneidebrett Holz 3er Set Akazie, Holzschnedebrett mit Saftrille | Schneidbretter ohne Mikroplastik aus Akazie 2 cm | I16: EDELHAUS 金合欢木切菜板三件套，带汁槽，厚2厘米，宣称无微塑料（原文截断） | J16: {"bestSeller": "N", "amazonChoice": "Amazons Tipp", "newRelease": "N", "ebc": "Y", "video": "Y"} | K16: Küche, Haushalt & Wohnen:Küche, Kochen & Backen:Küchenhelfer & Kochzubehör:Schneidbretter & -matten:Hackbretter | L16: kitchen | M16: 9056 | N16: Hackbretter（砧板） | O16: 15 | R16: 43.4 x 32.5 x 2.5 cm | S16: 42.1 x 31.9 x 7.8 cm | T16: 3.39 kg | V16: 15 | W16: 202608 | X16: 1 | Y16: 已匹配202608 | Z16: 49.95 | AA16: 45 | AB16: 4.6 | AC16: 卖家精灵 | AF16: 2026-05-16 | AI16: 1 | AJ16: 143 | AK16: 6473.61 | AL16: 37.95 | AM16: 0.714 | AN16: 5.16 | AO16: 4.9 | AP16: 20 | AQ16: 11.89 | AR16: 17 | AU16: 2026-05-16 | AW16: 1 | AX16: 1 | AY16: EDELHAUS DE | AZ16: CZ | BB16: FBA | BC16: 1.36 kg | BD16: 43.4 x 32.5 x 2.5 cm | BE16: 同子体匹配 | BF16: Schneidebrett Holz 3er Set Akazie, Holzschnedebrett mit Saftrille | BG16: Marke: EDELHAUS | Farbe: Doppelseitiges Design 3er Set | Produktabmessungen: 44L x 33B x 11D cm | Material: Akazienholz | Empfohlene Anwendungen für Produkt: Brot, Fisch, Fleisch, Käse, Obst | Form: Rechteckig | Besonderes Merkmal: Eingebaute Nut | Enthaltene Komponenten: Rutschfeste Füße | Artikelgewicht: 1,36 Kilograms | Namen des Sets: Akazienholz Schneidebrett 3er Set | BH16: ROBUSTE AKAZIE – Unsere Schneidebretter aus hochwertigem Akazienholz sind extrem langlebig und bieten die perfekte Balance zwischen Stabilität und Messerschonung. Ideal für jede Küche! IDEALE GRÖßEN – Das Schneidebrett Set umfasst drei praktische Größen: 40x30 cm, 33x24 cm und 26x18 cm. Perfekt für verschiedene Küchenaufgaben und alle Ihre Schneidbedürfnisse. HYGIENISCH & DURCHDACHT – Eingravierte Lebensmittelsymbole zeigen auf einen Blick, welche Brettseite für Fleisch, Gemüse, Obst oder Käse vorgesehen ist. So lassen sich verschiedene Lebensmittel gezielt trennen. Für hygienischeres Schneiden und mehr Ordnung bei der Zubereitung. ELEGANTES DESIGN – Die natürliche Maserung des Akazienholzes macht jedes Holzbrett zu einem Unikat und verleiht Ihrer Küche einen stilvollen Look. Ideal als Servierbrett für Ihre Gäste! SAFTRILLE & RUTSCHFESTE FÜSSE – Die tiefe Saftrille fängt Flüssigkeiten von Fleisch, Obst und Gemüse zuverlässig auf, bevor sie auf die Arbeitsfläche gelangen. Rutschfeste Füße sorgen gleichzeitig für einen stabilen Halt beim Schneiden und Hacken. Kein lästiges Verrutschen des Schneidebretts. | BI16: 100 | BJ16: 4286 | BP16: 115 | BQ16: 1 | BS16: -28 | BT16: 历史为固定父体样本，不能分配给该规格；子体原值多为50/100等阶梯值，不视为精确订单。 | BU16: 74 | BV16: 74
B17: B0FJR2M8F4 | C17: B0FJXT4BZ9 | D17: Farbe: Grün | E17: https://www.amazon.de/dp/B0FJR2M8F4 | F17: https://images-na.ssl-images-amazon.com/images/I/61W4RXxOqGL._AC_US200_.jpg | G17: Culiex | H17: Holzfaser Schneidebrett 2er-Pack, Spülmaschinenfest Composite Cutting Board | Nicht Giftig, BPA-frei, Rutschfeste Füße, Hohe | I17: 木纤维复合切菜板两件套，宣称可洗碗机清洗、无毒、不含双酚A（BPA），带防滑脚（原文截断） | J17: {"bestSeller": "N", "amazonChoice": "Amazons Tipp", "newRelease": "N", "ebc": "Y", "video": "Y"} | K17: Küche, Haushalt & Wohnen:Küche, Kochen & Backen:Küchenhelfer & Kochzubehör:Schneidbretter & -matten:Hackbretter | L17: kitchen | M17: 2049 | N17: Hackbretter（砧板） | O17: 16 | R17: 36.7 x 27 x 1.2 cm | S17: 37.3 x 32 x 2.4 cm | T17: 1.37 kg | V17: 16 | W17: 202608 | X17: 2 | Y17: 已匹配202608 | Z17: 59.99 | AA17: 457 | AB17: 4.2 | AC17: 卖家精灵 | AF17: 2025-09-28 | AI17: 1 | AJ17: 1202 | AK17: 68634.2 | AL17: 59.99 | AM17: 0.7857 | AN17: 3.86 | AO17: 4.1 | AP17: 574 | AQ17: 4.66 | AR17: 56 | AU17: 2025-09-28 | AW17: 3 | AX17: 2 | AY17: Culiex Direct | AZ17: CN | BB17: FBA | BC17: 1,37 Kilograms | BD17: 36.7 x 27 x 1.2 cm | BE17: 仅同父体；属性不借用 | BM17: 866 | BN17: 1192 | BO17: 864 | BP17: 1215 | BQ17: 4 | BR17: 864 | BS17: 13 | BT17: 历史为固定父体样本，不能分配给该规格；子体原值多为50/100等阶梯值，不视为精确订单。未按同父体借用其他变体参数。 | BV17: 61
B18: B09PN2V36H | C18: B0CT8QWW3G | D18: Farbe: Schwarz | Größe: 20.3L x 15.2B cm | E18: https://www.amazon.de/dp/B09PN2V36H | F18: https://images-na.ssl-images-amazon.com/images/I/71JvCq1aS8L._AC_US200_.jpg | G18: Victorinox | H18: Victorinox Schneidebrett, Klingenschonend, Spülmaschinenfest, XS, Schwarz | 20.3 x 15.2 x 0.6, Robustes Hackbrett aus Papierv | I18: Victorinox XS号黑色切菜板，20.3×15.2×0.6，保护刀刃，可洗碗机清洗；材质原文截断 | J18: {"bestSeller": "N", "amazonChoice": "Amazons Tipp", "newRelease": "N", "ebc": "Y", "video": "Y"} | K18: Küche, Haushalt & Wohnen:Küche, Kochen & Backen:Küchenhelfer & Kochzubehör:Schneidbretter & -matten:Hackbretter | L18: kitchen | M18: 5270 | N18: Hackbretter（砧板） | O18: 17 | R18: 15.2 x 20.3 x 0.6 cm | S18: 20.3 x 14.7 x 0.7 cm | T18: 210 g | V18: 17 | W18: 202608 | X18: 1 | Y18: 已匹配202608 | Z18: 12.96 | AA18: 577 | AB18: 4.1 | AC18: 卖家精灵 | AF18: 2022-03-11 | AI18: 1 | AJ18: 878 | AK18: 13538.76 | AL18: 15.42 | AM18: 0.6814 | AN18: 2.6 | AO18: 4 | AP18: 568 | AQ18: 0.8 | AR18: 7 | AU18: 2022-03-11 | AW18: 8 | AX18: 12 | AY18: Amazon | AZ18: DE | BB18: AMZ | BC18: 210 g | BD18: 15.2 x 20.3 x 0.6 cm | BE18: 同子体匹配 | BF18: Victorinox Schneidebrett, Klingenschonend, Spülmaschinenfest, XS, Schwarz | BG18: Marke: Victorinox | Farbe: Schwarz | Produktabmessungen: 20,3L x 15,2B x 0,6D cm | Material: Kunststoff | Empfohlene Anwendungen für Produkt: Brot, Gemüse, Käse, Meat, Obst | Form: Rechteckig | Produktpflegeanweisungen: Spülmaschinenfest | Besonderes Merkmal: Heat Resistant, Long Lasting, Reversible | Enthaltene Komponenten: Components included in description | Artikelgewicht: 210 g | BH18: IMMER GRIFFBEREIT: Das klingenschonende Schneidebrett von Victorinox ist die perfekte Lösung für Ihre Küche. Mit seinem schlanken, kompakten Design passt es in jede Küche und ist immer griffbereit. PRAKTISCH UND ROBUST: Aus Papierverbundstoff gefertigt, ist es spülmaschinenfest und bis zu 175 °C hitzebeständig. Es vereint Funktionalität und Langlebigkeit in einem Produkt. ELEGANZ UND VIELSEITIGKEIT: Mit seinem eleganten Design ist es nicht nur zum Schneiden und Hacken geeignet, sondern auch zum Zubereiten und Servieren. Es ist ein vielseitiges und stilvolles Küchenwerkzeug. HÖCHSTE SCHWEIZER QUALITÄT: Victorinox steht für meisterhafte Handwerkskunst und innovatives Design. In die Entwicklung unserer ikonischen, hochwertigen Messer, Uhren, Taschen, Koffer und Düfte bringen wir 130 Jahre Erfahrung mit ein. PRODUKTDETAILS: Länge 203 mm, Breite 152 mm, Höhe 6 mm, Gewicht 227 g, Farbe Schwarz, Artikel 7.4120, Schneidebrett Kitchen Series XS | BI18: 100 | BJ18: 1542 | BM18: 409 | BN18: 432 | BO18: 493 | BP18: 885 | BQ18: 4 | BR18: 409 | BS18: 7 | BT18: 历史为固定父体样本，不能分配给该规格；子体原值多为50/100等阶梯值，不视为精确订单。 | BU18: 70 | BV18: 70
B19: B0HFHL3Y37 | C19: NA | D19: NA | E19: https://www.amazon.de/dp/B0HFHL3Y37 | F19: NA | G19: NA | H19: 3er-Set Titan Schneidebrett, doppelseitig, aus S316 Edelstahl, BPA-frei | Für Fleisch, Brot, Gemüse und Obst, leichte Reinigu | I19: 双面切菜板三件套，宣称不含双酚A（BPA），用于肉、面包、蔬菜及水果；原文同时称钛与S316不锈钢（原文截断） | J19: NA | K19: NA | L19: NA | M19: NA | N19: Hackbretter（砧板） | O19: 18 | R19: NA | S19: NA | T19: NA | V19: 18 | W19: 202608 | X19: NA | Y19: NA｜源端未返回202608记录 | Z19: NA | AA19: 18 | AB19: 5 | AC19: 卖家精灵 | AF19: NA | AI19: 1 | AJ19: NA | AK19: NA | AL19: NA | AM19: NA | AN19: NA | AO19: NA | AP19: NA | AQ19: NA | AR19: NA | AU19: NA | AW19: NA | AX19: NA | AY19: NA | AZ19: NA | BB19: NA | BC19: NA | BD19: NA | BE19: 未匹配 | BQ19: 0 | BT19: 历史为固定父体样本，不能分配给该规格；子体原值多为50/100等阶梯值，不视为精确订单。未按同父体借用其他变体参数。
B20: B0FVYFBN8G | C20: B0FVYFBN8G | D20: NA | E20: https://www.amazon.de/dp/B0FVYFBN8G | F20: https://images-na.ssl-images-amazon.com/images/I/710n2CVTkhL._AC_US200_.jpg | G20: iWangDunD | H20: 3PCS Schneidebrett Titan,BPA-freies Doppelseitiges Lebensmittel Titanium Cutting Board,S316 Schneidebrett Edelstahl,für Fleis | I20: 双面金属切菜板三件套，宣称不含双酚A（BPA）；原文同时称钛与S316不锈钢（原文截断） | J20: {"bestSeller": "N", "amazonChoice": "N", "newRelease": "N", "ebc": "Y", "video": "Y"} | K20: Küche, Haushalt & Wohnen:Küche, Kochen & Backen:Küchenhelfer & Kochzubehör:Schneidbretter & -matten:Hackbretter | L20: kitchen | M20: 3045 | N20: Hackbretter（砧板） | O20: 19 | R20: 29 x 20 x 1 cm | S20: 39.4 x 28.4 x 1.1 cm | T20: 1.58 kg | V20: 19 | W20: 202608 | X20: 1 | Y20: 已匹配202608 | Z20: 16.83 | AA20: 121 | AB20: 3.9 | AC20: 卖家精灵 | AF20: 2025-11-21 | AI20: 1 | AJ20: 1163 | AK20: 23166.96 | AL20: 19.99 | AM20: 0.6494 | AN20: 4.01 | AO20: 3.9 | AP20: 106 | AQ20: 2.75 | AR20: 32 | AU20: 2025-11-21 | AW20: 1 | AX20: 1 | AY20: jiujiangshiwangdundundianzishangwuyouxiangongsi | AZ20: CN | BB20: FBA | BC20: 1,58 Kilograms | BD20: 29 x 20 x 1 cm | BE20: 同子体匹配 | BF20: 3PCS Schneidebrett Titan,BPA-freies Doppelseitiges Lebensmittel Titanium Cutting Board,S316 Schneidebrett Edelstahl,für Fleisch, Brot, Gemüse & Obst (S+M+L) | BG20: Marke: iWangDunD | Farbe: Silber | Produktabmessungen: 29L x 20B x 1D cm | Material: Edelstahl | Empfohlene Anwendungen für Produkt: Gemüse | Form: Rechteckig | Produktpflegeanweisungen: Spülmaschinenfest | Besonderes Merkmal: Antimikrobiell, Rutschfeste Füße, Wechselseitig | Artikelgewicht: 1,58 Kilograms | Anzahl der Packungen: 3 | BH20: 🎯【Drei Optimale Größen (39x28cm, 34x23cm, 29x20cm) & Beidseitig Nutzbar】:Unser Set aus drei Boards deckt jede Küchenaufgabe ab: Klein (29x20cm) für Kräuter & Knoblauch, Medium (34x23cm) für Gemüse & Obst, Large (39x28cm) für Fleisch & Fisch. Jedes Brett ist beidseitig nutzbar – trennen Sie rohe und gekochte Lebensmittel für absolute Hygiene. 🔬【Hochwertiger Edelstahl & Antibakteriell】:Hergestellt aus lebensmittelechtem, rostfreiem 316er Edelstahl. Die ultra-glatte Oberfläche hemmt Bakterienwachstum natürlich, verhindert Gerüche und ist geschmacksneutral. Perfekt für den hygienischen Umgang mit allen Lebensmitteln. 💦【Extrem Pflegeleicht & Langlebig】:Spülmaschinengeeignet für blitzschnelle Reinigung. Edelstahl ist unempfindlich gegen Messerschnitte, splittert nicht und nimmt keine Feuchtigkeit auf. Eine langlebige Investition, resistent gegen Verfärbungen und Verformungen. 🛡【Maximale Sicherheit & Stabilität】:Jedes Brett verfügt über einen stabilen, rutschfesten Gummi-Rahmen. Dieser sorgt für sicheren Halt auf der Arbeitsfläche, verhindert Verrutschen und schont Ihre Messerklingen. Inklusive praktischem Aufhänger. 🌀【Vielseitig Einsetzbar in Küche & Haushalt】:Ideal als Schneidebrett, Servierplatte für Käse/Aufschnitt oder Unterlage für Teig. Die große Platte (39x28cm) eignet sich auch perfekt als Tablett für Grillgut. Ein unverzichtbares Utensil für Hobbyköche und Profis. | BI20: 800 | BJ20: 15992 | BK20: 400 | BL20: 7824 | BM20: 405 | BN20: 664 | BO20: 884 | BP20: 1273 | BQ20: 4 | BR20: 405 | BS20: 110 | BT20: 历史为固定父体样本，不能分配给该规格；子体原值多为50/100等阶梯值，不视为精确订单。 | BU20: 65 | BV20: 65
B21: B071NG664G | C21: B0DBZWS24J | D21: Größe: 42L x 30B cm | Farbe: Braun | E21: https://www.amazon.de/dp/B071NG664G | F21: https://images-na.ssl-images-amazon.com/images/I/51brnO9PPpL._AC_US200_.jpg | G21: Kesper | H21: KESPER | Profi-Schneidbrett, Material: Akazienholz (Stirnholz), Maße: 42 x 30 x 4 cm, Farbe: Braun, Natur | 28151 | I21: KESPER 金合欢端纹木专业切菜板，42×30×4厘米，棕色原木色，型号28151 | J21: {"bestSeller": "N", "amazonChoice": "Amazons Tipp", "newRelease": "N", "ebc": "Y", "video": "Y"} | K21: Küche, Haushalt & Wohnen:Küche, Kochen & Backen:Küchenhelfer & Kochzubehör:Schneidbretter & -matten:Hackbretter | L21: kitchen | M21: 6538 | N21: Hackbretter（砧板） | O21: 20 | R21: 42 x 30 x 4 cm | S21: 42.1 x 30.1 x 3.9 cm | T21: 2.64 kg | V21: 20 | W21: 202608 | X21: 1 | Y21: 已匹配202608 | Z21: 18.24 | AA21: 292 | AB21: 4.3 | AC21: 卖家精灵 | AF21: 2017-06-15 | AI21: 1 | AJ21: 712 | AK21: 16326.16 | AL21: 21.71 | AM21: 0.6377 | AN21: 4.61 | AO21: 4.2 | AP21: 289 | AQ21: 1.83 | AR21: 13 | AU21: 2017-06-15 | AW21: 3 | AX21: 10 | AY21: Amazon | AZ21: DE | BB21: AMZ | BC21: 499 g | BD21: 42 x 30 x 4 cm | BE21: 同子体匹配 | BF21: KESPER | Profi-Schneidbrett, Material: Akazienholz (Stirnholz), Maße: 42 x 30 x 4 cm, Farbe: Braun, Natur | 28151 | BG21: Marke: Kesper | Farbe: Braun | Produktabmessungen: 42L x 30B x 4D cm | Material: Akazienholz | Empfohlene Anwendungen für Produkt: Brot, Fisch, Fleisch, Gemüse, Käse, Obst | Form: Rechteckig | Produktpflegeanweisungen: Nur Handwäsche | Besonderes Merkmal: Langanhaltend | Enthaltene Komponenten: Messer | Artikelgewicht: 499 g | BH21: aus FSC-zertifiziertem Holz Stirnholz, mosaikförmig verleimt mit 2 Griffmulden hohe Schnittfestigkeit und besonders messerschonend | BI21: 300 | BJ21: 6828 | BK21: 100 | BL21: 2265 | BM21: 434 | BN21: 548 | BO21: 678 | BP21: 760 | BQ21: 4 | BR21: 434 | BS21: 48 | BT21: 历史为固定父体样本，不能分配给该规格；子体原值多为50/100等阶梯值，不视为精确订单。 | BU21: 71 | BV21: 71
B22: B0FGJ41MY5 | C22: B0DP8YDQ84 | D22: Stil: 50. Geburtstag | E22: https://www.amazon.de/dp/B0FGJ41MY5 | F22: https://images-na.ssl-images-amazon.com/images/I/71DItL69+oL._AC_US200_.jpg | G22: Giftasy | H22: Giftasy 50 Geburtstag Mann - Graviertes Bambus Schneidebrett, Geschenke zum 50 Geburtstag Mann | I22: Giftasy 雕刻竹切菜板，男士50岁生日礼物 | J22: {"bestSeller": "N", "amazonChoice": "Amazons Tipp", "newRelease": "N", "ebc": "Y", "video": "N"} | K22: Küche, Haushalt & Wohnen:Küche, Kochen & Backen:Küchenhelfer & Kochzubehör:Schneidbretter & -matten:Hackbretter | L22: kitchen | M22: 6288 | N22: Hackbretter（砧板） | O22: 21 | R22: 31.2 x 22 x 1 cm | S22: 30.9 x 21.8 x 1.1 cm | T22: 410 g | V22: 21 | W22: 202608 | X22: 1 | Y22: 已匹配202608 | Z22: 17.99 | AA22: 410 | AB22: 4.6 | AC22: 卖家精灵 | AF22: 2025-07-21 | AI22: 1 | AJ22: 804 | AK22: 14021.76 | AL22: 15.29 | AM22: 0.6988 | AN22: 2.72 | AO22: 4.6 | AP22: 407 | AQ22: 2.61 | AR22: 21 | AU22: 2025-07-21 | AW22: 12 | AX22: 2 | AY22: MOQIULI | AZ22: CN | BB22: FBA | BC22: 410 g | BD22: 31.2 x 22 x 1 cm | BE22: 同子体匹配 | BF22: 50 Geburtstag Mann - Graviertes Bambus Schneidebrett, Geschenke zum 50 Geburtstag Mann | BG22: Marke: Giftasy | Farbe: Naturbambus | Produktabmessungen: 31,2L x 1B x 22D cm | Material: Bambus | Empfohlene Anwendungen für Produkt: Brot, Gemüse, Käse, Obst | Form: Rechteckig | Produktpflegeanweisungen: Nur Handwäsche | Besonderes Merkmal: Eingebauter Griff, Langanhaltend, Leichtgewichtig, Platzsparend, Umweltfreundlich | Artikelgewicht: 410 g | Anzahl der Artikel: 1 | BH22: Kreatives Geschenk zum 50 Geburtstag: Dieses Schneidebrett aus umweltfreundlichem Bambus ist ein besonderes und durchdachtes Geburtstagsgeschenk für Männer. Die Gravur „Alles Gute zum 50. Geburtstag – Grillmeister“ verleiht dem Brett eine persönliche und humorvolle Note Perfekte Geschenke für den Mann zum 50 Geburtstag: Ob für Vater, Ehemann, Freund oder Kollege – dieses praktische Schneidebrett ist ein ideales Geschenk für jeden Mann zum 50. Geburtstag, besonders für leidenschaftliche Grillfans Nützlich und dekorativ zugleich: Das Brett überzeugt nicht nur durch seine Funktionalität, sondern auch als stilvolle Deko für Küche oder Grillbereich. Es verleiht jeder Männerküche eine persönliche Note Stabil langlebig hochwertig: Hergestellt aus robustem, dichtem Bambus ist das Brett besonders strapazierfähig, schnittfest und pflegeleicht – ideal für den täglichen Einsatz oder den Grillabend im Garten Mit Liebe gemacht zuverlässiger Service: Giftasy steht für kreative Geschenke für Männer mit Herz. Sollte einmal etwas nicht passen, sorgt unser Kundenservice schnell und unkompliziert für eine Lösung – damit dein Geburtstagsgeschenk rundum überzeugt | BI22: 100 | BJ22: 1799 | BK22: 50 | BL22: 877 | BM22: 1388 | BN22: 967 | BO22: 730 | BP22: 844 | BQ22: 4 | BR22: 730 | BS22: 40 | BT22: 历史为固定父体样本，不能分配给该规格；子体原值多为50/100等阶梯值，不视为精确订单。 | BU22: 68 | BV22: 68
B23: B0DPDKLHYM | C23: B0F9THXWPY | D23: Farbe: 3 Stück Titan Schneidebrett Set | E23: https://www.amazon.de/dp/B0DPDKLHYM | F23: https://images-na.ssl-images-amazon.com/images/I/81D-tOyv9YL._AC_US200_.jpg | G23: Bafeil | H23: Bafeil Titan Schneidebrett Set 3 Stück - 316 Edelstahl Schneidebrett | Titanium Cutting Board, Doppelseitiges Lebensmittel Gr | I23: Bafeil 双面切菜板三件套；原文同时称钛与316不锈钢，材质待确认（原文截断） | J23: {"bestSeller": "N", "amazonChoice": "N", "newRelease": "N", "ebc": "Y", "video": "Y"} | K23: Küche, Haushalt & Wohnen:Küche, Kochen & Backen:Küchenhelfer & Kochzubehör:Schneidbretter & -matten:Hackbretter | L23: kitchen | M23: 16234 | N23: Hackbretter（砧板） | O23: 22 | R23: 39 x 28 x 0.1 cm | S23: 39.8 x 30.8 x 0.7 cm | T23: 1.64 kg | V23: 22 | W23: 202608 | X23: 1 | Y23: 已匹配202608 | Z23: 19.19 | AA23: 425 | AB23: 4.1 | AC23: 卖家精灵 | AF23: 2025-02-09 | AI23: 1 | AJ23: 547 | AK23: 14550.2 | AL23: 22.69 | AM23: 0.6733 | AN23: 4.01 | AO23: 4 | AP23: 415 | AQ23: 10.05 | AR23: 55 | AU23: 2025-02-09 | AW23: 4 | AX23: 1 | AY23: Bafeil | AZ23: CN | BB23: FBA | BC23: 1.56 kg | BD23: 39 x 28 x 0.1 cm | BE23: 同子体匹配 | BF23: Titan Schneidebrett Set 3 Stück - 316 Edelstahl Schneidebrett | BG23: Marke: Bafeil | Farbe: 3 Stück Titan Schneidebrett Set | Produktabmessungen: 39L x 28B x 0,2D cm | Material: Titan | Empfohlene Anwendungen für Produkt: Brot, Fisch, Gemüse, Käse, Meat, Obst | Form: Rechteckig | Produktpflegeanweisungen: Spülmaschinenfest | Besonderes Merkmal: Wechselseitig | Enthaltene Komponenten: 3 Stück Titan Schneidebretter | Artikelgewicht: 1,56 Kilograms | BH23: 3 Stück Titan Schneidebrett - Unser schneidebrett edelstahl ist medizinischem Titan gefertigt, was es zur sichersten Wahl in Ihrer Küche macht. Dieses titanschneidebrett ist langlebig und gleichermaßen sicher für Ihre Gesundheit und Ihre Messer. Optimale Küchenutensilien - Unser Titan-Schneidebrett, das als perfektes Küchenzubehör dient, kann beidseitig verwendet werden. Eine Seite für Obst und Gemüse und die andere Seite für Fleisch, um einen Kreuzgebrauch zu vermeiden. Ideal als robustes und stilvolles Titanium Schneidebrett. Messerfreundlich - Titan ist dreimal weicher als der Stahl, der in 99% der Küchenmesser verwendet wird. Dies bedeutet, dass unsere Schneidebretter aus Titan Ihre Messer scharf halten, während Sie sämtliches Hacken und Schneiden ausführen. Hochwertiges Material und weit verbreitet - Das hochwertige edelstahl schneidebrett ist stark genug, um starkem Hacken und Schneiden standzuhalten. Es ist vielseitig und eignet sich zum Ausrollen von Kuchenteig, Kneten von Brot oder Schneiden von Obst, Gemüse und Brot. Ideal als Titanium Cutting Board für Küche, Kochen und Camping. Aussergewöhnlich Einfach Zu Reinigen: Vergessen Sie das Schrubben von Flecken und Gerüchen auf Holz- oder Plastik-Schneidebrettern. Titan schneidebrett spülmaschinenfest, Unser schneidebrett aus titan schneidbrett edelstahl lässt Lebensmittel nicht haften, einfach mit Leitungswasser abspülen und sofort wieder bereit. Perfekt als schneidebrett ohne plastik für mühelose Hygiene. | BI23: 200 | BJ23: 5162 | BK23: 200 | BL23: 4770 | BM23: 551 | BN23: 859 | BO23: 474 | BP23: 599 | BQ23: 4 | BR23: 474 | BS23: 52 | BT23: 历史为固定父体样本，不能分配给该规格；子体原值多为50/100等阶梯值，不视为精确订单。 | BU23: 47 | BV23: 47
B24: B0FLXV8ZXD | C24: B0FLXV8ZXD | D24: NA | E24: https://www.amazon.de/dp/B0FLXV8ZXD | F24: https://images-na.ssl-images-amazon.com/images/I/81NoujQBtJL._AC_US200_.jpg | G24: Matakumi | H24: Matakumi Holzschneidebrett – Schneidebrett aus Holz aus Akazie mit Seitengriffen, Saftrille und Stirnholzfläche zum Schutz de | I24: Matakumi 金合欢木切菜板，带侧把手、汁槽及端纹板面（原文截断） | J24: {"bestSeller": "N", "amazonChoice": "Amazons Tipp", "newRelease": "N", "ebc": "Y", "video": "N"} | K24: Küche, Haushalt & Wohnen:Küche, Kochen & Backen:Küchenhelfer & Kochzubehör:Schneidbretter & -matten:Hackbretter | L24: kitchen | M24: 19874 | N24: Hackbretter（砧板） | O24: 23 | R24: 40 x 30 x 3 cm | S24: 44.2 x 32.9 x 5.5 cm | T24: 2.45 kg | V24: 23 | W24: 202608 | X24: 1 | Y24: 已匹配202608 | Z24: 37.99 | AA24: 197 | AB24: 4.4 | AC24: 卖家精灵 | AF24: 2025-08-15 | AI24: 1 | AJ24: 394 | AK24: 15440.86 | AL24: 39.99 | AM24: 0.7286 | AN24: 4.61 | AO24: 4.4 | AP24: 185 | AQ24: 5.58 | AR24: 22 | AU24: 2025-08-15 | AW24: 1 | AX24: 1 | AY24: Kranis B.V. | AZ24: NL | BB24: FBA | BC24: 2.6 kg | BD24: 40 x 30 x 3 cm | BE24: 同子体匹配 | BF24: Matakumi Holzschneidebrett – Schneidebrett aus Holz aus Akazie mit Seitengriffen, Saftrille und Stirnholzfläche zum Schutz der Messerklingen – Beidseitig Holzbrett (40 x 30 x 3 cm) | BG24: Marke: Matakumi | Farbe: Braun | Produktabmessungen: 40L x 30B x 3D cm | Empfohlene Anwendungen für Produkt: Fleisch | Form: Rechteckig | Produktpflegeanweisungen: Nur Handwäsche | Besonderes Merkmal: Stirnholz-Konstruktion, Beidseitig nutzbar, Umweltfreundlich | Artikelgewicht: 2,6 Kilograms | Anzahl der Packungen: 1 | Größe: 40 cm x 30 cm | BH24: LANGLEBIG & UMWELTFREUNDLICH: Hergestellt aus dichtem akazienholz, ist dieses langlebige, feuchtigkeitsbeständige holzbrett FSC-zertifiziert und plastikfrei, was eine umweltfreundliche wahl bietet, ohne kompromisse bei qualität oder design einzugehen. SCHONEND FÜR MESSER: Die stirnholz-konstruktion dieses schneidbretts lässt die klingen zwischen die holzfasern gleiten, absorbiert stöße und reduziert abrieb. Sie bewahrt die schärfe und sorgt dafür, dass messer länger leistungsfähig bleiben. BEIDSEITIG NUTZBAR: Die gerillte seite fängt fleischsäfte auf. Die glatte seite ist ideal zum schneiden oder servieren von trockenen lebensmitteln. Wechseln sie mühelos zwischen vorbereitung und präsentation mit nur einem küchenbrett. LEICHT ZU TRAGEN: Integrierte seitengriffe erleichtern das anheben und tragen der schneidebretter, sodass sie mühelos vom arbeitsbereich zum esstisch bewegt werden können, ganz ohne zusätzliche tabletts. DIE PERFEKTE GRÖßE FÜR DEN TÄGLICHEN GEBRAUCH: Die 40 x 30 x 3 cm große fläche bietet ausreichend platz zum schneiden, hacken oder servieren, ohne die arbeitsfläche zu überladen. Fügen sie dieses holz schneidebrett noch heute ihrer küche hinzu! | BI24: 200 | BJ24: 7806 | BK24: 50 | BL24: 1999 | BM24: 169 | BN24: 164 | BO24: 166 | BP24: 403 | BQ24: 4 | BR24: 164 | BS24: 9 | BT24: 历史为固定父体样本，不能分配给该规格；子体原值多为50/100等阶梯值，不视为精确订单。 | BU24: 4 | BV24: 4
B25: B0F4CKS1FV | C25: B0CJK1YNT8 | D25: Farbe: Dunkelgrau | E25: https://www.amazon.de/dp/B0F4CKS1FV | F25: https://images-na.ssl-images-amazon.com/images/I/71Digun7iEL._AC_US200_.jpg | G25: KIMIUP | H25: KIMIUP Schneidebrett Kunststoff, 3 Stück, BPA-freie, Spülmaschinenfest | Kunststoff Schneidebrett Set mit Rutschfeste Füße, S | I25: KIMIUP 塑料切菜板三件套，宣称不含双酚A（BPA）、可洗碗机清洗，带防滑脚（原文截断） | J25: {"bestSeller": "N", "amazonChoice": "Amazons Tipp", "newRelease": "N", "ebc": "Y", "video": "Y"} | K25: Küche, Haushalt & Wohnen:Küche, Kochen & Backen:Küchenhelfer & Kochzubehör:Schneidbretter & -matten:Hackbretter | L25: kitchen | M25: 9181 | N25: Hackbretter（砧板） | O25: 24 | R25: 40 x 24 x 2.5 cm | S25: 39.7 x 23.8 x 2.3 cm | T25: 1.12 kg | V25: 24 | W25: 202608 | X25: 1 | Y25: 已匹配202608 | Z25: 13.29 | AA25: 1102 | AB25: 4.7 | AC25: 卖家精灵 | AF25: 2025-06-05 | AI25: 1 | AJ25: 891 | AK25: 12233.43 | AL25: 13.55 | AM25: 0.5498 | AN25: 3.99 | AO25: 4.6 | AP25: 1093 | AQ25: 2.13 | AR25: 19 | AU25: 2025-06-05 | AW25: 4 | AX25: 1 | AY25: zhimaotech | AZ25: CN | BB25: FBA | BC25: 1.3 kg | BD25: 40 x 24 x 2.5 cm | BE25: 同子体匹配 | BF25: KIMIUP Schneidebrett Kunststoff, 3 Stück, BPA-freie, Spülmaschinenfest | BG25: Marke: KIMIUP | Farbe: Dunkelgrau | Produktabmessungen: 40L x 24B x 0,9D cm | Material: cutting board, frühstücksbrettchen spülmaschinenfest, schneidbrett kunststoff, schneidbretter für die küche, schneidebrett kunststoff, schneidebrett ohne mikroplastik, schneidebrett schwarz, schneidebrett set, schneidebrett spülmaschinenfest, schneidebretter ohne mikroplastik, schneidebretter spülmaschinenfest | Empfohlene Anwendungen für Produkt: 3-teiliges Schneidebrett-Set, Gummi-Schneidebrett, Kleines Schneidebrett, Kunststoff-Schneidebrett für die Küche, Küchenbretter zum Zerkleinern, Küchenschneidebretter, Obstschneidebrett, Rutschfestes Schneidebrett, Schneidebrett schwarz, Schwarzes Schneidebrett-Set | Form: Rechteckig | Produktpflegeanweisungen: Spülmaschinenfest | Besonderes Merkmal: Eingebaute Nut, Eingebauter Griff, Rutschfeste Füße | Enthaltene Komponenten: Rutschfeste Füße | Artikelgewicht: 1,3 Kilograms | BH25: 【𝐇𝐨𝐜𝐡𝐰𝐞𝐫𝐭𝐢𝐠𝐞𝐬 𝐌𝐚𝐭𝐞𝐫𝐢𝐚𝐥】Dieses KIMIUP Schneidbrett besteht aus hochwertigem, BPA-freiem Kunststoff, geruchlos, schmutzabweisend, leicht zu reinigen, sicher bei Lebensmittelkontakt. Die Marmoroberfläche des Schneidebretter wertet die Küche auf, reduziert Kratzer und schont Messer. Es hält täglichem Gebrauch stand. Die porenfreie Oberfläche verhindert das Eindringen von Säften und Rückständen – für maximale Sicherheit. Unsere Schneidebrett kunststoff bieten dauerhaften Schutz für Ihre Familie. 【𝐑𝐮𝐭𝐬𝐜𝐡𝐟𝐞𝐬𝐭𝐞 𝐅üß𝐞 + 𝐆𝐫𝐢𝐟𝐟】Dieses Schneidbrett hat vier rutschfeste Gummifüße, die beim Schneiden fest auf der Arbeitsplatte haften – kein Verrutschen, auch bei harten Zutaten. Das Kunststoff Schneidebrett hat einen bequemen Griff, der das Halten erleichtert; nach Reinigung lässt es sich zum Lüften und Abtropfen aufhängen, hält Arbeitsfläche frei und sorgt für Ordnung. Es ist spülmaschinengeeignet, zeitsparend und hygienisch. Ideal für kleine Küchen oder Apartments, da es wenig Platz braucht. 【𝐙𝐰𝐞𝐢𝐬𝐞𝐢𝐭𝐢𝐠𝐞𝐬 𝐃𝐞𝐬𝐢𝐠𝐧 + 𝐒𝐚𝐟𝐭𝐫𝐢𝐥𝐥𝐞】Dieses Schneidebrett spülmaschinenfest verfügt über zwei Seiten: Eine mit umlaufender Saftrille, die Fleisch- und Tomatensäfte auffängt und die Arbeitsplatte sauber hält; die andere glatt für normales Schneiden oder Anrichten. Die klare Zweiteilung trennt rohe und gekochte Speisen– ein Küchenbrett, das sauber und Effizienz vereint. 【3 𝐒𝐞𝐭, 𝐯𝐢𝐞𝐥𝐬𝐞𝐢𝐭𝐢𝐠 𝐞𝐢𝐧𝐬𝐞𝐭𝐳𝐛𝐚𝐫】Das Schneidebrett Set umfasst 3 Größen für alle Küchenanwendungen: Groß (15,6 x 9,4 Zoll) ideal für Fleisch und Steaks, mit reichlich Schnittfläche; Mittel (12,4 x 7,8 Zoll) perfekt für tägliches Gemüseschneiden und -julienne; Klein (9,6 x 5,7 Zoll) genau richtig für Speisen. Jedes Brettchen spülmaschinenfest ist 0,35 Zoll dicke 0,35 Zoll dick und verzieht sich nicht. Ob Alltag oder Festtag – von der Vorbereitung bis zum Servieren gibt es immer die passende Größe. 【𝐈𝐧𝐭𝐞𝐠𝐫𝐢𝐞𝐫𝐭𝐞𝐫 𝐑𝐞𝐢𝐛𝐞𝐟𝐥ä𝐜𝐡𝐞 ，𝐳𝐞𝐢𝐭𝐬𝐩𝐚𝐫𝐞𝐧𝐝&𝐦ü𝐡𝐞𝐥𝐨𝐬】Die großen und mittleren Schneidebrett Kunststoff haben zusätzlich eine Reibefläche (kleine Größe ohne), speziell zum Reiben von Knoblauch, Ingwer, Zwiebeln usw. Auf einem Schneidbrett können Sie sowohl schneiden als auch reiben, was den Reinigungsaufwand reduziert und das Kochen erleichtert. Die doppelseitiges schneidbretter– eine Seite zum Schneiden, die andere zum Reiben – behindert sich nicht und verdoppelt den praktischen Wert. 【𝐊𝐈𝐌𝐈𝐔𝐏 𝐒𝐜𝐡𝐧𝐞𝐢𝐝𝐛𝐫𝐞𝐭𝐭 – 𝐈𝐡𝐫 𝐢𝐝𝐞𝐚𝐥𝐞𝐬 𝐆𝐞𝐬𝐜𝐡𝐞𝐧𝐤】Dieses Schneidebrett Set mit gebürsteter Oberfläche bietet marmorähnliche Eleganz und wertet jede Küche auf. Ob zum Hauswarming, Geburtstag, Weihnachten, Vatertag oder Muttertag – dieses Kunststoff Schneidebrett ist ein geschmackvolles und praktisches Geschenk für Freunde und Familie. Es begeistert jeden Kochliebhaber und eignet sich für Zuhause, Küche und Outdoor. | BI25: 600 | BJ25: 8292 | BK25: 300 | BL25: 4197 | BM25: 716 | BN25: 734 | BO25: 589 | BP25: 930 | BQ25: 4 | BR25: 589 | BS25: 39 | BT25: 历史为固定父体样本，不能分配给该规格；子体原值多为50/100等阶梯值，不视为精确订单。 | BU25: 73 | BV25: 73
B26: B0GK6N6YKB | C26: B0GK6N6YKB | D26: NA | E26: https://www.amazon.de/dp/B0GK6N6YKB | F26: https://images-na.ssl-images-amazon.com/images/I/51uEmhFvFWL._AC_US200_.jpg | G26: Tosean | H26: Tosean Edelstahl-Schneidebrett 30 x 40cm,Küche Schneidbrettchen,Schweres Schneidebrett zum Kochen, Backen Brot Restaurant zum | I26: Tosean 不锈钢切菜板，30×40厘米，重型，用于厨房烹饪及面包烘焙（原文截断） | J26: {"bestSeller": "N", "amazonChoice": "N", "newRelease": "N", "ebc": "Y", "video": "N"} | K26: Küche, Haushalt & Wohnen:Küche, Kochen & Backen:Küchenhelfer & Kochzubehör:Schneidbretter & -matten:Hackbretter | L26: kitchen | M26: 6174 | N26: Hackbretter（砧板） | O26: 25 | R26: 40 x 30 x 0.2 cm | S26: 40.4 x 30.1 x 2.2 cm | T26: 940 g | V26: 25 | W26: 202608 | X26: 1 | Y26: 已匹配202608 | Z26: 19.99 | AA26: 37 | AB26: 4.5 | AC26: 卖家精灵 | AF26: 2026-02-21 | AI26: 1 | AJ26: 574 | AK26: 11990.86 | AL26: 19.99 | AM26: 0.6504 | AN26: 3.99 | AO26: 4.5 | AP26: 37 | AQ26: 1.39 | AR26: 8 | AU26: 2026-02-21 | AW26: 1 | AX26: 2 | AY26: air velocity | AZ26: CN | BB26: FBA | BC26: 940 g | BD26: 40 x 30 x 0.2 cm | BE26: 同子体匹配 | BF26: Edelstahl-Schneidebrett 30 x 40cm,Küche Schneidbrettchen,Schweres Schneidebrett zum Kochen, Backen Brot Restaurant zum Kneten, für Fleisch, Gemüse für Küche Bar | BG26: Marke: Tosean | Farbe: Maße: 40 X 30 Cm | Produktabmessungen: 40L x 30B x 0,2D cm | Material: Edelstahl | Empfohlene Anwendungen für Produkt: Brot, Fisch, Fleisch, Gemüse, Käse, Obst | Form: Rechteckig | Produktpflegeanweisungen: Spülmaschinenfest | Besonderes Merkmal: Extra erhöhte Kanten | Enthaltene Komponenten: Messer | Artikelgewicht: 940 g | BH26: 【Produktname】Schneidbretter, Edelstahl Schneidebrett, Backbrett, Schneidebrett für Küche, Bar, Restaurants 【Große Größe】Große größe, breite 30, länge 40, gefaltete kantenstärke 1,5 mm, bequemer zum kneten von teig und schneiden von obst und gemüse usw., kann alle ihre anforderungen an das schneiden, schneiden und kneten von gemüse in der küche erfüllen 【Rutschfestes Design】 Dieses schneidebrett aus edelstahl verfügt über extra erhöhte kanten für eine sichere und nahtlose befestigung an ihrer theke, was zur stabilisierung des schneidebretts während des gebrauchs beiträgt. perfekt für alle hack- und schneideaufgaben in der küche 【Stabiles&Leicht zu reinigen】Edelstahl-Schneidebrett Hergestellt aus hochwertigem Edelstahl.Die Dicke beträgt 0,15 cm (0.06inch) .Perfect für alle Ihre Hacken und Schneiden Bedürfnisse in der Küche die Schneidplatten sicher in der Spülmaschine gewaschen werden.Es ist leicht zu reinigen und schmutzabweisend 【Positive und negative Doppelnutzung】Die vorderseite kann geknetet werden, um zu verhindern, dass teig oder süßigkeiten an der oberfläche kleben bleiben; die rückseite kann zum schneiden von gemüse, obst und fleisch verwendet werden,Idee für Hochzeiten, Ruhestand, Geburtstage und Weihnachtsgeschenke für alle Küchen Enthusiasten | BI26: 400 | BJ26: 8252 | BK26: 50 | BL26: 1046 | BM26: 223 | BN26: 165 | BO26: 243 | BP26: 596 | BQ26: 4 | BR26: 165 | BS26: 22 | BT26: 历史为固定父体样本，不能分配给该规格；子体原值多为50/100等阶梯值，不视为精确订单。 | BU26: 75 | BV26: 75
B27: B08YNB45N4 | C27: B0FBMLNYFG | D27: Größe: Klein | Farbe: 2x | E27: https://www.amazon.de/dp/B08YNB45N4 | F27: https://images-na.ssl-images-amazon.com/images/I/91b68n-JWAL._AC_US200_.jpg | G27: Moritz &amp; Moritz | H27: Moritz & Moritz 2x Schneidebrett Kunststoff Set in Granit Optik - 25 x 15 cm - Schneidebretter BPA frei - Frühstücksbrettchen | I27: Moritz & Moritz 花岗岩外观塑料切菜板两件套，25×15厘米，宣称不含双酚A（BPA），可作早餐板 | J27: {"bestSeller": "N", "amazonChoice": "Amazons Tipp", "newRelease": "N", "ebc": "Y", "video": "N"} | K27: Küche, Haushalt & Wohnen:Küche, Kochen & Backen:Küchenhelfer & Kochzubehör:Schneidbretter & -matten:Hackbretter | L27: kitchen | M27: 11290 | N27: Hackbretter（砧板） | O27: 26 | R27: 25 x 15 x 2 cm | S27: 25.2 x 15.4 x 1.8 cm | T27: 540 g | V27: 26 | W27: 202608 | X27: 1 | Y27: 已匹配202608 | Z27: 10.92 | AA27: 786 | AB27: 4.3 | AC27: 卖家精灵 | AF27: 2021-08-25 | AI27: 1 | AJ27: 537 | AK27: 6975.63 | AL27: 12.99 | AM27: 0.6129 | AN27: 3.08 | AO27: 4.3 | AP27: 785 | AQ27: 0.56 | AR27: 3 | AU27: 2021-08-25 | AW27: 6 | AX27: 3 | AY27: Amazon | AZ27: DE | BB27: AMZ | BC27: 450 g | BD27: 25 x 15 x 2 cm | BE27: 同子体匹配 | BF27: Moritz & Moritz 2x Schneidebrett Kunststoff Set in Granit Optik - 25 x 15 cm - Schneidebretter BPA frei - Frühstücksbrettchen - Schneidebrett Set hygienisch und spülmaschinenfest | BG27: Marke: Moritz & Moritz | Farbe: 2x | Produktabmessungen: 25L x 15B x 1D cm | Material: Kunststoff | Empfohlene Anwendungen für Produkt: Brot | Form: Rechteckig | Produktpflegeanweisungen: Spülmaschinenfest | Besonderes Merkmal: Eingebauter Griff, Rutschfeste Füße | Enthaltene Komponenten: 2x Bretter | Artikelgewicht: 450 g | BH27: KÜCHENZUBEHÖR – 2 x Schneidebrett Granitoptik, je 25 x 15 cm, Kunststoff für hygienische Zubereitung von Lebensmitteln DURCHDACHT – Schneidbrett Spülmaschinenfest mit praktischer Eingriffsöffnung für einfaches Handling, ideal zum Aufhängen UNIVERSALTALENT – Schneidebrett Kunststoff zum Schneiden und Servieren, als Unterlage von Käse-, Wurst- oder Schinkenplatten, cool in moderner, gesprenkelter Optik SPITZEN VERARBEITUNG – Frühstücksbrettchen Set hergestellt aus hochwertigem, robustem und BPA-freiem Kunststoff, lebensmittelecht, geschmacks- und geruchsneutral, spülmaschinengeeignet ROBUST –Küchenbrett Kunststoff innovativ in Design und Funktion, zur Erleichterung der Küchenarbeit, strapazierfähige Qualität für garantiert langlebigen Schneidekomfort | BI27: 100 | BJ27: 1315 | BK27: 100 | BL27: 1163 | BM27: 576 | BN27: 691 | BO27: 561 | BP27: 561 | BQ27: 4 | BR27: 561 | BS27: 24 | BT27: 历史为固定父体样本，不能分配给该规格；子体原值多为50/100等阶梯值，不视为精确订单。 | BU27: 82 | BV27: 82
B28: B07FSSYLVM | C28: B0FZRZB8RJ | D28: Farbe: Weiß | Größe: 35L x 24B cm | E28: https://www.amazon.de/dp/B07FSSYLVM | F28: https://images-na.ssl-images-amazon.com/images/I/812PXRvZFAL._AC_US200_.jpg | G28: Chef Aid | H28: Chef Aid Schneidebrett Kunststoff Weiß 35 x 24 cm Rutschfest Spülmaschinenfest mit Griff Küchenbrett Frühstücksbrettchen | I28: Chef Aid 白色塑料切菜板，35×24厘米，防滑、带把手，可洗碗机清洗，可作早餐板 | J28: {"bestSeller": "N", "amazonChoice": "Amazons Tipp", "newRelease": "N", "ebc": "Y", "video": "N"} | K28: Küche, Haushalt & Wohnen:Küche, Kochen & Backen:Küchenhelfer & Kochzubehör:Schneidbretter & -matten:Hackbretter | L28: kitchen | M28: 9309 | N28: Hackbretter（砧板） | O28: 27 | R28: 0.4 x 24.4 x 36.2 cm | S28: 35.3 x 24.4 x 0.3 cm | T28: 300 g | V28: 27 | W28: 202608 | X28: 1 | Y28: 已匹配202608 | Z28: 4.48 | AA28: 4869 | AB28: 4.3 | AC28: 卖家精灵 | AF28: 2018-12-16 | AI28: 1 | AJ28: 599 | AK28: 3372.37 | AL28: 5.55 | AM28: 0.2074 | AN28: 3.47 | AO28: 4.3 | AP28: 4850 | AQ28: 10.85 | AR28: 65 | AU28: 2018-12-16 | AW28: 9 | AX28: 1 | AY28: Amazon | AZ28: DE | BB28: AMZ | BC28: 282 g | BD28: 0.4 x 24.4 x 36.2 cm | BE28: 同子体匹配 | BF28: Chef Aid Schneidebrett Kunststoff Weiß 35 x 24 cm Rutschfest Spülmaschinenfest mit Griff Küchenbrett Frühstücksbrettchen | BG28: Marke: Chef Aid | Farbe: Weiß | Produktabmessungen: 35L x 25B x 0,4D cm | Material: Kunststoff | Empfohlene Anwendungen für Produkt: Fisch, Fleisch, Gemüse, Obst | Form: Rechteckig | Produktpflegeanweisungen: Spülmaschinenfest | Besonderes Merkmal: Spülmaschinenfest | Enthaltene Komponenten: 1 x weißes Poly-Schneidebrett. | Artikelgewicht: 282 g | BH28: LEBENSMITTELECHTER KUNSTSTOFF: Das Schneidebrett aus robustem Kunststoff bietet eine stabile Arbeitsfläche für tägliche Küchenaufgaben und eignet sich für vielseitige Vorbereitungen RUTSCHFESTE OBERFLÄCHE: Die strukturierte Oberfläche unterstützt kontrolliertes Schneiden im Küchenalltag und eignet sich für Brot Obst Gemüse Kräuter und weitere Zutaten MIT INTEGRIERTEM GRIFF: Der praktische Griff erleichtert das Anheben Tragen und Verstauen des Bretts vor und nach der Zubereitung in Küche Haushalt oder Garten SPÜLMASCHINENFEST UND PFLEGELEICHT: Das Kunststoffbrett lässt sich nach dem Gebrauch einfach reinigen und ist für eine schnelle hygienische Pflege im Alltag ausgelegt PRAKTISCHE GRÖSSE 35 X 24 CM: Das Schneidebrett bietet ausreichend Fläche für tägliche Vorbereitungen und passt zugleich gut in Schrank Schublade oder auf die Arbeitsplatte | BI28: 100 | BJ28: 562 | BK28: 50 | BL28: 285 | BM28: 566 | BN28: 720 | BO28: 753 | BP28: 625 | BQ28: 4 | BR28: 566 | BS28: 26 | BT28: 历史为固定父体样本，不能分配给该规格；子体原值多为50/100等阶梯值，不视为精确订单。 | BU28: 79 | BV28: 79
B29: B0G64SWBWL | C29: B0H7RF77ZW | D29: Farbe: Schwarz | Größe: 30L x 23.5B cm | E29: https://www.amazon.de/dp/B0G64SWBWL | F29: https://images-na.ssl-images-amazon.com/images/I/51-czV20yJL._AC_US200_.jpg | G29: BESTCOOK | H29: Schneidebrett Holzfaser Küche, Spülmaschinenfest Composite Cutting Board | 30x23cm, Nicht Giftig, Hohe Dichte, Porenfrei, BPA | I29: 木纤维复合切菜板，30×23厘米，宣称可洗碗机清洗、无毒、高密度、无孔（原文截断） | J29: {"bestSeller": "N", "amazonChoice": "Amazons Tipp", "newRelease": "N", "ebc": "Y", "video": "Y"} | K29: Küche, Haushalt & Wohnen:Küche, Kochen & Backen:Küchenhelfer & Kochzubehör:Schneidbretter & -matten:Hackbretter | L29: kitchen | M29: 7024 | N29: Hackbretter（砧板） | O29: 28 | R29: 30L x 23.5B cm | S29: 29.4 x 23.1 x 0.7 cm | T29: 580 g | V29: 28 | W29: 202608 | X29: 1 | Y29: 已匹配202608 | Z29: 27.99 | AA29: 124 | AB29: 4.2 | AC29: 卖家精灵 | AF29: 2026-01-23 | AI29: 1 | AJ29: 468 | AK29: 12266.28 | AL29: 21.79 | AM29: 0.7086 | AN29: 3.08 | AO29: 4.3 | AP29: 120 | AQ29: 2.35 | AR29: 11 | AU29: 2026-01-23 | AW29: 4 | AX29: 1 | AY29: Bestcook DE | AZ29: CN | BB29: FBA | BC29: 580 g | BD29: 30L x 23.5B cm | BE29: 同子体匹配 | BF29: Schneidebrett Holzfaser Küche, Spülmaschinenfest Composite Cutting Board | BG29: Marke: BESTCOOK | Farbe: Schwarz | Produktabmessungen: 30L x 23,5B x 0,6D cm | Material: Holzfasern | Empfohlene Anwendungen für Produkt: Fleisch Schneiden | Form: Rechteckig | Produktpflegeanweisungen: Spülmaschinenfest | Besonderes Merkmal: Bpa-frei | Enthaltene Komponenten: Schneidebrett | Artikelgewicht: 580 g | BH29: 【Spülmaschinenfestes Schneidebrett】 Mühelose Reinigung! Das spülmaschinenfeste BESTCOOK Schneidebrett ist leicht zu reinigen und zu pflegen und wird Ihr bester Küchenhelfer bei alltäglichen Küchenarbeiten! 【Umweltfreundliche Naturholzfaser】 Das aus Naturholzfaser gefertigte Schneidebrett ist BPA-frei, ungiftig und FSC-zertifiziert. Es sorgt für eine sichere und gesunde Zubereitung Ihrer Mahlzeiten beim täglichen Kochen. 【Messerfreundlich & Hitzebeständig】 Das Holzschneidebrett schützt Ihre Messer vor Beschädigungen und Abstumpfung und hält Temperaturen bis zu 175 °C stand, sodass es auch als Untersetzer oder Wurstbrett verwendet werden kann. 【Hohe Dichte & Haltbarkeit】 Dank der porenfreien Oberfläche ist das BESTCOOK Schneidebrett geruchs- und rückstandsfrei. Es ist äußerst langlebig und verzieht sich beim Kochen nicht. 【Vielseitig und Praktisch】 Das wendbare Design eignet sich für verschiedene Lebensmittel von Fleisch bis Käse und verfügt über eine integrierte Öffnung für bequeme Handhabung und Aufbewahrung. 【Ideales Geschenk】 Das stilvolle und praktische Schneidebrett Holzfaser in großem braunem Design ist perfekt für Familien oder Freunde, die gerne kochen. | BI29: 100 | BJ29: 2564 | BK29: 100 | BL29: 2391 | BM29: 489 | BN29: 482 | BO29: 356 | BP29: 495 | BQ29: 4 | BR29: 356 | BS29: 27 | BT29: 历史为固定父体样本，不能分配给该规格；子体原值多为50/100等阶梯值，不视为精确订单。 | BU29: 66 | BV29: 66
B30: B092JPBC1H | C30: B0HG1RQCVV | D30: Farbe: Heller Bambus | Größe: XXL | E30: https://www.amazon.de/dp/B092JPBC1H | F30: https://images-na.ssl-images-amazon.com/images/I/81gcG3BiqyL._AC_US200_.jpg | G30: Deer &amp; Oak | H30: Deer & Oak Schneidebrett Bambus XXL 44x30x2 cm, vorgeölt | Wasserabweisend · Messerfreundlich · für Fleisch, Gemüse & Brot | I30: Deer & Oak XXL号竹切菜板，44×30×2厘米，预涂油，防水、保护刀刃，用于肉、蔬菜及面包 | J30: {"bestSeller": "N", "amazonChoice": "Amazons Tipp", "newRelease": "N", "ebc": "Y", "video": "Y"} | K30: Küche, Haushalt & Wohnen:Küche, Kochen & Backen:Küchenhelfer & Kochzubehör:Schneidbretter & -matten:Hackbretter | L30: kitchen | M30: 347 | N30: Hackbretter（砧板） | O30: 29 | R30: 45 x 30 x 2 cm | S30: 44.4 x 30.1 x 2.2 cm | T30: 1.68 kg | V30: 29 | W30: 202608 | X30: 1 | Y30: 已匹配202608 | Z30: 16.95 | AA30: 7846 | AB30: 4.6 | AC30: 卖家精灵 | AF30: 2021-09-07 | AI30: 1 | AJ30: 2728 | AK30: 44711.92 | AL30: 14.41 | AM30: 0.5718 | AN30: 4.01 | AO30: 4.6 | AP30: 7755 | AQ30: 0 | AR30: 4779 | AU30: 2021-09-07 | AW30: 3 | AX30: 1 | AY30: Great Ideas | AZ30: GB | BB30: FBA | BC30: 1.68 kg | BD30: 45 x 30 x 2 cm | BE30: 同子体匹配 | BF30: Deer & Oak Schneidebrett Bambus XXL 44x30x2 cm, vorgeölt | BG30: Marke: Deer & Oak | Farbe: Heller Bambus | Produktabmessungen: 44L x 30B x 2D cm | Material: Bambus | Empfohlene Anwendungen für Produkt: Brot, Fisch, Fleisch, Gemüse, Obst | Form: Rechteckig | Produktpflegeanweisungen: Nur Handwäsche | Besonderes Merkmal: Leichtgewichtig, Nicht porös | Enthaltene Komponenten: XXL | Artikelgewicht: 1,68 Kilograms | BH30: SCHNEIDBRETT AUS 100 % NATÜRLICHEM BAMBUS: Das Deer & Oak Holzschneidebrett besteht aus hochwertigem Bambus und verbindet die Langlebigkeit eines Hackblocks mit einem leichten, attraktiven Design für Ihre Küche. Perfekt zum Schneiden von Fleisch, Gemüse und mehr. WASSERFEST & LANGLEBIG: Unsere Schneidebretter aus Holz nehmen kaum Wasser auf und verringern somit das Risiko von Rissbildung oder Verformung im Laufe der Zeit. Obwohl unser Küchenbrett aus Holz robust genug für den täglichen Gebrauch ist, sollten Sie es nicht in die Spülmaschine geben, damit es in Topform bleibt. HYGIENISCH: Unser Holz Schneidebrett ist von Natur aus nicht porös und resistent gegen Messerschnitte. Dadurch wird es zu einer sichereren, hygienischeren Wahl im Vergleich zu Plastikbrettern. Es ist einfach zu reinigen und ideal für die Zubereitung von Essen in jeder Küche. VIRALER HIT BEI DAILY MAIL & AUF TIKTOK: Das Schneidebrett aus Bambus von Deer & Oak wurde für seine Qualität gelobt, ist bekannt aus Daily Mail und ging viral auf TikTok. Entdecken Sie, warum Tausende unserem Brett aufgrund seiner Langlebigkeit, seinem Stil und seiner erstklassigen Leistung vertrauen. UMWELTFREUNDLICHE WAHL: Dieses große Holz-Schneidebrett ist nicht nur stabil und sanft zu Ihren Messern, sondern auch eine umweltfreundlichere Alternative zu traditionellen Holzbrettern. Perfekt für umweltbewusste Köche. | BI30: 100 | BJ30: 1441 | BK30: 100 | BL30: 1694 | BM30: 1213 | BN30: 2458 | BO30: 2541 | BP30: 1863 | BQ30: 4 | BR30: 1213 | BS30: -865 | BT30: 历史为固定父体样本，不能分配给该规格；子体原值多为50/100等阶梯值，不视为精确订单。 | BU30: 78 | BV30: 78
