Workbook

Sheet 说明与图例
B2: VC 利润核算与 NET PPM 自动计算模板
B3: 配套《跨境电商亚马逊 VC 自营供应商渠道专项基础运营及部分推广操作指导》· 天机跨境 · 阳亚运
B5: 一、用途
B6: 本模板参考「欧洲VC毛利测算」的成本结构重建，用于逐 SKU × 站点 × 促销力度核算 VC 供应商的单位毛利、毛利率，并自动计算亚马逊考核用的 NET PPM。填入蓝色列，其余列（含 NET PPM）自动算出。
B8: 二、颜色图例
B9: 蓝色字 = 手动输入
B10: 绿色字 = 跨表引用（自动取自『参数与站点费率』）
B11: 黑色字 = 公式自动计算，请勿手改
B12: 黄色底 = 关键全局假设，可按账号实际调整
B14: 三、NET PPM 公式（团队实测口径，本模板自动套用）
B15: NET PPM（不促销）= (List Price − Cost Price + 佣金扣点 × Cost Price) / List Price
B16: NET PPM（BD/Coupon 促销）= (促销后 List − Cost + 促销 Funding + 佣金扣点 × Cost) / 促销后 List
... B28: 4) 前 19 行为真实示例（除螨仪/布艺机/空净等，可复算原表数字）；示例下方留有空行，可直接套用或整表复制扩展。

Sheet 参数与站点费率
A1: 参数与站点费率
A2: 黄色单元格可按你的账号/站点实际修改；『VC利润测算』的公式全部引用此处。
A3: 全局参数
A4: 采购增值税率（¥ 含税转不含税） | B4: 0.13
A5: 安全边际（保本 Coupon 目标毛利率） | B5: 0.15
A6: 目标 NET PPM（类目均值，达标线） | B6: 0.35
A7: 利润灯 · 红线（毛利率 <） | B7: 0.1
A8: 利润灯 · 绿线（毛利率 >） | B8: 0.25
A10: 站点费率表
A11: 站点 | B11: 币种 | C11: VAT% | D11: 二程整箱费(外币) | E11: 汇率(¥/外币)
A12: UK | B12: GBP | C12: 0.2 | D12: 8.95 | E12: 9
A13: DE | B13: EUR | C13: 0.2 | D13: 7.75 | E13: 8
A14: FR | B14: EUR | C14: 0.2 | D14: 14.25 | E14: 8
A15: IT | B15: EUR | C15: 0.2 | D15: 15.25 | E15: 8
A16: ES | B16: EUR | C16: 0.2 | D16: 19.25 | E16: 8
A17: NL | B17: EUR | C17: 0.2 | D17: 16.75 | E17: 8
A18: PL | B18: PLN | C18: 0.2 | D18: 14.05 | E18: 2
A19: SE | B19: SEK | C19: 0.2 | D19: 18.25 | E19: 0.75
A20: BE | B20: EUR | C20: 0.2 | D20: 14.25 | E20: 8

Sheet VC利润测算
A1: VC 利润核算与 NET PPM 测算表
A2: 蓝色列=手动输入；绿色列=自动取自参数表；黑色列=自动计算。站点须与『参数与站点费率』一致。
A3: 站点 | B3: SKU | C3: ASIN | D3: 产品名称 | E3: 供货价 Cost (不含税·外币) | F3: 建议价 List (含税·外币) | G3: Coupon 促销折扣% | H3: 佣金扣点% Dam+Frt+Coop | I3: 广告/件 外币 | J3: 其他% | K3: 采购成本 ¥含税 | L3: 头程 ¥/件 | M3: 装箱数 | N3: VAT% | O3: 汇率 ¥/外币 | P3: 二程/件 外币 | Q3: List不含税 外币 | R3: 促销Funding 外币 | S3: 成交价含税 外币 | T3: 佣金额 外币 | U3: 采购¥ 不含税 | V3: 头程 外币 | W3: 产品成本 外币 | X3: 其他 外币 | Y3: 单位毛利 外币 | Z3: 毛利率 | AA3: NET PPM | AB3: 利润灯 | AC3: NET PPM 达标 | AD3: 保本Coupon 上限%
A4: UK | B4: R0001UK | C4: B0F1F535PC | D4: 除螨仪 | E4: 48.3 | F4: 69.99 | G4: 0 | H4: 0.178 | I4: 8 | J4: 0.01 | K4: 138.5 | L4: 20 | M4: 4 | N4: =IFERROR(VLOOKUP($A4,参数与站点费率!$A$12:$E$20,3,0),"") -> 0.2 | O4: =IFERROR(VLOOKUP($A4,参数与站点费率!$A$12:$E$20,5,0),"") -> 9 | P4: =IFERROR(VLOOKUP($A4,参数与站点费率!$A$12:$E$20,4,0)/$M4,"") -> 2.2375 | Q4: =IF(OR($E4="",$F4=""),"",$F4/(1+$N4)) -> 58.325 | R4: =IF(OR($E4="",$F4=""),"",$G4*$F4) -> 0 | S4: =IF(OR($E4="",$F4=""),"",$F4-$R4) -> 69.99 | T4: =IF(OR($E4="",$F4=""),"",$H4*$E4) -> 8.5974 | U4: =IF($K4="","",$K4/(1+参数与站点费率!$B$4)) -> 122.56637 | V4: =IF(OR($L4="",$O4=""),"",$L4/$O4) -> 2.2222222 | W4: =IF(OR($U4="",$O4=""),"",($U4+$L4)/$O4) -> 15.840708 | X4: =IF(OR($E4="",$F4=""),"",$E4*$J4) -> 0.483 | Y4: =IF(OR($E4="",$F4=""),"",$E4-$W4-$T4-$I4-$P4-$R4-$X4) -> 13.141392 | Z4: =IF(OR($E4="",$Y4=""),"",$Y4/$E4) -> 0.27207851 | AA4: =IF(OR($Q4="",$R4=""),"",($Q4-$E4+$T4)/($Q4-$R4)) -> 0.31928676 | AB4: =IF($Z4="","",IF($Z4>参数与站点费率!$B$8,"绿",IF($Z4>参数与站点费率!$B$7,"黄","红"))) -> 绿 | AC4: =IF($AA4="","",IF($AA4>=参数与站点费率!$B$6,"达标","偏低")) -> 偏低 | AD4: =IF(OR($Y4="",$F4=""),"",MAX(0,($Y4+$R4-参数与站点费率!$B$5*$E4)/$F4)) -> 0.084246207
A5: UK | B5: R0001UK | C5: B0F1F535PC | D5: 除螨仪（Coupon 5%） | E5: 48.3 | F5: 69.99 | G5: 0.05 | H5: 0.178 | I5: 8 | J5: 0.01 | K5: 138.5 | L5: 20 | M5: 4 | N5: =IFERROR(VLOOKUP($A5,参数与站点费率!$A$12:$E$20,3,0),"") -> 0.2 | O5: =IFERROR(VLOOKUP($A5,参数与站点费率!$A$12:$E$20,5,0),"") -> 9 | P5: =IFERROR(VLOOKUP($A5,参数与站点费率!$A$12:$E$20,4,0)/$M5,"") -> 2.2375 | Q5: =IF(OR($E5="",$F5=""),"",$F5/(1+$N5)) -> 58.325 | R5: =IF(OR($E5="",$F5=""),"",$G5*$F5) -> 3.4995 | S5: =IF(OR($E5="",$F5=""),"",$F5-$R5) -> 66.4905 | T5: =IF(OR($E5="",$F5=""),"",$H5*$E5) -> 8.5974 | U5: =IF($K5="","",$K5/(1+参数与站点费率!$B$4)) -> 122.56637 | V5: =IF(OR($L5="",$O5=""),"",$L5/$O5) -> 2.2222222 | W5: =IF(OR($U5="",$O5=""),"",($U5+$L5)/$O5) -> 15.840708 | X5: =IF(OR($E5="",$F5=""),"",$E5*$J5) -> 0.483 | Y5: =IF(OR($E5="",$F5=""),"",$E5-$W5-$T5-$I5-$P5-$R5-$X5) -> 9.641892 | Z5: =IF(OR($E5="",$Y5=""),"",$Y5/$E5) -> 0.19962509 | AA5: =IF(OR($Q5="",$R5=""),"",($Q5-$E5+$T5)/($Q5-$R5)) -> 0.33966676 | AB5: =IF($Z5="","",IF($Z5>参数与站点费率!$B$8,"绿",IF($Z5>参数与站点费率!$B$7,"黄","红"))) -> 黄 | AC5: =IF($AA5="","",IF($AA5>=参数与站点费率!$B$6,"达标","偏低")) -> 偏低 | AD5: =IF(OR($Y5="",$F5=""),"",MAX(0,($Y5+$R5-参数与站点费率!$B$5*$E5)/$F5)) -> 0.084246207
A6: UK | B6: R0001UK | C6: B0F1F535PC | D6: 除螨仪（Coupon 10%） | E6: 48.3 | F6: 69.99 | G6: 0.1 | H6: 0.178 | I6: 8 | J6: 0.01 | K6: 138.5 | L6: 20 | M6: 4 | N6: =IFERROR(VLOOKUP($A6,参数与站点费率!$A$12:$E$20,3,0),"") -> 0.2 | O6: =IFERROR(VLOOKUP($A6,参数与站点费率!$A$12:$E$20,5,0),"") -> 9 | P6: =IFERROR(VLOOKUP($A6,参数与站点费率!$A$12:$E$20,4,0)/$M6,"") -> 2.2375 | Q6: =IF(OR($E6="",$F6=""),"",$F6/(1+$N6)) -> 58.325 | R6: =IF(OR($E6="",$F6=""),"",$G6*$F6) -> 6.999 | S6: =IF(OR($E6="",$F6=""),"",$F6-$R6) -> 62.991 | T6: =IF(OR($E6="",$F6=""),"",$H6*$E6) -> 8.5974 | U6: =IF($K6="","",$K6/(1+参数与站点费率!$B$4)) -> 122.56637 | V6: =IF(OR($L6="",$O6=""),"",$L6/$O6) -> 2.2222222 | W6: =IF(OR($U6="",$O6=""),"",($U6+$L6)/$O6) -> 15.840708 | X6: =IF(OR($E6="",$F6=""),"",$E6*$J6) -> 0.483 | Y6: =IF(OR($E6="",$F6=""),"",$E6-$W6-$T6-$I6-$P6-$R6-$X6) -> 6.142392 | Z6: =IF(OR($E6="",$Y6=""),"",$Y6/$E6) -> 0.12717168 | AA6: =IF(OR($Q6="",$R6=""),"",($Q6-$E6+$T6)/($Q6-$R6)) -> 0.36282586 | AB6: =IF($Z6="","",IF($Z6>参数与站点费率!$B$8,"绿",IF($Z6>参数与站点费率!$B$7,"黄","红"))) -> 黄 | AC6: =IF($AA6="","",IF($AA6>=参数与站点费率!$B$6,"达标","偏低")) -> 达标 | AD6: =IF(OR($Y6="",$F6=""),"",MAX(0,($Y6+$R6-参数与站点费率!$B$5*$E6)/$F6)) -> 0.084246207
A7: UK | B7: R0001UK | C7: B0F1F535PC | D7: 除螨仪（Coupon 15%） | E7: 48.3 | F7: 69.99 | G7: 0.15 | H7: 0.178 | I7: 8 | J7: 0.01 | K7: 138.5 | L7: 20 | M7: 4 | N7: =IFERROR(VLOOKUP($A7,参数与站点费率!$A$12:$E$20,3,0),"") -> 0.2 | O7: =IFERROR(VLOOKUP($A7,参数与站点费率!$A$12:$E$20,5,0),"") -> 9 | P7: =IFERROR(VLOOKUP($A7,参数与站点费率!$A$12:$E$20,4,0)/$M7,"") -> 2.2375 | Q7: =IF(OR($E7="",$F7=""),"",$F7/(1+$N7)) -> 58.325 | R7: =IF(OR($E7="",$F7=""),"",$G7*$F7) -> 10.4985 | S7: =IF(OR($E7="",$F7=""),"",$F7-$R7) -> 59.4915 | T7: =IF(OR($E7="",$F7=""),"",$H7*$E7) -> 8.5974 | U7: =IF($K7="","",$K7/(1+参数与站点费率!$B$4)) -> 122.56637 | V7: =IF(OR($L7="",$O7=""),"",$L7/$O7) -> 2.2222222 | W7: =IF(OR($U7="",$O7=""),"",($U7+$L7)/$O7) -> 15.840708 | X7: =IF(OR($E7="",$F7=""),"",$E7*$J7) -> 0.483 | Y7: =IF(OR($E7="",$F7=""),"",$E7-$W7-$T7-$I7-$P7-$R7-$X7) -> 2.642892 | Z7: =IF(OR($E7="",$Y7=""),"",$Y7/$E7) -> 0.054718262 | AA7: =IF(OR($Q7="",$R7=""),"",($Q7-$E7+$T7)/($Q7-$R7)) -> 0.38937409 | AB7: =IF($Z7="","",IF($Z7>参数与站点费率!$B$8,"绿",IF($Z7>参数与站点费率!$B$7,"黄","红"))) -> 红 | AC7: =IF($AA7="","",IF($AA7>=参数与站点费率!$B$6,"达标","偏低")) -> 达标 | AD7: =IF(OR($Y7="",$F7=""),"",MAX(0,($Y7+$R7-参数与站点费率!$B$5*$E7)/$F7)) -> 0.084246207
A8: DE | B8: R0001EU | C8: B0F1F7J8V3 | D8: 除螨仪 | E8: 55.85 | F8: 79.99 | G8: 0 | H8: 0.188 | I8: 8 | J8: 0.01 | K8: 138.5 | L8: 20 | M8: 4 | N8: =IFERROR(VLOOKUP($A8,参数与站点费率!$A$12:$E$20,3,0),"") -> 0.2 | O8: =IFERROR(VLOOKUP($A8,参数与站点费率!$A$12:$E$20,5,0),"") -> 8 | P8: =IFERROR(VLOOKUP($A8,参数与站点费率!$A$12:$E$20,4,0)/$M8,"") -> 1.9375 | Q8: =IF(OR($E8="",$F8=""),"",$F8/(1+$N8)) -> 66.658333 | R8: =IF(OR($E8="",$F8=""),"",$G8*$F8) -> 0 | S8: =IF(OR($E8="",$F8=""),"",$F8-$R8) -> 79.99 | T8: =IF(OR($E8="",$F8=""),"",$H8*$E8) -> 10.4998 | U8: =IF($K8="","",$K8/(1+参数与站点费率!$B$4)) -> 122.56637 | V8: =IF(OR($L8="",$O8=""),"",$L8/$O8) -> 2.5 | W8: =IF(OR($U8="",$O8=""),"",($U8+$L8)/$O8) -> 17.820796 | X8: =IF(OR($E8="",$F8=""),"",$E8*$J8) -> 0.5585 | Y8: =IF(OR($E8="",$F8=""),"",$E8-$W8-$T8-$I8-$P8-$R8-$X8) -> 17.033404 | Z8: =IF(OR($E8="",$Y8=""),"",$Y8/$E8) -> 0.30498484 | AA8: =IF(OR($Q8="",$R8=""),"",($Q8-$E8+$T8)/($Q8-$R8)) -> 0.31966196 | AB8: =IF($Z8="","",IF($Z8>参数与站点费率!$B$8,"绿",IF($Z8>参数与站点费率!$B$7,"黄","红"))) -> 绿 | AC8: =IF($AA8="","",IF($AA8>=参数与站点费率!$B$6,"达标","偏低")) -> 偏低 | AD8: =IF(OR($Y8="",$F8=""),"",MAX(0,($Y8+$R8-参数与站点费率!$B$5*$E8)/$F8)) -> 0.10821232
A9: FR | B9: R0001EU | C9: B0F1F7J8V3 | D9: 除螨仪 | E9: 55.35 | F9: 79.99 | G9: 0 | H9: 0.188 | I9: 8 | J9: 0.01 | K9: 138.5 | L9: 20 | M9: 4 | N9: =IFERROR(VLOOKUP($A9,参数与站点费率!$A$12:$E$20,3,0),"") -> 0.2 | O9: =IFERROR(VLOOKUP($A9,参数与站点费率!$A$12:$E$20,5,0),"") -> 8 | P9: =IFERROR(VLOOKUP($A9,参数与站点费率!$A$12:$E$20,4,0)/$M9,"") -> 3.5625 | Q9: =IF(OR($E9="",$F9=""),"",$F9/(1+$N9)) -> 66.658333 | R9: =IF(OR($E9="",$F9=""),"",$G9*$F9) -> 0 | S9: =IF(OR($E9="",$F9=""),"",$F9-$R9) -> 79.99 | T9: =IF(OR($E9="",$F9=""),"",$H9*$E9) -> 10.4058 | U9: =IF($K9="","",$K9/(1+参数与站点费率!$B$4)) -> 122.56637 | V9: =IF(OR($L9="",$O9=""),"",$L9/$O9) -> 2.5 | W9: =IF(OR($U9="",$O9=""),"",($U9+$L9)/$O9) -> 17.820796 | X9: =IF(OR($E9="",$F9=""),"",$E9*$J9) -> 0.5535 | Y9: =IF(OR($E9="",$F9=""),"",$E9-$W9-$T9-$I9-$P9-$R9-$X9) -> 15.007404 | Z9: =IF(OR($E9="",$Y9=""),"",$Y9/$E9) -> 0.27113647 | AA9: =IF(OR($Q9="",$R9=""),"",($Q9-$E9+$T9)/($Q9-$R9)) -> 0.32575272 | AB9: =IF($Z9="","",IF($Z9>参数与站点费率!$B$8,"绿",IF($Z9>参数与站点费率!$B$7,"黄","红"))) -> 绿 | AC9: =IF($AA9="","",IF($AA9>=参数与站点费率!$B$6,"达标","偏低")) -> 偏低 | AD9: =IF(OR($Y9="",$F9=""),"",MAX(0,($Y9+$R9-参数与站点费率!$B$5*$E9)/$F9)) -> 0.083821772
A10: IT | B10: R0001EU | C10: B0F1F7J8V3 | D10: 除螨仪 | E10: 55.35 | F10: 79.99 | G10: 0 | H10: 0.188 | I10: 8 | J10: 0.01 | K10: 138.5 | L10: 20 | M10: 4 | N10: =IFERROR(VLOOKUP($A10,参数与站点费率!$A$12:$E$20,3,0),"") -> 0.2 | O10: =IFERROR(VLOOKUP($A10,参数与站点费率!$A$12:$E$20,5,0),"") -> 8 | P10: =IFERROR(VLOOKUP($A10,参数与站点费率!$A$12:$E$20,4,0)/$M10,"") -> 3.8125 | Q10: =IF(OR($E10="",$F10=""),"",$F10/(1+$N10)) -> 66.658333 | R10: =IF(OR($E10="",$F10=""),"",$G10*$F10) -> 0 | S10: =IF(OR($E10="",$F10=""),"",$F10-$R10) -> 79.99 | T10: =IF(OR($E10="",$F10=""),"",$H10*$E10) -> 10.4058 | U10: =IF($K10="","",$K10/(1+参数与站点费率!$B$4)) -> 122.56637 | V10: =IF(OR($L10="",$O10=""),"",$L10/$O10) -> 2.5 | W10: =IF(OR($U10="",$O10=""),"",($U10+$L10)/$O10) -> 17.820796 | X10: =IF(OR($E10="",$F10=""),"",$E10*$J10) -> 0.5535 | Y10: =IF(OR($E10="",$F10=""),"",$E10-$W10-$T10-$I10-$P10-$R10-$X10) -> 14.757404 | Z10: =IF(OR($E10="",$Y10=""),"",$Y10/$E10) -> 0.26661976 | AA10: =IF(OR($Q10="",$R10=""),"",($Q10-$E10+$T10)/($Q10-$R10)) -> 0.32575272 | AB10: =IF($Z10="","",IF($Z10>参数与站点费率!$B$8,"绿",IF($Z10>参数与站点费率!$B$7,"黄","红"))) -> 绿 | AC10: =IF($AA10="","",IF($AA10>=参数与站点费率!$B$6,"达标","偏低")) -> 偏低 | AD10: =IF(OR($Y10="",$F10=""),"",MAX(0,($Y10+$R10-参数与站点费率!$B$5*$E10)/$F10)) -> 0.080696381
A11: ES | B11: R0001EU | C11: B0F1F7J8V3 | D11: 除螨仪 | E11: 55.35 | F11: 79.99 | G11: 0 | H11: 0.188 | I11: 8 | J11: 0.01 | K11: 138.5 | L11: 20 | M11: 4 | N11: =IFERROR(VLOOKUP($A11,参数与站点费率!$A$12:$E$20,3,0),"") -> 0.2 | O11: =IFERROR(VLOOKUP($A11,参数与站点费率!$A$12:$E$20,5,0),"") -> 8 | P11: =IFERROR(VLOOKUP($A11,参数与站点费率!$A$12:$E$20,4,0)/$M11,"") -> 4.8125 | Q11: =IF(OR($E11="",$F11=""),"",$F11/(1+$N11)) -> 66.658333 | R11: =IF(OR($E11="",$F11=""),"",$G11*$F11) -> 0 | S11: =IF(OR($E11="",$F11=""),"",$F11-$R11) -> 79.99 | T11: =IF(OR($E11="",$F11=""),"",$H11*$E11) -> 10.4058 | U11: =IF($K11="","",$K11/(1+参数与站点费率!$B$4)) -> 122.56637 | V11: =IF(OR($L11="",$O11=""),"",$L11/$O11) -> 2.5 | W11: =IF(OR($U11="",$O11=""),"",($U11+$L11)/$O11) -> 17.820796 | X11: =IF(OR($E11="",$F11=""),"",$E11*$J11) -> 0.5535 | Y11: =IF(OR($E11="",$F11=""),"",$E11-$W11-$T11-$I11-$P11-$R11-$X11) -> 13.757404 | Z11: =IF(OR($E11="",$Y11=""),"",$Y11/$E11) -> 0.24855291 | AA11: =IF(OR($Q11="",$R11=""),"",($Q11-$E11+$T11)/($Q11-$R11)) -> 0.32575272 | AB11: =IF($Z11="","",IF($Z11>参数与站点费率!$B$8,"绿",IF($Z11>参数与站点费率!$B$7,"黄","红"))) -> 黄 | AC11: =IF($AA11="","",IF($AA11>=参数与站点费率!$B$6,"达标","偏低")) -> 偏低 | AD11: =IF(OR($Y11="",$F11=""),"",MAX(0,($Y11+$R11-参数与站点费率!$B$5*$E11)/$F11)) -> 0.068194819
A12: UK | B12: R0002UK | C12: B0GDDKS6ZJ | D12: 布艺清洗机 | E12: 76 | F12: 109.99 | G12: 0 | H12: 0.178 | I12: 12 | J12: 0.01 | K12: 249 | L12: 25 | M12: 3 | N12: =IFERROR(VLOOKUP($A12,参数与站点费率!$A$12:$E$20,3,0),"") -> 0.2 | O12: =IFERROR(VLOOKUP($A12,参数与站点费率!$A$12:$E$20,5,0),"") -> 9 | P12: =IFERROR(VLOOKUP($A12,参数与站点费率!$A$12:$E$20,4,0)/$M12,"") -> 2.9833333 | Q12: =IF(OR($E12="",$F12=""),"",$F12/(1+$N12)) -> 91.658333 | R12: =IF(OR($E12="",$F12=""),"",$G12*$F12) -> 0 | S12: =IF(OR($E12="",$F12=""),"",$F12-$R12) -> 109.99 | T12: =IF(OR($E12="",$F12=""),"",$H12*$E12) -> 13.528 | U12: =IF($K12="","",$K12/(1+参数与站点费率!$B$4)) -> 220.35398 | V12: =IF(OR($L12="",$O12=""),"",$L12/$O12) -> 2.7777778 | W12: =IF(OR($U12="",$O12=""),"",($U12+$L12)/$O12) -> 27.261554 | X12: =IF(OR($E12="",$F12=""),"",$E12*$J12) -> 0.76 | Y12: =IF(OR($E12="",$F12=""),"",$E12-$W12-$T12-$I12-$P12-$R12-$X12) -> 19.467113 | Z12: =IF(OR($E12="",$Y12=""),"",$Y12/$E12) -> 0.25614622 | AA12: =IF(OR($Q12="",$R12=""),"",($Q12-$E12+$T12)/($Q12-$R12)) -> 0.31842531 | AB12: =IF($Z12="","",IF($Z12>参数与站点费率!$B$8,"绿",IF($Z12>参数与站点费率!$B$7,"黄","红"))) -> 绿 | AC12: =IF($AA12="","",IF($AA12>=参数与站点费率!$B$6,"达标","偏低")) -> 偏低 | AD12: =IF(OR($Y12="",$F12=""),"",MAX(0,($Y12+$R12-参数与站点费率!$B$5*$E12)/$F12)) -> 0.073344059
A13: DE | B13: R0002EU | C13: B0GDCZ7BWK | D13: 布艺清洗机 | E13: 86 | F13: 124.99 | G13: 0 | H13: 0.188 | I13: 12 | J13: 0.01 | K13: 249 | L13: 30 | M13: 3 | N13: =IFERROR(VLOOKUP($A13,参数与站点费率!$A$12:$E$20,3,0),"") -> 0.2 | O13: =IFERROR(VLOOKUP($A13,参数与站点费率!$A$12:$E$20,5,0),"") -> 8 | P13: =IFERROR(VLOOKUP($A13,参数与站点费率!$A$12:$E$20,4,0)/$M13,"") -> 2.5833333 | Q13: =IF(OR($E13="",$F13=""),"",$F13/(1+$N13)) -> 104.15833 | R13: =IF(OR($E13="",$F13=""),"",$G13*$F13) -> 0 | S13: =IF(OR($E13="",$F13=""),"",$F13-$R13) -> 124.99 | T13: =IF(OR($E13="",$F13=""),"",$H13*$E13) -> 16.168 | U13: =IF($K13="","",$K13/(1+参数与站点费率!$B$4)) -> 220.35398 | V13: =IF(OR($L13="",$O13=""),"",$L13/$O13) -> 3.75 | W13: =IF(OR($U13="",$O13=""),"",($U13+$L13)/$O13) -> 31.294248 | X13: =IF(OR($E13="",$F13=""),"",$E13*$J13) -> 0.86 | Y13: =IF(OR($E13="",$F13=""),"",$E13-$W13-$T13-$I13-$P13-$R13-$X13) -> 23.094419 | Z13: =IF(OR($E13="",$Y13=""),"",$Y13/$E13) -> 0.26853975 | AA13: =IF(OR($Q13="",$R13=""),"",($Q13-$E13+$T13)/($Q13-$R13)) -> 0.32955916 | AB13: =IF($Z13="","",IF($Z13>参数与站点费率!$B$8,"绿",IF($Z13>参数与站点费率!$B$7,"黄","红"))) -> 绿 | AC13: =IF($AA13="","",IF($AA13>=参数与站点费率!$B$6,"达标","偏低")) -> 偏低 | AD13: =IF(OR($Y13="",$F13=""),"",MAX(0,($Y13+$R13-参数与站点费率!$B$5*$E13)/$F13)) -> 0.081561876
A14: FR | B14: R0002EU | C14: B0GDCZ7BWK | D14: 布艺清洗机 | E14: 90 | F14: 129.99 | G14: 0 | H14: 0.188 | I14: 12 | J14: 0.01 | K14: 249 | L14: 30 | M14: 3 | N14: =IFERROR(VLOOKUP($A14,参数与站点费率!$A$12:$E$20,3,0),"") -> 0.2 | O14: =IFERROR(VLOOKUP($A14,参数与站点费率!$A$12:$E$20,5,0),"") -> 8 | P14: =IFERROR(VLOOKUP($A14,参数与站点费率!$A$12:$E$20,4,0)/$M14,"") -> 4.75 | Q14: =IF(OR($E14="",$F14=""),"",$F14/(1+$N14)) -> 108.325 | R14: =IF(OR($E14="",$F14=""),"",$G14*$F14) -> 0 | S14: =IF(OR($E14="",$F14=""),"",$F14-$R14) -> 129.99 | T14: =IF(OR($E14="",$F14=""),"",$H14*$E14) -> 16.92 | U14: =IF($K14="","",$K14/(1+参数与站点费率!$B$4)) -> 220.35398 | V14: =IF(OR($L14="",$O14=""),"",$L14/$O14) -> 3.75 | W14: =IF(OR($U14="",$O14=""),"",($U14+$L14)/$O14) -> 31.294248 | X14: =IF(OR($E14="",$F14=""),"",$E14*$J14) -> 0.9 | Y14: =IF(OR($E14="",$F14=""),"",$E14-$W14-$T14-$I14-$P14-$R14-$X14) -> 24.135752 | Z14: =IF(OR($E14="",$Y14=""),"",$Y14/$E14) -> 0.26817502 | AA14: =IF(OR($Q14="",$R14=""),"",($Q14-$E14+$T14)/($Q14-$R14)) -> 0.32536349 | AB14: =IF($Z14="","",IF($Z14>参数与站点费率!$B$8,"绿",IF($Z14>参数与站点费率!$B$7,"黄","红"))) -> 绿 | AC14: =IF($AA14="","",IF($AA14>=参数与站点费率!$B$6,"达标","偏低")) -> 偏低 | AD14: =IF(OR($Y14="",$F14=""),"",MAX(0,($Y14+$R14-参数与站点费率!$B$5*$E14)/$F14)) -> 0.081819772
A15: IT | B15: R0002EU | C15: B0GDCZ7BWK | D15: 布艺清洗机 | E15: 90 | F15: 129.99 | G15: 0 | H15: 0.188 | I15: 12 | J15: 0.01 | K15: 249 | L15: 30 | M15: 3 | N15: =IFERROR(VLOOKUP($A15,参数与站点费率!$A$12:$E$20,3,0),"") -> 0.2 | O15: =IFERROR(VLOOKUP($A15,参数与站点费率!$A$12:$E$20,5,0),"") -> 8 | P15: =IFERROR(VLOOKUP($A15,参数与站点费率!$A$12:$E$20,4,0)/$M15,"") -> 5.0833333 | Q15: =IF(OR($E15="",$F15=""),"",$F15/(1+$N15)) -> 108.325 | R15: =IF(OR($E15="",$F15=""),"",$G15*$F15) -> 0 | S15: =IF(OR($E15="",$F15=""),"",$F15-$R15) -> 129.99 | T15: =IF(OR($E15="",$F15=""),"",$H15*$E15) -> 16.92 | U15: =IF($K15="","",$K15/(1+参数与站点费率!$B$4)) -> 220.35398 | V15: =IF(OR($L15="",$O15=""),"",$L15/$O15) -> 3.75 | W15: =IF(OR($U15="",$O15=""),"",($U15+$L15)/$O15) -> 31.294248 | X15: =IF(OR($E15="",$F15=""),"",$E15*$J15) -> 0.9 | Y15: =IF(OR($E15="",$F15=""),"",$E15-$W15-$T15-$I15-$P15-$R15-$X15) -> 23.802419 | Z15: =IF(OR($E15="",$Y15=""),"",$Y15/$E15) -> 0.26447132 | AA15: =IF(OR($Q15="",$R15=""),"",($Q15-$E15+$T15)/($Q15-$R15)) -> 0.32536349 | AB15: =IF($Z15="","",IF($Z15>参数与站点费率!$B$8,"绿",IF($Z15>参数与站点费率!$B$7,"黄","红"))) -> 绿 | AC15: =IF($AA15="","",IF($AA15>=参数与站点费率!$B$6,"达标","偏低")) -> 偏低 | AD15: =IF(OR($Y15="",$F15=""),"",MAX(0,($Y15+$R15-参数与站点费率!$B$5*$E15)/$F15)) -> 0.079255473
... A22: UK | B22: R0001EU | C22: B0FFGKNZNN | D22: 气泵 | E22: 51.5 | F22: 74.99 | G22: 0 | H22: 0.178 | I22: 8 | J22: 0.01 | K22: 208 | L22: 18 | M22: 12 | N22: =IFERROR(VLOOKUP($A22,参数与站点费率!$A$12:$E$20,3,0),"") -> 0.2 | O22: =IFERROR(VLOOKUP($A22,参数与站点费率!$A$12:$E$20,5,0),"") -> 9 | P22: =IFERROR(VLOOKUP($A22,参数与站点费率!$A$12:$E$20,4,0)/$M22,"") -> 0.74583333 | Q22: =IF(OR($E22="",$F22=""),"",$F22/(1+$N22)) -> 62.491667 | R22: =IF(OR($E22="",$F22=""),"",$G22*$F22) -> 0 | S22: =IF(OR($E22="",$F22=""),"",$F22-$R22) -> 74.99 | T22: =IF(OR($E22="",$F22=""),"",$H22*$E22) -> 9.167 | U22: =IF($K22="","",$K22/(1+参数与站点费率!$B$4)) -> 184.0708 | V22: =IF(OR($L22="",$O22=""),"",$L22/$O22) -> 2 | W22: =IF(OR($U22="",$O22=""),"",($U22+$L22)/$O22) -> 22.452311 | X22: =IF(OR($E22="",$F22=""),"",$E22*$J22) -> 0.515 | Y22: =IF(OR($E22="",$F22=""),"",$E22-$W22-$T22-$I22-$P22-$R22-$X22) -> 10.619856 | Z22: =IF(OR($E22="",$Y22=""),"",$Y22/$E22) -> 0.2062108 | AA22: =IF(OR($Q22="",$R22=""),"",($Q22-$E22+$T22)/($Q22-$R22)) -> 0.32258168 | AB22: =IF($Z22="","",IF($Z22>参数与站点费率!$B$8,"绿",IF($Z22>参数与站点费率!$B$7,"黄","红"))) -> 黄 | AC22: =IF($AA22="","",IF($AA22>=参数与站点费率!$B$6,"达标","偏低")) -> 偏低 | AD22: =IF(OR($Y22="",$F22=""),"",MAX(0,($Y22+$R22-参数与站点费率!$B$5*$E22)/$F22)) -> 0.038603226
N23: =IFERROR(VLOOKUP($A23,参数与站点费率!$A$12:$E$20,3,0),"") | O23: =IFERROR(VLOOKUP($A23,参数与站点费率!$A$12:$E$20,5,0),"") | P23: =IFERROR(VLOOKUP($A23,参数与站点费率!$A$12:$E$20,4,0)/$M23,"") | Q23: =IF(OR($E23="",$F23=""),"",$F23/(1+$N23)) | R23: =IF(OR($E23="",$F23=""),"",$G23*$F23) | S23: =IF(OR($E23="",$F23=""),"",$F23-$R23) | T23: =IF(OR($E23="",$F23=""),"",$H23*$E23) | U23: =IF($K23="","",$K23/(1+参数与站点费率!$B$4)) | V23: =IF(OR($L23="",$O23=""),"",$L23/$O23) | W23: =IF(OR($U23="",$O23=""),"",($U23+$L23)/$O23) | X23: =IF(OR($E23="",$F23=""),"",$E23*$J23) | Y23: =IF(OR($E23="",$F23=""),"",$E23-$W23-$T23-$I23-$P23-$R23-$X23) | Z23: =IF(OR($E23="",$Y23=""),"",$Y23/$E23) | AA23: =IF(OR($Q23="",$R23=""),"",($Q23-$E23+$T23)/($Q23-$R23)) | AB23: =IF($Z23="","",IF($Z23>参数与站点费率!$B$8,"绿",IF($Z23>参数与站点费率!$B$7,"黄","红"))) | AC23: =IF($AA23="","",IF($AA23>=参数与站点费率!$B$6,"达标","偏低")) | AD23: =IF(OR($Y23="",$F23=""),"",MAX(0,($Y23+$R23-参数与站点费率!$B$5*$E23)/$F23))
N24: =IFERROR(VLOOKUP($A24,参数与站点费率!$A$12:$E$20,3,0),"") | O24: =IFERROR(VLOOKUP($A24,参数与站点费率!$A$12:$E$20,5,0),"") | P24: =IFERROR(VLOOKUP($A24,参数与站点费率!$A$12:$E$20,4,0)/$M24,"") | Q24: =IF(OR($E24="",$F24=""),"",$F24/(1+$N24)) | R24: =IF(OR($E24="",$F24=""),"",$G24*$F24) | S24: =IF(OR($E24="",$F24=""),"",$F24-$R24) | T24: =IF(OR($E24="",$F24=""),"",$H24*$E24) | U24: =IF($K24="","",$K24/(1+参数与站点费率!$B$4)) | V24: =IF(OR($L24="",$O24=""),"",$L24/$O24) | W24: =IF(OR($U24="",$O24=""),"",($U24+$L24)/$O24) | X24: =IF(OR($E24="",$F24=""),"",$E24*$J24) | Y24: =IF(OR($E24="",$F24=""),"",$E24-$W24-$T24-$I24-$P24-$R24-$X24) | Z24: =IF(OR($E24="",$Y24=""),"",$Y24/$E24) | AA24: =IF(OR($Q24="",$R24=""),"",($Q24-$E24+$T24)/($Q24-$R24)) | AB24: =IF($Z24="","",IF($Z24>参数与站点费率!$B$8,"绿",IF($Z24>参数与站点费率!$B$7,"黄","红"))) | AC24: =IF($AA24="","",IF($AA24>=参数与站点费率!$B$6,"达标","偏低")) | AD24: =IF(OR($Y24="",$F24=""),"",MAX(0,($Y24+$R24-参数与站点费率!$B$5*$E24)/$F24))
N25: =IFERROR(VLOOKUP($A25,参数与站点费率!$A$12:$E$20,3,0),"") | O25: =IFERROR(VLOOKUP($A25,参数与站点费率!$A$12:$E$20,5,0),"") | P25: =IFERROR(VLOOKUP($A25,参数与站点费率!$A$12:$E$20,4,0)/$M25,"") | Q25: =IF(OR($E25="",$F25=""),"",$F25/(1+$N25)) | R25: =IF(OR($E25="",$F25=""),"",$G25*$F25) | S25: =IF(OR($E25="",$F25=""),"",$F25-$R25) | T25: =IF(OR($E25="",$F25=""),"",$H25*$E25) | U25: =IF($K25="","",$K25/(1+参数与站点费率!$B$4)) | V25: =IF(OR($L25="",$O25=""),"",$L25/$O25) | W25: =IF(OR($U25="",$O25=""),"",($U25+$L25)/$O25) | X25: =IF(OR($E25="",$F25=""),"",$E25*$J25) | Y25: =IF(OR($E25="",$F25=""),"",$E25-$W25-$T25-$I25-$P25-$R25-$X25) | Z25: =IF(OR($E25="",$Y25=""),"",$Y25/$E25) | AA25: =IF(OR($Q25="",$R25=""),"",($Q25-$E25+$T25)/($Q25-$R25)) | AB25: =IF($Z25="","",IF($Z25>参数与站点费率!$B$8,"绿",IF($Z25>参数与站点费率!$B$7,"黄","红"))) | AC25: =IF($AA25="","",IF($AA25>=参数与站点费率!$B$6,"达标","偏低")) | AD25: =IF(OR($Y25="",$F25=""),"",MAX(0,($Y25+$R25-参数与站点费率!$B$5*$E25)/$F25))
N26: =IFERROR(VLOOKUP($A26,参数与站点费率!$A$12:$E$20,3,0),"") | O26: =IFERROR(VLOOKUP($A26,参数与站点费率!$A$12:$E$20,5,0),"") | P26: =IFERROR(VLOOKUP($A26,参数与站点费率!$A$12:$E$20,4,0)/$M26,"") | Q26: =IF(OR($E26="",$F26=""),"",$F26/(1+$N26)) | R26: =IF(OR($E26="",$F26=""),"",$G26*$F26) | S26: =IF(OR($E26="",$F26=""),"",$F26-$R26) | T26: =IF(OR($E26="",$F26=""),"",$H26*$E26) | U26: =IF($K26="","",$K26/(1+参数与站点费率!$B$4)) | V26: =IF(OR($L26="",$O26=""),"",$L26/$O26) | W26: =IF(OR($U26="",$O26=""),"",($U26+$L26)/$O26) | X26: =IF(OR($E26="",$F26=""),"",$E26*$J26) | Y26: =IF(OR($E26="",$F26=""),"",$E26-$W26-$T26-$I26-$P26-$R26-$X26) | Z26: =IF(OR($E26="",$Y26=""),"",$Y26/$E26) | AA26: =IF(OR($Q26="",$R26=""),"",($Q26-$E26+$T26)/($Q26-$R26)) | AB26: =IF($Z26="","",IF($Z26>参数与站点费率!$B$8,"绿",IF($Z26>参数与站点费率!$B$7,"黄","红"))) | AC26: =IF($AA26="","",IF($AA26>=参数与站点费率!$B$6,"达标","偏低")) | AD26: =IF(OR($Y26="",$F26=""),"",MAX(0,($Y26+$R26-参数与站点费率!$B$5*$E26)/$F26))
N27: =IFERROR(VLOOKUP($A27,参数与站点费率!$A$12:$E$20,3,0),"") | O27: =IFERROR(VLOOKUP($A27,参数与站点费率!$A$12:$E$20,5,0),"") | P27: =IFERROR(VLOOKUP($A27,参数与站点费率!$A$12:$E$20,4,0)/$M27,"") | Q27: =IF(OR($E27="",$F27=""),"",$F27/(1+$N27)) | R27: =IF(OR($E27="",$F27=""),"",$G27*$F27) | S27: =IF(OR($E27="",$F27=""),"",$F27-$R27) | T27: =IF(OR($E27="",$F27=""),"",$H27*$E27) | U27: =IF($K27="","",$K27/(1+参数与站点费率!$B$4)) | V27: =IF(OR($L27="",$O27=""),"",$L27/$O27) | W27: =IF(OR($U27="",$O27=""),"",($U27+$L27)/$O27) | X27: =IF(OR($E27="",$F27=""),"",$E27*$J27) | Y27: =IF(OR($E27="",$F27=""),"",$E27-$W27-$T27-$I27-$P27-$R27-$X27) | Z27: =IF(OR($E27="",$Y27=""),"",$Y27/$E27) | AA27: =IF(OR($Q27="",$R27=""),"",($Q27-$E27+$T27)/($Q27-$R27)) | AB27: =IF($Z27="","",IF($Z27>参数与站点费率!$B$8,"绿",IF($Z27>参数与站点费率!$B$7,"黄","红"))) | AC27: =IF($AA27="","",IF($AA27>=参数与站点费率!$B$6,"达标","偏低")) | AD27: =IF(OR($Y27="",$F27=""),"",MAX(0,($Y27+$R27-参数与站点费率!$B$5*$E27)/$F27))
N28: =IFERROR(VLOOKUP($A28,参数与站点费率!$A$12:$E$20,3,0),"") | O28: =IFERROR(VLOOKUP($A28,参数与站点费率!$A$12:$E$20,5,0),"") | P28: =IFERROR(VLOOKUP($A28,参数与站点费率!$A$12:$E$20,4,0)/$M28,"") | Q28: =IF(OR($E28="",$F28=""),"",$F28/(1+$N28)) | R28: =IF(OR($E28="",$F28=""),"",$G28*$F28) | S28: =IF(OR($E28="",$F28=""),"",$F28-$R28) | T28: =IF(OR($E28="",$F28=""),"",$H28*$E28) | U28: =IF($K28="","",$K28/(1+参数与站点费率!$B$4)) | V28: =IF(OR($L28="",$O28=""),"",$L28/$O28) | W28: =IF(OR($U28="",$O28=""),"",($U28+$L28)/$O28) | X28: =IF(OR($E28="",$F28=""),"",$E28*$J28) | Y28: =IF(OR($E28="",$F28=""),"",$E28-$W28-$T28-$I28-$P28-$R28-$X28) | Z28: =IF(OR($E28="",$Y28=""),"",$Y28/$E28) | AA28: =IF(OR($Q28="",$R28=""),"",($Q28-$E28+$T28)/($Q28-$R28)) | AB28: =IF($Z28="","",IF($Z28>参数与站点费率!$B$8,"绿",IF($Z28>参数与站点费率!$B$7,"黄","红"))) | AC28: =IF($AA28="","",IF($AA28>=参数与站点费率!$B$6,"达标","偏低")) | AD28: =IF(OR($Y28="",$F28=""),"",MAX(0,($Y28+$R28-参数与站点费率!$B$5*$E28)/$F28))
N29: =IFERROR(VLOOKUP($A29,参数与站点费率!$A$12:$E$20,3,0),"") | O29: =IFERROR(VLOOKUP($A29,参数与站点费率!$A$12:$E$20,5,0),"") | P29: =IFERROR(VLOOKUP($A29,参数与站点费率!$A$12:$E$20,4,0)/$M29,"") | Q29: =IF(OR($E29="",$F29=""),"",$F29/(1+$N29)) | R29: =IF(OR($E29="",$F29=""),"",$G29*$F29) | S29: =IF(OR($E29="",$F29=""),"",$F29-$R29) | T29: =IF(OR($E29="",$F29=""),"",$H29*$E29) | U29: =IF($K29="","",$K29/(1+参数与站点费率!$B$4)) | V29: =IF(OR($L29="",$O29=""),"",$L29/$O29) | W29: =IF(OR($U29="",$O29=""),"",($U29+$L29)/$O29) | X29: =IF(OR($E29="",$F29=""),"",$E29*$J29) | Y29: =IF(OR($E29="",$F29=""),"",$E29-$W29-$T29-$I29-$P29-$R29-$X29) | Z29: =IF(OR($E29="",$Y29=""),"",$Y29/$E29) | AA29: =IF(OR($Q29="",$R29=""),"",($Q29-$E29+$T29)/($Q29-$R29)) | AB29: =IF($Z29="","",IF($Z29>参数与站点费率!$B$8,"绿",IF($Z29>参数与站点费率!$B$7,"黄","红"))) | AC29: =IF($AA29="","",IF($AA29>=参数与站点费率!$B$6,"达标","偏低")) | AD29: =IF(OR($Y29="",$F29=""),"",MAX(0,($Y29+$R29-参数与站点费率!$B$5*$E29)/$F29))
N30: =IFERROR(VLOOKUP($A30,参数与站点费率!$A$12:$E$20,3,0),"") | O30: =IFERROR(VLOOKUP($A30,参数与站点费率!$A$12:$E$20,5,0),"") | P30: =IFERROR(VLOOKUP($A30,参数与站点费率!$A$12:$E$20,4,0)/$M30,"") | Q30: =IF(OR($E30="",$F30=""),"",$F30/(1+$N30)) | R30: =IF(OR($E30="",$F30=""),"",$G30*$F30) | S30: =IF(OR($E30="",$F30=""),"",$F30-$R30) | T30: =IF(OR($E30="",$F30=""),"",$H30*$E30) | U30: =IF($K30="","",$K30/(1+参数与站点费率!$B$4)) | V30: =IF(OR($L30="",$O30=""),"",$L30/$O30) | W30: =IF(OR($U30="",$O30=""),"",($U30+$L30)/$O30) | X30: =IF(OR($E30="",$F30=""),"",$E30*$J30) | Y30: =IF(OR($E30="",$F30=""),"",$E30-$W30-$T30-$I30-$P30-$R30-$X30) | Z30: =IF(OR($E30="",$Y30=""),"",$Y30/$E30) | AA30: =IF(OR($Q30="",$R30=""),"",($Q30-$E30+$T30)/($Q30-$R30)) | AB30: =IF($Z30="","",IF($Z30>参数与站点费率!$B$8,"绿",IF($Z30>参数与站点费率!$B$7,"黄","红"))) | AC30: =IF($AA30="","",IF($AA30>=参数与站点费率!$B$6,"达标","偏低")) | AD30: =IF(OR($Y30="",$F30=""),"",MAX(0,($Y30+$R30-参数与站点费率!$B$5*$E30)/$F30))

Sheet 汇总看板
A1: 汇总看板（按站点）
A2: 随『VC利润测算』自动刷新；统计示例+空行整个数据区。
A4: 站点 | B4: 产品数 | C4: 平均毛利率 | D4: 平均NET PPM | E4: 🔴红 | F4: 🟡黄 | G4: 🟢绿
A5: UK | B5: =COUNTIF(VC利润测算!$A$4:$A$30,$A5) -> 7 | C5: =IFERROR(AVERAGEIF(VC利润测算!$A$4:$A$30,$A5,VC利润测算!$Z$4:$Z$30),"") -> 0.17986607 | D5: =IFERROR(AVERAGEIF(VC利润测算!$A$4:$A$30,$A5,VC利润测算!$AA$4:$AA$30),"") -> 0.33735473 | E5: =COUNTIFS(VC利润测算!$A$4:$A$30,$A5,VC利润测算!$AB$4:$AB$30,"红") -> 1 | F5: =COUNTIFS(VC利润测算!$A$4:$A$30,$A5,VC利润测算!$AB$4:$AB$30,"黄") -> 4 | G5: =COUNTIFS(VC利润测算!$A$4:$A$30,$A5,VC利润测算!$AB$4:$AB$30,"绿") -> 2
A6: DE | B6: =COUNTIF(VC利润测算!$A$4:$A$30,$A6) -> 3 | C6: =IFERROR(AVERAGEIF(VC利润测算!$A$4:$A$30,$A6,VC利润测算!$Z$4:$Z$30),"") -> 0.24209643 | D6: =IFERROR(AVERAGEIF(VC利润测算!$A$4:$A$30,$A6,VC利润测算!$AA$4:$AA$30),"") -> 0.32232352 | E6: =COUNTIFS(VC利润测算!$A$4:$A$30,$A6,VC利润测算!$AB$4:$AB$30,"红") -> 0 | F6: =COUNTIFS(VC利润测算!$A$4:$A$30,$A6,VC利润测算!$AB$4:$AB$30,"黄") -> 1 | G6: =COUNTIFS(VC利润测算!$A$4:$A$30,$A6,VC利润测算!$AB$4:$AB$30,"绿") -> 2
A7: FR | B7: =COUNTIF(VC利润测算!$A$4:$A$30,$A7) -> 3 | C7: =IFERROR(AVERAGEIF(VC利润测算!$A$4:$A$30,$A7,VC利润测算!$Z$4:$Z$30),"") -> 0.22209417 | D7: =IFERROR(AVERAGEIF(VC利润测算!$A$4:$A$30,$A7,VC利润测算!$AA$4:$AA$30),"") -> 0.32295522 | E7: =COUNTIFS(VC利润测算!$A$4:$A$30,$A7,VC利润测算!$AB$4:$AB$30,"红") -> 0 | F7: =COUNTIFS(VC利润测算!$A$4:$A$30,$A7,VC利润测算!$AB$4:$AB$30,"黄") -> 1 | G7: =COUNTIFS(VC利润测算!$A$4:$A$30,$A7,VC利润测算!$AB$4:$AB$30,"绿") -> 2
A8: IT | B8: =COUNTIF(VC利润测算!$A$4:$A$30,$A8) -> 3 | C8: =IFERROR(AVERAGEIF(VC利润测算!$A$4:$A$30,$A8,VC利润测算!$Z$4:$Z$30),"") -> 0.21803128 | D8: =IFERROR(AVERAGEIF(VC利润测算!$A$4:$A$30,$A8,VC利润测算!$AA$4:$AA$30),"") -> 0.32295522 | E8: =COUNTIFS(VC利润测算!$A$4:$A$30,$A8,VC利润测算!$AB$4:$AB$30,"红") -> 0 | F8: =COUNTIFS(VC利润测算!$A$4:$A$30,$A8,VC利润测算!$AB$4:$AB$30,"黄") -> 1 | G8: =COUNTIFS(VC利润测算!$A$4:$A$30,$A8,VC利润测算!$AB$4:$AB$30,"绿") -> 2
A9: ES | B9: =COUNTIF(VC利润测算!$A$4:$A$30,$A9) -> 3 | C9: =IFERROR(AVERAGEIF(VC利润测算!$A$4:$A$30,$A9,VC利润测算!$Z$4:$Z$30),"") -> 0.20177972 | D9: =IFERROR(AVERAGEIF(VC利润测算!$A$4:$A$30,$A9,VC利润测算!$AA$4:$AA$30),"") -> 0.32295522 | E9: =COUNTIFS(VC利润测算!$A$4:$A$30,$A9,VC利润测算!$AB$4:$AB$30,"红") -> 0 | F9: =COUNTIFS(VC利润测算!$A$4:$A$30,$A9,VC利润测算!$AB$4:$AB$30,"黄") -> 3 | G9: =COUNTIFS(VC利润测算!$A$4:$A$30,$A9,VC利润测算!$AB$4:$AB$30,"绿") -> 0
A10: NL | B10: =COUNTIF(VC利润测算!$A$4:$A$30,$A10) -> 0 | C10: =IFERROR(AVERAGEIF(VC利润测算!$A$4:$A$30,$A10,VC利润测算!$Z$4:$Z$30),"") | D10: =IFERROR(AVERAGEIF(VC利润测算!$A$4:$A$30,$A10,VC利润测算!$AA$4:$AA$30),"") | E10: =COUNTIFS(VC利润测算!$A$4:$A$30,$A10,VC利润测算!$AB$4:$AB$30,"红") -> 0 | F10: =COUNTIFS(VC利润测算!$A$4:$A$30,$A10,VC利润测算!$AB$4:$AB$30,"黄") -> 0 | G10: =COUNTIFS(VC利润测算!$A$4:$A$30,$A10,VC利润测算!$AB$4:$AB$30,"绿") -> 0
A11: PL | B11: =COUNTIF(VC利润测算!$A$4:$A$30,$A11) -> 0 | C11: =IFERROR(AVERAGEIF(VC利润测算!$A$4:$A$30,$A11,VC利润测算!$Z$4:$Z$30),"") | D11: =IFERROR(AVERAGEIF(VC利润测算!$A$4:$A$30,$A11,VC利润测算!$AA$4:$AA$30),"") | E11: =COUNTIFS(VC利润测算!$A$4:$A$30,$A11,VC利润测算!$AB$4:$AB$30,"红") -> 0 | F11: =COUNTIFS(VC利润测算!$A$4:$A$30,$A11,VC利润测算!$AB$4:$AB$30,"黄") -> 0 | G11: =COUNTIFS(VC利润测算!$A$4:$A$30,$A11,VC利润测算!$AB$4:$AB$30,"绿") -> 0
A12: SE | B12: =COUNTIF(VC利润测算!$A$4:$A$30,$A12) -> 0 | C12: =IFERROR(AVERAGEIF(VC利润测算!$A$4:$A$30,$A12,VC利润测算!$Z$4:$Z$30),"") | D12: =IFERROR(AVERAGEIF(VC利润测算!$A$4:$A$30,$A12,VC利润测算!$AA$4:$AA$30),"") | E12: =COUNTIFS(VC利润测算!$A$4:$A$30,$A12,VC利润测算!$AB$4:$AB$30,"红") -> 0 | F12: =COUNTIFS(VC利润测算!$A$4:$A$30,$A12,VC利润测算!$AB$4:$AB$30,"黄") -> 0 | G12: =COUNTIFS(VC利润测算!$A$4:$A$30,$A12,VC利润测算!$AB$4:$AB$30,"绿") -> 0
A13: BE | B13: =COUNTIF(VC利润测算!$A$4:$A$30,$A13) -> 0 | C13: =IFERROR(AVERAGEIF(VC利润测算!$A$4:$A$30,$A13,VC利润测算!$Z$4:$Z$30),"") | D13: =IFERROR(AVERAGEIF(VC利润测算!$A$4:$A$30,$A13,VC利润测算!$AA$4:$AA$30),"") | E13: =COUNTIFS(VC利润测算!$A$4:$A$30,$A13,VC利润测算!$AB$4:$AB$30,"红") -> 0 | F13: =COUNTIFS(VC利润测算!$A$4:$A$30,$A13,VC利润测算!$AB$4:$AB$30,"黄") -> 0 | G13: =COUNTIFS(VC利润测算!$A$4:$A$30,$A13,VC利润测算!$AB$4:$AB$30,"绿") -> 0
A14: 合计/均值 | B14: =SUM(B5:B13) -> 19 | C14: =IFERROR(AVERAGE(VC利润测算!$Z$4:$Z$30),"") -> 0.20584565 | D14: =IFERROR(AVERAGE(VC利润测算!$AA$4:$AA$30),"") -> 0.32816056 | E14: =SUM(E5:E13) -> 1 | F14: =SUM(F5:F13) -> 10 | G14: =SUM(G5:G13) -> 8
