Workbook

Sheet 项目进度
A1: 项目进度计划表
A2: 一、项目基本情况
A3: 项目名称 | B3: 英国 扫地机 | G3: 项目编号 | M3: XXXX-111
A4: 负责人 | B4: 西悉尼下1 | G4: 执行人 | M4: 西悉尼下3
A5: 知情人 | B5: 西悉尼下2 | G5: 顾问 | M5: 西悉尼下4
A6: 二、关键节点图
A8: 三、项目进度表
B9: 周 | C9: 1 | I9: 休 | J9: 2 | O9: 休 | P9: 休 | Q9: 3 | V9: 年假 | AC9: 4 | AK9: 休 | AL9: 5 | AQ9: 休 | AR9: 休 | AS9: 6 | AY9: 休 | AZ9: 7 | BE9: 休 | BF9: 休 | BG9: 8 | BM9: 休 | BN9: 9 | BS9: 休 | BT9: 休 | BU9: 10
A10: 版块 | B10: 关键动作 | C10: 44571 | D10: 44572 | E10: 44573 | F10: 44574 | G10: 44575 | H10: 44576 | I10: 44577 | J10: 44578 | K10: 44579 | L10: 44580 | M10: 44581 | N10: 44582 | O10: 44583 | P10: 44584 | Q10: 44585 | R10: 44586 | S10: 44587 | T10: 44588 | U10: 44589 | V10: 44590 | W10: 44591 | X10: 44592 | Y10: 44593 | Z10: 44594 | AA10: 44595 | AB10: 44596 | AC10: 44597 | AD10: 44598 | AE10: 44599 | AF10: 44600 | AG10: 44601 | AH10: 44602 | AI10: 44603 | AJ10: 44604 | AK10: 44605 | AL10: 44606 | AM10: 44607 | AN10: 44608 | AO10: 44609 | AP10: 44610 | AQ10: 44611 | AR10: 44612 | AS10: 44613 | AT10: 44614 | AU10: 44615 | AV10: 44616 | AW10: 44617 | AX10: 44618 | AY10: 44619 | AZ10: 44620 | BA10: 44621 | BB10: 44622 | BC10: 44623 | BD10: 44624 | BE10: 44625 | BF10: 44626 | BG10: 44627 | BH10: 44628 | BI10: 44629 | BJ10: 44630 | BK10: 44631 | BL10: 44632 | BM10: 44633 | BN10: 44634 | BO10: 44635 | BP10: 44636 | BQ10: 44637 | BR10: 44638 | BS10: 44639 | BT10: 44640 | BU10: 44641 | BV10: 44642
A11: PMC XXX | B11: 立项开模12.10
B12: T0验证12.30
B13: 修模
B14: T1验证1.8
B15: 修模
B16: 签样量产
B17: 评议营销计划
B18: 首批原材料下单
B19: 原材料生产
B20: 提醒创建X00
B21: 完成BOM录入系统
B22: 提醒走Listing流程
B23: 交货 | AP23: 1 | AQ23: 1 | AR23: 1 | AS23: 1 | AT23: 1 | AU23: 1
B24: 发货 | AR24: 2 | AT24: 2 | AV24: 2
B25: 到货 | AZ25: US-1K | BB25: US-2K | BG25: DE-1K | BK25: DE-2K
B26: 上架 | BJ26: US-1K | BK26: DE-1K | BL26: US-2K | BO26: DE-1K
B27: 审核首单配送费用
A28: 市场调研 | B28: 了解墙头充电历史容量、同类型产品市场表现等
B29: 确定产品USP、基础卖点
A30: 营销计划（销量预估） 李子云 | B30: 初稿（60天计划）
B31: 内部会议、修改
B32: 第一次会议-AAA
B33: 营销计划修改
B34: 营销计划定稿
A35: 图片：主副图、A+ XXX | B35: 图片需求调研
B36: 运营头脑风暴确定图片需求
B37: 图片需求同频给设计
B38: 设计出草图方案
B39: 运营、设计一起进行草图评议
B40: 草图修改后最终确认
B41: 设计下渲染图
B42: 渲染图给运营、设计看质感和角度（群沟通）
B43: 第一版稿设计输出(主图一张）给运营确定
B44: 渲染输出成品给设计
B45: 设计精修排版（一套）
B46: 输出一套给到运营：增加文案+调整
B47: 主副图最终交稿
... B50: A+最终交稿
A51: 文案：标题、五点、图片文案、长描、ST | B51: 关键词、流量词调研
B52: 卖点调研（结合国内外）
B53: 卖点最终确认会议
B54: 关键词、市调报告、主要卖点给客服
B55: 标题、五点第一版-给客服
B56: 标题、五点文案第一次会议
B57: 标题、五点修改及二次会议
B58: 标题、五点给本土人修改
B59: 标题、五点三次评议
B60: 标题、五点上级评议及定稿
B61: 产品信息、长描、ST第一版
B62: 产品信息、长描、ST评议及修改
B63: 产品信息、长描、ST定稿
A64: QA&RV XXX | B64: QA&RV市场调研
B65: 确认QA、RV拍摄主题
B66: 拍摄QA、RV
B67: QA及RV图片&视频草图评议
B68: QA及RV图片&视频补拍及草图定稿
B69: 输出QA剪辑需求及视频文案
B70: QA提交视频、文案给设计剪辑
B71: QA二次评议及修改
B72: QA视频定稿
B73: QA&RV文案撰写
B74: QA&RV文案评议
B75: RV文案修改及定稿
A76: 推广 XXX | B76: 测评需求对接推广负责人员
B77: 红人需求对接推广负责人员
B78: 测评及红人计划表
B79: 测评及红人资源预约
B80: 测评预约情况同频（例会前）
B81: 红人寄送样品及视频制作
B82: 红人视频上传
B83: 红人视频前台显示
B84: 买家秀及RV文案评议
B85: 买家秀交付（根据S22发布进行时间顺移）
B86: 开始测评下单
B87: 直评前台显评（2） | BN87: 2
B88: 测评前台显评（2） | BR88: 2
B89: 测评显评节奏 | BS89: 2 | BT89: 2 | BU89: 2 | BV89: 2
A90: 广告框架 XXX | B90: 广告架构
B91: 广告架构初稿评议
B92: 广告架构修改
B93: 广告框架二次评议
B94: 广告架构修改及定稿
A95: 站外营销 XXX | B95: 确定产品USP(并需要产品实物）
B96: 寻找对标视频
B97: 视频评议（确定方向+核对合作表格）
B98: 寻找红人
B99: 寄送样品
B100: 确定收货
B101: 视频跟进
B102: 合作视频评议会
B103: 视频问题修正时间
...

Sheet 设计进度安排
A1: 设计出图项目周期管理表
A2: 项目决策权：XXX 负责人：XX 参与人员 XX | H2: 1月 | AF2: 2月
A3: 项目 | C3: 任务内容 | D3: 负责人 | E3: 开始日期 | F3: 完成日期 | G3: 利益干系人 | H3: 准备期 | K3: 方案确定期 | Z3: 出图中期 | AW3: 调整期后期
H4: 8 | I4: 9 | J4: 10 | K4: 11 | L4: 12 | M4: 13 | N4: 14 | O4: 15 | P4: 16 | Q4: 17 | R4: 18 | S4: 19 | T4: 20 | U4: 21 | V4: 22 | W4: 23 | X4: 24 | Y4: 25 | Z4: 26 | AA4: 27 | AB4: 28 | AC4: 29 | AD4: 30 | AE4: 31 | AF4: 1 | AG4: 2 | AH4: 3 | AI4: 4 | AJ4: 5 | AK4: 6 | AL4: 7 | AM4: 8 | AN4: 9 | AO4: 10 | AP4: 11 | AQ4: 12 | AR4: 13 | AS4: 14 | AT4: 15 | AU4: 16 | AV4: 17 | AW4: 18 | AX4: 19 | AY4: 20 | AZ4: 21 | BA4: 22 | BB4: 23 | BC4: 24 | BD4: 25 | BE4: 26 | BF4: 27 | BG4: 28 | BH4: 29 | BI4: 30 | BJ4: 31 | BK4: 32
A5: XXX-111 | B5: 主图 | C5: 3D模型确定，拿样品 | D5: xxx | E5: 202/1/8 | F5: 46366 | G5: xxx
C6: 项目启动会议 | D6: xxx | E6: 202/1/10 | F6: 46032 | G6: xxx
C7: 运营输出需求PPT对接（USP/功能卖点） | D7: xxx | E7: 46034 | F7: 46040 | G7: xxx
C8: 设计出草图方案-第一版 | D8: xxx | E8: 46041 | F8: 46048 | G8: xxx
C9: 设计运营一起讨论确定草图方案-第二版 | D9: xxx | E9: 46048 | F9: 46050 | G9: xxx
C10: 设计下渲染图 | D10: xxx | E10: 46048 | F10: 46050 | G10: xxx
C11: 渲染出主图给设计，确定质感和角度（群沟通） | D11: xxx | E11: 46049 | F11: 46050 | G11: xxx
C12: 第一版稿设计输出(主图一张）给运营确定 | D12: xxx | E12: 46050 | F12: 46051 | G12: xxx
C13: 渲染输出成品给设计 | D13: xxx | E13: 46048 | F13: 46073 | G13: xxx
C14: 设计精修排版（一套） | D14: xxx | E14: 46051 | F14: 46075 | G14: xxx
C15: 输出一套给到运营-增加文案+调整 | D15: xxx | E15: 46075 | F15: 46076 | G15: 全员参与
C16: 最终交稿（主副） | D16: xxx | E16: 46076 | F16: 46077 | G16: xxx
B17: A+ | C17: 设计精修排版（一套） | D17: xxx | E17: 46077 | F17: 46080 | G17: xxx
C18: 输出一套给到运营-增加文案+调整 | D18: xxx | E18: 46079 | F18: 46080 | G18: xxx
C19: A+终稿 | D19: xxx | E19: 46081 | F19: 46081 | G19: xxx
C20: 开会确定 | D20: xxx | E20: 46081 | F20: 46081 | G20: xxx | H20: 蓝色为工作日，黄色为休息日，红色为评议日 全员参与：全员参与评议，由负责人组织，全员讨论，最终有项目决策人决策
C21: MEIG+SHEJI
C22: MEIG+SHEJI

Sheet 测评
A1: 链接 | D1: 周 | E1: 8 | K1: 休 | L1: 9 | Q1: 休 | R1: 休 | S1: 10 | Y1: 休
A2: 美国 | B2: 板块 | D2: 关键动作 | E2: 44627 | F2: 44628 | G2: 44629 | H2: 44630 | I2: 44631 | J2: 44632 | K2: 44633 | L2: 44634 | M2: 44635 | N2: 44636 | O2: 44637 | P2: 44638 | Q2: 44639 | R2: 44640 | S2: 44641 | T2: 44642 | U2: 44643 | V2: 44644 | W2: 44645 | X2: 44646 | Y2: 44647 | Z2: 44648 | AA2: 44649 | AB2: 44650
B3: 测评下单 | C3: 1 | D3: 优质评论：文字+7图 | G3: 1
C4: 1 | D4: TOP：文字+5图+1视频 | H4: 1
C5: 2 | D5: 2个优质评论（文字+7图*2） | I5: 2
C6: 2 | D6: 1个优质评论（文字+5图+1视频）+1个优质评论（文字+7图） | N6: 2
C7: 2 | D7: 1个优质评论（文字+5图）+1个优质评论（文字+7图） | O7: 2
C8: 2 | D8: 1个优质评论（文字+5图）+1个优质评论（文字+7图） | P8: 2
C9: 20 | D9: 普评（20个）推广14个，运营6个 | G9: 1 | H9: 1 | J9: 2 | K9: 2 | L9: 2 | M9: 2 | Q9: 2 | R9: 2 | S9: 2（运营） | T9: 2（运营） | U9: 2（运营）
B11: 显评 | C11: 1 | D11: 优质评论：文字+7图 | N11: 1
C12: 1 | D12: TOP：文字+5图+1视频 | O12: 1
C13: 2 | D13: 2个优质评论（文字+7图*2） | P13: 2
C14: 2 | D14: 1个优质评论（文字+5图+1视频）+1个优质评论（文字+7图） | U14: 2
C15: 2 | D15: 1个优质评论（文字+5图）+1个优质评论（文字+7图） | V15: 2
C16: 2 | D16: 1个优质评论（文字+5图）+1个优质评论（文字+7图） | W16: 2
C17: 20 | D17: 普评（14个） | N17: 1 | O17: 1 | Q17: 2 | R17: 2 | S17: 2 | T17: 2 | X17: 2 | Y17: 2 | Z17: 2 | AA17: 2 | AB17: 2
B21: 备注 | D21: 1. 推广：10（优质）+15（普评） 2. Profile要求 -10个优质：9（100w）+1TOP（10万以内） -Profile不可有XXX的产品 -15个普评：Profile不可超过2个XXX的产品 -所有测评人的Profile不可空白 3. 不可一测二 4. 普评说明 -运营需要确定15个普评的主题 -有10个普评的文案运营写，字数在300字以内，可以跟顾客提一下附上3-5张图片，但不强求。 -另外5个普评的文案只给顾客提供主题，让顾客自由发挥，图片同样是3-5图，但不强求。
B29: 说明

Sheet 站外营销
A1: XXX产品系列项目时间节点图(市场营销）
A12: 市场合作计划表
A13: 平台
A14: 产品USP | B14: XXX
A15: 真机 | B15: 机模4个
A16: 红人时长 | B16: 3-5分钟
A17: 合作方式 | B17: 健身、户外运动、开箱
A18: 视频类型 | B18: 每个人介绍2个型号S22/S22U
A19: 红人合作数量 | B19: 2个
A20: 红人级别 | B20: YT——xxxx粉+
A21: 红人预算 | B21: 200$
A22: 红人佣金 | B22: $1/单
A23: 链接放置位置： | B23: 视频下方
A24: 链接放置时间（以美国东部时间为准） | B24: 3月18上链接
A25: 链接落地页 | B25: 产品页(流量风险)
... A27: 折扣使用范围 | B27: 指定产品
A28: 目标单量
A30: 周 | AR30: 发货 | BI30: 上架
A31: 模块 | B31: 项目 | C31: 44572 | D31: 44573 | E31: 44574 | F31: 44575 | G31: 44576 | H31: 44577 | I31: 44578 | J31: 44579 | K31: 44580 | L31: 44581 | M31: 44582 | N31: 44583 | O31: 44584 | P31: 44585 | Q31: 44586 | R31: 44587 | S31: 44588 | T31: 44589 | U31: 44590 | V31: 44591 | W31: 44592 | X31: 44593 | Y31: 44594 | Z31: 44595 | AA31: 44596 | AB31: 44597 | AC31: 44598 | AD31: 44599 | AE31: 44600 | AF31: 44601 | AG31: 44602 | AH31: 44603 | AI31: 44604 | AJ31: 44605 | AK31: 44606 | AL31: 44607 | AM31: 44608 | AN31: 44609 | AO31: 44610 | AP31: 44611 | AQ31: 44612 | AR31: 44613 | AS31: 44614 | AT31: 44615 | AU31: 44616 | AV31: 44617 | AW31: 44618 | AX31: 44619 | AY31: 44620 | AZ31: 44621 | BA31: 44622 | BB31: 44623 | BC31: 44624 | BD31: 44625 | BE31: 44626 | BF31: 44627 | BG31: 44628 | BH31: 44629 | BI31: 44630 | BJ31: 44631 | BK31: 44632 | BL31: 44633 | BM31: 44634 | BN31: 44635 | BO31: 44636 | BP31: 44637 | BQ31: 44638 | BR31: 44639 | BS31: 44640 | BT31: 44641 | BU31: 44642 | BV31: 44643 | BW31: 44644 | BX31: 44645 | BY31: 44646 | BZ31: 44647
A32: 红人营销 | B32: 确定产品USP(并需要产品实物） | U32: 年假
B33: 寻找对标视频
B34: 视频评议（确定方向+核对合作表格）
B35: 寻找红人+寄送样品
B36: 确定收货
B37: 视频跟进
B38: 合作视频评议会
B39: 视频问题修正时间
B40: 视频发布（折扣有效期3.18-3.27)
B41: 监测数据至活动结束
A42: 社媒 | B42: ⭐站外营销图片和文案准备PPT
B43: 下单
B44: 所有社媒图片的定稿
B45: 社媒发布3月18-3月27

Sheet 1.1核心竞争对手调研
A1: 变体形式
A2: ASIN
A3: 品牌
A4: 图片
A5: 卖点提炼
A6: 销售价格
A7: 尺寸信息
A8: FBA配送费
A9: reviews星级
A10: reviews数量
A11: 类目
A12: review内容分析
... A14: 历史销售数据
A15: 产品总结 | B15: 1.尺寸对比-分析配送费，优化价格 2.对比五点，找出共同描述的点，找出自己产品的差异点 3.查看星级 -是否需要控评 4.review数量-预估上评数量 5.reviews布局- 图片review内容（室内or室外），文字review内容（尺寸，材质，颜色，款式，质量），是否中评卡位 6.对比售价，定位自家价格 7.对比排名情况，设定目标 8.关键词分析

Sheet 1.2 产品定价
A1: 产品采购信息
A2: 产品型号 | B2: 每箱毛重 | C2: 每箱体积 | D2: 每箱数量 | E2: 头程运费 | F2: 产品采购成本
A3: XXXX-111 | B3: 5 | C3: 1 | D3: 20 | E3: =C3*1500/D3 -> 75 | F3: 20
A4: XXXX-222 | B4: 5 | C4: 1 | D4: 20 | E4: =C4*1500/D4 -> 75 | F4: 20
A6: 产品信息 | E6: 亚马逊销售核算公式
A7: 货号/品名 | B7: 图片 | C7: 英文品名 | D7: 产品型号 Model No. | E7: 销售价格 | F7: 类目佣金 | G7: FBA配送费 | H7: 头程运费 | I7: 产品成本 | J7: 毛利润 | K7: 毛利润率
C8: XXXXX | D8: XXXX-111 | E8: 25 | F8: =E8*0.15 -> 3.75 | G8: 4.75 | H8: =E3/6.5 -> 11.538462 | I8: =F3/6.5 -> 3.0769231 | J8: =E8-F8-G8-H8-I8 -> 1.8846154 | K8: =J8/E8 -> 0.075384615
C9: XXXXX | D9: XXXX-222 | E9: 25 | F9: =E9*0.15 -> 3.75 | G9: 4.75 | H9: =E4/6.5 -> 11.538462 | I9: =F4/6.5 -> 3.0769231 | J9: =E9-F9-G9-H9-I9 -> 1.8846154 | K9: =J9/E9 -> 0.075384615

Sheet 2.1 销售和库存规划
A1: 图片 | B1: 产品型号 | H1: 退货 | I1: 0.05 | J1: 25 | K1: =J1*('1.2 产品定价'!I8+'1.2 产品定价'!H8+'1.2 产品定价'!G8*0.15) -> 383.19712
B2: XXXX-111 | H2: 广告 | I2: 30 | J2: 30天 | K2: 900
B3: 1000 | H3: 仓储成本 | I3: 30天 | J3: 500个 | K3: =(1000/'1.2 产品定价'!D4*'1.2 产品定价'!C4)*35*0.83 -> 1452.5
A4: 日期 | B4: 每日销量目标 | C4: 目标剩余库存 | D4: 实际每日销量 | E4: 实际剩余库存 | F4: 实际售价 | G4: 单个利润 | H4: 利润 | I4: 实际广告成本 | J4: 每日销量完成率 | K4: 实际利润
A5: 2026.8.23 | B5: 1 | C5: =B3-B5 -> 999 | D5: 2 | E5: =B3-D5 -> 998 | F5: 13.99 | G5: 3.528 | H5: =G5*D5 -> 7.056 | I5: 20.95 | J5: =D5/B5 -> 2 | K5: =H5-I5 -> -13.894
A6: 2026.8.24 | B6: 1 | C6: =C5-B6 -> 998 | D6: 1 | E6: =E5-D6 -> 997 | F6: 13.99 | G6: 3.528 | H6: =G6*D6 -> 3.528 | I6: 18.32 | J6: =D6/B6 -> 1 | K6: =H6-I6 -> -14.792
A7: 2026.8.25 | B7: 1 | C7: =C6-B7 -> 997 | D7: 0 | E7: =E6-D7 -> 997 | F7: 13.99 | G7: 3.528 | H7: =G7*D7 -> 0 | I7: 4.72 | J7: =D7/B7 -> 0 | K7: =H7-I7 -> -4.72
A8: 2026.8.26 | B8: 1 | C8: =C7-B8 -> 996 | D8: 1 | E8: =E7-D8 -> 996 | F8: 13.99 | G8: 3.528 | H8: =G8*D8 -> 3.528 | I8: 20.26 | J8: =D8/B8 -> 1 | K8: =H8-I8 -> -16.732
A9: 2026.8.27 | B9: 1 | C9: =C8-B9 -> 995 | D9: 3 | E9: =E8-D9 -> 993 | F9: 13.99 | G9: 3.528 | H9: =G9*D9 -> 10.584 | I9: 26 | J9: =D9/B9 -> 3 | K9: =H9-I9 -> -15.416
A10: 2026.8.28 | B10: 1 | C10: =C9-B10 -> 994 | D10: 3 | E10: =E9-D10 -> 990 | F10: 13.99 | G10: 3.528 | H10: =G10*D10 -> 10.584 | I10: 23.48 | J10: =D10/B10 -> 3 | K10: =H10-I10 -> -12.896
A11: 2026.8.29 | B11: 1 | C11: =C10-B11 -> 993 | D11: 9 | E11: =E10-D11 -> 981 | F11: 13.99 | G11: 3.528 | H11: =G11*D11 -> 31.752 | I11: 20.61 | J11: =D11/B11 -> 9 | K11: =H11-I11 -> 11.142
A12: 2026.8.30 | B12: 1 | C12: =C11-B12 -> 992 | D12: 5 | E12: =E11-D12 -> 976 | F12: 13.99 | G12: 3.528 | H12: =G12*D12 -> 17.64 | I12: 19.58 | J12: =D12/B12 -> 5 | K12: =H12-I12 -> -1.94
A13: 2026.8.31 | B13: 2 | C13: =C12-B13 -> 990 | D13: 9 | E13: =E12-D13 -> 967 | F13: 13.99 | G13: 3.528 | H13: =G13*D13 -> 31.752 | I13: 20.38 | J13: =D13/B13 -> 4.5 | K13: =H13-I13 -> 11.372
A14: 2026.9.1 | B14: 5 | C14: =C13-B14 -> 985 | D14: 4 | E14: =E13-D14 -> 963 | F14: 13.99 | G14: 3.528 | H14: =G14*D14 -> 14.112 | I14: 20.3 | J14: =D14/B14 -> 0.8 | K14: =H14-I14 -> -6.188
A15: 2026.9.2 | B15: 5 | C15: =C14-B15 -> 980 | D15: 9 | E15: =E14-D15 -> 954 | F15: 13.99 | G15: 3.528 | H15: =G15*D15 -> 31.752 | I15: 20.22 | J15: =D15/B15 -> 1.8 | K15: =H15-I15 -> 11.532
A16: 2026.9.3 | B16: 5 | C16: =C15-B16 -> 975 | D16: 9 | E16: =E15-D16 -> 945 | F16: 13.99 | G16: 3.528 | H16: =G16*D16 -> 31.752 | I16: 19.49 | J16: =D16/B16 -> 1.8 | K16: =H16-I16 -> 12.262
A17: 2026.9.4 | B17: 5 | C17: =C16-B17 -> 970 | D17: 8 | E17: =E16-D17 -> 937 | F17: 13.99 | G17: 3.528 | H17: =G17*D17 -> 28.224 | I17: 19.53 | J17: =D17/B17 -> 1.6 | K17: =H17-I17 -> 8.694
... A74: 2026.10.31 | B74: 5 | C74: =C73-B74 -> 0 | D74: 18 | E74: =E73-D74 -> -323 | F74: 21.99 | G74: 10.328 | H74: =G74*D74 -> 185.904 | I74: 0 | J74: =D74/B74 -> 3.6 | K74: =H74-I74 -> 185.904

Sheet 2.2 运营策略
A1: 变体合并策略 | C1: 执行细节及实际情况 | D1: 整体推广策略 | F1: 使用指南
A2: XXXX-111和XXXX-222合并 使用颜色进行合并 XXXXX等细节 | C2: 记录情况:8.18号 变体合并成功 | D2: 1、XXXX-111和XXXX-222 先开自动广告测款定主推款 3、推广节奏 第一阶段：Listing校验----自动广告 第二阶段：变体策略验证， 提升关键词排序---手动广告， 站外 第三阶段：提升订单量和关键词排序 | F2: 1、根据实际运营情况，每周对整体推广策略进行调整 2、基于上周运营表现，对下一周的核心目标、运营措施等进行更新调整并执行 3、记录运营数据到板块3
A3: 主推款运营框架 | C3: 执行细节及实际情况 | D3: 次推款运营框架 | F3: 执行细节及实际情况
A4: 【时间节点】 | B4: 第一阶段：9月第一周 | D4: 【时间节点】 | E4: 第一阶段：9月第一周
A5: 【核心目标】 | B5: 1.校正Listing的准确性， 完成LISTING基础收录，积累基础权重 2. 测词， 测款 | C5: 【执行细节】 1. 8.23号， 开自动广告， 预算$20， Bid $1.2 【核心指标情况】 1. 预算$20 能花完，展示量正常，整体点击率0.17%，偏低， 每日访客数在30-40，呈递增趋势，转化率7.88%正常 2. 广告展示量主要在商品页面， 预算花费在商品页面最多， 结合投放来看， 花费主要分布在紧密匹配和宽泛匹配， 说明目前市场上的竞品还不多 3. 从用户搜索词看， 目前主要也是跑的关键词，ASIN少。 关键词与我们Listing定位的关键词非常匹配， 主要是XXXXXXXXXXXX等相关词 ，与我们Listing的定位一致 4. 虽然看不到广告展示位， 但是关键词自然排序位置靠前， 可以继续按照现在的自动广告跑。 【遇到问题及后续计划】 问题： 1. 进一步提升关键词自然排序和订单量 2. 预算花费很分散， 现在没有特别热销的ASIN 计划： 1. 预算增加到$30 2. 自动广告中关掉同类商品和关联商品。 | D5: 【核心目标】 | E5: 1.校正Listing的准确性， 完成LISTING基础收录，积累基础权重 2. 测词， 测款 | F5: 【执行细节】 1. 8.23号， 开自动广告， 预算$20， Bid $1.2 【核心指标情况】 1. 预算$20能花完， 展示量偏低， 点击率正常， 转化率正常 2. 广告位来看， 广告主要展示在商品页面，预算主要花费在搜索结果其余位置， 从投放来看， 预算主要分配在紧密匹配和宽泛匹配， 说明现在竞品还不多。 3.看不到广告位 4. 用户搜索词： 主要是跑的一些跟xxxx相关的关键词，，与我们Listing的定位一致 5. 从关键词排序上看， XXXX-111主要在XXXXXX下有排序， 跟XXXX-222关键词排序形成互补， 所以目前XXXX-111和XXXX-222的自然广告都可以开。 【遇到问题及后续计划】 问题： 1. 进一步提升关键词自然排序和订单量 2. 预算花费很分散， 现在没有特别热销的ASIN，跑了很多长尾词 计划： 1. 预算增加到$30， Bid提高到$1.5 2. 自动广告中关掉同类商品和关联商品。
A6: 【本阶段运营措施】 | B6: 广告策略： 开自动广告 价格策略： 站外策略: | D6: 【本阶段运营措施】 | E6: 广告策略： 开自动广告 价格策略： 站外策略:
A7: 【重点跟进关注指标】 | B7: 1.Listing资料定位准确 2. 跑出的关键词与我们定位的关键词一致 3.广告曝光量正常 4. 关注核心关键词的排序， 广告位置展示 | D7: 【重点跟进关注指标】 | E7: 1.Listing资料定位准确 2. 跑出的关键词与我们定位的关键词一致 3.广告曝光量正常 4. 关注核心关键词的排序， 广告位置展示
A8: 【指标变动后的应对策略】 | B8: 1. 关键词排序提升， 订单量增长， 广告继续这也跑， 直到每日订单量20， 逐渐减少广告预算， 靠关键词自然位出单 2. 关键词排序和订单量没有增长， 那我们集中预算主要跑核心关键词，关闭同类商品和关联商品 | D8: 【指标变动后的应对策略】 | E8: 1. 关键词排序提升， 订单量增长， 广告继续这也跑， 直到每日订单量20， 逐渐减少广告预算， 靠关键词自然位出单 2. 关键词排序和订单量没有增长， 那我们集中预算主要跑核心关键词，关闭同类商品和关联商品
A9: 【时间节点】 | B9: 第二阶段：9月第二周 | D9: 【时间节点】 | E9: 第二阶段：9月第二周
A10: 【核心目标】 | B10: 提升关键词排序占据流量坑位 | C10: 【执行细节】 1. 9.7号 优化listing 【核心指标情况】 1. 订单量增长明显 2. 关键词XXXXXXXXXX P3， XXXXXXXX P1， 关键词位置提升明显 【遇到问题及后续计划】 问题： 1.出现了一个3星rating， 影响订单量 计划： 1. 与其他链接合并，解决评论的问题 | D10: 【核心目标】 | E10: 提升关键词排序占据流量坑位 | F10: 【执行细节】 1. 9.6号 关闭自动广告 2. 9.7号 优化listing 【核心指标情况】 1. 订单量增长明显， 关闭自动广告后 ， 订单量有下降 2. 关键词XXXXXXXX 排序在P3-P4， 变化不大 【遇到问题及后续计划】
A11: 【本阶段运营措施】 | B11: 1. 优化Listing标题， 资料文案， 让关键词跑出 XXXXXXXXXXXXX | D11: 【本阶段运营措施】 | E11: 1. 优化Listing标题， 资料文案， 让关键词跑出 XXXXXXXX 2. 关闭自动广告
A12: 【重点关注指标】 | B12: 1. 订单量的增长 2. 关键词排序的变化 | D12: 【重点关注指标】 | E12: 1. 订单量的增长 2. 关键词排序的变化
A13: 【指标变动后的应对策略】 | D13: 【指标变动后的应对策略】
A14: 【时间节点】 | B14: 第三阶段：9月第三周 | D14: 【时间节点】 | E14: 第三阶段：9月第三周
A15: 【核心目标】 | B15: 推动关键词排序进一步增长，抢占更靠前位置 | C15: 【执行细节】 9.13号 关闭自动广告 【核心指标情况】 1.订单量能够稳住， 并有增长 2. 关键词自然排序XXXXXXX 在P2， XXXXXXX在P1 能够稳住 3. 访客数也在增长 【遇到问题及后续计划】 计划： XXXX-111 涨价 | D15: 【核心目标】 | F15: 【执行细节】 【核心指标情况】 XXX 【遇到问题及后续计划】 XXX。
A16: 【本阶段运营措施】 | B16: 广告策略： 关闭自动广告， 靠自然出单 | D16: 【本阶段运营措施】
A17: 【重点关注指标】 | B17: 1. 订单量的变化 2. 关键词排序的变化 | D17: 【重点关注指标】
A18: 【指标变动后的应对策略】 | D18: 【指标变动后的应对策略】
A19: 【时间节点】 | B19: 第四阶段：9月第四周 | D19: 【时间节点】 | E19: 第四阶段：9月第四周
A20: 【核心目标】 | B20: 保证每日单量 整个链接40+， 提价做利润 | C20: 【执行细节】 9.17 号 XXXX-111 涨价 $13.99--$15.99 9.19号 XXXX-111 涨价 $15.99-$16.99 XXXX-222 涨价 $13.99-$14.99 【核心指标情况】 1.订单量能够稳住， 并有增长 2. 关键词自然排序XXXXXXXXX 在P2， XXXXXXXX在P1 能够稳住 3. 访客数也在增长 【遇到问题及后续计划】 | D20: 【核心目标】 | E20: 例：保持库存动销，避免库存积压 | F20: 【执行细节】 【核心指标情况】 XXX 【遇到问题及后续计划】 XXXX
A21: 【本阶段运营措施】 | B21: 价格策略：9.17 号 XXXX-111 涨价 $13.99--$15.99 9.19号 XXXX-111 涨价 $15.99-$16.99 XXXX-222 涨价 $13.99-$14.99 | D21: 【本阶段运营措施】
A22: 【重点关注指标】 | D22: 【重点关注指标】
A23: 【指标变动后的应对策略】 | D23: 【指标变动后的应对策略】
A25: 【时间节点】 | B25: 第五阶段：10月第一周 | D25: 【时间节点】 | E25: 第五阶段：10月第一周
A26: 【核心目标】 | B26: 例：保持每日XX销量，视情况提价释放利润 | C26: 【执行细节】 【核心指标情况】 【遇到问题及后续计划】 XXX | D26: 【核心目标】 | E26: 例：转化主推款流量，保持动销 | F26: 【执行细节】 【核心指标情况】 XXX 【遇到问题及后续计划】 XXX。
A27: 【本阶段运营措施】 | D27: 【本阶段运营措施】
A28: 【重点关注指标】 | D28: 【重点关注指标】
A29: 【指标变动后的应对策略】 | D29: 【指标变动后的应对策略】
A30: 【时间节点】 | B30: 第六阶段：10月第二周 | D30: 【时间节点】 | E30: 第六阶段：10月第二周
A31: 【核心目标】 | B31: 例：保持每日XX销量，视情况提价释放利润 | C31: 【执行细节】 【核心指标情况】 XXX 【遇到问题及后续计划】 XXX | D31: 【核心目标】 | E31: 例：保持库存动销，避免库存积压 | F31: 【执行细节】 【核心指标情况】 XXX 【遇到问题及后续计划】 XXXX
A32: 【本阶段运营措施】 | D32: 【本阶段运营措施】
A33: 【重点关注指标】 | D33: 【重点关注指标】
A34: 【指标变动后的应对策略】 | D34: 【指标变动后的应对策略】

Sheet  3.1 ASIN数据
A1: 分析指南 | B1: 1、关注数据重点：整个链接的整体数据规模到了什么程度？哪些指标需要重点分析？ 2、关注产品重点：主推款与次推款之间的数据占比如何？变体之间是否出现任何异常情况？ 3、关注工作重点：下阶段的工作重点是什么？如何帮助我们更好完成目标？后续需要重点关注哪些指标？
A2: 主推款SKU | B2: XXXX-111 | C2: ASIN | D2: ASIN1 | E2: 主图 | H2: 次推款SKU | I2: XXXX-222 | J2: ASIN | K2: ASIN2 | L2: 主图
A3: 日期 | B3: 销量 | C3: SESSION | D3: 销量转化率 | E3: 价格变动 | F3: 运营细节备注 | H3: 日期 | I3: 销量 | J3: 总SESSION | K3: 销量转化率 | L3: 运营细节备注
A4: 2022-08-23 | B4: =VLOOKUP($A4&$B$2,'4.2 产品详情原始数据'!$A:$BG,10,FALSE) -> #N/A | C4: =VLOOKUP($A4&$B$2,'4.2 产品详情原始数据'!$A:$BG,37,FALSE) -> #N/A | D4: =VLOOKUP($A4&$B$2,'4.2 产品详情原始数据'!$A:$BG,43,FALSE) -> #N/A | E4: =VLOOKUP($A4&$B$2,'4.2 产品详情原始数据'!$A:$BG,7,FALSE) -> #N/A | H4: 2022-08-23 | I4: =VLOOKUP(H4&$I$2,'4.2 产品详情原始数据'!$A:$BG,10,FALSE) -> #N/A | J4: =VLOOKUP($H4&$I$2,'4.2 产品详情原始数据'!$A:$BG,37,FALSE) -> #N/A | K4: =VLOOKUP($H4&$I$2,'4.2 产品详情原始数据'!$A:$BG,43,FALSE) -> #N/A
A5: 2022-08-24 | B5: =VLOOKUP($A5&$B$2,'4.2 产品详情原始数据'!$A:$BG,10,FALSE) -> #N/A | C5: =VLOOKUP($A5&$B$2,'4.2 产品详情原始数据'!$A:$BG,37,FALSE) -> #N/A | D5: =VLOOKUP($A5&$B$2,'4.2 产品详情原始数据'!$A:$BG,43,FALSE) -> #N/A | E5: =VLOOKUP($A5&$B$2,'4.2 产品详情原始数据'!$A:$BG,7,FALSE) -> #N/A | H5: 2022-08-24 | I5: =VLOOKUP(H5&$I$2,'4.2 产品详情原始数据'!$A:$BG,10,FALSE) -> #N/A | J5: =VLOOKUP($H5&$I$2,'4.2 产品详情原始数据'!$A:$BG,37,FALSE) -> #N/A | K5: =VLOOKUP($H5&$I$2,'4.2 产品详情原始数据'!$A:$BG,43,FALSE) -> #N/A
A6: 2022-08-25 | B6: =VLOOKUP($A6&$B$2,'4.2 产品详情原始数据'!$A:$BG,10,FALSE) -> #N/A | C6: =VLOOKUP($A6&$B$2,'4.2 产品详情原始数据'!$A:$BG,37,FALSE) -> #N/A | D6: =VLOOKUP($A6&$B$2,'4.2 产品详情原始数据'!$A:$BG,43,FALSE) -> #N/A | E6: =VLOOKUP($A6&$B$2,'4.2 产品详情原始数据'!$A:$BG,7,FALSE) -> #N/A | H6: 2022-08-25 | I6: =VLOOKUP(H6&$I$2,'4.2 产品详情原始数据'!$A:$BG,10,FALSE) -> #N/A | J6: =VLOOKUP($H6&$I$2,'4.2 产品详情原始数据'!$A:$BG,37,FALSE) -> #N/A | K6: =VLOOKUP($H6&$I$2,'4.2 产品详情原始数据'!$A:$BG,43,FALSE) -> #N/A
A7: 2022-08-26 | B7: =VLOOKUP($A7&$B$2,'4.2 产品详情原始数据'!$A:$BG,10,FALSE) -> #N/A | C7: =VLOOKUP($A7&$B$2,'4.2 产品详情原始数据'!$A:$BG,37,FALSE) -> #N/A | D7: =VLOOKUP($A7&$B$2,'4.2 产品详情原始数据'!$A:$BG,43,FALSE) -> #N/A | E7: =VLOOKUP($A7&$B$2,'4.2 产品详情原始数据'!$A:$BG,7,FALSE) -> #N/A | H7: 2022-08-26 | I7: =VLOOKUP(H7&$I$2,'4.2 产品详情原始数据'!$A:$BG,10,FALSE) -> #N/A | J7: =VLOOKUP($H7&$I$2,'4.2 产品详情原始数据'!$A:$BG,37,FALSE) -> #N/A | K7: =VLOOKUP($H7&$I$2,'4.2 产品详情原始数据'!$A:$BG,43,FALSE) -> #N/A
A8: 2022-08-27 | B8: =VLOOKUP($A8&$B$2,'4.2 产品详情原始数据'!$A:$BG,10,FALSE) -> #N/A | C8: =VLOOKUP($A8&$B$2,'4.2 产品详情原始数据'!$A:$BG,37,FALSE) -> #N/A | D8: =VLOOKUP($A8&$B$2,'4.2 产品详情原始数据'!$A:$BG,43,FALSE) -> #N/A | E8: =VLOOKUP($A8&$B$2,'4.2 产品详情原始数据'!$A:$BG,7,FALSE) -> #N/A | H8: 2022-08-27 | I8: =VLOOKUP(H8&$I$2,'4.2 产品详情原始数据'!$A:$BG,10,FALSE) -> #N/A | J8: =VLOOKUP($H8&$I$2,'4.2 产品详情原始数据'!$A:$BG,37,FALSE) -> #N/A | K8: =VLOOKUP($H8&$I$2,'4.2 产品详情原始数据'!$A:$BG,43,FALSE) -> #N/A
A9: 2022-08-28 | B9: =VLOOKUP($A9&$B$2,'4.2 产品详情原始数据'!$A:$BG,10,FALSE) -> #N/A | C9: =VLOOKUP($A9&$B$2,'4.2 产品详情原始数据'!$A:$BG,37,FALSE) -> #N/A | D9: =VLOOKUP($A9&$B$2,'4.2 产品详情原始数据'!$A:$BG,43,FALSE) -> #N/A | E9: =VLOOKUP($A9&$B$2,'4.2 产品详情原始数据'!$A:$BG,7,FALSE) -> #N/A | H9: 2022-08-28 | I9: =VLOOKUP(H9&$I$2,'4.2 产品详情原始数据'!$A:$BG,10,FALSE) -> #N/A | J9: =VLOOKUP($H9&$I$2,'4.2 产品详情原始数据'!$A:$BG,37,FALSE) -> #N/A | K9: =VLOOKUP($H9&$I$2,'4.2 产品详情原始数据'!$A:$BG,43,FALSE) -> #N/A
A10: 2022-08-29 | B10: =VLOOKUP($A10&$B$2,'4.2 产品详情原始数据'!$A:$BG,10,FALSE) -> #N/A | C10: =VLOOKUP($A10&$B$2,'4.2 产品详情原始数据'!$A:$BG,37,FALSE) -> #N/A | D10: =VLOOKUP($A10&$B$2,'4.2 产品详情原始数据'!$A:$BG,43,FALSE) -> #N/A | E10: =VLOOKUP($A10&$B$2,'4.2 产品详情原始数据'!$A:$BG,7,FALSE) -> #N/A | H10: 2022-08-29 | I10: =VLOOKUP(H10&$I$2,'4.2 产品详情原始数据'!$A:$BG,10,FALSE) -> #N/A | J10: =VLOOKUP($H10&$I$2,'4.2 产品详情原始数据'!$A:$BG,37,FALSE) -> #N/A | K10: =VLOOKUP($H10&$I$2,'4.2 产品详情原始数据'!$A:$BG,43,FALSE) -> #N/A
A11: 2022-08-30 | B11: =VLOOKUP($A11&$B$2,'4.2 产品详情原始数据'!$A:$BG,10,FALSE) -> #N/A | C11: =VLOOKUP($A11&$B$2,'4.2 产品详情原始数据'!$A:$BG,37,FALSE) -> #N/A | D11: =VLOOKUP($A11&$B$2,'4.2 产品详情原始数据'!$A:$BG,43,FALSE) -> #N/A | E11: =VLOOKUP($A11&$B$2,'4.2 产品详情原始数据'!$A:$BG,7,FALSE) -> #N/A | H11: 2022-08-30 | I11: =VLOOKUP(H11&$I$2,'4.2 产品详情原始数据'!$A:$BG,10,FALSE) -> #N/A | J11: =VLOOKUP($H11&$I$2,'4.2 产品详情原始数据'!$A:$BG,37,FALSE) -> #N/A | K11: =VLOOKUP($H11&$I$2,'4.2 产品详情原始数据'!$A:$BG,43,FALSE) -> #N/A
A12: 2022-08-31 | B12: =VLOOKUP($A12&$B$2,'4.2 产品详情原始数据'!$A:$BG,10,FALSE) -> #N/A | C12: =VLOOKUP($A12&$B$2,'4.2 产品详情原始数据'!$A:$BG,37,FALSE) -> #N/A | D12: =VLOOKUP($A12&$B$2,'4.2 产品详情原始数据'!$A:$BG,43,FALSE) -> #N/A | E12: =VLOOKUP($A12&$B$2,'4.2 产品详情原始数据'!$A:$BG,7,FALSE) -> #N/A | H12: 2022-08-31 | I12: =VLOOKUP(H12&$I$2,'4.2 产品详情原始数据'!$A:$BG,10,FALSE) -> #N/A | J12: =VLOOKUP($H12&$I$2,'4.2 产品详情原始数据'!$A:$BG,37,FALSE) -> #N/A | K12: =VLOOKUP($H12&$I$2,'4.2 产品详情原始数据'!$A:$BG,43,FALSE) -> #N/A
A13: 2022-09-01 | B13: =VLOOKUP($A13&$B$2,'4.2 产品详情原始数据'!$A:$BG,10,FALSE) -> #N/A | C13: =VLOOKUP($A13&$B$2,'4.2 产品详情原始数据'!$A:$BG,37,FALSE) -> #N/A | D13: =VLOOKUP($A13&$B$2,'4.2 产品详情原始数据'!$A:$BG,43,FALSE) -> #N/A | E13: =VLOOKUP($A13&$B$2,'4.2 产品详情原始数据'!$A:$BG,7,FALSE) -> #N/A | H13: 2022-09-01 | I13: =VLOOKUP(H13&$I$2,'4.2 产品详情原始数据'!$A:$BG,10,FALSE) -> #N/A | J13: =VLOOKUP($H13&$I$2,'4.2 产品详情原始数据'!$A:$BG,37,FALSE) -> #N/A | K13: =VLOOKUP($H13&$I$2,'4.2 产品详情原始数据'!$A:$BG,43,FALSE) -> #N/A
A14: 2022-09-02 | B14: =VLOOKUP($A14&$B$2,'4.2 产品详情原始数据'!$A:$BG,10,FALSE) -> #N/A | C14: =VLOOKUP($A14&$B$2,'4.2 产品详情原始数据'!$A:$BG,37,FALSE) -> #N/A | D14: =VLOOKUP($A14&$B$2,'4.2 产品详情原始数据'!$A:$BG,43,FALSE) -> #N/A | E14: =VLOOKUP($A14&$B$2,'4.2 产品详情原始数据'!$A:$BG,7,FALSE) -> #N/A | H14: 2022-09-02 | I14: =VLOOKUP(H14&$I$2,'4.2 产品详情原始数据'!$A:$BG,10,FALSE) -> #N/A | J14: =VLOOKUP($H14&$I$2,'4.2 产品详情原始数据'!$A:$BG,37,FALSE) -> #N/A | K14: =VLOOKUP($H14&$I$2,'4.2 产品详情原始数据'!$A:$BG,43,FALSE) -> #N/A
A15: 2022-09-03 | B15: =VLOOKUP($A15&$B$2,'4.2 产品详情原始数据'!$A:$BG,10,FALSE) -> #N/A | C15: =VLOOKUP($A15&$B$2,'4.2 产品详情原始数据'!$A:$BG,37,FALSE) -> #N/A | D15: =VLOOKUP($A15&$B$2,'4.2 产品详情原始数据'!$A:$BG,43,FALSE) -> #N/A | E15: =VLOOKUP($A15&$B$2,'4.2 产品详情原始数据'!$A:$BG,7,FALSE) -> #N/A | H15: 2022-09-03 | I15: =VLOOKUP(H15&$I$2,'4.2 产品详情原始数据'!$A:$BG,10,FALSE) -> #N/A | J15: =VLOOKUP($H15&$I$2,'4.2 产品详情原始数据'!$A:$BG,37,FALSE) -> #N/A | K15: =VLOOKUP($H15&$I$2,'4.2 产品详情原始数据'!$A:$BG,43,FALSE) -> #N/A
... A57: 2022-10-15 | B57: =VLOOKUP($A57&$B$2,'4.2 产品详情原始数据'!$A:$BG,10,FALSE) -> #N/A | C57: =VLOOKUP($A57&$B$2,'4.2 产品详情原始数据'!$A:$BG,37,FALSE) -> #N/A | D57: =VLOOKUP($A57&$B$2,'4.2 产品详情原始数据'!$A:$BG,43,FALSE) -> #N/A | E57: =VLOOKUP($A57&$B$2,'4.2 产品详情原始数据'!$A:$BG,7,FALSE) -> #N/A | H57: 2022-10-15 | I57: =VLOOKUP(H57&$I$2,'4.2 产品详情原始数据'!$A:$BG,10,FALSE) -> #N/A | J57: =VLOOKUP($H57&$I$2,'4.2 产品详情原始数据'!$A:$BG,37,FALSE) -> #N/A | K57: =VLOOKUP($H57&$I$2,'4.2 产品详情原始数据'!$A:$BG,43,FALSE) -> #N/A
AF69: 求和项:Sessions-Total | AG69: MSKU
AF70: 时间 | AG70: XXXX-111 | AH70: XXXX-222 | AI70: 总计
AF71: 2022-08-20 | AG71: 0 | AH71: 0 | AI71: 0
AF72: 2022-08-21 | AG72: 0 | AH72: 0 | AI72: 0
AF73: 2022-08-22 | AG73: 0 | AH73: 0 | AI73: 0
AF74: 2022-08-23 | AG74: 29 | AH74: 25 | AI74: 54
AF75: 2022-08-24 | AG75: 25 | AH75: 16 | AI75: 41
A76: 求和项:Sessions-Total | B76: MSKU | H76: 求和项:销量 | I76: MSKU | N76: 求和项:销量CVR | O76: MSKU | AF76: 2022-08-25 | AG76: 17 | AH76: 28 | AI76: 45
A77: 时间 | B77: XXXX-111 | C77: XXXX-222 | D77: 总计 | H77: 时间 | I77: XXXX-111 | J77: XXXX-222 | K77: 总计 | N77: 时间 | O77: XXXX-111 | P77: XXXX-222 | Q77: 总计 | AF77: 2022-08-26 | AG77: 32 | AH77: 37 | AI77: 69
A78: 2022-08-20 | B78: 0 | C78: 0 | D78: 0 | H78: 2022-08-20 | I78: 0 | J78: 0 | K78: 0 | N78: 2022-08-20 | O78: 0 | P78: 0 | Q78: 0 | AF78: 2022-08-27 | AG78: 40 | AH78: 47 | AI78: 87
A79: 2022-08-21 | B79: 0 | C79: 0 | D79: 0 | H79: 2022-08-21 | I79: 0 | J79: 0 | K79: 0 | N79: 2022-08-21 | O79: 0 | P79: 0 | Q79: 0 | AF79: 2022-08-28 | AG79: 54 | AH79: 50 | AI79: 104
A80: 2022-08-22 | B80: 0 | C80: 0 | D80: 0 | H80: 2022-08-22 | I80: 0 | J80: 0 | K80: 0 | N80: 2022-08-22 | O80: 0 | P80: 0 | Q80: 0 | AF80: 2022-08-29 | AG80: 46 | AH80: 34 | AI80: 80
A81: 2022-08-23 | B81: 29 | C81: 25 | D81: 54 | H81: 2022-08-23 | I81: 2 | J81: 1 | K81: 3 | N81: 2022-08-23 | O81: 0.069 | P81: 0.04 | Q81: 0.109 | AF81: 2022-08-30 | AG81: 78 | AH81: 48 | AI81: 126
A82: 2022-08-24 | B82: 25 | C82: 16 | D82: 41 | H82: 2022-08-24 | I82: 1 | J82: 0 | K82: 1 | N82: 2022-08-24 | O82: 0.04 | P82: 0 | Q82: 0.04 | AF82: 2022-08-31 | AG82: 71 | AH82: 62 | AI82: 133
A83: 2022-08-25 | B83: 17 | C83: 28 | D83: 45 | H83: 2022-08-25 | I83: 0 | J83: 1 | K83: 1 | N83: 2022-08-25 | O83: 0 | P83: 0.0357 | Q83: 0.0357 | AF83: 2022-09-01 | AG83: 85 | AH83: 52 | AI83: 137
A84: 2022-08-26 | B84: 32 | C84: 37 | D84: 69 | H84: 2022-08-26 | I84: 1 | J84: 5 | K84: 6 | N84: 2022-08-26 | O84: 0.0312 | P84: 0.1351 | Q84: 0.1663 | AF84: 2022-09-02 | AG84: 94 | AH84: 61 | AI84: 155
A85: 2022-08-27 | B85: 40 | C85: 47 | D85: 87 | H85: 2022-08-27 | I85: 3 | J85: 2 | K85: 5 | N85: 2022-08-27 | O85: 0.075 | P85: 0.0426 | Q85: 0.1176 | AF85: 2022-09-03 | AG85: 124 | AH85: 81 | AI85: 205
A86: 2022-08-28 | B86: 54 | C86: 50 | D86: 104 | H86: 2022-08-28 | I86: 3 | J86: 1 | K86: 4 | N86: 2022-08-28 | O86: 0.0556 | P86: 0.02 | Q86: 0.0756 | AF86: 2022-09-04 | AG86: 149 | AH86: 90 | AI86: 239
A87: 2022-08-29 | B87: 46 | C87: 34 | D87: 80 | H87: 2022-08-29 | I87: 9 | J87: 1 | K87: 10 | N87: 2022-08-29 | O87: 0.1957 | P87: 0.0294 | Q87: 0.2251 | AF87: 2022-09-05 | AG87: 203 | AH87: 129 | AI87: 332
A88: 2022-08-30 | B88: 78 | C88: 48 | D88: 126 | H88: 2022-08-30 | I88: 5 | J88: 5 | K88: 10 | N88: 2022-08-30 | O88: 0.0641 | P88: 0.1042 | Q88: 0.1683 | AF88: 2022-09-06 | AG88: 138 | AH88: 77 | AI88: 215
A89: 2022-08-31 | B89: 71 | C89: 62 | D89: 133 | H89: 2022-08-31 | I89: 9 | J89: 3 | K89: 12 | N89: 2022-08-31 | O89: 0.1268 | P89: 0.0484 | Q89: 0.1752 | AF89: 2022-09-07 | AG89: 142 | AH89: 62 | AI89: 204
... A93: 2022-09-04 | B93: 149 | C93: 90 | D93: 239 | H93: 2022-09-04 | I93: 8 | J93: 11 | K93: 19 | N93: 2022-09-04 | O93: 0.0537 | P93: 0.1222 | Q93: 0.1759 | AF93: 总计 | AG93: 1723 | AH93: 1085 | AI93: 2808
A94: 2022-09-05 | B94: 203 | C94: 129 | D94: 332 | H94: 2022-09-05 | I94: 23 | J94: 11 | K94: 34 | N94: 2022-09-05 | O94: 0.1133 | P94: 0.0853 | Q94: 0.1986
A95: 2022-09-06 | B95: 138 | C95: 77 | D95: 215 | H95: 2022-09-06 | I95: 17 | J95: 10 | K95: 27 | N95: 2022-09-06 | O95: 0.1232 | P95: 0.1299 | Q95: 0.2531
A96: 2022-09-07 | B96: 142 | C96: 62 | D96: 204 | H96: 2022-09-07 | I96: 11 | J96: 4 | K96: 15 | N96: 2022-09-07 | O96: 0.0775 | P96: 0.0645 | Q96: 0.142
A97: 2022-09-08 | B97: 122 | C97: 61 | D97: 183 | H97: 2022-09-08 | I97: 12 | J97: 4 | K97: 16 | N97: 2022-09-08 | O97: 0.0984 | P97: 0.0656 | Q97: 0.164
A98: 2022-09-09 | B98: 102 | C98: 58 | D98: 160 | H98: 2022-09-09 | I98: 9 | J98: 5 | K98: 14 | N98: 2022-09-09 | O98: 0.0882 | P98: 0.0862 | Q98: 0.1744
A99: 2022-09-10 | B99: 172 | C99: 67 | D99: 239 | H99: 2022-09-10 | I99: 11 | J99: 5 | K99: 16 | N99: 2022-09-10 | O99: 0.064 | P99: 0.0746 | Q99: 0.1386
A100: 2022-09-11 | B100: 204 | C100: 81 | D100: 285 | H100: 2022-09-11 | I100: 14 | J100: 10 | K100: 24 | N100: 2022-09-11 | O100: 0.0686 | P100: 0.1235 | Q100: 0.1921
A101: 2022-09-12 | B101: 165 | C101: 56 | D101: 221 | H101: 2022-09-12 | I101: 18 | J101: 5 | K101: 23 | N101: 2022-09-12 | O101: 0.1091 | P101: 0.0893 | Q101: 0.1984
A102: 2022-09-13 | B102: 175 | C102: 60 | D102: 235 | H102: 2022-09-13 | I102: 19 | J102: 10 | K102: 29 | N102: 2022-09-13 | O102: 0.1086 | P102: 0.1667 | Q102: 0.2753
A103: 2022-09-14 | B103: 200 | C103: 71 | D103: 271 | H103: 2022-09-14 | I103: 21 | J103: 6 | K103: 27 | N103: 2022-09-14 | O103: 0.105 | P103: 0.0845 | Q103: 0.1895
A104: 2022-09-15 | B104: 176 | C104: 72 | D104: 248 | H104: 2022-09-15 | I104: 22 | J104: 14 | K104: 36 | N104: 2022-09-15 | O104: 0.125 | P104: 0.1944 | Q104: 0.3194
A105: 2022-09-16 | B105: 187 | C105: 67 | D105: 254 | H105: 2022-09-16 | I105: 29 | J105: 7 | K105: 36 | N105: 2022-09-16 | O105: 0.1551 | P105: 0.1045 | Q105: 0.2596
... A109: 2022-09-20 | B109: 235 | C109: 92 | D109: 327 | H109: 2022-09-20 | I109: 26 | J109: 10 | K109: 36 | N109: 2022-09-20 | O109: 0.1106 | P109: 0.1087 | Q109: 0.2193
A110: 2022-09-21 | B110: 226 | C110: 85 | D110: 311 | H110: 2022-09-21 | I110: 21 | J110: 13 | K110: 34 | N110: 2022-09-21 | O110: 0.0929 | P110: 0.1529 | Q110: 0.2458 | AC110: 求和项:销量CVR | AD110: MSKU
A111: 2022-09-22 | B111: 220 | C111: 66 | D111: 286 | H111: 2022-09-22 | I111: 35 | J111: 7 | K111: 42 | N111: 2022-09-22 | O111: 0.1591 | P111: 0.1061 | Q111: 0.2652 | AC111: 时间 | AD111: 总计
A112: 2022-09-23 | B112: 206 | C112: 74 | D112: 280 | H112: 2022-09-23 | I112: 27 | J112: 13 | K112: 40 | N112: 2022-09-23 | O112: 0.1311 | P112: 0.1757 | Q112: 0.3068 | AC112: 总计
A113: 2022-09-24 | B113: 250 | C113: 77 | D113: 327 | H113: 2022-09-24 | I113: 24 | J113: 18 | K113: 42 | N113: 2022-09-24 | O113: 0.096 | P113: 0.2338 | Q113: 0.3298
A114: 2022-09-25 | B114: 314 | C114: 113 | D114: 427 | H114: 2022-09-25 | I114: 35 | J114: 8 | K114: 43 | N114: 2022-09-25 | O114: 0.1115 | P114: 0.0708 | Q114: 0.1823
A115: 2022-09-26 | B115: 231 | C115: 85 | D115: 316 | H115: 2022-09-26 | I115: 25 | J115: 12 | K115: 37 | N115: 2022-09-26 | O115: 0.1082 | P115: 0.1412 | Q115: 0.2494
A116: 2022-09-27 | B116: 214 | C116: 61 | D116: 275 | H116: 2022-09-27 | I116: 31 | J116: 14 | K116: 45 | N116: 2022-09-27 | O116: 0.1449 | P116: 0.2295 | Q116: 0.3744
A117: 2022-09-28 | B117: 191 | C117: 60 | D117: 251 | H117: 2022-09-28 | I117: 24 | J117: 9 | K117: 33 | N117: 2022-09-28 | O117: 0.1257 | P117: 0.15 | Q117: 0.2757
A118: 2022-09-29 | B118: 191 | C118: 69 | D118: 260 | H118: 2022-09-29 | I118: 29 | J118: 6 | K118: 35 | N118: 2022-09-29 | O118: 0.1518 | P118: 0.087 | Q118: 0.2388
A119: 2022-09-30 | B119: 216 | C119: 69 | D119: 285 | H119: 2022-09-30 | I119: 29 | J119: 10 | K119: 39 | N119: 2022-09-30 | O119: 0.1343 | P119: 0.1449 | Q119: 0.2792
A120: 2022-10-01 | B120: 353 | C120: 180 | D120: 533 | H120: 2022-10-01 | I120: 47 | J120: 36 | K120: 83 | N120: 2022-10-01 | O120: 0.1331 | P120: 0.2 | Q120: 0.3331
A121: 2022-10-02 | B121: 403 | C121: 221 | D121: 624 | H121: 2022-10-02 | I121: 49 | J121: 40 | K121: 89 | N121: 2022-10-02 | O121: 0.1216 | P121: 0.181 | Q121: 0.3026
A122: 2022-10-03 | B122: 285 | C122: 126 | D122: 411 | H122: 2022-10-03 | I122: 38 | J122: 23 | K122: 61 | N122: 2022-10-03 | O122: 0.1333 | P122: 0.1825 | Q122: 0.3158
A123: 2022-10-04 | B123: 229 | C123: 119 | D123: 348 | H123: 2022-10-04 | I123: 27 | J123: 18 | K123: 45 | N123: 2022-10-04 | O123: 0.1179 | P123: 0.1513 | Q123: 0.2692
A124: 2022-10-05 | B124: 208 | C124: 117 | D124: 325 | H124: 2022-10-05 | I124: 32 | J124: 26 | K124: 58 | N124: 2022-10-05 | O124: 0.1538 | P124: 0.2222 | Q124: 0.376
... A135: 总计 | B135: 8810 | C135: 4481 | D135: 13291 | H135: 总计 | I135: 993 | J135: 653 | K135: 1646 | N135: 总计 | O135: 5.4481 | P135: 6.338 | Q135: 11.7861

Sheet 3.2 关键词数据
B1: XXXX-111 | J1: XXXX-222 | S1: 辅助列
S2: 7 | T2: 8 | U2: 9 | V2: 10 | W2: 11 | X2: 12 | Y2: 13 | Z2: 14 | AA2: 15 | AB2: 16 | AC2: 17 | AD2: 18 | AE2: 19 | AF2: 20 | AG2: 21 | AH2: 22 | AI2: 23 | AJ2: 24 | AK2: 25 | AL2: 26 | AM2: 27 | AN2: 28 | AO2: 29 | AP2: 30 | AQ2: 31 | AR2: 32 | AS2: 33 | AT2: 34 | AU2: 35
B3: 关键词1 | D3: 关键词2 | F3: 关键词3 | H3: 关键词4 | J3: 关键词1 | L3: 关键词2 | N3: 关键词3 | P3: 关键词4
A4: 日期 | B4: 广告位 | C4: 自然位 | D4: 广告位 | E4: 自然位 | F4: 广告位 | G4: 自然位 | H4: 广告位 | I4: 自然位 | J4: 广告位 | K4: 自然位 | L4: 广告位 | M4: 自然位 | N4: 广告位 | O4: 自然位 | P4: 广告位 | Q4: 自然位
A5: 8月31日上午 | B5: =_xlfn.IFNA(IF(VLOOKUP($B$1&$A5,'4.1 关键词原始数据'!$A:$N,S$2,FALSE)=0," ",VLOOKUP($B$1&$A5,'4.1 关键词原始数据'!$A:$N,S$2,FALSE))," ") | C5: =_xlfn.IFNA(IF(VLOOKUP($B$1&$A5,'4.1 关键词原始数据'!$A:$N,T$2,FALSE)=0," ",VLOOKUP($B$1&$A5,'4.1 关键词原始数据'!$A:$N,T$2,FALSE))," ") -> 3-7-2 | D5: =_xlfn.IFNA(IF(VLOOKUP($B$1&$A5,'4.1 关键词原始数据'!$A:$N,U$2,FALSE)=0," ",VLOOKUP($B$1&$A5,'4.1 关键词原始数据'!$A:$N,U$2,FALSE))," ") | E5: =_xlfn.IFNA(IF(VLOOKUP($B$1&$A5,'4.1 关键词原始数据'!$A:$N,V$2,FALSE)=0," ",VLOOKUP($B$1&$A5,'4.1 关键词原始数据'!$A:$N,V$2,FALSE))," ") | F5: =_xlfn.IFNA(IF(VLOOKUP($B$1&$A5,'4.1 关键词原始数据'!$A:$N,W$2,FALSE)=0," ",VLOOKUP($B$1&$A5,'4.1 关键词原始数据'!$A:$N,W$2,FALSE))," ") | G5: =_xlfn.IFNA(IF(VLOOKUP($B$1&$A5,'4.1 关键词原始数据'!$A:$N,X$2,FALSE)=0," ",VLOOKUP($B$1&$A5,'4.1 关键词原始数据'!$A:$N,X$2,FALSE))," ") -> 1-17-1 | H5: =_xlfn.IFNA(IF(VLOOKUP($B$1&$A5,'4.1 关键词原始数据'!$A:$N,Y$2,FALSE)=0," ",VLOOKUP($B$1&$A5,'4.1 关键词原始数据'!$A:$N,Y$2,FALSE))," ") | I5: =_xlfn.IFNA(IF(VLOOKUP($B$1&$A5,'4.1 关键词原始数据'!$A:$N,Z$2,FALSE)=0," ",VLOOKUP($B$1&$A5,'4.1 关键词原始数据'!$A:$N,Z$2,FALSE))," ") | J5: =_xlfn.IFNA(IF(VLOOKUP($J$1&$A5,'4.1 关键词原始数据'!$A:$N,S$2,FALSE)=0," ",VLOOKUP($J$1&$A5,'4.1 关键词原始数据'!$A:$N,S$2,FALSE))," ") | K5: =_xlfn.IFNA(IF(VLOOKUP($J$1&$A5,'4.1 关键词原始数据'!$A:$N,T$2,FALSE)=0," ",VLOOKUP($J$1&$A5,'4.1 关键词原始数据'!$A:$N,T$2,FALSE))," ") | L5: =_xlfn.IFNA(IF(VLOOKUP($J$1&$A5,'4.1 关键词原始数据'!$A:$N,U$2,FALSE)=0," ",VLOOKUP($J$1&$A5,'4.1 关键词原始数据'!$A:$N,U$2,FALSE))," ") | M5: =_xlfn.IFNA(IF(VLOOKUP($J$1&$A5,'4.1 关键词原始数据'!$A:$N,V$2,FALSE)=0," ",VLOOKUP($J$1&$A5,'4.1 关键词原始数据'!$A:$N,V$2,FALSE))," ") | N5: =_xlfn.IFNA(IF(VLOOKUP($J$1&$A5,'4.1 关键词原始数据'!$A:$N,W$2,FALSE)=0," ",VLOOKUP($J$1&$A5,'4.1 关键词原始数据'!$A:$N,W$2,FALSE))," ") | O5: =_xlfn.IFNA(IF(VLOOKUP($J$1&$A5,'4.1 关键词原始数据'!$A:$N,X$2,FALSE)=0," ",VLOOKUP($J$1&$A5,'4.1 关键词原始数据'!$A:$N,X$2,FALSE))," ") | P5: =_xlfn.IFNA(IF(VLOOKUP($J$1&$A5,'4.1 关键词原始数据'!$A:$N,Y$2,FALSE)=0," ",VLOOKUP($J$1&$A5,'4.1 关键词原始数据'!$A:$N,Y$2,FALSE))," ") | Q5: =_xlfn.IFNA(IF(VLOOKUP($J$1&$A5,'4.1 关键词原始数据'!$A:$N,Z$2,FALSE)=0," ",VLOOKUP($J$1&$A5,'4.1 关键词原始数据'!$A:$N,Z$2,FALSE))," ")
A6: 8月31日晚上 | B6: =_xlfn.IFNA(IF(VLOOKUP($B$1&$A6,'4.1 关键词原始数据'!$A:$N,S$2,FALSE)=0," ",VLOOKUP($B$1&$A6,'4.1 关键词原始数据'!$A:$N,S$2,FALSE))," ") | C6: =_xlfn.IFNA(IF(VLOOKUP($B$1&$A6,'4.1 关键词原始数据'!$A:$N,T$2,FALSE)=0," ",VLOOKUP($B$1&$A6,'4.1 关键词原始数据'!$A:$N,T$2,FALSE))," ") | D6: =_xlfn.IFNA(IF(VLOOKUP($B$1&$A6,'4.1 关键词原始数据'!$A:$N,U$2,FALSE)=0," ",VLOOKUP($B$1&$A6,'4.1 关键词原始数据'!$A:$N,U$2,FALSE))," ") | E6: =_xlfn.IFNA(IF(VLOOKUP($B$1&$A6,'4.1 关键词原始数据'!$A:$N,V$2,FALSE)=0," ",VLOOKUP($B$1&$A6,'4.1 关键词原始数据'!$A:$N,V$2,FALSE))," ") | F6: =_xlfn.IFNA(IF(VLOOKUP($B$1&$A6,'4.1 关键词原始数据'!$A:$N,W$2,FALSE)=0," ",VLOOKUP($B$1&$A6,'4.1 关键词原始数据'!$A:$N,W$2,FALSE))," ") | G6: =_xlfn.IFNA(IF(VLOOKUP($B$1&$A6,'4.1 关键词原始数据'!$A:$N,X$2,FALSE)=0," ",VLOOKUP($B$1&$A6,'4.1 关键词原始数据'!$A:$N,X$2,FALSE))," ") | H6: =_xlfn.IFNA(IF(VLOOKUP($B$1&$A6,'4.1 关键词原始数据'!$A:$N,Y$2,FALSE)=0," ",VLOOKUP($B$1&$A6,'4.1 关键词原始数据'!$A:$N,Y$2,FALSE))," ") | I6: =_xlfn.IFNA(IF(VLOOKUP($B$1&$A6,'4.1 关键词原始数据'!$A:$N,Z$2,FALSE)=0," ",VLOOKUP($B$1&$A6,'4.1 关键词原始数据'!$A:$N,Z$2,FALSE))," ") | J6: =_xlfn.IFNA(IF(VLOOKUP($J$1&$A6,'4.1 关键词原始数据'!$A:$N,S$2,FALSE)=0," ",VLOOKUP($J$1&$A6,'4.1 关键词原始数据'!$A:$N,S$2,FALSE))," ") | K6: =_xlfn.IFNA(IF(VLOOKUP($J$1&$A6,'4.1 关键词原始数据'!$A:$N,T$2,FALSE)=0," ",VLOOKUP($J$1&$A6,'4.1 关键词原始数据'!$A:$N,T$2,FALSE))," ") | L6: =_xlfn.IFNA(IF(VLOOKUP($J$1&$A6,'4.1 关键词原始数据'!$A:$N,U$2,FALSE)=0," ",VLOOKUP($J$1&$A6,'4.1 关键词原始数据'!$A:$N,U$2,FALSE))," ") | M6: =_xlfn.IFNA(IF(VLOOKUP($J$1&$A6,'4.1 关键词原始数据'!$A:$N,V$2,FALSE)=0," ",VLOOKUP($J$1&$A6,'4.1 关键词原始数据'!$A:$N,V$2,FALSE))," ") | N6: =_xlfn.IFNA(IF(VLOOKUP($J$1&$A6,'4.1 关键词原始数据'!$A:$N,W$2,FALSE)=0," ",VLOOKUP($J$1&$A6,'4.1 关键词原始数据'!$A:$N,W$2,FALSE))," ") | O6: =_xlfn.IFNA(IF(VLOOKUP($J$1&$A6,'4.1 关键词原始数据'!$A:$N,X$2,FALSE)=0," ",VLOOKUP($J$1&$A6,'4.1 关键词原始数据'!$A:$N,X$2,FALSE))," ") | P6: =_xlfn.IFNA(IF(VLOOKUP($J$1&$A6,'4.1 关键词原始数据'!$A:$N,Y$2,FALSE)=0," ",VLOOKUP($J$1&$A6,'4.1 关键词原始数据'!$A:$N,Y$2,FALSE))," ") | Q6: =_xlfn.IFNA(IF(VLOOKUP($J$1&$A6,'4.1 关键词原始数据'!$A:$N,Z$2,FALSE)=0," ",VLOOKUP($J$1&$A6,'4.1 关键词原始数据'!$A:$N,Z$2,FALSE))," ")
A7: 9月1日上午 | B7: =_xlfn.IFNA(IF(VLOOKUP($B$1&$A7,'4.1 关键词原始数据'!$A:$N,S$2,FALSE)=0," ",VLOOKUP($B$1&$A7,'4.1 关键词原始数据'!$A:$N,S$2,FALSE))," ") | C7: =_xlfn.IFNA(IF(VLOOKUP($B$1&$A7,'4.1 关键词原始数据'!$A:$N,T$2,FALSE)=0," ",VLOOKUP($B$1&$A7,'4.1 关键词原始数据'!$A:$N,T$2,FALSE))," ") -> 2-12-4 | D7: =_xlfn.IFNA(IF(VLOOKUP($B$1&$A7,'4.1 关键词原始数据'!$A:$N,U$2,FALSE)=0," ",VLOOKUP($B$1&$A7,'4.1 关键词原始数据'!$A:$N,U$2,FALSE))," ") | E7: =_xlfn.IFNA(IF(VLOOKUP($B$1&$A7,'4.1 关键词原始数据'!$A:$N,V$2,FALSE)=0," ",VLOOKUP($B$1&$A7,'4.1 关键词原始数据'!$A:$N,V$2,FALSE))," ") -> 2-4-4 | F7: =_xlfn.IFNA(IF(VLOOKUP($B$1&$A7,'4.1 关键词原始数据'!$A:$N,W$2,FALSE)=0," ",VLOOKUP($B$1&$A7,'4.1 关键词原始数据'!$A:$N,W$2,FALSE))," ") | G7: =_xlfn.IFNA(IF(VLOOKUP($B$1&$A7,'4.1 关键词原始数据'!$A:$N,X$2,FALSE)=0," ",VLOOKUP($B$1&$A7,'4.1 关键词原始数据'!$A:$N,X$2,FALSE))," ") | H7: =_xlfn.IFNA(IF(VLOOKUP($B$1&$A7,'4.1 关键词原始数据'!$A:$N,Y$2,FALSE)=0," ",VLOOKUP($B$1&$A7,'4.1 关键词原始数据'!$A:$N,Y$2,FALSE))," ") | I7: =_xlfn.IFNA(IF(VLOOKUP($B$1&$A7,'4.1 关键词原始数据'!$A:$N,Z$2,FALSE)=0," ",VLOOKUP($B$1&$A7,'4.1 关键词原始数据'!$A:$N,Z$2,FALSE))," ") | J7: =_xlfn.IFNA(IF(VLOOKUP($J$1&$A7,'4.1 关键词原始数据'!$A:$N,S$2,FALSE)=0," ",VLOOKUP($J$1&$A7,'4.1 关键词原始数据'!$A:$N,S$2,FALSE))," ") | K7: =_xlfn.IFNA(IF(VLOOKUP($J$1&$A7,'4.1 关键词原始数据'!$A:$N,T$2,FALSE)=0," ",VLOOKUP($J$1&$A7,'4.1 关键词原始数据'!$A:$N,T$2,FALSE))," ") | L7: =_xlfn.IFNA(IF(VLOOKUP($J$1&$A7,'4.1 关键词原始数据'!$A:$N,U$2,FALSE)=0," ",VLOOKUP($J$1&$A7,'4.1 关键词原始数据'!$A:$N,U$2,FALSE))," ") | M7: =_xlfn.IFNA(IF(VLOOKUP($J$1&$A7,'4.1 关键词原始数据'!$A:$N,V$2,FALSE)=0," ",VLOOKUP($J$1&$A7,'4.1 关键词原始数据'!$A:$N,V$2,FALSE))," ") | N7: =_xlfn.IFNA(IF(VLOOKUP($J$1&$A7,'4.1 关键词原始数据'!$A:$N,W$2,FALSE)=0," ",VLOOKUP($J$1&$A7,'4.1 关键词原始数据'!$A:$N,W$2,FALSE))," ") | O7: =_xlfn.IFNA(IF(VLOOKUP($J$1&$A7,'4.1 关键词原始数据'!$A:$N,X$2,FALSE)=0," ",VLOOKUP($J$1&$A7,'4.1 关键词原始数据'!$A:$N,X$2,FALSE))," ") | P7: =_xlfn.IFNA(IF(VLOOKUP($J$1&$A7,'4.1 关键词原始数据'!$A:$N,Y$2,FALSE)=0," ",VLOOKUP($J$1&$A7,'4.1 关键词原始数据'!$A:$N,Y$2,FALSE))," ") | Q7: =_xlfn.IFNA(IF(VLOOKUP($J$1&$A7,'4.1 关键词原始数据'!$A:$N,Z$2,FALSE)=0," ",VLOOKUP($J$1&$A7,'4.1 关键词原始数据'!$A:$N,Z$2,FALSE))," ")
A8: 9月1日晚上 | B8: =_xlfn.IFNA(IF(VLOOKUP($B$1&$A8,'4.1 关键词原始数据'!$A:$N,S$2,FALSE)=0," ",VLOOKUP($B$1&$A8,'4.1 关键词原始数据'!$A:$N,S$2,FALSE))," ") | C8: =_xlfn.IFNA(IF(VLOOKUP($B$1&$A8,'4.1 关键词原始数据'!$A:$N,T$2,FALSE)=0," ",VLOOKUP($B$1&$A8,'4.1 关键词原始数据'!$A:$N,T$2,FALSE))," ") | D8: =_xlfn.IFNA(IF(VLOOKUP($B$1&$A8,'4.1 关键词原始数据'!$A:$N,U$2,FALSE)=0," ",VLOOKUP($B$1&$A8,'4.1 关键词原始数据'!$A:$N,U$2,FALSE))," ") | E8: =_xlfn.IFNA(IF(VLOOKUP($B$1&$A8,'4.1 关键词原始数据'!$A:$N,V$2,FALSE)=0," ",VLOOKUP($B$1&$A8,'4.1 关键词原始数据'!$A:$N,V$2,FALSE))," ") | F8: =_xlfn.IFNA(IF(VLOOKUP($B$1&$A8,'4.1 关键词原始数据'!$A:$N,W$2,FALSE)=0," ",VLOOKUP($B$1&$A8,'4.1 关键词原始数据'!$A:$N,W$2,FALSE))," ") | G8: =_xlfn.IFNA(IF(VLOOKUP($B$1&$A8,'4.1 关键词原始数据'!$A:$N,X$2,FALSE)=0," ",VLOOKUP($B$1&$A8,'4.1 关键词原始数据'!$A:$N,X$2,FALSE))," ") | H8: =_xlfn.IFNA(IF(VLOOKUP($B$1&$A8,'4.1 关键词原始数据'!$A:$N,Y$2,FALSE)=0," ",VLOOKUP($B$1&$A8,'4.1 关键词原始数据'!$A:$N,Y$2,FALSE))," ") | I8: =_xlfn.IFNA(IF(VLOOKUP($B$1&$A8,'4.1 关键词原始数据'!$A:$N,Z$2,FALSE)=0," ",VLOOKUP($B$1&$A8,'4.1 关键词原始数据'!$A:$N,Z$2,FALSE))," ") | J8: =_xlfn.IFNA(IF(VLOOKUP($J$1&$A8,'4.1 关键词原始数据'!$A:$N,S$2,FALSE)=0," ",VLOOKUP($J$1&$A8,'4.1 关键词原始数据'!$A:$N,S$2,FALSE))," ") | K8: =_xlfn.IFNA(IF(VLOOKUP($J$1&$A8,'4.1 关键词原始数据'!$A:$N,T$2,FALSE)=0," ",VLOOKUP($J$1&$A8,'4.1 关键词原始数据'!$A:$N,T$2,FALSE))," ") | L8: =_xlfn.IFNA(IF(VLOOKUP($J$1&$A8,'4.1 关键词原始数据'!$A:$N,U$2,FALSE)=0," ",VLOOKUP($J$1&$A8,'4.1 关键词原始数据'!$A:$N,U$2,FALSE))," ") | M8: =_xlfn.IFNA(IF(VLOOKUP($J$1&$A8,'4.1 关键词原始数据'!$A:$N,V$2,FALSE)=0," ",VLOOKUP($J$1&$A8,'4.1 关键词原始数据'!$A:$N,V$2,FALSE))," ") | N8: =_xlfn.IFNA(IF(VLOOKUP($J$1&$A8,'4.1 关键词原始数据'!$A:$N,W$2,FALSE)=0," ",VLOOKUP($J$1&$A8,'4.1 关键词原始数据'!$A:$N,W$2,FALSE))," ") | O8: =_xlfn.IFNA(IF(VLOOKUP($J$1&$A8,'4.1 关键词原始数据'!$A:$N,X$2,FALSE)=0," ",VLOOKUP($J$1&$A8,'4.1 关键词原始数据'!$A:$N,X$2,FALSE))," ") | P8: =_xlfn.IFNA(IF(VLOOKUP($J$1&$A8,'4.1 关键词原始数据'!$A:$N,Y$2,FALSE)=0," ",VLOOKUP($J$1&$A8,'4.1 关键词原始数据'!$A:$N,Y$2,FALSE))," ") | Q8: =_xlfn.IFNA(IF(VLOOKUP($J$1&$A8,'4.1 关键词原始数据'!$A:$N,Z$2,FALSE)=0," ",VLOOKUP($J$1&$A8,'4.1 关键词原始数据'!$A:$N,Z$2,FALSE))," ")
A9: 9月2日上午 | B9: =_xlfn.IFNA(IF(VLOOKUP($B$1&$A9,'4.1 关键词原始数据'!$A:$N,S$2,FALSE)=0," ",VLOOKUP($B$1&$A9,'4.1 关键词原始数据'!$A:$N,S$2,FALSE))," ") | C9: =_xlfn.IFNA(IF(VLOOKUP($B$1&$A9,'4.1 关键词原始数据'!$A:$N,T$2,FALSE)=0," ",VLOOKUP($B$1&$A9,'4.1 关键词原始数据'!$A:$N,T$2,FALSE))," ") -> 2-14-4 | D9: =_xlfn.IFNA(IF(VLOOKUP($B$1&$A9,'4.1 关键词原始数据'!$A:$N,U$2,FALSE)=0," ",VLOOKUP($B$1&$A9,'4.1 关键词原始数据'!$A:$N,U$2,FALSE))," ") | E9: =_xlfn.IFNA(IF(VLOOKUP($B$1&$A9,'4.1 关键词原始数据'!$A:$N,V$2,FALSE)=0," ",VLOOKUP($B$1&$A9,'4.1 关键词原始数据'!$A:$N,V$2,FALSE))," ") | F9: =_xlfn.IFNA(IF(VLOOKUP($B$1&$A9,'4.1 关键词原始数据'!$A:$N,W$2,FALSE)=0," ",VLOOKUP($B$1&$A9,'4.1 关键词原始数据'!$A:$N,W$2,FALSE))," ") | G9: =_xlfn.IFNA(IF(VLOOKUP($B$1&$A9,'4.1 关键词原始数据'!$A:$N,X$2,FALSE)=0," ",VLOOKUP($B$1&$A9,'4.1 关键词原始数据'!$A:$N,X$2,FALSE))," ") -> 2-7-4 | H9: =_xlfn.IFNA(IF(VLOOKUP($B$1&$A9,'4.1 关键词原始数据'!$A:$N,Y$2,FALSE)=0," ",VLOOKUP($B$1&$A9,'4.1 关键词原始数据'!$A:$N,Y$2,FALSE))," ") | I9: =_xlfn.IFNA(IF(VLOOKUP($B$1&$A9,'4.1 关键词原始数据'!$A:$N,Z$2,FALSE)=0," ",VLOOKUP($B$1&$A9,'4.1 关键词原始数据'!$A:$N,Z$2,FALSE))," ") | J9: =_xlfn.IFNA(IF(VLOOKUP($J$1&$A9,'4.1 关键词原始数据'!$A:$N,S$2,FALSE)=0," ",VLOOKUP($J$1&$A9,'4.1 关键词原始数据'!$A:$N,S$2,FALSE))," ") | K9: =_xlfn.IFNA(IF(VLOOKUP($J$1&$A9,'4.1 关键词原始数据'!$A:$N,T$2,FALSE)=0," ",VLOOKUP($J$1&$A9,'4.1 关键词原始数据'!$A:$N,T$2,FALSE))," ") | L9: =_xlfn.IFNA(IF(VLOOKUP($J$1&$A9,'4.1 关键词原始数据'!$A:$N,U$2,FALSE)=0," ",VLOOKUP($J$1&$A9,'4.1 关键词原始数据'!$A:$N,U$2,FALSE))," ") | M9: =_xlfn.IFNA(IF(VLOOKUP($J$1&$A9,'4.1 关键词原始数据'!$A:$N,V$2,FALSE)=0," ",VLOOKUP($J$1&$A9,'4.1 关键词原始数据'!$A:$N,V$2,FALSE))," ") -> 3-16-4 | N9: =_xlfn.IFNA(IF(VLOOKUP($J$1&$A9,'4.1 关键词原始数据'!$A:$N,W$2,FALSE)=0," ",VLOOKUP($J$1&$A9,'4.1 关键词原始数据'!$A:$N,W$2,FALSE))," ") | O9: =_xlfn.IFNA(IF(VLOOKUP($J$1&$A9,'4.1 关键词原始数据'!$A:$N,X$2,FALSE)=0," ",VLOOKUP($J$1&$A9,'4.1 关键词原始数据'!$A:$N,X$2,FALSE))," ") | P9: =_xlfn.IFNA(IF(VLOOKUP($J$1&$A9,'4.1 关键词原始数据'!$A:$N,Y$2,FALSE)=0," ",VLOOKUP($J$1&$A9,'4.1 关键词原始数据'!$A:$N,Y$2,FALSE))," ") | Q9: =_xlfn.IFNA(IF(VLOOKUP($J$1&$A9,'4.1 关键词原始数据'!$A:$N,Z$2,FALSE)=0," ",VLOOKUP($J$1&$A9,'4.1 关键词原始数据'!$A:$N,Z$2,FALSE))," ")
A10: 9月2日晚上 | B10: =_xlfn.IFNA(IF(VLOOKUP($B$1&$A10,'4.1 关键词原始数据'!$A:$N,S$2,FALSE)=0," ",VLOOKUP($B$1&$A10,'4.1 关键词原始数据'!$A:$N,S$2,FALSE))," ") | C10: =_xlfn.IFNA(IF(VLOOKUP($B$1&$A10,'4.1 关键词原始数据'!$A:$N,T$2,FALSE)=0," ",VLOOKUP($B$1&$A10,'4.1 关键词原始数据'!$A:$N,T$2,FALSE))," ") | D10: =_xlfn.IFNA(IF(VLOOKUP($B$1&$A10,'4.1 关键词原始数据'!$A:$N,U$2,FALSE)=0," ",VLOOKUP($B$1&$A10,'4.1 关键词原始数据'!$A:$N,U$2,FALSE))," ") | E10: =_xlfn.IFNA(IF(VLOOKUP($B$1&$A10,'4.1 关键词原始数据'!$A:$N,V$2,FALSE)=0," ",VLOOKUP($B$1&$A10,'4.1 关键词原始数据'!$A:$N,V$2,FALSE))," ") | F10: =_xlfn.IFNA(IF(VLOOKUP($B$1&$A10,'4.1 关键词原始数据'!$A:$N,W$2,FALSE)=0," ",VLOOKUP($B$1&$A10,'4.1 关键词原始数据'!$A:$N,W$2,FALSE))," ") | G10: =_xlfn.IFNA(IF(VLOOKUP($B$1&$A10,'4.1 关键词原始数据'!$A:$N,X$2,FALSE)=0," ",VLOOKUP($B$1&$A10,'4.1 关键词原始数据'!$A:$N,X$2,FALSE))," ") | H10: =_xlfn.IFNA(IF(VLOOKUP($B$1&$A10,'4.1 关键词原始数据'!$A:$N,Y$2,FALSE)=0," ",VLOOKUP($B$1&$A10,'4.1 关键词原始数据'!$A:$N,Y$2,FALSE))," ") | I10: =_xlfn.IFNA(IF(VLOOKUP($B$1&$A10,'4.1 关键词原始数据'!$A:$N,Z$2,FALSE)=0," ",VLOOKUP($B$1&$A10,'4.1 关键词原始数据'!$A:$N,Z$2,FALSE))," ") | J10: =_xlfn.IFNA(IF(VLOOKUP($J$1&$A10,'4.1 关键词原始数据'!$A:$N,S$2,FALSE)=0," ",VLOOKUP($J$1&$A10,'4.1 关键词原始数据'!$A:$N,S$2,FALSE))," ") | K10: =_xlfn.IFNA(IF(VLOOKUP($J$1&$A10,'4.1 关键词原始数据'!$A:$N,T$2,FALSE)=0," ",VLOOKUP($J$1&$A10,'4.1 关键词原始数据'!$A:$N,T$2,FALSE))," ") | L10: =_xlfn.IFNA(IF(VLOOKUP($J$1&$A10,'4.1 关键词原始数据'!$A:$N,U$2,FALSE)=0," ",VLOOKUP($J$1&$A10,'4.1 关键词原始数据'!$A:$N,U$2,FALSE))," ") | M10: =_xlfn.IFNA(IF(VLOOKUP($J$1&$A10,'4.1 关键词原始数据'!$A:$N,V$2,FALSE)=0," ",VLOOKUP($J$1&$A10,'4.1 关键词原始数据'!$A:$N,V$2,FALSE))," ") | N10: =_xlfn.IFNA(IF(VLOOKUP($J$1&$A10,'4.1 关键词原始数据'!$A:$N,W$2,FALSE)=0," ",VLOOKUP($J$1&$A10,'4.1 关键词原始数据'!$A:$N,W$2,FALSE))," ") | O10: =_xlfn.IFNA(IF(VLOOKUP($J$1&$A10,'4.1 关键词原始数据'!$A:$N,X$2,FALSE)=0," ",VLOOKUP($J$1&$A10,'4.1 关键词原始数据'!$A:$N,X$2,FALSE))," ") | P10: =_xlfn.IFNA(IF(VLOOKUP($J$1&$A10,'4.1 关键词原始数据'!$A:$N,Y$2,FALSE)=0," ",VLOOKUP($J$1&$A10,'4.1 关键词原始数据'!$A:$N,Y$2,FALSE))," ") | Q10: =_xlfn.IFNA(IF(VLOOKUP($J$1&$A10,'4.1 关键词原始数据'!$A:$N,Z$2,FALSE)=0," ",VLOOKUP($J$1&$A10,'4.1 关键词原始数据'!$A:$N,Z$2,FALSE))," ")
A11: 9月3日上午 | B11: =_xlfn.IFNA(IF(VLOOKUP($B$1&$A11,'4.1 关键词原始数据'!$A:$N,S$2,FALSE)=0," ",VLOOKUP($B$1&$A11,'4.1 关键词原始数据'!$A:$N,S$2,FALSE))," ") | C11: =_xlfn.IFNA(IF(VLOOKUP($B$1&$A11,'4.1 关键词原始数据'!$A:$N,T$2,FALSE)=0," ",VLOOKUP($B$1&$A11,'4.1 关键词原始数据'!$A:$N,T$2,FALSE))," ") -> 3-12-4 | D11: =_xlfn.IFNA(IF(VLOOKUP($B$1&$A11,'4.1 关键词原始数据'!$A:$N,U$2,FALSE)=0," ",VLOOKUP($B$1&$A11,'4.1 关键词原始数据'!$A:$N,U$2,FALSE))," ") | E11: =_xlfn.IFNA(IF(VLOOKUP($B$1&$A11,'4.1 关键词原始数据'!$A:$N,V$2,FALSE)=0," ",VLOOKUP($B$1&$A11,'4.1 关键词原始数据'!$A:$N,V$2,FALSE))," ") | F11: =_xlfn.IFNA(IF(VLOOKUP($B$1&$A11,'4.1 关键词原始数据'!$A:$N,W$2,FALSE)=0," ",VLOOKUP($B$1&$A11,'4.1 关键词原始数据'!$A:$N,W$2,FALSE))," ") | G11: =_xlfn.IFNA(IF(VLOOKUP($B$1&$A11,'4.1 关键词原始数据'!$A:$N,X$2,FALSE)=0," ",VLOOKUP($B$1&$A11,'4.1 关键词原始数据'!$A:$N,X$2,FALSE))," ") -> 1-16-4 | H11: =_xlfn.IFNA(IF(VLOOKUP($B$1&$A11,'4.1 关键词原始数据'!$A:$N,Y$2,FALSE)=0," ",VLOOKUP($B$1&$A11,'4.1 关键词原始数据'!$A:$N,Y$2,FALSE))," ") | I11: =_xlfn.IFNA(IF(VLOOKUP($B$1&$A11,'4.1 关键词原始数据'!$A:$N,Z$2,FALSE)=0," ",VLOOKUP($B$1&$A11,'4.1 关键词原始数据'!$A:$N,Z$2,FALSE))," ") | J11: =_xlfn.IFNA(IF(VLOOKUP($J$1&$A11,'4.1 关键词原始数据'!$A:$N,S$2,FALSE)=0," ",VLOOKUP($J$1&$A11,'4.1 关键词原始数据'!$A:$N,S$2,FALSE))," ") | K11: =_xlfn.IFNA(IF(VLOOKUP($J$1&$A11,'4.1 关键词原始数据'!$A:$N,T$2,FALSE)=0," ",VLOOKUP($J$1&$A11,'4.1 关键词原始数据'!$A:$N,T$2,FALSE))," ") | L11: =_xlfn.IFNA(IF(VLOOKUP($J$1&$A11,'4.1 关键词原始数据'!$A:$N,U$2,FALSE)=0," ",VLOOKUP($J$1&$A11,'4.1 关键词原始数据'!$A:$N,U$2,FALSE))," ") | M11: =_xlfn.IFNA(IF(VLOOKUP($J$1&$A11,'4.1 关键词原始数据'!$A:$N,V$2,FALSE)=0," ",VLOOKUP($J$1&$A11,'4.1 关键词原始数据'!$A:$N,V$2,FALSE))," ") -> 4-12-4 | N11: =_xlfn.IFNA(IF(VLOOKUP($J$1&$A11,'4.1 关键词原始数据'!$A:$N,W$2,FALSE)=0," ",VLOOKUP($J$1&$A11,'4.1 关键词原始数据'!$A:$N,W$2,FALSE))," ") | O11: =_xlfn.IFNA(IF(VLOOKUP($J$1&$A11,'4.1 关键词原始数据'!$A:$N,X$2,FALSE)=0," ",VLOOKUP($J$1&$A11,'4.1 关键词原始数据'!$A:$N,X$2,FALSE))," ") | P11: =_xlfn.IFNA(IF(VLOOKUP($J$1&$A11,'4.1 关键词原始数据'!$A:$N,Y$2,FALSE)=0," ",VLOOKUP($J$1&$A11,'4.1 关键词原始数据'!$A:$N,Y$2,FALSE))," ") | Q11: =_xlfn.IFNA(IF(VLOOKUP($J$1&$A11,'4.1 关键词原始数据'!$A:$N,Z$2,FALSE)=0," ",VLOOKUP($J$1&$A11,'4.1 关键词原始数据'!$A:$N,Z$2,FALSE))," ")
A12: 9月4日晚上 | B12: =_xlfn.IFNA(IF(VLOOKUP($B$1&$A12,'4.1 关键词原始数据'!$A:$N,S$2,FALSE)=0," ",VLOOKUP($B$1&$A12,'4.1 关键词原始数据'!$A:$N,S$2,FALSE))," ") | C12: =_xlfn.IFNA(IF(VLOOKUP($B$1&$A12,'4.1 关键词原始数据'!$A:$N,T$2,FALSE)=0," ",VLOOKUP($B$1&$A12,'4.1 关键词原始数据'!$A:$N,T$2,FALSE))," ") | D12: =_xlfn.IFNA(IF(VLOOKUP($B$1&$A12,'4.1 关键词原始数据'!$A:$N,U$2,FALSE)=0," ",VLOOKUP($B$1&$A12,'4.1 关键词原始数据'!$A:$N,U$2,FALSE))," ") | E12: =_xlfn.IFNA(IF(VLOOKUP($B$1&$A12,'4.1 关键词原始数据'!$A:$N,V$2,FALSE)=0," ",VLOOKUP($B$1&$A12,'4.1 关键词原始数据'!$A:$N,V$2,FALSE))," ") | F12: =_xlfn.IFNA(IF(VLOOKUP($B$1&$A12,'4.1 关键词原始数据'!$A:$N,W$2,FALSE)=0," ",VLOOKUP($B$1&$A12,'4.1 关键词原始数据'!$A:$N,W$2,FALSE))," ") | G12: =_xlfn.IFNA(IF(VLOOKUP($B$1&$A12,'4.1 关键词原始数据'!$A:$N,X$2,FALSE)=0," ",VLOOKUP($B$1&$A12,'4.1 关键词原始数据'!$A:$N,X$2,FALSE))," ") | H12: =_xlfn.IFNA(IF(VLOOKUP($B$1&$A12,'4.1 关键词原始数据'!$A:$N,Y$2,FALSE)=0," ",VLOOKUP($B$1&$A12,'4.1 关键词原始数据'!$A:$N,Y$2,FALSE))," ") | I12: =_xlfn.IFNA(IF(VLOOKUP($B$1&$A12,'4.1 关键词原始数据'!$A:$N,Z$2,FALSE)=0," ",VLOOKUP($B$1&$A12,'4.1 关键词原始数据'!$A:$N,Z$2,FALSE))," ") | J12: =_xlfn.IFNA(IF(VLOOKUP($J$1&$A12,'4.1 关键词原始数据'!$A:$N,S$2,FALSE)=0," ",VLOOKUP($J$1&$A12,'4.1 关键词原始数据'!$A:$N,S$2,FALSE))," ") | K12: =_xlfn.IFNA(IF(VLOOKUP($J$1&$A12,'4.1 关键词原始数据'!$A:$N,T$2,FALSE)=0," ",VLOOKUP($J$1&$A12,'4.1 关键词原始数据'!$A:$N,T$2,FALSE))," ") | L12: =_xlfn.IFNA(IF(VLOOKUP($J$1&$A12,'4.1 关键词原始数据'!$A:$N,U$2,FALSE)=0," ",VLOOKUP($J$1&$A12,'4.1 关键词原始数据'!$A:$N,U$2,FALSE))," ") | M12: =_xlfn.IFNA(IF(VLOOKUP($J$1&$A12,'4.1 关键词原始数据'!$A:$N,V$2,FALSE)=0," ",VLOOKUP($J$1&$A12,'4.1 关键词原始数据'!$A:$N,V$2,FALSE))," ") | N12: =_xlfn.IFNA(IF(VLOOKUP($J$1&$A12,'4.1 关键词原始数据'!$A:$N,W$2,FALSE)=0," ",VLOOKUP($J$1&$A12,'4.1 关键词原始数据'!$A:$N,W$2,FALSE))," ") | O12: =_xlfn.IFNA(IF(VLOOKUP($J$1&$A12,'4.1 关键词原始数据'!$A:$N,X$2,FALSE)=0," ",VLOOKUP($J$1&$A12,'4.1 关键词原始数据'!$A:$N,X$2,FALSE))," ") | P12: =_xlfn.IFNA(IF(VLOOKUP($J$1&$A12,'4.1 关键词原始数据'!$A:$N,Y$2,FALSE)=0," ",VLOOKUP($J$1&$A12,'4.1 关键词原始数据'!$A:$N,Y$2,FALSE))," ") | Q12: =_xlfn.IFNA(IF(VLOOKUP($J$1&$A12,'4.1 关键词原始数据'!$A:$N,Z$2,FALSE)=0," ",VLOOKUP($J$1&$A12,'4.1 关键词原始数据'!$A:$N,Z$2,FALSE))," ")
A13: 9月5日上午 | B13: =_xlfn.IFNA(IF(VLOOKUP($B$1&$A13,'4.1 关键词原始数据'!$A:$N,S$2,FALSE)=0," ",VLOOKUP($B$1&$A13,'4.1 关键词原始数据'!$A:$N,S$2,FALSE))," ") | C13: =_xlfn.IFNA(IF(VLOOKUP($B$1&$A13,'4.1 关键词原始数据'!$A:$N,T$2,FALSE)=0," ",VLOOKUP($B$1&$A13,'4.1 关键词原始数据'!$A:$N,T$2,FALSE))," ") -> 3-11-1 | D13: =_xlfn.IFNA(IF(VLOOKUP($B$1&$A13,'4.1 关键词原始数据'!$A:$N,U$2,FALSE)=0," ",VLOOKUP($B$1&$A13,'4.1 关键词原始数据'!$A:$N,U$2,FALSE))," ") | E13: =_xlfn.IFNA(IF(VLOOKUP($B$1&$A13,'4.1 关键词原始数据'!$A:$N,V$2,FALSE)=0," ",VLOOKUP($B$1&$A13,'4.1 关键词原始数据'!$A:$N,V$2,FALSE))," ") -> 5-11-2 | F13: =_xlfn.IFNA(IF(VLOOKUP($B$1&$A13,'4.1 关键词原始数据'!$A:$N,W$2,FALSE)=0," ",VLOOKUP($B$1&$A13,'4.1 关键词原始数据'!$A:$N,W$2,FALSE))," ") | G13: =_xlfn.IFNA(IF(VLOOKUP($B$1&$A13,'4.1 关键词原始数据'!$A:$N,X$2,FALSE)=0," ",VLOOKUP($B$1&$A13,'4.1 关键词原始数据'!$A:$N,X$2,FALSE))," ") -> 1-17-4 | H13: =_xlfn.IFNA(IF(VLOOKUP($B$1&$A13,'4.1 关键词原始数据'!$A:$N,Y$2,FALSE)=0," ",VLOOKUP($B$1&$A13,'4.1 关键词原始数据'!$A:$N,Y$2,FALSE))," ") | I13: =_xlfn.IFNA(IF(VLOOKUP($B$1&$A13,'4.1 关键词原始数据'!$A:$N,Z$2,FALSE)=0," ",VLOOKUP($B$1&$A13,'4.1 关键词原始数据'!$A:$N,Z$2,FALSE))," ") | J13: =_xlfn.IFNA(IF(VLOOKUP($J$1&$A13,'4.1 关键词原始数据'!$A:$N,S$2,FALSE)=0," ",VLOOKUP($J$1&$A13,'4.1 关键词原始数据'!$A:$N,S$2,FALSE))," ") | K13: =_xlfn.IFNA(IF(VLOOKUP($J$1&$A13,'4.1 关键词原始数据'!$A:$N,T$2,FALSE)=0," ",VLOOKUP($J$1&$A13,'4.1 关键词原始数据'!$A:$N,T$2,FALSE))," ") | L13: =_xlfn.IFNA(IF(VLOOKUP($J$1&$A13,'4.1 关键词原始数据'!$A:$N,U$2,FALSE)=0," ",VLOOKUP($J$1&$A13,'4.1 关键词原始数据'!$A:$N,U$2,FALSE))," ") | M13: =_xlfn.IFNA(IF(VLOOKUP($J$1&$A13,'4.1 关键词原始数据'!$A:$N,V$2,FALSE)=0," ",VLOOKUP($J$1&$A13,'4.1 关键词原始数据'!$A:$N,V$2,FALSE))," ") | N13: =_xlfn.IFNA(IF(VLOOKUP($J$1&$A13,'4.1 关键词原始数据'!$A:$N,W$2,FALSE)=0," ",VLOOKUP($J$1&$A13,'4.1 关键词原始数据'!$A:$N,W$2,FALSE))," ") | O13: =_xlfn.IFNA(IF(VLOOKUP($J$1&$A13,'4.1 关键词原始数据'!$A:$N,X$2,FALSE)=0," ",VLOOKUP($J$1&$A13,'4.1 关键词原始数据'!$A:$N,X$2,FALSE))," ") | P13: =_xlfn.IFNA(IF(VLOOKUP($J$1&$A13,'4.1 关键词原始数据'!$A:$N,Y$2,FALSE)=0," ",VLOOKUP($J$1&$A13,'4.1 关键词原始数据'!$A:$N,Y$2,FALSE))," ") | Q13: =_xlfn.IFNA(IF(VLOOKUP($J$1&$A13,'4.1 关键词原始数据'!$A:$N,Z$2,FALSE)=0," ",VLOOKUP($J$1&$A13,'4.1 关键词原始数据'!$A:$N,Z$2,FALSE))," ")
A14: 9月6日晚上 | B14: =_xlfn.IFNA(IF(VLOOKUP($B$1&$A14,'4.1 关键词原始数据'!$A:$N,S$2,FALSE)=0," ",VLOOKUP($B$1&$A14,'4.1 关键词原始数据'!$A:$N,S$2,FALSE))," ") | C14: =_xlfn.IFNA(IF(VLOOKUP($B$1&$A14,'4.1 关键词原始数据'!$A:$N,T$2,FALSE)=0," ",VLOOKUP($B$1&$A14,'4.1 关键词原始数据'!$A:$N,T$2,FALSE))," ") | D14: =_xlfn.IFNA(IF(VLOOKUP($B$1&$A14,'4.1 关键词原始数据'!$A:$N,U$2,FALSE)=0," ",VLOOKUP($B$1&$A14,'4.1 关键词原始数据'!$A:$N,U$2,FALSE))," ") | E14: =_xlfn.IFNA(IF(VLOOKUP($B$1&$A14,'4.1 关键词原始数据'!$A:$N,V$2,FALSE)=0," ",VLOOKUP($B$1&$A14,'4.1 关键词原始数据'!$A:$N,V$2,FALSE))," ") | F14: =_xlfn.IFNA(IF(VLOOKUP($B$1&$A14,'4.1 关键词原始数据'!$A:$N,W$2,FALSE)=0," ",VLOOKUP($B$1&$A14,'4.1 关键词原始数据'!$A:$N,W$2,FALSE))," ") | G14: =_xlfn.IFNA(IF(VLOOKUP($B$1&$A14,'4.1 关键词原始数据'!$A:$N,X$2,FALSE)=0," ",VLOOKUP($B$1&$A14,'4.1 关键词原始数据'!$A:$N,X$2,FALSE))," ") | H14: =_xlfn.IFNA(IF(VLOOKUP($B$1&$A14,'4.1 关键词原始数据'!$A:$N,Y$2,FALSE)=0," ",VLOOKUP($B$1&$A14,'4.1 关键词原始数据'!$A:$N,Y$2,FALSE))," ") | I14: =_xlfn.IFNA(IF(VLOOKUP($B$1&$A14,'4.1 关键词原始数据'!$A:$N,Z$2,FALSE)=0," ",VLOOKUP($B$1&$A14,'4.1 关键词原始数据'!$A:$N,Z$2,FALSE))," ") | J14: =_xlfn.IFNA(IF(VLOOKUP($J$1&$A14,'4.1 关键词原始数据'!$A:$N,S$2,FALSE)=0," ",VLOOKUP($J$1&$A14,'4.1 关键词原始数据'!$A:$N,S$2,FALSE))," ") | K14: =_xlfn.IFNA(IF(VLOOKUP($J$1&$A14,'4.1 关键词原始数据'!$A:$N,T$2,FALSE)=0," ",VLOOKUP($J$1&$A14,'4.1 关键词原始数据'!$A:$N,T$2,FALSE))," ") | L14: =_xlfn.IFNA(IF(VLOOKUP($J$1&$A14,'4.1 关键词原始数据'!$A:$N,U$2,FALSE)=0," ",VLOOKUP($J$1&$A14,'4.1 关键词原始数据'!$A:$N,U$2,FALSE))," ") | M14: =_xlfn.IFNA(IF(VLOOKUP($J$1&$A14,'4.1 关键词原始数据'!$A:$N,V$2,FALSE)=0," ",VLOOKUP($J$1&$A14,'4.1 关键词原始数据'!$A:$N,V$2,FALSE))," ") | N14: =_xlfn.IFNA(IF(VLOOKUP($J$1&$A14,'4.1 关键词原始数据'!$A:$N,W$2,FALSE)=0," ",VLOOKUP($J$1&$A14,'4.1 关键词原始数据'!$A:$N,W$2,FALSE))," ") | O14: =_xlfn.IFNA(IF(VLOOKUP($J$1&$A14,'4.1 关键词原始数据'!$A:$N,X$2,FALSE)=0," ",VLOOKUP($J$1&$A14,'4.1 关键词原始数据'!$A:$N,X$2,FALSE))," ") | P14: =_xlfn.IFNA(IF(VLOOKUP($J$1&$A14,'4.1 关键词原始数据'!$A:$N,Y$2,FALSE)=0," ",VLOOKUP($J$1&$A14,'4.1 关键词原始数据'!$A:$N,Y$2,FALSE))," ") | Q14: =_xlfn.IFNA(IF(VLOOKUP($J$1&$A14,'4.1 关键词原始数据'!$A:$N,Z$2,FALSE)=0," ",VLOOKUP($J$1&$A14,'4.1 关键词原始数据'!$A:$N,Z$2,FALSE))," ")
A15: 9月7日上午 | B15: =_xlfn.IFNA(IF(VLOOKUP($B$1&$A15,'4.1 关键词原始数据'!$A:$N,S$2,FALSE)=0," ",VLOOKUP($B$1&$A15,'4.1 关键词原始数据'!$A:$N,S$2,FALSE))," ") | C15: =_xlfn.IFNA(IF(VLOOKUP($B$1&$A15,'4.1 关键词原始数据'!$A:$N,T$2,FALSE)=0," ",VLOOKUP($B$1&$A15,'4.1 关键词原始数据'!$A:$N,T$2,FALSE))," ") -> 3-12-3 | D15: =_xlfn.IFNA(IF(VLOOKUP($B$1&$A15,'4.1 关键词原始数据'!$A:$N,U$2,FALSE)=0," ",VLOOKUP($B$1&$A15,'4.1 关键词原始数据'!$A:$N,U$2,FALSE))," ") | E15: =_xlfn.IFNA(IF(VLOOKUP($B$1&$A15,'4.1 关键词原始数据'!$A:$N,V$2,FALSE)=0," ",VLOOKUP($B$1&$A15,'4.1 关键词原始数据'!$A:$N,V$2,FALSE))," ") | F15: =_xlfn.IFNA(IF(VLOOKUP($B$1&$A15,'4.1 关键词原始数据'!$A:$N,W$2,FALSE)=0," ",VLOOKUP($B$1&$A15,'4.1 关键词原始数据'!$A:$N,W$2,FALSE))," ") | G15: =_xlfn.IFNA(IF(VLOOKUP($B$1&$A15,'4.1 关键词原始数据'!$A:$N,X$2,FALSE)=0," ",VLOOKUP($B$1&$A15,'4.1 关键词原始数据'!$A:$N,X$2,FALSE))," ") -> 2-3-1 | H15: =_xlfn.IFNA(IF(VLOOKUP($B$1&$A15,'4.1 关键词原始数据'!$A:$N,Y$2,FALSE)=0," ",VLOOKUP($B$1&$A15,'4.1 关键词原始数据'!$A:$N,Y$2,FALSE))," ") | I15: =_xlfn.IFNA(IF(VLOOKUP($B$1&$A15,'4.1 关键词原始数据'!$A:$N,Z$2,FALSE)=0," ",VLOOKUP($B$1&$A15,'4.1 关键词原始数据'!$A:$N,Z$2,FALSE))," ") | J15: =_xlfn.IFNA(IF(VLOOKUP($J$1&$A15,'4.1 关键词原始数据'!$A:$N,S$2,FALSE)=0," ",VLOOKUP($J$1&$A15,'4.1 关键词原始数据'!$A:$N,S$2,FALSE))," ") | K15: =_xlfn.IFNA(IF(VLOOKUP($J$1&$A15,'4.1 关键词原始数据'!$A:$N,T$2,FALSE)=0," ",VLOOKUP($J$1&$A15,'4.1 关键词原始数据'!$A:$N,T$2,FALSE))," ") | L15: =_xlfn.IFNA(IF(VLOOKUP($J$1&$A15,'4.1 关键词原始数据'!$A:$N,U$2,FALSE)=0," ",VLOOKUP($J$1&$A15,'4.1 关键词原始数据'!$A:$N,U$2,FALSE))," ") | M15: =_xlfn.IFNA(IF(VLOOKUP($J$1&$A15,'4.1 关键词原始数据'!$A:$N,V$2,FALSE)=0," ",VLOOKUP($J$1&$A15,'4.1 关键词原始数据'!$A:$N,V$2,FALSE))," ") -> 4-4-4 | N15: =_xlfn.IFNA(IF(VLOOKUP($J$1&$A15,'4.1 关键词原始数据'!$A:$N,W$2,FALSE)=0," ",VLOOKUP($J$1&$A15,'4.1 关键词原始数据'!$A:$N,W$2,FALSE))," ") | O15: =_xlfn.IFNA(IF(VLOOKUP($J$1&$A15,'4.1 关键词原始数据'!$A:$N,X$2,FALSE)=0," ",VLOOKUP($J$1&$A15,'4.1 关键词原始数据'!$A:$N,X$2,FALSE))," ") | P15: =_xlfn.IFNA(IF(VLOOKUP($J$1&$A15,'4.1 关键词原始数据'!$A:$N,Y$2,FALSE)=0," ",VLOOKUP($J$1&$A15,'4.1 关键词原始数据'!$A:$N,Y$2,FALSE))," ") | Q15: =_xlfn.IFNA(IF(VLOOKUP($J$1&$A15,'4.1 关键词原始数据'!$A:$N,Z$2,FALSE)=0," ",VLOOKUP($J$1&$A15,'4.1 关键词原始数据'!$A:$N,Z$2,FALSE))," ")
A16: 9月7日晚上 | B16: =_xlfn.IFNA(IF(VLOOKUP($B$1&$A16,'4.1 关键词原始数据'!$A:$N,S$2,FALSE)=0," ",VLOOKUP($B$1&$A16,'4.1 关键词原始数据'!$A:$N,S$2,FALSE))," ") | C16: =_xlfn.IFNA(IF(VLOOKUP($B$1&$A16,'4.1 关键词原始数据'!$A:$N,T$2,FALSE)=0," ",VLOOKUP($B$1&$A16,'4.1 关键词原始数据'!$A:$N,T$2,FALSE))," ") | D16: =_xlfn.IFNA(IF(VLOOKUP($B$1&$A16,'4.1 关键词原始数据'!$A:$N,U$2,FALSE)=0," ",VLOOKUP($B$1&$A16,'4.1 关键词原始数据'!$A:$N,U$2,FALSE))," ") | E16: =_xlfn.IFNA(IF(VLOOKUP($B$1&$A16,'4.1 关键词原始数据'!$A:$N,V$2,FALSE)=0," ",VLOOKUP($B$1&$A16,'4.1 关键词原始数据'!$A:$N,V$2,FALSE))," ") | F16: =_xlfn.IFNA(IF(VLOOKUP($B$1&$A16,'4.1 关键词原始数据'!$A:$N,W$2,FALSE)=0," ",VLOOKUP($B$1&$A16,'4.1 关键词原始数据'!$A:$N,W$2,FALSE))," ") | G16: =_xlfn.IFNA(IF(VLOOKUP($B$1&$A16,'4.1 关键词原始数据'!$A:$N,X$2,FALSE)=0," ",VLOOKUP($B$1&$A16,'4.1 关键词原始数据'!$A:$N,X$2,FALSE))," ") | H16: =_xlfn.IFNA(IF(VLOOKUP($B$1&$A16,'4.1 关键词原始数据'!$A:$N,Y$2,FALSE)=0," ",VLOOKUP($B$1&$A16,'4.1 关键词原始数据'!$A:$N,Y$2,FALSE))," ") | I16: =_xlfn.IFNA(IF(VLOOKUP($B$1&$A16,'4.1 关键词原始数据'!$A:$N,Z$2,FALSE)=0," ",VLOOKUP($B$1&$A16,'4.1 关键词原始数据'!$A:$N,Z$2,FALSE))," ") | J16: =_xlfn.IFNA(IF(VLOOKUP($J$1&$A16,'4.1 关键词原始数据'!$A:$N,S$2,FALSE)=0," ",VLOOKUP($J$1&$A16,'4.1 关键词原始数据'!$A:$N,S$2,FALSE))," ") | K16: =_xlfn.IFNA(IF(VLOOKUP($J$1&$A16,'4.1 关键词原始数据'!$A:$N,T$2,FALSE)=0," ",VLOOKUP($J$1&$A16,'4.1 关键词原始数据'!$A:$N,T$2,FALSE))," ") | L16: =_xlfn.IFNA(IF(VLOOKUP($J$1&$A16,'4.1 关键词原始数据'!$A:$N,U$2,FALSE)=0," ",VLOOKUP($J$1&$A16,'4.1 关键词原始数据'!$A:$N,U$2,FALSE))," ") | M16: =_xlfn.IFNA(IF(VLOOKUP($J$1&$A16,'4.1 关键词原始数据'!$A:$N,V$2,FALSE)=0," ",VLOOKUP($J$1&$A16,'4.1 关键词原始数据'!$A:$N,V$2,FALSE))," ") | N16: =_xlfn.IFNA(IF(VLOOKUP($J$1&$A16,'4.1 关键词原始数据'!$A:$N,W$2,FALSE)=0," ",VLOOKUP($J$1&$A16,'4.1 关键词原始数据'!$A:$N,W$2,FALSE))," ") | O16: =_xlfn.IFNA(IF(VLOOKUP($J$1&$A16,'4.1 关键词原始数据'!$A:$N,X$2,FALSE)=0," ",VLOOKUP($J$1&$A16,'4.1 关键词原始数据'!$A:$N,X$2,FALSE))," ") | P16: =_xlfn.IFNA(IF(VLOOKUP($J$1&$A16,'4.1 关键词原始数据'!$A:$N,Y$2,FALSE)=0," ",VLOOKUP($J$1&$A16,'4.1 关键词原始数据'!$A:$N,Y$2,FALSE))," ") | Q16: =_xlfn.IFNA(IF(VLOOKUP($J$1&$A16,'4.1 关键词原始数据'!$A:$N,Z$2,FALSE)=0," ",VLOOKUP($J$1&$A16,'4.1 关键词原始数据'!$A:$N,Z$2,FALSE))," ")
... A84: 10月15日上午 | B84: =_xlfn.IFNA(IF(VLOOKUP($B$1&$A84,'4.1 关键词原始数据'!$A:$N,S$2,FALSE)=0," ",VLOOKUP($B$1&$A84,'4.1 关键词原始数据'!$A:$N,S$2,FALSE))," ") | C84: =_xlfn.IFNA(IF(VLOOKUP($B$1&$A84,'4.1 关键词原始数据'!$A:$N,T$2,FALSE)=0," ",VLOOKUP($B$1&$A84,'4.1 关键词原始数据'!$A:$N,T$2,FALSE))," ") | D84: =_xlfn.IFNA(IF(VLOOKUP($B$1&$A84,'4.1 关键词原始数据'!$A:$N,U$2,FALSE)=0," ",VLOOKUP($B$1&$A84,'4.1 关键词原始数据'!$A:$N,U$2,FALSE))," ") | E84: =_xlfn.IFNA(IF(VLOOKUP($B$1&$A84,'4.1 关键词原始数据'!$A:$N,V$2,FALSE)=0," ",VLOOKUP($B$1&$A84,'4.1 关键词原始数据'!$A:$N,V$2,FALSE))," ") | F84: =_xlfn.IFNA(IF(VLOOKUP($B$1&$A84,'4.1 关键词原始数据'!$A:$N,W$2,FALSE)=0," ",VLOOKUP($B$1&$A84,'4.1 关键词原始数据'!$A:$N,W$2,FALSE))," ") | G84: =_xlfn.IFNA(IF(VLOOKUP($B$1&$A84,'4.1 关键词原始数据'!$A:$N,X$2,FALSE)=0," ",VLOOKUP($B$1&$A84,'4.1 关键词原始数据'!$A:$N,X$2,FALSE))," ") -> 5-3-1 | H84: =_xlfn.IFNA(IF(VLOOKUP($B$1&$A84,'4.1 关键词原始数据'!$A:$N,Y$2,FALSE)=0," ",VLOOKUP($B$1&$A84,'4.1 关键词原始数据'!$A:$N,Y$2,FALSE))," ") | I84: =_xlfn.IFNA(IF(VLOOKUP($B$1&$A84,'4.1 关键词原始数据'!$A:$N,Z$2,FALSE)=0," ",VLOOKUP($B$1&$A84,'4.1 关键词原始数据'!$A:$N,Z$2,FALSE))," ") | J84: =_xlfn.IFNA(IF(VLOOKUP($J$1&$A84,'4.1 关键词原始数据'!$A:$N,S$2,FALSE)=0," ",VLOOKUP($J$1&$A84,'4.1 关键词原始数据'!$A:$N,S$2,FALSE))," ") | K84: =_xlfn.IFNA(IF(VLOOKUP($J$1&$A84,'4.1 关键词原始数据'!$A:$N,T$2,FALSE)=0," ",VLOOKUP($J$1&$A84,'4.1 关键词原始数据'!$A:$N,T$2,FALSE))," ") | L84: =_xlfn.IFNA(IF(VLOOKUP($J$1&$A84,'4.1 关键词原始数据'!$A:$N,U$2,FALSE)=0," ",VLOOKUP($J$1&$A84,'4.1 关键词原始数据'!$A:$N,U$2,FALSE))," ") | M84: =_xlfn.IFNA(IF(VLOOKUP($J$1&$A84,'4.1 关键词原始数据'!$A:$N,V$2,FALSE)=0," ",VLOOKUP($J$1&$A84,'4.1 关键词原始数据'!$A:$N,V$2,FALSE))," ") -> 4-2-2 | N84: =_xlfn.IFNA(IF(VLOOKUP($J$1&$A84,'4.1 关键词原始数据'!$A:$N,W$2,FALSE)=0," ",VLOOKUP($J$1&$A84,'4.1 关键词原始数据'!$A:$N,W$2,FALSE))," ") -> 1-1-1 | O84: =_xlfn.IFNA(IF(VLOOKUP($J$1&$A84,'4.1 关键词原始数据'!$A:$N,X$2,FALSE)=0," ",VLOOKUP($J$1&$A84,'4.1 关键词原始数据'!$A:$N,X$2,FALSE))," ") | P84: =_xlfn.IFNA(IF(VLOOKUP($J$1&$A84,'4.1 关键词原始数据'!$A:$N,Y$2,FALSE)=0," ",VLOOKUP($J$1&$A84,'4.1 关键词原始数据'!$A:$N,Y$2,FALSE))," ") | Q84: =_xlfn.IFNA(IF(VLOOKUP($J$1&$A84,'4.1 关键词原始数据'!$A:$N,Z$2,FALSE)=0," ",VLOOKUP($J$1&$A84,'4.1 关键词原始数据'!$A:$N,Z$2,FALSE))," ")
A85: 10月15日晚上

Sheet 3.3 广告数据
A1: 分析指南 | B1: 1、发现问题：整体数据是否正常且符合预期，对主推SKU做重点分析，次推SKU做简要总结（花费、展示位置、搜索词、是否有特殊情况等） 2、业务优化：广告结构是否需要进行一定的优化？ 3、数据跟踪：后续应当关注哪些重点指标？（如关键词排序、曝光量、曝光位置等） 4、展示位、搜索词等辅助信息，在分析时如果需要再截取，不要每个SKU每个广告组都截
A2: 主推款SKU | B2: XXXX-111 | C2: ASIN | D2: ASIN1 | E2: 主图 | I2: 次推款SKU | J2: XXXX-222 | K2: ASIN | L2: ASIN2 | M2: 主图
A3: 日期 | B3: 广告总花费 | C3: 广告展示量 | D3: 广告点击量 | E3: 广告点击率 | F3: 广告订单量 | G3: 广告转化率 | I3: 日期 | J3: 广告总花费 | K3: 广告展示量 | L3: 广告点击量 | M3: 广告点击率 | N3: 广告订单量 | O3: 广告转化率
A4: 2026-08-23 | I4: 2026-08-23
A5: 2026-08-24 | I5: 2026-08-24
A6: 2026-08-25 | I6: 2026-08-25
A7: 2026-08-26 | I7: 2026-08-26
A8: 2026-08-27 | I8: 2026-08-27
A9: 2026-08-28 | I9: 2026-08-28
A10: 2026-08-29 | I10: 2026-08-29
A11: 2026-08-30 | I11: 2026-08-30
A12: 2026-08-31 | I12: 2026-08-31
A13: 2026-09-1 | I13: 2026-09-1
A14: 2026-09-2 | I14: 2026-09-2
A15: 2026-09-3 | I15: 2026-09-3
... A36: 2026-09-24 | I36: 2026-09-24
A222: MYTD-157

Sheet 4.1 关键词原始数据
B1: 品牌 | C1: 产品系列 | D1: 款式 | E1: SKU | G1: 关键词排序
G2: 关键词1 | I2: 关键词2 | K2: 关键词3 | M2: 关键词4
A3: 辅助标识 | F3: 日期 | G3: 广告位 | H3: 自然位 | I3: 广告位 | J3: 自然位 | K3: 广告位 | L3: 自然位 | M3: 广告位 | N3: 自然位
A4: =E4&F4 -> XXXX-1118月31日上午 | E4: XXXX-111 | F4: 8月31日上午 | H4: 3-7-2 | L4: 1-17-1
A5: =E5&F5 -> XXXX-2228月31日上午 | E5: XXXX-222 | F5: 8月31日上午
A6: =E6&F6 -> 8月31日上午 | F6: 8月31日上午
A7: =E7&F7 -> 8月31日上午 | F7: 8月31日上午 | J7: 6-12-3
A8: =E8&F8 -> 8月31日上午 | F8: 8月31日上午
A9: =E9&F9 -> 8月31日上午 | F9: 8月31日上午
A10: =E10&F10 -> 8月31日上午 | F10: 8月31日上午
A11: =E11&F11 | G11: 关键词排序
A12: =E12&F12 | G12: 关键词1 | I12: 关键词2 | K12: 关键词3 | M12: 关键词4
A13: =E13&F13 -> 日期 | F13: 日期 | G13: 广告位 | H13: 自然位 | I13: 广告位 | J13: 自然位 | K13: 广告位 | L13: 自然位 | M13: 广告位 | N13: 自然位
A14: =E14&F14 -> XXXX-1118月31日晚上 | E14: XXXX-111 | F14: 8月31日晚上
A15: =E15&F15 -> XXXX-2228月31日晚上 | E15: XXXX-222 | F15: 8月31日晚上
A16: =E16&F16 -> 8月31日晚上 | F16: 8月31日晚上
A17: =E17&F17 -> 8月31日晚上 | F17: 8月31日晚上
A18: =E18&F18 -> 8月31日晚上 | F18: 8月31日晚上
A19: =E19&F19 -> 8月31日晚上 | F19: 8月31日晚上
A20: =E20&F20 -> 8月31日晚上 | F20: 8月31日晚上
A22: =E22&F22
A23: =E23&F23
A24: =E24&F24 -> SKU | B24: 品牌 | C24: 产品系列 | D24: 款式 | E24: SKU | G24: 关键词排序
A25: =E25&F25 | G25: 关键词1 | I25: 关键词2 | K25: 关键词3 | M25: 关键词4
A26: =E26&F26 -> 日期 | F26: 日期 | G26: 广告位 | H26: 自然位 | I26: 广告位 | J26: 自然位 | K26: 广告位 | L26: 自然位 | M26: 广告位 | N26: 自然位
A27: =E27&F27 -> XXXX-1119月1日上午 | E27: XXXX-111 | F27: 9月1日上午 | H27: 2-12-4 | J27: 2-4-4
A28: =E28&F28 -> XXXX-2229月1日上午 | E28: XXXX-222 | F28: 9月1日上午
A29: =E29&F29 -> 9月1日上午 | F29: 9月1日上午 | J29: 6-5-1
A30: =E30&F30 -> 9月1日上午 | F30: 9月1日上午
A31: =E31&F31 -> 9月1日上午 | F31: 9月1日上午 | J31: 5-4-4
A32: =E32&F32 -> 9月1日上午 | F32: 9月1日上午
A33: =E33&F33 -> 9月1日上午 | F33: 9月1日上午
A34: =E34&F34 | G34: 关键词1 | I34: 关键词2 | K34: 关键词3 | M34: 关键词4
A35: =E35&F35 -> 日期 | F35: 日期 | G35: 广告位 | H35: 自然位 | I35: 广告位 | J35: 自然位 | K35: 广告位 | L35: 自然位 | M35: 广告位 | N35: 自然位
A36: =E36&F36 -> XXXX-1119月1日晚上 | E36: XXXX-111 | F36: 9月1日晚上
A37: =E37&F37 -> XXXX-2229月1日晚上 | E37: XXXX-222 | F37: 9月1日晚上
A38: =E38&F38 -> 9月1日晚上 | F38: 9月1日晚上
A39: =E39&F39 -> 9月1日晚上 | F39: 9月1日晚上
A40: =E40&F40 -> 9月1日晚上 | F40: 9月1日晚上
A41: =E41&F41 -> 9月1日晚上 | F41: 9月1日晚上
A42: =E42&F42 -> 9月1日晚上 | F42: 9月1日晚上
A43: =E43&F43
A44: =E44&F44 -> SKU | B44: 品牌 | C44: 产品系列 | D44: 款式 | E44: SKU | G44: 关键词排序
A45: =E45&F45 | G45: 关键词1 | I45: 关键词2 | K45: 关键词3 | M45: 关键词4
A46: =E46&F46 -> 日期 | F46: 日期 | G46: 广告位 | H46: 自然位 | I46: 广告位 | J46: 自然位 | K46: 广告位 | L46: 自然位 | M46: 广告位 | N46: 自然位
A47: =E47&F47 -> XXXX-1119月2日上午 | E47: XXXX-111 | F47: 9月2日上午 | H47: 2-14-4 | L47: 2-7-4
A48: =E48&F48 -> XXXX-2229月2日上午 | E48: XXXX-222 | F48: 9月2日上午 | J48: 3-16-4
A49: =E49&F49 -> 9月2日上午 | F49: 9月2日上午 | J49: 5-9-1
A50: =E50&F50 -> 9月2日上午 | F50: 9月2日上午
A51: =E51&F51 -> 9月2日上午 | F51: 9月2日上午 | J51: 5-3-2
A52: =E52&F52 -> 9月2日上午 | F52: 9月2日上午
A53: =E53&F53 -> 9月2日上午 | F53: 9月2日上午
A54: =E54&F54
A55: =E55&F55 -> SKU | B55: 品牌 | C55: 产品系列 | D55: 款式 | E55: SKU | G55: 关键词排序
A56: =E56&F56 | G56: 关键词1 | I56: 关键词2 | K56: 关键词3 | M56: 关键词4
A57: =E57&F57 -> 日期 | F57: 日期 | G57: 广告位 | H57: 自然位 | I57: 广告位 | J57: 自然位 | K57: 广告位 | L57: 自然位 | M57: 广告位 | N57: 自然位
A58: =E58&F58 -> XXXX-1119月2日晚上 | E58: XXXX-111 | F58: 9月2日晚上
A59: =E59&F59 -> XXXX-2229月2日晚上 | E59: XXXX-222 | F59: 9月2日晚上
A60: =E60&F60 -> 9月2日晚上 | F60: 9月2日晚上
A61: =E61&F61 -> 9月2日晚上 | F61: 9月2日晚上
A62: =E62&F62 -> 9月2日晚上 | F62: 9月2日晚上
A63: =E63&F63 -> 9月2日晚上 | F63: 9月2日晚上
A64: =E64&F64 -> 9月2日晚上 | F64: 9月2日晚上
A65: =E65&F65
A66: =E66&F66
A67: =E67&F67 -> SKU | B67: 品牌 | C67: 产品系列 | D67: 款式 | E67: SKU | G67: 关键词排序
A68: =E68&F68 | G68: 关键词1 | I68: 关键词2 | K68: 关键词3 | M68: 关键词4
A69: =E69&F69 -> 日期 | F69: 日期 | G69: 广告位 | H69: 自然位 | I69: 广告位 | J69: 自然位 | K69: 广告位 | L69: 自然位 | M69: 广告位 | N69: 自然位
A70: =E70&F70 -> XXXX-1119月3日上午 | E70: XXXX-111 | F70: 9月3日上午 | H70: 3-12-4 | L70: 1-16-4
A71: =E71&F71 -> XXXX-2229月3日上午 | E71: XXXX-222 | F71: 9月3日上午 | J71: 4-12-4
A72: =E72&F72 -> 9月3日上午 | F72: 9月3日上午 | J72: 6-9-3
A73: =E73&F73 -> 9月3日上午 | F73: 9月3日上午
A74: =E74&F74 -> 9月3日上午 | F74: 9月3日上午 | L74: 5-12-1
A75: =E75&F75 -> 9月3日上午 | F75: 9月3日上午
A76: =E76&F76 -> 9月3日上午 | F76: 9月3日上午
A77: =E77&F77
A78: =E78&F78 -> SKU | B78: 品牌 | C78: 产品系列 | D78: 款式 | E78: SKU | G78: 关键词排序
A79: =E79&F79 | G79: 关键词1 | I79: 关键词2 | K79: 关键词3 | M79: 关键词4
A80: =E80&F80 -> 日期 | F80: 日期 | G80: 广告位 | H80: 自然位 | I80: 广告位 | J80: 自然位 | K80: 广告位 | L80: 自然位 | M80: 广告位 | N80: 自然位
A81: =E81&F81 -> XXXX-1119月3日晚上 | E81: XXXX-111 | F81: 9月3日晚上
A82: =E82&F82 -> XXXX-2229月3日晚上 | E82: XXXX-222 | F82: 9月3日晚上
A83: =E83&F83 -> 9月3日晚上 | F83: 9月3日晚上
A84: =E84&F84 -> 9月3日晚上 | F84: 9月3日晚上
A85: =E85&F85 -> 9月3日晚上 | F85: 9月3日晚上
A86: =E86&F86 -> 9月3日晚上 | F86: 9月3日晚上
A87: =E87&F87 -> 9月3日晚上 | F87: 9月3日晚上
A88: =E88&F88
A89: =E89&F89 -> SKU | B89: 品牌 | C89: 产品系列 | D89: 款式 | E89: SKU | G89: 关键词排序
A90: =E90&F90 | G90: 关键词1 | I90: 关键词2 | K90: 关键词3 | M90: 关键词4
A91: =E91&F91 -> 日期 | F91: 日期 | G91: 广告位 | H91: 自然位 | I91: 广告位 | J91: 自然位 | K91: 广告位 | L91: 自然位 | M91: 广告位 | N91: 自然位
A92: =E92&F92 -> XXXX-1119月4日上午 | E92: XXXX-111 | F92: 9月4日上午
A93: =E93&F93 -> XXXX-2229月4日上午 | E93: XXXX-222 | F93: 9月4日上午
A94: =E94&F94 -> 9月4日上午 | F94: 9月4日上午
A95: =E95&F95 -> 9月4日上午 | F95: 9月4日上午
A96: =E96&F96 -> 9月4日上午 | F96: 9月4日上午
A97: =E97&F97 -> 9月4日上午 | F97: 9月4日上午
A98: =E98&F98 -> 9月4日上午 | F98: 9月4日上午
A99: =E99&F99
A100: =E100&F100 -> SKU | B100: 品牌 | C100: 产品系列 | D100: 款式 | E100: SKU | G100: 关键词排序
A101: =E101&F101 | G101: 关键词1 | I101: 关键词2 | K101: 关键词3 | M101: 关键词4
...

Sheet 4.2 产品详情原始数据
A1: 产品标识 | B1: 时间 | C1: ASIN | D1: 父ASIN | E1: MSKU | F1: 品名 | G1: 价格 | H1: FBA可售 | I1: FBM可售 | J1: 销量 | K1: 订单量 | L1: 销售额 | M1: 净销售额 | N1: B2B 销量 | O1: B2B 销售额 | P1: B2B 订单量 | Q1: 促销销量 | R1: 促销销售额 | S1: 促销订单量 | T1: 平均客单价 | U1: 平均销量 | V1: 大类排名 | W1: 小类排名 | X1: 退款量 | Y1: 退款率 | Z1: 评分 | AA1: 评论数 | AB1: 留评率 | AC1: 促销折扣 | AD1: 毛利润 | AE1: 毛利率 | AF1: ROI | AG1: 退货量 | AH1: 退货率 | AI1: Sessions-Browser | AJ1: Sessions-Mobile | AK1: Sessions-Total | AL1: PV-Browser | AM1: PV-Mobile | AN1: PV-Total | AO1: Buybox | AP1: CVR | AQ1: 销量CVR | AR1: CPC | AS1: CTR | AT1: 广告花费 | AU1: ROAS | AV1: ACOS | AW1: ACoAS | AX1: ASoAS | AY1: CPO | AZ1: CPM | BA1: 广告销售额 | BB1: 广告订单量 | BC1: 广告订单占比 | BD1: 广告CVR | BE1: 展示 | BF1: 点击 | BG1: 运营日志1
A2: =B2&E2 -> 46254XXXX-111 | B2: 46254 | C2: ASIN1 | E2: XXXX-111 | G2: 13.99 | H2: 199 | I2: 0 | J2: 0 | K2: 0 | L2: 0 | M2: 0 | N2: 0 | O2: 0 | P2: 0 | Q2: 0 | R2: 0 | S2: 0 | U2: 0 | X2: 0 | Y2: 0 | Z2: 0 | AA2: 0 | AB2: 0 | AC2: 0 | AD2: 0 | AE2: 0 | AF2: 0 | AG2: 0 | AH2: 0 | AI2: 0 | AJ2: 0 | AK2: 0 | AL2: 0 | AM2: 0 | AN2: 0 | AP2: 0 | AQ2: 0 | AS2: 0 | AT2: 0 | AU2: 0 | AV2: 0 | AW2: 0 | AX2: 0 | AZ2: 0 | BA2: 0 | BB2: 0 | BC2: 0 | BD2: 0 | BE2: 0 | BF2: 0
A3: =B3&E3 -> 46255XXXX-111 | B3: 46255 | C3: ASIN1 | E3: XXXX-111 | G3: 13.99 | H3: 259 | I3: 0 | J3: 0 | K3: 0 | L3: 0 | M3: 0 | N3: 0 | O3: 0 | P3: 0 | Q3: 0 | R3: 0 | S3: 0 | U3: 0 | X3: 0 | Y3: 0 | Z3: 0 | AA3: 0 | AB3: 0 | AC3: 0 | AD3: 0 | AE3: 0 | AF3: 0 | AG3: 0 | AH3: 0 | AI3: 0 | AJ3: 0 | AK3: 0 | AL3: 0 | AM3: 0 | AN3: 0 | AP3: 0 | AQ3: 0 | AS3: 0 | AT3: 0 | AU3: 0 | AV3: 0 | AW3: 0 | AX3: 0 | AZ3: 0 | BA3: 0 | BB3: 0 | BC3: 0 | BD3: 0 | BE3: 0 | BF3: 0
A4: =B4&E4 -> 46256XXXX-111 | B4: 46256 | C4: ASIN1 | E4: XXXX-111 | G4: 13.99 | H4: 319 | I4: 0 | J4: 0 | K4: 0 | L4: 0 | M4: 0 | N4: 0 | O4: 0 | P4: 0 | Q4: 0 | R4: 0 | S4: 0 | U4: 0 | X4: 0 | Y4: 0 | Z4: 0 | AA4: 0 | AB4: 0 | AC4: 0 | AD4: 0 | AE4: 0 | AF4: 0 | AG4: 0 | AH4: 0 | AI4: 0 | AJ4: 0 | AK4: 0 | AL4: 0 | AM4: 0 | AN4: 0 | AP4: 0 | AQ4: 0 | AS4: 0 | AT4: 0 | AU4: 0 | AV4: 0 | AW4: 0 | AX4: 0 | AZ4: 0 | BA4: 0 | BB4: 0 | BC4: 0 | BD4: 0 | BE4: 0 | BF4: 0
A5: =B5&E5 -> 46257XXXX-111 | B5: 46257 | C5: ASIN1 | E5: XXXX-111 | G5: 13.99 | H5: 340 | I5: 0 | J5: 2 | K5: 2 | L5: 27.98 | M5: 27.98 | N5: 0 | O5: 0 | P5: 0 | Q5: 0 | R5: 0 | S5: 0 | T5: 13.99 | U5: 0 | X5: 0 | Y5: 0 | Z5: 0 | AA5: 0 | AB5: 0 | AC5: 0 | AD5: -20.95 | AE5: 0 | AF5: 0.2452 | AG5: 0 | AH5: 0 | AI5: 9 | AJ5: 20 | AK5: 29 | AL5: 14 | AM5: 23 | AN5: 37 | AO5: 1 | AP5: 0.069 | AQ5: 0.069 | AR5: 0.91 | AS5: 0.002 | AT5: -20.95 | AU5: 2.67 | AV5: 0.3744 | AW5: 0.7487 | AX5: 2 | AY5: 5.24 | AZ5: 1.81 | BA5: 55.96 | BB5: 4 | BC5: 2 | BD5: 0.1739 | BE5: 11582 | BF5: 23
A6: =B6&E6 -> 46258XXXX-111 | B6: 46258 | C6: ASIN1 | E6: XXXX-111 | G6: 13.99 | H6: 337 | I6: 0 | J6: 1 | K6: 1 | L6: 13.99 | M6: 13.99 | N6: 0 | O6: 0 | P6: 0 | Q6: 0 | R6: 0 | S6: 0 | T6: 13.99 | U6: 0 | X6: 0 | Y6: 0 | Z6: 0 | AA6: 0 | AB6: 0 | AC6: 0 | AD6: -18.32 | AE6: 0 | AF6: -2.5339 | AG6: 0 | AH6: 0 | AI6: 9 | AJ6: 16 | AK6: 25 | AL6: 11 | AM6: 22 | AN6: 33 | AO6: 1 | AP6: 0.04 | AQ6: 0.04 | AR6: 0.92 | AS6: 0.0024 | AT6: -18.32 | AU6: 0 | AV6: 1 | AW6: 1.3095 | AX6: 0 | AZ6: 2.19 | BA6: 0 | BB6: 0 | BC6: 0 | BD6: 0 | BE6: 8355 | BF6: 20
A7: =B7&E7 -> 46259XXXX-111 | B7: 46259 | C7: ASIN1 | E7: XXXX-111 | G7: 13.99 | H7: 334 | I7: 0 | J7: 0 | K7: 0 | L7: 0 | M7: 0 | N7: 0 | O7: 0 | P7: 0 | Q7: 0 | R7: 0 | S7: 0 | U7: 0 | X7: 0 | Y7: 0 | Z7: 0 | AA7: 0 | AB7: 0 | AC7: 0 | AD7: -1.13 | AE7: -0.081 | AF7: 0 | AG7: 0 | AH7: 0 | AI7: 8 | AJ7: 9 | AK7: 17 | AL7: 8 | AM7: 15 | AN7: 23 | AO7: 0.83 | AP7: 0 | AQ7: 0 | AR7: 0.79 | AS7: 0.0017 | AT7: -4.72 | AU7: 0 | AV7: 1 | AW7: 1 | AX7: 0 | AZ7: 1.35 | BA7: 0 | BB7: 0 | BC7: 0 | BD7: 0 | BE7: 3488 | BF7: 6
A8: =B8&E8 -> 46260XXXX-111 | B8: 46260 | C8: ASIN1 | E8: XXXX-111 | G8: 13.99 | H8: 493 | I8: 0 | J8: 1 | K8: 1 | L8: 13.99 | M8: 13.99 | N8: 0 | O8: 0 | P8: 0 | Q8: 0 | R8: 0 | S8: 0 | T8: 13.99 | U8: 0 | X8: 0 | Y8: 0 | Z8: 0 | AA8: 0 | AB8: 0 | AC8: 0 | AD8: -20.26 | AE8: 0 | AF8: -3.2212 | AG8: 0 | AH8: 0 | AI8: 15 | AJ8: 17 | AK8: 32 | AL8: 23 | AM8: 19 | AN8: 42 | AO8: 0.88 | AP8: 0.0312 | AQ8: 0.0312 | AR8: 1.07 | AS8: 0.0019 | AT8: -20.26 | AU8: 1.38 | AV8: 0.7241 | AW8: 1.4482 | AX8: 2 | AY8: 10.13 | AZ8: 1.98 | BA8: 27.98 | BB8: 2 | BC8: 2 | BD8: 0.1053 | BE8: 10230 | BF8: 19
A9: =B9&E9 -> 46261XXXX-111 | B9: 46261 | C9: ASIN1 | E9: XXXX-111 | G9: 13.99 | H9: 513 | I9: 0 | J9: 3 | K9: 3 | L9: 41.97 | M9: 41.97 | N9: 0 | O9: 0 | P9: 0 | Q9: 0 | R9: 0 | S9: 0 | T9: 13.99 | U9: 0.1 | X9: 0 | Y9: 0 | Z9: 0 | AA9: 0 | AB9: 0 | AC9: 0 | AD9: -22.85 | AE9: -1.6335 | AF9: 0.8858 | AG9: 0 | AH9: 0 | AI9: 16 | AJ9: 24 | AK9: 40 | AL9: 18 | AM9: 37 | AN9: 55 | AO9: 0.96 | AP9: 0.075 | AQ9: 0.075 | AR9: 1.08 | AS9: 0.0027 | AT9: -26 | AU9: 0.54 | AV9: 1.8585 | AW9: 0.6195 | AX9: 0.3333 | AY9: 26 | AZ9: 2.97 | BA9: 13.99 | BB9: 1 | BC9: 0.3333 | BD9: 0.0417 | BE9: 8753 | BF9: 24
A10: =B10&E10 -> 46262XXXX-111 | B10: 46262 | C10: ASIN1 | E10: XXXX-111 | G10: 13.99 | H10: 526 | I10: 0 | J10: 3 | K10: 2 | L10: 41.97 | M10: 41.97 | N10: 0 | O10: 0 | P10: 0 | Q10: 0 | R10: 0 | S10: 0 | T10: 13.99 | U10: 0.1 | X10: 0 | Y10: 0 | Z10: 0 | AA10: 0 | AB10: 0 | AC10: 0 | AD10: -23.48 | AE10: 0 | AF10: 1.1834 | AG10: 0 | AH10: 0 | AI10: 17 | AJ10: 37 | AK10: 54 | AL10: 21 | AM10: 52 | AN10: 73 | AO10: 0.96 | AP10: 0.037 | AQ10: 0.0556 | AR10: 1.07 | AS10: 0.0013 | AT10: -23.48 | AU10: 1.79 | AV10: 0.5594 | AW10: 0.5594 | AX10: 1 | AY10: 7.83 | AZ10: 1.4 | BA10: 41.97 | BB10: 3 | BC10: 1.5 | BD10: 0.1364 | BE10: 16751 | BF10: 22
A11: =B11&E11 -> 46263XXXX-111 | B11: 46263 | C11: ASIN1 | E11: XXXX-111 | G11: 13.99 | H11: 524 | I11: 0 | J11: 9 | K11: 9 | L11: 125.91 | M11: 125.91 | N11: 0 | O11: 0 | P11: 0 | Q11: 0 | R11: 0 | S11: 0 | T11: 13.99 | U11: 0.2 | X11: 0 | Y11: 0 | Z11: 0 | AA11: 0 | AB11: 0 | AC11: 0 | AD11: -0.2 | AE11: -0.0029 | AF11: 3.1507 | AG11: 0 | AH11: 0 | AI11: 16 | AJ11: 30 | AK11: 46 | AL11: 19 | AM11: 34 | AN11: 53 | AO11: 0.96 | AP11: 0.1957 | AQ11: 0.1957 | AR11: 1.08 | AS11: 0.0014 | AT11: -20.61 | AU11: 1.36 | AV11: 0.7366 | AW11: 0.1637 | AX11: 0.2222 | AY11: 10.3 | AZ11: 1.51 | BA11: 27.98 | BB11: 2 | BC11: 0.2222 | BD11: 0.1053 | BE11: 13659 | BF11: 19
A12: =B12&E12 -> 46264XXXX-111 | B12: 46264 | C12: ASIN1 | E12: XXXX-111 | G12: 13.99 | H12: 555 | I12: 0 | J12: 5 | K12: 5 | L12: 69.95 | M12: 69.95 | N12: 0 | O12: 0 | P12: 0 | Q12: 0 | R12: 0 | S12: 0 | T12: 13.99 | U12: 0.1 | X12: 0 | Y12: 0 | Z12: 0 | AA12: 0 | AB12: 0 | AC12: 0 | AD12: 19.73 | AE12: 0.1409 | AF12: 2.5688 | AG12: 0 | AH12: 0 | AI12: 23 | AJ12: 55 | AK12: 78 | AL12: 32 | AM12: 64 | AN12: 96 | AO12: 0.98 | AP12: 0.0641 | AQ12: 0.0641 | AR12: 1.09 | AS12: 0.0014 | AT12: -19.58 | AU12: 3.57 | AV12: 0.2799 | AW12: 0.2799 | AX12: 1 | AY12: 3.92 | AZ12: 1.52 | BA12: 69.95 | BB12: 5 | BC12: 1 | BD12: 0.2778 | BE12: 12849 | BF12: 18
A13: =B13&E13 -> 46265XXXX-111 | B13: 46265 | C13: ASIN1 | E13: XXXX-111 | G13: 13.99 | H13: 613 | I13: 0 | J13: 9 | K13: 7 | L13: 125.91 | M13: 113.6 | N13: 0 | O13: 0 | P13: 0 | Q13: 0 | R13: 0 | S13: 0 | T13: 12.62 | U13: 0.2 | X13: 1 | Y13: 0.1111 | Z13: 0 | AA13: 0 | AB13: 0 | AC13: 0 | AD13: -0.9 | AE13: -0.0081 | AF13: 3.1539 | AG13: 0 | AH13: 0 | AI13: 25 | AJ13: 46 | AK13: 71 | AL13: 35 | AM13: 51 | AN13: 86 | AO13: 0.95 | AP13: 0.0986 | AQ13: 0.1268 | AR13: 1.13 | AS13: 0.0033 | AT13: -20.38 | AU13: 1.37 | AV13: 0.7284 | AW13: 0.1619 | AX13: 0.2222 | AY13: 10.19 | AZ13: 3.69 | BA13: 27.98 | BB13: 2 | BC13: 0.2857 | BD13: 0.1111 | BE13: 5518 | BF13: 18
A14: =B14&E14 -> 46266XXXX-111 | B14: 46266 | C14: ASIN1 | E14: XXXX-111 | G14: 13.99 | H14: 758 | I14: 0 | J14: 4 | K14: 4 | L14: 55.96 | M14: 55.96 | N14: 0 | O14: 0 | P14: 0 | Q14: 0 | R14: 0 | S14: 0 | T14: 13.99 | U14: 0.1 | X14: 0 | Y14: 0 | Z14: 0 | AA14: 0 | AB14: 0 | AC14: 0 | AD14: -5.41 | AE14: -0.0967 | AF14: 2.1582 | AG14: 0 | AH14: 0 | AI14: 24 | AJ14: 61 | AK14: 85 | AL14: 34 | AM14: 75 | AN14: 109 | AO14: 0.99 | AP14: 0.0471 | AQ14: 0.0471 | AR14: 1.19 | AS14: 0.0036 | AT14: -20.3 | AU14: 0.69 | AV14: 1.451 | AW14: 0.3628 | AX14: 0.25 | AY14: 20.3 | AZ14: 4.35 | BA14: 13.99 | BB14: 1 | BC14: 0.25 | BD14: 0.0588 | BE14: 4668 | BF14: 17
A15: =B15&E15 -> 46267XXXX-111 | B15: 46267 | C15: ASIN1 | E15: XXXX-111 | G15: 13.99 | H15: 812 | I15: 0 | J15: 9 | K15: 9 | L15: 125.91 | M15: 125.91 | N15: 0 | O15: 0 | P15: 0 | Q15: 0 | R15: 0 | S15: 0 | T15: 13.99 | U15: 0.2 | X15: 0 | Y15: 0 | Z15: 0 | AA15: 0 | AB15: 0 | AC15: 0 | AD15: 1.98 | AE15: 0.0236 | AF15: 3.1602 | AG15: 0 | AH15: 0 | AI15: 31 | AJ15: 63 | AK15: 94 | AL15: 44 | AM15: 84 | AN15: 128 | AO15: 0.98 | AP15: 0.0957 | AQ15: 0.0957 | AR15: 1.19 | AS15: 0.0043 | AT15: -20.22 | AU15: 2.08 | AV15: 0.4818 | AW15: 0.1606 | AX15: 0.3333 | AY15: 6.74 | AZ15: 5.13 | BA15: 41.97 | BB15: 3 | BC15: 0.3333 | BD15: 0.1765 | BE15: 3943 | BF15: 17
A16: =B16&E16 -> 46268XXXX-111 | B16: 46268 | C16: ASIN1 | E16: XXXX-111 | G16: 13.99 | H16: 803 | I16: 0 | J16: 9 | K16: 9 | L16: 125.91 | M16: 125.91 | N16: 0 | O16: 0 | P16: 0 | Q16: 0 | R16: 0 | S16: 0 | T16: 13.99 | U16: 0.2 | X16: 0 | Y16: 0 | Z16: 0 | AA16: 0 | AB16: 0 | AC16: 0 | AD16: 6.54 | AE16: 0.0668 | AF16: 3.1889 | AG16: 0 | AH16: 0 | AI16: 35 | AJ16: 89 | AK16: 124 | AL16: 41 | AM16: 110 | AN16: 151 | AO16: 0.98 | AP16: 0.0726 | AQ16: 0.0726 | AR16: 1.08 | AS16: 0.0036 | AT16: -19.49 | AU16: 2.15 | AV16: 0.4644 | AW16: 0.1548 | AX16: 0.3333 | AY16: 6.5 | AZ16: 3.86 | BA16: 41.97 | BB16: 3 | BC16: 0.3333 | BD16: 0.1667 | BE16: 5051 | BF16: 18
A17: =B17&E17 -> 46269XXXX-111 | B17: 46269 | C17: ASIN1 | E17: XXXX-111 | G17: 13.99 | H17: 797 | I17: 0 | J17: 8 | K17: 8 | L17: 111.92 | M17: 111.92 | N17: 0 | O17: 0 | P17: 0 | Q17: 0 | R17: 0 | S17: 0 | T17: 13.99 | U17: 0.1 | X17: 0 | Y17: 0 | Z17: 0 | AA17: 0 | AB17: 0 | AC17: 0 | AD17: 10.03 | AE17: 0.0896 | AF17: 3.2679 | AG17: 0 | AH17: 0 | AI17: 47 | AJ17: 102 | AK17: 149 | AL17: 66 | AM17: 126 | AN17: 192 | AO17: 0.99 | AP17: 0.0537 | AQ17: 0.0537 | AR17: 1.15 | AS17: 0.0042 | AT17: -19.53 | AU17: 2.87 | AV17: 0.349 | AW17: 0.1745 | AX17: 0.5 | AY17: 4.88 | AZ17: 4.83 | BA17: 55.96 | BB17: 4 | BC17: 0.5 | BD17: 0.2353 | BE17: 4046 | BF17: 17
A18: =B18&E18 -> 46270XXXX-111 | B18: 46270 | C18: ASIN1 | E18: XXXX-111 | G18: 13.99 | H18: 835 | I18: 0 | J18: 23 | K18: 22 | L18: 321.77 | M18: 321.77 | N18: 0 | O18: 0 | P18: 0 | Q18: 0 | R18: 0 | S18: 0 | T18: 13.99 | U18: 0.4 | X18: 0 | Y18: 0 | Z18: 0 | AA18: 0 | AB18: 0 | AC18: 0 | AD18: 30.29 | AE18: 0.163 | AF18: 3.7123 | AG18: 0 | AH18: 0 | AI18: 64 | AJ18: 139 | AK18: 203 | AL18: 82 | AM18: 168 | AN18: 250 | AO18: 0.99 | AP18: 0.1084 | AQ18: 0.1133 | AR18: 1.18 | AS18: 0.0038 | AT18: -18.89 | AU18: 0 | AV18: 1 | AW18: 0.0587 | AX18: 0 | AZ18: 4.5 | BA18: 0 | BB18: 0 | BC18: 0 | BD18: 0 | BE18: 4194 | BF18: 16
A19: =B19&E19 -> 46271XXXX-111 | B19: 46271 | C19: ASIN1 | E19: XXXX-111 | G19: 13.99 | H19: 863 | I19: 0 | J19: 17 | K19: 16 | L19: 237.83 | M19: 237.83 | N19: 1 | O19: 13.99 | P19: 1 | Q19: 0 | R19: 0 | S19: 0 | T19: 13.99 | U19: 0.3 | X19: 0 | Y19: 0 | Z19: 0 | AA19: 0 | AB19: 0 | AC19: 0 | AD19: 54.47 | AE19: 0.1926 | AF19: 3.5316 | AG19: 0 | AH19: 0 | AI19: 37 | AJ19: 101 | AK19: 138 | AL19: 52 | AM19: 128 | AN19: 180 | AO19: 0.98 | AP19: 0.1159 | AQ19: 0.1232 | AR19: 1.13 | AS19: 0.0042 | AT19: -20.37 | AU19: 0 | AV19: 1 | AW19: 0.0856 | AX19: 0 | AZ19: 4.79 | BA19: 0 | BB19: 0 | BC19: 0 | BD19: 0 | BE19: 4253 | BF19: 18
A20: =B20&E20 -> 46272XXXX-111 | B20: 46272 | C20: ASIN1 | E20: XXXX-111 | G20: 13.99 | H20: 842 | I20: 0 | J20: 11 | K20: 11 | L20: 153.89 | M20: 153.89 | N20: 1 | O20: 13.99 | P20: 1 | Q20: 0 | R20: 0 | S20: 0 | T20: 13.99 | U20: 0.2 | X20: 0 | Y20: 0 | Z20: 0 | AA20: 0 | AB20: 0 | AC20: 0 | AD20: 40.68 | AE20: 0.1711 | AF20: 3.2427 | AG20: 0 | AH20: 0 | AI20: 43 | AJ20: 99 | AK20: 142 | AL20: 68 | AM20: 115 | AN20: 183 | AO20: 0.98 | AP20: 0.0775 | AQ20: 0.0775 | AR20: 1.11 | AS20: 0.0034 | AT20: -22.15 | AU20: 1.26 | AV20: 0.7916 | AW20: 0.1439 | AX20: 0.1818 | AY20: 11.07 | AZ20: 3.73 | BA20: 27.98 | BB20: 2 | BC20: 0.1818 | BD20: 0.1 | BE20: 5936 | BF20: 20
A21: =B21&E21 -> 46273XXXX-111 | B21: 46273 | C21: ASIN1 | E21: XXXX-111 | G21: 13.99 | H21: 838 | I21: 0 | J21: 12 | K21: 12 | L21: 167.88 | M21: 167.88 | N21: 0 | O21: 0 | P21: 0 | Q21: 0 | R21: 0 | S21: 0 | T21: 13.99 | U21: 0.2 | X21: 0 | Y21: 0 | Z21: 0 | AA21: 0 | AB21: 0 | AC21: 0 | AD21: 23.06 | AE21: 0.1373 | AF21: 3.3465 | AG21: 0 | AH21: 0 | AI21: 41 | AJ21: 81 | AK21: 122 | AL21: 58 | AM21: 101 | AN21: 159 | AO21: 0.98 | AP21: 0.0984 | AQ21: 0.0984 | AR21: 1.15 | AS21: 0.0028 | AT21: -20.65 | AU21: 2.03 | AV21: 0.492 | AW21: 0.123 | AX21: 0.25 | AY21: 6.88 | AZ21: 3.26 | BA21: 41.97 | BB21: 3 | BC21: 0.25 | BD21: 0.1667 | BE21: 6325 | BF21: 18
A22: =B22&E22 -> 46274XXXX-111 | B22: 46274 | C22: ASIN1 | E22: XXXX-111 | G22: 13.99 | H22: 843 | I22: 0 | J22: 9 | K22: 9 | L22: 125.91 | M22: 125.91 | N22: 1 | O22: 13.99 | P22: 1 | Q22: 0 | R22: 0 | S22: 0 | T22: 13.99 | U22: 0.2 | X22: 0 | Y22: 0 | Z22: 3 | AA22: 1 | AB22: 0 | AC22: 0 | AD22: 10.64 | AE22: 0.095 | AF22: 3.2881 | AG22: 0 | AH22: 0 | AI22: 29 | AJ22: 73 | AK22: 102 | AL22: 39 | AM22: 96 | AN22: 135 | AO22: 0.96 | AP22: 0.0882 | AQ22: 0.0882 | AR22: 1.13 | AS22: 0.0037 | AT22: -19.25 | AU22: 1.45 | AV22: 0.688 | AW22: 0.1529 | AX22: 0.2222 | AY22: 9.62 | AZ22: 4.16 | BA22: 27.98 | BB22: 2 | BC22: 0.2222 | BD22: 0.1176 | BE22: 4629 | BF22: 17
A23: =B23&E23 -> 46275XXXX-111 | B23: 46275 | C23: ASIN1 | E23: XXXX-111 | G23: 13.99 | H23: 830 | I23: 0 | J23: 11 | K23: 11 | L23: 153.89 | M23: 153.89 | N23: 0 | O23: 0 | P23: 0 | Q23: 0 | R23: 0 | S23: 0 | T23: 13.99 | U23: 0.2 | X23: 0 | Y23: 0 | Z23: 3 | AA23: 1 | AB23: 0 | AC23: 0 | AD23: 28.77 | AE23: 0.1563 | AF23: 3.3188 | AG23: 0 | AH23: 0 | AI23: 41 | AJ23: 131 | AK23: 172 | AL23: 54 | AM23: 153 | AN23: 207 | AO23: 0.99 | AP23: 0.064 | AQ23: 0.064 | AR23: 1.1 | AS23: 0.0045 | AT23: -19.79 | AU23: 1.41 | AV23: 0.7073 | AW23: 0.1286 | AX23: 0.1818 | AY23: 9.89 | AZ23: 4.91 | BA23: 27.98 | BB23: 2 | BC23: 0.1818 | BD23: 0.1111 | BE23: 4027 | BF23: 18
A24: =B24&E24 -> 46276XXXX-111 | B24: 46276 | C24: ASIN1 | E24: XXXX-111 | G24: 13.99 | H24: 818 | I24: 0 | J24: 14 | K24: 14 | L24: 195.86 | M24: 195.86 | N24: 0 | O24: 0 | P24: 0 | Q24: 0 | R24: 0 | S24: 0 | T24: 13.99 | U24: 0.2 | X24: 0 | Y24: 0 | Z24: 3 | AA24: 1 | AB24: 0 | AC24: 0 | AD24: 18.01 | AE24: 0.1288 | AF24: 3.4455 | AG24: 1 | AH24: 0.0714 | AI24: 46 | AJ24: 158 | AK24: 204 | AL24: 60 | AM24: 182 | AN24: 242 | AO24: 0.98 | AP24: 0.0686 | AQ24: 0.0686 | AR24: 1.19 | AS24: 0.0032 | AT24: -20.18 | AU24: 1.39 | AV24: 0.7212 | AW24: 0.103 | AX24: 0.1429 | AY24: 10.09 | AZ24: 3.75 | BA24: 27.98 | BB24: 2 | BC24: 0.1429 | BD24: 0.1176 | BE24: 5376 | BF24: 17
A25: =B25&E25 -> 46277XXXX-111 | B25: 46277 | C25: ASIN1 | E25: XXXX-111 | G25: 13.99 | H25: 807 | I25: 0 | J25: 18 | K25: 18 | L25: 251.82 | M25: 251.82 | N25: 1 | O25: 13.99 | P25: 1 | Q25: 0 | R25: 0 | S25: 0 | T25: 13.99 | U25: 0.3 | X25: 0 | Y25: 0 | Z25: 4.6 | AA25: 16 | AB25: 0 | AC25: 0 | AD25: 42.39 | AE25: 0.1894 | AF25: 3.5725 | AG25: 0 | AH25: 0 | AI25: 54 | AJ25: 111 | AK25: 165 | AL25: 77 | AM25: 131 | AN25: 208 | AO25: 0.99 | AP25: 0.1091 | AQ25: 0.1091 | AR25: 1.08 | AS25: 0.0035 | AT25: -19.49 | AU25: 2.15 | AV25: 0.4644 | AW25: 0.0774 | AX25: 0.1667 | AY25: 6.5 | AZ25: 3.79 | BA25: 41.97 | BB25: 3 | BC25: 0.1667 | BD25: 0.1667 | BE25: 5139 | BF25: 18
A26: =B26&E26 -> 46278XXXX-111 | B26: 46278 | C26: ASIN1 | E26: XXXX-111 | G26: 13.99 | H26: 781 | I26: 0 | J26: 19 | K26: 19 | L26: 265.81 | M26: 265.81 | N26: 0 | O26: 0 | P26: 0 | Q26: 0 | R26: 0 | S26: 0 | T26: 13.99 | U26: 0.3 | X26: 0 | Y26: 0 | Z26: 4.6 | AA26: 16 | AB26: 0 | AC26: 0 | AD26: 77.09 | AE26: 0.2755 | AF26: 4.024 | AG26: 0 | AH26: 0 | AI26: 55 | AJ26: 120 | AK26: 175 | AL26: 71 | AM26: 151 | AN26: 222 | AO26: 0.98 | AP26: 0.1086 | AQ26: 0.1086 | AS26: 0 | AT26: 0 | AU26: 0 | AV26: 0 | AW26: 0 | AX26: 0 | AZ26: 0 | BA26: 0 | BB26: 0 | BC26: 0 | BD26: 0 | BE26: 0 | BF26: 0
A27: =B27&E27 -> 46279XXXX-111 | B27: 46279 | C27: ASIN1 | E27: XXXX-111 | G27: 13.99 | H27: 759 | I27: 0 | J27: 21 | K27: 21 | L27: 293.79 | M27: 293.79 | N27: 0 | O27: 0 | P27: 0 | Q27: 0 | R27: 0 | S27: 0 | T27: 13.99 | U27: 0.4 | X27: 0 | Y27: 0 | Z27: 4.6 | AA27: 16 | AB27: 0 | AC27: 0 | AD27: 75.64 | AE27: 0.2846 | AF27: 4.0627 | AG27: 0 | AH27: 0 | AI27: 59 | AJ27: 141 | AK27: 200 | AL27: 91 | AM27: 172 | AN27: 263 | AO27: 0.98 | AP27: 0.105 | AQ27: 0.105 | AS27: 0 | AT27: 0 | AU27: 0 | AV27: 0 | AW27: 0 | AX27: 0 | AZ27: 0 | BA27: 0 | BB27: 0 | BC27: 0 | BD27: 0 | BE27: 0 | BF27: 0
A28: =B28&E28 -> 46280XXXX-111 | B28: 46280 | C28: ASIN1 | E28: XXXX-111 | G28: 13.99 | H28: 736 | I28: 0 | J28: 22 | K28: 22 | L28: 307.78 | M28: 307.78 | N28: 0 | O28: 0 | P28: 0 | Q28: 0 | R28: 0 | S28: 0 | T28: 13.99 | U28: 0.4 | X28: 0 | Y28: 0 | Z28: 4.6 | AA28: 16 | AB28: 0 | AC28: 0 | AD28: 57.52 | AE28: 0.2252 | AF28: 3.9561 | AG28: 0 | AH28: 0 | AI28: 53 | AJ28: 123 | AK28: 176 | AL28: 78 | AM28: 147 | AN28: 225 | AO28: 0.97 | AP28: 0.125 | AQ28: 0.125 | AS28: 0 | AT28: 0 | AU28: 0 | AV28: 0 | AW28: 0 | AX28: 0 | AZ28: 0 | BA28: 0 | BB28: 0 | BC28: 0 | BD28: 0 | BE28: 0 | BF28: 0
A29: =B29&E29 -> 46281XXXX-111 | B29: 46281 | C29: ASIN1 | E29: XXXX-111 | G29: 13.99 | H29: 706 | I29: 0 | J29: 29 | K29: 29 | L29: 413.71 | M29: 413.71 | N29: 0 | O29: 0 | P29: 0 | Q29: 0 | R29: 0 | S29: 0 | T29: 14.27 | U29: 0.5 | X29: 0 | Y29: 0 | Z29: 4.6 | AA29: 16 | AB29: 0 | AC29: 0 | AD29: 79.12 | AE29: 0.2693 | AF29: 4.0538 | AG29: 0 | AH29: 0 | AI29: 61 | AJ29: 126 | AK29: 187 | AL29: 79 | AM29: 149 | AN29: 228 | AO29: 0.97 | AP29: 0.1551 | AQ29: 0.1551 | AS29: 0 | AT29: 0 | AU29: 0 | AV29: 0 | AW29: 0 | AX29: 0 | AZ29: 0 | BA29: 0 | BB29: 0 | BC29: 0 | BD29: 0 | BE29: 0 | BF29: 0
A30: =B30&E30 -> 46282XXXX-111 | B30: 46282 | C30: ASIN1 | E30: XXXX-111 | G30: 15.99 | H30: 682 | I30: 0 | J30: 18 | K30: 18 | L30: 287.82 | M30: 275.51 | N30: 0 | O30: 0 | P30: 0 | Q30: 0 | R30: 0 | S30: 0 | T30: 15.31 | U30: 0.3 | X30: 1 | Y30: 0.0556 | Z30: 4.6 | AA30: 16 | AB30: 0 | AC30: 0 | AD30: 106.15 | AE30: 0.2694 | AF30: 4.6646 | AG30: 0 | AH30: 0 | AI30: 67 | AJ30: 174 | AK30: 241 | AL30: 93 | AM30: 207 | AN30: 300 | AO30: 0.98 | AP30: 0.0747 | AQ30: 0.0747 | AS30: 0 | AT30: 0 | AU30: 0 | AV30: 0 | AW30: 0 | AX30: 0 | AZ30: 0 | BA30: 0 | BB30: 0 | BC30: 0 | BD30: 0 | BE30: 0 | BF30: 0
A31: =B31&E31 -> 46283XXXX-111 | B31: 46283 | C31: ASIN1 | E31: XXXX-111 | G31: 15.99 | H31: 653 | I31: 0 | J31: 40 | K31: 40 | L31: 639.6 | M31: 627.29 | N31: 0 | O31: 0 | P31: 0 | Q31: 0 | R31: 0 | S31: 0 | T31: 15.68 | U31: 0.7 | X31: 1 | Y31: 0.025 | Z31: 4.6 | AA31: 16 | AB31: 0 | AC31: 0 | AD31: 112.65 | AE31: 0.303 | AF31: 4.6687 | AG31: 1 | AH31: 0.025 | AI31: 96 | AJ31: 245 | AK31: 341 | AL31: 128 | AM31: 303 | AN31: 431 | AO31: 0.97 | AP31: 0.1173 | AQ31: 0.1173 | AS31: 0 | AT31: 0 | AU31: 0 | AV31: 0 | AW31: 0 | AX31: 0 | AZ31: 0 | BA31: 0 | BB31: 0 | BC31: 0 | BD31: 0 | BE31: 0 | BF31: 0
A32: =B32&E32 -> 46284XXXX-111 | B32: 46284 | C32: ASIN1 | E32: XXXX-111 | G32: 16.99 | H32: 612 | I32: 0 | J32: 28 | K32: 28 | L32: 475.72 | M32: 475.72 | N32: 0 | O32: 0 | P32: 0 | Q32: 0 | R32: 0 | S32: 0 | T32: 16.99 | U32: 0.5 | X32: 0 | Y32: 0 | Z32: 4.6 | AA32: 16 | AB32: 0.0357 | AC32: 0 | AD32: 165.68 | AE32: 0.3527 | AF32: 5.0258 | AG32: 0 | AH32: 0 | AI32: 78 | AJ32: 147 | AK32: 225 | AL32: 103 | AM32: 175 | AN32: 278 | AO32: 0.98 | AP32: 0.1244 | AQ32: 0.1244 | AS32: 0 | AT32: 0 | AU32: 0 | AV32: 0 | AW32: 0 | AX32: 0 | AZ32: 0 | BA32: 0 | BB32: 0 | BC32: 0 | BD32: 0 | BE32: 0 | BF32: 0
A33: =B33&E33 -> 46285XXXX-111 | B33: 46285 | C33: ASIN1 | E33: XXXX-111 | G33: 16.99 | H33: 584 | I33: 0 | J33: 26 | K33: 26 | L33: 441.74 | M33: 441.74 | N33: 2 | O33: 33.98 | P33: 2 | Q33: 0 | R33: 0 | S33: 0 | T33: 16.99 | U33: 0.5 | X33: 0 | Y33: 0 | Z33: 4.7 | AA33: 18 | AB33: 0 | AC33: 0 | AD33: 196.97 | AE33: 0.3344 | AF33: 5.0189 | AG33: 0 | AH33: 0 | AI33: 91 | AJ33: 144 | AK33: 235 | AL33: 120 | AM33: 183 | AN33: 303 | AO33: 0.97 | AP33: 0.1106 | AQ33: 0.1106 | AS33: 0 | AT33: 0 | AU33: 0 | AV33: 0 | AW33: 0 | AX33: 0 | AZ33: 0 | BA33: 0 | BB33: 0 | BC33: 0 | BD33: 0 | BE33: 0 | BF33: 0
A34: =B34&E34 -> 46286XXXX-111 | B34: 46286 | C34: ASIN1 | E34: XXXX-111 | G34: 16.99 | H34: 572 | I34: 0 | J34: 21 | K34: 21 | L34: 356.79 | M34: 356.79 | N34: 0 | O34: 0 | P34: 0 | Q34: 0 | R34: 0 | S34: 0 | T34: 16.99 | U34: 0.4 | X34: 0 | Y34: 0 | Z34: 4.7 | AA34: 18 | AB34: 0 | AC34: 0 | AD34: 136.59 | AE34: 0.3343 | AF34: 5.1586 | AG34: 0 | AH34: 0 | AI34: 88 | AJ34: 138 | AK34: 226 | AL34: 121 | AM34: 186 | AN34: 307 | AO34: 0.98 | AP34: 0.0929 | AQ34: 0.0929 | AS34: 0 | AT34: 0 | AU34: 0 | AV34: 0 | AW34: 0 | AX34: 0 | AZ34: 0 | BA34: 0 | BB34: 0 | BC34: 0 | BD34: 0 | BE34: 0 | BF34: 0
A35: =B35&E35 -> 46287XXXX-111 | B35: 46287 | C35: ASIN1 | E35: XXXX-111 | G35: 16.99 | H35: 546 | I35: 0 | J35: 35 | K35: 35 | L35: 594.65 | M35: 594.65 | N35: 2 | O35: 33.98 | P35: 2 | Q35: 0 | R35: 0 | S35: 0 | T35: 16.99 | U35: 0.6 | X35: 0 | Y35: 0 | Z35: 4.7 | AA35: 18 | AB35: 0 | AC35: 0 | AD35: 127.92 | AE35: 0.371 | AF35: 5.091 | AG35: 1 | AH35: 0.0286 | AI35: 76 | AJ35: 144 | AK35: 220 | AL35: 100 | AM35: 179 | AN35: 279 | AO35: 0.99 | AP35: 0.1591 | AQ35: 0.1591 | AS35: 0 | AT35: 0 | AU35: 0 | AV35: 0 | AW35: 0 | AX35: 0 | AZ35: 0 | BA35: 0 | BB35: 0 | BC35: 0 | BD35: 0 | BE35: 0 | BF35: 0
A36: =B36&E36 -> 46288XXXX-111 | B36: 46288 | C36: ASIN1 | E36: XXXX-111 | G36: 16.99 | H36: 530 | I36: 0 | J36: 27 | K36: 27 | L36: 458.73 | M36: 446.42 | N36: 0 | O36: 0 | P36: 0 | Q36: 0 | R36: 0 | S36: 0 | T36: 16.53 | U36: 0.5 | X36: 2 | Y36: 0.0741 | Z36: 4.7 | AA36: 21 | AB36: 0 | AC36: 0 | AD36: 195.34 | AE36: 0.3466 | AF36: 5.0606 | AG36: 0 | AH36: 0 | AI36: 67 | AJ36: 139 | AK36: 206 | AL36: 87 | AM36: 176 | AN36: 263 | AO36: 0.99 | AP36: 0.1311 | AQ36: 0.1311 | AS36: 0 | AT36: 0 | AU36: 0 | AV36: 0 | AW36: 0 | AX36: 0 | AZ36: 0 | BA36: 0 | BB36: 0 | BC36: 0 | BD36: 0 | BE36: 0 | BF36: 0
A37: =B37&E37 -> 46289XXXX-111 | B37: 46289 | C37: ASIN1 | E37: XXXX-111 | G37: 16.99 | H37: 507 | I37: 0 | J37: 24 | K37: 24 | L37: 407.76 | M37: 407.76 | N37: 0 | O37: 0 | P37: 0 | Q37: 0 | R37: 0 | S37: 0 | T37: 16.99 | U37: 0.4 | X37: 0 | Y37: 0 | Z37: 4.7 | AA37: 21 | AB37: 0 | AC37: 0 | AD37: 153.31 | AE37: 0.3749 | AF37: 5.0189 | AG37: 0 | AH37: 0 | AI37: 73 | AJ37: 177 | AK37: 250 | AL37: 93 | AM37: 224 | AN37: 317 | AO37: 0.98 | AP37: 0.096 | AQ37: 0.096 | AS37: 0 | AT37: 0 | AU37: 0 | AV37: 0 | AW37: 0 | AX37: 0 | AZ37: 0 | BA37: 0 | BB37: 0 | BC37: 0 | BD37: 0 | BE37: 0 | BF37: 0
... A56: =B56&E56 -> 46308XXXX-111 | B56: 46308 | C56: ASIN1 | E56: XXXX-111 | G56: 19.99 | H56: 6 | I56: 0 | J56: 8 | K56: 8 | L56: 159.92 | M56: 159.92 | N56: 2 | O56: 39.98 | P56: 2 | Q56: 0 | R56: 0 | S56: 0 | T56: 19.99 | U56: 0.1 | X56: 0 | Y56: 0 | Z56: 4.4 | AA56: 36 | AB56: 0 | AC56: 0 | AD56: 67.39 | AE56: 0.4665 | AF56: 6.0817 | AG56: 0 | AH56: 0 | AI56: 27 | AJ56: 58 | AK56: 85 | AL56: 33 | AM56: 69 | AN56: 102 | AO56: 0.99 | AP56: 0.0941 | AQ56: 0.0941 | AS56: 0 | AT56: 0 | AU56: 0 | AV56: 0 | AW56: 0 | AX56: 0 | AZ56: 0 | BA56: 0 | BB56: 0 | BC56: 0 | BD56: 0 | BE56: 0 | BF56: 0
A57: =B57&E57 -> 46309XXXX-111 | B57: 46309 | C57: ASIN1 | E57: XXXX-111 | G57: 19.99 | H57: 1 | I57: 0 | J57: 4 | K57: 4 | L57: 79.96 | M57: 79.96 | N57: 1 | O57: 19.99 | P57: 1 | Q57: 0 | R57: 0 | S57: 0 | T57: 19.99 | U57: 0.1 | X57: 2 | Y57: 0.5 | Z57: 4.4 | AA57: 36 | AB57: 0 | AC57: 0 | AD57: 30.12 | AE57: 0.3075 | AF57: 6.0817 | AG57: 0 | AH57: 0 | AI57: 0 | AJ57: 0 | AK57: 0 | AL57: 0 | AM57: 0 | AN57: 0 | AP57: 0 | AQ57: 0 | AS57: 0 | AT57: 0 | AU57: 0 | AV57: 0 | AW57: 0 | AX57: 0 | AZ57: 0 | BA57: 0 | BB57: 0 | BC57: 0 | BD57: 0 | BE57: 0 | BF57: 0
A58: =B58&E58 -> 46310XXXX-111 | B58: 46310 | C58: ASIN1 | E58: XXXX-111 | G58: 19.99 | H58: 1 | I58: 0 | J58: 0 | K58: 0 | L58: 0 | M58: 0 | N58: 0 | O58: 0 | P58: 0 | Q58: 0 | R58: 0 | S58: 0 | U58: 0 | X58: 0 | Y58: 0 | Z58: 4.4 | AA58: 36 | AB58: 0 | AC58: 0 | AD58: 0 | AE58: 0 | AF58: 0 | AG58: 0 | AH58: 0 | AI58: 0 | AJ58: 0 | AK58: 0 | AL58: 0 | AM58: 0 | AN58: 0 | AP58: 0 | AQ58: 0 | AS58: 0 | AT58: 0 | AU58: 0 | AV58: 0 | AW58: 0 | AX58: 0 | AZ58: 0 | BA58: 0 | BB58: 0 | BC58: 0 | BD58: 0 | BE58: 0 | BF58: 0
A59: =B59&E59
A60: =B60&E60 -> 时间MSKU | B60: 时间 | C60: ASIN | D60: 父ASIN | E60: MSKU | F60: 品名 | G60: 价格 | H60: FBA可售 | I60: FBM可售 | J60: 销量 | K60: 订单量 | L60: 销售额 | M60: 净销售额 | N60: B2B 销量 | O60: B2B 销售额 | P60: B2B 订单量 | Q60: 促销销量 | R60: 促销销售额 | S60: 促销订单量 | T60: 平均客单价 | U60: 平均销量 | X60: 退款量 | Y60: 退款率 | Z60: 评分 | AA60: 评论数 | AB60: 留评率 | AC60: 促销折扣 | AD60: 毛利润 | AE60: 毛利率 | AF60: ROI | AG60: 退货量 | AH60: 退货率 | AI60: Sessions-Browser | AJ60: Sessions-Mobile | AK60: Sessions-Total | AL60: PV-Browser | AM60: PV-Mobile | AN60: PV-Total | AO60: Buybox | AP60: CVR | AQ60: 销量CVR | AR60: CPC | AS60: CTR | AT60: 广告花费 | AU60: ROAS | AV60: ACOS | AW60: ACoAS | AX60: ASoAS | AY60: CPO | AZ60: CPM | BA60: 广告销售额 | BB60: 广告订单量 | BC60: 广告订单占比 | BD60: 广告CVR | BE60: 展示 | BF60: 点击
A61: =B61&E61 -> 46254XXXX-222 | B61: 46254 | C61: ASIN2 | E61: XXXX-222 | G61: 13.99 | H61: 240 | I61: 0 | J61: 0 | K61: 0 | L61: 0 | M61: 0 | N61: 0 | O61: 0 | P61: 0 | Q61: 0 | R61: 0 | S61: 0 | U61: 0 | X61: 0 | Y61: 0 | Z61: 0 | AA61: 0 | AB61: 0 | AC61: 0 | AD61: 0 | AE61: 0 | AF61: 0 | AG61: 0 | AH61: 0 | AI61: 0 | AJ61: 0 | AK61: 0 | AL61: 0 | AM61: 0 | AN61: 0 | AP61: 0 | AQ61: 0 | AS61: 0 | AT61: 0 | AU61: 0 | AV61: 0 | AW61: 0 | AX61: 0 | AZ61: 0 | BA61: 0 | BB61: 0 | BC61: 0 | BD61: 0 | BE61: 0 | BF61: 0
A62: =B62&E62 -> 46255XXXX-222 | B62: 46255 | C62: ASIN2 | E62: XXXX-222 | G62: 13.99 | H62: 284 | I62: 0 | J62: 0 | K62: 0 | L62: 0 | M62: 0 | N62: 0 | O62: 0 | P62: 0 | Q62: 0 | R62: 0 | S62: 0 | U62: 0 | X62: 0 | Y62: 0 | Z62: 0 | AA62: 0 | AB62: 0 | AC62: 0 | AD62: 0 | AE62: 0 | AF62: 0 | AG62: 0 | AH62: 0 | AI62: 0 | AJ62: 0 | AK62: 0 | AL62: 0 | AM62: 0 | AN62: 0 | AP62: 0 | AQ62: 0 | AS62: 0 | AT62: 0 | AU62: 0 | AV62: 0 | AW62: 0 | AX62: 0 | AZ62: 0 | BA62: 0 | BB62: 0 | BC62: 0 | BD62: 0 | BE62: 0 | BF62: 0
A63: =B63&E63 -> 46256XXXX-222 | B63: 46256 | C63: ASIN2 | E63: XXXX-222 | G63: 13.99 | H63: 344 | I63: 0 | J63: 0 | K63: 0 | L63: 0 | M63: 0 | N63: 0 | O63: 0 | P63: 0 | Q63: 0 | R63: 0 | S63: 0 | U63: 0 | X63: 0 | Y63: 0 | Z63: 0 | AA63: 0 | AB63: 0 | AC63: 0 | AD63: 0 | AE63: 0 | AF63: 0 | AG63: 0 | AH63: 0 | AI63: 0 | AJ63: 0 | AK63: 0 | AL63: 0 | AM63: 0 | AN63: 0 | AP63: 0 | AQ63: 0 | AS63: 0 | AT63: 0 | AU63: 0 | AV63: 0 | AW63: 0 | AX63: 0 | AZ63: 0 | BA63: 0 | BB63: 0 | BC63: 0 | BD63: 0 | BE63: 0 | BF63: 0
A64: =B64&E64 -> 46257XXXX-222 | B64: 46257 | C64: ASIN2 | E64: XXXX-222 | G64: 13.99 | H64: 365 | I64: 0 | J64: 1 | K64: 1 | L64: 13.99 | M64: 13.99 | N64: 0 | O64: 0 | P64: 0 | Q64: 0 | R64: 0 | S64: 0 | T64: 13.99 | U64: 0 | X64: 0 | Y64: 0 | Z64: 0 | AA64: 0 | AB64: 0 | AC64: 0 | AD64: -15.72 | AE64: 0 | AF64: -1.6129 | AG64: 0 | AH64: 0 | AI64: 6 | AJ64: 19 | AK64: 25 | AL64: 7 | AM64: 23 | AN64: 30 | AO64: 1 | AP64: 0.04 | AQ64: 0.04 | AR64: 0.98 | AS64: 0.0045 | AT64: -15.72 | AU64: 0 | AV64: 1 | AW64: 1.1237 | AX64: 0 | AZ64: 4.43 | BA64: 0 | BB64: 0 | BC64: 0 | BD64: 0 | BE64: 3551 | BF64: 16
A65: =B65&E65 -> 46258XXXX-222 | B65: 46258 | C65: ASIN2 | E65: XXXX-222 | G65: 13.99 | H65: 364 | I65: 0 | J65: 0 | K65: 0 | L65: 0 | M65: 0 | N65: 0 | O65: 0 | P65: 0 | Q65: 0 | R65: 0 | S65: 0 | U65: 0 | X65: 0 | Y65: 0 | Z65: 0 | AA65: 0 | AB65: 0 | AC65: 0 | AD65: -6.68 | AE65: 0 | AF65: 0 | AG65: 0 | AH65: 0 | AI65: 7 | AJ65: 9 | AK65: 16 | AL65: 7 | AM65: 10 | AN65: 17 | AO65: 1 | AP65: 0 | AQ65: 0 | AR65: 0.83 | AS65: 0.0031 | AT65: -6.68 | AU65: 0 | AV65: 1 | AW65: 1 | AX65: 0 | AZ65: 2.57 | BA65: 0 | BB65: 0 | BC65: 0 | BD65: 0 | BE65: 2595 | BF65: 8
A66: =B66&E66 -> 46259XXXX-222 | B66: 46259 | C66: ASIN2 | E66: XXXX-222 | G66: 13.99 | H66: 379 | I66: 0 | J66: 1 | K66: 1 | L66: 13.99 | M66: 13.99 | N66: 0 | O66: 0 | P66: 0 | Q66: 0 | R66: 0 | S66: 0 | T66: 13.99 | U66: 0 | X66: 0 | Y66: 0 | Z66: 0 | AA66: 0 | AB66: 0 | AC66: 0 | AD66: -25.23 | AE66: 0 | AF66: -4.9819 | AG66: 0 | AH66: 0 | AI66: 11 | AJ66: 17 | AK66: 28 | AL66: 13 | AM66: 24 | AN66: 37 | AO66: 1 | AP66: 0.0357 | AQ66: 0.0357 | AR66: 1.01 | AS66: 0.0059 | AT66: -25.23 | AU66: 1.66 | AV66: 0.6011 | AW66: 1.8034 | AX66: 3 | AY66: 8.41 | AZ66: 5.94 | BA66: 41.97 | BB66: 3 | BC66: 3 | BD66: 0.12 | BE66: 4249 | BF66: 25
A67: =B67&E67 -> 46260XXXX-222 | B67: 46260 | C67: ASIN2 | E67: XXXX-222 | G67: 13.99 | H67: 497 | I67: 0 | J67: 5 | K67: 5 | L67: 69.95 | M67: 69.95 | N67: 0 | O67: 0 | P67: 0 | Q67: 0 | R67: 0 | S67: 0 | T67: 13.99 | U67: 0.1 | X67: 0 | Y67: 0 | Z67: 0 | AA67: 0 | AB67: 0 | AC67: 0 | AD67: -14.15 | AE67: -0.3146 | AF67: 2.369 | AG67: 0 | AH67: 0 | AI67: 14 | AJ67: 23 | AK67: 37 | AL67: 16 | AM67: 31 | AN67: 47 | AO67: 1 | AP67: 0.1351 | AQ67: 0.1351 | AR67: 1.02 | AS67: 0.003 | AT67: -25.39 | AU67: 1.65 | AV67: 0.605 | AW67: 0.363 | AX67: 0.6 | AY67: 8.46 | AZ67: 3.03 | BA67: 41.97 | BB67: 3 | BC67: 0.6 | BD67: 0.12 | BE67: 8366 | BF67: 25
A68: =B68&E68 -> 46261XXXX-222 | B68: 46261 | C68: ASIN2 | E68: XXXX-222 | G68: 13.99 | H68: 513 | I68: 0 | J68: 2 | K68: 2 | L68: 27.98 | M68: 27.98 | N68: 0 | O68: 0 | P68: 0 | Q68: 0 | R68: 0 | S68: 0 | T68: 13.99 | U68: 0 | X68: 0 | Y68: 0 | Z68: 0 | AA68: 0 | AB68: 0 | AC68: 0 | AD68: -11.46 | AE68: -0.2729 | AF68: 0.2559 | AG68: 0 | AH68: 0 | AI68: 11 | AJ68: 36 | AK68: 47 | AL68: 13 | AM68: 42 | AN68: 55 | AO68: 1 | AP68: 0.0426 | AQ68: 0.0426 | AR68: 1.04 | AS68: 0.0043 | AT68: -20.89 | AU68: 0.67 | AV68: 1.4932 | AW68: 0.7466 | AX68: 0.5 | AY68: 20.89 | AZ68: 4.46 | BA68: 13.99 | BB68: 1 | BC68: 0.5 | BD68: 0.05 | BE68: 4684 | BF68: 20
A69: =B69&E69 -> 46262XXXX-222 | B69: 46262 | C69: ASIN2 | E69: XXXX-222 | G69: 13.99 | H69: 551 | I69: 0 | J69: 1 | K69: 1 | L69: 13.99 | M69: 1.68 | N69: 0 | O69: 0 | P69: 0 | Q69: 0 | R69: 0 | S69: 0 | T69: 1.68 | U69: 0 | X69: 1 | Y69: 1 | Z69: 0 | AA69: 0 | AB69: 0 | AC69: 0 | AD69: -27.75 | AE69: -1.9838 | AF69: -2.9768 | AG69: 0 | AH69: 0 | AI69: 16 | AJ69: 34 | AK69: 50 | AL69: 20 | AM69: 43 | AN69: 63 | AO69: 1 | AP69: 0.02 | AQ69: 0.02 | AR69: 0.98 | AS69: 0.0099 | AT69: -19.57 | AU69: 2.14 | AV69: 0.4663 | AW69: 1.3989 | AX69: 3 | AY69: 9.79 | AZ69: 9.65 | BA69: 41.97 | BB69: 2 | BC69: 2 | BD69: 0.1 | BE69: 2027 | BF69: 20
A70: =B70&E70 -> 46263XXXX-222 | B70: 46263 | C70: ASIN2 | E70: XXXX-222 | G70: 13.99 | H70: 550 | I70: 0 | J70: 1 | K70: 1 | L70: 13.99 | M70: 13.99 | N70: 0 | O70: 0 | P70: 0 | Q70: 0 | R70: 0 | S70: 0 | T70: 13.99 | U70: 0 | X70: 0 | Y70: 0 | Z70: 0 | AA70: 0 | AB70: 0 | AC70: 0 | AD70: -11.42 | AE70: -0.408 | AF70: -2.9803 | AG70: 0 | AH70: 0 | AI70: 16 | AJ70: 18 | AK70: 34 | AL70: 21 | AM70: 19 | AN70: 40 | AO70: 1 | AP70: 0.0294 | AQ70: 0.0294 | AR70: 1.03 | AS70: 0.0081 | AT70: -19.58 | AU70: 0.71 | AV70: 1.3996 | AW70: 1.3996 | AX70: 1 | AY70: 19.58 | AZ70: 8.35 | BA70: 13.99 | BB70: 1 | BC70: 1 | BD70: 0.0526 | BE70: 2344 | BF70: 19
A71: =B71&E71 -> 46264XXXX-222 | B71: 46264 | C71: ASIN2 | E71: XXXX-222 | G71: 13.99 | H71: 565 | I71: 0 | J71: 5 | K71: 5 | L71: 69.95 | M71: 69.95 | N71: 0 | O71: 0 | P71: 0 | Q71: 0 | R71: 0 | S71: 0 | T71: 13.99 | U71: 0.1 | X71: 0 | Y71: 0 | Z71: 0 | AA71: 0 | AB71: 0 | AC71: 0 | AD71: -16.15 | AE71: -1.1546 | AF71: 2.5972 | AG71: 0 | AH71: 0 | AI71: 10 | AJ71: 38 | AK71: 48 | AL71: 11 | AM71: 46 | AN71: 57 | AO71: 1 | AP71: 0.1042 | AQ71: 0.1042 | AR71: 1.18 | AS71: 0.0063 | AT71: -20.08 | AU71: 0.7 | AV71: 1.4353 | AW71: 0.2871 | AX71: 0.2 | AY71: 20.08 | AZ71: 7.49 | BA71: 13.99 | BB71: 1 | BC71: 0.2 | BD71: 0.0588 | BE71: 2680 | BF71: 17
A72: =B72&E72 -> 46265XXXX-222 | B72: 46265 | C72: ASIN2 | E72: XXXX-222 | G72: 13.99 | H72: 644 | I72: 0 | J72: 3 | K72: 3 | L72: 41.97 | M72: 41.97 | N72: 0 | O72: 0 | P72: 0 | Q72: 0 | R72: 0 | S72: 0 | T72: 13.99 | U72: 0.1 | X72: 0 | Y72: 0 | Z72: 0 | AA72: 0 | AB72: 0 | AC72: 0 | AD72: -8.25 | AE72: -0.1924 | AF72: 1.5743 | AG72: 0 | AH72: 0 | AI72: 17 | AJ72: 45 | AK72: 62 | AL72: 18 | AM72: 57 | AN72: 75 | AO72: 1 | AP72: 0.0484 | AQ72: 0.0484 | AR72: 1.12 | AS72: 0.0044 | AT72: -20.17 | AU72: 0 | AV72: 1 | AW72: 0.4806 | AX72: 0 | AZ72: 4.97 | BA72: 0 | BB72: 0 | BC72: 0 | BD72: 0 | BE72: 4058 | BF72: 18
A73: =B73&E73 -> 46266XXXX-222 | B73: 46266 | C73: ASIN2 | E73: XXXX-222 | G73: 13.99 | H73: 780 | I73: 0 | J73: 5 | K73: 5 | L73: 69.95 | M73: 69.95 | N73: 0 | O73: 0 | P73: 0 | Q73: 0 | R73: 0 | S73: 0 | T73: 13.99 | U73: 0.1 | X73: 0 | Y73: 0 | Z73: 0 | AA73: 0 | AB73: 0 | AC73: 0 | AD73: 12.65 | AE73: 0.1005 | AF73: 2.4788 | AG73: 0 | AH73: 0 | AI73: 13 | AJ73: 39 | AK73: 52 | AL73: 17 | AM73: 52 | AN73: 69 | AO73: 1 | AP73: 0.0962 | AQ73: 0.0962 | AR73: 1.16 | AS73: 0.0053 | AT73: -20.85 | AU73: 2.01 | AV73: 0.4968 | AW73: 0.2981 | AX73: 0.6 | AY73: 6.95 | AZ73: 6.19 | BA73: 41.97 | BB73: 3 | BC73: 0.6 | BD73: 0.1667 | BE73: 3370 | BF73: 18
A74: =B74&E74 -> 46267XXXX-222 | B74: 46267 | C74: ASIN2 | E74: XXXX-222 | G74: 13.99 | H74: 819 | I74: 0 | J74: 3 | K74: 3 | L74: 41.97 | M74: 41.97 | N74: 0 | O74: 0 | P74: 0 | Q74: 0 | R74: 0 | S74: 0 | T74: 13.99 | U74: 0.1 | X74: 0 | Y74: 0 | Z74: 0 | AA74: 0 | AB74: 0 | AC74: 0 | AD74: -15.83 | AE74: -1.1317 | AF74: 1.6499 | AG74: 0 | AH74: 0 | AI74: 19 | AJ74: 42 | AK74: 61 | AL74: 25 | AM74: 48 | AN74: 73 | AO74: 1 | AP74: 0.0492 | AQ74: 0.0492 | AR74: 1.15 | AS74: 0.0082 | AT74: -19.53 | AU74: 0.72 | AV74: 1.396 | AW74: 0.4653 | AX74: 0.3333 | AY74: 19.53 | AZ74: 9.37 | BA74: 13.99 | BB74: 1 | BC74: 0.3333 | BD74: 0.0588 | BE74: 2085 | BF74: 17
A75: =B75&E75 -> 46268XXXX-222 | B75: 46268 | C75: ASIN2 | E75: XXXX-222 | G75: 13.99 | H75: 816 | I75: 0 | J75: 2 | K75: 2 | L75: 27.98 | M75: 27.98 | N75: 0 | O75: 0 | P75: 0 | Q75: 0 | R75: 0 | S75: 0 | T75: 13.99 | U75: 0 | X75: 0 | Y75: 0 | Z75: 0 | AA75: 0 | AB75: 0 | AC75: 0 | AD75: -16.01 | AE75: -1.1446 | AF75: 0.4613 | AG75: 0 | AH75: 0 | AI75: 12 | AJ75: 69 | AK75: 81 | AL75: 19 | AM75: 89 | AN75: 108 | AO75: 1 | AP75: 0.0247 | AQ75: 0.0247 | AR75: 1.16 | AS75: 0.0078 | AT75: -19.73 | AU75: 1.42 | AV75: 0.7051 | AW75: 0.7051 | AX75: 1 | AY75: 9.87 | AZ75: 9.09 | BA75: 27.98 | BB75: 2 | BC75: 1 | BD75: 0.1176 | BE75: 2171 | BF75: 17
A76: =B76&E76 -> 46269XXXX-222 | B76: 46269 | C76: ASIN2 | E76: XXXX-222 | G76: 13.99 | H76: 803 | I76: 0 | J76: 11 | K76: 11 | L76: 153.89 | M76: 141.58 | N76: 1 | O76: 13.99 | P76: 1 | Q76: 0 | R76: 0 | S76: 0 | T76: 12.87 | U76: 0.2 | X76: 1 | Y76: 0.0909 | Z76: 0 | AA76: 0 | AB76: 0 | AC76: 0 | AD76: -13.09 | AE76: -0.1872 | AF76: 3.3358 | AG76: 0 | AH76: 0 | AI76: 28 | AJ76: 62 | AK76: 90 | AL76: 40 | AM76: 80 | AN76: 120 | AO76: 1 | AP76: 0.1222 | AQ76: 0.1222 | AR76: 1.13 | AS76: 0.0078 | AT76: -19.26 | AU76: 2.18 | AV76: 0.4589 | AW76: 0.1252 | AX76: 0.2727 | AY76: 6.42 | AZ76: 8.85 | BA76: 41.97 | BB76: 3 | BC76: 0.2727 | BD76: 0.1765 | BE76: 2177 | BF76: 17
A77: =B77&E77 -> 46270XXXX-222 | B77: 46270 | C77: ASIN2 | E77: XXXX-222 | G77: 13.99 | H77: 827 | I77: 0 | J77: 11 | K77: 11 | L77: 153.89 | M77: 153.89 | N77: 1 | O77: 13.99 | P77: 1 | Q77: 0 | R77: 0 | S77: 0 | T77: 13.99 | U77: 0.2 | X77: 0 | Y77: 0 | Z77: 0 | AA77: 0 | AB77: 0 | AC77: 0 | AD77: 6.5 | AE77: 0.0644 | AF77: 3.4089 | AG77: 0 | AH77: 0 | AI77: 37 | AJ77: 92 | AK77: 129 | AL77: 46 | AM77: 117 | AN77: 163 | AO77: 1 | AP77: 0.0853 | AQ77: 0.0853 | AR77: 1.18 | AS77: 0.0036 | AT77: -19.98 | AU77: 0.7 | AV77: 1.4282 | AW77: 0.1298 | AX77: 0.0909 | AY77: 19.98 | AZ77: 4.22 | BA77: 13.99 | BB77: 1 | BC77: 0.0909 | BD77: 0.0588 | BE77: 4737 | BF77: 17
A78: =B78&E78 -> 46271XXXX-222 | B78: 46271 | C78: ASIN2 | E78: XXXX-222 | G78: 13.99 | H78: 859 | I78: 0 | J78: 10 | K78: 7 | L78: 139.9 | M78: 139.9 | N78: 4 | O78: 55.96 | P78: 1 | Q78: 0 | R78: 0 | S78: 0 | T78: 13.99 | U78: 0.2 | X78: 0 | Y78: 0 | Z78: 0 | AA78: 0 | AB78: 0 | AC78: 0 | AD78: 58.96 | AE78: 0.281 | AF78: 3.9561 | AG78: 1 | AH78: 0.1 | AI78: 12 | AJ78: 65 | AK78: 77 | AL78: 15 | AM78: 80 | AN78: 95 | AO78: 1 | AP78: 0.0909 | AQ78: 0.1299 | AS78: 0 | AT78: 0 | AU78: 0 | AV78: 0 | AW78: 0 | AX78: 0 | AZ78: 0 | BA78: 0 | BB78: 0 | BC78: 0 | BD78: 0 | BE78: 299 | BF78: 0
A79: =B79&E79 -> 46272XXXX-222 | B79: 46272 | C79: ASIN2 | E79: XXXX-222 | G79: 13.99 | H79: 886 | I79: 0 | J79: 4 | K79: 4 | L79: 55.96 | M79: 55.96 | N79: 1 | O79: 13.99 | P79: 1 | Q79: 0 | R79: 0 | S79: 0 | T79: 13.99 | U79: 0.1 | X79: 0 | Y79: 0 | Z79: 0 | AA79: 0 | AB79: 0 | AC79: 0 | AD79: 25.87 | AE79: 0.2642 | AF79: 3.9561 | AG79: 0 | AH79: 0 | AI79: 16 | AJ79: 46 | AK79: 62 | AL79: 20 | AM79: 61 | AN79: 81 | AO79: 1 | AP79: 0.0645 | AQ79: 0.0645 | AS79: 0 | AT79: 0 | AU79: 0 | AV79: 0 | AW79: 0 | AX79: 0 | AZ79: 0 | BA79: 0 | BB79: 0 | BC79: 0 | BD79: 0 | BE79: 0 | BF79: 0
A80: =B80&E80 -> 46273XXXX-222 | B80: 46273 | C80: ASIN2 | E80: XXXX-222 | G80: 13.99 | H80: 882 | I80: 0 | J80: 4 | K80: 4 | L80: 55.96 | M80: 31.34 | N80: 0 | O80: 0 | P80: 0 | Q80: 0 | R80: 0 | S80: 0 | T80: 7.84 | U80: 0.1 | X80: 2 | Y80: 0.5 | Z80: 0 | AA80: 0 | AB80: 0 | AC80: 0 | AD80: -2.77 | AE80: -0.033 | AF80: 3.9561 | AG80: 0 | AH80: 0 | AI80: 20 | AJ80: 41 | AK80: 61 | AL80: 25 | AM80: 50 | AN80: 75 | AO80: 1 | AP80: 0.0656 | AQ80: 0.0656 | AS80: 0 | AT80: 0 | AU80: 0 | AV80: 0 | AW80: 0 | AX80: 0 | AZ80: 0 | BA80: 0 | BB80: 0 | BC80: 0 | BD80: 0 | BE80: 0 | BF80: 0
A81: =B81&E81 -> 46274XXXX-222 | B81: 46274 | C81: ASIN2 | E81: XXXX-222 | G81: 13.99 | H81: 878 | I81: 0 | J81: 5 | K81: 5 | L81: 69.95 | M81: 69.95 | N81: 0 | O81: 0 | P81: 0 | Q81: 0 | R81: 0 | S81: 0 | T81: 13.99 | U81: 0.1 | X81: 0 | Y81: 0 | Z81: 3 | AA81: 1 | AB81: 0 | AC81: 0 | AD81: 11.21 | AE81: 0.2671 | AF81: 3.9561 | AG81: 0 | AH81: 0 | AI81: 14 | AJ81: 44 | AK81: 58 | AL81: 16 | AM81: 53 | AN81: 69 | AO81: 1 | AP81: 0.0862 | AQ81: 0.0862 | AS81: 0 | AT81: 0 | AU81: 0 | AV81: 0 | AW81: 0 | AX81: 0 | AZ81: 0 | BA81: 0 | BB81: 0 | BC81: 0 | BD81: 0 | BE81: 0 | BF81: 0
A82: =B82&E82 -> 46275XXXX-222 | B82: 46275 | C82: ASIN2 | E82: XXXX-222 | G82: 13.99 | H82: 872 | I82: 0 | J82: 5 | K82: 5 | L82: 69.95 | M82: 69.95 | N82: 0 | O82: 0 | P82: 0 | Q82: 0 | R82: 0 | S82: 0 | T82: 13.99 | U82: 0.1 | X82: 0 | Y82: 0 | Z82: 3 | AA82: 1 | AB82: 0 | AC82: 0 | AD82: 14.94 | AE82: 0.267 | AF82: 3.9561 | AG82: 1 | AH82: 0.2 | AI82: 16 | AJ82: 51 | AK82: 67 | AL82: 19 | AM82: 63 | AN82: 82 | AO82: 1 | AP82: 0.0746 | AQ82: 0.0746 | AS82: 0 | AT82: 0 | AU82: 0 | AV82: 0 | AW82: 0 | AX82: 0 | AZ82: 0 | BA82: 0 | BB82: 0 | BC82: 0 | BD82: 0 | BE82: 0 | BF82: 0
A83: =B83&E83 -> 46276XXXX-222 | B83: 46276 | C83: ASIN2 | E83: XXXX-222 | G83: 13.99 | H83: 861 | I83: 0 | J83: 10 | K83: 10 | L83: 139.9 | M83: 139.9 | N83: 0 | O83: 0 | P83: 0 | Q83: 0 | R83: 0 | S83: 0 | T83: 13.99 | U83: 0.2 | X83: 0 | Y83: 0 | Z83: 3 | AA83: 1 | AB83: 0 | AC83: 0 | AD83: 22.91 | AE83: 0.273 | AF83: 3.9561 | AG83: 0 | AH83: 0 | AI83: 19 | AJ83: 62 | AK83: 81 | AL83: 23 | AM83: 77 | AN83: 100 | AO83: 1 | AP83: 0.1235 | AQ83: 0.1235 | AS83: 0 | AT83: 0 | AU83: 0 | AV83: 0 | AW83: 0 | AX83: 0 | AZ83: 0 | BA83: 0 | BB83: 0 | BC83: 0 | BD83: 0 | BE83: 0 | BF83: 0
A84: =B84&E84 -> 46277XXXX-222 | B84: 46277 | C84: ASIN2 | E84: XXXX-222 | G84: 13.99 | H84: 859 | I84: 0 | J84: 5 | K84: 5 | L84: 69.95 | M84: 69.95 | N84: 0 | O84: 0 | P84: 0 | Q84: 0 | R84: 0 | S84: 0 | T84: 13.99 | U84: 0.1 | X84: 0 | Y84: 0 | Z84: 4.6 | AA84: 16 | AB84: 0 | AC84: 0 | AD84: 34.8 | AE84: 0.2764 | AF84: 3.9561 | AG84: 0 | AH84: 0 | AI84: 19 | AJ84: 37 | AK84: 56 | AL84: 25 | AM84: 48 | AN84: 73 | AO84: 1 | AP84: 0.0893 | AQ84: 0.0893 | AS84: 0 | AT84: 0 | AU84: 0 | AV84: 0 | AW84: 0 | AX84: 0 | AZ84: 0 | BA84: 0 | BB84: 0 | BC84: 0 | BD84: 0 | BE84: 0 | BF84: 0
A85: =B85&E85 -> 46278XXXX-222 | B85: 46278 | C85: ASIN2 | E85: XXXX-222 | G85: 13.99 | H85: 849 | I85: 0 | J85: 10 | K85: 10 | L85: 139.9 | M85: 139.9 | N85: 1 | O85: 13.99 | P85: 1 | Q85: 0 | R85: 0 | S85: 0 | T85: 13.99 | U85: 0.2 | X85: 0 | Y85: 0 | Z85: 4.6 | AA85: 16 | AB85: 0 | AC85: 0 | AD85: 23.13 | AE85: 0.2756 | AF85: 3.9823 | AG85: 0 | AH85: 0 | AI85: 29 | AJ85: 31 | AK85: 60 | AL85: 44 | AM85: 38 | AN85: 82 | AO85: 1 | AP85: 0.1667 | AQ85: 0.1667 | AS85: 0 | AT85: 0 | AU85: 0 | AV85: 0 | AW85: 0 | AX85: 0 | AZ85: 0 | BA85: 0 | BB85: 0 | BC85: 0 | BD85: 0 | BE85: 0 | BF85: 0
A86: =B86&E86 -> 46279XXXX-222 | B86: 46279 | C86: ASIN2 | E86: XXXX-222 | G86: 13.99 | H86: 827 | I86: 0 | J86: 6 | K86: 6 | L86: 83.94 | M86: 71.63 | N86: 1 | O86: 13.99 | P86: 1 | Q86: 0 | R86: 0 | S86: 0 | T86: 11.94 | U86: 0.1 | X86: 1 | Y86: 0.1667 | Z86: 4.6 | AA86: 16 | AB86: 0 | AC86: 0 | AD86: 11.57 | AE86: 0.1379 | AF86: 3.9561 | AG86: 0 | AH86: 0 | AI86: 22 | AJ86: 49 | AK86: 71 | AL86: 31 | AM86: 57 | AN86: 88 | AO86: 1 | AP86: 0.0845 | AQ86: 0.0845 | AS86: 0 | AT86: 0 | AU86: 0 | AV86: 0 | AW86: 0 | AX86: 0 | AZ86: 0 | BA86: 0 | BB86: 0 | BC86: 0 | BD86: 0 | BE86: 0 | BF86: 0
A87: =B87&E87 -> 46280XXXX-222 | B87: 46280 | C87: ASIN2 | E87: XXXX-222 | G87: 13.99 | H87: 821 | I87: 0 | J87: 14 | K87: 13 | L87: 195.86 | M87: 183.55 | N87: 0 | O87: 0 | P87: 0 | Q87: 0 | R87: 0 | S87: 0 | T87: 13.11 | U87: 0.2 | X87: 1 | Y87: 0.0714 | Z87: 4.6 | AA87: 16 | AB87: 0 | AC87: 0 | AD87: 22.84 | AE87: 0.1455 | AF87: 4.0158 | AG87: 1 | AH87: 0.0714 | AI87: 22 | AJ87: 50 | AK87: 72 | AL87: 29 | AM87: 61 | AN87: 90 | AO87: 1 | AP87: 0.1806 | AQ87: 0.1944 | AS87: 0 | AT87: 0 | AU87: 0 | AV87: 0 | AW87: 0 | AX87: 0 | AZ87: 0 | BA87: 0 | BB87: 0 | BC87: 0 | BD87: 0 | BE87: 0 | BF87: 0
A88: =B88&E88 -> 46281XXXX-222 | B88: 46281 | C88: ASIN2 | E88: XXXX-222 | G88: 13.99 | H88: 812 | I88: 0 | J88: 7 | K88: 7 | L88: 97.93 | M88: 85.62 | N88: 0 | O88: 0 | P88: 0 | Q88: 0 | R88: 0 | S88: 0 | T88: 12.23 | U88: 0.1 | X88: 1 | Y88: 0.1429 | Z88: 4.6 | AA88: 16 | AB88: 0 | AC88: 0 | AD88: 40.45 | AE88: 0.2065 | AF88: 3.9561 | AG88: 0 | AH88: 0 | AI88: 15 | AJ88: 52 | AK88: 67 | AL88: 17 | AM88: 65 | AN88: 82 | AO88: 1 | AP88: 0.1045 | AQ88: 0.1045 | AS88: 0 | AT88: 0 | AU88: 0 | AV88: 0 | AW88: 0 | AX88: 0 | AZ88: 0 | BA88: 0 | BB88: 0 | BC88: 0 | BD88: 0 | BE88: 0 | BF88: 0
A89: =B89&E89 -> 46282XXXX-222 | B89: 46282 | C89: ASIN2 | E89: XXXX-222 | G89: 13.99 | H89: 804 | I89: 0 | J89: 8 | K89: 8 | L89: 111.92 | M89: 111.92 | N89: 0 | O89: 0 | P89: 0 | Q89: 0 | R89: 0 | S89: 0 | T89: 13.99 | U89: 0.1 | X89: 0 | Y89: 0 | Z89: 4.6 | AA89: 16 | AB89: 0 | AC89: 0 | AD89: 30.44 | AE89: 0.272 | AF89: 3.9561 | AG89: 0 | AH89: 0 | AI89: 21 | AJ89: 70 | AK89: 91 | AL89: 27 | AM89: 85 | AN89: 112 | AO89: 1 | AP89: 0.0879 | AQ89: 0.0879 | AS89: 0 | AT89: 0 | AU89: 0 | AV89: 0 | AW89: 0 | AX89: 0 | AZ89: 0 | BA89: 0 | BB89: 0 | BC89: 0 | BD89: 0 | BE89: 0 | BF89: 0
... A111: =B111&E111 -> 46304XXXX-222 | B111: 46304 | C111: ASIN2 | E111: XXXX-222 | G111: 11.99 | H111: 504 | I111: 0 | J111: 24 | K111: 24 | L111: 273.76 | M111: 273.76 | N111: 0 | O111: 0 | P111: 0 | Q111: 0 | R111: 0 | S111: 0 | T111: 11.41 | U111: 0.4 | X111: 0 | Y111: 0 | Z111: 4.4 | AA111: 30 | AB111: 0 | AC111: 0 | AD111: 48.74 | AE111: 0.1983 | AF111: 0.7515 | AG111: 0 | AH111: 0 | AI111: 41 | AJ111: 91 | AK111: 132 | AL111: 56 | AM111: 119 | AN111: 175 | AO111: 1 | AP111: 0.1818 | AQ111: 0.1818 | AS111: 0 | AT111: 0 | AU111: 0 | AV111: 0 | AW111: 0 | AX111: 0 | AZ111: 0 | BA111: 0 | BB111: 0 | BC111: 0 | BD111: 0 | BE111: 0 | BF111: 0
A112: =B112&E112 -> 46305XXXX-222 | B112: 46305 | C112: ASIN2 | E112: XXXX-222 | G112: 9.99 | H112: 471 | I112: 0 | J112: 18 | K112: 18 | L112: 179.82 | M112: 169.27 | N112: 0 | O112: 0 | P112: 0 | Q112: 0 | R112: 0 | S112: 0 | T112: 9.4 | U112: 0.3 | X112: 1 | Y112: 0.0556 | Z112: 4.4 | AA112: 33 | AB112: 0 | AC112: 0 | AD112: 20.23 | AE112: 0.0686 | AF112: 0.1911 | AG112: 1 | AH112: 0.0556 | AI112: 57 | AJ112: 111 | AK112: 168 | AL112: 69 | AM112: 133 | AN112: 202 | AO112: 1 | AP112: 0.1071 | AQ112: 0.1071 | AR112: 0.85 | AS112: 0.0113 | AT112: -6.8 | AU112: 1.47 | AV112: 0.6807 | AW112: 0.0378 | AX112: 0.0556 | AY112: 3.4 | AZ112: 9.6 | BA112: 9.99 | BB112: 2 | BC112: 0.1111 | BD112: 0.25 | BE112: 708 | BF112: 8
A113: =B113&E113 -> 46306XXXX-222 | B113: 46306 | C113: ASIN2 | E113: XXXX-222 | G113: 9.99 | H113: 444 | I113: 0 | J113: 38 | K113: 38 | L113: 379.62 | M113: 358.52 | N113: 5 | O113: 49.95 | P113: 5 | Q113: 0 | R113: 0 | S113: 0 | T113: 9.43 | U113: 0.7 | X113: 2 | Y113: 0.0526 | Z113: 4.4 | AA113: 33 | AB113: 0 | AC113: 0 | AD113: -12.84 | AE113: -0.0409 | AF113: 0.1297 | AG113: 1 | AH113: 0.0263 | AI113: 62 | AJ113: 96 | AK113: 158 | AL113: 94 | AM113: 132 | AN113: 226 | AO113: 0.99 | AP113: 0.2405 | AQ113: 0.2405 | AR113: 0.85 | AS113: 0.0057 | AT113: -27.19 | AU113: 0.37 | AV113: 2.7217 | AW113: 0.0716 | AX113: 0.0263 | AY113: 27.19 | AZ113: 4.84 | BA113: 9.99 | BB113: 1 | BC113: 0.0263 | BD113: 0.0312 | BE113: 5618 | BF113: 32
A114: =B114&E114 -> 46307XXXX-222 | B114: 46307 | C114: ASIN2 | E114: XXXX-222 | G114: 9.99 | H114: 417 | I114: 0 | J114: 34 | K114: 33 | L114: 329.67 | M114: 306.81 | N114: 2 | O114: 19.98 | P114: 2 | Q114: 0 | R114: 0 | S114: 0 | T114: 9.02 | U114: 0.6 | X114: 2 | Y114: 0.0588 | Z114: 4.4 | AA114: 33 | AB114: 0 | AC114: 0 | AD114: -47.36 | AE114: -0.173 | AF114: 0.1019 | AG114: 1 | AH114: 0.0294 | AI114: 40 | AJ114: 101 | AK114: 141 | AL114: 48 | AM114: 128 | AN114: 176 | AO114: 1 | AP114: 0.234 | AQ114: 0.2411 | AR114: 0.84 | AS114: 0.0073 | AT114: -30.18 | AU114: 2.85 | AV114: 0.3512 | AW114: 0.0915 | AX114: 0.2607 | AY114: 4.31 | AZ114: 6.1 | BA114: 85.93 | BB114: 7 | BC114: 0.2121 | BD114: 0.1944 | BE114: 4948 | BF114: 36
A115: =B115&E115 -> 46308XXXX-222 | B115: 46308 | C115: ASIN2 | E115: XXXX-222 | G115: 9.99 | H115: 385 | I115: 0 | J115: 27 | K115: 23 | L115: 269.73 | M115: 260.94 | N115: 3 | O115: 29.97 | P115: 1 | Q115: 0 | R115: 0 | S115: 0 | T115: 9.66 | U115: 0.5 | X115: 1 | Y115: 0.037 | Z115: 4.4 | AA115: 36 | AB115: 0 | AC115: 0 | AD115: -20.93 | AE115: -0.0771 | AF115: 1.0938 | AG115: 0 | AH115: 0 | AI115: 61 | AJ115: 81 | AK115: 142 | AL115: 81 | AM115: 102 | AN115: 183 | AO115: 0.99 | AP115: 0.162 | AQ115: 0.1901 | AR115: 0.78 | AS115: 0.0049 | AT115: -28.91 | AU115: 2.7 | AV115: 0.371 | AW115: 0.1072 | AX115: 0.2889 | AY115: 3.61 | AZ115: 3.81 | BA115: 77.92 | BB115: 8 | BC115: 0.3478 | BD115: 0.2162 | BE115: 7592 | BF115: 37
A116: =B116&E116 -> 46309XXXX-222 | B116: 46309 | C116: ASIN2 | E116: XXXX-222 | G116: 9.99 | H116: 355 | I116: 0 | J116: 28 | K116: 26 | L116: 279.72 | M116: 279.72 | N116: 1 | O116: 9.99 | P116: 1 | Q116: 0 | R116: 0 | S116: 0 | T116: 9.99 | U116: 0.5 | X116: 1 | Y116: 0.0357 | Z116: 4.4 | AA116: 36 | AB116: 0 | AC116: 0 | AD116: -36.52 | AE116: -0.7312 | AF116: 2.1829 | AG116: 0 | AH116: 0 | AI116: 0 | AJ116: 0 | AK116: 0 | AL116: 0 | AM116: 0 | AN116: 0 | AP116: 0 | AQ116: 0 | AR116: 0.98 | AS116: 0.0035 | AT116: -33.32 | AU116: 1.5 | AV116: 0.6671 | AW116: 0.1191 | AX116: 0.1786 | AY116: 6.66 | AZ116: 3.38 | BA116: 49.95 | BB116: 5 | BC116: 0.1923 | BD116: 0.1471 | BE116: 9844 | BF116: 34
A117: =B117&E117 -> 46310XXXX-222 | B117: 46310 | C117: ASIN2 | E117: XXXX-222 | G117: 9.99 | H117: 342 | I117: 0 | J117: 0 | K117: 0 | L117: 0 | M117: 0 | N117: 0 | O117: 0 | P117: 0 | Q117: 0 | R117: 0 | S117: 0 | U117: 0 | X117: 0 | Y117: 0 | Z117: 4.4 | AA117: 36 | AB117: 0 | AC117: 0 | AD117: 0 | AE117: 0 | AF117: 0 | AG117: 0 | AH117: 0 | AI117: 0 | AJ117: 0 | AK117: 0 | AL117: 0 | AM117: 0 | AN117: 0 | AP117: 0 | AQ117: 0 | AS117: 0 | AT117: 0 | AU117: 0 | AV117: 0 | AW117: 0 | AX117: 0 | AZ117: 0 | BA117: 0 | BB117: 0 | BC117: 0 | BD117: 0 | BE117: 0 | BF117: 0
