Workbook

Sheet 阶段实际盈亏
A1: 时间 | B1: 实际 | C1: 价格 | D1: 站内 coupon | E1: 站内 code | F1: 站外 折扣 | G1: 站外 订单 | H1: 站内 自然单 | I1: 站内 广告单 | J1: 阶段 销售 订单 | K1: 时间 /天 | L1: 阶段广告费 （出1单广告单预估） | M1: 阶段站外费用 （5美金/单） | N1: 阶段订单 盈亏 | O1: 阶段亏损 /美金 | P1: 六阶段 总亏损 | Q1: 资金ROI | R1: 阶段日均 订单 | S1: 阶段日均 广告订单 | T1: 阶段日均 自然订单 | U1: 新品 排行榜 | V1: 小类目 排名
A2: 9月7-9月12 | B2: 第一阶段 | C2: 89.99 | D2: 0.05 | E2: 0.5 | F2: 0.68 | G2: 58 | H2: 10 | I2: 20 | J2: =SUM(G2:I2) -> 88 | K2: 6 | L2: =5*I2 -> 100 | M2: =5*G2 -> 290 | N2: =SUM(J2) -> 88 | O2: =SUM(L2:N2) -> 478 | P2: =SUM(L2:O2) -> 956 | R2: =J2/7 -> 12.571429 | S2: =I2/7 -> 2.8571429 | T2: =H2/7 -> 1.4285714 | V2: 25
A3: 9月13-9月21 | B3: 第二阶段 | C3: 79.99 | D3: 0.3 | E3: 0.2 | F3: 0.3 | G3: 81 | H3: 14 | I3: 20 | J3: =SUM(G3:I3) -> 115 | K3: 9 | L3: =5*I3 -> 100 | M3: =5*G3 -> 405 | N3: =SUM(J3) -> 115 | O3: =SUM(L3:N3) -> 620 | P3: =SUM(L3:O3) -> 1240 | R3: =J3/7 -> 16.428571 | S3: =I3/7 -> 2.8571429 | T3: =H3/7 -> 2 | V3: 22
A4: 9月22-10月1 | B4: 第三阶段 | C4: 69.99 | D4: 0.3 | E4: 0.2 | F4: 0.25 | G4: 45 | H4: 60 | I4: 23 | J4: =SUM(G4:I4) -> 128 | K4: 10 | L4: =5*I4 -> 115 | M4: =5*G4 -> 225 | N4: =SUM(J4) -> 128 | O4: =SUM(L4:N4) -> 468 | P4: =SUM(L4:O4) -> 936 | R4: =J4/7 -> 18.285714 | S4: =I4/7 -> 3.2857143 | T4: =H4/7 -> 8.5714286 | V4: 20
A5: 10月2-10月11 | B5: 第四阶段 | C5: 69.99 | D5: 0.3 | E5: 0 | F5: 0.25 | G5: 55 | H5: 65 | I5: 30 | J5: =SUM(G5:I5) -> 150 | K5: 10 | L5: =5*I5 -> 150 | M5: =5*G5 -> 275 | N5: =SUM(J5) -> 150 | O5: =SUM(L5:N5) -> 575 | P5: =SUM(L5:O5) -> 1150 | R5: =J5/7 -> 21.428571 | S5: =I5/7 -> 4.2857143 | T5: =H5/7 -> 9.2857143 | V5: 18
A6: 10月12-10月21 | B6: 第五阶段 | C6: 69.99 | D6: 0.3 | E6: 0 | F6: 0.25 | G6: 60 | H6: 70 | I6: 30 | J6: =SUM(G6:I6) -> 160 | K6: 10 | L6: =5*I6 -> 150 | M6: =5*G6 -> 300 | N6: =SUM(J6) -> 160 | O6: =SUM(L6:N6) -> 610 | P6: =SUM(L6:O6) -> 1220 | R6: =J6/7 -> 22.857143 | S6: =I6/7 -> 4.2857143 | T6: =H6/7 -> 10 | V6: 16
A7: 10月22-10月31 | B7: 第六阶段 | C7: 69.99 | D7: 0.3 | E7: 0 | F7: 0 | G7: 65 | H7: 80 | I7: 35 | J7: =SUM(G7:I7) -> 180 | K7: 12 | L7: =5*I7 -> 175 | M7: =5*G7 -> 325 | N7: =SUM(J7) -> 180 | O7: =SUM(L7:N7) -> 680 | P7: =SUM(L7:O7) -> 1360 | R7: =J7/7 -> 25.714286 | S7: =I7/7 -> 5 | T7: =H7/7 -> 11.428571 | V7: 10
A8: 稳定期
A9: 11月1-11月30 | B9: 十一月份 | C9: 69.99 | D9: 0.2 | E9: 0 | F9: 0 | G9: 70 | H9: 85 | I9: 30 | J9: =SUM(G9:I9) -> 185 | K9: 14 | L9: =5*I9 -> 150 | M9: =5*G9 -> 350 | N9: =SUM(J9) -> 185 | O9: =SUM(L9:N9) -> 685 | P9: =SUM(L9:O9) -> 1370 | R9: =J9/7 -> 26.428571 | S9: =I9/7 -> 4.2857143 | T9: =H9/7 -> 12.142857 | V9: 5
A10: 12月1-12月31 | B10: 十二月份 | C10: 69.99 | D10: 0.2 | E10: 0 | F10: 0 | G10: 75 | H10: 90 | I10: 30 | J10: =SUM(G10:I10) -> 195 | K10: 15 | L10: =5*I10 -> 150 | M10: =5*G10 -> 375 | N10: =SUM(J10) -> 195 | O10: =SUM(L10:N10) -> 720 | P10: =SUM(L10:O10) -> 1440 | R10: =J10/7 -> 27.857143 | S10: =I10/7 -> 4.2857143 | T10: =H10/7 -> 12.857143 | V10: 4
A11: 1月1-1月31 | B11: 一月份 | C11: 69.99 | D11: 0.2 | E11: 0 | F11: 0 | G11: 80 | H11: 100 | I11: 30 | J11: =SUM(G11:I11) -> 210 | K11: 16 | L11: =5*I11 -> 150 | M11: =5*G11 -> 400 | N11: =SUM(J11) -> 210 | O11: =SUM(L11:N11) -> 760 | P11: =SUM(L11:O11) -> 1520 | R11: =J11/7 -> 30 | S11: =I11/7 -> 4.2857143 | T11: =H11/7 -> 14.285714 | V11: 3
A12: 2月1-2月28 | B12: 二月份 | C12: 69.99 | D12: 0.2 | E12: 0 | F12: 0 | G12: 80 | H12: 100 | I12: 30 | J12: =SUM(G12:I12) -> 210 | K12: 16 | L12: =5*I12 -> 150 | M12: =5*G12 -> 400 | N12: =SUM(J12) -> 210 | O12: =SUM(L12:N12) -> 760 | P12: =SUM(L12:O12) -> 1520 | R12: =J12/7 -> 30 | S12: =I12/7 -> 4.2857143 | T12: =H12/7 -> 14.285714 | V12: 1
A14: 新品迭代期
A15: 3月1-3月28 | B15: 第一阶段 | C15: 99.99 | D15: 0.05 | E15: 0.5 | F15: 0.68 | G15: 58 | H15: 10 | I15: 20 | J15: =SUM(G15:I15) -> 88 | K15: 6 | L15: =5*I15 -> 100 | M15: =5*G15 -> 290 | N15: =SUM(J15) -> 88 | O15: =SUM(L15:N15) -> 478 | P15: =SUM(L15:O15) -> 956 | R15: =J15/7 -> 12.571429 | S15: =I15/7 -> 2.8571429 | T15: =H15/7 -> 1.4285714 | V15: 50
A16: 4月1-4月28 | B16: 第二阶段 | C16: 79.99 | D16: 0.3 | E16: 0.2 | F16: 0.3 | G16: 81 | H16: 14 | I16: 20 | J16: =SUM(G16:I16) -> 115 | K16: 9 | L16: =5*I16 -> 100 | M16: =5*G16 -> 405 | N16: =SUM(J16) -> 115 | O16: =SUM(L16:N16) -> 620 | P16: =SUM(L16:O16) -> 1240 | R16: =J16/7 -> 16.428571 | S16: =I16/7 -> 2.8571429 | T16: =H16/7 -> 2 | V16: 32
A17: 5月1-5月28 | B17: 第三阶段 | C17: 69.99 | D17: 0.3 | E17: 0.2 | F17: 0.25 | G17: 45 | H17: 60 | I17: 23 | J17: =SUM(G17:I17) -> 128 | K17: 10 | L17: =5*I17 -> 115 | M17: =5*G17 -> 225 | N17: =SUM(J17) -> 128 | O17: =SUM(L17:N17) -> 468 | P17: =SUM(L17:O17) -> 936 | R17: =J17/7 -> 18.285714 | S17: =I17/7 -> 3.2857143 | T17: =H17/7 -> 8.5714286 | V17: 20
A19: 新品迭代期

Sheet 价格策略模拟
A1: 字段 | B1: 价格策略模拟
A2: 阶段 | B2: 定价 | C2: coupon | D2: code | E2: 折后价 | F2: FBA 配送费 | G2: 亚马逊 佣金 | H2: 账号 回款 | I2: 仓储费+入库配置费 | J2: coupon 费用 | K2: 产品成本 | L2: 物流费 | M2: 退货成本(公式后面加的是单套产品的移除费） | N2: 退货率 | O2: 每单平摊 退货成本 | P2: 每单 毛利 | Q2: 毛利率 | R2: 订单 数量 | S2: 阶段 订单 亏损 | T2: 阶段 订单 总盈亏
A3: 第一阶段 | B3: 79.99 | C3: 0.3 | D3: 0 | E3: =SUM(B3*(1-C3-D3)) -> 55.993 | F3: 10.51 | G3: =SUM(E3*8%) -> 4.47944 | H3: =SUM(E3-F3-G3) -> 41.00356 | I3: 0.5 | J3: 0.6 | K3: =80/7 -> 11.428571 | L3: 3 | M3: =SUM(20%*15%*E3+F3+I3+K3+L3+1.04) -> 28.158361 | N3: 0.044 | O3: =SUM(M3*N3/(1-N3)) -> 1.2959915 | P3: =SUM(H3-I3-J3-K3-L3-O3) -> 24.178997 | Q3: =SUM(P3/B3) -> 0.30227525 | R3: 1 | S3: =SUM(P3*R3) -> 24.178997 | T3: =SUM(S3) -> 24.178997
A4: 第二阶段 | B4: 85.99 | C4: 0.2 | D4: 0 | E4: =SUM(B4*(1-C4-D4)) -> 68.792 | F4: 10.51 | G4: =SUM(E4*8%) -> 5.50336 | H4: =SUM(E4-F4-G4) -> 52.77864 | I4: 0.5 | J4: 0.6 | K4: =80/7 -> 11.428571 | L4: 3 | M4: =SUM(20%*15%*E4+F4+I4+K4+L4+1.04) -> 28.542331 | N4: 0.044 | O4: =SUM(M4*N4/(1-N4)) -> 1.3136638 | P4: =SUM(H4-I4-J4-K4-L4-O4) -> 35.936405 | Q4: =SUM(P4/B4) -> 0.41791377 | R4: 1 | S4: =SUM(P4*R4) -> 35.936405 | T4: =SUM(S4) -> 35.936405
A5: 第三阶段 | B5: 89.99 | C5: 0.1 | D5: 0 | E5: =SUM(B5*(1-C5-D5)) -> 80.991 | F5: 10.51 | G5: =SUM(E5*8%) -> 6.47928 | H5: =SUM(E5-F5-G5) -> 64.00172 | I5: 0.5 | J5: 0 | K5: =80/7 -> 11.428571 | L5: 3 | M5: =SUM(20%*15%*E5+F5+I5+K5+L5+1.04) -> 28.908301 | N5: 0.044 | O5: =SUM(M5*N5/(1-N5)) -> 1.3305076 | P5: =SUM(H5-I5-J5-K5-L5-O5) -> 47.742641 | Q5: =SUM(P5/B5) -> 0.53053274 | R5: 1 | S5: =SUM(P5*R5) -> 47.742641 | T5: =SUM(S5) -> 47.742641
A6: 第四阶段 | B6: 89.99 | C6: 0.05 | D6: 0 | E6: =SUM(B6*(1-C6-D6)) -> 85.4905 | F6: 10.51 | G6: =SUM(E6*8%) -> 6.83924 | H6: =SUM(E6-F6-G6) -> 68.14126 | I6: 0.5 | J6: 0 | K6: =80/7 -> 11.428571 | L6: 3 | M6: =SUM(20%*15%*E6+F6+I6+K6+L6+1.04) -> 29.043286 | N6: 0.044 | O6: =SUM(M6*N6/(1-N6)) -> 1.3367203 | P6: =SUM(H6-I6-J6-K6-L6-O6) -> 51.875968 | Q6: =SUM(P6/B6) -> 0.5764637 | R6: 1 | S6: =SUM(P6*R6) -> 51.875968 | T6: =SUM(S6) -> 51.875968
A7: 第五阶段 | B7: 89.59 | C7: 0.05 | D7: 0 | E7: =SUM(B7*(1-C7-D7)) -> 85.1105 | F7: 10.51 | G7: =SUM(E7*8%) -> 6.80884 | H7: =SUM(E7-F7-G7) -> 67.79166 | I7: 0.5 | J7: 0 | K7: =80/7 -> 11.428571 | L7: 3 | M7: =SUM(20%*15%*E7+F7+I7+K7+L7+1.04) -> 29.031886 | N7: 0.044 | O7: =SUM(M7*N7/(1-N7)) -> 1.3361956 | P7: =SUM(H7-I7-J7-K7-L7-O7) -> 51.526893 | Q7: =SUM(P7/B7) -> 0.57514112 | R7: 1 | S7: =SUM(P7*R7) -> 51.526893 | T7: =SUM(S7) -> 51.526893
A8: 第六阶段 | B8: 89.99 | C8: 0.05 | D8: 0 | E8: =SUM(B8*(1-C8-D8)) -> 85.4905 | F8: 10.51 | G8: =SUM(E8*8%) -> 6.83924 | H8: =SUM(E8-F8-G8) -> 68.14126 | I8: 0.5 | J8: 0 | K8: =80/7 -> 11.428571 | L8: 3 | M8: =SUM(20%*15%*E8+F8+I8+K8+L8+1.04) -> 29.043286 | N8: 0.044 | O8: =SUM(M8*N8/(1-N8)) -> 1.3367203 | P8: =SUM(H8-I8-J8-K8-L8-O8) -> 51.875968 | Q8: =SUM(P8/B8) -> 0.5764637 | R8: 1 | S8: =SUM(P8*R8) -> 51.875968 | T8: =SUM(S8) -> 51.875968
A9: 第七阶段 | B9: 89.99 | C9: 0.05 | D9: 0 | E9: =SUM(B9*(1-C9-D9)) -> 85.4905 | F9: 10.51 | G9: =SUM(E9*8%) -> 6.83924 | H9: =SUM(E9-F9-G9) -> 68.14126 | I9: 0.5 | J9: 0 | K9: =80/7 -> 11.428571 | L9: 3 | M9: =SUM(20%*15%*E9+F9+I9+K9+L9+1.04) -> 29.043286 | N9: 0.044 | O9: =SUM(M9*N9/(1-N9)) -> 1.3367203 | P9: =SUM(H9-I9-J9-K9-L9-O9) -> 51.875968 | Q9: =SUM(P9/B9) -> 0.5764637 | R9: 1 | S9: =SUM(P9*R9) -> 51.875968 | T9: =SUM(S9) -> 51.875968
A10: 竞品日常价格 | B10: 79.99 | C10: 0 | D10: 0 | E10: =SUM(B10*(1-C10-D10)) -> 79.99 | F10: 10.51 | G10: =SUM(E10*15%) -> 11.9985 | H10: =SUM(E10-F10-G10) -> 57.4815 | I10: 0.5 | J10: 0 | K10: =80/7 -> 11.428571 | L10: 3 | M10: =SUM(20%*15%*E10+F10+I10+K10+L10+1.46) -> 29.298271 | N10: 0.044 | O10: =SUM(M10*N10/(1-N10)) -> 1.348456 | P10: =SUM(H10-I10-J10-K10-L10-O10) -> 41.204473 | Q10: =SUM(P10/B10) -> 0.5151203 | R10: 1 | S10: =SUM(P10*R10) -> 41.204473 | T10: =SUM(S10) -> 41.204473
A11: 竞品活动价格 | B11: 99.99 | C11: 0.2 | D11: 0 | E11: =SUM(B11*(1-C11-D11)) -> 79.992 | F11: 10.51 | G11: =SUM(E11*15%) -> 11.9988 | H11: =SUM(E11-F11-G11) -> 57.4832 | I11: 0.5 | J11: 0.6 | K11: =80/7 -> 11.428571 | L11: 3 | M11: =SUM(20%*15%*E11+F11+I11+K11+L11+1.46) -> 29.298331 | N11: 0.044 | O11: =SUM(M11*N11/(1-N11)) -> 1.3484588 | P11: =SUM(H11-I11-J11-K11-L11-O11) -> 40.60617 | Q11: =SUM(P11/B11) -> 0.40610231 | R11: 1 | S11: =SUM(P11*R11) -> 40.60617 | T11: =SUM(S11) -> 40.60617
A12: 竞品链接 | B12: 85.99 | C12: 0.2 | D12: 0 | E12: =SUM(B12*(1-C12-D12)) -> 68.792 | F12: 10.51 | G12: =SUM(E12*8%) -> 5.50336 | H12: =SUM(E12-F12-G12) -> 52.77864 | I12: 0.5 | J12: 0.6 | K12: =80/7 -> 11.428571 | L12: 3 | M12: =SUM(20%*15%*E12+F12+I12+K12+L12+1.04) -> 28.542331 | N12: 0.044 | O12: =SUM(M12*N12/(1-N12)) -> 1.3136638 | P12: =SUM(H12-I12-J12-K12-L12-O12) -> 35.936405 | Q12: =SUM(P12/B12) -> 0.41791377 | R12: 1 | S12: =SUM(P12*R12) -> 35.936405 | T12: =SUM(S12) -> 35.936405
A13: 竞品链接所在类目 | B13: https://www.amazon.com/gp/bestsellers/pet-supplies/3024205011
A15: 阶段 | B15: 型号 | C15: 采购成本（手写） | D15: 头程 （手写） | E15: FBA费用 （手写） | F15: 平台佣金（8%） | G15: 退货（2%） | H15: 优惠卷兑（2.5%） | I15: 在库成本 | J15: 展示售价 （手写） | K15: 折扣券 （手写） | L15: 实际售价 （手写） | M15: 毛利（不含人工、测评、推广等） | N15: 毛利率 | O15: 毛利/人民币 | P15: 汇率 | Q15: 备注
A16: 第一阶段 | B16: RD01 | C16: =80/7 -> 11.428571 | D16: 2 | E16: 10.51 | F16: =L16*8% -> 4.4472 | G16: =L16*2% -> 1.1118 | H16: =L16*2.5% -> 1.38975 | I16: =SUM(C16:H16) -> 30.887321 | J16: 79.99 | K16: 0.3 | L16: 55.59 | M16: =L16-I16 -> 24.702679 | N16: =M16/L16 -> 0.4443727 | O16: =M16*P16 -> 175.38902 | P16: 7.1
A17: 第二阶段 | B17: RD02 | C17: =80/7 -> 11.428571 | D17: 2 | E17: 10.51 | F17: =L17*8% -> 5.5032 | G17: =L17*2% -> 1.3758 | H17: =L17*2.5% -> 1.71975 | I17: =SUM(C17:H17) -> 32.537321 | J17: 85.99 | K17: 0.2 | L17: 68.79 | M17: =L17-I17 -> 36.252679 | N17: =M17/L17 -> 0.52700507 | O17: =M17*P17 -> 257.39402 | P17: 7.1
A18: 第三阶段 | B18: RD03 | C18: =80/7 -> 11.428571 | D18: 2 | E18: 10.51 | F18: =L18*8% -> 6.4792 | G18: =L18*2% -> 1.6198 | H18: =L18*2.5% -> 2.02475 | I18: =SUM(C18:H18) -> 34.062321 | J18: 89.99 | K18: 0.1 | L18: 80.99 | M18: =L18-I18 -> 46.927679 | N18: =M18/L18 -> 0.57942559 | O18: =M18*P18 -> 333.18652 | P18: 7.1
A20: 竞品日常价格 | B20: JP01 | C20: 11.43 | D20: 2 | E20: 10.51 | F20: =L20*8% -> 6.3992 | G20: =L20*2% -> 1.5998 | H20: =L20*2.5% -> 1.99975 | I20: =SUM(C20:H20) -> 33.93875 | J20: 77.99 | K20: =J20/L20 -> 0.97499687 | L20: 79.99 | M20: =L20-I20 -> 46.05125 | N20: =M20/L20 -> 0.57571259 | O20: =M20*P20 -> 326.96387 | P20: 7.1
A21: 竞品活动价格 | B21: - | C21: 11.43 | D21: 2 | E21: 10.51 | F21: =L21*8% -> 7.1992 | G21: =L21*2% -> 1.7998 | H21: =L21*2.5% -> 2.24975 | I21: =SUM(C21:H21) -> 35.18875 | J21: 79.99 | K21: =J21/L21 -> 0.88887654 | L21: 89.99 | M21: =L21-I21 -> 54.80125 | N21: =M21/L21 -> 0.60897044 | O21: =M21*P21 -> 389.08887 | P21: 7.1
A22: 竞品链接 | B22: - | C22: 11.43 | D22: 2 | E22: 10.51 | F22: =L22*8% -> 6.3992 | G22: =L22*2% -> 1.5998 | H22: =L22*2.5% -> 1.99975 | I22: =SUM(C22:H22) -> 33.93875 | J22: 77.99 | K22: =J22/L22 -> 0.97499687 | L22: 79.99 | M22: =L22-I22 -> 46.05125 | N22: =M22/L22 -> 0.57571259 | O22: =M22*P22 -> 326.96387 | P22: 7.1

Sheet 总表（阶段盈亏）
A1: 阶段盈亏模拟数据
A2: 阶段 | B2: 日期 | C2: 定价 | D2: cou pon | E2: code | F2: 折后价 | G2: 站内 自然单 | H2: 站内 广告单 | I2: 阶段 销售 订单 | J2: 时间 /天 | K2: CPA | L2: 阶段 广告费 | M2: 毛利 盈亏 | N2: 阶段盈亏 /美金 | O2: 评论 数量 | P2: 阶段 日均 订单 | Q2: 阶段 日均 广告单 | R2: 阶段 日均 自然单 | S2: 日均 广告费 | T2: 新品 排行榜 | U2: 小类目 排名 | V2: 备注 | W2: 种子评论费/（开3条VINE，预计来70条评论）,视觉化费用预估3000美金 | X2: 前期亏损/美金 | Y2: 人民币
A3: 第一阶段 | B3: WEEK1 | C3: 89.99 | D3: 0.3 | E3: 0 | F3: =SUM(C3*(1-D3-E3)) -> 62.993 | G3: =J3*R3 -> 0 | H3: =J3*Q3 -> 21 | I3: 21 | J3: 7 | K3: =CPC表格!V4 -> 23.875 | L3: =SUM(H3*-K3) -> -501.375 | M3: =毛利盈亏!T3 -> 15.180904 | N3: =SUM(L3:M3) -> -486.1941 | O3: 20 | P3: 3 | Q3: 3 | R3: =SUM(P3-Q3) -> 0 | S3: =SUM(L3/J3) -> -71.625 | T3: 150 | U3: 前300名 | V3: 一开售投放广告 | W3: 3000 | X3: =SUM(N3:N10)+W3 -> -2124.3253 | Y3: =X3*7 -> -14870.277
B4: WEEK2 | C4: 89.99 | D4: 0.3 | E4: 0 | F4: =SUM(C4*(1-D4-E4)) -> 62.993 | G4: =J4*R4 -> 14 | H4: =J4*Q4 -> 35 | I4: =SUM(G4:H4) -> 49 | J4: 7 | K4: =CPC表格!V5 -> 23.875 | L4: =SUM(H4*-K4) -> -835.625 | M4: =毛利盈亏!T4 -> 35.42211 | N4: =SUM(L4:M4) -> -800.20289 | O4: 25 | P4: 7 | Q4: 5 | R4: =SUM(P4-Q4) -> 2 | S4: =SUM(L4/J4) -> -119.375 | T4: 120 | U4: 前300名 | V4: 一开售投放广告 | W4: 0 | X4: =SUM(N4:N11)+W4 -> -3501.0567 | Y4: =X4*7 -> -24507.397
B5: WEEK3 | C5: 89.99 | D5: 0.3 | E5: 0 | F5: =SUM(C5*(1-D5-E5)) -> 62.993 | G5: =J5*R5 -> 28 | H5: =J5*Q5 -> 42 | I5: =SUM(G5:H5) -> 70 | J5: 7 | K5: =CPC表格!V6 -> 23.875 | L5: =SUM(H5*-K5) -> -1002.75 | M5: =毛利盈亏!T5 -> 50.603015 | N5: =SUM(L5:M5) -> -952.14699 | O5: 30 | P5: 10 | Q5: 6 | R5: =SUM(P5-Q5) -> 4 | S5: =SUM(L5/J5) -> -143.25 | T5: 100 | U5: 前250名 | W5: 0 | X5: =SUM(N5:N12)+W5 -> -378.16219 | Y5: =X5*7 -> -2647.1354
B6: WEEK4 | C6: 89.99 | D6: 0.3 | E6: 0 | F6: =SUM(C6*(1-D6-E6)) -> 62.993 | G6: =J6*R6 -> 35 | H6: =J6*Q6 -> 49 | I6: =SUM(G6:H6) -> 84 | J6: 7 | K6: =CPC表格!V7 -> 23.875 | L6: =SUM(H6*-K6) -> -1169.875 | M6: =毛利盈亏!T6 -> 60.723618 | N6: =SUM(L6:M6) -> -1109.1514 | O6: 35 | P6: 12 | Q6: 7 | R6: =SUM(P6-Q6) -> 5 | S6: =SUM(L6/J6) -> -167.125 | T6: 50 | U6: 前250名 | W6: 0 | X6: =SUM(N6:N13)+W6 -> 2051.1221 | Y6: =X6*7 -> 14357.855
A7: 第二阶段 | B7: WEEK5 | C7: 85.99 | D7: 0.2 | E7: 0 | F7: =SUM(C7*(1-D7-E7)) -> 68.792 | G7: =J7*R7 -> 42 | H7: =J7*Q7 -> 63 | I7: =SUM(G7:H7) -> 105 | J7: 7 | K7: =CPC表格!V8 -> 22 | L7: =SUM(H7*-K7) -> -1386 | M7: =毛利盈亏!T7 -> 943.90326 | N7: =SUM(L7:M7) -> -442.09674 | O7: 40 | P7: 15 | Q7: 9 | R7: =SUM(P7-Q7) -> 6 | S7: =SUM(L7/J7) -> -198 | T7: 40 | U7: 前200名 | W7: 0 | X7: =SUM(N7:N14)+W7 -> 7272.5494 | Y7: =X7*7 -> 50907.846
B8: WEEK6 | C8: 85.99 | D8: 0.2 | E8: 0 | F8: =SUM(C8*(1-D8-E8)) -> 68.792 | G8: =J8*R8 -> 56 | H8: =J8*Q8 -> 70 | I8: =SUM(G8:H8) -> 126 | J8: 7 | K8: =CPC表格!V9 -> 22 | L8: =SUM(H8*-K8) -> -1540 | M8: =毛利盈亏!T8 -> 1132.6839 | N8: =SUM(L8:M8) -> -407.31609 | O8: 50 | P8: 18 | Q8: 10 | R8: =SUM(P8-Q8) -> 8 | S8: =SUM(L8/J8) -> -220 | T8: 30 | U8: 前200名 | W8: 0 | X8: =SUM(N8:N15)+W8 -> 9788.6789 | Y8: =X8*7 -> 68520.752
B9: WEEK7 | C9: 85.99 | D9: 0.2 | E9: 0 | F9: =SUM(C9*(1-D9-E9)) -> 68.792 | G9: =J9*R9 -> 56 | H9: =J9*Q9 -> 84 | I9: =SUM(G9:H9) -> 140 | J9: 7 | K9: =CPC表格!V10 -> 22 | L9: =SUM(H9*-K9) -> -1848 | M9: =毛利盈亏!T9 -> 1258.5377 | N9: =SUM(L9:M9) -> -589.46233 | O9: 60 | P9: 20 | Q9: 12 | R9: =SUM(P9-Q9) -> 8 | S9: =SUM(L9/J9) -> -264 | T9: 20 | U9: 前150名 | W9: 0 | X9: =SUM(N9:N16)+W9 -> 12566.341 | Y9: =X9*7 -> 87964.384
B10: WEEK8 | C10: 85.99 | D10: 0.2 | E10: 0 | F10: =SUM(C10*(1-D10-E10)) -> 68.792 | G10: =J10*R10 -> 84 | H10: =J10*Q10 -> 84 | I10: =SUM(G10:H10) -> 168 | J10: 7 | K10: =CPC表格!V11 -> 22 | L10: =SUM(H10*-K10) -> -1848 | M10: =毛利盈亏!T10 -> 1510.2452 | N10: =SUM(L10:M10) -> -337.75479 | O10: 70 | P10: 24 | Q10: 12 | R10: =SUM(P10-Q10) -> 12 | S10: =SUM(L10/J10) -> -264 | T10: 10 | U10: 前150名 | W10: 0 | X10: =SUM(N10:N17)+W10 -> 15822.462 | Y10: =X10*7 -> 110757.23
A11: 第三阶段 | B11: WEEK9 | C11: 85.99 | D11: 0.1 | E11: 0 | F11: =SUM(C11*(1-D11-E11)) -> 77.391 | G11: =J11*R11 -> 84 | H11: =J11*Q11 -> 98 | I11: =SUM(G11:H11) -> 182 | J11: 7 | K11: =CPC表格!V12 -> 20.444444 | L11: =SUM(H11*-K11) -> -2003.5556 | M11: =毛利盈亏!T11 -> 3140.6301 | N11: =SUM(L11:M11) -> 1137.0746 | O11: 80 | P11: 26 | Q11: 14 | R11: =SUM(P11-Q11) -> 12 | S11: =SUM(L11/J11) -> -286.22222 | T11: 10 | U11: 前100名 | W11: 0 | X11: =SUM(N11:N34)+W11 -> 53300.888 | Y11: =X11*7 -> 373106.22
B12: WEEK10 | C12: 85.99 | D12: 0.1 | E12: 0 | F12: =SUM(C12*(1-D12-E12)) -> 77.391 | G12: =J12*R12 -> 154 | H12: =J12*Q12 -> 105 | I12: =SUM(G12:H12) -> 259 | J12: 7 | K12: =CPC表格!V13 -> 20.444444 | L12: =SUM(H12*-K12) -> -2146.6667 | M12: =毛利盈亏!T12 -> 4469.3582 | N12: =SUM(L12:M12) -> 2322.6916 | O12: 90 | P12: 28 | Q12: 15 | R12: 22 | S12: =SUM(L12/J12) -> -306.66667 | T12: 5 | U12: 前100名 | W12: 0 | X12: =SUM(N12:N35)+W12 -> 51574.352 | Y12: =X12*7 -> 361020.46
B13: WEEK11 | C13: 85.99 | D13: 0.1 | E13: 0 | F13: =SUM(C13*(1-D13-E13)) -> 77.391 | G13: =J13*R13 -> 105 | H13: =J13*Q13 -> 105 | I13: =SUM(G13:H13) -> 210 | J13: 7 | K13: =CPC表格!V14 -> 20.444444 | L13: =SUM(H13*-K13) -> -2146.6667 | M13: =毛利盈亏!T13 -> 3623.804 | N13: =SUM(L13:M13) -> 1477.1373 | O13: 100 | P13: 30 | Q13: 15 | R13: =P13-Q13 -> 15 | S13: =SUM(L13/J13) -> -306.66667 | T13: 5 | U13: 前80名 | W13: 0 | X13: =SUM(N13:N36)+W13 -> 48913.905 | Y13: =X13*7 -> 342397.34
B14: WEEK12 | C14: 85.99 | D14: 0.1 | E14: 0 | F14: =SUM(C14*(1-D14-E14)) -> 77.391 | G14: =J14*R14 -> 259 | H14: =J14*Q14 -> 112 | I14: =SUM(G14:H14) -> 371 | J14: 7 | K14: =CPC表格!V15 -> 20.444444 | L14: =SUM(H14*-K14) -> -2289.7778 | M14: =毛利盈亏!T14 -> 6402.0537 | N14: =SUM(L14:M14) -> 4112.2759 | O14: 110 | P14: 35 | Q14: 16 | R14: 37 | S14: =SUM(L14/J14) -> -327.11111 | T14: 4 | U14: 前80名 | W14: 0 | X14: =SUM(N14:N37)+W14 -> 48573.842 | Y14: =X14*7 -> 340016.9
A15: 第四阶段 | B15: WEEK13 | C15: 79.99 | D15: 0 | E15: 0 | F15: =SUM(C15*(1-D15-E15)) -> 79.99 | G15: =J15*R15 -> 154 | H15: =J15*Q15 -> 126 | I15: =SUM(G15:H15) -> 280 | J15: 7 | K15: =CPC表格!V16 -> 21.176471 | L15: =SUM(H15*-K15) -> -2668.2353 | M15: =毛利盈亏!T15 -> 4742.268 | N15: =SUM(L15:M15) -> 2074.0327 | O15: 120 | P15: 40 | Q15: 18 | R15: =SUM(P15-Q15) -> 22 | S15: =SUM(L15/J15) -> -381.17647 | T15: 4 | U15: 前50名 | W15: 0 | X15: =SUM(N15:N38)+W15 -> 46784.258 | Y15: =X15*7 -> 327489.81
B16: WEEK14 | C16: 79.99 | D16: 0 | E16: 0 | F16: =SUM(C16*(1-D16-E16)) -> 79.99 | G16: =J16*R16 -> 175 | H16: =J16*Q16 -> 140 | I16: =SUM(G16:H16) -> 315 | J16: 7 | K16: =CPC表格!V17 -> 21.176471 | L16: =SUM(H16*-K16) -> -2964.7059 | M16: =毛利盈亏!T16 -> 5335.0515 | N16: =SUM(L16:M16) -> 2370.3457 | O16: 130 | P16: 45 | Q16: 20 | R16: =SUM(P16-Q16) -> 25 | S16: =SUM(L16/J16) -> -423.52941 | T16: 3 | U16: 前50名 | W16: 0 | X16: =SUM(N16:N39)+W16 -> 46187.363 | Y16: =X16*7 -> 323311.54
B17: WEEK15 | C17: 79.99 | D17: 0 | E17: 0 | F17: =SUM(C17*(1-D17-E17)) -> 79.99 | G17: =J17*R17 -> 196 | H17: =J17*Q17 -> 154 | I17: =SUM(G17:H17) -> 350 | J17: 7 | K17: =CPC表格!V18 -> 21.176471 | L17: =SUM(H17*-K17) -> -3261.1765 | M17: =毛利盈亏!T17 -> 5927.835 | N17: =SUM(L17:M17) -> 2666.6586 | O17: 140 | P17: 50 | Q17: 22 | R17: =SUM(P17-Q17) -> 28 | S17: =SUM(L17/J17) -> -465.88235 | T17: 3 | U17: 前20名 | W17: 0 | X17: =SUM(N17:N40)+W17 -> 47929.293 | Y17: =X17*7 -> 335505.05
B18: WEEK16 | C18: 79.99 | D18: 0 | E18: 0 | F18: =SUM(C18*(1-D18-E18)) -> 79.99 | G18: =J18*R18 -> 315 | H18: =J18*Q18 -> 175 | I18: =SUM(G18:H18) -> 490 | J18: 7 | K18: =CPC表格!V19 -> 21.176471 | L18: =SUM(H18*-K18) -> -3705.8824 | M18: =毛利盈亏!T18 -> 8298.9691 | N18: =SUM(L18:M18) -> 4593.0867 | O18: 150 | P18: 70 | Q18: 25 | R18: =SUM(P18-Q18) -> 45 | S18: =SUM(L18/J18) -> -529.41176 | T18: 2 | U18: 前20名 | W18: 0 | X18: =SUM(N18:N41)+W18 -> 47336.667 | Y18: =X18*7 -> 331356.67
A19: 第五阶段 | B19: WEEK17 | C19: 79.99 | D19: 0 | E19: 0 | F19: =SUM(C19*(1-D19-E19)) -> 79.99 | G19: =J19*R19 -> 315 | H19: =J19*Q19 -> 175 | I19: =SUM(G19:H19) -> 490 | J19: 7 | K19: =CPC表格!V20 -> 21.176471 | L19: =SUM(H19*-K19) -> -3705.8824 | M19: =毛利盈亏!T19 -> 8298.9691 | N19: =SUM(L19:M19) -> 4593.0867 | O19: 160 | P19: 70 | Q19: 25 | R19: =SUM(P19-Q19) -> 45 | S19: =SUM(L19/J19) -> -529.41176 | T19: 2 | U19: 前20名 | W19: 0 | X19: =SUM(N19:N42)+W19 -> 45113.926 | Y19: =X19*7 -> 315797.48
B20: WEEK18 | C20: 79.99 | D20: 0 | E20: 0 | F20: =SUM(C20*(1-D20-E20)) -> 79.99 | G20: =J20*R20 -> 315 | H20: =J20*Q20 -> 175 | I20: =SUM(G20:H20) -> 490 | J20: 7 | K20: =CPC表格!V21 -> 21.176471 | L20: =SUM(H20*-K20) -> -3705.8824 | M20: =毛利盈亏!T20 -> 8298.9691 | N20: =SUM(L20:M20) -> 4593.0867 | O20: 170 | P20: 70 | Q20: 25 | R20: =SUM(P20-Q20) -> 45 | S20: =SUM(L20/J20) -> -529.41176 | T20: 2 | U20: 前20名 | W20: 0 | X20: =SUM(N20:N43)+W20 -> 43187.498 | Y20: =X20*7 -> 302312.49
B21: WEEK19 | C21: 79.99 | D21: 0 | E21: 0 | F21: =SUM(C21*(1-D21-E21)) -> 79.99 | G21: =J21*R21 -> 315 | H21: =J21*Q21 -> 175 | I21: =SUM(G21:H21) -> 490 | J21: 7 | K21: =CPC表格!V22 -> 21.176471 | L21: =SUM(H21*-K21) -> -3705.8824 | M21: =毛利盈亏!T21 -> 8298.9691 | N21: =SUM(L21:M21) -> 4593.0867 | O21: 180 | P21: 70 | Q21: 25 | R21: =SUM(P21-Q21) -> 45 | S21: =SUM(L21/J21) -> -529.41176 | T21: 1 | U21: 前20名 | W21: 0 | X21: =SUM(N21:N44)+W21 -> 43187.498 | Y21: =X21*7 -> 302312.49
B22: WEEK20 | C22: 79.99 | D22: 0 | E22: 0 | F22: =SUM(C22*(1-D22-E22)) -> 79.99 | G22: =J22*R22 -> 315 | H22: =J22*Q22 -> 175 | I22: =SUM(G22:H22) -> 490 | J22: 7 | K22: =CPC表格!V23 -> 21.176471 | L22: =SUM(H22*-K22) -> -3705.8824 | M22: =毛利盈亏!T22 -> 8298.9691 | N22: =SUM(L22:M22) -> 4593.0867 | O22: 190 | P22: 70 | Q22: 25 | R22: =SUM(P22-Q22) -> 45 | S22: =SUM(L22/J22) -> -529.41176 | T22: 1 | U22: 前20名 | W22: 0 | X22: =SUM(N22:N45)+W22 -> 43187.498 | Y22: =X22*7 -> 302312.49
A23: 第六阶段 | B23: WEEK21 | C23: 79.99 | D23: 0 | E23: 0 | F23: =SUM(C23*(1-D23-E23)) -> 79.99 | G23: =J23*R23 -> 315 | H23: =J23*Q23 -> 175 | I23: =SUM(G23:H23) -> 490 | J23: 7 | K23: =CPC表格!V24 -> 21.176471 | L23: =SUM(H23*-K23) -> -3705.8824 | M23: =毛利盈亏!T23 -> 8298.9691 | N23: =SUM(L23:M23) -> 4593.0867 | O23: 200 | P23: 70 | Q23: 25 | R23: =SUM(P23-Q23) -> 45 | S23: =SUM(L23/J23) -> -529.41176 | T23: 1 | U23: 前10名 | W23: 0 | X23: =SUM(N23:N46)+W23 -> 43187.498 | Y23: =X23*7 -> 302312.49
B24: WEEK22 | C24: 79.99 | D24: 0 | E24: 0 | F24: =SUM(C24*(1-D24-E24)) -> 79.99 | G24: =J24*R24 -> 315 | H24: =J24*Q24 -> 175 | I24: =SUM(G24:H24) -> 490 | J24: 7 | K24: =CPC表格!V25 -> 21.176471 | L24: =SUM(H24*-K24) -> -3705.8824 | M24: =毛利盈亏!T24 -> 8298.9691 | N24: =SUM(L24:M24) -> 4593.0867 | O24: 220 | P24: 70 | Q24: 25 | R24: =SUM(P24-Q24) -> 45 | S24: =SUM(L24/J24) -> -529.41176 | T24: 1 | U24: 前10名 | W24: 0 | X24: =SUM(N24:N47)+W24 -> 43187.498 | Y24: =X24*7 -> 302312.49
B25: WEEK23 | C25: 79.99 | D25: 0 | E25: 0 | F25: =SUM(C25*(1-D25-E25)) -> 79.99 | G25: =J25*R25 -> 315 | H25: =J25*Q25 -> 175 | I25: =SUM(G25:H25) -> 490 | J25: 7 | K25: =CPC表格!V26 -> 21.176471 | L25: =SUM(H25*-K25) -> -3705.8824 | M25: =毛利盈亏!T25 -> 8298.9691 | N25: =SUM(L25:M25) -> 4593.0867 | O25: 240 | P25: 70 | Q25: 25 | R25: =SUM(P25-Q25) -> 45 | S25: =SUM(L25/J25) -> -529.41176 | T25: 1 | U25: 前10名 | W25: 0 | X25: =SUM(N25:N48)+W25 -> 43187.498 | Y25: =X25*7 -> 302312.49
B26: WEEK24 | C26: 79.99 | D26: 0 | E26: 0 | F26: =SUM(C26*(1-D26-E26)) -> 79.99 | G26: =J26*R26 -> 315 | H26: =J26*Q26 -> 175 | I26: =SUM(G26:H26) -> 490 | J26: 7 | K26: =CPC表格!V27 -> 21.176471 | L26: =SUM(H26*-K26) -> -3705.8824 | M26: =毛利盈亏!T26 -> 8298.9691 | N26: =SUM(L26:M26) -> 4593.0867 | O26: 260 | P26: 70 | Q26: 25 | R26: =SUM(P26-Q26) -> 45 | S26: =SUM(L26/J26) -> -529.41176 | T26: 1 | U26: 前5名 | W26: 0 | X26: =SUM(N26:N49)+W26 -> 43187.498 | Y26: =X26*7 -> 302312.49
A28: 阶段盈亏真实数据
A29: 第一阶段 | B29: 第1周 | C29: 89.99 | D29: 0.3 | E29: 0 | F29: 62.993 | G29: 0 | H29: 21 | I29: 21 | J29: 7 | K29: 23.875 | L29: -501.375 | M29: 15.180904 | N29: -486.1941 | O29: 20 | P29: 3 | Q29: 3 | R29: 0 | S29: -71.625 | T29: 150 | U29: 前300名 | V29: 一开售投放广告 | W29: 3000 | X29: -2124.3253 | Y29: -14870.277
B30: 第2周 | C30: 89.99 | D30: 0.3 | E30: 0 | F30: 62.993 | G30: 14 | H30: 35 | I30: 49 | J30: 7 | K30: 23.875 | L30: -835.625 | M30: 35.42211 | N30: -800.20289 | O30: 25 | P30: 7 | Q30: 5 | R30: 2 | S30: -119.375 | T30: 120 | U30: 前300名 | V30: 一开售投放广告 | W30: 0 | X30: -3501.0567 | Y30: -24507.397
B31: 第3周 | C31: 89.99 | D31: 0.3 | E31: 0 | F31: 62.993 | G31: 28 | H31: 42 | I31: 70 | J31: 7 | K31: 23.875 | L31: -1002.75 | M31: 50.603015 | N31: -952.14699 | O31: 30 | P31: 10 | Q31: 6 | R31: 4 | S31: -143.25 | T31: 100 | U31: 前250名 | W31: 0 | X31: -378.16219 | Y31: -2647.1354
B32: 第4周 | C32: 89.99 | D32: 0.3 | E32: 0 | F32: 62.993 | G32: 35 | H32: 49 | I32: 84 | J32: 7 | K32: 23.875 | L32: -1169.875 | M32: 60.723618 | N32: -1109.1514 | O32: 35 | P32: 12 | Q32: 7 | R32: 5 | S32: -167.125 | T32: 50 | U32: 前250名 | W32: 0 | X32: 2051.1221 | Y32: 14357.855
A33: 第二阶段 | B33: 第5周 | C33: 85.99 | D33: 0.2 | E33: 0 | F33: 68.792 | G33: 42 | H33: 63 | I33: 105 | J33: 7 | K33: 22 | L33: -1386 | M33: 943.90326 | N33: -442.09674 | O33: 40 | P33: 15 | Q33: 9 | R33: 6 | S33: -198 | T33: 40 | U33: 前200名 | W33: 0 | X33: 7272.5494 | Y33: 50907.846
B34: 第6周 | C34: 85.99 | D34: 0.2 | E34: 0 | F34: 68.792 | G34: 56 | H34: 70 | I34: 126 | J34: 7 | K34: 22 | L34: -1540 | M34: 1132.6839 | N34: -407.31609 | O34: 50 | P34: 18 | Q34: 10 | R34: 8 | S34: -220 | T34: 30 | U34: 前200名 | W34: 0 | X34: 9788.6789 | Y34: 68520.752
B35: 第7周 | C35: 85.99 | D35: 0.2 | E35: 0 | F35: 68.792 | G35: 56 | H35: 84 | I35: 140 | J35: 7 | K35: 22 | L35: -1848 | M35: 1258.5377 | N35: -589.46233 | O35: 60 | P35: 20 | Q35: 12 | R35: 8 | S35: -264 | T35: 20 | U35: 前150名 | W35: 0 | X35: 12566.341 | Y35: 87964.384
B36: 第8周 | C36: 85.99 | D36: 0.2 | E36: 0 | F36: 68.792 | G36: 84 | H36: 84 | I36: 168 | J36: 7 | K36: 22 | L36: -1848 | M36: 1510.2452 | N36: -337.75479 | O36: 70 | P36: 24 | Q36: 12 | R36: 12 | S36: -264 | T36: 10 | U36: 前150名 | W36: 0 | X36: 15822.462 | Y36: 110757.23
A37: 第三阶段 | B37: 第9周 | C37: 85.99 | D37: 0.1 | E37: 0 | F37: 77.391 | G37: 84 | H37: 98 | I37: 182 | J37: 7 | K37: 20.444444 | L37: -2003.5556 | M37: 3140.6301 | N37: 1137.0746 | O37: 80 | P37: 26 | Q37: 14 | R37: 12 | S37: -286.22222 | T37: 10 | U37: 前100名 | W37: 0 | X37: 57497.997 | Y37: 402485.98
B38: 第10周 | C38: 85.99 | D38: 0.1 | E38: 0 | F38: 77.391 | G38: 154 | H38: 105 | I38: 259 | J38: 7 | K38: 20.444444 | L38: -2146.6667 | M38: 4469.3582 | N38: 2322.6916 | O38: 90 | P38: 28 | Q38: 15 | R38: 22 | S38: -306.66667 | T38: 5 | U38: 前100名 | W38: 0 | X38: 56360.922 | Y38: 394526.45
B39: 第11周 | C39: 85.99 | D39: 0.1 | E39: 0 | F39: 77.391 | G39: 105 | H39: 105 | I39: 210 | J39: 7 | K39: 20.444444 | L39: -2146.6667 | M39: 3623.804 | N39: 1477.1373 | O39: 100 | P39: 30 | Q39: 15 | R39: 15 | S39: -306.66667 | T39: 5 | U39: 前80名 | W39: 0 | X39: 54038.231 | Y39: 378267.61
B40: 第12周 | C40: 85.99 | D40: 0.1 | E40: 0 | F40: 77.391 | G40: 259 | H40: 112 | I40: 371 | J40: 7 | K40: 20.444444 | L40: -2289.7778 | M40: 6402.0537 | N40: 4112.2759 | O40: 110 | P40: 35 | Q40: 16 | R40: 37 | S40: -327.11111 | T40: 4 | U40: 前80名 | W40: 0 | X40: 52561.093 | Y40: 367927.65
A41: 第四阶段 | B41: 第13周 | C41: 79.99 | D41: 0 | E41: 0 | F41: 79.99 | G41: 154 | H41: 126 | I41: 280 | J41: 7 | K41: 21.176471 | L41: -2668.2353 | M41: 4742.268 | N41: 2074.0327 | O41: 120 | P41: 40 | Q41: 18 | R41: 22 | S41: -381.17647 | T41: 4 | U41: 前50名 | W41: 0 | X41: 48448.817 | Y41: 339141.72
B42: 第14周 | C42: 79.99 | D42: 0 | E42: 0 | F42: 79.99 | G42: 175 | H42: 140 | I42: 315 | J42: 7 | K42: 21.176471 | L42: -2964.7059 | M42: 5335.0515 | N42: 2370.3457 | O42: 130 | P42: 45 | Q42: 20 | R42: 25 | S42: -423.52941 | T42: 3 | U42: 前50名 | W42: 0 | X42: 46374.785 | Y42: 324623.49
B43: 第15周 | C43: 79.99 | D43: 0 | E43: 0 | F43: 79.99 | G43: 196 | H43: 154 | I43: 350 | J43: 7 | K43: 21.176471 | L43: -3261.1765 | M43: 5927.835 | N43: 2666.6586 | O43: 140 | P43: 50 | Q43: 22 | R43: 28 | S43: -465.88235 | T43: 3 | U43: 前20名 | W43: 0 | X43: 44004.439 | Y43: 308031.07
B44: 第16周 | C44: 79.99 | D44: 0 | E44: 0 | F44: 79.99 | G44: 315 | H44: 175 | I44: 490 | J44: 7 | K44: 21.176471 | L44: -3705.8824 | M44: 8298.9691 | N44: 4593.0867 | O44: 150 | P44: 70 | Q44: 25 | R44: 45 | S44: -529.41176 | T44: 2 | U44: 前20名 | W44: 0 | X44: 41337.78 | Y44: 289364.46
A45: 第五阶段 | B45: 第17周 | C45: 79.99 | D45: 0 | E45: 0 | F45: 79.99 | G45: 315 | H45: 175 | I45: 490 | J45: 7 | K45: 21.176471 | L45: -3705.8824 | M45: 8298.9691 | N45: 4593.0867 | O45: 160 | P45: 70 | Q45: 25 | R45: 45 | S45: -529.41176 | T45: 2 | U45: 前20名 | W45: 0 | X45: 36744.694 | Y45: 257212.86
B46: 第18周 | C46: 79.99 | D46: 0 | E46: 0 | F46: 79.99 | G46: 315 | H46: 175 | I46: 490 | J46: 7 | K46: 21.176471 | L46: -3705.8824 | M46: 8298.9691 | N46: 4593.0867 | O46: 170 | P46: 70 | Q46: 25 | R46: 45 | S46: -529.41176 | T46: 2 | U46: 前20名 | W46: 0 | X46: 32151.607 | Y46: 225061.25
B47: 第19周 | C47: 79.99 | D47: 0 | E47: 0 | F47: 79.99 | G47: 315 | H47: 175 | I47: 490 | J47: 7 | K47: 21.176471 | L47: -3705.8824 | M47: 8298.9691 | N47: 4593.0867 | O47: 180 | P47: 70 | Q47: 25 | R47: 45 | S47: -529.41176 | T47: 1 | U47: 前20名 | W47: 0 | X47: 27558.52 | Y47: 192909.64
B48: 第20周 | C48: 79.99 | D48: 0 | E48: 0 | F48: 79.99 | G48: 315 | H48: 175 | I48: 490 | J48: 7 | K48: 21.176471 | L48: -3705.8824 | M48: 8298.9691 | N48: 4593.0867 | O48: 190 | P48: 70 | Q48: 25 | R48: 45 | S48: -529.41176 | T48: 1 | U48: 前20名 | W48: 0 | X48: 22965.434 | Y48: 160758.03
A49: 第六阶段 | B49: 第21周 | C49: 79.99 | D49: 0 | E49: 0 | F49: 79.99 | G49: 315 | H49: 175 | I49: 490 | J49: 7 | K49: 21.176471 | L49: -3705.8824 | M49: 8298.9691 | N49: 4593.0867 | O49: 200 | P49: 70 | Q49: 25 | R49: 45 | S49: -529.41176 | T49: 1 | U49: 前10名 | W49: 0 | X49: 18372.347 | Y49: 128606.43
B50: 第22周 | C50: 79.99 | D50: 0 | E50: 0 | F50: 79.99 | G50: 315 | H50: 175 | I50: 490 | J50: 7 | K50: 21.176471 | L50: -3705.8824 | M50: 8298.9691 | N50: 4593.0867 | O50: 220 | P50: 70 | Q50: 25 | R50: 45 | S50: -529.41176 | T50: 1 | U50: 前10名 | W50: 0 | X50: 13779.26 | Y50: 96454.821
B51: 第23周 | C51: 79.99 | D51: 0 | E51: 0 | F51: 79.99 | G51: 315 | H51: 175 | I51: 490 | J51: 7 | K51: 21.176471 | L51: -3705.8824 | M51: 8298.9691 | N51: 4593.0867 | O51: 240 | P51: 70 | Q51: 25 | R51: 45 | S51: -529.41176 | T51: 1 | U51: 前10名 | W51: 0 | X51: 9186.1734 | Y51: 64303.214
B52: 第24周 | C52: 79.99 | D52: 0 | E52: 0 | F52: 79.99 | G52: 315 | H52: 175 | I52: 490 | J52: 7 | K52: 21.176471 | L52: -3705.8824 | M52: 8298.9691 | N52: 4593.0867 | O52: 260 | P52: 70 | Q52: 25 | R52: 45 | S52: -529.41176 | T52: 1 | U52: 前5名 | W52: 0 | X52: 4593.0867 | Y52: 32151.607

Sheet 毛利盈亏
A1: 每日盈亏数据预估
A2: 阶段 | B2: 日期 | C2: 定价 | D2: coupon | E2: code | F2: 折后价 | G2: FBA 配送费 | H2: 亚马逊 佣金 | I2: 账号 回款 | J2: 仓储费+入库配置费 | K2: coupon 费用 | L2: 产品 成本 | M2: 物流费 | N2: 退货成本(公式后面加的是单套产品的移除费） | O2: 退货率 | P2: 每单平摊 退货成本 | Q2: 每单 毛利 | R2: 毛利率 | S2: 订单 数量 | T2: 阶段 订单 亏损 | U2: 阶段 订单 总盈亏
A3: 第一阶段 | B3: week01 | C3: 89.99 | D3: 0.3 | E3: 0 | F3: =SUM(C3*(1-D3-E3)) -> 62.993 | G3: 10.51 | H3: =SUM(F3*8%) -> 5.03944 | I3: =SUM(F3-G3-H3) -> 47.44356 | J3: 0.5 | K3: 0.6 | L3: 40 | M3: 3 | N3: =SUM(20%*15%*F3+G3+J3+L3+M3+1.04) -> 56.93979 | O3: 0.044 | P3: =SUM(N3*O3/(1-O3)) -> 2.6206598 | Q3: =SUM(I3-J3-K3-L3-M3-P3) -> 0.72290021 | R3: =SUM(Q3/C3) -> 0.0080331171 | S3: ='总表（阶段盈亏）'!I3 -> 21 | T3: =SUM(Q3*S3) -> 15.180904 | U3: =SUM(T3) -> 15.180904
B4: week02 | C4: 89.99 | D4: 0.3 | E4: 0 | F4: =SUM(C4*(1-D4-E4)) -> 62.993 | G4: 10.51 | H4: =SUM(F4*8%) -> 5.03944 | I4: =SUM(F4-G4-H4) -> 47.44356 | J4: 0.5 | K4: 0.6 | L4: 40 | M4: 3 | N4: =SUM(20%*15%*F4+G4+J4+L4+M4+1.04) -> 56.93979 | O4: 0.044 | P4: =SUM(N4*O4/(1-O4)) -> 2.6206598 | Q4: =SUM(I4-J4-K4-L4-M4-P4) -> 0.72290021 | R4: =SUM(Q4/C4) -> 0.0080331171 | S4: ='总表（阶段盈亏）'!I4 -> 49 | T4: =SUM(Q4*S4) -> 35.42211 | U4: =SUM(T4) -> 35.42211
B5: week03 | C5: 89.99 | D5: 0.3 | E5: 0 | F5: =SUM(C5*(1-D5-E5)) -> 62.993 | G5: 10.51 | H5: =SUM(F5*8%) -> 5.03944 | I5: =SUM(F5-G5-H5) -> 47.44356 | J5: 0.5 | K5: 0.6 | L5: 40 | M5: 3 | N5: =SUM(20%*15%*F5+G5+J5+L5+M5+1.04) -> 56.93979 | O5: 0.044 | P5: =SUM(N5*O5/(1-O5)) -> 2.6206598 | Q5: =SUM(I5-J5-K5-L5-M5-P5) -> 0.72290021 | R5: =SUM(Q5/C5) -> 0.0080331171 | S5: ='总表（阶段盈亏）'!I5 -> 70 | T5: =SUM(Q5*S5) -> 50.603015 | U5: =SUM(T5) -> 50.603015
B6: week04 | C6: 89.99 | D6: 0.3 | E6: 0 | F6: =SUM(C6*(1-D6-E6)) -> 62.993 | G6: 10.51 | H6: =SUM(F6*8%) -> 5.03944 | I6: =SUM(F6-G6-H6) -> 47.44356 | J6: 0.5 | K6: 0.6 | L6: 40 | M6: 3 | N6: =SUM(20%*15%*F6+G6+J6+L6+M6+1.04) -> 56.93979 | O6: 0.044 | P6: =SUM(N6*O6/(1-O6)) -> 2.6206598 | Q6: =SUM(I6-J6-K6-L6-M6-P6) -> 0.72290021 | R6: =SUM(Q6/C6) -> 0.0080331171 | S6: ='总表（阶段盈亏）'!I6 -> 84 | T6: =SUM(Q6*S6) -> 60.723618 | U6: =SUM(T6) -> 60.723618
A7: 第二阶段 | B7: week05 | C7: 89.99 | D7: 0.2 | E7: 0 | F7: =SUM(C7*(1-D7-E7)) -> 71.992 | G7: 10.51 | H7: =SUM(F7*8%) -> 5.75936 | I7: =SUM(F7-G7-H7) -> 55.72264 | J7: 0.5 | K7: 0.6 | L7: 40 | M7: 3 | N7: =SUM(20%*15%*F7+G7+J7+L7+M7+1.04) -> 57.20976 | O7: 0.044 | P7: =SUM(N7*O7/(1-O7)) -> 2.6330852 | Q7: =SUM(I7-J7-K7-L7-M7-P7) -> 8.9895548 | R7: =SUM(Q7/C7) -> 0.099895042 | S7: ='总表（阶段盈亏）'!I7 -> 105 | T7: =SUM(Q7*S7) -> 943.90326 | U7: =SUM(T7) -> 943.90326
B8: week06 | C8: 89.99 | D8: 0.2 | E8: 0 | F8: =SUM(C8*(1-D8-E8)) -> 71.992 | G8: 10.51 | H8: =SUM(F8*8%) -> 5.75936 | I8: =SUM(F8-G8-H8) -> 55.72264 | J8: 0.5 | K8: 0.6 | L8: 40 | M8: 3 | N8: =SUM(20%*15%*F8+G8+J8+L8+M8+1.04) -> 57.20976 | O8: 0.044 | P8: =SUM(N8*O8/(1-O8)) -> 2.6330852 | Q8: =SUM(I8-J8-K8-L8-M8-P8) -> 8.9895548 | R8: =SUM(Q8/C8) -> 0.099895042 | S8: ='总表（阶段盈亏）'!I8 -> 126 | T8: =SUM(Q8*S8) -> 1132.6839 | U8: =SUM(T8) -> 1132.6839
B9: week07 | C9: 89.99 | D9: 0.2 | E9: 0 | F9: =SUM(C9*(1-D9-E9)) -> 71.992 | G9: 10.51 | H9: =SUM(F9*8%) -> 5.75936 | I9: =SUM(F9-G9-H9) -> 55.72264 | J9: 0.5 | K9: 0.6 | L9: 40 | M9: 3 | N9: =SUM(20%*15%*F9+G9+J9+L9+M9+1.04) -> 57.20976 | O9: 0.044 | P9: =SUM(N9*O9/(1-O9)) -> 2.6330852 | Q9: =SUM(I9-J9-K9-L9-M9-P9) -> 8.9895548 | R9: =SUM(Q9/C9) -> 0.099895042 | S9: ='总表（阶段盈亏）'!I9 -> 140 | T9: =SUM(Q9*S9) -> 1258.5377 | U9: =SUM(T9) -> 1258.5377
B10: week08 | C10: 89.99 | D10: 0.2 | E10: 0 | F10: =SUM(C10*(1-D10-E10)) -> 71.992 | G10: 10.51 | H10: =SUM(F10*8%) -> 5.75936 | I10: =SUM(F10-G10-H10) -> 55.72264 | J10: 0.5 | K10: 0.6 | L10: 40 | M10: 3 | N10: =SUM(20%*15%*F10+G10+J10+L10+M10+1.04) -> 57.20976 | O10: 0.044 | P10: =SUM(N10*O10/(1-O10)) -> 2.6330852 | Q10: =SUM(I10-J10-K10-L10-M10-P10) -> 8.9895548 | R10: =SUM(Q10/C10) -> 0.099895042 | S10: ='总表（阶段盈亏）'!I10 -> 168 | T10: =SUM(Q10*S10) -> 1510.2452 | U10: =SUM(T10) -> 1510.2452
A11: 第三阶段 | B11: week09 | C11: 89.99 | D11: 0.1 | E11: 0 | F11: =SUM(C11*(1-D11-E11)) -> 80.991 | G11: 10.51 | H11: =SUM(F11*8%) -> 6.47928 | I11: =SUM(F11-G11-H11) -> 64.00172 | J11: 0.5 | K11: 0.6 | L11: 40 | M11: 3 | N11: =SUM(20%*15%*F11+G11+J11+L11+M11+1.04) -> 57.47973 | O11: 0.044 | P11: =SUM(N11*O11/(1-O11)) -> 2.6455106 | Q11: =SUM(I11-J11-K11-L11-M11-P11) -> 17.256209 | R11: =SUM(Q11/C11) -> 0.19175697 | S11: ='总表（阶段盈亏）'!I11 -> 182 | T11: =SUM(Q11*S11) -> 3140.6301 | U11: =SUM(T11) -> 3140.6301
B12: week10 | C12: 89.99 | D12: 0.1 | E12: 0 | F12: =SUM(C12*(1-D12-E12)) -> 80.991 | G12: 10.51 | H12: =SUM(F12*8%) -> 6.47928 | I12: =SUM(F12-G12-H12) -> 64.00172 | J12: 0.5 | K12: 0.6 | L12: 40 | M12: 3 | N12: =SUM(20%*15%*F12+G12+J12+L12+M12+1.04) -> 57.47973 | O12: 0.044 | P12: =SUM(N12*O12/(1-O12)) -> 2.6455106 | Q12: =SUM(I12-J12-K12-L12-M12-P12) -> 17.256209 | R12: =SUM(Q12/C12) -> 0.19175697 | S12: ='总表（阶段盈亏）'!I12 -> 259 | T12: =SUM(Q12*S12) -> 4469.3582 | U12: =SUM(T12) -> 4469.3582
B13: week11 | C13: 89.99 | D13: 0.1 | E13: 0 | F13: =SUM(C13*(1-D13-E13)) -> 80.991 | G13: 10.51 | H13: =SUM(F13*8%) -> 6.47928 | I13: =SUM(F13-G13-H13) -> 64.00172 | J13: 0.5 | K13: 0.6 | L13: 40 | M13: 3 | N13: =SUM(20%*15%*F13+G13+J13+L13+M13+1.04) -> 57.47973 | O13: 0.044 | P13: =SUM(N13*O13/(1-O13)) -> 2.6455106 | Q13: =SUM(I13-J13-K13-L13-M13-P13) -> 17.256209 | R13: =SUM(Q13/C13) -> 0.19175697 | S13: ='总表（阶段盈亏）'!I13 -> 210 | T13: =SUM(Q13*S13) -> 3623.804 | U13: =SUM(T13) -> 3623.804
B14: week12 | C14: 89.99 | D14: 0.1 | E14: 0 | F14: =SUM(C14*(1-D14-E14)) -> 80.991 | G14: 10.51 | H14: =SUM(F14*8%) -> 6.47928 | I14: =SUM(F14-G14-H14) -> 64.00172 | J14: 0.5 | K14: 0.6 | L14: 40 | M14: 3 | N14: =SUM(20%*15%*F14+G14+J14+L14+M14+1.04) -> 57.47973 | O14: 0.044 | P14: =SUM(N14*O14/(1-O14)) -> 2.6455106 | Q14: =SUM(I14-J14-K14-L14-M14-P14) -> 17.256209 | R14: =SUM(Q14/C14) -> 0.19175697 | S14: ='总表（阶段盈亏）'!I14 -> 371 | T14: =SUM(Q14*S14) -> 6402.0537 | U14: =SUM(T14) -> 6402.0537
A15: 第四阶段 | B15: week13 | C15: 79.99 | D15: 0 | E15: 0 | F15: =SUM(C15*(1-D15-E15)) -> 79.99 | G15: 10.51 | H15: =SUM(F15*8%) -> 6.3992 | I15: =SUM(F15-G15-H15) -> 63.0808 | J15: 0.5 | K15: 0 | L15: 40 | M15: 3 | N15: =SUM(20%*15%*F15+G15+J15+L15+M15+1.04) -> 57.4497 | O15: 0.044 | P15: =SUM(N15*O15/(1-O15)) -> 2.6441285 | Q15: =SUM(I15-J15-K15-L15-M15-P15) -> 16.936672 | R15: =SUM(Q15/C15) -> 0.21173486 | S15: ='总表（阶段盈亏）'!I15 -> 280 | T15: =SUM(Q15*S15) -> 4742.268 | U15: =SUM(T15) -> 4742.268
B16: week14 | C16: 79.99 | D16: 0 | E16: 0 | F16: =SUM(C16*(1-D16-E16)) -> 79.99 | G16: 10.51 | H16: =SUM(F16*8%) -> 6.3992 | I16: =SUM(F16-G16-H16) -> 63.0808 | J16: 0.5 | K16: 0 | L16: 40 | M16: 3 | N16: =SUM(20%*15%*F16+G16+J16+L16+M16+1.04) -> 57.4497 | O16: 0.044 | P16: =SUM(N16*O16/(1-O16)) -> 2.6441285 | Q16: =SUM(I16-J16-K16-L16-M16-P16) -> 16.936672 | R16: =SUM(Q16/C16) -> 0.21173486 | S16: ='总表（阶段盈亏）'!I16 -> 315 | T16: =SUM(Q16*S16) -> 5335.0515 | U16: =SUM(T16) -> 5335.0515
B17: week15 | C17: 79.99 | D17: 0 | E17: 0 | F17: =SUM(C17*(1-D17-E17)) -> 79.99 | G17: 10.51 | H17: =SUM(F17*8%) -> 6.3992 | I17: =SUM(F17-G17-H17) -> 63.0808 | J17: 0.5 | K17: 0 | L17: 40 | M17: 3 | N17: =SUM(20%*15%*F17+G17+J17+L17+M17+1.04) -> 57.4497 | O17: 0.044 | P17: =SUM(N17*O17/(1-O17)) -> 2.6441285 | Q17: =SUM(I17-J17-K17-L17-M17-P17) -> 16.936672 | R17: =SUM(Q17/C17) -> 0.21173486 | S17: ='总表（阶段盈亏）'!I17 -> 350 | T17: =SUM(Q17*S17) -> 5927.835 | U17: =SUM(T17) -> 5927.835
B18: week16 | C18: 79.99 | D18: 0 | E18: 0 | F18: =SUM(C18*(1-D18-E18)) -> 79.99 | G18: 10.51 | H18: =SUM(F18*8%) -> 6.3992 | I18: =SUM(F18-G18-H18) -> 63.0808 | J18: 0.5 | K18: 0 | L18: 40 | M18: 3 | N18: =SUM(20%*15%*F18+G18+J18+L18+M18+1.04) -> 57.4497 | O18: 0.044 | P18: =SUM(N18*O18/(1-O18)) -> 2.6441285 | Q18: =SUM(I18-J18-K18-L18-M18-P18) -> 16.936672 | R18: =SUM(Q18/C18) -> 0.21173486 | S18: ='总表（阶段盈亏）'!I18 -> 490 | T18: =SUM(Q18*S18) -> 8298.9691 | U18: =SUM(T18) -> 8298.9691
A19: 第五阶段 | B19: week17 | C19: 79.99 | D19: 0 | E19: 0 | F19: =SUM(C19*(1-D19-E19)) -> 79.99 | G19: 10.51 | H19: =SUM(F19*8%) -> 6.3992 | I19: =SUM(F19-G19-H19) -> 63.0808 | J19: 0.5 | K19: 0 | L19: 40 | M19: 3 | N19: =SUM(20%*15%*F19+G19+J19+L19+M19+1.04) -> 57.4497 | O19: 0.044 | P19: =SUM(N19*O19/(1-O19)) -> 2.6441285 | Q19: =SUM(I19-J19-K19-L19-M19-P19) -> 16.936672 | R19: =SUM(Q19/C19) -> 0.21173486 | S19: ='总表（阶段盈亏）'!I19 -> 490 | T19: =SUM(Q19*S19) -> 8298.9691 | U19: =SUM(T19) -> 8298.9691
B20: week18 | C20: 79.99 | D20: 0 | E20: 0 | F20: =SUM(C20*(1-D20-E20)) -> 79.99 | G20: 10.51 | H20: =SUM(F20*8%) -> 6.3992 | I20: =SUM(F20-G20-H20) -> 63.0808 | J20: 0.5 | K20: 0 | L20: 40 | M20: 3 | N20: =SUM(20%*15%*F20+G20+J20+L20+M20+1.04) -> 57.4497 | O20: 0.044 | P20: =SUM(N20*O20/(1-O20)) -> 2.6441285 | Q20: =SUM(I20-J20-K20-L20-M20-P20) -> 16.936672 | R20: =SUM(Q20/C20) -> 0.21173486 | S20: ='总表（阶段盈亏）'!I20 -> 490 | T20: =SUM(Q20*S20) -> 8298.9691 | U20: =SUM(T20) -> 8298.9691
B21: week19 | C21: 79.99 | D21: 0 | E21: 0 | F21: =SUM(C21*(1-D21-E21)) -> 79.99 | G21: 10.51 | H21: =SUM(F21*8%) -> 6.3992 | I21: =SUM(F21-G21-H21) -> 63.0808 | J21: 0.5 | K21: 0 | L21: 40 | M21: 3 | N21: =SUM(20%*15%*F21+G21+J21+L21+M21+1.04) -> 57.4497 | O21: 0.044 | P21: =SUM(N21*O21/(1-O21)) -> 2.6441285 | Q21: =SUM(I21-J21-K21-L21-M21-P21) -> 16.936672 | R21: =SUM(Q21/C21) -> 0.21173486 | S21: ='总表（阶段盈亏）'!I21 -> 490 | T21: =SUM(Q21*S21) -> 8298.9691 | U21: =SUM(T21) -> 8298.9691
B22: week20 | C22: 79.99 | D22: 0 | E22: 0 | F22: =SUM(C22*(1-D22-E22)) -> 79.99 | G22: 10.51 | H22: =SUM(F22*8%) -> 6.3992 | I22: =SUM(F22-G22-H22) -> 63.0808 | J22: 0.5 | K22: 0 | L22: 40 | M22: 3 | N22: =SUM(20%*15%*F22+G22+J22+L22+M22+1.04) -> 57.4497 | O22: 0.044 | P22: =SUM(N22*O22/(1-O22)) -> 2.6441285 | Q22: =SUM(I22-J22-K22-L22-M22-P22) -> 16.936672 | R22: =SUM(Q22/C22) -> 0.21173486 | S22: ='总表（阶段盈亏）'!I22 -> 490 | T22: =SUM(Q22*S22) -> 8298.9691 | U22: =SUM(T22) -> 8298.9691
A23: 第六阶段 | B23: week21 | C23: 79.99 | D23: 0 | E23: 0 | F23: =SUM(C23*(1-D23-E23)) -> 79.99 | G23: 10.51 | H23: =SUM(F23*8%) -> 6.3992 | I23: =SUM(F23-G23-H23) -> 63.0808 | J23: 0.5 | K23: 0 | L23: 40 | M23: 3 | N23: =SUM(20%*15%*F23+G23+J23+L23+M23+1.04) -> 57.4497 | O23: 0.044 | P23: =SUM(N23*O23/(1-O23)) -> 2.6441285 | Q23: =SUM(I23-J23-K23-L23-M23-P23) -> 16.936672 | R23: =SUM(Q23/C23) -> 0.21173486 | S23: ='总表（阶段盈亏）'!I23 -> 490 | T23: =SUM(Q23*S23) -> 8298.9691 | U23: =SUM(T23) -> 8298.9691
B24: week22 | C24: 79.99 | D24: 0 | E24: 0 | F24: =SUM(C24*(1-D24-E24)) -> 79.99 | G24: 10.51 | H24: =SUM(F24*8%) -> 6.3992 | I24: =SUM(F24-G24-H24) -> 63.0808 | J24: 0.5 | K24: 0 | L24: 40 | M24: 3 | N24: =SUM(20%*15%*F24+G24+J24+L24+M24+1.04) -> 57.4497 | O24: 0.044 | P24: =SUM(N24*O24/(1-O24)) -> 2.6441285 | Q24: =SUM(I24-J24-K24-L24-M24-P24) -> 16.936672 | R24: =SUM(Q24/C24) -> 0.21173486 | S24: ='总表（阶段盈亏）'!I24 -> 490 | T24: =SUM(Q24*S24) -> 8298.9691 | U24: =SUM(T24) -> 8298.9691
B25: week23 | C25: 79.99 | D25: 0 | E25: 0 | F25: =SUM(C25*(1-D25-E25)) -> 79.99 | G25: 10.51 | H25: =SUM(F25*8%) -> 6.3992 | I25: =SUM(F25-G25-H25) -> 63.0808 | J25: 0.5 | K25: 0 | L25: 40 | M25: 3 | N25: =SUM(20%*15%*F25+G25+J25+L25+M25+1.04) -> 57.4497 | O25: 0.044 | P25: =SUM(N25*O25/(1-O25)) -> 2.6441285 | Q25: =SUM(I25-J25-K25-L25-M25-P25) -> 16.936672 | R25: =SUM(Q25/C25) -> 0.21173486 | S25: ='总表（阶段盈亏）'!I25 -> 490 | T25: =SUM(Q25*S25) -> 8298.9691 | U25: =SUM(T25) -> 8298.9691
B26: week24 | C26: 79.99 | D26: 0 | E26: 0 | F26: =SUM(C26*(1-D26-E26)) -> 79.99 | G26: 10.51 | H26: =SUM(F26*8%) -> 6.3992 | I26: =SUM(F26-G26-H26) -> 63.0808 | J26: 0.5 | K26: 0 | L26: 40 | M26: 3 | N26: =SUM(20%*15%*F26+G26+J26+L26+M26+1.04) -> 57.4497 | O26: 0.044 | P26: =SUM(N26*O26/(1-O26)) -> 2.6441285 | Q26: =SUM(I26-J26-K26-L26-M26-P26) -> 16.936672 | R26: =SUM(Q26/C26) -> 0.21173486 | S26: ='总表（阶段盈亏）'!I26 -> 490 | T26: =SUM(Q26*S26) -> 8298.9691 | U26: =SUM(T26) -> 8298.9691
A28: 每日盈亏真实数据
A29: 第一阶段 | B29: 第1周 | C29: 89.99 | D29: 0.3 | E29: 0 | F29: 62.993 | G29: 10.51 | H29: 5.03944 | I29: 47.44356 | J29: 0.5 | K29: 0.6 | L29: 40 | M29: 3 | N29: 56.93979 | O29: 0.044 | P29: 2.6206598 | Q29: 0.72290021 | R29: 0.0080331171 | S29: 21 | T29: 15.180904 | U29: 15.180904
B30: 第2周 | C30: 89.99 | D30: 0.3 | E30: 0 | F30: 62.993 | G30: 10.51 | H30: 5.03944 | I30: 47.44356 | J30: 0.5 | K30: 0.6 | L30: 40 | M30: 3 | N30: 56.93979 | O30: 0.044 | P30: 2.6206598 | Q30: 0.72290021 | R30: 0.0080331171 | S30: 49 | T30: 35.42211 | U30: 35.42211
B31: 第3周 | C31: 89.99 | D31: 0.3 | E31: 0 | F31: 62.993 | G31: 10.51 | H31: 5.03944 | I31: 47.44356 | J31: 0.5 | K31: 0.6 | L31: 40 | M31: 3 | N31: 56.93979 | O31: 0.044 | P31: 2.6206598 | Q31: 0.72290021 | R31: 0.0080331171 | S31: 70 | T31: 50.603015 | U31: 50.603015
B32: 第4周 | C32: 89.99 | D32: 0.3 | E32: 0 | F32: 62.993 | G32: 10.51 | H32: 5.03944 | I32: 47.44356 | J32: 0.5 | K32: 0.6 | L32: 40 | M32: 3 | N32: 56.93979 | O32: 0.044 | P32: 2.6206598 | Q32: 0.72290021 | R32: 0.0080331171 | S32: 84 | T32: 60.723618 | U32: 60.723618
A33: 第二阶段 | B33: 第5周 | C33: 89.99 | D33: 0.2 | E33: 0 | F33: 71.992 | G33: 10.51 | H33: 5.75936 | I33: 55.72264 | J33: 0.5 | K33: 0.6 | L33: 40 | M33: 3 | N33: 57.20976 | O33: 0.044 | P33: 2.6330852 | Q33: 8.9895548 | R33: 0.099895042 | S33: 105 | T33: 943.90326 | U33: 943.90326
B34: 第6周 | C34: 89.99 | D34: 0.2 | E34: 0 | F34: 71.992 | G34: 10.51 | H34: 5.75936 | I34: 55.72264 | J34: 0.5 | K34: 0.6 | L34: 40 | M34: 3 | N34: 57.20976 | O34: 0.044 | P34: 2.6330852 | Q34: 8.9895548 | R34: 0.099895042 | S34: 126 | T34: 1132.6839 | U34: 1132.6839
B35: 第7周 | C35: 89.99 | D35: 0.2 | E35: 0 | F35: 71.992 | G35: 10.51 | H35: 5.75936 | I35: 55.72264 | J35: 0.5 | K35: 0.6 | L35: 40 | M35: 3 | N35: 57.20976 | O35: 0.044 | P35: 2.6330852 | Q35: 8.9895548 | R35: 0.099895042 | S35: 140 | T35: 1258.5377 | U35: 1258.5377
B36: 第8周 | C36: 89.99 | D36: 0.2 | E36: 0 | F36: 71.992 | G36: 10.51 | H36: 5.75936 | I36: 55.72264 | J36: 0.5 | K36: 0.6 | L36: 40 | M36: 3 | N36: 57.20976 | O36: 0.044 | P36: 2.6330852 | Q36: 8.9895548 | R36: 0.099895042 | S36: 168 | T36: 1510.2452 | U36: 1510.2452
A37: 第三阶段 | B37: 第9周 | C37: 89.99 | D37: 0.1 | E37: 0 | F37: 80.991 | G37: 10.51 | H37: 6.47928 | I37: 64.00172 | J37: 0.5 | K37: 0.6 | L37: 40 | M37: 3 | N37: 57.47973 | O37: 0.044 | P37: 2.6455106 | Q37: 17.256209 | R37: 0.19175697 | S37: 182 | T37: 3140.6301 | U37: 3140.6301
B38: 第10周 | C38: 89.99 | D38: 0.1 | E38: 0 | F38: 80.991 | G38: 10.51 | H38: 6.47928 | I38: 64.00172 | J38: 0.5 | K38: 0.6 | L38: 40 | M38: 3 | N38: 57.47973 | O38: 0.044 | P38: 2.6455106 | Q38: 17.256209 | R38: 0.19175697 | S38: 259 | T38: 4469.3582 | U38: 4469.3582
B39: 第11周 | C39: 89.99 | D39: 0.1 | E39: 0 | F39: 80.991 | G39: 10.51 | H39: 6.47928 | I39: 64.00172 | J39: 0.5 | K39: 0.6 | L39: 40 | M39: 3 | N39: 57.47973 | O39: 0.044 | P39: 2.6455106 | Q39: 17.256209 | R39: 0.19175697 | S39: 210 | T39: 3623.804 | U39: 3623.804
B40: 第12周 | C40: 89.99 | D40: 0.1 | E40: 0 | F40: 80.991 | G40: 10.51 | H40: 6.47928 | I40: 64.00172 | J40: 0.5 | K40: 0.6 | L40: 40 | M40: 3 | N40: 57.47973 | O40: 0.044 | P40: 2.6455106 | Q40: 17.256209 | R40: 0.19175697 | S40: 371 | T40: 6402.0537 | U40: 6402.0537
A41: 第四阶段 | B41: 第13周 | C41: 79.99 | D41: 0 | E41: 0 | F41: 79.99 | G41: 10.51 | H41: 6.3992 | I41: 63.0808 | J41: 0.5 | K41: 0 | L41: 40 | M41: 3 | N41: 57.4497 | O41: 0.044 | P41: 2.6441285 | Q41: 16.936672 | R41: 0.21173486 | S41: 280 | T41: 4742.268 | U41: 4742.268
B42: 第14周 | C42: 79.99 | D42: 0 | E42: 0 | F42: 79.99 | G42: 10.51 | H42: 6.3992 | I42: 63.0808 | J42: 0.5 | K42: 0 | L42: 40 | M42: 3 | N42: 57.4497 | O42: 0.044 | P42: 2.6441285 | Q42: 16.936672 | R42: 0.21173486 | S42: 315 | T42: 5335.0515 | U42: 5335.0515
B43: 第15周 | C43: 79.99 | D43: 0 | E43: 0 | F43: 79.99 | G43: 10.51 | H43: 6.3992 | I43: 63.0808 | J43: 0.5 | K43: 0 | L43: 40 | M43: 3 | N43: 57.4497 | O43: 0.044 | P43: 2.6441285 | Q43: 16.936672 | R43: 0.21173486 | S43: 350 | T43: 5927.835 | U43: 5927.835
B44: 第16周 | C44: 79.99 | D44: 0 | E44: 0 | F44: 79.99 | G44: 10.51 | H44: 6.3992 | I44: 63.0808 | J44: 0.5 | K44: 0 | L44: 40 | M44: 3 | N44: 57.4497 | O44: 0.044 | P44: 2.6441285 | Q44: 16.936672 | R44: 0.21173486 | S44: 490 | T44: 8298.9691 | U44: 8298.9691
A45: 第五阶段 | B45: 第17周 | C45: 79.99 | D45: 0 | E45: 0 | F45: 79.99 | G45: 10.51 | H45: 6.3992 | I45: 63.0808 | J45: 0.5 | K45: 0 | L45: 40 | M45: 3 | N45: 57.4497 | O45: 0.044 | P45: 2.6441285 | Q45: 16.936672 | R45: 0.21173486 | S45: 490 | T45: 8298.9691 | U45: 8298.9691
B46: 第18周 | C46: 79.99 | D46: 0 | E46: 0 | F46: 79.99 | G46: 10.51 | H46: 6.3992 | I46: 63.0808 | J46: 0.5 | K46: 0 | L46: 40 | M46: 3 | N46: 57.4497 | O46: 0.044 | P46: 2.6441285 | Q46: 16.936672 | R46: 0.21173486 | S46: 490 | T46: 8298.9691 | U46: 8298.9691
B47: 第19周 | C47: 79.99 | D47: 0 | E47: 0 | F47: 79.99 | G47: 10.51 | H47: 6.3992 | I47: 63.0808 | J47: 0.5 | K47: 0 | L47: 40 | M47: 3 | N47: 57.4497 | O47: 0.044 | P47: 2.6441285 | Q47: 16.936672 | R47: 0.21173486 | S47: 490 | T47: 8298.9691 | U47: 8298.9691
B48: 第20周 | C48: 79.99 | D48: 0 | E48: 0 | F48: 79.99 | G48: 10.51 | H48: 6.3992 | I48: 63.0808 | J48: 0.5 | K48: 0 | L48: 40 | M48: 3 | N48: 57.4497 | O48: 0.044 | P48: 2.6441285 | Q48: 16.936672 | R48: 0.21173486 | S48: 490 | T48: 8298.9691 | U48: 8298.9691
A49: 第六阶段 | B49: 第21周 | C49: 79.99 | D49: 0 | E49: 0 | F49: 79.99 | G49: 10.51 | H49: 6.3992 | I49: 63.0808 | J49: 0.5 | K49: 0 | L49: 40 | M49: 3 | N49: 57.4497 | O49: 0.044 | P49: 2.6441285 | Q49: 16.936672 | R49: 0.21173486 | S49: 490 | T49: 8298.9691 | U49: 8298.9691
B50: 第22周 | C50: 79.99 | D50: 0 | E50: 0 | F50: 79.99 | G50: 10.51 | H50: 6.3992 | I50: 63.0808 | J50: 0.5 | K50: 0 | L50: 40 | M50: 3 | N50: 57.4497 | O50: 0.044 | P50: 2.6441285 | Q50: 16.936672 | R50: 0.21173486 | S50: 490 | T50: 8298.9691 | U50: 8298.9691
B51: 第23周 | C51: 79.99 | D51: 0 | E51: 0 | F51: 79.99 | G51: 10.51 | H51: 6.3992 | I51: 63.0808 | J51: 0.5 | K51: 0 | L51: 40 | M51: 3 | N51: 57.4497 | O51: 0.044 | P51: 2.6441285 | Q51: 16.936672 | R51: 0.21173486 | S51: 490 | T51: 8298.9691 | U51: 8298.9691
B52: 第24周 | C52: 79.99 | D52: 0 | E52: 0 | F52: 79.99 | G52: 10.51 | H52: 6.3992 | I52: 63.0808 | J52: 0.5 | K52: 0 | L52: 40 | M52: 3 | N52: 57.4497 | O52: 0.044 | P52: 2.6441285 | Q52: 16.936672 | R52: 0.21173486 | S52: 490 | T52: 8298.9691 | U52: 8298.9691

Sheet 总表（阶段盈亏） (调整后)
A1: 按照每周/每日不同的数据表现情况进行调整： | AB1: https://mp.weixin.qq.com/s/hJXWLb-KpYE6J5aK37fUqA?poc_token=HER7cGijba2sEL_p1d8TCVeaPrsbMxX-Mtg-J8JD
A2: 周 | B2: 星期 | C2: 名称 | D2: 店铺SKU | E2: ASIN | F2: Rating数 | G2: 星级 | H2: QA数量 | I2: 操作 | J2: flashlihte | K2: 访问IP数 | L2: 自然流量 | M2: 浏览量 | N2: 转化率 | O2: 总订单 | P2: 总销售额 | Q2: 总销量 | R2: 曝光量 | S2: 点击 | T2: 广告订单 | U2: CTR | V2: CVR | W2: 总花费 | X2: CPC | Y2: 广告销售额 | Z2: ACOS | AA2: 广告订单占比 | AB2: 广告订单占比
A3: ①周 | B3: 星期一 | AB3: Q&A数 QA图片视频， 评论数，星级，评论的质量： 前台首页无差评 3星，以及点赞数量（前3个评论，首页）
B4: 星期二
B5: 星期三
B6: 星期四
B7: 星期五
B8: 星期六
B9: 星期日
A10: 第一周
A11: ②周 | B11: 星期一
B12: 星期二
B13: 星期三
B14: 星期四
B15: 星期五
B16: 星期六
B17: 星期日
A18: 第二周
A19: ③周 | B19: 星期一
B20: 星期二
B21: 星期三
B22: 星期四
B23: 星期五
B24: 星期六
B25: 星期日
A26: 第三周
A27: ④周 | B27: 星期一
B28: 星期二
B29: 星期三
B30: 星期四
B31: 星期五
B32: 星期六
B33: 星期日
A34: 第四周
A35: ⑤周 | B35: 星期一
B36: 星期二
B37: 星期三
B38: 星期四
B39: 星期五
B40: 星期六
B41: 星期日
A42: 第五周
A43: ⑥周 | B43: 星期一
B44: 星期二
B45: 星期三
B46: 星期四
B47: 星期五
B48: 星期六
B49: 星期日
A50: 第六周
A67: 周盈亏真实数据
A68: 第一周 | B68: 第1周
B69: 第2周
B70: 第3周
B71: 第4周
A72: 第二周 | B72: 第5周
B73: 第6周
B74: 第7周
B75: 第8周
A76: 第三周 | B76: 第9周
B77: 第10周
B78: 第11周
B79: 第12周
A80: 第四周 | B80: 第13周
B81: 第14周
B82: 第15周
B83: 第16周
A84: 第五周 | B84: 第17周
B85: 第18周
B86: 第19周
B87: 第20周
A88: 第六周 | B88: 第21周
B89: 第22周
B90: 第23周
B91: 第24周

Sheet CPC表格
A1: 广告数据模拟
A2: 常规数据 | N2: 广告数据 | AB2: 实时更新 | AC2: 操作备注
A3: 阶段 | B3: 周 | C3: 价格 | D3: 站内 coupon | E3: 站内 code | F3: 折后价 | G3: 新品 榜单 | H3: 小类目 排名 | I3: 总 销量 | J3: 总访 问量 | K3: CVR | L3: 评论 数量 | M3: 评分 | N3: 曝光量 | O3: 点击量 | P3: CTR | Q3: 广告单 | R3: CVR | S3: 平均 CPC | T3: 花费 | U3: ACOS | V3: CPA | W3: 日均 广告费 | X3: 自然 访问 | Y3: 自然 订单 | Z3: 自然 单占比 | AA3: 最终 盈亏 | AB3: Sif 质量分 | AC3: 运营调整 | AD3: 广告操作
A4: 第一阶段 | C4: 79.99 | D4: 0.3 | E4: 0 | F4: =SUM(C4*(1-D4-E4)) -> 55.993 | O4: =SUM(Q4/R4) -> 262.5 | Q4: ='总表（阶段盈亏）'!H3 -> 21 | R4: 0.08 | S4: 1.91 | T4: =SUM(O4*S4) -> 501.375 | U4: =SUM(S4/R4/C4) -> 0.29847481 | V4: =SUM(T4/Q4) -> 23.875 | W4: =T4/7 -> 71.625
C5: 89.99 | D5: 0.3 | E5: 0 | F5: =SUM(C5*(1-D5-E5)) -> 62.993 | O5: =SUM(Q5/R5) -> 437.5 | Q5: ='总表（阶段盈亏）'!H4 -> 35 | R5: 0.08 | S5: 1.91 | T5: =SUM(O5*S5) -> 835.625 | U5: =SUM(S5/R5/C5) -> 0.26530726 | V5: =SUM(T5/Q5) -> 23.875 | W5: =T5/7 -> 119.375
C6: 89.99 | D6: 0.3 | E6: 0 | F6: =SUM(C6*(1-D6-E6)) -> 62.993 | O6: =SUM(Q6/R6) -> 525 | Q6: ='总表（阶段盈亏）'!H5 -> 42 | R6: 0.08 | S6: 1.91 | T6: =SUM(O6*S6) -> 1002.75 | U6: =SUM(S6/R6/C6) -> 0.26530726 | V6: =SUM(T6/Q6) -> 23.875 | W6: =T6/7 -> 143.25
C7: 89.99 | D7: 0.3 | E7: 0 | F7: =SUM(C7*(1-D7-E7)) -> 62.993 | O7: =SUM(Q7/R7) -> 612.5 | Q7: ='总表（阶段盈亏）'!H6 -> 49 | R7: 0.08 | S7: 1.91 | T7: =SUM(O7*S7) -> 1169.875 | U7: =SUM(S7/R7/C7) -> 0.26530726 | V7: =SUM(T7/Q7) -> 23.875 | W7: =T7/7 -> 167.125
A8: 第二阶段 | C8: 85.99 | D8: 0.2 | E8: 0 | F8: =SUM(C8*(1-D8-E8)) -> 68.792 | O8: =SUM(Q8/R8) -> 741.17647 | Q8: ='总表（阶段盈亏）'!H7 -> 63 | R8: 0.085 | S8: 1.87 | T8: =SUM(O8*S8) -> 1386 | U8: =SUM(S8/R8/C8) -> 0.2558437 | V8: =SUM(T8/Q8) -> 22 | W8: =T8/7 -> 198
C9: 85.99 | D9: 0.2 | E9: 0 | F9: =SUM(C9*(1-D9-E9)) -> 68.792 | O9: =SUM(Q9/R9) -> 823.52941 | Q9: ='总表（阶段盈亏）'!H8 -> 70 | R9: 0.085 | S9: 1.87 | T9: =SUM(O9*S9) -> 1540 | U9: =SUM(S9/R9/C9) -> 0.2558437 | V9: =SUM(T9/Q9) -> 22 | W9: =T9/7 -> 220
C10: 85.99 | D10: 0.2 | E10: 0 | F10: =SUM(C10*(1-D10-E10)) -> 68.792 | O10: =SUM(Q10/R10) -> 988.23529 | Q10: ='总表（阶段盈亏）'!H9 -> 84 | R10: 0.085 | S10: 1.87 | T10: =SUM(O10*S10) -> 1848 | U10: =SUM(S10/R10/C10) -> 0.2558437 | V10: =SUM(T10/Q10) -> 22 | W10: =T10/7 -> 264
C11: 85.99 | D11: 0.2 | E11: 0 | F11: =SUM(C11*(1-D11-E11)) -> 68.792 | O11: =SUM(Q11/R11) -> 988.23529 | Q11: ='总表（阶段盈亏）'!H10 -> 84 | R11: 0.085 | S11: 1.87 | T11: =SUM(O11*S11) -> 1848 | U11: =SUM(S11/R11/C11) -> 0.2558437 | V11: =SUM(T11/Q11) -> 22 | W11: =T11/7 -> 264
A12: 第三阶段 | C12: 85.99 | D12: 0.1 | E12: 0 | F12: =SUM(C12*(1-D12-E12)) -> 77.391 | O12: =SUM(Q12/R12) -> 1088.8889 | Q12: ='总表（阶段盈亏）'!H11 -> 98 | R12: 0.09 | S12: 1.84 | T12: =SUM(O12*S12) -> 2003.5556 | U12: =SUM(S12/R12/C12) -> 0.23775374 | V12: =SUM(T12/Q12) -> 20.444444 | W12: =T12/7 -> 286.22222
C13: 85.99 | D13: 0.1 | E13: 0 | F13: =SUM(C13*(1-D13-E13)) -> 77.391 | O13: =SUM(Q13/R13) -> 1166.6667 | Q13: ='总表（阶段盈亏）'!H12 -> 105 | R13: 0.09 | S13: 1.84 | T13: =SUM(O13*S13) -> 2146.6667 | U13: =SUM(S13/R13/C13) -> 0.23775374 | V13: =SUM(T13/Q13) -> 20.444444 | W13: =T13/7 -> 306.66667
C14: 85.99 | D14: 0.1 | E14: 0 | F14: =SUM(C14*(1-D14-E14)) -> 77.391 | O14: =SUM(Q14/R14) -> 1166.6667 | Q14: ='总表（阶段盈亏）'!H13 -> 105 | R14: 0.09 | S14: 1.84 | T14: =SUM(O14*S14) -> 2146.6667 | U14: =SUM(S14/R14/C14) -> 0.23775374 | V14: =SUM(T14/Q14) -> 20.444444 | W14: =T14/7 -> 306.66667
C15: 85.99 | D15: 0.1 | E15: 0 | F15: =SUM(C15*(1-D15-E15)) -> 77.391 | O15: =SUM(Q15/R15) -> 1244.4444 | Q15: ='总表（阶段盈亏）'!H14 -> 112 | R15: 0.09 | S15: 1.84 | T15: =SUM(O15*S15) -> 2289.7778 | U15: =SUM(S15/R15/C15) -> 0.23775374 | V15: =SUM(T15/Q15) -> 20.444444 | W15: =T15/7 -> 327.11111
A16: 第四阶段 | C16: 79.99 | D16: 0 | E16: 0 | F16: =SUM(C16*(1-D16-E16)) -> 79.99 | O16: =SUM(Q16/R16) -> 1482.3529 | Q16: ='总表（阶段盈亏）'!H15 -> 126 | R16: 0.085 | S16: 1.8 | T16: =SUM(O16*S16) -> 2668.2353 | U16: =SUM(S16/R16/C16) -> 0.26473897 | V16: =SUM(T16/Q16) -> 21.176471 | W16: =T16/7 -> 381.17647
C17: 79.99 | D17: 0 | E17: 0 | F17: =SUM(C17*(1-D17-E17)) -> 79.99 | O17: =SUM(Q17/R17) -> 1647.0588 | Q17: ='总表（阶段盈亏）'!H16 -> 140 | R17: 0.085 | S17: 1.8 | T17: =SUM(O17*S17) -> 2964.7059 | U17: =SUM(S17/R17/C17) -> 0.26473897 | V17: =SUM(T17/Q17) -> 21.176471 | W17: =T17/7 -> 423.52941
C18: 79.99 | D18: 0 | E18: 0 | F18: =SUM(C18*(1-D18-E18)) -> 79.99 | O18: =SUM(Q18/R18) -> 1811.7647 | Q18: ='总表（阶段盈亏）'!H17 -> 154 | R18: 0.085 | S18: 1.8 | T18: =SUM(O18*S18) -> 3261.1765 | U18: =SUM(S18/R18/C18) -> 0.26473897 | V18: =SUM(T18/Q18) -> 21.176471 | W18: =T18/7 -> 465.88235
C19: 79.99 | D19: 0 | E19: 0 | F19: =SUM(C19*(1-D19-E19)) -> 79.99 | O19: =SUM(Q19/R19) -> 2058.8235 | Q19: ='总表（阶段盈亏）'!H18 -> 175 | R19: 0.085 | S19: 1.8 | T19: =SUM(O19*S19) -> 3705.8824 | U19: =SUM(S19/R19/C19) -> 0.26473897 | V19: =SUM(T19/Q19) -> 21.176471 | W19: =T19/7 -> 529.41176
A20: 第五阶段 | C20: 79.99 | D20: 0 | E20: 0 | F20: =SUM(C20*(1-D20-E20)) -> 79.99 | O20: =SUM(Q20/R20) -> 2058.8235 | Q20: ='总表（阶段盈亏）'!H19 -> 175 | R20: 0.085 | S20: 1.8 | T20: =SUM(O20*S20) -> 3705.8824 | U20: =SUM(S20/R20/C20) -> 0.26473897 | V20: =SUM(T20/Q20) -> 21.176471 | W20: =T20/7 -> 529.41176
C21: 79.99 | D21: 0 | E21: 0 | F21: =SUM(C21*(1-D21-E21)) -> 79.99 | O21: =SUM(Q21/R21) -> 2058.8235 | Q21: ='总表（阶段盈亏）'!H20 -> 175 | R21: 0.085 | S21: 1.8 | T21: =SUM(O21*S21) -> 3705.8824 | U21: =SUM(S21/R21/C21) -> 0.26473897 | V21: =SUM(T21/Q21) -> 21.176471 | W21: =T21/7 -> 529.41176
C22: 79.99 | D22: 0 | E22: 0 | F22: =SUM(C22*(1-D22-E22)) -> 79.99 | O22: =SUM(Q22/R22) -> 2058.8235 | Q22: ='总表（阶段盈亏）'!H21 -> 175 | R22: 0.085 | S22: 1.8 | T22: =SUM(O22*S22) -> 3705.8824 | U22: =SUM(S22/R22/C22) -> 0.26473897 | V22: =SUM(T22/Q22) -> 21.176471 | W22: =T22/7 -> 529.41176
C23: 79.99 | D23: 0 | E23: 0 | F23: =SUM(C23*(1-D23-E23)) -> 79.99 | O23: =SUM(Q23/R23) -> 2058.8235 | Q23: ='总表（阶段盈亏）'!H22 -> 175 | R23: 0.085 | S23: 1.8 | T23: =SUM(O23*S23) -> 3705.8824 | U23: =SUM(S23/R23/C23) -> 0.26473897 | V23: =SUM(T23/Q23) -> 21.176471 | W23: =T23/7 -> 529.41176
A24: 第六阶段 | C24: 79.99 | D24: 0 | E24: 0 | F24: =SUM(C24*(1-D24-E24)) -> 79.99 | O24: =SUM(Q24/R24) -> 2058.8235 | Q24: ='总表（阶段盈亏）'!H23 -> 175 | R24: 0.085 | S24: 1.8 | T24: =SUM(O24*S24) -> 3705.8824 | U24: =SUM(S24/R24/C24) -> 0.26473897 | V24: =SUM(T24/Q24) -> 21.176471 | W24: =T24/7 -> 529.41176
C25: 79.99 | D25: 0 | E25: 0 | F25: =SUM(C25*(1-D25-E25)) -> 79.99 | O25: =SUM(Q25/R25) -> 2058.8235 | Q25: ='总表（阶段盈亏）'!H24 -> 175 | R25: 0.085 | S25: 1.8 | T25: =SUM(O25*S25) -> 3705.8824 | U25: =SUM(S25/R25/C25) -> 0.26473897 | V25: =SUM(T25/Q25) -> 21.176471 | W25: =T25/7 -> 529.41176
C26: 79.99 | D26: 0 | E26: 0 | F26: =SUM(C26*(1-D26-E26)) -> 79.99 | O26: =SUM(Q26/R26) -> 2058.8235 | Q26: ='总表（阶段盈亏）'!H25 -> 175 | R26: 0.085 | S26: 1.8 | T26: =SUM(O26*S26) -> 3705.8824 | U26: =SUM(S26/R26/C26) -> 0.26473897 | V26: =SUM(T26/Q26) -> 21.176471 | W26: =T26/7 -> 529.41176
C27: 79.99 | D27: 0 | E27: 0 | F27: =SUM(C27*(1-D27-E27)) -> 79.99 | O27: =SUM(Q27/R27) -> 2058.8235 | Q27: ='总表（阶段盈亏）'!H26 -> 175 | R27: 0.085 | S27: 1.8 | T27: =SUM(O27*S27) -> 3705.8824 | U27: =SUM(S27/R27/C27) -> 0.26473897 | V27: =SUM(T27/Q27) -> 21.176471 | W27: =T27/7 -> 529.41176
A29: 广告真实数据
A30: 常规数据 | N30: 广告数据 | AB30: 实时更新 | AC30: 操作备注
A31: 阶段 | B31: 周 | C31: 价格 | D31: 站内 coupon | E31: 站内 code | F31: 折后价 | G31: 新品 榜单 | H31: 小类目 排名 | I31: 总 销量 | J31: 总访 问量 | K31: CVR | L31: 评论 数量 | M31: 评分 | N31: 曝光量 | O31: 点击量 | P31: CTR | Q31: 广告单 | R31: CVR | S31: 平均 CPC | T31: 花费 | U31: ACOS | V31: CPA | W31: 日均 广告费 | X31: 自然 访问 | Y31: 自然 订单 | Z31: 自然 单占比 | AA31: 最终 盈亏 | AB31: Sif 质量分 | AC31: 运营调整 | AD31: 广告操作
A32: 第一阶段 | B32: 第1周 | C32: 79.99 | D32: 0.3 | E32: 0 | F32: 55.993 | O32: 262.5 | Q32: 21 | R32: 0.08 | S32: 1.91 | T32: 501.375 | U32: 0.29847481 | V32: 23.875 | W32: 71.625
B33: 第2周 | C33: 89.99 | D33: 0.3 | E33: 0 | F33: 62.993 | O33: 437.5 | Q33: 35 | R33: 0.08 | S33: 1.91 | T33: 835.625 | U33: 0.26530726 | V33: 23.875 | W33: 119.375
B34: 第3周 | C34: 89.99 | D34: 0.3 | E34: 0 | F34: 62.993 | O34: 525 | Q34: 42 | R34: 0.08 | S34: 1.91 | T34: 1002.75 | U34: 0.26530726 | V34: 23.875 | W34: 143.25
B35: 第4周 | C35: 89.99 | D35: 0.3 | E35: 0 | F35: 62.993 | O35: 612.5 | Q35: 49 | R35: 0.08 | S35: 1.91 | T35: 1169.875 | U35: 0.26530726 | V35: 23.875 | W35: 167.125
A36: 第二阶段 | B36: 第5周 | C36: 85.99 | D36: 0.2 | E36: 0 | F36: 68.792 | O36: 741.17647 | Q36: 63 | R36: 0.085 | S36: 1.87 | T36: 1386 | U36: 0.2558437 | V36: 22 | W36: 198
B37: 第6周 | C37: 85.99 | D37: 0.2 | E37: 0 | F37: 68.792 | O37: 823.52941 | Q37: 70 | R37: 0.085 | S37: 1.87 | T37: 1540 | U37: 0.2558437 | V37: 22 | W37: 220
B38: 第7周 | C38: 85.99 | D38: 0.2 | E38: 0 | F38: 68.792 | O38: 988.23529 | Q38: 84 | R38: 0.085 | S38: 1.87 | T38: 1848 | U38: 0.2558437 | V38: 22 | W38: 264
B39: 第8周 | C39: 85.99 | D39: 0.2 | E39: 0 | F39: 68.792 | O39: 988.23529 | Q39: 84 | R39: 0.085 | S39: 1.87 | T39: 1848 | U39: 0.2558437 | V39: 22 | W39: 264
A40: 第三阶段 | B40: 第9周 | C40: 85.99 | D40: 0.1 | E40: 0 | F40: 77.391 | O40: 1088.8889 | Q40: 98 | R40: 0.09 | S40: 1.84 | T40: 2003.5556 | U40: 0.23775374 | V40: 20.444444 | W40: 286.22222
B41: 第10周 | C41: 85.99 | D41: 0.1 | E41: 0 | F41: 77.391 | O41: 1166.6667 | Q41: 105 | R41: 0.09 | S41: 1.84 | T41: 2146.6667 | U41: 0.23775374 | V41: 20.444444 | W41: 306.66667
B42: 第11周 | C42: 85.99 | D42: 0.1 | E42: 0 | F42: 77.391 | O42: 1166.6667 | Q42: 105 | R42: 0.09 | S42: 1.84 | T42: 2146.6667 | U42: 0.23775374 | V42: 20.444444 | W42: 306.66667
B43: 第12周 | C43: 85.99 | D43: 0.1 | E43: 0 | F43: 77.391 | O43: 1244.4444 | Q43: 112 | R43: 0.09 | S43: 1.84 | T43: 2289.7778 | U43: 0.23775374 | V43: 20.444444 | W43: 327.11111
A44: 第四阶段 | B44: 第13周 | C44: 79.99 | D44: 0 | E44: 0 | F44: 79.99 | O44: 1482.3529 | Q44: 126 | R44: 0.085 | S44: 1.8 | T44: 2668.2353 | U44: 0.26473897 | V44: 21.176471 | W44: 381.17647
B45: 第14周 | C45: 79.99 | D45: 0 | E45: 0 | F45: 79.99 | O45: 1647.0588 | Q45: 140 | R45: 0.085 | S45: 1.8 | T45: 2964.7059 | U45: 0.26473897 | V45: 21.176471 | W45: 423.52941
B46: 第15周 | C46: 79.99 | D46: 0 | E46: 0 | F46: 79.99 | O46: 1811.7647 | Q46: 154 | R46: 0.085 | S46: 1.8 | T46: 3261.1765 | U46: 0.26473897 | V46: 21.176471 | W46: 465.88235
B47: 第16周 | C47: 79.99 | D47: 0 | E47: 0 | F47: 79.99 | O47: 2058.8235 | Q47: 175 | R47: 0.085 | S47: 1.8 | T47: 3705.8824 | U47: 0.26473897 | V47: 21.176471 | W47: 529.41176
A48: 第五阶段 | B48: 第17周 | C48: 79.99 | D48: 0 | E48: 0 | F48: 79.99 | O48: 2058.8235 | Q48: 175 | R48: 0.085 | S48: 1.8 | T48: 3705.8824 | U48: 0.26473897 | V48: 21.176471 | W48: 529.41176
B49: 第18周 | C49: 79.99 | D49: 0 | E49: 0 | F49: 79.99 | O49: 2058.8235 | Q49: 175 | R49: 0.085 | S49: 1.8 | T49: 3705.8824 | U49: 0.26473897 | V49: 21.176471 | W49: 529.41176
B50: 第19周 | C50: 79.99 | D50: 0 | E50: 0 | F50: 79.99 | O50: 2058.8235 | Q50: 175 | R50: 0.085 | S50: 1.8 | T50: 3705.8824 | U50: 0.26473897 | V50: 21.176471 | W50: 529.41176
B51: 第20周 | C51: 79.99 | D51: 0 | E51: 0 | F51: 79.99 | O51: 2058.8235 | Q51: 175 | R51: 0.085 | S51: 1.8 | T51: 3705.8824 | U51: 0.26473897 | V51: 21.176471 | W51: 529.41176
A52: 第六阶段 | B52: 第21周 | C52: 79.99 | D52: 0 | E52: 0 | F52: 79.99 | O52: 2058.8235 | Q52: 175 | R52: 0.085 | S52: 1.8 | T52: 3705.8824 | U52: 0.26473897 | V52: 21.176471 | W52: 529.41176
B53: 第22周 | C53: 79.99 | D53: 0 | E53: 0 | F53: 79.99 | O53: 2058.8235 | Q53: 175 | R53: 0.085 | S53: 1.8 | T53: 3705.8824 | U53: 0.26473897 | V53: 21.176471 | W53: 529.41176
B54: 第23周 | C54: 79.99 | D54: 0 | E54: 0 | F54: 79.99 | O54: 2058.8235 | Q54: 175 | R54: 0.085 | S54: 1.8 | T54: 3705.8824 | U54: 0.26473897 | V54: 21.176471 | W54: 529.41176
B55: 第24周 | C55: 79.99 | D55: 0 | E55: 0 | F55: 79.99 | O55: 2058.8235 | Q55: 175 | R55: 0.085 | S55: 1.8 | T55: 3705.8824 | U55: 0.26473897 | V55: 21.176471 | W55: 529.41176

Sheet 推广目标
A1: SKU：skuR0001EU ASIN：Bxxxxxxxx3 | I1: 关键词
A3: 上架销售时间： | B3: 45765
A4: 推广周期： | B4: 4月20日-6月31日 | I4: 关键词 | J4: 关键词翻译 | K4: 流量占比 | L4: 预估周曝光量 | M4: 关键词类型 | N4: 转化效果自然流量占比
A5: 排名目标： | B5: Matratzensauger #50 | I5: milbensauger | J5: 吸螨虫 | K5: 0.497508 | L5: 13984 | M5: 主要流量词 | N5: 0.3471
A6: 目标销量： | B6: 20-25pcs/天 | I6: milbensauger für matratzen | J6: 用于床垫的吸尘器 | K6: 0.294441 | L6: 8276 | M6: 主要流量词 | N6: 0.41862
I7: sofa reiniger | J7: 沙发清洁剂 | K7: 0.059295 | L7: 1667 | N7: 0.61722
I8: matratzenreiniger | J8: 床垫清洁剂 | K8: 0.047246 | L8: 1328 | N8: 0.80955
I9: milbensauger für matratzen testsieger | J9: 用于床垫测试的螨虫吸尘器测试获胜者 | K9: 0.02472 | L9: 695 | N9: 0.46301
A10: 目标管理 | B10: 目标 | C10: ASIN 1 | I10: milbensauger mit uv licht | J10: 带紫外线灯的螨虫奶嘴 | K10: 0.019301 | L10: 543 | N10: 0.06106
A11: 对标竞品 | B11: B0DKPGKSYS | C11: B0DKPGKSYS | I11: hoover milbensauger | J11: 胡佛螨吸盘 | K11: 0.017954 | L11: 505 | M11: 精准长尾词 | N11: 0.50632
A12: 目标排名 | B12: 21-24 | C12: B0DKPGKSYS | I12: milbenstaubsauger | J12: 螨吸尘器 | K12: 0.008428 | L12: 237 | N12: 0.28778
A13: 目标日销 | B13: 20-25 日销 | C13: B0DKPGKSYS | I13: polsterreiniger | J13: 室内装饰品清洁剂 | K13: 0.007424 | L13: 209 | N13: 15
A14: 价格 | B14: 109-129.99 | C14: B0DKPGKSYS | I14: teppichreiniger gerät | J14: 地毯清洁装置 | K14: 0.002209 | L14: 62 | M14: 、 | N14: 16
A15: rating | B15: 136 | C15: B0DKPGKSYS | I15: polsterreinigungsgerät | J15: 室内装潢清洗机 | K15: 0.001316 | L15: 37 | M15: 、 | N15: 6
A16: 评分 | B16: 4.7 | C16: B0DKPGKSYS
A17: 主推词 | B17: milbensauger | C17: B0DKPGKSYS
D20: 广泛 | E20: 词组 | F20: 精准
A21: 核心关键词 选取， | B21: milbensauger | C21: 除螨仪 | D21: 1.33 | E21: 1.2 | F21: 1.23
B22: milbenstaubsauger | C22: 除螨仪 | D22: 1.39 | E22: 1.24 | F22: 1.29
B23: milbensauger für matratzen | C23: 床垫除螨仪 | D23: 1.33 | E23: 1.2 | F23: 1.21
B24: milbensauger mit uv licht | C24: 带紫外除螨仪 | D24: 1.36 | E24: 1.22 | F24: 1.28
B25: milbensauger für matratzen testsieger | C25: 床垫除螨仪冠军 | D25: 1.29 | E25: 1.16 | F25: 1.21
B26: Milbensauger | C26: 除螨仪 | D26: 1.33 | E26: 1.2 | F26: 1.23
B27: jigoo milbensauger | C27: jigoo 除螨仪 | D27: 1.47 | E27: 1.3 | F27: 1.36
B28: Hoover milbensauger | C28: Hoover除螨仪 | D28: 1.65 | E28: 1.33 | F28: 2.01
A29: 长尾词 选取
B30: milbenstaubsauger | C30: 除螨仪 | D30: 1.39 | E30: 1.2 | F30: 1.23
B31: handstaubsauger | C31: 手持吸尘器 | D31: 0.64 | E31: 0.58 | F31: 0.63
B32: milbensauger für matratzen testsieger | C32: 床垫除螨仪冠军 | D32: 1.29 | E32: 1.16 | F32: 1.21
B33: matratzenreiniger gerät | C33: 除螨仪冠军 | D33: 1.08 | E33: 0.97 | F33: 1.01
A35: 蓝海词 | B35: polsterreiniger gerät | C35: “沙发清洁器”“软家具清洁设备” | D35: 1.01 | E35: 0.94 | F35: 0.89
B37: 其他品牌相关 品牌词词组 | C37: brand name+keywords
A79: 关键词 | B79: 关键词翻译 | C79: 流量占比 | D79: 预估周曝光量 | E79: 关键词类型 | F79: 转化效果自然流量占比 | G79: B0F1F7J8V3
A80: milbensauger | B80: 吸螨虫 | C80: 0.497508 | D80: 13984 | E80: 主要流量词 | F80: 0.3471
A81: milbensauger für matratzen | B81: 用于床垫的吸尘器 | C81: 0.294441 | D81: 8276 | E81: 主要流量词 | F81: 0.41862
A82: sofa reiniger | B82: 沙发清洁剂 | C82: 0.059295 | D82: 1667 | F82: 0.61722
A83: matratzenreiniger | B83: 床垫清洁剂 | C83: 0.047246 | D83: 1328 | F83: 0.80955
A84: milbensauger für matratzen testsieger | B84: 用于床垫测试的螨虫吸尘器测试获胜者 | C84: 0.02472 | D84: 695 | F84: 0.46301
A85: milbensauger mit uv licht | B85: 带紫外线灯的螨虫奶嘴 | C85: 0.019301 | D85: 543 | F85: 0.06106
A86: hoover milbensauger | B86: 胡佛螨吸盘 | C86: 0.017954 | D86: 505 | E86: 精准长尾词 | F86: 0.50632
A87: milbenstaubsauger | B87: 螨吸尘器 | C87: 0.008428 | D87: 237 | F87: 0.28778
A88: polsterreiniger | B88: 室内装饰品清洁剂 | C88: 0.007424 | D88: 209
A89: teppichreiniger gerät | B89: 地毯清洁装置 | C89: 0.002209 | D89: 62
A90: polsterreinigungsgerät | B90: 室内装潢清洗机 | C90: 0.001316 | D90: 37

Sheet 推广计划
A1: WEEK | B1: Date | C1: SKU | D1: 售价 | E1: COUPON | F1: Action | G1: 目标平均日销 | H1: 周销 | I1: 目标排名 | J1: Review星级/数量 | K1: REVIEW计划 | M1: 周消耗库存 | N1: 销售额 | O1: 日均流量 | P1: 转化率 | Q1: 主关键词自然搜索排名 | R1: 广告计划 | X1: 库存计划
K2: 送出数量 | L2: 措施 | R2: 广告日预算 | S2: 每日点击 | T2: CPC | U2: CVR | V2: 广告日订单 | W2: 广告订单占比 | Z2: LBS库存 | AA2: SZ | AB2: LBS在途 | AC2: LBS发货 | AD2: 采购计划
A3: WEEK1 | B3: 4.18-4.25 | C3: R0001EU | D3: 109.99 | E3: 20 | F3: 10 coupon+广告 | G3: =M3/7 -> 6.2857143 | H3: =G3*7 -> 44 | I3: 60 | J3: 4.7 | K3: 首单测评1单5星 | L3: 直评 10个 | M3: 44 | N3: =D3*H3 -> 4839.56 | O3: 66 | P3: =G3/O3 -> 0.095238095 | Q3: 主推关键词：milbensauger,milbensauger für matratzen 目标：第5页 | R3: =T3*S3 -> 48 | S3: =V3/U3 -> 40 | T3: 1.2 | U3: 0.11 | V3: =G3*W3 -> 4.4 | W3: 0.7 | X3: 1200 | Y3: 0 | Z3: 0 | AA3: 1310 | AB3: 2490海运
A4: WEEK2 | B4: 4.26-5.2 | C4: R0001EU | D4: 109.99 | E4: 20 | F4: coupon+广告 | G4: =M4/7 -> 11.571429 | H4: =G4*7 -> 81 | I4: 40 | J4: 4.7 | K4: 绿标10个 | L4: 直评补 3-5个 | M4: 81 | N4: =D4*H4 -> 8909.19 | O4: 88 | P4: =G4/O4 -> 0.13149351 | Q4: 主推关键词：milbensauger,milbensauger für matratzen 目标：第4页 | R4: =T4*S4 -> 75.214286 | S4: =V4/U4 -> 62.678571 | T4: 1.2 | U4: 0.12 | V4: =G4*W4 -> 7.5214286 | W4: 0.65 | X4: =X3-H3 -> 1156 | Y4: 0 | Z4: 0 | AA4: 1310 | AB4: 2490
A5: WEEK3 | B5: 5.3-5.9 | C5: R0001EU | D5: 109.99 | E5: 20 | F5: coupon+广告 | G5: =M5/7 -> 7.8571429 | H5: =G5*7 -> 55 | I5: 30 | J5: 4.7 | K5: 1 | L5: 测评 | M5: 55 | N5: =D5*H5 -> 6049.45 | O5: 60 | P5: =G5/O5 -> 0.13095238 | Q5: 主推关键词：milbensauger,milbensauger für matratzen 目标：第3页 | R5: =T5*S5 -> 39.89011 | S5: =V5/U5 -> 36.263736 | T5: 1.1 | U5: 0.13 | V5: =G5*W5 -> 4.7142857 | W5: 0.6 | X5: =X4-H4 -> 1075 | Y5: 0 | Z5: 2490 | AA5: 0 | AB5: 1310卡派 | AC5: 720至TT 600至RUI备用
A6: WEEK4 | B6: 5.10-5.16 | C6: R0001EU | D6: 109.99 | E6: 20 | F6: 10 coupon+7DD+加大广告投放 | G6: =M6/7 -> 6.8571429 | H6: =G6*7 -> 48 | I6: 20 | J6: 4.6 | K6: 2 | L6: 测评 | M6: 48 | N6: =D6*H6 -> 5279.52 | O6: 50 | P6: =G6/O6 -> 0.13714286 | Q6: 主推关键词：milbensauger,milbensauger für matratzen 目标：第3页 | R6: =T6*S6 -> 25.142857 | S6: =V6/U6 -> 22.857143 | T6: 1.1 | U6: 0.15 | V6: =G6*W6 -> 3.4285714 | W6: 0.5 | X6: =X5-H5+720 -> 1740 | Y6: 600 | Z6: 1170 | AA6: 0 | AB6: 1310 | AD6: 1500
A7: WEEK5 | B7: 5.17-5.23 | C7: R0001EU | D7: 119.99 | E7: 10 | F7: coupon+广告 | G7: =M7/7 -> 7.4285714 | H7: =G7*7 -> 52 | I7: 28 | J7: 4.6 | K7: 2 | L7: 测评 | M7: 52 | N7: =D7*H7 -> 6239.48 | O7: 56 | P7: =G7/O7 -> 0.13265306 | Q7: 主推关键词：milbensauger,milbensauger für matratzen 目标：第2页 | R7: =T7*S7 -> 27.238095 | S7: =V7/U7 -> 27.238095 | T7: 1 | U7: 0.15 | V7: =G7*W7 -> 4.0857143 | W7: 0.55 | X7: =X6-H6 -> 1692 | Y7: 600 | Z7: 1170 | AA7: 0 | AB7: 1310
A8: WEEK6 | B8: 5.24-5.30 | C8: R0001EU | D8: 119.99 | E8: 10 | F8: coupon+广告 | G8: =M8/7 -> 7.1428571 | H8: =G8*7 -> 50 | I8: 26 | J8: 4.6 | K8: 2 | L8: 测评 | M8: 50 | N8: =D8*H8 -> 5999.5 | O8: 60 | P8: =G8/O8 -> 0.11904762 | Q8: 主推关键词：milbensauger,milbensauger für matratzen 目标：第2页 | R8: =T8*S8 -> 23.809524 | S8: =V8/U8 -> 23.809524 | T8: 1 | U8: 0.15 | V8: =G8*W8 -> 3.5714286 | W8: 0.5 | X8: =X7-H7 -> 1640 | Y8: 600 | Z8: 1170 | AA8: 0 | AB8: 1310 | AC8: 900至TT
A9: WEEK7 | B9: 5.31-6.6 | C9: R0001EU | D9: 119.99 | E9: 10 | F9: 7DD+加大广告投放 | G9: =M9/7 -> 8.2857143 | H9: =G9*7 -> 58 | I9: 20 | J9: 4.6 | K9: 2 | L9: 测评 | M9: 58 | N9: =D9*H9 -> 6959.42 | O9: 68 | P9: =G9/O9 -> 0.12184874 | Q9: 主推关键词：milbensauger,milbensauger für matratzen 目标：第2页 | R9: =T9*S9 -> 18.642857 | S9: =V9/U9 -> 20.714286 | T9: 0.9 | U9: 0.16 | V9: =G9*W9 -> 3.3142857 | W9: 0.4 | X9: =X8-H8+900 -> 2490 | Y9: 600 | Z9: =Z8-900 -> 270 | AA9: 0 | AB9: 1310 | AD9: 1980(PD)
A10: WEEK8 | B10: 6.7-6.13 | C10: R0001EU | D10: 119.99 | E10: 10 | F10: coupon+广告 | G10: =M10/7 -> 7.1428571 | H10: =G10*7 -> 50 | I10: 25 | J10: 4.6 | K10: 2 | L10: 测评 | M10: 50 | N10: =D10*H10 -> 5999.5 | O10: 68 | P10: =G10/O10 -> 0.10504202 | Q10: 主推关键词：milbensauger,milbensauger für matratzen 目标：第1页 | R10: =T10*S10 -> 18.080357 | S10: =V10/U10 -> 20.089286 | T10: 0.9 | U10: 0.16 | V10: =G10*W10 -> 3.2142857 | W10: 0.45 | X10: =X9-H9 -> 2432 | Y10: 600 | Z10: 1580 | AA10: 1500 | AB10: 0 | AC10: 900至TT
A11: WEEK9 | B11: 6.14-6.20 | C11: R0001EU | D11: 119.99 | E11: 10 | F11: coupon+广告 | G11: =M11/7 -> 7.8571429 | H11: =G11*7 -> 55 | I11: 24 | J11: 4.6 | K11: 2 | L11: 测评 | M11: 55 | N11: =D11*H11 -> 6599.45 | O11: 70 | P11: =G11/O11 -> 0.1122449 | Q11: 主推关键词：milbensauger,milbensauger für matratzen 目标：第1页 | R11: =T11*S11 -> 17.678571 | S11: =V11/U11 -> 19.642857 | T11: 0.9 | U11: 0.16 | V11: =G11*W11 -> 3.1428571 | W11: 0.4 | X11: =X10-H10+900 -> 3282 | Y11: 600 | Z11: 680 | AA11: 0 | AB11: 1500卡派 | AD11: 2100
A12: WEEK10 | B12: 6.21-6.27 | C12: R0001EU | D12: 119.99 | E12: 10 | F12: 7DD+加大广告投放 | G12: =M12/7 -> 9.2857143 | H12: =G12*7 -> 65 | I12: 20 | J12: 4.6 | K12: 2 | L12: 测评 | M12: 65 | N12: =D12*H12 -> 7799.35 | O12: 75 | P12: =G12/O12 -> 0.12380952 | Q12: 主推关键词：milbensauger,milbensauger für matratzen 目标：第1页 | R12: =T12*S12 -> 18.28125 | S12: =V12/U12 -> 20.3125 | T12: 0.9 | U12: 0.16 | V12: =G12*W12 -> 3.25 | W12: 0.35 | X12: =X11-H11 -> 3227 | Y12: 600 | Z12: 680 | AA12: 0 | AB12: 1500 | AC12: 680至TT
A13: WEEK11 | B13: 6.28-7.4 | C13: R0001EU | D13: 119.99 | E13: 10 | F13: coupon+广告 | G13: =M13/7 -> 10.285714 | H13: =G13*7 -> 72 | I13: 22 | J13: 4.6 | K13: 2 | L13: 测评 | M13: 72 | N13: =D13*H13 -> 8639.28 | O13: 75 | P13: =G13/O13 -> 0.13714286 | Q13: 主推关键词：milbensauger,milbensauger für matratzen 目标：第1页 | R13: =T13*S13 -> 20.25 | S13: =V13/U13 -> 22.5 | T13: 0.9 | U13: 0.16 | V13: =G13*W13 -> 3.6 | W13: 0.35 | X13: =X12-H12+680 -> 3842 | Y13: 600 | Z13: 0 | AA13: 1980 | AB13: 1500
A14: WEEK12 | B14: 7.5-7.11 | C14: R0001EU | D14: 119.99 | E14: 10 | F14: coupon+广告 | G14: =M14/7 -> 10.714286 | H14: =G14*7 -> 75 | I14: 21 | J14: 4.6 | K14: 2 | L14: 测评 | M14: 75 | N14: =D14*H14 -> 8999.25 | O14: 75 | P14: =G14/O14 -> 0.14285714 | Q14: 主推关键词：milbensauger,milbensauger für matratzen 目标：第1页 | R14: =T14*S14 -> 18.080357 | S14: =V14/U14 -> 20.089286 | T14: 0.9 | U14: 0.16 | V14: =G14*W14 -> 3.2142857 | W14: 0.3 | X14: 1355 | Y14: =Y13-H13 -> 528 | Z14: 1500 | AA14: 0 | AB14: 1980卡派 | AE14: 切换到RUI卖
A15: WEEK13 | B15: 7.12-7.18 | C15: R0001EU | D15: 119.99 | E15: 10 | F15: 7DD+加大广告投放 | G15: =M15/7 -> 11.428571 | H15: =G15*7 -> 80 | I15: 20 | J15: 4.6 | K15: 2 | L15: 测评 | M15: 80 | N15: =D15*H15 -> 9599.2 | O15: 75 | P15: =G15/O15 -> 0.15238095 | Q15: 主推关键词：milbensauger,milbensauger für matratzen 目标：第1页 | R15: =T15*S15 -> 18.151261 | S15: =V15/U15 -> 20.168067 | T15: 0.9 | U15: 0.17 | V15: =G15*W15 -> 3.4285714 | W15: 0.3 | X15: =X14-H14 -> 1280 | Y15: 264 | Z15: 1500 | AA15: 2100 | AB15: 1980
A16: WEEK14 | B16: 7.19-7.25 | C16: R0001EU | D16: 119.99 | E16: 0.1 | F16: 7DD+加大广告投放 | G16: =M16/7 -> 12.142857 | H16: =G16*7 -> 85 | I16: 20 | J16: 4.6 | K16: 2 | L16: 测评 | M16: 85 | N16: =D16*H16 -> 10199.15 | O16: 75 | P16: =G16/O16 -> 0.16190476 | Q16: 主推关键词：milbensauger,milbensauger für matratzen 目标：第1页 | R16: =T16*S16 -> 19.285714 | S16: =V16/U16 -> 21.428571 | T16: 0.9 | U16: 0.17 | V16: =G16*W16 -> 3.6428571 | W16: 0.3 | X16: =X15-H15 -> 1200 | Y16: 264 | Z16: 1500 | AA16: 2100 | AB16: 1980
A17: WEEK15 | B17: 7.26--8.2 | C17: R0001EU | D17: 119.99 | E17: 0.1 | F17: 7DD+加大广告投放 | G17: =M17/7 -> 13.571429 | H17: =G17*7 -> 95 | I17: 20 | J17: 4.6 | K17: 2 | L17: 测评 | M17: 95 | N17: =D17*H17 -> 11399.05 | O17: 80 | P17: =G17/O17 -> 0.16964286 | Q17: 主推关键词：milbensauger,milbensauger für matratzen 目标：第1页 | R17: =T17*S17 -> 21.554622 | S17: =V17/U17 -> 23.94958 | T17: 0.9 | U17: 0.17 | V17: =G17*W17 -> 4.0714286 | W17: 0.3 | X17: =X16-H16 -> 1115 | Y17: 264 | Z17: 1500 | AA17: 2100 | AB17: 1980
A18: WEEK16 | B18: 8.3-8.9 | C18: R0001EU | D18: 119.99 | E18: 0.1 | F18: 7DD+加大广告投放 | G18: =M18/7 -> 14.285714 | H18: =G18*7 -> 100 | I18: 20 | J18: 4.6 | K18: 2 | L18: 测评 | M18: 100 | N18: =D18*H18 -> 11999 | O18: 80 | P18: =G18/O18 -> 0.17857143 | Q18: 主推关键词：milbensauger,milbensauger für matratzen 目标：第1页 | R18: =T18*S18 -> 22.689076 | S18: =V18/U18 -> 25.210084 | T18: 0.9 | U18: 0.17 | V18: =G18*W18 -> 4.2857143 | W18: 0.3 | X18: =X17-H17 -> 1020 | Y18: 264 | Z18: 1500 | AA18: 2100 | AB18: 1980
A19: WEEK17 | B19: 8.10-8.16 | C19: R0001EU | D19: 119.99 | E19: 0.1 | F19: 7DD+加大广告投放 | G19: =M19/7 -> 11.428571 | H19: =G19*7 -> 80 | I19: 20 | J19: 4.6 | K19: 2 | L19: 测评 | M19: 80 | N19: =D19*H19 -> 9599.2 | O19: 80 | P19: =G19/O19 -> 0.14285714 | Q19: 主推关键词：milbensauger,milbensauger für matratzen 目标：第1页 | R19: =T19*S19 -> 18.151261 | S19: =V19/U19 -> 20.168067 | T19: 0.9 | U19: 0.17 | V19: =G19*W19 -> 3.4285714 | W19: 0.3 | X19: =X18-H18 -> 920 | Y19: 264 | Z19: 1500 | AA19: 2100 | AB19: 1980
A20: WEEK18 | B20: 8.17-8.23 | C20: R0001EU | D20: 119.99 | E20: 0.1 | F20: 7DD+加大广告投放 | G20: =M20/7 -> 8.5714286 | H20: =G20*7 -> 60 | I20: 20 | J20: 4.6 | K20: 2 | L20: 测评 | M20: 60 | N20: =D20*H20 -> 7199.4 | O20: 60 | P20: =G20/O20 -> 0.14285714 | Q20: 主推关键词：milbensauger,milbensauger für matratzen 目标：第1页 | R20: =T20*S20 -> 13.613445 | S20: =V20/U20 -> 15.12605 | T20: 0.9 | U20: 0.17 | V20: =G20*W20 -> 2.5714286 | W20: 0.3 | X20: =X19-H19 -> 840 | Y20: 264 | Z20: 1500 | AA20: 2100 | AB20: 1980
A21: WEEK19 | B21: 8.24-8.30 | C21: R0001EU | D21: 119.99 | E21: 0.1 | F21: 7DD+加大广告投放 | G21: =M21/7 -> 9.2857143 | H21: =G21*7 -> 65 | I21: 20 | J21: 4.6 | K21: 2 | L21: 测评 | M21: 65 | N21: =D21*H21 -> 7799.35 | O21: 60 | P21: =G21/O21 -> 0.1547619 | Q21: 主推关键词：milbensauger,milbensauger für matratzen 目标：第1页 | R21: =T21*S21 -> 14.747899 | S21: =V21/U21 -> 16.386555 | T21: 0.9 | U21: 0.17 | V21: =G21*W21 -> 2.7857143 | W21: 0.3 | X21: =X20-H20 -> 780 | Y21: 264 | Z21: 1500 | AA21: 2100 | AB21: 1980
A22: WEEK20 | B22: 8.24-8.30 | C22: R0001EU | D22: 119.99 | E22: 0.1 | F22: 7DD+加大广告投放 | G22: =M22/7 -> 10.714286 | H22: =G22*7 -> 75 | I22: 20 | J22: 4.6 | K22: 2 | L22: 测评 | M22: 75 | N22: =D22*H22 -> 8999.25 | O22: 60 | P22: =G22/O22 -> 0.17857143 | Q22: 主推关键词：milbensauger,milbensauger für matratzen 目标：第1页 | R22: =T22*S22 -> #DIV/0! | S22: =V22/U22 -> #DIV/0! | T22: 0.9
A23: WEEK21 | B23: 8.24-8.30 | C23: R0001EU | D23: 119.99 | E23: 0.1 | F23: 7DD+加大广告投放 | G23: =M23/7 -> 11.428571 | H23: =G23*7 -> 80 | I23: 20 | J23: 4.6 | K23: 2 | L23: 测评 | M23: 80 | N23: =D23*H23 -> 9599.2 | O23: 60 | P23: =G23/O23 -> 0.19047619 | Q23: 主推关键词：milbensauger,milbensauger für matratzen 目标：第1页 | R23: =T23*S23 -> #DIV/0! | S23: =V23/U23 -> #DIV/0! | T23: 0.9
A24: WEEK22 | B24: 8.24-8.30 | C24: R0001EU | D24: 119.99 | E24: 0.1 | F24: 7DD+加大广告投放 | G24: =M24/7 -> 12.857143 | H24: =G24*7 -> 90 | I24: 20 | J24: 4.6 | K24: 2 | L24: 测评 | M24: 90 | N24: =D24*H24 -> 10799.1 | O24: 60 | P24: =G24/O24 -> 0.21428571 | Q24: 主推关键词：milbensauger,milbensauger für matratzen 目标：第1页 | R24: =T24*S24 -> #DIV/0! | S24: =V24/U24 -> #DIV/0! | T24: 0.9
A25: WEEK23 | B25: 8.24-8.30 | C25: R0001EU | D25: 119.99 | E25: 0.1 | F25: 7DD+加大广告投放 | G25: =M25/7 -> 13.571429 | H25: =G25*7 -> 95 | I25: 20 | J25: 4.6 | K25: 2 | L25: 测评 | M25: 95 | N25: =D25*H25 -> 11399.05 | O25: 60 | P25: =G25/O25 -> 0.22619048 | Q25: 主推关键词：milbensauger,milbensauger für matratzen 目标：第1页 | R25: =T25*S25 -> #DIV/0! | S25: =V25/U25 -> #DIV/0! | T25: 0.9
A26: WEEK24 | B26: 8.24-8.30 | C26: R0001EU | D26: 119.99 | E26: 0.1 | F26: 7DD+加大广告投放 | G26: =M26/7 -> 14.285714 | H26: =G26*7 -> 100 | I26: 20 | J26: 4.6 | K26: 2 | L26: 测评 | M26: 100 | N26: =D26*H26 -> 11999 | O26: 60 | P26: =G26/O26 -> 0.23809524 | Q26: 主推关键词：milbensauger,milbensauger für matratzen 目标：第1页 | R26: =T26*S26 -> #DIV/0! | S26: =V26/U26 -> #DIV/0! | T26: 0.9
A27: WEEK25 | B27: 8.24-8.30 | C27: R0001EU | D27: 119.99 | E27: 0.1 | F27: 7DD+加大广告投放 | G27: =M27/7 -> 17.142857 | H27: =G27*7 -> 120 | I27: 20 | J27: 4.6 | K27: 2 | L27: 测评 | M27: 120 | N27: =D27*H27 -> 14398.8 | O27: 60 | P27: =G27/O27 -> 0.28571429 | Q27: 主推关键词：milbensauger,milbensauger für matratzen 目标：第1页 | R27: =T27*S27 -> #DIV/0! | S27: =V27/U27 -> #DIV/0! | T27: 0.9
A28: WEEK25 | B28: 8.24-8.30 | C28: R0001EU | D28: 119.99 | E28: 0.1 | F28: 7DD+加大广告投放 | G28: =M28/7 -> 17.142857 | H28: =G28*7 -> 120 | I28: 20 | J28: 4.6 | K28: 2 | L28: 测评 | M28: 120 | N28: =D28*H28 -> 14398.8 | O28: 60 | P28: =G28/O28 -> 0.28571429 | Q28: 主推关键词：milbensauger,milbensauger für matratzen 目标：第1页 | R28: =T28*S28 -> #DIV/0! | S28: =V28/U28 -> #DIV/0! | T28: 0.9
A29: WEEK25 | B29: 8.24-8.30 | C29: R0001EU | D29: 119.99 | E29: 0.1 | F29: 7DD+加大广告投放 | G29: =M29/7 -> 17.142857 | H29: =G29*7 -> 120 | I29: 20 | J29: 4.6 | K29: 2 | L29: 测评 | M29: 120 | N29: =D29*H29 -> 14398.8 | O29: 60 | P29: =G29/O29 -> 0.28571429 | Q29: 主推关键词：milbensauger,milbensauger für matratzen 目标：第1页 | R29: =T29*S29 -> #DIV/0! | S29: =V29/U29 -> #DIV/0! | T29: 0.9
A30: WEEK26 | B30: 8.24-8.30 | C30: R0001EU | D30: 119.99 | E30: 0.1 | F30: 7DD+加大广告投放 | G30: =M30/7 -> 17.142857 | H30: =G30*7 -> 120 | I30: 20 | J30: 4.6 | K30: 2 | L30: 测评 | M30: 120 | N30: =D30*H30 -> 14398.8 | O30: 60 | P30: =G30/O30 -> 0.28571429 | Q30: 主推关键词：milbensauger,milbensauger für matratzen 目标：第1页 | R30: =T30*S30 -> #DIV/0! | S30: =V30/U30 -> #DIV/0! | T30: 0.9
A31: WEEK27 | B31: 8.24-8.30 | C31: R0001EU | D31: 119.99 | E31: 0.1 | F31: 7DD+加大广告投放 | G31: =M31/7 -> 17.142857 | H31: =G31*7 -> 120 | I31: 20 | J31: 4.6 | K31: 2 | L31: 测评 | M31: 120 | N31: =D31*H31 -> 14398.8 | O31: 60 | P31: =G31/O31 -> 0.28571429 | Q31: 主推关键词：milbensauger,milbensauger für matratzen 目标：第1页 | R31: =T31*S31 -> #DIV/0! | S31: =V31/U31 -> #DIV/0! | T31: 0.9
A32: WEEK28 | B32: 8.24-8.30 | C32: R0001EU | D32: 119.99 | E32: 0.1 | F32: 7DD+加大广告投放 | G32: =M32/7 -> 17.142857 | H32: =G32*7 -> 120 | I32: 20 | J32: 4.6 | K32: 2 | L32: 测评 | M32: 120 | N32: =D32*H32 -> 14398.8 | O32: 60 | P32: =G32/O32 -> 0.28571429 | Q32: 主推关键词：milbensauger,milbensauger für matratzen 目标：第1页 | R32: =T32*S32 -> #DIV/0! | S32: =V32/U32 -> #DIV/0! | T32: 0.9
A33: WEEK26 | B33: 8.24-8.30 | C33: R0001EU | D33: 119.99 | E33: 0.1 | F33: 7DD+加大广告投放 | G33: =M33/7 -> 17.142857 | H33: =G33*7 -> 120 | I33: 20 | J33: 4.6 | K33: 2 | L33: 测评 | M33: 120 | N33: =D33*H33 -> 14398.8 | O33: 60 | P33: =G33/O33 -> 0.28571429 | Q33: 主推关键词：milbensauger,milbensauger für matratzen 目标：第1页 | R33: =T33*S33 -> #DIV/0! | S33: =V33/U33 -> #DIV/0! | T33: 0.9
A34: WEEK26 | B34: 8.24-8.30 | C34: R0001EU | D34: 119.99 | E34: 0.1 | F34: 7DD+加大广告投放 | G34: =M34/7 -> 17.142857 | H34: =G34*7 -> 120 | I34: 20 | J34: 4.6 | K34: 2 | L34: 测评 | M34: 120 | N34: =D34*H34 -> 14398.8 | O34: 60 | P34: =G34/O34 -> 0.28571429 | Q34: 主推关键词：milbensauger,milbensauger für matratzen 目标：第1页 | R34: =T34*S34 -> #DIV/0! | S34: =V34/U34 -> #DIV/0! | T34: 0.9

Sheet 广告计划
A1: 预估量说明： 平均cpc和转化率的值的预估方法： 1.市场调研得到同行平均cpc的基础上适当上调； 2.正在做的同品类商品的历史cpc基础上适当上调； 平均cpc和转化率计划制定的说明： 新品期间波动大，采用梯度预估 eg:当cpc为2.5$,转化率为5%的时候，完成日销目标对应的广告费为105$/天； 当cpc为2.3$.转化率为7%的时候，完成日销目标对应的广告费为69$/天 B0F1F7J8V3
A10: WEEK | B10: Date | C10: 售价 | D10: 目标平均日销 | E10: 销售额 | F10: 转化率 | G10: 日均流量 | H10: 广告销量 | I10: 广告销售额 | J10: 广告订单占比 | K10: 广告费 | L10: 点击量 | M10: 预估量 | O10: 广告结构 | P10: 广告目标及关注指标 | Q10: 广告关键词 | R10: 不同广告类型预算分配
L11: 点击量 | M11: 平均cpc | N11: 广告转化率
A12: WEEK1 | B12: 4.28-5.6 | C12: 109.99 | D12: 6.2857143 | E12: =C12*D12*7 -> 4839.56 | F12: 0.095238095 | G12: =D12/F12 -> 66 | H12: =D12*J12 -> 4.4 | I12: =H12*C12 -> 483.956 | J12: 0.7 | K12: =L12*M12 -> 48 | L12: =$H$12/N12 -> 40 | M12: 1.2 | N12: 0.11 | O12: campaign1：自动广告 campaign2：手动广告测试组B campaign3：SD-categories campaign4：PT campaign5：手动广告核心关键词E | P12: 有效流量引入 点击率；转化率；订单量 | Q12: milbensauger（主推） milbensauger für matratzen 核心词 milbensauger milbenstaubsauger milbensauger für matratzen milbensauger mit uv licht milbensauger für matratzen testsieger Milbensauger Hoover milbensauger 长尾词 milbenstaubsauger handstaubsauger milbensauger für matratzen testsieger matratzenreiniger gerät polsterreiniger gerät “沙发清洁器”“软家具清洁设备” milbensauger milbenstaubsauger milbensauger für matratzen testsieger 欧11531 jimmy jv35 12362 jigoo t600 milbensauger 44157 jigoo milbensauger 53568 hoover milbensauger 62790 milbensauger für matratzen testsieger 90467 jimmy jv35 milbensauger 125594 milbenstaubsauger 247901 milbensauger mit uv licht 2625420 milbensauger für matratzen 5657246 milbensauger 关键词分析 milbensauger， milbensauger für matratzen testsieger， Milbenstaubsauger milbensauger mit uv licht milbensauger für matratzen Milbensauger jigoo milbensauger Hoover milbensauger 核心关键词 选取，milbensauger， milbenstaubsauger milbensauger für matratzen， milbensauger mit uv licht 长尾词 milbenstaubsauger handstaubsauger手持吸尘器 milbensauger für matratzen testsieger matratzenreiniger gerät 关键词竞价分析：除螨仪milbensauger 竞价CPC 1-1.54欧 Milbenstaubsauger 除螨仪 1.5-2.3欧 关键词竞价分析：床垫除螨仪milbensauger für matratzen 竞价CPC 1-2.4欧 带紫外线除螨仪 milbensauger mit uv licht 1.8-2.9欧 milbensauger für matratzen testsieger 1- 2.2欧 hoover milbensauger 1.8-2.8欧 jimmy jv35 milbensauger 1.1-3欧 以词拓词 Milbensauger
K13: =L13*M13 -> 48 | L13: =$H$12/N13 -> 40 | M13: 1.2 | N13: 0.11
K14: =L14*M14 -> 48 | L14: =$H$12/N14 -> 40 | M14: 1.2 | N14: 0.11
K15: =L15*M15 -> 48 | L15: =$H$12/N15 -> 40 | M15: 1.2 | N15: 0.11
A16: WEEK2 | B16: 5.7-5.13 | C16: 109.99 | D16: 11.571429 | E16: =C16*D16*7 -> 8909.19 | F16: 0.13149351 | G16: =D16/F16 -> 88 | H16: =D16*J16 -> 7.5214286 | I16: =H16*C16 -> 827.28193 | J16: 0.65 | K16: =L16*M16 -> 75.214286 | L16: =$H$16/N16 -> 62.678571 | M16: 1.2 | N16: 0.12 | O16: campaign1：自动广告 campaign2：手动广告测试组B campaign3：SD-categories campaign4：PT campaign5：手动广告核心关键词E campaign6：SBV-PT / SBV-KT | R16: SP:70% SD:15% SB:15% | S16: 关键词 | T16: 关键词翻译 | U16: 流量占比 | V16: 预估周曝光量 | W16: 关键词类型 | X16: 转化效果自然流量占比
K17: =L17*M17 -> 75.214286 | L17: =$H$16/N17 -> 62.678571 | M17: 1.2 | N17: 0.12 | S17: milbensauger | T17: 吸螨虫 | U17: 0.497508 | V17: 13984 | W17: 主要流量词 | X17: 0.3471
K18: =L18*M18 -> 75.214286 | L18: =$H$16/N18 -> 62.678571 | M18: 1.2 | N18: 0.12 | S18: milbensauger für matratzen | T18: 用于床垫的吸尘器 | U18: 0.294441 | V18: 8276 | W18: 主要流量词 | X18: 0.41862
K19: =L19*M19 -> 75.214286 | L19: =$H$16/N19 -> 62.678571 | M19: 1.2 | N19: 0.12 | S19: sofa reiniger | T19: 沙发清洁剂 | U19: 0.059295 | V19: 1667 | X19: 0.61722
A20: WEEK3 | B20: 5.14-5.20 | C20: 109.99 | D20: 7.8571429 | E20: =C20*D20*7 -> 6049.45 | F20: 0.13095238 | G20: =D20/F20 -> 60 | H20: =D20*J20 -> 4.7142857 | I20: =H20*C20 -> 518.52429 | J20: 0.6 | K20: =L20*M20 -> 39.89011 | L20: =$H$20/N20 -> 36.263736 | M20: 1.1 | N20: 0.13 | O20: campaign1：自动广告 campaign2：手动广告测试组B campaign3：SD-categories campaign4：PT campaign5：手动广告核心关键词E campaign6：SBV-PT / SBV-KT | S20: matratzenreiniger | T20: 床垫清洁剂 | U20: 0.047246 | V20: 1328 | X20: 0.80955
K21: =L21*M21 -> 39.89011 | L21: =$H$20/N21 -> 36.263736 | M21: 1.1 | N21: 0.13 | S21: milbensauger für matratzen testsieger | T21: 用于床垫测试的螨虫吸尘器测试获胜者 | U21: 0.02472 | V21: 695 | X21: 0.46301
K22: =L22*M22 -> 39.89011 | L22: =$H$20/N22 -> 36.263736 | M22: 1.1 | N22: 0.13 | S22: milbensauger mit uv licht | T22: 带紫外线灯的螨虫奶嘴 | U22: 0.019301 | V22: 543 | X22: 0.06106
K23: =L23*M23 -> 39.89011 | L23: =$H$20/N23 -> 36.263736 | M23: 1.1 | N23: 0.13 | S23: hoover milbensauger | T23: 胡佛螨吸盘 | U23: 0.017954 | V23: 505 | W23: 精准长尾词 | X23: 0.50632
A24: WEEK4 | B24: 5.21-5.27 | C24: 109.99 | D24: 6.8571429 | E24: =C24*D24*7 -> 5279.52 | F24: 0.13714286 | G24: =D24/F24 -> 50 | H24: =D24*J24 -> 3.7714286 | I24: =H24*C24 -> 414.81943 | J24: 0.55 | K24: =L24*M24 -> 27.657143 | L24: =$H$24/N24 -> 25.142857 | M24: 1.1 | N24: 0.15 | O24: campaign1：自动广告 campaign2：手动广告测试组B campaign3：SD-categories campaign4：PT campaign5：手动广告核心关键词E campaign6：SBV-PT / SBV-KT | R24: SP:70% SD:15% SB:15% | S24: milbenstaubsauger | T24: 螨吸尘器 | U24: 0.008428 | V24: 237 | X24: 0.28778
K25: =L25*M25 -> 27.657143 | L25: =$H$24/N25 -> 25.142857 | M25: 1.1 | N25: 0.15 | S25: polsterreiniger | T25: 室内装饰品清洁剂 | U25: 0.007424 | V25: 209
K26: =L26*M26 -> 27.657143 | L26: =$H$24/N26 -> 25.142857 | M26: 1.1 | N26: 0.15 | S26: teppichreiniger gerät | T26: 地毯清洁装置 | U26: 0.002209 | V26: 62
K27: =L27*M27 -> 27.657143 | L27: =$H$24/N27 -> 25.142857 | M27: 1.1 | N27: 0.15 | S27: polsterreinigungsgerät | T27: 室内装潢清洗机 | U27: 0.001316 | V27: 37
A28: WEEK5 | B28: 5.28-6.3 | C28: 119.99 | D28: 7.4285714 | E28: =C28*D28*7 -> 6239.48 | F28: 0.13265306 | G28: =D28/F28 -> 56 | H28: =D28*J28 -> 3.7142857 | I28: =H28*C28 -> 445.67714 | J28: 0.5 | K28: =L28*M28 -> 24.761905 | L28: =$H$28/N28 -> 24.761905 | M28: 1 | N28: 0.15 | O28: campaign1：自动广告 campaign2：手动广告主推词BP campaign3：SD-categories campaign4：PT campaign5：手动广告核心关键词E campaign6：SBV-PT / SBV-KT | P28: 推动销售 点击率；转化率；订单量；Acos
K29: =L29*M29 -> 24.761905 | L29: =$H$28/N29 -> 24.761905 | M29: 1 | N29: 0.15
K30: =L30*M30 -> 24.761905 | L30: =$H$28/N30 -> 24.761905 | M30: 1 | N30: 0.15
K31: =L31*M31 -> 24.761905 | L31: =$H$28/N31 -> 24.761905 | M31: 1 | N31: 0.15
A32: WEEK6 | B32: 6.4-6.10 | C32: 119.99 | D32: 7.1428571 | E32: =C32*D32*7 -> 5999.5 | F32: 0.11904762 | G32: =D32/F32 -> 60 | H32: =D32*J32 -> 3.5714286 | I32: =H32*C32 -> 428.53571 | J32: 0.5 | K32: =L32*M32 -> 23.809524 | L32: =$H$32/N32 -> 23.809524 | M32: 1 | N32: 0.15 | O32: campaign1：自动广告 campaign2：手动广告主推词BP campaign3：SD-categories campaign4：PT campaign5：手动广告核心关键词E campaign6：SBV-PT / SBV-KT | R32: SP:70% SD:15% SB:15%
K33: =L33*M33 -> 23.809524 | L33: =$H$32/N33 -> 23.809524 | M33: 1 | N33: 0.15
K34: =L34*M34 -> 23.809524 | L34: =$H$32/N34 -> 23.809524 | M34: 1 | N34: 0.15
K35: =L35*M35 -> 23.809524 | L35: =$H$32/N35 -> 23.809524 | M35: 1 | N35: 0.15
A36: WEEK7 | B36: 6.11-6.17 | C36: 119.99 | D36: 8.2857143 | E36: =C36*D36*7 -> 6959.42 | F36: 0.12184874 | G36: =D36/F36 -> 68 | H36: =D36*J36 -> 4.1428571 | I36: =H36*C36 -> 497.10143 | J36: 0.5 | K36: =L36*M36 -> 23.303571 | L36: =$H$36/N36 -> 25.892857 | M36: 0.9 | N36: 0.16 | O36: campaign1：自动广告 campaign2：手动广告主推词BP campaign3：SD-categories campaign4：PT campaign5：手动广告核心关键词E campaign6：SBV-PT / SBV-KT
K37: =L37*M37 -> 23.303571 | L37: =$H$36/N37 -> 25.892857 | M37: 0.9 | N37: 0.16
K38: =L38*M38 -> 23.303571 | L38: =$H$36/N38 -> 25.892857 | M38: 0.9 | N38: 0.16
K39: =L39*M39 -> 23.303571 | L39: =$H$36/N39 -> 25.892857 | M39: 0.9 | N39: 0.16
A40: WEEK8 | B40: 6.18-6.24 | C40: 119.99 | D40: 7.1428571 | E40: =C40*D40*7 -> 5999.5 | F40: 0.10504202 | G40: =D40/F40 -> 68 | H40: =D40*J40 -> 3.2142857 | I40: =H40*C40 -> 385.68214 | J40: 0.45 | K40: =L40*M40 -> 18.080357 | L40: =$H$40/N40 -> 20.089286 | M40: 0.9 | N40: 0.16 | O40: campaign1：自动广告 campaign2：手动广告主推词BP campaign3：SD-categories campaign4：PT campaign5：手动广告核心关键词E campaign6：SBV-PT / SBV-KT | R40: SP:70% SD:15% SB:15%
K41: =L41*M41 -> 18.080357 | L41: =$H$40/N41 -> 20.089286 | M41: 0.9 | N41: 0.16
K42: =L42*M42 -> 18.080357 | L42: =$H$40/N42 -> 20.089286 | M42: 0.9 | N42: 0.16
K43: =L43*M43 -> 18.080357 | L43: =$H$40/N43 -> 20.089286 | M43: 0.9 | N43: 0.16
A44: WEEK9 | B44: 6.25-7.1 | C44: 119.99 | D44: 7.8571429 | E44: =C44*D44*7 -> 6599.45 | F44: 0.1122449 | G44: =D44/F44 -> 70 | H44: =D44*J44 -> 3.5357143 | I44: =H44*C44 -> 424.25036 | J44: 0.45 | K44: =L44*M44 -> 19.888393 | L44: =$H$44/N44 -> 22.098214 | M44: 0.9 | N44: 0.16 | O44: campaign1：自动广告 campaign2：手动广告主推词BP campaign3：SD-categories campaign4：PT campaign5：手动广告核心关键词E campaign6：SBV-PT / SBV-KT
K45: =L45*M45 -> 19.888393 | L45: =$H$44/N45 -> 22.098214 | M45: 0.9 | N45: 0.16
K46: =L46*M46 -> 19.888393 | L46: =$H$44/N46 -> 22.098214 | M46: 0.9 | N46: 0.16
K47: =L47*M47 -> 19.888393 | L47: =$H$44/N47 -> 22.098214 | M47: 0.9 | N47: 0.16
A48: WEEK10 | B48: 7.2-7.8 | C48: 119.99 | D48: 9.2857143 | E48: =C48*D48*7 -> 7799.35 | F48: 0.12380952 | G48: =D48/F48 -> 75 | H48: =D48*J48 -> 3.7142857 | I48: =H48*C48 -> 445.67714 | J48: 0.4 | K48: =L48*M48 -> 20.892857 | L48: =$H$48/N48 -> 23.214286 | M48: 0.9 | N48: 0.16 | O48: campaign1：自动广告 campaign2：手动广告主推词BP campaign3：SD-categories campaign4：PT campaign5：手动广告核心关键词E campaign6：SBV-PT / SBV-KT | R48: SP:70% SD:15% SB:15%
K49: =L49*M49 -> 20.892857 | L49: =$H$48/N49 -> 23.214286 | M49: 0.9 | N49: 0.16
K50: =L50*M50 -> 20.892857 | L50: =$H$48/N50 -> 23.214286 | M50: 0.9 | N50: 0.16
K51: =L51*M51 -> 20.892857 | L51: =$H$48/N51 -> 23.214286 | M51: 0.9 | N51: 0.16
A52: WEEK11 | B52: 7.9-7.15 | C52: 119.99 | D52: 10.285714 | E52: =C52*D52*7 -> 8639.28 | F52: 0.13714286 | G52: =D52/F52 -> 75 | H52: =D52*J52 -> 3.6 | I52: =H52*C52 -> 431.964 | J52: 0.35 | K52: =L52*M52 -> 20.25 | L52: =$H$52/N52 -> 22.5 | M52: 0.9 | N52: 0.16 | O52: campaign1：自动广告 campaign2：手动广告主推词BP campaign3：SD-categories campaign4：PT campaign5：手动广告核心关键词E campaign6：SBV-PT / SBV-KT
K53: =L53*M53 -> 20.25 | L53: =$H$52/N53 -> 22.5 | M53: 0.9 | N53: 0.16
K54: =L54*M54 -> 20.25 | L54: =$H$52/N54 -> 22.5 | M54: 0.9 | N54: 0.16
K55: =L55*M55 -> 20.25 | L55: =$H$52/N55 -> 22.5 | M55: 0.9 | N55: 0.16
A56: WEEK12 | B56: 7.16-7.22 | C56: 119.99 | D56: 10.714286 | E56: =C56*D56*7 -> 8999.25 | F56: 0.14285714 | G56: =D56/F56 -> 75 | H56: =D56*J56 -> 3.2142857 | I56: =H56*C56 -> 385.68214 | J56: 0.3 | K56: =L56*M56 -> 18.080357 | L56: =$H$56/N56 -> 20.089286 | M56: 0.9 | N56: 0.16 | O56: campaign1：自动广告 campaign2：手动广告主推词PE campaign3：SD-categories campaign4：PT campaign5：手动广告核心关键词E campaign6：SBV-PT / SBV-KT | P56: 防守&进攻 转化率；订单量；Acos/Roas | R56: SP:60% SD:20% SB:20%
K57: =L57*M57 -> 18.080357 | L57: =$H$56/N57 -> 20.089286 | M57: 0.9 | N57: 0.16
K58: =L58*M58 -> 18.080357 | L58: =$H$56/N58 -> 20.089286 | M58: 0.9 | N58: 0.16
K59: =L59*M59 -> 18.080357 | L59: =$H$56/N59 -> 20.089286 | M59: 0.9 | N59: 0.16
A60: WEEK13 | B60: 7.23-7.31 | C60: 119.99 | D60: 11.428571 | E60: =C60*D60*7 -> 9599.2 | F60: 0.15238095 | G60: =D60/F60 -> 75 | H60: =D60*J60 -> 3.4285714 | I60: =H60*C60 -> 411.39429 | J60: 0.3 | K60: =L60*M60 -> 18.151261 | L60: =$H$60/N60 -> 20.168067 | M60: 0.9 | N60: 0.17 | O60: campaign1：自动广告 campaign2：手动广告主推词PE campaign3：SD-categories campaign4：PT campaign5：手动广告核心关键词E campaign6：SBV-PT / SBV-KT
K61: =L61*M61 -> 18.151261 | L61: =$H$60/N61 -> 20.168067 | M61: 0.9 | N61: 0.17
K62: =L62*M62 -> 18.151261 | L62: =$H$60/N62 -> 20.168067 | M62: 0.9 | N62: 0.17
K63: =L63*M63 -> 18.151261 | L63: =$H$60/N63 -> 20.168067 | M63: 0.9 | N63: 0.17
A64: WEEK12 | B64: 7.16-7.22 | C64: 119.99 | D64: 10.714286 | E64: =C64*D64*7 -> 8999.25 | F64: 0.17857143 | G64: =D64/F64 -> 60 | H64: =D64*J64 -> 3.2142857 | I64: =H64*C64 -> 385.68214 | J64: 0.3 | K64: =L64*M64 -> 17.016807 | L64: =$H$56/N64 -> 18.907563 | M64: 0.9 | N64: 0.17 | O64: campaign1：自动广告 campaign2：手动广告主推词PE campaign3：SD-categories campaign4：PT campaign5：手动广告核心关键词E campaign6：SBV-PT / SBV-KT | P64: 防守&进攻 转化率；订单量；Acos/Roas milbensauger | Q64: milbensauger | R64: SP:60% SD:20% SB:20%
K65: =L65*M65 -> 17.016807 | L65: =$H$56/N65 -> 18.907563 | M65: 0.9 | N65: 0.17 | Q65: milbensauger
K66: =L66*M66 -> 17.016807 | L66: =$H$56/N66 -> 18.907563 | M66: 0.9 | N66: 0.17 | Q66: milbensauger
K67: =L67*M67 -> 17.016807 | L67: =$H$56/N67 -> 18.907563 | M67: 0.9 | N67: 0.17 | Q67: milbensauger
A68: WEEK13 | B68: 7.23-7.31 | C68: 119.99 | D68: 11.428571 | E68: =C68*D68*7 -> 9599.2 | F68: 0.19047619 | G68: =D68/F68 -> 60 | H68: =D68*J68 -> 3.4285714 | I68: =H68*C68 -> 411.39429 | J68: 0.3 | K68: =L68*M68 -> 18.151261 | L68: =$H$60/N68 -> 20.168067 | M68: 0.9 | N68: 0.17 | O68: campaign1：自动广告 campaign2：手动广告主推词PE campaign3：SD-categories campaign4：PT campaign5：手动广告核心关键词E campaign6：SBV-PT / SBV-KT | Q68: milbensauger
K69: =L69*M69 -> 18.151261 | L69: =$H$60/N69 -> 20.168067 | M69: 0.9 | N69: 0.17 | Q69: milbensauger
K70: =L70*M70 -> 18.151261 | L70: =$H$60/N70 -> 20.168067 | M70: 0.9 | N70: 0.17 | Q70: milbensauger
K71: =L71*M71 -> 18.151261 | L71: =$H$60/N71 -> 20.168067 | M71: 0.9 | N71: 0.17 | Q71: milbensauger

Sheet 利润&ROI测算
A1: 细分项 | L1: 4月 | AB1: 5月 | AR1: 6月 | BH1: 达标后每月销售
A2: 状态 | B2: Asin | C2: Model# | D2: 国家 | E2: 佣金比例 | F2: RMA比例 | G2: 广告费占比 | H2: MC/个 | I2: FBA配送费 | J2: 退换货分摊 /个 | K2: VAT | L2: 待办操作 | M2: 售价 | N2: 月销量 | O2: 销售总额 | P2: MC | Q2: 佣金 | R2: 配送费 | S2: RMA扣减 | T2: 广告费 | U2: 促销费 | V2: VAT | W2: 成本总计 | X2: 回款额 UK | Y2: 回款率 | Z2: 净毛利 US | AA2: 净毛利率 | AB2: 操作 | AC2: 售价 | AD2: 月销量 | AE2: 销售总额 | AF2: MC | AG2: 佣金 | AH2: 配送费 | AI2: RMA扣减 | AJ2: 广告费 | AK2: 促销费 | AL2: VAT | AM2: 成本总计 | AN2: 回款额 US | AO2: 回款率 | AP2: 净毛利 US | AQ2: 净毛利率 | AR2: 操作 | AS2: 售价 | AT2: 月销量 | AU2: 销售总额 | AV2: MC | AW2: 佣金 | AX2: 配送费 | AY2: RMA扣减 | AZ2: 广告费 | BA2: 促销费 | BB2: VAT | BC2: 成本总计 | BD2: 回款额 US | BE2: 回款率 | BF2: 净毛利 US | BG2: 净毛利率 | BH2: 操作 | BI2: 售价 | BJ2: 月销量 | BK2: 销售总额 | BL2: 产品成本 | BM2: 佣金 | BN2: 配送费 | BO2: RMA扣减 | BP2: 广告费 | BQ2: 促销费 | BR2: VAT | BS2: 成本总计 | BT2: 回款额 EU | BU2: 回款率 | BV2: 净毛利 EU | BW2: 净毛利率
A3: 卡航 | B3: B0XXXXXXV3 | C3: SK0001EU | D3: DE | E3: 0.15 | F3: 0.07 | G3: 0.15 | H3: =122.56/7.4 -> 16.562162 | I3: 5.69 | J3: =(H3+I3)*F3 -> 1.5576514 | K3: 0.16 | L3: B0XXXXXXV3 | M3: 109.99 | N3: 450 | O3: =M3*N3 -> 49495.5 | P3: =$H3*N3 -> 7452.973 | Q3: =M3*$E3*N3 -> 7424.325 | R3: =I3*N3 -> 2560.5 | S3: =$J3*N3 -> 700.94311 | T3: =O3*18% -> 8909.19 | U3: =O3*12% -> 5939.46 | V3: =O3*K3 -> 7919.28 | W3: =P3+Q3+R3+S3+T3+U3+V3 -> 40906.671 | X3: =O3-Q3-R3-T3-U3-V3 -> 16742.745 | Y3: =X3/O3 -> 0.33826802 | Z3: =O3-W3 -> 8588.8289 | AA3: =Z3/O3 -> 0.17352747 | AC3: 114.99 | AD3: 500 | AE3: =AC3*AD3 -> 57495 | AF3: =$H3*AD3 -> 8281.0811 | AG3: =AC3*$E3*AD3 -> 8624.25 | AH3: =AD3*I3 -> 2845 | AI3: =$J3*AD3 -> 778.82568 | AJ3: =AE3*10% -> 5749.5 | AK3: =AE3*6% -> 3449.7 | AL3: =AE3*K3 -> 9199.2 | AM3: =AF3+AG3+AH3+AI3+AJ3+AK3+AL3 -> 38927.557 | AN3: =AE3-AG3-AH3-AJ3-AL3 -> 31077.05 | AO3: =AN3/AE3 -> 0.54051744 | AP3: =AE3-AM3 -> 18567.443 | AQ3: =AP3/AE3 -> 0.32294014 | AS3: 116.99 | AT3: 700 | AU3: =AS3*AT3 -> 81893 | AV3: =$H3*AT3 -> 11593.514 | AW3: =AS3*$E3*AT3 -> 12283.95 | AX3: =AT3*I3 -> 3983 | AY3: =$J3*AT3 -> 1090.3559 | AZ3: =AU3*7% -> 5732.51 | BA3: =AU3*15% -> 12283.95 | BB3: =K3*AU3 -> 13102.88 | BC3: =AV3+AW3+AX3+AY3+AZ3+BA3+BB3 -> 60070.159 | BD3: =AU3-AW3-AX3-AZ3-BB3 -> 46790.66 | BE3: =BD3/AU3 -> 0.57136336 | BF3: =AU3-BC3 -> 21822.841 | BG3: =BF3/AU3 -> 0.26647993 | BI3: 119.99 | BJ3: 1500 | BK3: =BI3*BJ3 -> 179985 | BL3: =$H3*BJ3 -> 24843.243 | BM3: =E3*BK3 -> 26997.75 | BN3: =I3*BJ3 -> 8535 | BO3: =$J3*BJ3 -> 2336.477 | BP3: =BK3*5.5% -> 9899.175 | BQ3: =BK3*8% -> 14398.8 | BR3: =K3*BK3 -> 28797.6 | BS3: =BL3+BM3+BN3+BO3+BP3+BQ3+BR3 -> 115808.05 | BT3: =BK3-BM3-BN3-BP3-BR3 -> 105755.48 | BU3: =BT3/BK3 -> 0.58757938 | BV3: =BK3-BS3 -> 64176.955 | BW3: =BV3/BK3 -> 0.35656835
A4: 铁路 | B4: B0XXXXXXV3 | C4: SK0001EU | D4: DE | E4: 0.15 | F4: 0.07 | G4: 0.15 | H4: =122.56/7.4 -> 16.562162 | I4: 5.69 | J4: =(H4+I4)*F4 -> 1.5576514 | K4: 0.16 | L4: B0XXXXXXV3 | M4: 109.99 | N4: 450 | O4: =M4*N4 -> 49495.5 | P4: =$H4*N4 -> 7452.973 | Q4: =M4*$E4*N4 -> 7424.325 | R4: =I4*N4 -> 2560.5 | S4: =$J4*N4 -> 700.94311 | T4: =O4*18% -> 8909.19 | U4: =O4*12% -> 5939.46 | V4: =O4*K4 -> 7919.28 | W4: =P4+Q4+R4+S4+T4+U4+V4 -> 40906.671 | X4: =O4-Q4-R4-T4-U4-V4 -> 16742.745 | Y4: =X4/O4 -> 0.33826802 | Z4: =O4-W4 -> 8588.8289 | AA4: =Z4/O4 -> 0.17352747 | AC4: 114.99 | AD4: 500 | AE4: =AC4*AD4 -> 57495 | AF4: =$H4*AD4 -> 8281.0811 | AG4: =AC4*$E4*AD4 -> 8624.25 | AH4: =AD4*I4 -> 2845 | AI4: =$J4*AD4 -> 778.82568 | AJ4: =AE4*10% -> 5749.5 | AK4: =AE4*6% -> 3449.7 | AL4: =AE4*K4 -> 9199.2 | AM4: =AF4+AG4+AH4+AI4+AJ4+AK4+AL4 -> 38927.557 | AN4: =AE4-AG4-AH4-AJ4-AL4 -> 31077.05 | AO4: =AN4/AE4 -> 0.54051744 | AP4: =AE4-AM4 -> 18567.443 | AQ4: =AP4/AE4 -> 0.32294014 | AS4: 116.99 | AT4: 700 | AU4: =AS4*AT4 -> 81893 | AV4: =$H4*AT4 -> 11593.514 | AW4: =AS4*$E4*AT4 -> 12283.95 | AX4: =AT4*I4 -> 3983 | AY4: =$J4*AT4 -> 1090.3559 | AZ4: =AU4*7% -> 5732.51 | BA4: =AU4*15% -> 12283.95 | BB4: =K4*AU4 -> 13102.88 | BC4: =AV4+AW4+AX4+AY4+AZ4+BA4+BB4 -> 60070.159 | BD4: =AU4-AW4-AX4-AZ4-BB4 -> 46790.66 | BE4: =BD4/AU4 -> 0.57136336 | BF4: =AU4-BC4 -> 21822.841 | BG4: =BF4/AU4 -> 0.26647993 | BI4: 119.99 | BJ4: 1500 | BK4: =BI4*BJ4 -> 179985 | BL4: =$H4*BJ4 -> 24843.243 | BM4: =E4*BK4 -> 26997.75 | BN4: =I4*BJ4 -> 8535 | BO4: =$J4*BJ4 -> 2336.477 | BP4: =BK4*5.5% -> 9899.175 | BQ4: =BK4*8% -> 14398.8 | BR4: =K4*BK4 -> 28797.6 | BS4: =BL4+BM4+BN4+BO4+BP4+BQ4+BR4 -> 115808.05 | BT4: =BK4-BM4-BN4-BP4-BR4 -> 105755.48 | BU4: =BT4/BK4 -> 0.58757938 | BV4: =BK4-BS4 -> 64176.955 | BW4: =BV4/BK4 -> 0.35656835
A5: 海运 | B5: B0XXXXXXV3 | C5: SK0001EU | D5: DE | E5: 0.15 | F5: 0.07 | G5: 0.15 | H5: =122.56/7.4 -> 16.562162 | I5: 5.69 | J5: =(H5+I5)*F5 -> 1.5576514 | K5: 0.16 | L5: B0XXXXXXV3 | M5: 109.99 | N5: 450 | O5: =M5*N5 -> 49495.5 | P5: =$H5*N5 -> 7452.973 | Q5: =M5*$E5*N5 -> 7424.325 | R5: =I5*N5 -> 2560.5 | S5: =$J5*N5 -> 700.94311 | T5: =O5*18% -> 8909.19 | U5: =O5*12% -> 5939.46 | V5: =O5*K5 -> 7919.28 | W5: =P5+Q5+R5+S5+T5+U5+V5 -> 40906.671 | X5: =O5-Q5-R5-T5-U5-V5 -> 16742.745 | Y5: =X5/O5 -> 0.33826802 | Z5: =O5-W5 -> 8588.8289 | AA5: =Z5/O5 -> 0.17352747
A6: 空运 | B6: B0XXXXXXV3 | C6: SK0001EU | D6: DE | E6: 0.15 | F6: 0.07 | G6: 0.15 | H6: =122.56/7.4 -> 16.562162 | I6: 5.69 | J6: =(H6+I6)*F6 -> 1.5576514 | K6: 0.16 | L6: B0XXXXXXV3 | M6: 109.99 | N6: 450 | O6: =M6*N6 -> 49495.5 | P6: =$H6*N6 -> 7452.973 | Q6: =M6*$E6*N6 -> 7424.325 | R6: =I6*N6 -> 2560.5 | S6: =$J6*N6 -> 700.94311 | T6: =O6*18% -> 8909.19 | U6: =O6*12% -> 5939.46 | V6: =O6*K6 -> 7919.28 | W6: =P6+Q6+R6+S6+T6+U6+V6 -> 40906.671 | X6: =O6-Q6-R6-T6-U6-V6 -> 16742.745 | Y6: =X6/O6 -> 0.33826802 | Z6: =O6-W6 -> 8588.8289 | AA6: =Z6/O6 -> 0.17352747
N8: =SUM(N3:N6) -> 1800 | O8: =SUM(O3:O6) -> 197982 | P8: =SUM(P3:P6) -> 29811.892 | Q8: =SUM(Q3:Q6) -> 29697.3 | R8: =SUM(R3:R6) -> 10242 | S8: =SUM(S3:S6) -> 2803.7724 | T8: =SUM(T3:T6) -> 35636.76 | U8: =SUM(U3:U6) -> 23757.84 | ... X8: =SUM(X3:X6) -> 66970.98 | Y8: =X8/O8 -> 0.33826802 | Z8: =SUM(Z3:Z6) -> 34355.316 | AA8: =Z8/O8 -> 0.17352747 | AD8: =SUM(AD3:AD6) -> 1000 | AE8: =SUM(AE3:AE6) -> 114990 | AF8: =SUM(AF3:AF6) -> 16562.162 | AG8: =SUM(AG3:AG6) -> 17248.5 | AH8: =SUM(AH3:AH6) -> 5690 | AI8: =SUM(AI3:AI6) -> 1557.6514 | AJ8: =SUM(AJ3:AJ6) -> 11499 | AK8: =SUM(AK3:AK6) -> 6899.4 | ... AN8: =SUM(AN3:AN6) -> 62154.1 | AO8: =AN8/AE8 -> 0.54051744 | AP8: =SUM(AP3:AP6) -> 37134.886 | AQ8: =AP8/AE8 -> 0.32294014 | AT8: =SUM(AT3:AT6) -> 1400 | AU8: =SUM(AU3:AU6) -> 163786 | AV8: =SUM(AV3:AV6) -> 23187.027 | AW8: =SUM(AW3:AW6) -> 24567.9 | AX8: =SUM(AX3:AX6) -> 7966 | AY8: =SUM(AY3:AY6) -> 2180.7119 | AZ8: =SUM(AZ3:AZ6) -> 11465.02 | BA8: =SUM(BA3:BA6) -> 24567.9 | ... BD8: =SUM(BD3:BD6) -> 93581.32 | BE8: =BD8/AU8 -> 0.57136336 | BF8: =SUM(BF3:BF6) -> 43645.681 | BG8: =BF8/AU8 -> 0.26647993 | BJ8: =SUM(BJ3:BJ6) -> 3000 | BK8: =SUM(BK3:BK6) -> 359970 | BL8: =SUM(BL3:BL6) -> 49686.486 | BM8: =SUM(BM3:BM6) -> 53995.5 | BN8: =SUM(BN3:BN6) -> 17070 | BO8: =SUM(BO3:BO6) -> 4672.9541 | BP8: =SUM(BP3:BP6) -> 19798.35 | BQ8: =SUM(BQ3:BQ6) -> 28797.6 | ... BT8: =SUM(BT3:BT6) -> 211510.95 | BU8: =BT8/BK8 -> 0.58757938 | BV8: =SUM(BV3:BV6) -> 128353.91 | BW8: =BV8/BK8 -> 0.35656835
A11: 价格利润测算
A13: Asin | B13: Model | C13: Price | D13: All cost | E13: Profit | F13: Profit% | G13: MC | H13: 佣金 | I13: 配送费 | J13: 退货均摊 | K13: VAT税率 | L13: 佣金率 | M13: 退货率 | N13: 折扣% off | O13: 底价
A14: B0XXXXXXV3 | B14: SK0001EU | C14: =$M$3 -> 109.99 | D14: =G14+H14+I14+J14+K14*C14+C14*N14 -> 64.7552 | E14: =C14-D14 -> 45.2348 | F14: =E14/C14 -> 0.41126284 | G14: 6.27 | H14: =C14*L14 -> 16.4985 | I14: =$I$3 -> 5.69 | J14: =C14*M14 -> 7.6993 | K14: 0.16 | L14: =$E$3 -> 0.15 | M14: =$F$3 -> 0.07 | N14: 0.1 | O14: =(G14+I14)/(1-L14-M14-K14) -> 19.290323
A15: B0XXXXXXV3 | B15: SK0001EU | C15: =$M$3 -> 109.99 | D15: =G15+H15+I15+J15+K15*C15+C15*N15 -> 59.2557 | E15: =C15-D15 -> 50.7343 | F15: =E15/C15 -> 0.46126284 | G15: 6.27 | H15: =C15*L15 -> 16.4985 | I15: =$I$3 -> 5.69 | J15: =C15*M15 -> 7.6993 | K15: 0.16 | L15: =$E$3 -> 0.15 | M15: =$F$3 -> 0.07 | N15: 0.05 | O15: =(G15+I15)/(1-L15-M15-K15) -> 19.290323
A16: B0XXXXXXV3 | B16: SK0001EU | C16: =$M$3 -> 109.99 | D16: =G16+H16+I16+J16+K16*C16+C16*N16 -> 59.2557 | E16: =C16-D16 -> 50.7343 | F16: =E16/C16 -> 0.46126284 | G16: 6.27 | H16: =C16*L16 -> 16.4985 | I16: =$I$3 -> 5.69 | J16: =C16*M16 -> 7.6993 | K16: 0.16 | L16: =$E$3 -> 0.15 | M16: =$F$3 -> 0.07 | N16: 0.05 | O16: =(G16+I16)/(1-L16-M16-K16) -> 19.290323
A17: B0XXXXXXV3 | B17: SK0001EU | C17: =$M$3 -> 109.99 | D17: =G17+H17+I17+J17+K17*C17+C17*N17 -> 59.2557 | E17: =C17-D17 -> 50.7343 | F17: =E17/C17 -> 0.46126284 | G17: 6.27 | H17: =C17*L17 -> 16.4985 | I17: =$I$3 -> 5.69 | J17: =C17*M17 -> 7.6993 | K17: 0.16 | L17: =$E$3 -> 0.15 | M17: =$F$3 -> 0.07 | N17: 0.05 | O17: =(G17+I17)/(1-L17-M17-K17) -> 19.290323
A18: B0XXXXXXV3 | B18: SK0001EU | C18: =$M$3 -> 109.99 | D18: =G18+H18+I18+J18+K18*C18+C18*N18 -> 59.2557 | E18: =C18-D18 -> 50.7343 | F18: =E18/C18 -> 0.46126284 | G18: 6.27 | H18: =C18*L18 -> 16.4985 | I18: =$I$3 -> 5.69 | J18: =C18*M18 -> 7.6993 | K18: 0.16 | L18: =$E$3 -> 0.15 | M18: =$F$3 -> 0.07 | N18: 0.05 | O18: =(G18+I18)/(1-L18-M18-K18) -> 19.290323
A19: B0XXXXXXV3 | B19: SK0001EU | C19: 119.99 | D19: =G19+H19+I19+J19+K19*C19+C19*N19 -> 57.5562 | E19: =C19-D19 -> 62.4338 | F19: =E19/C19 -> 0.52032503 | G19: 6.27 | H19: =C19*L19 -> 17.9985 | I19: =$I$3 -> 5.69 | J19: =C19*M19 -> 8.3993 | K19: 0.16 | L19: =$E$3 -> 0.15 | M19: =$F$3 -> 0.07 | N19: 0 | O19: =(G19+I19)/(1-L19-M19-K19) -> 19.290323
A20: B0XXXXXXV3 | B20: SK0001EU | C20: 116.99 | D20: =G20+H20+I20+J20+K20*C20+C20*N20 -> 56.4162 | E20: =C20-D20 -> 60.5738 | F20: =E20/C20 -> 0.51776904 | G20: 6.27 | H20: =C20*L20 -> 17.5485 | I20: =$I$3 -> 5.69 | J20: =C20*M20 -> 8.1893 | K20: 0.16 | L20: =$E$3 -> 0.15 | M20: =$F$3 -> 0.07 | N20: 0 | O20: =(G20+I20)/(1-L20-M20-K20) -> 19.290323
A21: B0XXXXXXV3 | B21: SK0001EU | C21: 112.99 | D21: =G21+H21+I21+J21+K21*C21+C21*N21 -> 54.8962 | E21: =C21-D21 -> 58.0938 | F21: =E21/C21 -> 0.51414992 | G21: 6.27 | H21: =C21*L21 -> 16.9485 | I21: =$I$3 -> 5.69 | J21: =C21*M21 -> 7.9093 | K21: 0.16 | L21: =$E$3 -> 0.15 | M21: =$F$3 -> 0.07 | N21: 0 | O21: =(G21+I21)/(1-L21-M21-K21) -> 19.290323
A24: ROI测算
A25: 月份 | B25: 售价 | C25: 月销量 | D25: 总销售额 | E25: MC | F25: 佣金 | G25: 配送费 | H25: RMA扣减 | I25: 广告费 | J25: 促销费 | K25: VAT | L25: 成本总计 | M25: 回款额 US | N25: 回款率 | O25: 净毛利 US | P25: 净毛利率 | Q25: 累计净毛利
A26: 3月 | B26: =119.99 -> 119.99 | C26: =N3 -> 450 | D26: =O3 -> 49495.5 | E26: =P3 -> 7452.973 | F26: =Q3 -> 7424.325 | G26: =R3 -> 2560.5 | H26: =S3 -> 700.94311 | I26: =T3 -> 8909.19 | J26: =U3 -> 5939.46 | ... P26: =AA3 -> 0.17352747 | Q26: =O26 -> 8588.8289
A27: 4月 | B27: 119.99 | C27: 1500 | D27: =AE4 -> 57495 | E27: =AF4 -> 8281.0811 | F27: =AG4 -> 8624.25 | G27: =AH4 -> 2845 | H27: =AI4 -> 778.82568 | I27: =AJ4 -> 5749.5 | J27: =AK4 -> 3449.7 | K27: =AL4 -> 9199.2 | ... P27: =AQ4 -> 0.32294014 | Q27: =SUM(O26:O27) -> 27156.272
A28: 5月 | B28: 116.99 | C28: 1700 | D28: =AU4 -> 81893 | E28: =AV4 -> 11593.514 | F28: =AW4 -> 12283.95 | G28: =AX4 -> 3983 | H28: =AY4 -> 1090.3559 | I28: =AZ4 -> 5732.51 | J28: =BA4 -> 12283.95 | K28: =BB4 -> 13102.88 | ... P28: =BG4 -> 0.26647993 | Q28: =SUM(O26:O28) -> 48979.113
A29: 6月 | B29: 116.99 | C29: 1500 | D29: 25485 | E29: 8430 | F29: 3822.75 | G29: 2805 | H29: 561.75 | I29: 1401.675 | J29: 2038.8 | K29: 4247.5 | L29: 23307.475 | M29: 13208.075 | N29: 0.51826859 | O29: 2177.525 | P29: 0.085443398 | Q29: =SUM(O26:O29) -> 51156.638
A30: 7月 | B30: 119.99 | C30: 1500 | D30: 25485 | E30: 8430 | F30: 3822.75 | G30: 2805 | H30: 561.75 | I30: 1401.675 | J30: 2038.8 | K30: 4247.5 | L30: 23307.475 | M30: 13208.075 | N30: 0.51826859 | O30: 2177.525 | P30: 0.085443398 | Q30: =SUM(O27:O30) -> 44745.334
A31: 8月 | B31: 119.99 | C31: 1500 | D31: 25485 | E31: 8430 | F31: 3822.75 | G31: 2805 | H31: 561.75 | I31: 1401.675 | J31: 2038.8 | K31: 4247.5 | L31: 23307.475 | M31: 13208.075 | N31: 0.51826859 | O31: 2177.525 | P31: 0.085443398 | Q31: =SUM(O28:O31) -> 28355.416
A32: 9月 | B32: 119.99 | C32: 1500 | D32: 25485 | E32: 8430 | F32: 3822.75 | G32: 2805 | H32: 561.75 | I32: 1401.675 | J32: 2038.8 | K32: 4247.5 | L32: 23307.475 | M32: 13208.075 | N32: 0.51826859 | O32: 2177.525 | P32: 0.085443398 | Q32: =SUM(O29:O32) -> 8710.1
A33: 10月 | B33: 119.99 | C33: 1500 | D33: 25485 | E33: 8430 | F33: 3822.75 | G33: 2805 | H33: 561.75 | I33: 1401.675 | J33: 2038.8 | K33: 4247.5 | L33: 23307.475 | M33: 13208.075 | N33: 0.51826859 | O33: 2177.525 | P33: 0.085443398 | Q33: =SUM(O30:O33) -> 8710.1
A34: 11月 | B34: 119.99 | C34: 1500 | D34: 25485 | E34: 8430 | F34: 3822.75 | G34: 2805 | H34: 561.75 | I34: 1401.675 | J34: 2038.8 | K34: 4247.5 | L34: 23307.475 | M34: 13208.075 | N34: 0.51826859 | O34: 2177.525 | P34: 0.085443398 | Q34: =SUM(O31:O34) -> 8710.1
A35: 12月 | B35: 119.99 | C35: 1500 | D35: 25485 | E35: 8430 | F35: 3822.75 | G35: 2805 | H35: 561.75 | I35: 1401.675 | J35: 2038.8 | K35: 4247.5 | L35: 23307.475 | M35: 13208.075 | N35: 0.51826859 | O35: 2177.525 | P35: 0.085443398 | Q35: =SUM(O32:O35) -> 8710.1
A36: 1月 | B36: 119.99 | C36: 1500 | D36: 25485 | E36: 8430 | F36: 3822.75 | G36: 2805 | H36: 561.75 | I36: 1401.675 | J36: 2038.8 | K36: 4247.5 | L36: 23307.475 | M36: 13208.075 | N36: 0.51826859 | O36: 2177.525 | P36: 0.085443398 | Q36: =SUM(O33:O36) -> 8710.1
A37: 2 | B37: 119.99 | C37: 1500 | D37: 25485 | E37: 8430 | F37: 3822.75 | G37: 2805 | H37: 561.75 | I37: 1401.675 | J37: 2038.8 | K37: 4247.5 | L37: 23307.475 | M37: 13208.075 | N37: 0.51826859 | O37: 2177.525 | P37: 0.085443398 | Q37: =SUM(O34:O37) -> 8710.1
A38: 3
A40: ROI实际数据
A41: 月份 | B41: 售价 | C41: 月销量 | D41: 总销售额 | E41: MC | F41: 佣金 | G41: 配送费 | H41: RMA扣减 | I41: 广告费 | J41: 促销费 | K41: VAT | L41: 成本总计 | M41: 回款额 US | N41: 回款率 | O41: 净毛利 US | P41: 净毛利率 | Q41: 累计净毛利
A42: 3月 | B42: =119.99 -> 119.99 | C42: =N19 -> 0 | D42: =O19 -> 19.290323 | E42: =P19 -> 0 | F42: =Q19 -> 0 | G42: =R19 -> 0 | H42: =S19 -> 0 | I42: =T19 -> 0 | J42: =U19 -> 0 | ... P42: =AA19 -> 0 | Q42: =O42 -> 0
A43: 4月 | B43: 119.99 | C43: 1500 | D43: =AE20 -> 0 | E43: =AF20 -> 0 | F43: =AG20 -> 0 | G43: =AH20 -> 0 | H43: =AI20 -> 0 | I43: =AJ20 -> 0 | J43: =AK20 -> 0 | K43: =AL20 -> 0 | ... P43: =AQ20 -> 0 | Q43: =SUM(O42:O43) -> 0
A44: 5月 | B44: 116.99 | C44: 1700 | D44: =AU20 -> 0 | E44: =AV20 -> 0 | F44: =AW20 -> 0 | G44: =AX20 -> 0 | H44: =AY20 -> 0 | I44: =AZ20 -> 0 | J44: =BA20 -> 0 | K44: =BB20 -> 0 | ... P44: =BG20 -> 0 | Q44: =SUM(O42:O44) -> 0
A45: 6月 | B45: 116.99 | C45: 1500 | D45: 25485 | E45: 8430 | F45: 3822.75 | G45: 2805 | H45: 561.75 | I45: 1401.675 | J45: 2038.8 | K45: 4247.5 | L45: 23307.475 | M45: 13208.075 | N45: 0.51826859 | O45: 2177.525 | P45: 0.085443398 | Q45: =SUM(O42:O45) -> 2177.525
A46: 7月 | B46: 119.99 | C46: 1500 | D46: 25485 | E46: 8430 | F46: 3822.75 | G46: 2805 | H46: 561.75 | I46: 1401.675 | J46: 2038.8 | K46: 4247.5 | L46: 23307.475 | M46: 13208.075 | N46: 0.51826859 | O46: 2177.525 | P46: 0.085443398 | Q46: =SUM(O43:O46) -> 4355.05
A47: 8月 | B47: 119.99 | C47: 1500 | D47: 25485 | E47: 8430 | F47: 3822.75 | G47: 2805 | H47: 561.75 | I47: 1401.675 | J47: 2038.8 | K47: 4247.5 | L47: 23307.475 | M47: 13208.075 | N47: 0.51826859 | O47: 2177.525 | P47: 0.085443398 | Q47: =SUM(O44:O47) -> 6532.575
A48: 9月 | B48: 119.99 | C48: 1500 | D48: 25485 | E48: 8430 | F48: 3822.75 | G48: 2805 | H48: 561.75 | I48: 1401.675 | J48: 2038.8 | K48: 4247.5 | L48: 23307.475 | M48: 13208.075 | N48: 0.51826859 | O48: 2177.525 | P48: 0.085443398 | Q48: =SUM(O45:O48) -> 8710.1
A49: 10月 | B49: 119.99 | C49: 1500 | D49: 25485 | E49: 8430 | F49: 3822.75 | G49: 2805 | H49: 561.75 | I49: 1401.675 | J49: 2038.8 | K49: 4247.5 | L49: 23307.475 | M49: 13208.075 | N49: 0.51826859 | O49: 2177.525 | P49: 0.085443398 | Q49: =SUM(O46:O49) -> 8710.1
A50: 11月 | B50: 119.99 | C50: 1500 | D50: 25485 | E50: 8430 | F50: 3822.75 | G50: 2805 | H50: 561.75 | I50: 1401.675 | J50: 2038.8 | K50: 4247.5 | L50: 23307.475 | M50: 13208.075 | N50: 0.51826859 | O50: 2177.525 | P50: 0.085443398 | Q50: =SUM(O47:O50) -> 8710.1
A51: 12月 | B51: 119.99 | C51: 1500 | D51: 25485 | E51: 8430 | F51: 3822.75 | G51: 2805 | H51: 561.75 | I51: 1401.675 | J51: 2038.8 | K51: 4247.5 | L51: 23307.475 | M51: 13208.075 | N51: 0.51826859 | O51: 2177.525 | P51: 0.085443398 | Q51: =SUM(O48:O51) -> 8710.1
A52: 1 | B52: 119.99 | C52: 1500 | D52: 25485 | E52: 8430 | F52: 3822.75 | G52: 2805 | H52: 561.75 | I52: 1401.675 | J52: 2038.8 | K52: 4247.5 | L52: 23307.475 | M52: 13208.075 | N52: 0.51826859 | O52: 2177.525 | P52: 0.085443398 | Q52: =SUM(O49:O52) -> 8710.1
A53: 2 | B53: 119.99 | C53: 1500 | D53: 25485 | E53: 8430 | F53: 3822.75 | G53: 2805 | H53: 561.75 | I53: 1401.675 | J53: 2038.8 | K53: 4247.5 | L53: 23307.475 | M53: 13208.075 | N53: 0.51826859 | O53: 2177.525 | P53: 0.085443398 | Q53: =SUM(O50:O53) -> 8710.1
A54: 3
A56: ROI差异数据
A57: 3月
A58: 4月
A59: 5月
A60: 6月
A61: 7月
A62: 8月
A63: 9月
A64: 10月
A65: 11月
A66: 12月
A67: 1
A68: 2
A69: 3

Sheet 2
A1: amazon-order-id | B1: merchant-order-id | C1: purchase-date | D1: last-updated-date | E1: order-status | F1: fulfillment-channel | G1: sales-channel | H1: order-channel | I1: url | J1: ship-service-level | K1: product-name | L1: sku | M1: asin | N1: item-status | O1: quantity | P1: currency | Q1: item-price | R1: item-tax | S1: shipping-price | T1: shipping-tax | U1: gift-wrap-price | V1: gift-wrap-tax | W1: item-promotion-discount | X1: ship-promotion-discount | Y1: ship-city | Z1: ship-state | AA1: ship-postal-code | AB1: ship-country | AC1: promotion-ids | AD1: is-business-order | AE1: purchase-order-number | AF1: price-designation | AG1: default-ship-from-address-name | AH1: default-ship-from-address-field-1 | AI1: default-ship-from-address-field-2 | AJ1: default-ship-from-address-field-3 | AK1: default-ship-from-city | AL1: default-ship-from-state | AM1: default-ship-from-country | AN1: default-ship-from-postal-code | AO1: actual-ship-from-address-name | AP1: actual-ship-from-address-field-1 | AQ1: actual-ship-from-address-field-2 | AR1: actual-ship-from-address-field-3 | AS1: actual-ship-from-city | AT1: actual-ship-from-state | AU1: actual-ship-from-country | AV1: actual-ship-from-postal-code | AW1: is-buyer-requested-cancellation | AX1: buyer-requested-cancel-reason | AY1: serial-numbers | AZ1: signature-confirmation-recommended
A2: 111-9858618-2103444 | B2: 111-9858618-2103444 | C2: 2023-09-12T05:37:43+00:00 | D2: 2023-09-12T05:37:48+00:00 | E2: Pending | F2: Amazon | G2: Amazon.com | J2: Expedited | K2: Dash Cam Front with FHD 1080p, Wanlipo 2 Inch LCD Dashcam, Dashboard Camera for Cars with 24h Parking Monitor, G-Sensor, Loop Recording, Free 32GB SD | L2: J09-C1 | M2: B0BG6WPM3W | N2: Unshipped | O2: 1 | P2: USD | Q2: 79.99 | Y2: BELLMAWR | Z2: NJ | AA2: 08031-2115 | AB2: US | AC2: MPC-S Percentage Off 2023/09/10 11-52-12-900 | AD2: FALSE | AW2: FALSE | AZ2: FALSE
A3: 114-5667916-6324215 | B3: 114-5667916-6324215 | C3: 2023-09-12T03:37:05+00:00 | D3: 2023-09-12T09:02:46+00:00 | E3: Shipped | F3: Amazon | G3: Amazon.com | J3: Expedited | K3: 4K Dash Cam Front Built-in WiFi, WANLIPO Dash Camera for Cars with 64GB SD Card, Car Camera with 3" IPS Screen, 2160P Dashcam for Cars with App Contro | L3: Wanlipo M03-3 | M3: B0CC8CHTTJ | N3: Shipped | O3: 1 | P3: USD | Q3: 99.99 | R3: 1.89 | W3: 72.99 | Y3: MONROE | Z3: GA | AA3: 30656-4723 | AB3: US | AC3: MPC-S Percentage Off 2023/09/11 9-53-46-600 | AD3: FALSE | AW3: FALSE | AZ3: FALSE
A4: 111-1595396-9168227 | B4: 111-1595396-9168227 | C4: 2023-09-11T23:55:05+00:00 | D4: 2023-09-11T23:55:11+00:00 | E4: Pending | F4: Amazon | G4: Amazon.com | J4: Expedited | K4: Dash Cam Front with FHD 1080p, Wanlipo 2 Inch LCD Dashcam, Dashboard Camera for Cars with 24h Parking Monitor, G-Sensor, Loop Recording, Free 32GB SD | L4: J09-C1 | M4: B0BG6WPM3W | N4: Unshipped | O4: 1 | P4: USD | Q4: 79.99 | Y4: SILVER SPRING | Z4: MD | AA4: 20906-4527 | AB4: US | AC4: MPC-S Percentage Off 2023/09/10 11-52-3-698 | AD4: FALSE | AW4: FALSE | AZ4: FALSE
A5: 112-7810040-2837843 | B5: 112-7810040-2837843 | C5: 2023-09-11T19:41:13+00:00 | D5: 2023-09-12T01:35:23+00:00 | E5: Shipped | F5: Amazon | G5: Amazon.com | J5: Expedited | K5: Dash Cam Front with FHD 1080p, Wanlipo 2 Inch LCD Dashcam, Dashboard Camera for Cars with 24h Parking Monitor, G-Sensor, Loop Recording, Free 32GB SD | L5: J09-C1 | M5: B0BG6WPM3W | N5: Shipped | O5: 1 | P5: USD | Q5: 79.99 | R5: 1.85 | W5: 59.99 | Y5: Nashville | Z5: TN | AA5: 37208-1058 | AB5: US | AC5: MPC-S Percentage Off 2023/09/10 11-52-13-889 | AD5: FALSE | AW5: FALSE | AZ5: FALSE
A6: 111-4369826-2407442 | B6: 111-4369826-2407442 | C6: 2023-09-11T18:52:15+00:00 | D6: 2023-09-11T18:52:21+00:00 | E6: Pending | F6: Amazon | G6: Amazon.com | J6: Standard | K6: 4K Dash Cam Front with WiFi 2160P, VOFRTY Dash Camera for Cars with 3" IPS, Car Camera with App Control, Dashcam with G-Sensor, Loop Recording, 64GB S | L6: M03-3 | M6: B0C1C9T9KP | N6: Unshipped | O6: 1 | P6: USD | Q6: 79.99 | Y6: HUNTINGTON | Z6: WV | AA6: 25704-1119 | AB6: US | AC6: US Core Free Shipping Promotion A3JU1FCINF5SD0,Percentage Off 2023/08/28 6-17-47-400 | AD6: FALSE | AW6: FALSE | AZ6: FALSE
A7: 114-0862837-0430606 | B7: 114-0862837-0430606 | C7: 2023-09-11T17:17:31+00:00 | D7: 2023-09-11T17:17:37+00:00 | E7: Pending | F7: Amazon | G7: Amazon.com | J7: Expedited | K7: Dash Cam Front with FHD 1080p, Wanlipo 2 Inch LCD Dashcam, Dashboard Camera for Cars with 24h Parking Monitor, G-Sensor, Loop Recording, Free 32GB SD | L7: J09-C1 | M7: B0BG6WPM3W | N7: Unshipped | O7: 1 | P7: USD | Q7: 79.99 | Y7: LOS ANGELES | Z7: CA | AA7: 90016-2009 | AB7: US | AC7: MPC-S Percentage Off 2023/09/10 11-52-3-698 | AD7: FALSE | AW7: FALSE | AZ7: FALSE
A8: 114-2447819-7327466 | B8: 114-2447819-7327466 | C8: 2023-09-11T15:45:23+00:00 | D8: 2023-09-11T15:45:29+00:00 | E8: Pending | F8: Amazon | G8: Amazon.com | J8: Expedited | K8: 4K Dash Cam Front with WiFi 2160P, VOFRTY Dash Camera for Cars with 3" IPS, Car Camera with App Control, Dashcam with G-Sensor, Loop Recording, 64GB S | L8: M03-3 | M8: B0C1C9T9KP | N8: Unshipped | O8: 1 | P8: USD | Q8: 79.99 | Y8: DES MOINES | Z8: IA | AA8: 50317-6307 | AB8: US | AC8: MPC-S Percentage Off 2023/09/11 9-54-8-40 | AD8: FALSE | AW8: FALSE | AZ8: FALSE
A9: 114-3078544-2276207 | B9: 114-3078544-2276207 | C9: 2023-09-11T15:21:19+00:00 | D9: 2023-09-12T04:25:37+00:00 | E9: Shipped | F9: Amazon | G9: Amazon.com | J9: Expedited | K9: 4K Dash Cam Front with WiFi 2160P, VOFRTY Dash Camera for Cars with 3" IPS, Car Camera with App Control, Dashcam with G-Sensor, Loop Recording, 64GB S | L9: M03-3 | M9: B0C1C9T9KP | N9: Shipped | O9: 1 | P9: USD | Q9: 79.99 | R9: 3.12 | W9: 47.99 | Y9: LA VERGNE | Z9: TN | AA9: 37086-1439 | AB9: US | AC9: MPC-S Percentage Off 2023/09/11 9-54-8-40 | AD9: FALSE | AW9: FALSE | AZ9: FALSE
A10: 114-1356066-5534643 | B10: 114-1356066-5534643 | C10: 2023-09-11T13:58:53+00:00 | D10: 2023-09-12T07:08:25+00:00 | E10: Shipped | F10: Amazon | G10: Amazon.com | J10: Expedited | K10: Dash Cam Front with FHD 1080p, Wanlipo 2 Inch LCD Dashcam, Dashboard Camera for Cars with 24h Parking Monitor, G-Sensor, Loop Recording, Free 32GB SD | L10: J09-C1 | M10: B0BG6WPM3W | N10: Shipped | O10: 1 | P10: USD | Q10: 79.99 | R10: 1.25 | S10: 2.99 | W10: 59.99 | X10: 2.99 | Y10: BLACKSTONE | Z10: MA | AA10: 01504-1408 | AB10: US | AC10: MPC-S Percentage Off 2023/09/10 5-41-22-292 | AD10: FALSE | AW10: FALSE | AZ10: FALSE
A11: 112-9726611-4879461 | B11: 112-9726611-4879461 | C11: 2023-09-11T12:39:23+00:00 | D11: 2023-09-12T09:25:25+00:00 | E11: Shipped | F11: Amazon | G11: Amazon.com | J11: Standard | K11: 4K Dash Cam Front Built-in WiFi, WANLIPO Dash Camera for Cars with 64GB SD Card, Car Camera with 3" IPS Screen, 2160P Dashcam for Cars with App Contro | L11: Wanlipo M03-3 | M11: B0CC8CHTTJ | N11: Shipped | O11: 1 | P11: USD | Q11: 99.99 | R11: 2.84 | W11: 67.99 | Y11: Brooklyn | Z11: NY | AA11: 11235 | AB11: US | AC11: MPC-S Percentage Off 2023/09/07 1-34-35-547 | AD11: FALSE | AW11: FALSE | AZ11: FALSE
A12: 113-6400382-4997016 | B12: 113-6400382-4997016 | C12: 2023-09-11T11:06:47+00:00 | D12: 2023-09-11T11:06:52+00:00 | E12: Pending | F12: Amazon | G12: Amazon.com | J12: Expedited | K12: Dash Cam Front with FHD 1080p, Wanlipo 2 Inch LCD Dashcam, Dashboard Camera for Cars with 24h Parking Monitor, G-Sensor, Loop Recording, Free 32GB SD | L12: J09-C1 | M12: B0BG6WPM3W | N12: Unshipped | O12: 1 | P12: USD | Q12: 79.99 | Y12: BRONX | Z12: NY | AA12: 10461 | AB12: US | AC12: MPC-S Percentage Off 2023/09/10 11-52-12-900 | AD12: FALSE | AW12: FALSE | AZ12: FALSE
A13: 112-9947498-4884232 | B13: 112-9947498-4884232 | C13: 2023-09-11T07:15:23+00:00 | D13: 2023-09-11T18:12:08+00:00 | E13: Shipped | F13: Amazon | G13: Amazon.com | J13: Expedited | K13: 4K Dash Cam Front with WiFi 2160P, VOFRTY Dash Camera for Cars with 3" IPS, Car Camera with App Control, Dashcam with G-Sensor, Loop Recording, 64GB S | L13: M03-3 | M13: B0C1C9T9KP | N13: Shipped | O13: 1 | P13: USD | Q13: 79.99 | R13: 3.8 | W13: 40 | Y13: WEST COVINA | Z13: CA | AA13: 91792-1494 | AB13: US | AC13: Percentage Off 2023/08/28 6-17-47-400 | AD13: FALSE | AW13: FALSE | AZ13: FALSE

Sheet 逮虾户上贴费用详情
A1: 标题 | B1: 产品链接 | C1: ASIN | D1: 原价 | E1: 折后价 | F1: 折扣码 | G1: 折扣力度 | H1: 其他叠加优惠 | I1: 资源名称 | J1: 资源链接 | K1: 费用 | L1: 状态 | M1: 帖子链接 | N1: 上帖图片 | O1: 失败原因 | P1: 下单时间 | Q1: 接单时间 | R1: 上帖时间 | S1: 退款时间
A2: 4K Dash Cam Front Built-in WiFi, WANLIPO Dash Camera for Cars with 64GB SD Card App Control | B2: https://www.amazon.com/promocode/A1DX8GZASC5MLT | C2: B0CC8CHTTJ | D2: $99.99 | E2: $31.99 | F2: 68WHPID3 | G2: 68 | I2: INSANE CHRISTMAS DEALS, Forking Good Deals | J2: 查看链接 | K2: 37 | L2: 已完成 | M2: 查看帖子 | P2: 2023-09-07 15:24:49 | Q2: 2023-09-07 18:22:38 | R2: 2023-09-08 11:44:55
A3: 4K Dash Cam Front Built-in WiFi, WANLIPO Dash Camera for Cars with 64GB SD Card App Control | B3: https://www.amazon.com/promocode/A1DX8GZASC5MLT | C3: B0CC8CHTTJ | D3: $99.99 | E3: $31.99 | F3: 68WHPID3 | G3: 68 | I3: Saving With Joy- Online Deals and Giveaways | J3: 查看链接 | K3: 14 | L3: 已完成 | M3: 查看帖子 | P3: 2023-09-07 15:24:49 | Q3: 2023-09-07 16:49:59 | R3: 2023-09-08 13:42:22
A4: 4K Dash Cam Front Built-in WiFi, WANLIPO Dash Camera for Cars with 64GB SD Card App Control | B4: https://www.amazon.com/promocode/A1DX8GZASC5MLT | C4: B0CC8CHTTJ | D4: $99.99 | E4: $31.99 | F4: 68WHPID3 | G4: 68 | I4: The Frugal SAHM | Deals & Discounts for Moms + Babies | J4: 查看链接 | K4: 30 | L4: 已完成 | M4: 查看帖子 | P4: 2023-09-07 15:24:49 | Q4: 2023-09-07 18:10:10 | R4: 2023-09-09 03:49:38
A5: 4K Dash Cam Front Built-in WiFi, WANLIPO Dash Camera for Cars with 64GB SD Card App Control | B5: https://www.amazon.com/promocode/A1DX8GZASC5MLT | C5: B0CC8CHTTJ | D5: $99.99 | E5: $31.99 | F5: 68WHPID3 | G5: 68 | I5: Leave it on the Porch | J5: 查看链接 | K5: 63 | L5: 已完成 | M5: 查看帖子 | P5: 2023-09-07 15:24:49 | Q5: 2023-09-07 15:34:15 | R5: 2023-09-08 09:11:21
A6: 4K Dash Cam Front Built-in WiFi, WANLIPO Dash Camera for Cars with 64GB SD Card App Control | B6: https://www.amazon.com/promocode/A1DX8GZASC5MLT | C6: B0CC8CHTTJ | D6: $99.99 | E6: $31.99 | F6: 68WHPID3 | G6: 68 | I6: Nats daily deals and codes | J6: 查看链接 | K6: 32 | L6: 已取消/退款 | O6: 未入选 | P6: 2023-09-07 15:24:49 | Q6: 2023-09-07 18:13:47 | S6: 2023-09-13 15:39:13
A7: 4K Dash Cam Front Built-in WiFi, WANLIPO Dash Camera for Cars with 64GB SD Card App Control | B7: https://www.amazon.com/promocode/A1DX8GZASC5MLT | C7: B0CC8CHTTJ | D7: $99.99 | E7: $31.99 | F7: 68WHPID3 | G7: 68 | I7: Bomb Deals - Promo Codes - Coupons | J7: 查看链接 | K7: 32 | L7: 已完成 | M7: 查看帖子 | P7: 2023-09-07 15:24:49 | Q7: 2023-09-07 22:32:59 | R7: 2023-09-08 10:43:22
A8: 4K Dash Cam Front Built-in WiFi, WANLIPO Dash Camera for Cars with 64GB SD Card App Control | B8: https://www.amazon.com/promocode/A1DX8GZASC5MLT | C8: B0CC8CHTTJ | D8: $99.99 | E8: $31.99 | F8: 68WHPID3 | G8: 68 | I8: Oopsie Deals | J8: 查看链接 | K8: 49 | L8: 已完成 | N8: 查看图片 | P8: 2023-09-07 15:24:49 | Q8: 2023-09-07 15:27:44 | R8: 2023-09-08 09:53:51
A9: 4K Dash Cam Front Built-in WiFi, WANLIPO Dash Camera for Cars with 64GB SD Card App Control | B9: https://www.amazon.com/promocode/A1DX8GZASC5MLT | C9: B0CC8CHTTJ | D9: $99.99 | E9: $31.99 | F9: 68WHPID3 | G9: 68 | I9: Dysautomama Deals | J9: 查看链接 | K9: 24 | L9: 已完成 | M9: 查看帖子 | P9: 2023-09-07 15:24:49 | Q9: 2023-09-07 16:25:17 | R9: 2023-09-08 15:28:24
A10: 4K Dash Cam Front Built-in WiFi, WANLIPO Dash Camera for Cars with 64GB SD Card App Control | B10: https://www.amazon.com/promocode/A1DX8GZASC5MLT | C10: B0CC8CHTTJ | D10: $99.99 | E10: $31.99 | F10: 68WHPID3 | G10: 68 | I10: Gretchen's Adventures Deals | J10: 查看链接 | K10: 14 | L10: 已取消/退款 | O10: 未入选 | P10: 2023-09-07 15:24:49 | Q10: 2023-09-07 18:16:12 | S10: 2023-09-08 18:19:33
A11: 4K Dash Cam Front Built-in WiFi, WANLIPO Dash Camera for Cars with 64GB SD Card App Control | B11: https://www.amazon.com/promocode/A1DX8GZASC5MLT | C11: B0CC8CHTTJ | D11: $99.99 | E11: $31.99 | F11: 68WHPID3 | G11: 68 | I11: Ohana Farmhouse 🌺 Daily Deals & Steals | J11: 查看链接 | K11: 28 | L11: 已完成 | M11: 查看帖子 | P11: 2023-09-07 15:24:49 | Q11: 2023-09-07 16:18:35 | R11: 2023-09-08 23:27:38
A12: 4K Dash Cam Front Built-in WiFi, WANLIPO Dash Camera for Cars with 64GB SD Card App Control | B12: https://www.amazon.com/promocode/A6V41M33IJCOY | C12: - | D12: $99.99 | E12: $31.99 | F12: 685AXW4O | G12: 68 | I12: HarcarSisters - (Deals & Steals) | J12: 查看链接 | K12: 22 | L12: 已取消/退款 | O12: 管理员超时不回复 | P12: 2023-09-08 12:05:34 | S12: 2023-09-10 18:13:38
A13: 4K Dash Cam Front Built-in WiFi, WANLIPO Dash Camera for Cars with 64GB SD Card App Control | B13: https://www.amazon.com/promocode/A6V41M33IJCOY | C13: - | D13: $99.99 | E13: $31.99 | F13: 685AXW4O | G13: 68 | I13: Compras toxicas con la patrona | J13: 查看链接 | K13: 25 | L13: 已完成 | N13: 查看图片 | P13: 2023-09-08 12:05:34 | Q13: 2023-09-08 23:37:45 | R13: 2023-09-09 10:11:14
A14: 4K Dash Cam Front Built-in WiFi, WANLIPO Dash Camera for Cars with 64GB SD Card App Control | B14: https://www.amazon.com/promocode/A6V41M33IJCOY | C14: - | D14: $99.99 | E14: $31.99 | F14: 685AXW4O | G14: 68 | I14: Kristen's Deals and Discounts | J14: 查看链接 | K14: 17 | L14: 已取消/退款 | O14: 未入选 | P14: 2023-09-08 12:05:34 | Q14: 2023-09-08 18:20:51 | S14: 2023-09-09 12:12:40
A15: 4K Dash Cam Front Built-in WiFi, WANLIPO Dash Camera for Cars with 64GB SD Card App Control | B15: https://www.amazon.com/promocode/A6V41M33IJCOY | C15: - | D15: $99.99 | E15: $31.99 | F15: 685AXW4O | G15: 68 | I15: Sales-aholic.com Deals, Glitches, & Free Things | J15: 查看链接 | K15: 80 | L15: 已完成 | M15: 查看帖子 | P15: 2023-09-08 12:05:34 | Q15: 2023-09-08 14:15:56 | R15: 2023-09-09 07:14:41
A16: 4K Dash Cam Front Built-in WiFi, WANLIPO Dash Camera for Cars with 64GB SD Card App Control | B16: https://www.amazon.com/promocode/A6V41M33IJCOY | C16: - | D16: $99.99 | E16: $31.99 | F16: 685AXW4O | G16: 68 | I16: Jackie's Fun Finds | J16: 查看链接 | K16: 51 | L16: 已取消/退款 | O16: 未入选 | P16: 2023-09-08 12:05:34 | Q16: 2023-09-08 18:18:53 | S16: 2023-09-09 14:09:58
A17: 4K Dash Cam Front Built-in WiFi, WANLIPO Dash Camera for Cars with 64GB SD Card App Control | B17: https://www.amazon.com/promocode/A6V41M33IJCOY | C17: - | D17: $99.99 | E17: $31.99 | F17: 685AXW4O | G17: 68 | I17: Coupon with Nada | J17: 查看链接 | K17: 13 | L17: 已完成 | M17: 查看帖子 | P17: 2023-09-08 12:05:34 | Q17: 2023-09-08 19:25:02 | R17: 2023-09-11 09:06:26
A18: 4K Dash Cam Front Built-in WiFi, WANLIPO Dash Camera for Cars with 64GB SD Card App Control | B18: https://www.amazon.com/promocode/A6V41M33IJCOY | C18: - | D18: $99.99 | E18: $31.99 | F18: 685AXW4O | G18: 68 | I18: Thrifty Babes®: The Shop Society | J18: 查看链接 | K18: 30 | L18: 已取消/退款 | O18: 未入选 | P18: 2023-09-08 12:05:34 | Q18: 2023-09-08 12:49:48 | S18: 2023-09-12 22:29:32
A19: 4K Dash Cam Front Built-in WiFi, WANLIPO Dash Camera for Cars with 64GB SD Card App Control | B19: https://www.amazon.com/promocode/A6V41M33IJCOY | C19: - | D19: $99.99 | E19: $31.99 | F19: 685AXW4O | G19: 68 | I19: LaurenLovesDeals & more! | J19: 查看链接 | K19: 47 | L19: 已取消/退款 | O19: Reviews数量不足 | P19: 2023-09-08 12:05:34 | S19: 2023-09-08 13:09:33
A20: 4K Dash Cam Front Built-in WiFi, WANLIPO Dash Camera for Cars with 64GB SD Card App Control | B20: https://www.amazon.com/promocode/A6V41M33IJCOY | C20: - | D20: $99.99 | E20: $31.99 | F20: 685AXW4O | G20: 68 | I20: Amazing - Deals & Codes | J20: 查看链接 | K20: 15 | L20: 已取消/退款 | O20: 拼帖人要求退款 | P20: 2023-09-08 12:05:34 | Q20: 2023-09-08 19:24:03 | S20: 2023-09-13 20:13:33
A21: 4K Dash Cam Front Built-in WiFi, WANLIPO Dash Camera for Cars with 64GB SD Card App Control | B21: https://www.amazon.com/promocode/A6V41M33IJCOY | C21: - | D21: $99.99 | E21: $31.99 | F21: 685AXW4O | G21: 68 | I21: Bullseye🎯on the Bargain | J21: 查看链接 | K21: 47 | L21: 已完成 | M21: 查看帖子 | P21: 2023-09-08 12:05:34 | Q21: 2023-09-08 18:10:20 | R21: 2023-09-11 14:06:40
A22: 4K Dash Cam Front Built-in WiFi, WANLIPO Dash Camera for Cars with 64GB SD Card App Control | B22: https://www.amazon.com/promocode/A6V41M33IJCOY | C22: - | D22: $99.99 | E22: $31.99 | F22: 685AXW4O | G22: 68 | I22: KB's Deals™ | J22: 查看链接 | K22: 28 | L22: 已取消/退款 | O22: 未入选 | P22: 2023-09-08 12:05:34 | Q22: 2023-09-08 12:42:32 | S22: 2023-09-12 20:36:32
A23: 4K Dash Cam Front Built-in WiFi, WANLIPO Dash Camera for Cars with 64GB SD Card App Control | B23: https://www.amazon.com/promocode/A6V41M33IJCOY | C23: - | D23: $99.99 | E23: $31.99 | F23: 685AXW4O | G23: 68 | I23: 🌷simply sales with Alyssa & Sarah | J23: 查看链接 | K23: 39 | L23: 已完成 | M23: 查看帖子 | P23: 2023-09-08 12:05:34 | Q23: 2023-09-08 14:57:17 | R23: 2023-09-09 18:48:42
A24: 4K Dash Cam Front Built-in WiFi, WANLIPO Dash Camera for Cars with 64GB SD Card App Control | B24: https://www.amazon.com/promocode/A3KI4FHP7QJ2RZ | C24: B0CC8CHTTJ | D24: $99.99 | E24: $31.99 | F24: 68Z5D8VU | G24: 68 | I24: LaurenLovesDeals & more! | J24: 查看链接 | K24: 37 | L24: 已取消/退款 | O24: 未入选 | P24: 2023-09-09 11:16:31 | Q24: 2023-09-09 17:18:41 | S24: 2023-09-10 22:43:33
A25: 4K Dash Cam Front Built-in WiFi, WANLIPO Dash Camera for Cars with 64GB SD Card App Control | B25: https://www.amazon.com/promocode/A3KI4FHP7QJ2RZ | C25: B0CC8CHTTJ | D25: $99.99 | E25: $31.99 | F25: 68Z5D8VU | G25: 68 | I25: The Glitch Witch - A Snarky Deals Group | J25: 查看链接 | K25: 36 | L25: 已完成 | M25: 查看帖子 | P25: 2023-09-09 11:16:31 | Q25: 2023-09-09 18:11:16 | R25: 2023-09-09 23:58:34
A26: 4K Dash Cam Front Built-in WiFi, WANLIPO Dash Camera for Cars with 64GB SD Card App Control | B26: https://www.amazon.com/promocode/A3KI4FHP7QJ2RZ | C26: B0CC8CHTTJ | D26: $99.99 | E26: $31.99 | F26: 68Z5D8VU | G26: 68 | I26: Kristen's Deals and Discounts | J26: 查看链接 | K26: 17 | L26: 已取消/退款 | O26: 未入选 | P26: 2023-09-09 11:16:31 | Q26: 2023-09-09 18:10:39 | S26: 2023-09-12 12:32:38
A27: 4K Dash Cam Front Built-in WiFi, WANLIPO Dash Camera for Cars with 64GB SD Card App Control | B27: https://www.amazon.com/promocode/A3KI4FHP7QJ2RZ | C27: B0CC8CHTTJ | D27: $99.99 | E27: $31.99 | F27: 68Z5D8VU | G27: 68 | I27: HarcarSisters - (Deals & Steals) | J27: 查看链接 | K27: 28 | L27: 已取消/退款 | O27: 未入选 | P27: 2023-09-09 11:16:31 | Q27: 2023-09-09 14:42:00 | S27: 2023-09-13 20:05:36
A28: 4K Dash Cam Front Built-in WiFi, WANLIPO Dash Camera for Cars with 64GB SD Card App Control | B28: https://www.amazon.com/promocode/A3KI4FHP7QJ2RZ | C28: B0CC8CHTTJ | D28: $99.99 | E28: $31.99 | F28: 68Z5D8VU | G28: 68 | I28: Thrifty Babes®: The Shop Society | J28: 查看链接 | K28: 30 | L28: 已取消/退款 | O28: 未入选 | P28: 2023-09-09 11:16:31 | Q28: 2023-09-09 14:41:20 | S28: 2023-09-12 22:29:33
A29: 4K Dash Cam Front Built-in WiFi, WANLIPO Dash Camera for Cars with 64GB SD Card App Control | B29: https://www.amazon.com/promocode/A3KI4FHP7QJ2RZ | C29: B0CC8CHTTJ | D29: $99.99 | E29: $31.99 | F29: 68Z5D8VU | G29: 68 | I29: BUT It Was On Sale..💥💥 | J29: 查看链接 | K29: 77 | L29: 已取消/退款 | O29: 未入选 | P29: 2023-09-09 11:16:31 | Q29: 2023-09-09 18:06:35 | S29: 2023-09-10 20:05:36
A30: 4K Dash Cam Front Built-in WiFi, WANLIPO Dash Camera for Cars with 64GB SD Card App Control | B30: https://www.amazon.com/promocode/A3KI4FHP7QJ2RZ | C30: B0CC8CHTTJ | D30: $99.99 | E30: $31.99 | F30: 68Z5D8VU | G30: 68 | I30: Mommy & Me Deals | J30: 查看链接 | K30: 48 | L30: 已完成 | M30: 查看帖子 | P30: 2023-09-09 11:16:31 | Q30: 2023-09-09 17:19:45 | R30: 2023-09-11 22:55:21
A31: 4K Dash Cam Front Built-in WiFi, WANLIPO Dash Camera for Cars with 64GB SD Card App Control | B31: https://www.amazon.com/promocode/A3KI4FHP7QJ2RZ | C31: B0CC8CHTTJ | D31: $99.99 | E31: $31.99 | F31: 68Z5D8VU | G31: 68 | I31: Kouponing With Katie | J31: 查看链接 | K31: 28 | L31: 已完成 | M31: 查看帖子 | P31: 2023-09-09 11:16:31 | Q31: 2023-09-09 18:12:13 | R31: 2023-09-10 09:36:07
A32: 4K Dash Cam Front Built-in WiFi, WANLIPO Dash Camera for Cars with 64GB SD Card App Control | B32: https://www.amazon.com/promocode/A3KI4FHP7QJ2RZ | C32: B0CC8CHTTJ | D32: $99.99 | E32: $31.99 | F32: 68Z5D8VU | G32: 68 | I32: 🍑 Peachy Keen Deals and Steals | J32: 查看链接 | K32: 30 | L32: 已取消/退款 | O32: 未入选 | P32: 2023-09-09 11:16:31 | Q32: 2023-09-09 14:43:07 | S32: 2023-09-11 19:40:40
A33: 4K Dash Cam Front Built-in WiFi, WANLIPO Dash Camera for Cars with 64GB SD Card App Control | B33: https://www.amazon.com/promocode/A3KI4FHP7QJ2RZ | C33: B0CC8CHTTJ | D33: $99.99 | E33: $31.99 | F33: 68Z5D8VU | G33: 68 | I33: Savvy Money Saving Shopaholics Group | J33: 查看链接 | K33: 48 | L33: 进行中 | P33: 2023-09-09 11:16:31 | Q33: 2023-09-11 18:20:47
A34: 4K Dash Cam Front Built-in WiFi, WANLIPO Dash Camera for Cars with 64GB SD Card App Control | B34: https://www.amazon.com/promocode/A3KI4FHP7QJ2RZ | C34: B0CC8CHTTJ | D34: $99.99 | E34: $31.99 | F34: 68Z5D8VU | G34: 68 | I34: Crazy Discount Codes | J34: 查看链接 | K34: 26 | L34: 已完成 | M34: 查看帖子 | P34: 2023-09-09 11:16:31 | Q34: 2023-09-11 10:40:36 | R34: 2023-09-11 11:59:28

Sheet 西柚找词垃圾词
A1: 否定精准 | B1: 否定词组 | C1: 品牌词
A2: car screen | B2: monitor | C2: ring
A3: 4k monitor | B3: digital | C3: VIOFO
A4: digital dash | B4: real | C4: VANTRUE
A5: car wifi | B5: blackvue | C5: Thinkware
A6: screen for car | B6: laser | C6: Blackvue
A7: wifi for car | B7: jammer | C7: Garmin
A8: parking sensor | B8: echo | C8: 70mai
A9: real car | B9: auto | C9: NEXT BASE
A10: digital dashboard | B10: small | C10: REXING
A11: 4k monitors | B11: battery | C11: Blueskysea
A12: car monitor | B12: filler | C12: IIWEY
... A31: camera monitor | B31: front and inside | C31: Zhrmghg
A32: small dash cam | B32: front and back | C32: 360
A33: vehicle | B33: front and backup | C33: ABASK
A34: blue car | B34: pruveeo | C34: Amazon Renewed
A35: dash cam battery pack | B35: 3 channel | C35: AXIL
A36: sticky dash fix | B36: wifi for car | C36: Dongar Technologies
A37: memory saver for car battery | B37: luxi | C37: dosili
A38: wifi battery monitor | B38: ring | C38: FocuWay
A39: wifi password | B39: nexar | C39: Heaboli
A40: amazon auto | B40: link | C40: LAMTTO
A41: battery filler | B41: rove | C41: OBEST
A42: camas | B42: r2 4k | C42: QSAEHLS
A43: dash | B43: pruveeo | C43: QveeQ
A44: pruveeo 3 channel dash cam | B44: car front camera | C44: ROVE
... A72: front camera for car | B72: screen for car | C72: WonVon
A73: dash cam with 1080p dual cameras, fhd dvr 3.0 ips screen 170° wide angle g-sensor parking monitor lo | B73: wolfbox | C73: 360
A74: digital dash | B74: ddpai | C74: Abodost
A75: toguard dash cam | B75: front and back | C75: AIPLUGER
A76: dash cam no wires | B76: apexview | C76: AKKAHH
A77: 70mai | B77: solar | C77: AMORTEK
A78: dashcam front and rear camera wireless | B78: 3 channel | C78: Anumit
A79: desk for car | B79: red tiger | C79: Apexcam
A80: dash cam front and rear 4k | B80: car needs | C80: ARECORD
A81: minolta dash cam | B81: monitor | C81: ASTSH
A82: seicane 10.26 carplay dash camera | B82: car monitor | C82: ATOTO
A83: nexar dash cam front and rear | B83: battery powered | C83: Avaett
A84: dashcams for cars front and rear | B84: stuff for car | C84: AVISIGHT
A85: cooau dash cam | B85: thinkware | C85: BlackboxMyCar
... A91: apexview dash cam | B91: gopro | C91: Car and Driver
A92: 4k | B92: 360 | C92: Carpuride
A93: aukey dash cam | B93: roav | C93: ChargerCity
A94: solar dash cam | B94: car screen | C94: D.DA.D
A95: 3 channel dash cam | B95: bluetooth screen | C95: Digital Village
A96: red tiger dash cam | B96: cloud | C96: Dorman
A97: car needs | B97: screen | C97: Escort
A98: dashcam front and rear camera | B98: fitcamx | C98: E-SHOW TREE
A99: ring dash camera for cars | B99: speed | C99: EYETOO
A100: car monitor | B100: viofo | C100: Frvesroe
A101: stuff for car | B101: garmin | C101: Gebildet
A102: thinkware f70 | B102: car step | C102: Generic
A103: drive cam luxidrive | B103: mini 2 | C103: GILAYGROW
A104: viofo a229 pro | B104: apex view | C104: HUBANFLY
... A112: fitcamx | B112: parking | C112: MEKNIC
A113: dash cam with speed recording | B113: 57 | C113: Minolta
A114: viofo dash cam | B114: car gadgets | C114: Miofive
A115: garmin dashcam mini 2 | B115: car living | C115: Moplasz
A116: car step | B116: cobra sc 201 | C116: MSAFF
A117: apex view dash cam | B117: car stuff | C117: N\C
A118: dash cam with gps | B118: car emergency | C118: nezini
A119: dash cam viofo | B119: star | C119: NUNET
A120: ofertas | B120: truck | C120: OldShark
A121: rove r2 4k | B121: link | C121: Orgtoy
A122: apeman dash cam | B122: trucks | C122: PlayBetter
A123: parking sensors for cars | B123: car driving | C123: PORMIDO
A124: 360 degree dash cam | B124: car engine | C124: Street Guardian
A125: garmin dash cam 57 | B125: real cars | C125: SYLVANIA
... A141: auto camera dash cam front and rear | B141: car camera dash cam front | C141: ZWHT
A142: rove | B142: dash am
A143: dash cam gps | B143: sticky dash fix
A144: dash cam with gps and speed | B144: cars accessories
A145: dash cam battery pack | B145: monitor
A146: battery dash cam | B146: viofo a139 pro
A147: car auto accessories | B147: red tiger
A148: gps car | B148: front and rear 4k
A149: dadh cam | B149: 3 channel
A150: wifi card | B150: amazon renewed store
A151: car camera baby | B151: sd cars
A152: camaras para carros | B152: bodycam c
A153: garmin dash cam 47 | B153: prime deals
... A228: prime deals of the day clearance | B228: izeeker
A229: azdome m550
A230: car alarm
A231: warehouse sale clearance
A232: blue car
A233: car accessories men
A234: link click
A235: cami
A236: warehouse amazon warehouse deals
A237: dash cam ring
A238: wifi dash cam front and rear
A239: car screen
A240: dashcam front and rear

Sheet 发补货模型
A1: JP补货模型 | B1: SKU | C1: 可售月（发货值1.5） | D1: FBA库存 | E1: 未交订单 | F1: 工厂 | G1: 海外仓 | H1: 路上 | I1: 30天销量 | J1: 可售月（下单值2）
B2: D18 | C2: =(D2+F2+G2+H2)/I2 -> 0.7 | D2: 210 | E2: 500 | I2: 300 | J2: =(D2+E2+F2+G2+H2)/I2 -> 2.3666667
B3: D19 | C3: =(D3+F3+G3+H3)/I3 -> 0 | I3: 500 | J3: =(D3+E3+F3+G3+H3)/I3 -> 0
B4: D20 | C4: =(D4+F4+G4+H4)/I4 -> 0 | I4: 600 | J4: =(D4+E4+F4+G4+H4)/I4 -> 0
B5: D21 | C5: =(D5+F5+G5+H5)/I5 -> 0 | I5: 800 | J5: =(D5+E5+F5+G5+H5)/I5 -> 0
A9: US补货模型 | B9: SKU | C9: 可售月（发货值2） | D9: FBA库存 | E9: 未交订单 | F9: 工厂 | G9: 海外仓 | H9: 路上 | I9: 30天销量 | J9: 可售月（下单值2.5）
B10: D18 | C10: =(D10+F10+G10+H10)/I10 -> 0.7 | D10: 210 | E10: 500 | I10: 300 | J10: =(D10+E10+F10+G10+H10)/I10 -> 2.3666667
B11: D19 | C11: =(D11+F11+G11+H11)/I11 -> 0 | I11: 500 | J11: =(D11+E11+F11+G11+H11)/I11 -> 0
B12: D20 | C12: =(D12+F12+G12+H12)/I12 -> 0 | I12: 600 | J12: =(D12+E12+F12+G12+H12)/I12 -> 0
B13: D21 | C13: =(D13+F13+G13+H13)/I13 -> 0 | I13: 800 | J13: =(D13+E13+F13+G13+H13)/I13 -> 0
A15: 补货申请单 | K15: 采购填写
A16: 申请人 | B16: 申请日期 | C16: asin | D16: fnsku | E16: 数量 | F16: 补货原因 | G16: 上级审核 | H16: 盒标 | I16: 箱标 | J16: 物流方式 | K16: 预计到达日期
F17: 截图可售月份

Sheet 关键词追踪表
A1: 型号XXX | C1: 46095 | E1: 46096 | G1: 46097 | I1: 46098 | K1: 46099 | M1: 46100 | O1: 46101 | Q1: 46102 | S1: 46103 | U1: 46104 | W1: 46105 | Y1: 46106 | AA1: 46107 | AC1: 46108 | AE1: 46109 | AG1: 46110 | AI1: 46111 | AK1: 46112
A2: # | B2: Keyword | C2: AD | D2: ORGANIC | E2: AD | F2: ORGANIC | G2: AD | H2: ORGANIC | I2: AD | J2: ORGANIC | K2: AD | L2: ORGANIC | M2: AD | N2: ORGANIC | O2: AD | P2: ORGANIC | Q2: AD | R2: ORGANIC | S2: AD | T2: ORGANIC | U2: AD | V2: ORGANIC | W2: AD（广告位） | X2: ORGANIC（自然位） | Y2: AD（广告位） | Z2: ORGANIC（自然位） | AA2: AD（广告位） | AB2: ORGANIC（自然位） | AC2: AD（广告位） | AD2: ORGANIC（自然位） | AE2: AD（广告位） | AF2: ORGANIC（自然位） | AG2: AD（广告位） | AH2: ORGANIC（自然位） | AI2: AD（广告位） | AJ2: ORGANIC（自然位） | AK2: AD（广告位） | AL2: ORGANIC（自然位）
A3: 1
A4: 2
A5: 3
A6: 4
A7: 5
A8: 6
A9: 7
A10: 8
A11: 9
A12: 10
A14: 型号XXX | C14: 46095 | E14: 46096 | G14: 46097 | I14: 46098 | K14: 46099 | M14: 46100 | O14: 46101 | Q14: 46102 | S14: 46103 | U14: 46104 | W14: 46105 | Y14: 46106 | AA14: 46107 | AC14: 46108 | AE14: 46109 | AG14: 46110 | AI14: 46111 | AK14: 46112
A15: # | B15: Keyword | C15: AD | D15: ORGANIC | E15: AD | F15: ORGANIC | G15: AD | H15: ORGANIC | I15: AD | J15: ORGANIC | K15: AD | L15: ORGANIC | M15: AD | N15: ORGANIC | O15: AD | P15: ORGANIC | Q15: AD | R15: ORGANIC | S15: AD | T15: ORGANIC | U15: AD | V15: ORGANIC | W15: AD（广告位） | X15: ORGANIC（自然位） | Y15: AD（广告位） | Z15: ORGANIC（自然位） | AA15: AD（广告位） | AB15: ORGANIC（自然位） | AC15: AD（广告位） | AD15: ORGANIC（自然位） | AE15: AD（广告位） | AF15: ORGANIC（自然位） | AG15: AD（广告位） | AH15: ORGANIC（自然位） | AI15: AD（广告位） | AJ15: ORGANIC（自然位） | AK15: AD（广告位） | AL15: ORGANIC（自然位）
A16: 1
A17: 2
A18: 3
A19: 4
A20: 5
A21: 6
A22: 7
A23: 8
A24: 9
A25: 10
A27: 型号XXX | C27: 46059 | E27: 46060 | G27: 46061 | I27: 46062 | K27: 46063 | M27: 46064 | O27: 46065 | Q27: 46066 | S27: 46067 | U27: 46068 | W27: 46069 | Y27: 46070 | AA27: 46071 | AC27: 46072 | AE27: 46073 | AG27: 46074
A28: # | B28: Keyword | C28: AD | D28: ORGANIC | E28: AD | F28: ORGANIC | G28: AD | H28: ORGANIC | I28: AD | J28: ORGANIC | K28: AD | L28: ORGANIC | M28: AD | N28: ORGANIC | O28: AD | P28: ORGANIC | Q28: AD | R28: ORGANIC | S28: AD | T28: ORGANIC | U28: AD | V28: ORGANIC | W28: AD（广告位） | X28: ORGANIC（自然位） | Y28: AD（广告位） | Z28: ORGANIC（自然位） | AA28: AD（广告位） | AB28: ORGANIC（自然位） | AC28: AD（广告位） | AD28: ORGANIC（自然位） | AE28: AD（广告位） | AF28: ORGANIC（自然位） | AG28: AD（广告位） | AH28: ORGANIC（自然位） | AI28: AD（广告位） | AJ28: ORGANIC（自然位） | AK28: AD（广告位） | AL28: ORGANIC（自然位）
A29: 1
A30: 2
A31: 3
A32: 4
A33: 5
A34: 6
A35: 7
A36: 8
A37: 9
A38: 10

Sheet 每日竞品追踪
A1: 序号 | B1: pic | C1: asin | D1: 类目 | E1: 46093 | F1: 46094 | G1: 46095 | H1: 46096 | I1: 46097 | J1: 46098 | K1: 46099 | L1: 46100 | M1: 46101 | N1: 46102 | O1: 46103 | P1: 46104 | Q1: 46105 | R1: 46106 | S1: 46107 | T1: 46108 | U1: 46109 | V1: 46110 | W1: 46111 | X1: 46112
A2: 1 | D2: 大类
D3: 小类
D4: rating数
D5: review分
D6: 售价
D7: 运营观察与记录
D8: 原因分析
A10: 3 | D10: 大类
D11: 小类
D12: rating数
D13: review分
D14: 售价
D15: 运营观察与记录
D16: 原因分析
A18: 4 | D18: 大类
D19: 小类
D20: rating数
D21: review分
D22: 售价
D23: 运营观察与记录
D24: 原因分析
A26: 5 | D26: 大类
D27: 小类
D28: rating数
D29: review分
D30: 售价
D31: 运营观察与记录
D32: 原因分析
