Workbook

Sheet 阶段实际盈亏
A1: 时间 | B1: 实际 | C1: 价格 | D1: 站内 coupon | E1: 站内 code | F1: 站外 折扣 | G1: 站外 订单 | H1: 站内 自然单 | I1: 站内 广告单 | J1: 阶段 销售 订单 | K1: 时间 /天 | L1: 阶段广告费 （出1单广告单预估） | M1: 阶段站外费用 （5美金/单） | N1: 阶段订单 盈亏 | O1: 阶段亏损 /美金 | P1: 六阶段 总亏损 | R1: 阶段日均 订单 | S1: 阶段日均 广告订单 | T1: 阶段日均 自然订单 | U1: 新品 排行榜 | V1: 小类目 排名
A2: 9月7-9月12 | B2: 第一阶段 | C2: 99.99 | D2: 0.05 | E2: 0.5 | F2: 0.68 | G2: =SUM(#REF!) -> #REF! | H2: 0 | I2: 0 | J2: =SUM(G2:I2) -> #REF! | K2: 6 | L2: 0 | M2: =SUM(#REF!) -> #REF! | N2: =SUM(#REF!) -> #REF! | O2: =SUM(L2:N2) -> #REF!
A3: 9月13-9月21 | B3: 第二阶段 | C3: 79.99 | D3: 0.3 | E3: 0.2 | F3: 0.3 | G3: 81 | H3: 14 | I3: 0 | J3: =SUM(G3:I3) -> 95 | K3: 9 | L3: =SUM(#REF!) -> #REF! | M3: =SUM(#REF!) -> #REF! | N3: =SUM(#REF!) -> #REF! | O3: =SUM(L3:N3) -> #REF!
A4: 9月22-10月1 | B4: 第三阶段 | C4: 69.99 | D4: 0.3 | E4: 0.2 | F4: 0.25 | G4: 45 | H4: 60 | I4: 3 | J4: =SUM(G4:I4) -> 108 | K4: 10 | L4: =SUM(#REF!) -> #REF! | M4: =SUM(#REF!) -> #REF! | N4: =SUM(#REF!) -> #REF! | O4: =SUM(L4:N4) -> #REF!
A5: 10月2-10月11 | B5: 第四阶段 | C5: 69.99 | D5: 0.3 | E5: 0 | F5: 0.25
A6: 10月12-10月21 | B6: 第五阶段 | C6: 69.99 | D6: 0.3 | E6: 0 | F6: 0.25
A7: 10月22-10月31 | B7: 第六阶段 | C7: 69.99 | D7: 0.3 | E7: 0 | F7: 0
A9: 11月1-11月30 | B9: 十一月份 | C9: 69.99 | D9: 0.2 | E9: 0 | F9: 0
A10: 12月1-12月31 | B10: 十二月份 | C10: 69.99 | D10: 0.2 | E10: 0 | F10: 0
A11: 1月1-1月31 | B11: 一月份 | C11: 69.99 | D11: 0.2 | E11: 0 | F11: 0

Sheet 时间节点+发货表格
Q1: 出货时间表 | R1: 数量 | S1: 颜色 | T1: 占比 | U1: 实际数量 | V1: 1箱8个装
Q2: 45627 | R2: 150 | S2: 不锈钢色 | T2: 1 | U2: 150
S3: 种子链接
Q5: 45632 | R5: 640 | S5: 不锈钢色 | T5: 0.9 | U5: 544 | V5: 184
S6: 磨砂黑 | T6: 0.08 | U6: 64 | V6: 16
S7: 金色 | T7: 0.02 | U7: 32 | V7: 8
Q8: 45672 | R8: 4456 | S8: 不锈钢色 | T8: 0.9 | U8: 4048 | V8: 大货3696 | W8: 种子352
S9: 磨砂黑 | T9: 0.08 | U9: 328
S10: 金色 | T10: 0.02 | U10: 80
Q11: 45731 | R11: 3992 | S11: 不锈钢色 | T11: 0.9 | U11: 3600 | V11: 大货3344 | W11: 种子256
S12: 磨砂黑 | T12: 0.08 | U12: 320
S13: 金色 | T13: 0.02 | U13: 72
T17: 2月开始推广，考虑到过年+物流时效，11.19此次下采购单需要下3个月量，即2月+3月+4月的量 2月推广所需640个，何杰已下432个，现还需204个，银色184个，黑色16个，金色8个； 3月推广所需1536个，银色1376个，黑色128个，金色32个 4月推广所需2568个，银色2320个，黑色200个，金色48个 种子链接：2月150个何杰已下，3月+4月种子链接352个银色 银色共：184+1376+2320+352=4232个 黑色共：16+128+200=344个 金色共：8+32+48=88个
Q19: 银色 | R19: 黑色 | S19: 金色
Q20: 184+3696+352 | R20: 16+328 | S20: 8+80
Q21: 4232 | R21: 344 | S21: 88
Q36: 父ASIN
Q37: B0DJW7214X
Q38: MSKU | R38: SKU | S38: FNSKU | T38: 数量
Q39: AZ-US-SOEBIZ-CFSLT-BN-01 | R39: 420F0013BN1 | S39: X004GZH2GB | T39: 4232
Q40: AZ-US-SOEBIZ-CFSLT-BK-02 | R40: 420F0013BK1 | S40: X004GZH3BF | T40: 344
Q41: AZ-US-SOEBIZ-CFSLT-GD-03 | R41: 420F0013BG1 | S41: X004GZPR6D | T41: 88

Sheet 一、竞品对比&定位
A1: 竞品分析（厨房水龙头）
A2: 产品基础信息 | B2: 品牌 | C2: FORIOUS | D2: IBOFYY | E2: BASDEHEN | F2: HOTIS HOME | G2: Hiokay | H2: WEWE | I2: 供应商产品
B3: 图片
B4: 链接 | C4: https://www.amazon.com/dp/B0CPDHBCC6?th=1 | D4: https://www.amazon.com/Pull-Down-Commercial-Stainless-Suitable-Farmhouse/dp/B0BV2NVH1N/ref=cm_cr_arp_d_product_top?ie=UTF8&th=1 | E4: https://www.amazon.com/dp/B0CD25DR34?th=1 | F4: https://www.amazon.com/dp/B0CFX9CK5R?th=1 | G4: https://www.amazon.com/dp/B0BY8K99BW?th=1 | H4: https://www.amazon.com/WEWE-Brushed-Kitchen-Stainless-Faucets/dp/B01H3OMH7Y/ref=sr_1_5?th=1 | I4: /
B5: ASIN | C5: B0CPDHBCC6 | D5: B0BV2NVH1N | E5: B0CD25DR34 | F5: B0CFX9CK5R | G5: B0BY8K99BW | H5: B01H3OMH7Y | I5: /
B6: 卖家 | C6: FORIOUS-USA | D6: Hengzhi Sanitary Ware | E6: chenfeng Store | F6: Hotis home | G6: Hiokay Hardware | H6: MAYYAYA-Direct | I6: /
B7: 库存 | C7: 474 | D7: 限购10 | E7: 限购10 | F7: 1000+ | G7: 限购5 | H7: 限购20 | I7: /
B8: 价格 | C8: 54.99 | D8: 29.99 | E8: 29.99 | F8: 23.99 | G8: 25.99 | H8: 49.88 | I8: 建议定价25.99-35.99
B9: 优惠卷 | C9: 0.2 | D9: 0 | E9: 0 | F9: 0 | G9: 0 | H9: 0 | I9: 0.1
B10: keepa分析 | C10: 24.2.1开售价54.99，通过Vine Voice获得初始评论，大类22489 BS79，3.22断货 大类32912 BS121，5.11Coupon价格48.39-46.74 大类17046 BS52，7.16Coupon价格43.99 大类14607 BS41，8.14-28期间开了2长Deal 售价46.74 大类10440 BS30， -通过绿标获取评论+通过Coupon降价出单+秒杀促销冲排名+合理价格维持 | D10: 23.7.25开售价29.99，通过Vine Voice获得初始评论，23.8.4划线价39.99-29.99，大类8777，BS26 11.19做Deal 售价25.49 大类6827 BS22，1.19涨价31.99-29.99，大类1099，BS4 -通过绿标获取评论+通过小号进行测评+秒杀促销冲排名+合理价格维持 | E10: 23.9.18上架销售售价29.99，通过Vine Voice获得初始评论，11.7划线价59 购物车价格29-31.99-34.99-28.99-29.99 -通过绿标获取评论+通过划线价降价+广告 | F10: 23.10.11上架销售24.99（划线价39.99），通过合并变体获得评价 大类73187 BS249，24.3.8-16断货 大类156104 BS614，7.16-21Coupon价23.49 大类32714 BS100，8.29划线价32.99 售价23.98 大类37897 BS115 -通过和变体获取评论+通过划线价降价+广告 | G10: 23.5.20上架销售28.99，通过Vine Voice获得初始评论，8.4划现价后27.49 大类64896 BS198，10.20划线价25.99 大类23764 BS77，11.22Prime价格20.99 大类57707 BS167，11.22-12.22Prime价格20.99 大类114376 BS400，12.23Prime价格18.62 大类4933 BS18，24.1.5购物车价格21.69-31.99，5.19-6.25Prime价格27.19-26.87，大类10895 BS35，6.26购物车价格25.99 大类11266 BS37 -通过绿标获取评论+通过划线价降价+站内活动+广告 | H10: 24.1.23上架销售19.99，通过Vine Voice获得初始评论，3.12涨价23.99，大类93304 BS367 | I10: 前期绿标+划线价降价+Deal+广告
B11: 变体数 | C11: 8 | D11: 4 | E11: 3 | F11: 2 | G11: 2 | H11: 13 | I11: 13
B12: rating数（review） | C12: 168 | D12: 992 | E12: 751 | F12: 796 | G12: 318 | H12: 49697 | I12: 49674
B13: 星级 | C13: 4.7 | D13: 4.6 | E13: 4.6 | F13: 4.2 | G13: 4.2 | H13: 4.7 | I13: 4.7
B14: QA数 | C14: 0 | D14: 0 | E14: 0 | F14: 0 | G14: 0 | H14: 0 | I14: 0
B15: 上架时间 | C15: 2023-12-03(275天) | D15: 2023-02-06(575天) | E15: 2023-07-27(404天) | F15: 2023-08-16(385天) | G15: 2023-03-12(542天) | H15: 2016-06-14(3,009天) | I15: 2016-06-15(3,004天)
B16: 发货方式 | C16: FBA | D16: FBA | E16: FBA | F16: FBA | G16: FBA | H16: FBA | I16: FBA
B17: 类目、排名 | C17: #9,804 in Tools & Home Improvement #29 in Touch On Kitchen Sink Faucets | D17: #1,065 in Tools & Home Improvement #4 in Touch On Kitchen Sink Faucets | E17: #2,786 in Tools & Home Improvement #10 in Touch On Kitchen Sink Faucets | F17: #33,277 in Tools & Home Improvement #108 in Touch On Kitchen Sink Faucets | G17: #21,097 in Tools & Home Improvement #66 in Touch On Kitchen Sink Faucets | H17: #223 in Tools & Home Improvement #1 in Touch On Kitchen Sink Faucets | I17: #270 in Tools & Home Improvement #1 in Touch On Kitchen Sink Faucets
B18: A+/视频 | C18: 1video | D18: video | E18: video | F18: 1video | G18: 无 | I18: video
A19: 月销量及趋势 | B19: 月销量 | C19: 500+ | D19: 2000+ | E19: 1000+ | F19: 300+ | G19: 200 | H19: 6000 | I19: 5000+
B20: 月销售额 | C20: 49491 | D20: 121010 | E20: 76115 | F20: 9880 | G20: 13905 | H20: =H19*H8 -> 299280 | I20: 379000
B21: 月销量趋势图
A22: 功能 | B22: 应用场景 | C22: 酒吧、房车、厨房和户外 | D22: 厨房水槽 | E22: 厨房 | F22: 厨房 | G22: 厨房 | H22: 厨房 | I22: 酒吧、房车、厨房和户外
A23: 材质 | B23: 材质 | C23: 不锈钢 | D23: 不锈钢、黄铜 | E23: 不锈钢 | F23: 不锈钢 | G23: 不锈钢 | H23: 不锈钢 | I23: 不锈钢
A24: 配件 | B24: 配件 | C24: 喷头、台面板、皂液器、安装五金件、使用说明书 | D24: 喷头、冷热水供应软管、台面板、水龙头本体、使用说明书 | E24: 喷头、台面板、安装硬件、使用说明书 | F24: 水龙头 | G24: 水龙头 | H24: 厨房水龙头、台面板、安装配件、使用说明书、保修卡 | I24: 喷头、台面板、皂液器、安装五金件、使用说明书
A25: 使用方法 | B25: 安装使用方法 | C25: 台面安装 | D25: 台面安装 | E25: 台面安装 | F25: 台面安装 | G25: 嵌入式单孔台面安装 | H25: 单孔或三孔台面安装 | I25: 台面安装
A26: 产品参数 | B26: 1.手柄数量 | C26: 1 | D26: 1 | E26: 1 | F26: 1 | G26: 1 | H26: 1 | I26: 1
B27: 2.孔洞数 | C27: 1 | D27: 1 | E27: / | F27: 1 | G27: 1 | H27: 1 | I27: 1
B28: 3.把手类型 | C28: 杠杆式 | D28: 杠杆式 | E28: 杠杆式 | F28: 杠杆式 | G28: 旋钮 | H28: 杠杆式 | I28: 杠杆式
B29: 4.每分钟最大流量 | C29: 1.8加仑 | D29: / | E29: 1.75加仑 | F29: 1.8加仑 | G29: / | H29: 1.8加仑 | I29: 1.8加仑
B30: 5.阀门类型 | C30: 筒式阀芯阀门 | D30: / | E30: / | F30: / | G30: / | H30: 陶瓷阀芯 | I30: 陶瓷阀芯
B31: 6.出水口高度 | C31: 6.69inch | D31: 8inch | E31: 8inch | F31: 8.5inch | G31: 8.75inch | H31: 8.5inches | I31: 8.5inch
B32: 7.出水口伸展长度 | C32: 8.27inch | D32: 23inch | E32: / | F32: 8.54inch | G32: / | H32: 8.5inches | I32: 8.5inch
B33: 8.伸缩软管长度 | C33: 27.56inch | D33: 31inch | E33: 17inch | F33: 22inch | G33: 20.5inch | H33: 70.9inches | I33: 71inch
B34: 9.水管长度 | H34: 冷：33.5/热：31.5inches
B35: 10.安装孔尺寸 | H35: 1.5inches
B36: 11.特殊功能 | C36: 可拉出式喷头、可下拉式喷头、易于安装、360 度旋转、无铅 | D36: 可拉出式喷头、360 度旋转 | E36: 可拉出式喷头、可下拉式喷头、360 度旋转 | F36: 易于安装 | G36: 可抽出式喷头、易于安装、360 度旋转、双功能喷头。 | H36: 安静关闭，高弧度可下拉式 - 360° 旋转 | I36: 静音闭合
A37: 包装 | B37: 包装尺寸 | C37: 9.84×10.04 ×14.76inch （24.99 x 25.50 x 37.49cm） | D37: 3 x 10 x 15.3 inch（7.62x25.4x38.86cm） | E37: 10.24 x 10.24x 15.35incH (41.4X32.89X11.99CM) | F37: 8.5 x 7.8 x 14.5incH (21.59 x 19.81 x 36.83 CM) | G37: 7.85 x 10x 15.75 inches （19.94 x 25.40 x 40.01cm) | H37: 8.5x 10x 15.7inches （21.59 x 25.40 x 39.88 cm） | I37: 8.5x 10 x 15.7inch (21.59 x 25.40 x 39.88 cm)
B38: 重量 | C38: 3.98 Pounces(1.8KG) | D38: 4.11Pounds(1.86 kg) | E38: 4.09 Pounds(1.86 kg) | F38: 3.45 Pounds(1.56 kg) | G38: 3.06 Pounds(1.39KG) | H38: 1.84 Kilograms(1.84 kg) | I38: 1.84 Kilograms(1.84 kg)
B39: FBA fee | C39: 7.4 | D39: 7.56 | E39: 7.09 | F39: 7.32 | G39: 7.24 | H39: 7.32 | I39: 7.32
B40: 属于什么件 | C40: 大号大件 | D40: 大号标准尺寸 | E40: 大号大件 | F40: 大号大件 | G40: 大号标准尺寸 | H40: 大号标准尺寸 | I40: 大号大件
B41: 包装数量 | C41: ‎Sprayer, Deck Plate, Soap Dispenser, Installation Hardware, Instruction Manual | D41: ‎Sprayer, Hot and cold water supply hose, Deck Plate, Faucet body, Instruction Manual | E41: Sprayer, Deck Plate, Installation Hardware, Instruction Manual | F41: Faucet | G41: Faucet | H41: 厨房水龙头、台面板、安装配件、使用说明书、保修卡 | I41: 厨房水龙头、台面板、安装配件、使用说明书、保修卡。
A42: 标题 | B42: 标题(为挖掘主关键词) | C42: FORIOUS Black Kitchen Faucets with Soap Dispenser, Kitchen Faucet with Pull Down Sprayer, Commercial Stainless Steel Kitchen Sink Faucet, High Arc Single Hole Faucets for Kitchen Sink RV Bar Farmhouse | D42: Kitchen Faucet with Pull-Down Spray Single Handle high arc Commercial Stainless Steel Brushed Nickel Kitchen Sink Faucet with Deck Suitable for bar Laundry RV Farmhouse (Brushed Nickel) | E42: Single Handle High Arc Brushed Nickel Pull Out Kitchen Faucet, Single Level Stainless Steel Kitchen Sink Faucet with Pull Down Sprayer and 10 Inch Deck (Brushed Nickel) | F42: HOTIS Brushed Nickel Kitchen Sink Faucet, Kitchen Faucet with Pull Down Sprayer, Small RV Stainless Steel Single Handle Pull Out Faucet for Kitchen Sink with Deck Plate | G42: Stainless Steel 304 Kitchen Sink Faucet with Pull Down Spray Outdoor Kitchen Faucet Pull Out Extension Utility Farmhouse Faucets for Sink 1 Hole,Single Handle Rent Apartment Dorm Kitchen Faucet | H42: WEWE Single Handle High Arc Brushed Nickel Pull Out Kitchen Faucet,Single Level Stainless Steel Kitchen Sink Faucets with Pull Down Sprayer | I42: Stainless Steel 304 Kitchen Faucet with Pull Out Sprayer, retractable extension and modern design for 1-hole sink. Single handle. For indoor kitchen sink, RV bar and farmhouse.
A43: 关键词 | B43: 主流量词1 | C43: kitchen faucets | D43: kitchen faucets | E43: kitchen faucets | F43: kitchen faucet with pull down sprayer | G43: kitchen faucets | H43: kitchen faucets
B44: 主流量词2 | C44: kitchen faucet | D44: kitchen faucet | E44: kitchen sink | F44: sink faucet | G44: sink faucet | H44: kitchen faucet
B45: 主流量词3 | C45: kitchen sink faucet | D45: kitchen sink faucet | E45: kitchen faucet | F45: faucet for kitchen sink | G45: kitchen sink faucet | H45: kitchen sink faucet
B46: 主流量词4 | C46: black kitchen faucet | D46: kitchen faucet with pull down sprayer | E46: kitchen sink faucet | F46: faucet | G46: kitchen faucet with pull down sprayer | H46: kitchen faucet with pull down sprayer
A47: 五点卖点提炼 | C47: 你将获得什么？：福瑞斯厨房水龙头套装包括一个 14.76 英寸的水龙头和一个 11.83 盎司（350 毫升）的皂液器。这个多功能皂液器非常适合装洗手液、洗洁精、乳液等更多物品。这个套装旨在完美满足您的厨房需求。 无铅材质：我们的厨房水龙头由优质 SUS304 不锈钢制成，可长久使用，其陶瓷阀芯经过 500 万次以上测试，具有防漏性能。水流速度：每分钟 1.8 加仑，可节约用水 20%。 多功能厨房水龙头：福瑞斯高弧形下拉式喷头厨房水龙头有三种喷水模式 —— 水流模式、喷雾模式和暂停模式，可多功能使用。它包括一个 360° 旋转头和一个 18 英寸可伸缩软管，可完全覆盖水槽。 易于清洁，简化你的生活：我们的不锈钢抽拉式厨房水龙头具有五层纳米技术涂层，可防止指纹和污渍。只需用湿布简单擦拭即可保持其原始外观。 便于自行安装：无需专业协助，可在 15 分钟内轻松安装我们的水槽水龙头。它包括一个 10 英寸可拆卸台面板，适用于单孔或三孔厨房水槽，以及所有安装硬件，便于轻松设置。 全天候技术支持：这款符合美国 / 加拿大标准的水龙头适用于厨房水槽、洗衣房、休闲车和酒吧。请放心，我们的全面支持包括两年有限保修和专门的技术支持 —— 放心购买，随时联系。 | D47: 1. 经典外观：拉丝表面处理，高弧形单手柄设计，15.3 英寸的高度适合大多数水槽，360 度旋转，就像一朵花在厨房中绽放，满足你的用水需求。 2. 功能实用：23 英寸可拉伸的抽拉软管覆盖整个水槽，三种喷水模式（水流、喷雾、暂停）让清洁更容易。 3. 可靠品质：整个水龙头由 304 不锈钢制成，环保无铅，内部采用实心黄铜和陶瓷阀芯，通过 CEC 认证，品质高且耐用，没有渗漏烦恼。 4. 易于安装：我们的水龙头包括安装所需的所有配件，按照手册中的步骤很容易安装，无需水管工，15 分钟内即可独立完成安装。（不包括转接头，如果需要请联系我们）。 5. 卓越的售后服务：当你收到我们的产品时，无论在安装或使用过程中遇到任何问题，请通过亚马逊平台（产品购买按钮下方的商店名称）联系我们，我们的客服将在 12 小时内回复你的电子邮件并尽力帮助你解决问题。 | E47: 时尚设计：15.3 英寸的高度适合大多数厨房，17 英寸可抽出式喷头设计可适用于各种水槽，让你的用水更加轻松便捷。 多功能喷头：三种出水模式（水流、喷雾、暂停），水流模式用于注水，喷雾模式用于冲洗，暂停模式可在多任务模式下避免溅水，提供稳定的水压，喷头可拆除以便于清洁。 质量保证：高品质的防腐防锈表面处理可防止污垢附着在水龙头表面，日常使用中只需用抹布擦拭即可轻松清洁水龙头。 易于安装：我们的水龙头包括安装所需的所有配件，按照使用手册中的步骤很容易安装，15 分钟内即可独立完成安装，无需水管工。 优质售后服务：当你收到我们的产品后，无论在安装或使用过程中遇到任何问题，请通过电子邮件联系我们，我们的客服将在 12 小时内回复你的电子邮件并尽力帮助你解决问题。 | F47: 【下拉式风格】我们的商用厨房水龙头拥有时尚的设计，为您的厨房装饰增添一抹简约与清新。它能轻松搭配大多数水槽风格。灵活的出水口具有广泛的活动范围，让您可以将水准确地引向所需之处。 【易操作】单把手厨房水龙头可轻松控制水温和水流速度，高弧度 360 度旋转喷嘴提供全方位清洁通道，每次使用后喷嘴始终能缩回。 【多功能选择】我们的单把手厨房水龙头有三种喷水模式（水流、喷雾、暂停），水流模式用于注水，喷雾模式用于冲洗，暂停模式可在多任务模式下避免溅水。流量：每分钟 1.8 加仑，使清洁更轻松。 【尺寸】最大台面厚度：2.6 英寸，出水口伸出长度 8.5 英寸，总高度 14.5 英寸。 【易安装】我们的厨房水龙头适用于单孔或三孔，并且非常容易安装。（如果您有任何问题，请随时通过亚马逊给我们发电子邮件，我们将在 24 小时内回复您。） | G47: 实心芯厨房水龙头耐腐蚀、防锈，使用寿命长。食品级材质品质——优质 PEX 内软管和 SUS304 不锈钢主体厨房水龙头为您提供安全健康的生活。 银色厨房水龙头台面板可兼容单孔。重金属质感。易于保养——卓越的耐腐蚀和防锈表面处理可防止污垢粘在水龙头表面，日常使用中用布清洁水龙头就足够了。 高弧形弹簧厨房商用水龙头具有时尚的现代风格设计，它有可抽出的双功能喷头，可根据您的所有需求选择加气水流或强力喷雾，让您的厨房简洁清新。 厨房商用水龙头比郁金香厨房水龙头更美观，它与橱柜把手、门把或厨房配件搭配，易于匹配大多数装饰风格——复古、时尚、简约、国际、古典。 品牌 Hiokay 的实用厨房水龙头可用于各种场合：酒吧、锅炉房、传统洗衣房。镀铬水龙头的使用时间比缎面/拉丝镍/哑光黑色厨房水龙头更长。 在厨房装置中，它是必不可少的。看起来像饮用水水龙头的风格。长时间使用仍如新。大尺寸厨房水龙头，水压比小尺寸的更大。 单孔厨房水龙头易于安装，带有台面板的这款防漏厨房水龙头方便您安装，兼容单孔厨房水槽，您无需雇佣任何水管工即可完成安装。 | H47: 卖点总结： 时尚设计：郁金香造型简约清新，适配大多数水槽。 多功能出水：三种喷水模式（直流、喷雾、暂停），满足不同需求，避免水花飞溅，且符合 CEC 认证，流量为每分钟 1.8 加仑。 易于安装：软管和水管预先安装，无需水管工，30 分钟内可完成 DIY 安装。 易于操作：单把手控制水温和流量，高弧度 360 度旋转水龙头提供全方位清洗范围，喷头自动缩回。 易于维护：表面处理优质，防止污垢粘连，用布即可清洁。 | I47: /
A48: 差评分析 | C48: 1. 质量差 2. 安装困难： 3.水流问题：水压过高或水流不佳，有些人报告说喷雾器无法正常运行 4.泄露 | D48: 1.泄露 2.质量差 3.水流问题 4.安装难 5.设计不佳 | E48: 1.质量差 2.水流问题 3.安装困难 4.泄露 5.设计不好：水龙头太低 | F48: 1.水流问题 2.泄露 3.质量差 4.安装难 | G48: 1.质量差 2.泄露 3.安装难 4.说明书不够详细 | H48: 1.泄露21%：从喷雾器中泄漏，关闭后滴落，水管/水管连接处漏水 2.水流问题18%：水压过高或水流不佳，喷雾器无法正常工作，水压力下降*15， 3.安装困难15%：无法正确拧紧水龙头、安装软管困难， 4.质量差15%：水龙头移位，阀门声音嘈杂，塑料材料*4，开关损坏*1，喷洒模式水外喷*1，喷雾器坏*2，阀芯坏*4，缺少背板*2，热水开关不起作用*6，软管无法正常缩回*6，冷热水颠倒*1，水管比描述短＜3*1，软管短*2，颈部松动/脱落*7，淋雨喷头坏*2，掉漆*1，软管破裂*4，密封件损坏*1，螺母坏*2 5.开关问题8%：喷洒开关故障 软松动断裂，喷洒开光失灵*3，开关折断*4，损坏*3 | I48: /
A49: 评论分析 | C49: 好评 1.简单易用 2.高品质 3.安装方便 4.外观精美 设计时尚 未被满足的点 难用，更长的软管，更美观的设计 | D49: 好评 1.安装方便 2.精美外观 3.高品质 4.易于使用 5.物超所值 未被满足的点 耐用，更好的品质，减少飞溅，无泄漏 | E49: 好评 1.安装方便 2.高品质 3.外观精美 4.易于使用 5.良好的水压 未被满足的点 安装更简单，更长的软管，更好的质量 | F49: 好评 1.安装方便 2.高品质 3.精美外观 4.良好的水压 5.易于使用 未被满足的点 更好的质量，持久耐用，功能丰富，安装简单 | G49: 好评 1.安装方便 2.精美外观 3.高品质 4.好用 5.水压稳定 未被满足的点 难用，更高的水压，寿命更长，设计更好看 | H49: 好评 1.安装方便32%：安装过程简单，没有泄漏或问题。 2.外观精美25%：很好看 3.高品质16%：金属结构看起来很有质感，质量很好 4.易于使用13%：自由悬挂式喷雾器和 Magnatite 对接装置使水龙头易于操作和使用 5.物超所值5%：物美价廉，很划算 未被满足的点 1.更好的质量40%：使用寿命太短 2.改进设计16%：希望安装起来更方便，更好的整体设计和改进喷淋功能 3.更长的软管12%：更长的软管，它可以在水槽区域实现更好的伸展范围和更大的灵活性。更长的软管也使其更容易连接到标准管道。 4.安装更简单12% | I49: /
A50: QA汇总
A51: 竞品分析总结：
C52: 1、所有的竞品基本上都是FBA发货，且页面优化完整，都有A+页面/视频；
C53: 2、款式和颜色，以黑色为主，银色为主；
C54: 3、产品的评分均4.4分以上，多数差评由于质量差，安装困难，泄露，水压不理想等问题导致；
C55: 4、产品材质多以不锈钢为主；
C56: 5、产品重量集中在3-4Pounds，盒子的边长影响尺寸分段，FBAfee基本7-7.6左右，售价20-40美金以上居多 部分品牌100美金以上（可考虑29.99美金入场）
C57: 6、目前该类型产品市场差异化多样，买家关注点是颜色，外观设计，喷头长度，配件等方面
C58: 7、产品的主要卖点有：①拉出式喷头，喷头软管长度30inch、②多功能喷头（水流、喷雾、暂停）、③颜色：黑色，撞色设计、④外观设计：欧式复古，简约现代、⑤感应水流开关、⑥材质：304不锈钢，无铅
C59: 8、产品主要的差评点有：①不能正常连接、②说明书不清晰、③不聚焦、④画质不清晰、⑤管道内深处无法看清
C60: 9、产品主要的客问有：①质量不好，漏水，寿命短、②安装困难、③水流水压不够、④外观不佳：不美观，太矮

Sheet 流量拆解
A1: 图片 | B1: 品牌 | C1: ASIN | D1: 售价 | E1: 优惠劵 | F1: 月销 | G1: 日销目标 | H1: 子体月销 | I1: 月销售额 | J1: 上架时间 | K1: 星级 | L1: 评论 | M1: 变体 | N1: 总收录 | O1: 自然 | P1: 广告 | Q1: 推荐 | R1: 大类 | S1: 小节点 | T1: 对手流量结构 | U1: 分析1 | V1: 反查流量词 | W1: 分析2 | X1: 时光机查运营打法 | Y1: 分析3 | Z1: 广告透视仪查广告架构 | AA1: 分析4 | AB1: 广告透视仪查广告组 | AC1: 分析5
B2: FORIOUS | C2: B0CPDHBCC6 | D2: 54.99 | E2: 0.2 | F2: 949 | G2: 23.333333 | H2: 500 | I2: 52570 | K2: 4.6 | L2: 106 | M2: 8 | N2: 502 | O2: 439 | P2: 164 | Q2: 42 | R2: #9,132 in Tools & Home Improvement | S2: #25 in Touch On Kitchen Sink Faucets | U2: 黑色款流量占比94%，银色款4%，黑色为主推款 | W2: 流量结构占比 1.自然流量：51.77% 2.推荐流量：41.04% 3.广告流量：7.19% 前十流量量词占比60%，主打二级精准词，以场景词和属性词为主“厨房，水槽，带喷头/皂液器，水龙头” 结论：前期以二级三级精准词为主 | Y2: 历史广告流量走势 2月29% 3月13% 4月8% 5月9% 6月6.21% 7月8% 8月7% 8月9% 从走势看出付费流量随着排名提升比重在逐步降低，整体占比8-10% | AA2: 共计有 33 个SP广告活动、130 个投放小组，主投精准+定向 前期可以以SP广告为主，主投精准和定向，以二三级精准场景词和属性词为主 | AC2: SP广告总共有31个广告活动、66个投放小组 小组1：1*高转化词+1*产品 小组2：3-15*个精准二三级词+产品 广告词类型：场景词，属性词，品牌词 结论：主投SP广告，以二三级精准词，场景词，属性词，品牌词为主，多组投放
B3: BASDEHEN | C3: B0CD25DR34 | D3: 29.99 | E3: 0.5 | F3: 2511 | G3: 40 | H3: 1000 | I3: 75305 | K3: 4.6 | L3: 293 | M3: 3 | N3: 432 | O3: 409 | P3: 52 | Q3: 1 | R3: #2,996 in Tools & Home Improvement | S3: #9 in Touch On Kitchen Sink Faucets | U3: 银色款流量占比74%，金色款26%，银色为主推款 | W3: 流量结构占比 1.自然流量：87.5% 2.推荐流量：10.75% 3.广告流量：1.75% 前十流量量词占比70%，主打二级三级精准词，以场景词和属性词为主“厨房，水槽，带喷头/皂液器，水龙头”，也有少量一级词“faucet” 结论：以二级精准词为主 | Y3: 历史广告流量走势 集中在0.38-3.14%，平均3%，走势比较稳定 因为排名比较靠前，付费流量占比较低，占整体3%左右 | AA3: 共计有 5 个SP广告活动、5 个投放小组，主投SP精准 排名上BS，关键词收录较高的情况下可以下调广告，少量投放SP精准广告 | AC3: SP广告总共有5个广告活动、5个投放小组 小组1：3-15*个精准二三级词+1*产品 广告词类型：场景词，属性词 结论：主投SP广告，以二三级精准词，场景词，属性词，品牌词为主，多组投放
B4: BASDEHEN | C4: B0CD25DR34 | D4: 29.99 | E4: 0.5 | F4: 2511 | G4: 80 | H4: 1000 | I4: 75305 | K4: 4.6 | L4: 293 | M4: 3 | N4: 432 | O4: 409 | P4: 52 | Q4: 1 | R4: #2,996 in Tools & Home Improvement | S4: #9 in Touch On Kitchen Sink Faucets
B5: IBOFYY | C5: B0BV2NVH1N | D5: 29.99 | E5: 0 | F5: 4300 | G5: 100 | H5: 3000 | I5: 127218 | K5: 4.6 | L5: 400 | M5: 4 | N5: 470 | O5: 469 | P5: 10 | Q5: 0 | R5: #2,571 in Tools & Home Improvement | S5: #8 in Touch On Kitchen Sink Faucets | U5: 银色款流量占比95%，黑色款5%，银色为主推款 | W5: 流量结构占比 1.自然流量：79.36% 2.推荐流量：20.46% 3.广告流量：0.18% 前十流量量词占比90%，前五占80%，主打二级精准词，以场景词为主“厨房，水槽，” 结论：以1级和2级别精准词为主 | Y5: 历史广告流量走势 集中在0.28-0.36%，平均0.3%左右，走势比较稳定 因为排名比较靠前，所以付费流量占比较低，占整体0.3%左右 | AA5: 共计有 7 个SP广告活动、8 个投放小组，主投SP精准 排名上BS，关键词收录较高的情况下可以下调广告，少量投放SP精准广告 | AC5: SP广告总共有7个广告活动、7个投放小组 小组1：1*高转化词+1*产品 小组2：15-20*精准二三级词+1*产品 广告词类型：场景词，属性词 结论：主投SP广告，以二三级精准词，场景词，属性词，品牌词为主，多组投放
B6: IBOFYY | C6: B0BV2NVH1N | D6: 29.99 | E6: 0 | F6: 4300 | G6: 150 | H6: 3000 | I6: 127218 | K6: 4.6 | L6: 400 | M6: 4 | N6: 470 | O6: 469 | P6: 10 | Q6: 0 | R6: #2,571 in Tools & Home Improvement | S6: #8 in Touch On Kitchen Sink Faucets
B7: IBOFYY | C7: B0BV2NVH1N | D7: 29.99 | E7: 0 | F7: 4300 | G7: 150 | H7: 3000 | I7: 127218 | K7: 4.6 | L7: 400 | M7: 4 | N7: 470 | O7: 469 | P7: 10 | Q7: 0 | R7: #2,571 in Tools & Home Improvement | S7: #8 in Touch On Kitchen Sink Faucets

Sheet 竞品爆发力
A1: 项目 | B1: ASIN | C1: LD | D1: BD | E1: 会员日 | F1: 秋季会员日 | G1: 黑五（11.17） | H1: 网一（11.20） | I1: 圣诞节
A2: =_xlfn.DISPIMG("ID_BCC32FEA360E445B9C349589D07816E1",1) -> =DISPIMG("ID_BCC32FEA360E445B9C349589D07816E1",1) | B2: B0BV2NVH1N | C2: / | D2: / | E2: 会员两天平均199单/天，会员日前一周平均日销为68单，翻倍数为199/68=2.9倍 | F2: 秋促两天平均单 78/天，秋促前一周平均日销为44单，78/44=1.8倍 | G2: 黑五出单45/天，黑五前一周平均日销为45单，无翻倍 大类10000名，小类30名 | H2: 网一出单45/天，网一前一周平均日销为45单，无翻倍 黑五网一（11.17-11.27）共出：505单 | I2: 圣诞节出单29/天，圣诞节前一周平均日销为47单，圣诞节销量差
C3: 无LD | D3: 5月BD,136单/天，136/73=1.8倍
C4: 无LD | D4: 7月BD,121单/天，121/65=1.8倍
C5: / | D5: /
C6: / | D6: /
C7: / | D7: /
C8: 几乎每个月BD一次，1次LD
A9: =_xlfn.DISPIMG("ID_26D443FD906C4072AFAB43A781D66430",1) -> =DISPIMG("ID_26D443FD906C4072AFAB43A781D66430",1) | B9: B0CD25DR34 | C9: 无LD | D9: 5月BD,165单/天，165/103=1.6倍 | E9: 会员两天平均578单/天，会员日前一周平均日销为42单，翻倍数为578/42=13.7倍 | F9: 秋促两天平均单 89/天，秋促前一周平均日销为74单，89/74=1.2倍 | G9: 黑五出单75/天，黑五前一周平均日销为58单，翻倍数为75/58=1.3倍 大类5244名，小类20名 | H9: 网一出单75/天，网一前一周平均日销为58单，翻倍数为75/58=1.3倍 黑五网一（11.17-11.27）共出：831单 | I9: 圣诞节出单23/天，圣诞节前一周平均日销为44单，圣诞节销量差
C10: 无LD | D10: 6月BD,121单/天，121/57=2.1倍
C11: 无LD | D11: 7月BD,216单/天，216/123=1.8倍
C12: 无LD | D12: 无BD
C13: 无LD | D13: 无BD
C14: 无LD | D14: 无BD
C15: /
A16: =_xlfn.DISPIMG("ID_A9B25EA367114AC8BFB6C92ACF39AE30",1) -> =DISPIMG("ID_A9B25EA367114AC8BFB6C92ACF39AE30",1) | B16: B0CPDHBCC6 | C16: 8.14-LD-37/33=1.1倍 | D16: 6月BD,121单/天，121/57=2.1倍 | E16: 会员两天平均60单/天，会员日前一周平均日销为21单，翻倍数为60/21=2.8倍 | F16: 秋促两天平均单 97/天，秋促前一周平均日销为39单，97/39=2.5倍 | G16: / | H16: / | I16: /
C17: 8.29-LD-37/30=1.2倍 | D17: 10月BD,216单/天，216/123=1.8倍
C18: 9.26-LD-53/36=1.5倍 | D18: /
C19: / | D19: /
C20: / | D20: /
C21: / | D21: /
C22: /
C23: B0CD25DR34 | D23: B0C6JSW8PF
C24: B0CPDHBCC6 | D24: B0CN362S8M
A25: 站点 | B25: 时间 | C25: ASIN | D25: 日销量 | F25: 站点 | G25: 时间 | H25: ASIN | I25: 日销量 | N25: 站点 | O25: 时间 | P25: ASIN | Q25: 日销量
A26: US | B26: 2024/11/05 | C26: B0BV2NVH1N | D26: 106 | F26: US | G26: 2024/11/05 | H26: B0CD25DR34 | I26: 49 | N26: US | O26: 2024/11/05 | P26: B0CPDHBCC6 | Q26: 37
A27: US | B27: 2024/11/04 | C27: B0BV2NVH1N | D27: 149 | F27: US | G27: 2024/11/04 | H27: B0CD25DR34 | I27: 46 | N27: US | O27: 2024/11/04 | P27: B0CPDHBCC6 | Q27: 38
A28: US | B28: 2024/11/03 | C28: B0BV2NVH1N | D28: 131 | F28: US | G28: 2024/11/03 | H28: B0CD25DR34 | I28: 48 | N28: US | O28: 2024/11/03 | P28: B0CPDHBCC6 | Q28: 40
A29: US | B29: 2024/11/02 | C29: B0BV2NVH1N | D29: 111 | F29: US | G29: 2024/11/02 | H29: B0CD25DR34 | I29: 51 | N29: US | O29: 2024/11/02 | P29: B0CPDHBCC6 | Q29: 44
A30: US | B30: 2024/11/01 | C30: B0BV2NVH1N | D30: 95 | F30: US | G30: 2024/11/01 | H30: B0CD25DR34 | I30: 49 | N30: US | O30: 2024/11/01 | P30: B0CPDHBCC6 | Q30: 43
A31: US | B31: 2024/10/31 | C31: B0BV2NVH1N | D31: 76 | F31: US | G31: 2024/10/31 | H31: B0CD25DR34 | I31: 48 | N31: US | O31: 2024/10/31 | P31: B0CPDHBCC6 | Q31: 45
A32: US | B32: 2024/10/30 | C32: B0BV2NVH1N | D32: 73 | F32: US | G32: 2024/10/30 | H32: B0CD25DR34 | I32: 45 | N32: US | O32: 2024/10/30 | P32: B0CPDHBCC6 | Q32: 44
A33: US | B33: 2024/10/29 | C33: B0BV2NVH1N | D33: 62 | F33: US | G33: 2024/10/29 | H33: B0CD25DR34 | I33: 45 | N33: US | O33: 2024/10/29 | P33: B0CPDHBCC6 | Q33: 51
A34: US | B34: 2024/10/28 | C34: B0BV2NVH1N | D34: 57 | F34: US | G34: 2024/10/28 | H34: B0CD25DR34 | I34: 55 | N34: US | O34: 2024/10/28 | P34: B0CPDHBCC6 | Q34: 57 | R34: BD
A35: US | B35: 2024/10/27 | C35: B0BV2NVH1N | D35: 62 | F35: US | G35: 2024/10/27 | H35: B0CD25DR34 | I35: 60 | N35: US | O35: 2024/10/27 | P35: B0CPDHBCC6 | Q35: 63 | R35: BD
A36: US | B36: 2024/10/26 | C36: B0BV2NVH1N | D36: 50 | F36: US | G36: 2024/10/26 | H36: B0CD25DR34 | I36: 48 | N36: US | O36: 2024/10/26 | P36: B0CPDHBCC6 | Q36: 43 | R36: BD
A37: US | B37: 2024/10/25 | C37: B0BV2NVH1N | D37: 55 | F37: US | G37: 2024/10/25 | H37: B0CD25DR34 | I37: 46 | N37: US | O37: 2024/10/25 | P37: B0CPDHBCC6 | Q37: 53 | R37: BD
A38: US | B38: 2024/10/24 | C38: B0BV2NVH1N | D38: 60 | F38: US | G38: 2024/10/24 | H38: B0CD25DR34 | I38: 53 | N38: US | O38: 2024/10/24 | P38: B0CPDHBCC6 | Q38: 53 | R38: BD
A39: US | B39: 2024/10/23 | C39: B0BV2NVH1N | D39: 53 | F39: US | G39: 2024/10/23 | H39: B0CD25DR34 | I39: 57 | N39: US | O39: 2024/10/23 | P39: B0CPDHBCC6 | Q39: 45 | R39: BD
A40: US | B40: 2024/10/22 | C40: B0BV2NVH1N | D40: 62 | F40: US | G40: 2024/10/22 | H40: B0CD25DR34 | I40: 77 | N40: US | O40: 2024/10/22 | P40: B0CPDHBCC6 | Q40: 59 | R40: BD
A41: US | B41: 2024/10/21 | C41: B0BV2NVH1N | D41: 58 | F41: US | G41: 2024/10/21 | H41: B0CD25DR34 | I41: 67 | J41: BD | N41: US | O41: 2024/10/21 | P41: B0CPDHBCC6 | Q41: 57 | R41: BD
A42: US | B42: 2024/10/20 | C42: B0BV2NVH1N | D42: 60 | F42: US | G42: 2024/10/20 | H42: B0CD25DR34 | I42: 96 | J42: BD | N42: US | O42: 2024/10/20 | P42: B0CPDHBCC6 | Q42: 39
A43: US | B43: 2024/10/19 | C43: B0BV2NVH1N | D43: 40 | F43: US | G43: 2024/10/19 | H43: B0CD25DR34 | I43: 70 | J43: BD | N43: US | O43: 2024/10/19 | P43: B0CPDHBCC6 | Q43: 29
A44: US | B44: 2024/10/18 | C44: B0BV2NVH1N | D44: 36 | F44: US | G44: 2024/10/18 | H44: B0CD25DR34 | I44: 80 | J44: BD | N44: US | O44: 2024/10/18 | P44: B0CPDHBCC6 | Q44: 33
A45: US | B45: 2024/10/17 | C45: B0BV2NVH1N | D45: 53 | F45: US | G45: 2024/10/17 | H45: B0CD25DR34 | I45: 97 | J45: BD | N45: US | O45: 2024/10/17 | P45: B0CPDHBCC6 | Q45: 42
A46: US | B46: 2024/10/16 | C46: B0BV2NVH1N | D46: 47 | F46: US | G46: 2024/10/16 | H46: B0CD25DR34 | I46: 72 | J46: BD | N46: US | O46: 2024/10/16 | P46: B0CPDHBCC6 | Q46: 32
A47: US | B47: 2024/10/15 | C47: B0BV2NVH1N | D47: 52 | F47: US | G47: 2024/10/15 | H47: B0CD25DR34 | I47: 71 | J47: BD | N47: US | O47: 2024/10/15 | P47: B0CPDHBCC6 | Q47: 44
A48: US | B48: 2024/10/14 | C48: B0BV2NVH1N | D48: 51 | F48: US | G48: 2024/10/14 | H48: B0CD25DR34 | I48: 68 | J48: BD | N48: US | O48: 2024/10/14 | P48: B0CPDHBCC6 | Q48: 37
A49: US | B49: 2024/10/13 | C49: B0BV2NVH1N | D49: 53 | F49: US | G49: 2024/10/13 | H49: B0CD25DR34 | I49: 43 | N49: US | O49: 2024/10/13 | P49: B0CPDHBCC6 | Q49: 38
A50: US | B50: 2024/10/12 | C50: B0BV2NVH1N | D50: 59 | F50: US | G50: 2024/10/12 | H50: B0CD25DR34 | I50: 46 | N50: US | O50: 2024/10/12 | P50: B0CPDHBCC6 | Q50: 37
A51: US | B51: 2024/10/11 | C51: B0BV2NVH1N | D51: 47 | F51: US | G51: 2024/10/11 | H51: B0CD25DR34 | I51: 44 | N51: US | O51: 2024/10/11 | P51: B0CPDHBCC6 | Q51: 40
A52: US | B52: 2024/10/10 | C52: B0BV2NVH1N | D52: 42 | F52: US | G52: 2024/10/10 | H52: B0CD25DR34 | I52: 40 | N52: US | O52: 2024/10/10 | P52: B0CPDHBCC6 | Q52: 42
A53: US | B53: 2024/10/09 | C53: B0BV2NVH1N | D53: 86 | E53: 秋季会员日 | F53: US | G53: 2024/10/09 | H53: B0CD25DR34 | I53: 79 | J53: 秋季会员日 | N53: US | O53: 2024/10/09 | P53: B0CPDHBCC6 | Q53: 100 | R53: 秋季会员日
A54: US | B54: 2024/10/08 | C54: B0BV2NVH1N | D54: 71 | E54: 秋季会员日 | F54: US | G54: 2024/10/08 | H54: B0CD25DR34 | I54: 99 | J54: 秋季会员日 | N54: US | O54: 2024/10/08 | P54: B0CPDHBCC6 | Q54: 94 | R54: 秋季会员日
A55: US | B55: 2024/10/07 | C55: B0BV2NVH1N | D55: 37 | F55: US | G55: 2024/10/07 | H55: B0CD25DR34 | I55: 54 | N55: US | O55: 2024/10/07 | P55: B0CPDHBCC6 | Q55: 37
A56: US | B56: 2024/10/06 | C56: B0BV2NVH1N | D56: 34 | F56: US | G56: 2024/10/06 | H56: B0CD25DR34 | I56: 54 | N56: US | O56: 2024/10/06 | P56: B0CPDHBCC6 | Q56: 37
A57: US | B57: 2024/10/05 | C57: B0BV2NVH1N | D57: 40 | F57: US | G57: 2024/10/05 | H57: B0CD25DR34 | I57: 79 | N57: US | O57: 2024/10/05 | P57: B0CPDHBCC6 | Q57: 34
A58: US | B58: 2024/10/04 | C58: B0BV2NVH1N | D58: 42 | F58: US | G58: 2024/10/04 | H58: B0CD25DR34 | I58: 78 | N58: US | O58: 2024/10/04 | P58: B0CPDHBCC6 | Q58: 40
A59: US | B59: 2024/10/03 | C59: B0BV2NVH1N | D59: 49 | F59: US | G59: 2024/10/03 | H59: B0CD25DR34 | I59: 82 | N59: US | O59: 2024/10/03 | P59: B0CPDHBCC6 | Q59: 46
A60: US | B60: 2024/10/02 | C60: B0BV2NVH1N | D60: 53 | F60: US | G60: 2024/10/02 | H60: B0CD25DR34 | I60: 85 | N60: US | O60: 2024/10/02 | P60: B0CPDHBCC6 | Q60: 43
A61: US | B61: 2024/10/01 | C61: B0BV2NVH1N | D61: 54 | F61: US | G61: 2024/10/01 | H61: B0CD25DR34 | I61: 88 | N61: US | O61: 2024/10/01 | P61: B0CPDHBCC6 | Q61: 39
A62: US | B62: 2024/09/30 | C62: B0BV2NVH1N | D62: 57 | F62: US | G62: 2024/09/30 | H62: B0CD25DR34 | I62: 91 | N62: US | O62: 2024/09/30 | P62: B0CPDHBCC6 | Q62: 42
A63: US | B63: 2024/09/29 | C63: B0BV2NVH1N | D63: 52 | F63: US | G63: 2024/09/29 | H63: B0CD25DR34 | I63: 106 | N63: US | O63: 2024/09/29 | P63: B0CPDHBCC6 | Q63: 33
A64: US | B64: 2024/09/28 | C64: B0BV2NVH1N | D64: 55 | F64: US | G64: 2024/09/28 | H64: B0CD25DR34 | I64: 99 | N64: US | O64: 2024/09/28 | P64: B0CPDHBCC6 | Q64: 27
A65: US | B65: 2024/09/27 | C65: B0BV2NVH1N | D65: 50 | F65: US | G65: 2024/09/27 | H65: B0CD25DR34 | I65: 82 | N65: US | O65: 2024/09/27 | P65: B0CPDHBCC6 | Q65: 25
A66: US | B66: 2024/09/26 | C66: B0BV2NVH1N | D66: 53 | F66: US | G66: 2024/09/26 | H66: B0CD25DR34 | I66: 87 | N66: US | O66: 2024/09/26 | P66: B0CPDHBCC6 | Q66: 29
A67: US | B67: 2024/09/25 | C67: B0BV2NVH1N | D67: 64 | F67: US | G67: 2024/09/25 | H67: B0CD25DR34 | I67: 107 | N67: US | O67: 2024/09/25 | P67: B0CPDHBCC6 | Q67: 34 | R67: LD
A68: US | B68: 2024/09/24 | C68: B0BV2NVH1N | D68: 84 | F68: US | G68: 2024/09/24 | H68: B0CD25DR34 | I68: 138 | N68: US | O68: 2024/09/24 | P68: B0CPDHBCC6 | Q68: 37
A69: US | B69: 2024/09/23 | C69: B0BV2NVH1N | D69: 80 | F69: US | G69: 2024/09/23 | H69: B0CD25DR34 | I69: 158 | N69: US | O69: 2024/09/23 | P69: B0CPDHBCC6 | Q69: 34
A70: US | B70: 2024/09/22 | C70: B0BV2NVH1N | D70: 74 | F70: US | G70: 2024/09/22 | H70: B0CD25DR34 | I70: 165 | N70: US | O70: 2024/09/22 | P70: B0CPDHBCC6 | Q70: 33
A71: US | B71: 2024/09/21 | C71: B0BV2NVH1N | D71: 64 | F71: US | G71: 2024/09/21 | H71: B0CD25DR34 | I71: 135 | N71: US | O71: 2024/09/21 | P71: B0CPDHBCC6 | Q71: 26
A72: US | B72: 2024/09/20 | C72: B0BV2NVH1N | D72: 68 | F72: US | G72: 2024/09/20 | H72: B0CD25DR34 | I72: 140 | N72: US | O72: 2024/09/20 | P72: B0CPDHBCC6 | Q72: 34
A73: US | B73: 2024/09/19 | C73: B0BV2NVH1N | D73: 86 | F73: US | G73: 2024/09/19 | H73: B0CD25DR34 | I73: 159 | N73: US | O73: 2024/09/19 | P73: B0CPDHBCC6 | Q73: 37
A74: US | B74: 2024/09/18 | C74: B0BV2NVH1N | D74: 81 | F74: US | G74: 2024/09/18 | H74: B0CD25DR34 | I74: 163 | N74: US | O74: 2024/09/18 | P74: B0CPDHBCC6 | Q74: 36
A75: US | B75: 2024/09/17 | C75: B0BV2NVH1N | D75: 76 | F75: US | G75: 2024/09/17 | H75: B0CD25DR34 | I75: 167 | N75: US | O75: 2024/09/17 | P75: B0CPDHBCC6 | Q75: 36
A76: US | B76: 2024/09/16 | C76: B0BV2NVH1N | D76: 86 | F76: US | G76: 2024/09/16 | H76: B0CD25DR34 | I76: 221 | N76: US | O76: 2024/09/16 | P76: B0CPDHBCC6 | Q76: 54
A77: US | B77: 2024/09/15 | C77: B0BV2NVH1N | D77: 70 | F77: US | G77: 2024/09/15 | H77: B0CD25DR34 | I77: 271 | N77: US | O77: 2024/09/15 | P77: B0CPDHBCC6 | Q77: 49
A78: US | B78: 2024/09/14 | C78: B0BV2NVH1N | D78: 73 | F78: US | G78: 2024/09/14 | H78: B0CD25DR34 | I78: 249 | N78: US | O78: 2024/09/14 | P78: B0CPDHBCC6 | Q78: 42
A79: US | B79: 2024/09/13 | C79: B0BV2NVH1N | D79: 70 | F79: US | G79: 2024/09/13 | H79: B0CD25DR34 | I79: 174 | N79: US | O79: 2024/09/13 | P79: B0CPDHBCC6 | Q79: 31
... A94: US | B94: 2024/08/29 | C94: B0BV2NVH1N | D94: 129 | F94: US | G94: 2024/08/29 | H94: B0CD25DR34 | I94: 104 | N94: US | O94: 2024/08/29 | P94: B0CPDHBCC6 | Q94: 33
A95: US | B95: 2024/08/28 | C95: B0BV2NVH1N | D95: 130 | F95: US | G95: 2024/08/28 | H95: B0CD25DR34 | I95: 94 | N95: US | O95: 2024/08/28 | P95: B0CPDHBCC6 | Q95: 37 | R95: LD
A96: US | B96: 2024/08/27 | C96: B0BV2NVH1N | D96: 143 | F96: US | G96: 2024/08/27 | H96: B0CD25DR34 | I96: 95 | N96: US | O96: 2024/08/27 | P96: B0CPDHBCC6 | Q96: 32
A97: US | B97: 2024/08/26 | C97: B0BV2NVH1N | D97: 132 | F97: US | G97: 2024/08/26 | H97: B0CD25DR34 | I97: 100 | N97: US | O97: 2024/08/26 | P97: B0CPDHBCC6 | Q97: 36
A98: US | B98: 2024/08/25 | C98: B0BV2NVH1N | D98: 118 | F98: US | G98: 2024/08/25 | H98: B0CD25DR34 | I98: 96 | N98: US | O98: 2024/08/25 | P98: B0CPDHBCC6 | Q98: 30
A99: US | B99: 2024/08/24 | C99: B0BV2NVH1N | D99: 98 | F99: US | G99: 2024/08/24 | H99: B0CD25DR34 | I99: 71 | N99: US | O99: 2024/08/24 | P99: B0CPDHBCC6 | Q99: 20
A100: US | B100: 2024/08/23 | C100: B0BV2NVH1N | D100: 116 | F100: US | G100: 2024/08/23 | H100: B0CD25DR34 | I100: 76 | N100: US | O100: 2024/08/23 | P100: B0CPDHBCC6 | Q100: 27
A101: US | B101: 2024/08/22 | C101: B0BV2NVH1N | D101: 136 | F101: US | G101: 2024/08/22 | H101: B0CD25DR34 | I101: 86 | N101: US | O101: 2024/08/22 | P101: B0CPDHBCC6 | Q101: 36
A102: US | B102: 2024/08/21 | C102: B0BV2NVH1N | D102: 158 | F102: US | G102: 2024/08/21 | H102: B0CD25DR34 | I102: 85 | N102: US | O102: 2024/08/21 | P102: B0CPDHBCC6 | Q102: 32
A103: US | B103: 2024/08/20 | C103: B0BV2NVH1N | D103: 120 | F103: US | G103: 2024/08/20 | H103: B0CD25DR34 | I103: 71 | N103: US | O103: 2024/08/20 | P103: B0CPDHBCC6 | Q103: 23
A104: US | B104: 2024/08/19 | C104: B0BV2NVH1N | D104: 164 | F104: US | G104: 2024/08/19 | H104: B0CD25DR34 | I104: 96 | N104: US | O104: 2024/08/19 | P104: B0CPDHBCC6 | Q104: 28
A105: US | B105: 2024/08/18 | C105: B0BV2NVH1N | D105: 154 | F105: US | G105: 2024/08/18 | H105: B0CD25DR34 | I105: 89 | N105: US | O105: 2024/08/18 | P105: B0CPDHBCC6 | Q105: 32
A106: US | B106: 2024/08/17 | C106: B0BV2NVH1N | D106: 145 | F106: US | G106: 2024/08/17 | H106: B0CD25DR34 | I106: 77 | N106: US | O106: 2024/08/17 | P106: B0CPDHBCC6 | Q106: 32
A107: US | B107: 2024/08/16 | C107: B0BV2NVH1N | D107: 146 | F107: US | G107: 2024/08/16 | H107: B0CD25DR34 | I107: 79 | N107: US | O107: 2024/08/16 | P107: B0CPDHBCC6 | Q107: 36
A108: US | B108: 2024/08/15 | C108: B0BV2NVH1N | D108: 139 | F108: US | G108: 2024/08/15 | H108: B0CD25DR34 | I108: 83 | N108: US | O108: 2024/08/15 | P108: B0CPDHBCC6 | Q108: 33
A109: US | B109: 2024/08/14 | C109: B0BV2NVH1N | D109: 144 | F109: US | G109: 2024/08/14 | H109: B0CD25DR34 | I109: 87 | N109: US | O109: 2024/08/14 | P109: B0CPDHBCC6 | Q109: 42 | R109: LD
A110: US | B110: 2024/08/13 | C110: B0BV2NVH1N | D110: 126 | F110: US | G110: 2024/08/13 | H110: B0CD25DR34 | I110: 59 | N110: US | O110: 2024/08/13 | P110: B0CPDHBCC6 | Q110: 28
A111: US | B111: 2024/08/12 | C111: B0BV2NVH1N | D111: 154 | F111: US | G111: 2024/08/12 | H111: B0CD25DR34 | I111: 67 | N111: US | O111: 2024/08/12 | P111: B0CPDHBCC6 | Q111: 29
A112: US | B112: 2024/08/11 | C112: B0BV2NVH1N | D112: 147 | F112: US | G112: 2024/08/11 | H112: B0CD25DR34 | I112: 66 | N112: US | O112: 2024/08/11 | P112: B0CPDHBCC6 | Q112: 28
A113: US | B113: 2024/08/10 | C113: B0BV2NVH1N | D113: 121 | F113: US | G113: 2024/08/10 | H113: B0CD25DR34 | I113: 67 | N113: US | O113: 2024/08/10 | P113: B0CPDHBCC6 | Q113: 29
A114: US | B114: 2024/08/09 | C114: B0BV2NVH1N | D114: 126 | F114: US | G114: 2024/08/09 | H114: B0CD25DR34 | I114: 79 | N114: US | O114: 2024/08/09 | P114: B0CPDHBCC6 | Q114: 24
...

Sheet BS1拆解
A1: =_xlfn.DISPIMG("ID_11B0E9C9CF6B4F85995A17C98EE8FEA6",1) -> =DISPIMG("ID_11B0E9C9CF6B4F85995A17C98EE8FEA6",1) | D1: 整体下来通过前期BD快速起量，积累权重且通过不断调整价格刺激链接出单，保持高评分 | I1: 产品目前的阶段 | K1: 老链接，旨在分析近一年的表现，毕竟趋于稳定，主要看产出效果，中心放在广告推广上
I2: 理想状态 | K2: 稳定状态，理想目标竞品
A3: 产品 | B3: ASIN | C3: 竞品情况 | I3: 第1，店铺实力；第2，看上新有无操作，第3，分析流量结构来源，第4，品牌效益，第5，动作跟踪
A4: 厨房水龙头 | B4: B0BV2NVH1N | C4: 核心竞品
A5: 店铺实力 | B5: =_xlfn.DISPIMG("ID_218FC67E0C504C1B90B12363E44DB4BC",1) -> =DISPIMG("ID_218FC67E0C504C1B90B12363E44DB4BC",1) | H5: =_xlfn.DISPIMG("ID_DFD78A542A25499A99DB7326D74B48C3",1) -> =DISPIMG("ID_DFD78A542A25499A99DB7326D74B48C3",1) | O5: 总结：新店铺，只有两个产品，但是有一个爆款，应该是某个大牌的小牌子来占据坑位，或者新进来的实力强悍的卖家，总结就是不简单这个店铺运营，还有实力都很OK
A6: 链接分析一 排名变化情况 | B6: =_xlfn.DISPIMG("ID_816FD132DE8B4A9895B44D1D40D4FC81",1) -> =DISPIMG("ID_816FD132DE8B4A9895B44D1D40D4FC81",1) | K6: 一上来没有合并种子链接，现在是49.99美金+20% CP (10美金折扣)，后面卖了一周之后，开始大幅度降价几乎对半砍-$29.99-BD（服务商提报预估），两周之后才开始有评价，属于无评价上线，且有不错的量，广告流量占比很少，还有自然流量暴增的情况，考虑刷单和站外的情况。也可能是价格触底反弹引起大量的自然流（这种情况可能性大） 8.14-8.27有可能是连秒BD，且从7.28开始全是自然流，一方面广告打得很少，广告单占比上很少，所以几乎自然流，但是还能保持不错的量，有可能站外或者刷单。上来撬动自然流量也有可能。 9.4号开始有广告流量，但是整体占比很低，几乎自然流 价格调整方面：7.10：$49.99+$10 CP→7.18-7.24（BD）：$29.99→7.24：$39.99→8.9：$37.99+5% CP→8.14-8.27（怀疑连秒BD）：$29.99→8.27：$35.99→8.29：$39.99→9.4：$37.99→9.5-9.19：$29.99→9.30：$37.99→10.11：$34.99+5% CP→10.18之后：$29.99 5.20-5.27,6.17-6.23,7.22-7.29每个月一次BD稳定销量排名。
A7: 链接分析二 流量结构 | B7: =_xlfn.DISPIMG("ID_81181E073A7E4BFDA581DDAE348FDDB7",1) -> =DISPIMG("ID_81181E073A7E4BFDA581DDAE348FDDB7",1) | E7: =_xlfn.DISPIMG("ID_1B6ED065D5C34582B6319A4D3BF952BB",1) -> =DISPIMG("ID_1B6ED065D5C34582B6319A4D3BF952BB",1) | I7: =_xlfn.DISPIMG("ID_AF650015AFE74AEAABCB682ECE2D624F",1) -> =DISPIMG("ID_AF650015AFE74AEAABCB682ECE2D624F",1) | M7: 推荐流量和广告流量占大头，尤其是推荐流量，所以后续要关注关联流量的布局，看广告框架是哪些？怎么打出这个推荐流量的？广告效果怎么样？
A8: 链接分析四 品牌效益 | B8: =_xlfn.DISPIMG("ID_C4B528863E04408286DE061B55472EF8",1) -> =DISPIMG("ID_C4B528863E04408286DE061B55472EF8",1) | I8: =_xlfn.DISPIMG("ID_B74CDA86B09F437B9EBC30D21FB65A43",1) -> =DISPIMG("ID_B74CDA86B09F437B9EBC30D21FB65A43",1) | Q8: 无自家品牌广告词，无品牌广告，就核心关键词，私域这块有待考究，可能没有，可能站外有放量，SP流量为主
A9: 链接分析五 增长点分析 | B9: 第一周 （7.9-7.15这周） | C9: 流量来源 | D9: 自然流 | L9: 销量情况 | M9: 平均每天3单
C10: 投放效果 | D10: 无广告投入，全部自然流，而且排名还不错，要么就是合并老链接有一定的流量，要么就是刷单做了一些站外。
B11: 第二周 （7.16-7.22这周） | C11: 广告动作 | D11: 增加了广告投放，开了4组，都是核心关键词精准 | L11: 销量情况 | M11: 7.16-4单 7.17-3单 7.18-7单 7.19-7单 7.20-26单 7.21-35单 7.22-57单 | P11: 关键词情况 | Q11: =_xlfn.DISPIMG("ID_0C40702702104A77B73EA6FFDA451033",1) -> =DISPIMG("ID_0C40702702104A77B73EA6FFDA451033",1)
C12: 链接动作 | D12: 降价或者BD，售价$29.99，无评分 Tools & Home Improvement-大类6059 Kitchen Sink Faucets-小类21（一天57单左右）
C13: 流量来源 | D13: 自然流贡献最大
C14: 投放效果 | D14: kitchen faucets贡献最多流量，必打的关键词，自然流爆发，考虑站外和BD的作用
B15: 第三周 （7.23-7.29这周） | C15: 广告动作 | D15: 广告增加7组，可能会减少一些词的投放，否定一些词 | L15: 销量情况 | M15: 7.23-63单 7.24-93单 7.25-94单 7.26-30单 7.27-59单 7.28-47单 7.29-42单 | P15: 关键词情况 | Q15: =_xlfn.DISPIMG("ID_62DBF25E293941138C3F1EDB75319C55",1) -> =DISPIMG("ID_62DBF25E293941138C3F1EDB75319C55",1)
C16: 链接动作 | D16: 售价$39.99，无优惠卷和会员折扣，这一周来评价，评分5.0 Tools & Home Improvement-大类8833 Kitchen Sink Faucets-小类32（一天42单左右）
C17: 流量来源 | D17: 自然流量+SP流量，所有流量都是暴涨状态，自然流继续暴涨，同时也带动了很多关键词自然位提升，广告位置靠后但是也在首页，整体贡献上SP流量占比还是很少。
C18: 投放效果 | D18: 上周投放的广告很好，引入了大量的流量，销量也是爆发式突进，像站外那种爆发并且持续能力很强。
B19: 第四周 （7.30-8.5这周） | C19: 广告动作 | D19: 增加一组广告两个核心关键词精准投放 | M19: 7.30-40单 7.31-42单 8.1-35单 8.2-38单 8.3-31单 8.4-27单 8.5-27单 | P19: 关键词情况 | Q19: =_xlfn.DISPIMG("ID_E75705BDD4E64593BD39A05F73E41561",1) -> =DISPIMG("ID_E75705BDD4E64593BD39A05F73E41561",1)
C20: 链接动作 | D20: 售价$39.99，无优惠卷和会员折扣，7个评价，评分4.7 Tools & Home Improvement-大类12572 Kitchen Sink Faucets-小类32（一天31单左右）
C21: 流量来源 | D21: 自然流量+SP流量，所有流量下跌，广告流量下滑严重，可能是砍广告预算或者降低CPC导致广告烧不出去。但整体上还是不错的
C22: 投放效果 | D22: 核心关键词流量词位置下降，导致流量下降不少广告位置也靠后了，证明是下调CPC这种情况比较大
A23: 链接分析六 站外 | B23: 短期站内爆款? | C23: 是 | O23: 很新的品牌，几乎没有任何平台的布局，所以TK上没有布局，全新状态能打上头部，属实是大卖下的小牌给钱，给资源，起来得快，店铺实力不一般
B24: 新媒体渠道引流
B25: FB | C25: 无FB
B26: 独立站 | C26: 无独立站

Sheet NR1拆解
A1: =_xlfn.DISPIMG("ID_13804CCF1F6F4DF2AAB44757F01DC781",1) -> =DISPIMG("ID_13804CCF1F6F4DF2AAB44757F01DC781",1) | D1: 正常新品链接推广，聚焦精准投放关键词，自然流占比大，需要进一步研究。 | I1: 产品目前的阶段 | K1: 老链接，旨在分析近一年的表现，毕竟趋于稳定，主要看产出效果，中心放在广告推广上
I2: 理想状态 | K2: 稳定状态，理想目标竞品
A3: 产品 | B3: ASIN | C3: 竞品情况 | I3: 第1，店铺实力；第2，看上新有无操作，第3，分析流量结构来源，第4，品牌效益，第5，动作跟踪
A4: 厨房水龙头 | B4: B0DCJ76VFY | C4: 核心新品
A5: 店铺实力 | B5: =_xlfn.DISPIMG("ID_72E6FE6225B04FE3A73D340F1F11CD4B",1) -> =DISPIMG("ID_72E6FE6225B04FE3A73D340F1F11CD4B",1) | H5: =_xlfn.DISPIMG("ID_069C5FE4218B4E41961822405EC99E4E",1) -> =DISPIMG("ID_069C5FE4218B4E41961822405EC99E4E",1) | O5: 总结：新店铺，只有4个产品，但是整体上没有做种子链接也没有维护好评价，店铺产品一般般，整体的实力偏弱，但也不排除是大牌下的某个小牌，需要再观察，毕竟现在也是拿到NR的标。上线时间不到一个月的时间。
A6: 链接分析一 排名变化情况 | B6: =_xlfn.DISPIMG("ID_F8F721EBDA3647738E657F6AE66EFAE7",1) -> =DISPIMG("ID_F8F721EBDA3647738E657F6AE66EFAE7",1) | K6: 一上来没有合并种子链接，现在是49.99美金+5% CP，后面卖了一周之后，开始大幅度降价-$32.99，10天左右来了一个5星评价,整体上没有太多操作，保持高评分 价格调整方面：10.2：$49.99+5% CP→10.8：$32.99→10.11-10.15：$32.99+30% CP→10.16：$32.99+10% CP→10.17-11.01：$32.99(JP $29.69)+10% CP→11.2：$32.99+15% CP→11.3-至今：$33.99+5% CP
A7: 链接分析二 流量结构 | B7: =_xlfn.DISPIMG("ID_82F0EBA1EFBC4536A987C4B401D6559C",1) -> =DISPIMG("ID_82F0EBA1EFBC4536A987C4B401D6559C",1) | M7: 自然流量占比超大，一上去就有自然流量，有点奇怪，要么就是这个类目特性，要么就是有操作手段
A8: 链接分析四 品牌效益 | B8: =_xlfn.DISPIMG("ID_185C75B0F95546BD821F5B8887D8B941",1) -> =DISPIMG("ID_185C75B0F95546BD821F5B8887D8B941",1) | I8: =_xlfn.DISPIMG("ID_CD36F4B537434C58AD83DABA155C1910",1) -> =DISPIMG("ID_CD36F4B537434C58AD83DABA155C1910",1) | Q8: 无自家品牌广告词，无品牌广告，就核心关键词SP，私域这块有待考究，可能没有，可能站外有放量，SP流量为主，再次验证小店铺不大品牌广告的情况，也可能是新品初期已精准流量SP为主。
A9: 链接分析五 增长点分析 | B9: 第一周 （9.26-10.5这周） | C9: 流量来源 | D9: 主要是广告流量，但整体不是很多，估计也没有舍得投放 | L9: 销量情况 | M9: 无出单
C10: 投放效果 | D10: 投放两组核心属性瀑布流关键词，效果一般，流量太少，因为CPC太低或者新品没有权重
B11: 第二周 （10.06-10.12这周） | C11: 广告动作 | D11: 增加了广告投放，开了4组，都是核心大词属性（颜色，瀑布流等属性+大词）精准 | L11: 销量情况 | M11: 10.06-0单 10.07-8单 10.08-16单 10.09-16单 10.10-8单 10.11-8单 10.12-6单 | P11: 关键词情况 | Q11: =_xlfn.DISPIMG("ID_E433708EF0ED487892F77A50B58B9F0E",1) -> =DISPIMG("ID_E433708EF0ED487892F77A50B58B9F0E",1)
C12: 链接动作 | D12: $49.99+5% CP降价到$32.99+30% CP，10.12来一个评价5星 Kitchen Sink Faucets-小类546（一天2单左右）
C13: 流量来源 | D13: 自然和广告对半分，各占一半，流程比上周上涨
C14: 投放效果 | D14: kitchen sink faucet贡献最多流量，必打的关键词，整体上还是有不错的效果，打的广告
B15: 第三周 （10.13-10.19这周） | C15: 广告动作 | D15: 广告关闭4组（关闭了带属性，颜色的广告），新增2组广告（1组出单品牌关键词，1组核心产品词精准） | L15: 销量情况 | M15: 10.13-9单 10.14-3单 10.15-3单 10.16-3单 10.17-6单 10.18-5单 10.19-5单 | P15: 关键词情况 | Q15: =_xlfn.DISPIMG("ID_96C51F48C9374257A0F5D8F3A0A66C1E",1) -> =DISPIMG("ID_96C51F48C9374257A0F5D8F3A0A66C1E",1)
C16: 链接动作 | D16: $32.99+30% CP改为JP$29.69+10%CP，这一周来4个五星评价，评分5.0 Tools & Home Improvement-大类100023 Kitchen Sink Faucets-小类352（一天4单左右）
C17: 流量来源 | D17: 自然流量+SP流量，所有流量都是暴涨状态，自然流暴涨，同时也带动了很多关键词自然位提升，证明广告投放有效果，位置上涨流量上涨，曝光上涨，可能转化差一些些
C18: 投放效果 | D18: 投放的广告很好，引入了大量的流量
B19: 第四周 （10.20-10.26这周） | C19: 广告动作 | D19: 关闭2组广告，开了5组广告（精准投放出单词或者是反查竞品的出单词） | M19: 10.20-5单 10.21-6单 10.22-3单 10.23-4单 10.24-6单 10.25-6单 10.26-6单 | P19: 关键词情况 | Q19: =_xlfn.DISPIMG("ID_06B5D7B4E6B74B0C95040C2D09CD3394",1) -> =DISPIMG("ID_06B5D7B4E6B74B0C95040C2D09CD3394",1)
C20: 链接动作 | D20: 保持JP$29.69+10%CP，5个评价，评分5.0 Tools & Home Improvement-大类106669 Kitchen Sink Faucets-小类351（一天4单左右）
C21: 流量来源 | D21: 自然流量+SP流量，核心自然流量，自然流量下滑，但是整体影响不是很大，属于新品的正常波动。
C22: 投放效果 | D22: 核心关键词流量词位置下降，导致流量下降不少广告位置也靠后了，证明是下调CPC
B23: 第五周 （10.27-11.2这周） | C23: 广告动作 | D23: 关闭3组广告，重开老广告4组 | M23: 10.27-6单 10.28-6单 10.29-11单 10.30-12单 10.31-12单 11.01-12单 11.02-12单 | P23: 关键词情况 | Q23: =_xlfn.DISPIMG("ID_FD8F115F67F646F29EFE33D2A61C09D5",1) -> =DISPIMG("ID_FD8F115F67F646F29EFE33D2A61C09D5",1)
C24: 链接动作 | D24: 保持JP$29.69+10%CP，6个评价，评分5.0 Tools & Home Improvement-大类30729 Kitchen Sink Faucets-小类351（一天12单左右）
C25: 流量来源 | D25: 自然流量+SP流量，核心自然流量，自然流量上升，关键词位置往前走，展示的时间长，一方面证明广告效果可能不错，一方面单量有聚焦
C26: 投放效果 | D26: 看一下投放那些词，那些是核心流量词，后面广告可以投放一下
A27: 链接分析六 站外 | B27: 短期站内爆款? | C27: 是
B28: 新媒体渠道引流 | C28: 很新的品牌，几乎没有任何平台的布局，所以TK上没有布局，全新状态能打上头部，属实是大卖下的小牌给钱，给资源，起来得快，店铺实力不一般
B29: FB | C29: 无FB
B30: 独立站 | C30: 无独立站

Sheet 可行性打法
A1: 间断流打法 | B1: 第一阶段 第一周 1.测试链接数据的第一周，测点击率，转化率，且配合大额折扣+种子链接高评分。5个买家秀，1个主图视频，5组QA全部上传完毕。 2.刷出链接新品榜（确保种子链接在1月的时候能到，这样到2月推广能有评价且还在新品期，合并起来没有影响） 3.广告只打A组精准占70%的预算，B组广泛占20%预算，自动广告D组占10%预算，精准核心关键词有效测位置转化率和点击率，所以A组核心预算。 第二周 1.上周已经测试出好的主图跟位置转化了，这周就敲到文案和图片不再做大幅度调整。 2.采用40-50%折扣做5-7天站外，通过大折扣力度促进站外出单，甚至说小爆单，这个可以让新品总CVR大于小类目平均转化率！这几天先不要给很多广告预算，让自然流为主导。控住点击率和转化率。 3.将产品权重全面拉升，让部分核心关键词有自然位，为后续降低CPC奠定基础。顺便帮链接突破单量瓶颈，拉升到20单以上。 第三周 会员折扣+优惠卷，慢慢承接住大部分关键词的自然流量了！这个阶段要把广告框架布局上来，把广告预算逐渐提升起来，自然订单/广告订单。 第四周 根据推广计划去走就行，完成指标，没有达标复盘改进。 | K1: 推新品爆款链接，一定要跟进BSR排名来推进，比如新品第一天我就要出现在小类目新品排行榜前50名，然后从新品排行榜前50名到40名到30名到20名，最后到进入前10名！ 这个过程中不一定每天都能够把排名控制好，可能某天会爆单，然后进入小类目新品排行前10名，假如这个阶段只需要小类目前30名，那么我们可以等到一两天，小类目排名掉到30多名，当天再安排站外把排名稳住在30名之前！反正一句话，就是通过站外出单不能让新品排名掉出来我们制定的排名！ | S1: 如果测试了几个站外渠道都出单很不好（几单的情况下），放弃站外方式，后续就用不了站外的方式做突破，则考虑用LD或者BD的方式去突破，调整推广计划。只能靠广告去拉升单量，加大投入。所以前期需要做测试站外渠道。
K10: 一定要重点观察新品CVR，在业务报名那里可以看到链接的总转化率。想要打造成爆款链接必须要把CVR转化率大于平均转化率，竞品的小类目平均转化率为8%，那么我们的新品必须每天平均转化率大于8%以上。是必须每天平均转化率大于8%以上，要不自然排名会非常不稳定。FB折扣小组用高折扣，其他的站外资源灵活应变，如果FB给的折扣低，一定不要进行FB投放，要不会拉低新品【总CVR】，会搞死链接的，要投放就【高价格高折扣】投放，要不就不要投放不要投放！

Sheet 二、BSR排名销量计划（日月-目标）
A1: 第一阶段20-50个评论 第二阶段50-150个评论 第三阶段150-200个评论
A2: 时间 | C2: 单量目标 | I2: 目标坑位 | J2: 库存计划 | L2: 可售天数 | M2: 备注 | N2: 目标竞对信息 | Z2: 关键词收录 | AD2: 排名 | AF2: 图片 | AG2: Keepa分析
A3: 推品阶段 | B3: 日期 | C3: 总订单 | D3: 增幅 | E3: 广告订单 | F3: 广告订单占比 | G3: 自然订单 | H3: 站外订单 | I3: 小类排名 | J3: 销量 | K3: 库存 | N3: 品牌 | O3: ASIN | P3: 售价 | Q3: 优惠劵 | R3: 月销 | S3: 子体月销 | T3: 日销目标 | U3: 月销售额 | V3: 上架时间 | W3: 星级 | X3: 评论 | Y3: 变体 | Z3: 总收录 | AA3: 自然 | AB3: 广告 | AC3: 推荐 | AD3: 大类 | AE3: 小节点
A4: 二月 | B4: 45689 | C4: 1 | D4: =C4/C4 -> 1 | E4: =C4*F4 -> 1 | F4: 1 | G4: =C4*(1-F4) -> 0 | I4: 30 | J4: =C4 -> 1 | K4: 800 | L4: =K4/J4 -> 800 | N4: FORIOUS | O4: B0CPDHBCC6 | P4: 54.99 | Q4: 0.2 | R4: 1052 | S4: 500 | T4: =K4/30 -> 26.666667 | U4: 57849 | V4: 45263 | W4: 4.5 | X4: 234 | Y4: 7 | Z4: 502 | AA4: 439 | AB4: 164 | AC4: 42 | AD4: #9,132 in Tools & Home Improvement | AE4: #25 in Touch On Kitchen Sink Faucets
A5: 二月 | B5: 45690 | C5: 2 | D5: =(C5-C4)/C5 -> 0.5 | E5: =C5*F5 -> 1.8 | F5: 0.9 | G5: =C5*(1-F5) -> 0.2 | I5: 30 | J5: =C5 -> 2 | K5: =K4-J5 -> 798 | L5: =K5/J5 -> 399 | O5: 会员折扣 | P5: 49.49
A6: 二月 | B6: 45691 | C6: 3 | D6: =(C6-C5)/C6 -> 0.33333333 | E6: =C6*F6 -> 2.4 | F6: 0.8 | G6: =C6*(1-F6) -> 0.6 | I6: 30 | J6: =C6 -> 3 | K6: =K5-J6 -> 795 | L6: =K6/J6 -> 265 | O6: 主要颜色黑+银+金
A7: 二月 | B7: 45692 | C7: 4 | D7: =(C7-C6)/C7 -> 0.25 | E7: =C7*F7 -> 3.2 | F7: 0.8 | G7: =C7*(1-F7) -> 0.8 | I7: 30 | J7: =C7 -> 4 | K7: =K6-J7 -> 791 | L7: =K7/J7 -> 197.75 | O7: 第一阶段主要第一周优化数据，调整链接，尽量测出好的数据，广告以精准为主
A8: 二月 | B8: 45693 | C8: 5 | D8: =(C8-C7)/C8 -> 0.2 | E8: =C8*F8 -> 4 | F8: 0.8 | G8: =C8*(1-F8) -> 1 | I8: 30 | J8: =C8 -> 5 | K8: =K7-J8 -> 786 | L8: =K8/J8 -> 157.2 | O8: 30单已经可以在前30名，有几率出LD，利用LD突破流量单量瓶颈，多参加几次，有就报名
A9: 二月 | B9: 45694 | C9: 6 | D9: =(C9-C8)/C9 -> 0.16666667 | E9: =C9*F9 -> 4.8 | F9: 0.8 | G9: =C9*(1-F9) -> 1.2 | I9: 30 | J9: =C9 -> 6 | K9: =K8-J9 -> 780 | L9: =K9/J9 -> 130
A10: 二月 | B10: 45695 | C10: 8 | D10: =(C10-C9)/C10 -> 0.25 | E10: =C10*F10 -> 6.4 | F10: 0.8 | G10: =C10*(1-F10) -> 1.6 | I10: 30 | J10: =C10 -> 8 | K10: =K9-J10 -> 772 | L10: =K10/J10 -> 96.5 | O10: 日销14-20单能拿到 NR
A11: 二月 | B11: 45696 | C11: 10 | D11: =(C11-C10)/C11 -> 0.2 | E11: =C11*F11 -> 7 | F11: 0.7 | G11: =C11*(1-F11) -> 3 | I11: 30 | J11: =C11 -> 10 | K11: =K10-J11 -> 762 | L11: =K11/J11 -> 76.2 | O11: 所以第一个月 | P11: 新品 排行榜 | R11: 小类目 排名 | T11: 大类目 排名
A12: 二月 | B12: 45697 | C12: 11 | D12: =(C12-C11)/C12 -> 0.090909091 | E12: =C12*F12 -> 7.7 | F12: 0.7 | G12: =C12*(1-F12) -> 3.3 | I12: 30 | J12: =C12 -> 11 | K12: =K11-J12 -> 751 | L12: =K12/J12 -> 68.272727 | O12: 第1周 | P12: 前10名 | R12: 稳定在前120名 | T12: 稳定在前120000名
A13: 二月 | B13: 45698 | C13: 13 | D13: =(C13-C12)/C13 -> 0.15384615 | E13: =C13*F13 -> 9.1 | F13: 0.7 | G13: =C13*(1-F13) -> 3.9 | I13: 30 | J13: =C13 -> 13 | K13: =K12-J13 -> 738 | L13: =K13/J13 -> 56.769231 | O13: 第2周 | P13: NR #1 | R13: 稳定在前100名 | T13: 稳定在前30000名
A14: 二月 | B14: 45699 | C14: 15 | D14: =(C14-C13)/C14 -> 0.13333333 | E14: =C14*F14 -> 10.5 | F14: 0.7 | G14: =C14*(1-F14) -> 4.5 | I14: 30 | J14: =C14 -> 15 | K14: =K13-J14 -> 723 | L14: =K14/J14 -> 48.2 | O14: 第3周 | P14: NR #1 | R14: 稳定在前50名 | T14: 稳定在前17000名
A15: 二月 | B15: 45700 | C15: 16 | D15: =(C15-C14)/C15 -> 0.0625 | E15: =C15*F15 -> 11.2 | F15: 0.7 | G15: =C15*(1-F15) -> 4.8 | I15: 30 | J15: =C15 -> 16 | K15: =K14-J15 -> 707 | L15: =K15/J15 -> 44.1875 | O15: 第4周 | P15: NR #1 | R15: 稳定在前30名 | T15: 稳定在前10000名
A16: 二月 | B16: 45701 | C16: 18 | D16: =(C16-C15)/C16 -> 0.11111111 | E16: =C16*F16 -> 12.6 | F16: 0.7 | G16: =C16*(1-F16) -> 5.4 | I16: 30 | J16: =C16 -> 18 | K16: =K15-J16 -> 689 | L16: =K16/J16 -> 38.277778
A17: 二月 | B17: 45702 | C17: 20 | D17: =(C17-C16)/C17 -> 0.1 | E17: =C17*F17 -> 14 | F17: 0.7 | G17: =C17*(1-F17) -> 6 | I17: 30 | J17: =C17 -> 20 | K17: =K16-J17 -> 669 | L17: =K17/J17 -> 33.45
A18: 二月 | B18: 45703 | C18: 23 | D18: =(C18-C17)/C18 -> 0.13043478 | E18: =C18*F18 -> 16.1 | F18: 0.7 | G18: =C18*(1-F18) -> 6.9 | I18: 30 | J18: =C18 -> 23 | K18: =K17-J18 -> 646 | L18: =K18/J18 -> 28.086957
A19: 二月 | B19: 45704 | C19: 25 | D19: =(C19-C18)/C19 -> 0.08 | E19: =C19*F19 -> 17.5 | F19: 0.7 | G19: =C19*(1-F19) -> 7.5 | I19: 30 | J19: =C19 -> 25 | K19: =K18-J19 -> 621 | L19: =K19/J19 -> 24.84
A20: 二月 | B20: 45705 | C20: 25 | D20: =(C20-C19)/C20 -> 0 | E20: =C20*F20 -> 17.5 | F20: 0.7 | G20: =C20*(1-F20) -> 7.5 | I20: 30 | J20: =C20 -> 25 | K20: =K19-J20 -> 596 | L20: =K20/J20 -> 23.84
A21: 二月 | B21: 45706 | C21: 26 | D21: =(C21-C20)/C21 -> 0.038461538 | E21: =C21*F21 -> 18.2 | F21: 0.7 | G21: =C21*(1-F21) -> 7.8 | I21: 30 | J21: =C21 -> 26 | K21: =K20-J21 -> 570 | L21: =K21/J21 -> 21.923077
A22: 二月 | B22: 45707 | C22: 26 | D22: =(C22-C21)/C22 -> 0 | E22: =C22*F22 -> 18.2 | F22: 0.7 | G22: =C22*(1-F22) -> 7.8 | I22: 30 | J22: =C22 -> 26 | K22: =K21-J22 -> 544 | L22: =K22/J22 -> 20.923077
A23: 二月 | B23: 45708 | C23: 27 | D23: =(C23-C22)/C23 -> 0.037037037 | E23: =C23*F23 -> 18.9 | F23: 0.7 | G23: =C23*(1-F23) -> 8.1 | I23: 30 | J23: =C23 -> 27 | K23: =K22-J23 -> 517 | L23: =K23/J23 -> 19.148148
A24: 二月 | B24: 45709 | C24: 27 | D24: =(C24-C23)/C24 -> 0 | E24: =C24*F24 -> 18.9 | F24: 0.7 | G24: =C24*(1-F24) -> 8.1 | I24: 30 | J24: =C24 -> 27 | K24: =K23-J24 -> 490 | L24: =K24/J24 -> 18.148148
A25: 二月 | B25: 45710 | C25: 28 | D25: =(C25-C24)/C25 -> 0.035714286 | E25: =C25*F25 -> 19.6 | F25: 0.7 | G25: =C25*(1-F25) -> 8.4 | I25: 30 | J25: =C25 -> 28 | K25: =K24-J25 -> 462 | L25: =K25/J25 -> 16.5
A26: 二月 | B26: 45711 | C26: 28 | D26: =(C26-C25)/C26 -> 0 | E26: =C26*F26 -> 19.6 | F26: 0.7 | G26: =C26*(1-F26) -> 8.4 | I26: 30 | J26: =C26 -> 28 | K26: =K25-J26 -> 434 | L26: =K26/J26 -> 15.5
A27: 二月 | B27: 45712 | C27: 29 | D27: =(C27-C26)/C27 -> 0.034482759 | E27: =C27*F27 -> 20.3 | F27: 0.7 | G27: =C27*(1-F27) -> 8.7 | I27: 30 | J27: =C27 -> 29 | K27: =K26-J27 -> 405 | L27: =K27/J27 -> 13.965517
... A31: 二月 | B31: 45716 | C31: 32 | D31: =(C31-C30)/C31 -> 0.0625 | E31: =C31*F31 -> 22.4 | F31: 0.7 | G31: =C31*(1-F31) -> 9.6 | I31: 30 | J31: =C31 -> 32 | K31: =K30-J31 -> 284 | L31: =K31/J31 -> 8.875
A32: 二月 | B32: 二月汇总 | C32: =SUM(C4:C31) -> 517 | E32: =SUM(E4:E31) -> 365.2 | F32: =E32/C32 -> 0.70638298 | G32: =SUM(G4:G31) -> 151.8 | H32: 0 | I32: / | J32: =C32 -> 517 | K32: 1316 | L32: =K32/J32 -> 2.5454545 | N32: BASDEHEN | O32: B0CD25DR34 | P32: 29.99 | Q32: 0.5 | R32: 2511 | S32: 1000 | T32: =K33/30 -> 53.333333 | U32: 75305 | V32: 45134 | W32: 4.6 | X32: 293 | Y32: 3 | Z32: 432 | AA32: 409 | AB32: 52 | AC32: 1 | AD32: #2,996 in Tools & Home Improvement | AE32: #9 in Touch On Kitchen Sink Faucets
A33: 三月 | B33: 45717 | C33: 33 | D33: =C33/C33 -> 1 | E33: =C33*F33 -> 19.8 | F33: 0.6 | G33: =C33*(1-F33) -> 13.2 | I33: 20 | J33: =C33 -> 33 | K33: =K32+K31 -> 1600 | L33: =K33/J33 -> 48.484848
A34: 三月 | B34: 45718 | C34: 34 | D34: =(C34-C33)/C34 -> 0.029411765 | E34: =C34*F34 -> 20.4 | F34: 0.6 | G34: =C34*(1-F34) -> 13.6 | I34: 20 | J34: =C34 -> 34 | K34: =K33-J34 -> 1566 | L34: =K34/J34 -> 46.058824 | O34: 第二阶段总体目标，日均41单，月1271单，具体需要根据第一阶段的推广数据调整
A35: 三月 | B35: 45719 | C35: 34 | D35: =(C35-C34)/C35 -> 0 | E35: =C35*F35 -> 20.4 | F35: 0.6 | G35: =C35*(1-F35) -> 13.6 | I35: 20 | J35: =C35 -> 34 | K35: =K34-J35 -> 1532 | L35: =K35/J35 -> 45.058824 | O35: 第二阶段是突破到前20，前20名是拿到市场差不多80%的量，所以难度成倍增加，必须要借助秒杀，最好是BD进行辅助，需要用到广告补单，甚至是站外。如果评价稳定在300个，加上种子链接，可以低价开始冲刺起量。必须要完成目标销量，多个流量入口占据，会员折扣还有优惠卷都要使用，甚至是code。核心关键词都要在首页
A36: 三月 | B36: 45720 | C36: 35 | D36: =(C36-C35)/C36 -> 0.028571429 | E36: =C36*F36 -> 21 | F36: 0.6 | G36: =C36*(1-F36) -> 14 | I36: 20 | J36: =C36 -> 35 | K36: =K35-J36 -> 1497 | L36: =K36/J36 -> 42.771429
A37: 三月 | B37: 45721 | C37: 35 | D37: =(C37-C36)/C37 -> 0 | E37: =C37*F37 -> 21 | F37: 0.6 | G37: =C37*(1-F37) -> 14 | I37: 20 | J37: =C37 -> 35 | K37: =K36-J37 -> 1462 | L37: =K37/J37 -> 41.771429
A38: 三月 | B38: 45722 | C38: 35 | D38: =(C38-C37)/C38 -> 0 | E38: =C38*F38 -> 21 | F38: 0.6 | G38: =C38*(1-F38) -> 14 | I38: 20 | J38: =C38 -> 35 | K38: =K37-J38 -> 1427 | L38: =K38/J38 -> 40.771429
A39: 三月 | B39: 45723 | C39: 36 | D39: =(C39-C38)/C39 -> 0.027777778 | E39: =C39*F39 -> 21.6 | F39: 0.6 | G39: =C39*(1-F39) -> 14.4 | I39: 20 | J39: =C39 -> 36 | K39: =K38-J39 -> 1391 | L39: =K39/J39 -> 38.638889 | O39: 所以第二个月 | P39: 新品 排行榜 | R39: 小类目 排名 | T39: 大类目 排名
A40: 三月 | B40: 45724 | C40: 36 | D40: =(C40-C39)/C40 -> 0 | E40: =C40*F40 -> 21.6 | F40: 0.6 | G40: =C40*(1-F40) -> 14.4 | I40: 20 | J40: =C40 -> 36 | K40: =K39-J40 -> 1355 | L40: =K40/J40 -> 37.638889 | O40: 第1周 | P40: NR #1 | R40: 稳定在前30名 | T40: 稳定在前10000名
A41: 三月 | B41: 45725 | C41: 36 | D41: =(C41-C40)/C41 -> 0 | E41: =C41*F41 -> 21.6 | F41: 0.6 | G41: =C41*(1-F41) -> 14.4 | I41: 20 | J41: =C41 -> 36 | K41: =K40-J41 -> 1319 | L41: =K41/J41 -> 36.638889 | O41: 第2周 | P41: NR #1 | R41: 稳定在前30名 | T41: 稳定在前10000名
A42: 三月 | B42: 45726 | C42: 36 | D42: =(C42-C41)/C42 -> 0 | E42: =C42*F42 -> 21.6 | F42: 0.6 | G42: =C42*(1-F42) -> 14.4 | I42: 20 | J42: =C42 -> 36 | K42: =K41-J42 -> 1283 | L42: =K42/J42 -> 35.638889 | O42: 第3周 | P42: NR #1 | R42: 稳定在前25名 | T42: 稳定在前8000名
A43: 三月 | B43: 45727 | C43: 37 | D43: =(C43-C42)/C43 -> 0.027027027 | E43: =C43*F43 -> 22.2 | F43: 0.6 | G43: =C43*(1-F43) -> 14.8 | I43: 20 | J43: =C43 -> 37 | K43: =K42-J43 -> 1246 | L43: =K43/J43 -> 33.675676 | O43: 第4周 | P43: NR #1 | R43: 稳定在前20名 | T43: 稳定在前7500名
A44: 三月 | B44: 45728 | C44: 37 | D44: =(C44-C43)/C44 -> 0 | E44: =C44*F44 -> 22.2 | F44: 0.6 | G44: =C44*(1-F44) -> 14.8 | I44: 20 | J44: =C44 -> 37 | K44: =K43-J44 -> 1209 | L44: =K44/J44 -> 32.675676
A45: 三月 | B45: 45729 | C45: 38 | D45: =(C45-C44)/C45 -> 0.026315789 | E45: =C45*F45 -> 22.8 | F45: 0.6 | G45: =C45*(1-F45) -> 15.2 | I45: 20 | J45: =C45 -> 38 | K45: =K44-J45 -> 1171 | L45: =K45/J45 -> 30.815789
A46: 三月 | B46: 45730 | C46: 40 | D46: =(C46-C45)/C46 -> 0.05 | E46: =C46*F46 -> 24 | F46: 0.6 | G46: =C46*(1-F46) -> 16 | I46: 20 | J46: =C46 -> 40 | K46: =K45-J46 -> 1131 | L46: =K46/J46 -> 28.275
A47: 三月 | B47: 45731 | C47: 40 | D47: =(C47-C46)/C47 -> 0 | E47: =C47*F47 -> 24 | F47: 0.6 | G47: =C47*(1-F47) -> 16 | I47: 20 | J47: =C47 -> 40 | K47: =K46-J47 -> 1091 | L47: =K47/J47 -> 27.275
A48: 三月 | B48: 45732 | C48: 42 | D48: =(C48-C47)/C48 -> 0.047619048 | E48: =C48*F48 -> 25.2 | F48: 0.6 | G48: =C48*(1-F48) -> 16.8 | I48: 20 | J48: =C48 -> 42 | K48: =K47-J48 -> 1049 | L48: =K48/J48 -> 24.97619
A49: 三月 | B49: 45733 | C49: 42 | D49: =(C49-C48)/C49 -> 0 | E49: =C49*F49 -> 25.2 | F49: 0.6 | G49: =C49*(1-F49) -> 16.8 | I49: 20 | J49: =C49 -> 42 | K49: =K48-J49 -> 1007 | L49: =K49/J49 -> 23.97619
A50: 三月 | B50: 45734 | C50: 43 | D50: =(C50-C49)/C50 -> 0.023255814 | E50: =C50*F50 -> 25.8 | F50: 0.6 | G50: =C50*(1-F50) -> 17.2 | I50: 20 | J50: =C50 -> 43 | K50: =K49-J50 -> 964 | L50: =K50/J50 -> 22.418605
A51: 三月 | B51: 45735 | C51: 43 | D51: =(C51-C50)/C51 -> 0 | E51: =C51*F51 -> 25.8 | F51: 0.6 | G51: =C51*(1-F51) -> 17.2 | I51: 20 | J51: =C51 -> 43 | K51: =K50-J51 -> 921 | L51: =K51/J51 -> 21.418605
A52: 三月 | B52: 45736 | C52: 44 | D52: =(C52-C51)/C52 -> 0.022727273 | E52: =C52*F52 -> 26.4 | F52: 0.6 | G52: =C52*(1-F52) -> 17.6 | I52: 20 | J52: =C52 -> 44 | K52: =K51-J52 -> 877 | L52: =K52/J52 -> 19.931818
A53: 三月 | B53: 45737 | C53: 45 | D53: =(C53-C52)/C53 -> 0.022222222 | E53: =C53*F53 -> 27 | F53: 0.6 | G53: =C53*(1-F53) -> 18 | I53: 20 | J53: =C53 -> 45 | K53: =K52-J53 -> 832 | L53: =K53/J53 -> 18.488889
A54: 三月 | B54: 45738 | C54: 45 | D54: =(C54-C53)/C54 -> 0 | E54: =C54*F54 -> 27 | F54: 0.6 | G54: =C54*(1-F54) -> 18 | I54: 20 | J54: =C54 -> 45 | K54: =K53-J54 -> 787 | L54: =K54/J54 -> 17.488889
A55: 三月 | B55: 45739 | C55: 45 | D55: =(C55-C54)/C55 -> 0 | E55: =C55*F55 -> 27 | F55: 0.6 | G55: =C55*(1-F55) -> 18 | I55: 20 | J55: =C55 -> 45 | K55: =K54-J55 -> 742 | L55: =K55/J55 -> 16.488889
... A63: 三月 | B63: 45747 | C63: 50 | D63: =(C63-C62)/C63 -> 0.02 | E63: =C63*F63 -> 30 | F63: 0.6 | G63: =C63*(1-F63) -> 20 | I63: 20 | J63: =C63 -> 50 | K63: =K62-J63 -> 362 | L63: =K63/J63 -> 7.24
A64: 三月 | B64: 三月汇总 | C64: =SUM(C33:C63) -> 1271 | E64: =SUM(E33:E63) -> 762.6 | F64: =E64/C64 -> 0.6 | G64: =SUM(G33:G63) -> 508.4 | H64: 0 | I64: 60 | J64: =C64 -> 1271 | K64: 2338 | L64: =K64/J64 -> 1.8394965 | N64: BASDEHEN | O64: B0CD25DR34 | P64: 29.99 | Q64: 0.5 | R64: 2511 | S64: 1000 | T64: 80 | U64: 75305 | V64: 45134 | W64: 4.6 | X64: 293 | Y64: 3 | Z64: 432 | AA64: 409 | AB64: 52 | AC64: 1 | AD64: #2,996 in Tools & Home Improvement | AE64: #9 in Touch On Kitchen Sink Faucets
A65: 四月 | B65: 45748 | C65: 50 | D65: =C65/C65 -> 1 | E65: =C65*F65 -> 25 | F65: 0.5 | G65: =C65*(1-F65) -> 25 | I65: 15 | J65: =C65 -> 50 | K65: =K64+K63 -> 2700 | L65: =K65/J65 -> 54
A66: 四月 | B66: 45749 | C66: 50 | D66: =(C66-C65)/C66 -> 0 | E66: =C66*F66 -> 25 | F66: 0.5 | G66: =C66*(1-F66) -> 25 | I66: 15 | J66: =C66 -> 50 | K66: =K65-J66 -> 2650 | L66: =K66/J66 -> 53
A67: 四月 | B67: 45750 | C67: 50 | D67: =(C67-C66)/C67 -> 0 | E67: =C67*F67 -> 25 | F67: 0.5 | G67: =C67*(1-F67) -> 25 | I67: 15 | J67: =C67 -> 50 | K67: =K66-J67 -> 2600 | L67: =K67/J67 -> 52 | O67: 第三阶段 继续做销量增量，达到目标排名
A68: 四月 | B68: 45751 | C68: 50 | D68: =(C68-C67)/C68 -> 0 | E68: =C68*F68 -> 25 | F68: 0.5 | G68: =C68*(1-F68) -> 25 | I68: 15 | J68: =C68 -> 50 | K68: =K67-J68 -> 2550 | L68: =K68/J68 -> 51
A69: 四月 | B69: 45752 | C69: 50 | D69: =(C69-C68)/C69 -> 0 | E69: =C69*F69 -> 25 | F69: 0.5 | G69: =C69*(1-F69) -> 25 | I69: 15 | J69: =C69 -> 50 | K69: =K68-J69 -> 2500 | L69: =K69/J69 -> 50 | O69: 第三阶段是来到第三个月，这个阶段已经开始处于产品的成熟期，销量会经常处于一个瓶颈期，销量趋于稳定，这个时候就需要额外手段的去做提升，广告的流量开始瓶颈，必须有BD帮扶且在没有BD的情况下，需要低价在跑一周模拟BD的转化，可以是CODE形式提转化，或者站外出单补充，否则很难做突破。核心关键词慢慢都在首页第一的位置
A70: 四月 | B70: 45753 | C70: 70 | D70: =(C70-C69)/C70 -> 0.28571429 | E70: =C70*F70 -> 35 | F70: 0.5 | G70: =C70*(1-F70) -> 35 | I70: 15 | J70: =C70 -> 70 | K70: =K69-J70 -> 2430 | L70: =K70/J70 -> 34.714286
A71: 四月 | B71: 45754 | C71: 70 | D71: =(C71-C70)/C71 -> 0 | E71: =C71*F71 -> 35 | F71: 0.5 | G71: =C71*(1-F71) -> 35 | I71: 15 | J71: =C71 -> 70 | K71: =K70-J71 -> 2360 | L71: =K71/J71 -> 33.714286
A72: 四月 | B72: 45755 | C72: 70 | D72: =(C72-C71)/C72 -> 0 | E72: =C72*F72 -> 35 | F72: 0.5 | G72: =C72*(1-F72) -> 35 | I72: 15 | J72: =C72 -> 70 | K72: =K71-J72 -> 2290 | L72: =K72/J72 -> 32.714286
A73: 四月 | B73: 45756 | C73: 70 | D73: =(C73-C72)/C73 -> 0 | E73: =C73*F73 -> 35 | F73: 0.5 | G73: =C73*(1-F73) -> 35 | I73: 15 | J73: =C73 -> 70 | K73: =K72-J73 -> 2220 | L73: =K73/J73 -> 31.714286
A74: 四月 | B74: 45757 | C74: 70 | D74: =(C74-C73)/C74 -> 0 | E74: =C74*F74 -> 35 | F74: 0.5 | G74: =C74*(1-F74) -> 35 | I74: 15 | J74: =C74 -> 70 | K74: =K73-J74 -> 2150 | L74: =K74/J74 -> 30.714286 | O74: 所以第三个月 | P74: 新品 排行榜 | R74: 小类目 排名 | T74: 大类目 排名
A75: 四月 | B75: 45758 | C75: 70 | D75: =(C75-C74)/C75 -> 0 | E75: =C75*F75 -> 35 | F75: 0.5 | G75: =C75*(1-F75) -> 35 | I75: 15 | J75: =C75 -> 70 | K75: =K74-J75 -> 2080 | L75: =K75/J75 -> 29.714286 | O75: 第1周 | P75: NR #1 | R75: 稳定在前20名 | T75: 稳定在前7500名
A76: 四月 | B76: 45759 | C76: 70 | D76: =(C76-C75)/C76 -> 0 | E76: =C76*F76 -> 35 | F76: 0.5 | G76: =C76*(1-F76) -> 35 | I76: 15 | J76: =C76 -> 70 | K76: =K75-J76 -> 2010 | L76: =K76/J76 -> 28.714286 | O76: 第2周 | P76: NR #1 | R76: 稳定在前20名 | T76: 稳定在前7500名
A77: 四月 | B77: 45760 | C77: 70 | D77: =(C77-C76)/C77 -> 0 | E77: =C77*F77 -> 35 | F77: 0.5 | G77: =C77*(1-F77) -> 35 | I77: 15 | J77: =C77 -> 70 | K77: =K76-J77 -> 1940 | L77: =K77/J77 -> 27.714286 | O77: 第3周 | P77: NR #1 | R77: 稳定在前15名 | T77: 稳定在前5000名
A78: 四月 | B78: 45761 | C78: 75 | D78: =(C78-C77)/C78 -> 0.066666667 | E78: =C78*F78 -> 37.5 | F78: 0.5 | G78: =C78*(1-F78) -> 37.5 | I78: 15 | J78: =C78 -> 75 | K78: =K77-J78 -> 1865 | L78: =K78/J78 -> 24.866667 | O78: 第4周 | P78: NR #1 | R78: 稳定在前15名 | T78: 稳定在前5000名
A79: 四月 | B79: 45762 | C79: 75 | D79: =(C79-C78)/C79 -> 0 | E79: =C79*F79 -> 37.5 | F79: 0.5 | G79: =C79*(1-F79) -> 37.5 | I79: 15 | J79: =C79 -> 75 | K79: =K78-J79 -> 1790 | L79: =K79/J79 -> 23.866667
A80: 四月 | B80: 45763 | C80: 75 | D80: =(C80-C79)/C80 -> 0 | E80: =C80*F80 -> 37.5 | F80: 0.5 | G80: =C80*(1-F80) -> 37.5 | I80: 15 | J80: =C80 -> 75 | K80: =K79-J80 -> 1715 | L80: =K80/J80 -> 22.866667
A81: 四月 | B81: 45764 | C81: 75 | D81: =(C81-C80)/C81 -> 0 | E81: =C81*F81 -> 37.5 | F81: 0.5 | G81: =C81*(1-F81) -> 37.5 | I81: 15 | J81: =C81 -> 75 | K81: =K80-J81 -> 1640 | L81: =K81/J81 -> 21.866667
A82: 四月 | B82: 45765 | C82: 75 | D82: =(C82-C81)/C82 -> 0 | E82: =C82*F82 -> 37.5 | F82: 0.5 | G82: =C82*(1-F82) -> 37.5 | I82: 15 | J82: =C82 -> 75 | K82: =K81-J82 -> 1565 | L82: =K82/J82 -> 20.866667
A83: 四月 | B83: 45766 | C83: 80 | D83: =(C83-C82)/C83 -> 0.0625 | E83: =C83*F83 -> 40 | F83: 0.5 | G83: =C83*(1-F83) -> 40 | I83: 15 | J83: =C83 -> 80 | K83: =K82-J83 -> 1485 | L83: =K83/J83 -> 18.5625
A84: 四月 | B84: 45767 | C84: 80 | D84: =(C84-C83)/C84 -> 0 | E84: =C84*F84 -> 40 | F84: 0.5 | G84: =C84*(1-F84) -> 40 | I84: 15 | J84: =C84 -> 80 | K84: =K83-J84 -> 1405 | L84: =K84/J84 -> 17.5625
A85: 四月 | B85: 45768 | C85: 80 | D85: =(C85-C84)/C85 -> 0 | E85: =C85*F85 -> 40 | F85: 0.5 | G85: =C85*(1-F85) -> 40 | I85: 15 | J85: =C85 -> 80 | K85: =K84-J85 -> 1325 | L85: =K85/J85 -> 16.5625
A86: 四月 | B86: 45769 | C86: 80 | D86: =(C86-C85)/C86 -> 0 | E86: =C86*F86 -> 40 | F86: 0.5 | G86: =C86*(1-F86) -> 40 | I86: 15 | J86: =C86 -> 80 | K86: =K85-J86 -> 1245 | L86: =K86/J86 -> 15.5625
A87: 四月 | B87: 45770 | C87: 80 | D87: =(C87-C86)/C87 -> 0 | E87: =C87*F87 -> 40 | F87: 0.5 | G87: =C87*(1-F87) -> 40 | I87: 15 | J87: =C87 -> 80 | K87: =K86-J87 -> 1165 | L87: =K87/J87 -> 14.5625
A88: 四月 | B88: 45771 | C88: 80 | D88: =(C88-C87)/C88 -> 0 | E88: =C88*F88 -> 40 | F88: 0.5 | G88: =C88*(1-F88) -> 40 | I88: 15 | J88: =C88 -> 80 | K88: =K87-J88 -> 1085 | L88: =K88/J88 -> 13.5625
A89: 四月 | B89: 45772 | C89: 80 | D89: =(C89-C88)/C89 -> 0 | E89: =C89*F89 -> 40 | F89: 0.5 | G89: =C89*(1-F89) -> 40 | I89: 15 | J89: =C89 -> 80 | K89: =K88-J89 -> 1005 | L89: =K89/J89 -> 12.5625
A90: 四月 | B90: 45773 | C90: 80 | D90: =(C90-C89)/C90 -> 0 | E90: =C90*F90 -> 40 | F90: 0.5 | G90: =C90*(1-F90) -> 40 | I90: 15 | J90: =C90 -> 80 | K90: =K89-J90 -> 925 | L90: =K90/J90 -> 11.5625
... A94: 四月 | B94: 45777 | C94: 80 | D94: =(C94-C93)/C94 -> 0 | E94: =C94*F94 -> 40 | F94: 0.5 | G94: =C94*(1-F94) -> 40 | I94: 15 | J94: =C94 -> 80 | K94: =K93-J94 -> 605 | L94: =K94/J94 -> 7.5625
A95: 四月 | B95: 四月汇总 | C95: =SUM(C65:C94) -> 2145 | E95: =SUM(E65:E94) -> 1072.5 | F95: =E95/C95 -> 0.5 | G95: =SUM(G65:G94) -> 1072.5 | H95: 0 | I95: 34 | J95: =C95 -> 2145 | K95: 3200 | L95: =K95/J95 -> 1.4918415 | N95: IBOFYY | O95: B0BV2NVH1N | P95: 29.99 | Q95: 0 | R95: 4300 | S95: 3000 | T95: 100 | U95: 127218 | V95: 44963 | W95: 4.6 | X95: 400 | Y95: 4 | Z95: 470 | AA95: 469 | AB95: 10 | AC95: 0 | AD95: #2,571 in Tools & Home Improvement | AE95: #8 in Touch On Kitchen Sink Faucets
A96: 五月 | B96: 45778 | C96: 100 | E96: =C96*F96 -> 40 | F96: 0.4 | G96: =C96*(1-F96) -> 60 | I96: 10 | J96: =C96 -> 100 | K96: =K95+K94 -> 3805 | L96: =K96/J96 -> 38.05
A97: 五月 | B97: 45779 | C97: 100 | E97: =C97*F97 -> 40 | F97: 0.4 | G97: =C97*(1-F97) -> 60 | I97: 10 | J97: =C97 -> 100 | K97: =K96-J97 -> 3705 | L97: =K97/J97 -> 37.05
A98: 五月 | B98: 45780 | C98: 100 | E98: =C98*F98 -> 40 | F98: 0.4 | G98: =C98*(1-F98) -> 60 | I98: 10 | J98: =C98 -> 100 | K98: =K97-J98 -> 3605 | L98: =K98/J98 -> 36.05 | O98: 第四阶段 继续超越目标并稳住排名，等待BD时机，保住销量
A99: 五月 | B99: 45781 | C99: 100 | E99: =C99*F99 -> 40 | F99: 0.4 | G99: =C99*(1-F99) -> 60 | I99: 10 | J99: =C99 -> 100 | K99: =K98-J99 -> 3505 | L99: =K99/J99 -> 35.05 | O99: 同第三阶段一样，做销量突破，则必须要大额折扣配合，同时评价也要不断增加做提升一点链接竞争力。一样的要么每周LD，做突破，大额优惠锁住转化，或者站外流量补单，广告转化有限，预算有限，宁愿降价让利也不要花太大代价花广告去推，提升关键词在首页第一位置的数量
A100: 五月 | B100: 45782 | C100: 100 | E100: =C100*F100 -> 40 | F100: 0.4 | G100: =C100*(1-F100) -> 60 | I100: 10 | J100: =C100 -> 100 | K100: =K99-J100 -> 3405 | L100: =K100/J100 -> 34.05
A101: 五月 | B101: 45783 | C101: 100 | E101: =C101*F101 -> 40 | F101: 0.4 | G101: =C101*(1-F101) -> 60 | I101: 10 | J101: =C101 -> 100 | K101: =K100-J101 -> 3305 | L101: =K101/J101 -> 33.05
A102: 五月 | B102: 45784 | C102: 100 | E102: =C102*F102 -> 40 | F102: 0.4 | G102: =C102*(1-F102) -> 60 | I102: 10 | J102: =C102 -> 100 | K102: =K101-J102 -> 3205 | L102: =K102/J102 -> 32.05
A103: 五月 | B103: 45785 | C103: 100 | E103: =C103*F103 -> 40 | F103: 0.4 | G103: =C103*(1-F103) -> 60 | I103: 10 | J103: =C103 -> 100 | K103: =K102-J103 -> 3105 | L103: =K103/J103 -> 31.05
A104: 五月 | B104: 45786 | C104: 100 | E104: =C104*F104 -> 40 | F104: 0.4 | G104: =C104*(1-F104) -> 60 | I104: 10 | J104: =C104 -> 100 | K104: =K103-J104 -> 3005 | L104: =K104/J104 -> 30.05 | O104: 所以第四个月 | P104: 新品 排行榜 | R104: 小类目 排名 | T104: 大类目 排名
A105: 五月 | B105: 45787 | C105: 100 | E105: =C105*F105 -> 40 | F105: 0.4 | G105: =C105*(1-F105) -> 60 | I105: 10 | J105: =C105 -> 100 | K105: =K104-J105 -> 2905 | L105: =K105/J105 -> 29.05 | O105: 第1周 | P105: / | R105: 稳定在前12名 | T105: 稳定在前4000名
A106: 五月 | B106: 45788 | C106: 100 | E106: =C106*F106 -> 40 | F106: 0.4 | G106: =C106*(1-F106) -> 60 | I106: 10 | J106: =C106 -> 100 | K106: =K105-J106 -> 2805 | L106: =K106/J106 -> 28.05 | O106: 第2周 | P106: / | R106: 稳定在前12名 | T106: 稳定在前4000名
A107: 五月 | B107: 45789 | C107: 100 | E107: =C107*F107 -> 40 | F107: 0.4 | G107: =C107*(1-F107) -> 60 | I107: 10 | J107: =C107 -> 100 | K107: =K106-J107 -> 2705 | L107: =K107/J107 -> 27.05 | O107: 第3周 | P107: / | R107: 稳定在前10名 | T107: 稳定在前3000名
A108: 五月 | B108: 45790 | C108: 100 | E108: =C108*F108 -> 40 | F108: 0.4 | G108: =C108*(1-F108) -> 60 | I108: 10 | J108: =C108 -> 100 | K108: =K107-J108 -> 2605 | L108: =K108/J108 -> 26.05 | O108: 第4周 | P108: / | R108: 稳定在前10名 | T108: 稳定在前3000名
A109: 五月 | B109: 45791 | C109: 100 | E109: =C109*F109 -> 40 | F109: 0.4 | G109: =C109*(1-F109) -> 60 | I109: 10 | J109: =C109 -> 100 | K109: =K108-J109 -> 2505 | L109: =K109/J109 -> 25.05
A110: 五月 | B110: 45792 | C110: 100 | E110: =C110*F110 -> 40 | F110: 0.4 | G110: =C110*(1-F110) -> 60 | I110: 10 | J110: =C110 -> 100 | K110: =K109-J110 -> 2405 | L110: =K110/J110 -> 24.05
A111: 五月 | B111: 45793 | C111: 100 | E111: =C111*F111 -> 40 | F111: 0.4 | G111: =C111*(1-F111) -> 60 | I111: 10 | J111: =C111 -> 100 | K111: =K110-J111 -> 2305 | L111: =K111/J111 -> 23.05
A112: 五月 | B112: 45794 | C112: 100 | E112: =C112*F112 -> 40 | F112: 0.4 | G112: =C112*(1-F112) -> 60 | I112: 10 | J112: =C112 -> 100 | K112: =K111-J112 -> 2205 | L112: =K112/J112 -> 22.05
A113: 五月 | B113: 45795 | C113: 100 | E113: =C113*F113 -> 40 | F113: 0.4 | G113: =C113*(1-F113) -> 60 | I113: 10 | J113: =C113 -> 100 | K113: =K112-J113 -> 2105 | L113: =K113/J113 -> 21.05
...

Sheet 盈亏核算-汇总
A1: 【产品定位及销售目标预测】 | B1: 月份 | C1: 2月 | D1: 3月 | E1: 4月 | F1: 5月 | G1: 6月 | H1: 7月 | I1: 合计
A2: 产品图片 产品名称： 站点：US 品牌： lisitng负责人： listing所属团队： 开售时间：2024年11月13日 产品等级定位：头部 ASIN： 子ASIN | B2: listing售价 | C2: =阶段盈亏!C3 -> 54.99 | D2: =阶段盈亏!C7 -> 54.99 | E2: =阶段盈亏!C11 -> 54.99 | F2: =阶段盈亏!C15 -> 49.99 | G2: =阶段盈亏!C19 -> 49.99 | H2: =阶段盈亏!C23 -> 36.99 | I2: =H2 -> 36.99
B3: 净售价 | C3: =C2*(1-C4) -> 32.994 | D3: =D2*(1-D4) -> 27.495 | E3: =E2*(1-E4) -> 24.7455 | F3: =F2*(1-F4) -> 32.4935 | G3: =G2*(1-G4) -> 37.4925 | H3: =H2*(1-H4) -> 36.99 | I3: =H3 -> 36.99
B4: 折扣占比% | C4: 0.4 | D4: 0.5 | E4: 0.55 | F4: 0.35 | G4: 0.25 | H4: 0 | I4: =H4 -> 0
B5: 采购 | C5: 10 | D5: 10 | E5: 10 | F5: 10 | G5: 10 | H5: 10 | I5: =H5 -> 10
B6: 头程 | C6: 4 | D6: 4 | E6: 4 | F6: 4 | G6: 4 | H6: 4 | I6: =H6 -> 4 | K6: 填写黄色数字项
B7: AMZ佣金 | C7: 0.15 | D7: 0.15 | E7: 0.15 | F7: 0.15 | G7: 0.15 | H7: 0.15 | I7: =H7 -> 0.15
B8: FBA配送费 | C8: 7.86 | D8: 7.86 | E8: 7.86 | F8: 7.86 | G8: 7.86 | H8: 7.86 | I8: =H8 -> 7.86
B9: 仓储 | C9: 0.1 | D9: 0.1 | E9: 0.1 | F9: 0.1 | G9: 0.1 | H9: 0.1 | I9: =H9 -> 0.1
B10: 优惠劵fee | C10: 0.6 | D10: 0.6 | E10: 0.6 | F10: 0.6 | G10: 0.6 | H10: 0.6 | I10: =H10 -> 0.6
B11: 领取coupon | C11: 0.4 | D11: 0.4 | E11: 0.4 | F11: 0.3 | G11: 0.3 | H11: 0 | I11: =H11 -> 0
B12: 未领取coupon | C12: 0.6 | D12: 0.6 | E12: 0.6 | F12: 0.7 | G12: 0.7 | H12: 1 | I12: =H12 -> 1
B13: 销量 | C13: ='二、BSR排名销量计划（日月-目标）'!C32 -> 517 | D13: ='二、BSR排名销量计划（日月-目标）'!C64 -> 1271 | E13: ='二、BSR排名销量计划（日月-目标）'!C95 -> 2145 | F13: ='二、BSR排名销量计划（日月-目标）'!C127 -> 3100 | G13: ='二、BSR排名销量计划（日月-目标）'!C158 -> 4020 | H13: ='二、BSR排名销量计划（日月-目标）'!C190 -> 4650 | I13: =SUM(C13:H13) -> 15703
B14: 产品成本货值 | C14: =(C5+C6)*C13 -> 7238 | D14: =(D5+D6)*D13 -> 17794 | E14: =(E5+E6)*E13 -> 30030 | F14: =(F5+F6)*F13 -> 43400 | G14: =(G5+G6)*G13 -> 56280 | H14: =(H5+H6)*H13 -> 65100 | I14: =SUM(C14:H14) -> 219842 | J14: =I14*7 -> 1538894
B15: 净销售额 | C15: =C13*C3 -> 17057.898 | D15: =D13*D3 -> 34946.145 | E15: =E13*E3 -> 53079.098 | F15: =F13*F3 -> 100729.85 | G15: =G13*G3 -> 150719.85 | H15: =H13*H3 -> 172003.5 | I15: =SUM(C15:H15) -> 528536.34
B16: 广告花费 | C16: =-SUM(阶段盈亏!L3:L6) -> 13687.5 | D16: =-SUM(阶段盈亏!L7:L10) -> 27017 | E16: =-SUM(阶段盈亏!L11:L14) -> 26486.667 | F16: =-SUM(阶段盈亏!L15:L18) -> 22545.455 | G16: =-SUM(阶段盈亏!L19:L22) -> 18090 | H16: =-SUM(阶段盈亏!L23:L26) -> 12400 | I16: =SUM(C16:H16) -> 120226.62 | J16: =I16*7 -> 841586.35
B17: ACOAs% | C17: =C16/C15 -> 0.80241422 | D17: =D16/D15 -> 0.77310387 | E17: =E16/E15 -> 0.49900371 | F17: =F16/F15 -> 0.22382099 | G17: =G16/G15 -> 0.120024 | H17: =H16/H15 -> 0.072091556 | I17: =I16/I15 -> 0.22747087
B18: 广告单占比 | C18: =SUM(阶段盈亏!H3:H6)/SUM(阶段盈亏!I3:I6) -> 0.70599613 | D18: =SUM(阶段盈亏!H7:H10)/SUM(阶段盈亏!I7:I10) -> 0.59952793 | E18: =SUM(阶段盈亏!H11:H14)/SUM(阶段盈亏!I11:I14) -> 0.4997669 | F18: =SUM(阶段盈亏!H15:H18)/SUM(阶段盈亏!I15:I18) -> 0.4 | G18: =SUM(阶段盈亏!H19:H22)/SUM(阶段盈亏!I19:I22) -> 0.3 | H18: =SUM(阶段盈亏!H23:H26)/SUM(阶段盈亏!I23:I26) -> 0.2 | I18: =H18 -> 0.2
B19: CPC | C19: =AVERAGE(CPC表格!S4:S7) -> 3 | D19: =AVERAGE(CPC表格!S8:S11) -> 3.625 | E19: =AVERAGE(CPC表格!S12:S15) -> 3 | F19: =AVERAGE(CPC表格!S16:S19) -> 2 | G19: =AVERAGE(CPC表格!S20:S23) -> 1.5 | H19: =AVERAGE(CPC表格!S24:S27) -> 1.2 | I19: =H19 -> 1.2
B20: ACOS% | C20: =C19/C21/C3 -> 1.1365703 | D20: 0.35 | E20: 0.3 | F20: 0.25 | G20: 0.25 | H20: 0.25 | I20: =H20 -> 0.25
B21: ASIN转化率% | C21: 0.08 | D21: 0.1 | E21: 0.12 | F21: 0.11 | G21: 0.1 | H21: 0.09 | I21: =H21 -> 0.09
B22: 退款率% | C22: 0.08 | D22: 0.08 | E22: 0.08 | F22: 0.08 | G22: 0.08 | H22: 0.08 | I22: =H22 -> 0.08
B23: 种子链接成本 | C23: =五、评论策略!K2/7+600 -> 4654 | D23: =五、评论策略!K3/7 -> 4054 | E23: =五、评论策略!K4/7 -> 5422 | F23: =五、评论策略!K5/7 -> 6765 | G23: =五、评论策略!K6/7 -> 8108 | H23: =五、评论策略!K7/7 -> 8108 | I23: =SUM(C23:H23) -> 37111 | J23: =I23*7 -> 259777
B24: 净毛利润 | C24: =SUM(阶段盈亏!N3:N6) -> -12088.074 | D24: =SUM(阶段盈亏!N7:N10) -> -29024.336 | E24: =SUM(阶段盈亏!N11:N14) -> -34886.137 | F24: =SUM(阶段盈亏!N15:N18) -> -14273.582 | G24: =SUM(阶段盈亏!N19:N22) -> 9714.1397 | H24: =SUM(阶段盈亏!N23:N26) -> 20565.861 | I24: =SUM(C24:H24) -> -59992.129 | J24: 成本合计 | K24: =J23+J16+J14 -> 2640257.3
B25: 净毛利润率% | C25: =C24/C15 -> -0.70864971 | D25: =D24/D15 -> -0.83054471 | E25: =E24/E15 -> -0.65724812 | F25: =F24/F15 -> -0.14170161 | G25: =G24/G15 -> 0.064451628 | H25: =H24/H15 -> 0.11956653 | I25: =I24/I15 -> -0.11350616
B26: 平均评分及数量 | C26: 4.8/150 | D26: 4.7/300 | E26: 4.6/500 | F26: 4.5/750 | G26: 4.5/1050 | H26: 4.5/1350 | I26: =H26 -> 4.5/1350
B27: ASIN所在节点 | C27: #Touch On Kitchen Sink Faucets | D27: #Touch On Kitchen Sink Faucets | E27: #Touch On Kitchen Sink Faucets | F27: #Touch On Kitchen Sink Faucets | G27: #Touch On Kitchen Sink Faucets | H27: #Touch On Kitchen Sink Faucets | I27: =H27 -> #Touch On Kitchen Sink Faucets
B28: 排名(定位) | C28: #30 | D28: #20 | E28: #15 | F28: #10 | G28: #6 | H28: #5 | I28: =H28 -> #5
A29: 新品至少做半年6个月的销售预测数据，主要看下该项目的销售数据，以及经营数据的情况。
A30: 【新品销售趋势图】 | H30: 【新品销售额VS利润趋势图】

Sheet 阶段盈亏
A1: 阶段盈亏模拟数据
A2: 阶段 | B2: 日期 | C2: 定价 | D2: cou pon | E2: code | F2: 折后价 | G2: 自然单 | H2: 站内 广告单 | I2: 阶段 销售 订单 | J2: 时间 /天 | K2: CPA | L2: 阶段 广告费 | M2: 阶段订单 盈亏 | N2: 阶段盈亏 /美金 | O2: 评论 数量 | P2: 阶段 日均 订单 | Q2: 阶段 日均 广告单 | R2: 阶段 日均 自然单 | S2: 日均 广告费 | T2: 小类目 排名 | U2: 大类目 排名 | V2: 备注 | W2: 种子评论费/（开5条VINE，预计来150条评论）,视觉化费用预估1100美金 | X2: 前期亏损/美金 | Y2: 人民币
A3: 第一阶段 | B3: 第1周 | C3: 54.99 | D3: 0.3 | E3: 0.1 | F3: =SUM(C3*(1-D3-E3)) -> 32.994 | G3: 5 | H3: 24 | I3: =SUM(G3:H3) -> 29 | J3: 7 | K3: =CPC表格!V4 -> 37.5 | L3: =SUM(H3*-K3) -> -900 | M3: =毛利表格!T3 -> 89.716328 | N3: =SUM(L3:M3) -> -810.28367 | O3: 150 | P3: =SUM(I3/J3) -> 4.1428571 | Q3: =SUM(H3/J3) -> 3.4285714 | R3: =SUM(G3/J3) -> 0.71428571 | S3: =SUM(L3/J3) -> -128.57143 | T3: 稳定在前120名 | U3: 稳定在前120000名 | V3: 一开售投放广告 | W3: =-(10*150+1000+1100) -> -3600 | X3: =SUM(N3:N6)+W3 -> -15688.074 | Y3: =X3*7 -> -109816.52
B4: 第2周 | C4: 54.99 | D4: 0.3 | E4: 0.1 | F4: =SUM(C4*(1-D4-E4)) -> 32.994 | G4: 31 | H4: 72 | I4: =SUM(G4:H4) -> 103 | J4: 7 | K4: =CPC表格!V5 -> 37.5 | L4: =SUM(H4*-K4) -> -2700 | M4: =毛利表格!T4 -> 318.64765 | N4: =SUM(L4:M4) -> -2381.3524 | P4: =SUM(I4/J4) -> 14.714286 | Q4: =SUM(H4/J4) -> 10.285714 | R4: =SUM(G4/J4) -> 4.4285714 | S4: =SUM(L4/J4) -> -385.71429 | T4: 稳定在前100名 | U4: 稳定在前30000名 | V4: 第一个月 | W4: 视觉=拍摄+主图视频+买家秀
B5: 第3周 | C5: 54.99 | D5: 0.3 | E5: 0.1 | F5: =SUM(C5*(1-D5-E5)) -> 32.994 | G5: 54 | H5: 125 | I5: =SUM(G5:H5) -> 179 | J5: 7 | K5: =CPC表格!V6 -> 37.5 | L5: =SUM(H5*-K5) -> -4687.5 | M5: =毛利表格!T5 -> 553.7663 | N5: =SUM(L5:M5) -> -4133.7337 | P5: =SUM(I5/J5) -> 25.571429 | Q5: =SUM(H5/J5) -> 17.857143 | R5: =SUM(G5/J5) -> 7.7142857 | S5: =SUM(L5/J5) -> -669.64286 | T5: 稳定在前50名 | U5: 稳定在前17000名
B6: 第4周 | C6: 54.99 | D6: 0.3 | E6: 0.1 | F6: =SUM(C6*(1-D6-E6)) -> 32.994 | G6: 62 | H6: 144 | I6: =SUM(G6:H6) -> 206 | J6: 7 | K6: =CPC表格!V7 -> 37.5 | L6: =SUM(H6*-K6) -> -5400 | M6: =毛利表格!T6 -> 637.29529 | N6: =SUM(L6:M6) -> -4762.7047 | P6: =SUM(I6/J6) -> 29.428571 | Q6: =SUM(H6/J6) -> 20.571429 | R6: =SUM(G6/J6) -> 8.8571429 | S6: =SUM(L6/J6) -> -771.42857 | T6: 稳定在前30名 | U6: 稳定在前10000名
A7: 第二阶段 | B7: 第5周 | C7: 54.99 | D7: 0.4 | E7: 0.1 | F7: =SUM(C7*(1-D7-E7)) -> 27.495 | G7: 97 | H7: 145 | I7: =SUM(G7:H7) -> 242 | J7: 7 | K7: =CPC表格!V8 -> 40 | L7: =SUM(H7*-K7) -> -5800 | M7: =毛利表格!T7 -> -382.19929 | N7: =SUM(L7:M7) -> -6182.1993 | O7: 300 | P7: =SUM(I7/J7) -> 34.571429 | Q7: =SUM(H7/J7) -> 20.714286 | R7: =SUM(G7/J7) -> 13.857143 | S7: =SUM(L7/J7) -> -828.57143 | T7: 稳定在前30名 | U7: 稳定在前10000名 | V7: 第二个月 | W7: 上个月亏损/美金 | X7: 累计亏损/美金 | Y7: 人民币
B8: 第6周 | C8: 54.99 | D8: 0.4 | E8: 0.1 | F8: =SUM(C8*(1-D8-E8)) -> 27.495 | G8: 104 | H8: 156 | I8: =SUM(G8:H8) -> 260 | J8: 7 | K8: =CPC表格!V9 -> 38 | L8: =SUM(H8*-K8) -> -5928 | M8: =毛利表格!T8 -> -410.62734 | N8: =SUM(L8:M8) -> -6338.6273 | P8: =SUM(I8/J8) -> 37.142857 | Q8: =SUM(H8/J8) -> 22.285714 | R8: =SUM(G8/J8) -> 14.857143 | S8: =SUM(L8/J8) -> -846.85714 | T8: 稳定在前30名 | U8: 稳定在前10000名 | W8: =X3 -> -15688.074 | X8: =W8+SUM(N7:N10) -> -44712.41 | Y8: =X8*7 -> -312986.87
B9: 第7周 | C9: 54.99 | D9: 0.4 | E9: 0.1 | F9: =SUM(C9*(1-D9-E9)) -> 27.495 | G9: 120 | H9: 179 | I9: =SUM(G9:H9) -> 299 | J9: 7 | K9: =CPC表格!V10 -> 35 | L9: =SUM(H9*-K9) -> -6265 | M9: =毛利表格!T9 -> -472.22144 | N9: =SUM(L9:M9) -> -6737.2214 | P9: =SUM(I9/J9) -> 42.714286 | Q9: =SUM(H9/J9) -> 25.571429 | R9: =SUM(G9/J9) -> 17.142857 | S9: =SUM(L9/J9) -> -895 | T9: 稳定在前25名 | U9: 稳定在前8000名
B10: 第8周 | C10: 54.99 | D10: 0.4 | E10: 0.1 | F10: =SUM(C10*(1-D10-E10)) -> 27.495 | G10: 188 | H10: 282 | I10: =SUM(G10:H10) -> 470 | J10: 10 | K10: =CPC表格!V11 -> 32 | L10: =SUM(H10*-K10) -> -9024 | M10: =毛利表格!T10 -> -742.28788 | N10: =SUM(L10:M10) -> -9766.2879 | P10: =SUM(I10/J10) -> 47 | Q10: =SUM(H10/J10) -> 28.2 | R10: =SUM(G10/J10) -> 18.8 | S10: =SUM(L10/J10) -> -902.4 | T10: 稳定在前20名 | U10: 稳定在前7500名
A11: 第三阶段 | B11: 第9周 | C11: 54.99 | D11: 0.4 | E11: 0.15 | F11: =SUM(C11*(1-D11-E11)) -> 24.7455 | G11: 195 | H11: 195 | I11: =SUM(G11:H11) -> 390 | J11: 7 | K11: =CPC表格!V12 -> 26.666667 | L11: =SUM(H11*-K11) -> -5200 | M11: =毛利表格!T11 -> -1527.1765 | N11: =SUM(L11:M11) -> -6727.1765 | O11: 450 | P11: =SUM(I11/J11) -> 55.714286 | Q11: =SUM(H11/J11) -> 27.857143 | R11: =SUM(G11/J11) -> 27.857143 | S11: =SUM(L11/J11) -> -742.85714 | T11: 稳定在前20名 | U11: 稳定在前7500名 | V11: 第三个月 | W11: 上个月亏损/美金 | X11: 累计亏损/美金 | Y11: 人民币
B12: 第10周 | C12: 54.99 | D12: 0.4 | E12: 0.15 | F12: =SUM(C12*(1-D12-E12)) -> 24.7455 | G12: 248 | H12: 247 | I12: =SUM(G12:H12) -> 495 | J12: 7 | K12: =CPC表格!V13 -> 26.666667 | L12: =SUM(H12*-K12) -> -6586.6667 | M12: =毛利表格!T12 -> -1938.3394 | N12: =SUM(L12:M12) -> -8525.006 | P12: =SUM(I12/J12) -> 70.714286 | Q12: =SUM(H12/J12) -> 35.285714 | R12: =SUM(G12/J12) -> 35.428571 | S12: =SUM(L12/J12) -> -940.95238 | T12: 稳定在前20名 | U12: 稳定在前7500名 | W12: =X8 -> -44712.41 | X12: =W12+SUM(N11:N14) -> -79598.548 | Y12: =X12*7 -> -557189.83
B13: 第11周 | C13: 54.99 | D13: 0.4 | E13: 0.15 | F13: =SUM(C13*(1-D13-E13)) -> 24.7455 | G13: 270 | H13: 270 | I13: =SUM(G13:H13) -> 540 | J13: 7 | K13: =CPC表格!V14 -> 23.333333 | L13: =SUM(H13*-K13) -> -6300 | M13: =毛利表格!T13 -> -2114.552 | N13: =SUM(L13:M13) -> -8414.552 | P13: =SUM(I13/J13) -> 77.142857 | Q13: =SUM(H13/J13) -> 38.571429 | R13: =SUM(G13/J13) -> 38.571429 | S13: =SUM(L13/J13) -> -900 | T13: 稳定在前15名 | U13: 稳定在前5000名
B14: 第12周 | C14: 54.99 | D14: 0.4 | E14: 0.15 | F14: =SUM(C14*(1-D14-E14)) -> 24.7455 | G14: 360 | H14: 360 | I14: =SUM(G14:H14) -> 720 | J14: 9 | K14: =CPC表格!V15 -> 23.333333 | L14: =SUM(H14*-K14) -> -8400 | M14: =毛利表格!T14 -> -2819.4027 | N14: =SUM(L14:M14) -> -11219.403 | P14: =SUM(I14/J14) -> 80 | Q14: =SUM(H14/J14) -> 40 | R14: =SUM(G14/J14) -> 40 | S14: =SUM(L14/J14) -> -933.33333 | T14: 稳定在前15名 | U14: 稳定在前5000名
A15: 第四阶段 | B15: 第13周 | C15: 49.99 | D15: 0.35 | E15: 0 | F15: =SUM(C15*(1-D15-E15)) -> 32.4935 | G15: 420 | H15: 280 | I15: =SUM(G15:H15) -> 700 | J15: 7 | K15: =CPC表格!V16 -> 18.181818 | L15: =SUM(H15*-K15) -> -5090.9091 | M15: =毛利表格!T15 -> 1867.8421 | N15: =SUM(L15:M15) -> -3223.0669 | O15: 600 | P15: =SUM(I15/J15) -> 100 | Q15: =SUM(H15/J15) -> 40 | R15: =SUM(G15/J15) -> 60 | S15: =SUM(L15/J15) -> -727.27273 | T15: 稳定在前12名 | U15: 稳定在前4000名 | V15: 第四个月 | W15: 上个月亏损/美金 | X15: 累计亏损/美金 | Y15: 人民币
B16: 第14周 | C16: 49.99 | D16: 0.35 | E16: 0 | F16: =SUM(C16*(1-D16-E16)) -> 32.4935 | G16: 420 | H16: 280 | I16: =SUM(G16:H16) -> 700 | J16: 7 | K16: =CPC表格!V17 -> 18.181818 | L16: =SUM(H16*-K16) -> -5090.9091 | M16: =毛利表格!T16 -> 1867.8421 | N16: =SUM(L16:M16) -> -3223.0669 | P16: =SUM(I16/J16) -> 100 | Q16: =SUM(H16/J16) -> 40 | R16: =SUM(G16/J16) -> 60 | S16: =SUM(L16/J16) -> -727.27273 | T16: 稳定在前12名 | U16: 稳定在前4000名 | W16: =X12 -> -79598.548 | X16: =W16+SUM(N15:N18) -> -93872.13 | Y16: =X16*7 -> -657104.91
B17: 第15周 | C17: 49.99 | D17: 0.35 | E17: 0 | F17: =SUM(C17*(1-D17-E17)) -> 32.4935 | G17: 420 | H17: 280 | I17: =SUM(G17:H17) -> 700 | J17: 7 | K17: =CPC表格!V18 -> 18.181818 | L17: =SUM(H17*-K17) -> -5090.9091 | M17: =毛利表格!T17 -> 1867.8421 | N17: =SUM(L17:M17) -> -3223.0669 | P17: =SUM(I17/J17) -> 100 | Q17: =SUM(H17/J17) -> 40 | R17: =SUM(G17/J17) -> 60 | S17: =SUM(L17/J17) -> -727.27273 | T17: 稳定在前10名 | U17: 稳定在前3000名
B18: 第16周 | C18: 49.99 | D18: 0.35 | E18: 0 | F18: =SUM(C18*(1-D18-E18)) -> 32.4935 | G18: 600 | H18: 400 | I18: =SUM(G18:H18) -> 1000 | J18: 10 | K18: =CPC表格!V19 -> 18.181818 | L18: =SUM(H18*-K18) -> -7272.7273 | M18: =毛利表格!T18 -> 2668.3459 | N18: =SUM(L18:M18) -> -4604.3814 | P18: =SUM(I18/J18) -> 100 | Q18: =SUM(H18/J18) -> 40 | R18: =SUM(G18/J18) -> 60 | S18: =SUM(L18/J18) -> -727.27273 | T18: 稳定在前10名 | U18: 稳定在前3000名
A19: 第五阶段 | B19: 第17周 | C19: 49.99 | D19: 0.25 | E19: 0 | F19: =SUM(C19*(1-D19-E19)) -> 37.4925 | G19: 567 | H19: 243 | I19: =SUM(G19:H19) -> 810 | J19: 7 | K19: =CPC表格!V20 -> 15 | L19: =SUM(H19*-K19) -> -3645 | M19: =毛利表格!T19 -> 5602.3266 | N19: =SUM(L19:M19) -> 1957.3266 | O19: 750 | P19: =SUM(I19/J19) -> 115.71429 | Q19: =SUM(H19/J19) -> 34.714286 | R19: =SUM(G19/J19) -> 81 | S19: =SUM(L19/J19) -> -520.71429 | T19: 稳定在前10名 | U19: 稳定在前3000名 | V19: 第五个月 | W19: 上个月亏损/美金 | X19: 累计亏损/美金 | Y19: 人民币
B20: 第18周 | C20: 49.99 | D20: 0.25 | E20: 0 | F20: =SUM(C20*(1-D20-E20)) -> 37.4925 | G20: 588 | H20: 252 | I20: =SUM(G20:H20) -> 840 | J20: 7 | K20: =CPC表格!V21 -> 15 | L20: =SUM(H20*-K20) -> -3780 | M20: =毛利表格!T20 -> 5809.8202 | N20: =SUM(L20:M20) -> 2029.8202 | P20: =SUM(I20/J20) -> 120 | Q20: =SUM(H20/J20) -> 36 | R20: =SUM(G20/J20) -> 84 | S20: =SUM(L20/J20) -> -540 | T20: 稳定在前8名 | U20: 稳定在前2500名 | W20: =X16 -> -93872.13 | X20: =W20+SUM(N19:N22) -> -84157.99 | Y20: =X20*7 -> -589105.93
B21: 第19周 | C21: 49.99 | D21: 0.25 | E21: 0 | F21: =SUM(C21*(1-D21-E21)) -> 37.4925 | G21: 714 | H21: 306 | I21: =SUM(G21:H21) -> 1020 | J21: 7 | K21: =CPC表格!V22 -> 15 | L21: =SUM(H21*-K21) -> -4590 | M21: =毛利表格!T21 -> 7054.7817 | N21: =SUM(L21:M21) -> 2464.7817 | P21: =SUM(I21/J21) -> 145.71429 | Q21: =SUM(H21/J21) -> 43.714286 | R21: =SUM(G21/J21) -> 102 | S21: =SUM(L21/J21) -> -655.71429 | T21: 稳定在前5名 | U21: 稳定在前1500名
B22: 第20周 | C22: 49.99 | D22: 0.25 | E22: 0 | F22: =SUM(C22*(1-D22-E22)) -> 37.4925 | G22: 945 | H22: 405 | I22: =SUM(G22:H22) -> 1350 | J22: 9 | K22: =CPC表格!V23 -> 15 | L22: =SUM(H22*-K22) -> -6075 | M22: =毛利表格!T22 -> 9337.2111 | N22: =SUM(L22:M22) -> 3262.2111 | P22: =SUM(I22/J22) -> 150 | Q22: =SUM(H22/J22) -> 45 | R22: =SUM(G22/J22) -> 105 | S22: =SUM(L22/J22) -> -675 | T22: 稳定在前5名 | U22: 稳定在前1500名
A23: 第六阶段 | B23: 第21周 | C23: 36.99 | D23: 0 | E23: 0 | F23: =SUM(C23*(1-D23-E23)) -> 36.99 | G23: 840 | H23: 210 | I23: =SUM(G23:H23) -> 1050 | J23: 7 | K23: =CPC表格!V24 -> 13.333333 | L23: =SUM(H23*-K23) -> -2800 | M23: =毛利表格!T23 -> 7443.9041 | N23: =SUM(L23:M23) -> 4643.9041 | O23: 900 | P23: =SUM(I23/J23) -> 150 | Q23: =SUM(H23/J23) -> 30 | R23: =SUM(G23/J23) -> 120 | S23: =SUM(L23/J23) -> -400 | T23: 稳定在前5名 | U23: 稳定在前1500名 | V23: 第六个月 | W23: 上个月亏损/美金 | X23: 累计亏损/美金 | Y23: 人民币
B24: 第22周 | C24: 36.99 | D24: 0 | E24: 0 | F24: =SUM(C24*(1-D24-E24)) -> 36.99 | G24: 840 | H24: 210 | I24: =SUM(G24:H24) -> 1050 | J24: 7 | K24: =CPC表格!V25 -> 13.333333 | L24: =SUM(H24*-K24) -> -2800 | M24: =毛利表格!T24 -> 7443.9041 | N24: =SUM(L24:M24) -> 4643.9041 | P24: =SUM(I24/J24) -> 150 | Q24: =SUM(H24/J24) -> 30 | R24: =SUM(G24/J24) -> 120 | S24: =SUM(L24/J24) -> -400 | T24: 稳定在前5名 | U24: 稳定在前1500名 | W24: =X20 -> -84157.99 | X24: =W24+SUM(N23:N26) -> -63592.129 | Y24: =X24*7 -> -445144.9
B25: 第23周 | C25: 36.99 | D25: 0 | E25: 0 | F25: =SUM(C25*(1-D25-E25)) -> 36.99 | G25: 840 | H25: 210 | I25: =SUM(G25:H25) -> 1050 | J25: 7 | K25: =CPC表格!V26 -> 13.333333 | L25: =SUM(H25*-K25) -> -2800 | M25: =毛利表格!T25 -> 7443.9041 | N25: =SUM(L25:M25) -> 4643.9041 | P25: =SUM(I25/J25) -> 150 | Q25: =SUM(H25/J25) -> 30 | R25: =SUM(G25/J25) -> 120 | S25: =SUM(L25/J25) -> -400 | T25: 稳定在前5名 | U25: 稳定在前1500名 | W25: 第5个月开始挣钱，第9个月回本
B26: 第24周 | C26: 36.99 | D26: 0 | E26: 0 | F26: =SUM(C26*(1-D26-E26)) -> 36.99 | G26: 1200 | H26: 300 | I26: =SUM(G26:H26) -> 1500 | J26: 10 | K26: =CPC表格!V27 -> 13.333333 | L26: =SUM(H26*-K26) -> -4000 | M26: =毛利表格!T26 -> 10634.149 | N26: =SUM(L26:M26) -> 6634.1488 | P26: =SUM(I26/J26) -> 150 | Q26: =SUM(H26/J26) -> 30 | R26: =SUM(G26/J26) -> 120 | S26: =SUM(L26/J26) -> -400 | T26: 稳定在前5名 | U26: 稳定在前1500名

Sheet 价格策略模拟
A1: 产品名 | B1: 推品时间 | C1: 订单类型 | D1: 定价 | E1: 会员折扣/7天秒杀 | F1: coupon/code/LD | G1: 折扣价 | H1: FBA配送费 | I1: 佣金 | J1: 每单账号回款 | K1: 仓储费 | L1: coupon费用 | M1: 产品成本 | N1: 海运费 | O1: 退货成本 | P1: 退货率 | Q1: 每单平摊 退货成本 | R1: 每单毛利 (不含广告） | S1: 毛利率 （最高ACOS) | T1: 广告占比 | U1: 广告花费 | V1: 广告花费占比 | W1: 毛利盈亏 （包含广告） | X1: 毛利盈亏 （包含广告）
B2: 定价表 | C2: 正常价 | D2: 54.99 | E2: 0 | F2: 0.4 | G2: =(D2*(1-E2))*(1-F2) -> 32.994 | H2: 7.86 | I2: =G2*0.15 -> 4.9491 | J2: =G2-H2-I2 -> 20.1849 | K2: 0.3 | L2: 0.6 | M2: 10 | N2: 4 | O2: =M2+N2+I2*20%+H2+L2+K2 -> 23.74982 | P2: 0.08 | Q2: =O2*P2 -> 1.8999856 | R2: =G2-H2-I2-K2-L2-M2-N2-Q2 -> 3.3849144 | S2: =R2/G2 -> 0.10259182 | T2: 0.05 | U2: =T2*G2 -> 1.6497 | V2: =U2/G2 -> 0.05 | W2: =R2-U2 -> 1.7352144 | X2: =W2/G2 -> 0.052591817
C3: 秒杀价 | D3: 54.99 | E3: 0.15 | F3: 0.4 | G3: =D3-(D3*E3)-(D3*F3) -> 24.7455 | H3: 7.86 | I3: =G3*0.15 -> 3.711825 | J3: =G3-H3-I3 -> 13.173675 | K3: 0.3 | L3: 0.6 | M3: 10 | N3: 4 | O3: =M3+N3+I3*20%+H3+L3+K3 -> 23.502365 | P3: 0.08 | Q3: =O3*P3 -> 1.8801892 | R3: =G3-H3-I3-K3-L3-M3-N3-Q3 -> -3.6065142 | S3: =R3/G3 -> -0.14574424 | T3: 0.05 | U3: =T3*G3 -> 1.237275 | V3: =U3/G3 -> 0.05 | W3: =R3-U3 -> -4.8437892 | X3: =W3/G3 -> -0.19574424
C4: 平本价 | D4: 54.99 | E4: 0 | F4: 0.5 | G4: =D4-(D4*E4)-(D4*F4) -> 27.495 | H4: 7.86 | I4: =G4*0.15 -> 4.12425 | J4: =G4-H4-I4 -> 15.51075 | K4: 0.3 | L4: 0.6 | M4: 10 | N4: 4 | O4: =M4+N4+I4*20%+H4+L4+K4 -> 23.58485 | P4: 0.08 | Q4: =O4*P4 -> 1.886788 | R4: =G4-H4-I4-K4-L4-M4-N4-Q4 -> -1.276038 | S4: =R4/G4 -> -0.04640982 | T4: 0 | U4: =T4*G4 -> 0 | V4: =U4/G4 -> 0 | W4: =R4-U4 -> -1.276038 | X4: =W4/G4 -> -0.04640982
A6: 阶段 | B6: 定价 | C6: coupon | D6: code/JP | E6: 折后价 | F6: FBA 配送费 | G6: 亚马逊 佣金 | H6: 账号 回款 | I6: 仓储费+入库配置费 | J6: coupon 费用 | K6: 产品 成本 | L6: 物流费 | M6: 退货成本(公式后面加的是单套产品的移除费） | N6: 退货率 | O6: 每单平摊 退货成本 | P6: 每单 毛利 | Q6: 毛利率 | R6: 订单 数量 | S6: 阶段 订单 亏损 | T6: 阶段 订单 总盈亏
A7: 第一阶段 | B7: 54.99 | C7: 0.3 | D7: 0.1 | E7: =SUM(B7*(1-C7-D7)) -> 32.994 | F7: 7.86 | G7: =SUM(E7*15%) -> 4.9491 | H7: =SUM(E7-F7-G7) -> 20.1849 | I7: =0.08+0.34 -> 0.42 | J7: 0.6 | K7: 10 | L7: 4 | M7: =SUM(20%*N7*G7+F7+I7+K7+L7+1.46) -> 23.819186 | N7: 0.08 | O7: =SUM(M7*N7/(1-N7)) -> 2.0712335 | P7: =SUM(H7-I7-J7-K7-L7-O7) -> 3.0936665 | Q7: =SUM(P7/B7) -> 0.05625871 | R7: 1 | S7: =SUM(P7*R7) -> 3.0936665 | T7: =SUM(S7:S7) -> 3.0936665
A8: 第二阶段 | B8: 54.99 | C8: 0.4 | D8: 0.1 | E8: =SUM(B8*(1-C8-D8)) -> 27.495 | F8: 7.86 | G8: =SUM(E8*15%) -> 4.12425 | H8: =SUM(E8-F8-G8) -> 15.51075 | I8: =0.08+0.34 -> 0.42 | J8: 0.6 | K8: 10 | L8: 4 | M8: =SUM(20%*N8*G8+F8+I8+K8+L8+1.46) -> 23.805988 | N8: 0.08 | O8: =SUM(M8*N8/(1-N8)) -> 2.0700859 | P8: =SUM(H8-I8-J8-K8-L8-O8) -> -1.5793359 | Q8: =SUM(P8/B8) -> -0.02872042 | R8: 1 | S8: =SUM(P8*R8) -> -1.5793359 | T8: =SUM(S8:S8) -> -1.5793359
A9: 第三阶段 | B9: 54.99 | C9: 0.4 | D9: 0.15 | E9: =SUM(B9*(1-C9-D9)) -> 24.7455 | F9: 7.86 | G9: =SUM(E9*15%) -> 3.711825 | H9: =SUM(E9-F9-G9) -> 13.173675 | I9: =0.08+0.34 -> 0.42 | J9: 0.6 | K9: 10 | L9: 4 | M9: =SUM(20%*N9*G9+F9+I9+K9+L9+1.46) -> 23.799389 | N9: 0.08 | O9: =SUM(M9*N9/(1-N9)) -> 2.0695121 | P9: =SUM(H9-I9-J9-K9-L9-O9) -> -3.9158371 | Q9: =SUM(P9/B9) -> -0.071209986 | R9: 1 | S9: =SUM(P9*R9) -> -3.9158371 | T9: =SUM(S9:S9) -> -3.9158371
A10: 第四阶段 | B10: 49.99 | C10: 0.35 | D10: 0 | E10: =SUM(B10*(1-C10-D10)) -> 32.4935 | F10: 7.86 | G10: =SUM(E10*15%) -> 4.874025 | H10: =SUM(E10-F10-G10) -> 19.759475 | I10: =0.08+0.34 -> 0.42 | J10: 0.6 | K10: 10 | L10: 4 | M10: =SUM(20%*N10*G10+F10+I10+K10+L10+1.46) -> 23.817984 | N10: 0.08 | O10: =SUM(M10*N10/(1-N10)) -> 2.0711291 | P10: =SUM(H10-I10-J10-K10-L10-O10) -> 2.6683459 | Q10: =SUM(P10/B10) -> 0.053377594 | R10: 1 | S10: =SUM(P10*R10) -> 2.6683459 | T10: =SUM(S10:S10) -> 2.6683459
A11: 第五阶段 | B11: 49.99 | C11: 0.25 | D11: 0 | E11: =SUM(B11*(1-C11-D11)) -> 37.4925 | F11: 7.86 | G11: =SUM(E11*15%) -> 5.623875 | H11: =SUM(E11-F11-G11) -> 24.008625 | I11: =0.08+0.34 -> 0.42 | J11: 0.6 | K11: 10 | L11: 4 | M11: =SUM(20%*N11*G11+F11+I11+K11+L11+1.46) -> 23.829982 | N11: 0.08 | O11: =SUM(M11*N11/(1-N11)) -> 2.0721723 | P11: =SUM(H11-I11-J11-K11-L11-O11) -> 6.9164527 | Q11: =SUM(P11/B11) -> 0.13835672 | R11: 1 | S11: =SUM(P11*R11) -> 6.9164527 | T11: =SUM(S11:S11) -> 6.9164527
A12: 第六阶段 | B12: 36.99 | C12: 0 | D12: 0 | E12: =SUM(B12*(1-C12-D12)) -> 36.99 | F12: 7.86 | G12: =SUM(E12*15%) -> 5.5485 | H12: =SUM(E12-F12-G12) -> 23.5815 | I12: =0.08+0.34 -> 0.42 | J12: 0 | K12: 10 | L12: 4 | M12: =SUM(20%*N12*G12+F12+I12+K12+L12+1.46) -> 23.828776 | N12: 0.08 | O12: =SUM(M12*N12/(1-N12)) -> 2.0720675 | P12: =SUM(H12-I12-J12-K12-L12-O12) -> 7.0894325 | Q12: =SUM(P12/B12) -> 0.19165808 | R12: 1 | S12: =SUM(P12*R12) -> 7.0894325 | T12: =SUM(S12:S12) -> 7.0894325
A15: 竞品日常价格 | B15: 65.51 | C15: 0.1 | D15: 0.23 | E15: 44.97 | F15: 7.86 | G15: =SUM(E15*15%) -> 6.7455 | H15: =SUM(E15-F15-G15) -> 30.3645 | I15: =0.08+0.34 -> 0.42 | J15: 0 | K15: 40 | L15: 3 | M15: =SUM(20%*N15*G15+F15+I15+K15+L15+1.46) -> 52.942365 | N15: 0.15 | O15: =SUM(M15*N15/(1-N15)) -> 9.3427703 | P15: =SUM(H15-I15-J15-K15-L15-O15) -> -22.39827 | Q15: =SUM(P15/B15) -> -0.34190613 | R15: 1 | S15: =SUM(P15*R15) -> -22.39827 | T15: =SUM(S15:S15) -> -22.39827
A16: 竞品活动价格 | B16: 49.98 | C16: 0 | D16: 0 | E16: =SUM(B16*(1-C16-D16)) -> 49.98 | F16: 7.86 | G16: =SUM(E16*15%) -> 7.497 | H16: =SUM(E16-F16-G16) -> 34.623 | I16: =0.08+0.34 -> 0.42 | J16: 0 | K16: 40 | L16: 3 | M16: =SUM(20%*N16*G16+F16+I16+K16+L16+1.46) -> 52.96491 | N16: 0.15 | O16: =SUM(M16*N16/(1-N16)) -> 9.3467488 | P16: =SUM(H16-I16-J16-K16-L16-O16) -> -18.143749 | Q16: =SUM(P16/B16) -> -0.36302018 | R16: 1 | S16: =SUM(P16*R16) -> -18.143749 | T16: =SUM(S16:S16) -> -18.143749
A17: 竞品链接 | B17: https://www.amazon.com/WEWE-Brushed-Kitchen-Stainless-Faucets/dp/B01H3OMH7Y
A20: 0013厨房水龙头（带广告） | F20: 0013厨房水龙头（带广告）
K21: 0013厨房水龙头（无广告） | P21: 0013厨房水龙头（无广告）
A22: 成本价 | C22: 70 | D22: =C22/C24 -> 10 | F22: 成本价 | H22: 70
A23: 头程费用 | C23: 28 | F23: 头程费用 | H23: 28 | K23: 成本价 | M23: 70 | P23: 成本价 | R23: 70
A24: 汇率 | C24: 7 | F24: 汇率 | H24: 7 | K24: 头程费用 | M24: 28 | P24: 头程费用 | R24: 28
A25: 佣金比例 | C25: 0.15 | D25: 0.15 | F25: 佣金比例 | H25: 0.15 | I25: 0.15 | K25: 汇率 | M25: 7 | P25: 汇率 | R25: 7
A26: FBA配送费 | C26: 7.86 | F26: FBA配送费 | H26: 7.86 | K26: 佣金比例 | M26: 0.15 | P26: 佣金比例 | R26: 0.15
A27: 退货率（8%） | C27: =C33*0.08 -> 3.9992 | D27: 0.08 | F27: 退货率（8%） | H27: =H33*0.08 -> 2.6392 | I27: 0.15 | K27: FBA配送费 | M27: 7.86 | P27: FBA配送费 | R27: 7.86
A28: 广告成本 | C28: =C33*D28 -> 7.4985 | D28: 0.15 | F28: 广告成本 | H28: =H33*I28 -> 4.9485 | I28: 0.15 | K28: 退货率（8%） | M28: =M34*0.08 -> 4.3992 | P28: 退货率（8%） | R28: =R34*0.08 -> 3.9992
A29: 仓储成本 | C29: 0.3 | F29: 仓储成本 | H29: 0.3 | K29: 广告成本 | M29: =M34*N29 -> 0 | P29: 广告成本 | R29: =R34*S29 -> 0
A30: 促销成本 （34%领取率） | C30: 0.6 | F30: 促销成本 （34%领取率） | H30: 0.6 | K30: 仓储成本 | M30: 0.3 | P30: 仓储成本 | R30: 0.3
A31: 配置费 | C31: 0.3 | F31: 配置费 | H31: 0.3 | K31: 促销成本 （34%领取率） | M31: 0.6 | P31: 促销成本 （34%领取率） | R31: 0.6
A32: 最低售价 | C32: 49.99 | F32: 最低售价 | H32: 32.99 | K32: 配置费 | M32: 0.3 | P32: 配置费 | R32: 0.3
A33: 平均售价 | C33: 49.99 | F33: 平均售价 | H33: 32.99 | K33: 最低售价 | M33: 54.99 | P33: 最低售价 | R33: 49.99
A34: 利润 | C34: =(C33-C26-C27-C28-C29-C30-C31-C33*C25)*C24-C23-C22 -> 55.5366 | F34: 利润 | H34: =(H33-H26-H27-H28-H29-H30-H31-H33*H25)*H24-H23-H22 -> -18.2434 | K34: 平均售价 | M34: 54.99 | P34: 平均售价 | R34: 49.99
A35: 利润率 | C35: =C34/(C33*C24) -> 0.15870774 | F35: 利润率 | H35: =H34/(H33*H24) -> -0.078999697 | K35: 利润 | M35: =(M34-M27-M28-M29-M30-M31-M32-M34*M26)*M25-M24-M23 -> 134.9761 | P35: 利润 | R35: =(R34-R27-R28-R29-R30-R31-R32-R34*R26)*R25-R24-R23 -> 108.0261
A36: 盈亏平衡 | C36: =(C22+C23)/C24+C33*C25+C26+C29+C31 -> 29.9585 | F36: 盈亏平衡 | H36: =(H22+H23)/H24+H33*H25+H26+H29+H31 -> 27.4085 | K36: 利润率 | M36: =M35/(M34*M25) -> 0.35065103 | P36: 利润率 | R36: =R35/(R34*R25) -> 0.30870774
A37: 盈亏平衡 （头尾程+成本+佣金） | C37: =(C22+C23)/C24+C33*C25+C26 -> 29.3585 | F37: 盈亏平衡 （头尾程+成本+佣金） | H37: =(H22+H23)/H24+H33*H25+H26 -> 26.8085 | K37: 盈亏平衡 | M37: =(M23+M24)/M25+M34*M26+M27+M30+M32 -> 30.7085 | P37: 盈亏平衡 | R37: =(R23+R24)/R25+R34*R26+R27+R30+R32 -> 29.9585
K38: 盈亏平衡 （头尾程+成本+佣金） | M38: =(M23+M24)/M25+M34*M26+M27 -> 30.1085 | P38: 盈亏平衡 （头尾程+成本+佣金） | R38: =(R23+R24)/R25+R34*R26+R27 -> 29.3585
F40: 产品交期 | G40: 35天 | H40: 前期时间
A41: 广告占比10-15% | F41: 海运时间 | G41: 45天 | H41: 75天-90天 (保守得下这么多天的量)
A42: 淋浴类利润率在10%以上 | F42: 上架时间（旺季） | G42: 5天

Sheet 毛利表格
A1: 每日盈亏数据预估
A2: 阶段 | B2: 日期 | C2: 定价 | D2: coupon | E2: code | F2: 折后价 | G2: FBA 配送费 | H2: 亚马逊 佣金 | I2: 账号 回款 | J2: 仓储费+入库配置费 | K2: coupon 费用 | L2: 产品 成本 | M2: 物流费 | N2: 退货成本(公式后面加的是单套产品的移除费） | O2: 退货率 | P2: 每单平摊 退货成本 | Q2: 每单 毛利 | R2: 毛利率 | S2: 订单 数量 | T2: 阶段 订单 亏损 | U2: 阶段 订单 总盈亏
A3: 第一阶段 | B3: 第1周 | C3: 54.99 | D3: 0.3 | E3: 0.1 | F3: =SUM(C3*(1-D3-E3)) -> 32.994 | G3: 7.86 | H3: =SUM(F3*15%) -> 4.9491 | I3: =SUM(F3-G3-H3) -> 20.1849 | J3: =0.08+0.34 -> 0.42 | K3: 0.6 | L3: 10 | M3: 4 | N3: =SUM(20%*O3*H3+G3+J3+L3+M3+1.46) -> 23.819186 | O3: 0.08 | P3: =SUM(N3*O3/(1-O3)) -> 2.0712335 | Q3: =SUM(I3-J3-K3-L3-M3-P3) -> 3.0936665 | R3: =SUM(Q3/C3) -> 0.05625871 | S3: =阶段盈亏!I3 -> 29 | T3: =SUM(Q3*S3) -> 89.716328 | U3: =SUM(T3:T3) -> 89.716328
B4: 第2周 | C4: 54.99 | D4: 0.3 | E4: 0.1 | F4: =SUM(C4*(1-D4-E4)) -> 32.994 | G4: 7.86 | H4: =SUM(F4*15%) -> 4.9491 | I4: =SUM(F4-G4-H4) -> 20.1849 | J4: =0.08+0.34 -> 0.42 | K4: 0.6 | L4: 10 | M4: 4 | N4: =SUM(20%*O4*H4+G4+J4+L4+M4+1.46) -> 23.819186 | O4: 0.08 | P4: =SUM(N4*O4/(1-O4)) -> 2.0712335 | Q4: =SUM(I4-J4-K4-L4-M4-P4) -> 3.0936665 | R4: =SUM(Q4/C4) -> 0.05625871 | S4: =阶段盈亏!I4 -> 103 | T4: =SUM(Q4*S4) -> 318.64765 | U4: =SUM(T4:T4) -> 318.64765
B5: 第3周 | C5: 54.99 | D5: 0.3 | E5: 0.1 | F5: =SUM(C5*(1-D5-E5)) -> 32.994 | G5: 7.86 | H5: =SUM(F5*15%) -> 4.9491 | I5: =SUM(F5-G5-H5) -> 20.1849 | J5: =0.08+0.34 -> 0.42 | K5: 0.6 | L5: 10 | M5: 4 | N5: =SUM(20%*O5*H5+G5+J5+L5+M5+1.46) -> 23.819186 | O5: 0.08 | P5: =SUM(N5*O5/(1-O5)) -> 2.0712335 | Q5: =SUM(I5-J5-K5-L5-M5-P5) -> 3.0936665 | R5: =SUM(Q5/C5) -> 0.05625871 | S5: =阶段盈亏!I5 -> 179 | T5: =SUM(Q5*S5) -> 553.7663 | U5: =SUM(T5:T5) -> 553.7663
B6: 第4周 | C6: 54.99 | D6: 0.3 | E6: 0.1 | F6: =SUM(C6*(1-D6-E6)) -> 32.994 | G6: 7.86 | H6: =SUM(F6*15%) -> 4.9491 | I6: =SUM(F6-G6-H6) -> 20.1849 | J6: =0.08+0.34 -> 0.42 | K6: 0.6 | L6: 10 | M6: 4 | N6: =SUM(20%*O6*H6+G6+J6+L6+M6+1.46) -> 23.819186 | O6: 0.08 | P6: =SUM(N6*O6/(1-O6)) -> 2.0712335 | Q6: =SUM(I6-J6-K6-L6-M6-P6) -> 3.0936665 | R6: =SUM(Q6/C6) -> 0.05625871 | S6: =阶段盈亏!I6 -> 206 | T6: =SUM(Q6*S6) -> 637.29529 | U6: =SUM(T6:T6) -> 637.29529
A7: 第二阶段 | B7: 第5周 | C7: 54.99 | D7: 0.4 | E7: 0.1 | F7: =SUM(C7*(1-D7-E7)) -> 27.495 | G7: 7.86 | H7: =SUM(F7*15%) -> 4.12425 | I7: =SUM(F7-G7-H7) -> 15.51075 | J7: =0.08+0.34 -> 0.42 | K7: 0.6 | L7: 10 | M7: 4 | N7: =SUM(20%*O7*H7+G7+J7+L7+M7+1.46) -> 23.805988 | O7: 0.08 | P7: =SUM(N7*O7/(1-O7)) -> 2.0700859 | Q7: =SUM(I7-J7-K7-L7-M7-P7) -> -1.5793359 | R7: =SUM(Q7/C7) -> -0.02872042 | S7: =阶段盈亏!I7 -> 242 | T7: =SUM(Q7*S7) -> -382.19929 | U7: =SUM(T7:T7) -> -382.19929
B8: 第6周 | C8: 54.99 | D8: 0.4 | E8: 0.1 | F8: =SUM(C8*(1-D8-E8)) -> 27.495 | G8: 7.86 | H8: =SUM(F8*15%) -> 4.12425 | I8: =SUM(F8-G8-H8) -> 15.51075 | J8: =0.08+0.34 -> 0.42 | K8: 0.6 | L8: 10 | M8: 4 | N8: =SUM(20%*O8*H8+G8+J8+L8+M8+1.46) -> 23.805988 | O8: 0.08 | P8: =SUM(N8*O8/(1-O8)) -> 2.0700859 | Q8: =SUM(I8-J8-K8-L8-M8-P8) -> -1.5793359 | R8: =SUM(Q8/C8) -> -0.02872042 | S8: =阶段盈亏!I8 -> 260 | T8: =SUM(Q8*S8) -> -410.62734 | U8: =SUM(T8:T8) -> -410.62734
B9: 第7周 | C9: 54.99 | D9: 0.4 | E9: 0.1 | F9: =SUM(C9*(1-D9-E9)) -> 27.495 | G9: 7.86 | H9: =SUM(F9*15%) -> 4.12425 | I9: =SUM(F9-G9-H9) -> 15.51075 | J9: =0.08+0.34 -> 0.42 | K9: 0.6 | L9: 10 | M9: 4 | N9: =SUM(20%*O9*H9+G9+J9+L9+M9+1.46) -> 23.805988 | O9: 0.08 | P9: =SUM(N9*O9/(1-O9)) -> 2.0700859 | Q9: =SUM(I9-J9-K9-L9-M9-P9) -> -1.5793359 | R9: =SUM(Q9/C9) -> -0.02872042 | S9: =阶段盈亏!I9 -> 299 | T9: =SUM(Q9*S9) -> -472.22144 | U9: =SUM(T9:T9) -> -472.22144
B10: 第8周 | C10: 54.99 | D10: 0.4 | E10: 0.1 | F10: =SUM(C10*(1-D10-E10)) -> 27.495 | G10: 7.86 | H10: =SUM(F10*15%) -> 4.12425 | I10: =SUM(F10-G10-H10) -> 15.51075 | J10: =0.08+0.34 -> 0.42 | K10: 0.6 | L10: 10 | M10: 4 | N10: =SUM(20%*O10*H10+G10+J10+L10+M10+1.46) -> 23.805988 | O10: 0.08 | P10: =SUM(N10*O10/(1-O10)) -> 2.0700859 | Q10: =SUM(I10-J10-K10-L10-M10-P10) -> -1.5793359 | R10: =SUM(Q10/C10) -> -0.02872042 | S10: =阶段盈亏!I10 -> 470 | T10: =SUM(Q10*S10) -> -742.28788 | U10: =SUM(T10:T10) -> -742.28788
A11: 第三阶段 | B11: 第9周 | C11: 54.99 | D11: 0.4 | E11: 0.15 | F11: =SUM(C11*(1-D11-E11)) -> 24.7455 | G11: 7.86 | H11: =SUM(F11*15%) -> 3.711825 | I11: =SUM(F11-G11-H11) -> 13.173675 | J11: =0.08+0.34 -> 0.42 | K11: 0.6 | L11: 10 | M11: 4 | N11: =SUM(20%*O11*H11+G11+J11+L11+M11+1.46) -> 23.799389 | O11: 0.08 | P11: =SUM(N11*O11/(1-O11)) -> 2.0695121 | Q11: =SUM(I11-J11-K11-L11-M11-P11) -> -3.9158371 | R11: =SUM(Q11/C11) -> -0.071209986 | S11: =阶段盈亏!I11 -> 390 | T11: =SUM(Q11*S11) -> -1527.1765 | U11: =SUM(T11:T11) -> -1527.1765
B12: 第10周 | C12: 54.99 | D12: 0.4 | E12: 0.15 | F12: =SUM(C12*(1-D12-E12)) -> 24.7455 | G12: 7.86 | H12: =SUM(F12*15%) -> 3.711825 | I12: =SUM(F12-G12-H12) -> 13.173675 | J12: =0.08+0.34 -> 0.42 | K12: 0.6 | L12: 10 | M12: 4 | N12: =SUM(20%*O12*H12+G12+J12+L12+M12+1.46) -> 23.799389 | O12: 0.08 | P12: =SUM(N12*O12/(1-O12)) -> 2.0695121 | Q12: =SUM(I12-J12-K12-L12-M12-P12) -> -3.9158371 | R12: =SUM(Q12/C12) -> -0.071209986 | S12: =阶段盈亏!I12 -> 495 | T12: =SUM(Q12*S12) -> -1938.3394 | U12: =SUM(T12:T12) -> -1938.3394
B13: 第11周 | C13: 54.99 | D13: 0.4 | E13: 0.15 | F13: =SUM(C13*(1-D13-E13)) -> 24.7455 | G13: 7.86 | H13: =SUM(F13*15%) -> 3.711825 | I13: =SUM(F13-G13-H13) -> 13.173675 | J13: =0.08+0.34 -> 0.42 | K13: 0.6 | L13: 10 | M13: 4 | N13: =SUM(20%*O13*H13+G13+J13+L13+M13+1.46) -> 23.799389 | O13: 0.08 | P13: =SUM(N13*O13/(1-O13)) -> 2.0695121 | Q13: =SUM(I13-J13-K13-L13-M13-P13) -> -3.9158371 | R13: =SUM(Q13/C13) -> -0.071209986 | S13: =阶段盈亏!I13 -> 540 | T13: =SUM(Q13*S13) -> -2114.552 | U13: =SUM(T13:T13) -> -2114.552
B14: 第12周 | C14: 54.99 | D14: 0.4 | E14: 0.15 | F14: =SUM(C14*(1-D14-E14)) -> 24.7455 | G14: 7.86 | H14: =SUM(F14*15%) -> 3.711825 | I14: =SUM(F14-G14-H14) -> 13.173675 | J14: =0.08+0.34 -> 0.42 | K14: 0.6 | L14: 10 | M14: 4 | N14: =SUM(20%*O14*H14+G14+J14+L14+M14+1.46) -> 23.799389 | O14: 0.08 | P14: =SUM(N14*O14/(1-O14)) -> 2.0695121 | Q14: =SUM(I14-J14-K14-L14-M14-P14) -> -3.9158371 | R14: =SUM(Q14/C14) -> -0.071209986 | S14: =阶段盈亏!I14 -> 720 | T14: =SUM(Q14*S14) -> -2819.4027 | U14: =SUM(T14:T14) -> -2819.4027
A15: 第四阶段 | B15: 第13周 | C15: 49.99 | D15: 0.35 | E15: 0 | F15: =SUM(C15*(1-D15-E15)) -> 32.4935 | G15: 7.86 | H15: =SUM(F15*15%) -> 4.874025 | I15: =SUM(F15-G15-H15) -> 19.759475 | J15: =0.08+0.34 -> 0.42 | K15: 0.6 | L15: 10 | M15: 4 | N15: =SUM(20%*O15*H15+G15+J15+L15+M15+1.46) -> 23.817984 | O15: 0.08 | P15: =SUM(N15*O15/(1-O15)) -> 2.0711291 | Q15: =SUM(I15-J15-K15-L15-M15-P15) -> 2.6683459 | R15: =SUM(Q15/C15) -> 0.053377594 | S15: =阶段盈亏!I15 -> 700 | T15: =SUM(Q15*S15) -> 1867.8421 | U15: =SUM(T15:T15) -> 1867.8421
B16: 第14周 | C16: 49.99 | D16: 0.35 | E16: 0 | F16: =SUM(C16*(1-D16-E16)) -> 32.4935 | G16: 7.86 | H16: =SUM(F16*15%) -> 4.874025 | I16: =SUM(F16-G16-H16) -> 19.759475 | J16: =0.08+0.34 -> 0.42 | K16: 0.6 | L16: 10 | M16: 4 | N16: =SUM(20%*O16*H16+G16+J16+L16+M16+1.46) -> 23.817984 | O16: 0.08 | P16: =SUM(N16*O16/(1-O16)) -> 2.0711291 | Q16: =SUM(I16-J16-K16-L16-M16-P16) -> 2.6683459 | R16: =SUM(Q16/C16) -> 0.053377594 | S16: =阶段盈亏!I16 -> 700 | T16: =SUM(Q16*S16) -> 1867.8421 | U16: =SUM(T16:T16) -> 1867.8421
B17: 第15周 | C17: 49.99 | D17: 0.35 | E17: 0 | F17: =SUM(C17*(1-D17-E17)) -> 32.4935 | G17: 7.86 | H17: =SUM(F17*15%) -> 4.874025 | I17: =SUM(F17-G17-H17) -> 19.759475 | J17: =0.08+0.34 -> 0.42 | K17: 0.6 | L17: 10 | M17: 4 | N17: =SUM(20%*O17*H17+G17+J17+L17+M17+1.46) -> 23.817984 | O17: 0.08 | P17: =SUM(N17*O17/(1-O17)) -> 2.0711291 | Q17: =SUM(I17-J17-K17-L17-M17-P17) -> 2.6683459 | R17: =SUM(Q17/C17) -> 0.053377594 | S17: =阶段盈亏!I17 -> 700 | T17: =SUM(Q17*S17) -> 1867.8421 | U17: =SUM(T17:T17) -> 1867.8421
B18: 第16周 | C18: 49.99 | D18: 0.35 | E18: 0 | F18: =SUM(C18*(1-D18-E18)) -> 32.4935 | G18: 7.86 | H18: =SUM(F18*15%) -> 4.874025 | I18: =SUM(F18-G18-H18) -> 19.759475 | J18: =0.08+0.34 -> 0.42 | K18: 0.6 | L18: 10 | M18: 4 | N18: =SUM(20%*O18*H18+G18+J18+L18+M18+1.46) -> 23.817984 | O18: 0.08 | P18: =SUM(N18*O18/(1-O18)) -> 2.0711291 | Q18: =SUM(I18-J18-K18-L18-M18-P18) -> 2.6683459 | R18: =SUM(Q18/C18) -> 0.053377594 | S18: =阶段盈亏!I18 -> 1000 | T18: =SUM(Q18*S18) -> 2668.3459 | U18: =SUM(T18:T18) -> 2668.3459
A19: 第五阶段 | B19: 第17周 | C19: 49.99 | D19: 0.25 | E19: 0 | F19: =SUM(C19*(1-D19-E19)) -> 37.4925 | G19: 7.86 | H19: =SUM(F19*15%) -> 5.623875 | I19: =SUM(F19-G19-H19) -> 24.008625 | J19: =0.08+0.34 -> 0.42 | K19: 0.6 | L19: 10 | M19: 4 | N19: =SUM(20%*O19*H19+G19+J19+L19+M19+1.46) -> 23.829982 | O19: 0.08 | P19: =SUM(N19*O19/(1-O19)) -> 2.0721723 | Q19: =SUM(I19-J19-K19-L19-M19-P19) -> 6.9164527 | R19: =SUM(Q19/C19) -> 0.13835672 | S19: =阶段盈亏!I19 -> 810 | T19: =SUM(Q19*S19) -> 5602.3266 | U19: =SUM(T19:T19) -> 5602.3266
B20: 第18周 | C20: 49.99 | D20: 0.25 | E20: 0 | F20: =SUM(C20*(1-D20-E20)) -> 37.4925 | G20: 7.86 | H20: =SUM(F20*15%) -> 5.623875 | I20: =SUM(F20-G20-H20) -> 24.008625 | J20: =0.08+0.34 -> 0.42 | K20: 0.6 | L20: 10 | M20: 4 | N20: =SUM(20%*O20*H20+G20+J20+L20+M20+1.46) -> 23.829982 | O20: 0.08 | P20: =SUM(N20*O20/(1-O20)) -> 2.0721723 | Q20: =SUM(I20-J20-K20-L20-M20-P20) -> 6.9164527 | R20: =SUM(Q20/C20) -> 0.13835672 | S20: =阶段盈亏!I20 -> 840 | T20: =SUM(Q20*S20) -> 5809.8202 | U20: =SUM(T20:T20) -> 5809.8202
B21: 第19周 | C21: 49.99 | D21: 0.25 | E21: 0 | F21: =SUM(C21*(1-D21-E21)) -> 37.4925 | G21: 7.86 | H21: =SUM(F21*15%) -> 5.623875 | I21: =SUM(F21-G21-H21) -> 24.008625 | J21: =0.08+0.34 -> 0.42 | K21: 0.6 | L21: 10 | M21: 4 | N21: =SUM(20%*O21*H21+G21+J21+L21+M21+1.46) -> 23.829982 | O21: 0.08 | P21: =SUM(N21*O21/(1-O21)) -> 2.0721723 | Q21: =SUM(I21-J21-K21-L21-M21-P21) -> 6.9164527 | R21: =SUM(Q21/C21) -> 0.13835672 | S21: =阶段盈亏!I21 -> 1020 | T21: =SUM(Q21*S21) -> 7054.7817 | U21: =SUM(T21:T21) -> 7054.7817
B22: 第20周 | C22: 49.99 | D22: 0.25 | E22: 0 | F22: =SUM(C22*(1-D22-E22)) -> 37.4925 | G22: 7.86 | H22: =SUM(F22*15%) -> 5.623875 | I22: =SUM(F22-G22-H22) -> 24.008625 | J22: =0.08+0.34 -> 0.42 | K22: 0.6 | L22: 10 | M22: 4 | N22: =SUM(20%*O22*H22+G22+J22+L22+M22+1.46) -> 23.829982 | O22: 0.08 | P22: =SUM(N22*O22/(1-O22)) -> 2.0721723 | Q22: =SUM(I22-J22-K22-L22-M22-P22) -> 6.9164527 | R22: =SUM(Q22/C22) -> 0.13835672 | S22: =阶段盈亏!I22 -> 1350 | T22: =SUM(Q22*S22) -> 9337.2111 | U22: =SUM(T22:T22) -> 9337.2111
A23: 第六阶段 | B23: 第21周 | C23: 36.99 | D23: 0 | E23: 0 | F23: =SUM(C23*(1-D23-E23)) -> 36.99 | G23: 7.86 | H23: =SUM(F23*15%) -> 5.5485 | I23: =SUM(F23-G23-H23) -> 23.5815 | J23: =0.08+0.34 -> 0.42 | K23: 0 | L23: 10 | M23: 4 | N23: =SUM(20%*O23*H23+G23+J23+L23+M23+1.46) -> 23.828776 | O23: 0.08 | P23: =SUM(N23*O23/(1-O23)) -> 2.0720675 | Q23: =SUM(I23-J23-K23-L23-M23-P23) -> 7.0894325 | R23: =SUM(Q23/C23) -> 0.19165808 | S23: =阶段盈亏!I23 -> 1050 | T23: =SUM(Q23*S23) -> 7443.9041 | U23: =SUM(T23:T23) -> 7443.9041
B24: 第22周 | C24: 36.99 | D24: 0 | E24: 0 | F24: =SUM(C24*(1-D24-E24)) -> 36.99 | G24: 7.86 | H24: =SUM(F24*15%) -> 5.5485 | I24: =SUM(F24-G24-H24) -> 23.5815 | J24: =0.08+0.34 -> 0.42 | K24: 0 | L24: 10 | M24: 4 | N24: =SUM(20%*O24*H24+G24+J24+L24+M24+1.46) -> 23.828776 | O24: 0.08 | P24: =SUM(N24*O24/(1-O24)) -> 2.0720675 | Q24: =SUM(I24-J24-K24-L24-M24-P24) -> 7.0894325 | R24: =SUM(Q24/C24) -> 0.19165808 | S24: =阶段盈亏!I24 -> 1050 | T24: =SUM(Q24*S24) -> 7443.9041 | U24: =SUM(T24:T24) -> 7443.9041
B25: 第23周 | C25: 36.99 | D25: 0 | E25: 0 | F25: =SUM(C25*(1-D25-E25)) -> 36.99 | G25: 7.86 | H25: =SUM(F25*15%) -> 5.5485 | I25: =SUM(F25-G25-H25) -> 23.5815 | J25: =0.08+0.34 -> 0.42 | K25: 0 | L25: 10 | M25: 4 | N25: =SUM(20%*O25*H25+G25+J25+L25+M25+1.46) -> 23.828776 | O25: 0.08 | P25: =SUM(N25*O25/(1-O25)) -> 2.0720675 | Q25: =SUM(I25-J25-K25-L25-M25-P25) -> 7.0894325 | R25: =SUM(Q25/C25) -> 0.19165808 | S25: =阶段盈亏!I25 -> 1050 | T25: =SUM(Q25*S25) -> 7443.9041 | U25: =SUM(T25:T25) -> 7443.9041
B26: 第24周 | C26: 36.99 | D26: 0 | E26: 0 | F26: =SUM(C26*(1-D26-E26)) -> 36.99 | G26: 7.86 | H26: =SUM(F26*15%) -> 5.5485 | I26: =SUM(F26-G26-H26) -> 23.5815 | J26: =0.08+0.34 -> 0.42 | K26: 0 | L26: 10 | M26: 4 | N26: =SUM(20%*O26*H26+G26+J26+L26+M26+1.46) -> 23.828776 | O26: 0.08 | P26: =SUM(N26*O26/(1-O26)) -> 2.0720675 | Q26: =SUM(I26-J26-K26-L26-M26-P26) -> 7.0894325 | R26: =SUM(Q26/C26) -> 0.19165808 | S26: =阶段盈亏!I26 -> 1500 | T26: =SUM(Q26*S26) -> 10634.149 | U26: =SUM(T26:T26) -> 10634.149

Sheet CPC表格
A1: 广告数据模拟
A2: 常规数据 | N2: 广告数据 | AB2: 实时更新 | AC2: 操作备注
A3: 阶段 | B3: 周 | C3: 价格 | D3: 站内 coupon | E3: 站内 code | F3: 折后价 | G3: 新品 榜单 | H3: 小类目 排名 | I3: 总 销量 | J3: 平均日销 | K3: CVR | L3: 评论 数量 | M3: 评分 | N3: 曝光量 | O3: 点击量 | P3: CTR | Q3: 广告单 | R3: CVR | S3: 平均 CPC | T3: 花费 | U3: ACOS | V3: CPA | W3: 日均 广告费 | X3: 自然 访问 | Y3: 自然 订单 | Z3: 自然 单占比 | AA3: 最终 盈亏 | AB3: Sif 质量分 | AC3: 运营调整 | AD3: 广告操作
A4: 第一阶段 | B4: 第1周 | C4: 54.99 | D4: 0.3 | E4: 0.1 | F4: =SUM(C4*(1-D4-E4)) -> 32.994 | I4: =阶段盈亏!I3 -> 29 | J4: =I4/7 -> 4.1428571 | O4: =SUM(Q4/R4) -> 300 | Q4: =阶段盈亏!H3 -> 24 | R4: 0.08 | S4: 3 | T4: =SUM(O4*S4) -> 900 | U4: =SUM(S4/R4/C4) -> 0.68194217 | V4: =SUM(T4/Q4) -> 37.5 | W4: =T4/7 -> 128.57143 | Z4: =(I4-Q4)/I4 -> 0.17241379
B5: 第2周 | C5: 54.99 | D5: 0.3 | E5: 0.1 | F5: =SUM(C5*(1-D5-E5)) -> 32.994 | I5: =阶段盈亏!I4 -> 103 | J5: =I5/7 -> 14.714286 | O5: =SUM(Q5/R5) -> 900 | Q5: =阶段盈亏!H4 -> 72 | R5: 0.08 | S5: 3 | T5: =SUM(O5*S5) -> 2700 | U5: =SUM(S5/R5/C5) -> 0.68194217 | V5: =SUM(T5/Q5) -> 37.5 | W5: =T5/7 -> 385.71429 | Z5: =(I5-Q5)/I5 -> 0.30097087
B6: 第3周 | C6: 54.99 | D6: 0.3 | E6: 0.1 | F6: =SUM(C6*(1-D6-E6)) -> 32.994 | I6: =阶段盈亏!I5 -> 179 | J6: =I6/7 -> 25.571429 | O6: =SUM(Q6/R6) -> 1562.5 | Q6: =阶段盈亏!H5 -> 125 | R6: 0.08 | S6: 3 | T6: =SUM(O6*S6) -> 4687.5 | U6: =SUM(S6/R6/C6) -> 0.68194217 | V6: =SUM(T6/Q6) -> 37.5 | W6: =T6/7 -> 669.64286 | Z6: =(I6-Q6)/I6 -> 0.30167598
B7: 第4周 | C7: 54.99 | D7: 0.3 | E7: 0.1 | F7: =SUM(C7*(1-D7-E7)) -> 32.994 | I7: =阶段盈亏!I6 -> 206 | J7: =I7/7 -> 29.428571 | O7: =SUM(Q7/R7) -> 1800 | Q7: =阶段盈亏!H6 -> 144 | R7: 0.08 | S7: 3 | T7: =SUM(O7*S7) -> 5400 | U7: =SUM(S7/R7/C7) -> 0.68194217 | V7: =SUM(T7/Q7) -> 37.5 | W7: =T7/7 -> 771.42857 | Z7: =(I7-Q7)/I7 -> 0.30097087
A8: 第二阶段 | B8: 第5周 | C8: 54.99 | D8: 0.4 | E8: 0.1 | F8: =SUM(C8*(1-D8-E8)) -> 27.495 | I8: =阶段盈亏!I7 -> 242 | J8: =I8/7 -> 34.571429 | O8: =SUM(Q8/R8) -> 1450 | Q8: =阶段盈亏!H7 -> 145 | R8: 0.1 | S8: 4 | T8: =SUM(O8*S8) -> 5800 | U8: =SUM(S8/R8/C8) -> 0.72740498 | V8: =SUM(T8/Q8) -> 40 | W8: =T8/7 -> 828.57143 | Z8: =(I8-Q8)/I8 -> 0.40082645
B9: 第6周 | C9: 54.99 | D9: 0.4 | E9: 0.1 | F9: =SUM(C9*(1-D9-E9)) -> 27.495 | I9: =阶段盈亏!I8 -> 260 | J9: =I9/7 -> 37.142857 | O9: =SUM(Q9/R9) -> 1560 | Q9: =阶段盈亏!H8 -> 156 | R9: 0.1 | S9: 3.8 | T9: =SUM(O9*S9) -> 5928 | U9: =SUM(S9/R9/C9) -> 0.69103473 | V9: =SUM(T9/Q9) -> 38 | W9: =T9/7 -> 846.85714 | Z9: =(I9-Q9)/I9 -> 0.4
B10: 第7周 | C10: 54.99 | D10: 0.4 | E10: 0.1 | F10: =SUM(C10*(1-D10-E10)) -> 27.495 | I10: =阶段盈亏!I9 -> 299 | J10: =I10/7 -> 42.714286 | O10: =SUM(Q10/R10) -> 1790 | Q10: =阶段盈亏!H9 -> 179 | R10: 0.1 | S10: 3.5 | T10: =SUM(O10*S10) -> 6265 | U10: =SUM(S10/R10/C10) -> 0.63647936 | V10: =SUM(T10/Q10) -> 35 | W10: =T10/7 -> 895 | Z10: =(I10-Q10)/I10 -> 0.40133779
B11: 第8周 | C11: 54.99 | D11: 0.4 | E11: 0.1 | F11: =SUM(C11*(1-D11-E11)) -> 27.495 | I11: =阶段盈亏!I10 -> 470 | J11: =I11/10 -> 47 | O11: =SUM(Q11/R11) -> 2820 | Q11: =阶段盈亏!H10 -> 282 | R11: 0.1 | S11: 3.2 | T11: =SUM(O11*S11) -> 9024 | U11: =SUM(S11/R11/C11) -> 0.58192399 | V11: =SUM(T11/Q11) -> 32 | W11: =T11/7 -> 1289.1429 | Z11: =(I11-Q11)/I11 -> 0.4
A12: 第三阶段 | B12: 第9周 | C12: 54.99 | D12: 0.4 | E12: 0.15 | F12: =SUM(C12*(1-D12-E12)) -> 24.7455 | I12: =阶段盈亏!I11 -> 390 | J12: =I12/7 -> 55.714286 | O12: =SUM(Q12/R12) -> 1625 | Q12: =阶段盈亏!H11 -> 195 | R12: 0.12 | S12: 3.2 | T12: =SUM(O12*S12) -> 5200 | U12: =SUM(S12/R12/C12) -> 0.48493666 | V12: =SUM(T12/Q12) -> 26.666667 | W12: =T12/7 -> 742.85714 | Z12: =(I12-Q12)/I12 -> 0.5
B13: 第10周 | C13: 54.99 | D13: 0.4 | E13: 0.15 | F13: =SUM(C13*(1-D13-E13)) -> 24.7455 | I13: =阶段盈亏!I12 -> 495 | J13: =I13/7 -> 70.714286 | O13: =SUM(Q13/R13) -> 2058.3333 | Q13: =阶段盈亏!H12 -> 247 | R13: 0.12 | S13: 3.2 | T13: =SUM(O13*S13) -> 6586.6667 | U13: =SUM(S13/R13/C13) -> 0.48493666 | V13: =SUM(T13/Q13) -> 26.666667 | W13: =T13/7 -> 940.95238 | Z13: =(I13-Q13)/I13 -> 0.5010101
B14: 第11周 | C14: 54.99 | D14: 0.4 | E14: 0.15 | F14: =SUM(C14*(1-D14-E14)) -> 24.7455 | I14: =阶段盈亏!I13 -> 540 | J14: =I14/7 -> 77.142857 | O14: =SUM(Q14/R14) -> 2250 | Q14: =阶段盈亏!H13 -> 270 | R14: 0.12 | S14: 2.8 | T14: =SUM(O14*S14) -> 6300 | U14: =SUM(S14/R14/C14) -> 0.42431957 | V14: =SUM(T14/Q14) -> 23.333333 | W14: =T14/7 -> 900 | Z14: =(I14-Q14)/I14 -> 0.5
B15: 第12周 | C15: 54.99 | D15: 0.4 | E15: 0.15 | F15: =SUM(C15*(1-D15-E15)) -> 24.7455 | I15: =阶段盈亏!I14 -> 720 | J15: =I15/9 -> 80 | O15: =SUM(Q15/R15) -> 3000 | Q15: =阶段盈亏!H14 -> 360 | R15: 0.12 | S15: 2.8 | T15: =SUM(O15*S15) -> 8400 | U15: =SUM(S15/R15/C15) -> 0.42431957 | V15: =SUM(T15/Q15) -> 23.333333 | W15: =T15/7 -> 1200 | Z15: =(I15-Q15)/I15 -> 0.5
A16: 第四阶段 | B16: 第13周 | C16: 49.99 | D16: 0.35 | E16: 0 | F16: =SUM(C16*(1-D16-E16)) -> 32.4935 | I16: =阶段盈亏!I15 -> 700 | J16: =I16/7 -> 100 | O16: =SUM(Q16/R16) -> 2545.4545 | Q16: =阶段盈亏!H15 -> 280 | R16: 0.11 | S16: 2 | T16: =SUM(O16*S16) -> 5090.9091 | U16: =SUM(S16/R16/C16) -> 0.36370911 | V16: =SUM(T16/Q16) -> 18.181818 | W16: =T16/7 -> 727.27273 | Z16: =(I16-Q16)/I16 -> 0.6
B17: 第14周 | C17: 49.99 | D17: 0.35 | E17: 0 | F17: =SUM(C17*(1-D17-E17)) -> 32.4935 | I17: =阶段盈亏!I16 -> 700 | J17: =I17/7 -> 100 | O17: =SUM(Q17/R17) -> 2545.4545 | Q17: =阶段盈亏!H16 -> 280 | R17: 0.11 | S17: 2 | T17: =SUM(O17*S17) -> 5090.9091 | U17: =SUM(S17/R17/C17) -> 0.36370911 | V17: =SUM(T17/Q17) -> 18.181818 | W17: =T17/7 -> 727.27273 | Z17: =(I17-Q17)/I17 -> 0.6
B18: 第15周 | C18: 49.99 | D18: 0.35 | E18: 0 | F18: =SUM(C18*(1-D18-E18)) -> 32.4935 | I18: =阶段盈亏!I17 -> 700 | J18: =I18/7 -> 100 | O18: =SUM(Q18/R18) -> 2545.4545 | Q18: =阶段盈亏!H17 -> 280 | R18: 0.11 | S18: 2 | T18: =SUM(O18*S18) -> 5090.9091 | U18: =SUM(S18/R18/C18) -> 0.36370911 | V18: =SUM(T18/Q18) -> 18.181818 | W18: =T18/7 -> 727.27273 | Z18: =(I18-Q18)/I18 -> 0.6
B19: 第16周 | C19: 49.99 | D19: 0.35 | E19: 0 | F19: =SUM(C19*(1-D19-E19)) -> 32.4935 | I19: =阶段盈亏!I18 -> 1000 | J19: =I19/10 -> 100 | O19: =SUM(Q19/R19) -> 3636.3636 | Q19: =阶段盈亏!H18 -> 400 | R19: 0.11 | S19: 2 | T19: =SUM(O19*S19) -> 7272.7273 | U19: =SUM(S19/R19/C19) -> 0.36370911 | V19: =SUM(T19/Q19) -> 18.181818 | W19: =T19/7 -> 1038.961 | Z19: =(I19-Q19)/I19 -> 0.6
A20: 第五阶段 | B20: 第17周 | C20: 49.99 | D20: 0.25 | E20: 0 | F20: =SUM(C20*(1-D20-E20)) -> 37.4925 | I20: =阶段盈亏!I19 -> 810 | J20: =I20/7 -> 115.71429 | O20: =SUM(Q20/R20) -> 2430 | Q20: =阶段盈亏!H19 -> 243 | R20: 0.1 | S20: 1.5 | T20: =SUM(O20*S20) -> 3645 | U20: =SUM(S20/R20/C20) -> 0.30006001 | V20: =SUM(T20/Q20) -> 15 | W20: =T20/7 -> 520.71429 | Z20: =(I20-Q20)/I20 -> 0.7
B21: 第18周 | C21: 49.99 | D21: 0.25 | E21: 0 | F21: =SUM(C21*(1-D21-E21)) -> 37.4925 | I21: =阶段盈亏!I20 -> 840 | J21: =I21/7 -> 120 | O21: =SUM(Q21/R21) -> 2520 | Q21: =阶段盈亏!H20 -> 252 | R21: 0.1 | S21: 1.5 | T21: =SUM(O21*S21) -> 3780 | U21: =SUM(S21/R21/C21) -> 0.30006001 | V21: =SUM(T21/Q21) -> 15 | W21: =T21/7 -> 540 | Z21: =(I21-Q21)/I21 -> 0.7
B22: 第19周 | C22: 49.99 | D22: 0.25 | E22: 0 | F22: =SUM(C22*(1-D22-E22)) -> 37.4925 | I22: =阶段盈亏!I21 -> 1020 | J22: =I22/7 -> 145.71429 | O22: =SUM(Q22/R22) -> 3060 | Q22: =阶段盈亏!H21 -> 306 | R22: 0.1 | S22: 1.5 | T22: =SUM(O22*S22) -> 4590 | U22: =SUM(S22/R22/C22) -> 0.30006001 | V22: =SUM(T22/Q22) -> 15 | W22: =T22/7 -> 655.71429 | Z22: =(I22-Q22)/I22 -> 0.7
B23: 第20周 | C23: 49.99 | D23: 0.25 | E23: 0 | F23: =SUM(C23*(1-D23-E23)) -> 37.4925 | I23: =阶段盈亏!I22 -> 1350 | J23: =I23/9 -> 150 | O23: =SUM(Q23/R23) -> 4050 | Q23: =阶段盈亏!H22 -> 405 | R23: 0.1 | S23: 1.5 | T23: =SUM(O23*S23) -> 6075 | U23: =SUM(S23/R23/C23) -> 0.30006001 | V23: =SUM(T23/Q23) -> 15 | W23: =T23/7 -> 867.85714 | Z23: =(I23-Q23)/I23 -> 0.7
A24: 第六阶段 | B24: 第21周 | C24: 36.99 | D24: 0 | E24: 0 | F24: =SUM(C24*(1-D24-E24)) -> 36.99 | I24: =阶段盈亏!I23 -> 1050 | J24: =I24/7 -> 150 | O24: =SUM(Q24/R24) -> 2333.3333 | Q24: =阶段盈亏!H23 -> 210 | R24: 0.09 | S24: 1.2 | T24: =SUM(O24*S24) -> 2800 | U24: =SUM(S24/R24/C24) -> 0.36045778 | V24: =SUM(T24/Q24) -> 13.333333 | W24: =T24/7 -> 400 | Z24: =(I24-Q24)/I24 -> 0.8
B25: 第22周 | C25: 36.99 | D25: 0 | E25: 0 | F25: =SUM(C25*(1-D25-E25)) -> 36.99 | I25: =阶段盈亏!I24 -> 1050 | J25: =I25/7 -> 150 | O25: =SUM(Q25/R25) -> 2333.3333 | Q25: =阶段盈亏!H24 -> 210 | R25: 0.09 | S25: 1.2 | T25: =SUM(O25*S25) -> 2800 | U25: =SUM(S25/R25/C25) -> 0.36045778 | V25: =SUM(T25/Q25) -> 13.333333 | W25: =T25/7 -> 400 | Z25: =(I25-Q25)/I25 -> 0.8
B26: 第23周 | C26: 36.99 | D26: 0 | E26: 0 | F26: =SUM(C26*(1-D26-E26)) -> 36.99 | I26: =阶段盈亏!I25 -> 1050 | J26: =I26/7 -> 150 | O26: =SUM(Q26/R26) -> 2333.3333 | Q26: =阶段盈亏!H25 -> 210 | R26: 0.09 | S26: 1.2 | T26: =SUM(O26*S26) -> 2800 | U26: =SUM(S26/R26/C26) -> 0.36045778 | V26: =SUM(T26/Q26) -> 13.333333 | W26: =T26/7 -> 400 | Z26: =(I26-Q26)/I26 -> 0.8
B27: 第24周 | C27: 36.99 | D27: 0 | E27: 0 | F27: =SUM(C27*(1-D27-E27)) -> 36.99 | I27: =阶段盈亏!I26 -> 1500 | J27: =I27/10 -> 150 | O27: =SUM(Q27/R27) -> 3333.3333 | Q27: =阶段盈亏!H26 -> 300 | R27: 0.09 | S27: 1.2 | T27: =SUM(O27*S27) -> 4000 | U27: =SUM(S27/R27/C27) -> 0.36045778 | V27: =SUM(T27/Q27) -> 13.333333 | W27: =T27/7 -> 571.42857 | Z27: =(I27-Q27)/I27 -> 0.8

Sheet 四、库存计划
A1: 产品名 | B1: 推品 时间 | C1: 阶段订单 | D1: 竞对月销 | E1: 备货数量 | F1: 产品单箱尺寸 | G1: 单箱重量 | H1: 装箱数 | I1: 装箱尺寸 | J1: 装箱重量 | K1: 采购价￥ | L1: 预估货值￥ | M1: 备注
B2: 第一个月 | C2: ='二、BSR排名销量计划（日月-目标）'!C32 -> 517 | D2: 950 | E2: =C2*1.2 -> 620.4 | K2: 68.5 | L2: =K2*C2 -> 35414.5 | M2: 快船25天
B3: 第二个月 | C3: ='二、BSR排名销量计划（日月-目标）'!C64 -> 1271 | D3: 1000 | E3: =C3*1.2 -> 1525.2 | K3: 68.5 | L3: =K3*C3 -> 87063.5 | M3: 慢船45天
B4: 第三个月 | C4: ='二、BSR排名销量计划（日月-目标）'!C95 -> 2145 | D4: 2500 | E4: =C4*1.2 -> 2574 | K4: 68.5 | L4: =K4*C4 -> 146932.5
B5: 第四个月 | C5: ='二、BSR排名销量计划（日月-目标）'!C127 -> 3100 | D5: 4300 | E5: =C5*1.2 -> 3720 | K5: 68.5 | L5: =K5*C5 -> 212350
B6: 第五个月 | C6: ='二、BSR排名销量计划（日月-目标）'!C158 -> 4020 | D6: 4500 | E6: =C6*1.2 -> 4824 | K6: 68.5 | L6: =K6*C6 -> 275370
B7: 第六个月 | C7: ='二、BSR排名销量计划（日月-目标）'!C190 -> 4650 | D7: 4500 | E7: =C7*1.2 -> 5580 | K7: 68.5 | L7: =K7*C7 -> 318525
B8: 合计 | C8: =SUM(C2:C7) -> 15703 | D8: =SUM(D2:D7) -> 17750 | E8: =SUM(E2:E7) -> 18843.6 | K8: =AVERAGE(K2:K7) -> 68.5 | L8: =SUM(L2:L7) -> 1075655.5
C11: 填写黄色字列
I12: 15天交期+40天慢船（20天快船）
I13: 不锈钢色 | J13: 3600 | K13: =J13/J16 -> 0.9 | L13: =E2*K13/2 -> 279.18
I14: 磨砂黑 | J14: 300 | K14: =J14/J16 -> 0.075 | L14: =E2*K14/2 -> 23.265
I15: 金色 | J15: 100 | K15: =J15/J16 -> 0.025 | L15: =E2*K15/2 -> 7.755
J16: 4000 | L16: 半个月下采购单数量

Sheet 五、评论策略
A1: 产品名 | B1: 推品 时间 | C1: 阶段订单 | D1: 种子链接 | E1: vine数量 | F1: 头程（单个） | G1: 采购价（单个） | H1: Vine产品成本 | I1: AMZ费用 | J1: VINE报名费 | K1: 预估总费用 | L1: 回评数量 | M1: 星级 | O1: 填写黄色字列
B2: 第一个月 | C2: 700 | D2: 5 | E2: 150 | F2: 19 | G2: 68.5 | H2: =(G2+F2)*E2 -> 13125 | I2: =E2*毛利表格!G3*7 -> 8253 | J2: =5*200*7 -> 7000 | K2: =H2+I2+J2 -> 28378 | L2: =E2*0.8 -> 120 | M2: 4.5 | O2: 总结： 1.在新品中，普遍卖得好的产品，星级很高，至少都是4.9星以上，但是整体的评价数量不多，20个左右，如果我们新品上线的话，最好能又有至少50个评论且星级至少4.7分以上。 2.在对标头部产品中，普遍评价上千，我们在有量的同时会有自然回评，但是整体基础种子链接也要有900个评价，分6个月上去，维持住自己的星级且能晋升头部。
B3: 第二个月 | C3: 1200 | D3: 5 | E3: 150 | F3: 19 | G3: 68.5 | H3: =(G3+F3)*E3 -> 13125 | I3: =E3*毛利表格!G7*7 -> 8253 | J3: =5*200*7 -> 7000 | K3: =H3+I3+J3 -> 28378 | L3: =E3*0.8 -> 120 | M3: 4.5
B4: 第三个月 | C4: 2480 | D4: 8 | E4: 200 | F4: 19 | G4: 68.5 | H4: =(G4+F4)*E4 -> 17500 | I4: =E4*毛利表格!G11*7 -> 11004 | J4: =(6*200+2*75)*7 -> 9450 | K4: =H4+I4+J4 -> 37954 | L4: =E4*0.8 -> 160 | M4: 4.5
B5: 第四个月 | C5: 3100 | D5: 9 | E5: 250 | F5: 19 | G5: 68.5 | H5: =(G5+F5)*E5 -> 21875 | I5: =E5*毛利表格!G15*7 -> 13755 | J5: =(8*200+1*75)*7 -> 11725 | K5: =H5+I5+J5 -> 47355 | L5: =E5*0.8 -> 200 | M5: 4.5
B6: 第五个月 | C6: 4650 | D6: 10 | E6: 300 | F6: 19 | G6: 68.5 | H6: =(G6+F6)*E6 -> 26250 | I6: =E6*毛利表格!G19*7 -> 16506 | J6: =10*200*7 -> 14000 | K6: =H6+I6+J6 -> 56756 | L6: =E6*0.8 -> 240 | M6: 4.5
B7: 第六个月 | C7: 4650 | D7: 10 | E7: 300 | F7: 19 | G7: 68.5 | H7: =(G7+F7)*E7 -> 26250 | I7: =E7*毛利表格!G23*7 -> 16506 | J7: =10*200*7 -> 14000 | K7: =H7+I7+J7 -> 56756 | L7: =E7*0.8 -> 240 | M7: 4.5
B8: 合计 | C8: =SUM(C2:C7) -> 16780 | D8: =SUM(D2:D7) -> 47 | E8: =SUM(E2:E7) -> 1350 | F8: / | G8: / | H8: =SUM(H2:H7) -> 118125 | I8: =SUM(I2:I7) -> 74277 | J8: =SUM(J2:J7) -> 63175 | K8: =H8+I8+J8 -> 255577 | L8: =E8*0.8 -> 1080 | M8: 4.5
A10: 新品销量&销售额最高的评分和评论数量 | B10: 图片 | F10: 评分&评分数量 | K10: 图片 | O10: 评分&评分数量 | S10: 图片（新品榜） | W10: 评分&评分数量
B11: =_xlfn.DISPIMG("ID_89E3915423FE4C3CB92D1428A47513EC",1) -> =DISPIMG("ID_89E3915423FE4C3CB92D1428A47513EC",1) | F11: =_xlfn.DISPIMG("ID_1665786D65FF4C32B937EDC2EDEC8DCE",1) -> =DISPIMG("ID_1665786D65FF4C32B937EDC2EDEC8DCE",1) | K11: =_xlfn.DISPIMG("ID_FFBC2CA56D11485293B9D7E737CC38FE",1) -> =DISPIMG("ID_FFBC2CA56D11485293B9D7E737CC38FE",1) | O11: =_xlfn.DISPIMG("ID_78099D9FA13746919690178FE648C3E4",1) -> =DISPIMG("ID_78099D9FA13746919690178FE648C3E4",1) | S11: =_xlfn.DISPIMG("ID_C4B28CB879C84D229C22B9D5DDB9ADAC",1) -> =DISPIMG("ID_C4B28CB879C84D229C22B9D5DDB9ADAC",1)
A23: 头部销量&销售额最高的评分和评论数量 | B23: 对标竞品图片（B01H3OMH7Y） | F23: 评分&评分数量 | K23: 对标竞品图片（B0BV2NVH1N） | O23: 评分&评分数量 | S23: 对标竞品图片（B092VQTNW1） | W23: 评分&评分数量
B24: =_xlfn.DISPIMG("ID_22498B22056C47D48D786F280B7E7F0C",1) -> =DISPIMG("ID_22498B22056C47D48D786F280B7E7F0C",1) | F24: =_xlfn.DISPIMG("ID_564A442398F84FD693A654B35682E1B5",1) -> =DISPIMG("ID_564A442398F84FD693A654B35682E1B5",1) | K24: =_xlfn.DISPIMG("ID_AC047195971242799E8D87650D3B1A92",1) -> =DISPIMG("ID_AC047195971242799E8D87650D3B1A92",1) | O24: =_xlfn.DISPIMG("ID_D727A8BD797F4D809B5B6E35AD048108",1) -> =DISPIMG("ID_D727A8BD797F4D809B5B6E35AD048108",1) | S24: =_xlfn.DISPIMG("ID_F0A7D078E8454A33BA9E26BD54AE484F",1) -> =DISPIMG("ID_F0A7D078E8454A33BA9E26BD54AE484F",1) | W24: =_xlfn.DISPIMG("ID_30BA5F07C5424A88ACEB2DCFD270EBA0",1) -> =DISPIMG("ID_30BA5F07C5424A88ACEB2DCFD270EBA0",1)
A36: 飞书抓取 自己定价 | B36: =_xlfn.DISPIMG("ID_2755F8DB56EF40F78367E97D091663DF",1) -> =DISPIMG("ID_2755F8DB56EF40F78367E97D091663DF",1)
B56: =_xlfn.DISPIMG("ID_2E2C877D182C498DAC8100516CF5F920",1) -> =DISPIMG("ID_2E2C877D182C498DAC8100516CF5F920",1)

Sheet 六、广告框架
A1: 广告组名称 | B1: 精准-A1 核心主推词 | C1: 精准-A2 10W以内 | D1: 精准-A3 10W-20W | E1: 精准-A4 品牌 | F1: 精准-A5 AC词 | G1: 自动-紧密 | H1: 自动-同类 | I1: 西语 | J1: 广泛-大流量词(10W以内) | K1: 广泛-中流量（10W以上） | L1: 广泛-捡漏（20W以上） | M1: SP-ASIN定投-精准 进攻 | N1: SP-ASIN定投-精准 进攻-价格优势 | O1: SP-ASIN定投-拓展 拓流量机会（前100） | P1: SP-类目投放 | Q1: SD 类目/ASIN 自己 | R1: SD 受众 | S1: SBV-KW 广泛 | T1: SBV-KW 精准
B2: kitchen faucets | C2: kitchen sink faucet | D2: faucet | E2: moen kitchen faucet | F2: faucets for sinks | G2: 自动-宽泛 | H2: 自动-关联 | I2: grifo de cocina | J2: kitchen faucets | K2: kraus kitchen faucet | L2: llave para fregadero de cocina | M2: B01H3OMH7Y | N2: B08BHX8SGZ | O2: B07Y4Y88Y6 | S2: kitchen faucets | T2: kitchen faucets
B3: kitchen faucet | C3: kitchen faucet with pull down sprayer | D3: kitchen faucets with pull down sprayer | E3: delta kitchen faucet | F3: faucets for kitchen | G3: 尽可能打紧密和同类，关联起来 | I3: llave para fregadero de cocina | J3: kitchen faucet | K3: kitchen faucets with pull down sprayer | L3: matte black kitchen faucet | M3: B07Y4Y88Y6 | N3: B0B82FK122 | O3: B01H3OMH7Y | S3: kitchen faucet | T3: kitchen faucet
C4: sink faucet | D4: llaves para fregaderos de cocina | E4: delta faucet | F4: kitchen facet with sprayer | I4: grifos de cocina | J4: kitchen sink faucet | K4: faucet filter for kitchen sink | L4: brushed nickel kitchen faucet | M4: B07D8F5NCW | N4: B0CN362S8M | O4: B01E0M4PJ0 | S4: kitchen sink faucet | T4: kitchen sink faucet
C5: black kitchen faucet | D5: rv kitchen faucet | F5: glacier bay kitchen faucet | I5: llave de fregadero de cocina | J5: kitchen faucet with pull down sprayer | K5: rv kitchen faucet | L5: delta kitchen faucets with pull down sprayer | M5: B08BHX8SGZ | N5: B07M7J7RBB | O5: B07D8F5NCW | S5: kitchen faucet with pull down sprayer | T5: kitchen faucet with pull down sprayer
C6: faucet for kitchen sink | D6: brass kitchen faucet | F6: pull down faucet | I6: grifos para fregaderos de cocina | J6: faucet mat for kitchen sink | K6: brass kitchen faucet | L6: kitchen faucets with sprayer | M6: B08KXPTL8C | N6: B094VVQJPM | O6: B0BV2NVH1N | S6: sink faucet | T6: sink faucet
A7: A组广告优先高相关，谁转化好，保留在原来的广告活动，没有抢到预算和没有曝光点击的，复制新开组测试 | C7: kitchen faucet with sprayer | D7: grifos para fregaderos de cocina | F7: kitchen faucet￼ | I7: llaves para fregaderos de cocina | J7: black kitchen faucet | K7: faucet water filter for kitchen sink | L7: kitchen faucet black | M7: B07R8KNPL1 | N7: B0CCJMZWRZ | O7: B07VCWJJHC | S7: black kitchen faucet | T7: black kitchen faucet
C8: kitchen sink faucet with sprayer | D8: brushed gold kitchen faucet | F8: kitchen pull down faucet | I8: grifería para cocina | J8: moen kitchen faucet | K8: grohe kitchen faucet | L8: gold faucet for kitchen sink | M8: B01E0M4PJ0 | N8: B0D14DL6VW | O8: B07R8KNPL1 | S8: faucet for kitchen sink | T8: faucet for kitchen sink
C9: kitchen sink faucets | D9: champagne bronze kitchen faucet | F9: grifo para cocina | I9: griferia para cocina | J9: delta kitchen faucet | K9: brushed gold kitchen faucet | L9: kitchen faucet with soap dispenser | M9: B07V71NRHG | N9: B0CSK29WXB | O9: B08KXPTL8C | S9: kitchen faucet with sprayer | T9: kitchen faucet with sprayer
D10: kitchen faucets touchless | F10: llave de cocina | I10: grifo de cocina acero inoxidable | J10: faucet for kitchen sink | K10: faucet splash guard for kitchen sink | L10: rv faucet | M10: B082VWC75W | N10: B0CY2HFGF4 | O10: B07V71NRHG | S10: kitchen sink faucet with sprayer | T10: kitchen sink faucet with sprayer
D11: pull down kitchen faucet | F11: faucet for kitchen | I11: llave de agua para cocina | J11: kitchen faucet with sprayer | K11: champagne bronze kitchen faucet | L11: faucets | M11: B09FSWGYJK | N11: B09WN6Y2XQ | O11: B082VWC75W | S11: kitchen sink faucets | T11: kitchen sink faucets
D12: black faucet kitchen | F12: faucet for a sink | I12: llaves de agua para cocina | J12: gold kitchen faucet | K12: kitchen faucets touchless | L12: rv kitchen sink faucet | M12: B07C1L21SF | N12: B0BHQJFCKR | S12: faucet
F13: faucet for the sink | I13: llave de cocina | J13: touchless kitchen faucet | K13: pull down kitchen faucet | L13: oil rubbed bronze kitchen faucet | M13: B0CJ6RD8VB | N13: B089VVWMSM | S13: kitchen faucets with pull down sprayer
F14: kitchen faucet for sink | I14: grifo cocina | J14: kitchen faucet head replacement | K14: black faucet kitchen | L14: black sink faucet kitchen | M14: B0CM85C3ZL | N14: B099M9CQ16 | S14: llaves para fregaderos de cocina
F15: llave de fregadero de cocina | I15: llave para sink de cocina | J15: kohler kitchen faucet | L15: bronze kitchen faucet | M15: B0CD25DR34 | N15: B09GXZZX49 | S15: rv kitchen faucet
F16: faucet kitchen | I16: llaves para cocina | J16: kitchen faucet mat | L16: llave de fregadero de cocina | M16: B012I44K8S | N16: B0BDLQSKBT | S16: brass kitchen faucet
F17: sink faucet kitchen | I17: mezcladora de cocina fregadero | J17: kitchen sink faucet with sprayer | L17: kitchen faucets black | M17: B0BV2NVH1N | N17: B0932DJ14S | S17: grifos para fregaderos de cocina
F18: faucet kitchen sink | I18: grifo para cocina | J18: kitchen sink faucets | L18: wewe kitchen faucet | M18: B012I44KK6 | N18: B0CKSQ7DGC | S18: brushed gold kitchen faucet
F19: stainless kitchen faucets | I19: llaves para sink de cocina | L19: water faucet | M19: B08R715DXT | N19: B07QVP4G36 | S19: champagne bronze kitchen faucet
F20: llave de agua para cocina | I20: yaves de agua para cocina | L20: black kitchen faucet with pull down sprayer | M20: B012I44KZG | N20: B07MNFRVM3 | S20: kitchen faucets touchless
F21: faucet sink | I21: pluma de fregadero de cocina | L21: stainless steel kitchen faucet | M21: B0BHQJFCKR | N21: B09YQYX483 | S21: pull down kitchen faucet
F22: faucet with sprayer | I22: llave para fregadero | L22: faucet kitchen | M22: B0CKSQ7DGC | N22: B07Z7PK4SF | S22: black faucet kitchen
F23: kitchen facet | I23: llave de fregadero | L23: touch kitchen faucet | M23: B012I44QM8 | N23: B07MNJPQHF
F24: kitchen tap | I24: llave para lavaplatos | L24: single hole kitchen faucet | M24: B0CPDHBCC6 | N24: B0D7CLPSBL
F25: faucets for kitchen sink | I25: llave lavaplatos | L25: grifo de cocina | M25: B0C9BZJ5B6 | N25: B08BWL6FZZ
F26: facet kitchen sink | I26: mezcladora de fregadero | L26: gold sink faucet kitchen | M26: B09J4GZZVF | N26: B01E0M4PJ0
F27: llaves para cocina | I27: grifería lavaplatos | L27: moen kitchen faucets | M27: B08WYHN2CD | N27: B07C1L21SF
F28: grifos de cocina | L28: delta kitchen faucets | M28: B0BKRV8322 | N28: B07CVTJZ4W
F29: pull-down sprayer kitchen faucets | L29: black kitchen sink faucet | M29: B0B82FK122 | N29: B0CPS3PD1J
F30: faucet for sink | L30: single handle kitchen faucet | M30: B001U6I1Y0 | N30: B07YD924F8
F31: 3 in 1 kitchen faucet | L31: moen kitchen faucets with pull down sprayer | M31: B07QVP4G36 | N31: B082LSMLHQ
F32: faucets | L32: 水龙头 | M32: B084RGKVZF | N32: B000A0GWX4
F33: rv kitchen sink faucet | L33: kitchen faucets with soap dispenser | M33: B08Z3M9HPM
F34: grifo de cocina | L34: brushed brass kitchen faucet | M34: B0CSJRMCPM
F35: faucets for kitchen sinks with sprayer | L35: rv faucets kitchen | M35: B07KT2VF3H
F36: modern kitchen faucet | L36: kitchen faucet gold | M36: B0CN362S8M
F37: grifería para cocina | L37: delta faucet kitchen | M37: B084RNBLTD
F38: kitchen water faucet | L38: moen faucet | M38: B0CY9NSBQ5
F39: stainless steel faucet for kitchen sink | L39: black and gold kitchen faucet | M39: B0CV9TBR9B
F40: sink faucet with sprayer | L40: delta touchless kitchen faucet | M40: B07MNFRVM3
F41: llave para sink de cocina | L41: forious kitchen faucet | M41: B089VVWMSM
F42: llave lavaplatos | L42: faucets for kitchen sinks with sprayer | M42: B08JPWRSL3
F43: llave para fregadero | L43: kitchen facet with sprayer | M43: B06XWZSM3N
F44: faucets for sink | L44: touch faucet for kitchen sink | M44: B0CGDNQHW5
... F71: delta kitchen faucets with pull down sprayer | L71: kitchen water faucet | M71: B0856YGV4J
F72: delta faucet kitchen | L72: kitchen faucet with water filter built in
F73: touch faucet for kitchen sink | L73: gold kitchen sink faucet
F74: wewe kitchen faucet | L74: delta touch kitchen faucet
F75: stainless steel kitchen faucet | L75: brushed bronze kitchen faucet
F76: single hole kitchen faucet | L76: american standard kitchen faucet
F77: delta kitchen faucets | L77: kitchen faucets delta
F78: single handle kitchen faucet | L78: stainless kitchen faucets
F79: touch on kitchen sink faucets | L79: single hole faucet
F80: faucet for kitchen sink with sprayer | L80: black kitchen faucets
F81: delta essa pull down kitchen faucet | L81: black kitchen faucet with soap dispenser
F82: touch faucet | L82: 3 hole kitchen faucet with sprayer
F83: pulldown kitchen faucet | L83: kitchen faucet brushed nickel
... F144: champagne bronze faucet | L144: black touch kitchen faucets with pull down sprayer
F145: griferia
F146: mezcladora de cocina fregadero
F147: kitchen upgrades
F148: wewe
F149: brushed nickel
F150: moen kitchen faucets with pull down sprayer
F151: kitchen sink faucet with soap dispenser
F152: kitchen faucet moen
F153: delta touchless kitchen faucet
F154: moen kitchen faucets
F155: kitchen faucets moen
F156: delta touch kitchen faucet
... F168: matte black kitchen faucet with pull down sprayer

Sheet 关键词准备
A1: 搜索词(ABA) | B1: 搜索频率排名 | C1: CPC | D1: 点击转化率 | F1: 关键词 | G1: 翻译 | H1: 相关性-自动百分比 | I1: 相关性-自动 | J1: 自然位前4占位率 | K1: 自然位前8占位率 | L1: 自然位前16占位率 | M1: 自然位前32占位率 | N1: 自然位前48占位率 | O1: 搜索量 | P1: 排名 | Q1: 相关性-手动 | R1: CPC | S1: 点击转化率 | T1: 预期ACOS | V1: 共用关键词 | W1: 关键词 | X1: 翻译 | Y1: 周搜索量排名 | AA1: 竞品拓词导出_2024-11-07 ASIN:B0B82FK122,B01N4L0IGO,B084RNBLTD,B012I44KZG,B07RTZ2MRL,B0CN362S8M,B07CJRJ6Q7,B08KXPTL8C,B0BHQJFCKR,B012I44K8S///B082VWC75W,B0CV9TBR9B,B001U6I1Y0,B01H3OMH7Y,B09BBZ3X5S,B012I44QM8,B012I44KK6,B084R895Z5,B0CR1B43WR,B0064OW4WS///B0BV2NVH1N,B06XWTWHFJ,B08JPWRSL3,B0CZDL6CN1,B087466GKM,B07KT2VF3H,B0CD25DR34,B0CPDHBCC6,B07Y4Y88Y6,B099M9CQ16
A2: kitchen faucets | B2: 1778 | C2: 3.76 | D2: 0.060369053 | F2: kitchen faucets | G2: 厨房水龙头 | H2: 59.69% | I2: 高相关 | J2: 65.63% | K2: 62.5% | L2: 45.31% | M2: 45.7% | N2: 41.93% | O2: 71478 | P2: 1778 | R2: 3.76 | S2: 0.060369053 | T2: 1.1326344 | W2: kitchen faucets | X2: 厨房水龙头 | Y2: 1778 | AA2: # | AB2: 关键词 | AC2: 翻译 | AD2: 相关性-自动百分比 | AE2: 相关性-自动 | AF2: 自然位前4占位率 | AG2: 自然位前8占位率 | AH2: 自然位前16占位率 | AI2: 自然位前32占位率 | AJ2: 自然位前48占位率 | AK2: 搜索量 | AL2: 排名 | AM2: 相关性-手动 | AN2: CPC | AO2: 点击转化率 | AP2: 预期ACOS
A3: kitchen faucet | B3: 6562 | C3: 3.76 | D3: 0.062491534 | F3: kitchen faucet | G3: 厨房水龙头 | H3: 56.96% | I3: 高相关 | J3: 62.5% | K3: 57.81% | L3: 46.09% | M3: 44.92% | N3: 40.1% | O3: 29414 | P3: 6562 | R3: 3.76 | S3: 0.062491534 | T3: 1.0941653 | W3: kitchen faucet | X3: 厨房水龙头 | Y3: 6562 | AA3: 1 | AB3: delta essa pull down kitchen faucet | AC3: 三角洲埃萨下拉式厨房水龙头 | AD3: 86.64% | AE3: 高相关 | AF3: 100% | AG3: 85.94% | AH3: 67.97% | AI3: 52.73% | AJ3: 42.19% | AK3: 348 | AL3: 919116 | AN3: 3.4 | AO3: 0.079887 | AP3: 0.77396101
A4: kitchen sink faucet | B4: 10754 | C4: 3.19 | D4: 0.061680725 | F4: kitchen sink faucet | G4: 厨房水槽水龙头 | H4: 56.88% | I4: 高相关 | J4: 65.63% | K4: 54.69% | L4: 40.63% | M4: 44.53% | N4: 39.58% | O4: 21045 | P4: 10754 | R4: 3.19 | S4: 0.061680725 | T4: 0.94049717 | W4: kitchen sink faucet | X4: 厨房水槽水龙头 | Y4: 10754 | AA4: 2 | AB4: delta kitchen faucets with pull down sprayer | AC4: 三角洲厨房水龙头带下拉喷头 | AD4: 75.61% | AE4: 高相关 | AF4: 81.25% | AG4: 76.56% | AH4: 76.56% | AI4: 44.92% | AJ4: 40.36% | AK4: 1297 | AL4: 245442 | AN4: 4.18 | AO4: 0.081352 | AP4: 0.93438171
A5: kitchen faucet with pull down sprayer | B5: 11369 | C5: 2.58 | D5: 0.056448382 | F5: kitchen faucet with pull down sprayer | G5: 带下拉喷头的厨房水龙头 | H5: 53.23% | I5: 高相关 | J5: 53.13% | K5: 56.25% | L5: 50.78% | M5: 51.56% | N5: 45.83% | O5: 20191 | P5: 11369 | R5: 2.58 | S5: 0.056448382 | T5: 0.83115972 | W5: kitchen faucet with pull down sprayer | X5: 带下拉喷头的厨房水龙头 | Y5: 11369 | AA5: 3 | AB5: delta faucet kitchen | AC5: 三角洲水龙头厨房 | AD5: 72.21% | AE5: 高相关 | AF5: 75% | AG5: 81.25% | AH5: 66.41% | AI5: 46.88% | AJ5: 38.54% | AK5: 641 | AL5: 501803 | AN5: 2.56 | AO5: 0.081352 | AP5: 0.57225291
A6: faucet mat for kitchen sink | B6: 13681 | C6: 0.51 | D6: 0.055100302 | F6: sink faucet | G6: 水槽水龙头 | H6: 56.76% | I6: 高相关 | J6: 75% | K6: 46.88% | L6: 34.38% | M6: 24.61% | N6: 22.14% | O6: 13797 | P6: 18299 | R6: 2.51 | S6: 0.06614596 | T6: 0.69005972 | W6: sink faucet | X6: 水槽水龙头 | Y6: 18299 | AA6: 4 | AB6: kitchen faucets delta | AC6: Delta品牌厨房水龙头 | AD6: 71% | AE6: 高相关 | AF6: 75% | AG6: 78.13% | AH6: 64.84% | AI6: 44.53% | AJ6: 37.5% | AK6: 378 | AL6: 847101 | AN6: 2.87 | AO6: 0.081352 | AP6: 0.64154916
A7: black kitchen faucet | B7: 27388 | C7: 3.5 | D7: 0.057400552 | F7: black kitchen faucet | G7: 黑色厨房水龙头 | H7: 40.2% | I7: 高相关 | J7: 37.5% | K7: 42.19% | L7: 48.44% | M7: 39.84% | N7: 28.13% | O7: 9803 | P7: 27388 | R7: 3.5 | S7: 0.057400552 | T7: 1.1088384 | W7: faucet | X7: 水龙头 | Y7: 29423 | AA7: 5 | AB7: delta kitchen faucet | AC7: 三角洲厨房水龙头 | AD7: 70.14% | AE7: 高相关 | AF7: 71.88% | AG7: 79.69% | AH7: 66.41% | AI7: 46.09% | AJ7: 36.46% | AK7: 7025 | AL7: 39981 | AN7: 4.02 | AO7: 0.046845727 | AP7: 1.5605308
A8: moen kitchen faucet | B8: 29648 | C8: 2.54 | D8: 0.050911445 | F8: faucet | G8: 水龙头 | H8: 56.69% | I8: 高相关 | J8: 68.75% | K8: 54.69% | L8: 38.28% | M8: 30.47% | N8: 25.52% | O8: 9202 | P8: 29423 | R8: 2.43 | S8: 0.064988734 | T8: 0.67996174 | W8: moen kitchen faucet | X8: 摩恩厨房水龙头 | Y8: 29648 | AA8: 6 | AB8: kitchen facet with sprayer | AD8: 69.32% | AE8: 高相关 | AF8: 81.25% | AG8: 68.75% | AH8: 48.44% | AI8: 44.14% | AJ8: 38.28% | AK8: 560 | AL8: 574490 | AN8: 1.47 | AO8: 0.081352 | AP8: 0.32859835
A9: delta kitchen faucet | B9: 39981 | C9: 4.02 | D9: 0.046845727 | F9: moen kitchen faucet | G9: 摩恩厨房水龙头 | H9: 40.83% | I9: 高相关 | J9: 56.25% | K9: 34.38% | L9: 18.75% | M9: 12.5% | N9: 14.06% | O9: 9141 | P9: 29648 | R9: 2.54 | S9: 0.050911445 | T9: 0.90726587 | W9: delta kitchen faucet | X9: 三角洲厨房水龙头 | Y9: 39981 | AA9: 7 | AB9: delta kitchen faucets | AC9: 三角洲厨房水龙头 | AD9: 67.84% | AE9: 高相关 | AF9: 71.88% | AG9: 73.44% | AH9: 61.72% | AI9: 45.31% | AJ9: 37.24% | AK9: 752 | AL9: 427201 | AN9: 4.02 | AO9: 0.081352 | AP9: 0.8986159
A10: faucet for kitchen sink | B10: 42322 | C10: 2.26 | D10: 0.062756054 | F10: delta kitchen faucet | G10: 三角洲厨房水龙头 | H10: 70.14% | I10: 高相关 | J10: 71.88% | K10: 79.69% | L10: 66.41% | M10: 46.09% | N10: 36.46% | O10: 7025 | P10: 39981 | R10: 4.02 | S10: 0.046845727 | T10: 1.5605308 | W10: faucet for kitchen sink | X10: 厨房水槽用水龙头 | Y10: 42322 | AA10: 8 | AB10: delta touchless kitchen faucet | AC10: 三角洲无触摸厨房水龙头 | AD10: 67.7% | AE10: 高相关 | AF10: 75% | AG10: 68.75% | AH10: 58.59% | AI10: 45.7% | AJ10: 34.11% | AK10: 611 | AL10: 526679 | AN10: 2.45 | AO10: 0.039254311 | AP10: 1.1349978
A11: kitchen faucet with sprayer | B11: 45751 | C11: 3.59 | D11: 0.064897773 | F11: faucet for kitchen sink | G11: 厨房水槽用水龙头 | H11: 60.78% | I11: 高相关 | J11: 71.88% | K11: 57.81% | L11: 40.63% | M11: 41.8% | N11: 45.57% | O11: 6676 | P11: 42322 | R11: 2.26 | S11: 0.062756054 | T11: 0.6548911 | W11: kitchen faucet with sprayer | X11: 带喷头的厨房水龙头 | Y11: 45751 | AA11: 9 | AB11: pulldown kitchen faucet | AC11: 下拉式厨房水龙头 | AD11: 66.06% | AE11: 高相关 | AF11: 75% | AG11: 59.38% | AH11: 59.38% | AI11: 50.78% | AJ11: 41.93% | AK11: 156 | AL11: 1970885 | AN11: 3.36 | AO11: 0.081352 | AP11: 0.75108195
A12: gold kitchen faucet | B12: 47740 | C12: 3.69 | D12: 0.044260531 | F12: kitchen faucet with sprayer | G12: 带喷头的厨房水龙头 | H12: 53.62% | I12: 高相关 | J12: 65.63% | K12: 48.44% | L12: 35.16% | M12: 35.16% | N12: 32.03% | O12: 6247 | P12: 45751 | R12: 3.59 | S12: 0.064897773 | T12: 1.0059605 | W12: touchless kitchen faucet | X12: 无接触厨房水龙头 | Y12: 70627 | AA12: 10 | AB12: brushed nickel kitchen faucet with sprayer | AC12: 带喷头的拉丝镍厨房水龙头 | AD12: 65.04% | AE12: 高相关 | AF12: 78.13% | AG12: 56.25% | AH12: 53.13% | AI12: 41.8% | AJ12: 33.85% | AK12: 0 | AL12: 0 | AN12: #N/A | AO12: #N/A | AP12: #N/A
A13: touchless kitchen faucet | B13: 70627 | C13: 3.15 | D13: 0.035559433 | F13: gold kitchen faucet | G13: 金色厨房水龙头 | H13: 39.64% | I13: 中相关 | J13: 40.63% | K13: 45.31% | L13: 38.28% | M13: 24.61% | N13: 17.71% | O13: 6025 | P13: 47740 | R13: 3.69 | S13: 0.044260531 | T13: 1.5160936 | W13: kohler kitchen faucet | X13: 科勒 厨房水龙头 | Y13: 85167 | AA13: 11 | AB13: pulldown kitchen faucets | AC13: 下拉式厨房水龙头 | AD13: 64.75% | AE13: 高相关 | AF13: 75% | AG13: 54.69% | AH13: 57.81% | AI13: 51.17% | AJ13: 44.01% | AK13: 252 | AL13: 1255818 | AN13: 3.36 | AO13: 0.081352 | AP13: 0.75108195
A14: kitchen faucet head replacement | B14: 76603 | C14: 2.09 | D14: 0.12129871 | F14: touchless kitchen faucet | G14: 无接触厨房水龙头 | H14: 21.47% | I14: 中相关 | J14: 18.75% | K14: 21.88% | L14: 26.56% | M14: 28.13% | N14: 22.4% | O14: 4227 | P14: 70627 | R14: 3.15 | S14: 0.035559433 | T14: 1.6109127 | W14: kitchen sink faucet with sprayer | X14: 带喷头的厨房水槽龙头 | Y14: 90629 | AA14: 12 | AB14: stainless steel kitchen faucet | AC14: 不锈钢厨房水龙头 | AD14: 64.32% | AE14: 高相关 | AF14: 75% | AG14: 59.38% | AH14: 53.91% | AI14: 41.02% | AJ14: 34.11% | AK14: 863 | AL14: 371903 | AN14: 3.71 | AO14: 0.081352 | AP14: 0.82931965
A15: kohler kitchen faucet | B15: 85167 | C15: 2.42 | D15: 0.035202906 | F15: kohler kitchen faucet | G15: 科勒 厨房水龙头 | H15: 24.97% | I15: 中相关 | J15: 31.25% | K15: 25% | L15: 12.5% | M15: 11.33% | N15: 14.32% | O15: 3560 | P15: 85167 | R15: 2.42 | S15: 0.035202906 | T15: 1.2501241 | W15: kitchen sink faucets | X15: 厨房水槽龙头 | Y15: 94780 | AA15: 13 | AB15: faucet for kitchen | AC15: 厨房用水龙头 | AD15: 63.92% | AE15: 高相关 | AF15: 75% | AG15: 62.5% | AH15: 42.19% | AI15: 46.88% | AJ15: 39.58% | AK15: 186 | AL15: 1671777 | AN15: 1.7 | AO15: 0.092629 | AP15: 0.33374766
A16: kitchen faucet mat | B16: 90044 | C16: 0.35 | D16: 0.049361467 | F16: kitchen sink faucet with sprayer | G16: 带喷头的厨房水槽龙头 | H16: 47.51% | I16: 高相关 | J16: 50% | K16: 48.44% | L16: 42.97% | M16: 41.41% | N16: 35.16% | O16: 3353 | P16: 90629 | R16: 4.02 | S16: 0.060667653 | T16: 1.2049947 | W16: kraus kitchen faucet | X16: 克劳斯厨房龙头 | Y16: 114377 | AA16: 14 | AB16: pull down faucet | AC16: 下拉水龙头 | AD16: 63.67% | AE16: 高相关 | AF16: 75% | AG16: 64.06% | AH16: 42.19% | AI16: 38.28% | AJ16: 38.28% | AK16: 348 | AL16: 919116 | AN16: 2.06 | AO16: 0.081352 | AP16: 0.46048477
A17: kitchen sink faucet with sprayer | B17: 90629 | C17: 4.02 | D17: 0.060667653 | F17: kitchen sink faucets | G17: 厨房水槽龙头 | H17: 53.34% | I17: 高相关 | J17: 53.13% | K17: 62.5% | L17: 46.09% | M17: 43.75% | N17: 39.06% | O17: 3217 | P17: 94780 | R17: 3.19 | S17: 0.056598755 | T17: 1.0249439 | W17: kitchen faucets with pull down sprayer | X17: 带下拉喷头的厨房水龙头 | Y17: 123841 | AA17: 15 | AB17: kitchen faucet brushed nickel | AC17: 拉丝镍厨房水龙头 | AD17: 63.19% | AE17: 高相关 | AF17: 71.88% | AG17: 60.94% | AH17: 52.34% | AI17: 44.92% | AJ17: 34.11% | AK17: 353 | AL17: 906155 | AN17: 2.42 | AO17: 0.131739 | AP17: 0.33405447
A18: kitchen sink faucets | B18: 94780 | C18: 3.19 | D18: 0.056598755 | F18: kitchen faucets with pull down sprayer | G18: 带下拉喷头的厨房水龙头 | H18: 58.16% | I18: 高相关 | J18: 53.13% | K18: 67.19% | L18: 64.84% | M18: 54.69% | N18: 41.41% | O18: 2505 | P18: 123841 | R18: 3.29 | S18: 0.05320486 | T18: 1.1245037 | W18: llaves para fregaderos de cocina | X18: 厨房水槽钥匙 | Y18: 140745 | AA18: 16 | AB18: pull-down sprayer kitchen faucets | AC18: 拉下喷头厨房水龙头 | AD18: 62.95% | AE18: 高相关 | AF18: 71.88% | AG18: 57.81% | AH18: 50.78% | AI18: 51.17% | AJ18: 45.31% | AK18: 0 | AL18: 0 | AN18: 1.87 | AO18: 0.081352 | AP18: 0.41801287
A19: kraus kitchen faucet | B19: 114377 | C19: 1.9 | D19: 0.038233 | F19: llaves para fregaderos de cocina | G19: 厨房水槽钥匙 | H19: 42.23% | I19: 高相关 | J19: 50% | K19: 40.63% | L19: 31.25% | M19: 25% | N19: 21.35% | O19: 2217 | P19: 140745 | R19: 2.86 | S19: 0.065509249 | T19: 0.79392539 | W19: rv kitchen faucet | X19: 房车厨房水龙头 | Y19: 143856 | AA19: 17 | AB19: brushed nickel kitchen faucet | AC19: 拉丝镍厨房水龙头 | AD19: 62.57% | AE19: 高相关 | AF19: 68.75% | AG19: 64.06% | AH19: 53.91% | AI19: 44.14% | AJ19: 33.59% | AK19: 1313 | AL19: 242533 | AN19: 2.82 | AO19: 0.081352 | AP19: 0.63037235
A20: kitchen faucets with pull down sprayer | B20: 123841 | C20: 3.29 | D20: 0.05320486 | F20: rv kitchen faucet | G20: 房车厨房水龙头 | H20: 32.68% | I20: 中相关 | J20: 46.88% | K20: 25% | L20: 12.5% | M20: 11.72% | N20: 9.9% | O20: 2171 | P20: 143856 | R20: 0.91 | S20: 0.070128538 | T20: 0.23597331 | W20: grifos para fregaderos de cocina | X20: 厨房水槽龙头 | Y20: 171725 | AA20: 18 | AB20: oil rubbed bronze kitchen faucet | AC20: 油擦青铜厨房水龙头 | AD20: 62.46% | AE20: 高相关 | AF20: 78.13% | AG20: 57.81% | AH20: 39.06% | AI20: 33.59% | AJ20: 24.48% | AK20: 1075 | AL20: 297177 | AN20: 3.32 | AO20: 0.047758928 | AP20: 1.2641534
A21: faucet filter for kitchen sink | B21: 133583 | C21: 0.76 | D21: 0.076039462 | F21: brass kitchen faucet | G21: 黄铜厨房水龙头 | H21: 35.21% | I21: 中相关 | J21: 43.75% | K21: 34.38% | L21: 21.88% | M21: 14.45% | N21: 14.84% | O21: 1893 | P21: 166073 | R21: 2.16 | S21: 0.033496014 | T21: 1.1726729 | W21: grohe kitchen faucet | X21: 高仪厨房水龙头 | Y21: 174721 | AA21: 19 | AB21: faucets for kitchen sinks with sprayer | AC21: 带喷头的厨房水槽用水龙头 | AD21: 62.34% | AE21: 高相关 | AF21: 71.88% | AG21: 60.94% | AH21: 46.88% | AI21: 43.75% | AJ21: 35.68% | AK21: 580 | AL21: 554620 | AN21: 2.51 | AO21: 0.081352 | AP21: 0.5610761
A22: rv kitchen faucet | B22: 143856 | C22: 0.91 | D22: 0.070128538 | F22: grifos para fregaderos de cocina | G22: 厨房水槽龙头 | H22: 43.99% | I22: 高相关 | J22: 53.13% | K22: 45.31% | L22: 26.56% | M22: 21.48% | N22: 20.31% | O22: 1833 | P22: 171725 | R22: 2.62 | S22: 0.035506 | T22: 1.3418866 | W22: kitchen faucets touchless | X22: 厨房水龙头免触摸 | Y22: 183879 | AA22: 20 | AB22: kitchen faucet bronze | AC22: 青铜厨房水龙头 | AD22: 61.94% | AE22: 高相关 | AF22: 78.13% | AG22: 54.69% | AH22: 38.28% | AI22: 37.11% | AJ22: 28.91% | AK22: 166 | AL22: 1860299 | AN22: 1.94 | AO22: 0.060749 | AP22: 0.58073617
A23: brass kitchen faucet | B23: 166073 | C23: 2.16 | D23: 0.033496014 | F23: brushed gold kitchen faucet | G23: 拉丝金厨房龙头 | H23: 42.29% | I23: 高相关 | J23: 46.88% | K23: 48.44% | L23: 32.81% | M23: 19.53% | N23: 15.1% | O23: 1747 | P23: 180526 | R23: 3.43 | S23: 0.037947732 | T23: 1.6437076 | W23: delta faucet | X23: Delta水龙头 | Y23: 187867 | AA23: 21 | AB23: faucet kitchen | AC23: 厨房水龙头 | AD23: 61.54% | AE23: 高相关 | AF23: 75% | AG23: 51.56% | AH23: 45.31% | AI23: 44.92% | AJ23: 40.1% | AK23: 863 | AL23: 371903 | AN23: 3.36 | AO23: 0.081352 | AP23: 0.75108195
A24: faucet water filter for kitchen sink | B24: 170795 | C24: 3.47 | D24: 0.067677758 | F24: champagne bronze kitchen faucet | G24: 香槟青铜厨房水龙头 | H24: 39.32% | I24: 中相关 | J24: 50% | K24: 32.81% | L24: 28.13% | M24: 19.53% | N24: 17.71% | O24: 1727 | P24: 182747 | R24: 2.59 | S24: 0.042947797 | T24: 1.096668 | W24: pull down kitchen faucet | X24: 厨房用下拉水龙头 | Y24: 189072 | AA24: 22 | AB24: faucet kitchen sink | AC24: 厨房水槽水龙头 | AD24: 61.06% | AE24: 高相关 | AF24: 71.88% | AG24: 56.25% | AH24: 44.53% | AI24: 44.92% | AJ24: 41.15% | AK24: 510 | AL24: 630809 | AN24: 3.7 | AO24: 0.081352 | AP24: 0.82708429
... A28: champagne bronze kitchen faucet | B28: 182747 | C28: 2.59 | D28: 0.042947797 | F28: black faucet kitchen | G28: 厨房黑色水龙头 | H28: 34.75% | I28: 中相关 | J28: 25% | K28: 48.44% | L28: 43.75% | M28: 37.5% | N28: 31.77% | O28: 1525 | P28: 207944 | R28: 2.26 | S28: 0.077946 | T28: 0.52726736 | W28: brushed nickel kitchen faucet | X28: 拉丝镍厨房水龙头 | Y28: 242533 | AA28: 26 | AB28: kitchen faucet￼ | AC28: 厨房水龙头￼ | AD28: 60.39% | AE28: 高相关 | AF28: 75% | AG28: 53.13% | AH28: 38.28% | AI28: 38.67% | AJ28: 38.54% | AK28: 333 | AL28: 960105 | AN28: 1.9 | AO28: 0.098268 | AP28: 0.3516072
A29: kitchen faucets touchless | B29: 183879 | C29: 3.49 | D29: 0.07493 | F29: llave para fregadero de cocina | G29: 厨房水槽钥匙 | H29: 48.79% | I29: 高相关 | J29: 56.25% | K29: 51.56% | L29: 35.94% | M29: 24.61% | N29: 22.14% | O29: 1484 | P29: 213831 | R29: 1.65 | S29: 0.081352 | T29: 0.36883488 | W29: delta kitchen faucets with pull down sprayer | X29: 三角洲厨房水龙头带下拉喷头 | Y29: 245442 | AA29: 27 | AB29: chrome kitchen sink faucet | AC29: 镀铬厨房水槽水龙头 | AD29: 59.8% | AE29: 高相关 | AF29: 68.75% | AG29: 64.06% | AH29: 42.97% | AI29: 30.47% | AJ29: 27.6% | AK29: 0 | AL29: 0 | AN29: #N/A | AO29: #N/A | AP29: #N/A
A30: pull down kitchen faucet | B30: 189072 | C30: 3.52 | D30: 0.07119 | F30: matte black kitchen faucet | G30: 哑光黑色厨房水龙头 | H30: 38.64% | I30: 中相关 | J30: 37.5% | K30: 39.06% | L30: 43.75% | M30: 37.5% | N30: 31.25% | O30: 1409 | P30: 225674 | R30: 1.13 | S30: 0.084534 | T30: 0.24308788 | W30: kitchen faucets with sprayer | X30: 带喷头的厨房水龙头 | Y30: 245442 | AA30: 28 | AB30: kitchen water faucet | AC30: 厨房水龙头 | AD30: 59.77% | AE30: 高相关 | AF30: 71.88% | AG30: 56.25% | AH30: 42.19% | AI30: 35.94% | AJ30: 30.99% | AK30: 414 | AL30: 775813 | AN30: 2.94 | AO30: 0.081352 | AP30: 0.6571967
A31: black faucet kitchen | B31: 207944 | C31: 2.26 | D31: 0.077946 | F31: brushed nickel kitchen faucet | G31: 拉丝镍厨房水龙头 | H31: 62.57% | I31: 高相关 | J31: 68.75% | K31: 64.06% | L31: 53.91% | M31: 44.14% | N31: 33.59% | O31: 1313 | P31: 242533 | R31: 2.82 | S31: 0.081352 | T31: 0.63037235 | W31: kitchen faucet with soap dispenser | X31: 带肥皂分配器的厨房水龙头 | Y31: 272532 | AA31: 29 | AB31: kitchen faucets | AC31: 厨房水龙头 | AD31: 59.69% | AE31: 高相关 | AF31: 65.63% | AG31: 62.5% | AH31: 45.31% | AI31: 45.7% | AJ31: 41.93% | AK31: 71478 | AL31: 1778 | AN31: 3.76 | AO31: 0.060369053 | AP31: 1.1326344
A32: kitchen sink faucet mat | B32: 210135 | C32: 0.55 | D32: 0.042928 | F32: delta kitchen faucets with pull down sprayer | G32: 三角洲厨房水龙头带下拉喷头 | H32: 75.61% | I32: 高相关 | J32: 81.25% | K32: 76.56% | L32: 76.56% | M32: 44.92% | N32: 40.36% | O32: 1297 | P32: 245442 | R32: 4.18 | S32: 0.081352 | T32: 0.93438171 | W32: laundry sink faucet | X32: 洗衣槽水龙头 | Y32: 273735 | AA32: 30 | AB32: kitchen fixtures | AC32: 厨房固定装置 | AD32: 59.07% | AE32: 高相关 | AF32: 71.88% | AG32: 59.38% | AH32: 40.63% | AI32: 24.22% | AJ32: 16.67% | AK32: 353 | AL32: 906155 | AN32: 1.78 | AO32: 0.081352 | AP32: 0.3978946
A33: matte black kitchen faucet | B33: 225674 | C33: 1.13 | D33: 0.084534 | F33: kitchen faucets with sprayer | G33: 带喷头的厨房水龙头 | H33: 40.52% | I33: 高相关 | J33: 46.88% | K33: 37.5% | L33: 31.25% | M33: 30.47% | N33: 29.69% | O33: 1297 | P33: 245442 | R33: 1.99 | S33: 0.081352 | T33: 0.44483722 | W33: faucets | X33: 水龙头 | Y33: 281151 | AA33: 31 | AB33: top rated kitchen sink faucets | AC33: 顶级厨房水槽龙头 | AD33: 58.87% | AE33: 高相关 | AF33: 75% | AG33: 50% | AH33: 41.41% | AI33: 27.34% | AJ33: 24.74% | AK33: 0 | AL33: 0 | AN33: #N/A | AO33: #N/A | AP33: #N/A
A34: brushed nickel kitchen faucet | B34: 242533 | C34: 2.82 | D34: 0.081352 | F34: kitchen faucet black | G34: 黑色厨房水龙头 | H34: 51.5% | I34: 高相关 | J34: 56.25% | K34: 51.56% | L34: 45.31% | M34: 38.67% | N34: 32.55% | O34: 1222 | P34: 261110 | R34: 4.11 | S34: 0.081352 | T34: 0.91873417 | W34: rv kitchen sink faucet | X34: 房车厨房水槽水龙头 | Y34: 284945 | AA34: 32 | AB34: sink faucet kitchen | AC34: 厨房水槽水龙头 | AD34: 58.78% | AE34: 高相关 | AF34: 75% | AG34: 46.88% | AH34: 37.5% | AI34: 39.84% | AJ34: 38.28% | AK34: 550 | AL34: 585104 | AN34: 1.93 | AO34: 0.081352 | AP34: 0.43142505
A35: delta kitchen faucets with pull down sprayer | B35: 245442 | C35: 4.18 | D35: 0.081352 | F35: gold faucet for kitchen sink | G35: 厨房洗手盆金色水龙头 | H35: 44.96% | I35: 高相关 | J35: 40.63% | K35: 60.94% | L35: 46.09% | M35: 26.95% | N35: 20.57% | O35: 1202 | P35: 265538 | R35: 1.18 | S35: 0.045220813 | T35: 0.4745259 | W35: hansgrohe kitchen faucet | X35: 汉斯格雅厨房龙头 | Y35: 317039 | AA35: 33 | AB35: touch on kitchen sink faucets | AC35: 触摸厨房水槽龙头 | AD35: 58.62% | AE35: 高相关 | AF35: 65.63% | AG35: 54.69% | AH35: 51.56% | AI35: 44.53% | AJ35: 42.71% | AK35: 479 | AL35: 670474 | AN35: 2.26 | AO35: 0.081352 | AP35: 0.50519202
A36: kitchen faucets with sprayer | B36: 245442 | C36: 1.99 | D36: 0.081352 | F36: kitchen faucet with soap dispenser | G36: 带肥皂分配器的厨房水龙头 | H36: 43.6% | I36: 高相关 | J36: 50% | K36: 46.88% | L36: 28.13% | M36: 28.52% | N36: 22.14% | O36: 1171 | P36: 272532 | R36: 2.81 | S36: 0.081352 | T36: 0.62813699 | W36: pfister kitchen faucet | X36: Pfister 厨房水龙头 | Y36: 320294 | AA36: 34 | AB36: faucets | AC36: 水龙头 | AD36: 58.58% | AE36: 高相关 | AF36: 71.88% | AG36: 53.13% | AH36: 42.19% | AI36: 32.03% | AJ36: 26.3% | AK36: 1136 | AL36: 281151 | AN36: 2.43 | AO36: 0.077772 | AP36: 0.56819746
A37: kitchen faucet black | B37: 261110 | C37: 4.11 | D37: 0.081352 | F37: rv faucet | G37: 房车水龙头 | H37: 27.05% | I37: 中相关 | J37: 37.5% | K37: 23.44% | L37: 12.5% | M37: 6.25% | N37: 4.43% | O37: 1171 | P37: 272532 | R37: 0.79 | S37: 0.086178 | T37: 0.16670436 | W37: llave de fregadero de cocina | X37: 厨房水槽龙头 | Y37: 325241 | AA37: 35 | AB37: kitchen faucet for sink | AC37: 厨房水槽龙头 | AD37: 58.58% | AE37: 高相关 | AF37: 75% | AG37: 45.31% | AH37: 39.06% | AI37: 39.84% | AJ37: 36.72% | AK37: 0 | AL37: 0 | AN37: #N/A | AO37: #N/A | AP37: #N/A
A38: gold faucet for kitchen sink | B38: 265538 | C38: 1.18 | D38: 0.045220813 | F38: faucets | G38: 水龙头 | H38: 58.58% | I38: 高相关 | J38: 71.88% | K38: 53.13% | L38: 42.19% | M38: 32.03% | N38: 26.3% | O38: 1136 | P38: 281151 | R38: 2.43 | S38: 0.077772 | T38: 0.56819746 | W38: wewe kitchen faucet | X38: wewe 厨房水龙头 | Y38: 332095 | AA38: 36 | AB38: kitchen faucets with pull down sprayer | AC38: 带下拉喷头的厨房水龙头 | AD38: 58.16% | AE38: 高相关 | AF38: 53.13% | AG38: 67.19% | AH38: 64.84% | AI38: 54.69% | AJ38: 41.41% | AK38: 2505 | AL38: 123841 | AN38: 3.29 | AO38: 0.05320486 | AP38: 1.1245037
A39: kitchen faucet with soap dispenser | B39: 272532 | C39: 2.81 | D39: 0.081352 | F39: rv kitchen sink faucet | G39: 房车厨房水槽水龙头 | H39: 23.58% | I39: 中相关 | J39: 28.13% | K39: 25% | L39: 12.5% | M39: 14.06% | N39: 13.54% | O39: 1121 | P39: 284945 | R39: 2.52 | S39: 0.09705 | T39: 0.47219489 | W39: faucet kitchen | X39: 厨房水龙头 | Y39: 371903 | AA39: 37 | AB39: kitchen faucet delta | AC39: Delta厨房水龙头 | AD39: 57.69% | AE39: 高相关 | AF39: 62.5% | AG39: 64.06% | AH39: 46.88% | AI39: 35.94% | AJ39: 29.17% | AK39: 297 | AL39: 1070767 | AN39: 2.87 | AO39: 0.081352 | AP39: 0.64154916
A40: kitchen faucet head | B40: 281151 | C40: 0.82 | D40: 0.12143636 | F40: oil rubbed bronze kitchen faucet | G40: 油擦青铜厨房水龙头 | H40: 62.46% | I40: 高相关 | J40: 78.13% | K40: 57.81% | L40: 39.06% | M40: 33.59% | N40: 24.48% | O40: 1075 | P40: 297177 | R40: 3.32 | S40: 0.047758928 | T40: 1.2641534 | W40: stainless steel kitchen faucet | X40: 不锈钢厨房水龙头 | Y40: 371903 | AA40: 38 | AB40: delta champagne bronze kitchen faucet | AC40: 三角洲香槟青铜厨房水龙头 | AD40: 57.33% | AE40: 高相关 | AF40: 75% | AG40: 53.13% | AH40: 32.03% | AI40: 18.75% | AJ40: 14.32% | AK40: 479 | AL40: 670474 | AN40: 6.24 | AO40: 0.046416446 | AP40: 2.4447192
A41: rv kitchen sink faucet | B41: 284945 | C41: 2.52 | D41: 0.09705 | F41: black sink faucet kitchen | G41: 黑色厨房水槽水龙头 | H41: 24.18% | I41: 中相关 | J41: 12.5% | K41: 35.94% | L41: 38.28% | M41: 33.98% | N41: 27.34% | O41: 1060 | P41: 301637 | R41: 1.94 | S41: 0.094647 | T41: 0.37274443 | W41: touch kitchen faucet | X41: 触摸厨房水龙头 | Y41: 378490 | AA41: 39 | AB41: faucet for sink | AC41: 水槽龙头 | AD41: 57.16% | AE41: 高相关 | AF41: 75% | AG41: 51.56% | AH41: 31.25% | AI41: 22.27% | AJ41: 17.45% | AK41: 0 | AL41: 0 | AN41: #N/A | AO41: #N/A | AP41: #N/A
A42: silicone faucet mat for kitchen sink | B42: 286293 | C42: 0.35 | D42: 0.054148 | F42: bronze kitchen faucet | G42: 青铜厨房水龙头 | H42: 50.52% | I42: 高相关 | J42: 59.38% | K42: 45.31% | L42: 40.63% | M42: 36.72% | N42: 27.86% | O42: 1055 | P42: 303115 | R42: 1.94 | S42: 0.048941187 | T42: 0.72084769 | W42: single hole kitchen faucet | X42: 单孔厨房水龙头 | Y42: 397400 | AA42: 40 | AB42: kitchen faucet | AC42: 厨房水龙头 | AD42: 56.96% | AE42: 高相关 | AF42: 62.5% | AG42: 57.81% | AH42: 46.09% | AI42: 44.92% | AJ42: 40.1% | AK42: 29414 | AL42: 6562 | AN42: 3.76 | AO42: 0.062491534 | AP42: 1.0941653
A43: oil rubbed bronze kitchen faucet | B43: 297177 | C43: 3.32 | D43: 0.047758928 | F43: llave de fregadero de cocina | G43: 厨房水槽龙头 | H43: 47.62% | I43: 高相关 | J43: 56.25% | K43: 50% | L43: 28.13% | M43: 29.3% | N43: 24.22% | O43: 984 | P43: 325241 | R43: 1.93 | S43: 0.093296 | T43: 0.37619287 | W43: grifo de cocina | X43: 厨房水龙头 | Y43: 410241 | AA43: 41 | AB43: kitchen sink faucet | AC43: 厨房水槽水龙头 | AD43: 56.88% | AE43: 高相关 | AF43: 65.63% | AG43: 54.69% | AH43: 40.63% | AI43: 44.53% | AJ43: 39.58% | AK43: 21045 | AL43: 10754 | AN43: 3.19 | AO43: 0.061680725 | AP43: 0.94049717
A44: black sink faucet kitchen | B44: 301637 | C44: 1.94 | D44: 0.094647 | F44: kitchen faucets black | G44: 黑色厨房水龙头 | H44: 34.88% | I44: 中相关 | J44: 28.13% | K44: 39.06% | L44: 48.44% | M44: 39.84% | N44: 33.07% | O44: 964 | P44: 332095 | R44: 1.13 | S44: 0.093227 | T44: 0.22042102 | W44: kitchen faucet sprayer | X44: 厨房水龙头喷头 | Y44: 421330 | AA44: 42 | AB44: faucets for sink | AC44: 水槽用水龙头 | AD44: 56.82% | AE44: 高相关 | AF44: 75% | AG44: 50% | AH44: 31.25% | AI44: 22.66% | AJ44: 18.23% | AK44: 0 | AL44: 0 | AN44: #N/A | AO44: #N/A | AP44: #N/A
A45: bronze kitchen faucet | B45: 303115 | C45: 1.94 | D45: 0.048941187 | F45: wewe kitchen faucet | G45: wewe 厨房水龙头 | H45: 33.25% | I45: 中相关 | J45: 28.13% | K45: 46.88% | L45: 30.47% | M45: 29.69% | N45: 27.34% | O45: 964 | P45: 332095 | R45: 1.62 | S45: 0 | T45: #DIV/0! | W45: moen kitchen faucets | X45: 摩恩厨房水龙头 | Y45: 424252 | AA45: 43 | AB45: sink faucet | AC45: 水槽水龙头 | AD45: 56.76% | AE45: 高相关 | AF45: 75% | AG45: 46.88% | AH45: 34.38% | AI45: 24.61% | AJ45: 22.14% | AK45: 13797 | AL45: 18299 | AN45: 2.51 | AO45: 0.06614596 | AP45: 0.69005972
A46: kitchen faucet aerator | B46: 306199 | C46: 0.72 | D46: 0.12987385 | F46: water faucet | G46: 水龙头 | H46: 45.29% | I46: 高相关 | J46: 56.25% | K46: 45.31% | L46: 28.13% | M46: 17.19% | N46: 13.8% | O46: 924 | P46: 346854 | R46: 2.51 | S46: 0.081352 | T46: 0.5610761 | W46: delta kitchen faucets | X46: 三角洲厨房水龙头 | Y46: 427201 | AA46: 44 | AB46: faucet | AC46: 水龙头 | AD46: 56.69% | AE46: 高相关 | AF46: 68.75% | AG46: 54.69% | AH46: 38.28% | AI46: 30.47% | AJ46: 25.52% | AK46: 9202 | AL46: 29423 | AN46: 2.43 | AO46: 0.064988734 | AP46: 0.67996174
A47: moen kitchen faucet head replacement | B47: 315425 | C47: 1.63 | D47: 0.10875867 | F47: black kitchen faucet with pull down sprayer | G47: 带下拉喷头的黑色厨房水龙头 | H47: 37.22% | I47: 中相关 | J47: 37.5% | K47: 34.38% | L47: 39.84% | M47: 41.41% | N47: 33.33% | O47: 868 | P47: 369605 | R47: 3.12 | S47: 0.081352 | T47: 0.69743324 | W47: single handle kitchen faucet | X47: 单柄厨房水龙头 | Y47: 451647 | AA47: 45 | AB47: touch faucet kitchen | AC47: 厨房触控水龙头 | AD47: 56.28% | AE47: 高相关 | AF47: 71.88% | AG47: 46.88% | AH47: 36.72% | AI47: 31.64% | AJ47: 29.95% | AK47: 0 | AL47: 0 | AN47: #N/A | AO47: #N/A | AP47: #N/A
A48: hansgrohe kitchen faucet | B48: 317039 | C48: 9.27 | D48: 0.029531486 | F48: stainless steel kitchen faucet | G48: 不锈钢厨房水龙头 | H48: 64.32% | I48: 高相关 | J48: 75% | K48: 59.38% | L48: 53.91% | M48: 41.02% | N48: 34.11% | O48: 863 | P48: 371903 | R48: 3.71 | S48: 0.081352 | T48: 0.82931965 | W48: kitchen faucet with side sprayer | X48: 带侧喷头的厨房水龙头 | Y48: 454941 | AA48: 46 | AB48: faucets for kitchen | AC48: 厨房用水龙头 | AD48: 56.2% | AE48: 高相关 | AF48: 65.63% | AG48: 51.56% | AH48: 42.97% | AI48: 41.41% | AJ48: 38.28% | AK48: 0 | AL48: 0 | AN48: #N/A | AO48: #N/A | AP48: #N/A
A49: pfister kitchen faucet | B49: 320294 | C49: 12.58 | D49: 0.031911 | F49: faucet kitchen | G49: 厨房水龙头 | H49: 61.54% | I49: 高相关 | J49: 75% | K49: 51.56% | L49: 45.31% | M49: 44.92% | N49: 40.1% | O49: 863 | P49: 371903 | R49: 3.36 | S49: 0.081352 | T49: 0.75108195 | W49: moen kitchen faucets with pull down sprayer | X49: 摩恩带下拉喷头的厨房水龙头 | Y49: 458152 | AA49: 47 | AB49: chrome kitchen faucet | AC49: 镀铬厨房水龙头 | AD49: 56.09% | AE49: 高相关 | AF49: 68.75% | AG49: 50% | AH49: 41.41% | AI49: 31.25% | AJ49: 27.34% | AK49: 444 | AL49: 723302 | AN49: 2.37 | AO49: 0.081352 | AP49: 0.52978102
A50: kitchen faucet splash guard | B50: 323583 | C50: 0.51 | D50: 0.049027 | F50: touch kitchen faucet | G50: 触摸厨房水龙头 | H50: 54.64% | I50: 高相关 | J50: 65.63% | K50: 50% | L50: 39.06% | M50: 36.33% | N50: 30.73% | O50: 848 | P50: 378490 | R50: 2.22 | S50: 0.079793 | T50: 0.50594634 | W50: kitchen faucets with soap dispenser | X50: 带肥皂分配器的厨房水龙头 | Y50: 475276 | AA50: 48 | AB50: faucet for a sink | AC50: 水槽用水龙头 | AD50: 55.49% | AE50: 高相关 | AF50: 71.88% | AG50: 50% | AH50: 32.03% | AI50: 23.44% | AJ50: 20.31% | AK50: 0 | AL50: 0 | AN50: #N/A | AO50: #N/A | AP50: #N/A
A51: kitchen sink faucet head | B51: 325241 | C51: 0.79 | D51: 0.11681268 | F51: single hole kitchen faucet | G51: 单孔厨房水龙头 | H51: 52.82% | I51: 高相关 | J51: 59.38% | K51: 46.88% | L51: 49.22% | M51: 42.97% | N51: 34.11% | O51: 808 | P51: 397400 | R51: 2.6 | S51: 0.092445 | T51: 0.51145355 | W51: brushed brass kitchen faucet | X51: 拉丝黄铜厨房水龙头 | Y51: 475276 | AA51: 49 | AB51: pull down kitchen faucet | AC51: 厨房用下拉水龙头 | AD51: 55.44% | AE51: 高相关 | AF51: 65.63% | AG51: 48.44% | AH51: 43.75% | AI51: 41.02% | AJ51: 36.2% | AK51: 1671 | AL51: 189072 | AN51: 3.52 | AO51: 0.07119 | AP51: 0.89916615
A52: wewe kitchen faucet | B52: 332095 | C52: 1.62 | D52: 0 | F52: grifo de cocina | G52: 厨房水龙头 | H52: 55.2% | I52: 高相关 | J52: 65.63% | K52: 54.69% | L52: 37.5% | M52: 32.81% | N52: 26.3% | O52: 782 | P52: 410241 | R52: 2.86 | S52: 0.081352 | T52: 0.6393138 | W52: kitchen sprayer | X52: 厨房喷雾器 | Y52: 486243 | AA52: 50 | AB52: sink faucets | AC52: 水槽水龙头 | AD52: 55.24% | AE52: 高相关 | AF52: 68.75% | AG52: 51.56% | AH52: 33.59% | AI52: 28.52% | AJ52: 31.25% | AK52: 348 | AL52: 919116 | AN52: 1.96 | AO52: 0.094026 | AP52: 0.37907434
A53: kitchen faucets black | B53: 332095 | C53: 1.13 | D53: 0.093227 | F53: gold sink faucet kitchen | G53: 金色厨房水龙头 | H53: 41.65% | I53: 高相关 | J53: 40.63% | K53: 50% | L53: 41.41% | M53: 28.52% | N53: 21.09% | O53: 772 | P53: 415698 | R53: 0.5 | S53: 0.048068237 | T53: 0.18915947 | W53: laundry faucet | X53: 洗衣水龙头 | Y53: 493900 | AA53: 51 | AB53: grifo de cocina | AC53: 厨房水龙头 | AD53: 55.2% | AE53: 高相关 | AF53: 65.63% | AG53: 54.69% | AH53: 37.5% | AI53: 32.81% | AJ53: 26.3% | AK53: 782 | AL53: 410241 | AN53: 2.86 | AO53: 0.081352 | AP53: 0.6393138
A54: faucet draining mat for kitchen sink | B54: 352880 | C54: 0.54 | D54: 0.044492708 | F54: moen kitchen faucets | G54: 摩恩厨房水龙头 | H54: 39.46% | I54: 中相关 | J54: 53.13% | K54: 34.38% | L54: 18.75% | M54: 14.45% | N54: 16.15% | O54: 757 | P54: 424252 | R54: 3.55 | S54: 0.081352 | T54: 0.79355384 | W54: delta faucet kitchen | X54: 三角洲水龙头厨房 | Y54: 501803 | AA54: 52 | AB54: faucet for the sink | AC54: 水槽龙头 | AD54: 54.71% | AE54: 高相关 | AF54: 71.88% | AG54: 48.44% | AH54: 28.91% | AI54: 25.39% | AJ54: 18.49% | AK54: 0 | AL54: 0 | AN54: #N/A | AO54: #N/A | AP54: #N/A
A55: antique brass kitchen faucet | B55: 363232 | C55: 2.19 | D55: 0.024804127 | F55: delta kitchen faucets | G55: 三角洲厨房水龙头 | H55: 67.84% | I55: 高相关 | J55: 71.88% | K55: 73.44% | L55: 61.72% | M55: 45.31% | N55: 37.24% | O55: 752 | P55: 427201 | R55: 4.02 | S55: 0.081352 | T55: 0.8986159 | W55: moen faucet | X55: 摩恩水龙头 | Y55: 501803 | AA55: 53 | AB55: kitchen faucet touch | AC55: 厨房水龙头触摸 | AD55: 54.66% | AE55: 高相关 | AF55: 68.75% | AG55: 45.31% | AH55: 37.5% | AI55: 34.77% | AJ55: 29.95% | AK55: 0 | AL55: 0 | AN55: 2.72 | AO55: 0.081352 | AP55: 0.60801872
A56: faucet mat for kitchen sink 2 holes | B56: 367432 | C56: 0.45 | D56: 0.037289903 | F56: black kitchen sink faucet | G56: 黑色厨房水槽水龙头 | H56: 33.98% | I56: 中相关 | J56: 28.13% | K56: 39.06% | L56: 45.31% | M56: 35.16% | N56: 29.95% | O56: 722 | P56: 445187 | R56: 4.18 | S56: 0.077921 | T56: 0.97552419 | W56: forious kitchen faucet | X56: forious 厨房水龙头 | Y56: 526679 | AA56: 54 | AB56: touch kitchen faucet | AC56: 触摸厨房水龙头 | AD56: 54.64% | AE56: 高相关 | AF56: 65.63% | AG56: 50% | AH56: 39.06% | AI56: 36.33% | AJ56: 30.73% | AK56: 848 | AL56: 378490 | AN56: 2.22 | AO56: 0.079793 | AP56: 0.50594634
A57: black kitchen faucet with pull down sprayer | B57: 369605 | C57: 3.12 | D57: 0.081352 | F57: single handle kitchen faucet | G57: 单柄厨房水龙头 | H57: 42.39% | I57: 高相关 | J57: 46.88% | K57: 45.31% | L57: 32.81% | M57: 27.73% | N57: 25.52% | O57: 712 | P57: 451647 | R57: 2.66 | S57: 0.09219 | T57: 0.52470367 | W57: delta touchless kitchen faucet | X57: 三角洲无触摸厨房水龙头 | Y57: 526679 | AA57: 55 | AB57: delta kitchen sink faucet | AC57: 三角洲厨房水槽水龙头 | AD57: 54.59% | AE57: 高相关 | AF57: 56.25% | AG57: 64.06% | AH57: 47.66% | AI57: 34.77% | AJ57: 28.91% | AK57: 257 | AL57: 1232165 | AN57: 3 | AO57: 0.081352 | AP57: 0.67060888
A58: faucet kitchen | B58: 371903 | C58: 3.36 | D58: 0.081352 | F58: moen kitchen faucets with pull down sprayer | G58: 摩恩带下拉喷头的厨房水龙头 | H58: 53.63% | I58: 高相关 | J58: 75% | K58: 37.5% | L58: 28.13% | M58: 27.34% | N58: 20.83% | O58: 702 | P58: 458152 | R58: 3.42 | S58: 0.081352 | T58: 0.76449412 | W58: faucets for kitchen sinks with sprayer | X58: 带喷头的厨房水槽用水龙头 | Y58: 554620 | AA58: 56 | AB58: faucets for sinks | AC58: 水槽用水龙头 | AD58: 53.9% | AE58: 高相关 | AF58: 68.75% | AG58: 50% | AH58: 31.25% | AI58: 25% | AJ58: 19.53% | AK58: 0 | AL58: 0 | AN58: #N/A | AO58: #N/A | AP58: #N/A
A59: kitchen sink faucet organizer | B59: 371903 | C59: 0.78 | D59: 0.060814866 | F59: 水龙头 | G59: Water Faucet | H59: 47.43% | I59: 高相关 | J59: 62.5% | K59: 40.63% | L59: 28.91% | M59: 18.75% | N59: 12.5% | O59: 676 | P59: 475276 | R59: 1.49 | S59: 0.09467 | T59: 0.28621354 | W59: mop sink faucet | X59: 拖把池水龙头 | Y59: 564374 | AA59: 57 | AB59: touch kitchen faucets with pull down sprayer | AC59: 触摸带下拉喷头的厨房水龙头 | AD59: 53.83% | AE59: 高相关 | AF59: 68.75% | AG59: 43.75% | AH59: 35.16% | AI59: 33.2% | AJ59: 30.73% | AK59: 424 | AL59: 757686 | AN59: 2.37 | AO59: 0.081352 | AP59: 0.52978102
A60: stainless steel kitchen faucet | B60: 371903 | C60: 3.71 | D60: 0.081352 | F60: kitchen faucets with soap dispenser | G60: 带肥皂分配器的厨房水龙头 | H60: 43.53% | I60: 高相关 | J60: 50% | K60: 48.44% | L60: 28.91% | M60: 20.31% | N60: 22.14% | O60: 676 | P60: 475276 | R60: 1.93 | S60: 0.095449 | T60: 0.36770726 | W60: bar faucets single hole | X60: 单孔酒吧水龙头 | Y60: 569370 | AA60: 58 | AB60: moen kitchen faucets with pull down sprayer | AC60: 摩恩带下拉喷头的厨房水龙头 | AD60: 53.63% | AE60: 高相关 | AF60: 75% | AG60: 37.5% | AH60: 28.13% | AI60: 27.34% | AJ60: 20.83% | AK60: 702 | AL60: 458152 | AN60: 3.42 | AO60: 0.081352 | AP60: 0.76449412
A61: touch kitchen faucet | B61: 378490 | C61: 2.22 | D61: 0.079793 | F61: brushed brass kitchen faucet | G61: 拉丝黄铜厨房水龙头 | H61: 31.72% | I61: 中相关 | J61: 34.38% | K61: 34.38% | L61: 26.56% | M61: 21.09% | N61: 15.89% | O61: 676 | P61: 475276 | R61: 2.15 | S61: 0.036696698 | T61: 1.0654369 | W61: kitchen facet with sprayer | Y61: 574490 | AA61: 59 | AB61: kitchen faucet with sprayer | AC61: 带喷头的厨房水龙头 | AD61: 53.62% | AE61: 高相关 | AF61: 65.63% | AG61: 48.44% | AH61: 35.16% | AI61: 35.16% | AJ61: 32.03% | AK61: 6247 | AL61: 45751 | AN61: 3.59 | AO61: 0.064897773 | AP61: 1.0059605
A62: single hole kitchen faucet | B62: 397400 | C62: 2.6 | D62: 0.092445 | F62: rv faucets kitchen | G62: 房车厨房水龙头 | H62: 24.57% | I62: 中相关 | J62: 31.25% | K62: 25% | L62: 12.5% | M62: 7.42% | N62: 10.16% | O62: 666 | P62: 482537 | R62: 0.92 | S62: 0.096836 | T62: 0.17276958 | W62: touch faucet for kitchen sink | X62: 厨房水槽用触控水龙头 | Y62: 574490 | AA62: 60 | AB62: kitchen sink faucets | AC62: 厨房水槽龙头 | AD62: 53.34% | AE62: 高相关 | AF62: 53.13% | AG62: 62.5% | AH62: 46.09% | AI62: 43.75% | AJ62: 39.06% | AK62: 3217 | AL62: 94780 | AN62: 3.19 | AO62: 0.056598755 | AP62: 1.0249439
A63: commercial kitchen faucet | B63: 404983 | C63: 3.34 | D63: 0.067426837 | F63: kitchen faucet gold | G63: 金色厨房水龙头 | H63: 43.91% | I63: 高相关 | J63: 43.75% | K63: 56.25% | L63: 39.06% | M63: 22.66% | N63: 17.45% | O63: 646 | P63: 497869 | R63: 1.02 | S63: 0.040934696 | T63: 0.45313216 | W63: glacier bay kitchen faucet | X63: 冰川湾厨房水龙头 | Y63: 579826 | AA63: 61 | AB63: stainless kitchen faucets | AC63: 不锈钢厨房水龙头 | AD63: 53.26% | AE63: 高相关 | AF63: 50% | AG63: 62.5% | AH63: 59.38% | AI63: 39.06% | AJ63: 33.07% | AK63: 378 | AL63: 847101 | AN63: 1.74 | AO63: 0.096388 | AP63: 0.32827859
A64: faucet head for kitchen sink | B64: 404983 | C64: 2.08 | D64: 0.113681 | F64: delta faucet kitchen | G64: 三角洲水龙头厨房 | H64: 72.21% | I64: 高相关 | J64: 75% | K64: 81.25% | L64: 66.41% | M64: 46.88% | N64: 38.54% | O64: 641 | P64: 501803 | R64: 2.56 | S64: 0.081352 | T64: 0.57225291 | W64: 3 hole kitchen faucet | X64: 三孔厨房水龙头 | Y64: 579826 | AA64: 62 | AB64: kitchen faucet with pull down sprayer | AC64: 带下拉喷头的厨房水龙头 | AD64: 53.23% | AE64: 高相关 | AF64: 53.13% | AG64: 56.25% | AH64: 50.78% | AI64: 51.56% | AJ64: 45.83% | AK64: 20191 | AL64: 11369 | AN64: 2.58 | AO64: 0.056448382 | AP64: 0.83115972
A65: gold sink faucet kitchen | B65: 415698 | C65: 0.5 | D65: 0.048068237 | F65: moen faucet | G65: 摩恩水龙头 | H65: 34.44% | I65: 中相关 | J65: 50% | K65: 25% | L65: 15.63% | M65: 9.38% | N65: 6.25% | O65: 641 | P65: 501803 | R65: 3.39 | S65: 0.037374 | T65: 1.6494775 | W65: sink faucet kitchen | X65: 厨房水槽水龙头 | Y65: 585104 | AA65: 63 | AB65: kitchen sink faucet black matte modern | AC65: 厨房水槽水龙头黑色哑光现代 | AD65: 53.14% | AE65: 高相关 | AF65: 62.5% | AG65: 48.44% | AH65: 44.53% | AI65: 32.42% | AJ65: 27.6% | AK65: 0 | AL65: 0 | AN65: #N/A | AO65: #N/A | AP65: #N/A
A66: kitchen faucet sprayer head replacement | B66: 418510 | C66: 1.99 | D66: 0.12448846 | F66: black and gold kitchen faucet | G66: 黑金色厨房水龙头 | H66: 23.16% | I66: 中相关 | J66: 28.13% | K66: 25% | L66: 12.5% | M66: 9.77% | N66: 9.64% | O66: 636 | P66: 505844 | R66: 4.68 | S66: 0.039944473 | T66: 2.1306172 | W66: faucet sprayer | X66: 水龙头喷雾器 | Y66: 613009 | AA66: 64 | AB66: single hole kitchen faucet | AC66: 单孔厨房水龙头 | AD66: 52.82% | AE66: 高相关 | AF66: 59.38% | AG66: 46.88% | AH66: 49.22% | AI66: 42.97% | AJ66: 34.11% | AK66: 808 | AL66: 397400 | AN66: 2.6 | AO66: 0.092445 | AP66: 0.51145355
A67: kitchen faucet sprayer | B67: 421330 | C67: 0.7 | D67: 0.11248319 | F67: delta touchless kitchen faucet | G67: 三角洲无触摸厨房水龙头 | H67: 67.7% | I67: 高相关 | J67: 75% | K67: 68.75% | L67: 58.59% | M67: 45.7% | N67: 34.11% | O67: 611 | P67: 526679 | R67: 2.45 | S67: 0.039254311 | T67: 1.1349978 | W67: kohler kitchen faucets with pull down sprayer | X67: 科勒 带下拉喷头的厨房水龙头 | Y67: 618802 | AA67: 65 | AB67: touch faucet for kitchen sink | AC67: 厨房水槽用触控水龙头 | AD67: 52.79% | AE67: 高相关 | AF67: 68.75% | AG67: 39.06% | AH67: 36.72% | AI67: 32.03% | AJ67: 29.95% | AK67: 560 | AL67: 574490 | AN67: 2.16 | AO67: 0.036353439 | AP67: 1.0804994
A68: moen kitchen faucets | B68: 424252 | C68: 3.55 | D68: 0.081352 | F68: forious kitchen faucet | G68: forious 厨房水龙头 | H68: 41.46% | I68: 高相关 | J68: 50% | K68: 39.06% | L68: 28.91% | M68: 25.78% | N68: 18.49% | O68: 611 | P68: 526679 | R68: 1.92 | S68: 0.094934 | T68: 0.36778645 | W68: white kitchen faucet | X68: 白色厨房水龙头 | Y68: 618802 | AA68: 66 | AB68: kitchen faucet black | AC68: 黑色厨房水龙头 | AD68: 51.5% | AE68: 高相关 | AF68: 56.25% | AG68: 51.56% | AH68: 45.31% | AI68: 38.67% | AJ68: 32.55% | AK68: 1222 | AL68: 261110 | AN68: 4.11 | AO68: 0.081352 | AP68: 0.91873417
A69: delta kitchen faucets | B69: 427201 | C69: 4.02 | D69: 0.081352 | F69: faucets for kitchen sinks with sprayer | G69: 带喷头的厨房水槽用水龙头 | H69: 62.34% | I69: 高相关 | J69: 71.88% | K69: 60.94% | L69: 46.88% | M69: 43.75% | N69: 35.68% | O69: 580 | P69: 554620 | R69: 2.51 | S69: 0.081352 | T69: 0.5610761 | W69: faucet kitchen sink | X69: 厨房水槽水龙头 | Y69: 630809 | AA69: 67 | AB69: kitchen tap | AC69: 厨房水龙头 | AD69: 51.43% | AE69: 高相关 | AF69: 56.25% | AG69: 50% | AH69: 47.66% | AI69: 38.28% | AJ69: 32.55% | AK69: 237 | AL69: 1332510 | AN69: 4.1 | AO69: 0.081352 | AP69: 0.9164988
A70: kitchen faucet filter | B70: 433103 | C70: 1.97 | D70: 0.124332 | F70: kitchen facet with sprayer | H70: 69.32% | I70: 高相关 | J70: 81.25% | K70: 68.75% | L70: 48.44% | M70: 44.14% | N70: 38.28% | O70: 560 | P70: 574490 | R70: 1.47 | S70: 0.081352 | T70: 0.32859835 | W70: modern kitchen faucet | X70: 现代厨房水龙头 | Y70: 656742 | AA70: 68 | AB70: kitchen sink faucets with pullout sprayer | AC70: 带拉出喷头的厨房水槽龙头 | AD70: 51.19% | AE70: 高相关 | AF70: 59.38% | AG70: 53.13% | AH70: 36.72% | AI70: 26.56% | AJ70: 28.39% | AK70: 0 | AL70: 0 | AN70: #N/A | AO70: #N/A | AP70: #N/A
A71: copper kitchen faucet | B71: 442126 | C71: 3.3 | D71: 0.029135307 | F71: touch faucet for kitchen sink | G71: 厨房水槽用触控水龙头 | H71: 52.79% | I71: 高相关 | J71: 68.75% | K71: 39.06% | L71: 36.72% | M71: 32.03% | N71: 29.95% | O71: 560 | P71: 574490 | R71: 2.16 | S71: 0.036353439 | T71: 1.0804994 | W71: delta trinsic kitchen faucet | X71: 三角洲特林西克厨房水龙头 | Y71: 663610 | AA71: 69 | AB71: kitchen pull down faucet | AC71: 厨房下拉式水龙头 | AD71: 50.62% | AE71: 高相关 | AF71: 56.25% | AG71: 51.56% | AH71: 41.41% | AI71: 34.77% | AJ71: 32.03% | AK71: 257 | AL71: 1232165 | AN71: 3.67 | AO71: 0.081352 | AP71: 0.8203782
A72: black kitchen sink faucet | B72: 445187 | C72: 4.18 | D72: 0.077921 | F72: glacier bay kitchen faucet | G72: 冰川湾厨房水龙头 | H72: 38.93% | I72: 中相关 | J72: 50% | K72: 34.38% | L72: 23.44% | M72: 18.36% | N72: 17.71% | O72: 555 | P72: 579826 | R72: 1.66 | S72: 0.081352 | T72: 0.37107025 | W72: kitchen faucet touchless | X72: 厨房水龙头无触摸 | Y72: 663610 | AA72: 70 | AB72: bronze kitchen faucet | AC72: 青铜厨房水龙头 | AD72: 50.52% | AE72: 高相关 | AF72: 59.38% | AG72: 45.31% | AH72: 40.63% | AI72: 36.72% | AJ72: 27.86% | AK72: 1055 | AL72: 303115 | AN72: 1.94 | AO72: 0.048941187 | AP72: 0.72084769
A73: moen kitchen faucet parts | B73: 448307 | C73: 0.61 | D73: 0.13433177 | F73: sink faucet kitchen | G73: 厨房水槽水龙头 | H73: 58.78% | I73: 高相关 | J73: 75% | K73: 46.88% | L73: 37.5% | M73: 39.84% | N73: 38.28% | O73: 550 | P73: 585104 | R73: 1.93 | S73: 0.081352 | T73: 0.43142505 | W73: kitchen sink faucet with soap dispenser | X73: 带肥皂分配器的厨房水槽龙头 | Y73: 670474 | AA73: 71 | AB73: black kitchen faucets | AC73: 黑色厨房水龙头 | AD73: 50.5% | AE73: 高相关 | AF73: 50% | AG73: 56.25% | AH73: 52.34% | AI73: 37.5% | AJ73: 32.03% | AK73: 363 | AL73: 881675 | AN73: 2.09 | AO73: 0.101835 | AP73: 0.37322051
A74: single handle kitchen faucet | B74: 451647 | C74: 2.66 | D74: 0.09219 | F74: kitchen faucets gold | G74: 金色厨房水龙头 | H74: 42.18% | I74: 高相关 | J74: 40.63% | K74: 53.13% | L74: 42.19% | M74: 24.61% | N74: 17.71% | O74: 535 | P74: 601475 | R74: 1.02 | S74: 0.041988438 | T74: 0.44176035 | W74: touch on kitchen sink faucets | X74: 触摸厨房水槽龙头 | Y74: 670474 | AA74: 72 | AB74: touch faucet | AC74: 触控水龙头 | AD74: 49.09% | AE74: 高相关 | AF74: 56.25% | AG74: 48.44% | AH74: 39.06% | AI74: 29.69% | AJ74: 30.73% | AK74: 171 | AL74: 1809308 | AN74: 0.99 | AO74: 0.048251 | AP74: 0.3731171
A75: kitchen faucet with side sprayer | B75: 454941 | C75: 2.7 | D75: 0.081352 | F75: kohler kitchen faucets with pull down sprayer | G75: 科勒 带下拉喷头的厨房水龙头 | H75: 22.35% | I75: 中相关 | J75: 25% | K75: 18.75% | L75: 22.66% | M75: 16.02% | N75: 21.35% | O75: 520 | P75: 618802 | R75: 5.65 | S75: 0.033103 | T75: 3.1038261 | W75: delta leland kitchen faucet | X75: delta leland 厨房水龙头 | Y75: 670474 | AA75: 73 | AB75: black stainless kitchen pull down faucet | AC75: 黑色不锈钢厨房下拉式水龙头 | AD75: 49.07% | AE75: 高相关 | AF75: 43.75% | AG75: 60.94% | AH75: 53.13% | AI75: 42.58% | AJ75: 33.85% | AK75: 0 | AL75: 0 | AN75: #N/A | AO75: #N/A | AP75: #N/A
A76: kitchen sink with faucet combo | B76: 454941 | C76: 2.22 | D76: 0.033454 | F76: faucet kitchen sink | G76: 厨房水槽水龙头 | H76: 61.06% | I76: 高相关 | J76: 71.88% | K76: 56.25% | L76: 44.53% | M76: 44.92% | N76: 41.15% | O76: 510 | P76: 630809 | R76: 3.7 | S76: 0.081352 | T76: 0.82708429 | W76: brizo kitchen faucet | X76: brizo 厨房水龙头 | Y76: 670474 | AA76: 74 | AB76: llave para fregadero de cocina | AC76: 厨房水槽钥匙 | AD76: 48.79% | AE76: 高相关 | AF76: 56.25% | AG76: 51.56% | AH76: 35.94% | AI76: 24.61% | AJ76: 22.14% | AK76: 1484 | AL76: 213831 | AN76: 1.65 | AO76: 0.081352 | AP76: 0.36883488
A77: moen kitchen faucets with pull down sprayer | B77: 458152 | C77: 3.42 | D77: 0.081352 | F77: touchless kitchen faucets | G77: 无接触厨房水龙头 | H77: 25.31% | I77: 中相关 | J77: 18.75% | K77: 31.25% | L77: 37.5% | M77: 25% | N77: 25% | O77: 505 | P77: 637148 | R77: 5.12 | S77: 0.080401 | T77: 1.1580433 | W77: kitchen faucets moen | X77: Moen品牌厨房水龙头 | Y77: 677618 | AA77: 75 | AB77: grifos de cocina | AC77: 厨房龙头 | AD77: 48.69% | AE77: 高相关 | AF77: 56.25% | AG77: 51.56% | AH77: 32.03% | AI77: 28.52% | AJ77: 29.17% | AK77: 146 | AL77: 2094984 | AN77: 1.51 | AO77: 0.081352 | AP77: 0.3375398
A78: kitchen sink mats for around faucet | B78: 461418 | C78: 0.35 | D78: 0.115756 | F78: modern kitchen faucet | G78: 现代厨房水龙头 | H78: 36.84% | I78: 中相关 | J78: 43.75% | K78: 29.69% | L78: 28.91% | M78: 33.2% | N78: 29.43% | O78: 489 | P78: 656742 | R78: 2.9 | S78: 0.081352 | T78: 0.64825525 | W78: pull out kitchen faucet | X78: 拉出式厨房水龙头 | Y78: 677618 | AA78: 76 | AB78: stainless steel faucet | AC78: 不锈钢水龙头 | AD78: 48.53% | AE78: 高相关 | AF78: 53.13% | AG78: 53.13% | AH78: 35.94% | AI78: 34.38% | AJ78: 29.69% | AK78: 257 | AL78: 1232165 | AN78: 1.13 | AO78: 0.091787 | AP78: 0.2238791
A79: brushed brass kitchen faucet | B79: 475276 | C79: 2.15 | D79: 0.036696698 | F79: delta trinsic kitchen faucet | G79: 三角洲特林西克厨房水龙头 | H79: 31.68% | I79: 中相关 | J79: 31.25% | K79: 29.69% | L79: 35.16% | M79: 36.33% | N79: 27.34% | O79: 484 | P79: 663610 | R79: 2.86 | S79: 0.081352 | T79: 0.6393138 | W79: sprayer for kitchen sink | X79: 厨房水槽喷雾器 | Y79: 684880 | AA79: 77 | AB79: gold kitchen sink faucet | AC79: 金色厨房水槽水龙头 | AD79: 48% | AE79: 高相关 | AF79: 50% | AG79: 54.69% | AH79: 43.75% | AI79: 30.47% | AJ79: 21.09% | AK79: 409 | AL79: 785288 | AN79: 2.6 | AO79: 0.04554301 | AP79: 1.0381686
A80: kitchen faucets with soap dispenser | B80: 475276 | C80: 1.93 | D80: 0.095449 | F80: kitchen faucet touchless | G80: 厨房水龙头无触摸 | H80: 23.21% | I80: 中相关 | J80: 15.63% | K80: 32.81% | L80: 31.25% | M80: 26.17% | N80: 22.66% | O80: 484 | P80: 663610 | R80: 3.49 | S80: 0.078474 | T80: 0.80875302 | W80: 4 hole kitchen faucet | X80: 4孔厨房水龙头 | Y80: 692214 | AA80: 78 | AB80: black faucet with sprayer | AD80: 47.73% | AE80: 高相关 | AF80: 50% | AG80: 54.69% | AH80: 40.63% | AI80: 31.25% | AJ80: 25.78% | AK80: 0 | AL80: 0 | AN80: #N/A | AO80: #N/A | AP80: #N/A
A81: rv faucets kitchen | B81: 482537 | C81: 0.92 | D81: 0.096836 | F81: touch on kitchen sink faucets | G81: 触摸厨房水槽龙头 | H81: 58.62% | I81: 高相关 | J81: 65.63% | K81: 54.69% | L81: 51.56% | M81: 44.53% | N81: 42.71% | O81: 479 | P81: 670474 | R81: 2.26 | S81: 0.081352 | T81: 0.50519202 | W81: bar sink faucet single hole | X81: 吧台水槽水龙头单孔 | Y81: 707284 | AA81: 79 | AB81: matte black kitchen faucet with pull down sprayer | AC81: 带下拉喷头的哑光黑色厨房水龙头 | AD81: 47.62% | AE81: 高相关 | AF81: 50% | AG81: 48.44% | AH81: 44.53% | AI81: 39.45% | AJ81: 35.68% | AK81: 0 | AL81: 0 | AN81: #N/A | AO81: #N/A | AP81: #N/A
A82: kitchen faucet gold | B82: 497869 | C82: 1.02 | D82: 0.040934696 | F82: delta champagne bronze kitchen faucet | G82: 三角洲香槟青铜厨房水龙头 | H82: 57.33% | I82: 高相关 | J82: 75% | K82: 53.13% | L82: 32.03% | M82: 18.75% | N82: 14.32% | O82: 479 | P82: 670474 | R82: 6.24 | S82: 0.046416446 | T82: 2.4447192 | W82: touchless faucet for kitchen sink | X82: 无接触厨房水槽水龙头 | Y82: 723302 | AA82: 80 | AB82: llave de fregadero de cocina | AC82: 厨房水槽龙头 | AD82: 47.62% | AE82: 高相关 | AF82: 56.25% | AG82: 50% | AH82: 28.13% | AI82: 29.3% | AJ82: 24.22% | AK82: 984 | AL82: 325241 | AN82: 1.93 | AO82: 0.093296 | AP82: 0.37619287
A83: delta faucet kitchen | B83: 501803 | C83: 2.56 | D83: 0.081352 | F83: kitchen sink faucet with soap dispenser | G83: 带肥皂分配器的厨房水槽龙头 | H83: 43.28% | I83: 高相关 | J83: 50% | K83: 45.31% | L83: 31.25% | M83: 23.83% | N83: 19.79% | O83: 479 | P83: 670474 | R83: 2.18 | S83: 0.081352 | T83: 0.48730912 | W83: kitchen sink with faucet | X83: 带水龙头的厨房水槽 | Y83: 740039 | AA83: 81 | AB83: kitchen facet | AC83: 厨房水龙头 | AD83: 47.54% | AE83: 高相关 | AF83: 62.5% | AG83: 43.75% | AH83: 23.44% | AI83: 17.97% | AJ83: 19.27% | AK83: 297 | AL83: 1070767 | AN83: 0.72 | AO83: 0.081352 | AP83: 0.16094613
A84: black and gold kitchen faucet | B84: 505844 | C84: 4.68 | D84: 0.039944473 | F84: delta leland kitchen faucet | G84: delta leland 厨房水龙头 | H84: 32.12% | I84: 中相关 | J84: 25% | K84: 35.94% | L84: 46.09% | M84: 39.45% | N84: 32.03% | O84: 479 | P84: 670474 | R84: 2.34 | S84: 0.072552 | T84: 0.5865199 | W84: kitchen faucet 3 hole | X84: 三孔厨房水龙头 | Y84: 740039 | AA84: 82 | AB84: kitchen sink faucet with sprayer | AC84: 带喷头的厨房水槽龙头 | AD84: 47.51% | AE84: 高相关 | AF84: 50% | AG84: 48.44% | AH84: 42.97% | AI84: 41.41% | AJ84: 35.16% | AK84: 3353 | AL84: 90629 | AN84: 4.02 | AO84: 0.060667653 | AP84: 1.2049947
A85: delta kitchen faucet head replacement | B85: 526679 | C85: 1.49 | D85: 0.11573413 | F85: kitchen faucets moen | G85: Moen品牌厨房水龙头 | H85: 38.7% | I85: 中相关 | J85: 50% | K85: 32.81% | L85: 23.44% | M85: 19.53% | N85: 20.57% | O85: 474 | P85: 677618 | R85: 3.41 | S85: 0.081352 | T85: 0.76225876 | W85: moen adler kitchen faucet | X85: moen adler 厨房水龙头 | Y85: 740039 | AA85: 83 | AB85: 水龙头 | AC85: Water Faucet | AD85: 47.43% | AE85: 高相关 | AF85: 62.5% | AG85: 40.63% | AH85: 28.91% | AI85: 18.75% | AJ85: 12.5% | AK85: 676 | AL85: 475276 | AN85: 1.49 | AO85: 0.09467 | AP85: 0.28621354
A86: delta touchless kitchen faucet | B86: 526679 | C86: 2.45 | D86: 0.039254311 | F86: pull out kitchen faucet | G86: 拉出式厨房水龙头 | H86: 34.57% | I86: 中相关 | J86: 40.63% | K86: 34.38% | L86: 24.22% | M86: 19.14% | N86: 22.92% | O86: 474 | P86: 677618 | R86: 2.85 | S86: 0.081352 | T86: 0.63707844 | W86: touch kitchen faucets with pull down sprayer | X86: 触摸带下拉喷头的厨房水龙头 | Y86: 757686 | AA86: 84 | AB86: kitchen sink faucet gold | AC86: 厨房水槽金色水龙头 | AD86: 47.18% | AE86: 高相关 | AF86: 43.75% | AG86: 60.94% | AH86: 49.22% | AI86: 29.3% | AJ86: 21.09% | AK86: 272 | AL86: 1166314 | AN86: 2.96 | AO86: 0.051315 | AP86: 1.0489714
A87: forious kitchen faucet | B87: 526679 | C87: 1.92 | D87: 0.094934 | F87: matte black kitchen sink faucet | G87: 哑光黑色厨房水槽水龙头 | H87: 45.09% | I87: 高相关 | J87: 43.75% | K87: 51.56% | L87: 44.53% | M87: 38.28% | N87: 32.29% | O87: 469 | P87: 684880 | R87: 1 | S87: 0.093493 | T87: 0.19450787 | W87: grifería para cocina | X87: 厨房用水龙头 | Y87: 757686 | AA87: 85 | AB87: stainless steel faucet for kitchen sink | AC87: 厨房水槽用不锈钢水龙头 | AD87: 45.47% | AE87: 高相关 | AF87: 50% | AG87: 39.06% | AH87: 45.31% | AI87: 41.02% | AJ87: 34.64% | AK87: 348 | AL87: 919116 | AN87: 2.71 | AO87: 0.081352 | AP87: 0.60578336
A88: kitchen sink splash guard behind faucet | B88: 549784 | C88: 0.64 | D88: 0.054261 | F88: water tap | G88: 水龙头 | H88: 22.25% | I88: 中相关 | J88: 28.13% | K88: 21.88% | L88: 12.5% | M88: 9.38% | N88: 6.25% | O88: 459 | P88: 699704 | R88: 0.73 | S88: 0.051948 | T88: 0.25554672 | W88: kitchen water faucet | X88: 厨房水龙头 | Y88: 775813 | AA88: 86 | AB88: water faucet | AC88: 水龙头 | AD88: 45.29% | AE88: 高相关 | AF88: 56.25% | AG88: 45.31% | AH88: 28.13% | AI88: 17.19% | AJ88: 13.8% | AK88: 924 | AL88: 346854 | AN88: 2.51 | AO88: 0.081352 | AP88: 0.5610761
A89: water faucet filter for kitchen sink | B89: 549784 | C89: 1.41 | D89: 0.084665 | F89: brass faucet kitchen | G89: 厨房黄铜水龙头 | H89: 33.21% | I89: 中相关 | J89: 34.38% | K89: 37.5% | L89: 31.25% | M89: 20.7% | N89: 16.93% | O89: 454 | P89: 707284 | R89: 2.79 | S89: 0.035158175 | T89: 1.4430925 | W89: delta touch kitchen faucet | X89: 三角洲触摸厨房水龙头 | Y89: 794989 | AA89: 87 | AB89: laundry room faucet | AC89: 洗衣房水龙头 | AD89: 45.18% | AE89: 高相关 | AF89: 53.13% | AG89: 48.44% | AH89: 31.25% | AI89: 19.14% | AJ89: 15.89% | AK89: 328 | AL89: 974560 | AN89: 1.87 | AO89: 0.082072 | AP89: 0.41434573
A90: faucets for kitchen sinks with sprayer | B90: 554620 | C90: 2.51 | D90: 0.081352 | F90: chrome kitchen faucet | G90: 镀铬厨房水龙头 | H90: 56.09% | I90: 高相关 | J90: 68.75% | K90: 50% | L90: 41.41% | M90: 31.25% | N90: 27.34% | O90: 444 | P90: 723302 | R90: 2.37 | S90: 0.081352 | T90: 0.52978102 | W90: american standard kitchen faucet | X90: 美标厨房水龙头 | Y90: 815053 | AA90: 88 | AB90: matte black kitchen sink faucet | AC90: 哑光黑色厨房水槽水龙头 | AD90: 45.09% | AE90: 高相关 | AF90: 43.75% | AG90: 51.56% | AH90: 44.53% | AI90: 38.28% | AJ90: 32.29% | AK90: 469 | AL90: 684880 | AN90: 1 | AO90: 0.093493 | AP90: 0.19450787
A91: kitchen faucet water filter | B91: 569370 | C91: 2.06 | D91: 0.120183 | F91: touchless faucet for kitchen sink | G91: 无接触厨房水槽水龙头 | H91: 24.16% | I91: 中相关 | J91: 25% | K91: 25% | L91: 21.88% | M91: 21.48% | N91: 20.83% | O91: 444 | P91: 723302 | R91: 2 | S91: 0.036853944 | T91: 0.98687536 | W91: polished nickel kitchen faucet | X91: 抛光镍厨房水龙头 | Y91: 825433 | AA91: 89 | AB91: grifería lavaplatos | AC91: 洗碗池水龙头 | AD91: 45.06% | AE91: 高相关 | AF91: 53.13% | AG91: 50% | AH91: 28.91% | AI91: 16.8% | AJ91: 16.15% | AK91: 0 | AL91: 0 | AN91: #N/A | AO91: #N/A | AP91: #N/A
A92: touch faucet for kitchen sink | B92: 574490 | C92: 2.16 | D92: 0.036353439 | F92: kitchen faucet 3 hole | G92: 三孔厨房水龙头 | H92: 29.38% | I92: 中相关 | J92: 40.63% | K92: 23.44% | L92: 14.06% | M92: 10.94% | N92: 11.2% | O92: 434 | P92: 740039 | R92: 1.94 | S92: 0.081352 | T92: 0.43366041 | W92: stainless kitchen faucets | X92: 不锈钢厨房水龙头 | Y92: 847101 | AA92: 90 | AB92: gold faucet for kitchen sink | AC92: 厨房洗手盆金色水龙头 | AD92: 44.96% | AE92: 高相关 | AF92: 40.63% | AG92: 60.94% | AH92: 46.09% | AI92: 26.95% | AJ92: 20.57% | AK92: 1202 | AL92: 265538 | AN92: 1.18 | AO92: 0.045220813 | AP92: 0.4745259
A93: 3 hole kitchen faucet | B93: 579826 | C93: 1.96 | D93: 0.081352 | F93: moen adler kitchen faucet | G93: moen adler 厨房水龙头 | H93: 27.33% | I93: 中相关 | J93: 25% | K93: 37.5% | L93: 25% | M93: 16.8% | N93: 17.71% | O93: 434 | P93: 740039 | R93: 2.95 | S93: 0.115528 | T93: 0.46435598 | W93: kitchen faucets delta | X93: Delta品牌厨房水龙头 | Y93: 847101 | AA93: 91 | AB93: delta faucet | AC93: Delta水龙头 | AD93: 44.93% | AE93: 高相关 | AF93: 50% | AG93: 43.75% | AH93: 40.63% | AI93: 30.08% | AJ93: 26.3% | AK93: 1681 | AL93: 187867 | AN93: 0.35 | AO93: 0.059235218 | AP93: 0.10744948
A94: glacier bay kitchen faucet | B94: 579826 | C94: 1.66 | D94: 0.081352 | F94: rv kitchen faucet replacement | G94: 房车厨房水龙头更换 | H94: 20.33% | I94: 中相关 | J94: 25% | K94: 20.31% | L94: 12.5% | M94: 9.38% | N94: 7.29% | O94: 429 | P94: 748753 | R94: 0.78 | S94: 0.087209 | T94: 0.16264832 | W94: 3 hole kitchen faucet with sprayer | X94: 带喷头的三孔厨房水龙头 | Y94: 881675 | AA94: 92 | AB94: commercial high arch kitchen faucet | AC94: 商用高拱厨房水龙头 | AD94: 44.84% | AE94: 高相关 | AF94: 53.13% | AG94: 42.19% | AH94: 37.5% | AI94: 22.66% | AJ94: 17.45% | AK94: 0 | AL94: 0 | AN94: #N/A | AO94: #N/A | AP94: #N/A
A95: sink faucet kitchen | B95: 585104 | C95: 1.93 | D95: 0.081352 | F95: touch kitchen faucets with pull down sprayer | G95: 触摸带下拉喷头的厨房水龙头 | H95: 53.83% | I95: 高相关 | J95: 68.75% | K95: 43.75% | L95: 35.16% | M95: 33.2% | N95: 30.73% | O95: 424 | P95: 757686 | R95: 2.37 | S95: 0.081352 | T95: 0.52978102 | W95: kraus faucet | X95: 克劳斯龙头 | Y95: 893732 | AA95: 93 | AB95: gold faucet kitchen | AC95: 厨房金色水龙头 | AD95: 44.07% | AE95: 高相关 | AF95: 50% | AG95: 46.88% | AH95: 35.94% | AI95: 21.48% | AJ95: 15.36% | AK95: 222 | AL95: 1419130 | AN95: 2.76 | AO95: 0.056896 | AP95: 0.88215242
A96: kitchen faucets gold | B96: 601475 | C96: 1.02 | D96: 0.041988438 | F96: grifería para cocina | G96: 厨房用水龙头 | H96: 35.21% | I96: 中相关 | J96: 34.38% | K96: 40.63% | L96: 33.59% | M96: 28.91% | N96: 26.82% | O96: 424 | P96: 757686 | R96: 1.32 | S96: 0.081352 | T96: 0.29506791 | W96: waterfall kitchen faucet | X96: 瀑布厨房水龙头 | Y96: 893732 | AA96: 94 | AB96: grifos para fregaderos de cocina | AC96: 厨房水槽龙头 | AD96: 43.99% | AE96: 高相关 | AF96: 53.13% | AG96: 45.31% | AH96: 26.56% | AI96: 21.48% | AJ96: 20.31% | AK96: 1833 | AL96: 171725 | AN96: 2.62 | AO96: 0.035506 | AP96: 1.3418866
A97: white kitchen faucet | B97: 618802 | C97: 1.24 | D97: 0.048369187 | F97: kitchen sink faucet black | G97: 厨房水槽黑色水龙头 | H97: 29.87% | I97: 中相关 | J97: 21.88% | K97: 37.5% | L97: 39.84% | M97: 38.28% | N97: 29.95% | O97: 419 | P97: 766647 | R97: 3.8 | S97: 0.081352 | T97: 0.84943792 | W97: kitchen faucet brushed nickel | X97: 拉丝镍厨房水龙头 | Y97: 906155 | AA97: 95 | AB97: kitchen faucet gold | AC97: 金色厨房水龙头 | AD97: 43.91% | AE97: 高相关 | AF97: 43.75% | AG97: 56.25% | AH97: 39.06% | AI97: 22.66% | AJ97: 17.45% | AK97: 646 | AL97: 497869 | AN97: 1.02 | AO97: 0.040934696 | AP97: 0.45313216
A98: kohler kitchen faucets with pull down sprayer | B98: 618802 | C98: 5.65 | D98: 0.033103 | F98: kitchen water faucet | G98: 厨房水龙头 | H98: 59.77% | I98: 高相关 | J98: 71.88% | K98: 56.25% | L98: 42.19% | M98: 35.94% | N98: 30.99% | O98: 414 | P98: 775813 | R98: 2.94 | S98: 0.081352 | T98: 0.6571967 | W98: faucet for kitchen sink with sprayer | X98: 带喷头的厨房水槽龙头 | Y98: 919116 | AA98: 96 | AB98: kitchen faucet with soap dispenser | AC98: 带肥皂分配器的厨房水龙头 | AD98: 43.6% | AE98: 高相关 | AF98: 50% | AG98: 46.88% | AH98: 28.13% | AI98: 28.52% | AJ98: 22.14% | AK98: 1171 | AL98: 272532 | AN98: 2.81 | AO98: 0.081352 | AP98: 0.62813699
A99: faucet kitchen sink | B99: 630809 | C99: 3.7 | D99: 0.081352 | F99: kitchen faucet with water filter built in | G99: 内置水过滤器的厨房水龙头 | H99: 20.96% | I99: 中相关 | J99: 25% | K99: 23.44% | L99: 12.5% | M99: 6.64% | N99: 8.59% | O99: 414 | P99: 775813 | R99: 2.7 | S99: 0.0165 | T99: 2.9757477 | W99: delta essa pull down kitchen faucet | X99: 三角洲埃萨下拉式厨房水龙头 | Y99: 919116 | AA99: 97 | AB99: kitchen faucets with soap dispenser | AC99: 带肥皂分配器的厨房水龙头 | AD99: 43.53% | AE99: 高相关 | AF99: 50% | AG99: 48.44% | AH99: 28.91% | AI99: 20.31% | AJ99: 22.14% | AK99: 676 | AL99: 475276 | AN99: 1.93 | AO99: 0.095449 | AP99: 0.36770726
A100: kitchen sink filter water faucet | B100: 630809 | C100: 2.69 | D100: 0.04853 | F100: gold kitchen sink faucet | G100: 金色厨房水槽水龙头 | H100: 48% | I100: 高相关 | J100: 50% | K100: 54.69% | L100: 43.75% | M100: 30.47% | N100: 21.09% | O100: 409 | P100: 785288 | R100: 2.6 | S100: 0.04554301 | T100: 1.0381686 | W100: pull down faucet | X100: 下拉水龙头 | Y100: 919116 | AA100: 98 | AB100: faucet for kitchen sink with sprayer | AC100: 带喷头的厨房水槽龙头 | AD100: 43.4% | AE100: 高相关 | AF100: 53.13% | AG100: 35.94% | AH100: 29.69% | AI100: 34.77% | AJ100: 32.29% | AK100: 348 | AL100: 919116 | AN100: 2.05 | AO100: 0.100739 | AP100: 0.37006031
A101: touchless kitchen faucets | B101: 637148 | C101: 5.12 | D101: 0.080401 | F101: delta touch kitchen faucet | G101: 三角洲触摸厨房水龙头 | H101: 60.69% | I101: 高相关 | J101: 65.63% | K101: 67.19% | L101: 52.34% | M101: 35.16% | N101: 25.52% | O101: 404 | P101: 794989 | R101: 3.33 | S101: 0.039663257 | T101: 1.5267648 | W101: sink faucets | X101: 水槽水龙头 | Y101: 919116 | AA101: 99 | AB101: brushed bronze kitchen faucet | AC101: 拉丝青铜厨房水龙头 | AD101: 43.31% | AE101: 高相关 | AF101: 46.88% | AG101: 45.31% | AH101: 35.94% | AI101: 33.2% | AJ101: 27.6% | AK101: 404 | AL101: 794989 | AN101: 1.83 | AO101: 0.040185836 | AP101: 0.82812208
A102: faucet storage rack for kitchen sink | B102: 643548 | C102: 0.65 | D102: 0.096569 | F102: brushed bronze kitchen faucet | G102: 拉丝青铜厨房水龙头 | H102: 43.31% | I102: 高相关 | J102: 46.88% | K102: 45.31% | L102: 35.94% | M102: 33.2% | N102: 27.6% | O102: 404 | P102: 794989 | R102: 1.83 | S102: 0.040185836 | T102: 0.82812208 | W102: stainless steel faucet for kitchen sink | X102: 厨房水槽用不锈钢水龙头 | Y102: 919116 | AA102: 100 | AB102: kitchen sink faucet with soap dispenser | AC102: 带肥皂分配器的厨房水槽龙头 | AD102: 43.28% | AE102: 高相关 | AF102: 50% | AG102: 45.31% | AH102: 31.25% | AI102: 23.83% | AJ102: 19.79% | AK102: 479 | AL102: 670474 | AN102: 2.18 | AO102: 0.081352 | AP102: 0.48730912
A103: kitchen faucet sprayer attachment | B103: 643548 | C103: 0.71 | D103: 0.1019103 | F103: american standard kitchen faucet | G103: 美标厨房水龙头 | H103: 30.96% | I103: 中相关 | J103: 37.5% | K103: 23.44% | L103: 28.13% | M103: 22.66% | N103: 18.23% | O103: 393 | P103: 815053 | R103: 2.86 | S103: 0.117881 | T103: 0.44120305 | W103: kohler kitchen faucets | X103: 科勒 厨房水龙头 | Y103: 932345 | AA103: 101 | AB103: single handle kitchen faucet | AC103: 单柄厨房水龙头 | AD103: 42.39% | AE103: 高相关 | AF103: 46.88% | AG103: 45.31% | AH103: 32.81% | AI103: 27.73% | AJ103: 25.52% | AK103: 712 | AL103: 451647 | AN103: 2.66 | AO103: 0.09219 | AP103: 0.52470367
...

Sheet 肯否关键词
A1: 竞品数据来源ASIN | B1: 子体都挖出来 | C1: 关键词词库总表
A2: B0B82FK122,B01N4L0IGO,B084RNBLTD,B012I44KZG,B07RTZ2MRL,B0CN362S8M,B07CJRJ6Q7,B08KXPTL8C,B0BHQJFCKR,B012I44K8S | C2: 关键词词库总表 | D2: 肯定词库总表 | G2: 否定词库总表 | J2: 备注
A3: B082VWC75W,B0CV9TBR9B,B001U6I1Y0,B01H3OMH7Y,B09BBZ3X5S,B012I44QM8,B012I44KK6,B084R895Z5,B0CR1B43WR,B0064OW4WS | D3: 词组 | E3: 词根 | F3: 频率次数 | G3: 词组 | H3: 词根 | I3: 频率次数 | J3: 需添加词根
A4: B0BV2NVH1N,B06XWTWHFJ,B08JPWRSL3,B0CZDL6CN1,B087466GKM,B07KT2VF3H,B0CD25DR34,B0CPDHBCC6,B07Y4Y88Y6,B099M9CQ16 | C4: delta essa pull down kitchen faucet | D4: pulldown kitchen faucet | E4: pulldown | F4: 2 | G4: kitchen facet with sprayer | H4: dispenser | I4: 77
C5: delta kitchen faucets with pull down sprayer | D5: pulldown kitchen faucets | E5: faucet | F5: 241 | G5: brushed nickel kitchen faucet with sprayer | H5: soap | I5: 63
C6: delta faucet kitchen | D6: stainless steel kitchen faucet | E6: kitchen | F6: 152 | G6: kitchen faucet brushed nickel | H6: replacement | I6: 31
A7: 品牌 | C7: kitchen faucets delta | D7: faucet for kitchen | E7: sink | F7: 99 | G7: brushed nickel kitchen faucet | H7: wall | I7: 28
A8: Moen | C8: delta kitchen faucet | D8: pull down faucet | E8: filter | F8: 36 | G8: oil rubbed bronze kitchen faucet | H8: nickel | I8: 26
A9: Delta | C9: kitchen facet with sprayer | D9: pull-down sprayer kitchen faucets | E9: sprayer | F9: 34 | G9: kitchen faucet￼ | H9: 3 | I9: 26
A10: KOHLER | C10: delta kitchen faucets | D10: faucets for kitchen sinks with sprayer | E10: faucets | F10: 31 | G10: chrome kitchen sink faucet | H10: touchless | I10: 23
A11: Pfister | C11: delta touchless kitchen faucet | D11: kitchen faucet bronze | E11: water | F11: 30 | G11: kitchen fixtures | H11: toilet | I11: 22
A12: Kraus | C12: pulldown kitchen faucet | D12: faucet kitchen | E12: gold | F12: 28 | G12: top rated kitchen sink faucets | H12: can | I12: 21
A13: GROHE | C13: brushed nickel kitchen faucet with sprayer | D13: faucet kitchen sink | E13: pull | F13: 22 | G13: touch on kitchen sink faucets | H13: mount | I13: 20
A14: Kingston Brass | C14: pulldown kitchen faucets | D14: high arc kitchen faucet | E14: down | F14: 17 | G14: touch faucet kitchen | H14: trash | I14: 19
A15: FORIOUS | C15: stainless steel kitchen faucet | D15: faucet for kitchen sink | E15: matte | F15: 12 | G15: chrome kitchen faucet | H15: laundry | I15: 17
A16: OWOFAN | C16: faucet for kitchen | D16: kitchen water faucet | E16: commercial | F16: 12 | G16: grifo de cocina | H16: garbage | I16: 16
A17: Peerless | C17: pull down faucet | D17: kitchen faucets | E17: head | F17: 12 | G17: kitchen faucet touch | H17: attachment | I17: 15
A18: American Standard | C18: kitchen faucet brushed nickel | D18: sink faucet kitchen | E18: stainless | F18: 11 | G18: touch kitchen faucet | H18: touch | I18: 12
A19: hansgrohe | C19: pull-down sprayer kitchen faucets | D19: faucets | E19: single | F19: 11 | G19: touch kitchen faucets with pull down sprayer | H19: fregadero | I19: 12
A20: APPASO | C20: brushed nickel kitchen faucet | D20: kitchen faucet for sink | E20: bathroom | F20: 11 | G20: touch faucet for kitchen sink | H20: brass | I20: 12
A21: EZ-FLO | C21: oil rubbed bronze kitchen faucet | D21: kitchen faucets with pull down sprayer | E21: bronze | F21: 10 | G21: kitchen tap | H21: disposal | I21: 12
... A47: Apaix | C47: faucet | D47: gold kitchen sink faucet | E47: pull-down | F47: 1 | G47: kitchen faucet 3 hole | H47: hot | I47: 8
C48: touch faucet kitchen | D48: black faucet with sprayer | E48: arc | F48: 1 | G48: 3 hole kitchen faucet with sprayer | H48: drop | I48: 8
C49: faucets for kitchen | D49: matte black kitchen faucet with pull down sprayer | E49: pullout | F49: 1 | G49: brushed nickel | H49: thermostat | I49: 8
C50: chrome kitchen faucet | D50: kitchen sink faucet with sprayer | E50: arch | F50: 1 | G50: touchless kitchen faucets | H50: extension | I50: 8
C51: faucet for a sink | D51: kitchen sink faucet gold | E51: silver | F51: 1 | G51: touchless faucet for kitchen sink | H51: chrome | I51: 7
C52: pull down kitchen faucet | D52: stainless steel faucet for kitchen sink | E52: standard | F52: 1 | G52: kitchen faucet touchless | H52: fregaderos | I52: 7
C53: sink faucets | D53: water faucet | E53: cold | F53: 1 | G53: kitchen faucets for sink 3 hole | H53: champagne | I53: 7
C54: grifo de cocina | D54: matte black kitchen sink faucet | E54: hand | F54: 1 | G54: water tap | H54: accessories | I54: 7
C55: faucet for the sink | D55: gold faucet for kitchen sink | E55: filters | F55: 1 | G55: kitchen faucets touchless | H55: filtered | I55: 7
C56: kitchen faucet touch | D56: commercial high arch kitchen faucet | G56: touchless kitchen faucet | H56: small | I56: 7
C57: touch kitchen faucet | D57: gold faucet kitchen | G57: touchless kitchen faucet with pull down sprayer | H57: gap | I57: 7
C58: delta kitchen sink faucet | D58: kitchen faucet gold | G58: kitchen faucet with water filter built in | H58: parts | I58: 7
C59: faucets for sinks | D59: faucet for kitchen sink with sprayer | G59: rv kitchen faucet replacement | H59: automatic | I59: 7
C60: touch kitchen faucets with pull down sprayer | D60: brushed bronze kitchen faucet | G60: kitchen upgrades | H60: nozzle | I60: 7
C61: moen kitchen faucets with pull down sprayer | D61: single handle kitchen faucet | G61: 3 in 1 kitchen faucet | H61: aerator | I61: 7
C62: kitchen faucet with sprayer | D62: brushed gold kitchen faucet | G62: 3 way faucet | H62: grifo | I62: 6
C63: kitchen sink faucets | D63: kitchen faucets gold | G63: kitchen faucet oil rubbed bronze | H63: 2 | I63: 6
C64: stainless kitchen faucets | D64: gold sink faucet kitchen | G64: motion sensor kitchen faucet | H64: tub | I64: 6
C65: kitchen faucet with pull down sprayer | D65: matte black faucet kitchen | G65: high flow kitchen faucet 2.2 | H65: led | I65: 6
C66: kitchen sink faucet black matte modern | D66: kitchen faucets with sprayer | G66: waterfall kitchen faucet | H66: white | I66: 6
C67: single hole kitchen faucet | D67: faucet with sprayer | G67: 厨房水龙头 | H67: & | I67: 6
C68: touch faucet for kitchen sink | D68: black kitchen faucet | G68: 3 hole kitchen faucet | H68: under | I68: 6
C69: kitchen faucet black | D69: black matte kitchen faucet | G69: black kitchen | H69: handles | I69: 6
C70: kitchen tap | D70: gold kitchen faucet | G70: llave para fregadero | H70: squeegee | I70: 6
C71: kitchen sink faucets with pullout sprayer | D71: sink faucet with sprayer | G71: grifo de cocina acero inoxidable | H71: bowl | I71: 6
C72: kitchen pull down faucet | D72: matte black kitchen faucet | G72: llave de agua para cocina | H72: fixtures | I72: 5
C73: bronze kitchen faucet | D73: black kitchen faucet with pull down sprayer | G73: kitchen sink accessories | H73: lavaplatos | I73: 5
C74: black kitchen faucets | D74: modern kitchen faucet | G74: kitchen faucet soap dispenser | H74: upgrades | I74: 5
C75: touch faucet | D75: kitchen faucets black | G75: kitchen remodel | H75: waterfall | I75: 5
... C95: commercial high arch kitchen faucet | D95: faucet sprayer | G95: sink faucet with soap dispenser | H95: holes | I95: 4
C96: gold faucet kitchen | D96: kitchen faucet with water filter | G96: llave de fregadero | H96: 4 | I96: 4
C97: grifos para fregaderos de cocina | D97: outdoor kitchen faucet | G97: kitchen faucet replacement | H97: antique | I97: 4
C98: kitchen faucet gold | D98: faucets for kitchen sink | G98: kitchen faucet with pull down sprayer and soap dispenser | H98: house | I98: 4
C99: kitchen faucet with soap dispenser | D99: black and gold faucet kitchen | G99: touchless faucet | H99: items | I99: 4
C100: kitchen faucets with soap dispenser | D100: utility sink faucet with sprayer | G100: black kitchen faucet touchless | H100: lefton | I100: 4
C101: faucet for kitchen sink with sprayer | D101: gold faucet | G101: kitchen-faucets | H101: kitchens | I101: 4
C102: brushed bronze kitchen faucet | D102: faucet sink | G102: touchless kitchen sink faucets | H102: out | I102: 4
C103: kitchen sink faucet with soap dispenser | D103: kitchen faucet with pull down sprayer black | G103: kitchen deals | H103: portable | I103: 4
C104: single handle kitchen faucet | D104: commercial kitchen faucet with pull down sprayer | G104: 2 hole kitchen faucet | H104: clearance | I104: 4
C105: brushed gold kitchen faucet | D105: brushed gold faucet | G105: kitchen fauset | H105: cabinet | I105: 4
C106: llaves para fregaderos de cocina | D106: single kitchen faucet | G106: gold kitchen | H106: gallon | I106: 4
C107: kitchen faucets gold | D107: black sink faucet | G107: highest gpm kitchen faucet | H107: purifier | I107: 4
C108: gold sink faucet kitchen | D108: llave de cocina | G108: mezcladora de cocina fregadero | H108: farm | I108: 4
... C116: black matte kitchen faucet | D116: kitchen faucet pull down | G116: laundry room faucets for utility sink | H116: basura | I116: 4
C117: gold kitchen faucet with soap dispenser | D117: sink kitchen faucet | G117: facet | H117: 6 | I117: 4
C118: gold kitchen faucet | D118: bronze faucet kitchen | G118: champagne kitchen faucet | H118: vanity | I118: 4
C119: moen kitchen faucets | D119: faucet with pull down sprayer | G119: high pressure kitchen faucet | H119: electric | I119: 4
C120: champagne bronze kitchen faucet | D120: outdoor sink faucet | G120: faucet with soap dispenser | H120: griferia | I120: 3
C121: sink faucet with sprayer | D121: brushed gold faucet kitchen | G121: torneira para pia de cozinha | H121: flow | I121: 3
C122: is kitchen faucets | D122: farmhouse kitchen faucet | G122: kitch faucet | H122: gpm | I122: 3
C123: glacier bay kitchen faucet | D123: black faucet | G123: tall kitchen faucet | H123: low | I123: 3
C124: appaso bronze kitchen faucet | D124: gold kitchen faucet with pull down sprayer | G124: llave lavaplatos | H124: mobile | I124: 3
C125: kitchen faucets moen | D125: matte black faucet | G125: amazon kitchen faucets | H125: swivel | I125: 3
C126: matte black kitchen faucet | D126: llave para sink de cocina | G126: yaves de agua para cocina | H126: style | I126: 3
C127: black kitchen faucet with pull down sprayer | D127: llaves para cocina | G127: polished nickel kitchen faucet | H127: waterdrop | I127: 3
C128: appaso oil rubbed bronze kitchen faucet | D128: silver kitchen faucet | G128: mezcladora de fregadero | H128: pur | I128: 3
C129: modern kitchen faucet | D129: gold kitchen faucets | G129: kitchen faucets touch sensor | H129: mujer | I129: 3
C130: grifería para cocina | D130: kitchen faucet brushed gold | G130: brushed nickel faucet | H130: 13 | I130: 3
C131: brass kitchen faucet | D131: single faucet kitchen sink | G131: high flow kitchen faucet | H131: bottle | I131: 3
C132: kitchen faucets black | D132: single hole kitchen faucet with sprayer | G132: motion sensor faucet for kitchen sink | H132: brita | I132: 3
C133: black faucet kitchen | D133: brush gold kitchen faucet | G133: kitchen sink faucet 3 hole | H133: vessel | I133: 3
C134: griferia para cocina | D134: bar faucet | G134: champagne bronze faucet | H134: bars | I134: 3
C135: pull out kitchen faucet | D135: llaves para sink de cocina | G135: kitchen faucets 3 hole | H135: drain | I135: 3
C136: black kitchen faucet with soap dispenser | D136: kitchen faucet black matte | G136: 3 holes faucet for kitchen sink | H136: vigo | I136: 3
C137: moen faucet | D137: one handle kitchen faucet | G137: rv replacement faucet | H137: double | I137: 3
C138: champagne gold kitchen faucet | D138: gold and black kitchen faucet | G138: kitchen faucet with sprayer 3 hole | H138: extender | I138: 3
C139: black kitchen sink faucet | D139: sink faucet gold | G139: lavabos de cocina | H139: bridge | I139: 3
C140: matte black kitchen faucet with sprayer | D140: kitchen faucet with pull out sprayer | G140: pluma de fregadero de cocina | H140: fan | I140: 3
C141: wewe kitchen faucet | D141: one hole kitchen faucet | G141: laundry sink faucet with sprayer | H141: appliances | I141: 3
C142: brass faucet kitchen | D142: commercial sprayer faucet | G142: fregadero de cocina | H142: filtration | I142: 3
... C158: gold sink faucet | D158: rv sink faucet kitchen | G158: brass faucet | H158: built | I158: 2
C159: brushed nickel | D159: bar sink faucets | G159: kitchen faucet with filtered water dispenser | H159: 1 | I159: 2
C160: touchless kitchen faucets | D160: commercial kitchen faucet | G160: faucet for laundry sink | H160: way | I160: 2
C161: black kitchen faucet with sprayer | D161: camper rv faucet kitchen | G161: low arc kitchen faucet | H161: mezcladora | I161: 2
C162: kohler kitchen faucet | D162: modern kitchen | G162: laundry room sink faucet | H162: cozinha | I162: 2
C163: rv faucets kitchen | D163: utility sink faucet | G163: small sink faucet | H163: amazon | I163: 2
C164: black sink faucet kitchen | D164: bar sink faucet single hole | G164: cocina | H164: polished | I164: 2
C165: touchless faucet for kitchen sink | D165: camper sink faucet | G165: griferia lavamanos | H165: pluma | I165: 2
C166: rv kitchen sink faucet | D166: bar faucets single hole | G166: kitchen faucet low | H166: reach | I166: 2
...

Sheet 2
A1: amazon-order-id | B1: merchant-order-id | C1: purchase-date | D1: last-updated-date | E1: order-status | F1: fulfillment-channel | G1: sales-channel | H1: order-channel | I1: url | J1: ship-service-level | K1: product-name | L1: sku | M1: asin | N1: item-status | O1: quantity | P1: currency | Q1: item-price | R1: item-tax | S1: shipping-price | T1: shipping-tax | U1: gift-wrap-price | V1: gift-wrap-tax | W1: item-promotion-discount | X1: ship-promotion-discount | Y1: ship-city | Z1: ship-state | AA1: ship-postal-code | AB1: ship-country | AC1: promotion-ids | AD1: is-business-order | AE1: purchase-order-number | AF1: price-designation | AG1: default-ship-from-address-name | AH1: default-ship-from-address-field-1 | AI1: default-ship-from-address-field-2 | AJ1: default-ship-from-address-field-3 | AK1: default-ship-from-city | AL1: default-ship-from-state | AM1: default-ship-from-country | AN1: default-ship-from-postal-code | AO1: actual-ship-from-address-name | AP1: actual-ship-from-address-field-1 | AQ1: actual-ship-from-address-field-2 | AR1: actual-ship-from-address-field-3 | AS1: actual-ship-from-city | AT1: actual-ship-from-state | AU1: actual-ship-from-country | AV1: actual-ship-from-postal-code | AW1: is-buyer-requested-cancellation | AX1: buyer-requested-cancel-reason | AY1: serial-numbers | AZ1: signature-confirmation-recommended
A2: 111-9858618-2103444 | B2: 111-9858618-2103444 | C2: 2023-09-12T05:37:43+00:00 | D2: 2023-09-12T05:37:48+00:00 | E2: Pending | F2: Amazon | G2: Amazon.com | J2: Expedited | K2: Dash Cam Front with FHD 1080p, Wanlipo 2 Inch LCD Dashcam, Dashboard Camera for Cars with 24h Parking Monitor, G-Sensor, Loop Recording, Free 32GB SD | L2: J09-C1 | M2: B0BG6WPM3W | N2: Unshipped | O2: 1 | P2: USD | Q2: 79.99 | Y2: BELLMAWR | Z2: NJ | AA2: 08031-2115 | AB2: US | AC2: MPC-S Percentage Off 2023/09/10 11-52-12-900 | AD2: FALSE | AW2: FALSE | AZ2: FALSE
A3: 114-5667916-6324215 | B3: 114-5667916-6324215 | C3: 2023-09-12T03:37:05+00:00 | D3: 2023-09-12T09:02:46+00:00 | E3: Shipped | F3: Amazon | G3: Amazon.com | J3: Expedited | K3: 4K Dash Cam Front Built-in WiFi, WANLIPO Dash Camera for Cars with 64GB SD Card, Car Camera with 3" IPS Screen, 2160P Dashcam for Cars with App Contro | L3: Wanlipo M03-3 | M3: B0CC8CHTTJ | N3: Shipped | O3: 1 | P3: USD | Q3: 99.99 | R3: 1.89 | W3: 72.99 | Y3: MONROE | Z3: GA | AA3: 30656-4723 | AB3: US | AC3: MPC-S Percentage Off 2023/09/11 9-53-46-600 | AD3: FALSE | AW3: FALSE | AZ3: FALSE
A4: 111-1595396-9168227 | B4: 111-1595396-9168227 | C4: 2023-09-11T23:55:05+00:00 | D4: 2023-09-11T23:55:11+00:00 | E4: Pending | F4: Amazon | G4: Amazon.com | J4: Expedited | K4: Dash Cam Front with FHD 1080p, Wanlipo 2 Inch LCD Dashcam, Dashboard Camera for Cars with 24h Parking Monitor, G-Sensor, Loop Recording, Free 32GB SD | L4: J09-C1 | M4: B0BG6WPM3W | N4: Unshipped | O4: 1 | P4: USD | Q4: 79.99 | Y4: SILVER SPRING | Z4: MD | AA4: 20906-4527 | AB4: US | AC4: MPC-S Percentage Off 2023/09/10 11-52-3-698 | AD4: FALSE | AW4: FALSE | AZ4: FALSE
A5: 112-7810040-2837843 | B5: 112-7810040-2837843 | C5: 2023-09-11T19:41:13+00:00 | D5: 2023-09-12T01:35:23+00:00 | E5: Shipped | F5: Amazon | G5: Amazon.com | J5: Expedited | K5: Dash Cam Front with FHD 1080p, Wanlipo 2 Inch LCD Dashcam, Dashboard Camera for Cars with 24h Parking Monitor, G-Sensor, Loop Recording, Free 32GB SD | L5: J09-C1 | M5: B0BG6WPM3W | N5: Shipped | O5: 1 | P5: USD | Q5: 79.99 | R5: 1.85 | W5: 59.99 | Y5: Nashville | Z5: TN | AA5: 37208-1058 | AB5: US | AC5: MPC-S Percentage Off 2023/09/10 11-52-13-889 | AD5: FALSE | AW5: FALSE | AZ5: FALSE
