Workbook

Sheet 1.主要运营数据目标
A1: 月份 | B1: 定价（$） | C1: 站内活动 | E1: 站外活动 | G1: 广告计划 | H1: Goal
A2: 月份 | B2: 定价（$） | C2: 活动销量 | D2: 折扣金额 | E2: 活动销量 | F2: 折扣金额 | G2: 广告销量（周） | H2: rank | I2: 日均总销量 | J2: 本周GMV | K2: 累计总GMV | L2: 毛利 | M2: 毛利率
A3: 8月W3 | B3: 49.99 | C3: =VLOOKUP(A:A,'5.投入产出分析'!A:E,5,0) -> 0 | D3: 0.15 | E3: 14 | F3: 0.3 | G3: =VLOOKUP(A:A,'5.投入产出分析'!A:K,11,0) -> 7 | H3: =VLOOKUP(A:A,'5.投入产出分析'!A:R,18,0) -> #1000 | I3: 2 | J3: =B3*I3*7 -> 699.86 | K3: =J3 -> 699.86 | L3: =VLOOKUP(A:A,'5.投入产出分析'!A:V,22,0) -> -98.286543 | M3: =VLOOKUP(A:A,'5.投入产出分析'!A:W,23,0) -> -0.14043743
A4: 8月W4 | B4: 49.99 | C4: =VLOOKUP(A:A,'5.投入产出分析'!A:E,5,0) -> 0 | D4: 0.15 | E4: 14 | F4: 0.3 | G4: =VLOOKUP(A:A,'5.投入产出分析'!A:K,11,0) -> 9 | H4: =VLOOKUP(A:A,'5.投入产出分析'!A:R,18,0) -> #800 | I4: 2 | J4: =B4*I4*7 -> 699.86 | K4: =K3+J4 -> 1399.72 | L4: =VLOOKUP(A:A,'5.投入产出分析'!A:V,22,0) -> -159.61988 | M4: =VLOOKUP(A:A,'5.投入产出分析'!A:W,23,0) -> -0.22807401
A5: 9月W1 | B5: 49.99 | C5: =VLOOKUP(A:A,'5.投入产出分析'!A:E,5,0) -> 0 | D5: 0.15 | E5: 14 | F5: 0.3 | G5: =VLOOKUP(A:A,'5.投入产出分析'!A:K,11,0) -> 15 | H5: =VLOOKUP(A:A,'5.投入产出分析'!A:R,18,0) -> #700 | I5: 3 | J5: =B5*I5*7 -> 1049.79 | K5: =K4+J5 -> 2449.51 | L5: =VLOOKUP(A:A,'5.投入产出分析'!A:V,22,0) -> -285.42981 | M5: =VLOOKUP(A:A,'5.投入产出分析'!A:W,23,0) -> -0.2718923
A6: 9月W2 | B6: 49.99 | C6: =VLOOKUP(A:A,'5.投入产出分析'!A:E,5,0) -> 0 | D6: 0.15 | E6: 14 | F6: 0.3 | G6: =VLOOKUP(A:A,'5.投入产出分析'!A:K,11,0) -> 16 | H6: =VLOOKUP(A:A,'5.投入产出分析'!A:R,18,0) -> #600 | I6: 4 | J6: =B6*I6*7 -> 1399.72 | K6: =K5+J6 -> 3849.23 | L6: =VLOOKUP(A:A,'5.投入产出分析'!A:V,22,0) -> -98.70706 | M6: =VLOOKUP(A:A,'5.投入产出分析'!A:W,23,0) -> -0.070519147
A7: 9月W3 | B7: 49.99 | C7: =VLOOKUP(A:A,'5.投入产出分析'!A:E,5,0) -> 15 | D7: 0.15 | E7: 14 | F7: 0.3 | G7: =VLOOKUP(A:A,'5.投入产出分析'!A:K,11,0) -> 21 | H7: =VLOOKUP(A:A,'5.投入产出分析'!A:R,18,0) -> #500 | I7: 5 | J7: =B7*I7*7 -> 1749.65 | K7: =K6+J7 -> 5598.88 | L7: =VLOOKUP(A:A,'5.投入产出分析'!A:V,22,0) -> 70.423408 | M7: =VLOOKUP(A:A,'5.投入产出分析'!A:W,23,0) -> 0.040249998
A8: 9月W4 | B8: 49.99 | C8: =VLOOKUP(A:A,'5.投入产出分析'!A:E,5,0) -> 0 | D8: 0.15 | E8: 14 | F8: 0.3 | G8: =VLOOKUP(A:A,'5.投入产出分析'!A:K,11,0) -> 25 | H8: =VLOOKUP(A:A,'5.投入产出分析'!A:R,18,0) -> #450 | I8: 5 | J8: =B8*I8*7 -> 1749.65 | K8: =K7+J8 -> 7348.53 | L8: =VLOOKUP(A:A,'5.投入产出分析'!A:V,22,0) -> -89.940182 | M8: =VLOOKUP(A:A,'5.投入产出分析'!A:W,23,0) -> -0.051404671
A9: 10月W1 | B9: 49.99 | C9: =VLOOKUP(A:A,'5.投入产出分析'!A:E,5,0) -> 20 | D9: 0.15 | E9: 14 | F9: 0.3 | G9: =VLOOKUP(A:A,'5.投入产出分析'!A:K,11,0) -> 25 | H9: =VLOOKUP(A:A,'5.投入产出分析'!A:R,18,0) -> #350 | I9: 6 | J9: =B9*I9*7 -> 2099.58 | K9: =K8+J9 -> 9448.11 | L9: =VLOOKUP(A:A,'5.投入产出分析'!A:V,22,0) -> 75.238478 | M9: =VLOOKUP(A:A,'5.投入产出分析'!A:W,23,0) -> 0.035835014
A10: 10月W2 | B10: 49.99 | C10: =VLOOKUP(A:A,'5.投入产出分析'!A:E,5,0) -> 0 | D10: 0.15 | E10: 14 | F10: 0.3 | G10: =VLOOKUP(A:A,'5.投入产出分析'!A:K,11,0) -> 25 | H10: =VLOOKUP(A:A,'5.投入产出分析'!A:R,18,0) -> #300 | I10: 6 | J10: =B10*I10*7 -> 2099.58 | K10: =K9+J10 -> 11547.69 | L10: =VLOOKUP(A:A,'5.投入产出分析'!A:V,22,0) -> 8.435841 | M10: =VLOOKUP(A:A,'5.投入产出分析'!A:W,23,0) -> 0.0040178707
A11: 10月W3 | B11: 49.99 | C11: =VLOOKUP(A:A,'5.投入产出分析'!A:E,5,0) -> 0 | D11: 0.15 | E11: 14 | F11: 0.3 | G11: =VLOOKUP(A:A,'5.投入产出分析'!A:K,11,0) -> 28 | H11: =VLOOKUP(A:A,'5.投入产出分析'!A:R,18,0) -> #250 | I11: 7 | J11: =B11*I11*7 -> 2449.51 | K11: =K10+J11 -> 13997.2 | L11: =VLOOKUP(A:A,'5.投入产出分析'!A:V,22,0) -> 139.92707 | M11: =VLOOKUP(A:A,'5.投入产出分析'!A:W,23,0) -> 0.057124513
A12: 10月W4 | B12: 49.99 | C12: =VLOOKUP(A:A,'5.投入产出分析'!A:E,5,0) -> 0 | D12: 0.15 | E12: 14 | F12: 0.3 | G12: =VLOOKUP(A:A,'5.投入产出分析'!A:K,11,0) -> 28 | H12: =VLOOKUP(A:A,'5.投入产出分析'!A:R,18,0) -> #200 | I12: 8 | J12: =B12*I12*7 -> 2799.44 | K12: =K11+J12 -> 16796.64 | L12: =VLOOKUP(A:A,'5.投入产出分析'!A:V,22,0) -> 225.51665 | M12: =VLOOKUP(A:A,'5.投入产出分析'!A:W,23,0) -> 0.080557772
A13: 11月W1 | B13: 49.99 | C13: =VLOOKUP(A:A,'5.投入产出分析'!A:E,5,0) -> 0 | D13: 0.15 | E13: 14 | F13: 0.3 | G13: =VLOOKUP(A:A,'5.投入产出分析'!A:K,11,0) -> 30 | H13: =VLOOKUP(A:A,'5.投入产出分析'!A:R,18,0) -> #150 | I13: 10 | J13: =B13*I13*7 -> 3499.3 | K13: =K12+J13 -> 20295.94 | L13: =VLOOKUP(A:A,'5.投入产出分析'!A:V,22,0) -> 363.89581 | M13: =VLOOKUP(A:A,'5.投入产出分析'!A:W,23,0) -> 0.10399103
A14: 11月W2 | B14: 49.99 | C14: =VLOOKUP(A:A,'5.投入产出分析'!A:E,5,0) -> 0 | D14: 0.15 | E14: 14 | F14: 0.3 | G14: =VLOOKUP(A:A,'5.投入产出分析'!A:K,11,0) -> 35 | H14: =VLOOKUP(A:A,'5.投入产出分析'!A:R,18,0) -> #130 | I14: 12 | J14: =B14*I14*7 -> 4199.16 | K14: =K13+J14 -> 24495.1 | L14: =VLOOKUP(A:A,'5.投入产出分析'!A:V,22,0) -> 453.07497 | M14: =VLOOKUP(A:A,'5.投入产出分析'!A:W,23,0) -> 0.10789657

Sheet 2.目标定位&推广思路
A1: 8月 | C1: 9月 | E1: 10月
A2: 目标日销 | B2: 目标排名 | C2: 目标日销 | D2: 目标排名 | E2: 目标日销 | F2: 目标排名
A3: 3 | B3: #600 | C3: 6 | D3: #300 | E3: 10 | F3: #150
A6: 运营推广思路——第一阶段
A7: 第一阶段 8月W3-9月W2 | B7: 目标售价 | C7: 49.99
B8: 目标日销 | C8: 3
B9: 对标竞品 | D9: 以B0XXXXX为竞争目标 竞品情况：预估日销8-10，排名#260-#150，售价 主要卖点： 我们产品： 主要卖点：
B10: 广告销量占比 | C10: 0.6 | D10: 每天广告总费用（45）： 1. 手动系列：预算25，投放方式多种配合， 1）主投精准流量中词，30%的Coupon显示在Listing页面提升这些词的转化率， 2）广泛匹配投大词和中词 3）利用产品和折扣优势定投在其他竞品上 2.自动广告预算20跑关联流量
B11: 目标流量 | C11: 广告流量：50 自然流量：35 | D11: 1.中等核心词目标流量（广告）：目标位置P4 2.中等核心词目标流量（自然）：目标位置P5 3.流量大词目标流量（广告）：目标位置：P4 4.流量大词目标流量（自然）：目标位置：P5 5.竞品asin关联位置引流 6. coupon &站外引流
B12: 目标转化率 | C12: listing转化率：4% 广告转化率：3% | D12: 1.多张主图测试 2.多次调整上架图顺序测试 3.逐步优化五点和埋词以及页面其他信息 4.拍摄开箱视频&买家秀
B13: 目标评分/数量 | C13: 4.4/6 | D13: 1.测评8个 2.自然留评（留评率3%） 3.优惠卡索评 4.Top reviewer 邀评
A14: 运营推广思路——第二阶段
A15: 第二阶段 9月W3-10月W2 | B15: 目标售价 | C15: 49.99
B16: 目标日销 | C16: 6
B17: 对标竞品 | D17: XXXXXXXXXXXXXXXXXXXXXXXXXX
B18: 广告销量占比 | C18: 0.5 | D18: 每天广告总费用（65）： 1. 手动系列：预算40，投放方式多种配合， 1）主投精准流量中词，另外一组投精准的长尾词，20%的Coupon显示在Listing页面提升这些词的转化率， 2）广泛匹配投大词和中词， 3）利用产品和折扣优势定投在其他竞品上 2.自动广告预算20 跑关联流量 3.SB 15/天 （作为组合型广告，从此链接中抽出$5/天的预算）
B19: 目标流量 | C19: 广告流量：75 自然流量：75 站外引流：20 | D19: 1.中等核心词目标流量（广告）：目标位置P3 2.中等核心词目标流量（自然）：目标位置P4 3.流量大词目标流量（广告）：目标位置：P3 4.流量大词目标流量（广告）：目标位置：P4 5.竞品asin关联位置引流 6. coupon &站外视频网站 & 站外deal网站 引流
B20: 目标转化率 | C20: listing转化率：4% 广告转化率：4% | D20: 1.多张主图测试 2.多次调整上架图顺序测试 3.逐步优化五点和埋词以及A+页面其他信息 4.优化QA布局
B21: 目标评分/数量 | C21: 4.2/18 | D21: 1.测评3-5单 2.自然留评 3.优惠卡索评 4.Top reviewer 邀评
A22: ——第三阶段
A23: 第三阶段 10月W3-11月W2 | B23: 目标售价 | C23: 49.99
B24: 目标日销 | C24: 10
B25: 对标竞品
B26: 广告销量占比 | C26: 0.35 | D26: 每天广告总费用（85）： 1. 手动系列：预算110，投放方式多种配合， 1）主投精准流量大词，另外一组投精准的长尾词，15%-20%的coupon显示在Listing页面提升这些词的转化率， 2）广泛匹配投大词和中词， 3）利用产品和价格优势定投在其他竞品上 2.自动广告预算90跑关联流量 3.SB广告和视频广告
B27: 目标流量 | C27: 广告流量：100 自然流量：120 站外引流：30 | D27: 1.中等核心词目标流量（广告）：目标位置P2 2.中等核心词目标流量（自然）：目标位置P2 3.流量大词目标流量（广告）：目标位置：P2 4.流量大词目标流量（自然）：目标位置：P3 5.竞品asin关联位置引流 6. coupon &站外折扣网站 & 站外deal网站 引流
B28: 目标转化率 | C28: listing转化率：5% 广告转化率：4% | D28: 1.多张主图测试 2.多次调整上架图顺序测试 3.做A+的AB方式，测试效果 4.优化QA布局
B29: 目标评分/数量 | C29: 4.0/42 | D29: 1.测评2-3单 2.自然留评 3.优惠卡索评 4.Top reviewer 邀评

Sheet 3.推广计划细化
A1: Date | B1: REVIEW计划 | C1: 定价 | D1: 推广计划 | E1: 目标日销 | F1: 广告计划（运营&广告） | J1: 小类排名
F2: 日预算 | G2: 流量 | H2: CVR | I2: 订单
A3: 8月W3 | B3: 1、测评 2、优惠卡索评 3、自然留评 4、Top reviewer 邀评 | C3: 49.99 | D3: 1、链接：完善listing内容 2、优惠券：30%coupon挂上 3、QA: 上4组基本操作的QA部分 4、视频部分：做一个安装和首次连接视频，放到QA上 5、测评：做3个测评单 6、广告：开自动广告，跑关联；开一组手动关键词，低预算，养关键词 | E3: 2 | F3: =G3*0.9 -> 36 | G3: =I3/H3 -> 40 | H3: 0.03 | I3: =E3*0.6 -> 1.2 | J3: #1000
A4: 8月W4 | B4: 1、测评 2、优惠卡索评 3、自然留评 4、Top reviewer 邀评 | C4: 49.99 | D4: 1、QA: 做6组QA上去 2、测评：做3个测评单 3、优惠券：做$15的coupon挂上； 4、广告：自动广告开启关键词和关联两组；手动广告开启核心关键词精准+广泛 5、站外：联系YouTube网红，做视频宣传 6、投放post模块，一周上3个post引流、 | E4: 2 | F4: =G4*0.9 -> 36 | G4: =I4/H4 -> 40 | H4: 0.03 | I4: =E4*0.6 -> 1.2 | J4: #800
A5: 9月W1 | B5: 1、测评 2、优惠卡索评 3、自然留评 4、Top reviewer 邀评 | C5: 49.99 | D5: 1、listing：调整橱窗图和A+的组合，测试出单效果 2、广告：广告逐步放量，主投SP广告的手动关键词，配合PA定投，重点提升精准中等词的自然排名；同时自动广告的预算慢慢加大，多跑关联 3、优惠券：根据前两周的结果，看哪一个方式的转化好，选择30% coupon或者$15 coupon 4、QA方面：准备8组QA，结合回评信息，逐步放上去 5、视频方面：联系YouTube主播，做相关视频，同时准备好关联视频 6、测评：结合实际情况，放1-2个测评单 7、post：一周上3-4个post | E5: 3 | F5: =G5*0.9 -> 54 | G5: =I5/H5 -> 60 | H5: 0.03 | I5: =E5*0.6 -> 1.8 | J5: #700
A6: 9月W2 | B6: 1、测评 2、优惠卡索评 3、自然留评 4、Top reviewer 邀评 | C6: 49.99 | D6: 1、广告：多种广告方式结合进行放量，主投SP广告手动，同时开始投放SB，加大流量入口； 2、listing：提交主图需求，测试不同主图的点击率； 3、优惠券：25% coupon，看出单情况； 4、活动：看后台有没有deal推荐，有的话就直接报，或者找服务商报活动 5、库存：关注实时库存情况，及时备货以确保之后的运营能够顺利进行 6、QA部分：上8组QA，保持链接的活跃度 7、测评：之前的测评单应该能够上一般的评论了，结合实际情况做1-2单测评单 | E6: 4 | F6: =G6*0.9 -> 45 | G6: =I6/H6 -> 50 | H6: 0.04 | I6: =E6*0.5 -> 2 | J6: #600
A7: 9月W3 | B7: 1、测评 2、优惠卡索评 3、自然留评 4、Top reviewer 邀评 | C7: 49.99 | D7: 1、listing：优化listing，特别是在五点与产品描述部分突出产品与竞品的差异化 2、广告：广告重点关注投放PA定投与SD定投等广告形式，形成与竞品的关联，打下关联位 3、优惠券：看能否跑LD活动，能跑活动就跑活动 4、站外：每日联系YouTube网红，争取获得更多的优质网红资源，同时根据实际情况，做站外促销，冲刺排名 | E7: 5 | F7: =G7*0.85 -> 53.125 | G7: =I7/H7 -> 62.5 | H7: 0.04 | I7: =E7*0.5 -> 2.5 | J7: #500
A8: 9月W4 | B8: 1、测评 2、优惠卡索评 3、自然留评 4、Top reviewer 邀评 | C8: 49.99 | D8: 1、广告：冲第1级和第2级关键词，结合站内站外活动连续刺激，目标一周内核心关键词到前3页； 2、优惠券：活动后设置大额coupon（20%左右）进行维稳， 3、每日监控listing数据表现，根据情况及时进行放量、优化等操作 | E8: 5 | F8: =G8*0.85 -> 53.125 | G8: =I8/H8 -> 62.5 | H8: 0.04 | I8: =E8*0.5 -> 2.5 | J8: #450
A9: 10月W1 | B9: 1、测评 2、优惠卡索评 3、自然留评 4、Top reviewer 邀评 | C9: 49.99 | D9: 跑BD，优化广告，稳关键词排名，关注自身流量转化率数据和跟进竞争对手随时采取有效措施 | E9: 6 | F9: =G9*0.85 -> 63.75 | G9: =I9/H9 -> 75 | H9: 0.04 | I9: =E9*0.5 -> 3 | J9: #350
A10: 10月W2 | B10: 1、测评 2、优惠卡索评 3、自然留评 4、Top reviewer 邀评 | C10: 49.99 | D10: 优化广告，稳关键词排名，关注自身流量转化率数据和跟进竞争对手随时采取有效措施 | E10: 6 | F10: =G10*0.85 -> 63.75 | G10: =I10/H10 -> 75 | H10: 0.04 | I10: =E10*0.5 -> 3 | J10: #300
A11: 10月W3 | B11: 1、测评 2、优惠卡索评 3、自然留评 4、Top reviewer 邀评 | C11: 49.99 | D11: 每周跑LD，定期优化广告和listing，稳关键词排名，关注自身流量转化率数据和跟进竞争对手随时采取有效措施 | E11: 7 | F11: =G11*0.83 -> 72.625 | G11: =I11/H11 -> 87.5 | H11: 0.04 | I11: =E11*0.5 -> 3.5 | J11: #250
A12: 10月W4 | B12: 1、测评 2、优惠卡索评 3、自然留评 4、Top reviewer 邀评 | C12: 49.99 | D12: 定期优化广告和listing，稳关键词排名，关注自身流量转化率数据和跟进竞争对手随时采取有效措施 | E12: 8 | F12: =G12*0.82 -> 65.6 | G12: =I12/H12 -> 80 | H12: 0.04 | I12: =E12*0.4 -> 3.2 | J12: #200
A13: 11月W1 | B13: 1、测评 2、优惠卡索评 3、自然留评 4、Top reviewer 邀评 | C13: 49.99 | D13: 每周跑LD，定期优化广告和listing，稳关键词排名，关注自身流量转化率数据和跟进竞争对手随时采取有效措施 | E13: 10 | F13: =G13*0.82 -> 82 | G13: =I13/H13 -> 100 | H13: 0.04 | I13: =E13*0.4 -> 4 | J13: #150
A14: 11月W2 | B14: 1、测评 2、优惠卡索评 3、自然留评 4、Top reviewer 邀评 | C14: 49.99 | D14: 定期优化广告和listing，稳关键词排名，关注自身流量转化率数据和跟进竞争对手随时采取有效措施 | E14: 12 | F14: =G14*0.82 -> 98.4 | G14: =I14/H14 -> 120 | H14: 0.04 | I14: =E14*0.4 -> 4.8 | J14: #130

Sheet 4.库存安排和跟进
A1: 发货记录
A2: 物流方式 | B2: 海运 | C2: 海运 | D2: 海运 | E2: 海运
A3: 店铺
A4: 发货时间
A5: 到货时间
A6: 发货库存
A9: Tronsmart Bang 库存计划
A10: 时间 | B10: 8月下 | C10: 9月上 | D10: 9月下 | E10: 10月上 | F10: 10月下 | G10: 11月上
A11: 预估日销 | B11: 2 | C11: 4 | D11: 5 | E11: 6 | F11: 8 | G11: 10
A12: 需要库存 | B12: =B11*15 -> 30 | C12: =C11*15 -> 60 | D12: =D11*15 -> 75 | E12: =E11*15 -> 90 | F12: =F11*15 -> 120 | G12: =G11*15 -> 150
A13: 现有库存
A14: 预计到货
A15: 剩余
A16: 可售天数
A17: 新订单预计发货时间
A18: 新订单预计发货数量
A19: 物流方式 | B19: 海运 | C19: 海运 | D19: 海运 | E19: 海运 | F19: 海运 | G19: 海运 | H19: 海运 | I19: 海运 | J19: 海运 | K19: 海运 | L19: 海运 | M19: 海运 | N19: 海运 | O19: 海运 | P19: 海运 | Q19: 海运
A20: 预计下单时间
A21: 预计下单数量
A22: 预计提货时间
A23: 预计提货数量
A25: 说明： | B25: 1、海运有效时效为30天左右
B26: 2、根据实际销售情况对备货、发货数据进行调整

Sheet 5.投入产出分析
A1: 月份 | B1: 定价（$） | C1: coupon额度 | D1: coupon预算 | E1: 站内活动 | H1: 站外活动 | K1: 广告计划 | N1: 固定成本（$） | Q1: FBA佣金 | R1: Goal | X1: 备货回款时间 | AB1: 退货
E2: 活动数量 | F2: 折扣金额 | G2: LD/7DD预算 | H2: 活动数量 | I2: 折扣金额 | J2: 预算 | K2: 广告销量（周） | L2: 预算 | M2: 花费占比 | N2: 产品成本 | O2: 头程物流 | P2: FBA fee | R2: rank | S2: 非活动单 | T2: 平均日销 | U2: GMV | V2: 毛利（$） | W2: 毛利率 | X2: 备货时间 | Y2: 回款时间 | Z2: 回款
A3: 8月W3 | B3: 49.99 | C3: 0.3 | D3: =B3*C3*S3*0.6*7 -> 125.9748 | E3: 0 | F3: 0.15 | G3: =E3*F3*B3 -> 0 | H3: 0 | I3: 0.3 | J3: =H3*I3*B3 -> 0 | K3: 7 | L3: =K3/0.03*0.92 -> 214.66667 | M3: =L3/U3 -> 0.30672801 | N3: 19.99 | O3: 1.28 | P3: 6.08 | Q3: =(U3-D3-G3-J3)*0.08 -> 45.910816 | R3: =VLOOKUP(A:A,'3.推广计划细化'!A:J,10,0) -> #1000 | S3: =(T3*7-H3)/7 -> 2 | T3: =VLOOKUP(A:A,'3.推广计划细化'!A:E,5,0) -> 2 | U3: =T3*7*B3 -> 699.86 | V3: =(B3-N3-O3-P3)*T3*7-D3-G3-J3-L3-Q3-AB3 -> -98.286543 | W3: =V3/U3 -> -0.14043743 | Z3: =V3+(N3+O3)*7*T3 -> 199.49346 | AB3: =(B3*T3*7-J3-G3-D3)*0.05 -> 28.69426
A4: 8月W4 | B4: 49.99 | C4: 0.3 | D4: =B4*C4*S4*0.6*7 -> 125.9748 | E4: 0 | F4: 0.15 | G4: =E4*F4*B4 -> 0 | H4: 0 | I4: 0.3 | J4: =H4*I4*B4 -> 0 | K4: 9 | L4: =K4/0.03*0.92 -> 276 | M4: =L4/U4 -> 0.39436459 | N4: 19.99 | O4: 1.28 | P4: 6.08 | Q4: =(U4-D4-G4-J4)*0.08 -> 45.910816 | R4: =VLOOKUP(A:A,'3.推广计划细化'!A:J,10,0) -> #800 | S4: =(T4*7-H4)/7 -> 2 | T4: =VLOOKUP(A:A,'3.推广计划细化'!A:E,5,0) -> 2 | U4: =T4*7*B4 -> 699.86 | V4: =(B4-N4-O4-P4)*T4*7-D4-G4-J4-L4-Q4-AB4 -> -159.61988 | W4: =V4/U4 -> -0.22807401 | Z4: =V4+(N4+O4)*7*T4 -> 138.16012 | AB4: =(B4*T4*7-J4-G4-D4)*0.05 -> 28.69426
A5: 9月W1 | B5: 49.99 | C5: 0.3 | D5: =B5*C5*S5*0.6*7 -> 188.9622 | E5: 0 | F5: 0.15 | G5: =E5*F5*B5 -> 0 | H5: 0 | I5: 0.3 | J5: =H5*I5*B5 -> 0 | K5: 15 | L5: =K5/0.03*0.92 -> 460 | M5: =L5/U5 -> 0.43818287 | N5: 19.99 | O5: 1.28 | P5: 6.08 | Q5: =(U5-D5-G5-J5)*0.08 -> 68.866224 | R5: =VLOOKUP(A:A,'3.推广计划细化'!A:J,10,0) -> #700 | S5: =(T5*7-H5)/7 -> 3 | T5: =VLOOKUP(A:A,'3.推广计划细化'!A:E,5,0) -> 3 | U5: =T5*7*B5 -> 1049.79 | V5: =(B5-N5-O5-P5)*T5*7-D5-G5-J5-L5-Q5-AB5 -> -285.42981 | W5: =V5/U5 -> -0.2718923 | Z5: =V5+(N5+O5)*7*T5 -> 161.24019 | AB5: =(B5*T5*7-J5-G5-D5)*0.05 -> 43.04139
A6: 9月W2 | B6: 49.99 | C6: 0.25 | D6: =B6*C6*S6*0.6*7 -> 209.958 | E6: 0 | F6: 0.15 | G6: =E6*F6*B6 -> 0 | H6: 0 | I6: 0.3 | J6: =H6*I6*B6 -> 0 | K6: 16 | L6: =K6/0.04*0.92 -> 368 | M6: =L6/U6 -> 0.26290972 | N6: 19.99 | O6: 1.28 | P6: 6.08 | Q6: =(U6-D6-G6-J6)*0.08 -> 95.18096 | R6: =VLOOKUP(A:A,'3.推广计划细化'!A:J,10,0) -> #600 | S6: =(T6*7-E6-H6)/7 -> 4 | T6: =VLOOKUP(A:A,'3.推广计划细化'!A:E,5,0) -> 4 | U6: =T6*7*B6 -> 1399.72 | V6: =(B6-N6-O6-P6)*T6*7-D6-G6-J6-L6-Q6-AB6 -> -98.70706 | W6: =V6/U6 -> -0.070519147 | Z6: =V6+(N6+O6)*7*T6 -> 496.85294 | AB6: =(B6*T6*7-J6-G6-D6)*0.05 -> 59.4881
A7: 9月W3 | B7: 49.99 | C7: 0 | D7: =B7*C7*S7*0.6*7 -> 0 | E7: 15 | F7: 0.15 | G7: =E7*F7*B7 -> 112.4775 | H7: 0 | I7: 0.3 | J7: =H7*I7*B7 -> 0 | K7: 21 | L7: =K7/0.045*0.85 -> 396.66667 | M7: =L7/U7 -> 0.22671201 | N7: 19.99 | O7: 1.28 | P7: 6.08 | Q7: =(U7-D7-G7-J7)*0.08 -> 130.9738 | R7: =VLOOKUP(A:A,'3.推广计划细化'!A:J,10,0) -> #500 | S7: =(T7*7-E7-H7)/7 -> 2.8571429 | T7: =VLOOKUP(A:A,'3.推广计划细化'!A:E,5,0) -> 5 | U7: =T7*7*B7 -> 1749.65 | V7: =(B7-N7-O7-P7)*T7*7-D7-G7-J7-L7-Q7-AB7 -> 70.423408 | W7: =V7/U7 -> 0.040249998 | Z7: =V7+(N7+O7)*7*T7 -> 814.87341 | AB7: =(B7*T7*7-J7-G7-D7)*0.05 -> 81.858625
A8: 9月W4 | B8: 49.99 | C8: 0.2 | D8: =B8*C8*S8*0.6*7 -> 209.958 | E8: 0 | F8: 0.15 | G8: =E8*F8*B8 -> 0 | H8: 0 | I8: 0.3 | J8: =H8*I8*B8 -> 0 | K8: 25 | L8: =K8/0.045*0.85 -> 472.22222 | M8: =L8/U8 -> 0.26989525 | N8: 19.99 | O8: 1.28 | P8: 6.08 | Q8: =(U8-D8-G8-J8)*0.08 -> 123.17536 | R8: =VLOOKUP(A:A,'3.推广计划细化'!A:J,10,0) -> #450 | S8: =(T8*7-E8-H8)/7 -> 5 | T8: =VLOOKUP(A:A,'3.推广计划细化'!A:E,5,0) -> 5 | U8: =T8*7*B8 -> 1749.65 | V8: =(B8-N8-O8-P8)*T8*7-D8-G8-J8-L8-Q8-AB8 -> -89.940182 | W8: =V8/U8 -> -0.051404671 | Z8: =V8+(N8+O8)*7*T8 -> 654.50982 | AB8: =(B8*T8*7-J8-G8-D8)*0.05 -> 76.9846
A9: 10月W1 | B9: 49.99 | C9: 0 | D9: =B9*C9*S9*0.6*7 -> 0 | E9: 20 | F9: 0.15 | G9: =E9*F9*B9 -> 149.97 | H9: 0 | I9: 0.3 | J9: =H9*I9*B9 -> 0 | K9: 25 | L9: =K9/0.045*0.85 -> 472.22222 | M9: =L9/U9 -> 0.22491271 | N9: 19.99 | O9: 1.28 | P9: 6.08 | Q9: =(U9-D9-G9-J9)*0.08 -> 155.9688 | R9: =VLOOKUP(A:A,'3.推广计划细化'!A:J,10,0) -> #350 | S9: =(T9*7-E9-H9)/7 -> 3.1428571 | T9: =VLOOKUP(A:A,'3.推广计划细化'!A:E,5,0) -> 6 | U9: =T9*7*B9 -> 2099.58 | V9: =(B9-N9-O9-P9)*T9*7-D9-G9-J9-L9-Q9-AB9 -> 75.238478 | W9: =V9/U9 -> 0.035835014 | Z9: =V9+(N9+O9)*7*T9 -> 968.57848 | AB9: =(B9*T9*7-J9-G9-D9)*0.05 -> 97.4805
A10: 10月W2 | B10: 49.99 | C10: 0.18 | D10: =B10*C10*S10*0.6*7 -> 226.75464 | E10: 0 | F10: 0.15 | G10: =E10*F10*B10 -> 0 | H10: 0 | I10: 0.3 | J10: =H10*I10*B10 -> 0 | K10: 25 | L10: =K10/0.045*0.85 -> 472.22222 | M10: =L10/U10 -> 0.22491271 | N10: 19.99 | O10: 1.28 | P10: 6.08 | Q10: =(U10-D10-G10-J10)*0.08 -> 149.82603 | R10: =VLOOKUP(A:A,'3.推广计划细化'!A:J,10,0) -> #300 | S10: =(T10*7-E10-H10)/7 -> 6 | T10: =VLOOKUP(A:A,'3.推广计划细化'!A:E,5,0) -> 6 | U10: =T10*7*B10 -> 2099.58 | V10: =(B10-N10-O10-P10)*T10*7-D10-G10-J10-L10-Q10-AB10 -> 8.435841 | W10: =V10/U10 -> 0.0040178707 | Z10: =V10+(N10+O10)*7*T10 -> 901.77584 | AB10: =(B10*T10*7-J10-G10-D10)*0.05 -> 93.641268
A11: 10月W3 | B11: 49.99 | C11: 0.15 | D11: =B11*C11*S11*0.6*7 -> 220.4559 | E11: 0 | F11: 0.15 | G11: =E11*F11*B11 -> 0 | H11: 0 | I11: 0.3 | J11: =H11*I11*B11 -> 0 | K11: 28 | L11: =K11/0.05*0.82 -> 459.2 | M11: =L11/U11 -> 0.18746606 | N11: 19.99 | O11: 1.28 | P11: 6.08 | Q11: =(U11-D11-G11-J11)*0.08 -> 178.32433 | R11: =VLOOKUP(A:A,'3.推广计划细化'!A:J,10,0) -> #250 | S11: =(T11*7-E11-H11)/7 -> 7 | T11: =VLOOKUP(A:A,'3.推广计划细化'!A:E,5,0) -> 7 | U11: =T11*7*B11 -> 2449.51 | V11: =(B11-N11-O11-P11)*T11*7-D11-G11-J11-L11-Q11-AB11 -> 139.92707 | W11: =V11/U11 -> 0.057124513 | Z11: =V11+(N11+O11)*7*T11 -> 1182.1571 | AB11: =(B11*T11*7-J11-G11-D11)*0.05 -> 111.4527
A12: 10月W4 | B12: 49.99 | C12: 0.15 | D12: =B12*C12*S12*0.6*7 -> 251.9496 | E12: 0 | F12: 0.15 | G12: =E12*F12*B12 -> 0 | H12: 0 | I12: 0.3 | J12: =H12*I12*B12 -> 0 | K12: 28 | L12: =K12/0.05*0.82 -> 459.2 | M12: =L12/U12 -> 0.16403281 | N12: 19.99 | O12: 1.28 | P12: 6.08 | Q12: =(U12-D12-G12-J12)*0.08 -> 203.79923 | R12: =VLOOKUP(A:A,'3.推广计划细化'!A:J,10,0) -> #200 | S12: =(T12*7-E12-H12)/7 -> 8 | T12: =VLOOKUP(A:A,'3.推广计划细化'!A:E,5,0) -> 8 | U12: =T12*7*B12 -> 2799.44 | V12: =(B12-N12-O12-P12)*T12*7-D12-G12-J12-L12-Q12-AB12 -> 225.51665 | W12: =V12/U12 -> 0.080557772 | Z12: =V12+(N12+O12)*7*T12 -> 1416.6366 | AB12: =(B12*T12*7-J12-G12-D12)*0.05 -> 127.37452
A13: 11月W1 | B13: 49.99 | C13: 0.15 | D13: =B13*C13*S13*0.6*7 -> 314.937 | E13: 0 | F13: 0.15 | G13: =E13*F13*B13 -> 0 | H13: 0 | I13: 0.3 | J13: =H13*I13*B13 -> 0 | K13: 30 | L13: =K13/0.05*0.82 -> 492 | M13: =L13/U13 -> 0.14059955 | N13: 19.99 | O13: 1.28 | P13: 6.08 | Q13: =(U13-D13-G13-J13)*0.08 -> 254.74904 | R13: =VLOOKUP(A:A,'3.推广计划细化'!A:J,10,0) -> #150 | S13: =(T13*7-E13-H13)/7 -> 10 | T13: =VLOOKUP(A:A,'3.推广计划细化'!A:E,5,0) -> 10 | U13: =T13*7*B13 -> 3499.3 | V13: =(B13-N13-O13-P13)*T13*7-D13-G13-J13-L13-Q13-AB13 -> 363.89581 | W13: =V13/U13 -> 0.10399103 | Z13: =V13+(N13+O13)*7*T13 -> 1852.7958 | AB13: =(B13*T13*7-J13-G13-D13)*0.05 -> 159.21815
A14: 11月W2 | B14: 49.99 | C14: 0.15 | D14: =B14*C14*S14*0.6*7 -> 377.9244 | E14: 0 | F14: 0.15 | G14: =E14*F14*B14 -> 0 | H14: 0 | I14: 0.3 | J14: =H14*I14*B14 -> 0 | K14: 35 | L14: =K14/0.05*0.82 -> 574 | M14: =L14/U14 -> 0.13669401 | N14: 19.99 | O14: 1.28 | P14: 6.08 | Q14: =(U14-D14-G14-J14)*0.08 -> 305.69885 | R14: =VLOOKUP(A:A,'3.推广计划细化'!A:J,10,0) -> #130 | S14: =(T14*7-E14-H14)/7 -> 12 | T14: =VLOOKUP(A:A,'3.推广计划细化'!A:E,5,0) -> 12 | U14: =T14*7*B14 -> 4199.16 | V14: =(B14-N14-O14-P14)*T14*7-D14-G14-J14-L14-Q14-AB14 -> 453.07497 | W14: =V14/U14 -> 0.10789657 | Z14: =V14+(N14+O14)*7*T14 -> 2239.755 | AB14: =(B14*T14*7-J14-G14-D14)*0.05 -> 191.06178
P18: 退货率按5个点算的 | T18: 利润回正 | V18: 10月W1
T19: 3个月总盈利 | V19: =SUM(V3:V14) -> 604.52875 | W19: USD
S20: 3个月总盈利RMB | V20: =V19*6.7 -> 4050.3426 | W20: RMB
Q23: 退货率按8个点算 | T23: 利润回正 | V23: 10月W1
T24: 3月总盈利 | V24: -23.37 | W24: USD
T25: 3个月总盈利RMB | V25: -126.59 | W25: RMB
Q28: 退货率按10个点算的 | T28: 利润回正 | V28: 8月W3
T29: 8个月总亏损 | V29: -463.72 | W29: USD
T30: 8个月总亏损RMB= | V30: -3106.91 | W30: RMB

Sheet 6.风控预案
A1: 1、前两周出现差评问题
A2: 在前两周尽量做安全的测评工作，争取在第三周上评，保护链接安全。
A4: 2、出现差评过多怎么办？
A5: 找欧洲链接，合并国际评论
